Compiled from "TestHFileSeek.java"
public class org.apache.hadoop.hbase.io.hfile.TestHFileSeek extends junit.framework.TestCase {
  public static final org.apache.hadoop.hbase.HBaseClassTestRule CLASS_RULE;

  public org.apache.hadoop.hbase.io.hfile.TestHFileSeek();
    Code:
       0: aload_0
       1: invokespecial #1                  // Method junit/framework/TestCase."<init>":()V
       4: return

  public void setUp() throws java.io.IOException;
    Code:
       0: aload_0
       1: getfield      #2                  // Field options:Lorg/apache/hadoop/hbase/io/hfile/TestHFileSeek$MyOptions;
       4: ifnonnull     22
       7: aload_0
       8: new           #3                  // class org/apache/hadoop/hbase/io/hfile/TestHFileSeek$MyOptions
      11: dup
      12: iconst_0
      13: anewarray     #4                  // class java/lang/String
      16: invokespecial #5                  // Method org/apache/hadoop/hbase/io/hfile/TestHFileSeek$MyOptions."<init>":([Ljava/lang/String;)V
      19: putfield      #2                  // Field options:Lorg/apache/hadoop/hbase/io/hfile/TestHFileSeek$MyOptions;
      22: aload_0
      23: new           #6                  // class org/apache/hadoop/conf/Configuration
      26: dup
      27: invokespecial #7                  // Method org/apache/hadoop/conf/Configuration."<init>":()V
      30: putfield      #8                  // Field conf:Lorg/apache/hadoop/conf/Configuration;
      33: aload_0
      34: getfield      #2                  // Field options:Lorg/apache/hadoop/hbase/io/hfile/TestHFileSeek$MyOptions;
      37: getfield      #9                  // Field org/apache/hadoop/hbase/io/hfile/TestHFileSeek$MyOptions.useRawFs:Z
      40: ifeq          56
      43: aload_0
      44: getfield      #8                  // Field conf:Lorg/apache/hadoop/conf/Configuration;
      47: ldc           #10                 // String fs.file.impl
      49: ldc           #11                 // class org/apache/hadoop/fs/RawLocalFileSystem
      51: ldc           #12                 // class org/apache/hadoop/fs/FileSystem
      53: invokevirtual #13                 // Method org/apache/hadoop/conf/Configuration.setClass:(Ljava/lang/String;Ljava/lang/Class;Ljava/lang/Class;)V
      56: aload_0
      57: getfield      #8                  // Field conf:Lorg/apache/hadoop/conf/Configuration;
      60: ldc           #14                 // String tfile.fs.input.buffer.size
      62: aload_0
      63: getfield      #2                  // Field options:Lorg/apache/hadoop/hbase/io/hfile/TestHFileSeek$MyOptions;
      66: getfield      #15                 // Field org/apache/hadoop/hbase/io/hfile/TestHFileSeek$MyOptions.fsInputBufferSize:I
      69: invokevirtual #16                 // Method org/apache/hadoop/conf/Configuration.setInt:(Ljava/lang/String;I)V
      72: aload_0
      73: getfield      #8                  // Field conf:Lorg/apache/hadoop/conf/Configuration;
      76: ldc           #17                 // String tfile.fs.output.buffer.size
      78: aload_0
      79: getfield      #2                  // Field options:Lorg/apache/hadoop/hbase/io/hfile/TestHFileSeek$MyOptions;
      82: getfield      #18                 // Field org/apache/hadoop/hbase/io/hfile/TestHFileSeek$MyOptions.fsOutputBufferSize:I
      85: invokevirtual #16                 // Method org/apache/hadoop/conf/Configuration.setInt:(Ljava/lang/String;I)V
      88: aload_0
      89: new           #19                 // class org/apache/hadoop/fs/Path
      92: dup
      93: new           #19                 // class org/apache/hadoop/fs/Path
      96: dup
      97: aload_0
      98: getfield      #2                  // Field options:Lorg/apache/hadoop/hbase/io/hfile/TestHFileSeek$MyOptions;
     101: getfield      #20                 // Field org/apache/hadoop/hbase/io/hfile/TestHFileSeek$MyOptions.rootDir:Ljava/lang/String;
     104: invokespecial #21                 // Method org/apache/hadoop/fs/Path."<init>":(Ljava/lang/String;)V
     107: aload_0
     108: getfield      #2                  // Field options:Lorg/apache/hadoop/hbase/io/hfile/TestHFileSeek$MyOptions;
     111: getfield      #22                 // Field org/apache/hadoop/hbase/io/hfile/TestHFileSeek$MyOptions.file:Ljava/lang/String;
     114: invokespecial #23                 // Method org/apache/hadoop/fs/Path."<init>":(Lorg/apache/hadoop/fs/Path;Ljava/lang/String;)V
     117: putfield      #24                 // Field path:Lorg/apache/hadoop/fs/Path;
     120: aload_0
     121: aload_0
     122: getfield      #24                 // Field path:Lorg/apache/hadoop/fs/Path;
     125: aload_0
     126: getfield      #8                  // Field conf:Lorg/apache/hadoop/conf/Configuration;
     129: invokevirtual #25                 // Method org/apache/hadoop/fs/Path.getFileSystem:(Lorg/apache/hadoop/conf/Configuration;)Lorg/apache/hadoop/fs/FileSystem;
     132: putfield      #26                 // Field fs:Lorg/apache/hadoop/fs/FileSystem;
     135: aload_0
     136: new           #27                 // class org/apache/hadoop/hbase/io/hfile/NanoTimer
     139: dup
     140: iconst_0
     141: invokespecial #28                 // Method org/apache/hadoop/hbase/io/hfile/NanoTimer."<init>":(Z)V
     144: putfield      #29                 // Field timer:Lorg/apache/hadoop/hbase/io/hfile/NanoTimer;
     147: aload_0
     148: new           #30                 // class java/util/Random
     151: dup
     152: aload_0
     153: getfield      #2                  // Field options:Lorg/apache/hadoop/hbase/io/hfile/TestHFileSeek$MyOptions;
     156: getfield      #31                 // Field org/apache/hadoop/hbase/io/hfile/TestHFileSeek$MyOptions.seed:J
     159: invokespecial #32                 // Method java/util/Random."<init>":(J)V
     162: putfield      #33                 // Field rng:Ljava/util/Random;
     165: aload_0
     166: new           #34                 // class org/apache/hadoop/hbase/io/hfile/RandomDistribution$Zipf
     169: dup
     170: new           #30                 // class java/util/Random
     173: dup
     174: aload_0
     175: getfield      #33                 // Field rng:Ljava/util/Random;
     178: invokevirtual #35                 // Method java/util/Random.nextLong:()J
     181: invokespecial #32                 // Method java/util/Random."<init>":(J)V
     184: aload_0
     185: getfield      #2                  // Field options:Lorg/apache/hadoop/hbase/io/hfile/TestHFileSeek$MyOptions;
     188: getfield      #36                 // Field org/apache/hadoop/hbase/io/hfile/TestHFileSeek$MyOptions.minKeyLen:I
     191: aload_0
     192: getfield      #2                  // Field options:Lorg/apache/hadoop/hbase/io/hfile/TestHFileSeek$MyOptions;
     195: getfield      #37                 // Field org/apache/hadoop/hbase/io/hfile/TestHFileSeek$MyOptions.maxKeyLen:I
     198: ldc2_w        #38                 // double 1.2d
     201: invokespecial #40                 // Method org/apache/hadoop/hbase/io/hfile/RandomDistribution$Zipf."<init>":(Ljava/util/Random;IID)V
     204: putfield      #41                 // Field keyLenGen:Lorg/apache/hadoop/hbase/io/hfile/RandomDistribution$DiscreteRNG;
     207: new           #42                 // class org/apache/hadoop/hbase/io/hfile/RandomDistribution$Flat
     210: dup
     211: new           #30                 // class java/util/Random
     214: dup
     215: aload_0
     216: getfield      #33                 // Field rng:Ljava/util/Random;
     219: invokevirtual #35                 // Method java/util/Random.nextLong:()J
     222: invokespecial #32                 // Method java/util/Random."<init>":(J)V
     225: aload_0
     226: getfield      #2                  // Field options:Lorg/apache/hadoop/hbase/io/hfile/TestHFileSeek$MyOptions;
     229: getfield      #43                 // Field org/apache/hadoop/hbase/io/hfile/TestHFileSeek$MyOptions.minValLength:I
     232: aload_0
     233: getfield      #2                  // Field options:Lorg/apache/hadoop/hbase/io/hfile/TestHFileSeek$MyOptions;
     236: getfield      #44                 // Field org/apache/hadoop/hbase/io/hfile/TestHFileSeek$MyOptions.maxValLength:I
     239: invokespecial #45                 // Method org/apache/hadoop/hbase/io/hfile/RandomDistribution$Flat."<init>":(Ljava/util/Random;II)V
     242: astore_1
     243: new           #42                 // class org/apache/hadoop/hbase/io/hfile/RandomDistribution$Flat
     246: dup
     247: new           #30                 // class java/util/Random
     250: dup
     251: aload_0
     252: getfield      #33                 // Field rng:Ljava/util/Random;
     255: invokevirtual #35                 // Method java/util/Random.nextLong:()J
     258: invokespecial #32                 // Method java/util/Random."<init>":(J)V
     261: aload_0
     262: getfield      #2                  // Field options:Lorg/apache/hadoop/hbase/io/hfile/TestHFileSeek$MyOptions;
     265: getfield      #46                 // Field org/apache/hadoop/hbase/io/hfile/TestHFileSeek$MyOptions.minWordLen:I
     268: aload_0
     269: getfield      #2                  // Field options:Lorg/apache/hadoop/hbase/io/hfile/TestHFileSeek$MyOptions;
     272: getfield      #47                 // Field org/apache/hadoop/hbase/io/hfile/TestHFileSeek$MyOptions.maxWordLen:I
     275: invokespecial #45                 // Method org/apache/hadoop/hbase/io/hfile/RandomDistribution$Flat."<init>":(Ljava/util/Random;II)V
     278: astore_2
     279: aload_0
     280: new           #48                 // class org/apache/hadoop/hbase/io/hfile/KVGenerator
     283: dup
     284: aload_0
     285: getfield      #33                 // Field rng:Ljava/util/Random;
     288: iconst_1
     289: aload_0
     290: getfield      #41                 // Field keyLenGen:Lorg/apache/hadoop/hbase/io/hfile/RandomDistribution$DiscreteRNG;
     293: aload_1
     294: aload_2
     295: aload_0
     296: getfield      #2                  // Field options:Lorg/apache/hadoop/hbase/io/hfile/TestHFileSeek$MyOptions;
     299: getfield      #49                 // Field org/apache/hadoop/hbase/io/hfile/TestHFileSeek$MyOptions.dictSize:I
     302: invokespecial #50                 // Method org/apache/hadoop/hbase/io/hfile/KVGenerator."<init>":(Ljava/util/Random;ZLorg/apache/hadoop/hbase/io/hfile/RandomDistribution$DiscreteRNG;Lorg/apache/hadoop/hbase/io/hfile/RandomDistribution$DiscreteRNG;Lorg/apache/hadoop/hbase/io/hfile/RandomDistribution$DiscreteRNG;I)V
     305: putfield      #51                 // Field kvGen:Lorg/apache/hadoop/hbase/io/hfile/KVGenerator;
     308: return

  public void tearDown();
    Code:
       0: aload_0
       1: getfield      #26                 // Field fs:Lorg/apache/hadoop/fs/FileSystem;
       4: invokevirtual #52                 // Method org/apache/hadoop/fs/FileSystem.close:()V
       7: goto          11
      10: astore_1
      11: return
    Exception table:
       from    to  target type
           0     7    10   Class java/lang/Exception

  public void seekTFile() throws java.io.IOException;
    Code:
       0: iconst_0
       1: istore_1
       2: lconst_0
       3: lstore_2
       4: aload_0
       5: getfield      #26                 // Field fs:Lorg/apache/hadoop/fs/FileSystem;
       8: aload_0
       9: getfield      #24                 // Field path:Lorg/apache/hadoop/fs/Path;
      12: invokevirtual #106                // Method org/apache/hadoop/fs/FileSystem.open:(Lorg/apache/hadoop/fs/Path;)Lorg/apache/hadoop/fs/FSDataInputStream;
      15: astore        4
      17: aload_0
      18: getfield      #24                 // Field path:Lorg/apache/hadoop/fs/Path;
      21: aload         4
      23: aload_0
      24: getfield      #26                 // Field fs:Lorg/apache/hadoop/fs/FileSystem;
      27: aload_0
      28: getfield      #24                 // Field path:Lorg/apache/hadoop/fs/Path;
      31: invokevirtual #77                 // Method org/apache/hadoop/fs/FileSystem.getFileStatus:(Lorg/apache/hadoop/fs/Path;)Lorg/apache/hadoop/fs/FileStatus;
      34: invokevirtual #78                 // Method org/apache/hadoop/fs/FileStatus.getLen:()J
      37: new           #107                // class org/apache/hadoop/hbase/io/hfile/CacheConfig
      40: dup
      41: aload_0
      42: getfield      #8                  // Field conf:Lorg/apache/hadoop/conf/Configuration;
      45: invokespecial #108                // Method org/apache/hadoop/hbase/io/hfile/CacheConfig."<init>":(Lorg/apache/hadoop/conf/Configuration;)V
      48: aload_0
      49: getfield      #8                  // Field conf:Lorg/apache/hadoop/conf/Configuration;
      52: invokestatic  #109                // Method org/apache/hadoop/hbase/io/hfile/HFile.createReaderFromStream:(Lorg/apache/hadoop/fs/Path;Lorg/apache/hadoop/fs/FSDataInputStream;JLorg/apache/hadoop/hbase/io/hfile/CacheConfig;Lorg/apache/hadoop/conf/Configuration;)Lorg/apache/hadoop/hbase/io/hfile/HFile$Reader;
      55: astore        5
      57: aload         5
      59: invokeinterface #110,  1          // InterfaceMethod org/apache/hadoop/hbase/io/hfile/HFile$Reader.loadFileInfo:()Ljava/util/Map;
      64: pop
      65: new           #111                // class org/apache/hadoop/hbase/io/hfile/KeySampler
      68: dup
      69: aload_0
      70: getfield      #33                 // Field rng:Ljava/util/Random;
      73: aload         5
      75: invokeinterface #112,  1          // InterfaceMethod org/apache/hadoop/hbase/io/hfile/HFile$Reader.getFirstKey:()Ljava/util/Optional;
      80: invokevirtual #113                // Method java/util/Optional.get:()Ljava/lang/Object;
      83: checkcast     #84                 // class org/apache/hadoop/hbase/KeyValue
      86: invokevirtual #114                // Method org/apache/hadoop/hbase/KeyValue.getKey:()[B
      89: aload         5
      91: invokeinterface #115,  1          // InterfaceMethod org/apache/hadoop/hbase/io/hfile/HFile$Reader.getLastKey:()Ljava/util/Optional;
      96: invokevirtual #113                // Method java/util/Optional.get:()Ljava/lang/Object;
      99: checkcast     #84                 // class org/apache/hadoop/hbase/KeyValue
     102: invokevirtual #114                // Method org/apache/hadoop/hbase/KeyValue.getKey:()[B
     105: aload_0
     106: getfield      #41                 // Field keyLenGen:Lorg/apache/hadoop/hbase/io/hfile/RandomDistribution$DiscreteRNG;
     109: invokespecial #116                // Method org/apache/hadoop/hbase/io/hfile/KeySampler."<init>":(Ljava/util/Random;[B[BLorg/apache/hadoop/hbase/io/hfile/RandomDistribution$DiscreteRNG;)V
     112: astore        6
     114: aload         5
     116: iconst_0
     117: iconst_1
     118: invokeinterface #118,  3          // InterfaceMethod org/apache/hadoop/hbase/io/hfile/HFile$Reader.getScanner:(ZZ)Lorg/apache/hadoop/hbase/io/hfile/HFileScanner;
     123: astore        7
     125: new           #72                 // class org/apache/hadoop/io/BytesWritable
     128: dup
     129: invokespecial #73                 // Method org/apache/hadoop/io/BytesWritable."<init>":()V
     132: astore        8
     134: aload_0
     135: getfield      #29                 // Field timer:Lorg/apache/hadoop/hbase/io/hfile/NanoTimer;
     138: invokevirtual #119                // Method org/apache/hadoop/hbase/io/hfile/NanoTimer.reset:()V
     141: aload_0
     142: getfield      #29                 // Field timer:Lorg/apache/hadoop/hbase/io/hfile/NanoTimer;
     145: invokevirtual #74                 // Method org/apache/hadoop/hbase/io/hfile/NanoTimer.start:()V
     148: iconst_0
     149: istore        9
     151: iload         9
     153: i2l
     154: aload_0
     155: getfield      #2                  // Field options:Lorg/apache/hadoop/hbase/io/hfile/TestHFileSeek$MyOptions;
     158: getfield      #120                // Field org/apache/hadoop/hbase/io/hfile/TestHFileSeek$MyOptions.seekCount:J
     161: lcmp
     162: ifge          284
     165: aload         6
     167: aload         8
     169: invokevirtual #121                // Method org/apache/hadoop/hbase/io/hfile/KeySampler.next:(Lorg/apache/hadoop/io/BytesWritable;)V
     172: aload         8
     174: invokevirtual #81                 // Method org/apache/hadoop/io/BytesWritable.getLength:()I
     177: newarray       byte
     179: astore        10
     181: aload         8
     183: invokevirtual #82                 // Method org/apache/hadoop/io/BytesWritable.getBytes:()[B
     186: iconst_0
     187: aload         10
     189: iconst_0
     190: aload         8
     192: invokevirtual #81                 // Method org/apache/hadoop/io/BytesWritable.getLength:()I
     195: invokestatic  #83                 // Method java/lang/System.arraycopy:(Ljava/lang/Object;ILjava/lang/Object;II)V
     198: new           #84                 // class org/apache/hadoop/hbase/KeyValue
     201: dup
     202: aload         10
     204: getstatic     #85                 // Field CF:[B
     207: getstatic     #86                 // Field QUAL:[B
     210: invokespecial #122                // Method org/apache/hadoop/hbase/KeyValue."<init>":([B[B[B)V
     213: astore        11
     215: aload         7
     217: aload         11
     219: invokeinterface #123,  2          // InterfaceMethod org/apache/hadoop/hbase/io/hfile/HFileScanner.seekTo:(Lorg/apache/hadoop/hbase/Cell;)I
     224: iflt          275
     227: aload         7
     229: invokeinterface #124,  1          // InterfaceMethod org/apache/hadoop/hbase/io/hfile/HFileScanner.getKey:()Lorg/apache/hadoop/hbase/Cell;
     234: checkcast     #84                 // class org/apache/hadoop/hbase/KeyValue
     237: invokevirtual #114                // Method org/apache/hadoop/hbase/KeyValue.getKey:()[B
     240: invokestatic  #125                // Method java/nio/ByteBuffer.wrap:([B)Ljava/nio/ByteBuffer;
     243: astore        12
     245: aload         7
     247: invokeinterface #126,  1          // InterfaceMethod org/apache/hadoop/hbase/io/hfile/HFileScanner.getValue:()Ljava/nio/ByteBuffer;
     252: astore        13
     254: lload_2
     255: aload         12
     257: invokevirtual #127                // Method java/nio/ByteBuffer.limit:()I
     260: i2l
     261: ladd
     262: lstore_2
     263: lload_2
     264: aload         13
     266: invokevirtual #127                // Method java/nio/ByteBuffer.limit:()I
     269: i2l
     270: ladd
     271: lstore_2
     272: goto          278
     275: iinc          1, 1
     278: iinc          9, 1
     281: goto          151
     284: aload_0
     285: getfield      #29                 // Field timer:Lorg/apache/hadoop/hbase/io/hfile/NanoTimer;
     288: invokevirtual #91                 // Method org/apache/hadoop/hbase/io/hfile/NanoTimer.stop:()V
     291: getstatic     #97                 // Field java/lang/System.out:Ljava/io/PrintStream;
     294: ldc           #128                // String time: %s...avg seek: %s...%d hit...%d miss...avg I/O size: %.2fKB\n
     296: iconst_5
     297: anewarray     #99                 // class java/lang/Object
     300: dup
     301: iconst_0
     302: aload_0
     303: getfield      #29                 // Field timer:Lorg/apache/hadoop/hbase/io/hfile/NanoTimer;
     306: invokevirtual #100                // Method org/apache/hadoop/hbase/io/hfile/NanoTimer.toString:()Ljava/lang/String;
     309: aastore
     310: dup
     311: iconst_1
     312: aload_0
     313: getfield      #29                 // Field timer:Lorg/apache/hadoop/hbase/io/hfile/NanoTimer;
     316: invokevirtual #94                 // Method org/apache/hadoop/hbase/io/hfile/NanoTimer.read:()J
     319: aload_0
     320: getfield      #2                  // Field options:Lorg/apache/hadoop/hbase/io/hfile/TestHFileSeek$MyOptions;
     323: getfield      #120                // Field org/apache/hadoop/hbase/io/hfile/TestHFileSeek$MyOptions.seekCount:J
     326: ldiv
     327: invokestatic  #129                // Method org/apache/hadoop/hbase/io/hfile/NanoTimer.nanoTimeToString:(J)Ljava/lang/String;
     330: aastore
     331: dup
     332: iconst_2
     333: aload_0
     334: getfield      #2                  // Field options:Lorg/apache/hadoop/hbase/io/hfile/TestHFileSeek$MyOptions;
     337: getfield      #120                // Field org/apache/hadoop/hbase/io/hfile/TestHFileSeek$MyOptions.seekCount:J
     340: iload_1
     341: i2l
     342: lsub
     343: invokestatic  #130                // Method java/lang/Long.valueOf:(J)Ljava/lang/Long;
     346: aastore
     347: dup
     348: iconst_3
     349: iload_1
     350: invokestatic  #131                // Method java/lang/Integer.valueOf:(I)Ljava/lang/Integer;
     353: aastore
     354: dup
     355: iconst_4
     356: lload_2
     357: l2d
     358: ldc2_w        #101                // double 1024.0d
     361: ddiv
     362: aload_0
     363: getfield      #2                  // Field options:Lorg/apache/hadoop/hbase/io/hfile/TestHFileSeek$MyOptions;
     366: getfield      #120                // Field org/apache/hadoop/hbase/io/hfile/TestHFileSeek$MyOptions.seekCount:J
     369: iload_1
     370: i2l
     371: lsub
     372: l2d
     373: ddiv
     374: invokestatic  #103                // Method java/lang/Double.valueOf:(D)Ljava/lang/Double;
     377: aastore
     378: invokevirtual #104                // Method java/io/PrintStream.printf:(Ljava/lang/String;[Ljava/lang/Object;)Ljava/io/PrintStream;
     381: pop
     382: return

  public void testSeeks() throws java.io.IOException;
    Code:
       0: aload_0
       1: getfield      #2                  // Field options:Lorg/apache/hadoop/hbase/io/hfile/TestHFileSeek$MyOptions;
       4: invokevirtual #132                // Method org/apache/hadoop/hbase/io/hfile/TestHFileSeek$MyOptions.doCreate:()Z
       7: ifeq          14
      10: aload_0
      11: invokespecial #133                // Method createTFile:()V
      14: aload_0
      15: getfield      #2                  // Field options:Lorg/apache/hadoop/hbase/io/hfile/TestHFileSeek$MyOptions;
      18: invokevirtual #134                // Method org/apache/hadoop/hbase/io/hfile/TestHFileSeek$MyOptions.doRead:()Z
      21: ifeq          28
      24: aload_0
      25: invokevirtual #135                // Method seekTFile:()V
      28: aload_0
      29: getfield      #2                  // Field options:Lorg/apache/hadoop/hbase/io/hfile/TestHFileSeek$MyOptions;
      32: invokevirtual #132                // Method org/apache/hadoop/hbase/io/hfile/TestHFileSeek$MyOptions.doCreate:()Z
      35: ifeq          51
      38: aload_0
      39: getfield      #26                 // Field fs:Lorg/apache/hadoop/fs/FileSystem;
      42: aload_0
      43: getfield      #24                 // Field path:Lorg/apache/hadoop/fs/Path;
      46: iconst_1
      47: invokevirtual #55                 // Method org/apache/hadoop/fs/FileSystem.delete:(Lorg/apache/hadoop/fs/Path;Z)Z
      50: pop
      51: return

  public static void main(java.lang.String[]) throws java.io.IOException;
    Code:
       0: new           #117                // class org/apache/hadoop/hbase/io/hfile/TestHFileSeek
       3: dup
       4: invokespecial #136                // Method "<init>":()V
       7: astore_1
       8: new           #3                  // class org/apache/hadoop/hbase/io/hfile/TestHFileSeek$MyOptions
      11: dup
      12: aload_0
      13: invokespecial #5                  // Method org/apache/hadoop/hbase/io/hfile/TestHFileSeek$MyOptions."<init>":([Ljava/lang/String;)V
      16: astore_2
      17: aload_2
      18: getfield      #137                // Field org/apache/hadoop/hbase/io/hfile/TestHFileSeek$MyOptions.proceed:Z
      21: ifne          25
      24: return
      25: aload_1
      26: aload_2
      27: putfield      #2                  // Field options:Lorg/apache/hadoop/hbase/io/hfile/TestHFileSeek$MyOptions;
      30: iconst_0
      31: istore_3
      32: iload_3
      33: i2l
      34: aload_2
      35: getfield      #138                // Field org/apache/hadoop/hbase/io/hfile/TestHFileSeek$MyOptions.trialCount:J
      38: lcmp
      39: ifge          89
      42: getstatic     #139                // Field LOG:Lorg/slf4j/Logger;
      45: new           #140                // class java/lang/StringBuilder
      48: dup
      49: invokespecial #141                // Method java/lang/StringBuilder."<init>":()V
      52: ldc           #142                // String Beginning trial
      54: invokevirtual #143                // Method java/lang/StringBuilder.append:(Ljava/lang/String;)Ljava/lang/StringBuilder;
      57: iload_3
      58: iconst_1
      59: iadd
      60: invokevirtual #144                // Method java/lang/StringBuilder.append:(I)Ljava/lang/StringBuilder;
      63: invokevirtual #145                // Method java/lang/StringBuilder.toString:()Ljava/lang/String;
      66: invokeinterface #146,  2          // InterfaceMethod org/slf4j/Logger.info:(Ljava/lang/String;)V
      71: aload_1
      72: invokevirtual #147                // Method setUp:()V
      75: aload_1
      76: invokevirtual #148                // Method testSeeks:()V
      79: aload_1
      80: invokevirtual #149                // Method tearDown:()V
      83: iinc          3, 1
      86: goto          32
      89: return

  static {};
    Code:
       0: ldc           #117                // class org/apache/hadoop/hbase/io/hfile/TestHFileSeek
       2: invokestatic  #150                // Method org/apache/hadoop/hbase/HBaseClassTestRule.forClass:(Ljava/lang/Class;)Lorg/apache/hadoop/hbase/HBaseClassTestRule;
       5: putstatic     #151                // Field CLASS_RULE:Lorg/apache/hadoop/hbase/HBaseClassTestRule;
       8: ldc           #152                // String f1
      10: invokestatic  #153                // Method org/apache/hadoop/hbase/util/Bytes.toBytes:(Ljava/lang/String;)[B
      13: putstatic     #85                 // Field CF:[B
      16: ldc           #154                // String q1
      18: invokestatic  #153                // Method org/apache/hadoop/hbase/util/Bytes.toBytes:(Ljava/lang/String;)[B
      21: putstatic     #86                 // Field QUAL:[B
      24: ldc           #117                // class org/apache/hadoop/hbase/io/hfile/TestHFileSeek
      26: invokestatic  #155                // Method org/slf4j/LoggerFactory.getLogger:(Ljava/lang/Class;)Lorg/slf4j/Logger;
      29: putstatic     #139                // Field LOG:Lorg/slf4j/Logger;
      32: return
}
