Compiled from "TestZKLeaderManager.java"
public class org.apache.hadoop.hbase.zookeeper.TestZKLeaderManager {
  public static final org.apache.hadoop.hbase.HBaseClassTestRule CLASS_RULE;

  public org.apache.hadoop.hbase.zookeeper.TestZKLeaderManager();
    Code:
       0: aload_0
       1: invokespecial #3                  // Method java/lang/Object."<init>":()V
       4: return

  public static void setupBeforeClass() throws java.lang.Exception;
    Code:
       0: new           #4                  // class org/apache/hadoop/hbase/HBaseZKTestingUtility
       3: dup
       4: invokespecial #5                  // Method org/apache/hadoop/hbase/HBaseZKTestingUtility."<init>":()V
       7: putstatic     #6                  // Field TEST_UTIL:Lorg/apache/hadoop/hbase/HBaseZKTestingUtility;
      10: getstatic     #6                  // Field TEST_UTIL:Lorg/apache/hadoop/hbase/HBaseZKTestingUtility;
      13: invokevirtual #7                  // Method org/apache/hadoop/hbase/HBaseZKTestingUtility.startMiniZKCluster:()Lorg/apache/hadoop/hbase/zookeeper/MiniZooKeeperCluster;
      16: pop
      17: getstatic     #6                  // Field TEST_UTIL:Lorg/apache/hadoop/hbase/HBaseZKTestingUtility;
      20: invokevirtual #8                  // Method org/apache/hadoop/hbase/HBaseZKTestingUtility.getConfiguration:()Lorg/apache/hadoop/conf/Configuration;
      23: astore_0
      24: new           #9                  // class org/apache/hadoop/hbase/zookeeper/TestZKLeaderManager$MockAbortable
      27: dup
      28: aconst_null
      29: invokespecial #10                 // Method org/apache/hadoop/hbase/zookeeper/TestZKLeaderManager$MockAbortable."<init>":(Lorg/apache/hadoop/hbase/zookeeper/TestZKLeaderManager$1;)V
      32: astore_1
      33: iconst_5
      34: istore_2
      35: iload_2
      36: anewarray     #11                 // class org/apache/hadoop/hbase/zookeeper/TestZKLeaderManager$MockLeader
      39: putstatic     #12                 // Field CANDIDATES:[Lorg/apache/hadoop/hbase/zookeeper/TestZKLeaderManager$MockLeader;
      42: iconst_0
      43: istore_3
      44: iload_3
      45: iload_2
      46: if_icmpge     104
      49: aload_0
      50: new           #13                 // class java/lang/StringBuilder
      53: dup
      54: invokespecial #14                 // Method java/lang/StringBuilder."<init>":()V
      57: ldc           #15                 // String server
      59: invokevirtual #16                 // Method java/lang/StringBuilder.append:(Ljava/lang/String;)Ljava/lang/StringBuilder;
      62: iload_3
      63: invokevirtual #17                 // Method java/lang/StringBuilder.append:(I)Ljava/lang/StringBuilder;
      66: invokevirtual #18                 // Method java/lang/StringBuilder.toString:()Ljava/lang/String;
      69: aload_1
      70: invokestatic  #19                 // Method newZK:(Lorg/apache/hadoop/conf/Configuration;Ljava/lang/String;Lorg/apache/hadoop/hbase/Abortable;)Lorg/apache/hadoop/hbase/zookeeper/ZKWatcher;
      73: astore        4
      75: getstatic     #12                 // Field CANDIDATES:[Lorg/apache/hadoop/hbase/zookeeper/TestZKLeaderManager$MockLeader;
      78: iload_3
      79: new           #11                 // class org/apache/hadoop/hbase/zookeeper/TestZKLeaderManager$MockLeader
      82: dup
      83: aload         4
      85: iload_3
      86: invokespecial #20                 // Method org/apache/hadoop/hbase/zookeeper/TestZKLeaderManager$MockLeader."<init>":(Lorg/apache/hadoop/hbase/zookeeper/ZKWatcher;I)V
      89: aastore
      90: getstatic     #12                 // Field CANDIDATES:[Lorg/apache/hadoop/hbase/zookeeper/TestZKLeaderManager$MockLeader;
      93: iload_3
      94: aaload
      95: invokevirtual #21                 // Method org/apache/hadoop/hbase/zookeeper/TestZKLeaderManager$MockLeader.start:()V
      98: iinc          3, 1
     101: goto          44
     104: return

  public static void tearDownAfterClass() throws java.lang.Exception;
    Code:
       0: getstatic     #6                  // Field TEST_UTIL:Lorg/apache/hadoop/hbase/HBaseZKTestingUtility;
       3: invokevirtual #22                 // Method org/apache/hadoop/hbase/HBaseZKTestingUtility.shutdownMiniZKCluster:()V
       6: return

  public void testLeaderSelection() throws java.lang.Exception;
    Code:
       0: aload_0
       1: invokespecial #23                 // Method getCurrentLeader:()Lorg/apache/hadoop/hbase/zookeeper/TestZKLeaderManager$MockLeader;
       4: astore_1
       5: ldc           #24                 // String Leader should exist
       7: aload_1
       8: invokestatic  #25                 // Method org/junit/Assert.assertNotNull:(Ljava/lang/String;Ljava/lang/Object;)V
      11: getstatic     #2                  // Field LOG:Lorg/slf4j/Logger;
      14: new           #13                 // class java/lang/StringBuilder
      17: dup
      18: invokespecial #14                 // Method java/lang/StringBuilder."<init>":()V
      21: ldc           #26                 // String Current leader index is
      23: invokevirtual #16                 // Method java/lang/StringBuilder.append:(Ljava/lang/String;)Ljava/lang/StringBuilder;
      26: aload_1
      27: invokevirtual #27                 // Method org/apache/hadoop/hbase/zookeeper/TestZKLeaderManager$MockLeader.getIndex:()I
      30: invokevirtual #17                 // Method java/lang/StringBuilder.append:(I)Ljava/lang/StringBuilder;
      33: invokevirtual #18                 // Method java/lang/StringBuilder.toString:()Ljava/lang/String;
      36: invokeinterface #28,  2           // InterfaceMethod org/slf4j/Logger.debug:(Ljava/lang/String;)V
      41: aload_1
      42: invokevirtual #29                 // Method org/apache/hadoop/hbase/zookeeper/TestZKLeaderManager$MockLeader.getWatcher:()Lorg/apache/hadoop/hbase/zookeeper/ZKWatcher;
      45: getstatic     #1                  // Field LEADER_ZNODE:Ljava/lang/String;
      48: invokestatic  #30                 // Method org/apache/hadoop/hbase/zookeeper/ZKUtil.getData:(Lorg/apache/hadoop/hbase/zookeeper/ZKWatcher;Ljava/lang/String;)[B
      51: astore_2
      52: ldc           #31                 // String Leader znode should contain leader index
      54: aload_2
      55: invokestatic  #25                 // Method org/junit/Assert.assertNotNull:(Ljava/lang/String;Ljava/lang/Object;)V
      58: ldc           #32                 // String Leader znode should not be empty
      60: aload_2
      61: arraylength
      62: ifle          69
      65: iconst_1
      66: goto          70
      69: iconst_0
      70: invokestatic  #33                 // Method org/junit/Assert.assertTrue:(Ljava/lang/String;Z)V
      73: aload_2
      74: invokestatic  #34                 // Method org/apache/hadoop/hbase/util/Bytes.toInt:([B)I
      77: istore_3
      78: getstatic     #2                  // Field LOG:Lorg/slf4j/Logger;
      81: new           #13                 // class java/lang/StringBuilder
      84: dup
      85: invokespecial #14                 // Method java/lang/StringBuilder."<init>":()V
      88: ldc           #35                 // String Stored leader index in ZK is
      90: invokevirtual #16                 // Method java/lang/StringBuilder.append:(Ljava/lang/String;)Ljava/lang/StringBuilder;
      93: iload_3
      94: invokevirtual #17                 // Method java/lang/StringBuilder.append:(I)Ljava/lang/StringBuilder;
      97: invokevirtual #18                 // Method java/lang/StringBuilder.toString:()Ljava/lang/String;
     100: invokeinterface #28,  2           // InterfaceMethod org/slf4j/Logger.debug:(Ljava/lang/String;)V
     105: ldc           #36                 // String Leader znode should match leader index
     107: aload_1
     108: invokevirtual #27                 // Method org/apache/hadoop/hbase/zookeeper/TestZKLeaderManager$MockLeader.getIndex:()I
     111: i2l
     112: iload_3
     113: i2l
     114: invokestatic  #37                 // Method org/junit/Assert.assertEquals:(Ljava/lang/String;JJ)V
     117: aload_1
     118: invokevirtual #38                 // Method org/apache/hadoop/hbase/zookeeper/TestZKLeaderManager$MockLeader.abdicate:()V
     121: aload_0
     122: invokespecial #23                 // Method getCurrentLeader:()Lorg/apache/hadoop/hbase/zookeeper/TestZKLeaderManager$MockLeader;
     125: astore_1
     126: ldc           #39                 // String New leader should exist after abdication
     128: aload_1
     129: invokestatic  #25                 // Method org/junit/Assert.assertNotNull:(Ljava/lang/String;Ljava/lang/Object;)V
     132: getstatic     #2                  // Field LOG:Lorg/slf4j/Logger;
     135: new           #13                 // class java/lang/StringBuilder
     138: dup
     139: invokespecial #14                 // Method java/lang/StringBuilder."<init>":()V
     142: ldc           #40                 // String New leader index is
     144: invokevirtual #16                 // Method java/lang/StringBuilder.append:(Ljava/lang/String;)Ljava/lang/StringBuilder;
     147: aload_1
     148: invokevirtual #27                 // Method org/apache/hadoop/hbase/zookeeper/TestZKLeaderManager$MockLeader.getIndex:()I
     151: invokevirtual #17                 // Method java/lang/StringBuilder.append:(I)Ljava/lang/StringBuilder;
     154: invokevirtual #18                 // Method java/lang/StringBuilder.toString:()Ljava/lang/String;
     157: invokeinterface #28,  2           // InterfaceMethod org/slf4j/Logger.debug:(Ljava/lang/String;)V
     162: aload_1
     163: invokevirtual #29                 // Method org/apache/hadoop/hbase/zookeeper/TestZKLeaderManager$MockLeader.getWatcher:()Lorg/apache/hadoop/hbase/zookeeper/ZKWatcher;
     166: getstatic     #1                  // Field LEADER_ZNODE:Ljava/lang/String;
     169: invokestatic  #30                 // Method org/apache/hadoop/hbase/zookeeper/ZKUtil.getData:(Lorg/apache/hadoop/hbase/zookeeper/ZKWatcher;Ljava/lang/String;)[B
     172: astore_2
     173: ldc           #31                 // String Leader znode should contain leader index
     175: aload_2
     176: invokestatic  #25                 // Method org/junit/Assert.assertNotNull:(Ljava/lang/String;Ljava/lang/Object;)V
     179: ldc           #32                 // String Leader znode should not be empty
     181: aload_2
     182: arraylength
     183: ifle          190
     186: iconst_1
     187: goto          191
     190: iconst_0
     191: invokestatic  #33                 // Method org/junit/Assert.assertTrue:(Ljava/lang/String;Z)V
     194: aload_2
     195: invokestatic  #34                 // Method org/apache/hadoop/hbase/util/Bytes.toInt:([B)I
     198: istore_3
     199: getstatic     #2                  // Field LOG:Lorg/slf4j/Logger;
     202: new           #13                 // class java/lang/StringBuilder
     205: dup
     206: invokespecial #14                 // Method java/lang/StringBuilder."<init>":()V
     209: ldc           #35                 // String Stored leader index in ZK is
     211: invokevirtual #16                 // Method java/lang/StringBuilder.append:(Ljava/lang/String;)Ljava/lang/StringBuilder;
     214: iload_3
     215: invokevirtual #17                 // Method java/lang/StringBuilder.append:(I)Ljava/lang/StringBuilder;
     218: invokevirtual #18                 // Method java/lang/StringBuilder.toString:()Ljava/lang/String;
     221: invokeinterface #28,  2           // InterfaceMethod org/slf4j/Logger.debug:(Ljava/lang/String;)V
     226: ldc           #36                 // String Leader znode should match leader index
     228: aload_1
     229: invokevirtual #27                 // Method org/apache/hadoop/hbase/zookeeper/TestZKLeaderManager$MockLeader.getIndex:()I
     232: i2l
     233: iload_3
     234: i2l
     235: invokestatic  #37                 // Method org/junit/Assert.assertEquals:(Ljava/lang/String;JJ)V
     238: aload_1
     239: ldc           #41                 // String Stopping for test
     241: invokevirtual #42                 // Method org/apache/hadoop/hbase/zookeeper/TestZKLeaderManager$MockLeader.stop:(Ljava/lang/String;)V
     244: aload_0
     245: invokespecial #23                 // Method getCurrentLeader:()Lorg/apache/hadoop/hbase/zookeeper/TestZKLeaderManager$MockLeader;
     248: astore_1
     249: ldc           #43                 // String New leader should exist after stop
     251: aload_1
     252: invokestatic  #25                 // Method org/junit/Assert.assertNotNull:(Ljava/lang/String;Ljava/lang/Object;)V
     255: getstatic     #2                  // Field LOG:Lorg/slf4j/Logger;
     258: new           #13                 // class java/lang/StringBuilder
     261: dup
     262: invokespecial #14                 // Method java/lang/StringBuilder."<init>":()V
     265: ldc           #40                 // String New leader index is
     267: invokevirtual #16                 // Method java/lang/StringBuilder.append:(Ljava/lang/String;)Ljava/lang/StringBuilder;
     270: aload_1
     271: invokevirtual #27                 // Method org/apache/hadoop/hbase/zookeeper/TestZKLeaderManager$MockLeader.getIndex:()I
     274: invokevirtual #17                 // Method java/lang/StringBuilder.append:(I)Ljava/lang/StringBuilder;
     277: invokevirtual #18                 // Method java/lang/StringBuilder.toString:()Ljava/lang/String;
     280: invokeinterface #28,  2           // InterfaceMethod org/slf4j/Logger.debug:(Ljava/lang/String;)V
     285: aload_1
     286: invokevirtual #29                 // Method org/apache/hadoop/hbase/zookeeper/TestZKLeaderManager$MockLeader.getWatcher:()Lorg/apache/hadoop/hbase/zookeeper/ZKWatcher;
     289: getstatic     #1                  // Field LEADER_ZNODE:Ljava/lang/String;
     292: invokestatic  #30                 // Method org/apache/hadoop/hbase/zookeeper/ZKUtil.getData:(Lorg/apache/hadoop/hbase/zookeeper/ZKWatcher;Ljava/lang/String;)[B
     295: astore_2
     296: ldc           #31                 // String Leader znode should contain leader index
     298: aload_2
     299: invokestatic  #25                 // Method org/junit/Assert.assertNotNull:(Ljava/lang/String;Ljava/lang/Object;)V
     302: ldc           #32                 // String Leader znode should not be empty
     304: aload_2
     305: arraylength
     306: ifle          313
     309: iconst_1
     310: goto          314
     313: iconst_0
     314: invokestatic  #33                 // Method org/junit/Assert.assertTrue:(Ljava/lang/String;Z)V
     317: aload_2
     318: invokestatic  #34                 // Method org/apache/hadoop/hbase/util/Bytes.toInt:([B)I
     321: istore_3
     322: getstatic     #2                  // Field LOG:Lorg/slf4j/Logger;
     325: new           #13                 // class java/lang/StringBuilder
     328: dup
     329: invokespecial #14                 // Method java/lang/StringBuilder."<init>":()V
     332: ldc           #35                 // String Stored leader index in ZK is
     334: invokevirtual #16                 // Method java/lang/StringBuilder.append:(Ljava/lang/String;)Ljava/lang/StringBuilder;
     337: iload_3
     338: invokevirtual #17                 // Method java/lang/StringBuilder.append:(I)Ljava/lang/StringBuilder;
     341: invokevirtual #18                 // Method java/lang/StringBuilder.toString:()Ljava/lang/String;
     344: invokeinterface #28,  2           // InterfaceMethod org/slf4j/Logger.debug:(Ljava/lang/String;)V
     349: ldc           #36                 // String Leader znode should match leader index
     351: aload_1
     352: invokevirtual #27                 // Method org/apache/hadoop/hbase/zookeeper/TestZKLeaderManager$MockLeader.getIndex:()I
     355: i2l
     356: iload_3
     357: i2l
     358: invokestatic  #37                 // Method org/junit/Assert.assertEquals:(Ljava/lang/String;JJ)V
     361: aload_1
     362: ldc           #41                 // String Stopping for test
     364: invokevirtual #42                 // Method org/apache/hadoop/hbase/zookeeper/TestZKLeaderManager$MockLeader.stop:(Ljava/lang/String;)V
     367: aload_0
     368: invokespecial #23                 // Method getCurrentLeader:()Lorg/apache/hadoop/hbase/zookeeper/TestZKLeaderManager$MockLeader;
     371: astore_1
     372: ldc           #44                 // String New leader should exist
     374: aload_1
     375: invokestatic  #25                 // Method org/junit/Assert.assertNotNull:(Ljava/lang/String;Ljava/lang/Object;)V
     378: return

  static org.slf4j.Logger access$000();
    Code:
       0: getstatic     #2                  // Field LOG:Lorg/slf4j/Logger;
       3: areturn

  static java.lang.String access$100();
    Code:
       0: getstatic     #1                  // Field LEADER_ZNODE:Ljava/lang/String;
       3: areturn

  static {};
    Code:
       0: ldc           #56                 // class org/apache/hadoop/hbase/zookeeper/TestZKLeaderManager
       2: invokestatic  #57                 // Method org/apache/hadoop/hbase/HBaseClassTestRule.forClass:(Ljava/lang/Class;)Lorg/apache/hadoop/hbase/HBaseClassTestRule;
       5: putstatic     #58                 // Field CLASS_RULE:Lorg/apache/hadoop/hbase/HBaseClassTestRule;
       8: ldc           #56                 // class org/apache/hadoop/hbase/zookeeper/TestZKLeaderManager
      10: invokestatic  #59                 // Method org/slf4j/LoggerFactory.getLogger:(Ljava/lang/Class;)Lorg/slf4j/Logger;
      13: putstatic     #2                  // Field LOG:Lorg/slf4j/Logger;
      16: new           #13                 // class java/lang/StringBuilder
      19: dup
      20: invokespecial #14                 // Method java/lang/StringBuilder."<init>":()V
      23: ldc           #60                 // String /test/
      25: invokevirtual #16                 // Method java/lang/StringBuilder.append:(Ljava/lang/String;)Ljava/lang/StringBuilder;
      28: ldc           #56                 // class org/apache/hadoop/hbase/zookeeper/TestZKLeaderManager
      30: invokevirtual #61                 // Method java/lang/Class.getSimpleName:()Ljava/lang/String;
      33: invokevirtual #16                 // Method java/lang/StringBuilder.append:(Ljava/lang/String;)Ljava/lang/StringBuilder;
      36: invokevirtual #18                 // Method java/lang/StringBuilder.toString:()Ljava/lang/String;
      39: putstatic     #1                  // Field LEADER_ZNODE:Ljava/lang/String;
      42: return
}
