Compiled from "TestAssignmentManagerBase.java"
public class org.apache.hadoop.hbase.master.assignment.TestAssignmentManagerBase$HangThenRSCrashExecutor extends org.apache.hadoop.hbase.master.assignment.TestAssignmentManagerBase$GoodRsExecutor {
  final org.apache.hadoop.hbase.master.assignment.TestAssignmentManagerBase this$0;

  protected org.apache.hadoop.hbase.master.assignment.TestAssignmentManagerBase$HangThenRSCrashExecutor(org.apache.hadoop.hbase.master.assignment.TestAssignmentManagerBase);
    Code:
       0: aload_0
       1: aload_1
       2: putfield      #1                  // Field this$0:Lorg/apache/hadoop/hbase/master/assignment/TestAssignmentManagerBase;
       5: aload_0
       6: aload_1
       7: invokespecial #2                  // Method org/apache/hadoop/hbase/master/assignment/TestAssignmentManagerBase$GoodRsExecutor."<init>":(Lorg/apache/hadoop/hbase/master/assignment/TestAssignmentManagerBase;)V
      10: return

  protected org.apache.hadoop.hbase.shaded.protobuf.generated.AdminProtos$OpenRegionResponse$RegionOpeningState execOpenRegion(org.apache.hadoop.hbase.ServerName, org.apache.hadoop.hbase.shaded.protobuf.generated.AdminProtos$OpenRegionRequest$RegionOpenInfo) throws java.io.IOException;
    Code:
       0: aload_0
       1: dup
       2: getfield      #3                  // Field invocations:I
       5: dup_x1
       6: iconst_1
       7: iadd
       8: putfield      #3                  // Field invocations:I
      11: ifle          21
      14: aload_0
      15: aload_1
      16: aload_2
      17: invokespecial #4                  // Method org/apache/hadoop/hbase/master/assignment/TestAssignmentManagerBase$GoodRsExecutor.execOpenRegion:(Lorg/apache/hadoop/hbase/ServerName;Lorg/apache/hadoop/hbase/shaded/protobuf/generated/AdminProtos$OpenRegionRequest$RegionOpenInfo;)Lorg/apache/hadoop/hbase/shaded/protobuf/generated/AdminProtos$OpenRegionResponse$RegionOpeningState;
      20: areturn
      21: invokestatic  #5                  // Method org/apache/hadoop/hbase/master/assignment/TestAssignmentManagerBase.access$000:()Lorg/slf4j/Logger;
      24: new           #6                  // class java/lang/StringBuilder
      27: dup
      28: invokespecial #7                  // Method java/lang/StringBuilder."<init>":()V
      31: ldc           #8                  // String Return null response from serverName=
      33: invokevirtual #9                  // Method java/lang/StringBuilder.append:(Ljava/lang/String;)Ljava/lang/StringBuilder;
      36: aload_1
      37: invokevirtual #10                 // Method java/lang/StringBuilder.append:(Ljava/lang/Object;)Ljava/lang/StringBuilder;
      40: ldc           #11                 // String ; means STUCK...TODO timeout
      42: invokevirtual #9                  // Method java/lang/StringBuilder.append:(Ljava/lang/String;)Ljava/lang/StringBuilder;
      45: invokevirtual #12                 // Method java/lang/StringBuilder.toString:()Ljava/lang/String;
      48: invokeinterface #13,  2           // InterfaceMethod org/slf4j/Logger.info:(Ljava/lang/String;)V
      53: aload_0
      54: getfield      #1                  // Field this$0:Lorg/apache/hadoop/hbase/master/assignment/TestAssignmentManagerBase;
      57: getfield      #14                 // Field org/apache/hadoop/hbase/master/assignment/TestAssignmentManagerBase.executor:Ljava/util/concurrent/ScheduledExecutorService;
      60: new           #15                 // class org/apache/hadoop/hbase/master/assignment/TestAssignmentManagerBase$HangThenRSCrashExecutor$1
      63: dup
      64: aload_0
      65: aload_1
      66: invokespecial #16                 // Method org/apache/hadoop/hbase/master/assignment/TestAssignmentManagerBase$HangThenRSCrashExecutor$1."<init>":(Lorg/apache/hadoop/hbase/master/assignment/TestAssignmentManagerBase$HangThenRSCrashExecutor;Lorg/apache/hadoop/hbase/ServerName;)V
      69: lconst_1
      70: getstatic     #17                 // Field java/util/concurrent/TimeUnit.SECONDS:Ljava/util/concurrent/TimeUnit;
      73: invokeinterface #18,  5           // InterfaceMethod java/util/concurrent/ScheduledExecutorService.schedule:(Ljava/lang/Runnable;JLjava/util/concurrent/TimeUnit;)Ljava/util/concurrent/ScheduledFuture;
      78: pop
      79: aconst_null
      80: areturn
}
