Compiled from "TestMetricsThriftServerSourceFactoryImpl.java"
public class org.apache.hadoop.hbase.thrift.TestMetricsThriftServerSourceFactoryImpl {
  public static final org.apache.hadoop.hbase.HBaseClassTestRule CLASS_RULE;

  public org.apache.hadoop.hbase.thrift.TestMetricsThriftServerSourceFactoryImpl();
    Code:
       0: aload_0
       1: invokespecial #1                  // Method java/lang/Object."<init>":()V
       4: return

  public void testCompatabilityRegistered();
    Code:
       0: ldc           #2                  // class org/apache/hadoop/hbase/thrift/MetricsThriftServerSourceFactory
       2: invokestatic  #3                  // Method org/apache/hadoop/hbase/CompatibilitySingletonFactory.getInstance:(Ljava/lang/Class;)Ljava/lang/Object;
       5: invokestatic  #4                  // Method org/junit/Assert.assertNotNull:(Ljava/lang/Object;)V
       8: ldc           #2                  // class org/apache/hadoop/hbase/thrift/MetricsThriftServerSourceFactory
      10: invokestatic  #3                  // Method org/apache/hadoop/hbase/CompatibilitySingletonFactory.getInstance:(Ljava/lang/Class;)Ljava/lang/Object;
      13: instanceof    #5                  // class org/apache/hadoop/hbase/thrift/MetricsThriftServerSourceFactoryImpl
      16: invokestatic  #6                  // Method org/junit/Assert.assertTrue:(Z)V
      19: return

  public void testCreateThriftOneSource();
    Code:
       0: new           #5                  // class org/apache/hadoop/hbase/thrift/MetricsThriftServerSourceFactoryImpl
       3: dup
       4: invokespecial #7                  // Method org/apache/hadoop/hbase/thrift/MetricsThriftServerSourceFactoryImpl."<init>":()V
       7: invokevirtual #8                  // Method org/apache/hadoop/hbase/thrift/MetricsThriftServerSourceFactoryImpl.createThriftOneSource:()Lorg/apache/hadoop/hbase/thrift/MetricsThriftServerSource;
      10: new           #5                  // class org/apache/hadoop/hbase/thrift/MetricsThriftServerSourceFactoryImpl
      13: dup
      14: invokespecial #7                  // Method org/apache/hadoop/hbase/thrift/MetricsThriftServerSourceFactoryImpl."<init>":()V
      17: invokevirtual #8                  // Method org/apache/hadoop/hbase/thrift/MetricsThriftServerSourceFactoryImpl.createThriftOneSource:()Lorg/apache/hadoop/hbase/thrift/MetricsThriftServerSource;
      20: invokestatic  #9                  // Method org/junit/Assert.assertSame:(Ljava/lang/Object;Ljava/lang/Object;)V
      23: return

  public void testCreateThriftTwoSource();
    Code:
       0: new           #5                  // class org/apache/hadoop/hbase/thrift/MetricsThriftServerSourceFactoryImpl
       3: dup
       4: invokespecial #7                  // Method org/apache/hadoop/hbase/thrift/MetricsThriftServerSourceFactoryImpl."<init>":()V
       7: invokevirtual #10                 // Method org/apache/hadoop/hbase/thrift/MetricsThriftServerSourceFactoryImpl.createThriftTwoSource:()Lorg/apache/hadoop/hbase/thrift/MetricsThriftServerSource;
      10: new           #5                  // class org/apache/hadoop/hbase/thrift/MetricsThriftServerSourceFactoryImpl
      13: dup
      14: invokespecial #7                  // Method org/apache/hadoop/hbase/thrift/MetricsThriftServerSourceFactoryImpl."<init>":()V
      17: invokevirtual #10                 // Method org/apache/hadoop/hbase/thrift/MetricsThriftServerSourceFactoryImpl.createThriftTwoSource:()Lorg/apache/hadoop/hbase/thrift/MetricsThriftServerSource;
      20: invokestatic  #9                  // Method org/junit/Assert.assertSame:(Ljava/lang/Object;Ljava/lang/Object;)V
      23: return

  static {};
    Code:
       0: ldc           #11                 // class org/apache/hadoop/hbase/thrift/TestMetricsThriftServerSourceFactoryImpl
       2: invokestatic  #12                 // Method org/apache/hadoop/hbase/HBaseClassTestRule.forClass:(Ljava/lang/Class;)Lorg/apache/hadoop/hbase/HBaseClassTestRule;
       5: putstatic     #13                 // Field CLASS_RULE:Lorg/apache/hadoop/hbase/HBaseClassTestRule;
       8: return
}
