Compiled from "TestFavoredNodeTableImport.java"
public class org.apache.hadoop.hbase.master.balancer.TestFavoredNodeTableImport {
  public static final org.apache.hadoop.hbase.HBaseClassTestRule CLASS_RULE;

  public org.apache.hadoop.hbase.master.balancer.TestFavoredNodeTableImport();
    Code:
       0: aload_0
       1: invokespecial #2                  // Method java/lang/Object."<init>":()V
       4: return

  public void stopCluster() throws java.lang.Exception;
    Code:
       0: getstatic     #3                  // Field UTIL:Lorg/apache/hadoop/hbase/HBaseTestingUtility;
       3: invokevirtual #4                  // Method org/apache/hadoop/hbase/HBaseTestingUtility.cleanupTestDir:()Z
       6: pop
       7: getstatic     #3                  // Field UTIL:Lorg/apache/hadoop/hbase/HBaseTestingUtility;
      10: invokevirtual #5                  // Method org/apache/hadoop/hbase/HBaseTestingUtility.shutdownMiniCluster:()V
      13: return

  public void testTableCreation() throws java.lang.Exception;
    Code:
       0: getstatic     #6                  // Field conf:Lorg/apache/hadoop/conf/Configuration;
       3: ldc           #8                  // String hbase.master.loadbalancer.class
       5: ldc           #9                  // class org/apache/hadoop/hbase/master/balancer/StochasticLoadBalancer
       7: invokevirtual #10                 // Method java/lang/Class.getName:()Ljava/lang/String;
      10: invokevirtual #11                 // Method org/apache/hadoop/conf/Configuration.set:(Ljava/lang/String;Ljava/lang/String;)V
      13: getstatic     #12                 // Field LOG:Lorg/slf4j/Logger;
      16: ldc           #13                 // String Starting up cluster
      18: invokeinterface #14,  2           // InterfaceMethod org/slf4j/Logger.info:(Ljava/lang/String;)V
      23: getstatic     #3                  // Field UTIL:Lorg/apache/hadoop/hbase/HBaseTestingUtility;
      26: iconst_3
      27: invokevirtual #16                 // Method org/apache/hadoop/hbase/HBaseTestingUtility.startMiniCluster:(I)Lorg/apache/hadoop/hbase/MiniHBaseCluster;
      30: pop
      31: getstatic     #3                  // Field UTIL:Lorg/apache/hadoop/hbase/HBaseTestingUtility;
      34: invokevirtual #17                 // Method org/apache/hadoop/hbase/HBaseTestingUtility.getMiniHBaseCluster:()Lorg/apache/hadoop/hbase/MiniHBaseCluster;
      37: invokevirtual #18                 // Method org/apache/hadoop/hbase/MiniHBaseCluster.getMaster:()Lorg/apache/hadoop/hbase/master/HMaster;
      40: invokevirtual #19                 // Method org/apache/hadoop/hbase/master/HMaster.isInitialized:()Z
      43: ifne          53
      46: lconst_1
      47: invokestatic  #20                 // Method org/apache/hadoop/hbase/util/Threads.sleep:(J)V
      50: goto          31
      53: getstatic     #3                  // Field UTIL:Lorg/apache/hadoop/hbase/HBaseTestingUtility;
      56: invokevirtual #21                 // Method org/apache/hadoop/hbase/HBaseTestingUtility.getAdmin:()Lorg/apache/hadoop/hbase/client/Admin;
      59: astore_1
      60: aload_1
      61: iconst_0
      62: iconst_1
      63: invokeinterface #22,  3           // InterfaceMethod org/apache/hadoop/hbase/client/Admin.balancerSwitch:(ZZ)Z
      68: pop
      69: ldc           #23                 // String testFNImport
      71: astore_2
      72: new           #24                 // class org/apache/hadoop/hbase/HTableDescriptor
      75: dup
      76: aload_2
      77: invokestatic  #25                 // Method org/apache/hadoop/hbase/TableName.valueOf:(Ljava/lang/String;)Lorg/apache/hadoop/hbase/TableName;
      80: invokespecial #26                 // Method org/apache/hadoop/hbase/HTableDescriptor."<init>":(Lorg/apache/hadoop/hbase/TableName;)V
      83: astore_3
      84: aload_3
      85: new           #27                 // class org/apache/hadoop/hbase/HColumnDescriptor
      88: dup
      89: getstatic     #28                 // Field org/apache/hadoop/hbase/HConstants.CATALOG_FAMILY:[B
      92: invokespecial #29                 // Method org/apache/hadoop/hbase/HColumnDescriptor."<init>":([B)V
      95: invokevirtual #30                 // Method org/apache/hadoop/hbase/HTableDescriptor.addFamily:(Lorg/apache/hadoop/hbase/HColumnDescriptor;)Lorg/apache/hadoop/hbase/HTableDescriptor;
      98: pop
      99: aload_1
     100: aload_3
     101: ldc           #31                 // String a
     103: invokestatic  #32                 // Method org/apache/hadoop/hbase/util/Bytes.toBytes:(Ljava/lang/String;)[B
     106: ldc           #33                 // String z
     108: invokestatic  #32                 // Method org/apache/hadoop/hbase/util/Bytes.toBytes:(Ljava/lang/String;)[B
     111: bipush        20
     113: invokeinterface #34,  5           // InterfaceMethod org/apache/hadoop/hbase/client/Admin.createTable:(Lorg/apache/hadoop/hbase/client/TableDescriptor;[B[BI)V
     118: getstatic     #3                  // Field UTIL:Lorg/apache/hadoop/hbase/HBaseTestingUtility;
     121: aload_3
     122: invokevirtual #35                 // Method org/apache/hadoop/hbase/HTableDescriptor.getTableName:()Lorg/apache/hadoop/hbase/TableName;
     125: invokevirtual #36                 // Method org/apache/hadoop/hbase/HBaseTestingUtility.waitTableAvailable:(Lorg/apache/hadoop/hbase/TableName;)V
     128: getstatic     #12                 // Field LOG:Lorg/slf4j/Logger;
     131: ldc           #37                 // String Shutting down cluster
     133: invokeinterface #14,  2           // InterfaceMethod org/slf4j/Logger.info:(Ljava/lang/String;)V
     138: getstatic     #3                  // Field UTIL:Lorg/apache/hadoop/hbase/HBaseTestingUtility;
     141: invokevirtual #38                 // Method org/apache/hadoop/hbase/HBaseTestingUtility.shutdownMiniHBaseCluster:()V
     144: ldc2_w        #39                 // long 2000l
     147: invokestatic  #41                 // Method java/lang/Thread.sleep:(J)V
     150: getstatic     #12                 // Field LOG:Lorg/slf4j/Logger;
     153: ldc           #42                 // String Starting cluster again with FN Balancer
     155: invokeinterface #14,  2           // InterfaceMethod org/slf4j/Logger.info:(Ljava/lang/String;)V
     160: getstatic     #3                  // Field UTIL:Lorg/apache/hadoop/hbase/HBaseTestingUtility;
     163: invokevirtual #43                 // Method org/apache/hadoop/hbase/HBaseTestingUtility.getConfiguration:()Lorg/apache/hadoop/conf/Configuration;
     166: ldc           #8                  // String hbase.master.loadbalancer.class
     168: ldc           #44                 // class org/apache/hadoop/hbase/master/balancer/FavoredStochasticBalancer
     170: invokevirtual #10                 // Method java/lang/Class.getName:()Ljava/lang/String;
     173: invokevirtual #11                 // Method org/apache/hadoop/conf/Configuration.set:(Ljava/lang/String;Ljava/lang/String;)V
     176: getstatic     #3                  // Field UTIL:Lorg/apache/hadoop/hbase/HBaseTestingUtility;
     179: iconst_3
     180: invokevirtual #45                 // Method org/apache/hadoop/hbase/HBaseTestingUtility.restartHBaseCluster:(I)V
     183: getstatic     #3                  // Field UTIL:Lorg/apache/hadoop/hbase/HBaseTestingUtility;
     186: invokevirtual #17                 // Method org/apache/hadoop/hbase/HBaseTestingUtility.getMiniHBaseCluster:()Lorg/apache/hadoop/hbase/MiniHBaseCluster;
     189: invokevirtual #18                 // Method org/apache/hadoop/hbase/MiniHBaseCluster.getMaster:()Lorg/apache/hadoop/hbase/master/HMaster;
     192: invokevirtual #19                 // Method org/apache/hadoop/hbase/master/HMaster.isInitialized:()Z
     195: ifne          205
     198: lconst_1
     199: invokestatic  #20                 // Method org/apache/hadoop/hbase/util/Threads.sleep:(J)V
     202: goto          183
     205: getstatic     #3                  // Field UTIL:Lorg/apache/hadoop/hbase/HBaseTestingUtility;
     208: invokevirtual #21                 // Method org/apache/hadoop/hbase/HBaseTestingUtility.getAdmin:()Lorg/apache/hadoop/hbase/client/Admin;
     211: astore_1
     212: getstatic     #3                  // Field UTIL:Lorg/apache/hadoop/hbase/HBaseTestingUtility;
     215: aload_3
     216: invokevirtual #35                 // Method org/apache/hadoop/hbase/HTableDescriptor.getTableName:()Lorg/apache/hadoop/hbase/TableName;
     219: invokevirtual #36                 // Method org/apache/hadoop/hbase/HBaseTestingUtility.waitTableAvailable:(Lorg/apache/hadoop/hbase/TableName;)V
     222: getstatic     #3                  // Field UTIL:Lorg/apache/hadoop/hbase/HBaseTestingUtility;
     225: invokevirtual #46                 // Method org/apache/hadoop/hbase/HBaseTestingUtility.getHBaseCluster:()Lorg/apache/hadoop/hbase/MiniHBaseCluster;
     228: invokevirtual #18                 // Method org/apache/hadoop/hbase/MiniHBaseCluster.getMaster:()Lorg/apache/hadoop/hbase/master/HMaster;
     231: invokevirtual #47                 // Method org/apache/hadoop/hbase/master/HMaster.getFavoredNodesManager:()Lorg/apache/hadoop/hbase/favored/FavoredNodesManager;
     234: astore        4
     236: aload_1
     237: aload_2
     238: invokestatic  #25                 // Method org/apache/hadoop/hbase/TableName.valueOf:(Ljava/lang/String;)Lorg/apache/hadoop/hbase/TableName;
     241: invokeinterface #48,  2           // InterfaceMethod org/apache/hadoop/hbase/client/Admin.getRegions:(Lorg/apache/hadoop/hbase/TableName;)Ljava/util/List;
     246: astore        5
     248: aload         5
     250: invokeinterface #49,  1           // InterfaceMethod java/util/List.iterator:()Ljava/util/Iterator;
     255: astore        6
     257: aload         6
     259: invokeinterface #50,  1           // InterfaceMethod java/util/Iterator.hasNext:()Z
     264: ifeq          380
     267: aload         6
     269: invokeinterface #51,  1           // InterfaceMethod java/util/Iterator.next:()Ljava/lang/Object;
     274: checkcast     #52                 // class org/apache/hadoop/hbase/client/RegionInfo
     277: astore        7
     279: aload         4
     281: aload         7
     283: invokevirtual #53                 // Method org/apache/hadoop/hbase/favored/FavoredNodesManager.getFavoredNodes:(Lorg/apache/hadoop/hbase/client/RegionInfo;)Ljava/util/List;
     286: invokestatic  #54                 // Method org/apache/hbase/thirdparty/com/google/common/collect/Sets.newHashSet:(Ljava/lang/Iterable;)Ljava/util/HashSet;
     289: astore        8
     291: aload         8
     293: invokestatic  #55                 // Method org/junit/Assert.assertNotNull:(Ljava/lang/Object;)V
     296: ldc           #56                 // String Required no of favored nodes not found.
     298: ldc2_w        #57                 // long 3l
     301: aload         8
     303: invokeinterface #59,  1           // InterfaceMethod java/util/Set.size:()I
     308: i2l
     309: invokestatic  #60                 // Method org/junit/Assert.assertEquals:(Ljava/lang/String;JJ)V
     312: aload         8
     314: invokeinterface #61,  1           // InterfaceMethod java/util/Set.iterator:()Ljava/util/Iterator;
     319: astore        9
     321: aload         9
     323: invokeinterface #50,  1           // InterfaceMethod java/util/Iterator.hasNext:()Z
     328: ifeq          377
     331: aload         9
     333: invokeinterface #51,  1           // InterfaceMethod java/util/Iterator.next:()Ljava/lang/Object;
     338: checkcast     #62                 // class org/apache/hadoop/hbase/ServerName
     341: astore        10
     343: new           #63                 // class java/lang/StringBuilder
     346: dup
     347: invokespecial #64                 // Method java/lang/StringBuilder."<init>":()V
     350: ldc           #65                 // String StartCode invalid for:
     352: invokevirtual #66                 // Method java/lang/StringBuilder.append:(Ljava/lang/String;)Ljava/lang/StringBuilder;
     355: aload         10
     357: invokevirtual #67                 // Method java/lang/StringBuilder.append:(Ljava/lang/Object;)Ljava/lang/StringBuilder;
     360: invokevirtual #68                 // Method java/lang/StringBuilder.toString:()Ljava/lang/String;
     363: ldc2_w        #69                 // long -1l
     366: aload         10
     368: invokevirtual #71                 // Method org/apache/hadoop/hbase/ServerName.getStartcode:()J
     371: invokestatic  #60                 // Method org/junit/Assert.assertEquals:(Ljava/lang/String;JJ)V
     374: goto          321
     377: goto          257
     380: return

  static {};
    Code:
       0: ldc           #15                 // class org/apache/hadoop/hbase/master/balancer/TestFavoredNodeTableImport
       2: invokestatic  #72                 // Method org/apache/hadoop/hbase/HBaseClassTestRule.forClass:(Ljava/lang/Class;)Lorg/apache/hadoop/hbase/HBaseClassTestRule;
       5: putstatic     #73                 // Field CLASS_RULE:Lorg/apache/hadoop/hbase/HBaseClassTestRule;
       8: ldc           #15                 // class org/apache/hadoop/hbase/master/balancer/TestFavoredNodeTableImport
      10: invokestatic  #74                 // Method org/slf4j/LoggerFactory.getLogger:(Ljava/lang/Class;)Lorg/slf4j/Logger;
      13: putstatic     #12                 // Field LOG:Lorg/slf4j/Logger;
      16: new           #75                 // class org/apache/hadoop/hbase/HBaseTestingUtility
      19: dup
      20: invokespecial #76                 // Method org/apache/hadoop/hbase/HBaseTestingUtility."<init>":()V
      23: putstatic     #3                  // Field UTIL:Lorg/apache/hadoop/hbase/HBaseTestingUtility;
      26: getstatic     #3                  // Field UTIL:Lorg/apache/hadoop/hbase/HBaseTestingUtility;
      29: invokevirtual #43                 // Method org/apache/hadoop/hbase/HBaseTestingUtility.getConfiguration:()Lorg/apache/hadoop/conf/Configuration;
      32: putstatic     #6                  // Field conf:Lorg/apache/hadoop/conf/Configuration;
      35: return
}
