Compiled from "TestAsyncProcess.java"
class org.apache.hadoop.hbase.client.TestAsyncProcess$MyAsyncProcess extends org.apache.hadoop.hbase.client.AsyncProcess {
  final java.util.concurrent.atomic.AtomicInteger nbMultiResponse;

  final java.util.concurrent.atomic.AtomicInteger nbActions;

  public java.util.List<org.apache.hadoop.hbase.client.AsyncRequestFuture> allReqs;

  public java.util.concurrent.atomic.AtomicInteger callsCt;

  final java.util.concurrent.ExecutorService service;

  protected <Res> org.apache.hadoop.hbase.client.AsyncRequestFutureImpl<Res> createAsyncRequestFuture(org.apache.hadoop.hbase.client.AsyncProcessTask, java.util.List<org.apache.hadoop.hbase.client.Action>, long);
    Code:
       0: new           #2                  // class org/apache/hadoop/hbase/client/TestAsyncProcess$MyAsyncProcess$1
       3: dup
       4: aload_0
       5: aload_1
       6: invokespecial #3                  // Method org/apache/hadoop/hbase/client/TestAsyncProcess$MyAsyncProcess$1."<init>":(Lorg/apache/hadoop/hbase/client/TestAsyncProcess$MyAsyncProcess;Lorg/apache/hadoop/hbase/client/AsyncProcessTask;)V
       9: astore        5
      11: new           #4                  // class org/apache/hadoop/hbase/client/TestAsyncProcess$MyAsyncRequestFutureImpl
      14: dup
      15: aload         5
      17: aload_2
      18: lload_3
      19: aload_0
      20: invokespecial #5                  // Method org/apache/hadoop/hbase/client/TestAsyncProcess$MyAsyncRequestFutureImpl."<init>":(Lorg/apache/hadoop/hbase/client/AsyncProcessTask;Ljava/util/List;JLorg/apache/hadoop/hbase/client/AsyncProcess;)V
      23: astore        6
      25: aload_0
      26: getfield      #6                  // Field allReqs:Ljava/util/List;
      29: aload         6
      31: invokeinterface #7,  2            // InterfaceMethod java/util/List.add:(Ljava/lang/Object;)Z
      36: pop
      37: aload         6
      39: areturn

  public org.apache.hadoop.hbase.client.TestAsyncProcess$MyAsyncProcess(org.apache.hadoop.hbase.client.ClusterConnection, org.apache.hadoop.conf.Configuration);
    Code:
       0: aload_0
       1: aload_1
       2: aload_2
       3: new           #8                  // class org/apache/hadoop/hbase/client/RpcRetryingCallerFactory
       6: dup
       7: aload_2
       8: invokespecial #9                  // Method org/apache/hadoop/hbase/client/RpcRetryingCallerFactory."<init>":(Lorg/apache/hadoop/conf/Configuration;)V
      11: new           #10                 // class org/apache/hadoop/hbase/ipc/RpcControllerFactory
      14: dup
      15: aload_2
      16: invokespecial #11                 // Method org/apache/hadoop/hbase/ipc/RpcControllerFactory."<init>":(Lorg/apache/hadoop/conf/Configuration;)V
      19: invokespecial #12                 // Method org/apache/hadoop/hbase/client/AsyncProcess."<init>":(Lorg/apache/hadoop/hbase/client/ClusterConnection;Lorg/apache/hadoop/conf/Configuration;Lorg/apache/hadoop/hbase/client/RpcRetryingCallerFactory;Lorg/apache/hadoop/hbase/ipc/RpcControllerFactory;)V
      22: aload_0
      23: new           #13                 // class java/util/concurrent/atomic/AtomicInteger
      26: dup
      27: invokespecial #14                 // Method java/util/concurrent/atomic/AtomicInteger."<init>":()V
      30: putfield      #15                 // Field nbMultiResponse:Ljava/util/concurrent/atomic/AtomicInteger;
      33: aload_0
      34: new           #13                 // class java/util/concurrent/atomic/AtomicInteger
      37: dup
      38: invokespecial #14                 // Method java/util/concurrent/atomic/AtomicInteger."<init>":()V
      41: putfield      #16                 // Field nbActions:Ljava/util/concurrent/atomic/AtomicInteger;
      44: aload_0
      45: new           #17                 // class java/util/ArrayList
      48: dup
      49: invokespecial #18                 // Method java/util/ArrayList."<init>":()V
      52: putfield      #6                  // Field allReqs:Ljava/util/List;
      55: aload_0
      56: new           #13                 // class java/util/concurrent/atomic/AtomicInteger
      59: dup
      60: invokespecial #14                 // Method java/util/concurrent/atomic/AtomicInteger."<init>":()V
      63: putfield      #19                 // Field callsCt:Ljava/util/concurrent/atomic/AtomicInteger;
      66: aload_0
      67: ldc2_w        #20                 // long -1l
      70: putfield      #1                  // Field previousTimeout:J
      73: aload_0
      74: iconst_5
      75: invokestatic  #22                 // Method java/util/concurrent/Executors.newFixedThreadPool:(I)Ljava/util/concurrent/ExecutorService;
      78: putfield      #23                 // Field service:Ljava/util/concurrent/ExecutorService;
      81: aload_0
      82: aload_2
      83: putfield      #24                 // Field conf:Lorg/apache/hadoop/conf/Configuration;
      86: return

  public org.apache.hadoop.hbase.client.TestAsyncProcess$MyAsyncProcess(org.apache.hadoop.hbase.client.ClusterConnection, org.apache.hadoop.conf.Configuration, java.util.concurrent.atomic.AtomicInteger);
    Code:
       0: aload_0
       1: aload_1
       2: aload_2
       3: new           #8                  // class org/apache/hadoop/hbase/client/RpcRetryingCallerFactory
       6: dup
       7: aload_2
       8: invokespecial #9                  // Method org/apache/hadoop/hbase/client/RpcRetryingCallerFactory."<init>":(Lorg/apache/hadoop/conf/Configuration;)V
      11: new           #10                 // class org/apache/hadoop/hbase/ipc/RpcControllerFactory
      14: dup
      15: aload_2
      16: invokespecial #11                 // Method org/apache/hadoop/hbase/ipc/RpcControllerFactory."<init>":(Lorg/apache/hadoop/conf/Configuration;)V
      19: invokespecial #12                 // Method org/apache/hadoop/hbase/client/AsyncProcess."<init>":(Lorg/apache/hadoop/hbase/client/ClusterConnection;Lorg/apache/hadoop/conf/Configuration;Lorg/apache/hadoop/hbase/client/RpcRetryingCallerFactory;Lorg/apache/hadoop/hbase/ipc/RpcControllerFactory;)V
      22: aload_0
      23: new           #13                 // class java/util/concurrent/atomic/AtomicInteger
      26: dup
      27: invokespecial #14                 // Method java/util/concurrent/atomic/AtomicInteger."<init>":()V
      30: putfield      #15                 // Field nbMultiResponse:Ljava/util/concurrent/atomic/AtomicInteger;
      33: aload_0
      34: new           #13                 // class java/util/concurrent/atomic/AtomicInteger
      37: dup
      38: invokespecial #14                 // Method java/util/concurrent/atomic/AtomicInteger."<init>":()V
      41: putfield      #16                 // Field nbActions:Ljava/util/concurrent/atomic/AtomicInteger;
      44: aload_0
      45: new           #17                 // class java/util/ArrayList
      48: dup
      49: invokespecial #18                 // Method java/util/ArrayList."<init>":()V
      52: putfield      #6                  // Field allReqs:Ljava/util/List;
      55: aload_0
      56: new           #13                 // class java/util/concurrent/atomic/AtomicInteger
      59: dup
      60: invokespecial #14                 // Method java/util/concurrent/atomic/AtomicInteger."<init>":()V
      63: putfield      #19                 // Field callsCt:Ljava/util/concurrent/atomic/AtomicInteger;
      66: aload_0
      67: ldc2_w        #20                 // long -1l
      70: putfield      #1                  // Field previousTimeout:J
      73: aload_0
      74: new           #25                 // class java/util/concurrent/ThreadPoolExecutor
      77: dup
      78: iconst_1
      79: bipush        20
      81: ldc2_w        #26                 // long 60l
      84: getstatic     #28                 // Field java/util/concurrent/TimeUnit.SECONDS:Ljava/util/concurrent/TimeUnit;
      87: new           #29                 // class java/util/concurrent/SynchronousQueue
      90: dup
      91: invokespecial #30                 // Method java/util/concurrent/SynchronousQueue."<init>":()V
      94: new           #31                 // class org/apache/hadoop/hbase/client/TestAsyncProcess$CountingThreadFactory
      97: dup
      98: aload_3
      99: invokespecial #32                 // Method org/apache/hadoop/hbase/client/TestAsyncProcess$CountingThreadFactory."<init>":(Ljava/util/concurrent/atomic/AtomicInteger;)V
     102: invokespecial #33                 // Method java/util/concurrent/ThreadPoolExecutor."<init>":(IIJLjava/util/concurrent/TimeUnit;Ljava/util/concurrent/BlockingQueue;Ljava/util/concurrent/ThreadFactory;)V
     105: putfield      #23                 // Field service:Ljava/util/concurrent/ExecutorService;
     108: return

  public <CResult> org.apache.hadoop.hbase.client.AsyncRequestFuture submit(java.util.concurrent.ExecutorService, org.apache.hadoop.hbase.TableName, java.util.List<? extends org.apache.hadoop.hbase.client.Row>, boolean, org.apache.hadoop.hbase.client.coprocessor.Batch$Callback<CResult>, boolean) throws java.io.InterruptedIOException;
    Code:
       0: aload         5
       2: invokestatic  #34                 // Method org/apache/hadoop/hbase/client/AsyncProcessTask.newBuilder:(Lorg/apache/hadoop/hbase/client/coprocessor/Batch$Callback;)Lorg/apache/hadoop/hbase/client/AsyncProcessTask$Builder;
       5: aload_1
       6: ifnonnull     16
       9: aload_0
      10: getfield      #23                 // Field service:Ljava/util/concurrent/ExecutorService;
      13: goto          17
      16: aload_1
      17: invokevirtual #35                 // Method org/apache/hadoop/hbase/client/AsyncProcessTask$Builder.setPool:(Ljava/util/concurrent/ExecutorService;)Lorg/apache/hadoop/hbase/client/AsyncProcessTask$Builder;
      20: aload_2
      21: invokevirtual #36                 // Method org/apache/hadoop/hbase/client/AsyncProcessTask$Builder.setTableName:(Lorg/apache/hadoop/hbase/TableName;)Lorg/apache/hadoop/hbase/client/AsyncProcessTask$Builder;
      24: aload_3
      25: invokevirtual #37                 // Method org/apache/hadoop/hbase/client/AsyncProcessTask$Builder.setRowAccess:(Ljava/util/List;)Lorg/apache/hadoop/hbase/client/AsyncProcessTask$Builder;
      28: iload         4
      30: ifeq          39
      33: getstatic     #38                 // Field org/apache/hadoop/hbase/client/AsyncProcessTask$SubmittedRows.AT_LEAST_ONE:Lorg/apache/hadoop/hbase/client/AsyncProcessTask$SubmittedRows;
      36: goto          42
      39: getstatic     #39                 // Field org/apache/hadoop/hbase/client/AsyncProcessTask$SubmittedRows.NORMAL:Lorg/apache/hadoop/hbase/client/AsyncProcessTask$SubmittedRows;
      42: invokevirtual #40                 // Method org/apache/hadoop/hbase/client/AsyncProcessTask$Builder.setSubmittedRows:(Lorg/apache/hadoop/hbase/client/AsyncProcessTask$SubmittedRows;)Lorg/apache/hadoop/hbase/client/AsyncProcessTask$Builder;
      45: iload         6
      47: invokevirtual #41                 // Method org/apache/hadoop/hbase/client/AsyncProcessTask$Builder.setNeedResults:(Z)Lorg/apache/hadoop/hbase/client/AsyncProcessTask$Builder;
      50: aload_0
      51: getfield      #24                 // Field conf:Lorg/apache/hadoop/conf/Configuration;
      54: ldc           #43                 // String hbase.rpc.read.timeout
      56: ldc           #44                 // int 60000
      58: invokevirtual #45                 // Method org/apache/hadoop/conf/Configuration.getInt:(Ljava/lang/String;I)I
      61: invokevirtual #46                 // Method org/apache/hadoop/hbase/client/AsyncProcessTask$Builder.setRpcTimeout:(I)Lorg/apache/hadoop/hbase/client/AsyncProcessTask$Builder;
      64: aload_0
      65: getfield      #24                 // Field conf:Lorg/apache/hadoop/conf/Configuration;
      68: ldc           #47                 // String hbase.client.operation.timeout
      70: ldc           #48                 // int 1200000
      72: invokevirtual #45                 // Method org/apache/hadoop/conf/Configuration.getInt:(Ljava/lang/String;I)I
      75: invokevirtual #49                 // Method org/apache/hadoop/hbase/client/AsyncProcessTask$Builder.setOperationTimeout:(I)Lorg/apache/hadoop/hbase/client/AsyncProcessTask$Builder;
      78: invokevirtual #50                 // Method org/apache/hadoop/hbase/client/AsyncProcessTask$Builder.build:()Lorg/apache/hadoop/hbase/client/AsyncProcessTask;
      81: astore        7
      83: aload_0
      84: aload         7
      86: invokevirtual #51                 // Method submit:(Lorg/apache/hadoop/hbase/client/AsyncProcessTask;)Lorg/apache/hadoop/hbase/client/AsyncRequestFuture;
      89: areturn

  public <CResult> org.apache.hadoop.hbase.client.AsyncRequestFuture submit(org.apache.hadoop.hbase.TableName, java.util.List<? extends org.apache.hadoop.hbase.client.Row>, boolean, org.apache.hadoop.hbase.client.coprocessor.Batch$Callback<CResult>, boolean) throws java.io.InterruptedIOException;
    Code:
       0: aload_0
       1: aconst_null
       2: aload_1
       3: aload_2
       4: iload_3
       5: aload         4
       7: iload         5
       9: invokevirtual #52                 // Method submit:(Ljava/util/concurrent/ExecutorService;Lorg/apache/hadoop/hbase/TableName;Ljava/util/List;ZLorg/apache/hadoop/hbase/client/coprocessor/Batch$Callback;Z)Lorg/apache/hadoop/hbase/client/AsyncRequestFuture;
      12: areturn

  public <Res> org.apache.hadoop.hbase.client.AsyncRequestFuture submit(org.apache.hadoop.hbase.client.AsyncProcessTask<Res>) throws java.io.InterruptedIOException;
    Code:
       0: aload_0
       1: aload_1
       2: invokevirtual #53                 // Method org/apache/hadoop/hbase/client/AsyncProcessTask.getRpcTimeout:()I
       5: i2l
       6: putfield      #1                  // Field previousTimeout:J
       9: new           #54                 // class org/apache/hadoop/hbase/client/TestAsyncProcess$MyAsyncProcess$2
      12: dup
      13: aload_0
      14: aload_1
      15: invokespecial #55                 // Method org/apache/hadoop/hbase/client/TestAsyncProcess$MyAsyncProcess$2."<init>":(Lorg/apache/hadoop/hbase/client/TestAsyncProcess$MyAsyncProcess;Lorg/apache/hadoop/hbase/client/AsyncProcessTask;)V
      18: astore_2
      19: aload_0
      20: aload_2
      21: invokespecial #56                 // Method org/apache/hadoop/hbase/client/AsyncProcess.submit:(Lorg/apache/hadoop/hbase/client/AsyncProcessTask;)Lorg/apache/hadoop/hbase/client/AsyncRequestFuture;
      24: areturn

  protected org.apache.hadoop.hbase.client.RpcRetryingCaller<org.apache.hadoop.hbase.client.AbstractResponse> createCaller(org.apache.hadoop.hbase.client.CancellableRegionServerCallable, int);
    Code:
       0: aload_0
       1: getfield      #19                 // Field callsCt:Ljava/util/concurrent/atomic/AtomicInteger;
       4: invokevirtual #57                 // Method java/util/concurrent/atomic/AtomicInteger.incrementAndGet:()I
       7: pop
       8: aload_1
       9: checkcast     #58                 // class org/apache/hadoop/hbase/client/MultiServerCallable
      12: astore_3
      13: aload_3
      14: invokevirtual #59                 // Method org/apache/hadoop/hbase/client/MultiServerCallable.getMulti:()Lorg/apache/hadoop/hbase/client/MultiAction;
      17: aload_0
      18: getfield      #15                 // Field nbMultiResponse:Ljava/util/concurrent/atomic/AtomicInteger;
      21: aload_0
      22: getfield      #16                 // Field nbActions:Ljava/util/concurrent/atomic/AtomicInteger;
      25: new           #60                 // class org/apache/hadoop/hbase/client/TestAsyncProcess$MyAsyncProcess$3
      28: dup
      29: aload_0
      30: invokespecial #61                 // Method org/apache/hadoop/hbase/client/TestAsyncProcess$MyAsyncProcess$3."<init>":(Lorg/apache/hadoop/hbase/client/TestAsyncProcess$MyAsyncProcess;)V
      33: invokestatic  #62                 // Method org/apache/hadoop/hbase/client/TestAsyncProcess.createMultiResponse:(Lorg/apache/hadoop/hbase/client/MultiAction;Ljava/util/concurrent/atomic/AtomicInteger;Ljava/util/concurrent/atomic/AtomicInteger;Lorg/apache/hadoop/hbase/client/TestAsyncProcess$ResponseGenerator;)Lorg/apache/hadoop/hbase/client/MultiResponse;
      36: astore        4
      38: new           #63                 // class org/apache/hadoop/hbase/client/TestAsyncProcess$MyAsyncProcess$4
      41: dup
      42: aload_0
      43: ldc2_w        #64                 // long 100l
      46: ldc2_w        #66                 // long 500l
      49: bipush        10
      51: bipush        9
      53: aload         4
      55: invokespecial #68                 // Method org/apache/hadoop/hbase/client/TestAsyncProcess$MyAsyncProcess$4."<init>":(Lorg/apache/hadoop/hbase/client/TestAsyncProcess$MyAsyncProcess;JJIILorg/apache/hadoop/hbase/client/MultiResponse;)V
      58: areturn

  static long access$1000(org.apache.hadoop.hbase.client.TestAsyncProcess$MyAsyncProcess);
    Code:
       0: aload_0
       1: getfield      #1                  // Field previousTimeout:J
       4: lreturn

  static long access$1002(org.apache.hadoop.hbase.client.TestAsyncProcess$MyAsyncProcess, long);
    Code:
       0: aload_0
       1: lload_1
       2: dup2_x1
       3: putfield      #1                  // Field previousTimeout:J
       6: lreturn
}
