Compiled from "TestHRegion.java"
class org.apache.hadoop.hbase.regionserver.TestHRegion$13 implements java.lang.Runnable {
  final java.util.concurrent.atomic.AtomicBoolean val$stopped;

  final org.apache.hadoop.hbase.regionserver.TestHRegion this$0;

  org.apache.hadoop.hbase.regionserver.TestHRegion$13(org.apache.hadoop.hbase.regionserver.TestHRegion, java.util.concurrent.atomic.AtomicBoolean);
    Code:
       0: aload_0
       1: aload_1
       2: putfield      #1                  // Field this$0:Lorg/apache/hadoop/hbase/regionserver/TestHRegion;
       5: aload_0
       6: aload_2
       7: putfield      #2                  // Field val$stopped:Ljava/util/concurrent/atomic/AtomicBoolean;
      10: aload_0
      11: invokespecial #3                  // Method java/lang/Object."<init>":()V
      14: return

  public void run();
    Code:
       0: aload_0
       1: getfield      #1                  // Field this$0:Lorg/apache/hadoop/hbase/regionserver/TestHRegion;
       4: getfield      #4                  // Field org/apache/hadoop/hbase/regionserver/TestHRegion.region:Lorg/apache/hadoop/hbase/regionserver/HRegion;
       7: getfield      #5                  // Field org/apache/hadoop/hbase/regionserver/HRegion.lock:Ljava/util/concurrent/locks/ReentrantReadWriteLock;
      10: invokevirtual #6                  // Method java/util/concurrent/locks/ReentrantReadWriteLock.writeLock:()Ljava/util/concurrent/locks/ReentrantReadWriteLock$WriteLock;
      13: invokevirtual #7                  // Method java/util/concurrent/locks/ReentrantReadWriteLock$WriteLock.lock:()V
      16: aload_0
      17: getfield      #2                  // Field val$stopped:Ljava/util/concurrent/atomic/AtomicBoolean;
      20: iconst_0
      21: invokevirtual #8                  // Method java/util/concurrent/atomic/AtomicBoolean.set:(Z)V
      24: aload_0
      25: getfield      #2                  // Field val$stopped:Ljava/util/concurrent/atomic/AtomicBoolean;
      28: invokevirtual #9                  // Method java/util/concurrent/atomic/AtomicBoolean.get:()Z
      31: ifne          43
      34: ldc2_w        #10                 // long 100l
      37: invokestatic  #12                 // Method java/lang/Thread.sleep:(J)V
      40: goto          24
      43: aload_0
      44: getfield      #1                  // Field this$0:Lorg/apache/hadoop/hbase/regionserver/TestHRegion;
      47: getfield      #4                  // Field org/apache/hadoop/hbase/regionserver/TestHRegion.region:Lorg/apache/hadoop/hbase/regionserver/HRegion;
      50: getfield      #5                  // Field org/apache/hadoop/hbase/regionserver/HRegion.lock:Ljava/util/concurrent/locks/ReentrantReadWriteLock;
      53: invokevirtual #6                  // Method java/util/concurrent/locks/ReentrantReadWriteLock.writeLock:()Ljava/util/concurrent/locks/ReentrantReadWriteLock$WriteLock;
      56: invokevirtual #13                 // Method java/util/concurrent/locks/ReentrantReadWriteLock$WriteLock.unlock:()V
      59: goto          101
      62: astore_1
      63: aload_0
      64: getfield      #1                  // Field this$0:Lorg/apache/hadoop/hbase/regionserver/TestHRegion;
      67: getfield      #4                  // Field org/apache/hadoop/hbase/regionserver/TestHRegion.region:Lorg/apache/hadoop/hbase/regionserver/HRegion;
      70: getfield      #5                  // Field org/apache/hadoop/hbase/regionserver/HRegion.lock:Ljava/util/concurrent/locks/ReentrantReadWriteLock;
      73: invokevirtual #6                  // Method java/util/concurrent/locks/ReentrantReadWriteLock.writeLock:()Ljava/util/concurrent/locks/ReentrantReadWriteLock$WriteLock;
      76: invokevirtual #13                 // Method java/util/concurrent/locks/ReentrantReadWriteLock$WriteLock.unlock:()V
      79: goto          101
      82: astore_2
      83: aload_0
      84: getfield      #1                  // Field this$0:Lorg/apache/hadoop/hbase/regionserver/TestHRegion;
      87: getfield      #4                  // Field org/apache/hadoop/hbase/regionserver/TestHRegion.region:Lorg/apache/hadoop/hbase/regionserver/HRegion;
      90: getfield      #5                  // Field org/apache/hadoop/hbase/regionserver/HRegion.lock:Ljava/util/concurrent/locks/ReentrantReadWriteLock;
      93: invokevirtual #6                  // Method java/util/concurrent/locks/ReentrantReadWriteLock.writeLock:()Ljava/util/concurrent/locks/ReentrantReadWriteLock$WriteLock;
      96: invokevirtual #13                 // Method java/util/concurrent/locks/ReentrantReadWriteLock$WriteLock.unlock:()V
      99: aload_2
     100: athrow
     101: return
    Exception table:
       from    to  target type
           0    43    62   Class java/lang/InterruptedException
           0    43    82   any
}
