Compiled from "TestConstraint.java"
public class org.apache.hadoop.hbase.constraint.TestConstraint$CheckWasRunConstraint extends org.apache.hadoop.hbase.constraint.BaseConstraint {
  public static boolean wasRun;

  public org.apache.hadoop.hbase.constraint.TestConstraint$CheckWasRunConstraint();
    Code:
       0: aload_0
       1: invokespecial #1                  // Method org/apache/hadoop/hbase/constraint/BaseConstraint."<init>":()V
       4: return

  public void check(org.apache.hadoop.hbase.client.Put);
    Code:
       0: iconst_1
       1: putstatic     #2                  // Field wasRun:Z
       4: return

  static {};
    Code:
       0: iconst_0
       1: putstatic     #2                  // Field wasRun:Z
       4: return
}
