Compiled from "TestNamespaceAuditor.java"
public class org.apache.hadoop.hbase.namespace.TestNamespaceAuditor$MasterSyncObserver implements org.apache.hadoop.hbase.coprocessor.MasterCoprocessor,org.apache.hadoop.hbase.coprocessor.MasterObserver {
  volatile java.util.concurrent.CountDownLatch tableDeletionLatch;

  static boolean throwExceptionInPreCreateTableAction;

  public org.apache.hadoop.hbase.namespace.TestNamespaceAuditor$MasterSyncObserver();
    Code:
       0: aload_0
       1: invokespecial #1                  // Method java/lang/Object."<init>":()V
       4: return

  public java.util.Optional<org.apache.hadoop.hbase.coprocessor.MasterObserver> getMasterObserver();
    Code:
       0: aload_0
       1: invokestatic  #2                  // Method java/util/Optional.of:(Ljava/lang/Object;)Ljava/util/Optional;
       4: areturn

  public void preDeleteTable(org.apache.hadoop.hbase.coprocessor.ObserverContext<org.apache.hadoop.hbase.coprocessor.MasterCoprocessorEnvironment>, org.apache.hadoop.hbase.TableName) throws java.io.IOException;
    Code:
       0: aload_0
       1: new           #3                  // class java/util/concurrent/CountDownLatch
       4: dup
       5: iconst_1
       6: invokespecial #4                  // Method java/util/concurrent/CountDownLatch."<init>":(I)V
       9: putfield      #5                  // Field tableDeletionLatch:Ljava/util/concurrent/CountDownLatch;
      12: return

  public void postCompletedDeleteTableAction(org.apache.hadoop.hbase.coprocessor.ObserverContext<org.apache.hadoop.hbase.coprocessor.MasterCoprocessorEnvironment>, org.apache.hadoop.hbase.TableName) throws java.io.IOException;
    Code:
       0: aload_0
       1: getfield      #5                  // Field tableDeletionLatch:Ljava/util/concurrent/CountDownLatch;
       4: invokevirtual #6                  // Method java/util/concurrent/CountDownLatch.countDown:()V
       7: return

  public void preCreateTableAction(org.apache.hadoop.hbase.coprocessor.ObserverContext<org.apache.hadoop.hbase.coprocessor.MasterCoprocessorEnvironment>, org.apache.hadoop.hbase.client.TableDescriptor, org.apache.hadoop.hbase.client.RegionInfo[]) throws java.io.IOException;
    Code:
       0: getstatic     #7                  // Field throwExceptionInPreCreateTableAction:Z
       3: ifeq          16
       6: new           #8                  // class java/io/IOException
       9: dup
      10: ldc           #9                  // String Throw exception as it is demanded.
      12: invokespecial #10                 // Method java/io/IOException."<init>":(Ljava/lang/String;)V
      15: athrow
      16: return
}
