Compiled from "TestProcedureBypass.java"
public class org.apache.hadoop.hbase.procedure2.TestProcedureBypass$SuspendProcedure extends org.apache.hadoop.hbase.procedure2.ProcedureTestingUtility$NoopProcedure<org.apache.hadoop.hbase.procedure2.TestProcedureBypass$TestProcEnv> {
  public org.apache.hadoop.hbase.procedure2.TestProcedureBypass$SuspendProcedure();
    Code:
       0: aload_0
       1: invokespecial #1                  // Method org/apache/hadoop/hbase/procedure2/ProcedureTestingUtility$NoopProcedure."<init>":()V
       4: return

  protected org.apache.hadoop.hbase.procedure2.Procedure[] execute(org.apache.hadoop.hbase.procedure2.TestProcedureBypass$TestProcEnv) throws org.apache.hadoop.hbase.procedure2.ProcedureSuspendedException;
    Code:
       0: new           #2                  // class org/apache/hadoop/hbase/procedure2/ProcedureSuspendedException
       3: dup
       4: invokespecial #3                  // Method org/apache/hadoop/hbase/procedure2/ProcedureSuspendedException."<init>":()V
       7: athrow

  protected org.apache.hadoop.hbase.procedure2.Procedure[] execute(java.lang.Object) throws org.apache.hadoop.hbase.procedure2.ProcedureYieldException, org.apache.hadoop.hbase.procedure2.ProcedureSuspendedException, java.lang.InterruptedException;
    Code:
       0: aload_0
       1: aload_1
       2: checkcast     #4                  // class org/apache/hadoop/hbase/procedure2/TestProcedureBypass$TestProcEnv
       5: invokevirtual #5                  // Method execute:(Lorg/apache/hadoop/hbase/procedure2/TestProcedureBypass$TestProcEnv;)[Lorg/apache/hadoop/hbase/procedure2/Procedure;
       8: areturn
}
