Compiled from "TestWakeUpUnexpectedProcedure.java"
final class org.apache.hadoop.hbase.master.assignment.TestWakeUpUnexpectedProcedure$RSRpcServicesForTest extends org.apache.hadoop.hbase.regionserver.RSRpcServices {
  public org.apache.hadoop.hbase.master.assignment.TestWakeUpUnexpectedProcedure$RSRpcServicesForTest(org.apache.hadoop.hbase.regionserver.HRegionServer) throws java.io.IOException;
    Code:
       0: aload_0
       1: aload_1
       2: invokespecial #1                  // Method org/apache/hadoop/hbase/regionserver/RSRpcServices."<init>":(Lorg/apache/hadoop/hbase/regionserver/HRegionServer;)V
       5: return

  public org.apache.hadoop.hbase.shaded.protobuf.generated.AdminProtos$ExecuteProceduresResponse executeProcedures(org.apache.hbase.thirdparty.com.google.protobuf.RpcController, org.apache.hadoop.hbase.shaded.protobuf.generated.AdminProtos$ExecuteProceduresRequest) throws org.apache.hbase.thirdparty.com.google.protobuf.ServiceException;
    Code:
       0: aload_2
       1: invokevirtual #2                  // Method org/apache/hadoop/hbase/shaded/protobuf/generated/AdminProtos$ExecuteProceduresRequest.getOpenRegionCount:()I
       4: ifle          71
       7: invokestatic  #3                  // Method org/apache/hadoop/hbase/master/assignment/TestWakeUpUnexpectedProcedure.access$000:()Ljava/util/concurrent/CountDownLatch;
      10: ifnull        71
      13: aload_0
      14: getfield      #4                  // Field regionServer:Lorg/apache/hadoop/hbase/regionserver/HRegionServer;
      17: invokevirtual #5                  // Method org/apache/hadoop/hbase/regionserver/HRegionServer.getServerName:()Lorg/apache/hadoop/hbase/ServerName;
      20: invokestatic  #6                  // Method org/apache/hadoop/hbase/master/assignment/TestWakeUpUnexpectedProcedure.access$102:(Lorg/apache/hadoop/hbase/ServerName;)Lorg/apache/hadoop/hbase/ServerName;
      23: pop
      24: invokestatic  #3                  // Method org/apache/hadoop/hbase/master/assignment/TestWakeUpUnexpectedProcedure.access$000:()Ljava/util/concurrent/CountDownLatch;
      27: invokevirtual #7                  // Method java/util/concurrent/CountDownLatch.countDown:()V
      30: aconst_null
      31: invokestatic  #8                  // Method org/apache/hadoop/hbase/master/assignment/TestWakeUpUnexpectedProcedure.access$002:(Ljava/util/concurrent/CountDownLatch;)Ljava/util/concurrent/CountDownLatch;
      34: pop
      35: invokestatic  #9                  // Method org/apache/hadoop/hbase/master/assignment/TestWakeUpUnexpectedProcedure.access$200:()Ljava/util/concurrent/CountDownLatch;
      38: invokevirtual #10                 // Method java/util/concurrent/CountDownLatch.await:()V
      41: goto          54
      44: astore_3
      45: new           #12                 // class java/lang/RuntimeException
      48: dup
      49: aload_3
      50: invokespecial #13                 // Method java/lang/RuntimeException."<init>":(Ljava/lang/Throwable;)V
      53: athrow
      54: new           #14                 // class org/apache/hbase/thirdparty/com/google/protobuf/ServiceException
      57: dup
      58: new           #15                 // class java/net/ConnectException
      61: dup
      62: ldc           #16                 // String Inject error
      64: invokespecial #17                 // Method java/net/ConnectException."<init>":(Ljava/lang/String;)V
      67: invokespecial #18                 // Method org/apache/hbase/thirdparty/com/google/protobuf/ServiceException."<init>":(Ljava/lang/Throwable;)V
      70: athrow
      71: aload_0
      72: aload_1
      73: aload_2
      74: invokespecial #19                 // Method org/apache/hadoop/hbase/regionserver/RSRpcServices.executeProcedures:(Lorg/apache/hbase/thirdparty/com/google/protobuf/RpcController;Lorg/apache/hadoop/hbase/shaded/protobuf/generated/AdminProtos$ExecuteProceduresRequest;)Lorg/apache/hadoop/hbase/shaded/protobuf/generated/AdminProtos$ExecuteProceduresResponse;
      77: areturn
    Exception table:
       from    to  target type
          35    41    44   Class java/lang/InterruptedException
}
