Compiled from "TestStateMachineProcedure.java"
public class org.apache.hadoop.hbase.procedure2.TestStateMachineProcedure$SimpleChildProcedure extends org.apache.hadoop.hbase.procedure2.ProcedureTestingUtility$NoopProcedure<org.apache.hadoop.hbase.procedure2.TestStateMachineProcedure$TestProcEnv> {
  public org.apache.hadoop.hbase.procedure2.TestStateMachineProcedure$SimpleChildProcedure();
    Code:
       0: aload_0
       1: invokespecial #1                  // Method org/apache/hadoop/hbase/procedure2/ProcedureTestingUtility$NoopProcedure."<init>":()V
       4: return

  protected org.apache.hadoop.hbase.procedure2.Procedure<org.apache.hadoop.hbase.procedure2.TestStateMachineProcedure$TestProcEnv>[] execute(org.apache.hadoop.hbase.procedure2.TestStateMachineProcedure$TestProcEnv);
    Code:
       0: invokestatic  #2                  // Method org/apache/hadoop/hbase/procedure2/TestStateMachineProcedure.access$000:()Lorg/slf4j/Logger;
       3: new           #3                  // class java/lang/StringBuilder
       6: dup
       7: invokespecial #4                  // Method java/lang/StringBuilder."<init>":()V
      10: ldc           #5                  // String EXEC
      12: invokevirtual #6                  // Method java/lang/StringBuilder.append:(Ljava/lang/String;)Ljava/lang/StringBuilder;
      15: aload_0
      16: invokevirtual #7                  // Method java/lang/StringBuilder.append:(Ljava/lang/Object;)Ljava/lang/StringBuilder;
      19: invokevirtual #8                  // Method java/lang/StringBuilder.toString:()Ljava/lang/String;
      22: invokeinterface #9,  2            // InterfaceMethod org/slf4j/Logger.info:(Ljava/lang/String;)V
      27: aload_1
      28: getfield      #10                 // Field org/apache/hadoop/hbase/procedure2/TestStateMachineProcedure$TestProcEnv.execCount:Ljava/util/concurrent/atomic/AtomicInteger;
      31: invokevirtual #11                 // Method java/util/concurrent/atomic/AtomicInteger.incrementAndGet:()I
      34: pop
      35: aload_1
      36: getfield      #12                 // Field org/apache/hadoop/hbase/procedure2/TestStateMachineProcedure$TestProcEnv.triggerChildRollback:Z
      39: ifeq          51
      42: aload_0
      43: ldc           #13                 // String test-failure
      45: invokestatic  #14                 // Method org/apache/hadoop/hbase/procedure2/TestStateMachineProcedure.access$100:()Ljava/lang/Exception;
      48: invokevirtual #15                 // Method setFailure:(Ljava/lang/String;Ljava/lang/Throwable;)V
      51: aconst_null
      52: areturn

  protected void rollback(org.apache.hadoop.hbase.procedure2.TestStateMachineProcedure$TestProcEnv);
    Code:
       0: invokestatic  #2                  // Method org/apache/hadoop/hbase/procedure2/TestStateMachineProcedure.access$000:()Lorg/slf4j/Logger;
       3: new           #3                  // class java/lang/StringBuilder
       6: dup
       7: invokespecial #4                  // Method java/lang/StringBuilder."<init>":()V
      10: ldc           #16                 // String ROLLBACK
      12: invokevirtual #6                  // Method java/lang/StringBuilder.append:(Ljava/lang/String;)Ljava/lang/StringBuilder;
      15: aload_0
      16: invokevirtual #7                  // Method java/lang/StringBuilder.append:(Ljava/lang/Object;)Ljava/lang/StringBuilder;
      19: invokevirtual #8                  // Method java/lang/StringBuilder.toString:()Ljava/lang/String;
      22: invokeinterface #9,  2            // InterfaceMethod org/slf4j/Logger.info:(Ljava/lang/String;)V
      27: aload_1
      28: getfield      #17                 // Field org/apache/hadoop/hbase/procedure2/TestStateMachineProcedure$TestProcEnv.rollbackCount:Ljava/util/concurrent/atomic/AtomicInteger;
      31: invokevirtual #11                 // Method java/util/concurrent/atomic/AtomicInteger.incrementAndGet:()I
      34: pop
      35: return

  protected void rollback(java.lang.Object) throws java.io.IOException, java.lang.InterruptedException;
    Code:
       0: aload_0
       1: aload_1
       2: checkcast     #18                 // class org/apache/hadoop/hbase/procedure2/TestStateMachineProcedure$TestProcEnv
       5: invokevirtual #19                 // Method rollback:(Lorg/apache/hadoop/hbase/procedure2/TestStateMachineProcedure$TestProcEnv;)V
       8: return

  protected org.apache.hadoop.hbase.procedure2.Procedure[] execute(java.lang.Object) throws org.apache.hadoop.hbase.procedure2.ProcedureYieldException, org.apache.hadoop.hbase.procedure2.ProcedureSuspendedException, java.lang.InterruptedException;
    Code:
       0: aload_0
       1: aload_1
       2: checkcast     #18                 // class org/apache/hadoop/hbase/procedure2/TestStateMachineProcedure$TestProcEnv
       5: invokevirtual #20                 // Method execute:(Lorg/apache/hadoop/hbase/procedure2/TestStateMachineProcedure$TestProcEnv;)[Lorg/apache/hadoop/hbase/procedure2/Procedure;
       8: areturn
}
