Compiled from "TestMasterNotCarryTable.java"
public class org.apache.hadoop.hbase.master.TestMasterNotCarryTable {
  public static final org.apache.hadoop.hbase.HBaseClassTestRule CLASS_RULE;

  public org.apache.hadoop.hbase.master.TestMasterNotCarryTable();
    Code:
       0: aload_0
       1: invokespecial #1                  // Method java/lang/Object."<init>":()V
       4: return

  public static void setUp() throws java.lang.Exception;
    Code:
       0: getstatic     #2                  // Field UTIL:Lorg/apache/hadoop/hbase/HBaseTestingUtility;
       3: invokevirtual #3                  // Method org/apache/hadoop/hbase/HBaseTestingUtility.getConfiguration:()Lorg/apache/hadoop/conf/Configuration;
       6: astore_0
       7: aload_0
       8: getstatic     #2                  // Field UTIL:Lorg/apache/hadoop/hbase/HBaseTestingUtility;
      11: invokevirtual #4                  // Method org/apache/hadoop/hbase/HBaseTestingUtility.getDataTestDir:()Lorg/apache/hadoop/fs/Path;
      14: invokestatic  #5                  // Method org/apache/hadoop/hbase/util/FSUtils.setRootDir:(Lorg/apache/hadoop/conf/Configuration;Lorg/apache/hadoop/fs/Path;)V
      17: getstatic     #2                  // Field UTIL:Lorg/apache/hadoop/hbase/HBaseTestingUtility;
      20: invokevirtual #6                  // Method org/apache/hadoop/hbase/HBaseTestingUtility.startMiniZKCluster:()Lorg/apache/hadoop/hbase/zookeeper/MiniZooKeeperCluster;
      23: pop
      24: new           #7                  // class org/apache/hadoop/hbase/master/HMaster
      27: dup
      28: getstatic     #2                  // Field UTIL:Lorg/apache/hadoop/hbase/HBaseTestingUtility;
      31: invokevirtual #3                  // Method org/apache/hadoop/hbase/HBaseTestingUtility.getConfiguration:()Lorg/apache/hadoop/conf/Configuration;
      34: invokespecial #8                  // Method org/apache/hadoop/hbase/master/HMaster."<init>":(Lorg/apache/hadoop/conf/Configuration;)V
      37: putstatic     #9                  // Field master:Lorg/apache/hadoop/hbase/master/HMaster;
      40: getstatic     #9                  // Field master:Lorg/apache/hadoop/hbase/master/HMaster;
      43: invokevirtual #10                 // Method org/apache/hadoop/hbase/master/HMaster.start:()V
      46: getstatic     #9                  // Field master:Lorg/apache/hadoop/hbase/master/HMaster;
      49: invokevirtual #11                 // Method org/apache/hadoop/hbase/master/HMaster.getAssignmentManager:()Lorg/apache/hadoop/hbase/master/assignment/AssignmentManager;
      52: ifnull        74
      55: getstatic     #12                 // Field LOG:Lorg/slf4j/Logger;
      58: ldc           #13                 // String Wait master to create AssignmentManager
      60: invokeinterface #14,  2           // InterfaceMethod org/slf4j/Logger.debug:(Ljava/lang/String;)V
      65: ldc2_w        #15                 // long 1000l
      68: invokestatic  #17                 // Method java/lang/Thread.sleep:(J)V
      71: goto          46
      74: return

  public static void tearDown() throws java.lang.Exception;
    Code:
       0: getstatic     #9                  // Field master:Lorg/apache/hadoop/hbase/master/HMaster;
       3: ldc           #18                 // String Shutdown
       5: invokevirtual #19                 // Method org/apache/hadoop/hbase/master/HMaster.stop:(Ljava/lang/String;)V
       8: getstatic     #2                  // Field UTIL:Lorg/apache/hadoop/hbase/HBaseTestingUtility;
      11: invokevirtual #20                 // Method org/apache/hadoop/hbase/HBaseTestingUtility.shutdownMiniZKCluster:()V
      14: return

  public void testMasterNotCarryTable();
    Code:
       0: getstatic     #2                  // Field UTIL:Lorg/apache/hadoop/hbase/HBaseTestingUtility;
       3: invokevirtual #3                  // Method org/apache/hadoop/hbase/HBaseTestingUtility.getConfiguration:()Lorg/apache/hadoop/conf/Configuration;
       6: invokestatic  #21                 // InterfaceMethod org/apache/hadoop/hbase/master/LoadBalancer.isTablesOnMaster:(Lorg/apache/hadoop/conf/Configuration;)Z
       9: invokestatic  #22                 // Method org/junit/Assert.assertFalse:(Z)V
      12: getstatic     #2                  // Field UTIL:Lorg/apache/hadoop/hbase/HBaseTestingUtility;
      15: invokevirtual #3                  // Method org/apache/hadoop/hbase/HBaseTestingUtility.getConfiguration:()Lorg/apache/hadoop/conf/Configuration;
      18: invokestatic  #23                 // InterfaceMethod org/apache/hadoop/hbase/master/LoadBalancer.isSystemTablesOnlyOnMaster:(Lorg/apache/hadoop/conf/Configuration;)Z
      21: invokestatic  #22                 // Method org/junit/Assert.assertFalse:(Z)V
      24: return

  public void testMasterBlockCache();
    Code:
       0: getstatic     #9                  // Field master:Lorg/apache/hadoop/hbase/master/HMaster;
       3: invokevirtual #24                 // Method org/apache/hadoop/hbase/master/HMaster.getBlockCache:()Ljava/util/Optional;
       6: invokevirtual #25                 // Method java/util/Optional.isPresent:()Z
       9: invokestatic  #22                 // Method org/junit/Assert.assertFalse:(Z)V
      12: return

  public void testMasterMOBFileCache();
    Code:
       0: getstatic     #9                  // Field master:Lorg/apache/hadoop/hbase/master/HMaster;
       3: invokevirtual #26                 // Method org/apache/hadoop/hbase/master/HMaster.getMobFileCache:()Ljava/util/Optional;
       6: invokevirtual #25                 // Method java/util/Optional.isPresent:()Z
       9: invokestatic  #22                 // Method org/junit/Assert.assertFalse:(Z)V
      12: return

  public void testMasterMemStoreLAB();
    Code:
       0: invokestatic  #27                 // Method org/apache/hadoop/hbase/regionserver/ChunkCreator.getInstance:()Lorg/apache/hadoop/hbase/regionserver/ChunkCreator;
       3: invokestatic  #28                 // Method org/junit/Assert.assertNull:(Ljava/lang/Object;)V
       6: return

  static {};
    Code:
       0: ldc           #29                 // class org/apache/hadoop/hbase/master/TestMasterNotCarryTable
       2: invokestatic  #30                 // Method org/apache/hadoop/hbase/HBaseClassTestRule.forClass:(Ljava/lang/Class;)Lorg/apache/hadoop/hbase/HBaseClassTestRule;
       5: putstatic     #31                 // Field CLASS_RULE:Lorg/apache/hadoop/hbase/HBaseClassTestRule;
       8: ldc           #29                 // class org/apache/hadoop/hbase/master/TestMasterNotCarryTable
      10: invokestatic  #32                 // Method org/slf4j/LoggerFactory.getLogger:(Ljava/lang/Class;)Lorg/slf4j/Logger;
      13: putstatic     #12                 // Field LOG:Lorg/slf4j/Logger;
      16: new           #33                 // class org/apache/hadoop/hbase/HBaseTestingUtility
      19: dup
      20: invokespecial #34                 // Method org/apache/hadoop/hbase/HBaseTestingUtility."<init>":()V
      23: putstatic     #2                  // Field UTIL:Lorg/apache/hadoop/hbase/HBaseTestingUtility;
      26: return
}
