Compiled from "TestAsyncBufferMutator.java"
final class org.apache.hadoop.hbase.client.TestAsyncBufferMutator$AsyncBufferMutatorForTest extends org.apache.hadoop.hbase.client.AsyncBufferedMutatorImpl {
  org.apache.hadoop.hbase.client.TestAsyncBufferMutator$AsyncBufferMutatorForTest(org.apache.hbase.thirdparty.io.netty.util.HashedWheelTimer, org.apache.hadoop.hbase.client.AsyncTable<?>, long, long, int);
    Code:
       0: aload_0
       1: aload_1
       2: aload_2
       3: lload_3
       4: lload         5
       6: iload         7
       8: invokespecial #2                  // Method org/apache/hadoop/hbase/client/AsyncBufferedMutatorImpl."<init>":(Lorg/apache/hbase/thirdparty/io/netty/util/HashedWheelTimer;Lorg/apache/hadoop/hbase/client/AsyncTable;JJI)V
      11: return

  protected void internalFlush();
    Code:
       0: aload_0
       1: dup
       2: getfield      #1                  // Field flushCount:I
       5: iconst_1
       6: iadd
       7: putfield      #1                  // Field flushCount:I
      10: aload_0
      11: invokespecial #3                  // Method org/apache/hadoop/hbase/client/AsyncBufferedMutatorImpl.internalFlush:()V
      14: return

  static int access$000(org.apache.hadoop.hbase.client.TestAsyncBufferMutator$AsyncBufferMutatorForTest);
    Code:
       0: aload_0
       1: getfield      #1                  // Field flushCount:I
       4: ireturn
}
