Compiled from "TestCompaction.java"
public class org.apache.hadoop.hbase.regionserver.TestCompaction$BlockingStoreMockMaker$BlockingCompactionContext extends org.apache.hadoop.hbase.regionserver.compactions.CompactionContext {
  public volatile boolean isInCompact;

  final org.apache.hadoop.hbase.regionserver.TestCompaction$BlockingStoreMockMaker this$1;

  public org.apache.hadoop.hbase.regionserver.TestCompaction$BlockingStoreMockMaker$BlockingCompactionContext(org.apache.hadoop.hbase.regionserver.TestCompaction$BlockingStoreMockMaker);
    Code:
       0: aload_0
       1: aload_1
       2: putfield      #1                  // Field this$1:Lorg/apache/hadoop/hbase/regionserver/TestCompaction$BlockingStoreMockMaker;
       5: aload_0
       6: invokespecial #2                  // Method org/apache/hadoop/hbase/regionserver/compactions/CompactionContext."<init>":()V
       9: aload_0
      10: iconst_0
      11: putfield      #3                  // Field isInCompact:Z
      14: return

  public void unblock();
    Code:
       0: aload_0
       1: dup
       2: astore_1
       3: monitorenter
       4: aload_0
       5: invokevirtual #4                  // Method java/lang/Object.notifyAll:()V
       8: aload_1
       9: monitorexit
      10: goto          18
      13: astore_2
      14: aload_1
      15: monitorexit
      16: aload_2
      17: athrow
      18: return
    Exception table:
       from    to  target type
           4    10    13   any
          13    16    13   any

  public java.util.List<org.apache.hadoop.fs.Path> compact(org.apache.hadoop.hbase.regionserver.throttle.ThroughputController, org.apache.hadoop.hbase.security.User) throws java.io.IOException;
    Code:
       0: aload_0
       1: iconst_1
       2: putfield      #3                  // Field isInCompact:Z
       5: aload_0
       6: dup
       7: astore_3
       8: monitorenter
       9: aload_0
      10: invokevirtual #5                  // Method java/lang/Object.wait:()V
      13: aload_3
      14: monitorexit
      15: goto          25
      18: astore        4
      20: aload_3
      21: monitorexit
      22: aload         4
      24: athrow
      25: goto          33
      28: astore_3
      29: aload_3
      30: invokestatic  #7                  // Method org/junit/Assume.assumeNoException:(Ljava/lang/Throwable;)V
      33: new           #8                  // class java/util/ArrayList
      36: dup
      37: invokespecial #9                  // Method java/util/ArrayList."<init>":()V
      40: areturn
    Exception table:
       from    to  target type
           9    15    18   any
          18    22    18   any
           0    25    28   Class java/lang/InterruptedException

  public java.util.List<org.apache.hadoop.hbase.regionserver.HStoreFile> preSelect(java.util.List<org.apache.hadoop.hbase.regionserver.HStoreFile>);
    Code:
       0: new           #8                  // class java/util/ArrayList
       3: dup
       4: invokespecial #9                  // Method java/util/ArrayList."<init>":()V
       7: areturn

  public boolean select(java.util.List<org.apache.hadoop.hbase.regionserver.HStoreFile>, boolean, boolean, boolean) throws java.io.IOException;
    Code:
       0: aload_0
       1: new           #10                 // class org/apache/hadoop/hbase/regionserver/compactions/CompactionRequestImpl
       4: dup
       5: new           #8                  // class java/util/ArrayList
       8: dup
       9: invokespecial #9                  // Method java/util/ArrayList."<init>":()V
      12: invokespecial #11                 // Method org/apache/hadoop/hbase/regionserver/compactions/CompactionRequestImpl."<init>":(Ljava/util/Collection;)V
      15: putfield      #12                 // Field request:Lorg/apache/hadoop/hbase/regionserver/compactions/CompactionRequestImpl;
      18: iconst_1
      19: ireturn
}
