Compiled from "TestAddress.java"
public class org.apache.hadoop.hbase.net.TestAddress {
  public static final org.apache.hadoop.hbase.HBaseClassTestRule CLASS_RULE;

  public org.apache.hadoop.hbase.net.TestAddress();
    Code:
       0: aload_0
       1: invokespecial #1                  // Method java/lang/Object."<init>":()V
       4: return

  public void testGetHostWithoutDomain();
    Code:
       0: ldc           #2                  // String a:123
       2: ldc           #3                  // String a.b.c
       4: bipush        123
       6: invokestatic  #4                  // Method org/apache/hadoop/hbase/net/Address.fromParts:(Ljava/lang/String;I)Lorg/apache/hadoop/hbase/net/Address;
       9: invokevirtual #5                  // Method org/apache/hadoop/hbase/net/Address.toStringWithoutDomain:()Ljava/lang/String;
      12: invokestatic  #6                  // Method org/junit/Assert.assertEquals:(Ljava/lang/Object;Ljava/lang/Object;)V
      15: ldc           #7                  // String 1:123
      17: ldc           #8                  // String 1.b.c
      19: bipush        123
      21: invokestatic  #4                  // Method org/apache/hadoop/hbase/net/Address.fromParts:(Ljava/lang/String;I)Lorg/apache/hadoop/hbase/net/Address;
      24: invokevirtual #5                  // Method org/apache/hadoop/hbase/net/Address.toStringWithoutDomain:()Ljava/lang/String;
      27: invokestatic  #6                  // Method org/junit/Assert.assertEquals:(Ljava/lang/Object;Ljava/lang/Object;)V
      30: ldc           #9                  // String 123.456.789.1:123
      32: ldc           #10                 // String 123.456.789.1
      34: bipush        123
      36: invokestatic  #4                  // Method org/apache/hadoop/hbase/net/Address.fromParts:(Ljava/lang/String;I)Lorg/apache/hadoop/hbase/net/Address;
      39: invokevirtual #5                  // Method org/apache/hadoop/hbase/net/Address.toStringWithoutDomain:()Ljava/lang/String;
      42: invokestatic  #6                  // Method org/junit/Assert.assertEquals:(Ljava/lang/Object;Ljava/lang/Object;)V
      45: ldc           #11                 // String [2001:db8::1]:80
      47: ldc           #12                 // String [2001:db8::1]:
      49: bipush        80
      51: invokestatic  #4                  // Method org/apache/hadoop/hbase/net/Address.fromParts:(Ljava/lang/String;I)Lorg/apache/hadoop/hbase/net/Address;
      54: invokevirtual #5                  // Method org/apache/hadoop/hbase/net/Address.toStringWithoutDomain:()Ljava/lang/String;
      57: invokestatic  #6                  // Method org/junit/Assert.assertEquals:(Ljava/lang/Object;Ljava/lang/Object;)V
      60: ldc           #11                 // String [2001:db8::1]:80
      62: ldc           #12                 // String [2001:db8::1]:
      64: bipush        80
      66: invokestatic  #4                  // Method org/apache/hadoop/hbase/net/Address.fromParts:(Ljava/lang/String;I)Lorg/apache/hadoop/hbase/net/Address;
      69: invokevirtual #5                  // Method org/apache/hadoop/hbase/net/Address.toStringWithoutDomain:()Ljava/lang/String;
      72: invokestatic  #6                  // Method org/junit/Assert.assertEquals:(Ljava/lang/Object;Ljava/lang/Object;)V
      75: return

  static {};
    Code:
       0: ldc           #13                 // class org/apache/hadoop/hbase/net/TestAddress
       2: invokestatic  #14                 // Method org/apache/hadoop/hbase/HBaseClassTestRule.forClass:(Ljava/lang/Class;)Lorg/apache/hadoop/hbase/HBaseClassTestRule;
       5: putstatic     #15                 // Field CLASS_RULE:Lorg/apache/hadoop/hbase/HBaseClassTestRule;
       8: return
}
