Compiled from "TestProcedureRecovery.java"
public class org.apache.hadoop.hbase.procedure2.TestProcedureRecovery$BaseTestStepProcedure extends org.apache.hadoop.hbase.procedure2.SequentialProcedure<org.apache.hadoop.hbase.procedure2.TestProcedureRecovery$TestProcEnv> {
  public org.apache.hadoop.hbase.procedure2.TestProcedureRecovery$BaseTestStepProcedure();
    Code:
       0: aload_0
       1: invokespecial #1                  // Method org/apache/hadoop/hbase/procedure2/SequentialProcedure."<init>":()V
       4: aload_0
       5: new           #2                  // class java/util/concurrent/atomic/AtomicBoolean
       8: dup
       9: iconst_0
      10: invokespecial #3                  // Method java/util/concurrent/atomic/AtomicBoolean."<init>":(Z)V
      13: putfield      #4                  // Field abort:Ljava/util/concurrent/atomic/AtomicBoolean;
      16: aload_0
      17: iconst_0
      18: putfield      #5                  // Field step:I
      21: return

  protected org.apache.hadoop.hbase.procedure2.Procedure[] execute(org.apache.hadoop.hbase.procedure2.TestProcedureRecovery$TestProcEnv) throws java.lang.InterruptedException;
    Code:
       0: aload_1
       1: invokevirtual #6                  // Method org/apache/hadoop/hbase/procedure2/TestProcedureRecovery$TestProcEnv.waitOnLatch:()V
       4: invokestatic  #7                  // Method org/apache/hadoop/hbase/procedure2/TestProcedureRecovery.access$100:()Lorg/slf4j/Logger;
       7: new           #8                  // class java/lang/StringBuilder
      10: dup
      11: invokespecial #9                  // Method java/lang/StringBuilder."<init>":()V
      14: ldc           #10                 // String execute procedure
      16: invokevirtual #11                 // Method java/lang/StringBuilder.append:(Ljava/lang/String;)Ljava/lang/StringBuilder;
      19: aload_0
      20: invokevirtual #12                 // Method java/lang/StringBuilder.append:(Ljava/lang/Object;)Ljava/lang/StringBuilder;
      23: ldc           #13                 // String  step=
      25: invokevirtual #11                 // Method java/lang/StringBuilder.append:(Ljava/lang/String;)Ljava/lang/StringBuilder;
      28: aload_0
      29: getfield      #5                  // Field step:I
      32: invokevirtual #14                 // Method java/lang/StringBuilder.append:(I)Ljava/lang/StringBuilder;
      35: invokevirtual #15                 // Method java/lang/StringBuilder.toString:()Ljava/lang/String;
      38: invokeinterface #16,  2           // InterfaceMethod org/slf4j/Logger.debug:(Ljava/lang/String;)V
      43: invokestatic  #17                 // Method org/apache/hadoop/hbase/procedure2/TestProcedureRecovery.access$200:()Lorg/apache/hadoop/hbase/procedure2/ProcedureExecutor;
      46: invokestatic  #18                 // Method org/apache/hadoop/hbase/procedure2/ProcedureTestingUtility.toggleKillBeforeStoreUpdate:(Lorg/apache/hadoop/hbase/procedure2/ProcedureExecutor;)V
      49: aload_0
      50: dup
      51: getfield      #5                  // Field step:I
      54: iconst_1
      55: iadd
      56: putfield      #5                  // Field step:I
      59: invokestatic  #19                 // Method org/apache/hadoop/hbase/procedure2/TestProcedureRecovery.access$300:()I
      62: i2l
      63: invokestatic  #20                 // Method org/apache/hadoop/hbase/util/Threads.sleepWithoutInterrupt:(J)V
      66: aload_0
      67: invokespecial #21                 // Method isAborted:()Z
      70: ifeq          137
      73: aload_0
      74: new           #22                 // class org/apache/hadoop/hbase/procedure2/RemoteProcedureException
      77: dup
      78: aload_0
      79: invokevirtual #23                 // Method java/lang/Object.getClass:()Ljava/lang/Class;
      82: invokevirtual #24                 // Method java/lang/Class.getName:()Ljava/lang/String;
      85: new           #25                 // class org/apache/hadoop/hbase/procedure2/ProcedureAbortedException
      88: dup
      89: new           #8                  // class java/lang/StringBuilder
      92: dup
      93: invokespecial #9                  // Method java/lang/StringBuilder."<init>":()V
      96: ldc           #26                 // String got an abort at
      98: invokevirtual #11                 // Method java/lang/StringBuilder.append:(Ljava/lang/String;)Ljava/lang/StringBuilder;
     101: aload_0
     102: invokevirtual #23                 // Method java/lang/Object.getClass:()Ljava/lang/Class;
     105: invokevirtual #24                 // Method java/lang/Class.getName:()Ljava/lang/String;
     108: invokevirtual #11                 // Method java/lang/StringBuilder.append:(Ljava/lang/String;)Ljava/lang/StringBuilder;
     111: ldc           #13                 // String  step=
     113: invokevirtual #11                 // Method java/lang/StringBuilder.append:(Ljava/lang/String;)Ljava/lang/StringBuilder;
     116: aload_0
     117: getfield      #5                  // Field step:I
     120: invokevirtual #14                 // Method java/lang/StringBuilder.append:(I)Ljava/lang/StringBuilder;
     123: invokevirtual #15                 // Method java/lang/StringBuilder.toString:()Ljava/lang/String;
     126: invokespecial #27                 // Method org/apache/hadoop/hbase/procedure2/ProcedureAbortedException."<init>":(Ljava/lang/String;)V
     129: invokespecial #28                 // Method org/apache/hadoop/hbase/procedure2/RemoteProcedureException."<init>":(Ljava/lang/String;Ljava/lang/Throwable;)V
     132: invokevirtual #29                 // Method setFailure:(Lorg/apache/hadoop/hbase/procedure2/RemoteProcedureException;)V
     135: aconst_null
     136: areturn
     137: aconst_null
     138: areturn

  protected void rollback(org.apache.hadoop.hbase.procedure2.TestProcedureRecovery$TestProcEnv);
    Code:
       0: invokestatic  #7                  // Method org/apache/hadoop/hbase/procedure2/TestProcedureRecovery.access$100:()Lorg/slf4j/Logger;
       3: new           #8                  // class java/lang/StringBuilder
       6: dup
       7: invokespecial #9                  // Method java/lang/StringBuilder."<init>":()V
      10: ldc           #30                 // String rollback procedure
      12: invokevirtual #11                 // Method java/lang/StringBuilder.append:(Ljava/lang/String;)Ljava/lang/StringBuilder;
      15: aload_0
      16: invokevirtual #12                 // Method java/lang/StringBuilder.append:(Ljava/lang/Object;)Ljava/lang/StringBuilder;
      19: ldc           #13                 // String  step=
      21: invokevirtual #11                 // Method java/lang/StringBuilder.append:(Ljava/lang/String;)Ljava/lang/StringBuilder;
      24: aload_0
      25: getfield      #5                  // Field step:I
      28: invokevirtual #14                 // Method java/lang/StringBuilder.append:(I)Ljava/lang/StringBuilder;
      31: invokevirtual #15                 // Method java/lang/StringBuilder.toString:()Ljava/lang/String;
      34: invokeinterface #16,  2           // InterfaceMethod org/slf4j/Logger.debug:(Ljava/lang/String;)V
      39: invokestatic  #17                 // Method org/apache/hadoop/hbase/procedure2/TestProcedureRecovery.access$200:()Lorg/apache/hadoop/hbase/procedure2/ProcedureExecutor;
      42: invokestatic  #18                 // Method org/apache/hadoop/hbase/procedure2/ProcedureTestingUtility.toggleKillBeforeStoreUpdate:(Lorg/apache/hadoop/hbase/procedure2/ProcedureExecutor;)V
      45: aload_0
      46: dup
      47: getfield      #5                  // Field step:I
      50: iconst_1
      51: iadd
      52: putfield      #5                  // Field step:I
      55: return

  protected boolean abort(org.apache.hadoop.hbase.procedure2.TestProcedureRecovery$TestProcEnv);
    Code:
       0: aload_0
       1: getfield      #4                  // Field abort:Ljava/util/concurrent/atomic/AtomicBoolean;
       4: iconst_1
       5: invokevirtual #31                 // Method java/util/concurrent/atomic/AtomicBoolean.set:(Z)V
       8: iconst_1
       9: ireturn

  protected boolean abort(java.lang.Object);
    Code:
       0: aload_0
       1: aload_1
       2: checkcast     #37                 // class org/apache/hadoop/hbase/procedure2/TestProcedureRecovery$TestProcEnv
       5: invokevirtual #38                 // Method abort:(Lorg/apache/hadoop/hbase/procedure2/TestProcedureRecovery$TestProcEnv;)Z
       8: ireturn

  protected void rollback(java.lang.Object) throws java.io.IOException, java.lang.InterruptedException;
    Code:
       0: aload_0
       1: aload_1
       2: checkcast     #37                 // class org/apache/hadoop/hbase/procedure2/TestProcedureRecovery$TestProcEnv
       5: invokevirtual #39                 // Method rollback:(Lorg/apache/hadoop/hbase/procedure2/TestProcedureRecovery$TestProcEnv;)V
       8: return

  protected org.apache.hadoop.hbase.procedure2.Procedure[] execute(java.lang.Object) throws org.apache.hadoop.hbase.procedure2.ProcedureYieldException, org.apache.hadoop.hbase.procedure2.ProcedureSuspendedException, java.lang.InterruptedException;
    Code:
       0: aload_0
       1: aload_1
       2: checkcast     #37                 // class org/apache/hadoop/hbase/procedure2/TestProcedureRecovery$TestProcEnv
       5: invokevirtual #40                 // Method execute:(Lorg/apache/hadoop/hbase/procedure2/TestProcedureRecovery$TestProcEnv;)[Lorg/apache/hadoop/hbase/procedure2/Procedure;
       8: areturn
}
