Compiled from "TestRegionReplicas.java"
class org.apache.hadoop.hbase.regionserver.TestRegionReplicas$1 implements java.lang.Runnable {
  int key;

  final java.util.concurrent.atomic.AtomicBoolean val$running;

  final java.util.concurrent.atomic.AtomicReference[] val$exceptions;

  final org.apache.hadoop.hbase.regionserver.TestRegionReplicas this$0;

  org.apache.hadoop.hbase.regionserver.TestRegionReplicas$1(org.apache.hadoop.hbase.regionserver.TestRegionReplicas, java.util.concurrent.atomic.AtomicBoolean, java.util.concurrent.atomic.AtomicReference[]);
    Code:
       0: aload_0
       1: aload_1
       2: putfield      #1                  // Field this$0:Lorg/apache/hadoop/hbase/regionserver/TestRegionReplicas;
       5: aload_0
       6: aload_2
       7: putfield      #2                  // Field val$running:Ljava/util/concurrent/atomic/AtomicBoolean;
      10: aload_0
      11: aload_3
      12: putfield      #3                  // Field val$exceptions:[Ljava/util/concurrent/atomic/AtomicReference;
      15: aload_0
      16: invokespecial #4                  // Method java/lang/Object."<init>":()V
      19: aload_0
      20: iconst_0
      21: putfield      #5                  // Field key:I
      24: return

  public void run();
    Code:
       0: aload_0
       1: getfield      #2                  // Field val$running:Ljava/util/concurrent/atomic/AtomicBoolean;
       4: invokevirtual #6                  // Method java/util/concurrent/atomic/AtomicBoolean.get:()Z
       7: ifeq          77
      10: aload_0
      11: getfield      #5                  // Field key:I
      14: invokestatic  #7                  // Method java/lang/String.valueOf:(I)Ljava/lang/String;
      17: invokestatic  #8                  // Method org/apache/hadoop/hbase/util/Bytes.toBytes:(Ljava/lang/String;)[B
      20: astore_1
      21: new           #9                  // class org/apache/hadoop/hbase/client/Put
      24: dup
      25: aload_1
      26: invokespecial #10                 // Method org/apache/hadoop/hbase/client/Put."<init>":([B)V
      29: astore_2
      30: aload_2
      31: invokestatic  #11                 // Method org/apache/hadoop/hbase/regionserver/TestRegionReplicas.access$000:()[B
      34: aconst_null
      35: aload_1
      36: invokevirtual #12                 // Method org/apache/hadoop/hbase/client/Put.addColumn:([B[B[B)Lorg/apache/hadoop/hbase/client/Put;
      39: pop
      40: invokestatic  #13                 // Method org/apache/hadoop/hbase/regionserver/TestRegionReplicas.access$100:()Lorg/apache/hadoop/hbase/client/Table;
      43: aload_2
      44: invokeinterface #14,  2           // InterfaceMethod org/apache/hadoop/hbase/client/Table.put:(Lorg/apache/hadoop/hbase/client/Put;)V
      49: aload_0
      50: dup
      51: getfield      #5                  // Field key:I
      54: iconst_1
      55: iadd
      56: putfield      #5                  // Field key:I
      59: aload_0
      60: getfield      #5                  // Field key:I
      63: sipush        1000
      66: if_icmpne     74
      69: aload_0
      70: iconst_0
      71: putfield      #5                  // Field key:I
      74: goto          0
      77: goto          106
      80: astore_1
      81: invokestatic  #16                 // Method org/apache/hadoop/hbase/regionserver/TestRegionReplicas.access$200:()Lorg/slf4j/Logger;
      84: aload_1
      85: invokevirtual #17                 // Method java/lang/Exception.toString:()Ljava/lang/String;
      88: aload_1
      89: invokeinterface #18,  3           // InterfaceMethod org/slf4j/Logger.warn:(Ljava/lang/String;Ljava/lang/Throwable;)V
      94: aload_0
      95: getfield      #3                  // Field val$exceptions:[Ljava/util/concurrent/atomic/AtomicReference;
      98: iconst_0
      99: aaload
     100: aconst_null
     101: aload_1
     102: invokevirtual #19                 // Method java/util/concurrent/atomic/AtomicReference.compareAndSet:(Ljava/lang/Object;Ljava/lang/Object;)Z
     105: pop
     106: return
    Exception table:
       from    to  target type
           0    77    80   Class java/lang/Exception
}
