Compiled from "TestConfigurationUtil.java"
public class org.apache.hadoop.hbase.util.TestConfigurationUtil {
  public static final org.apache.hadoop.hbase.HBaseClassTestRule CLASS_RULE;

  public org.apache.hadoop.hbase.util.TestConfigurationUtil();
    Code:
       0: aload_0
       1: invokespecial #1                  // Method java/lang/Object."<init>":()V
       4: return

  public void setUp() throws java.lang.Exception;
    Code:
       0: aload_0
       1: new           #2                  // class org/apache/hadoop/conf/Configuration
       4: dup
       5: invokespecial #3                  // Method org/apache/hadoop/conf/Configuration."<init>":()V
       8: putfield      #4                  // Field conf:Lorg/apache/hadoop/conf/Configuration;
      11: aload_0
      12: ldc           #5                  // String k1
      14: ldc           #6                  // String v1
      16: ldc           #7                  // String k2
      18: ldc           #8                  // String v2
      20: invokestatic  #9                  // Method org/apache/hbase/thirdparty/com/google/common/collect/ImmutableMap.of:(Ljava/lang/Object;Ljava/lang/Object;Ljava/lang/Object;Ljava/lang/Object;)Lorg/apache/hbase/thirdparty/com/google/common/collect/ImmutableMap;
      23: putfield      #10                 // Field keyValues:Ljava/util/Map;
      26: aload_0
      27: ldc           #11                 // String my_conf_key
      29: putfield      #12                 // Field key:Ljava/lang/String;
      32: return

  public void callSetKeyValues();
    Code:
       0: aload_0
       1: getfield      #4                  // Field conf:Lorg/apache/hadoop/conf/Configuration;
       4: aload_0
       5: getfield      #12                 // Field key:Ljava/lang/String;
       8: aload_0
       9: getfield      #10                 // Field keyValues:Ljava/util/Map;
      12: invokeinterface #13,  1           // InterfaceMethod java/util/Map.entrySet:()Ljava/util/Set;
      17: invokestatic  #14                 // Method org/apache/hadoop/hbase/util/ConfigurationUtil.setKeyValues:(Lorg/apache/hadoop/conf/Configuration;Ljava/lang/String;Ljava/util/Collection;)V
      20: return

  public java.util.List<java.util.Map$Entry<java.lang.String, java.lang.String>> callGetKeyValues();
    Code:
       0: aload_0
       1: getfield      #4                  // Field conf:Lorg/apache/hadoop/conf/Configuration;
       4: aload_0
       5: getfield      #12                 // Field key:Ljava/lang/String;
       8: invokestatic  #15                 // Method org/apache/hadoop/hbase/util/ConfigurationUtil.getKeyValues:(Lorg/apache/hadoop/conf/Configuration;Ljava/lang/String;)Ljava/util/List;
      11: areturn

  public void testGetAndSetKeyValuesWithValues() throws java.lang.Exception;
    Code:
       0: aload_0
       1: invokevirtual #16                 // Method callSetKeyValues:()V
       4: aload_0
       5: getfield      #10                 // Field keyValues:Ljava/util/Map;
       8: invokeinterface #13,  1           // InterfaceMethod java/util/Map.entrySet:()Ljava/util/Set;
      13: invokestatic  #17                 // Method org/apache/hbase/thirdparty/com/google/common/collect/Lists.newArrayList:(Ljava/lang/Iterable;)Ljava/util/ArrayList;
      16: aload_0
      17: invokevirtual #18                 // Method callGetKeyValues:()Ljava/util/List;
      20: invokestatic  #19                 // Method org/junit/Assert.assertEquals:(Ljava/lang/Object;Ljava/lang/Object;)V
      23: return

  public void testGetKeyValuesWithUnsetKey() throws java.lang.Exception;
    Code:
       0: aload_0
       1: invokevirtual #18                 // Method callGetKeyValues:()Ljava/util/List;
       4: invokestatic  #20                 // Method org/junit/Assert.assertNull:(Ljava/lang/Object;)V
       7: return

  static {};
    Code:
       0: ldc           #21                 // class org/apache/hadoop/hbase/util/TestConfigurationUtil
       2: invokestatic  #22                 // Method org/apache/hadoop/hbase/HBaseClassTestRule.forClass:(Ljava/lang/Class;)Lorg/apache/hadoop/hbase/HBaseClassTestRule;
       5: putstatic     #23                 // Field CLASS_RULE:Lorg/apache/hadoop/hbase/HBaseClassTestRule;
       8: return
}
