Compiled from "TestAsyncRegistryLeak.java"
public class org.apache.hadoop.hbase.client.TestAsyncRegistryLeak {
  public static final org.apache.hadoop.hbase.HBaseClassTestRule CLASS_RULE;

  public org.apache.hadoop.hbase.client.TestAsyncRegistryLeak();
    Code:
       0: aload_0
       1: invokespecial #2                  // Method java/lang/Object."<init>":()V
       4: return

  public static void setUp();
    Code:
       0: getstatic     #3                  // Field CONF:Lorg/apache/hadoop/conf/Configuration;
       3: ldc           #5                  // String hbase.client.registry.impl
       5: ldc           #6                  // class org/apache/hadoop/hbase/client/TestAsyncRegistryLeak$AsyncRegistryForTest
       7: ldc           #7                  // class org/apache/hadoop/hbase/client/AsyncRegistry
       9: invokevirtual #8                  // Method org/apache/hadoop/conf/Configuration.setClass:(Ljava/lang/String;Ljava/lang/Class;Ljava/lang/Class;)V
      12: return

  public void test() throws java.lang.InterruptedException;
    Code:
       0: iconst_0
       1: istore_1
       2: iload_1
       3: bipush        10
       5: if_icmpge     31
       8: getstatic     #3                  // Field CONF:Lorg/apache/hadoop/conf/Configuration;
      11: invokestatic  #9                  // Method org/apache/hadoop/hbase/client/ConnectionFactory.createAsyncConnection:(Lorg/apache/hadoop/conf/Configuration;)Ljava/util/concurrent/CompletableFuture;
      14: invokevirtual #10                 // Method java/util/concurrent/CompletableFuture.get:()Ljava/lang/Object;
      17: pop
      18: invokestatic  #11                 // Method org/junit/Assert.fail:()V
      21: goto          25
      24: astore_2
      25: iinc          1, 1
      28: goto          2
      31: ldc2_w        #13                 // long 10l
      34: getstatic     #1                  // Field CREATED:Ljava/util/List;
      37: invokeinterface #15,  1           // InterfaceMethod java/util/List.size:()I
      42: i2l
      43: invokestatic  #16                 // Method org/junit/Assert.assertEquals:(JJ)V
      46: getstatic     #1                  // Field CREATED:Ljava/util/List;
      49: invokedynamic #17,  0             // InvokeDynamic #0:accept:()Ljava/util/function/Consumer;
      54: invokeinterface #18,  2           // InterfaceMethod java/util/List.forEach:(Ljava/util/function/Consumer;)V
      59: return
    Exception table:
       from    to  target type
           8    21    24   Class java/util/concurrent/ExecutionException

  static java.util.List access$000();
    Code:
       0: getstatic     #1                  // Field CREATED:Ljava/util/List;
       3: areturn

  static {};
    Code:
       0: ldc           #21                 // class org/apache/hadoop/hbase/client/TestAsyncRegistryLeak
       2: invokestatic  #22                 // Method org/apache/hadoop/hbase/HBaseClassTestRule.forClass:(Ljava/lang/Class;)Lorg/apache/hadoop/hbase/HBaseClassTestRule;
       5: putstatic     #23                 // Field CLASS_RULE:Lorg/apache/hadoop/hbase/HBaseClassTestRule;
       8: new           #24                 // class java/util/ArrayList
      11: dup
      12: invokespecial #25                 // Method java/util/ArrayList."<init>":()V
      15: putstatic     #1                  // Field CREATED:Ljava/util/List;
      18: invokestatic  #26                 // Method org/apache/hadoop/hbase/HBaseConfiguration.create:()Lorg/apache/hadoop/conf/Configuration;
      21: putstatic     #3                  // Field CONF:Lorg/apache/hadoop/conf/Configuration;
      24: return
}
