Compiled from "TestSplitTransactionOnCluster.java"
public class org.apache.hadoop.hbase.regionserver.TestSplitTransactionOnCluster$MyMaster extends org.apache.hadoop.hbase.master.HMaster {
  public org.apache.hadoop.hbase.regionserver.TestSplitTransactionOnCluster$MyMaster(org.apache.hadoop.conf.Configuration) throws java.io.IOException, org.apache.zookeeper.KeeperException, java.lang.InterruptedException;
    Code:
       0: aload_0
       1: aload_1
       2: invokespecial #1                  // Method org/apache/hadoop/hbase/master/HMaster."<init>":(Lorg/apache/hadoop/conf/Configuration;)V
       5: return

  protected org.apache.hadoop.hbase.regionserver.RSRpcServices createRpcServices() throws java.io.IOException;
    Code:
       0: new           #2                  // class org/apache/hadoop/hbase/regionserver/TestSplitTransactionOnCluster$MyMasterRpcServices
       3: dup
       4: aload_0
       5: invokespecial #3                  // Method org/apache/hadoop/hbase/regionserver/TestSplitTransactionOnCluster$MyMasterRpcServices."<init>":(Lorg/apache/hadoop/hbase/master/HMaster;)V
       8: areturn
}
