Compiled from "TestZKNodeTracker.java"
class org.apache.hadoop.hbase.zookeeper.TestZKNodeTracker$1 extends java.lang.Thread {
  final org.apache.hadoop.hbase.zookeeper.TestZKNodeTracker$TestTracker val$tracker;

  final org.apache.hadoop.hbase.zookeeper.TestZKNodeTracker this$0;

  org.apache.hadoop.hbase.zookeeper.TestZKNodeTracker$1(org.apache.hadoop.hbase.zookeeper.TestZKNodeTracker, org.apache.hadoop.hbase.zookeeper.TestZKNodeTracker$TestTracker);
    Code:
       0: aload_0
       1: aload_1
       2: putfield      #1                  // Field this$0:Lorg/apache/hadoop/hbase/zookeeper/TestZKNodeTracker;
       5: aload_0
       6: aload_2
       7: putfield      #2                  // Field val$tracker:Lorg/apache/hadoop/hbase/zookeeper/TestZKNodeTracker$TestTracker;
      10: aload_0
      11: invokespecial #3                  // Method java/lang/Thread."<init>":()V
      14: return

  public void run();
    Code:
       0: aload_0
       1: getfield      #2                  // Field val$tracker:Lorg/apache/hadoop/hbase/zookeeper/TestZKNodeTracker$TestTracker;
       4: invokevirtual #4                  // Method org/apache/hadoop/hbase/zookeeper/TestZKNodeTracker$TestTracker.blockUntilAvailable:()[B
       7: pop
       8: goto          23
      11: astore_1
      12: new           #6                  // class java/lang/RuntimeException
      15: dup
      16: ldc           #7                  // String Interrupted
      18: aload_1
      19: invokespecial #8                  // Method java/lang/RuntimeException."<init>":(Ljava/lang/String;Ljava/lang/Throwable;)V
      22: athrow
      23: return
    Exception table:
       from    to  target type
           0     8    11   Class java/lang/InterruptedException
}
