Compiled from "TestDropTimeoutRequest.java"
public class org.apache.hadoop.hbase.client.TestDropTimeoutRequest {
  public static final org.apache.hadoop.hbase.HBaseClassTestRule CLASS_RULE;

  public org.junit.rules.TestName name;

  public org.apache.hadoop.hbase.client.TestDropTimeoutRequest();
    Code:
       0: aload_0
       1: invokespecial #1                  // Method java/lang/Object."<init>":()V
       4: aload_0
       5: new           #2                  // class org/junit/rules/TestName
       8: dup
       9: invokespecial #3                  // Method org/junit/rules/TestName."<init>":()V
      12: putfield      #4                  // Field name:Lorg/junit/rules/TestName;
      15: return

  public static void setUpBeforeClass() throws java.lang.Exception;
    Code:
       0: getstatic     #5                  // Field TEST_UTIL:Lorg/apache/hadoop/hbase/HBaseTestingUtility;
       3: invokevirtual #6                  // Method org/apache/hadoop/hbase/HBaseTestingUtility.getConfiguration:()Lorg/apache/hadoop/conf/Configuration;
       6: ldc           #8                  // String hbase.status.published
       8: iconst_1
       9: invokevirtual #9                  // Method org/apache/hadoop/conf/Configuration.setBoolean:(Ljava/lang/String;Z)V
      12: getstatic     #5                  // Field TEST_UTIL:Lorg/apache/hadoop/hbase/HBaseTestingUtility;
      15: invokevirtual #6                  // Method org/apache/hadoop/hbase/HBaseTestingUtility.getConfiguration:()Lorg/apache/hadoop/conf/Configuration;
      18: ldc           #10                 // String hbase.regionserver.metahandler.count
      20: bipush        10
      22: invokevirtual #11                 // Method org/apache/hadoop/conf/Configuration.setInt:(Ljava/lang/String;I)V
      25: getstatic     #5                  // Field TEST_UTIL:Lorg/apache/hadoop/hbase/HBaseTestingUtility;
      28: invokevirtual #6                  // Method org/apache/hadoop/hbase/HBaseTestingUtility.getConfiguration:()Lorg/apache/hadoop/conf/Configuration;
      31: ldc           #12                 // String hbase.client.retries.number
      33: iconst_5
      34: invokevirtual #11                 // Method org/apache/hadoop/conf/Configuration.setInt:(Ljava/lang/String;I)V
      37: getstatic     #5                  // Field TEST_UTIL:Lorg/apache/hadoop/hbase/HBaseTestingUtility;
      40: invokevirtual #6                  // Method org/apache/hadoop/hbase/HBaseTestingUtility.getConfiguration:()Lorg/apache/hadoop/conf/Configuration;
      43: ldc           #14                 // String hbase.regionserver.handler.count
      45: iconst_1
      46: invokevirtual #11                 // Method org/apache/hadoop/conf/Configuration.setInt:(Ljava/lang/String;I)V
      49: getstatic     #5                  // Field TEST_UTIL:Lorg/apache/hadoop/hbase/HBaseTestingUtility;
      52: iconst_2
      53: invokevirtual #15                 // Method org/apache/hadoop/hbase/HBaseTestingUtility.startMiniCluster:(I)Lorg/apache/hadoop/hbase/MiniHBaseCluster;
      56: pop
      57: return

  public static void tearDownAfterClass() throws java.lang.Exception;
    Code:
       0: getstatic     #5                  // Field TEST_UTIL:Lorg/apache/hadoop/hbase/HBaseTestingUtility;
       3: invokevirtual #16                 // Method org/apache/hadoop/hbase/HBaseTestingUtility.shutdownMiniCluster:()V
       6: return

  public void testDropTimeoutRequest() throws java.lang.Exception;
    Code:
       0: aload_0
       1: getfield      #4                  // Field name:Lorg/junit/rules/TestName;
       4: invokevirtual #17                 // Method org/junit/rules/TestName.getMethodName:()Ljava/lang/String;
       7: invokestatic  #18                 // Method org/apache/hadoop/hbase/TableName.valueOf:(Ljava/lang/String;)Lorg/apache/hadoop/hbase/TableName;
      10: invokestatic  #19                 // Method org/apache/hadoop/hbase/client/TableDescriptorBuilder.newBuilder:(Lorg/apache/hadoop/hbase/TableName;)Lorg/apache/hadoop/hbase/client/TableDescriptorBuilder;
      13: astore_1
      14: aload_1
      15: ldc           #20                 // class org/apache/hadoop/hbase/client/TestDropTimeoutRequest$SleepLongerAtFirstCoprocessor
      17: invokevirtual #21                 // Method java/lang/Class.getName:()Ljava/lang/String;
      20: invokevirtual #22                 // Method org/apache/hadoop/hbase/client/TableDescriptorBuilder.setCoprocessor:(Ljava/lang/String;)Lorg/apache/hadoop/hbase/client/TableDescriptorBuilder;
      23: pop
      24: getstatic     #23                 // Field FAM_NAM:[B
      27: invokestatic  #24                 // Method org/apache/hadoop/hbase/client/ColumnFamilyDescriptorBuilder.newBuilder:([B)Lorg/apache/hadoop/hbase/client/ColumnFamilyDescriptorBuilder;
      30: invokevirtual #25                 // Method org/apache/hadoop/hbase/client/ColumnFamilyDescriptorBuilder.build:()Lorg/apache/hadoop/hbase/client/ColumnFamilyDescriptor;
      33: astore_2
      34: aload_1
      35: aload_2
      36: invokevirtual #26                 // Method org/apache/hadoop/hbase/client/TableDescriptorBuilder.setColumnFamily:(Lorg/apache/hadoop/hbase/client/ColumnFamilyDescriptor;)Lorg/apache/hadoop/hbase/client/TableDescriptorBuilder;
      39: pop
      40: aload_1
      41: invokevirtual #27                 // Method org/apache/hadoop/hbase/client/TableDescriptorBuilder.build:()Lorg/apache/hadoop/hbase/client/TableDescriptor;
      44: astore_3
      45: getstatic     #5                  // Field TEST_UTIL:Lorg/apache/hadoop/hbase/HBaseTestingUtility;
      48: invokevirtual #28                 // Method org/apache/hadoop/hbase/HBaseTestingUtility.getConnection:()Lorg/apache/hadoop/hbase/client/Connection;
      51: invokeinterface #29,  1           // InterfaceMethod org/apache/hadoop/hbase/client/Connection.getAdmin:()Lorg/apache/hadoop/hbase/client/Admin;
      56: astore        4
      58: aconst_null
      59: astore        5
      61: aload         4
      63: aload_3
      64: invokeinterface #30,  2           // InterfaceMethod org/apache/hadoop/hbase/client/Admin.createTable:(Lorg/apache/hadoop/hbase/client/TableDescriptor;)V
      69: aload         4
      71: ifnull        164
      74: aload         5
      76: ifnull        101
      79: aload         4
      81: invokeinterface #31,  1           // InterfaceMethod org/apache/hadoop/hbase/client/Admin.close:()V
      86: goto          164
      89: astore        6
      91: aload         5
      93: aload         6
      95: invokevirtual #33                 // Method java/lang/Throwable.addSuppressed:(Ljava/lang/Throwable;)V
      98: goto          164
     101: aload         4
     103: invokeinterface #31,  1           // InterfaceMethod org/apache/hadoop/hbase/client/Admin.close:()V
     108: goto          164
     111: astore        6
     113: aload         6
     115: astore        5
     117: aload         6
     119: athrow
     120: astore        7
     122: aload         4
     124: ifnull        161
     127: aload         5
     129: ifnull        154
     132: aload         4
     134: invokeinterface #31,  1           // InterfaceMethod org/apache/hadoop/hbase/client/Admin.close:()V
     139: goto          161
     142: astore        8
     144: aload         5
     146: aload         8
     148: invokevirtual #33                 // Method java/lang/Throwable.addSuppressed:(Ljava/lang/Throwable;)V
     151: goto          161
     154: aload         4
     156: invokeinterface #31,  1           // InterfaceMethod org/apache/hadoop/hbase/client/Admin.close:()V
     161: aload         7
     163: athrow
     164: getstatic     #5                  // Field TEST_UTIL:Lorg/apache/hadoop/hbase/HBaseTestingUtility;
     167: invokevirtual #28                 // Method org/apache/hadoop/hbase/HBaseTestingUtility.getConnection:()Lorg/apache/hadoop/hbase/client/Connection;
     170: aload_3
     171: invokeinterface #34,  1           // InterfaceMethod org/apache/hadoop/hbase/client/TableDescriptor.getTableName:()Lorg/apache/hadoop/hbase/TableName;
     176: aconst_null
     177: invokeinterface #35,  3           // InterfaceMethod org/apache/hadoop/hbase/client/Connection.getTableBuilder:(Lorg/apache/hadoop/hbase/TableName;Ljava/util/concurrent/ExecutorService;)Lorg/apache/hadoop/hbase/client/TableBuilder;
     182: astore        4
     184: aload         4
     186: sipush        4000
     189: invokeinterface #36,  2           // InterfaceMethod org/apache/hadoop/hbase/client/TableBuilder.setReadRpcTimeout:(I)Lorg/apache/hadoop/hbase/client/TableBuilder;
     194: pop
     195: aload         4
     197: sipush        4000
     200: invokeinterface #37,  2           // InterfaceMethod org/apache/hadoop/hbase/client/TableBuilder.setWriteRpcTimeout:(I)Lorg/apache/hadoop/hbase/client/TableBuilder;
     205: pop
     206: aload         4
     208: invokeinterface #38,  1           // InterfaceMethod org/apache/hadoop/hbase/client/TableBuilder.build:()Lorg/apache/hadoop/hbase/client/Table;
     213: astore        5
     215: aconst_null
     216: astore        6
     218: aload         5
     220: new           #39                 // class org/apache/hadoop/hbase/client/Get
     223: dup
     224: getstatic     #23                 // Field FAM_NAM:[B
     227: invokespecial #40                 // Method org/apache/hadoop/hbase/client/Get."<init>":([B)V
     230: invokeinterface #41,  2           // InterfaceMethod org/apache/hadoop/hbase/client/Table.get:(Lorg/apache/hadoop/hbase/client/Get;)Lorg/apache/hadoop/hbase/client/Result;
     235: pop
     236: aload         5
     238: ifnull        331
     241: aload         6
     243: ifnull        268
     246: aload         5
     248: invokeinterface #42,  1           // InterfaceMethod org/apache/hadoop/hbase/client/Table.close:()V
     253: goto          331
     256: astore        7
     258: aload         6
     260: aload         7
     262: invokevirtual #33                 // Method java/lang/Throwable.addSuppressed:(Ljava/lang/Throwable;)V
     265: goto          331
     268: aload         5
     270: invokeinterface #42,  1           // InterfaceMethod org/apache/hadoop/hbase/client/Table.close:()V
     275: goto          331
     278: astore        7
     280: aload         7
     282: astore        6
     284: aload         7
     286: athrow
     287: astore        9
     289: aload         5
     291: ifnull        328
     294: aload         6
     296: ifnull        321
     299: aload         5
     301: invokeinterface #42,  1           // InterfaceMethod org/apache/hadoop/hbase/client/Table.close:()V
     306: goto          328
     309: astore        10
     311: aload         6
     313: aload         10
     315: invokevirtual #33                 // Method java/lang/Throwable.addSuppressed:(Ljava/lang/Throwable;)V
     318: goto          328
     321: aload         5
     323: invokeinterface #42,  1           // InterfaceMethod org/apache/hadoop/hbase/client/Table.close:()V
     328: aload         9
     330: athrow
     331: return
    Exception table:
       from    to  target type
          79    86    89   Class java/lang/Throwable
          61    69   111   Class java/lang/Throwable
          61    69   120   any
         132   139   142   Class java/lang/Throwable
         111   122   120   any
         246   253   256   Class java/lang/Throwable
         218   236   278   Class java/lang/Throwable
         218   236   287   any
         299   306   309   Class java/lang/Throwable
         278   289   287   any

  static {};
    Code:
       0: ldc           #13                 // class org/apache/hadoop/hbase/client/TestDropTimeoutRequest
       2: invokestatic  #43                 // Method org/apache/hadoop/hbase/HBaseClassTestRule.forClass:(Ljava/lang/Class;)Lorg/apache/hadoop/hbase/HBaseClassTestRule;
       5: putstatic     #44                 // Field CLASS_RULE:Lorg/apache/hadoop/hbase/HBaseClassTestRule;
       8: ldc           #13                 // class org/apache/hadoop/hbase/client/TestDropTimeoutRequest
      10: invokestatic  #45                 // Method org/slf4j/LoggerFactory.getLogger:(Ljava/lang/Class;)Lorg/slf4j/Logger;
      13: putstatic     #46                 // Field LOG:Lorg/slf4j/Logger;
      16: new           #47                 // class org/apache/hadoop/hbase/HBaseTestingUtility
      19: dup
      20: invokespecial #48                 // Method org/apache/hadoop/hbase/HBaseTestingUtility."<init>":()V
      23: putstatic     #5                  // Field TEST_UTIL:Lorg/apache/hadoop/hbase/HBaseTestingUtility;
      26: ldc           #49                 // String f
      28: invokestatic  #50                 // Method org/apache/hadoop/hbase/util/Bytes.toBytes:(Ljava/lang/String;)[B
      31: putstatic     #23                 // Field FAM_NAM:[B
      34: return
}
