Compiled from "TestSnapshotMetadata.java"
public class org.apache.hadoop.hbase.client.TestSnapshotMetadata {
  public static final org.apache.hadoop.hbase.HBaseClassTestRule CLASS_RULE;

  org.apache.hadoop.hbase.TableName originalTableName;

  public org.apache.hadoop.hbase.client.TestSnapshotMetadata();
    Code:
       0: aload_0
       1: invokespecial #1                  // Method java/lang/Object."<init>":()V
       4: return

  public static void setupCluster() throws java.lang.Exception;
    Code:
       0: getstatic     #2                  // Field UTIL:Lorg/apache/hadoop/hbase/HBaseTestingUtility;
       3: invokevirtual #3                  // Method org/apache/hadoop/hbase/HBaseTestingUtility.getConfiguration:()Lorg/apache/hadoop/conf/Configuration;
       6: invokestatic  #4                  // Method setupConf:(Lorg/apache/hadoop/conf/Configuration;)V
       9: getstatic     #2                  // Field UTIL:Lorg/apache/hadoop/hbase/HBaseTestingUtility;
      12: iconst_2
      13: invokevirtual #6                  // Method org/apache/hadoop/hbase/HBaseTestingUtility.startMiniCluster:(I)Lorg/apache/hadoop/hbase/MiniHBaseCluster;
      16: pop
      17: getstatic     #2                  // Field UTIL:Lorg/apache/hadoop/hbase/HBaseTestingUtility;
      20: invokevirtual #7                  // Method org/apache/hadoop/hbase/HBaseTestingUtility.getHBaseCluster:()Lorg/apache/hadoop/hbase/MiniHBaseCluster;
      23: invokevirtual #8                  // Method org/apache/hadoop/hbase/MiniHBaseCluster.getMaster:()Lorg/apache/hadoop/hbase/master/HMaster;
      26: invokevirtual #9                  // Method org/apache/hadoop/hbase/master/HMaster.getMasterFileSystem:()Lorg/apache/hadoop/hbase/master/MasterFileSystem;
      29: invokevirtual #10                 // Method org/apache/hadoop/hbase/master/MasterFileSystem.getFileSystem:()Lorg/apache/hadoop/fs/FileSystem;
      32: putstatic     #11                 // Field fs:Lorg/apache/hadoop/fs/FileSystem;
      35: getstatic     #2                  // Field UTIL:Lorg/apache/hadoop/hbase/HBaseTestingUtility;
      38: invokevirtual #7                  // Method org/apache/hadoop/hbase/HBaseTestingUtility.getHBaseCluster:()Lorg/apache/hadoop/hbase/MiniHBaseCluster;
      41: invokevirtual #8                  // Method org/apache/hadoop/hbase/MiniHBaseCluster.getMaster:()Lorg/apache/hadoop/hbase/master/HMaster;
      44: invokevirtual #9                  // Method org/apache/hadoop/hbase/master/HMaster.getMasterFileSystem:()Lorg/apache/hadoop/hbase/master/MasterFileSystem;
      47: invokevirtual #12                 // Method org/apache/hadoop/hbase/master/MasterFileSystem.getRootDir:()Lorg/apache/hadoop/fs/Path;
      50: putstatic     #13                 // Field rootDir:Lorg/apache/hadoop/fs/Path;
      53: return

  public static void cleanupTest() throws java.lang.Exception;
    Code:
       0: getstatic     #2                  // Field UTIL:Lorg/apache/hadoop/hbase/HBaseTestingUtility;
       3: invokevirtual #14                 // Method org/apache/hadoop/hbase/HBaseTestingUtility.shutdownMiniCluster:()V
       6: goto          21
       9: astore_0
      10: getstatic     #16                 // Field LOG:Lorg/slf4j/Logger;
      13: ldc           #17                 // String failure shutting down cluster
      15: aload_0
      16: invokeinterface #18,  3           // InterfaceMethod org/slf4j/Logger.warn:(Ljava/lang/String;Ljava/lang/Throwable;)V
      21: return
    Exception table:
       from    to  target type
           0     6     9   Class java/lang/Exception

  public void setup() throws java.lang.Exception;
    Code:
       0: aload_0
       1: getstatic     #2                  // Field UTIL:Lorg/apache/hadoop/hbase/HBaseTestingUtility;
       4: invokevirtual #35                 // Method org/apache/hadoop/hbase/HBaseTestingUtility.getAdmin:()Lorg/apache/hadoop/hbase/client/Admin;
       7: putfield      #36                 // Field admin:Lorg/apache/hadoop/hbase/client/Admin;
      10: aload_0
      11: invokespecial #37                 // Method createTableWithNonDefaultProperties:()V
      14: return

  public void tearDown() throws java.lang.Exception;
    Code:
       0: aload_0
       1: getfield      #36                 // Field admin:Lorg/apache/hadoop/hbase/client/Admin;
       4: invokestatic  #38                 // Method org/apache/hadoop/hbase/snapshot/SnapshotTestingUtils.deleteAllSnapshots:(Lorg/apache/hadoop/hbase/client/Admin;)V
       7: return

  public void testDescribeMatchesAfterClone() throws java.lang.Exception;
    Code:
       0: new           #40                 // class java/lang/StringBuilder
       3: dup
       4: invokespecial #41                 // Method java/lang/StringBuilder."<init>":()V
       7: ldc           #79                 // String clone
       9: invokevirtual #43                 // Method java/lang/StringBuilder.append:(Ljava/lang/String;)Ljava/lang/StringBuilder;
      12: aload_0
      13: getfield      #47                 // Field originalTableName:Lorg/apache/hadoop/hbase/TableName;
      16: invokevirtual #80                 // Method java/lang/StringBuilder.append:(Ljava/lang/Object;)Ljava/lang/StringBuilder;
      19: invokevirtual #45                 // Method java/lang/StringBuilder.toString:()Ljava/lang/String;
      22: astore_1
      23: aload_1
      24: invokestatic  #46                 // Method org/apache/hadoop/hbase/TableName.valueOf:(Ljava/lang/String;)Lorg/apache/hadoop/hbase/TableName;
      27: astore_2
      28: new           #40                 // class java/lang/StringBuilder
      31: dup
      32: invokespecial #41                 // Method java/lang/StringBuilder."<init>":()V
      35: ldc           #81                 // String snapshot
      37: invokevirtual #43                 // Method java/lang/StringBuilder.append:(Ljava/lang/String;)Ljava/lang/StringBuilder;
      40: aload_0
      41: getfield      #47                 // Field originalTableName:Lorg/apache/hadoop/hbase/TableName;
      44: invokevirtual #80                 // Method java/lang/StringBuilder.append:(Ljava/lang/Object;)Ljava/lang/StringBuilder;
      47: invokestatic  #39                 // Method java/lang/System.currentTimeMillis:()J
      50: invokevirtual #44                 // Method java/lang/StringBuilder.append:(J)Ljava/lang/StringBuilder;
      53: invokevirtual #45                 // Method java/lang/StringBuilder.toString:()Ljava/lang/String;
      56: astore_3
      57: aload_3
      58: astore        4
      60: new           #82                 // class java/util/ArrayList
      63: dup
      64: invokespecial #83                 // Method java/util/ArrayList."<init>":()V
      67: astore        5
      69: aload         5
      71: getstatic     #84                 // Field families:[[B
      74: invokestatic  #85                 // Method java/util/Collections.addAll:(Ljava/util/Collection;[Ljava/lang/Object;)Z
      77: pop
      78: aload_0
      79: getfield      #36                 // Field admin:Lorg/apache/hadoop/hbase/client/Admin;
      82: aload_0
      83: getfield      #47                 // Field originalTableName:Lorg/apache/hadoop/hbase/TableName;
      86: aconst_null
      87: aload         5
      89: aload_3
      90: getstatic     #13                 // Field rootDir:Lorg/apache/hadoop/fs/Path;
      93: getstatic     #11                 // Field fs:Lorg/apache/hadoop/fs/FileSystem;
      96: iconst_0
      97: invokestatic  #86                 // Method org/apache/hadoop/hbase/snapshot/SnapshotTestingUtils.createSnapshotAndValidate:(Lorg/apache/hadoop/hbase/client/Admin;Lorg/apache/hadoop/hbase/TableName;Ljava/util/List;Ljava/util/List;Ljava/lang/String;Lorg/apache/hadoop/fs/Path;Lorg/apache/hadoop/fs/FileSystem;Z)V
     100: aload_0
     101: getfield      #36                 // Field admin:Lorg/apache/hadoop/hbase/client/Admin;
     104: aload         4
     106: aload_2
     107: invokeinterface #87,  3           // InterfaceMethod org/apache/hadoop/hbase/client/Admin.cloneSnapshot:(Ljava/lang/String;Lorg/apache/hadoop/hbase/TableName;)V
     112: getstatic     #2                  // Field UTIL:Lorg/apache/hadoop/hbase/HBaseTestingUtility;
     115: invokevirtual #71                 // Method org/apache/hadoop/hbase/HBaseTestingUtility.getConnection:()Lorg/apache/hadoop/hbase/client/Connection;
     118: aload_2
     119: invokeinterface #72,  2           // InterfaceMethod org/apache/hadoop/hbase/client/Connection.getTable:(Lorg/apache/hadoop/hbase/TableName;)Lorg/apache/hadoop/hbase/client/Table;
     124: astore        6
     126: new           #60                 // class org/apache/hadoop/hbase/HTableDescriptor
     129: dup
     130: aload_0
     131: getfield      #36                 // Field admin:Lorg/apache/hadoop/hbase/client/Admin;
     134: aload_2
     135: invokeinterface #73,  2           // InterfaceMethod org/apache/hadoop/hbase/client/Admin.getDescriptor:(Lorg/apache/hadoop/hbase/TableName;)Lorg/apache/hadoop/hbase/client/TableDescriptor;
     140: invokespecial #74                 // Method org/apache/hadoop/hbase/HTableDescriptor."<init>":(Lorg/apache/hadoop/hbase/client/TableDescriptor;)V
     143: astore        7
     145: aload_0
     146: getfield      #77                 // Field originalTableDescription:Ljava/lang/String;
     149: aload_0
     150: getfield      #47                 // Field originalTableName:Lorg/apache/hadoop/hbase/TableName;
     153: invokevirtual #88                 // Method org/apache/hadoop/hbase/TableName.getNameAsString:()Ljava/lang/String;
     156: aload_1
     157: invokevirtual #89                 // Method java/lang/String.replace:(Ljava/lang/CharSequence;Ljava/lang/CharSequence;)Ljava/lang/String;
     160: aload         7
     162: invokevirtual #76                 // Method org/apache/hadoop/hbase/HTableDescriptor.toStringCustomizedValues:()Ljava/lang/String;
     165: invokestatic  #90                 // Method org/junit/Assert.assertEquals:(Ljava/lang/Object;Ljava/lang/Object;)V
     168: aload_0
     169: getfield      #75                 // Field originalTableDescriptor:Lorg/apache/hadoop/hbase/HTableDescriptor;
     172: invokevirtual #91                 // Method org/apache/hadoop/hbase/HTableDescriptor.getValues:()Ljava/util/Map;
     175: invokeinterface #68,  1           // InterfaceMethod java/util/Map.size:()I
     180: i2l
     181: aload         7
     183: invokevirtual #91                 // Method org/apache/hadoop/hbase/HTableDescriptor.getValues:()Ljava/util/Map;
     186: invokeinterface #68,  1           // InterfaceMethod java/util/Map.size:()I
     191: i2l
     192: invokestatic  #92                 // Method org/junit/Assert.assertEquals:(JJ)V
     195: aload_0
     196: getfield      #75                 // Field originalTableDescriptor:Lorg/apache/hadoop/hbase/HTableDescriptor;
     199: invokevirtual #67                 // Method org/apache/hadoop/hbase/HTableDescriptor.getConfiguration:()Ljava/util/Map;
     202: invokeinterface #68,  1           // InterfaceMethod java/util/Map.size:()I
     207: i2l
     208: aload         7
     210: invokevirtual #67                 // Method org/apache/hadoop/hbase/HTableDescriptor.getConfiguration:()Ljava/util/Map;
     213: invokeinterface #68,  1           // InterfaceMethod java/util/Map.size:()I
     218: i2l
     219: invokestatic  #92                 // Method org/junit/Assert.assertEquals:(JJ)V
     222: ldc           #63                 // String TestCustomValue
     224: aload         7
     226: ldc           #63                 // String TestCustomValue
     228: invokevirtual #93                 // Method org/apache/hadoop/hbase/HTableDescriptor.getValue:(Ljava/lang/String;)Ljava/lang/String;
     231: invokestatic  #90                 // Method org/junit/Assert.assertEquals:(Ljava/lang/Object;Ljava/lang/Object;)V
     234: ldc           #65                 // String TestCustomConf
     236: aload         7
     238: ldc           #65                 // String TestCustomConf
     240: invokevirtual #94                 // Method org/apache/hadoop/hbase/HTableDescriptor.getConfigurationValue:(Ljava/lang/String;)Ljava/lang/String;
     243: invokestatic  #90                 // Method org/junit/Assert.assertEquals:(Ljava/lang/Object;Ljava/lang/Object;)V
     246: aload_0
     247: getfield      #75                 // Field originalTableDescriptor:Lorg/apache/hadoop/hbase/HTableDescriptor;
     250: invokevirtual #91                 // Method org/apache/hadoop/hbase/HTableDescriptor.getValues:()Ljava/util/Map;
     253: aload         7
     255: invokevirtual #91                 // Method org/apache/hadoop/hbase/HTableDescriptor.getValues:()Ljava/util/Map;
     258: invokestatic  #90                 // Method org/junit/Assert.assertEquals:(Ljava/lang/Object;Ljava/lang/Object;)V
     261: aload_0
     262: getfield      #75                 // Field originalTableDescriptor:Lorg/apache/hadoop/hbase/HTableDescriptor;
     265: invokevirtual #67                 // Method org/apache/hadoop/hbase/HTableDescriptor.getConfiguration:()Ljava/util/Map;
     268: aload         7
     270: invokevirtual #67                 // Method org/apache/hadoop/hbase/HTableDescriptor.getConfiguration:()Ljava/util/Map;
     273: invokestatic  #90                 // Method org/junit/Assert.assertEquals:(Ljava/lang/Object;Ljava/lang/Object;)V
     276: aload_0
     277: getfield      #36                 // Field admin:Lorg/apache/hadoop/hbase/client/Admin;
     280: aload_0
     281: getfield      #47                 // Field originalTableName:Lorg/apache/hadoop/hbase/TableName;
     284: invokeinterface #95,  2           // InterfaceMethod org/apache/hadoop/hbase/client/Admin.enableTable:(Lorg/apache/hadoop/hbase/TableName;)V
     289: aload         6
     291: invokeinterface #78,  1           // InterfaceMethod org/apache/hadoop/hbase/client/Table.close:()V
     296: return

  public void testDescribeMatchesAfterRestore() throws java.lang.Exception;
    Code:
       0: aload_0
       1: iconst_0
       2: invokespecial #96                 // Method runRestoreWithAdditionalMetadata:(Z)V
       5: return

  public void testDescribeMatchesAfterMetadataChangeAndRestore() throws java.lang.Exception;
    Code:
       0: aload_0
       1: iconst_1
       2: invokespecial #96                 // Method runRestoreWithAdditionalMetadata:(Z)V
       5: return

  public void testDescribeOnEmptyTableMatchesAfterMetadataChangeAndRestore() throws java.lang.Exception;
    Code:
       0: aload_0
       1: iconst_1
       2: iconst_0
       3: invokespecial #97                 // Method runRestoreWithAdditionalMetadata:(ZZ)V
       6: return

  static {};
    Code:
       0: ldc           #5                  // class org/apache/hadoop/hbase/client/TestSnapshotMetadata
       2: invokestatic  #113                // Method org/apache/hadoop/hbase/HBaseClassTestRule.forClass:(Ljava/lang/Class;)Lorg/apache/hadoop/hbase/HBaseClassTestRule;
       5: putstatic     #114                // Field CLASS_RULE:Lorg/apache/hadoop/hbase/HBaseClassTestRule;
       8: ldc           #5                  // class org/apache/hadoop/hbase/client/TestSnapshotMetadata
      10: invokestatic  #115                // Method org/slf4j/LoggerFactory.getLogger:(Ljava/lang/Class;)Lorg/slf4j/Logger;
      13: putstatic     #16                 // Field LOG:Lorg/slf4j/Logger;
      16: new           #116                // class org/apache/hadoop/hbase/HBaseTestingUtility
      19: dup
      20: invokespecial #117                // Method org/apache/hadoop/hbase/HBaseTestingUtility."<init>":()V
      23: putstatic     #2                  // Field UTIL:Lorg/apache/hadoop/hbase/HBaseTestingUtility;
      26: ldc           #118                // String fam_max_columns
      28: invokestatic  #102                // Method org/apache/hadoop/hbase/util/Bytes.toBytes:(Ljava/lang/String;)[B
      31: putstatic     #49                 // Field MAX_VERSIONS_FAM:[B
      34: ldc           #119                // String fam_compressed
      36: invokestatic  #102                // Method org/apache/hadoop/hbase/util/Bytes.toBytes:(Ljava/lang/String;)[B
      39: putstatic     #52                 // Field COMPRESSED_FAM:[B
      42: ldc           #120                // String fam_blocksize
      44: invokestatic  #102                // Method org/apache/hadoop/hbase/util/Bytes.toBytes:(Ljava/lang/String;)[B
      47: putstatic     #53                 // Field BLOCKSIZE_FAM:[B
      50: ldc           #121                // String fam_bloomfilter
      52: invokestatic  #102                // Method org/apache/hadoop/hbase/util/Bytes.toBytes:(Ljava/lang/String;)[B
      55: putstatic     #51                 // Field BLOOMFILTER_FAM:[B
      58: iconst_4
      59: anewarray     #122                // class "[B"
      62: dup
      63: iconst_0
      64: getstatic     #49                 // Field MAX_VERSIONS_FAM:[B
      67: aastore
      68: dup
      69: iconst_1
      70: getstatic     #51                 // Field BLOOMFILTER_FAM:[B
      73: aastore
      74: dup
      75: iconst_2
      76: getstatic     #52                 // Field COMPRESSED_FAM:[B
      79: aastore
      80: dup
      81: iconst_3
      82: getstatic     #53                 // Field BLOCKSIZE_FAM:[B
      85: aastore
      86: putstatic     #84                 // Field families:[[B
      89: getstatic     #123                // Field org/apache/hadoop/hbase/io/encoding/DataBlockEncoding.FAST_DIFF:Lorg/apache/hadoop/hbase/io/encoding/DataBlockEncoding;
      92: putstatic     #57                 // Field DATA_BLOCK_ENCODING_TYPE:Lorg/apache/hadoop/hbase/io/encoding/DataBlockEncoding;
      95: getstatic     #124                // Field org/apache/hadoop/hbase/regionserver/BloomType.ROW:Lorg/apache/hadoop/hbase/regionserver/BloomType;
      98: putstatic     #55                 // Field BLOOM_TYPE:Lorg/apache/hadoop/hbase/regionserver/BloomType;
     101: return
}
