Compiled from "TestAES.java"
class org.apache.hadoop.hbase.io.crypto.aes.TestAES$TestProvider extends java.security.Provider {
  public org.apache.hadoop.hbase.io.crypto.aes.TestAES$TestProvider();
    Code:
       0: aload_0
       1: ldc           #1                  // String TEST
       3: dconst_1
       4: ldc           #2                  // String Test provider
       6: invokespecial #3                  // Method java/security/Provider."<init>":(Ljava/lang/String;DLjava/lang/String;)V
       9: new           #4                  // class org/apache/hadoop/hbase/io/crypto/aes/TestAES$TestProvider$1
      12: dup
      13: aload_0
      14: invokespecial #5                  // Method org/apache/hadoop/hbase/io/crypto/aes/TestAES$TestProvider$1."<init>":(Lorg/apache/hadoop/hbase/io/crypto/aes/TestAES$TestProvider;)V
      17: invokestatic  #6                  // Method java/security/AccessController.doPrivileged:(Ljava/security/PrivilegedAction;)Ljava/lang/Object;
      20: pop
      21: return
}
