Compiled from "TestStripeStoreFileManager.java"
public class org.apache.hadoop.hbase.regionserver.TestStripeStoreFileManager {
  public static final org.apache.hadoop.hbase.HBaseClassTestRule CLASS_RULE;

  public org.apache.hadoop.hbase.regionserver.TestStripeStoreFileManager();
    Code:
       0: aload_0
       1: invokespecial #1                  // Method java/lang/Object."<init>":()V
       4: return

  public void setUp() throws java.lang.Exception;
    Code:
       0: getstatic     #2                  // Field TEST_UTIL:Lorg/apache/hadoop/hbase/HBaseTestingUtility;
       3: invokevirtual #3                  // Method org/apache/hadoop/hbase/HBaseTestingUtility.getTestFileSystem:()Lorg/apache/hadoop/fs/FileSystem;
       6: astore_1
       7: aload_1
       8: getstatic     #4                  // Field CFDIR:Lorg/apache/hadoop/fs/Path;
      11: invokevirtual #5                  // Method org/apache/hadoop/fs/FileSystem.mkdirs:(Lorg/apache/hadoop/fs/Path;)Z
      14: ifne          46
      17: new           #6                  // class java/io/IOException
      20: dup
      21: new           #7                  // class java/lang/StringBuilder
      24: dup
      25: invokespecial #8                  // Method java/lang/StringBuilder."<init>":()V
      28: ldc           #9                  // String Cannot create test directory
      30: invokevirtual #10                 // Method java/lang/StringBuilder.append:(Ljava/lang/String;)Ljava/lang/StringBuilder;
      33: getstatic     #4                  // Field CFDIR:Lorg/apache/hadoop/fs/Path;
      36: invokevirtual #11                 // Method java/lang/StringBuilder.append:(Ljava/lang/Object;)Ljava/lang/StringBuilder;
      39: invokevirtual #12                 // Method java/lang/StringBuilder.toString:()Ljava/lang/String;
      42: invokespecial #13                 // Method java/io/IOException."<init>":(Ljava/lang/String;)V
      45: athrow
      46: return

  public void tearDown() throws java.lang.Exception;
    Code:
       0: getstatic     #2                  // Field TEST_UTIL:Lorg/apache/hadoop/hbase/HBaseTestingUtility;
       3: invokevirtual #3                  // Method org/apache/hadoop/hbase/HBaseTestingUtility.getTestFileSystem:()Lorg/apache/hadoop/fs/FileSystem;
       6: astore_1
       7: aload_1
       8: getstatic     #4                  // Field CFDIR:Lorg/apache/hadoop/fs/Path;
      11: invokevirtual #14                 // Method org/apache/hadoop/fs/FileSystem.exists:(Lorg/apache/hadoop/fs/Path;)Z
      14: ifeq          57
      17: aload_1
      18: getstatic     #4                  // Field CFDIR:Lorg/apache/hadoop/fs/Path;
      21: iconst_1
      22: invokevirtual #15                 // Method org/apache/hadoop/fs/FileSystem.delete:(Lorg/apache/hadoop/fs/Path;Z)Z
      25: ifne          57
      28: new           #6                  // class java/io/IOException
      31: dup
      32: new           #7                  // class java/lang/StringBuilder
      35: dup
      36: invokespecial #8                  // Method java/lang/StringBuilder."<init>":()V
      39: ldc           #16                 // String Cannot delete test directory
      41: invokevirtual #10                 // Method java/lang/StringBuilder.append:(Ljava/lang/String;)Ljava/lang/StringBuilder;
      44: getstatic     #4                  // Field CFDIR:Lorg/apache/hadoop/fs/Path;
      47: invokevirtual #11                 // Method java/lang/StringBuilder.append:(Ljava/lang/Object;)Ljava/lang/StringBuilder;
      50: invokevirtual #12                 // Method java/lang/StringBuilder.toString:()Ljava/lang/String;
      53: invokespecial #13                 // Method java/io/IOException."<init>":(Ljava/lang/String;)V
      56: athrow
      57: return

  public void testInsertFilesIntoL0() throws java.lang.Exception;
    Code:
       0: invokestatic  #17                 // Method createManager:()Lorg/apache/hadoop/hbase/regionserver/StripeStoreFileManager;
       3: astore_1
       4: invokestatic  #18                 // Method createFile:()Lorg/apache/hadoop/hbase/regionserver/MockHStoreFile;
       7: astore_2
       8: aload_1
       9: iconst_1
      10: anewarray     #19                 // class org/apache/hadoop/hbase/regionserver/HStoreFile
      13: dup
      14: iconst_0
      15: aload_2
      16: aastore
      17: invokestatic  #20                 // Method al:([Lorg/apache/hadoop/hbase/regionserver/HStoreFile;)Ljava/util/ArrayList;
      20: invokevirtual #21                 // Method org/apache/hadoop/hbase/regionserver/StripeStoreFileManager.insertNewFiles:(Ljava/util/Collection;)V
      23: lconst_1
      24: aload_1
      25: invokevirtual #22                 // Method org/apache/hadoop/hbase/regionserver/StripeStoreFileManager.getStorefileCount:()I
      28: i2l
      29: invokestatic  #23                 // Method org/junit/Assert.assertEquals:(JJ)V
      32: aload_1
      33: getstatic     #24                 // Field KEY_A:[B
      36: iconst_1
      37: getstatic     #24                 // Field KEY_A:[B
      40: iconst_1
      41: invokevirtual #25                 // Method org/apache/hadoop/hbase/regionserver/StripeStoreFileManager.getFilesForScan:([BZ[BZ)Ljava/util/Collection;
      44: astore_3
      45: lconst_1
      46: aload_3
      47: invokeinterface #26,  1           // InterfaceMethod java/util/Collection.size:()I
      52: i2l
      53: invokestatic  #23                 // Method org/junit/Assert.assertEquals:(JJ)V
      56: aload_3
      57: aload_2
      58: invokeinterface #27,  2           // InterfaceMethod java/util/Collection.contains:(Ljava/lang/Object;)Z
      63: invokestatic  #28                 // Method org/junit/Assert.assertTrue:(Z)V
      66: aload_1
      67: iconst_0
      68: anewarray     #19                 // class org/apache/hadoop/hbase/regionserver/HStoreFile
      71: invokestatic  #20                 // Method al:([Lorg/apache/hadoop/hbase/regionserver/HStoreFile;)Ljava/util/ArrayList;
      74: iconst_2
      75: anewarray     #19                 // class org/apache/hadoop/hbase/regionserver/HStoreFile
      78: dup
      79: iconst_0
      80: getstatic     #29                 // Field org/apache/hadoop/hbase/regionserver/StripeStoreFileManager.OPEN_KEY:[B
      83: getstatic     #30                 // Field KEY_B:[B
      86: invokestatic  #31                 // Method createFile:([B[B)Lorg/apache/hadoop/hbase/regionserver/MockHStoreFile;
      89: aastore
      90: dup
      91: iconst_1
      92: getstatic     #30                 // Field KEY_B:[B
      95: getstatic     #29                 // Field org/apache/hadoop/hbase/regionserver/StripeStoreFileManager.OPEN_KEY:[B
      98: invokestatic  #31                 // Method createFile:([B[B)Lorg/apache/hadoop/hbase/regionserver/MockHStoreFile;
     101: aastore
     102: invokestatic  #20                 // Method al:([Lorg/apache/hadoop/hbase/regionserver/HStoreFile;)Ljava/util/ArrayList;
     105: invokevirtual #32                 // Method org/apache/hadoop/hbase/regionserver/StripeStoreFileManager.addCompactionResults:(Ljava/util/Collection;Ljava/util/Collection;)V
     108: aload_1
     109: getstatic     #24                 // Field KEY_A:[B
     112: iconst_1
     113: getstatic     #24                 // Field KEY_A:[B
     116: iconst_1
     117: invokevirtual #25                 // Method org/apache/hadoop/hbase/regionserver/StripeStoreFileManager.getFilesForScan:([BZ[BZ)Ljava/util/Collection;
     120: aload_2
     121: invokeinterface #27,  2           // InterfaceMethod java/util/Collection.contains:(Ljava/lang/Object;)Z
     126: invokestatic  #28                 // Method org/junit/Assert.assertTrue:(Z)V
     129: aload_1
     130: getstatic     #33                 // Field KEY_C:[B
     133: iconst_1
     134: getstatic     #33                 // Field KEY_C:[B
     137: iconst_1
     138: invokevirtual #25                 // Method org/apache/hadoop/hbase/regionserver/StripeStoreFileManager.getFilesForScan:([BZ[BZ)Ljava/util/Collection;
     141: aload_2
     142: invokeinterface #27,  2           // InterfaceMethod java/util/Collection.contains:(Ljava/lang/Object;)Z
     147: invokestatic  #28                 // Method org/junit/Assert.assertTrue:(Z)V
     150: return

  public void testClearFiles() throws java.lang.Exception;
    Code:
       0: invokestatic  #17                 // Method createManager:()Lorg/apache/hadoop/hbase/regionserver/StripeStoreFileManager;
       3: astore_1
       4: aload_1
       5: iconst_1
       6: anewarray     #19                 // class org/apache/hadoop/hbase/regionserver/HStoreFile
       9: dup
      10: iconst_0
      11: invokestatic  #18                 // Method createFile:()Lorg/apache/hadoop/hbase/regionserver/MockHStoreFile;
      14: aastore
      15: invokestatic  #20                 // Method al:([Lorg/apache/hadoop/hbase/regionserver/HStoreFile;)Ljava/util/ArrayList;
      18: invokevirtual #21                 // Method org/apache/hadoop/hbase/regionserver/StripeStoreFileManager.insertNewFiles:(Ljava/util/Collection;)V
      21: aload_1
      22: iconst_1
      23: anewarray     #19                 // class org/apache/hadoop/hbase/regionserver/HStoreFile
      26: dup
      27: iconst_0
      28: invokestatic  #18                 // Method createFile:()Lorg/apache/hadoop/hbase/regionserver/MockHStoreFile;
      31: aastore
      32: invokestatic  #20                 // Method al:([Lorg/apache/hadoop/hbase/regionserver/HStoreFile;)Ljava/util/ArrayList;
      35: invokevirtual #21                 // Method org/apache/hadoop/hbase/regionserver/StripeStoreFileManager.insertNewFiles:(Ljava/util/Collection;)V
      38: aload_1
      39: iconst_0
      40: anewarray     #19                 // class org/apache/hadoop/hbase/regionserver/HStoreFile
      43: invokestatic  #20                 // Method al:([Lorg/apache/hadoop/hbase/regionserver/HStoreFile;)Ljava/util/ArrayList;
      46: iconst_2
      47: anewarray     #19                 // class org/apache/hadoop/hbase/regionserver/HStoreFile
      50: dup
      51: iconst_0
      52: getstatic     #29                 // Field org/apache/hadoop/hbase/regionserver/StripeStoreFileManager.OPEN_KEY:[B
      55: getstatic     #30                 // Field KEY_B:[B
      58: invokestatic  #31                 // Method createFile:([B[B)Lorg/apache/hadoop/hbase/regionserver/MockHStoreFile;
      61: aastore
      62: dup
      63: iconst_1
      64: getstatic     #30                 // Field KEY_B:[B
      67: getstatic     #29                 // Field org/apache/hadoop/hbase/regionserver/StripeStoreFileManager.OPEN_KEY:[B
      70: invokestatic  #31                 // Method createFile:([B[B)Lorg/apache/hadoop/hbase/regionserver/MockHStoreFile;
      73: aastore
      74: invokestatic  #20                 // Method al:([Lorg/apache/hadoop/hbase/regionserver/HStoreFile;)Ljava/util/ArrayList;
      77: invokevirtual #32                 // Method org/apache/hadoop/hbase/regionserver/StripeStoreFileManager.addCompactionResults:(Ljava/util/Collection;Ljava/util/Collection;)V
      80: ldc2_w        #34                 // long 4l
      83: aload_1
      84: invokevirtual #22                 // Method org/apache/hadoop/hbase/regionserver/StripeStoreFileManager.getStorefileCount:()I
      87: i2l
      88: invokestatic  #23                 // Method org/junit/Assert.assertEquals:(JJ)V
      91: aload_1
      92: invokevirtual #36                 // Method org/apache/hadoop/hbase/regionserver/StripeStoreFileManager.clearFiles:()Lorg/apache/hbase/thirdparty/com/google/common/collect/ImmutableCollection;
      95: astore_2
      96: ldc2_w        #34                 // long 4l
      99: aload_2
     100: invokeinterface #26,  1           // InterfaceMethod java/util/Collection.size:()I
     105: i2l
     106: invokestatic  #23                 // Method org/junit/Assert.assertEquals:(JJ)V
     109: lconst_0
     110: aload_1
     111: invokevirtual #22                 // Method org/apache/hadoop/hbase/regionserver/StripeStoreFileManager.getStorefileCount:()I
     114: i2l
     115: invokestatic  #23                 // Method org/junit/Assert.assertEquals:(JJ)V
     118: lconst_0
     119: aload_1
     120: invokevirtual #37                 // Method org/apache/hadoop/hbase/regionserver/StripeStoreFileManager.getStorefiles:()Ljava/util/Collection;
     123: invokeinterface #26,  1           // InterfaceMethod java/util/Collection.size:()I
     128: i2l
     129: invokestatic  #23                 // Method org/junit/Assert.assertEquals:(JJ)V
     132: return

  public void testRowKeyBefore() throws java.lang.Exception;
    Code:
       0: invokestatic  #17                 // Method createManager:()Lorg/apache/hadoop/hbase/regionserver/StripeStoreFileManager;
       3: astore_1
       4: invokestatic  #18                 // Method createFile:()Lorg/apache/hadoop/hbase/regionserver/MockHStoreFile;
       7: astore_2
       8: invokestatic  #18                 // Method createFile:()Lorg/apache/hadoop/hbase/regionserver/MockHStoreFile;
      11: astore_3
      12: aload_1
      13: iconst_1
      14: anewarray     #19                 // class org/apache/hadoop/hbase/regionserver/HStoreFile
      17: dup
      18: iconst_0
      19: aload_2
      20: aastore
      21: invokestatic  #20                 // Method al:([Lorg/apache/hadoop/hbase/regionserver/HStoreFile;)Ljava/util/ArrayList;
      24: invokevirtual #21                 // Method org/apache/hadoop/hbase/regionserver/StripeStoreFileManager.insertNewFiles:(Ljava/util/Collection;)V
      27: aload_1
      28: iconst_1
      29: anewarray     #19                 // class org/apache/hadoop/hbase/regionserver/HStoreFile
      32: dup
      33: iconst_0
      34: aload_3
      35: aastore
      36: invokestatic  #20                 // Method al:([Lorg/apache/hadoop/hbase/regionserver/HStoreFile;)Ljava/util/ArrayList;
      39: invokevirtual #21                 // Method org/apache/hadoop/hbase/regionserver/StripeStoreFileManager.insertNewFiles:(Ljava/util/Collection;)V
      42: aload_1
      43: getstatic     #43                 // Field KV_B:Lorg/apache/hadoop/hbase/KeyValue;
      46: invokevirtual #44                 // Method org/apache/hadoop/hbase/regionserver/StripeStoreFileManager.getCandidateFilesForRowKeyBefore:(Lorg/apache/hadoop/hbase/KeyValue;)Ljava/util/Iterator;
      49: astore        4
      51: aload         4
      53: invokeinterface #41,  1           // InterfaceMethod java/util/Iterator.next:()Ljava/lang/Object;
      58: pop
      59: aload         4
      61: invokeinterface #45,  1           // InterfaceMethod java/util/Iterator.remove:()V
      66: aload_1
      67: aload         4
      69: getstatic     #43                 // Field KV_B:Lorg/apache/hadoop/hbase/KeyValue;
      72: getstatic     #46                 // Field KV_A:Lorg/apache/hadoop/hbase/KeyValue;
      75: invokevirtual #47                 // Method org/apache/hadoop/hbase/regionserver/StripeStoreFileManager.updateCandidateFilesForRowKeyBefore:(Ljava/util/Iterator;Lorg/apache/hadoop/hbase/KeyValue;Lorg/apache/hadoop/hbase/Cell;)Ljava/util/Iterator;
      78: astore        4
      80: aload         4
      82: invokeinterface #40,  1           // InterfaceMethod java/util/Iterator.hasNext:()Z
      87: invokestatic  #28                 // Method org/junit/Assert.assertTrue:(Z)V
      90: lconst_0
      91: ldc2_w        #48                 // long 100l
      94: getstatic     #29                 // Field org/apache/hadoop/hbase/regionserver/StripeStoreFileManager.OPEN_KEY:[B
      97: getstatic     #30                 // Field KEY_B:[B
     100: invokestatic  #50                 // Method createFile:(JJ[B[B)Lorg/apache/hadoop/hbase/regionserver/MockHStoreFile;
     103: astore        5
     105: getstatic     #30                 // Field KEY_B:[B
     108: getstatic     #29                 // Field org/apache/hadoop/hbase/regionserver/StripeStoreFileManager.OPEN_KEY:[B
     111: invokestatic  #31                 // Method createFile:([B[B)Lorg/apache/hadoop/hbase/regionserver/MockHStoreFile;
     114: astore        6
     116: aload_1
     117: iconst_1
     118: anewarray     #19                 // class org/apache/hadoop/hbase/regionserver/HStoreFile
     121: dup
     122: iconst_0
     123: aload_2
     124: aastore
     125: invokestatic  #20                 // Method al:([Lorg/apache/hadoop/hbase/regionserver/HStoreFile;)Ljava/util/ArrayList;
     128: iconst_2
     129: anewarray     #19                 // class org/apache/hadoop/hbase/regionserver/HStoreFile
     132: dup
     133: iconst_0
     134: aload         5
     136: aastore
     137: dup
     138: iconst_1
     139: aload         6
     141: aastore
     142: invokestatic  #20                 // Method al:([Lorg/apache/hadoop/hbase/regionserver/HStoreFile;)Ljava/util/ArrayList;
     145: invokevirtual #32                 // Method org/apache/hadoop/hbase/regionserver/StripeStoreFileManager.addCompactionResults:(Ljava/util/Collection;Ljava/util/Collection;)V
     148: aload_1
     149: iconst_1
     150: anewarray     #19                 // class org/apache/hadoop/hbase/regionserver/HStoreFile
     153: dup
     154: iconst_0
     155: aload_2
     156: aastore
     157: invokestatic  #20                 // Method al:([Lorg/apache/hadoop/hbase/regionserver/HStoreFile;)Ljava/util/ArrayList;
     160: invokevirtual #51                 // Method org/apache/hadoop/hbase/regionserver/StripeStoreFileManager.removeCompactedFiles:(Ljava/util/Collection;)V
     163: aload_1
     164: getstatic     #46                 // Field KV_A:Lorg/apache/hadoop/hbase/KeyValue;
     167: invokevirtual #44                 // Method org/apache/hadoop/hbase/regionserver/StripeStoreFileManager.getCandidateFilesForRowKeyBefore:(Lorg/apache/hadoop/hbase/KeyValue;)Ljava/util/Iterator;
     170: invokestatic  #52                 // Method dumpIterator:(Ljava/util/Iterator;)Ljava/util/ArrayList;
     173: astore        7
     175: ldc2_w        #53                 // long 2l
     178: aload         7
     180: invokevirtual #55                 // Method java/util/ArrayList.size:()I
     183: i2l
     184: invokestatic  #23                 // Method org/junit/Assert.assertEquals:(JJ)V
     187: aload         7
     189: aload         5
     191: invokevirtual #56                 // Method java/util/ArrayList.contains:(Ljava/lang/Object;)Z
     194: invokestatic  #28                 // Method org/junit/Assert.assertTrue:(Z)V
     197: aload         7
     199: aload         6
     201: invokevirtual #56                 // Method java/util/ArrayList.contains:(Ljava/lang/Object;)Z
     204: invokestatic  #57                 // Method org/junit/Assert.assertFalse:(Z)V
     207: aload_1
     208: getstatic     #43                 // Field KV_B:Lorg/apache/hadoop/hbase/KeyValue;
     211: invokevirtual #44                 // Method org/apache/hadoop/hbase/regionserver/StripeStoreFileManager.getCandidateFilesForRowKeyBefore:(Lorg/apache/hadoop/hbase/KeyValue;)Ljava/util/Iterator;
     214: invokestatic  #52                 // Method dumpIterator:(Ljava/util/Iterator;)Ljava/util/ArrayList;
     217: astore        7
     219: ldc2_w        #58                 // long 3l
     222: aload         7
     224: invokevirtual #55                 // Method java/util/ArrayList.size:()I
     227: i2l
     228: invokestatic  #23                 // Method org/junit/Assert.assertEquals:(JJ)V
     231: aload         7
     233: aload         6
     235: invokevirtual #56                 // Method java/util/ArrayList.contains:(Ljava/lang/Object;)Z
     238: invokestatic  #28                 // Method org/junit/Assert.assertTrue:(Z)V
     241: aload_1
     242: getstatic     #60                 // Field KV_D:Lorg/apache/hadoop/hbase/KeyValue;
     245: invokevirtual #44                 // Method org/apache/hadoop/hbase/regionserver/StripeStoreFileManager.getCandidateFilesForRowKeyBefore:(Lorg/apache/hadoop/hbase/KeyValue;)Ljava/util/Iterator;
     248: invokestatic  #52                 // Method dumpIterator:(Ljava/util/Iterator;)Ljava/util/ArrayList;
     251: astore        7
     253: ldc2_w        #58                 // long 3l
     256: aload         7
     258: invokevirtual #55                 // Method java/util/ArrayList.size:()I
     261: i2l
     262: invokestatic  #23                 // Method org/junit/Assert.assertEquals:(JJ)V
     265: aload_1
     266: getstatic     #60                 // Field KV_D:Lorg/apache/hadoop/hbase/KeyValue;
     269: invokevirtual #44                 // Method org/apache/hadoop/hbase/regionserver/StripeStoreFileManager.getCandidateFilesForRowKeyBefore:(Lorg/apache/hadoop/hbase/KeyValue;)Ljava/util/Iterator;
     272: astore        4
     274: aload         4
     276: invokeinterface #41,  1           // InterfaceMethod java/util/Iterator.next:()Ljava/lang/Object;
     281: pop
     282: aload         4
     284: invokeinterface #45,  1           // InterfaceMethod java/util/Iterator.remove:()V
     289: aload_1
     290: aload         4
     292: getstatic     #60                 // Field KV_D:Lorg/apache/hadoop/hbase/KeyValue;
     295: getstatic     #61                 // Field KV_C:Lorg/apache/hadoop/hbase/KeyValue;
     298: invokevirtual #47                 // Method org/apache/hadoop/hbase/regionserver/StripeStoreFileManager.updateCandidateFilesForRowKeyBefore:(Ljava/util/Iterator;Lorg/apache/hadoop/hbase/KeyValue;Lorg/apache/hadoop/hbase/Cell;)Ljava/util/Iterator;
     301: astore        4
     303: aload         6
     305: aload         4
     307: invokeinterface #41,  1           // InterfaceMethod java/util/Iterator.next:()Ljava/lang/Object;
     312: invokestatic  #62                 // Method org/junit/Assert.assertEquals:(Ljava/lang/Object;Ljava/lang/Object;)V
     315: aload         4
     317: invokeinterface #40,  1           // InterfaceMethod java/util/Iterator.hasNext:()Z
     322: invokestatic  #57                 // Method org/junit/Assert.assertFalse:(Z)V
     325: lconst_0
     326: ldc2_w        #63                 // long 101l
     329: getstatic     #29                 // Field org/apache/hadoop/hbase/regionserver/StripeStoreFileManager.OPEN_KEY:[B
     332: getstatic     #30                 // Field KEY_B:[B
     335: invokestatic  #50                 // Method createFile:(JJ[B[B)Lorg/apache/hadoop/hbase/regionserver/MockHStoreFile;
     338: astore        8
     340: aload_1
     341: iconst_1
     342: anewarray     #19                 // class org/apache/hadoop/hbase/regionserver/HStoreFile
     345: dup
     346: iconst_0
     347: aload_3
     348: aastore
     349: invokestatic  #20                 // Method al:([Lorg/apache/hadoop/hbase/regionserver/HStoreFile;)Ljava/util/ArrayList;
     352: iconst_1
     353: anewarray     #19                 // class org/apache/hadoop/hbase/regionserver/HStoreFile
     356: dup
     357: iconst_0
     358: aload         8
     360: aastore
     361: invokestatic  #20                 // Method al:([Lorg/apache/hadoop/hbase/regionserver/HStoreFile;)Ljava/util/ArrayList;
     364: invokevirtual #32                 // Method org/apache/hadoop/hbase/regionserver/StripeStoreFileManager.addCompactionResults:(Ljava/util/Collection;Ljava/util/Collection;)V
     367: aload_1
     368: iconst_1
     369: anewarray     #19                 // class org/apache/hadoop/hbase/regionserver/HStoreFile
     372: dup
     373: iconst_0
     374: aload_3
     375: aastore
     376: invokestatic  #20                 // Method al:([Lorg/apache/hadoop/hbase/regionserver/HStoreFile;)Ljava/util/ArrayList;
     379: invokevirtual #51                 // Method org/apache/hadoop/hbase/regionserver/StripeStoreFileManager.removeCompactedFiles:(Ljava/util/Collection;)V
     382: aload_1
     383: getstatic     #46                 // Field KV_A:Lorg/apache/hadoop/hbase/KeyValue;
     386: invokevirtual #44                 // Method org/apache/hadoop/hbase/regionserver/StripeStoreFileManager.getCandidateFilesForRowKeyBefore:(Lorg/apache/hadoop/hbase/KeyValue;)Ljava/util/Iterator;
     389: astore        4
     391: aload         8
     393: aload         4
     395: invokeinterface #41,  1           // InterfaceMethod java/util/Iterator.next:()Ljava/lang/Object;
     400: invokestatic  #62                 // Method org/junit/Assert.assertEquals:(Ljava/lang/Object;Ljava/lang/Object;)V
     403: aload         4
     405: invokeinterface #45,  1           // InterfaceMethod java/util/Iterator.remove:()V
     410: aload_1
     411: aload         4
     413: getstatic     #46                 // Field KV_A:Lorg/apache/hadoop/hbase/KeyValue;
     416: getstatic     #46                 // Field KV_A:Lorg/apache/hadoop/hbase/KeyValue;
     419: invokevirtual #47                 // Method org/apache/hadoop/hbase/regionserver/StripeStoreFileManager.updateCandidateFilesForRowKeyBefore:(Ljava/util/Iterator;Lorg/apache/hadoop/hbase/KeyValue;Lorg/apache/hadoop/hbase/Cell;)Ljava/util/Iterator;
     422: astore        4
     424: aload         5
     426: aload         4
     428: invokeinterface #41,  1           // InterfaceMethod java/util/Iterator.next:()Ljava/lang/Object;
     433: invokestatic  #62                 // Method org/junit/Assert.assertEquals:(Ljava/lang/Object;Ljava/lang/Object;)V
     436: return

  public void testGetSplitPointEdgeCases() throws java.lang.Exception;
    Code:
       0: invokestatic  #17                 // Method createManager:()Lorg/apache/hadoop/hbase/regionserver/StripeStoreFileManager;
       3: astore_1
       4: aload_1
       5: invokevirtual #65                 // Method org/apache/hadoop/hbase/regionserver/StripeStoreFileManager.getSplitPoint:()Ljava/util/Optional;
       8: invokevirtual #66                 // Method java/util/Optional.isPresent:()Z
      11: invokestatic  #57                 // Method org/junit/Assert.assertFalse:(Z)V
      14: ldc2_w        #67                 // long 5l
      17: lconst_0
      18: invokestatic  #69                 // Method createFile:(JJ)Lorg/apache/hadoop/hbase/regionserver/MockHStoreFile;
      21: astore_2
      22: aload_2
      23: iconst_1
      24: newarray       byte
      26: dup
      27: iconst_0
      28: iconst_1
      29: bastore
      30: putfield      #70                 // Field org/apache/hadoop/hbase/regionserver/MockHStoreFile.splitPoint:[B
      33: aload_1
      34: iconst_1
      35: anewarray     #19                 // class org/apache/hadoop/hbase/regionserver/HStoreFile
      38: dup
      39: iconst_0
      40: aload_2
      41: aastore
      42: invokestatic  #20                 // Method al:([Lorg/apache/hadoop/hbase/regionserver/HStoreFile;)Ljava/util/ArrayList;
      45: invokevirtual #21                 // Method org/apache/hadoop/hbase/regionserver/StripeStoreFileManager.insertNewFiles:(Ljava/util/Collection;)V
      48: aload_1
      49: iconst_1
      50: anewarray     #19                 // class org/apache/hadoop/hbase/regionserver/HStoreFile
      53: dup
      54: iconst_0
      55: lconst_1
      56: lconst_0
      57: invokestatic  #69                 // Method createFile:(JJ)Lorg/apache/hadoop/hbase/regionserver/MockHStoreFile;
      60: aastore
      61: invokestatic  #20                 // Method al:([Lorg/apache/hadoop/hbase/regionserver/HStoreFile;)Ljava/util/ArrayList;
      64: invokevirtual #21                 // Method org/apache/hadoop/hbase/regionserver/StripeStoreFileManager.insertNewFiles:(Ljava/util/Collection;)V
      67: aload_2
      68: getfield      #70                 // Field org/apache/hadoop/hbase/regionserver/MockHStoreFile.splitPoint:[B
      71: aload_1
      72: invokevirtual #65                 // Method org/apache/hadoop/hbase/regionserver/StripeStoreFileManager.getSplitPoint:()Ljava/util/Optional;
      75: invokevirtual #71                 // Method java/util/Optional.get:()Ljava/lang/Object;
      78: checkcast     #72                 // class "[B"
      81: invokestatic  #73                 // Method org/junit/Assert.assertArrayEquals:([B[B)V
      84: aload_1
      85: iconst_0
      86: anewarray     #19                 // class org/apache/hadoop/hbase/regionserver/HStoreFile
      89: invokestatic  #20                 // Method al:([Lorg/apache/hadoop/hbase/regionserver/HStoreFile;)Ljava/util/ArrayList;
      92: iconst_1
      93: anewarray     #19                 // class org/apache/hadoop/hbase/regionserver/HStoreFile
      96: dup
      97: iconst_0
      98: ldc2_w        #53                 // long 2l
     101: lconst_0
     102: getstatic     #29                 // Field org/apache/hadoop/hbase/regionserver/StripeStoreFileManager.OPEN_KEY:[B
     105: getstatic     #29                 // Field org/apache/hadoop/hbase/regionserver/StripeStoreFileManager.OPEN_KEY:[B
     108: invokestatic  #50                 // Method createFile:(JJ[B[B)Lorg/apache/hadoop/hbase/regionserver/MockHStoreFile;
     111: aastore
     112: invokestatic  #20                 // Method al:([Lorg/apache/hadoop/hbase/regionserver/HStoreFile;)Ljava/util/ArrayList;
     115: invokevirtual #32                 // Method org/apache/hadoop/hbase/regionserver/StripeStoreFileManager.addCompactionResults:(Ljava/util/Collection;Ljava/util/Collection;)V
     118: aload_2
     119: getfield      #70                 // Field org/apache/hadoop/hbase/regionserver/MockHStoreFile.splitPoint:[B
     122: aload_1
     123: invokevirtual #65                 // Method org/apache/hadoop/hbase/regionserver/StripeStoreFileManager.getSplitPoint:()Ljava/util/Optional;
     126: invokevirtual #71                 // Method java/util/Optional.get:()Ljava/lang/Object;
     129: checkcast     #72                 // class "[B"
     132: invokestatic  #73                 // Method org/junit/Assert.assertArrayEquals:([B[B)V
     135: ldc2_w        #74                 // long 6l
     138: lconst_0
     139: getstatic     #29                 // Field org/apache/hadoop/hbase/regionserver/StripeStoreFileManager.OPEN_KEY:[B
     142: getstatic     #29                 // Field org/apache/hadoop/hbase/regionserver/StripeStoreFileManager.OPEN_KEY:[B
     145: invokestatic  #50                 // Method createFile:(JJ[B[B)Lorg/apache/hadoop/hbase/regionserver/MockHStoreFile;
     148: astore_3
     149: aload_3
     150: iconst_1
     151: newarray       byte
     153: dup
     154: iconst_0
     155: iconst_2
     156: bastore
     157: putfield      #70                 // Field org/apache/hadoop/hbase/regionserver/MockHStoreFile.splitPoint:[B
     160: aload_1
     161: iconst_0
     162: anewarray     #19                 // class org/apache/hadoop/hbase/regionserver/HStoreFile
     165: invokestatic  #20                 // Method al:([Lorg/apache/hadoop/hbase/regionserver/HStoreFile;)Ljava/util/ArrayList;
     168: iconst_1
     169: anewarray     #19                 // class org/apache/hadoop/hbase/regionserver/HStoreFile
     172: dup
     173: iconst_0
     174: aload_3
     175: aastore
     176: invokestatic  #20                 // Method al:([Lorg/apache/hadoop/hbase/regionserver/HStoreFile;)Ljava/util/ArrayList;
     179: invokevirtual #32                 // Method org/apache/hadoop/hbase/regionserver/StripeStoreFileManager.addCompactionResults:(Ljava/util/Collection;Ljava/util/Collection;)V
     182: aload_3
     183: getfield      #70                 // Field org/apache/hadoop/hbase/regionserver/MockHStoreFile.splitPoint:[B
     186: aload_1
     187: invokevirtual #65                 // Method org/apache/hadoop/hbase/regionserver/StripeStoreFileManager.getSplitPoint:()Ljava/util/Optional;
     190: invokevirtual #71                 // Method java/util/Optional.get:()Ljava/lang/Object;
     193: checkcast     #72                 // class "[B"
     196: invokestatic  #73                 // Method org/junit/Assert.assertArrayEquals:([B[B)V
     199: return

  public void testGetStripeBoundarySplits() throws java.lang.Exception;
    Code:
       0: aload_0
       1: iconst_5
       2: iconst_0
       3: fconst_0
       4: bipush        7
       6: newarray       int
       8: dup
       9: iconst_0
      10: iconst_2
      11: iastore
      12: dup
      13: iconst_1
      14: iconst_1
      15: iastore
      16: dup
      17: iconst_2
      18: iconst_1
      19: iastore
      20: dup
      21: iconst_3
      22: iconst_1
      23: iastore
      24: dup
      25: iconst_4
      26: iconst_1
      27: iastore
      28: dup
      29: iconst_5
      30: iconst_1
      31: iastore
      32: dup
      33: bipush        6
      35: bipush        10
      37: iastore
      38: invokespecial #76                 // Method verifySplitPointScenario:(IZF[I)V
      41: aload_0
      42: iconst_0
      43: iconst_0
      44: fconst_0
      45: iconst_5
      46: newarray       int
      48: dup
      49: iconst_0
      50: bipush        6
      52: iastore
      53: dup
      54: iconst_1
      55: iconst_3
      56: iastore
      57: dup
      58: iconst_2
      59: iconst_1
      60: iastore
      61: dup
      62: iconst_3
      63: iconst_1
      64: iastore
      65: dup
      66: iconst_4
      67: iconst_2
      68: iastore
      69: invokespecial #76                 // Method verifySplitPointScenario:(IZF[I)V
      72: aload_0
      73: iconst_2
      74: iconst_0
      75: fconst_0
      76: iconst_5
      77: newarray       int
      79: dup
      80: iconst_0
      81: iconst_1
      82: iastore
      83: dup
      84: iconst_1
      85: iconst_1
      86: iastore
      87: dup
      88: iconst_2
      89: iconst_1
      90: iastore
      91: dup
      92: iconst_3
      93: iconst_1
      94: iastore
      95: dup
      96: iconst_4
      97: iconst_2
      98: iastore
      99: invokespecial #76                 // Method verifySplitPointScenario:(IZF[I)V
     102: aload_0
     103: iconst_0
     104: iconst_0
     105: fconst_0
     106: iconst_2
     107: newarray       int
     109: dup
     110: iconst_0
     111: iconst_5
     112: iastore
     113: dup
     114: iconst_1
     115: iconst_4
     116: iastore
     117: invokespecial #76                 // Method verifySplitPointScenario:(IZF[I)V
     120: aload_0
     121: iconst_2
     122: iconst_0
     123: fconst_0
     124: iconst_5
     125: newarray       int
     127: dup
     128: iconst_0
     129: iconst_5
     130: iastore
     131: dup
     132: iconst_1
     133: iconst_2
     134: iastore
     135: dup
     136: iconst_2
     137: iconst_5
     138: iastore
     139: dup
     140: iconst_3
     141: iconst_5
     142: iastore
     143: dup
     144: iconst_4
     145: iconst_5
     146: iastore
     147: invokespecial #76                 // Method verifySplitPointScenario:(IZF[I)V
     150: return

  public void testGetUnbalancedSplits() throws java.lang.Exception;
    Code:
       0: aload_0
       1: iconst_0
       2: iconst_0
       3: ldc           #77                 // float 2.1f
       5: iconst_3
       6: newarray       int
       8: dup
       9: iconst_0
      10: iconst_4
      11: iastore
      12: dup
      13: iconst_1
      14: iconst_4
      15: iastore
      16: dup
      17: iconst_2
      18: iconst_4
      19: iastore
      20: invokespecial #76                 // Method verifySplitPointScenario:(IZF[I)V
      23: aload_0
      24: iconst_1
      25: iconst_1
      26: ldc           #78                 // float 1.5f
      28: iconst_3
      29: newarray       int
      31: dup
      32: iconst_0
      33: iconst_4
      34: iastore
      35: dup
      36: iconst_1
      37: iconst_4
      38: iastore
      39: dup
      40: iconst_2
      41: iconst_4
      42: iastore
      43: invokespecial #76                 // Method verifySplitPointScenario:(IZF[I)V
      46: aload_0
      47: iconst_1
      48: iconst_0
      49: ldc           #79                 // float 1.1f
      51: bipush        6
      53: newarray       int
      55: dup
      56: iconst_0
      57: iconst_3
      58: iastore
      59: dup
      60: iconst_1
      61: iconst_4
      62: iastore
      63: dup
      64: iconst_2
      65: iconst_1
      66: iastore
      67: dup
      68: iconst_3
      69: iconst_1
      70: iastore
      71: dup
      72: iconst_4
      73: iconst_2
      74: iastore
      75: dup
      76: iconst_5
      77: iconst_2
      78: iastore
      79: invokespecial #76                 // Method verifySplitPointScenario:(IZF[I)V
      82: aload_0
      83: iconst_1
      84: iconst_0
      85: ldc           #79                 // float 1.1f
      87: bipush        6
      89: newarray       int
      91: dup
      92: iconst_0
      93: iconst_3
      94: iastore
      95: dup
      96: iconst_1
      97: bipush        6
      99: iastore
     100: dup
     101: iconst_2
     102: iconst_1
     103: iastore
     104: dup
     105: iconst_3
     106: iconst_1
     107: iastore
     108: dup
     109: iconst_4
     110: iconst_2
     111: iastore
     112: dup
     113: iconst_5
     114: iconst_2
     115: iastore
     116: invokespecial #76                 // Method verifySplitPointScenario:(IZF[I)V
     119: aload_0
     120: iconst_1
     121: iconst_1
     122: ldc           #79                 // float 1.1f
     124: bipush        6
     126: newarray       int
     128: dup
     129: iconst_0
     130: iconst_3
     131: iastore
     132: dup
     133: iconst_1
     134: bipush        8
     136: iastore
     137: dup
     138: iconst_2
     139: iconst_1
     140: iastore
     141: dup
     142: iconst_3
     143: iconst_1
     144: iastore
     145: dup
     146: iconst_4
     147: iconst_2
     148: iastore
     149: dup
     150: iconst_5
     151: iconst_2
     152: iastore
     153: invokespecial #76                 // Method verifySplitPointScenario:(IZF[I)V
     156: aload_0
     157: iconst_3
     158: iconst_0
     159: ldc           #79                 // float 1.1f
     161: bipush        6
     163: newarray       int
     165: dup
     166: iconst_0
     167: iconst_2
     168: iastore
     169: dup
     170: iconst_1
     171: iconst_2
     172: iastore
     173: dup
     174: iconst_2
     175: iconst_1
     176: iastore
     177: dup
     178: iconst_3
     179: iconst_1
     180: iastore
     181: dup
     182: iconst_4
     183: iconst_4
     184: iastore
     185: dup
     186: iconst_5
     187: iconst_3
     188: iastore
     189: invokespecial #76                 // Method verifySplitPointScenario:(IZF[I)V
     192: aload_0
     193: iconst_4
     194: iconst_1
     195: ldc           #79                 // float 1.1f
     197: bipush        6
     199: newarray       int
     201: dup
     202: iconst_0
     203: iconst_2
     204: iastore
     205: dup
     206: iconst_1
     207: iconst_2
     208: iastore
     209: dup
     210: iconst_2
     211: iconst_1
     212: iastore
     213: dup
     214: iconst_3
     215: iconst_1
     216: iastore
     217: dup
     218: iconst_4
     219: bipush        8
     221: iastore
     222: dup
     223: iconst_5
     224: iconst_3
     225: iastore
     226: invokespecial #76                 // Method verifySplitPointScenario:(IZF[I)V
     229: aload_0
     230: iconst_0
     231: iconst_1
     232: ldc           #78                 // float 1.5f
     234: iconst_2
     235: newarray       int
     237: dup
     238: iconst_0
     239: bipush        10
     241: iastore
     242: dup
     243: iconst_1
     244: iconst_4
     245: iastore
     246: invokespecial #76                 // Method verifySplitPointScenario:(IZF[I)V
     249: aload_0
     250: iconst_0
     251: iconst_0
     252: ldc           #80                 // float 1.4f
     254: iconst_2
     255: newarray       int
     257: dup
     258: iconst_0
     259: bipush        6
     261: iastore
     262: dup
     263: iconst_1
     264: iconst_4
     265: iastore
     266: invokespecial #76                 // Method verifySplitPointScenario:(IZF[I)V
     269: aload_0
     270: iconst_1
     271: iconst_1
     272: ldc           #78                 // float 1.5f
     274: iconst_2
     275: newarray       int
     277: dup
     278: iconst_0
     279: iconst_4
     280: iastore
     281: dup
     282: iconst_1
     283: bipush        10
     285: iastore
     286: invokespecial #76                 // Method verifySplitPointScenario:(IZF[I)V
     289: aload_0
     290: iconst_0
     291: iconst_0
     292: ldc           #80                 // float 1.4f
     294: iconst_2
     295: newarray       int
     297: dup
     298: iconst_0
     299: iconst_4
     300: iastore
     301: dup
     302: iconst_1
     303: bipush        6
     305: iastore
     306: invokespecial #76                 // Method verifySplitPointScenario:(IZF[I)V
     309: return

  public void testGetFilesForGetAndScan() throws java.lang.Exception;
    Code:
       0: invokestatic  #17                 // Method createManager:()Lorg/apache/hadoop/hbase/regionserver/StripeStoreFileManager;
       3: astore_1
       4: aload_0
       5: aload_1
       6: aconst_null
       7: aconst_null
       8: iconst_0
       9: anewarray     #19                 // class org/apache/hadoop/hbase/regionserver/HStoreFile
      12: invokespecial #89                 // Method verifyGetAndScanScenario:(Lorg/apache/hadoop/hbase/regionserver/StripeStoreFileManager;[B[B[Lorg/apache/hadoop/hbase/regionserver/HStoreFile;)V
      15: aload_0
      16: aload_1
      17: getstatic     #30                 // Field KEY_B:[B
      20: getstatic     #33                 // Field KEY_C:[B
      23: iconst_0
      24: anewarray     #19                 // class org/apache/hadoop/hbase/regionserver/HStoreFile
      27: invokespecial #89                 // Method verifyGetAndScanScenario:(Lorg/apache/hadoop/hbase/regionserver/StripeStoreFileManager;[B[B[Lorg/apache/hadoop/hbase/regionserver/HStoreFile;)V
      30: invokestatic  #18                 // Method createFile:()Lorg/apache/hadoop/hbase/regionserver/MockHStoreFile;
      33: astore_2
      34: aload_1
      35: iconst_1
      36: anewarray     #19                 // class org/apache/hadoop/hbase/regionserver/HStoreFile
      39: dup
      40: iconst_0
      41: aload_2
      42: aastore
      43: invokestatic  #20                 // Method al:([Lorg/apache/hadoop/hbase/regionserver/HStoreFile;)Ljava/util/ArrayList;
      46: invokevirtual #21                 // Method org/apache/hadoop/hbase/regionserver/StripeStoreFileManager.insertNewFiles:(Ljava/util/Collection;)V
      49: aload_0
      50: aload_1
      51: aconst_null
      52: aconst_null
      53: iconst_1
      54: anewarray     #19                 // class org/apache/hadoop/hbase/regionserver/HStoreFile
      57: dup
      58: iconst_0
      59: aload_2
      60: aastore
      61: invokespecial #89                 // Method verifyGetAndScanScenario:(Lorg/apache/hadoop/hbase/regionserver/StripeStoreFileManager;[B[B[Lorg/apache/hadoop/hbase/regionserver/HStoreFile;)V
      64: aload_0
      65: aload_1
      66: aconst_null
      67: getstatic     #33                 // Field KEY_C:[B
      70: iconst_1
      71: anewarray     #19                 // class org/apache/hadoop/hbase/regionserver/HStoreFile
      74: dup
      75: iconst_0
      76: aload_2
      77: aastore
      78: invokespecial #89                 // Method verifyGetAndScanScenario:(Lorg/apache/hadoop/hbase/regionserver/StripeStoreFileManager;[B[B[Lorg/apache/hadoop/hbase/regionserver/HStoreFile;)V
      81: aload_0
      82: aload_1
      83: getstatic     #30                 // Field KEY_B:[B
      86: aconst_null
      87: iconst_1
      88: anewarray     #19                 // class org/apache/hadoop/hbase/regionserver/HStoreFile
      91: dup
      92: iconst_0
      93: aload_2
      94: aastore
      95: invokespecial #89                 // Method verifyGetAndScanScenario:(Lorg/apache/hadoop/hbase/regionserver/StripeStoreFileManager;[B[B[Lorg/apache/hadoop/hbase/regionserver/HStoreFile;)V
      98: aload_0
      99: aload_1
     100: getstatic     #30                 // Field KEY_B:[B
     103: getstatic     #33                 // Field KEY_C:[B
     106: iconst_1
     107: anewarray     #19                 // class org/apache/hadoop/hbase/regionserver/HStoreFile
     110: dup
     111: iconst_0
     112: aload_2
     113: aastore
     114: invokespecial #89                 // Method verifyGetAndScanScenario:(Lorg/apache/hadoop/hbase/regionserver/StripeStoreFileManager;[B[B[Lorg/apache/hadoop/hbase/regionserver/HStoreFile;)V
     117: getstatic     #29                 // Field org/apache/hadoop/hbase/regionserver/StripeStoreFileManager.OPEN_KEY:[B
     120: getstatic     #24                 // Field KEY_A:[B
     123: invokestatic  #31                 // Method createFile:([B[B)Lorg/apache/hadoop/hbase/regionserver/MockHStoreFile;
     126: astore_3
     127: getstatic     #24                 // Field KEY_A:[B
     130: getstatic     #30                 // Field KEY_B:[B
     133: invokestatic  #31                 // Method createFile:([B[B)Lorg/apache/hadoop/hbase/regionserver/MockHStoreFile;
     136: astore        4
     138: getstatic     #30                 // Field KEY_B:[B
     141: getstatic     #33                 // Field KEY_C:[B
     144: invokestatic  #31                 // Method createFile:([B[B)Lorg/apache/hadoop/hbase/regionserver/MockHStoreFile;
     147: astore        5
     149: getstatic     #33                 // Field KEY_C:[B
     152: getstatic     #90                 // Field KEY_D:[B
     155: invokestatic  #31                 // Method createFile:([B[B)Lorg/apache/hadoop/hbase/regionserver/MockHStoreFile;
     158: astore        6
     160: getstatic     #90                 // Field KEY_D:[B
     163: getstatic     #29                 // Field org/apache/hadoop/hbase/regionserver/StripeStoreFileManager.OPEN_KEY:[B
     166: invokestatic  #31                 // Method createFile:([B[B)Lorg/apache/hadoop/hbase/regionserver/MockHStoreFile;
     169: astore        7
     171: aload_1
     172: iconst_0
     173: anewarray     #19                 // class org/apache/hadoop/hbase/regionserver/HStoreFile
     176: invokestatic  #20                 // Method al:([Lorg/apache/hadoop/hbase/regionserver/HStoreFile;)Ljava/util/ArrayList;
     179: iconst_5
     180: anewarray     #19                 // class org/apache/hadoop/hbase/regionserver/HStoreFile
     183: dup
     184: iconst_0
     185: aload_3
     186: aastore
     187: dup
     188: iconst_1
     189: aload         4
     191: aastore
     192: dup
     193: iconst_2
     194: aload         5
     196: aastore
     197: dup
     198: iconst_3
     199: aload         6
     201: aastore
     202: dup
     203: iconst_4
     204: aload         7
     206: aastore
     207: invokestatic  #20                 // Method al:([Lorg/apache/hadoop/hbase/regionserver/HStoreFile;)Ljava/util/ArrayList;
     210: invokevirtual #32                 // Method org/apache/hadoop/hbase/regionserver/StripeStoreFileManager.addCompactionResults:(Ljava/util/Collection;Ljava/util/Collection;)V
     213: aload_0
     214: aload_1
     215: aconst_null
     216: aconst_null
     217: bipush        6
     219: anewarray     #19                 // class org/apache/hadoop/hbase/regionserver/HStoreFile
     222: dup
     223: iconst_0
     224: aload_2
     225: aastore
     226: dup
     227: iconst_1
     228: aload_3
     229: aastore
     230: dup
     231: iconst_2
     232: aload         4
     234: aastore
     235: dup
     236: iconst_3
     237: aload         5
     239: aastore
     240: dup
     241: iconst_4
     242: aload         6
     244: aastore
     245: dup
     246: iconst_5
     247: aload         7
     249: aastore
     250: invokespecial #89                 // Method verifyGetAndScanScenario:(Lorg/apache/hadoop/hbase/regionserver/StripeStoreFileManager;[B[B[Lorg/apache/hadoop/hbase/regionserver/HStoreFile;)V
     253: aload_0
     254: aload_1
     255: getstatic     #24                 // Field KEY_A:[B
     258: invokestatic  #91                 // Method keyAfter:([B)[B
     261: aconst_null
     262: iconst_5
     263: anewarray     #19                 // class org/apache/hadoop/hbase/regionserver/HStoreFile
     266: dup
     267: iconst_0
     268: aload_2
     269: aastore
     270: dup
     271: iconst_1
     272: aload         4
     274: aastore
     275: dup
     276: iconst_2
     277: aload         5
     279: aastore
     280: dup
     281: iconst_3
     282: aload         6
     284: aastore
     285: dup
     286: iconst_4
     287: aload         7
     289: aastore
     290: invokespecial #89                 // Method verifyGetAndScanScenario:(Lorg/apache/hadoop/hbase/regionserver/StripeStoreFileManager;[B[B[Lorg/apache/hadoop/hbase/regionserver/HStoreFile;)V
     293: aload_0
     294: aload_1
     295: aconst_null
     296: getstatic     #33                 // Field KEY_C:[B
     299: invokestatic  #91                 // Method keyAfter:([B)[B
     302: iconst_5
     303: anewarray     #19                 // class org/apache/hadoop/hbase/regionserver/HStoreFile
     306: dup
     307: iconst_0
     308: aload_2
     309: aastore
     310: dup
     311: iconst_1
     312: aload_3
     313: aastore
     314: dup
     315: iconst_2
     316: aload         4
     318: aastore
     319: dup
     320: iconst_3
     321: aload         5
     323: aastore
     324: dup
     325: iconst_4
     326: aload         6
     328: aastore
     329: invokespecial #89                 // Method verifyGetAndScanScenario:(Lorg/apache/hadoop/hbase/regionserver/StripeStoreFileManager;[B[B[Lorg/apache/hadoop/hbase/regionserver/HStoreFile;)V
     332: aload_0
     333: aload_1
     334: getstatic     #30                 // Field KEY_B:[B
     337: aconst_null
     338: iconst_4
     339: anewarray     #19                 // class org/apache/hadoop/hbase/regionserver/HStoreFile
     342: dup
     343: iconst_0
     344: aload_2
     345: aastore
     346: dup
     347: iconst_1
     348: aload         5
     350: aastore
     351: dup
     352: iconst_2
     353: aload         6
     355: aastore
     356: dup
     357: iconst_3
     358: aload         7
     360: aastore
     361: invokespecial #89                 // Method verifyGetAndScanScenario:(Lorg/apache/hadoop/hbase/regionserver/StripeStoreFileManager;[B[B[Lorg/apache/hadoop/hbase/regionserver/HStoreFile;)V
     364: aload_0
     365: aload_1
     366: aconst_null
     367: getstatic     #33                 // Field KEY_C:[B
     370: iconst_5
     371: anewarray     #19                 // class org/apache/hadoop/hbase/regionserver/HStoreFile
     374: dup
     375: iconst_0
     376: aload_2
     377: aastore
     378: dup
     379: iconst_1
     380: aload_3
     381: aastore
     382: dup
     383: iconst_2
     384: aload         4
     386: aastore
     387: dup
     388: iconst_3
     389: aload         5
     391: aastore
     392: dup
     393: iconst_4
     394: aload         6
     396: aastore
     397: invokespecial #89                 // Method verifyGetAndScanScenario:(Lorg/apache/hadoop/hbase/regionserver/StripeStoreFileManager;[B[B[Lorg/apache/hadoop/hbase/regionserver/HStoreFile;)V
     400: aload_0
     401: aload_1
     402: getstatic     #30                 // Field KEY_B:[B
     405: getstatic     #30                 // Field KEY_B:[B
     408: invokestatic  #91                 // Method keyAfter:([B)[B
     411: iconst_2
     412: anewarray     #19                 // class org/apache/hadoop/hbase/regionserver/HStoreFile
     415: dup
     416: iconst_0
     417: aload_2
     418: aastore
     419: dup
     420: iconst_1
     421: aload         5
     423: aastore
     424: invokespecial #89                 // Method verifyGetAndScanScenario:(Lorg/apache/hadoop/hbase/regionserver/StripeStoreFileManager;[B[B[Lorg/apache/hadoop/hbase/regionserver/HStoreFile;)V
     427: aload_0
     428: aload_1
     429: getstatic     #24                 // Field KEY_A:[B
     432: invokestatic  #91                 // Method keyAfter:([B)[B
     435: getstatic     #30                 // Field KEY_B:[B
     438: iconst_3
     439: anewarray     #19                 // class org/apache/hadoop/hbase/regionserver/HStoreFile
     442: dup
     443: iconst_0
     444: aload_2
     445: aastore
     446: dup
     447: iconst_1
     448: aload         4
     450: aastore
     451: dup
     452: iconst_2
     453: aload         5
     455: aastore
     456: invokespecial #89                 // Method verifyGetAndScanScenario:(Lorg/apache/hadoop/hbase/regionserver/StripeStoreFileManager;[B[B[Lorg/apache/hadoop/hbase/regionserver/HStoreFile;)V
     459: aload_0
     460: aload_1
     461: getstatic     #90                 // Field KEY_D:[B
     464: getstatic     #90                 // Field KEY_D:[B
     467: iconst_2
     468: anewarray     #19                 // class org/apache/hadoop/hbase/regionserver/HStoreFile
     471: dup
     472: iconst_0
     473: aload_2
     474: aastore
     475: dup
     476: iconst_1
     477: aload         7
     479: aastore
     480: invokespecial #89                 // Method verifyGetAndScanScenario:(Lorg/apache/hadoop/hbase/regionserver/StripeStoreFileManager;[B[B[Lorg/apache/hadoop/hbase/regionserver/HStoreFile;)V
     483: aload_0
     484: aload_1
     485: getstatic     #30                 // Field KEY_B:[B
     488: invokestatic  #91                 // Method keyAfter:([B)[B
     491: getstatic     #33                 // Field KEY_C:[B
     494: invokestatic  #91                 // Method keyAfter:([B)[B
     497: iconst_3
     498: anewarray     #19                 // class org/apache/hadoop/hbase/regionserver/HStoreFile
     501: dup
     502: iconst_0
     503: aload_2
     504: aastore
     505: dup
     506: iconst_1
     507: aload         5
     509: aastore
     510: dup
     511: iconst_2
     512: aload         6
     514: aastore
     515: invokespecial #89                 // Method verifyGetAndScanScenario:(Lorg/apache/hadoop/hbase/regionserver/StripeStoreFileManager;[B[B[Lorg/apache/hadoop/hbase/regionserver/HStoreFile;)V
     518: return

  public void testLoadFilesWithRecoverableBadFiles() throws java.lang.Exception;
    Code:
       0: iconst_4
       1: anewarray     #19                 // class org/apache/hadoop/hbase/regionserver/HStoreFile
       4: dup
       5: iconst_0
       6: getstatic     #29                 // Field org/apache/hadoop/hbase/regionserver/StripeStoreFileManager.OPEN_KEY:[B
       9: getstatic     #30                 // Field KEY_B:[B
      12: invokestatic  #31                 // Method createFile:([B[B)Lorg/apache/hadoop/hbase/regionserver/MockHStoreFile;
      15: aastore
      16: dup
      17: iconst_1
      18: getstatic     #30                 // Field KEY_B:[B
      21: getstatic     #33                 // Field KEY_C:[B
      24: invokestatic  #31                 // Method createFile:([B[B)Lorg/apache/hadoop/hbase/regionserver/MockHStoreFile;
      27: aastore
      28: dup
      29: iconst_2
      30: getstatic     #33                 // Field KEY_C:[B
      33: getstatic     #29                 // Field org/apache/hadoop/hbase/regionserver/StripeStoreFileManager.OPEN_KEY:[B
      36: invokestatic  #31                 // Method createFile:([B[B)Lorg/apache/hadoop/hbase/regionserver/MockHStoreFile;
      39: aastore
      40: dup
      41: iconst_3
      42: getstatic     #33                 // Field KEY_C:[B
      45: getstatic     #29                 // Field org/apache/hadoop/hbase/regionserver/StripeStoreFileManager.OPEN_KEY:[B
      48: invokestatic  #31                 // Method createFile:([B[B)Lorg/apache/hadoop/hbase/regionserver/MockHStoreFile;
      51: aastore
      52: invokestatic  #20                 // Method al:([Lorg/apache/hadoop/hbase/regionserver/HStoreFile;)Ljava/util/ArrayList;
      55: astore_1
      56: bipush        7
      58: anewarray     #19                 // class org/apache/hadoop/hbase/regionserver/HStoreFile
      61: dup
      62: iconst_0
      63: invokestatic  #18                 // Method createFile:()Lorg/apache/hadoop/hbase/regionserver/MockHStoreFile;
      66: aastore
      67: dup
      68: iconst_1
      69: aconst_null
      70: getstatic     #24                 // Field KEY_A:[B
      73: invokestatic  #31                 // Method createFile:([B[B)Lorg/apache/hadoop/hbase/regionserver/MockHStoreFile;
      76: aastore
      77: dup
      78: iconst_2
      79: getstatic     #90                 // Field KEY_D:[B
      82: aconst_null
      83: invokestatic  #31                 // Method createFile:([B[B)Lorg/apache/hadoop/hbase/regionserver/MockHStoreFile;
      86: aastore
      87: dup
      88: iconst_3
      89: getstatic     #90                 // Field KEY_D:[B
      92: getstatic     #24                 // Field KEY_A:[B
      95: invokestatic  #31                 // Method createFile:([B[B)Lorg/apache/hadoop/hbase/regionserver/MockHStoreFile;
      98: aastore
      99: dup
     100: iconst_4
     101: getstatic     #24                 // Field KEY_A:[B
     104: invokestatic  #91                 // Method keyAfter:([B)[B
     107: getstatic     #33                 // Field KEY_C:[B
     110: invokestatic  #31                 // Method createFile:([B[B)Lorg/apache/hadoop/hbase/regionserver/MockHStoreFile;
     113: aastore
     114: dup
     115: iconst_5
     116: getstatic     #29                 // Field org/apache/hadoop/hbase/regionserver/StripeStoreFileManager.OPEN_KEY:[B
     119: getstatic     #90                 // Field KEY_D:[B
     122: invokestatic  #31                 // Method createFile:([B[B)Lorg/apache/hadoop/hbase/regionserver/MockHStoreFile;
     125: aastore
     126: dup
     127: bipush        6
     129: getstatic     #90                 // Field KEY_D:[B
     132: getstatic     #90                 // Field KEY_D:[B
     135: invokestatic  #91                 // Method keyAfter:([B)[B
     138: invokestatic  #31                 // Method createFile:([B[B)Lorg/apache/hadoop/hbase/regionserver/MockHStoreFile;
     141: aastore
     142: invokestatic  #20                 // Method al:([Lorg/apache/hadoop/hbase/regionserver/HStoreFile;)Ljava/util/ArrayList;
     145: astore_2
     146: iconst_2
     147: anewarray     #38                 // class java/util/ArrayList
     150: dup
     151: iconst_0
     152: aload_1
     153: aastore
     154: dup
     155: iconst_1
     156: aload_2
     157: aastore
     158: invokestatic  #93                 // Method flattenLists:([Ljava/util/ArrayList;)Ljava/util/ArrayList;
     161: astore_3
     162: aload_3
     163: invokestatic  #94                 // Method java/util/Collections.shuffle:(Ljava/util/List;)V
     166: aload_3
     167: invokestatic  #95                 // Method createManager:(Ljava/util/ArrayList;)Lorg/apache/hadoop/hbase/regionserver/StripeStoreFileManager;
     170: astore        4
     172: aload         4
     174: invokevirtual #96                 // Method org/apache/hadoop/hbase/regionserver/StripeStoreFileManager.getLevel0Files:()Ljava/util/List;
     177: astore        5
     179: aload_2
     180: invokevirtual #55                 // Method java/util/ArrayList.size:()I
     183: i2l
     184: aload         5
     186: invokeinterface #97,  1           // InterfaceMethod java/util/List.size:()I
     191: i2l
     192: invokestatic  #23                 // Method org/junit/Assert.assertEquals:(JJ)V
     195: aload_2
     196: invokevirtual #98                 // Method java/util/ArrayList.iterator:()Ljava/util/Iterator;
     199: astore        6
     201: aload         6
     203: invokeinterface #40,  1           // InterfaceMethod java/util/Iterator.hasNext:()Z
     208: ifeq          238
     211: aload         6
     213: invokeinterface #41,  1           // InterfaceMethod java/util/Iterator.next:()Ljava/lang/Object;
     218: checkcast     #19                 // class org/apache/hadoop/hbase/regionserver/HStoreFile
     221: astore        7
     223: aload         5
     225: aload         7
     227: invokeinterface #99,  2           // InterfaceMethod java/util/List.contains:(Ljava/lang/Object;)Z
     232: invokestatic  #28                 // Method org/junit/Assert.assertTrue:(Z)V
     235: goto          201
     238: aload_0
     239: aload         4
     241: aload_3
     242: invokespecial #100                // Method verifyAllFiles:(Lorg/apache/hadoop/hbase/regionserver/StripeStoreFileManager;Ljava/util/Collection;)V
     245: return

  public void testLoadFilesWithBadStripe() throws java.lang.Exception;
    Code:
       0: iconst_4
       1: anewarray     #19                 // class org/apache/hadoop/hbase/regionserver/HStoreFile
       4: dup
       5: iconst_0
       6: getstatic     #29                 // Field org/apache/hadoop/hbase/regionserver/StripeStoreFileManager.OPEN_KEY:[B
       9: getstatic     #30                 // Field KEY_B:[B
      12: invokestatic  #31                 // Method createFile:([B[B)Lorg/apache/hadoop/hbase/regionserver/MockHStoreFile;
      15: aastore
      16: dup
      17: iconst_1
      18: getstatic     #30                 // Field KEY_B:[B
      21: getstatic     #33                 // Field KEY_C:[B
      24: invokestatic  #31                 // Method createFile:([B[B)Lorg/apache/hadoop/hbase/regionserver/MockHStoreFile;
      27: aastore
      28: dup
      29: iconst_2
      30: getstatic     #33                 // Field KEY_C:[B
      33: getstatic     #29                 // Field org/apache/hadoop/hbase/regionserver/StripeStoreFileManager.OPEN_KEY:[B
      36: invokestatic  #31                 // Method createFile:([B[B)Lorg/apache/hadoop/hbase/regionserver/MockHStoreFile;
      39: aastore
      40: dup
      41: iconst_3
      42: getstatic     #30                 // Field KEY_B:[B
      45: getstatic     #30                 // Field KEY_B:[B
      48: invokestatic  #91                 // Method keyAfter:([B)[B
      51: invokestatic  #31                 // Method createFile:([B[B)Lorg/apache/hadoop/hbase/regionserver/MockHStoreFile;
      54: aastore
      55: invokestatic  #20                 // Method al:([Lorg/apache/hadoop/hbase/regionserver/HStoreFile;)Ljava/util/ArrayList;
      58: astore_1
      59: aload_1
      60: invokestatic  #94                 // Method java/util/Collections.shuffle:(Ljava/util/List;)V
      63: aload_1
      64: invokestatic  #95                 // Method createManager:(Ljava/util/ArrayList;)Lorg/apache/hadoop/hbase/regionserver/StripeStoreFileManager;
      67: astore_2
      68: aload_1
      69: invokevirtual #55                 // Method java/util/ArrayList.size:()I
      72: i2l
      73: aload_2
      74: invokevirtual #96                 // Method org/apache/hadoop/hbase/regionserver/StripeStoreFileManager.getLevel0Files:()Ljava/util/List;
      77: invokeinterface #97,  1           // InterfaceMethod java/util/List.size:()I
      82: i2l
      83: invokestatic  #23                 // Method org/junit/Assert.assertEquals:(JJ)V
      86: return

  public void testLoadFilesWithGaps() throws java.lang.Exception;
    Code:
       0: iconst_2
       1: anewarray     #19                 // class org/apache/hadoop/hbase/regionserver/HStoreFile
       4: dup
       5: iconst_0
       6: getstatic     #29                 // Field org/apache/hadoop/hbase/regionserver/StripeStoreFileManager.OPEN_KEY:[B
       9: getstatic     #30                 // Field KEY_B:[B
      12: invokestatic  #31                 // Method createFile:([B[B)Lorg/apache/hadoop/hbase/regionserver/MockHStoreFile;
      15: aastore
      16: dup
      17: iconst_1
      18: getstatic     #33                 // Field KEY_C:[B
      21: getstatic     #29                 // Field org/apache/hadoop/hbase/regionserver/StripeStoreFileManager.OPEN_KEY:[B
      24: invokestatic  #31                 // Method createFile:([B[B)Lorg/apache/hadoop/hbase/regionserver/MockHStoreFile;
      27: aastore
      28: invokestatic  #20                 // Method al:([Lorg/apache/hadoop/hbase/regionserver/HStoreFile;)Ljava/util/ArrayList;
      31: invokestatic  #95                 // Method createManager:(Ljava/util/ArrayList;)Lorg/apache/hadoop/hbase/regionserver/StripeStoreFileManager;
      34: astore_1
      35: ldc2_w        #53                 // long 2l
      38: aload_1
      39: invokevirtual #96                 // Method org/apache/hadoop/hbase/regionserver/StripeStoreFileManager.getLevel0Files:()Ljava/util/List;
      42: invokeinterface #97,  1           // InterfaceMethod java/util/List.size:()I
      47: i2l
      48: invokestatic  #23                 // Method org/junit/Assert.assertEquals:(JJ)V
      51: iconst_1
      52: anewarray     #19                 // class org/apache/hadoop/hbase/regionserver/HStoreFile
      55: dup
      56: iconst_0
      57: getstatic     #29                 // Field org/apache/hadoop/hbase/regionserver/StripeStoreFileManager.OPEN_KEY:[B
      60: getstatic     #29                 // Field org/apache/hadoop/hbase/regionserver/StripeStoreFileManager.OPEN_KEY:[B
      63: invokestatic  #31                 // Method createFile:([B[B)Lorg/apache/hadoop/hbase/regionserver/MockHStoreFile;
      66: aastore
      67: invokestatic  #20                 // Method al:([Lorg/apache/hadoop/hbase/regionserver/HStoreFile;)Ljava/util/ArrayList;
      70: invokestatic  #95                 // Method createManager:(Ljava/util/ArrayList;)Lorg/apache/hadoop/hbase/regionserver/StripeStoreFileManager;
      73: astore_1
      74: lconst_0
      75: aload_1
      76: invokevirtual #96                 // Method org/apache/hadoop/hbase/regionserver/StripeStoreFileManager.getLevel0Files:()Ljava/util/List;
      79: invokeinterface #97,  1           // InterfaceMethod java/util/List.size:()I
      84: i2l
      85: invokestatic  #23                 // Method org/junit/Assert.assertEquals:(JJ)V
      88: lconst_1
      89: aload_1
      90: invokevirtual #22                 // Method org/apache/hadoop/hbase/regionserver/StripeStoreFileManager.getStorefileCount:()I
      93: i2l
      94: invokestatic  #23                 // Method org/junit/Assert.assertEquals:(JJ)V
      97: return

  public void testLoadFilesAfterSplit() throws java.lang.Exception;
    Code:
       0: getstatic     #30                 // Field KEY_B:[B
       3: getstatic     #33                 // Field KEY_C:[B
       6: invokestatic  #31                 // Method createFile:([B[B)Lorg/apache/hadoop/hbase/regionserver/MockHStoreFile;
       9: astore_1
      10: iconst_2
      11: anewarray     #19                 // class org/apache/hadoop/hbase/regionserver/HStoreFile
      14: dup
      15: iconst_0
      16: getstatic     #29                 // Field org/apache/hadoop/hbase/regionserver/StripeStoreFileManager.OPEN_KEY:[B
      19: getstatic     #30                 // Field KEY_B:[B
      22: invokestatic  #31                 // Method createFile:([B[B)Lorg/apache/hadoop/hbase/regionserver/MockHStoreFile;
      25: aastore
      26: dup
      27: iconst_1
      28: aload_1
      29: aastore
      30: invokestatic  #20                 // Method al:([Lorg/apache/hadoop/hbase/regionserver/HStoreFile;)Ljava/util/ArrayList;
      33: invokestatic  #95                 // Method createManager:(Ljava/util/ArrayList;)Lorg/apache/hadoop/hbase/regionserver/StripeStoreFileManager;
      36: astore_2
      37: lconst_0
      38: aload_2
      39: invokevirtual #96                 // Method org/apache/hadoop/hbase/regionserver/StripeStoreFileManager.getLevel0Files:()Ljava/util/List;
      42: invokeinterface #97,  1           // InterfaceMethod java/util/List.size:()I
      47: i2l
      48: invokestatic  #23                 // Method org/junit/Assert.assertEquals:(JJ)V
      51: aload_0
      52: aload_2
      53: iconst_1
      54: anewarray     #19                 // class org/apache/hadoop/hbase/regionserver/HStoreFile
      57: dup
      58: iconst_0
      59: aload_1
      60: aastore
      61: invokestatic  #20                 // Method al:([Lorg/apache/hadoop/hbase/regionserver/HStoreFile;)Ljava/util/ArrayList;
      64: iconst_1
      65: anewarray     #19                 // class org/apache/hadoop/hbase/regionserver/HStoreFile
      68: dup
      69: iconst_0
      70: getstatic     #30                 // Field KEY_B:[B
      73: getstatic     #33                 // Field KEY_C:[B
      76: invokestatic  #31                 // Method createFile:([B[B)Lorg/apache/hadoop/hbase/regionserver/MockHStoreFile;
      79: aastore
      80: invokestatic  #20                 // Method al:([Lorg/apache/hadoop/hbase/regionserver/HStoreFile;)Ljava/util/ArrayList;
      83: invokespecial #101                // Method verifyInvalidCompactionScenario:(Lorg/apache/hadoop/hbase/regionserver/StripeStoreFileManager;Ljava/util/ArrayList;Ljava/util/ArrayList;)V
      86: aload_2
      87: iconst_1
      88: anewarray     #19                 // class org/apache/hadoop/hbase/regionserver/HStoreFile
      91: dup
      92: iconst_0
      93: aload_1
      94: aastore
      95: invokestatic  #20                 // Method al:([Lorg/apache/hadoop/hbase/regionserver/HStoreFile;)Ljava/util/ArrayList;
      98: iconst_1
      99: anewarray     #19                 // class org/apache/hadoop/hbase/regionserver/HStoreFile
     102: dup
     103: iconst_0
     104: getstatic     #30                 // Field KEY_B:[B
     107: getstatic     #29                 // Field org/apache/hadoop/hbase/regionserver/StripeStoreFileManager.OPEN_KEY:[B
     110: invokestatic  #31                 // Method createFile:([B[B)Lorg/apache/hadoop/hbase/regionserver/MockHStoreFile;
     113: aastore
     114: invokestatic  #20                 // Method al:([Lorg/apache/hadoop/hbase/regionserver/HStoreFile;)Ljava/util/ArrayList;
     117: invokevirtual #32                 // Method org/apache/hadoop/hbase/regionserver/StripeStoreFileManager.addCompactionResults:(Ljava/util/Collection;Ljava/util/Collection;)V
     120: aload_2
     121: iconst_1
     122: anewarray     #19                 // class org/apache/hadoop/hbase/regionserver/HStoreFile
     125: dup
     126: iconst_0
     127: aload_1
     128: aastore
     129: invokestatic  #20                 // Method al:([Lorg/apache/hadoop/hbase/regionserver/HStoreFile;)Ljava/util/ArrayList;
     132: invokevirtual #51                 // Method org/apache/hadoop/hbase/regionserver/StripeStoreFileManager.removeCompactedFiles:(Ljava/util/Collection;)V
     135: iconst_2
     136: anewarray     #19                 // class org/apache/hadoop/hbase/regionserver/HStoreFile
     139: dup
     140: iconst_0
     141: aload_1
     142: aastore
     143: dup
     144: iconst_1
     145: getstatic     #33                 // Field KEY_C:[B
     148: getstatic     #29                 // Field org/apache/hadoop/hbase/regionserver/StripeStoreFileManager.OPEN_KEY:[B
     151: invokestatic  #31                 // Method createFile:([B[B)Lorg/apache/hadoop/hbase/regionserver/MockHStoreFile;
     154: aastore
     155: invokestatic  #20                 // Method al:([Lorg/apache/hadoop/hbase/regionserver/HStoreFile;)Ljava/util/ArrayList;
     158: invokestatic  #95                 // Method createManager:(Ljava/util/ArrayList;)Lorg/apache/hadoop/hbase/regionserver/StripeStoreFileManager;
     161: astore_2
     162: aload_0
     163: aload_2
     164: iconst_1
     165: anewarray     #19                 // class org/apache/hadoop/hbase/regionserver/HStoreFile
     168: dup
     169: iconst_0
     170: aload_1
     171: aastore
     172: invokestatic  #20                 // Method al:([Lorg/apache/hadoop/hbase/regionserver/HStoreFile;)Ljava/util/ArrayList;
     175: iconst_1
     176: anewarray     #19                 // class org/apache/hadoop/hbase/regionserver/HStoreFile
     179: dup
     180: iconst_0
     181: getstatic     #30                 // Field KEY_B:[B
     184: getstatic     #33                 // Field KEY_C:[B
     187: invokestatic  #31                 // Method createFile:([B[B)Lorg/apache/hadoop/hbase/regionserver/MockHStoreFile;
     190: aastore
     191: invokestatic  #20                 // Method al:([Lorg/apache/hadoop/hbase/regionserver/HStoreFile;)Ljava/util/ArrayList;
     194: invokespecial #101                // Method verifyInvalidCompactionScenario:(Lorg/apache/hadoop/hbase/regionserver/StripeStoreFileManager;Ljava/util/ArrayList;Ljava/util/ArrayList;)V
     197: aload_2
     198: iconst_1
     199: anewarray     #19                 // class org/apache/hadoop/hbase/regionserver/HStoreFile
     202: dup
     203: iconst_0
     204: aload_1
     205: aastore
     206: invokestatic  #20                 // Method al:([Lorg/apache/hadoop/hbase/regionserver/HStoreFile;)Ljava/util/ArrayList;
     209: iconst_1
     210: anewarray     #19                 // class org/apache/hadoop/hbase/regionserver/HStoreFile
     213: dup
     214: iconst_0
     215: getstatic     #29                 // Field org/apache/hadoop/hbase/regionserver/StripeStoreFileManager.OPEN_KEY:[B
     218: getstatic     #33                 // Field KEY_C:[B
     221: invokestatic  #31                 // Method createFile:([B[B)Lorg/apache/hadoop/hbase/regionserver/MockHStoreFile;
     224: aastore
     225: invokestatic  #20                 // Method al:([Lorg/apache/hadoop/hbase/regionserver/HStoreFile;)Ljava/util/ArrayList;
     228: invokevirtual #32                 // Method org/apache/hadoop/hbase/regionserver/StripeStoreFileManager.addCompactionResults:(Ljava/util/Collection;Ljava/util/Collection;)V
     231: aload_2
     232: iconst_1
     233: anewarray     #19                 // class org/apache/hadoop/hbase/regionserver/HStoreFile
     236: dup
     237: iconst_0
     238: aload_1
     239: aastore
     240: invokestatic  #20                 // Method al:([Lorg/apache/hadoop/hbase/regionserver/HStoreFile;)Ljava/util/ArrayList;
     243: invokevirtual #51                 // Method org/apache/hadoop/hbase/regionserver/StripeStoreFileManager.removeCompactedFiles:(Ljava/util/Collection;)V
     246: iconst_1
     247: anewarray     #19                 // class org/apache/hadoop/hbase/regionserver/HStoreFile
     250: dup
     251: iconst_0
     252: aload_1
     253: aastore
     254: invokestatic  #20                 // Method al:([Lorg/apache/hadoop/hbase/regionserver/HStoreFile;)Ljava/util/ArrayList;
     257: invokestatic  #95                 // Method createManager:(Ljava/util/ArrayList;)Lorg/apache/hadoop/hbase/regionserver/StripeStoreFileManager;
     260: astore_2
     261: aload_0
     262: aload_2
     263: iconst_1
     264: anewarray     #19                 // class org/apache/hadoop/hbase/regionserver/HStoreFile
     267: dup
     268: iconst_0
     269: aload_1
     270: aastore
     271: invokestatic  #20                 // Method al:([Lorg/apache/hadoop/hbase/regionserver/HStoreFile;)Ljava/util/ArrayList;
     274: iconst_1
     275: anewarray     #19                 // class org/apache/hadoop/hbase/regionserver/HStoreFile
     278: dup
     279: iconst_0
     280: getstatic     #30                 // Field KEY_B:[B
     283: getstatic     #33                 // Field KEY_C:[B
     286: invokestatic  #31                 // Method createFile:([B[B)Lorg/apache/hadoop/hbase/regionserver/MockHStoreFile;
     289: aastore
     290: invokestatic  #20                 // Method al:([Lorg/apache/hadoop/hbase/regionserver/HStoreFile;)Ljava/util/ArrayList;
     293: invokespecial #101                // Method verifyInvalidCompactionScenario:(Lorg/apache/hadoop/hbase/regionserver/StripeStoreFileManager;Ljava/util/ArrayList;Ljava/util/ArrayList;)V
     296: aload_2
     297: iconst_1
     298: anewarray     #19                 // class org/apache/hadoop/hbase/regionserver/HStoreFile
     301: dup
     302: iconst_0
     303: aload_1
     304: aastore
     305: invokestatic  #20                 // Method al:([Lorg/apache/hadoop/hbase/regionserver/HStoreFile;)Ljava/util/ArrayList;
     308: iconst_1
     309: anewarray     #19                 // class org/apache/hadoop/hbase/regionserver/HStoreFile
     312: dup
     313: iconst_0
     314: getstatic     #29                 // Field org/apache/hadoop/hbase/regionserver/StripeStoreFileManager.OPEN_KEY:[B
     317: getstatic     #29                 // Field org/apache/hadoop/hbase/regionserver/StripeStoreFileManager.OPEN_KEY:[B
     320: invokestatic  #31                 // Method createFile:([B[B)Lorg/apache/hadoop/hbase/regionserver/MockHStoreFile;
     323: aastore
     324: invokestatic  #20                 // Method al:([Lorg/apache/hadoop/hbase/regionserver/HStoreFile;)Ljava/util/ArrayList;
     327: invokevirtual #32                 // Method org/apache/hadoop/hbase/regionserver/StripeStoreFileManager.addCompactionResults:(Ljava/util/Collection;Ljava/util/Collection;)V
     330: return

  public void testAddingCompactionResults() throws java.lang.Exception;
    Code:
       0: invokestatic  #17                 // Method createManager:()Lorg/apache/hadoop/hbase/regionserver/StripeStoreFileManager;
       3: astore_1
       4: invokestatic  #18                 // Method createFile:()Lorg/apache/hadoop/hbase/regionserver/MockHStoreFile;
       7: astore_2
       8: invokestatic  #18                 // Method createFile:()Lorg/apache/hadoop/hbase/regionserver/MockHStoreFile;
      11: astore_3
      12: aload_1
      13: iconst_2
      14: anewarray     #19                 // class org/apache/hadoop/hbase/regionserver/HStoreFile
      17: dup
      18: iconst_0
      19: aload_2
      20: aastore
      21: dup
      22: iconst_1
      23: aload_3
      24: aastore
      25: invokestatic  #20                 // Method al:([Lorg/apache/hadoop/hbase/regionserver/HStoreFile;)Ljava/util/ArrayList;
      28: invokevirtual #21                 // Method org/apache/hadoop/hbase/regionserver/StripeStoreFileManager.insertNewFiles:(Ljava/util/Collection;)V
      31: aload_0
      32: aload_1
      33: iconst_1
      34: anewarray     #19                 // class org/apache/hadoop/hbase/regionserver/HStoreFile
      37: dup
      38: iconst_0
      39: aload_2
      40: aastore
      41: invokestatic  #20                 // Method al:([Lorg/apache/hadoop/hbase/regionserver/HStoreFile;)Ljava/util/ArrayList;
      44: iconst_1
      45: anewarray     #19                 // class org/apache/hadoop/hbase/regionserver/HStoreFile
      48: dup
      49: iconst_0
      50: getstatic     #29                 // Field org/apache/hadoop/hbase/regionserver/StripeStoreFileManager.OPEN_KEY:[B
      53: getstatic     #30                 // Field KEY_B:[B
      56: invokestatic  #31                 // Method createFile:([B[B)Lorg/apache/hadoop/hbase/regionserver/MockHStoreFile;
      59: aastore
      60: invokestatic  #20                 // Method al:([Lorg/apache/hadoop/hbase/regionserver/HStoreFile;)Ljava/util/ArrayList;
      63: invokespecial #101                // Method verifyInvalidCompactionScenario:(Lorg/apache/hadoop/hbase/regionserver/StripeStoreFileManager;Ljava/util/ArrayList;Ljava/util/ArrayList;)V
      66: aload_0
      67: aload_1
      68: iconst_1
      69: anewarray     #19                 // class org/apache/hadoop/hbase/regionserver/HStoreFile
      72: dup
      73: iconst_0
      74: aload_2
      75: aastore
      76: invokestatic  #20                 // Method al:([Lorg/apache/hadoop/hbase/regionserver/HStoreFile;)Ljava/util/ArrayList;
      79: iconst_2
      80: anewarray     #19                 // class org/apache/hadoop/hbase/regionserver/HStoreFile
      83: dup
      84: iconst_0
      85: getstatic     #29                 // Field org/apache/hadoop/hbase/regionserver/StripeStoreFileManager.OPEN_KEY:[B
      88: getstatic     #30                 // Field KEY_B:[B
      91: invokestatic  #31                 // Method createFile:([B[B)Lorg/apache/hadoop/hbase/regionserver/MockHStoreFile;
      94: aastore
      95: dup
      96: iconst_1
      97: getstatic     #33                 // Field KEY_C:[B
     100: getstatic     #29                 // Field org/apache/hadoop/hbase/regionserver/StripeStoreFileManager.OPEN_KEY:[B
     103: invokestatic  #31                 // Method createFile:([B[B)Lorg/apache/hadoop/hbase/regionserver/MockHStoreFile;
     106: aastore
     107: invokestatic  #20                 // Method al:([Lorg/apache/hadoop/hbase/regionserver/HStoreFile;)Ljava/util/ArrayList;
     110: invokespecial #101                // Method verifyInvalidCompactionScenario:(Lorg/apache/hadoop/hbase/regionserver/StripeStoreFileManager;Ljava/util/ArrayList;Ljava/util/ArrayList;)V
     113: aload_0
     114: aload_1
     115: iconst_1
     116: anewarray     #19                 // class org/apache/hadoop/hbase/regionserver/HStoreFile
     119: dup
     120: iconst_0
     121: aload_2
     122: aastore
     123: invokestatic  #20                 // Method al:([Lorg/apache/hadoop/hbase/regionserver/HStoreFile;)Ljava/util/ArrayList;
     126: iconst_3
     127: anewarray     #19                 // class org/apache/hadoop/hbase/regionserver/HStoreFile
     130: dup
     131: iconst_0
     132: getstatic     #29                 // Field org/apache/hadoop/hbase/regionserver/StripeStoreFileManager.OPEN_KEY:[B
     135: getstatic     #30                 // Field KEY_B:[B
     138: invokestatic  #31                 // Method createFile:([B[B)Lorg/apache/hadoop/hbase/regionserver/MockHStoreFile;
     141: aastore
     142: dup
     143: iconst_1
     144: getstatic     #30                 // Field KEY_B:[B
     147: getstatic     #29                 // Field org/apache/hadoop/hbase/regionserver/StripeStoreFileManager.OPEN_KEY:[B
     150: invokestatic  #31                 // Method createFile:([B[B)Lorg/apache/hadoop/hbase/regionserver/MockHStoreFile;
     153: aastore
     154: dup
     155: iconst_2
     156: getstatic     #24                 // Field KEY_A:[B
     159: getstatic     #90                 // Field KEY_D:[B
     162: invokestatic  #31                 // Method createFile:([B[B)Lorg/apache/hadoop/hbase/regionserver/MockHStoreFile;
     165: aastore
     166: invokestatic  #20                 // Method al:([Lorg/apache/hadoop/hbase/regionserver/HStoreFile;)Ljava/util/ArrayList;
     169: invokespecial #101                // Method verifyInvalidCompactionScenario:(Lorg/apache/hadoop/hbase/regionserver/StripeStoreFileManager;Ljava/util/ArrayList;Ljava/util/ArrayList;)V
     172: aload_0
     173: aload_1
     174: iconst_1
     175: anewarray     #19                 // class org/apache/hadoop/hbase/regionserver/HStoreFile
     178: dup
     179: iconst_0
     180: aload_2
     181: aastore
     182: invokestatic  #20                 // Method al:([Lorg/apache/hadoop/hbase/regionserver/HStoreFile;)Ljava/util/ArrayList;
     185: iconst_3
     186: anewarray     #19                 // class org/apache/hadoop/hbase/regionserver/HStoreFile
     189: dup
     190: iconst_0
     191: getstatic     #29                 // Field org/apache/hadoop/hbase/regionserver/StripeStoreFileManager.OPEN_KEY:[B
     194: getstatic     #30                 // Field KEY_B:[B
     197: invokestatic  #31                 // Method createFile:([B[B)Lorg/apache/hadoop/hbase/regionserver/MockHStoreFile;
     200: aastore
     201: dup
     202: iconst_1
     203: getstatic     #24                 // Field KEY_A:[B
     206: getstatic     #30                 // Field KEY_B:[B
     209: invokestatic  #31                 // Method createFile:([B[B)Lorg/apache/hadoop/hbase/regionserver/MockHStoreFile;
     212: aastore
     213: dup
     214: iconst_2
     215: getstatic     #30                 // Field KEY_B:[B
     218: getstatic     #29                 // Field org/apache/hadoop/hbase/regionserver/StripeStoreFileManager.OPEN_KEY:[B
     221: invokestatic  #31                 // Method createFile:([B[B)Lorg/apache/hadoop/hbase/regionserver/MockHStoreFile;
     224: aastore
     225: invokestatic  #20                 // Method al:([Lorg/apache/hadoop/hbase/regionserver/HStoreFile;)Ljava/util/ArrayList;
     228: invokespecial #101                // Method verifyInvalidCompactionScenario:(Lorg/apache/hadoop/hbase/regionserver/StripeStoreFileManager;Ljava/util/ArrayList;Ljava/util/ArrayList;)V
     231: getstatic     #29                 // Field org/apache/hadoop/hbase/regionserver/StripeStoreFileManager.OPEN_KEY:[B
     234: getstatic     #30                 // Field KEY_B:[B
     237: invokestatic  #31                 // Method createFile:([B[B)Lorg/apache/hadoop/hbase/regionserver/MockHStoreFile;
     240: astore        4
     242: getstatic     #30                 // Field KEY_B:[B
     245: getstatic     #33                 // Field KEY_C:[B
     248: invokestatic  #31                 // Method createFile:([B[B)Lorg/apache/hadoop/hbase/regionserver/MockHStoreFile;
     251: astore        5
     253: getstatic     #33                 // Field KEY_C:[B
     256: getstatic     #29                 // Field org/apache/hadoop/hbase/regionserver/StripeStoreFileManager.OPEN_KEY:[B
     259: invokestatic  #31                 // Method createFile:([B[B)Lorg/apache/hadoop/hbase/regionserver/MockHStoreFile;
     262: astore        6
     264: aload_1
     265: iconst_1
     266: anewarray     #19                 // class org/apache/hadoop/hbase/regionserver/HStoreFile
     269: dup
     270: iconst_0
     271: aload_2
     272: aastore
     273: invokestatic  #20                 // Method al:([Lorg/apache/hadoop/hbase/regionserver/HStoreFile;)Ljava/util/ArrayList;
     276: iconst_3
     277: anewarray     #19                 // class org/apache/hadoop/hbase/regionserver/HStoreFile
     280: dup
     281: iconst_0
     282: aload         4
     284: aastore
     285: dup
     286: iconst_1
     287: aload         5
     289: aastore
     290: dup
     291: iconst_2
     292: aload         6
     294: aastore
     295: invokestatic  #20                 // Method al:([Lorg/apache/hadoop/hbase/regionserver/HStoreFile;)Ljava/util/ArrayList;
     298: invokevirtual #32                 // Method org/apache/hadoop/hbase/regionserver/StripeStoreFileManager.addCompactionResults:(Ljava/util/Collection;Ljava/util/Collection;)V
     301: aload_1
     302: iconst_1
     303: anewarray     #19                 // class org/apache/hadoop/hbase/regionserver/HStoreFile
     306: dup
     307: iconst_0
     308: aload_2
     309: aastore
     310: invokestatic  #20                 // Method al:([Lorg/apache/hadoop/hbase/regionserver/HStoreFile;)Ljava/util/ArrayList;
     313: invokevirtual #51                 // Method org/apache/hadoop/hbase/regionserver/StripeStoreFileManager.removeCompactedFiles:(Ljava/util/Collection;)V
     316: aload_0
     317: aload_1
     318: iconst_4
     319: anewarray     #19                 // class org/apache/hadoop/hbase/regionserver/HStoreFile
     322: dup
     323: iconst_0
     324: aload_3
     325: aastore
     326: dup
     327: iconst_1
     328: aload         4
     330: aastore
     331: dup
     332: iconst_2
     333: aload         5
     335: aastore
     336: dup
     337: iconst_3
     338: aload         6
     340: aastore
     341: invokestatic  #20                 // Method al:([Lorg/apache/hadoop/hbase/regionserver/HStoreFile;)Ljava/util/ArrayList;
     344: invokespecial #100                // Method verifyAllFiles:(Lorg/apache/hadoop/hbase/regionserver/StripeStoreFileManager;Ljava/util/Collection;)V
     347: invokestatic  #18                 // Method createFile:()Lorg/apache/hadoop/hbase/regionserver/MockHStoreFile;
     350: astore        7
     352: getstatic     #29                 // Field org/apache/hadoop/hbase/regionserver/StripeStoreFileManager.OPEN_KEY:[B
     355: getstatic     #30                 // Field KEY_B:[B
     358: invokestatic  #31                 // Method createFile:([B[B)Lorg/apache/hadoop/hbase/regionserver/MockHStoreFile;
     361: astore        8
     363: getstatic     #30                 // Field KEY_B:[B
     366: getstatic     #33                 // Field KEY_C:[B
     369: invokestatic  #31                 // Method createFile:([B[B)Lorg/apache/hadoop/hbase/regionserver/MockHStoreFile;
     372: astore        9
     374: aload_1
     375: iconst_1
     376: anewarray     #19                 // class org/apache/hadoop/hbase/regionserver/HStoreFile
     379: dup
     380: iconst_0
     381: aload         7
     383: aastore
     384: invokestatic  #20                 // Method al:([Lorg/apache/hadoop/hbase/regionserver/HStoreFile;)Ljava/util/ArrayList;
     387: invokevirtual #21                 // Method org/apache/hadoop/hbase/regionserver/StripeStoreFileManager.insertNewFiles:(Ljava/util/Collection;)V
     390: aload_1
     391: iconst_2
     392: anewarray     #19                 // class org/apache/hadoop/hbase/regionserver/HStoreFile
     395: dup
     396: iconst_0
     397: aload_3
     398: aastore
     399: dup
     400: iconst_1
     401: aload         7
     403: aastore
     404: invokestatic  #20                 // Method al:([Lorg/apache/hadoop/hbase/regionserver/HStoreFile;)Ljava/util/ArrayList;
     407: iconst_2
     408: anewarray     #19                 // class org/apache/hadoop/hbase/regionserver/HStoreFile
     411: dup
     412: iconst_0
     413: aload         8
     415: aastore
     416: dup
     417: iconst_1
     418: aload         9
     420: aastore
     421: invokestatic  #20                 // Method al:([Lorg/apache/hadoop/hbase/regionserver/HStoreFile;)Ljava/util/ArrayList;
     424: invokevirtual #32                 // Method org/apache/hadoop/hbase/regionserver/StripeStoreFileManager.addCompactionResults:(Ljava/util/Collection;Ljava/util/Collection;)V
     427: aload_1
     428: iconst_2
     429: anewarray     #19                 // class org/apache/hadoop/hbase/regionserver/HStoreFile
     432: dup
     433: iconst_0
     434: aload_3
     435: aastore
     436: dup
     437: iconst_1
     438: aload         7
     440: aastore
     441: invokestatic  #20                 // Method al:([Lorg/apache/hadoop/hbase/regionserver/HStoreFile;)Ljava/util/ArrayList;
     444: invokevirtual #51                 // Method org/apache/hadoop/hbase/regionserver/StripeStoreFileManager.removeCompactedFiles:(Ljava/util/Collection;)V
     447: aload_0
     448: aload_1
     449: iconst_5
     450: anewarray     #19                 // class org/apache/hadoop/hbase/regionserver/HStoreFile
     453: dup
     454: iconst_0
     455: aload         4
     457: aastore
     458: dup
     459: iconst_1
     460: aload         5
     462: aastore
     463: dup
     464: iconst_2
     465: aload         6
     467: aastore
     468: dup
     469: iconst_3
     470: aload         8
     472: aastore
     473: dup
     474: iconst_4
     475: aload         9
     477: aastore
     478: invokestatic  #20                 // Method al:([Lorg/apache/hadoop/hbase/regionserver/HStoreFile;)Ljava/util/ArrayList;
     481: invokespecial #100                // Method verifyAllFiles:(Lorg/apache/hadoop/hbase/regionserver/StripeStoreFileManager;Ljava/util/Collection;)V
     484: aconst_null
     485: aconst_null
     486: invokestatic  #31                 // Method createFile:([B[B)Lorg/apache/hadoop/hbase/regionserver/MockHStoreFile;
     489: astore        10
     491: aload_1
     492: iconst_0
     493: anewarray     #19                 // class org/apache/hadoop/hbase/regionserver/HStoreFile
     496: invokestatic  #20                 // Method al:([Lorg/apache/hadoop/hbase/regionserver/HStoreFile;)Ljava/util/ArrayList;
     499: iconst_1
     500: anewarray     #19                 // class org/apache/hadoop/hbase/regionserver/HStoreFile
     503: dup
     504: iconst_0
     505: aload         10
     507: aastore
     508: invokestatic  #20                 // Method al:([Lorg/apache/hadoop/hbase/regionserver/HStoreFile;)Ljava/util/ArrayList;
     511: invokevirtual #32                 // Method org/apache/hadoop/hbase/regionserver/StripeStoreFileManager.addCompactionResults:(Ljava/util/Collection;Ljava/util/Collection;)V
     514: aload_1
     515: iconst_0
     516: anewarray     #19                 // class org/apache/hadoop/hbase/regionserver/HStoreFile
     519: invokestatic  #20                 // Method al:([Lorg/apache/hadoop/hbase/regionserver/HStoreFile;)Ljava/util/ArrayList;
     522: invokevirtual #51                 // Method org/apache/hadoop/hbase/regionserver/StripeStoreFileManager.removeCompactedFiles:(Ljava/util/Collection;)V
     525: aload_0
     526: aload_1
     527: bipush        6
     529: anewarray     #19                 // class org/apache/hadoop/hbase/regionserver/HStoreFile
     532: dup
     533: iconst_0
     534: aload         4
     536: aastore
     537: dup
     538: iconst_1
     539: aload         5
     541: aastore
     542: dup
     543: iconst_2
     544: aload         6
     546: aastore
     547: dup
     548: iconst_3
     549: aload         8
     551: aastore
     552: dup
     553: iconst_4
     554: aload         9
     556: aastore
     557: dup
     558: iconst_5
     559: aload         10
     561: aastore
     562: invokestatic  #20                 // Method al:([Lorg/apache/hadoop/hbase/regionserver/HStoreFile;)Ljava/util/ArrayList;
     565: invokespecial #100                // Method verifyAllFiles:(Lorg/apache/hadoop/hbase/regionserver/StripeStoreFileManager;Ljava/util/Collection;)V
     568: aload_1
     569: iconst_1
     570: anewarray     #19                 // class org/apache/hadoop/hbase/regionserver/HStoreFile
     573: dup
     574: iconst_0
     575: aload         10
     577: aastore
     578: invokestatic  #20                 // Method al:([Lorg/apache/hadoop/hbase/regionserver/HStoreFile;)Ljava/util/ArrayList;
     581: iconst_0
     582: anewarray     #19                 // class org/apache/hadoop/hbase/regionserver/HStoreFile
     585: invokestatic  #20                 // Method al:([Lorg/apache/hadoop/hbase/regionserver/HStoreFile;)Ljava/util/ArrayList;
     588: invokevirtual #32                 // Method org/apache/hadoop/hbase/regionserver/StripeStoreFileManager.addCompactionResults:(Ljava/util/Collection;Ljava/util/Collection;)V
     591: aload_1
     592: iconst_1
     593: anewarray     #19                 // class org/apache/hadoop/hbase/regionserver/HStoreFile
     596: dup
     597: iconst_0
     598: aload         10
     600: aastore
     601: invokestatic  #20                 // Method al:([Lorg/apache/hadoop/hbase/regionserver/HStoreFile;)Ljava/util/ArrayList;
     604: invokevirtual #51                 // Method org/apache/hadoop/hbase/regionserver/StripeStoreFileManager.removeCompactedFiles:(Ljava/util/Collection;)V
     607: getstatic     #29                 // Field org/apache/hadoop/hbase/regionserver/StripeStoreFileManager.OPEN_KEY:[B
     610: getstatic     #30                 // Field KEY_B:[B
     613: invokestatic  #31                 // Method createFile:([B[B)Lorg/apache/hadoop/hbase/regionserver/MockHStoreFile;
     616: astore        11
     618: aload_1
     619: iconst_2
     620: anewarray     #19                 // class org/apache/hadoop/hbase/regionserver/HStoreFile
     623: dup
     624: iconst_0
     625: aload         4
     627: aastore
     628: dup
     629: iconst_1
     630: aload         8
     632: aastore
     633: invokestatic  #20                 // Method al:([Lorg/apache/hadoop/hbase/regionserver/HStoreFile;)Ljava/util/ArrayList;
     636: iconst_1
     637: anewarray     #19                 // class org/apache/hadoop/hbase/regionserver/HStoreFile
     640: dup
     641: iconst_0
     642: aload         11
     644: aastore
     645: invokestatic  #20                 // Method al:([Lorg/apache/hadoop/hbase/regionserver/HStoreFile;)Ljava/util/ArrayList;
     648: invokevirtual #32                 // Method org/apache/hadoop/hbase/regionserver/StripeStoreFileManager.addCompactionResults:(Ljava/util/Collection;Ljava/util/Collection;)V
     651: aload_1
     652: iconst_2
     653: anewarray     #19                 // class org/apache/hadoop/hbase/regionserver/HStoreFile
     656: dup
     657: iconst_0
     658: aload         4
     660: aastore
     661: dup
     662: iconst_1
     663: aload         8
     665: aastore
     666: invokestatic  #20                 // Method al:([Lorg/apache/hadoop/hbase/regionserver/HStoreFile;)Ljava/util/ArrayList;
     669: invokevirtual #51                 // Method org/apache/hadoop/hbase/regionserver/StripeStoreFileManager.removeCompactedFiles:(Ljava/util/Collection;)V
     672: aload_0
     673: aload_1
     674: iconst_4
     675: anewarray     #19                 // class org/apache/hadoop/hbase/regionserver/HStoreFile
     678: dup
     679: iconst_0
     680: aload         5
     682: aastore
     683: dup
     684: iconst_1
     685: aload         6
     687: aastore
     688: dup
     689: iconst_2
     690: aload         9
     692: aastore
     693: dup
     694: iconst_3
     695: aload         11
     697: aastore
     698: invokestatic  #20                 // Method al:([Lorg/apache/hadoop/hbase/regionserver/HStoreFile;)Ljava/util/ArrayList;
     701: invokespecial #100                // Method verifyAllFiles:(Lorg/apache/hadoop/hbase/regionserver/StripeStoreFileManager;Ljava/util/Collection;)V
     704: getstatic     #30                 // Field KEY_B:[B
     707: getstatic     #90                 // Field KEY_D:[B
     710: invokestatic  #31                 // Method createFile:([B[B)Lorg/apache/hadoop/hbase/regionserver/MockHStoreFile;
     713: astore        12
     715: getstatic     #90                 // Field KEY_D:[B
     718: getstatic     #29                 // Field org/apache/hadoop/hbase/regionserver/StripeStoreFileManager.OPEN_KEY:[B
     721: invokestatic  #31                 // Method createFile:([B[B)Lorg/apache/hadoop/hbase/regionserver/MockHStoreFile;
     724: astore        13
     726: aload_1
     727: iconst_3
     728: anewarray     #19                 // class org/apache/hadoop/hbase/regionserver/HStoreFile
     731: dup
     732: iconst_0
     733: aload         5
     735: aastore
     736: dup
     737: iconst_1
     738: aload         6
     740: aastore
     741: dup
     742: iconst_2
     743: aload         9
     745: aastore
     746: invokestatic  #20                 // Method al:([Lorg/apache/hadoop/hbase/regionserver/HStoreFile;)Ljava/util/ArrayList;
     749: iconst_2
     750: anewarray     #19                 // class org/apache/hadoop/hbase/regionserver/HStoreFile
     753: dup
     754: iconst_0
     755: aload         12
     757: aastore
     758: dup
     759: iconst_1
     760: aload         13
     762: aastore
     763: invokestatic  #20                 // Method al:([Lorg/apache/hadoop/hbase/regionserver/HStoreFile;)Ljava/util/ArrayList;
     766: invokevirtual #32                 // Method org/apache/hadoop/hbase/regionserver/StripeStoreFileManager.addCompactionResults:(Ljava/util/Collection;Ljava/util/Collection;)V
     769: aload_1
     770: iconst_3
     771: anewarray     #19                 // class org/apache/hadoop/hbase/regionserver/HStoreFile
     774: dup
     775: iconst_0
     776: aload         5
     778: aastore
     779: dup
     780: iconst_1
     781: aload         6
     783: aastore
     784: dup
     785: iconst_2
     786: aload         9
     788: aastore
     789: invokestatic  #20                 // Method al:([Lorg/apache/hadoop/hbase/regionserver/HStoreFile;)Ljava/util/ArrayList;
     792: invokevirtual #51                 // Method org/apache/hadoop/hbase/regionserver/StripeStoreFileManager.removeCompactedFiles:(Ljava/util/Collection;)V
     795: aload_0
     796: aload_1
     797: iconst_3
     798: anewarray     #19                 // class org/apache/hadoop/hbase/regionserver/HStoreFile
     801: dup
     802: iconst_0
     803: aload         11
     805: aastore
     806: dup
     807: iconst_1
     808: aload         12
     810: aastore
     811: dup
     812: iconst_2
     813: aload         13
     815: aastore
     816: invokestatic  #20                 // Method al:([Lorg/apache/hadoop/hbase/regionserver/HStoreFile;)Ljava/util/ArrayList;
     819: invokespecial #100                // Method verifyAllFiles:(Lorg/apache/hadoop/hbase/regionserver/StripeStoreFileManager;Ljava/util/Collection;)V
     822: getstatic     #29                 // Field org/apache/hadoop/hbase/regionserver/StripeStoreFileManager.OPEN_KEY:[B
     825: getstatic     #24                 // Field KEY_A:[B
     828: invokestatic  #31                 // Method createFile:([B[B)Lorg/apache/hadoop/hbase/regionserver/MockHStoreFile;
     831: astore        14
     833: getstatic     #24                 // Field KEY_A:[B
     836: getstatic     #30                 // Field KEY_B:[B
     839: invokestatic  #31                 // Method createFile:([B[B)Lorg/apache/hadoop/hbase/regionserver/MockHStoreFile;
     842: astore        15
     844: aload_1
     845: iconst_1
     846: anewarray     #19                 // class org/apache/hadoop/hbase/regionserver/HStoreFile
     849: dup
     850: iconst_0
     851: aload         11
     853: aastore
     854: invokestatic  #20                 // Method al:([Lorg/apache/hadoop/hbase/regionserver/HStoreFile;)Ljava/util/ArrayList;
     857: iconst_2
     858: anewarray     #19                 // class org/apache/hadoop/hbase/regionserver/HStoreFile
     861: dup
     862: iconst_0
     863: aload         14
     865: aastore
     866: dup
     867: iconst_1
     868: aload         15
     870: aastore
     871: invokestatic  #20                 // Method al:([Lorg/apache/hadoop/hbase/regionserver/HStoreFile;)Ljava/util/ArrayList;
     874: invokevirtual #32                 // Method org/apache/hadoop/hbase/regionserver/StripeStoreFileManager.addCompactionResults:(Ljava/util/Collection;Ljava/util/Collection;)V
     877: aload_1
     878: iconst_1
     879: anewarray     #19                 // class org/apache/hadoop/hbase/regionserver/HStoreFile
     882: dup
     883: iconst_0
     884: aload         11
     886: aastore
     887: invokestatic  #20                 // Method al:([Lorg/apache/hadoop/hbase/regionserver/HStoreFile;)Ljava/util/ArrayList;
     890: invokevirtual #51                 // Method org/apache/hadoop/hbase/regionserver/StripeStoreFileManager.removeCompactedFiles:(Ljava/util/Collection;)V
     893: aload_0
     894: aload_1
     895: iconst_4
     896: anewarray     #19                 // class org/apache/hadoop/hbase/regionserver/HStoreFile
     899: dup
     900: iconst_0
     901: aload         12
     903: aastore
     904: dup
     905: iconst_1
     906: aload         13
     908: aastore
     909: dup
     910: iconst_2
     911: aload         14
     913: aastore
     914: dup
     915: iconst_3
     916: aload         15
     918: aastore
     919: invokestatic  #20                 // Method al:([Lorg/apache/hadoop/hbase/regionserver/HStoreFile;)Ljava/util/ArrayList;
     922: invokespecial #100                // Method verifyAllFiles:(Lorg/apache/hadoop/hbase/regionserver/StripeStoreFileManager;Ljava/util/Collection;)V
     925: getstatic     #30                 // Field KEY_B:[B
     928: getstatic     #33                 // Field KEY_C:[B
     931: invokestatic  #31                 // Method createFile:([B[B)Lorg/apache/hadoop/hbase/regionserver/MockHStoreFile;
     934: astore        16
     936: getstatic     #33                 // Field KEY_C:[B
     939: getstatic     #90                 // Field KEY_D:[B
     942: invokestatic  #31                 // Method createFile:([B[B)Lorg/apache/hadoop/hbase/regionserver/MockHStoreFile;
     945: astore        17
     947: aload_1
     948: iconst_1
     949: anewarray     #19                 // class org/apache/hadoop/hbase/regionserver/HStoreFile
     952: dup
     953: iconst_0
     954: aload         12
     956: aastore
     957: invokestatic  #20                 // Method al:([Lorg/apache/hadoop/hbase/regionserver/HStoreFile;)Ljava/util/ArrayList;
     960: iconst_2
     961: anewarray     #19                 // class org/apache/hadoop/hbase/regionserver/HStoreFile
     964: dup
     965: iconst_0
     966: aload         16
     968: aastore
     969: dup
     970: iconst_1
     971: aload         17
     973: aastore
     974: invokestatic  #20                 // Method al:([Lorg/apache/hadoop/hbase/regionserver/HStoreFile;)Ljava/util/ArrayList;
     977: invokevirtual #32                 // Method org/apache/hadoop/hbase/regionserver/StripeStoreFileManager.addCompactionResults:(Ljava/util/Collection;Ljava/util/Collection;)V
     980: aload_1
     981: iconst_1
     982: anewarray     #19                 // class org/apache/hadoop/hbase/regionserver/HStoreFile
     985: dup
     986: iconst_0
     987: aload         12
     989: aastore
     990: invokestatic  #20                 // Method al:([Lorg/apache/hadoop/hbase/regionserver/HStoreFile;)Ljava/util/ArrayList;
     993: invokevirtual #51                 // Method org/apache/hadoop/hbase/regionserver/StripeStoreFileManager.removeCompactedFiles:(Ljava/util/Collection;)V
     996: aload_0
     997: aload_1
     998: iconst_5
     999: anewarray     #19                 // class org/apache/hadoop/hbase/regionserver/HStoreFile
    1002: dup
    1003: iconst_0
    1004: aload         13
    1006: aastore
    1007: dup
    1008: iconst_1
    1009: aload         14
    1011: aastore
    1012: dup
    1013: iconst_2
    1014: aload         15
    1016: aastore
    1017: dup
    1018: iconst_3
    1019: aload         16
    1021: aastore
    1022: dup
    1023: iconst_4
    1024: aload         17
    1026: aastore
    1027: invokestatic  #20                 // Method al:([Lorg/apache/hadoop/hbase/regionserver/HStoreFile;)Ljava/util/ArrayList;
    1030: invokespecial #100                // Method verifyAllFiles:(Lorg/apache/hadoop/hbase/regionserver/StripeStoreFileManager;Ljava/util/Collection;)V
    1033: getstatic     #24                 // Field KEY_A:[B
    1036: getstatic     #33                 // Field KEY_C:[B
    1039: invokestatic  #31                 // Method createFile:([B[B)Lorg/apache/hadoop/hbase/regionserver/MockHStoreFile;
    1042: astore        18
    1044: aload_1
    1045: iconst_2
    1046: anewarray     #19                 // class org/apache/hadoop/hbase/regionserver/HStoreFile
    1049: dup
    1050: iconst_0
    1051: aload         15
    1053: aastore
    1054: dup
    1055: iconst_1
    1056: aload         16
    1058: aastore
    1059: invokestatic  #20                 // Method al:([Lorg/apache/hadoop/hbase/regionserver/HStoreFile;)Ljava/util/ArrayList;
    1062: iconst_1
    1063: anewarray     #19                 // class org/apache/hadoop/hbase/regionserver/HStoreFile
    1066: dup
    1067: iconst_0
    1068: aload         18
    1070: aastore
    1071: invokestatic  #20                 // Method al:([Lorg/apache/hadoop/hbase/regionserver/HStoreFile;)Ljava/util/ArrayList;
    1074: invokevirtual #32                 // Method org/apache/hadoop/hbase/regionserver/StripeStoreFileManager.addCompactionResults:(Ljava/util/Collection;Ljava/util/Collection;)V
    1077: aload_1
    1078: iconst_2
    1079: anewarray     #19                 // class org/apache/hadoop/hbase/regionserver/HStoreFile
    1082: dup
    1083: iconst_0
    1084: aload         15
    1086: aastore
    1087: dup
    1088: iconst_1
    1089: aload         16
    1091: aastore
    1092: invokestatic  #20                 // Method al:([Lorg/apache/hadoop/hbase/regionserver/HStoreFile;)Ljava/util/ArrayList;
    1095: invokevirtual #51                 // Method org/apache/hadoop/hbase/regionserver/StripeStoreFileManager.removeCompactedFiles:(Ljava/util/Collection;)V
    1098: aload_0
    1099: aload_1
    1100: iconst_4
    1101: anewarray     #19                 // class org/apache/hadoop/hbase/regionserver/HStoreFile
    1104: dup
    1105: iconst_0
    1106: aload         13
    1108: aastore
    1109: dup
    1110: iconst_1
    1111: aload         14
    1113: aastore
    1114: dup
    1115: iconst_2
    1116: aload         17
    1118: aastore
    1119: dup
    1120: iconst_3
    1121: aload         18
    1123: aastore
    1124: invokestatic  #20                 // Method al:([Lorg/apache/hadoop/hbase/regionserver/HStoreFile;)Ljava/util/ArrayList;
    1127: invokespecial #100                // Method verifyAllFiles:(Lorg/apache/hadoop/hbase/regionserver/StripeStoreFileManager;Ljava/util/Collection;)V
    1130: getstatic     #29                 // Field org/apache/hadoop/hbase/regionserver/StripeStoreFileManager.OPEN_KEY:[B
    1133: getstatic     #33                 // Field KEY_C:[B
    1136: invokestatic  #31                 // Method createFile:([B[B)Lorg/apache/hadoop/hbase/regionserver/MockHStoreFile;
    1139: astore        19
    1141: aload_1
    1142: iconst_2
    1143: anewarray     #19                 // class org/apache/hadoop/hbase/regionserver/HStoreFile
    1146: dup
    1147: iconst_0
    1148: aload         14
    1150: aastore
    1151: dup
    1152: iconst_1
    1153: aload         18
    1155: aastore
    1156: invokestatic  #20                 // Method al:([Lorg/apache/hadoop/hbase/regionserver/HStoreFile;)Ljava/util/ArrayList;
    1159: iconst_1
    1160: anewarray     #19                 // class org/apache/hadoop/hbase/regionserver/HStoreFile
    1163: dup
    1164: iconst_0
    1165: aload         19
    1167: aastore
    1168: invokestatic  #20                 // Method al:([Lorg/apache/hadoop/hbase/regionserver/HStoreFile;)Ljava/util/ArrayList;
    1171: invokevirtual #32                 // Method org/apache/hadoop/hbase/regionserver/StripeStoreFileManager.addCompactionResults:(Ljava/util/Collection;Ljava/util/Collection;)V
    1174: aload_1
    1175: iconst_2
    1176: anewarray     #19                 // class org/apache/hadoop/hbase/regionserver/HStoreFile
    1179: dup
    1180: iconst_0
    1181: aload         14
    1183: aastore
    1184: dup
    1185: iconst_1
    1186: aload         18
    1188: aastore
    1189: invokestatic  #20                 // Method al:([Lorg/apache/hadoop/hbase/regionserver/HStoreFile;)Ljava/util/ArrayList;
    1192: invokevirtual #51                 // Method org/apache/hadoop/hbase/regionserver/StripeStoreFileManager.removeCompactedFiles:(Ljava/util/Collection;)V
    1195: aload_0
    1196: aload_1
    1197: iconst_3
    1198: anewarray     #19                 // class org/apache/hadoop/hbase/regionserver/HStoreFile
    1201: dup
    1202: iconst_0
    1203: aload         13
    1205: aastore
    1206: dup
    1207: iconst_1
    1208: aload         17
    1210: aastore
    1211: dup
    1212: iconst_2
    1213: aload         19
    1215: aastore
    1216: invokestatic  #20                 // Method al:([Lorg/apache/hadoop/hbase/regionserver/HStoreFile;)Ljava/util/ArrayList;
    1219: invokespecial #100                // Method verifyAllFiles:(Lorg/apache/hadoop/hbase/regionserver/StripeStoreFileManager;Ljava/util/Collection;)V
    1222: getstatic     #29                 // Field org/apache/hadoop/hbase/regionserver/StripeStoreFileManager.OPEN_KEY:[B
    1225: getstatic     #29                 // Field org/apache/hadoop/hbase/regionserver/StripeStoreFileManager.OPEN_KEY:[B
    1228: invokestatic  #31                 // Method createFile:([B[B)Lorg/apache/hadoop/hbase/regionserver/MockHStoreFile;
    1231: astore        20
    1233: aload_1
    1234: iconst_3
    1235: anewarray     #19                 // class org/apache/hadoop/hbase/regionserver/HStoreFile
    1238: dup
    1239: iconst_0
    1240: aload         13
    1242: aastore
    1243: dup
    1244: iconst_1
    1245: aload         17
    1247: aastore
    1248: dup
    1249: iconst_2
    1250: aload         19
    1252: aastore
    1253: invokestatic  #20                 // Method al:([Lorg/apache/hadoop/hbase/regionserver/HStoreFile;)Ljava/util/ArrayList;
    1256: iconst_1
    1257: anewarray     #19                 // class org/apache/hadoop/hbase/regionserver/HStoreFile
    1260: dup
    1261: iconst_0
    1262: aload         20
    1264: aastore
    1265: invokestatic  #20                 // Method al:([Lorg/apache/hadoop/hbase/regionserver/HStoreFile;)Ljava/util/ArrayList;
    1268: invokevirtual #32                 // Method org/apache/hadoop/hbase/regionserver/StripeStoreFileManager.addCompactionResults:(Ljava/util/Collection;Ljava/util/Collection;)V
    1271: aload_1
    1272: iconst_3
    1273: anewarray     #19                 // class org/apache/hadoop/hbase/regionserver/HStoreFile
    1276: dup
    1277: iconst_0
    1278: aload         13
    1280: aastore
    1281: dup
    1282: iconst_1
    1283: aload         17
    1285: aastore
    1286: dup
    1287: iconst_2
    1288: aload         19
    1290: aastore
    1291: invokestatic  #20                 // Method al:([Lorg/apache/hadoop/hbase/regionserver/HStoreFile;)Ljava/util/ArrayList;
    1294: invokevirtual #51                 // Method org/apache/hadoop/hbase/regionserver/StripeStoreFileManager.removeCompactedFiles:(Ljava/util/Collection;)V
    1297: aload_0
    1298: aload_1
    1299: iconst_1
    1300: anewarray     #19                 // class org/apache/hadoop/hbase/regionserver/HStoreFile
    1303: dup
    1304: iconst_0
    1305: aload         20
    1307: aastore
    1308: invokestatic  #20                 // Method al:([Lorg/apache/hadoop/hbase/regionserver/HStoreFile;)Ljava/util/ArrayList;
    1311: invokespecial #100                // Method verifyAllFiles:(Lorg/apache/hadoop/hbase/regionserver/StripeStoreFileManager;Ljava/util/Collection;)V
    1314: return

  public void testCompactionAndFlushConflict() throws java.lang.Exception;
    Code:
       0: invokestatic  #17                 // Method createManager:()Lorg/apache/hadoop/hbase/regionserver/StripeStoreFileManager;
       3: astore_1
       4: lconst_0
       5: aload_1
       6: invokevirtual #102                // Method org/apache/hadoop/hbase/regionserver/StripeStoreFileManager.getStripeCount:()I
       9: i2l
      10: invokestatic  #23                 // Method org/junit/Assert.assertEquals:(JJ)V
      13: getstatic     #29                 // Field org/apache/hadoop/hbase/regionserver/StripeStoreFileManager.OPEN_KEY:[B
      16: getstatic     #33                 // Field KEY_C:[B
      19: invokestatic  #31                 // Method createFile:([B[B)Lorg/apache/hadoop/hbase/regionserver/MockHStoreFile;
      22: astore_2
      23: getstatic     #33                 // Field KEY_C:[B
      26: getstatic     #29                 // Field org/apache/hadoop/hbase/regionserver/StripeStoreFileManager.OPEN_KEY:[B
      29: invokestatic  #31                 // Method createFile:([B[B)Lorg/apache/hadoop/hbase/regionserver/MockHStoreFile;
      32: astore_3
      33: aload_1
      34: iconst_2
      35: anewarray     #19                 // class org/apache/hadoop/hbase/regionserver/HStoreFile
      38: dup
      39: iconst_0
      40: aload_2
      41: aastore
      42: dup
      43: iconst_1
      44: aload_3
      45: aastore
      46: invokestatic  #20                 // Method al:([Lorg/apache/hadoop/hbase/regionserver/HStoreFile;)Ljava/util/ArrayList;
      49: invokevirtual #21                 // Method org/apache/hadoop/hbase/regionserver/StripeStoreFileManager.insertNewFiles:(Ljava/util/Collection;)V
      52: ldc2_w        #53                 // long 2l
      55: aload_1
      56: invokevirtual #102                // Method org/apache/hadoop/hbase/regionserver/StripeStoreFileManager.getStripeCount:()I
      59: i2l
      60: invokestatic  #23                 // Method org/junit/Assert.assertEquals:(JJ)V
      63: getstatic     #29                 // Field org/apache/hadoop/hbase/regionserver/StripeStoreFileManager.OPEN_KEY:[B
      66: getstatic     #90                 // Field KEY_D:[B
      69: invokestatic  #31                 // Method createFile:([B[B)Lorg/apache/hadoop/hbase/regionserver/MockHStoreFile;
      72: astore        4
      74: getstatic     #90                 // Field KEY_D:[B
      77: getstatic     #29                 // Field org/apache/hadoop/hbase/regionserver/StripeStoreFileManager.OPEN_KEY:[B
      80: invokestatic  #31                 // Method createFile:([B[B)Lorg/apache/hadoop/hbase/regionserver/MockHStoreFile;
      83: astore        5
      85: aload_1
      86: iconst_2
      87: anewarray     #19                 // class org/apache/hadoop/hbase/regionserver/HStoreFile
      90: dup
      91: iconst_0
      92: aload         4
      94: aastore
      95: dup
      96: iconst_1
      97: aload         5
      99: aastore
     100: invokestatic  #20                 // Method al:([Lorg/apache/hadoop/hbase/regionserver/HStoreFile;)Ljava/util/ArrayList;
     103: invokevirtual #21                 // Method org/apache/hadoop/hbase/regionserver/StripeStoreFileManager.insertNewFiles:(Ljava/util/Collection;)V
     106: ldc2_w        #53                 // long 2l
     109: aload_1
     110: invokevirtual #102                // Method org/apache/hadoop/hbase/regionserver/StripeStoreFileManager.getStripeCount:()I
     113: i2l
     114: invokestatic  #23                 // Method org/junit/Assert.assertEquals:(JJ)V
     117: ldc2_w        #53                 // long 2l
     120: aload_1
     121: invokevirtual #96                 // Method org/apache/hadoop/hbase/regionserver/StripeStoreFileManager.getLevel0Files:()Ljava/util/List;
     124: invokeinterface #97,  1           // InterfaceMethod java/util/List.size:()I
     129: i2l
     130: invokestatic  #23                 // Method org/junit/Assert.assertEquals:(JJ)V
     133: aload_0
     134: aload_1
     135: getstatic     #33                 // Field KEY_C:[B
     138: getstatic     #33                 // Field KEY_C:[B
     141: iconst_3
     142: anewarray     #19                 // class org/apache/hadoop/hbase/regionserver/HStoreFile
     145: dup
     146: iconst_0
     147: aload         4
     149: aastore
     150: dup
     151: iconst_1
     152: aload         5
     154: aastore
     155: dup
     156: iconst_2
     157: aload_3
     158: aastore
     159: invokespecial #89                 // Method verifyGetAndScanScenario:(Lorg/apache/hadoop/hbase/regionserver/StripeStoreFileManager;[B[B[Lorg/apache/hadoop/hbase/regionserver/HStoreFile;)V
     162: aload_1
     163: iconst_2
     164: anewarray     #19                 // class org/apache/hadoop/hbase/regionserver/HStoreFile
     167: dup
     168: iconst_0
     169: aload         4
     171: aastore
     172: dup
     173: iconst_1
     174: aload         5
     176: aastore
     177: invokestatic  #20                 // Method al:([Lorg/apache/hadoop/hbase/regionserver/HStoreFile;)Ljava/util/ArrayList;
     180: iconst_0
     181: anewarray     #19                 // class org/apache/hadoop/hbase/regionserver/HStoreFile
     184: invokestatic  #20                 // Method al:([Lorg/apache/hadoop/hbase/regionserver/HStoreFile;)Ljava/util/ArrayList;
     187: invokevirtual #32                 // Method org/apache/hadoop/hbase/regionserver/StripeStoreFileManager.addCompactionResults:(Ljava/util/Collection;Ljava/util/Collection;)V
     190: aload_1
     191: iconst_2
     192: anewarray     #19                 // class org/apache/hadoop/hbase/regionserver/HStoreFile
     195: dup
     196: iconst_0
     197: aload         4
     199: aastore
     200: dup
     201: iconst_1
     202: aload         5
     204: aastore
     205: invokestatic  #20                 // Method al:([Lorg/apache/hadoop/hbase/regionserver/HStoreFile;)Ljava/util/ArrayList;
     208: invokevirtual #51                 // Method org/apache/hadoop/hbase/regionserver/StripeStoreFileManager.removeCompactedFiles:(Ljava/util/Collection;)V
     211: lconst_0
     212: aload_1
     213: invokevirtual #96                 // Method org/apache/hadoop/hbase/regionserver/StripeStoreFileManager.getLevel0Files:()Ljava/util/List;
     216: invokeinterface #97,  1           // InterfaceMethod java/util/List.size:()I
     221: i2l
     222: invokestatic  #23                 // Method org/junit/Assert.assertEquals:(JJ)V
     225: getstatic     #29                 // Field org/apache/hadoop/hbase/regionserver/StripeStoreFileManager.OPEN_KEY:[B
     228: getstatic     #33                 // Field KEY_C:[B
     231: invokestatic  #31                 // Method createFile:([B[B)Lorg/apache/hadoop/hbase/regionserver/MockHStoreFile;
     234: astore        6
     236: aload_1
     237: iconst_1
     238: anewarray     #19                 // class org/apache/hadoop/hbase/regionserver/HStoreFile
     241: dup
     242: iconst_0
     243: aload         6
     245: aastore
     246: invokestatic  #20                 // Method al:([Lorg/apache/hadoop/hbase/regionserver/HStoreFile;)Ljava/util/ArrayList;
     249: invokevirtual #21                 // Method org/apache/hadoop/hbase/regionserver/StripeStoreFileManager.insertNewFiles:(Ljava/util/Collection;)V
     252: aload_1
     253: iconst_2
     254: anewarray     #19                 // class org/apache/hadoop/hbase/regionserver/HStoreFile
     257: dup
     258: iconst_0
     259: aload_2
     260: aastore
     261: dup
     262: iconst_1
     263: aload_3
     264: aastore
     265: invokestatic  #20                 // Method al:([Lorg/apache/hadoop/hbase/regionserver/HStoreFile;)Ljava/util/ArrayList;
     268: iconst_2
     269: anewarray     #19                 // class org/apache/hadoop/hbase/regionserver/HStoreFile
     272: dup
     273: iconst_0
     274: aload         4
     276: aastore
     277: dup
     278: iconst_1
     279: aload         5
     281: aastore
     282: invokestatic  #20                 // Method al:([Lorg/apache/hadoop/hbase/regionserver/HStoreFile;)Ljava/util/ArrayList;
     285: invokevirtual #32                 // Method org/apache/hadoop/hbase/regionserver/StripeStoreFileManager.addCompactionResults:(Ljava/util/Collection;Ljava/util/Collection;)V
     288: aload_1
     289: iconst_2
     290: anewarray     #19                 // class org/apache/hadoop/hbase/regionserver/HStoreFile
     293: dup
     294: iconst_0
     295: aload_2
     296: aastore
     297: dup
     298: iconst_1
     299: aload_3
     300: aastore
     301: invokestatic  #20                 // Method al:([Lorg/apache/hadoop/hbase/regionserver/HStoreFile;)Ljava/util/ArrayList;
     304: invokevirtual #51                 // Method org/apache/hadoop/hbase/regionserver/StripeStoreFileManager.removeCompactedFiles:(Ljava/util/Collection;)V
     307: lconst_1
     308: aload_1
     309: invokevirtual #96                 // Method org/apache/hadoop/hbase/regionserver/StripeStoreFileManager.getLevel0Files:()Ljava/util/List;
     312: invokeinterface #97,  1           // InterfaceMethod java/util/List.size:()I
     317: i2l
     318: invokestatic  #23                 // Method org/junit/Assert.assertEquals:(JJ)V
     321: aload_0
     322: aload_1
     323: getstatic     #33                 // Field KEY_C:[B
     326: getstatic     #33                 // Field KEY_C:[B
     329: iconst_2
     330: anewarray     #19                 // class org/apache/hadoop/hbase/regionserver/HStoreFile
     333: dup
     334: iconst_0
     335: aload         4
     337: aastore
     338: dup
     339: iconst_1
     340: aload         6
     342: aastore
     343: invokespecial #89                 // Method verifyGetAndScanScenario:(Lorg/apache/hadoop/hbase/regionserver/StripeStoreFileManager;[B[B[Lorg/apache/hadoop/hbase/regionserver/HStoreFile;)V
     346: return

  public void testEmptyResultsForStripes() throws java.lang.Exception;
    Code:
       0: invokestatic  #17                 // Method createManager:()Lorg/apache/hadoop/hbase/regionserver/StripeStoreFileManager;
       3: astore_1
       4: invokestatic  #18                 // Method createFile:()Lorg/apache/hadoop/hbase/regionserver/MockHStoreFile;
       7: astore_2
       8: invokestatic  #18                 // Method createFile:()Lorg/apache/hadoop/hbase/regionserver/MockHStoreFile;
      11: astore_3
      12: aload_1
      13: iconst_1
      14: anewarray     #19                 // class org/apache/hadoop/hbase/regionserver/HStoreFile
      17: dup
      18: iconst_0
      19: aload_2
      20: aastore
      21: invokestatic  #20                 // Method al:([Lorg/apache/hadoop/hbase/regionserver/HStoreFile;)Ljava/util/ArrayList;
      24: invokevirtual #21                 // Method org/apache/hadoop/hbase/regionserver/StripeStoreFileManager.insertNewFiles:(Ljava/util/Collection;)V
      27: aload_1
      28: iconst_1
      29: anewarray     #19                 // class org/apache/hadoop/hbase/regionserver/HStoreFile
      32: dup
      33: iconst_0
      34: aload_3
      35: aastore
      36: invokestatic  #20                 // Method al:([Lorg/apache/hadoop/hbase/regionserver/HStoreFile;)Ljava/util/ArrayList;
      39: invokevirtual #21                 // Method org/apache/hadoop/hbase/regionserver/StripeStoreFileManager.insertNewFiles:(Ljava/util/Collection;)V
      42: iconst_3
      43: anewarray     #19                 // class org/apache/hadoop/hbase/regionserver/HStoreFile
      46: dup
      47: iconst_0
      48: getstatic     #29                 // Field org/apache/hadoop/hbase/regionserver/StripeStoreFileManager.OPEN_KEY:[B
      51: getstatic     #30                 // Field KEY_B:[B
      54: invokestatic  #31                 // Method createFile:([B[B)Lorg/apache/hadoop/hbase/regionserver/MockHStoreFile;
      57: aastore
      58: dup
      59: iconst_1
      60: getstatic     #30                 // Field KEY_B:[B
      63: getstatic     #33                 // Field KEY_C:[B
      66: invokestatic  #31                 // Method createFile:([B[B)Lorg/apache/hadoop/hbase/regionserver/MockHStoreFile;
      69: aastore
      70: dup
      71: iconst_2
      72: getstatic     #33                 // Field KEY_C:[B
      75: getstatic     #29                 // Field org/apache/hadoop/hbase/regionserver/StripeStoreFileManager.OPEN_KEY:[B
      78: invokestatic  #31                 // Method createFile:([B[B)Lorg/apache/hadoop/hbase/regionserver/MockHStoreFile;
      81: aastore
      82: invokestatic  #20                 // Method al:([Lorg/apache/hadoop/hbase/regionserver/HStoreFile;)Ljava/util/ArrayList;
      85: astore        4
      87: aload_1
      88: iconst_1
      89: anewarray     #19                 // class org/apache/hadoop/hbase/regionserver/HStoreFile
      92: dup
      93: iconst_0
      94: aload_2
      95: aastore
      96: invokestatic  #20                 // Method al:([Lorg/apache/hadoop/hbase/regionserver/HStoreFile;)Ljava/util/ArrayList;
      99: aload         4
     101: invokevirtual #32                 // Method org/apache/hadoop/hbase/regionserver/StripeStoreFileManager.addCompactionResults:(Ljava/util/Collection;Ljava/util/Collection;)V
     104: aload_1
     105: iconst_1
     106: anewarray     #19                 // class org/apache/hadoop/hbase/regionserver/HStoreFile
     109: dup
     110: iconst_0
     111: aload_2
     112: aastore
     113: invokestatic  #20                 // Method al:([Lorg/apache/hadoop/hbase/regionserver/HStoreFile;)Ljava/util/ArrayList;
     116: invokevirtual #51                 // Method org/apache/hadoop/hbase/regionserver/StripeStoreFileManager.removeCompactedFiles:(Ljava/util/Collection;)V
     119: iconst_2
     120: anewarray     #19                 // class org/apache/hadoop/hbase/regionserver/HStoreFile
     123: dup
     124: iconst_0
     125: getstatic     #29                 // Field org/apache/hadoop/hbase/regionserver/StripeStoreFileManager.OPEN_KEY:[B
     128: getstatic     #30                 // Field KEY_B:[B
     131: invokestatic  #31                 // Method createFile:([B[B)Lorg/apache/hadoop/hbase/regionserver/MockHStoreFile;
     134: aastore
     135: dup
     136: iconst_1
     137: getstatic     #33                 // Field KEY_C:[B
     140: getstatic     #29                 // Field org/apache/hadoop/hbase/regionserver/StripeStoreFileManager.OPEN_KEY:[B
     143: invokestatic  #31                 // Method createFile:([B[B)Lorg/apache/hadoop/hbase/regionserver/MockHStoreFile;
     146: aastore
     147: invokestatic  #20                 // Method al:([Lorg/apache/hadoop/hbase/regionserver/HStoreFile;)Ljava/util/ArrayList;
     150: astore        5
     152: aload_1
     153: iconst_1
     154: anewarray     #19                 // class org/apache/hadoop/hbase/regionserver/HStoreFile
     157: dup
     158: iconst_0
     159: aload_3
     160: aastore
     161: invokestatic  #20                 // Method al:([Lorg/apache/hadoop/hbase/regionserver/HStoreFile;)Ljava/util/ArrayList;
     164: aload         5
     166: invokevirtual #32                 // Method org/apache/hadoop/hbase/regionserver/StripeStoreFileManager.addCompactionResults:(Ljava/util/Collection;Ljava/util/Collection;)V
     169: aload_1
     170: iconst_1
     171: anewarray     #19                 // class org/apache/hadoop/hbase/regionserver/HStoreFile
     174: dup
     175: iconst_0
     176: aload_3
     177: aastore
     178: invokestatic  #20                 // Method al:([Lorg/apache/hadoop/hbase/regionserver/HStoreFile;)Ljava/util/ArrayList;
     181: invokevirtual #51                 // Method org/apache/hadoop/hbase/regionserver/StripeStoreFileManager.removeCompactedFiles:(Ljava/util/Collection;)V
     184: aload         4
     186: aload         5
     188: invokevirtual #103                // Method java/util/ArrayList.addAll:(Ljava/util/Collection;)Z
     191: pop
     192: aload_0
     193: aload_1
     194: aload         4
     196: invokespecial #100                // Method verifyAllFiles:(Lorg/apache/hadoop/hbase/regionserver/StripeStoreFileManager;Ljava/util/Collection;)V
     199: return

  public void testPriority() throws java.lang.Exception;
    Code:
       0: aload_0
       1: iconst_5
       2: iconst_5
       3: iconst_0
       4: iconst_0
       5: iconst_0
       6: invokespecial #104                // Method testPriorityScenario:(IIIII)V
       9: aload_0
      10: iconst_2
      11: iconst_5
      12: iconst_0
      13: iconst_0
      14: iconst_3
      15: invokespecial #104                // Method testPriorityScenario:(IIIII)V
      18: aload_0
      19: iconst_4
      20: bipush        25
      22: iconst_5
      23: iconst_1
      24: iconst_0
      25: invokespecial #104                // Method testPriorityScenario:(IIIII)V
      28: aload_0
      29: iconst_3
      30: bipush        25
      32: iconst_5
      33: iconst_1
      34: iconst_1
      35: invokespecial #104                // Method testPriorityScenario:(IIIII)V
      38: aload_0
      39: iconst_3
      40: bipush        25
      42: iconst_5
      43: iconst_2
      44: iconst_0
      45: invokespecial #104                // Method testPriorityScenario:(IIIII)V
      48: aload_0
      49: iconst_2
      50: bipush        25
      52: iconst_5
      53: iconst_4
      54: iconst_0
      55: invokespecial #104                // Method testPriorityScenario:(IIIII)V
      58: aload_0
      59: iconst_2
      60: bipush        25
      62: iconst_5
      63: iconst_4
      64: iconst_4
      65: invokespecial #104                // Method testPriorityScenario:(IIIII)V
      68: aload_0
      69: iconst_2
      70: bipush        25
      72: iconst_5
      73: iconst_1
      74: bipush        10
      76: invokespecial #104                // Method testPriorityScenario:(IIIII)V
      79: aload_0
      80: iconst_0
      81: bipush        25
      83: iconst_5
      84: iconst_4
      85: iconst_5
      86: invokespecial #104                // Method testPriorityScenario:(IIIII)V
      89: aload_0
      90: bipush        -5
      92: bipush        25
      94: iconst_5
      95: bipush        6
      97: iconst_0
      98: invokespecial #104                // Method testPriorityScenario:(IIIII)V
     101: aload_0
     102: iconst_m1
     103: bipush        25
     105: iconst_0
     106: iconst_0
     107: bipush        26
     109: invokespecial #104                // Method testPriorityScenario:(IIIII)V
     112: return

  static {};
    Code:
       0: ldc           #132                // class org/apache/hadoop/hbase/regionserver/TestStripeStoreFileManager
       2: invokestatic  #133                // Method org/apache/hadoop/hbase/HBaseClassTestRule.forClass:(Ljava/lang/Class;)Lorg/apache/hadoop/hbase/HBaseClassTestRule;
       5: putstatic     #134                // Field CLASS_RULE:Lorg/apache/hadoop/hbase/HBaseClassTestRule;
       8: new           #135                // class org/apache/hadoop/hbase/HBaseTestingUtility
      11: dup
      12: invokespecial #136                // Method org/apache/hadoop/hbase/HBaseTestingUtility."<init>":()V
      15: putstatic     #2                  // Field TEST_UTIL:Lorg/apache/hadoop/hbase/HBaseTestingUtility;
      18: getstatic     #2                  // Field TEST_UTIL:Lorg/apache/hadoop/hbase/HBaseTestingUtility;
      21: ldc           #132                // class org/apache/hadoop/hbase/regionserver/TestStripeStoreFileManager
      23: invokevirtual #137                // Method java/lang/Class.getSimpleName:()Ljava/lang/String;
      26: invokevirtual #138                // Method org/apache/hadoop/hbase/HBaseTestingUtility.getDataTestDir:(Ljava/lang/String;)Lorg/apache/hadoop/fs/Path;
      29: putstatic     #139                // Field BASEDIR:Lorg/apache/hadoop/fs/Path;
      32: getstatic     #139                // Field BASEDIR:Lorg/apache/hadoop/fs/Path;
      35: ldc           #140                // String region
      37: ldc           #141                // String cf
      39: invokestatic  #142                // Method org/apache/hadoop/hbase/util/Bytes.toBytes:(Ljava/lang/String;)[B
      42: invokestatic  #143                // Method org/apache/hadoop/hbase/regionserver/HStore.getStoreHomedir:(Lorg/apache/hadoop/fs/Path;Ljava/lang/String;[B)Lorg/apache/hadoop/fs/Path;
      45: putstatic     #4                  // Field CFDIR:Lorg/apache/hadoop/fs/Path;
      48: ldc           #144                // String aaa
      50: invokestatic  #142                // Method org/apache/hadoop/hbase/util/Bytes.toBytes:(Ljava/lang/String;)[B
      53: putstatic     #24                 // Field KEY_A:[B
      56: ldc           #145                // String aab
      58: invokestatic  #142                // Method org/apache/hadoop/hbase/util/Bytes.toBytes:(Ljava/lang/String;)[B
      61: putstatic     #30                 // Field KEY_B:[B
      64: ldc           #146                // String aac
      66: invokestatic  #142                // Method org/apache/hadoop/hbase/util/Bytes.toBytes:(Ljava/lang/String;)[B
      69: putstatic     #33                 // Field KEY_C:[B
      72: ldc           #147                // String aad
      74: invokestatic  #142                // Method org/apache/hadoop/hbase/util/Bytes.toBytes:(Ljava/lang/String;)[B
      77: putstatic     #90                 // Field KEY_D:[B
      80: new           #148                // class org/apache/hadoop/hbase/KeyValue
      83: dup
      84: getstatic     #24                 // Field KEY_A:[B
      87: lconst_0
      88: invokespecial #149                // Method org/apache/hadoop/hbase/KeyValue."<init>":([BJ)V
      91: putstatic     #46                 // Field KV_A:Lorg/apache/hadoop/hbase/KeyValue;
      94: new           #148                // class org/apache/hadoop/hbase/KeyValue
      97: dup
      98: getstatic     #30                 // Field KEY_B:[B
     101: lconst_0
     102: invokespecial #149                // Method org/apache/hadoop/hbase/KeyValue."<init>":([BJ)V
     105: putstatic     #43                 // Field KV_B:Lorg/apache/hadoop/hbase/KeyValue;
     108: new           #148                // class org/apache/hadoop/hbase/KeyValue
     111: dup
     112: getstatic     #33                 // Field KEY_C:[B
     115: lconst_0
     116: invokespecial #149                // Method org/apache/hadoop/hbase/KeyValue."<init>":([BJ)V
     119: putstatic     #61                 // Field KV_C:Lorg/apache/hadoop/hbase/KeyValue;
     122: new           #148                // class org/apache/hadoop/hbase/KeyValue
     125: dup
     126: getstatic     #90                 // Field KEY_D:[B
     129: lconst_0
     130: invokespecial #149                // Method org/apache/hadoop/hbase/KeyValue."<init>":([BJ)V
     133: putstatic     #60                 // Field KV_D:Lorg/apache/hadoop/hbase/KeyValue;
     136: return
}
