Compiled from "TestScannerWithBulkload.java"
class org.apache.hadoop.hbase.regionserver.TestScannerWithBulkload$1 extends java.lang.Thread {
  final long val$l;

  final org.apache.hadoop.hbase.client.Table val$table;

  final org.apache.hadoop.hbase.TableName val$tableName;

  final org.apache.hadoop.hbase.tool.LoadIncrementalHFiles val$bulkload;

  final org.apache.hadoop.fs.Path val$hfilePath;

  final org.apache.hadoop.hbase.client.Admin val$admin;

  final java.util.concurrent.CountDownLatch val$latch;

  final org.apache.hadoop.hbase.regionserver.TestScannerWithBulkload this$0;

  org.apache.hadoop.hbase.regionserver.TestScannerWithBulkload$1(org.apache.hadoop.hbase.regionserver.TestScannerWithBulkload, long, org.apache.hadoop.hbase.client.Table, org.apache.hadoop.hbase.TableName, org.apache.hadoop.hbase.tool.LoadIncrementalHFiles, org.apache.hadoop.fs.Path, org.apache.hadoop.hbase.client.Admin, java.util.concurrent.CountDownLatch);
    Code:
       0: aload_0
       1: aload_1
       2: putfield      #1                  // Field this$0:Lorg/apache/hadoop/hbase/regionserver/TestScannerWithBulkload;
       5: aload_0
       6: lload_2
       7: putfield      #2                  // Field val$l:J
      10: aload_0
      11: aload         4
      13: putfield      #3                  // Field val$table:Lorg/apache/hadoop/hbase/client/Table;
      16: aload_0
      17: aload         5
      19: putfield      #4                  // Field val$tableName:Lorg/apache/hadoop/hbase/TableName;
      22: aload_0
      23: aload         6
      25: putfield      #5                  // Field val$bulkload:Lorg/apache/hadoop/hbase/tool/LoadIncrementalHFiles;
      28: aload_0
      29: aload         7
      31: putfield      #6                  // Field val$hfilePath:Lorg/apache/hadoop/fs/Path;
      34: aload_0
      35: aload         8
      37: putfield      #7                  // Field val$admin:Lorg/apache/hadoop/hbase/client/Admin;
      40: aload_0
      41: aload         9
      43: putfield      #8                  // Field val$latch:Ljava/util/concurrent/CountDownLatch;
      46: aload_0
      47: invokespecial #9                  // Method java/lang/Thread."<init>":()V
      50: return

  public void run();
    Code:
       0: new           #10                 // class org/apache/hadoop/hbase/client/Put
       3: dup
       4: ldc           #11                 // String row5
       6: invokestatic  #12                 // Method org/apache/hadoop/hbase/util/Bytes.toBytes:(Ljava/lang/String;)[B
       9: invokespecial #13                 // Method org/apache/hadoop/hbase/client/Put."<init>":([B)V
      12: astore_1
      13: aload_1
      14: new           #14                 // class org/apache/hadoop/hbase/KeyValue
      17: dup
      18: ldc           #11                 // String row5
      20: invokestatic  #12                 // Method org/apache/hadoop/hbase/util/Bytes.toBytes:(Ljava/lang/String;)[B
      23: ldc           #15                 // String col
      25: invokestatic  #12                 // Method org/apache/hadoop/hbase/util/Bytes.toBytes:(Ljava/lang/String;)[B
      28: ldc           #16                 // String q
      30: invokestatic  #12                 // Method org/apache/hadoop/hbase/util/Bytes.toBytes:(Ljava/lang/String;)[B
      33: aload_0
      34: getfield      #2                  // Field val$l:J
      37: ldc           #17                 // String version0
      39: invokestatic  #12                 // Method org/apache/hadoop/hbase/util/Bytes.toBytes:(Ljava/lang/String;)[B
      42: invokespecial #18                 // Method org/apache/hadoop/hbase/KeyValue."<init>":([B[B[BJ[B)V
      45: invokevirtual #19                 // Method org/apache/hadoop/hbase/client/Put.add:(Lorg/apache/hadoop/hbase/Cell;)Lorg/apache/hadoop/hbase/client/Put;
      48: pop
      49: aload_0
      50: getfield      #3                  // Field val$table:Lorg/apache/hadoop/hbase/client/Table;
      53: aload_1
      54: invokeinterface #20,  2           // InterfaceMethod org/apache/hadoop/hbase/client/Table.put:(Lorg/apache/hadoop/hbase/client/Put;)V
      59: invokestatic  #21                 // Method org/apache/hadoop/hbase/regionserver/TestScannerWithBulkload.access$000:()Lorg/apache/hadoop/hbase/HBaseTestingUtility;
      62: invokevirtual #22                 // Method org/apache/hadoop/hbase/HBaseTestingUtility.getConnection:()Lorg/apache/hadoop/hbase/client/Connection;
      65: aload_0
      66: getfield      #4                  // Field val$tableName:Lorg/apache/hadoop/hbase/TableName;
      69: invokeinterface #23,  2           // InterfaceMethod org/apache/hadoop/hbase/client/Connection.getRegionLocator:(Lorg/apache/hadoop/hbase/TableName;)Lorg/apache/hadoop/hbase/client/RegionLocator;
      74: astore_2
      75: aconst_null
      76: astore_3
      77: aload_0
      78: getfield      #5                  // Field val$bulkload:Lorg/apache/hadoop/hbase/tool/LoadIncrementalHFiles;
      81: aload_0
      82: getfield      #6                  // Field val$hfilePath:Lorg/apache/hadoop/fs/Path;
      85: aload_0
      86: getfield      #7                  // Field val$admin:Lorg/apache/hadoop/hbase/client/Admin;
      89: aload_0
      90: getfield      #3                  // Field val$table:Lorg/apache/hadoop/hbase/client/Table;
      93: aload_2
      94: invokevirtual #24                 // Method org/apache/hadoop/hbase/tool/LoadIncrementalHFiles.doBulkLoad:(Lorg/apache/hadoop/fs/Path;Lorg/apache/hadoop/hbase/client/Admin;Lorg/apache/hadoop/hbase/client/Table;Lorg/apache/hadoop/hbase/client/RegionLocator;)Ljava/util/Map;
      97: pop
      98: aload_2
      99: ifnull        182
     102: aload_3
     103: ifnull        126
     106: aload_2
     107: invokeinterface #25,  1           // InterfaceMethod org/apache/hadoop/hbase/client/RegionLocator.close:()V
     112: goto          182
     115: astore        4
     117: aload_3
     118: aload         4
     120: invokevirtual #27                 // Method java/lang/Throwable.addSuppressed:(Ljava/lang/Throwable;)V
     123: goto          182
     126: aload_2
     127: invokeinterface #25,  1           // InterfaceMethod org/apache/hadoop/hbase/client/RegionLocator.close:()V
     132: goto          182
     135: astore        4
     137: aload         4
     139: astore_3
     140: aload         4
     142: athrow
     143: astore        5
     145: aload_2
     146: ifnull        179
     149: aload_3
     150: ifnull        173
     153: aload_2
     154: invokeinterface #25,  1           // InterfaceMethod org/apache/hadoop/hbase/client/RegionLocator.close:()V
     159: goto          179
     162: astore        6
     164: aload_3
     165: aload         6
     167: invokevirtual #27                 // Method java/lang/Throwable.addSuppressed:(Ljava/lang/Throwable;)V
     170: goto          179
     173: aload_2
     174: invokeinterface #25,  1           // InterfaceMethod org/apache/hadoop/hbase/client/RegionLocator.close:()V
     179: aload         5
     181: athrow
     182: aload_0
     183: getfield      #8                  // Field val$latch:Ljava/util/concurrent/CountDownLatch;
     186: invokevirtual #28                 // Method java/util/concurrent/CountDownLatch.countDown:()V
     189: goto          197
     192: astore_1
     193: goto          197
     196: astore_1
     197: return
    Exception table:
       from    to  target type
         106   112   115   Class java/lang/Throwable
          77    98   135   Class java/lang/Throwable
          77    98   143   any
         153   159   162   Class java/lang/Throwable
         135   145   143   any
           0   189   192   Class org/apache/hadoop/hbase/TableNotFoundException
           0   189   196   Class java/io/IOException
}
