Compiled from "TestRegionServerAbort.java"
public class org.apache.hadoop.hbase.regionserver.TestRegionServerAbort$ErrorThrowingHRegion extends org.apache.hadoop.hbase.regionserver.HRegion {
  public org.apache.hadoop.hbase.regionserver.TestRegionServerAbort$ErrorThrowingHRegion(org.apache.hadoop.fs.Path, org.apache.hadoop.hbase.wal.WAL, org.apache.hadoop.fs.FileSystem, org.apache.hadoop.conf.Configuration, org.apache.hadoop.hbase.client.RegionInfo, org.apache.hadoop.hbase.client.TableDescriptor, org.apache.hadoop.hbase.regionserver.RegionServerServices);
    Code:
       0: aload_0
       1: aload_1
       2: aload_2
       3: aload_3
       4: aload         4
       6: aload         5
       8: aload         6
      10: aload         7
      12: invokespecial #1                  // Method org/apache/hadoop/hbase/regionserver/HRegion."<init>":(Lorg/apache/hadoop/fs/Path;Lorg/apache/hadoop/hbase/wal/WAL;Lorg/apache/hadoop/fs/FileSystem;Lorg/apache/hadoop/conf/Configuration;Lorg/apache/hadoop/hbase/client/RegionInfo;Lorg/apache/hadoop/hbase/client/TableDescriptor;Lorg/apache/hadoop/hbase/regionserver/RegionServerServices;)V
      15: return

  public org.apache.hadoop.hbase.regionserver.TestRegionServerAbort$ErrorThrowingHRegion(org.apache.hadoop.hbase.regionserver.HRegionFileSystem, org.apache.hadoop.hbase.wal.WAL, org.apache.hadoop.conf.Configuration, org.apache.hadoop.hbase.client.TableDescriptor, org.apache.hadoop.hbase.regionserver.RegionServerServices);
    Code:
       0: aload_0
       1: aload_1
       2: aload_2
       3: aload_3
       4: aload         4
       6: aload         5
       8: invokespecial #2                  // Method org/apache/hadoop/hbase/regionserver/HRegion."<init>":(Lorg/apache/hadoop/hbase/regionserver/HRegionFileSystem;Lorg/apache/hadoop/hbase/wal/WAL;Lorg/apache/hadoop/conf/Configuration;Lorg/apache/hadoop/hbase/client/TableDescriptor;Lorg/apache/hadoop/hbase/regionserver/RegionServerServices;)V
      11: return

  protected boolean refreshStoreFiles(boolean) throws java.io.IOException;
    Code:
       0: iload_1
       1: ifeq          14
       4: new           #3                  // class java/io/IOException
       7: dup
       8: ldc           #4                  // String Failing file refresh for testing
      10: invokespecial #5                  // Method java/io/IOException."<init>":(Ljava/lang/String;)V
      13: athrow
      14: aload_0
      15: iload_1
      16: invokespecial #6                  // Method org/apache/hadoop/hbase/regionserver/HRegion.refreshStoreFiles:(Z)Z
      19: ireturn
}
