Compiled from "TestTimeoutExceptionInjector.java"
public class org.apache.hadoop.hbase.errorhandling.TestTimeoutExceptionInjector {
  public static final org.apache.hadoop.hbase.HBaseClassTestRule CLASS_RULE;

  public org.apache.hadoop.hbase.errorhandling.TestTimeoutExceptionInjector();
    Code:
       0: aload_0
       1: invokespecial #1                  // Method java/lang/Object."<init>":()V
       4: return

  public void testTimerTrigger();
    Code:
       0: ldc2_w        #2                  // long 10000000l
       3: lstore_1
       4: ldc           #4                  // class org/apache/hadoop/hbase/errorhandling/ForeignExceptionListener
       6: invokestatic  #5                  // Method org/mockito/Mockito.mock:(Ljava/lang/Class;)Ljava/lang/Object;
       9: checkcast     #4                  // class org/apache/hadoop/hbase/errorhandling/ForeignExceptionListener
      12: astore_3
      13: new           #6                  // class org/apache/hadoop/hbase/errorhandling/TimeoutExceptionInjector
      16: dup
      17: aload_3
      18: ldc2_w        #2                  // long 10000000l
      21: invokespecial #7                  // Method org/apache/hadoop/hbase/errorhandling/TimeoutExceptionInjector."<init>":(Lorg/apache/hadoop/hbase/errorhandling/ForeignExceptionListener;J)V
      24: astore        4
      26: aload         4
      28: invokevirtual #8                  // Method org/apache/hadoop/hbase/errorhandling/TimeoutExceptionInjector.start:()V
      31: aload         4
      33: invokevirtual #9                  // Method org/apache/hadoop/hbase/errorhandling/TimeoutExceptionInjector.trigger:()V
      36: aload_3
      37: iconst_1
      38: invokestatic  #10                 // Method org/mockito/Mockito.times:(I)Lorg/mockito/verification/VerificationMode;
      41: invokestatic  #11                 // Method org/mockito/Mockito.verify:(Ljava/lang/Object;Lorg/mockito/verification/VerificationMode;)Ljava/lang/Object;
      44: checkcast     #4                  // class org/apache/hadoop/hbase/errorhandling/ForeignExceptionListener
      47: invokestatic  #12                 // Method org/mockito/Mockito.any:()Ljava/lang/Object;
      50: checkcast     #13                 // class org/apache/hadoop/hbase/errorhandling/ForeignException
      53: invokeinterface #14,  2           // InterfaceMethod org/apache/hadoop/hbase/errorhandling/ForeignExceptionListener.receive:(Lorg/apache/hadoop/hbase/errorhandling/ForeignException;)V
      58: return

  public void testTimerPassesOnErrorInfo();
    Code:
       0: ldc2_w        #15                 // long 1000000l
       3: lstore_1
       4: ldc           #4                  // class org/apache/hadoop/hbase/errorhandling/ForeignExceptionListener
       6: invokestatic  #5                  // Method org/mockito/Mockito.mock:(Ljava/lang/Class;)Ljava/lang/Object;
       9: checkcast     #4                  // class org/apache/hadoop/hbase/errorhandling/ForeignExceptionListener
      12: astore_3
      13: new           #6                  // class org/apache/hadoop/hbase/errorhandling/TimeoutExceptionInjector
      16: dup
      17: aload_3
      18: ldc2_w        #15                 // long 1000000l
      21: invokespecial #7                  // Method org/apache/hadoop/hbase/errorhandling/TimeoutExceptionInjector."<init>":(Lorg/apache/hadoop/hbase/errorhandling/ForeignExceptionListener;J)V
      24: astore        4
      26: aload         4
      28: invokevirtual #8                  // Method org/apache/hadoop/hbase/errorhandling/TimeoutExceptionInjector.start:()V
      31: aload         4
      33: invokevirtual #9                  // Method org/apache/hadoop/hbase/errorhandling/TimeoutExceptionInjector.trigger:()V
      36: aload_3
      37: invokestatic  #17                 // Method org/mockito/Mockito.verify:(Ljava/lang/Object;)Ljava/lang/Object;
      40: checkcast     #4                  // class org/apache/hadoop/hbase/errorhandling/ForeignExceptionListener
      43: invokestatic  #12                 // Method org/mockito/Mockito.any:()Ljava/lang/Object;
      46: checkcast     #13                 // class org/apache/hadoop/hbase/errorhandling/ForeignException
      49: invokeinterface #14,  2           // InterfaceMethod org/apache/hadoop/hbase/errorhandling/ForeignExceptionListener.receive:(Lorg/apache/hadoop/hbase/errorhandling/ForeignException;)V
      54: return

  public void testStartAfterComplete() throws java.lang.InterruptedException;
    Code:
       0: ldc2_w        #18                 // long 10l
       3: lstore_1
       4: ldc           #4                  // class org/apache/hadoop/hbase/errorhandling/ForeignExceptionListener
       6: invokestatic  #5                  // Method org/mockito/Mockito.mock:(Ljava/lang/Class;)Ljava/lang/Object;
       9: checkcast     #4                  // class org/apache/hadoop/hbase/errorhandling/ForeignExceptionListener
      12: astore_3
      13: new           #6                  // class org/apache/hadoop/hbase/errorhandling/TimeoutExceptionInjector
      16: dup
      17: aload_3
      18: ldc2_w        #18                 // long 10l
      21: invokespecial #7                  // Method org/apache/hadoop/hbase/errorhandling/TimeoutExceptionInjector."<init>":(Lorg/apache/hadoop/hbase/errorhandling/ForeignExceptionListener;J)V
      24: astore        4
      26: aload         4
      28: invokevirtual #20                 // Method org/apache/hadoop/hbase/errorhandling/TimeoutExceptionInjector.complete:()V
      31: aload         4
      33: invokevirtual #8                  // Method org/apache/hadoop/hbase/errorhandling/TimeoutExceptionInjector.start:()V
      36: ldc           #21                 // String Timer should fail to start after complete.
      38: invokestatic  #22                 // Method org/junit/Assert.fail:(Ljava/lang/String;)V
      41: goto          77
      44: astore        5
      46: getstatic     #24                 // Field LOG:Lorg/slf4j/Logger;
      49: new           #25                 // class java/lang/StringBuilder
      52: dup
      53: invokespecial #26                 // Method java/lang/StringBuilder."<init>":()V
      56: ldc           #27                 // String Correctly failed timer:
      58: invokevirtual #28                 // Method java/lang/StringBuilder.append:(Ljava/lang/String;)Ljava/lang/StringBuilder;
      61: aload         5
      63: invokevirtual #29                 // Method java/lang/IllegalStateException.getMessage:()Ljava/lang/String;
      66: invokevirtual #28                 // Method java/lang/StringBuilder.append:(Ljava/lang/String;)Ljava/lang/StringBuilder;
      69: invokevirtual #30                 // Method java/lang/StringBuilder.toString:()Ljava/lang/String;
      72: invokeinterface #31,  2           // InterfaceMethod org/slf4j/Logger.debug:(Ljava/lang/String;)V
      77: ldc2_w        #32                 // long 11l
      80: invokestatic  #34                 // Method java/lang/Thread.sleep:(J)V
      83: iconst_1
      84: anewarray     #35                 // class java/lang/Object
      87: dup
      88: iconst_0
      89: aload_3
      90: aastore
      91: invokestatic  #36                 // Method org/mockito/Mockito.verifyZeroInteractions:([Ljava/lang/Object;)V
      94: return
    Exception table:
       from    to  target type
          31    41    44   Class java/lang/IllegalStateException

  public void testStartAfterTrigger() throws java.lang.InterruptedException;
    Code:
       0: ldc2_w        #18                 // long 10l
       3: lstore_1
       4: ldc           #4                  // class org/apache/hadoop/hbase/errorhandling/ForeignExceptionListener
       6: invokestatic  #5                  // Method org/mockito/Mockito.mock:(Ljava/lang/Class;)Ljava/lang/Object;
       9: checkcast     #4                  // class org/apache/hadoop/hbase/errorhandling/ForeignExceptionListener
      12: astore_3
      13: new           #6                  // class org/apache/hadoop/hbase/errorhandling/TimeoutExceptionInjector
      16: dup
      17: aload_3
      18: ldc2_w        #18                 // long 10l
      21: invokespecial #7                  // Method org/apache/hadoop/hbase/errorhandling/TimeoutExceptionInjector."<init>":(Lorg/apache/hadoop/hbase/errorhandling/ForeignExceptionListener;J)V
      24: astore        4
      26: aload         4
      28: invokevirtual #9                  // Method org/apache/hadoop/hbase/errorhandling/TimeoutExceptionInjector.trigger:()V
      31: aload         4
      33: invokevirtual #8                  // Method org/apache/hadoop/hbase/errorhandling/TimeoutExceptionInjector.start:()V
      36: ldc           #21                 // String Timer should fail to start after complete.
      38: invokestatic  #22                 // Method org/junit/Assert.fail:(Ljava/lang/String;)V
      41: goto          77
      44: astore        5
      46: getstatic     #24                 // Field LOG:Lorg/slf4j/Logger;
      49: new           #25                 // class java/lang/StringBuilder
      52: dup
      53: invokespecial #26                 // Method java/lang/StringBuilder."<init>":()V
      56: ldc           #27                 // String Correctly failed timer:
      58: invokevirtual #28                 // Method java/lang/StringBuilder.append:(Ljava/lang/String;)Ljava/lang/StringBuilder;
      61: aload         5
      63: invokevirtual #29                 // Method java/lang/IllegalStateException.getMessage:()Ljava/lang/String;
      66: invokevirtual #28                 // Method java/lang/StringBuilder.append:(Ljava/lang/String;)Ljava/lang/StringBuilder;
      69: invokevirtual #30                 // Method java/lang/StringBuilder.toString:()Ljava/lang/String;
      72: invokeinterface #31,  2           // InterfaceMethod org/slf4j/Logger.debug:(Ljava/lang/String;)V
      77: ldc2_w        #37                 // long 20l
      80: invokestatic  #34                 // Method java/lang/Thread.sleep:(J)V
      83: aload_3
      84: iconst_1
      85: invokestatic  #10                 // Method org/mockito/Mockito.times:(I)Lorg/mockito/verification/VerificationMode;
      88: invokestatic  #11                 // Method org/mockito/Mockito.verify:(Ljava/lang/Object;Lorg/mockito/verification/VerificationMode;)Ljava/lang/Object;
      91: checkcast     #4                  // class org/apache/hadoop/hbase/errorhandling/ForeignExceptionListener
      94: invokestatic  #12                 // Method org/mockito/Mockito.any:()Ljava/lang/Object;
      97: checkcast     #13                 // class org/apache/hadoop/hbase/errorhandling/ForeignException
     100: invokeinterface #14,  2           // InterfaceMethod org/apache/hadoop/hbase/errorhandling/ForeignExceptionListener.receive:(Lorg/apache/hadoop/hbase/errorhandling/ForeignException;)V
     105: iconst_1
     106: anewarray     #35                 // class java/lang/Object
     109: dup
     110: iconst_0
     111: aload_3
     112: aastore
     113: invokestatic  #39                 // Method org/mockito/Mockito.verifyNoMoreInteractions:([Ljava/lang/Object;)V
     116: return
    Exception table:
       from    to  target type
          31    41    44   Class java/lang/IllegalStateException

  static {};
    Code:
       0: ldc           #40                 // class org/apache/hadoop/hbase/errorhandling/TestTimeoutExceptionInjector
       2: invokestatic  #41                 // Method org/apache/hadoop/hbase/HBaseClassTestRule.forClass:(Ljava/lang/Class;)Lorg/apache/hadoop/hbase/HBaseClassTestRule;
       5: putstatic     #42                 // Field CLASS_RULE:Lorg/apache/hadoop/hbase/HBaseClassTestRule;
       8: ldc           #40                 // class org/apache/hadoop/hbase/errorhandling/TestTimeoutExceptionInjector
      10: invokestatic  #43                 // Method org/slf4j/LoggerFactory.getLogger:(Ljava/lang/Class;)Lorg/slf4j/Logger;
      13: putstatic     #24                 // Field LOG:Lorg/slf4j/Logger;
      16: return
}
