Compiled from "TestExpressionParser.java"
public class org.apache.hadoop.hbase.security.visibility.TestExpressionParser {
  public static final org.apache.hadoop.hbase.HBaseClassTestRule CLASS_RULE;

  public org.apache.hadoop.hbase.security.visibility.TestExpressionParser();
    Code:
       0: aload_0
       1: invokespecial #1                  // Method java/lang/Object."<init>":()V
       4: aload_0
       5: new           #2                  // class org/apache/hadoop/hbase/security/visibility/ExpressionParser
       8: dup
       9: invokespecial #3                  // Method org/apache/hadoop/hbase/security/visibility/ExpressionParser."<init>":()V
      12: putfield      #4                  // Field parser:Lorg/apache/hadoop/hbase/security/visibility/ExpressionParser;
      15: return

  public void testPositiveCases() throws java.lang.Exception;
    Code:
       0: aload_0
       1: getfield      #4                  // Field parser:Lorg/apache/hadoop/hbase/security/visibility/ExpressionParser;
       4: ldc           #5                  // String abc
       6: invokevirtual #6                  // Method org/apache/hadoop/hbase/security/visibility/ExpressionParser.parse:(Ljava/lang/String;)Lorg/apache/hadoop/hbase/security/visibility/expression/ExpressionNode;
       9: astore_1
      10: aload_1
      11: instanceof    #7                  // class org/apache/hadoop/hbase/security/visibility/expression/LeafExpressionNode
      14: invokestatic  #8                  // Method org/junit/Assert.assertTrue:(Z)V
      17: ldc           #5                  // String abc
      19: aload_1
      20: checkcast     #7                  // class org/apache/hadoop/hbase/security/visibility/expression/LeafExpressionNode
      23: invokevirtual #9                  // Method org/apache/hadoop/hbase/security/visibility/expression/LeafExpressionNode.getIdentifier:()Ljava/lang/String;
      26: invokestatic  #10                 // Method org/junit/Assert.assertEquals:(Ljava/lang/Object;Ljava/lang/Object;)V
      29: aload_0
      30: getfield      #4                  // Field parser:Lorg/apache/hadoop/hbase/security/visibility/ExpressionParser;
      33: ldc           #11                 // String a&b|c&d
      35: invokevirtual #6                  // Method org/apache/hadoop/hbase/security/visibility/ExpressionParser.parse:(Ljava/lang/String;)Lorg/apache/hadoop/hbase/security/visibility/expression/ExpressionNode;
      38: astore_1
      39: aload_1
      40: instanceof    #12                 // class org/apache/hadoop/hbase/security/visibility/expression/NonLeafExpressionNode
      43: invokestatic  #8                  // Method org/junit/Assert.assertTrue:(Z)V
      46: aload_1
      47: checkcast     #12                 // class org/apache/hadoop/hbase/security/visibility/expression/NonLeafExpressionNode
      50: astore_2
      51: getstatic     #13                 // Field org/apache/hadoop/hbase/security/visibility/expression/Operator.AND:Lorg/apache/hadoop/hbase/security/visibility/expression/Operator;
      54: aload_2
      55: invokevirtual #14                 // Method org/apache/hadoop/hbase/security/visibility/expression/NonLeafExpressionNode.getOperator:()Lorg/apache/hadoop/hbase/security/visibility/expression/Operator;
      58: invokestatic  #10                 // Method org/junit/Assert.assertEquals:(Ljava/lang/Object;Ljava/lang/Object;)V
      61: ldc2_w        #15                 // long 2l
      64: aload_2
      65: invokevirtual #17                 // Method org/apache/hadoop/hbase/security/visibility/expression/NonLeafExpressionNode.getChildExps:()Ljava/util/List;
      68: invokeinterface #18,  1           // InterfaceMethod java/util/List.size:()I
      73: i2l
      74: invokestatic  #19                 // Method org/junit/Assert.assertEquals:(JJ)V
      77: ldc           #20                 // String d
      79: aload_2
      80: invokevirtual #17                 // Method org/apache/hadoop/hbase/security/visibility/expression/NonLeafExpressionNode.getChildExps:()Ljava/util/List;
      83: iconst_1
      84: invokeinterface #21,  2           // InterfaceMethod java/util/List.get:(I)Ljava/lang/Object;
      89: checkcast     #7                  // class org/apache/hadoop/hbase/security/visibility/expression/LeafExpressionNode
      92: invokevirtual #9                  // Method org/apache/hadoop/hbase/security/visibility/expression/LeafExpressionNode.getIdentifier:()Ljava/lang/String;
      95: invokestatic  #10                 // Method org/junit/Assert.assertEquals:(Ljava/lang/Object;Ljava/lang/Object;)V
      98: aload_2
      99: invokevirtual #17                 // Method org/apache/hadoop/hbase/security/visibility/expression/NonLeafExpressionNode.getChildExps:()Ljava/util/List;
     102: iconst_0
     103: invokeinterface #21,  2           // InterfaceMethod java/util/List.get:(I)Ljava/lang/Object;
     108: instanceof    #12                 // class org/apache/hadoop/hbase/security/visibility/expression/NonLeafExpressionNode
     111: invokestatic  #8                  // Method org/junit/Assert.assertTrue:(Z)V
     114: aload_2
     115: invokevirtual #17                 // Method org/apache/hadoop/hbase/security/visibility/expression/NonLeafExpressionNode.getChildExps:()Ljava/util/List;
     118: iconst_0
     119: invokeinterface #21,  2           // InterfaceMethod java/util/List.get:(I)Ljava/lang/Object;
     124: checkcast     #12                 // class org/apache/hadoop/hbase/security/visibility/expression/NonLeafExpressionNode
     127: astore_2
     128: getstatic     #22                 // Field org/apache/hadoop/hbase/security/visibility/expression/Operator.OR:Lorg/apache/hadoop/hbase/security/visibility/expression/Operator;
     131: aload_2
     132: invokevirtual #14                 // Method org/apache/hadoop/hbase/security/visibility/expression/NonLeafExpressionNode.getOperator:()Lorg/apache/hadoop/hbase/security/visibility/expression/Operator;
     135: invokestatic  #10                 // Method org/junit/Assert.assertEquals:(Ljava/lang/Object;Ljava/lang/Object;)V
     138: ldc2_w        #15                 // long 2l
     141: aload_2
     142: invokevirtual #17                 // Method org/apache/hadoop/hbase/security/visibility/expression/NonLeafExpressionNode.getChildExps:()Ljava/util/List;
     145: invokeinterface #18,  1           // InterfaceMethod java/util/List.size:()I
     150: i2l
     151: invokestatic  #19                 // Method org/junit/Assert.assertEquals:(JJ)V
     154: ldc           #23                 // String c
     156: aload_2
     157: invokevirtual #17                 // Method org/apache/hadoop/hbase/security/visibility/expression/NonLeafExpressionNode.getChildExps:()Ljava/util/List;
     160: iconst_1
     161: invokeinterface #21,  2           // InterfaceMethod java/util/List.get:(I)Ljava/lang/Object;
     166: checkcast     #7                  // class org/apache/hadoop/hbase/security/visibility/expression/LeafExpressionNode
     169: invokevirtual #9                  // Method org/apache/hadoop/hbase/security/visibility/expression/LeafExpressionNode.getIdentifier:()Ljava/lang/String;
     172: invokestatic  #10                 // Method org/junit/Assert.assertEquals:(Ljava/lang/Object;Ljava/lang/Object;)V
     175: aload_2
     176: invokevirtual #17                 // Method org/apache/hadoop/hbase/security/visibility/expression/NonLeafExpressionNode.getChildExps:()Ljava/util/List;
     179: iconst_0
     180: invokeinterface #21,  2           // InterfaceMethod java/util/List.get:(I)Ljava/lang/Object;
     185: instanceof    #12                 // class org/apache/hadoop/hbase/security/visibility/expression/NonLeafExpressionNode
     188: invokestatic  #8                  // Method org/junit/Assert.assertTrue:(Z)V
     191: aload_2
     192: invokevirtual #17                 // Method org/apache/hadoop/hbase/security/visibility/expression/NonLeafExpressionNode.getChildExps:()Ljava/util/List;
     195: iconst_0
     196: invokeinterface #21,  2           // InterfaceMethod java/util/List.get:(I)Ljava/lang/Object;
     201: checkcast     #12                 // class org/apache/hadoop/hbase/security/visibility/expression/NonLeafExpressionNode
     204: astore_2
     205: getstatic     #13                 // Field org/apache/hadoop/hbase/security/visibility/expression/Operator.AND:Lorg/apache/hadoop/hbase/security/visibility/expression/Operator;
     208: aload_2
     209: invokevirtual #14                 // Method org/apache/hadoop/hbase/security/visibility/expression/NonLeafExpressionNode.getOperator:()Lorg/apache/hadoop/hbase/security/visibility/expression/Operator;
     212: invokestatic  #10                 // Method org/junit/Assert.assertEquals:(Ljava/lang/Object;Ljava/lang/Object;)V
     215: ldc2_w        #15                 // long 2l
     218: aload_2
     219: invokevirtual #17                 // Method org/apache/hadoop/hbase/security/visibility/expression/NonLeafExpressionNode.getChildExps:()Ljava/util/List;
     222: invokeinterface #18,  1           // InterfaceMethod java/util/List.size:()I
     227: i2l
     228: invokestatic  #19                 // Method org/junit/Assert.assertEquals:(JJ)V
     231: ldc           #24                 // String b
     233: aload_2
     234: invokevirtual #17                 // Method org/apache/hadoop/hbase/security/visibility/expression/NonLeafExpressionNode.getChildExps:()Ljava/util/List;
     237: iconst_1
     238: invokeinterface #21,  2           // InterfaceMethod java/util/List.get:(I)Ljava/lang/Object;
     243: checkcast     #7                  // class org/apache/hadoop/hbase/security/visibility/expression/LeafExpressionNode
     246: invokevirtual #9                  // Method org/apache/hadoop/hbase/security/visibility/expression/LeafExpressionNode.getIdentifier:()Ljava/lang/String;
     249: invokestatic  #10                 // Method org/junit/Assert.assertEquals:(Ljava/lang/Object;Ljava/lang/Object;)V
     252: ldc           #25                 // String a
     254: aload_2
     255: invokevirtual #17                 // Method org/apache/hadoop/hbase/security/visibility/expression/NonLeafExpressionNode.getChildExps:()Ljava/util/List;
     258: iconst_0
     259: invokeinterface #21,  2           // InterfaceMethod java/util/List.get:(I)Ljava/lang/Object;
     264: checkcast     #7                  // class org/apache/hadoop/hbase/security/visibility/expression/LeafExpressionNode
     267: invokevirtual #9                  // Method org/apache/hadoop/hbase/security/visibility/expression/LeafExpressionNode.getIdentifier:()Ljava/lang/String;
     270: invokestatic  #10                 // Method org/junit/Assert.assertEquals:(Ljava/lang/Object;Ljava/lang/Object;)V
     273: aload_0
     274: getfield      #4                  // Field parser:Lorg/apache/hadoop/hbase/security/visibility/ExpressionParser;
     277: ldc           #26                 // String (a)
     279: invokevirtual #6                  // Method org/apache/hadoop/hbase/security/visibility/ExpressionParser.parse:(Ljava/lang/String;)Lorg/apache/hadoop/hbase/security/visibility/expression/ExpressionNode;
     282: astore_1
     283: aload_1
     284: instanceof    #7                  // class org/apache/hadoop/hbase/security/visibility/expression/LeafExpressionNode
     287: invokestatic  #8                  // Method org/junit/Assert.assertTrue:(Z)V
     290: ldc           #25                 // String a
     292: aload_1
     293: checkcast     #7                  // class org/apache/hadoop/hbase/security/visibility/expression/LeafExpressionNode
     296: invokevirtual #9                  // Method org/apache/hadoop/hbase/security/visibility/expression/LeafExpressionNode.getIdentifier:()Ljava/lang/String;
     299: invokestatic  #10                 // Method org/junit/Assert.assertEquals:(Ljava/lang/Object;Ljava/lang/Object;)V
     302: aload_0
     303: getfield      #4                  // Field parser:Lorg/apache/hadoop/hbase/security/visibility/ExpressionParser;
     306: ldc           #27                 // String  ( a & b )
     308: invokevirtual #6                  // Method org/apache/hadoop/hbase/security/visibility/ExpressionParser.parse:(Ljava/lang/String;)Lorg/apache/hadoop/hbase/security/visibility/expression/ExpressionNode;
     311: astore_1
     312: aload_1
     313: instanceof    #12                 // class org/apache/hadoop/hbase/security/visibility/expression/NonLeafExpressionNode
     316: invokestatic  #8                  // Method org/junit/Assert.assertTrue:(Z)V
     319: aload_1
     320: checkcast     #12                 // class org/apache/hadoop/hbase/security/visibility/expression/NonLeafExpressionNode
     323: astore_2
     324: getstatic     #13                 // Field org/apache/hadoop/hbase/security/visibility/expression/Operator.AND:Lorg/apache/hadoop/hbase/security/visibility/expression/Operator;
     327: aload_2
     328: invokevirtual #14                 // Method org/apache/hadoop/hbase/security/visibility/expression/NonLeafExpressionNode.getOperator:()Lorg/apache/hadoop/hbase/security/visibility/expression/Operator;
     331: invokestatic  #10                 // Method org/junit/Assert.assertEquals:(Ljava/lang/Object;Ljava/lang/Object;)V
     334: ldc2_w        #15                 // long 2l
     337: aload_2
     338: invokevirtual #17                 // Method org/apache/hadoop/hbase/security/visibility/expression/NonLeafExpressionNode.getChildExps:()Ljava/util/List;
     341: invokeinterface #18,  1           // InterfaceMethod java/util/List.size:()I
     346: i2l
     347: invokestatic  #19                 // Method org/junit/Assert.assertEquals:(JJ)V
     350: ldc           #25                 // String a
     352: aload_2
     353: invokevirtual #17                 // Method org/apache/hadoop/hbase/security/visibility/expression/NonLeafExpressionNode.getChildExps:()Ljava/util/List;
     356: iconst_0
     357: invokeinterface #21,  2           // InterfaceMethod java/util/List.get:(I)Ljava/lang/Object;
     362: checkcast     #7                  // class org/apache/hadoop/hbase/security/visibility/expression/LeafExpressionNode
     365: invokevirtual #9                  // Method org/apache/hadoop/hbase/security/visibility/expression/LeafExpressionNode.getIdentifier:()Ljava/lang/String;
     368: invokestatic  #10                 // Method org/junit/Assert.assertEquals:(Ljava/lang/Object;Ljava/lang/Object;)V
     371: ldc           #24                 // String b
     373: aload_2
     374: invokevirtual #17                 // Method org/apache/hadoop/hbase/security/visibility/expression/NonLeafExpressionNode.getChildExps:()Ljava/util/List;
     377: iconst_1
     378: invokeinterface #21,  2           // InterfaceMethod java/util/List.get:(I)Ljava/lang/Object;
     383: checkcast     #7                  // class org/apache/hadoop/hbase/security/visibility/expression/LeafExpressionNode
     386: invokevirtual #9                  // Method org/apache/hadoop/hbase/security/visibility/expression/LeafExpressionNode.getIdentifier:()Ljava/lang/String;
     389: invokestatic  #10                 // Method org/junit/Assert.assertEquals:(Ljava/lang/Object;Ljava/lang/Object;)V
     392: aload_0
     393: getfield      #4                  // Field parser:Lorg/apache/hadoop/hbase/security/visibility/ExpressionParser;
     396: ldc           #28                 // String ((((a&b))))
     398: invokevirtual #6                  // Method org/apache/hadoop/hbase/security/visibility/ExpressionParser.parse:(Ljava/lang/String;)Lorg/apache/hadoop/hbase/security/visibility/expression/ExpressionNode;
     401: astore_1
     402: aload_1
     403: instanceof    #12                 // class org/apache/hadoop/hbase/security/visibility/expression/NonLeafExpressionNode
     406: invokestatic  #8                  // Method org/junit/Assert.assertTrue:(Z)V
     409: aload_1
     410: checkcast     #12                 // class org/apache/hadoop/hbase/security/visibility/expression/NonLeafExpressionNode
     413: astore_2
     414: getstatic     #13                 // Field org/apache/hadoop/hbase/security/visibility/expression/Operator.AND:Lorg/apache/hadoop/hbase/security/visibility/expression/Operator;
     417: aload_2
     418: invokevirtual #14                 // Method org/apache/hadoop/hbase/security/visibility/expression/NonLeafExpressionNode.getOperator:()Lorg/apache/hadoop/hbase/security/visibility/expression/Operator;
     421: invokestatic  #10                 // Method org/junit/Assert.assertEquals:(Ljava/lang/Object;Ljava/lang/Object;)V
     424: ldc2_w        #15                 // long 2l
     427: aload_2
     428: invokevirtual #17                 // Method org/apache/hadoop/hbase/security/visibility/expression/NonLeafExpressionNode.getChildExps:()Ljava/util/List;
     431: invokeinterface #18,  1           // InterfaceMethod java/util/List.size:()I
     436: i2l
     437: invokestatic  #19                 // Method org/junit/Assert.assertEquals:(JJ)V
     440: ldc           #25                 // String a
     442: aload_2
     443: invokevirtual #17                 // Method org/apache/hadoop/hbase/security/visibility/expression/NonLeafExpressionNode.getChildExps:()Ljava/util/List;
     446: iconst_0
     447: invokeinterface #21,  2           // InterfaceMethod java/util/List.get:(I)Ljava/lang/Object;
     452: checkcast     #7                  // class org/apache/hadoop/hbase/security/visibility/expression/LeafExpressionNode
     455: invokevirtual #9                  // Method org/apache/hadoop/hbase/security/visibility/expression/LeafExpressionNode.getIdentifier:()Ljava/lang/String;
     458: invokestatic  #10                 // Method org/junit/Assert.assertEquals:(Ljava/lang/Object;Ljava/lang/Object;)V
     461: ldc           #24                 // String b
     463: aload_2
     464: invokevirtual #17                 // Method org/apache/hadoop/hbase/security/visibility/expression/NonLeafExpressionNode.getChildExps:()Ljava/util/List;
     467: iconst_1
     468: invokeinterface #21,  2           // InterfaceMethod java/util/List.get:(I)Ljava/lang/Object;
     473: checkcast     #7                  // class org/apache/hadoop/hbase/security/visibility/expression/LeafExpressionNode
     476: invokevirtual #9                  // Method org/apache/hadoop/hbase/security/visibility/expression/LeafExpressionNode.getIdentifier:()Ljava/lang/String;
     479: invokestatic  #10                 // Method org/junit/Assert.assertEquals:(Ljava/lang/Object;Ljava/lang/Object;)V
     482: aload_0
     483: getfield      #4                  // Field parser:Lorg/apache/hadoop/hbase/security/visibility/ExpressionParser;
     486: ldc           #29                 // String ( a | b ) & (cc|def)
     488: invokevirtual #6                  // Method org/apache/hadoop/hbase/security/visibility/ExpressionParser.parse:(Ljava/lang/String;)Lorg/apache/hadoop/hbase/security/visibility/expression/ExpressionNode;
     491: astore_1
     492: aload_1
     493: instanceof    #12                 // class org/apache/hadoop/hbase/security/visibility/expression/NonLeafExpressionNode
     496: invokestatic  #8                  // Method org/junit/Assert.assertTrue:(Z)V
     499: aload_1
     500: checkcast     #12                 // class org/apache/hadoop/hbase/security/visibility/expression/NonLeafExpressionNode
     503: astore_2
     504: getstatic     #13                 // Field org/apache/hadoop/hbase/security/visibility/expression/Operator.AND:Lorg/apache/hadoop/hbase/security/visibility/expression/Operator;
     507: aload_2
     508: invokevirtual #14                 // Method org/apache/hadoop/hbase/security/visibility/expression/NonLeafExpressionNode.getOperator:()Lorg/apache/hadoop/hbase/security/visibility/expression/Operator;
     511: invokestatic  #10                 // Method org/junit/Assert.assertEquals:(Ljava/lang/Object;Ljava/lang/Object;)V
     514: ldc2_w        #15                 // long 2l
     517: aload_2
     518: invokevirtual #17                 // Method org/apache/hadoop/hbase/security/visibility/expression/NonLeafExpressionNode.getChildExps:()Ljava/util/List;
     521: invokeinterface #18,  1           // InterfaceMethod java/util/List.size:()I
     526: i2l
     527: invokestatic  #19                 // Method org/junit/Assert.assertEquals:(JJ)V
     530: aload_2
     531: invokevirtual #17                 // Method org/apache/hadoop/hbase/security/visibility/expression/NonLeafExpressionNode.getChildExps:()Ljava/util/List;
     534: iconst_0
     535: invokeinterface #21,  2           // InterfaceMethod java/util/List.get:(I)Ljava/lang/Object;
     540: instanceof    #12                 // class org/apache/hadoop/hbase/security/visibility/expression/NonLeafExpressionNode
     543: invokestatic  #8                  // Method org/junit/Assert.assertTrue:(Z)V
     546: aload_2
     547: invokevirtual #17                 // Method org/apache/hadoop/hbase/security/visibility/expression/NonLeafExpressionNode.getChildExps:()Ljava/util/List;
     550: iconst_1
     551: invokeinterface #21,  2           // InterfaceMethod java/util/List.get:(I)Ljava/lang/Object;
     556: instanceof    #12                 // class org/apache/hadoop/hbase/security/visibility/expression/NonLeafExpressionNode
     559: invokestatic  #8                  // Method org/junit/Assert.assertTrue:(Z)V
     562: aload_2
     563: invokevirtual #17                 // Method org/apache/hadoop/hbase/security/visibility/expression/NonLeafExpressionNode.getChildExps:()Ljava/util/List;
     566: iconst_0
     567: invokeinterface #21,  2           // InterfaceMethod java/util/List.get:(I)Ljava/lang/Object;
     572: checkcast     #12                 // class org/apache/hadoop/hbase/security/visibility/expression/NonLeafExpressionNode
     575: astore_3
     576: aload_2
     577: invokevirtual #17                 // Method org/apache/hadoop/hbase/security/visibility/expression/NonLeafExpressionNode.getChildExps:()Ljava/util/List;
     580: iconst_1
     581: invokeinterface #21,  2           // InterfaceMethod java/util/List.get:(I)Ljava/lang/Object;
     586: checkcast     #12                 // class org/apache/hadoop/hbase/security/visibility/expression/NonLeafExpressionNode
     589: astore        4
     591: getstatic     #22                 // Field org/apache/hadoop/hbase/security/visibility/expression/Operator.OR:Lorg/apache/hadoop/hbase/security/visibility/expression/Operator;
     594: aload_3
     595: invokevirtual #14                 // Method org/apache/hadoop/hbase/security/visibility/expression/NonLeafExpressionNode.getOperator:()Lorg/apache/hadoop/hbase/security/visibility/expression/Operator;
     598: invokestatic  #10                 // Method org/junit/Assert.assertEquals:(Ljava/lang/Object;Ljava/lang/Object;)V
     601: ldc2_w        #15                 // long 2l
     604: aload_3
     605: invokevirtual #17                 // Method org/apache/hadoop/hbase/security/visibility/expression/NonLeafExpressionNode.getChildExps:()Ljava/util/List;
     608: invokeinterface #18,  1           // InterfaceMethod java/util/List.size:()I
     613: i2l
     614: invokestatic  #19                 // Method org/junit/Assert.assertEquals:(JJ)V
     617: ldc           #25                 // String a
     619: aload_3
     620: invokevirtual #17                 // Method org/apache/hadoop/hbase/security/visibility/expression/NonLeafExpressionNode.getChildExps:()Ljava/util/List;
     623: iconst_0
     624: invokeinterface #21,  2           // InterfaceMethod java/util/List.get:(I)Ljava/lang/Object;
     629: checkcast     #7                  // class org/apache/hadoop/hbase/security/visibility/expression/LeafExpressionNode
     632: invokevirtual #9                  // Method org/apache/hadoop/hbase/security/visibility/expression/LeafExpressionNode.getIdentifier:()Ljava/lang/String;
     635: invokestatic  #10                 // Method org/junit/Assert.assertEquals:(Ljava/lang/Object;Ljava/lang/Object;)V
     638: ldc           #24                 // String b
     640: aload_3
     641: invokevirtual #17                 // Method org/apache/hadoop/hbase/security/visibility/expression/NonLeafExpressionNode.getChildExps:()Ljava/util/List;
     644: iconst_1
     645: invokeinterface #21,  2           // InterfaceMethod java/util/List.get:(I)Ljava/lang/Object;
     650: checkcast     #7                  // class org/apache/hadoop/hbase/security/visibility/expression/LeafExpressionNode
     653: invokevirtual #9                  // Method org/apache/hadoop/hbase/security/visibility/expression/LeafExpressionNode.getIdentifier:()Ljava/lang/String;
     656: invokestatic  #10                 // Method org/junit/Assert.assertEquals:(Ljava/lang/Object;Ljava/lang/Object;)V
     659: getstatic     #22                 // Field org/apache/hadoop/hbase/security/visibility/expression/Operator.OR:Lorg/apache/hadoop/hbase/security/visibility/expression/Operator;
     662: aload         4
     664: invokevirtual #14                 // Method org/apache/hadoop/hbase/security/visibility/expression/NonLeafExpressionNode.getOperator:()Lorg/apache/hadoop/hbase/security/visibility/expression/Operator;
     667: invokestatic  #10                 // Method org/junit/Assert.assertEquals:(Ljava/lang/Object;Ljava/lang/Object;)V
     670: ldc2_w        #15                 // long 2l
     673: aload         4
     675: invokevirtual #17                 // Method org/apache/hadoop/hbase/security/visibility/expression/NonLeafExpressionNode.getChildExps:()Ljava/util/List;
     678: invokeinterface #18,  1           // InterfaceMethod java/util/List.size:()I
     683: i2l
     684: invokestatic  #19                 // Method org/junit/Assert.assertEquals:(JJ)V
     687: ldc           #30                 // String cc
     689: aload         4
     691: invokevirtual #17                 // Method org/apache/hadoop/hbase/security/visibility/expression/NonLeafExpressionNode.getChildExps:()Ljava/util/List;
     694: iconst_0
     695: invokeinterface #21,  2           // InterfaceMethod java/util/List.get:(I)Ljava/lang/Object;
     700: checkcast     #7                  // class org/apache/hadoop/hbase/security/visibility/expression/LeafExpressionNode
     703: invokevirtual #9                  // Method org/apache/hadoop/hbase/security/visibility/expression/LeafExpressionNode.getIdentifier:()Ljava/lang/String;
     706: invokestatic  #10                 // Method org/junit/Assert.assertEquals:(Ljava/lang/Object;Ljava/lang/Object;)V
     709: ldc           #31                 // String def
     711: aload         4
     713: invokevirtual #17                 // Method org/apache/hadoop/hbase/security/visibility/expression/NonLeafExpressionNode.getChildExps:()Ljava/util/List;
     716: iconst_1
     717: invokeinterface #21,  2           // InterfaceMethod java/util/List.get:(I)Ljava/lang/Object;
     722: checkcast     #7                  // class org/apache/hadoop/hbase/security/visibility/expression/LeafExpressionNode
     725: invokevirtual #9                  // Method org/apache/hadoop/hbase/security/visibility/expression/LeafExpressionNode.getIdentifier:()Ljava/lang/String;
     728: invokestatic  #10                 // Method org/junit/Assert.assertEquals:(Ljava/lang/Object;Ljava/lang/Object;)V
     731: aload_0
     732: getfield      #4                  // Field parser:Lorg/apache/hadoop/hbase/security/visibility/ExpressionParser;
     735: ldc           #32                 // String a&(cc|de)
     737: invokevirtual #6                  // Method org/apache/hadoop/hbase/security/visibility/ExpressionParser.parse:(Ljava/lang/String;)Lorg/apache/hadoop/hbase/security/visibility/expression/ExpressionNode;
     740: astore_1
     741: aload_1
     742: instanceof    #12                 // class org/apache/hadoop/hbase/security/visibility/expression/NonLeafExpressionNode
     745: invokestatic  #8                  // Method org/junit/Assert.assertTrue:(Z)V
     748: aload_1
     749: checkcast     #12                 // class org/apache/hadoop/hbase/security/visibility/expression/NonLeafExpressionNode
     752: astore_2
     753: getstatic     #13                 // Field org/apache/hadoop/hbase/security/visibility/expression/Operator.AND:Lorg/apache/hadoop/hbase/security/visibility/expression/Operator;
     756: aload_2
     757: invokevirtual #14                 // Method org/apache/hadoop/hbase/security/visibility/expression/NonLeafExpressionNode.getOperator:()Lorg/apache/hadoop/hbase/security/visibility/expression/Operator;
     760: invokestatic  #10                 // Method org/junit/Assert.assertEquals:(Ljava/lang/Object;Ljava/lang/Object;)V
     763: ldc2_w        #15                 // long 2l
     766: aload_2
     767: invokevirtual #17                 // Method org/apache/hadoop/hbase/security/visibility/expression/NonLeafExpressionNode.getChildExps:()Ljava/util/List;
     770: invokeinterface #18,  1           // InterfaceMethod java/util/List.size:()I
     775: i2l
     776: invokestatic  #19                 // Method org/junit/Assert.assertEquals:(JJ)V
     779: ldc           #25                 // String a
     781: aload_2
     782: invokevirtual #17                 // Method org/apache/hadoop/hbase/security/visibility/expression/NonLeafExpressionNode.getChildExps:()Ljava/util/List;
     785: iconst_0
     786: invokeinterface #21,  2           // InterfaceMethod java/util/List.get:(I)Ljava/lang/Object;
     791: checkcast     #7                  // class org/apache/hadoop/hbase/security/visibility/expression/LeafExpressionNode
     794: invokevirtual #9                  // Method org/apache/hadoop/hbase/security/visibility/expression/LeafExpressionNode.getIdentifier:()Ljava/lang/String;
     797: invokestatic  #10                 // Method org/junit/Assert.assertEquals:(Ljava/lang/Object;Ljava/lang/Object;)V
     800: aload_2
     801: invokevirtual #17                 // Method org/apache/hadoop/hbase/security/visibility/expression/NonLeafExpressionNode.getChildExps:()Ljava/util/List;
     804: iconst_1
     805: invokeinterface #21,  2           // InterfaceMethod java/util/List.get:(I)Ljava/lang/Object;
     810: instanceof    #12                 // class org/apache/hadoop/hbase/security/visibility/expression/NonLeafExpressionNode
     813: invokestatic  #8                  // Method org/junit/Assert.assertTrue:(Z)V
     816: aload_2
     817: invokevirtual #17                 // Method org/apache/hadoop/hbase/security/visibility/expression/NonLeafExpressionNode.getChildExps:()Ljava/util/List;
     820: iconst_1
     821: invokeinterface #21,  2           // InterfaceMethod java/util/List.get:(I)Ljava/lang/Object;
     826: checkcast     #12                 // class org/apache/hadoop/hbase/security/visibility/expression/NonLeafExpressionNode
     829: astore_2
     830: getstatic     #22                 // Field org/apache/hadoop/hbase/security/visibility/expression/Operator.OR:Lorg/apache/hadoop/hbase/security/visibility/expression/Operator;
     833: aload_2
     834: invokevirtual #14                 // Method org/apache/hadoop/hbase/security/visibility/expression/NonLeafExpressionNode.getOperator:()Lorg/apache/hadoop/hbase/security/visibility/expression/Operator;
     837: invokestatic  #10                 // Method org/junit/Assert.assertEquals:(Ljava/lang/Object;Ljava/lang/Object;)V
     840: ldc2_w        #15                 // long 2l
     843: aload_2
     844: invokevirtual #17                 // Method org/apache/hadoop/hbase/security/visibility/expression/NonLeafExpressionNode.getChildExps:()Ljava/util/List;
     847: invokeinterface #18,  1           // InterfaceMethod java/util/List.size:()I
     852: i2l
     853: invokestatic  #19                 // Method org/junit/Assert.assertEquals:(JJ)V
     856: ldc           #30                 // String cc
     858: aload_2
     859: invokevirtual #17                 // Method org/apache/hadoop/hbase/security/visibility/expression/NonLeafExpressionNode.getChildExps:()Ljava/util/List;
     862: iconst_0
     863: invokeinterface #21,  2           // InterfaceMethod java/util/List.get:(I)Ljava/lang/Object;
     868: checkcast     #7                  // class org/apache/hadoop/hbase/security/visibility/expression/LeafExpressionNode
     871: invokevirtual #9                  // Method org/apache/hadoop/hbase/security/visibility/expression/LeafExpressionNode.getIdentifier:()Ljava/lang/String;
     874: invokestatic  #10                 // Method org/junit/Assert.assertEquals:(Ljava/lang/Object;Ljava/lang/Object;)V
     877: ldc           #33                 // String de
     879: aload_2
     880: invokevirtual #17                 // Method org/apache/hadoop/hbase/security/visibility/expression/NonLeafExpressionNode.getChildExps:()Ljava/util/List;
     883: iconst_1
     884: invokeinterface #21,  2           // InterfaceMethod java/util/List.get:(I)Ljava/lang/Object;
     889: checkcast     #7                  // class org/apache/hadoop/hbase/security/visibility/expression/LeafExpressionNode
     892: invokevirtual #9                  // Method org/apache/hadoop/hbase/security/visibility/expression/LeafExpressionNode.getIdentifier:()Ljava/lang/String;
     895: invokestatic  #10                 // Method org/junit/Assert.assertEquals:(Ljava/lang/Object;Ljava/lang/Object;)V
     898: aload_0
     899: getfield      #4                  // Field parser:Lorg/apache/hadoop/hbase/security/visibility/ExpressionParser;
     902: ldc           #34                 // String (a&b)|c
     904: invokevirtual #6                  // Method org/apache/hadoop/hbase/security/visibility/ExpressionParser.parse:(Ljava/lang/String;)Lorg/apache/hadoop/hbase/security/visibility/expression/ExpressionNode;
     907: astore_1
     908: aload_1
     909: instanceof    #12                 // class org/apache/hadoop/hbase/security/visibility/expression/NonLeafExpressionNode
     912: invokestatic  #8                  // Method org/junit/Assert.assertTrue:(Z)V
     915: aload_1
     916: checkcast     #12                 // class org/apache/hadoop/hbase/security/visibility/expression/NonLeafExpressionNode
     919: astore_2
     920: getstatic     #22                 // Field org/apache/hadoop/hbase/security/visibility/expression/Operator.OR:Lorg/apache/hadoop/hbase/security/visibility/expression/Operator;
     923: aload_2
     924: invokevirtual #14                 // Method org/apache/hadoop/hbase/security/visibility/expression/NonLeafExpressionNode.getOperator:()Lorg/apache/hadoop/hbase/security/visibility/expression/Operator;
     927: invokestatic  #10                 // Method org/junit/Assert.assertEquals:(Ljava/lang/Object;Ljava/lang/Object;)V
     930: ldc2_w        #15                 // long 2l
     933: aload_2
     934: invokevirtual #17                 // Method org/apache/hadoop/hbase/security/visibility/expression/NonLeafExpressionNode.getChildExps:()Ljava/util/List;
     937: invokeinterface #18,  1           // InterfaceMethod java/util/List.size:()I
     942: i2l
     943: invokestatic  #19                 // Method org/junit/Assert.assertEquals:(JJ)V
     946: ldc           #23                 // String c
     948: aload_2
     949: invokevirtual #17                 // Method org/apache/hadoop/hbase/security/visibility/expression/NonLeafExpressionNode.getChildExps:()Ljava/util/List;
     952: iconst_1
     953: invokeinterface #21,  2           // InterfaceMethod java/util/List.get:(I)Ljava/lang/Object;
     958: checkcast     #7                  // class org/apache/hadoop/hbase/security/visibility/expression/LeafExpressionNode
     961: invokevirtual #9                  // Method org/apache/hadoop/hbase/security/visibility/expression/LeafExpressionNode.getIdentifier:()Ljava/lang/String;
     964: invokestatic  #10                 // Method org/junit/Assert.assertEquals:(Ljava/lang/Object;Ljava/lang/Object;)V
     967: aload_2
     968: invokevirtual #17                 // Method org/apache/hadoop/hbase/security/visibility/expression/NonLeafExpressionNode.getChildExps:()Ljava/util/List;
     971: iconst_0
     972: invokeinterface #21,  2           // InterfaceMethod java/util/List.get:(I)Ljava/lang/Object;
     977: instanceof    #12                 // class org/apache/hadoop/hbase/security/visibility/expression/NonLeafExpressionNode
     980: invokestatic  #8                  // Method org/junit/Assert.assertTrue:(Z)V
     983: aload_2
     984: invokevirtual #17                 // Method org/apache/hadoop/hbase/security/visibility/expression/NonLeafExpressionNode.getChildExps:()Ljava/util/List;
     987: iconst_0
     988: invokeinterface #21,  2           // InterfaceMethod java/util/List.get:(I)Ljava/lang/Object;
     993: checkcast     #12                 // class org/apache/hadoop/hbase/security/visibility/expression/NonLeafExpressionNode
     996: astore_2
     997: getstatic     #13                 // Field org/apache/hadoop/hbase/security/visibility/expression/Operator.AND:Lorg/apache/hadoop/hbase/security/visibility/expression/Operator;
    1000: aload_2
    1001: invokevirtual #14                 // Method org/apache/hadoop/hbase/security/visibility/expression/NonLeafExpressionNode.getOperator:()Lorg/apache/hadoop/hbase/security/visibility/expression/Operator;
    1004: invokestatic  #10                 // Method org/junit/Assert.assertEquals:(Ljava/lang/Object;Ljava/lang/Object;)V
    1007: ldc2_w        #15                 // long 2l
    1010: aload_2
    1011: invokevirtual #17                 // Method org/apache/hadoop/hbase/security/visibility/expression/NonLeafExpressionNode.getChildExps:()Ljava/util/List;
    1014: invokeinterface #18,  1           // InterfaceMethod java/util/List.size:()I
    1019: i2l
    1020: invokestatic  #19                 // Method org/junit/Assert.assertEquals:(JJ)V
    1023: ldc           #25                 // String a
    1025: aload_2
    1026: invokevirtual #17                 // Method org/apache/hadoop/hbase/security/visibility/expression/NonLeafExpressionNode.getChildExps:()Ljava/util/List;
    1029: iconst_0
    1030: invokeinterface #21,  2           // InterfaceMethod java/util/List.get:(I)Ljava/lang/Object;
    1035: checkcast     #7                  // class org/apache/hadoop/hbase/security/visibility/expression/LeafExpressionNode
    1038: invokevirtual #9                  // Method org/apache/hadoop/hbase/security/visibility/expression/LeafExpressionNode.getIdentifier:()Ljava/lang/String;
    1041: invokestatic  #10                 // Method org/junit/Assert.assertEquals:(Ljava/lang/Object;Ljava/lang/Object;)V
    1044: ldc           #24                 // String b
    1046: aload_2
    1047: invokevirtual #17                 // Method org/apache/hadoop/hbase/security/visibility/expression/NonLeafExpressionNode.getChildExps:()Ljava/util/List;
    1050: iconst_1
    1051: invokeinterface #21,  2           // InterfaceMethod java/util/List.get:(I)Ljava/lang/Object;
    1056: checkcast     #7                  // class org/apache/hadoop/hbase/security/visibility/expression/LeafExpressionNode
    1059: invokevirtual #9                  // Method org/apache/hadoop/hbase/security/visibility/expression/LeafExpressionNode.getIdentifier:()Ljava/lang/String;
    1062: invokestatic  #10                 // Method org/junit/Assert.assertEquals:(Ljava/lang/Object;Ljava/lang/Object;)V
    1065: aload_0
    1066: getfield      #4                  // Field parser:Lorg/apache/hadoop/hbase/security/visibility/ExpressionParser;
    1069: ldc           #35                 // String (a&b&c)|d
    1071: invokevirtual #6                  // Method org/apache/hadoop/hbase/security/visibility/ExpressionParser.parse:(Ljava/lang/String;)Lorg/apache/hadoop/hbase/security/visibility/expression/ExpressionNode;
    1074: astore_1
    1075: aload_1
    1076: instanceof    #12                 // class org/apache/hadoop/hbase/security/visibility/expression/NonLeafExpressionNode
    1079: invokestatic  #8                  // Method org/junit/Assert.assertTrue:(Z)V
    1082: aload_1
    1083: checkcast     #12                 // class org/apache/hadoop/hbase/security/visibility/expression/NonLeafExpressionNode
    1086: astore_2
    1087: getstatic     #22                 // Field org/apache/hadoop/hbase/security/visibility/expression/Operator.OR:Lorg/apache/hadoop/hbase/security/visibility/expression/Operator;
    1090: aload_2
    1091: invokevirtual #14                 // Method org/apache/hadoop/hbase/security/visibility/expression/NonLeafExpressionNode.getOperator:()Lorg/apache/hadoop/hbase/security/visibility/expression/Operator;
    1094: invokestatic  #10                 // Method org/junit/Assert.assertEquals:(Ljava/lang/Object;Ljava/lang/Object;)V
    1097: ldc2_w        #15                 // long 2l
    1100: aload_2
    1101: invokevirtual #17                 // Method org/apache/hadoop/hbase/security/visibility/expression/NonLeafExpressionNode.getChildExps:()Ljava/util/List;
    1104: invokeinterface #18,  1           // InterfaceMethod java/util/List.size:()I
    1109: i2l
    1110: invokestatic  #19                 // Method org/junit/Assert.assertEquals:(JJ)V
    1113: ldc           #20                 // String d
    1115: aload_2
    1116: invokevirtual #17                 // Method org/apache/hadoop/hbase/security/visibility/expression/NonLeafExpressionNode.getChildExps:()Ljava/util/List;
    1119: iconst_1
    1120: invokeinterface #21,  2           // InterfaceMethod java/util/List.get:(I)Ljava/lang/Object;
    1125: checkcast     #7                  // class org/apache/hadoop/hbase/security/visibility/expression/LeafExpressionNode
    1128: invokevirtual #9                  // Method org/apache/hadoop/hbase/security/visibility/expression/LeafExpressionNode.getIdentifier:()Ljava/lang/String;
    1131: invokestatic  #10                 // Method org/junit/Assert.assertEquals:(Ljava/lang/Object;Ljava/lang/Object;)V
    1134: aload_2
    1135: invokevirtual #17                 // Method org/apache/hadoop/hbase/security/visibility/expression/NonLeafExpressionNode.getChildExps:()Ljava/util/List;
    1138: iconst_0
    1139: invokeinterface #21,  2           // InterfaceMethod java/util/List.get:(I)Ljava/lang/Object;
    1144: instanceof    #12                 // class org/apache/hadoop/hbase/security/visibility/expression/NonLeafExpressionNode
    1147: invokestatic  #8                  // Method org/junit/Assert.assertTrue:(Z)V
    1150: aload_2
    1151: invokevirtual #17                 // Method org/apache/hadoop/hbase/security/visibility/expression/NonLeafExpressionNode.getChildExps:()Ljava/util/List;
    1154: iconst_0
    1155: invokeinterface #21,  2           // InterfaceMethod java/util/List.get:(I)Ljava/lang/Object;
    1160: checkcast     #12                 // class org/apache/hadoop/hbase/security/visibility/expression/NonLeafExpressionNode
    1163: astore_2
    1164: getstatic     #13                 // Field org/apache/hadoop/hbase/security/visibility/expression/Operator.AND:Lorg/apache/hadoop/hbase/security/visibility/expression/Operator;
    1167: aload_2
    1168: invokevirtual #14                 // Method org/apache/hadoop/hbase/security/visibility/expression/NonLeafExpressionNode.getOperator:()Lorg/apache/hadoop/hbase/security/visibility/expression/Operator;
    1171: invokestatic  #10                 // Method org/junit/Assert.assertEquals:(Ljava/lang/Object;Ljava/lang/Object;)V
    1174: ldc2_w        #15                 // long 2l
    1177: aload_2
    1178: invokevirtual #17                 // Method org/apache/hadoop/hbase/security/visibility/expression/NonLeafExpressionNode.getChildExps:()Ljava/util/List;
    1181: invokeinterface #18,  1           // InterfaceMethod java/util/List.size:()I
    1186: i2l
    1187: invokestatic  #19                 // Method org/junit/Assert.assertEquals:(JJ)V
    1190: ldc           #23                 // String c
    1192: aload_2
    1193: invokevirtual #17                 // Method org/apache/hadoop/hbase/security/visibility/expression/NonLeafExpressionNode.getChildExps:()Ljava/util/List;
    1196: iconst_1
    1197: invokeinterface #21,  2           // InterfaceMethod java/util/List.get:(I)Ljava/lang/Object;
    1202: checkcast     #7                  // class org/apache/hadoop/hbase/security/visibility/expression/LeafExpressionNode
    1205: invokevirtual #9                  // Method org/apache/hadoop/hbase/security/visibility/expression/LeafExpressionNode.getIdentifier:()Ljava/lang/String;
    1208: invokestatic  #10                 // Method org/junit/Assert.assertEquals:(Ljava/lang/Object;Ljava/lang/Object;)V
    1211: aload_2
    1212: invokevirtual #17                 // Method org/apache/hadoop/hbase/security/visibility/expression/NonLeafExpressionNode.getChildExps:()Ljava/util/List;
    1215: iconst_0
    1216: invokeinterface #21,  2           // InterfaceMethod java/util/List.get:(I)Ljava/lang/Object;
    1221: instanceof    #12                 // class org/apache/hadoop/hbase/security/visibility/expression/NonLeafExpressionNode
    1224: invokestatic  #8                  // Method org/junit/Assert.assertTrue:(Z)V
    1227: aload_2
    1228: invokevirtual #17                 // Method org/apache/hadoop/hbase/security/visibility/expression/NonLeafExpressionNode.getChildExps:()Ljava/util/List;
    1231: iconst_0
    1232: invokeinterface #21,  2           // InterfaceMethod java/util/List.get:(I)Ljava/lang/Object;
    1237: checkcast     #12                 // class org/apache/hadoop/hbase/security/visibility/expression/NonLeafExpressionNode
    1240: astore_2
    1241: getstatic     #13                 // Field org/apache/hadoop/hbase/security/visibility/expression/Operator.AND:Lorg/apache/hadoop/hbase/security/visibility/expression/Operator;
    1244: aload_2
    1245: invokevirtual #14                 // Method org/apache/hadoop/hbase/security/visibility/expression/NonLeafExpressionNode.getOperator:()Lorg/apache/hadoop/hbase/security/visibility/expression/Operator;
    1248: invokestatic  #10                 // Method org/junit/Assert.assertEquals:(Ljava/lang/Object;Ljava/lang/Object;)V
    1251: ldc2_w        #15                 // long 2l
    1254: aload_2
    1255: invokevirtual #17                 // Method org/apache/hadoop/hbase/security/visibility/expression/NonLeafExpressionNode.getChildExps:()Ljava/util/List;
    1258: invokeinterface #18,  1           // InterfaceMethod java/util/List.size:()I
    1263: i2l
    1264: invokestatic  #19                 // Method org/junit/Assert.assertEquals:(JJ)V
    1267: ldc           #24                 // String b
    1269: aload_2
    1270: invokevirtual #17                 // Method org/apache/hadoop/hbase/security/visibility/expression/NonLeafExpressionNode.getChildExps:()Ljava/util/List;
    1273: iconst_1
    1274: invokeinterface #21,  2           // InterfaceMethod java/util/List.get:(I)Ljava/lang/Object;
    1279: checkcast     #7                  // class org/apache/hadoop/hbase/security/visibility/expression/LeafExpressionNode
    1282: invokevirtual #9                  // Method org/apache/hadoop/hbase/security/visibility/expression/LeafExpressionNode.getIdentifier:()Ljava/lang/String;
    1285: invokestatic  #10                 // Method org/junit/Assert.assertEquals:(Ljava/lang/Object;Ljava/lang/Object;)V
    1288: ldc           #25                 // String a
    1290: aload_2
    1291: invokevirtual #17                 // Method org/apache/hadoop/hbase/security/visibility/expression/NonLeafExpressionNode.getChildExps:()Ljava/util/List;
    1294: iconst_0
    1295: invokeinterface #21,  2           // InterfaceMethod java/util/List.get:(I)Ljava/lang/Object;
    1300: checkcast     #7                  // class org/apache/hadoop/hbase/security/visibility/expression/LeafExpressionNode
    1303: invokevirtual #9                  // Method org/apache/hadoop/hbase/security/visibility/expression/LeafExpressionNode.getIdentifier:()Ljava/lang/String;
    1306: invokestatic  #10                 // Method org/junit/Assert.assertEquals:(Ljava/lang/Object;Ljava/lang/Object;)V
    1309: aload_0
    1310: getfield      #4                  // Field parser:Lorg/apache/hadoop/hbase/security/visibility/ExpressionParser;
    1313: ldc           #36                 // String a&(b|(c|d))
    1315: invokevirtual #6                  // Method org/apache/hadoop/hbase/security/visibility/ExpressionParser.parse:(Ljava/lang/String;)Lorg/apache/hadoop/hbase/security/visibility/expression/ExpressionNode;
    1318: astore_1
    1319: aload_1
    1320: instanceof    #12                 // class org/apache/hadoop/hbase/security/visibility/expression/NonLeafExpressionNode
    1323: invokestatic  #8                  // Method org/junit/Assert.assertTrue:(Z)V
    1326: aload_1
    1327: checkcast     #12                 // class org/apache/hadoop/hbase/security/visibility/expression/NonLeafExpressionNode
    1330: astore_2
    1331: getstatic     #13                 // Field org/apache/hadoop/hbase/security/visibility/expression/Operator.AND:Lorg/apache/hadoop/hbase/security/visibility/expression/Operator;
    1334: aload_2
    1335: invokevirtual #14                 // Method org/apache/hadoop/hbase/security/visibility/expression/NonLeafExpressionNode.getOperator:()Lorg/apache/hadoop/hbase/security/visibility/expression/Operator;
    1338: invokestatic  #10                 // Method org/junit/Assert.assertEquals:(Ljava/lang/Object;Ljava/lang/Object;)V
    1341: ldc2_w        #15                 // long 2l
    1344: aload_2
    1345: invokevirtual #17                 // Method org/apache/hadoop/hbase/security/visibility/expression/NonLeafExpressionNode.getChildExps:()Ljava/util/List;
    1348: invokeinterface #18,  1           // InterfaceMethod java/util/List.size:()I
    1353: i2l
    1354: invokestatic  #19                 // Method org/junit/Assert.assertEquals:(JJ)V
    1357: ldc           #25                 // String a
    1359: aload_2
    1360: invokevirtual #17                 // Method org/apache/hadoop/hbase/security/visibility/expression/NonLeafExpressionNode.getChildExps:()Ljava/util/List;
    1363: iconst_0
    1364: invokeinterface #21,  2           // InterfaceMethod java/util/List.get:(I)Ljava/lang/Object;
    1369: checkcast     #7                  // class org/apache/hadoop/hbase/security/visibility/expression/LeafExpressionNode
    1372: invokevirtual #9                  // Method org/apache/hadoop/hbase/security/visibility/expression/LeafExpressionNode.getIdentifier:()Ljava/lang/String;
    1375: invokestatic  #10                 // Method org/junit/Assert.assertEquals:(Ljava/lang/Object;Ljava/lang/Object;)V
    1378: aload_2
    1379: invokevirtual #17                 // Method org/apache/hadoop/hbase/security/visibility/expression/NonLeafExpressionNode.getChildExps:()Ljava/util/List;
    1382: iconst_1
    1383: invokeinterface #21,  2           // InterfaceMethod java/util/List.get:(I)Ljava/lang/Object;
    1388: instanceof    #12                 // class org/apache/hadoop/hbase/security/visibility/expression/NonLeafExpressionNode
    1391: invokestatic  #8                  // Method org/junit/Assert.assertTrue:(Z)V
    1394: aload_2
    1395: invokevirtual #17                 // Method org/apache/hadoop/hbase/security/visibility/expression/NonLeafExpressionNode.getChildExps:()Ljava/util/List;
    1398: iconst_1
    1399: invokeinterface #21,  2           // InterfaceMethod java/util/List.get:(I)Ljava/lang/Object;
    1404: checkcast     #12                 // class org/apache/hadoop/hbase/security/visibility/expression/NonLeafExpressionNode
    1407: astore_2
    1408: getstatic     #22                 // Field org/apache/hadoop/hbase/security/visibility/expression/Operator.OR:Lorg/apache/hadoop/hbase/security/visibility/expression/Operator;
    1411: aload_2
    1412: invokevirtual #14                 // Method org/apache/hadoop/hbase/security/visibility/expression/NonLeafExpressionNode.getOperator:()Lorg/apache/hadoop/hbase/security/visibility/expression/Operator;
    1415: invokestatic  #10                 // Method org/junit/Assert.assertEquals:(Ljava/lang/Object;Ljava/lang/Object;)V
    1418: ldc2_w        #15                 // long 2l
    1421: aload_2
    1422: invokevirtual #17                 // Method org/apache/hadoop/hbase/security/visibility/expression/NonLeafExpressionNode.getChildExps:()Ljava/util/List;
    1425: invokeinterface #18,  1           // InterfaceMethod java/util/List.size:()I
    1430: i2l
    1431: invokestatic  #19                 // Method org/junit/Assert.assertEquals:(JJ)V
    1434: ldc           #24                 // String b
    1436: aload_2
    1437: invokevirtual #17                 // Method org/apache/hadoop/hbase/security/visibility/expression/NonLeafExpressionNode.getChildExps:()Ljava/util/List;
    1440: iconst_0
    1441: invokeinterface #21,  2           // InterfaceMethod java/util/List.get:(I)Ljava/lang/Object;
    1446: checkcast     #7                  // class org/apache/hadoop/hbase/security/visibility/expression/LeafExpressionNode
    1449: invokevirtual #9                  // Method org/apache/hadoop/hbase/security/visibility/expression/LeafExpressionNode.getIdentifier:()Ljava/lang/String;
    1452: invokestatic  #10                 // Method org/junit/Assert.assertEquals:(Ljava/lang/Object;Ljava/lang/Object;)V
    1455: aload_2
    1456: invokevirtual #17                 // Method org/apache/hadoop/hbase/security/visibility/expression/NonLeafExpressionNode.getChildExps:()Ljava/util/List;
    1459: iconst_1
    1460: invokeinterface #21,  2           // InterfaceMethod java/util/List.get:(I)Ljava/lang/Object;
    1465: instanceof    #12                 // class org/apache/hadoop/hbase/security/visibility/expression/NonLeafExpressionNode
    1468: invokestatic  #8                  // Method org/junit/Assert.assertTrue:(Z)V
    1471: aload_2
    1472: invokevirtual #17                 // Method org/apache/hadoop/hbase/security/visibility/expression/NonLeafExpressionNode.getChildExps:()Ljava/util/List;
    1475: iconst_1
    1476: invokeinterface #21,  2           // InterfaceMethod java/util/List.get:(I)Ljava/lang/Object;
    1481: checkcast     #12                 // class org/apache/hadoop/hbase/security/visibility/expression/NonLeafExpressionNode
    1484: astore_2
    1485: getstatic     #22                 // Field org/apache/hadoop/hbase/security/visibility/expression/Operator.OR:Lorg/apache/hadoop/hbase/security/visibility/expression/Operator;
    1488: aload_2
    1489: invokevirtual #14                 // Method org/apache/hadoop/hbase/security/visibility/expression/NonLeafExpressionNode.getOperator:()Lorg/apache/hadoop/hbase/security/visibility/expression/Operator;
    1492: invokestatic  #10                 // Method org/junit/Assert.assertEquals:(Ljava/lang/Object;Ljava/lang/Object;)V
    1495: ldc2_w        #15                 // long 2l
    1498: aload_2
    1499: invokevirtual #17                 // Method org/apache/hadoop/hbase/security/visibility/expression/NonLeafExpressionNode.getChildExps:()Ljava/util/List;
    1502: invokeinterface #18,  1           // InterfaceMethod java/util/List.size:()I
    1507: i2l
    1508: invokestatic  #19                 // Method org/junit/Assert.assertEquals:(JJ)V
    1511: ldc           #23                 // String c
    1513: aload_2
    1514: invokevirtual #17                 // Method org/apache/hadoop/hbase/security/visibility/expression/NonLeafExpressionNode.getChildExps:()Ljava/util/List;
    1517: iconst_0
    1518: invokeinterface #21,  2           // InterfaceMethod java/util/List.get:(I)Ljava/lang/Object;
    1523: checkcast     #7                  // class org/apache/hadoop/hbase/security/visibility/expression/LeafExpressionNode
    1526: invokevirtual #9                  // Method org/apache/hadoop/hbase/security/visibility/expression/LeafExpressionNode.getIdentifier:()Ljava/lang/String;
    1529: invokestatic  #10                 // Method org/junit/Assert.assertEquals:(Ljava/lang/Object;Ljava/lang/Object;)V
    1532: ldc           #20                 // String d
    1534: aload_2
    1535: invokevirtual #17                 // Method org/apache/hadoop/hbase/security/visibility/expression/NonLeafExpressionNode.getChildExps:()Ljava/util/List;
    1538: iconst_1
    1539: invokeinterface #21,  2           // InterfaceMethod java/util/List.get:(I)Ljava/lang/Object;
    1544: checkcast     #7                  // class org/apache/hadoop/hbase/security/visibility/expression/LeafExpressionNode
    1547: invokevirtual #9                  // Method org/apache/hadoop/hbase/security/visibility/expression/LeafExpressionNode.getIdentifier:()Ljava/lang/String;
    1550: invokestatic  #10                 // Method org/junit/Assert.assertEquals:(Ljava/lang/Object;Ljava/lang/Object;)V
    1553: aload_0
    1554: getfield      #4                  // Field parser:Lorg/apache/hadoop/hbase/security/visibility/ExpressionParser;
    1557: ldc           #37                 // String (!a)
    1559: invokevirtual #6                  // Method org/apache/hadoop/hbase/security/visibility/ExpressionParser.parse:(Ljava/lang/String;)Lorg/apache/hadoop/hbase/security/visibility/expression/ExpressionNode;
    1562: astore_1
    1563: aload_1
    1564: instanceof    #12                 // class org/apache/hadoop/hbase/security/visibility/expression/NonLeafExpressionNode
    1567: invokestatic  #8                  // Method org/junit/Assert.assertTrue:(Z)V
    1570: aload_1
    1571: checkcast     #12                 // class org/apache/hadoop/hbase/security/visibility/expression/NonLeafExpressionNode
    1574: astore_2
    1575: getstatic     #38                 // Field org/apache/hadoop/hbase/security/visibility/expression/Operator.NOT:Lorg/apache/hadoop/hbase/security/visibility/expression/Operator;
    1578: aload_2
    1579: invokevirtual #14                 // Method org/apache/hadoop/hbase/security/visibility/expression/NonLeafExpressionNode.getOperator:()Lorg/apache/hadoop/hbase/security/visibility/expression/Operator;
    1582: invokestatic  #10                 // Method org/junit/Assert.assertEquals:(Ljava/lang/Object;Ljava/lang/Object;)V
    1585: ldc           #25                 // String a
    1587: aload_2
    1588: invokevirtual #17                 // Method org/apache/hadoop/hbase/security/visibility/expression/NonLeafExpressionNode.getChildExps:()Ljava/util/List;
    1591: iconst_0
    1592: invokeinterface #21,  2           // InterfaceMethod java/util/List.get:(I)Ljava/lang/Object;
    1597: checkcast     #7                  // class org/apache/hadoop/hbase/security/visibility/expression/LeafExpressionNode
    1600: invokevirtual #9                  // Method org/apache/hadoop/hbase/security/visibility/expression/LeafExpressionNode.getIdentifier:()Ljava/lang/String;
    1603: invokestatic  #10                 // Method org/junit/Assert.assertEquals:(Ljava/lang/Object;Ljava/lang/Object;)V
    1606: aload_0
    1607: getfield      #4                  // Field parser:Lorg/apache/hadoop/hbase/security/visibility/ExpressionParser;
    1610: ldc           #39                 // String a&(!b)
    1612: invokevirtual #6                  // Method org/apache/hadoop/hbase/security/visibility/ExpressionParser.parse:(Ljava/lang/String;)Lorg/apache/hadoop/hbase/security/visibility/expression/ExpressionNode;
    1615: astore_1
    1616: aload_1
    1617: instanceof    #12                 // class org/apache/hadoop/hbase/security/visibility/expression/NonLeafExpressionNode
    1620: invokestatic  #8                  // Method org/junit/Assert.assertTrue:(Z)V
    1623: aload_1
    1624: checkcast     #12                 // class org/apache/hadoop/hbase/security/visibility/expression/NonLeafExpressionNode
    1627: astore_2
    1628: getstatic     #13                 // Field org/apache/hadoop/hbase/security/visibility/expression/Operator.AND:Lorg/apache/hadoop/hbase/security/visibility/expression/Operator;
    1631: aload_2
    1632: invokevirtual #14                 // Method org/apache/hadoop/hbase/security/visibility/expression/NonLeafExpressionNode.getOperator:()Lorg/apache/hadoop/hbase/security/visibility/expression/Operator;
    1635: invokestatic  #10                 // Method org/junit/Assert.assertEquals:(Ljava/lang/Object;Ljava/lang/Object;)V
    1638: ldc2_w        #15                 // long 2l
    1641: aload_2
    1642: invokevirtual #17                 // Method org/apache/hadoop/hbase/security/visibility/expression/NonLeafExpressionNode.getChildExps:()Ljava/util/List;
    1645: invokeinterface #18,  1           // InterfaceMethod java/util/List.size:()I
    1650: i2l
    1651: invokestatic  #19                 // Method org/junit/Assert.assertEquals:(JJ)V
    1654: ldc           #25                 // String a
    1656: aload_2
    1657: invokevirtual #17                 // Method org/apache/hadoop/hbase/security/visibility/expression/NonLeafExpressionNode.getChildExps:()Ljava/util/List;
    1660: iconst_0
    1661: invokeinterface #21,  2           // InterfaceMethod java/util/List.get:(I)Ljava/lang/Object;
    1666: checkcast     #7                  // class org/apache/hadoop/hbase/security/visibility/expression/LeafExpressionNode
    1669: invokevirtual #9                  // Method org/apache/hadoop/hbase/security/visibility/expression/LeafExpressionNode.getIdentifier:()Ljava/lang/String;
    1672: invokestatic  #10                 // Method org/junit/Assert.assertEquals:(Ljava/lang/Object;Ljava/lang/Object;)V
    1675: aload_2
    1676: invokevirtual #17                 // Method org/apache/hadoop/hbase/security/visibility/expression/NonLeafExpressionNode.getChildExps:()Ljava/util/List;
    1679: iconst_1
    1680: invokeinterface #21,  2           // InterfaceMethod java/util/List.get:(I)Ljava/lang/Object;
    1685: instanceof    #12                 // class org/apache/hadoop/hbase/security/visibility/expression/NonLeafExpressionNode
    1688: invokestatic  #8                  // Method org/junit/Assert.assertTrue:(Z)V
    1691: aload_2
    1692: invokevirtual #17                 // Method org/apache/hadoop/hbase/security/visibility/expression/NonLeafExpressionNode.getChildExps:()Ljava/util/List;
    1695: iconst_1
    1696: invokeinterface #21,  2           // InterfaceMethod java/util/List.get:(I)Ljava/lang/Object;
    1701: checkcast     #12                 // class org/apache/hadoop/hbase/security/visibility/expression/NonLeafExpressionNode
    1704: astore_2
    1705: getstatic     #38                 // Field org/apache/hadoop/hbase/security/visibility/expression/Operator.NOT:Lorg/apache/hadoop/hbase/security/visibility/expression/Operator;
    1708: aload_2
    1709: invokevirtual #14                 // Method org/apache/hadoop/hbase/security/visibility/expression/NonLeafExpressionNode.getOperator:()Lorg/apache/hadoop/hbase/security/visibility/expression/Operator;
    1712: invokestatic  #10                 // Method org/junit/Assert.assertEquals:(Ljava/lang/Object;Ljava/lang/Object;)V
    1715: lconst_1
    1716: aload_2
    1717: invokevirtual #17                 // Method org/apache/hadoop/hbase/security/visibility/expression/NonLeafExpressionNode.getChildExps:()Ljava/util/List;
    1720: invokeinterface #18,  1           // InterfaceMethod java/util/List.size:()I
    1725: i2l
    1726: invokestatic  #19                 // Method org/junit/Assert.assertEquals:(JJ)V
    1729: ldc           #24                 // String b
    1731: aload_2
    1732: invokevirtual #17                 // Method org/apache/hadoop/hbase/security/visibility/expression/NonLeafExpressionNode.getChildExps:()Ljava/util/List;
    1735: iconst_0
    1736: invokeinterface #21,  2           // InterfaceMethod java/util/List.get:(I)Ljava/lang/Object;
    1741: checkcast     #7                  // class org/apache/hadoop/hbase/security/visibility/expression/LeafExpressionNode
    1744: invokevirtual #9                  // Method org/apache/hadoop/hbase/security/visibility/expression/LeafExpressionNode.getIdentifier:()Ljava/lang/String;
    1747: invokestatic  #10                 // Method org/junit/Assert.assertEquals:(Ljava/lang/Object;Ljava/lang/Object;)V
    1750: aload_0
    1751: getfield      #4                  // Field parser:Lorg/apache/hadoop/hbase/security/visibility/ExpressionParser;
    1754: ldc           #40                 // String !a&b
    1756: invokevirtual #6                  // Method org/apache/hadoop/hbase/security/visibility/ExpressionParser.parse:(Ljava/lang/String;)Lorg/apache/hadoop/hbase/security/visibility/expression/ExpressionNode;
    1759: astore_1
    1760: aload_1
    1761: instanceof    #12                 // class org/apache/hadoop/hbase/security/visibility/expression/NonLeafExpressionNode
    1764: invokestatic  #8                  // Method org/junit/Assert.assertTrue:(Z)V
    1767: aload_1
    1768: checkcast     #12                 // class org/apache/hadoop/hbase/security/visibility/expression/NonLeafExpressionNode
    1771: astore_2
    1772: getstatic     #13                 // Field org/apache/hadoop/hbase/security/visibility/expression/Operator.AND:Lorg/apache/hadoop/hbase/security/visibility/expression/Operator;
    1775: aload_2
    1776: invokevirtual #14                 // Method org/apache/hadoop/hbase/security/visibility/expression/NonLeafExpressionNode.getOperator:()Lorg/apache/hadoop/hbase/security/visibility/expression/Operator;
    1779: invokestatic  #10                 // Method org/junit/Assert.assertEquals:(Ljava/lang/Object;Ljava/lang/Object;)V
    1782: ldc2_w        #15                 // long 2l
    1785: aload_2
    1786: invokevirtual #17                 // Method org/apache/hadoop/hbase/security/visibility/expression/NonLeafExpressionNode.getChildExps:()Ljava/util/List;
    1789: invokeinterface #18,  1           // InterfaceMethod java/util/List.size:()I
    1794: i2l
    1795: invokestatic  #19                 // Method org/junit/Assert.assertEquals:(JJ)V
    1798: ldc           #24                 // String b
    1800: aload_2
    1801: invokevirtual #17                 // Method org/apache/hadoop/hbase/security/visibility/expression/NonLeafExpressionNode.getChildExps:()Ljava/util/List;
    1804: iconst_1
    1805: invokeinterface #21,  2           // InterfaceMethod java/util/List.get:(I)Ljava/lang/Object;
    1810: checkcast     #7                  // class org/apache/hadoop/hbase/security/visibility/expression/LeafExpressionNode
    1813: invokevirtual #9                  // Method org/apache/hadoop/hbase/security/visibility/expression/LeafExpressionNode.getIdentifier:()Ljava/lang/String;
    1816: invokestatic  #10                 // Method org/junit/Assert.assertEquals:(Ljava/lang/Object;Ljava/lang/Object;)V
    1819: aload_2
    1820: invokevirtual #17                 // Method org/apache/hadoop/hbase/security/visibility/expression/NonLeafExpressionNode.getChildExps:()Ljava/util/List;
    1823: iconst_0
    1824: invokeinterface #21,  2           // InterfaceMethod java/util/List.get:(I)Ljava/lang/Object;
    1829: instanceof    #12                 // class org/apache/hadoop/hbase/security/visibility/expression/NonLeafExpressionNode
    1832: invokestatic  #8                  // Method org/junit/Assert.assertTrue:(Z)V
    1835: aload_2
    1836: invokevirtual #17                 // Method org/apache/hadoop/hbase/security/visibility/expression/NonLeafExpressionNode.getChildExps:()Ljava/util/List;
    1839: iconst_0
    1840: invokeinterface #21,  2           // InterfaceMethod java/util/List.get:(I)Ljava/lang/Object;
    1845: checkcast     #12                 // class org/apache/hadoop/hbase/security/visibility/expression/NonLeafExpressionNode
    1848: astore_2
    1849: getstatic     #38                 // Field org/apache/hadoop/hbase/security/visibility/expression/Operator.NOT:Lorg/apache/hadoop/hbase/security/visibility/expression/Operator;
    1852: aload_2
    1853: invokevirtual #14                 // Method org/apache/hadoop/hbase/security/visibility/expression/NonLeafExpressionNode.getOperator:()Lorg/apache/hadoop/hbase/security/visibility/expression/Operator;
    1856: invokestatic  #10                 // Method org/junit/Assert.assertEquals:(Ljava/lang/Object;Ljava/lang/Object;)V
    1859: lconst_1
    1860: aload_2
    1861: invokevirtual #17                 // Method org/apache/hadoop/hbase/security/visibility/expression/NonLeafExpressionNode.getChildExps:()Ljava/util/List;
    1864: invokeinterface #18,  1           // InterfaceMethod java/util/List.size:()I
    1869: i2l
    1870: invokestatic  #19                 // Method org/junit/Assert.assertEquals:(JJ)V
    1873: ldc           #25                 // String a
    1875: aload_2
    1876: invokevirtual #17                 // Method org/apache/hadoop/hbase/security/visibility/expression/NonLeafExpressionNode.getChildExps:()Ljava/util/List;
    1879: iconst_0
    1880: invokeinterface #21,  2           // InterfaceMethod java/util/List.get:(I)Ljava/lang/Object;
    1885: checkcast     #7                  // class org/apache/hadoop/hbase/security/visibility/expression/LeafExpressionNode
    1888: invokevirtual #9                  // Method org/apache/hadoop/hbase/security/visibility/expression/LeafExpressionNode.getIdentifier:()Ljava/lang/String;
    1891: invokestatic  #10                 // Method org/junit/Assert.assertEquals:(Ljava/lang/Object;Ljava/lang/Object;)V
    1894: aload_0
    1895: getfield      #4                  // Field parser:Lorg/apache/hadoop/hbase/security/visibility/ExpressionParser;
    1898: ldc           #41                 // String !a&(!b)
    1900: invokevirtual #6                  // Method org/apache/hadoop/hbase/security/visibility/ExpressionParser.parse:(Ljava/lang/String;)Lorg/apache/hadoop/hbase/security/visibility/expression/ExpressionNode;
    1903: astore_1
    1904: aload_1
    1905: instanceof    #12                 // class org/apache/hadoop/hbase/security/visibility/expression/NonLeafExpressionNode
    1908: invokestatic  #8                  // Method org/junit/Assert.assertTrue:(Z)V
    1911: aload_1
    1912: checkcast     #12                 // class org/apache/hadoop/hbase/security/visibility/expression/NonLeafExpressionNode
    1915: astore_2
    1916: getstatic     #13                 // Field org/apache/hadoop/hbase/security/visibility/expression/Operator.AND:Lorg/apache/hadoop/hbase/security/visibility/expression/Operator;
    1919: aload_2
    1920: invokevirtual #14                 // Method org/apache/hadoop/hbase/security/visibility/expression/NonLeafExpressionNode.getOperator:()Lorg/apache/hadoop/hbase/security/visibility/expression/Operator;
    1923: invokestatic  #10                 // Method org/junit/Assert.assertEquals:(Ljava/lang/Object;Ljava/lang/Object;)V
    1926: ldc2_w        #15                 // long 2l
    1929: aload_2
    1930: invokevirtual #17                 // Method org/apache/hadoop/hbase/security/visibility/expression/NonLeafExpressionNode.getChildExps:()Ljava/util/List;
    1933: invokeinterface #18,  1           // InterfaceMethod java/util/List.size:()I
    1938: i2l
    1939: invokestatic  #19                 // Method org/junit/Assert.assertEquals:(JJ)V
    1942: aload_2
    1943: invokevirtual #17                 // Method org/apache/hadoop/hbase/security/visibility/expression/NonLeafExpressionNode.getChildExps:()Ljava/util/List;
    1946: iconst_0
    1947: invokeinterface #21,  2           // InterfaceMethod java/util/List.get:(I)Ljava/lang/Object;
    1952: instanceof    #12                 // class org/apache/hadoop/hbase/security/visibility/expression/NonLeafExpressionNode
    1955: invokestatic  #8                  // Method org/junit/Assert.assertTrue:(Z)V
    1958: aload_2
    1959: invokevirtual #17                 // Method org/apache/hadoop/hbase/security/visibility/expression/NonLeafExpressionNode.getChildExps:()Ljava/util/List;
    1962: iconst_1
    1963: invokeinterface #21,  2           // InterfaceMethod java/util/List.get:(I)Ljava/lang/Object;
    1968: instanceof    #12                 // class org/apache/hadoop/hbase/security/visibility/expression/NonLeafExpressionNode
    1971: invokestatic  #8                  // Method org/junit/Assert.assertTrue:(Z)V
    1974: aload_2
    1975: invokevirtual #17                 // Method org/apache/hadoop/hbase/security/visibility/expression/NonLeafExpressionNode.getChildExps:()Ljava/util/List;
    1978: iconst_0
    1979: invokeinterface #21,  2           // InterfaceMethod java/util/List.get:(I)Ljava/lang/Object;
    1984: checkcast     #12                 // class org/apache/hadoop/hbase/security/visibility/expression/NonLeafExpressionNode
    1987: astore_3
    1988: aload_2
    1989: invokevirtual #17                 // Method org/apache/hadoop/hbase/security/visibility/expression/NonLeafExpressionNode.getChildExps:()Ljava/util/List;
    1992: iconst_1
    1993: invokeinterface #21,  2           // InterfaceMethod java/util/List.get:(I)Ljava/lang/Object;
    1998: checkcast     #12                 // class org/apache/hadoop/hbase/security/visibility/expression/NonLeafExpressionNode
    2001: astore        4
    2003: getstatic     #38                 // Field org/apache/hadoop/hbase/security/visibility/expression/Operator.NOT:Lorg/apache/hadoop/hbase/security/visibility/expression/Operator;
    2006: aload_3
    2007: invokevirtual #14                 // Method org/apache/hadoop/hbase/security/visibility/expression/NonLeafExpressionNode.getOperator:()Lorg/apache/hadoop/hbase/security/visibility/expression/Operator;
    2010: invokestatic  #10                 // Method org/junit/Assert.assertEquals:(Ljava/lang/Object;Ljava/lang/Object;)V
    2013: lconst_1
    2014: aload_3
    2015: invokevirtual #17                 // Method org/apache/hadoop/hbase/security/visibility/expression/NonLeafExpressionNode.getChildExps:()Ljava/util/List;
    2018: invokeinterface #18,  1           // InterfaceMethod java/util/List.size:()I
    2023: i2l
    2024: invokestatic  #19                 // Method org/junit/Assert.assertEquals:(JJ)V
    2027: ldc           #25                 // String a
    2029: aload_3
    2030: invokevirtual #17                 // Method org/apache/hadoop/hbase/security/visibility/expression/NonLeafExpressionNode.getChildExps:()Ljava/util/List;
    2033: iconst_0
    2034: invokeinterface #21,  2           // InterfaceMethod java/util/List.get:(I)Ljava/lang/Object;
    2039: checkcast     #7                  // class org/apache/hadoop/hbase/security/visibility/expression/LeafExpressionNode
    2042: invokevirtual #9                  // Method org/apache/hadoop/hbase/security/visibility/expression/LeafExpressionNode.getIdentifier:()Ljava/lang/String;
    2045: invokestatic  #10                 // Method org/junit/Assert.assertEquals:(Ljava/lang/Object;Ljava/lang/Object;)V
    2048: getstatic     #38                 // Field org/apache/hadoop/hbase/security/visibility/expression/Operator.NOT:Lorg/apache/hadoop/hbase/security/visibility/expression/Operator;
    2051: aload         4
    2053: invokevirtual #14                 // Method org/apache/hadoop/hbase/security/visibility/expression/NonLeafExpressionNode.getOperator:()Lorg/apache/hadoop/hbase/security/visibility/expression/Operator;
    2056: invokestatic  #10                 // Method org/junit/Assert.assertEquals:(Ljava/lang/Object;Ljava/lang/Object;)V
    2059: lconst_1
    2060: aload         4
    2062: invokevirtual #17                 // Method org/apache/hadoop/hbase/security/visibility/expression/NonLeafExpressionNode.getChildExps:()Ljava/util/List;
    2065: invokeinterface #18,  1           // InterfaceMethod java/util/List.size:()I
    2070: i2l
    2071: invokestatic  #19                 // Method org/junit/Assert.assertEquals:(JJ)V
    2074: ldc           #24                 // String b
    2076: aload         4
    2078: invokevirtual #17                 // Method org/apache/hadoop/hbase/security/visibility/expression/NonLeafExpressionNode.getChildExps:()Ljava/util/List;
    2081: iconst_0
    2082: invokeinterface #21,  2           // InterfaceMethod java/util/List.get:(I)Ljava/lang/Object;
    2087: checkcast     #7                  // class org/apache/hadoop/hbase/security/visibility/expression/LeafExpressionNode
    2090: invokevirtual #9                  // Method org/apache/hadoop/hbase/security/visibility/expression/LeafExpressionNode.getIdentifier:()Ljava/lang/String;
    2093: invokestatic  #10                 // Method org/junit/Assert.assertEquals:(Ljava/lang/Object;Ljava/lang/Object;)V
    2096: aload_0
    2097: getfield      #4                  // Field parser:Lorg/apache/hadoop/hbase/security/visibility/ExpressionParser;
    2100: ldc           #42                 // String !a&!b
    2102: invokevirtual #6                  // Method org/apache/hadoop/hbase/security/visibility/ExpressionParser.parse:(Ljava/lang/String;)Lorg/apache/hadoop/hbase/security/visibility/expression/ExpressionNode;
    2105: astore_1
    2106: aload_1
    2107: instanceof    #12                 // class org/apache/hadoop/hbase/security/visibility/expression/NonLeafExpressionNode
    2110: invokestatic  #8                  // Method org/junit/Assert.assertTrue:(Z)V
    2113: aload_1
    2114: checkcast     #12                 // class org/apache/hadoop/hbase/security/visibility/expression/NonLeafExpressionNode
    2117: astore_2
    2118: getstatic     #13                 // Field org/apache/hadoop/hbase/security/visibility/expression/Operator.AND:Lorg/apache/hadoop/hbase/security/visibility/expression/Operator;
    2121: aload_2
    2122: invokevirtual #14                 // Method org/apache/hadoop/hbase/security/visibility/expression/NonLeafExpressionNode.getOperator:()Lorg/apache/hadoop/hbase/security/visibility/expression/Operator;
    2125: invokestatic  #10                 // Method org/junit/Assert.assertEquals:(Ljava/lang/Object;Ljava/lang/Object;)V
    2128: ldc2_w        #15                 // long 2l
    2131: aload_2
    2132: invokevirtual #17                 // Method org/apache/hadoop/hbase/security/visibility/expression/NonLeafExpressionNode.getChildExps:()Ljava/util/List;
    2135: invokeinterface #18,  1           // InterfaceMethod java/util/List.size:()I
    2140: i2l
    2141: invokestatic  #19                 // Method org/junit/Assert.assertEquals:(JJ)V
    2144: aload_2
    2145: invokevirtual #17                 // Method org/apache/hadoop/hbase/security/visibility/expression/NonLeafExpressionNode.getChildExps:()Ljava/util/List;
    2148: iconst_0
    2149: invokeinterface #21,  2           // InterfaceMethod java/util/List.get:(I)Ljava/lang/Object;
    2154: instanceof    #12                 // class org/apache/hadoop/hbase/security/visibility/expression/NonLeafExpressionNode
    2157: invokestatic  #8                  // Method org/junit/Assert.assertTrue:(Z)V
    2160: aload_2
    2161: invokevirtual #17                 // Method org/apache/hadoop/hbase/security/visibility/expression/NonLeafExpressionNode.getChildExps:()Ljava/util/List;
    2164: iconst_1
    2165: invokeinterface #21,  2           // InterfaceMethod java/util/List.get:(I)Ljava/lang/Object;
    2170: instanceof    #12                 // class org/apache/hadoop/hbase/security/visibility/expression/NonLeafExpressionNode
    2173: invokestatic  #8                  // Method org/junit/Assert.assertTrue:(Z)V
    2176: aload_2
    2177: invokevirtual #17                 // Method org/apache/hadoop/hbase/security/visibility/expression/NonLeafExpressionNode.getChildExps:()Ljava/util/List;
    2180: iconst_0
    2181: invokeinterface #21,  2           // InterfaceMethod java/util/List.get:(I)Ljava/lang/Object;
    2186: checkcast     #12                 // class org/apache/hadoop/hbase/security/visibility/expression/NonLeafExpressionNode
    2189: astore_3
    2190: aload_2
    2191: invokevirtual #17                 // Method org/apache/hadoop/hbase/security/visibility/expression/NonLeafExpressionNode.getChildExps:()Ljava/util/List;
    2194: iconst_1
    2195: invokeinterface #21,  2           // InterfaceMethod java/util/List.get:(I)Ljava/lang/Object;
    2200: checkcast     #12                 // class org/apache/hadoop/hbase/security/visibility/expression/NonLeafExpressionNode
    2203: astore        4
    2205: getstatic     #38                 // Field org/apache/hadoop/hbase/security/visibility/expression/Operator.NOT:Lorg/apache/hadoop/hbase/security/visibility/expression/Operator;
    2208: aload_3
    2209: invokevirtual #14                 // Method org/apache/hadoop/hbase/security/visibility/expression/NonLeafExpressionNode.getOperator:()Lorg/apache/hadoop/hbase/security/visibility/expression/Operator;
    2212: invokestatic  #10                 // Method org/junit/Assert.assertEquals:(Ljava/lang/Object;Ljava/lang/Object;)V
    2215: lconst_1
    2216: aload_3
    2217: invokevirtual #17                 // Method org/apache/hadoop/hbase/security/visibility/expression/NonLeafExpressionNode.getChildExps:()Ljava/util/List;
    2220: invokeinterface #18,  1           // InterfaceMethod java/util/List.size:()I
    2225: i2l
    2226: invokestatic  #19                 // Method org/junit/Assert.assertEquals:(JJ)V
    2229: ldc           #25                 // String a
    2231: aload_3
    2232: invokevirtual #17                 // Method org/apache/hadoop/hbase/security/visibility/expression/NonLeafExpressionNode.getChildExps:()Ljava/util/List;
    2235: iconst_0
    2236: invokeinterface #21,  2           // InterfaceMethod java/util/List.get:(I)Ljava/lang/Object;
    2241: checkcast     #7                  // class org/apache/hadoop/hbase/security/visibility/expression/LeafExpressionNode
    2244: invokevirtual #9                  // Method org/apache/hadoop/hbase/security/visibility/expression/LeafExpressionNode.getIdentifier:()Ljava/lang/String;
    2247: invokestatic  #10                 // Method org/junit/Assert.assertEquals:(Ljava/lang/Object;Ljava/lang/Object;)V
    2250: getstatic     #38                 // Field org/apache/hadoop/hbase/security/visibility/expression/Operator.NOT:Lorg/apache/hadoop/hbase/security/visibility/expression/Operator;
    2253: aload         4
    2255: invokevirtual #14                 // Method org/apache/hadoop/hbase/security/visibility/expression/NonLeafExpressionNode.getOperator:()Lorg/apache/hadoop/hbase/security/visibility/expression/Operator;
    2258: invokestatic  #10                 // Method org/junit/Assert.assertEquals:(Ljava/lang/Object;Ljava/lang/Object;)V
    2261: lconst_1
    2262: aload         4
    2264: invokevirtual #17                 // Method org/apache/hadoop/hbase/security/visibility/expression/NonLeafExpressionNode.getChildExps:()Ljava/util/List;
    2267: invokeinterface #18,  1           // InterfaceMethod java/util/List.size:()I
    2272: i2l
    2273: invokestatic  #19                 // Method org/junit/Assert.assertEquals:(JJ)V
    2276: ldc           #24                 // String b
    2278: aload         4
    2280: invokevirtual #17                 // Method org/apache/hadoop/hbase/security/visibility/expression/NonLeafExpressionNode.getChildExps:()Ljava/util/List;
    2283: iconst_0
    2284: invokeinterface #21,  2           // InterfaceMethod java/util/List.get:(I)Ljava/lang/Object;
    2289: checkcast     #7                  // class org/apache/hadoop/hbase/security/visibility/expression/LeafExpressionNode
    2292: invokevirtual #9                  // Method org/apache/hadoop/hbase/security/visibility/expression/LeafExpressionNode.getIdentifier:()Ljava/lang/String;
    2295: invokestatic  #10                 // Method org/junit/Assert.assertEquals:(Ljava/lang/Object;Ljava/lang/Object;)V
    2298: aload_0
    2299: getfield      #4                  // Field parser:Lorg/apache/hadoop/hbase/security/visibility/ExpressionParser;
    2302: ldc           #43                 // String !(a&b)
    2304: invokevirtual #6                  // Method org/apache/hadoop/hbase/security/visibility/ExpressionParser.parse:(Ljava/lang/String;)Lorg/apache/hadoop/hbase/security/visibility/expression/ExpressionNode;
    2307: astore_1
    2308: aload_1
    2309: instanceof    #12                 // class org/apache/hadoop/hbase/security/visibility/expression/NonLeafExpressionNode
    2312: invokestatic  #8                  // Method org/junit/Assert.assertTrue:(Z)V
    2315: aload_1
    2316: checkcast     #12                 // class org/apache/hadoop/hbase/security/visibility/expression/NonLeafExpressionNode
    2319: astore_2
    2320: getstatic     #38                 // Field org/apache/hadoop/hbase/security/visibility/expression/Operator.NOT:Lorg/apache/hadoop/hbase/security/visibility/expression/Operator;
    2323: aload_2
    2324: invokevirtual #14                 // Method org/apache/hadoop/hbase/security/visibility/expression/NonLeafExpressionNode.getOperator:()Lorg/apache/hadoop/hbase/security/visibility/expression/Operator;
    2327: invokestatic  #10                 // Method org/junit/Assert.assertEquals:(Ljava/lang/Object;Ljava/lang/Object;)V
    2330: lconst_1
    2331: aload_2
    2332: invokevirtual #17                 // Method org/apache/hadoop/hbase/security/visibility/expression/NonLeafExpressionNode.getChildExps:()Ljava/util/List;
    2335: invokeinterface #18,  1           // InterfaceMethod java/util/List.size:()I
    2340: i2l
    2341: invokestatic  #19                 // Method org/junit/Assert.assertEquals:(JJ)V
    2344: aload_2
    2345: invokevirtual #17                 // Method org/apache/hadoop/hbase/security/visibility/expression/NonLeafExpressionNode.getChildExps:()Ljava/util/List;
    2348: iconst_0
    2349: invokeinterface #21,  2           // InterfaceMethod java/util/List.get:(I)Ljava/lang/Object;
    2354: checkcast     #12                 // class org/apache/hadoop/hbase/security/visibility/expression/NonLeafExpressionNode
    2357: astore_2
    2358: getstatic     #13                 // Field org/apache/hadoop/hbase/security/visibility/expression/Operator.AND:Lorg/apache/hadoop/hbase/security/visibility/expression/Operator;
    2361: aload_2
    2362: invokevirtual #14                 // Method org/apache/hadoop/hbase/security/visibility/expression/NonLeafExpressionNode.getOperator:()Lorg/apache/hadoop/hbase/security/visibility/expression/Operator;
    2365: invokestatic  #10                 // Method org/junit/Assert.assertEquals:(Ljava/lang/Object;Ljava/lang/Object;)V
    2368: ldc2_w        #15                 // long 2l
    2371: aload_2
    2372: invokevirtual #17                 // Method org/apache/hadoop/hbase/security/visibility/expression/NonLeafExpressionNode.getChildExps:()Ljava/util/List;
    2375: invokeinterface #18,  1           // InterfaceMethod java/util/List.size:()I
    2380: i2l
    2381: invokestatic  #19                 // Method org/junit/Assert.assertEquals:(JJ)V
    2384: ldc           #25                 // String a
    2386: aload_2
    2387: invokevirtual #17                 // Method org/apache/hadoop/hbase/security/visibility/expression/NonLeafExpressionNode.getChildExps:()Ljava/util/List;
    2390: iconst_0
    2391: invokeinterface #21,  2           // InterfaceMethod java/util/List.get:(I)Ljava/lang/Object;
    2396: checkcast     #7                  // class org/apache/hadoop/hbase/security/visibility/expression/LeafExpressionNode
    2399: invokevirtual #9                  // Method org/apache/hadoop/hbase/security/visibility/expression/LeafExpressionNode.getIdentifier:()Ljava/lang/String;
    2402: invokestatic  #10                 // Method org/junit/Assert.assertEquals:(Ljava/lang/Object;Ljava/lang/Object;)V
    2405: ldc           #24                 // String b
    2407: aload_2
    2408: invokevirtual #17                 // Method org/apache/hadoop/hbase/security/visibility/expression/NonLeafExpressionNode.getChildExps:()Ljava/util/List;
    2411: iconst_1
    2412: invokeinterface #21,  2           // InterfaceMethod java/util/List.get:(I)Ljava/lang/Object;
    2417: checkcast     #7                  // class org/apache/hadoop/hbase/security/visibility/expression/LeafExpressionNode
    2420: invokevirtual #9                  // Method org/apache/hadoop/hbase/security/visibility/expression/LeafExpressionNode.getIdentifier:()Ljava/lang/String;
    2423: invokestatic  #10                 // Method org/junit/Assert.assertEquals:(Ljava/lang/Object;Ljava/lang/Object;)V
    2426: aload_0
    2427: getfield      #4                  // Field parser:Lorg/apache/hadoop/hbase/security/visibility/ExpressionParser;
    2430: ldc           #44                 // String a&!b
    2432: invokevirtual #6                  // Method org/apache/hadoop/hbase/security/visibility/ExpressionParser.parse:(Ljava/lang/String;)Lorg/apache/hadoop/hbase/security/visibility/expression/ExpressionNode;
    2435: astore_1
    2436: aload_1
    2437: instanceof    #12                 // class org/apache/hadoop/hbase/security/visibility/expression/NonLeafExpressionNode
    2440: invokestatic  #8                  // Method org/junit/Assert.assertTrue:(Z)V
    2443: aload_1
    2444: checkcast     #12                 // class org/apache/hadoop/hbase/security/visibility/expression/NonLeafExpressionNode
    2447: astore_2
    2448: getstatic     #13                 // Field org/apache/hadoop/hbase/security/visibility/expression/Operator.AND:Lorg/apache/hadoop/hbase/security/visibility/expression/Operator;
    2451: aload_2
    2452: invokevirtual #14                 // Method org/apache/hadoop/hbase/security/visibility/expression/NonLeafExpressionNode.getOperator:()Lorg/apache/hadoop/hbase/security/visibility/expression/Operator;
    2455: invokestatic  #10                 // Method org/junit/Assert.assertEquals:(Ljava/lang/Object;Ljava/lang/Object;)V
    2458: ldc2_w        #15                 // long 2l
    2461: aload_2
    2462: invokevirtual #17                 // Method org/apache/hadoop/hbase/security/visibility/expression/NonLeafExpressionNode.getChildExps:()Ljava/util/List;
    2465: invokeinterface #18,  1           // InterfaceMethod java/util/List.size:()I
    2470: i2l
    2471: invokestatic  #19                 // Method org/junit/Assert.assertEquals:(JJ)V
    2474: ldc           #25                 // String a
    2476: aload_2
    2477: invokevirtual #17                 // Method org/apache/hadoop/hbase/security/visibility/expression/NonLeafExpressionNode.getChildExps:()Ljava/util/List;
    2480: iconst_0
    2481: invokeinterface #21,  2           // InterfaceMethod java/util/List.get:(I)Ljava/lang/Object;
    2486: checkcast     #7                  // class org/apache/hadoop/hbase/security/visibility/expression/LeafExpressionNode
    2489: invokevirtual #9                  // Method org/apache/hadoop/hbase/security/visibility/expression/LeafExpressionNode.getIdentifier:()Ljava/lang/String;
    2492: invokestatic  #10                 // Method org/junit/Assert.assertEquals:(Ljava/lang/Object;Ljava/lang/Object;)V
    2495: aload_2
    2496: invokevirtual #17                 // Method org/apache/hadoop/hbase/security/visibility/expression/NonLeafExpressionNode.getChildExps:()Ljava/util/List;
    2499: iconst_1
    2500: invokeinterface #21,  2           // InterfaceMethod java/util/List.get:(I)Ljava/lang/Object;
    2505: instanceof    #12                 // class org/apache/hadoop/hbase/security/visibility/expression/NonLeafExpressionNode
    2508: invokestatic  #8                  // Method org/junit/Assert.assertTrue:(Z)V
    2511: aload_2
    2512: invokevirtual #17                 // Method org/apache/hadoop/hbase/security/visibility/expression/NonLeafExpressionNode.getChildExps:()Ljava/util/List;
    2515: iconst_1
    2516: invokeinterface #21,  2           // InterfaceMethod java/util/List.get:(I)Ljava/lang/Object;
    2521: checkcast     #12                 // class org/apache/hadoop/hbase/security/visibility/expression/NonLeafExpressionNode
    2524: astore_2
    2525: getstatic     #38                 // Field org/apache/hadoop/hbase/security/visibility/expression/Operator.NOT:Lorg/apache/hadoop/hbase/security/visibility/expression/Operator;
    2528: aload_2
    2529: invokevirtual #14                 // Method org/apache/hadoop/hbase/security/visibility/expression/NonLeafExpressionNode.getOperator:()Lorg/apache/hadoop/hbase/security/visibility/expression/Operator;
    2532: invokestatic  #10                 // Method org/junit/Assert.assertEquals:(Ljava/lang/Object;Ljava/lang/Object;)V
    2535: lconst_1
    2536: aload_2
    2537: invokevirtual #17                 // Method org/apache/hadoop/hbase/security/visibility/expression/NonLeafExpressionNode.getChildExps:()Ljava/util/List;
    2540: invokeinterface #18,  1           // InterfaceMethod java/util/List.size:()I
    2545: i2l
    2546: invokestatic  #19                 // Method org/junit/Assert.assertEquals:(JJ)V
    2549: ldc           #24                 // String b
    2551: aload_2
    2552: invokevirtual #17                 // Method org/apache/hadoop/hbase/security/visibility/expression/NonLeafExpressionNode.getChildExps:()Ljava/util/List;
    2555: iconst_0
    2556: invokeinterface #21,  2           // InterfaceMethod java/util/List.get:(I)Ljava/lang/Object;
    2561: checkcast     #7                  // class org/apache/hadoop/hbase/security/visibility/expression/LeafExpressionNode
    2564: invokevirtual #9                  // Method org/apache/hadoop/hbase/security/visibility/expression/LeafExpressionNode.getIdentifier:()Ljava/lang/String;
    2567: invokestatic  #10                 // Method org/junit/Assert.assertEquals:(Ljava/lang/Object;Ljava/lang/Object;)V
    2570: aload_0
    2571: getfield      #4                  // Field parser:Lorg/apache/hadoop/hbase/security/visibility/ExpressionParser;
    2574: ldc           #45                 // String !((a | b) & !(c & !b))
    2576: invokevirtual #6                  // Method org/apache/hadoop/hbase/security/visibility/ExpressionParser.parse:(Ljava/lang/String;)Lorg/apache/hadoop/hbase/security/visibility/expression/ExpressionNode;
    2579: astore_1
    2580: aload_1
    2581: instanceof    #12                 // class org/apache/hadoop/hbase/security/visibility/expression/NonLeafExpressionNode
    2584: invokestatic  #8                  // Method org/junit/Assert.assertTrue:(Z)V
    2587: aload_1
    2588: checkcast     #12                 // class org/apache/hadoop/hbase/security/visibility/expression/NonLeafExpressionNode
    2591: astore_2
    2592: getstatic     #38                 // Field org/apache/hadoop/hbase/security/visibility/expression/Operator.NOT:Lorg/apache/hadoop/hbase/security/visibility/expression/Operator;
    2595: aload_2
    2596: invokevirtual #14                 // Method org/apache/hadoop/hbase/security/visibility/expression/NonLeafExpressionNode.getOperator:()Lorg/apache/hadoop/hbase/security/visibility/expression/Operator;
    2599: invokestatic  #10                 // Method org/junit/Assert.assertEquals:(Ljava/lang/Object;Ljava/lang/Object;)V
    2602: lconst_1
    2603: aload_2
    2604: invokevirtual #17                 // Method org/apache/hadoop/hbase/security/visibility/expression/NonLeafExpressionNode.getChildExps:()Ljava/util/List;
    2607: invokeinterface #18,  1           // InterfaceMethod java/util/List.size:()I
    2612: i2l
    2613: invokestatic  #19                 // Method org/junit/Assert.assertEquals:(JJ)V
    2616: aload_2
    2617: invokevirtual #17                 // Method org/apache/hadoop/hbase/security/visibility/expression/NonLeafExpressionNode.getChildExps:()Ljava/util/List;
    2620: iconst_0
    2621: invokeinterface #21,  2           // InterfaceMethod java/util/List.get:(I)Ljava/lang/Object;
    2626: checkcast     #12                 // class org/apache/hadoop/hbase/security/visibility/expression/NonLeafExpressionNode
    2629: astore_2
    2630: getstatic     #13                 // Field org/apache/hadoop/hbase/security/visibility/expression/Operator.AND:Lorg/apache/hadoop/hbase/security/visibility/expression/Operator;
    2633: aload_2
    2634: invokevirtual #14                 // Method org/apache/hadoop/hbase/security/visibility/expression/NonLeafExpressionNode.getOperator:()Lorg/apache/hadoop/hbase/security/visibility/expression/Operator;
    2637: invokestatic  #10                 // Method org/junit/Assert.assertEquals:(Ljava/lang/Object;Ljava/lang/Object;)V
    2640: ldc2_w        #15                 // long 2l
    2643: aload_2
    2644: invokevirtual #17                 // Method org/apache/hadoop/hbase/security/visibility/expression/NonLeafExpressionNode.getChildExps:()Ljava/util/List;
    2647: invokeinterface #18,  1           // InterfaceMethod java/util/List.size:()I
    2652: i2l
    2653: invokestatic  #19                 // Method org/junit/Assert.assertEquals:(JJ)V
    2656: aload_2
    2657: invokevirtual #17                 // Method org/apache/hadoop/hbase/security/visibility/expression/NonLeafExpressionNode.getChildExps:()Ljava/util/List;
    2660: iconst_0
    2661: invokeinterface #21,  2           // InterfaceMethod java/util/List.get:(I)Ljava/lang/Object;
    2666: instanceof    #12                 // class org/apache/hadoop/hbase/security/visibility/expression/NonLeafExpressionNode
    2669: invokestatic  #8                  // Method org/junit/Assert.assertTrue:(Z)V
    2672: aload_2
    2673: invokevirtual #17                 // Method org/apache/hadoop/hbase/security/visibility/expression/NonLeafExpressionNode.getChildExps:()Ljava/util/List;
    2676: iconst_1
    2677: invokeinterface #21,  2           // InterfaceMethod java/util/List.get:(I)Ljava/lang/Object;
    2682: instanceof    #12                 // class org/apache/hadoop/hbase/security/visibility/expression/NonLeafExpressionNode
    2685: invokestatic  #8                  // Method org/junit/Assert.assertTrue:(Z)V
    2688: aload_2
    2689: invokevirtual #17                 // Method org/apache/hadoop/hbase/security/visibility/expression/NonLeafExpressionNode.getChildExps:()Ljava/util/List;
    2692: iconst_0
    2693: invokeinterface #21,  2           // InterfaceMethod java/util/List.get:(I)Ljava/lang/Object;
    2698: checkcast     #12                 // class org/apache/hadoop/hbase/security/visibility/expression/NonLeafExpressionNode
    2701: astore_3
    2702: aload_2
    2703: invokevirtual #17                 // Method org/apache/hadoop/hbase/security/visibility/expression/NonLeafExpressionNode.getChildExps:()Ljava/util/List;
    2706: iconst_1
    2707: invokeinterface #21,  2           // InterfaceMethod java/util/List.get:(I)Ljava/lang/Object;
    2712: checkcast     #12                 // class org/apache/hadoop/hbase/security/visibility/expression/NonLeafExpressionNode
    2715: astore        4
    2717: getstatic     #22                 // Field org/apache/hadoop/hbase/security/visibility/expression/Operator.OR:Lorg/apache/hadoop/hbase/security/visibility/expression/Operator;
    2720: aload_3
    2721: invokevirtual #14                 // Method org/apache/hadoop/hbase/security/visibility/expression/NonLeafExpressionNode.getOperator:()Lorg/apache/hadoop/hbase/security/visibility/expression/Operator;
    2724: invokestatic  #10                 // Method org/junit/Assert.assertEquals:(Ljava/lang/Object;Ljava/lang/Object;)V
    2727: ldc           #25                 // String a
    2729: aload_3
    2730: invokevirtual #17                 // Method org/apache/hadoop/hbase/security/visibility/expression/NonLeafExpressionNode.getChildExps:()Ljava/util/List;
    2733: iconst_0
    2734: invokeinterface #21,  2           // InterfaceMethod java/util/List.get:(I)Ljava/lang/Object;
    2739: checkcast     #7                  // class org/apache/hadoop/hbase/security/visibility/expression/LeafExpressionNode
    2742: invokevirtual #9                  // Method org/apache/hadoop/hbase/security/visibility/expression/LeafExpressionNode.getIdentifier:()Ljava/lang/String;
    2745: invokestatic  #10                 // Method org/junit/Assert.assertEquals:(Ljava/lang/Object;Ljava/lang/Object;)V
    2748: ldc           #24                 // String b
    2750: aload_3
    2751: invokevirtual #17                 // Method org/apache/hadoop/hbase/security/visibility/expression/NonLeafExpressionNode.getChildExps:()Ljava/util/List;
    2754: iconst_1
    2755: invokeinterface #21,  2           // InterfaceMethod java/util/List.get:(I)Ljava/lang/Object;
    2760: checkcast     #7                  // class org/apache/hadoop/hbase/security/visibility/expression/LeafExpressionNode
    2763: invokevirtual #9                  // Method org/apache/hadoop/hbase/security/visibility/expression/LeafExpressionNode.getIdentifier:()Ljava/lang/String;
    2766: invokestatic  #10                 // Method org/junit/Assert.assertEquals:(Ljava/lang/Object;Ljava/lang/Object;)V
    2769: getstatic     #38                 // Field org/apache/hadoop/hbase/security/visibility/expression/Operator.NOT:Lorg/apache/hadoop/hbase/security/visibility/expression/Operator;
    2772: aload         4
    2774: invokevirtual #14                 // Method org/apache/hadoop/hbase/security/visibility/expression/NonLeafExpressionNode.getOperator:()Lorg/apache/hadoop/hbase/security/visibility/expression/Operator;
    2777: invokestatic  #10                 // Method org/junit/Assert.assertEquals:(Ljava/lang/Object;Ljava/lang/Object;)V
    2780: lconst_1
    2781: aload         4
    2783: invokevirtual #17                 // Method org/apache/hadoop/hbase/security/visibility/expression/NonLeafExpressionNode.getChildExps:()Ljava/util/List;
    2786: invokeinterface #18,  1           // InterfaceMethod java/util/List.size:()I
    2791: i2l
    2792: invokestatic  #19                 // Method org/junit/Assert.assertEquals:(JJ)V
    2795: aload         4
    2797: invokevirtual #17                 // Method org/apache/hadoop/hbase/security/visibility/expression/NonLeafExpressionNode.getChildExps:()Ljava/util/List;
    2800: iconst_0
    2801: invokeinterface #21,  2           // InterfaceMethod java/util/List.get:(I)Ljava/lang/Object;
    2806: checkcast     #12                 // class org/apache/hadoop/hbase/security/visibility/expression/NonLeafExpressionNode
    2809: astore        4
    2811: getstatic     #13                 // Field org/apache/hadoop/hbase/security/visibility/expression/Operator.AND:Lorg/apache/hadoop/hbase/security/visibility/expression/Operator;
    2814: aload         4
    2816: invokevirtual #14                 // Method org/apache/hadoop/hbase/security/visibility/expression/NonLeafExpressionNode.getOperator:()Lorg/apache/hadoop/hbase/security/visibility/expression/Operator;
    2819: invokestatic  #10                 // Method org/junit/Assert.assertEquals:(Ljava/lang/Object;Ljava/lang/Object;)V
    2822: ldc2_w        #15                 // long 2l
    2825: aload         4
    2827: invokevirtual #17                 // Method org/apache/hadoop/hbase/security/visibility/expression/NonLeafExpressionNode.getChildExps:()Ljava/util/List;
    2830: invokeinterface #18,  1           // InterfaceMethod java/util/List.size:()I
    2835: i2l
    2836: invokestatic  #19                 // Method org/junit/Assert.assertEquals:(JJ)V
    2839: ldc           #23                 // String c
    2841: aload         4
    2843: invokevirtual #17                 // Method org/apache/hadoop/hbase/security/visibility/expression/NonLeafExpressionNode.getChildExps:()Ljava/util/List;
    2846: iconst_0
    2847: invokeinterface #21,  2           // InterfaceMethod java/util/List.get:(I)Ljava/lang/Object;
    2852: checkcast     #7                  // class org/apache/hadoop/hbase/security/visibility/expression/LeafExpressionNode
    2855: invokevirtual #9                  // Method org/apache/hadoop/hbase/security/visibility/expression/LeafExpressionNode.getIdentifier:()Ljava/lang/String;
    2858: invokestatic  #10                 // Method org/junit/Assert.assertEquals:(Ljava/lang/Object;Ljava/lang/Object;)V
    2861: aload         4
    2863: invokevirtual #17                 // Method org/apache/hadoop/hbase/security/visibility/expression/NonLeafExpressionNode.getChildExps:()Ljava/util/List;
    2866: iconst_1
    2867: invokeinterface #21,  2           // InterfaceMethod java/util/List.get:(I)Ljava/lang/Object;
    2872: instanceof    #12                 // class org/apache/hadoop/hbase/security/visibility/expression/NonLeafExpressionNode
    2875: invokestatic  #8                  // Method org/junit/Assert.assertTrue:(Z)V
    2878: aload         4
    2880: invokevirtual #17                 // Method org/apache/hadoop/hbase/security/visibility/expression/NonLeafExpressionNode.getChildExps:()Ljava/util/List;
    2883: iconst_1
    2884: invokeinterface #21,  2           // InterfaceMethod java/util/List.get:(I)Ljava/lang/Object;
    2889: checkcast     #12                 // class org/apache/hadoop/hbase/security/visibility/expression/NonLeafExpressionNode
    2892: astore        4
    2894: getstatic     #38                 // Field org/apache/hadoop/hbase/security/visibility/expression/Operator.NOT:Lorg/apache/hadoop/hbase/security/visibility/expression/Operator;
    2897: aload         4
    2899: invokevirtual #14                 // Method org/apache/hadoop/hbase/security/visibility/expression/NonLeafExpressionNode.getOperator:()Lorg/apache/hadoop/hbase/security/visibility/expression/Operator;
    2902: invokestatic  #10                 // Method org/junit/Assert.assertEquals:(Ljava/lang/Object;Ljava/lang/Object;)V
    2905: lconst_1
    2906: aload         4
    2908: invokevirtual #17                 // Method org/apache/hadoop/hbase/security/visibility/expression/NonLeafExpressionNode.getChildExps:()Ljava/util/List;
    2911: invokeinterface #18,  1           // InterfaceMethod java/util/List.size:()I
    2916: i2l
    2917: invokestatic  #19                 // Method org/junit/Assert.assertEquals:(JJ)V
    2920: ldc           #24                 // String b
    2922: aload         4
    2924: invokevirtual #17                 // Method org/apache/hadoop/hbase/security/visibility/expression/NonLeafExpressionNode.getChildExps:()Ljava/util/List;
    2927: iconst_0
    2928: invokeinterface #21,  2           // InterfaceMethod java/util/List.get:(I)Ljava/lang/Object;
    2933: checkcast     #7                  // class org/apache/hadoop/hbase/security/visibility/expression/LeafExpressionNode
    2936: invokevirtual #9                  // Method org/apache/hadoop/hbase/security/visibility/expression/LeafExpressionNode.getIdentifier:()Ljava/lang/String;
    2939: invokestatic  #10                 // Method org/junit/Assert.assertEquals:(Ljava/lang/Object;Ljava/lang/Object;)V
    2942: return

  public void testNegativeCases() throws java.lang.Exception;
    Code:
       0: aload_0
       1: ldc           #46                 // String (
       3: invokespecial #47                 // Method executeNegativeCase:(Ljava/lang/String;)V
       6: aload_0
       7: ldc           #48                 // String )
       9: invokespecial #47                 // Method executeNegativeCase:(Ljava/lang/String;)V
      12: aload_0
      13: ldc           #49                 // String ()
      15: invokespecial #47                 // Method executeNegativeCase:(Ljava/lang/String;)V
      18: aload_0
      19: ldc           #50                 // String (a
      21: invokespecial #47                 // Method executeNegativeCase:(Ljava/lang/String;)V
      24: aload_0
      25: ldc           #51                 // String a&
      27: invokespecial #47                 // Method executeNegativeCase:(Ljava/lang/String;)V
      30: aload_0
      31: ldc           #52                 // String a&|b
      33: invokespecial #47                 // Method executeNegativeCase:(Ljava/lang/String;)V
      36: aload_0
      37: ldc           #53                 // String !
      39: invokespecial #47                 // Method executeNegativeCase:(Ljava/lang/String;)V
      42: aload_0
      43: ldc           #54                 // String a!
      45: invokespecial #47                 // Method executeNegativeCase:(Ljava/lang/String;)V
      48: aload_0
      49: ldc           #55                 // String a!&
      51: invokespecial #47                 // Method executeNegativeCase:(Ljava/lang/String;)V
      54: aload_0
      55: ldc           #56                 // String &
      57: invokespecial #47                 // Method executeNegativeCase:(Ljava/lang/String;)V
      60: aload_0
      61: ldc           #57                 // String |
      63: invokespecial #47                 // Method executeNegativeCase:(Ljava/lang/String;)V
      66: aload_0
      67: ldc           #58                 // String !(a|(b&c)&!b
      69: invokespecial #47                 // Method executeNegativeCase:(Ljava/lang/String;)V
      72: aload_0
      73: ldc           #59                 // String !!a
      75: invokespecial #47                 // Method executeNegativeCase:(Ljava/lang/String;)V
      78: aload_0
      79: ldc           #60                 // String ( a & b ) | ( c & d e)
      81: invokespecial #47                 // Method executeNegativeCase:(Ljava/lang/String;)V
      84: aload_0
      85: ldc           #61                 // String ! a
      87: invokespecial #47                 // Method executeNegativeCase:(Ljava/lang/String;)V
      90: return

  public void testNonAsciiCases() throws java.lang.Exception;
    Code:
       0: aload_0
       1: getfield      #4                  // Field parser:Lorg/apache/hadoop/hbase/security/visibility/ExpressionParser;
       4: new           #62                 // class java/lang/StringBuilder
       7: dup
       8: invokespecial #63                 // Method java/lang/StringBuilder."<init>":()V
      11: ldc           #64                 // String '
      13: invokestatic  #65                 // Method org/apache/hadoop/hbase/security/visibility/CellVisibility.quote:(Ljava/lang/String;)Ljava/lang/String;
      16: invokevirtual #66                 // Method java/lang/StringBuilder.append:(Ljava/lang/String;)Ljava/lang/StringBuilder;
      19: ldc           #56                 // String &
      21: invokevirtual #66                 // Method java/lang/StringBuilder.append:(Ljava/lang/String;)Ljava/lang/StringBuilder;
      24: ldc           #67                 // String +
      26: invokestatic  #65                 // Method org/apache/hadoop/hbase/security/visibility/CellVisibility.quote:(Ljava/lang/String;)Ljava/lang/String;
      29: invokevirtual #66                 // Method java/lang/StringBuilder.append:(Ljava/lang/String;)Ljava/lang/StringBuilder;
      32: ldc           #57                 // String |
      34: invokevirtual #66                 // Method java/lang/StringBuilder.append:(Ljava/lang/String;)Ljava/lang/StringBuilder;
      37: ldc           #68                 // String -
      39: invokestatic  #65                 // Method org/apache/hadoop/hbase/security/visibility/CellVisibility.quote:(Ljava/lang/String;)Ljava/lang/String;
      42: invokevirtual #66                 // Method java/lang/StringBuilder.append:(Ljava/lang/String;)Ljava/lang/StringBuilder;
      45: ldc           #56                 // String &
      47: invokevirtual #66                 // Method java/lang/StringBuilder.append:(Ljava/lang/String;)Ljava/lang/StringBuilder;
      50: ldc           #69                 // String ?
      52: invokestatic  #65                 // Method org/apache/hadoop/hbase/security/visibility/CellVisibility.quote:(Ljava/lang/String;)Ljava/lang/String;
      55: invokevirtual #66                 // Method java/lang/StringBuilder.append:(Ljava/lang/String;)Ljava/lang/StringBuilder;
      58: invokevirtual #70                 // Method java/lang/StringBuilder.toString:()Ljava/lang/String;
      61: invokevirtual #6                  // Method org/apache/hadoop/hbase/security/visibility/ExpressionParser.parse:(Ljava/lang/String;)Lorg/apache/hadoop/hbase/security/visibility/expression/ExpressionNode;
      64: astore_1
      65: aload_1
      66: instanceof    #12                 // class org/apache/hadoop/hbase/security/visibility/expression/NonLeafExpressionNode
      69: invokestatic  #8                  // Method org/junit/Assert.assertTrue:(Z)V
      72: aload_1
      73: checkcast     #12                 // class org/apache/hadoop/hbase/security/visibility/expression/NonLeafExpressionNode
      76: astore_2
      77: getstatic     #13                 // Field org/apache/hadoop/hbase/security/visibility/expression/Operator.AND:Lorg/apache/hadoop/hbase/security/visibility/expression/Operator;
      80: aload_2
      81: invokevirtual #14                 // Method org/apache/hadoop/hbase/security/visibility/expression/NonLeafExpressionNode.getOperator:()Lorg/apache/hadoop/hbase/security/visibility/expression/Operator;
      84: invokestatic  #10                 // Method org/junit/Assert.assertEquals:(Ljava/lang/Object;Ljava/lang/Object;)V
      87: ldc2_w        #15                 // long 2l
      90: aload_2
      91: invokevirtual #17                 // Method org/apache/hadoop/hbase/security/visibility/expression/NonLeafExpressionNode.getChildExps:()Ljava/util/List;
      94: invokeinterface #18,  1           // InterfaceMethod java/util/List.size:()I
      99: i2l
     100: invokestatic  #19                 // Method org/junit/Assert.assertEquals:(JJ)V
     103: ldc           #69                 // String ?
     105: aload_2
     106: invokevirtual #17                 // Method org/apache/hadoop/hbase/security/visibility/expression/NonLeafExpressionNode.getChildExps:()Ljava/util/List;
     109: iconst_1
     110: invokeinterface #21,  2           // InterfaceMethod java/util/List.get:(I)Ljava/lang/Object;
     115: checkcast     #7                  // class org/apache/hadoop/hbase/security/visibility/expression/LeafExpressionNode
     118: invokevirtual #9                  // Method org/apache/hadoop/hbase/security/visibility/expression/LeafExpressionNode.getIdentifier:()Ljava/lang/String;
     121: invokestatic  #10                 // Method org/junit/Assert.assertEquals:(Ljava/lang/Object;Ljava/lang/Object;)V
     124: aload_2
     125: invokevirtual #17                 // Method org/apache/hadoop/hbase/security/visibility/expression/NonLeafExpressionNode.getChildExps:()Ljava/util/List;
     128: iconst_0
     129: invokeinterface #21,  2           // InterfaceMethod java/util/List.get:(I)Ljava/lang/Object;
     134: instanceof    #12                 // class org/apache/hadoop/hbase/security/visibility/expression/NonLeafExpressionNode
     137: invokestatic  #8                  // Method org/junit/Assert.assertTrue:(Z)V
     140: aload_2
     141: invokevirtual #17                 // Method org/apache/hadoop/hbase/security/visibility/expression/NonLeafExpressionNode.getChildExps:()Ljava/util/List;
     144: iconst_0
     145: invokeinterface #21,  2           // InterfaceMethod java/util/List.get:(I)Ljava/lang/Object;
     150: checkcast     #12                 // class org/apache/hadoop/hbase/security/visibility/expression/NonLeafExpressionNode
     153: astore_2
     154: getstatic     #22                 // Field org/apache/hadoop/hbase/security/visibility/expression/Operator.OR:Lorg/apache/hadoop/hbase/security/visibility/expression/Operator;
     157: aload_2
     158: invokevirtual #14                 // Method org/apache/hadoop/hbase/security/visibility/expression/NonLeafExpressionNode.getOperator:()Lorg/apache/hadoop/hbase/security/visibility/expression/Operator;
     161: invokestatic  #10                 // Method org/junit/Assert.assertEquals:(Ljava/lang/Object;Ljava/lang/Object;)V
     164: ldc2_w        #15                 // long 2l
     167: aload_2
     168: invokevirtual #17                 // Method org/apache/hadoop/hbase/security/visibility/expression/NonLeafExpressionNode.getChildExps:()Ljava/util/List;
     171: invokeinterface #18,  1           // InterfaceMethod java/util/List.size:()I
     176: i2l
     177: invokestatic  #19                 // Method org/junit/Assert.assertEquals:(JJ)V
     180: ldc           #68                 // String -
     182: aload_2
     183: invokevirtual #17                 // Method org/apache/hadoop/hbase/security/visibility/expression/NonLeafExpressionNode.getChildExps:()Ljava/util/List;
     186: iconst_1
     187: invokeinterface #21,  2           // InterfaceMethod java/util/List.get:(I)Ljava/lang/Object;
     192: checkcast     #7                  // class org/apache/hadoop/hbase/security/visibility/expression/LeafExpressionNode
     195: invokevirtual #9                  // Method org/apache/hadoop/hbase/security/visibility/expression/LeafExpressionNode.getIdentifier:()Ljava/lang/String;
     198: invokestatic  #10                 // Method org/junit/Assert.assertEquals:(Ljava/lang/Object;Ljava/lang/Object;)V
     201: aload_2
     202: invokevirtual #17                 // Method org/apache/hadoop/hbase/security/visibility/expression/NonLeafExpressionNode.getChildExps:()Ljava/util/List;
     205: iconst_0
     206: invokeinterface #21,  2           // InterfaceMethod java/util/List.get:(I)Ljava/lang/Object;
     211: instanceof    #12                 // class org/apache/hadoop/hbase/security/visibility/expression/NonLeafExpressionNode
     214: invokestatic  #8                  // Method org/junit/Assert.assertTrue:(Z)V
     217: aload_2
     218: invokevirtual #17                 // Method org/apache/hadoop/hbase/security/visibility/expression/NonLeafExpressionNode.getChildExps:()Ljava/util/List;
     221: iconst_0
     222: invokeinterface #21,  2           // InterfaceMethod java/util/List.get:(I)Ljava/lang/Object;
     227: checkcast     #12                 // class org/apache/hadoop/hbase/security/visibility/expression/NonLeafExpressionNode
     230: astore_2
     231: getstatic     #13                 // Field org/apache/hadoop/hbase/security/visibility/expression/Operator.AND:Lorg/apache/hadoop/hbase/security/visibility/expression/Operator;
     234: aload_2
     235: invokevirtual #14                 // Method org/apache/hadoop/hbase/security/visibility/expression/NonLeafExpressionNode.getOperator:()Lorg/apache/hadoop/hbase/security/visibility/expression/Operator;
     238: invokestatic  #10                 // Method org/junit/Assert.assertEquals:(Ljava/lang/Object;Ljava/lang/Object;)V
     241: ldc2_w        #15                 // long 2l
     244: aload_2
     245: invokevirtual #17                 // Method org/apache/hadoop/hbase/security/visibility/expression/NonLeafExpressionNode.getChildExps:()Ljava/util/List;
     248: invokeinterface #18,  1           // InterfaceMethod java/util/List.size:()I
     253: i2l
     254: invokestatic  #19                 // Method org/junit/Assert.assertEquals:(JJ)V
     257: ldc           #67                 // String +
     259: aload_2
     260: invokevirtual #17                 // Method org/apache/hadoop/hbase/security/visibility/expression/NonLeafExpressionNode.getChildExps:()Ljava/util/List;
     263: iconst_1
     264: invokeinterface #21,  2           // InterfaceMethod java/util/List.get:(I)Ljava/lang/Object;
     269: checkcast     #7                  // class org/apache/hadoop/hbase/security/visibility/expression/LeafExpressionNode
     272: invokevirtual #9                  // Method org/apache/hadoop/hbase/security/visibility/expression/LeafExpressionNode.getIdentifier:()Ljava/lang/String;
     275: invokestatic  #10                 // Method org/junit/Assert.assertEquals:(Ljava/lang/Object;Ljava/lang/Object;)V
     278: ldc           #64                 // String '
     280: aload_2
     281: invokevirtual #17                 // Method org/apache/hadoop/hbase/security/visibility/expression/NonLeafExpressionNode.getChildExps:()Ljava/util/List;
     284: iconst_0
     285: invokeinterface #21,  2           // InterfaceMethod java/util/List.get:(I)Ljava/lang/Object;
     290: checkcast     #7                  // class org/apache/hadoop/hbase/security/visibility/expression/LeafExpressionNode
     293: invokevirtual #9                  // Method org/apache/hadoop/hbase/security/visibility/expression/LeafExpressionNode.getIdentifier:()Ljava/lang/String;
     296: invokestatic  #10                 // Method org/junit/Assert.assertEquals:(Ljava/lang/Object;Ljava/lang/Object;)V
     299: aload_0
     300: getfield      #4                  // Field parser:Lorg/apache/hadoop/hbase/security/visibility/ExpressionParser;
     303: new           #62                 // class java/lang/StringBuilder
     306: dup
     307: invokespecial #63                 // Method java/lang/StringBuilder."<init>":()V
     310: ldc           #64                 // String '
     312: invokestatic  #65                 // Method org/apache/hadoop/hbase/security/visibility/CellVisibility.quote:(Ljava/lang/String;)Ljava/lang/String;
     315: invokevirtual #66                 // Method java/lang/StringBuilder.append:(Ljava/lang/String;)Ljava/lang/StringBuilder;
     318: ldc           #56                 // String &
     320: invokevirtual #66                 // Method java/lang/StringBuilder.append:(Ljava/lang/String;)Ljava/lang/StringBuilder;
     323: ldc           #67                 // String +
     325: invokestatic  #65                 // Method org/apache/hadoop/hbase/security/visibility/CellVisibility.quote:(Ljava/lang/String;)Ljava/lang/String;
     328: invokevirtual #66                 // Method java/lang/StringBuilder.append:(Ljava/lang/String;)Ljava/lang/StringBuilder;
     331: ldc           #57                 // String |
     333: invokevirtual #66                 // Method java/lang/StringBuilder.append:(Ljava/lang/String;)Ljava/lang/StringBuilder;
     336: ldc           #68                 // String -
     338: invokestatic  #65                 // Method org/apache/hadoop/hbase/security/visibility/CellVisibility.quote:(Ljava/lang/String;)Ljava/lang/String;
     341: invokevirtual #66                 // Method java/lang/StringBuilder.append:(Ljava/lang/String;)Ljava/lang/StringBuilder;
     344: ldc           #56                 // String &
     346: invokevirtual #66                 // Method java/lang/StringBuilder.append:(Ljava/lang/String;)Ljava/lang/StringBuilder;
     349: ldc           #69                 // String ?
     351: invokestatic  #65                 // Method org/apache/hadoop/hbase/security/visibility/CellVisibility.quote:(Ljava/lang/String;)Ljava/lang/String;
     354: invokevirtual #66                 // Method java/lang/StringBuilder.append:(Ljava/lang/String;)Ljava/lang/StringBuilder;
     357: invokevirtual #70                 // Method java/lang/StringBuilder.toString:()Ljava/lang/String;
     360: invokevirtual #6                  // Method org/apache/hadoop/hbase/security/visibility/ExpressionParser.parse:(Ljava/lang/String;)Lorg/apache/hadoop/hbase/security/visibility/expression/ExpressionNode;
     363: astore_1
     364: aload_1
     365: instanceof    #12                 // class org/apache/hadoop/hbase/security/visibility/expression/NonLeafExpressionNode
     368: invokestatic  #8                  // Method org/junit/Assert.assertTrue:(Z)V
     371: aload_1
     372: checkcast     #12                 // class org/apache/hadoop/hbase/security/visibility/expression/NonLeafExpressionNode
     375: astore_2
     376: getstatic     #13                 // Field org/apache/hadoop/hbase/security/visibility/expression/Operator.AND:Lorg/apache/hadoop/hbase/security/visibility/expression/Operator;
     379: aload_2
     380: invokevirtual #14                 // Method org/apache/hadoop/hbase/security/visibility/expression/NonLeafExpressionNode.getOperator:()Lorg/apache/hadoop/hbase/security/visibility/expression/Operator;
     383: invokestatic  #10                 // Method org/junit/Assert.assertEquals:(Ljava/lang/Object;Ljava/lang/Object;)V
     386: ldc2_w        #15                 // long 2l
     389: aload_2
     390: invokevirtual #17                 // Method org/apache/hadoop/hbase/security/visibility/expression/NonLeafExpressionNode.getChildExps:()Ljava/util/List;
     393: invokeinterface #18,  1           // InterfaceMethod java/util/List.size:()I
     398: i2l
     399: invokestatic  #19                 // Method org/junit/Assert.assertEquals:(JJ)V
     402: ldc           #69                 // String ?
     404: aload_2
     405: invokevirtual #17                 // Method org/apache/hadoop/hbase/security/visibility/expression/NonLeafExpressionNode.getChildExps:()Ljava/util/List;
     408: iconst_1
     409: invokeinterface #21,  2           // InterfaceMethod java/util/List.get:(I)Ljava/lang/Object;
     414: checkcast     #7                  // class org/apache/hadoop/hbase/security/visibility/expression/LeafExpressionNode
     417: invokevirtual #9                  // Method org/apache/hadoop/hbase/security/visibility/expression/LeafExpressionNode.getIdentifier:()Ljava/lang/String;
     420: invokestatic  #10                 // Method org/junit/Assert.assertEquals:(Ljava/lang/Object;Ljava/lang/Object;)V
     423: aload_2
     424: invokevirtual #17                 // Method org/apache/hadoop/hbase/security/visibility/expression/NonLeafExpressionNode.getChildExps:()Ljava/util/List;
     427: iconst_0
     428: invokeinterface #21,  2           // InterfaceMethod java/util/List.get:(I)Ljava/lang/Object;
     433: instanceof    #12                 // class org/apache/hadoop/hbase/security/visibility/expression/NonLeafExpressionNode
     436: invokestatic  #8                  // Method org/junit/Assert.assertTrue:(Z)V
     439: aload_2
     440: invokevirtual #17                 // Method org/apache/hadoop/hbase/security/visibility/expression/NonLeafExpressionNode.getChildExps:()Ljava/util/List;
     443: iconst_0
     444: invokeinterface #21,  2           // InterfaceMethod java/util/List.get:(I)Ljava/lang/Object;
     449: checkcast     #12                 // class org/apache/hadoop/hbase/security/visibility/expression/NonLeafExpressionNode
     452: astore_2
     453: getstatic     #22                 // Field org/apache/hadoop/hbase/security/visibility/expression/Operator.OR:Lorg/apache/hadoop/hbase/security/visibility/expression/Operator;
     456: aload_2
     457: invokevirtual #14                 // Method org/apache/hadoop/hbase/security/visibility/expression/NonLeafExpressionNode.getOperator:()Lorg/apache/hadoop/hbase/security/visibility/expression/Operator;
     460: invokestatic  #10                 // Method org/junit/Assert.assertEquals:(Ljava/lang/Object;Ljava/lang/Object;)V
     463: ldc2_w        #15                 // long 2l
     466: aload_2
     467: invokevirtual #17                 // Method org/apache/hadoop/hbase/security/visibility/expression/NonLeafExpressionNode.getChildExps:()Ljava/util/List;
     470: invokeinterface #18,  1           // InterfaceMethod java/util/List.size:()I
     475: i2l
     476: invokestatic  #19                 // Method org/junit/Assert.assertEquals:(JJ)V
     479: ldc           #68                 // String -
     481: aload_2
     482: invokevirtual #17                 // Method org/apache/hadoop/hbase/security/visibility/expression/NonLeafExpressionNode.getChildExps:()Ljava/util/List;
     485: iconst_1
     486: invokeinterface #21,  2           // InterfaceMethod java/util/List.get:(I)Ljava/lang/Object;
     491: checkcast     #7                  // class org/apache/hadoop/hbase/security/visibility/expression/LeafExpressionNode
     494: invokevirtual #9                  // Method org/apache/hadoop/hbase/security/visibility/expression/LeafExpressionNode.getIdentifier:()Ljava/lang/String;
     497: invokestatic  #10                 // Method org/junit/Assert.assertEquals:(Ljava/lang/Object;Ljava/lang/Object;)V
     500: aload_2
     501: invokevirtual #17                 // Method org/apache/hadoop/hbase/security/visibility/expression/NonLeafExpressionNode.getChildExps:()Ljava/util/List;
     504: iconst_0
     505: invokeinterface #21,  2           // InterfaceMethod java/util/List.get:(I)Ljava/lang/Object;
     510: instanceof    #12                 // class org/apache/hadoop/hbase/security/visibility/expression/NonLeafExpressionNode
     513: invokestatic  #8                  // Method org/junit/Assert.assertTrue:(Z)V
     516: aload_2
     517: invokevirtual #17                 // Method org/apache/hadoop/hbase/security/visibility/expression/NonLeafExpressionNode.getChildExps:()Ljava/util/List;
     520: iconst_0
     521: invokeinterface #21,  2           // InterfaceMethod java/util/List.get:(I)Ljava/lang/Object;
     526: checkcast     #12                 // class org/apache/hadoop/hbase/security/visibility/expression/NonLeafExpressionNode
     529: astore_2
     530: getstatic     #13                 // Field org/apache/hadoop/hbase/security/visibility/expression/Operator.AND:Lorg/apache/hadoop/hbase/security/visibility/expression/Operator;
     533: aload_2
     534: invokevirtual #14                 // Method org/apache/hadoop/hbase/security/visibility/expression/NonLeafExpressionNode.getOperator:()Lorg/apache/hadoop/hbase/security/visibility/expression/Operator;
     537: invokestatic  #10                 // Method org/junit/Assert.assertEquals:(Ljava/lang/Object;Ljava/lang/Object;)V
     540: ldc2_w        #15                 // long 2l
     543: aload_2
     544: invokevirtual #17                 // Method org/apache/hadoop/hbase/security/visibility/expression/NonLeafExpressionNode.getChildExps:()Ljava/util/List;
     547: invokeinterface #18,  1           // InterfaceMethod java/util/List.size:()I
     552: i2l
     553: invokestatic  #19                 // Method org/junit/Assert.assertEquals:(JJ)V
     556: ldc           #67                 // String +
     558: aload_2
     559: invokevirtual #17                 // Method org/apache/hadoop/hbase/security/visibility/expression/NonLeafExpressionNode.getChildExps:()Ljava/util/List;
     562: iconst_1
     563: invokeinterface #21,  2           // InterfaceMethod java/util/List.get:(I)Ljava/lang/Object;
     568: checkcast     #7                  // class org/apache/hadoop/hbase/security/visibility/expression/LeafExpressionNode
     571: invokevirtual #9                  // Method org/apache/hadoop/hbase/security/visibility/expression/LeafExpressionNode.getIdentifier:()Ljava/lang/String;
     574: invokestatic  #10                 // Method org/junit/Assert.assertEquals:(Ljava/lang/Object;Ljava/lang/Object;)V
     577: ldc           #64                 // String '
     579: aload_2
     580: invokevirtual #17                 // Method org/apache/hadoop/hbase/security/visibility/expression/NonLeafExpressionNode.getChildExps:()Ljava/util/List;
     583: iconst_0
     584: invokeinterface #21,  2           // InterfaceMethod java/util/List.get:(I)Ljava/lang/Object;
     589: checkcast     #7                  // class org/apache/hadoop/hbase/security/visibility/expression/LeafExpressionNode
     592: invokevirtual #9                  // Method org/apache/hadoop/hbase/security/visibility/expression/LeafExpressionNode.getIdentifier:()Ljava/lang/String;
     595: invokestatic  #10                 // Method org/junit/Assert.assertEquals:(Ljava/lang/Object;Ljava/lang/Object;)V
     598: return

  public void testCasesSeperatedByDoubleQuotes() throws java.lang.Exception;
    Code:
       0: aconst_null
       1: astore_1
       2: aload_0
       3: getfield      #4                  // Field parser:Lorg/apache/hadoop/hbase/security/visibility/ExpressionParser;
       6: ldc           #71                 // String '&\"|+&?
       8: invokevirtual #6                  // Method org/apache/hadoop/hbase/security/visibility/ExpressionParser.parse:(Ljava/lang/String;)Lorg/apache/hadoop/hbase/security/visibility/expression/ExpressionNode;
      11: astore_1
      12: ldc           #72                 // String Excpetion must be thrown as there are special characters without quotes
      14: invokestatic  #73                 // Method org/junit/Assert.fail:(Ljava/lang/String;)V
      17: goto          21
      20: astore_2
      21: aload_0
      22: getfield      #4                  // Field parser:Lorg/apache/hadoop/hbase/security/visibility/ExpressionParser;
      25: new           #62                 // class java/lang/StringBuilder
      28: dup
      29: invokespecial #63                 // Method java/lang/StringBuilder."<init>":()V
      32: ldc           #64                 // String '
      34: invokestatic  #65                 // Method org/apache/hadoop/hbase/security/visibility/CellVisibility.quote:(Ljava/lang/String;)Ljava/lang/String;
      37: invokevirtual #66                 // Method java/lang/StringBuilder.append:(Ljava/lang/String;)Ljava/lang/StringBuilder;
      40: ldc           #56                 // String &
      42: invokevirtual #66                 // Method java/lang/StringBuilder.append:(Ljava/lang/String;)Ljava/lang/StringBuilder;
      45: ldc           #75                 // String \"
      47: invokestatic  #65                 // Method org/apache/hadoop/hbase/security/visibility/CellVisibility.quote:(Ljava/lang/String;)Ljava/lang/String;
      50: invokevirtual #66                 // Method java/lang/StringBuilder.append:(Ljava/lang/String;)Ljava/lang/StringBuilder;
      53: ldc           #57                 // String |
      55: invokevirtual #66                 // Method java/lang/StringBuilder.append:(Ljava/lang/String;)Ljava/lang/StringBuilder;
      58: ldc           #76                 // String +&?
      60: invokestatic  #65                 // Method org/apache/hadoop/hbase/security/visibility/CellVisibility.quote:(Ljava/lang/String;)Ljava/lang/String;
      63: invokevirtual #66                 // Method java/lang/StringBuilder.append:(Ljava/lang/String;)Ljava/lang/StringBuilder;
      66: invokevirtual #70                 // Method java/lang/StringBuilder.toString:()Ljava/lang/String;
      69: invokevirtual #6                  // Method org/apache/hadoop/hbase/security/visibility/ExpressionParser.parse:(Ljava/lang/String;)Lorg/apache/hadoop/hbase/security/visibility/expression/ExpressionNode;
      72: astore_1
      73: aload_1
      74: instanceof    #12                 // class org/apache/hadoop/hbase/security/visibility/expression/NonLeafExpressionNode
      77: invokestatic  #8                  // Method org/junit/Assert.assertTrue:(Z)V
      80: aload_1
      81: checkcast     #12                 // class org/apache/hadoop/hbase/security/visibility/expression/NonLeafExpressionNode
      84: astore_2
      85: getstatic     #22                 // Field org/apache/hadoop/hbase/security/visibility/expression/Operator.OR:Lorg/apache/hadoop/hbase/security/visibility/expression/Operator;
      88: aload_2
      89: invokevirtual #14                 // Method org/apache/hadoop/hbase/security/visibility/expression/NonLeafExpressionNode.getOperator:()Lorg/apache/hadoop/hbase/security/visibility/expression/Operator;
      92: invokestatic  #10                 // Method org/junit/Assert.assertEquals:(Ljava/lang/Object;Ljava/lang/Object;)V
      95: ldc2_w        #15                 // long 2l
      98: aload_2
      99: invokevirtual #17                 // Method org/apache/hadoop/hbase/security/visibility/expression/NonLeafExpressionNode.getChildExps:()Ljava/util/List;
     102: invokeinterface #18,  1           // InterfaceMethod java/util/List.size:()I
     107: i2l
     108: invokestatic  #19                 // Method org/junit/Assert.assertEquals:(JJ)V
     111: ldc           #76                 // String +&?
     113: aload_2
     114: invokevirtual #17                 // Method org/apache/hadoop/hbase/security/visibility/expression/NonLeafExpressionNode.getChildExps:()Ljava/util/List;
     117: iconst_1
     118: invokeinterface #21,  2           // InterfaceMethod java/util/List.get:(I)Ljava/lang/Object;
     123: checkcast     #7                  // class org/apache/hadoop/hbase/security/visibility/expression/LeafExpressionNode
     126: invokevirtual #9                  // Method org/apache/hadoop/hbase/security/visibility/expression/LeafExpressionNode.getIdentifier:()Ljava/lang/String;
     129: invokestatic  #10                 // Method org/junit/Assert.assertEquals:(Ljava/lang/Object;Ljava/lang/Object;)V
     132: aload_2
     133: invokevirtual #17                 // Method org/apache/hadoop/hbase/security/visibility/expression/NonLeafExpressionNode.getChildExps:()Ljava/util/List;
     136: iconst_0
     137: invokeinterface #21,  2           // InterfaceMethod java/util/List.get:(I)Ljava/lang/Object;
     142: instanceof    #12                 // class org/apache/hadoop/hbase/security/visibility/expression/NonLeafExpressionNode
     145: invokestatic  #8                  // Method org/junit/Assert.assertTrue:(Z)V
     148: aload_2
     149: invokevirtual #17                 // Method org/apache/hadoop/hbase/security/visibility/expression/NonLeafExpressionNode.getChildExps:()Ljava/util/List;
     152: iconst_0
     153: invokeinterface #21,  2           // InterfaceMethod java/util/List.get:(I)Ljava/lang/Object;
     158: checkcast     #12                 // class org/apache/hadoop/hbase/security/visibility/expression/NonLeafExpressionNode
     161: astore_2
     162: getstatic     #13                 // Field org/apache/hadoop/hbase/security/visibility/expression/Operator.AND:Lorg/apache/hadoop/hbase/security/visibility/expression/Operator;
     165: aload_2
     166: invokevirtual #14                 // Method org/apache/hadoop/hbase/security/visibility/expression/NonLeafExpressionNode.getOperator:()Lorg/apache/hadoop/hbase/security/visibility/expression/Operator;
     169: invokestatic  #10                 // Method org/junit/Assert.assertEquals:(Ljava/lang/Object;Ljava/lang/Object;)V
     172: ldc2_w        #15                 // long 2l
     175: aload_2
     176: invokevirtual #17                 // Method org/apache/hadoop/hbase/security/visibility/expression/NonLeafExpressionNode.getChildExps:()Ljava/util/List;
     179: invokeinterface #18,  1           // InterfaceMethod java/util/List.size:()I
     184: i2l
     185: invokestatic  #19                 // Method org/junit/Assert.assertEquals:(JJ)V
     188: ldc           #75                 // String \"
     190: aload_2
     191: invokevirtual #17                 // Method org/apache/hadoop/hbase/security/visibility/expression/NonLeafExpressionNode.getChildExps:()Ljava/util/List;
     194: iconst_1
     195: invokeinterface #21,  2           // InterfaceMethod java/util/List.get:(I)Ljava/lang/Object;
     200: checkcast     #7                  // class org/apache/hadoop/hbase/security/visibility/expression/LeafExpressionNode
     203: invokevirtual #9                  // Method org/apache/hadoop/hbase/security/visibility/expression/LeafExpressionNode.getIdentifier:()Ljava/lang/String;
     206: invokestatic  #10                 // Method org/junit/Assert.assertEquals:(Ljava/lang/Object;Ljava/lang/Object;)V
     209: ldc           #64                 // String '
     211: aload_2
     212: invokevirtual #17                 // Method org/apache/hadoop/hbase/security/visibility/expression/NonLeafExpressionNode.getChildExps:()Ljava/util/List;
     215: iconst_0
     216: invokeinterface #21,  2           // InterfaceMethod java/util/List.get:(I)Ljava/lang/Object;
     221: checkcast     #7                  // class org/apache/hadoop/hbase/security/visibility/expression/LeafExpressionNode
     224: invokevirtual #9                  // Method org/apache/hadoop/hbase/security/visibility/expression/LeafExpressionNode.getIdentifier:()Ljava/lang/String;
     227: invokestatic  #10                 // Method org/junit/Assert.assertEquals:(Ljava/lang/Object;Ljava/lang/Object;)V
     230: aload_0
     231: getfield      #4                  // Field parser:Lorg/apache/hadoop/hbase/security/visibility/ExpressionParser;
     234: new           #62                 // class java/lang/StringBuilder
     237: dup
     238: invokespecial #63                 // Method java/lang/StringBuilder."<init>":()V
     241: ldc           #77                 // String '&\
     243: invokestatic  #65                 // Method org/apache/hadoop/hbase/security/visibility/CellVisibility.quote:(Ljava/lang/String;)Ljava/lang/String;
     246: invokevirtual #66                 // Method java/lang/StringBuilder.append:(Ljava/lang/String;)Ljava/lang/StringBuilder;
     249: ldc           #57                 // String |
     251: invokevirtual #66                 // Method java/lang/StringBuilder.append:(Ljava/lang/String;)Ljava/lang/StringBuilder;
     254: ldc           #78                 // String +&\
     256: invokestatic  #65                 // Method org/apache/hadoop/hbase/security/visibility/CellVisibility.quote:(Ljava/lang/String;)Ljava/lang/String;
     259: invokevirtual #66                 // Method java/lang/StringBuilder.append:(Ljava/lang/String;)Ljava/lang/StringBuilder;
     262: ldc           #79                 // String $$\"
     264: invokestatic  #65                 // Method org/apache/hadoop/hbase/security/visibility/CellVisibility.quote:(Ljava/lang/String;)Ljava/lang/String;
     267: invokevirtual #66                 // Method java/lang/StringBuilder.append:(Ljava/lang/String;)Ljava/lang/StringBuilder;
     270: invokevirtual #70                 // Method java/lang/StringBuilder.toString:()Ljava/lang/String;
     273: invokevirtual #6                  // Method org/apache/hadoop/hbase/security/visibility/ExpressionParser.parse:(Ljava/lang/String;)Lorg/apache/hadoop/hbase/security/visibility/expression/ExpressionNode;
     276: astore_1
     277: ldc           #80                 // String Excpetion must be thrown as there is not operator
     279: invokestatic  #73                 // Method org/junit/Assert.fail:(Ljava/lang/String;)V
     282: goto          286
     285: astore_3
     286: aload_0
     287: getfield      #4                  // Field parser:Lorg/apache/hadoop/hbase/security/visibility/ExpressionParser;
     290: new           #62                 // class java/lang/StringBuilder
     293: dup
     294: invokespecial #63                 // Method java/lang/StringBuilder."<init>":()V
     297: ldc           #77                 // String '&\
     299: invokestatic  #65                 // Method org/apache/hadoop/hbase/security/visibility/CellVisibility.quote:(Ljava/lang/String;)Ljava/lang/String;
     302: invokevirtual #66                 // Method java/lang/StringBuilder.append:(Ljava/lang/String;)Ljava/lang/StringBuilder;
     305: ldc           #57                 // String |
     307: invokevirtual #66                 // Method java/lang/StringBuilder.append:(Ljava/lang/String;)Ljava/lang/StringBuilder;
     310: ldc           #81                 // String ?&\
     312: invokestatic  #65                 // Method org/apache/hadoop/hbase/security/visibility/CellVisibility.quote:(Ljava/lang/String;)Ljava/lang/String;
     315: invokevirtual #66                 // Method java/lang/StringBuilder.append:(Ljava/lang/String;)Ljava/lang/StringBuilder;
     318: ldc           #56                 // String &
     320: invokevirtual #66                 // Method java/lang/StringBuilder.append:(Ljava/lang/String;)Ljava/lang/StringBuilder;
     323: ldc           #79                 // String $$\"
     325: invokestatic  #65                 // Method org/apache/hadoop/hbase/security/visibility/CellVisibility.quote:(Ljava/lang/String;)Ljava/lang/String;
     328: invokevirtual #66                 // Method java/lang/StringBuilder.append:(Ljava/lang/String;)Ljava/lang/StringBuilder;
     331: invokevirtual #70                 // Method java/lang/StringBuilder.toString:()Ljava/lang/String;
     334: invokevirtual #6                  // Method org/apache/hadoop/hbase/security/visibility/ExpressionParser.parse:(Ljava/lang/String;)Lorg/apache/hadoop/hbase/security/visibility/expression/ExpressionNode;
     337: astore_1
     338: aload_1
     339: instanceof    #12                 // class org/apache/hadoop/hbase/security/visibility/expression/NonLeafExpressionNode
     342: invokestatic  #8                  // Method org/junit/Assert.assertTrue:(Z)V
     345: aload_1
     346: checkcast     #12                 // class org/apache/hadoop/hbase/security/visibility/expression/NonLeafExpressionNode
     349: astore_2
     350: getstatic     #13                 // Field org/apache/hadoop/hbase/security/visibility/expression/Operator.AND:Lorg/apache/hadoop/hbase/security/visibility/expression/Operator;
     353: aload_2
     354: invokevirtual #14                 // Method org/apache/hadoop/hbase/security/visibility/expression/NonLeafExpressionNode.getOperator:()Lorg/apache/hadoop/hbase/security/visibility/expression/Operator;
     357: invokestatic  #10                 // Method org/junit/Assert.assertEquals:(Ljava/lang/Object;Ljava/lang/Object;)V
     360: ldc2_w        #15                 // long 2l
     363: aload_2
     364: invokevirtual #17                 // Method org/apache/hadoop/hbase/security/visibility/expression/NonLeafExpressionNode.getChildExps:()Ljava/util/List;
     367: invokeinterface #18,  1           // InterfaceMethod java/util/List.size:()I
     372: i2l
     373: invokestatic  #19                 // Method org/junit/Assert.assertEquals:(JJ)V
     376: ldc           #79                 // String $$\"
     378: aload_2
     379: invokevirtual #17                 // Method org/apache/hadoop/hbase/security/visibility/expression/NonLeafExpressionNode.getChildExps:()Ljava/util/List;
     382: iconst_1
     383: invokeinterface #21,  2           // InterfaceMethod java/util/List.get:(I)Ljava/lang/Object;
     388: checkcast     #7                  // class org/apache/hadoop/hbase/security/visibility/expression/LeafExpressionNode
     391: invokevirtual #9                  // Method org/apache/hadoop/hbase/security/visibility/expression/LeafExpressionNode.getIdentifier:()Ljava/lang/String;
     394: invokestatic  #10                 // Method org/junit/Assert.assertEquals:(Ljava/lang/Object;Ljava/lang/Object;)V
     397: aload_2
     398: invokevirtual #17                 // Method org/apache/hadoop/hbase/security/visibility/expression/NonLeafExpressionNode.getChildExps:()Ljava/util/List;
     401: iconst_0
     402: invokeinterface #21,  2           // InterfaceMethod java/util/List.get:(I)Ljava/lang/Object;
     407: instanceof    #12                 // class org/apache/hadoop/hbase/security/visibility/expression/NonLeafExpressionNode
     410: invokestatic  #8                  // Method org/junit/Assert.assertTrue:(Z)V
     413: aload_2
     414: invokevirtual #17                 // Method org/apache/hadoop/hbase/security/visibility/expression/NonLeafExpressionNode.getChildExps:()Ljava/util/List;
     417: iconst_0
     418: invokeinterface #21,  2           // InterfaceMethod java/util/List.get:(I)Ljava/lang/Object;
     423: checkcast     #12                 // class org/apache/hadoop/hbase/security/visibility/expression/NonLeafExpressionNode
     426: astore_2
     427: getstatic     #22                 // Field org/apache/hadoop/hbase/security/visibility/expression/Operator.OR:Lorg/apache/hadoop/hbase/security/visibility/expression/Operator;
     430: aload_2
     431: invokevirtual #14                 // Method org/apache/hadoop/hbase/security/visibility/expression/NonLeafExpressionNode.getOperator:()Lorg/apache/hadoop/hbase/security/visibility/expression/Operator;
     434: invokestatic  #10                 // Method org/junit/Assert.assertEquals:(Ljava/lang/Object;Ljava/lang/Object;)V
     437: ldc2_w        #15                 // long 2l
     440: aload_2
     441: invokevirtual #17                 // Method org/apache/hadoop/hbase/security/visibility/expression/NonLeafExpressionNode.getChildExps:()Ljava/util/List;
     444: invokeinterface #18,  1           // InterfaceMethod java/util/List.size:()I
     449: i2l
     450: invokestatic  #19                 // Method org/junit/Assert.assertEquals:(JJ)V
     453: ldc           #77                 // String '&\
     455: aload_2
     456: invokevirtual #17                 // Method org/apache/hadoop/hbase/security/visibility/expression/NonLeafExpressionNode.getChildExps:()Ljava/util/List;
     459: iconst_0
     460: invokeinterface #21,  2           // InterfaceMethod java/util/List.get:(I)Ljava/lang/Object;
     465: checkcast     #7                  // class org/apache/hadoop/hbase/security/visibility/expression/LeafExpressionNode
     468: invokevirtual #9                  // Method org/apache/hadoop/hbase/security/visibility/expression/LeafExpressionNode.getIdentifier:()Ljava/lang/String;
     471: invokestatic  #10                 // Method org/junit/Assert.assertEquals:(Ljava/lang/Object;Ljava/lang/Object;)V
     474: ldc           #81                 // String ?&\
     476: aload_2
     477: invokevirtual #17                 // Method org/apache/hadoop/hbase/security/visibility/expression/NonLeafExpressionNode.getChildExps:()Ljava/util/List;
     480: iconst_1
     481: invokeinterface #21,  2           // InterfaceMethod java/util/List.get:(I)Ljava/lang/Object;
     486: checkcast     #7                  // class org/apache/hadoop/hbase/security/visibility/expression/LeafExpressionNode
     489: invokevirtual #9                  // Method org/apache/hadoop/hbase/security/visibility/expression/LeafExpressionNode.getIdentifier:()Ljava/lang/String;
     492: invokestatic  #10                 // Method org/junit/Assert.assertEquals:(Ljava/lang/Object;Ljava/lang/Object;)V
     495: aload_0
     496: getfield      #4                  // Field parser:Lorg/apache/hadoop/hbase/security/visibility/ExpressionParser;
     499: new           #62                 // class java/lang/StringBuilder
     502: dup
     503: invokespecial #63                 // Method java/lang/StringBuilder."<init>":()V
     506: ldc           #78                 // String +&\
     508: invokestatic  #65                 // Method org/apache/hadoop/hbase/security/visibility/CellVisibility.quote:(Ljava/lang/String;)Ljava/lang/String;
     511: invokevirtual #66                 // Method java/lang/StringBuilder.append:(Ljava/lang/String;)Ljava/lang/StringBuilder;
     514: ldc           #57                 // String |
     516: invokevirtual #66                 // Method java/lang/StringBuilder.append:(Ljava/lang/String;)Ljava/lang/StringBuilder;
     519: ldc           #77                 // String '&\
     521: invokestatic  #65                 // Method org/apache/hadoop/hbase/security/visibility/CellVisibility.quote:(Ljava/lang/String;)Ljava/lang/String;
     524: invokevirtual #66                 // Method java/lang/StringBuilder.append:(Ljava/lang/String;)Ljava/lang/StringBuilder;
     527: ldc           #82                 // String &\"$$
     529: invokevirtual #66                 // Method java/lang/StringBuilder.append:(Ljava/lang/String;)Ljava/lang/StringBuilder;
     532: invokevirtual #70                 // Method java/lang/StringBuilder.toString:()Ljava/lang/String;
     535: invokevirtual #6                  // Method org/apache/hadoop/hbase/security/visibility/ExpressionParser.parse:(Ljava/lang/String;)Lorg/apache/hadoop/hbase/security/visibility/expression/ExpressionNode;
     538: astore_1
     539: ldc           #83                 // String Excpetion must be thrown as there is no end quote
     541: invokestatic  #73                 // Method org/junit/Assert.fail:(Ljava/lang/String;)V
     544: goto          548
     547: astore_3
     548: return
    Exception table:
       from    to  target type
           2    17    20   Class org/apache/hadoop/hbase/security/visibility/ParseException
         230   282   285   Class org/apache/hadoop/hbase/security/visibility/ParseException
         495   544   547   Class org/apache/hadoop/hbase/security/visibility/ParseException

  static {};
    Code:
       0: ldc           #85                 // class org/apache/hadoop/hbase/security/visibility/TestExpressionParser
       2: invokestatic  #86                 // Method org/apache/hadoop/hbase/HBaseClassTestRule.forClass:(Ljava/lang/Class;)Lorg/apache/hadoop/hbase/HBaseClassTestRule;
       5: putstatic     #87                 // Field CLASS_RULE:Lorg/apache/hadoop/hbase/HBaseClassTestRule;
       8: return
}
