Compiled from "TestCompaction.java"
public class org.apache.hadoop.hbase.regionserver.TestCompaction$BlockingStoreMockMaker extends org.apache.hadoop.hbase.regionserver.StatefulStoreMockMaker {
  org.apache.hadoop.hbase.regionserver.TestCompaction$BlockingStoreMockMaker$BlockingCompactionContext blocked;

  final org.apache.hadoop.hbase.regionserver.TestCompaction this$0;

  public org.apache.hadoop.hbase.regionserver.TestCompaction$BlockingStoreMockMaker(org.apache.hadoop.hbase.regionserver.TestCompaction);
    Code:
       0: aload_0
       1: aload_1
       2: putfield      #1                  // Field this$0:Lorg/apache/hadoop/hbase/regionserver/TestCompaction;
       5: aload_0
       6: invokespecial #2                  // Method org/apache/hadoop/hbase/regionserver/StatefulStoreMockMaker."<init>":()V
       9: aload_0
      10: aconst_null
      11: putfield      #3                  // Field blocked:Lorg/apache/hadoop/hbase/regionserver/TestCompaction$BlockingStoreMockMaker$BlockingCompactionContext;
      14: return

  public java.util.Optional<org.apache.hadoop.hbase.regionserver.compactions.CompactionContext> selectCompaction();
    Code:
       0: aload_0
       1: new           #4                  // class org/apache/hadoop/hbase/regionserver/TestCompaction$BlockingStoreMockMaker$BlockingCompactionContext
       4: dup
       5: aload_0
       6: invokespecial #5                  // Method org/apache/hadoop/hbase/regionserver/TestCompaction$BlockingStoreMockMaker$BlockingCompactionContext."<init>":(Lorg/apache/hadoop/hbase/regionserver/TestCompaction$BlockingStoreMockMaker;)V
       9: putfield      #3                  // Field blocked:Lorg/apache/hadoop/hbase/regionserver/TestCompaction$BlockingStoreMockMaker$BlockingCompactionContext;
      12: aload_0
      13: getfield      #3                  // Field blocked:Lorg/apache/hadoop/hbase/regionserver/TestCompaction$BlockingStoreMockMaker$BlockingCompactionContext;
      16: aconst_null
      17: iconst_0
      18: iconst_0
      19: iconst_0
      20: invokevirtual #6                  // Method org/apache/hadoop/hbase/regionserver/TestCompaction$BlockingStoreMockMaker$BlockingCompactionContext.select:(Ljava/util/List;ZZZ)Z
      23: pop
      24: goto          33
      27: astore_1
      28: ldc           #8                  // String Shouldn't happen
      30: invokestatic  #9                  // Method org/junit/Assert.fail:(Ljava/lang/String;)V
      33: aload_0
      34: getfield      #3                  // Field blocked:Lorg/apache/hadoop/hbase/regionserver/TestCompaction$BlockingStoreMockMaker$BlockingCompactionContext;
      37: invokestatic  #10                 // Method java/util/Optional.of:(Ljava/lang/Object;)Ljava/util/Optional;
      40: areturn
    Exception table:
       from    to  target type
          12    24    27   Class java/io/IOException

  public void cancelCompaction(java.lang.Object);
    Code:
       0: return

  public int getPriority();
    Code:
       0: ldc           #12                 // int -2147483648
       2: ireturn

  public org.apache.hadoop.hbase.regionserver.TestCompaction$BlockingStoreMockMaker$BlockingCompactionContext waitForBlocking();
    Code:
       0: aload_0
       1: getfield      #3                  // Field blocked:Lorg/apache/hadoop/hbase/regionserver/TestCompaction$BlockingStoreMockMaker$BlockingCompactionContext;
       4: ifnull        17
       7: aload_0
       8: getfield      #3                  // Field blocked:Lorg/apache/hadoop/hbase/regionserver/TestCompaction$BlockingStoreMockMaker$BlockingCompactionContext;
      11: getfield      #13                 // Field org/apache/hadoop/hbase/regionserver/TestCompaction$BlockingStoreMockMaker$BlockingCompactionContext.isInCompact:Z
      14: ifne          26
      17: ldc2_w        #14                 // long 50l
      20: invokestatic  #16                 // Method org/apache/hadoop/hbase/util/Threads.sleepWithoutInterrupt:(J)V
      23: goto          0
      26: aload_0
      27: getfield      #3                  // Field blocked:Lorg/apache/hadoop/hbase/regionserver/TestCompaction$BlockingStoreMockMaker$BlockingCompactionContext;
      30: astore_1
      31: aload_0
      32: aconst_null
      33: putfield      #3                  // Field blocked:Lorg/apache/hadoop/hbase/regionserver/TestCompaction$BlockingStoreMockMaker$BlockingCompactionContext;
      36: aload_1
      37: areturn

  public org.apache.hadoop.hbase.regionserver.HStore createStoreMock(java.lang.String) throws java.lang.Exception;
    Code:
       0: aload_0
       1: ldc           #12                 // int -2147483648
       3: aload_1
       4: invokevirtual #17                 // Method createStoreMock:(ILjava/lang/String;)Lorg/apache/hadoop/hbase/regionserver/HStore;
       7: areturn

  public org.apache.hadoop.hbase.regionserver.HStore createStoreMock(int, java.lang.String) throws java.lang.Exception;
    Code:
       0: aload_0
       1: aload_2
       2: invokespecial #18                 // Method org/apache/hadoop/hbase/regionserver/StatefulStoreMockMaker.createStoreMock:(Ljava/lang/String;)Lorg/apache/hadoop/hbase/regionserver/HStore;
       5: astore_3
       6: aload_3
       7: invokevirtual #19                 // Method org/apache/hadoop/hbase/regionserver/HStore.getCompactPriority:()I
      10: invokestatic  #20                 // Method java/lang/Integer.valueOf:(I)Ljava/lang/Integer;
      13: invokestatic  #21                 // Method org/mockito/Mockito.when:(Ljava/lang/Object;)Lorg/mockito/stubbing/OngoingStubbing;
      16: iload_1
      17: invokestatic  #20                 // Method java/lang/Integer.valueOf:(I)Ljava/lang/Integer;
      20: invokeinterface #22,  2           // InterfaceMethod org/mockito/stubbing/OngoingStubbing.thenReturn:(Ljava/lang/Object;)Lorg/mockito/stubbing/OngoingStubbing;
      25: pop
      26: aload_3
      27: areturn
}
