Compiled from "TestAsyncTableRpcPriority.java"
class org.apache.hadoop.hbase.client.TestAsyncTableRpcPriority$5$1 implements org.mockito.stubbing.Answer<java.util.concurrent.CompletableFuture<org.apache.hadoop.hbase.HRegionLocation>> {
  final org.apache.hadoop.hbase.client.TestAsyncTableRpcPriority$5 this$1;

  org.apache.hadoop.hbase.client.TestAsyncTableRpcPriority$5$1(org.apache.hadoop.hbase.client.TestAsyncTableRpcPriority$5);
    Code:
       0: aload_0
       1: aload_1
       2: putfield      #1                  // Field this$1:Lorg/apache/hadoop/hbase/client/TestAsyncTableRpcPriority$5;
       5: aload_0
       6: invokespecial #2                  // Method java/lang/Object."<init>":()V
       9: return

  public java.util.concurrent.CompletableFuture<org.apache.hadoop.hbase.HRegionLocation> answer(org.mockito.invocation.InvocationOnMock) throws java.lang.Throwable;
    Code:
       0: aload_1
       1: iconst_0
       2: invokeinterface #3,  2            // InterfaceMethod org/mockito/invocation/InvocationOnMock.getArgument:(I)Ljava/lang/Object;
       7: checkcast     #4                  // class org/apache/hadoop/hbase/TableName
      10: astore_2
      11: aload_2
      12: invokestatic  #5                  // Method org/apache/hadoop/hbase/client/RegionInfoBuilder.newBuilder:(Lorg/apache/hadoop/hbase/TableName;)Lorg/apache/hadoop/hbase/client/RegionInfoBuilder;
      15: invokevirtual #6                  // Method org/apache/hadoop/hbase/client/RegionInfoBuilder.build:()Lorg/apache/hadoop/hbase/client/RegionInfo;
      18: astore_3
      19: ldc           #7                  // String rs
      21: sipush        16010
      24: ldc2_w        #8                  // long 12345l
      27: invokestatic  #10                 // Method org/apache/hadoop/hbase/ServerName.valueOf:(Ljava/lang/String;IJ)Lorg/apache/hadoop/hbase/ServerName;
      30: astore        4
      32: new           #11                 // class org/apache/hadoop/hbase/HRegionLocation
      35: dup
      36: aload_3
      37: aload         4
      39: invokespecial #12                 // Method org/apache/hadoop/hbase/HRegionLocation."<init>":(Lorg/apache/hadoop/hbase/client/RegionInfo;Lorg/apache/hadoop/hbase/ServerName;)V
      42: astore        5
      44: aload         5
      46: invokestatic  #13                 // Method java/util/concurrent/CompletableFuture.completedFuture:(Ljava/lang/Object;)Ljava/util/concurrent/CompletableFuture;
      49: areturn

  public java.lang.Object answer(org.mockito.invocation.InvocationOnMock) throws java.lang.Throwable;
    Code:
       0: aload_0
       1: aload_1
       2: invokevirtual #14                 // Method answer:(Lorg/mockito/invocation/InvocationOnMock;)Ljava/util/concurrent/CompletableFuture;
       5: areturn
}
