Compiled from "TestGauge.java"
public class org.apache.hadoop.hbase.metrics.impl.TestGauge {
  public static final org.apache.hadoop.hbase.HBaseClassTestRule CLASS_RULE;

  public org.apache.hadoop.hbase.metrics.impl.TestGauge();
    Code:
       0: aload_0
       1: invokespecial #1                  // Method java/lang/Object."<init>":()V
       4: return

  public void testGetValue();
    Code:
       0: new           #2                  // class org/apache/hadoop/hbase/metrics/impl/TestGauge$SimpleGauge
       3: dup
       4: aconst_null
       5: invokespecial #3                  // Method org/apache/hadoop/hbase/metrics/impl/TestGauge$SimpleGauge."<init>":(Lorg/apache/hadoop/hbase/metrics/impl/TestGauge$1;)V
       8: astore_1
       9: lconst_0
      10: aload_1
      11: invokevirtual #4                  // Method org/apache/hadoop/hbase/metrics/impl/TestGauge$SimpleGauge.getValue:()Ljava/lang/Long;
      14: invokevirtual #5                  // Method java/lang/Long.longValue:()J
      17: invokestatic  #6                  // Method org/junit/Assert.assertEquals:(JJ)V
      20: aload_1
      21: ldc2_w        #7                  // long 1000l
      24: invokevirtual #9                  // Method org/apache/hadoop/hbase/metrics/impl/TestGauge$SimpleGauge.setValue:(J)V
      27: ldc2_w        #7                  // long 1000l
      30: aload_1
      31: invokevirtual #4                  // Method org/apache/hadoop/hbase/metrics/impl/TestGauge$SimpleGauge.getValue:()Ljava/lang/Long;
      34: invokevirtual #5                  // Method java/lang/Long.longValue:()J
      37: invokestatic  #6                  // Method org/junit/Assert.assertEquals:(JJ)V
      40: return

  static {};
    Code:
       0: ldc           #10                 // class org/apache/hadoop/hbase/metrics/impl/TestGauge
       2: invokestatic  #11                 // Method org/apache/hadoop/hbase/HBaseClassTestRule.forClass:(Ljava/lang/Class;)Lorg/apache/hadoop/hbase/HBaseClassTestRule;
       5: putstatic     #12                 // Field CLASS_RULE:Lorg/apache/hadoop/hbase/HBaseClassTestRule;
       8: return
}
