Compiled from "TestAssignmentManagerUtil.java"
public class org.apache.hadoop.hbase.master.assignment.TestAssignmentManagerUtil {
  public static final org.apache.hadoop.hbase.HBaseClassTestRule CLASS_RULE;

  public org.apache.hadoop.hbase.master.assignment.TestAssignmentManagerUtil();
    Code:
       0: aload_0
       1: invokespecial #1                  // Method java/lang/Object."<init>":()V
       4: return

  public static void setUp() throws java.lang.Exception;
    Code:
       0: getstatic     #2                  // Field UTIL:Lorg/apache/hadoop/hbase/HBaseTestingUtility;
       3: iconst_1
       4: invokevirtual #3                  // Method org/apache/hadoop/hbase/HBaseTestingUtility.startMiniCluster:(I)Lorg/apache/hadoop/hbase/MiniHBaseCluster;
       7: pop
       8: getstatic     #2                  // Field UTIL:Lorg/apache/hadoop/hbase/HBaseTestingUtility;
      11: invokevirtual #4                  // Method org/apache/hadoop/hbase/HBaseTestingUtility.getAdmin:()Lorg/apache/hadoop/hbase/client/Admin;
      14: iconst_0
      15: iconst_1
      16: invokeinterface #5,  3            // InterfaceMethod org/apache/hadoop/hbase/client/Admin.balancerSwitch:(ZZ)Z
      21: pop
      22: getstatic     #2                  // Field UTIL:Lorg/apache/hadoop/hbase/HBaseTestingUtility;
      25: getstatic     #6                  // Field TABLE_NAME:Lorg/apache/hadoop/hbase/TableName;
      28: invokestatic  #7                  // Method org/apache/hadoop/hbase/client/TableDescriptorBuilder.newBuilder:(Lorg/apache/hadoop/hbase/TableName;)Lorg/apache/hadoop/hbase/client/TableDescriptorBuilder;
      31: ldc           #8                  // String cf
      33: invokestatic  #9                  // Method org/apache/hadoop/hbase/client/ColumnFamilyDescriptorBuilder.of:(Ljava/lang/String;)Lorg/apache/hadoop/hbase/client/ColumnFamilyDescriptor;
      36: invokevirtual #10                 // Method org/apache/hadoop/hbase/client/TableDescriptorBuilder.setColumnFamily:(Lorg/apache/hadoop/hbase/client/ColumnFamilyDescriptor;)Lorg/apache/hadoop/hbase/client/TableDescriptorBuilder;
      39: getstatic     #11                 // Field REGION_REPLICATION:I
      42: invokevirtual #12                 // Method org/apache/hadoop/hbase/client/TableDescriptorBuilder.setRegionReplication:(I)Lorg/apache/hadoop/hbase/client/TableDescriptorBuilder;
      45: invokevirtual #13                 // Method org/apache/hadoop/hbase/client/TableDescriptorBuilder.build:()Lorg/apache/hadoop/hbase/client/TableDescriptor;
      48: iconst_1
      49: anewarray     #14                 // class "[B"
      52: dup
      53: iconst_0
      54: iconst_0
      55: invokestatic  #15                 // Method org/apache/hadoop/hbase/util/Bytes.toBytes:(I)[B
      58: aastore
      59: invokevirtual #16                 // Method org/apache/hadoop/hbase/HBaseTestingUtility.createTable:(Lorg/apache/hadoop/hbase/client/TableDescriptor;[[B)Lorg/apache/hadoop/hbase/client/Table;
      62: pop
      63: getstatic     #2                  // Field UTIL:Lorg/apache/hadoop/hbase/HBaseTestingUtility;
      66: getstatic     #6                  // Field TABLE_NAME:Lorg/apache/hadoop/hbase/TableName;
      69: invokevirtual #17                 // Method org/apache/hadoop/hbase/HBaseTestingUtility.waitTableAvailable:(Lorg/apache/hadoop/hbase/TableName;)V
      72: getstatic     #2                  // Field UTIL:Lorg/apache/hadoop/hbase/HBaseTestingUtility;
      75: invokevirtual #18                 // Method org/apache/hadoop/hbase/HBaseTestingUtility.getMiniHBaseCluster:()Lorg/apache/hadoop/hbase/MiniHBaseCluster;
      78: invokevirtual #19                 // Method org/apache/hadoop/hbase/MiniHBaseCluster.getMaster:()Lorg/apache/hadoop/hbase/master/HMaster;
      81: astore_0
      82: aload_0
      83: invokevirtual #20                 // Method org/apache/hadoop/hbase/master/HMaster.getMasterProcedureExecutor:()Lorg/apache/hadoop/hbase/procedure2/ProcedureExecutor;
      86: invokevirtual #21                 // Method org/apache/hadoop/hbase/procedure2/ProcedureExecutor.getEnvironment:()Ljava/lang/Object;
      89: checkcast     #22                 // class org/apache/hadoop/hbase/master/procedure/MasterProcedureEnv
      92: putstatic     #23                 // Field ENV:Lorg/apache/hadoop/hbase/master/procedure/MasterProcedureEnv;
      95: aload_0
      96: invokevirtual #24                 // Method org/apache/hadoop/hbase/master/HMaster.getAssignmentManager:()Lorg/apache/hadoop/hbase/master/assignment/AssignmentManager;
      99: putstatic     #25                 // Field AM:Lorg/apache/hadoop/hbase/master/assignment/AssignmentManager;
     102: return

  public void tearDownAfterTest() throws java.io.IOException;
    Code:
       0: getstatic     #2                  // Field UTIL:Lorg/apache/hadoop/hbase/HBaseTestingUtility;
       3: invokevirtual #4                  // Method org/apache/hadoop/hbase/HBaseTestingUtility.getAdmin:()Lorg/apache/hadoop/hbase/client/Admin;
       6: getstatic     #6                  // Field TABLE_NAME:Lorg/apache/hadoop/hbase/TableName;
       9: invokeinterface #26,  2           // InterfaceMethod org/apache/hadoop/hbase/client/Admin.getRegions:(Lorg/apache/hadoop/hbase/TableName;)Ljava/util/List;
      14: invokeinterface #27,  1           // InterfaceMethod java/util/List.iterator:()Ljava/util/Iterator;
      19: astore_1
      20: aload_1
      21: invokeinterface #28,  1           // InterfaceMethod java/util/Iterator.hasNext:()Z
      26: ifeq          83
      29: aload_1
      30: invokeinterface #29,  1           // InterfaceMethod java/util/Iterator.next:()Ljava/lang/Object;
      35: checkcast     #30                 // class org/apache/hadoop/hbase/client/RegionInfo
      38: astore_2
      39: getstatic     #25                 // Field AM:Lorg/apache/hadoop/hbase/master/assignment/AssignmentManager;
      42: invokevirtual #31                 // Method org/apache/hadoop/hbase/master/assignment/AssignmentManager.getRegionStates:()Lorg/apache/hadoop/hbase/master/assignment/RegionStates;
      45: aload_2
      46: invokevirtual #32                 // Method org/apache/hadoop/hbase/master/assignment/RegionStates.getRegionStateNode:(Lorg/apache/hadoop/hbase/client/RegionInfo;)Lorg/apache/hadoop/hbase/master/assignment/RegionStateNode;
      49: astore_3
      50: aload_3
      51: getfield      #33                 // Field org/apache/hadoop/hbase/master/assignment/RegionStateNode.lock:Ljava/util/concurrent/locks/Lock;
      54: checkcast     #34                 // class java/util/concurrent/locks/ReentrantLock
      57: invokevirtual #35                 // Method java/util/concurrent/locks/ReentrantLock.isLocked:()Z
      60: invokestatic  #36                 // Method org/junit/Assert.assertFalse:(Z)V
      63: aload_3
      64: invokevirtual #37                 // Method org/apache/hadoop/hbase/master/assignment/RegionStateNode.getProcedure:()Lorg/apache/hadoop/hbase/master/assignment/TransitRegionStateProcedure;
      67: astore        4
      69: aload         4
      71: ifnull        80
      74: aload_3
      75: aload         4
      77: invokevirtual #38                 // Method org/apache/hadoop/hbase/master/assignment/RegionStateNode.unsetProcedure:(Lorg/apache/hadoop/hbase/master/assignment/TransitRegionStateProcedure;)V
      80: goto          20
      83: return

  public static void tearDown() throws java.lang.Exception;
    Code:
       0: getstatic     #2                  // Field UTIL:Lorg/apache/hadoop/hbase/HBaseTestingUtility;
       3: invokevirtual #39                 // Method org/apache/hadoop/hbase/HBaseTestingUtility.shutdownMiniCluster:()V
       6: return

  public void testCreateUnassignProcedureForSplitFail() throws java.io.IOException;
    Code:
       0: aload_0
       1: invokespecial #46                 // Method getPrimaryRegions:()Ljava/util/List;
       4: iconst_0
       5: invokeinterface #47,  2           // InterfaceMethod java/util/List.get:(I)Ljava/lang/Object;
      10: checkcast     #30                 // class org/apache/hadoop/hbase/client/RegionInfo
      13: astore_1
      14: getstatic     #25                 // Field AM:Lorg/apache/hadoop/hbase/master/assignment/AssignmentManager;
      17: invokevirtual #31                 // Method org/apache/hadoop/hbase/master/assignment/AssignmentManager.getRegionStates:()Lorg/apache/hadoop/hbase/master/assignment/RegionStates;
      20: aload_1
      21: invokevirtual #32                 // Method org/apache/hadoop/hbase/master/assignment/RegionStates.getRegionStateNode:(Lorg/apache/hadoop/hbase/client/RegionInfo;)Lorg/apache/hadoop/hbase/master/assignment/RegionStateNode;
      24: getstatic     #23                 // Field ENV:Lorg/apache/hadoop/hbase/master/procedure/MasterProcedureEnv;
      27: aload_1
      28: invokestatic  #48                 // Method org/apache/hadoop/hbase/master/assignment/TransitRegionStateProcedure.unassign:(Lorg/apache/hadoop/hbase/master/procedure/MasterProcedureEnv;Lorg/apache/hadoop/hbase/client/RegionInfo;)Lorg/apache/hadoop/hbase/master/assignment/TransitRegionStateProcedure;
      31: invokevirtual #49                 // Method org/apache/hadoop/hbase/master/assignment/RegionStateNode.setProcedure:(Lorg/apache/hadoop/hbase/master/assignment/TransitRegionStateProcedure;)V
      34: getstatic     #23                 // Field ENV:Lorg/apache/hadoop/hbase/master/procedure/MasterProcedureEnv;
      37: aload_1
      38: invokestatic  #50                 // InterfaceMethod java/util/stream/Stream.of:(Ljava/lang/Object;)Ljava/util/stream/Stream;
      41: getstatic     #11                 // Field REGION_REPLICATION:I
      44: invokestatic  #51                 // Method org/apache/hadoop/hbase/master/assignment/AssignmentManagerUtil.createUnassignProceduresForSplitOrMerge:(Lorg/apache/hadoop/hbase/master/procedure/MasterProcedureEnv;Ljava/util/stream/Stream;I)[Lorg/apache/hadoop/hbase/master/assignment/TransitRegionStateProcedure;
      47: pop
      48: ldc           #52                 // String Should fail as the region is in transition
      50: invokestatic  #53                 // Method org/junit/Assert.fail:(Ljava/lang/String;)V
      53: goto          57
      56: astore_2
      57: return
    Exception table:
       from    to  target type
          34    53    56   Class org/apache/hadoop/hbase/HBaseIOException

  public void testCreateUnassignProceduresForMergeFail() throws java.io.IOException;
    Code:
       0: aload_0
       1: invokespecial #46                 // Method getPrimaryRegions:()Ljava/util/List;
       4: astore_1
       5: aload_1
       6: iconst_0
       7: invokeinterface #47,  2           // InterfaceMethod java/util/List.get:(I)Ljava/lang/Object;
      12: checkcast     #30                 // class org/apache/hadoop/hbase/client/RegionInfo
      15: astore_2
      16: aload_1
      17: iconst_1
      18: invokeinterface #47,  2           // InterfaceMethod java/util/List.get:(I)Ljava/lang/Object;
      23: checkcast     #30                 // class org/apache/hadoop/hbase/client/RegionInfo
      26: astore_3
      27: getstatic     #25                 // Field AM:Lorg/apache/hadoop/hbase/master/assignment/AssignmentManager;
      30: invokevirtual #31                 // Method org/apache/hadoop/hbase/master/assignment/AssignmentManager.getRegionStates:()Lorg/apache/hadoop/hbase/master/assignment/RegionStates;
      33: aload_3
      34: invokevirtual #32                 // Method org/apache/hadoop/hbase/master/assignment/RegionStates.getRegionStateNode:(Lorg/apache/hadoop/hbase/client/RegionInfo;)Lorg/apache/hadoop/hbase/master/assignment/RegionStateNode;
      37: getstatic     #23                 // Field ENV:Lorg/apache/hadoop/hbase/master/procedure/MasterProcedureEnv;
      40: aload_3
      41: invokestatic  #48                 // Method org/apache/hadoop/hbase/master/assignment/TransitRegionStateProcedure.unassign:(Lorg/apache/hadoop/hbase/master/procedure/MasterProcedureEnv;Lorg/apache/hadoop/hbase/client/RegionInfo;)Lorg/apache/hadoop/hbase/master/assignment/TransitRegionStateProcedure;
      44: invokevirtual #49                 // Method org/apache/hadoop/hbase/master/assignment/RegionStateNode.setProcedure:(Lorg/apache/hadoop/hbase/master/assignment/TransitRegionStateProcedure;)V
      47: getstatic     #23                 // Field ENV:Lorg/apache/hadoop/hbase/master/procedure/MasterProcedureEnv;
      50: iconst_2
      51: anewarray     #30                 // class org/apache/hadoop/hbase/client/RegionInfo
      54: dup
      55: iconst_0
      56: aload_2
      57: aastore
      58: dup
      59: iconst_1
      60: aload_3
      61: aastore
      62: invokestatic  #55                 // InterfaceMethod java/util/stream/Stream.of:([Ljava/lang/Object;)Ljava/util/stream/Stream;
      65: getstatic     #11                 // Field REGION_REPLICATION:I
      68: invokestatic  #51                 // Method org/apache/hadoop/hbase/master/assignment/AssignmentManagerUtil.createUnassignProceduresForSplitOrMerge:(Lorg/apache/hadoop/hbase/master/procedure/MasterProcedureEnv;Ljava/util/stream/Stream;I)[Lorg/apache/hadoop/hbase/master/assignment/TransitRegionStateProcedure;
      71: pop
      72: ldc           #52                 // String Should fail as the region is in transition
      74: invokestatic  #53                 // Method org/junit/Assert.fail:(Ljava/lang/String;)V
      77: goto          82
      80: astore        4
      82: iconst_0
      83: getstatic     #11                 // Field REGION_REPLICATION:I
      86: invokestatic  #56                 // InterfaceMethod java/util/stream/IntStream.range:(II)Ljava/util/stream/IntStream;
      89: aload_2
      90: invokedynamic #57,  0             // InvokeDynamic #1:apply:(Lorg/apache/hadoop/hbase/client/RegionInfo;)Ljava/util/function/IntFunction;
      95: invokeinterface #58,  2           // InterfaceMethod java/util/stream/IntStream.mapToObj:(Ljava/util/function/IntFunction;)Ljava/util/stream/Stream;
     100: getstatic     #25                 // Field AM:Lorg/apache/hadoop/hbase/master/assignment/AssignmentManager;
     103: invokevirtual #31                 // Method org/apache/hadoop/hbase/master/assignment/AssignmentManager.getRegionStates:()Lorg/apache/hadoop/hbase/master/assignment/RegionStates;
     106: dup
     107: invokevirtual #59                 // Method java/lang/Object.getClass:()Ljava/lang/Class;
     110: pop
     111: invokedynamic #60,  0             // InvokeDynamic #2:apply:(Lorg/apache/hadoop/hbase/master/assignment/RegionStates;)Ljava/util/function/Function;
     116: invokeinterface #61,  2           // InterfaceMethod java/util/stream/Stream.map:(Ljava/util/function/Function;)Ljava/util/stream/Stream;
     121: invokedynamic #62,  0             // InvokeDynamic #3:accept:()Ljava/util/function/Consumer;
     126: invokeinterface #63,  2           // InterfaceMethod java/util/stream/Stream.forEachOrdered:(Ljava/util/function/Consumer;)V
     131: return
    Exception table:
       from    to  target type
          47    77    80   Class org/apache/hadoop/hbase/HBaseIOException

  static {};
    Code:
       0: ldc           #74                 // class org/apache/hadoop/hbase/master/assignment/TestAssignmentManagerUtil
       2: invokestatic  #75                 // Method org/apache/hadoop/hbase/HBaseClassTestRule.forClass:(Ljava/lang/Class;)Lorg/apache/hadoop/hbase/HBaseClassTestRule;
       5: putstatic     #76                 // Field CLASS_RULE:Lorg/apache/hadoop/hbase/HBaseClassTestRule;
       8: new           #77                 // class org/apache/hadoop/hbase/HBaseTestingUtility
      11: dup
      12: invokespecial #78                 // Method org/apache/hadoop/hbase/HBaseTestingUtility."<init>":()V
      15: putstatic     #2                  // Field UTIL:Lorg/apache/hadoop/hbase/HBaseTestingUtility;
      18: ldc           #79                 // String AM
      20: invokestatic  #80                 // Method org/apache/hadoop/hbase/TableName.valueOf:(Ljava/lang/String;)Lorg/apache/hadoop/hbase/TableName;
      23: putstatic     #6                  // Field TABLE_NAME:Lorg/apache/hadoop/hbase/TableName;
      26: iconst_3
      27: putstatic     #11                 // Field REGION_REPLICATION:I
      30: return
}
