Compiled from "TestCompaction.java"
class org.apache.hadoop.hbase.regionserver.TestCompaction$StoreMockMaker extends org.apache.hadoop.hbase.regionserver.StatefulStoreMockMaker {
  public java.util.ArrayList<org.apache.hadoop.hbase.regionserver.HStoreFile> compacting;

  public java.util.ArrayList<org.apache.hadoop.hbase.regionserver.HStoreFile> notCompacting;

  final org.apache.hadoop.hbase.regionserver.TestCompaction this$0;

  public org.apache.hadoop.hbase.regionserver.TestCompaction$StoreMockMaker(java.util.ArrayList<java.lang.Integer>);
    Code:
       0: aload_0
       1: aload_1
       2: putfield      #1                  // Field this$0:Lorg/apache/hadoop/hbase/regionserver/TestCompaction;
       5: aload_0
       6: invokespecial #2                  // Method org/apache/hadoop/hbase/regionserver/StatefulStoreMockMaker."<init>":()V
       9: aload_0
      10: new           #3                  // class java/util/ArrayList
      13: dup
      14: invokespecial #4                  // Method java/util/ArrayList."<init>":()V
      17: putfield      #5                  // Field compacting:Ljava/util/ArrayList;
      20: aload_0
      21: new           #3                  // class java/util/ArrayList
      24: dup
      25: invokespecial #4                  // Method java/util/ArrayList."<init>":()V
      28: putfield      #6                  // Field notCompacting:Ljava/util/ArrayList;
      31: aload_0
      32: aload_2
      33: putfield      #7                  // Field results:Ljava/util/ArrayList;
      36: return

  public synchronized java.util.Optional<org.apache.hadoop.hbase.regionserver.compactions.CompactionContext> selectCompaction();
    Code:
       0: new           #8                  // class org/apache/hadoop/hbase/regionserver/TestCompaction$StoreMockMaker$TestCompactionContext
       3: dup
       4: aload_0
       5: new           #3                  // class java/util/ArrayList
       8: dup
       9: aload_0
      10: getfield      #6                  // Field notCompacting:Ljava/util/ArrayList;
      13: invokespecial #9                  // Method java/util/ArrayList."<init>":(Ljava/util/Collection;)V
      16: invokespecial #10                 // Method org/apache/hadoop/hbase/regionserver/TestCompaction$StoreMockMaker$TestCompactionContext."<init>":(Lorg/apache/hadoop/hbase/regionserver/TestCompaction$StoreMockMaker;Ljava/util/List;)V
      19: astore_1
      20: aload_0
      21: getfield      #5                  // Field compacting:Ljava/util/ArrayList;
      24: aload_0
      25: getfield      #6                  // Field notCompacting:Ljava/util/ArrayList;
      28: invokevirtual #11                 // Method java/util/ArrayList.addAll:(Ljava/util/Collection;)Z
      31: pop
      32: aload_0
      33: getfield      #6                  // Field notCompacting:Ljava/util/ArrayList;
      36: invokevirtual #12                 // Method java/util/ArrayList.clear:()V
      39: aload_1
      40: aconst_null
      41: iconst_0
      42: iconst_0
      43: iconst_0
      44: invokevirtual #13                 // Method org/apache/hadoop/hbase/regionserver/compactions/CompactionContext.select:(Ljava/util/List;ZZZ)Z
      47: pop
      48: goto          57
      51: astore_2
      52: ldc           #15                 // String Shouldn't happen
      54: invokestatic  #16                 // Method org/junit/Assert.fail:(Ljava/lang/String;)V
      57: aload_1
      58: invokestatic  #17                 // Method java/util/Optional.of:(Ljava/lang/Object;)Ljava/util/Optional;
      61: areturn
    Exception table:
       from    to  target type
          39    48    51   Class java/io/IOException

  public synchronized void cancelCompaction(java.lang.Object);
    Code:
       0: aload_1
       1: checkcast     #8                  // class org/apache/hadoop/hbase/regionserver/TestCompaction$StoreMockMaker$TestCompactionContext
       4: astore_2
       5: aload_0
       6: getfield      #5                  // Field compacting:Ljava/util/ArrayList;
       9: aload_2
      10: invokestatic  #18                 // Method org/apache/hadoop/hbase/regionserver/TestCompaction$StoreMockMaker$TestCompactionContext.access$100:(Lorg/apache/hadoop/hbase/regionserver/TestCompaction$StoreMockMaker$TestCompactionContext;)Ljava/util/List;
      13: invokevirtual #19                 // Method java/util/ArrayList.removeAll:(Ljava/util/Collection;)Z
      16: pop
      17: aload_0
      18: getfield      #6                  // Field notCompacting:Ljava/util/ArrayList;
      21: aload_2
      22: invokestatic  #18                 // Method org/apache/hadoop/hbase/regionserver/TestCompaction$StoreMockMaker$TestCompactionContext.access$100:(Lorg/apache/hadoop/hbase/regionserver/TestCompaction$StoreMockMaker$TestCompactionContext;)Ljava/util/List;
      25: invokevirtual #11                 // Method java/util/ArrayList.addAll:(Ljava/util/Collection;)Z
      28: pop
      29: return

  public synchronized void finishCompaction(java.util.List<org.apache.hadoop.hbase.regionserver.HStoreFile>);
    Code:
       0: aload_1
       1: invokeinterface #20,  1           // InterfaceMethod java/util/List.isEmpty:()Z
       6: ifeq          10
       9: return
      10: aload_0
      11: getfield      #7                  // Field results:Ljava/util/ArrayList;
      14: dup
      15: astore_2
      16: monitorenter
      17: aload_0
      18: getfield      #7                  // Field results:Ljava/util/ArrayList;
      21: aload_1
      22: invokeinterface #21,  1           // InterfaceMethod java/util/List.size:()I
      27: invokestatic  #22                 // Method java/lang/Integer.valueOf:(I)Ljava/lang/Integer;
      30: invokevirtual #23                 // Method java/util/ArrayList.add:(Ljava/lang/Object;)Z
      33: pop
      34: aload_2
      35: monitorexit
      36: goto          44
      39: astore_3
      40: aload_2
      41: monitorexit
      42: aload_3
      43: athrow
      44: aload_0
      45: getfield      #5                  // Field compacting:Ljava/util/ArrayList;
      48: aload_1
      49: invokevirtual #19                 // Method java/util/ArrayList.removeAll:(Ljava/util/Collection;)Z
      52: pop
      53: return
    Exception table:
       from    to  target type
          17    36    39   any
          39    42    39   any

  public int getPriority();
    Code:
       0: bipush        7
       2: aload_0
       3: getfield      #5                  // Field compacting:Ljava/util/ArrayList;
       6: invokevirtual #24                 // Method java/util/ArrayList.size:()I
       9: isub
      10: aload_0
      11: getfield      #6                  // Field notCompacting:Ljava/util/ArrayList;
      14: invokevirtual #24                 // Method java/util/ArrayList.size:()I
      17: isub
      18: ireturn
}
