Compiled from "TestRegionBypass.java"
class org.apache.hadoop.hbase.master.assignment.TestRegionBypass$1 {
  static final int[] $SwitchMap$org$apache$hadoop$hbase$shaded$protobuf$generated$MasterProcedureProtos$RegionStateTransitionState;

  static {};
    Code:
       0: invokestatic  #1                  // Method org/apache/hadoop/hbase/shaded/protobuf/generated/MasterProcedureProtos$RegionStateTransitionState.values:()[Lorg/apache/hadoop/hbase/shaded/protobuf/generated/MasterProcedureProtos$RegionStateTransitionState;
       3: arraylength
       4: newarray       int
       6: putstatic     #2                  // Field $SwitchMap$org$apache$hadoop$hbase$shaded$protobuf$generated$MasterProcedureProtos$RegionStateTransitionState:[I
       9: getstatic     #2                  // Field $SwitchMap$org$apache$hadoop$hbase$shaded$protobuf$generated$MasterProcedureProtos$RegionStateTransitionState:[I
      12: getstatic     #3                  // Field org/apache/hadoop/hbase/shaded/protobuf/generated/MasterProcedureProtos$RegionStateTransitionState.REGION_STATE_TRANSITION_GET_ASSIGN_CANDIDATE:Lorg/apache/hadoop/hbase/shaded/protobuf/generated/MasterProcedureProtos$RegionStateTransitionState;
      15: invokevirtual #4                  // Method org/apache/hadoop/hbase/shaded/protobuf/generated/MasterProcedureProtos$RegionStateTransitionState.ordinal:()I
      18: iconst_1
      19: iastore
      20: goto          24
      23: astore_0
      24: getstatic     #2                  // Field $SwitchMap$org$apache$hadoop$hbase$shaded$protobuf$generated$MasterProcedureProtos$RegionStateTransitionState:[I
      27: getstatic     #6                  // Field org/apache/hadoop/hbase/shaded/protobuf/generated/MasterProcedureProtos$RegionStateTransitionState.REGION_STATE_TRANSITION_OPEN:Lorg/apache/hadoop/hbase/shaded/protobuf/generated/MasterProcedureProtos$RegionStateTransitionState;
      30: invokevirtual #4                  // Method org/apache/hadoop/hbase/shaded/protobuf/generated/MasterProcedureProtos$RegionStateTransitionState.ordinal:()I
      33: iconst_2
      34: iastore
      35: goto          39
      38: astore_0
      39: return
    Exception table:
       from    to  target type
           9    20    23   Class java/lang/NoSuchFieldError
          24    35    38   Class java/lang/NoSuchFieldError
}
