Compiled from "TestByteBufferPool.java"
public class org.apache.hadoop.hbase.io.TestByteBufferPool {
  public static final org.apache.hadoop.hbase.HBaseClassTestRule CLASS_RULE;

  public org.apache.hadoop.hbase.io.TestByteBufferPool();
    Code:
       0: aload_0
       1: invokespecial #1                  // Method java/lang/Object."<init>":()V
       4: return

  public void testOffheapBBPool() throws java.lang.Exception;
    Code:
       0: iconst_1
       1: istore_1
       2: aload_0
       3: bipush        10
       5: bipush        100
       7: iload_1
       8: invokespecial #2                  // Method testBBPool:(IIZ)V
      11: return

  public void testOnheapBBPool() throws java.lang.Exception;
    Code:
       0: iconst_0
       1: istore_1
       2: aload_0
       3: bipush        10
       5: bipush        100
       7: iload_1
       8: invokespecial #2                  // Method testBBPool:(IIZ)V
      11: return

  static {};
    Code:
       0: ldc           #16                 // class org/apache/hadoop/hbase/io/TestByteBufferPool
       2: invokestatic  #17                 // Method org/apache/hadoop/hbase/HBaseClassTestRule.forClass:(Ljava/lang/Class;)Lorg/apache/hadoop/hbase/HBaseClassTestRule;
       5: putstatic     #18                 // Field CLASS_RULE:Lorg/apache/hadoop/hbase/HBaseClassTestRule;
       8: return
}
