Compiled from "TestAsyncToolAdminApi.java"
public class org.apache.hadoop.hbase.client.TestAsyncToolAdminApi extends org.apache.hadoop.hbase.client.TestAsyncAdminBase {
  public static final org.apache.hadoop.hbase.HBaseClassTestRule CLASS_RULE;

  public org.apache.hadoop.hbase.client.TestAsyncToolAdminApi();
    Code:
       0: aload_0
       1: invokespecial #1                  // Method org/apache/hadoop/hbase/client/TestAsyncAdminBase."<init>":()V
       4: return

  public void testBalancer() throws java.lang.Exception;
    Code:
       0: aload_0
       1: getfield      #2                  // Field admin:Lorg/apache/hadoop/hbase/client/AsyncAdmin;
       4: invokeinterface #3,  1            // InterfaceMethod org/apache/hadoop/hbase/client/AsyncAdmin.isBalancerEnabled:()Ljava/util/concurrent/CompletableFuture;
       9: invokevirtual #4                  // Method java/util/concurrent/CompletableFuture.get:()Ljava/lang/Object;
      12: checkcast     #5                  // class java/lang/Boolean
      15: invokevirtual #6                  // Method java/lang/Boolean.booleanValue:()Z
      18: istore_1
      19: aload_0
      20: getfield      #2                  // Field admin:Lorg/apache/hadoop/hbase/client/AsyncAdmin;
      23: iload_1
      24: ifne          31
      27: iconst_1
      28: goto          32
      31: iconst_0
      32: invokeinterface #7,  2            // InterfaceMethod org/apache/hadoop/hbase/client/AsyncAdmin.balancerSwitch:(Z)Ljava/util/concurrent/CompletableFuture;
      37: invokevirtual #4                  // Method java/util/concurrent/CompletableFuture.get:()Ljava/lang/Object;
      40: checkcast     #5                  // class java/lang/Boolean
      43: invokevirtual #6                  // Method java/lang/Boolean.booleanValue:()Z
      46: istore_2
      47: iload_1
      48: invokestatic  #8                  // Method java/lang/Boolean.valueOf:(Z)Ljava/lang/Boolean;
      51: iload_2
      52: invokestatic  #8                  // Method java/lang/Boolean.valueOf:(Z)Ljava/lang/Boolean;
      55: invokestatic  #9                  // Method org/junit/Assert.assertEquals:(Ljava/lang/Object;Ljava/lang/Object;)V
      58: iload_1
      59: ifne          66
      62: iconst_1
      63: goto          67
      66: iconst_0
      67: invokestatic  #8                  // Method java/lang/Boolean.valueOf:(Z)Ljava/lang/Boolean;
      70: aload_0
      71: getfield      #2                  // Field admin:Lorg/apache/hadoop/hbase/client/AsyncAdmin;
      74: invokeinterface #3,  1            // InterfaceMethod org/apache/hadoop/hbase/client/AsyncAdmin.isBalancerEnabled:()Ljava/util/concurrent/CompletableFuture;
      79: invokevirtual #4                  // Method java/util/concurrent/CompletableFuture.get:()Ljava/lang/Object;
      82: invokestatic  #9                  // Method org/junit/Assert.assertEquals:(Ljava/lang/Object;Ljava/lang/Object;)V
      85: aload_0
      86: getfield      #2                  // Field admin:Lorg/apache/hadoop/hbase/client/AsyncAdmin;
      89: iload_1
      90: invokeinterface #7,  2            // InterfaceMethod org/apache/hadoop/hbase/client/AsyncAdmin.balancerSwitch:(Z)Ljava/util/concurrent/CompletableFuture;
      95: invokevirtual #4                  // Method java/util/concurrent/CompletableFuture.get:()Ljava/lang/Object;
      98: checkcast     #5                  // class java/lang/Boolean
     101: invokevirtual #6                  // Method java/lang/Boolean.booleanValue:()Z
     104: istore_2
     105: iload_1
     106: ifne          113
     109: iconst_1
     110: goto          114
     113: iconst_0
     114: invokestatic  #8                  // Method java/lang/Boolean.valueOf:(Z)Ljava/lang/Boolean;
     117: iload_2
     118: invokestatic  #8                  // Method java/lang/Boolean.valueOf:(Z)Ljava/lang/Boolean;
     121: invokestatic  #9                  // Method org/junit/Assert.assertEquals:(Ljava/lang/Object;Ljava/lang/Object;)V
     124: iload_1
     125: invokestatic  #8                  // Method java/lang/Boolean.valueOf:(Z)Ljava/lang/Boolean;
     128: aload_0
     129: getfield      #2                  // Field admin:Lorg/apache/hadoop/hbase/client/AsyncAdmin;
     132: invokeinterface #3,  1            // InterfaceMethod org/apache/hadoop/hbase/client/AsyncAdmin.isBalancerEnabled:()Ljava/util/concurrent/CompletableFuture;
     137: invokevirtual #4                  // Method java/util/concurrent/CompletableFuture.get:()Ljava/lang/Object;
     140: invokestatic  #9                  // Method org/junit/Assert.assertEquals:(Ljava/lang/Object;Ljava/lang/Object;)V
     143: return

  public void testNormalizer() throws java.lang.Exception;
    Code:
       0: aload_0
       1: getfield      #2                  // Field admin:Lorg/apache/hadoop/hbase/client/AsyncAdmin;
       4: invokeinterface #10,  1           // InterfaceMethod org/apache/hadoop/hbase/client/AsyncAdmin.isNormalizerEnabled:()Ljava/util/concurrent/CompletableFuture;
       9: invokevirtual #4                  // Method java/util/concurrent/CompletableFuture.get:()Ljava/lang/Object;
      12: checkcast     #5                  // class java/lang/Boolean
      15: invokevirtual #6                  // Method java/lang/Boolean.booleanValue:()Z
      18: istore_1
      19: aload_0
      20: getfield      #2                  // Field admin:Lorg/apache/hadoop/hbase/client/AsyncAdmin;
      23: iload_1
      24: ifne          31
      27: iconst_1
      28: goto          32
      31: iconst_0
      32: invokeinterface #11,  2           // InterfaceMethod org/apache/hadoop/hbase/client/AsyncAdmin.normalizerSwitch:(Z)Ljava/util/concurrent/CompletableFuture;
      37: invokevirtual #4                  // Method java/util/concurrent/CompletableFuture.get:()Ljava/lang/Object;
      40: checkcast     #5                  // class java/lang/Boolean
      43: invokevirtual #6                  // Method java/lang/Boolean.booleanValue:()Z
      46: istore_2
      47: iload_1
      48: invokestatic  #8                  // Method java/lang/Boolean.valueOf:(Z)Ljava/lang/Boolean;
      51: iload_2
      52: invokestatic  #8                  // Method java/lang/Boolean.valueOf:(Z)Ljava/lang/Boolean;
      55: invokestatic  #9                  // Method org/junit/Assert.assertEquals:(Ljava/lang/Object;Ljava/lang/Object;)V
      58: iload_1
      59: ifne          66
      62: iconst_1
      63: goto          67
      66: iconst_0
      67: invokestatic  #8                  // Method java/lang/Boolean.valueOf:(Z)Ljava/lang/Boolean;
      70: aload_0
      71: getfield      #2                  // Field admin:Lorg/apache/hadoop/hbase/client/AsyncAdmin;
      74: invokeinterface #10,  1           // InterfaceMethod org/apache/hadoop/hbase/client/AsyncAdmin.isNormalizerEnabled:()Ljava/util/concurrent/CompletableFuture;
      79: invokevirtual #4                  // Method java/util/concurrent/CompletableFuture.get:()Ljava/lang/Object;
      82: invokestatic  #9                  // Method org/junit/Assert.assertEquals:(Ljava/lang/Object;Ljava/lang/Object;)V
      85: aload_0
      86: getfield      #2                  // Field admin:Lorg/apache/hadoop/hbase/client/AsyncAdmin;
      89: iload_1
      90: invokeinterface #11,  2           // InterfaceMethod org/apache/hadoop/hbase/client/AsyncAdmin.normalizerSwitch:(Z)Ljava/util/concurrent/CompletableFuture;
      95: invokevirtual #4                  // Method java/util/concurrent/CompletableFuture.get:()Ljava/lang/Object;
      98: checkcast     #5                  // class java/lang/Boolean
     101: invokevirtual #6                  // Method java/lang/Boolean.booleanValue:()Z
     104: istore_2
     105: iload_1
     106: ifne          113
     109: iconst_1
     110: goto          114
     113: iconst_0
     114: invokestatic  #8                  // Method java/lang/Boolean.valueOf:(Z)Ljava/lang/Boolean;
     117: iload_2
     118: invokestatic  #8                  // Method java/lang/Boolean.valueOf:(Z)Ljava/lang/Boolean;
     121: invokestatic  #9                  // Method org/junit/Assert.assertEquals:(Ljava/lang/Object;Ljava/lang/Object;)V
     124: iload_1
     125: invokestatic  #8                  // Method java/lang/Boolean.valueOf:(Z)Ljava/lang/Boolean;
     128: aload_0
     129: getfield      #2                  // Field admin:Lorg/apache/hadoop/hbase/client/AsyncAdmin;
     132: invokeinterface #10,  1           // InterfaceMethod org/apache/hadoop/hbase/client/AsyncAdmin.isNormalizerEnabled:()Ljava/util/concurrent/CompletableFuture;
     137: invokevirtual #4                  // Method java/util/concurrent/CompletableFuture.get:()Ljava/lang/Object;
     140: invokestatic  #9                  // Method org/junit/Assert.assertEquals:(Ljava/lang/Object;Ljava/lang/Object;)V
     143: return

  public void testCleanerChore() throws java.lang.Exception;
    Code:
       0: aload_0
       1: getfield      #2                  // Field admin:Lorg/apache/hadoop/hbase/client/AsyncAdmin;
       4: invokeinterface #12,  1           // InterfaceMethod org/apache/hadoop/hbase/client/AsyncAdmin.isCleanerChoreEnabled:()Ljava/util/concurrent/CompletableFuture;
       9: invokevirtual #4                  // Method java/util/concurrent/CompletableFuture.get:()Ljava/lang/Object;
      12: checkcast     #5                  // class java/lang/Boolean
      15: invokevirtual #6                  // Method java/lang/Boolean.booleanValue:()Z
      18: istore_1
      19: aload_0
      20: getfield      #2                  // Field admin:Lorg/apache/hadoop/hbase/client/AsyncAdmin;
      23: iload_1
      24: ifne          31
      27: iconst_1
      28: goto          32
      31: iconst_0
      32: invokeinterface #13,  2           // InterfaceMethod org/apache/hadoop/hbase/client/AsyncAdmin.cleanerChoreSwitch:(Z)Ljava/util/concurrent/CompletableFuture;
      37: invokevirtual #4                  // Method java/util/concurrent/CompletableFuture.get:()Ljava/lang/Object;
      40: checkcast     #5                  // class java/lang/Boolean
      43: invokevirtual #6                  // Method java/lang/Boolean.booleanValue:()Z
      46: istore_2
      47: iload_1
      48: invokestatic  #8                  // Method java/lang/Boolean.valueOf:(Z)Ljava/lang/Boolean;
      51: iload_2
      52: invokestatic  #8                  // Method java/lang/Boolean.valueOf:(Z)Ljava/lang/Boolean;
      55: invokestatic  #9                  // Method org/junit/Assert.assertEquals:(Ljava/lang/Object;Ljava/lang/Object;)V
      58: iload_1
      59: ifne          66
      62: iconst_1
      63: goto          67
      66: iconst_0
      67: invokestatic  #8                  // Method java/lang/Boolean.valueOf:(Z)Ljava/lang/Boolean;
      70: aload_0
      71: getfield      #2                  // Field admin:Lorg/apache/hadoop/hbase/client/AsyncAdmin;
      74: invokeinterface #12,  1           // InterfaceMethod org/apache/hadoop/hbase/client/AsyncAdmin.isCleanerChoreEnabled:()Ljava/util/concurrent/CompletableFuture;
      79: invokevirtual #4                  // Method java/util/concurrent/CompletableFuture.get:()Ljava/lang/Object;
      82: invokestatic  #9                  // Method org/junit/Assert.assertEquals:(Ljava/lang/Object;Ljava/lang/Object;)V
      85: aload_0
      86: getfield      #2                  // Field admin:Lorg/apache/hadoop/hbase/client/AsyncAdmin;
      89: iload_1
      90: invokeinterface #13,  2           // InterfaceMethod org/apache/hadoop/hbase/client/AsyncAdmin.cleanerChoreSwitch:(Z)Ljava/util/concurrent/CompletableFuture;
      95: invokevirtual #4                  // Method java/util/concurrent/CompletableFuture.get:()Ljava/lang/Object;
      98: checkcast     #5                  // class java/lang/Boolean
     101: invokevirtual #6                  // Method java/lang/Boolean.booleanValue:()Z
     104: istore_2
     105: iload_1
     106: ifne          113
     109: iconst_1
     110: goto          114
     113: iconst_0
     114: invokestatic  #8                  // Method java/lang/Boolean.valueOf:(Z)Ljava/lang/Boolean;
     117: iload_2
     118: invokestatic  #8                  // Method java/lang/Boolean.valueOf:(Z)Ljava/lang/Boolean;
     121: invokestatic  #9                  // Method org/junit/Assert.assertEquals:(Ljava/lang/Object;Ljava/lang/Object;)V
     124: iload_1
     125: invokestatic  #8                  // Method java/lang/Boolean.valueOf:(Z)Ljava/lang/Boolean;
     128: aload_0
     129: getfield      #2                  // Field admin:Lorg/apache/hadoop/hbase/client/AsyncAdmin;
     132: invokeinterface #12,  1           // InterfaceMethod org/apache/hadoop/hbase/client/AsyncAdmin.isCleanerChoreEnabled:()Ljava/util/concurrent/CompletableFuture;
     137: invokevirtual #4                  // Method java/util/concurrent/CompletableFuture.get:()Ljava/lang/Object;
     140: invokestatic  #9                  // Method org/junit/Assert.assertEquals:(Ljava/lang/Object;Ljava/lang/Object;)V
     143: return

  public void testCatalogJanitor() throws java.lang.Exception;
    Code:
       0: aload_0
       1: getfield      #2                  // Field admin:Lorg/apache/hadoop/hbase/client/AsyncAdmin;
       4: invokeinterface #14,  1           // InterfaceMethod org/apache/hadoop/hbase/client/AsyncAdmin.isCatalogJanitorEnabled:()Ljava/util/concurrent/CompletableFuture;
       9: invokevirtual #4                  // Method java/util/concurrent/CompletableFuture.get:()Ljava/lang/Object;
      12: checkcast     #5                  // class java/lang/Boolean
      15: invokevirtual #6                  // Method java/lang/Boolean.booleanValue:()Z
      18: istore_1
      19: aload_0
      20: getfield      #2                  // Field admin:Lorg/apache/hadoop/hbase/client/AsyncAdmin;
      23: iload_1
      24: ifne          31
      27: iconst_1
      28: goto          32
      31: iconst_0
      32: invokeinterface #15,  2           // InterfaceMethod org/apache/hadoop/hbase/client/AsyncAdmin.catalogJanitorSwitch:(Z)Ljava/util/concurrent/CompletableFuture;
      37: invokevirtual #4                  // Method java/util/concurrent/CompletableFuture.get:()Ljava/lang/Object;
      40: checkcast     #5                  // class java/lang/Boolean
      43: invokevirtual #6                  // Method java/lang/Boolean.booleanValue:()Z
      46: istore_2
      47: iload_1
      48: invokestatic  #8                  // Method java/lang/Boolean.valueOf:(Z)Ljava/lang/Boolean;
      51: iload_2
      52: invokestatic  #8                  // Method java/lang/Boolean.valueOf:(Z)Ljava/lang/Boolean;
      55: invokestatic  #9                  // Method org/junit/Assert.assertEquals:(Ljava/lang/Object;Ljava/lang/Object;)V
      58: iload_1
      59: ifne          66
      62: iconst_1
      63: goto          67
      66: iconst_0
      67: invokestatic  #8                  // Method java/lang/Boolean.valueOf:(Z)Ljava/lang/Boolean;
      70: aload_0
      71: getfield      #2                  // Field admin:Lorg/apache/hadoop/hbase/client/AsyncAdmin;
      74: invokeinterface #14,  1           // InterfaceMethod org/apache/hadoop/hbase/client/AsyncAdmin.isCatalogJanitorEnabled:()Ljava/util/concurrent/CompletableFuture;
      79: invokevirtual #4                  // Method java/util/concurrent/CompletableFuture.get:()Ljava/lang/Object;
      82: invokestatic  #9                  // Method org/junit/Assert.assertEquals:(Ljava/lang/Object;Ljava/lang/Object;)V
      85: aload_0
      86: getfield      #2                  // Field admin:Lorg/apache/hadoop/hbase/client/AsyncAdmin;
      89: iload_1
      90: invokeinterface #15,  2           // InterfaceMethod org/apache/hadoop/hbase/client/AsyncAdmin.catalogJanitorSwitch:(Z)Ljava/util/concurrent/CompletableFuture;
      95: invokevirtual #4                  // Method java/util/concurrent/CompletableFuture.get:()Ljava/lang/Object;
      98: checkcast     #5                  // class java/lang/Boolean
     101: invokevirtual #6                  // Method java/lang/Boolean.booleanValue:()Z
     104: istore_2
     105: iload_1
     106: ifne          113
     109: iconst_1
     110: goto          114
     113: iconst_0
     114: invokestatic  #8                  // Method java/lang/Boolean.valueOf:(Z)Ljava/lang/Boolean;
     117: iload_2
     118: invokestatic  #8                  // Method java/lang/Boolean.valueOf:(Z)Ljava/lang/Boolean;
     121: invokestatic  #9                  // Method org/junit/Assert.assertEquals:(Ljava/lang/Object;Ljava/lang/Object;)V
     124: iload_1
     125: invokestatic  #8                  // Method java/lang/Boolean.valueOf:(Z)Ljava/lang/Boolean;
     128: aload_0
     129: getfield      #2                  // Field admin:Lorg/apache/hadoop/hbase/client/AsyncAdmin;
     132: invokeinterface #14,  1           // InterfaceMethod org/apache/hadoop/hbase/client/AsyncAdmin.isCatalogJanitorEnabled:()Ljava/util/concurrent/CompletableFuture;
     137: invokevirtual #4                  // Method java/util/concurrent/CompletableFuture.get:()Ljava/lang/Object;
     140: invokestatic  #9                  // Method org/junit/Assert.assertEquals:(Ljava/lang/Object;Ljava/lang/Object;)V
     143: return

  static {};
    Code:
       0: ldc           #16                 // class org/apache/hadoop/hbase/client/TestAsyncToolAdminApi
       2: invokestatic  #17                 // Method org/apache/hadoop/hbase/HBaseClassTestRule.forClass:(Ljava/lang/Class;)Lorg/apache/hadoop/hbase/HBaseClassTestRule;
       5: putstatic     #18                 // Field CLASS_RULE:Lorg/apache/hadoop/hbase/HBaseClassTestRule;
       8: return
}
