Compiled from "TestWALSplit.java"
class org.apache.hadoop.hbase.wal.TestWALSplit$ZombieLastLogWriterRegionServer extends java.lang.Thread {
  final java.util.concurrent.atomic.AtomicLong editsCount;

  final java.util.concurrent.atomic.AtomicBoolean stop;

  final int numOfWriters;

  final java.lang.String region;

  final org.apache.hadoop.hbase.security.User user;

  final org.apache.hadoop.hbase.wal.TestWALSplit this$0;

  public org.apache.hadoop.hbase.wal.TestWALSplit$ZombieLastLogWriterRegionServer(org.apache.hadoop.hbase.wal.TestWALSplit, java.util.concurrent.atomic.AtomicLong, java.util.concurrent.atomic.AtomicBoolean, java.lang.String, int) throws java.io.IOException, java.lang.InterruptedException;
    Code:
       0: aload_0
       1: aload_1
       2: putfield      #2                  // Field this$0:Lorg/apache/hadoop/hbase/wal/TestWALSplit;
       5: aload_0
       6: ldc           #3                  // String ZombieLastLogWriterRegionServer
       8: invokespecial #4                  // Method java/lang/Thread."<init>":(Ljava/lang/String;)V
      11: aload_0
      12: iconst_1
      13: invokevirtual #5                  // Method setDaemon:(Z)V
      16: aload_0
      17: aload_3
      18: putfield      #6                  // Field stop:Ljava/util/concurrent/atomic/AtomicBoolean;
      21: aload_0
      22: aload_2
      23: putfield      #7                  // Field editsCount:Ljava/util/concurrent/atomic/AtomicLong;
      26: aload_0
      27: aload         4
      29: putfield      #8                  // Field region:Ljava/lang/String;
      32: aload_0
      33: invokestatic  #9                  // Method org/apache/hadoop/hbase/wal/TestWALSplit.access$900:()Lorg/apache/hadoop/conf/Configuration;
      36: invokestatic  #10                 // Method org/apache/hadoop/hbase/wal/TestWALSplit.access$1000:()Ljava/lang/String;
      39: invokestatic  #11                 // Method org/apache/hadoop/hbase/wal/TestWALSplit.access$1100:()[Ljava/lang/String;
      42: invokestatic  #12                 // Method org/apache/hadoop/hbase/security/User.createUserForTesting:(Lorg/apache/hadoop/conf/Configuration;Ljava/lang/String;[Ljava/lang/String;)Lorg/apache/hadoop/hbase/security/User;
      45: putfield      #13                 // Field user:Lorg/apache/hadoop/hbase/security/User;
      48: aload_0
      49: iload         5
      51: putfield      #14                 // Field numOfWriters:I
      54: return

  public void run();
    Code:
       0: aload_0
       1: invokespecial #15                 // Method doWriting:()V
       4: goto          80
       7: astore_1
       8: invokestatic  #17                 // Method org/apache/hadoop/hbase/wal/TestWALSplit.access$200:()Lorg/slf4j/Logger;
      11: new           #18                 // class java/lang/StringBuilder
      14: dup
      15: invokespecial #19                 // Method java/lang/StringBuilder."<init>":()V
      18: aload_0
      19: invokevirtual #20                 // Method getName:()Ljava/lang/String;
      22: invokevirtual #21                 // Method java/lang/StringBuilder.append:(Ljava/lang/String;)Ljava/lang/StringBuilder;
      25: ldc           #22                 // String  Writer exiting
      27: invokevirtual #21                 // Method java/lang/StringBuilder.append:(Ljava/lang/String;)Ljava/lang/StringBuilder;
      30: aload_1
      31: invokevirtual #23                 // Method java/lang/StringBuilder.append:(Ljava/lang/Object;)Ljava/lang/StringBuilder;
      34: invokevirtual #24                 // Method java/lang/StringBuilder.toString:()Ljava/lang/String;
      37: invokeinterface #25,  2           // InterfaceMethod org/slf4j/Logger.warn:(Ljava/lang/String;)V
      42: goto          80
      45: astore_1
      46: invokestatic  #17                 // Method org/apache/hadoop/hbase/wal/TestWALSplit.access$200:()Lorg/slf4j/Logger;
      49: new           #18                 // class java/lang/StringBuilder
      52: dup
      53: invokespecial #19                 // Method java/lang/StringBuilder."<init>":()V
      56: aload_0
      57: invokevirtual #20                 // Method getName:()Ljava/lang/String;
      60: invokevirtual #21                 // Method java/lang/StringBuilder.append:(Ljava/lang/String;)Ljava/lang/StringBuilder;
      63: ldc           #22                 // String  Writer exiting
      65: invokevirtual #21                 // Method java/lang/StringBuilder.append:(Ljava/lang/String;)Ljava/lang/StringBuilder;
      68: aload_1
      69: invokevirtual #23                 // Method java/lang/StringBuilder.append:(Ljava/lang/Object;)Ljava/lang/StringBuilder;
      72: invokevirtual #24                 // Method java/lang/StringBuilder.toString:()Ljava/lang/String;
      75: invokeinterface #25,  2           // InterfaceMethod org/slf4j/Logger.warn:(Ljava/lang/String;)V
      80: return
    Exception table:
       from    to  target type
           0     4     7   Class java/io/IOException
           0     4    45   Class java/lang/InterruptedException

  static void access$1300(org.apache.hadoop.hbase.wal.TestWALSplit$ZombieLastLogWriterRegionServer, org.apache.hadoop.hbase.wal.WALProvider$Writer);
    Code:
       0: aload_0
       1: aload_1
       2: invokespecial #1                  // Method loop:(Lorg/apache/hadoop/hbase/wal/WALProvider$Writer;)V
       5: return
}
