Compiled from "TestProcedureStoreTracker.java"
public class org.apache.hadoop.hbase.procedure2.store.TestProcedureStoreTracker {
  public static final org.apache.hadoop.hbase.HBaseClassTestRule CLASS_RULE;

  public org.apache.hadoop.hbase.procedure2.store.TestProcedureStoreTracker();
    Code:
       0: aload_0
       1: invokespecial #1                  // Method java/lang/Object."<init>":()V
       4: return

  public void testSeqInsertAndDelete();
    Code:
       0: new           #2                  // class org/apache/hadoop/hbase/procedure2/store/ProcedureStoreTracker
       3: dup
       4: invokespecial #3                  // Method org/apache/hadoop/hbase/procedure2/store/ProcedureStoreTracker."<init>":()V
       7: astore_1
       8: aload_1
       9: invokevirtual #4                  // Method org/apache/hadoop/hbase/procedure2/store/ProcedureStoreTracker.isEmpty:()Z
      12: invokestatic  #5                  // Method org/junit/Assert.assertTrue:(Z)V
      15: iconst_1
      16: istore_2
      17: sipush        1024
      20: istore_3
      21: iconst_1
      22: istore        4
      24: iload         4
      26: sipush        1024
      29: if_icmpge     115
      32: aload_1
      33: iload         4
      35: i2l
      36: invokevirtual #6                  // Method org/apache/hadoop/hbase/procedure2/store/ProcedureStoreTracker.insert:(J)V
      39: iconst_1
      40: istore        5
      42: iload         5
      44: iload         4
      46: if_icmpgt     68
      49: getstatic     #7                  // Field org/apache/hadoop/hbase/procedure2/store/ProcedureStoreTracker$DeleteState.NO:Lorg/apache/hadoop/hbase/procedure2/store/ProcedureStoreTracker$DeleteState;
      52: aload_1
      53: iload         5
      55: i2l
      56: invokevirtual #8                  // Method org/apache/hadoop/hbase/procedure2/store/ProcedureStoreTracker.isDeleted:(J)Lorg/apache/hadoop/hbase/procedure2/store/ProcedureStoreTracker$DeleteState;
      59: invokestatic  #9                  // Method org/junit/Assert.assertEquals:(Ljava/lang/Object;Ljava/lang/Object;)V
      62: iinc          5, 1
      65: goto          42
      68: iload         4
      70: iconst_1
      71: iadd
      72: istore        5
      74: iload         5
      76: sipush        1024
      79: if_icmpge     109
      82: aload_1
      83: iload         5
      85: i2l
      86: invokevirtual #8                  // Method org/apache/hadoop/hbase/procedure2/store/ProcedureStoreTracker.isDeleted:(J)Lorg/apache/hadoop/hbase/procedure2/store/ProcedureStoreTracker$DeleteState;
      89: getstatic     #7                  // Field org/apache/hadoop/hbase/procedure2/store/ProcedureStoreTracker$DeleteState.NO:Lorg/apache/hadoop/hbase/procedure2/store/ProcedureStoreTracker$DeleteState;
      92: if_acmpeq     99
      95: iconst_1
      96: goto          100
      99: iconst_0
     100: invokestatic  #5                  // Method org/junit/Assert.assertTrue:(Z)V
     103: iinc          5, 1
     106: goto          74
     109: iinc          4, 1
     112: goto          24
     115: iconst_1
     116: istore        4
     118: iload         4
     120: sipush        1024
     123: if_icmpge     201
     126: aload_1
     127: iload         4
     129: i2l
     130: invokevirtual #10                 // Method org/apache/hadoop/hbase/procedure2/store/ProcedureStoreTracker.delete:(J)V
     133: iconst_1
     134: istore        5
     136: iload         5
     138: iload         4
     140: if_icmpgt     162
     143: getstatic     #11                 // Field org/apache/hadoop/hbase/procedure2/store/ProcedureStoreTracker$DeleteState.YES:Lorg/apache/hadoop/hbase/procedure2/store/ProcedureStoreTracker$DeleteState;
     146: aload_1
     147: iload         5
     149: i2l
     150: invokevirtual #8                  // Method org/apache/hadoop/hbase/procedure2/store/ProcedureStoreTracker.isDeleted:(J)Lorg/apache/hadoop/hbase/procedure2/store/ProcedureStoreTracker$DeleteState;
     153: invokestatic  #9                  // Method org/junit/Assert.assertEquals:(Ljava/lang/Object;Ljava/lang/Object;)V
     156: iinc          5, 1
     159: goto          136
     162: iload         4
     164: iconst_1
     165: iadd
     166: istore        5
     168: iload         5
     170: sipush        1024
     173: if_icmpge     195
     176: getstatic     #7                  // Field org/apache/hadoop/hbase/procedure2/store/ProcedureStoreTracker$DeleteState.NO:Lorg/apache/hadoop/hbase/procedure2/store/ProcedureStoreTracker$DeleteState;
     179: aload_1
     180: iload         5
     182: i2l
     183: invokevirtual #8                  // Method org/apache/hadoop/hbase/procedure2/store/ProcedureStoreTracker.isDeleted:(J)Lorg/apache/hadoop/hbase/procedure2/store/ProcedureStoreTracker$DeleteState;
     186: invokestatic  #9                  // Method org/junit/Assert.assertEquals:(Ljava/lang/Object;Ljava/lang/Object;)V
     189: iinc          5, 1
     192: goto          168
     195: iinc          4, 1
     198: goto          118
     201: aload_1
     202: invokevirtual #4                  // Method org/apache/hadoop/hbase/procedure2/store/ProcedureStoreTracker.isEmpty:()Z
     205: invokestatic  #5                  // Method org/junit/Assert.assertTrue:(Z)V
     208: return

  public void testPartialTracker();
    Code:
       0: new           #2                  // class org/apache/hadoop/hbase/procedure2/store/ProcedureStoreTracker
       3: dup
       4: invokespecial #3                  // Method org/apache/hadoop/hbase/procedure2/store/ProcedureStoreTracker."<init>":()V
       7: astore_1
       8: aload_1
       9: iconst_1
      10: invokevirtual #12                 // Method org/apache/hadoop/hbase/procedure2/store/ProcedureStoreTracker.setPartialFlag:(Z)V
      13: aload_1
      14: invokevirtual #4                  // Method org/apache/hadoop/hbase/procedure2/store/ProcedureStoreTracker.isEmpty:()Z
      17: invokestatic  #5                  // Method org/junit/Assert.assertTrue:(Z)V
      20: getstatic     #13                 // Field org/apache/hadoop/hbase/procedure2/store/ProcedureStoreTracker$DeleteState.MAYBE:Lorg/apache/hadoop/hbase/procedure2/store/ProcedureStoreTracker$DeleteState;
      23: aload_1
      24: lconst_1
      25: invokevirtual #8                  // Method org/apache/hadoop/hbase/procedure2/store/ProcedureStoreTracker.isDeleted:(J)Lorg/apache/hadoop/hbase/procedure2/store/ProcedureStoreTracker$DeleteState;
      28: invokestatic  #9                  // Method org/junit/Assert.assertEquals:(Ljava/lang/Object;Ljava/lang/Object;)V
      31: getstatic     #13                 // Field org/apache/hadoop/hbase/procedure2/store/ProcedureStoreTracker$DeleteState.MAYBE:Lorg/apache/hadoop/hbase/procedure2/store/ProcedureStoreTracker$DeleteState;
      34: aload_1
      35: ldc2_w        #14                 // long 579l
      38: invokevirtual #8                  // Method org/apache/hadoop/hbase/procedure2/store/ProcedureStoreTracker.isDeleted:(J)Lorg/apache/hadoop/hbase/procedure2/store/ProcedureStoreTracker$DeleteState;
      41: invokestatic  #9                  // Method org/junit/Assert.assertEquals:(Ljava/lang/Object;Ljava/lang/Object;)V
      44: aload_1
      45: lconst_1
      46: iconst_1
      47: invokevirtual #16                 // Method org/apache/hadoop/hbase/procedure2/store/ProcedureStoreTracker.setDeleted:(JZ)V
      50: aload_1
      51: invokevirtual #17                 // Method org/apache/hadoop/hbase/procedure2/store/ProcedureStoreTracker.dump:()V
      54: getstatic     #11                 // Field org/apache/hadoop/hbase/procedure2/store/ProcedureStoreTracker$DeleteState.YES:Lorg/apache/hadoop/hbase/procedure2/store/ProcedureStoreTracker$DeleteState;
      57: aload_1
      58: lconst_1
      59: invokevirtual #8                  // Method org/apache/hadoop/hbase/procedure2/store/ProcedureStoreTracker.isDeleted:(J)Lorg/apache/hadoop/hbase/procedure2/store/ProcedureStoreTracker$DeleteState;
      62: invokestatic  #9                  // Method org/junit/Assert.assertEquals:(Ljava/lang/Object;Ljava/lang/Object;)V
      65: getstatic     #13                 // Field org/apache/hadoop/hbase/procedure2/store/ProcedureStoreTracker$DeleteState.MAYBE:Lorg/apache/hadoop/hbase/procedure2/store/ProcedureStoreTracker$DeleteState;
      68: aload_1
      69: ldc2_w        #18                 // long 2l
      72: invokevirtual #8                  // Method org/apache/hadoop/hbase/procedure2/store/ProcedureStoreTracker.isDeleted:(J)Lorg/apache/hadoop/hbase/procedure2/store/ProcedureStoreTracker$DeleteState;
      75: invokestatic  #9                  // Method org/junit/Assert.assertEquals:(Ljava/lang/Object;Ljava/lang/Object;)V
      78: getstatic     #13                 // Field org/apache/hadoop/hbase/procedure2/store/ProcedureStoreTracker$DeleteState.MAYBE:Lorg/apache/hadoop/hbase/procedure2/store/ProcedureStoreTracker$DeleteState;
      81: aload_1
      82: ldc2_w        #14                 // long 579l
      85: invokevirtual #8                  // Method org/apache/hadoop/hbase/procedure2/store/ProcedureStoreTracker.isDeleted:(J)Lorg/apache/hadoop/hbase/procedure2/store/ProcedureStoreTracker$DeleteState;
      88: invokestatic  #9                  // Method org/junit/Assert.assertEquals:(Ljava/lang/Object;Ljava/lang/Object;)V
      91: aload_1
      92: ldc2_w        #14                 // long 579l
      95: iconst_0
      96: invokevirtual #16                 // Method org/apache/hadoop/hbase/procedure2/store/ProcedureStoreTracker.setDeleted:(JZ)V
      99: getstatic     #11                 // Field org/apache/hadoop/hbase/procedure2/store/ProcedureStoreTracker$DeleteState.YES:Lorg/apache/hadoop/hbase/procedure2/store/ProcedureStoreTracker$DeleteState;
     102: aload_1
     103: lconst_1
     104: invokevirtual #8                  // Method org/apache/hadoop/hbase/procedure2/store/ProcedureStoreTracker.isDeleted:(J)Lorg/apache/hadoop/hbase/procedure2/store/ProcedureStoreTracker$DeleteState;
     107: invokestatic  #9                  // Method org/junit/Assert.assertEquals:(Ljava/lang/Object;Ljava/lang/Object;)V
     110: getstatic     #13                 // Field org/apache/hadoop/hbase/procedure2/store/ProcedureStoreTracker$DeleteState.MAYBE:Lorg/apache/hadoop/hbase/procedure2/store/ProcedureStoreTracker$DeleteState;
     113: aload_1
     114: ldc2_w        #18                 // long 2l
     117: invokevirtual #8                  // Method org/apache/hadoop/hbase/procedure2/store/ProcedureStoreTracker.isDeleted:(J)Lorg/apache/hadoop/hbase/procedure2/store/ProcedureStoreTracker$DeleteState;
     120: invokestatic  #9                  // Method org/junit/Assert.assertEquals:(Ljava/lang/Object;Ljava/lang/Object;)V
     123: getstatic     #7                  // Field org/apache/hadoop/hbase/procedure2/store/ProcedureStoreTracker$DeleteState.NO:Lorg/apache/hadoop/hbase/procedure2/store/ProcedureStoreTracker$DeleteState;
     126: aload_1
     127: ldc2_w        #14                 // long 579l
     130: invokevirtual #8                  // Method org/apache/hadoop/hbase/procedure2/store/ProcedureStoreTracker.isDeleted:(J)Lorg/apache/hadoop/hbase/procedure2/store/ProcedureStoreTracker$DeleteState;
     133: invokestatic  #9                  // Method org/junit/Assert.assertEquals:(Ljava/lang/Object;Ljava/lang/Object;)V
     136: getstatic     #13                 // Field org/apache/hadoop/hbase/procedure2/store/ProcedureStoreTracker$DeleteState.MAYBE:Lorg/apache/hadoop/hbase/procedure2/store/ProcedureStoreTracker$DeleteState;
     139: aload_1
     140: ldc2_w        #20                 // long 577l
     143: invokevirtual #8                  // Method org/apache/hadoop/hbase/procedure2/store/ProcedureStoreTracker.isDeleted:(J)Lorg/apache/hadoop/hbase/procedure2/store/ProcedureStoreTracker$DeleteState;
     146: invokestatic  #9                  // Method org/junit/Assert.assertEquals:(Ljava/lang/Object;Ljava/lang/Object;)V
     149: getstatic     #13                 // Field org/apache/hadoop/hbase/procedure2/store/ProcedureStoreTracker$DeleteState.MAYBE:Lorg/apache/hadoop/hbase/procedure2/store/ProcedureStoreTracker$DeleteState;
     152: aload_1
     153: ldc2_w        #22                 // long 580l
     156: invokevirtual #8                  // Method org/apache/hadoop/hbase/procedure2/store/ProcedureStoreTracker.isDeleted:(J)Lorg/apache/hadoop/hbase/procedure2/store/ProcedureStoreTracker$DeleteState;
     159: invokestatic  #9                  // Method org/junit/Assert.assertEquals:(Ljava/lang/Object;Ljava/lang/Object;)V
     162: aload_1
     163: ldc2_w        #14                 // long 579l
     166: iconst_1
     167: invokevirtual #16                 // Method org/apache/hadoop/hbase/procedure2/store/ProcedureStoreTracker.setDeleted:(JZ)V
     170: aload_1
     171: iconst_0
     172: invokevirtual #12                 // Method org/apache/hadoop/hbase/procedure2/store/ProcedureStoreTracker.setPartialFlag:(Z)V
     175: aload_1
     176: invokevirtual #4                  // Method org/apache/hadoop/hbase/procedure2/store/ProcedureStoreTracker.isEmpty:()Z
     179: invokestatic  #5                  // Method org/junit/Assert.assertTrue:(Z)V
     182: return

  public void testBasicCRUD();
    Code:
       0: new           #2                  // class org/apache/hadoop/hbase/procedure2/store/ProcedureStoreTracker
       3: dup
       4: invokespecial #3                  // Method org/apache/hadoop/hbase/procedure2/store/ProcedureStoreTracker."<init>":()V
       7: astore_1
       8: aload_1
       9: invokevirtual #4                  // Method org/apache/hadoop/hbase/procedure2/store/ProcedureStoreTracker.isEmpty:()Z
      12: invokestatic  #5                  // Method org/junit/Assert.assertTrue:(Z)V
      15: bipush        6
      17: newarray       long
      19: dup
      20: iconst_0
      21: lconst_1
      22: lastore
      23: dup
      24: iconst_1
      25: ldc2_w        #18                 // long 2l
      28: lastore
      29: dup
      30: iconst_2
      31: ldc2_w        #24                 // long 3l
      34: lastore
      35: dup
      36: iconst_3
      37: ldc2_w        #26                 // long 4l
      40: lastore
      41: dup
      42: iconst_4
      43: ldc2_w        #28                 // long 5l
      46: lastore
      47: dup
      48: iconst_5
      49: ldc2_w        #30                 // long 6l
      52: lastore
      53: astore_2
      54: aload_1
      55: aload_2
      56: iconst_0
      57: laload
      58: invokevirtual #6                  // Method org/apache/hadoop/hbase/procedure2/store/ProcedureStoreTracker.insert:(J)V
      61: aload_1
      62: aload_2
      63: iconst_1
      64: laload
      65: iconst_3
      66: newarray       long
      68: dup
      69: iconst_0
      70: aload_2
      71: iconst_2
      72: laload
      73: lastore
      74: dup
      75: iconst_1
      76: aload_2
      77: iconst_3
      78: laload
      79: lastore
      80: dup
      81: iconst_2
      82: aload_2
      83: iconst_4
      84: laload
      85: lastore
      86: invokevirtual #32                 // Method org/apache/hadoop/hbase/procedure2/store/ProcedureStoreTracker.insert:(J[J)V
      89: aload_1
      90: invokevirtual #4                  // Method org/apache/hadoop/hbase/procedure2/store/ProcedureStoreTracker.isEmpty:()Z
      93: invokestatic  #33                 // Method org/junit/Assert.assertFalse:(Z)V
      96: aload_1
      97: invokevirtual #34                 // Method org/apache/hadoop/hbase/procedure2/store/ProcedureStoreTracker.isAllModified:()Z
     100: invokestatic  #5                  // Method org/junit/Assert.assertTrue:(Z)V
     103: aload_1
     104: invokevirtual #35                 // Method org/apache/hadoop/hbase/procedure2/store/ProcedureStoreTracker.resetModified:()V
     107: aload_1
     108: invokevirtual #34                 // Method org/apache/hadoop/hbase/procedure2/store/ProcedureStoreTracker.isAllModified:()Z
     111: invokestatic  #33                 // Method org/junit/Assert.assertFalse:(Z)V
     114: iconst_0
     115: istore_3
     116: iload_3
     117: iconst_4
     118: if_icmpge     148
     121: aload_1
     122: aload_2
     123: iload_3
     124: laload
     125: invokevirtual #36                 // Method org/apache/hadoop/hbase/procedure2/store/ProcedureStoreTracker.update:(J)V
     128: aload_1
     129: invokevirtual #4                  // Method org/apache/hadoop/hbase/procedure2/store/ProcedureStoreTracker.isEmpty:()Z
     132: invokestatic  #33                 // Method org/junit/Assert.assertFalse:(Z)V
     135: aload_1
     136: invokevirtual #34                 // Method org/apache/hadoop/hbase/procedure2/store/ProcedureStoreTracker.isAllModified:()Z
     139: invokestatic  #33                 // Method org/junit/Assert.assertFalse:(Z)V
     142: iinc          3, 1
     145: goto          116
     148: aload_1
     149: aload_2
     150: iconst_4
     151: laload
     152: invokevirtual #36                 // Method org/apache/hadoop/hbase/procedure2/store/ProcedureStoreTracker.update:(J)V
     155: aload_1
     156: invokevirtual #4                  // Method org/apache/hadoop/hbase/procedure2/store/ProcedureStoreTracker.isEmpty:()Z
     159: invokestatic  #33                 // Method org/junit/Assert.assertFalse:(Z)V
     162: aload_1
     163: invokevirtual #34                 // Method org/apache/hadoop/hbase/procedure2/store/ProcedureStoreTracker.isAllModified:()Z
     166: invokestatic  #5                  // Method org/junit/Assert.assertTrue:(Z)V
     169: aload_1
     170: aload_2
     171: iconst_5
     172: laload
     173: invokevirtual #36                 // Method org/apache/hadoop/hbase/procedure2/store/ProcedureStoreTracker.update:(J)V
     176: aload_1
     177: invokevirtual #4                  // Method org/apache/hadoop/hbase/procedure2/store/ProcedureStoreTracker.isEmpty:()Z
     180: invokestatic  #33                 // Method org/junit/Assert.assertFalse:(Z)V
     183: aload_1
     184: invokevirtual #34                 // Method org/apache/hadoop/hbase/procedure2/store/ProcedureStoreTracker.isAllModified:()Z
     187: invokestatic  #5                  // Method org/junit/Assert.assertTrue:(Z)V
     190: iconst_0
     191: istore_3
     192: iload_3
     193: iconst_5
     194: if_icmpge     224
     197: aload_1
     198: aload_2
     199: iload_3
     200: laload
     201: invokevirtual #10                 // Method org/apache/hadoop/hbase/procedure2/store/ProcedureStoreTracker.delete:(J)V
     204: aload_1
     205: invokevirtual #4                  // Method org/apache/hadoop/hbase/procedure2/store/ProcedureStoreTracker.isEmpty:()Z
     208: invokestatic  #33                 // Method org/junit/Assert.assertFalse:(Z)V
     211: aload_1
     212: invokevirtual #34                 // Method org/apache/hadoop/hbase/procedure2/store/ProcedureStoreTracker.isAllModified:()Z
     215: invokestatic  #5                  // Method org/junit/Assert.assertTrue:(Z)V
     218: iinc          3, 1
     221: goto          192
     224: aload_1
     225: aload_2
     226: iconst_5
     227: laload
     228: invokevirtual #10                 // Method org/apache/hadoop/hbase/procedure2/store/ProcedureStoreTracker.delete:(J)V
     231: aload_1
     232: invokevirtual #4                  // Method org/apache/hadoop/hbase/procedure2/store/ProcedureStoreTracker.isEmpty:()Z
     235: invokestatic  #5                  // Method org/junit/Assert.assertTrue:(Z)V
     238: return

  public void testRandLoad();
    Code:
       0: sipush        2500
       3: istore_1
       4: sipush        5000
       7: istore_2
       8: new           #2                  // class org/apache/hadoop/hbase/procedure2/store/ProcedureStoreTracker
      11: dup
      12: invokespecial #3                  // Method org/apache/hadoop/hbase/procedure2/store/ProcedureStoreTracker."<init>":()V
      15: astore_3
      16: new           #37                 // class java/util/Random
      19: dup
      20: lconst_1
      21: invokespecial #38                 // Method java/util/Random."<init>":(J)V
      24: astore        4
      26: iconst_0
      27: istore        5
      29: iload         5
      31: sipush        5000
      34: if_icmpge     106
      37: aload_3
      38: invokevirtual #4                  // Method org/apache/hadoop/hbase/procedure2/store/ProcedureStoreTracker.isEmpty:()Z
      41: invokestatic  #5                  // Method org/junit/Assert.assertTrue:(Z)V
      44: iconst_0
      45: istore        6
      47: iload         6
      49: sipush        2500
      52: if_icmpge     96
      55: aload         4
      57: invokevirtual #39                 // Method java/util/Random.nextLong:()J
      60: lstore        7
      62: lload         7
      64: lconst_1
      65: lcmp
      66: ifge          72
      69: goto          47
      72: aload_3
      73: lload         7
      75: iload         5
      77: iconst_2
      78: irem
      79: ifne          86
      82: iconst_1
      83: goto          87
      86: iconst_0
      87: invokevirtual #16                 // Method org/apache/hadoop/hbase/procedure2/store/ProcedureStoreTracker.setDeleted:(JZ)V
      90: iinc          6, 1
      93: goto          47
      96: aload_3
      97: invokevirtual #40                 // Method org/apache/hadoop/hbase/procedure2/store/ProcedureStoreTracker.reset:()V
     100: iinc          5, 1
     103: goto          29
     106: return

  public void testLoad();
    Code:
       0: sipush        1000
       3: istore_1
       4: new           #2                  // class org/apache/hadoop/hbase/procedure2/store/ProcedureStoreTracker
       7: dup
       8: invokespecial #3                  // Method org/apache/hadoop/hbase/procedure2/store/ProcedureStoreTracker."<init>":()V
      11: astore_2
      12: iconst_1
      13: istore_3
      14: iload_3
      15: sipush        1000
      18: if_icmpge     138
      21: iconst_1
      22: istore        4
      24: iload         4
      26: iload_3
      27: if_icmpgt     132
      30: aload_2
      31: invokevirtual #4                  // Method org/apache/hadoop/hbase/procedure2/store/ProcedureStoreTracker.isEmpty:()Z
      34: invokestatic  #5                  // Method org/junit/Assert.assertTrue:(Z)V
      37: getstatic     #41                 // Field LOG:Lorg/slf4j/Logger;
      40: new           #42                 // class java/lang/StringBuilder
      43: dup
      44: invokespecial #43                 // Method java/lang/StringBuilder."<init>":()V
      47: ldc           #44                 // String loading
      49: invokevirtual #45                 // Method java/lang/StringBuilder.append:(Ljava/lang/String;)Ljava/lang/StringBuilder;
      52: iload_3
      53: invokevirtual #46                 // Method java/lang/StringBuilder.append:(I)Ljava/lang/StringBuilder;
      56: ldc           #47                 // String  procs from start=
      58: invokevirtual #45                 // Method java/lang/StringBuilder.append:(Ljava/lang/String;)Ljava/lang/StringBuilder;
      61: iload         4
      63: invokevirtual #46                 // Method java/lang/StringBuilder.append:(I)Ljava/lang/StringBuilder;
      66: invokevirtual #48                 // Method java/lang/StringBuilder.toString:()Ljava/lang/String;
      69: invokeinterface #49,  2           // InterfaceMethod org/slf4j/Logger.debug:(Ljava/lang/String;)V
      74: iload         4
      76: istore        5
      78: iload         5
      80: iload_3
      81: if_icmpgt     98
      84: aload_2
      85: iload         5
      87: i2l
      88: iconst_0
      89: invokevirtual #16                 // Method org/apache/hadoop/hbase/procedure2/store/ProcedureStoreTracker.setDeleted:(JZ)V
      92: iinc          5, 1
      95: goto          78
      98: iconst_1
      99: istore        5
     101: iload         5
     103: iload         4
     105: if_icmpge     122
     108: aload_2
     109: iload         5
     111: i2l
     112: iconst_0
     113: invokevirtual #16                 // Method org/apache/hadoop/hbase/procedure2/store/ProcedureStoreTracker.setDeleted:(JZ)V
     116: iinc          5, 1
     119: goto          101
     122: aload_2
     123: invokevirtual #40                 // Method org/apache/hadoop/hbase/procedure2/store/ProcedureStoreTracker.reset:()V
     126: iinc          4, 1
     129: goto          24
     132: iinc          3, 1
     135: goto          14
     138: return

  public void testDelete();
    Code:
       0: new           #2                  // class org/apache/hadoop/hbase/procedure2/store/ProcedureStoreTracker
       3: dup
       4: invokespecial #3                  // Method org/apache/hadoop/hbase/procedure2/store/ProcedureStoreTracker."<init>":()V
       7: astore_1
       8: iconst_3
       9: newarray       long
      11: dup
      12: iconst_0
      13: ldc2_w        #50                 // long 65l
      16: lastore
      17: dup
      18: iconst_1
      19: lconst_1
      20: lastore
      21: dup
      22: iconst_2
      23: ldc2_w        #52                 // long 193l
      26: lastore
      27: astore_2
      28: iconst_0
      29: istore_3
      30: iload_3
      31: aload_2
      32: arraylength
      33: if_icmpge     53
      36: aload_1
      37: aload_2
      38: iload_3
      39: laload
      40: invokevirtual #6                  // Method org/apache/hadoop/hbase/procedure2/store/ProcedureStoreTracker.insert:(J)V
      43: aload_1
      44: invokevirtual #17                 // Method org/apache/hadoop/hbase/procedure2/store/ProcedureStoreTracker.dump:()V
      47: iinc          3, 1
      50: goto          30
      53: iconst_0
      54: istore_3
      55: iload_3
      56: sipush        256
      59: if_icmpge     154
      62: iconst_0
      63: istore        4
      65: iconst_0
      66: istore        5
      68: iload         5
      70: aload_2
      71: arraylength
      72: if_icmpge     97
      75: aload_2
      76: iload         5
      78: laload
      79: iload_3
      80: i2l
      81: lcmp
      82: ifne          91
      85: iconst_1
      86: istore        4
      88: goto          97
      91: iinc          5, 1
      94: goto          68
      97: iload         4
      99: ifeq          117
     102: getstatic     #7                  // Field org/apache/hadoop/hbase/procedure2/store/ProcedureStoreTracker$DeleteState.NO:Lorg/apache/hadoop/hbase/procedure2/store/ProcedureStoreTracker$DeleteState;
     105: aload_1
     106: iload_3
     107: i2l
     108: invokevirtual #8                  // Method org/apache/hadoop/hbase/procedure2/store/ProcedureStoreTracker.isDeleted:(J)Lorg/apache/hadoop/hbase/procedure2/store/ProcedureStoreTracker$DeleteState;
     111: invokestatic  #9                  // Method org/junit/Assert.assertEquals:(Ljava/lang/Object;Ljava/lang/Object;)V
     114: goto          148
     117: new           #42                 // class java/lang/StringBuilder
     120: dup
     121: invokespecial #43                 // Method java/lang/StringBuilder."<init>":()V
     124: ldc           #54                 // String procId=
     126: invokevirtual #45                 // Method java/lang/StringBuilder.append:(Ljava/lang/String;)Ljava/lang/StringBuilder;
     129: iload_3
     130: invokevirtual #46                 // Method java/lang/StringBuilder.append:(I)Ljava/lang/StringBuilder;
     133: invokevirtual #48                 // Method java/lang/StringBuilder.toString:()Ljava/lang/String;
     136: getstatic     #11                 // Field org/apache/hadoop/hbase/procedure2/store/ProcedureStoreTracker$DeleteState.YES:Lorg/apache/hadoop/hbase/procedure2/store/ProcedureStoreTracker$DeleteState;
     139: aload_1
     140: iload_3
     141: i2l
     142: invokevirtual #8                  // Method org/apache/hadoop/hbase/procedure2/store/ProcedureStoreTracker.isDeleted:(J)Lorg/apache/hadoop/hbase/procedure2/store/ProcedureStoreTracker$DeleteState;
     145: invokestatic  #55                 // Method org/junit/Assert.assertEquals:(Ljava/lang/String;Ljava/lang/Object;Ljava/lang/Object;)V
     148: iinc          3, 1
     151: goto          55
     154: return

  public void testSetDeletedIfModified();
    Code:
       0: new           #2                  // class org/apache/hadoop/hbase/procedure2/store/ProcedureStoreTracker
       3: dup
       4: invokespecial #3                  // Method org/apache/hadoop/hbase/procedure2/store/ProcedureStoreTracker."<init>":()V
       7: astore_1
       8: bipush        7
      10: newarray       long
      12: dup
      13: iconst_0
      14: lconst_1
      15: lastore
      16: dup
      17: iconst_1
      18: ldc2_w        #24                 // long 3l
      21: lastore
      22: dup
      23: iconst_2
      24: ldc2_w        #56                 // long 7l
      27: lastore
      28: dup
      29: iconst_3
      30: ldc2_w        #58                 // long 152l
      33: lastore
      34: dup
      35: iconst_4
      36: ldc2_w        #60                 // long 512l
      39: lastore
      40: dup
      41: iconst_5
      42: ldc2_w        #62                 // long 1024l
      45: lastore
      46: dup
      47: bipush        6
      49: ldc2_w        #64                 // long 1025l
      52: lastore
      53: astore_2
      54: iconst_0
      55: istore_3
      56: iload_3
      57: aload_2
      58: arraylength
      59: if_icmpge     75
      62: aload_1
      63: aload_2
      64: iload_3
      65: laload
      66: invokevirtual #6                  // Method org/apache/hadoop/hbase/procedure2/store/ProcedureStoreTracker.insert:(J)V
      69: iinc          3, 1
      72: goto          56
      75: iconst_0
      76: invokestatic  #66                 // Method java/lang/Boolean.valueOf:(Z)Ljava/lang/Boolean;
      79: aload_1
      80: invokevirtual #4                  // Method org/apache/hadoop/hbase/procedure2/store/ProcedureStoreTracker.isEmpty:()Z
      83: invokestatic  #66                 // Method java/lang/Boolean.valueOf:(Z)Ljava/lang/Boolean;
      86: invokestatic  #9                  // Method org/junit/Assert.assertEquals:(Ljava/lang/Object;Ljava/lang/Object;)V
      89: iconst_0
      90: istore_3
      91: iload_3
      92: aload_2
      93: arraylength
      94: if_icmpge     146
      97: aload_1
      98: iconst_1
      99: newarray       long
     101: dup
     102: iconst_0
     103: aload_2
     104: iload_3
     105: laload
     106: lconst_1
     107: lsub
     108: lastore
     109: invokevirtual #67                 // Method org/apache/hadoop/hbase/procedure2/store/ProcedureStoreTracker.setDeletedIfModified:([J)V
     112: aload_1
     113: iconst_1
     114: newarray       long
     116: dup
     117: iconst_0
     118: aload_2
     119: iload_3
     120: laload
     121: lastore
     122: invokevirtual #67                 // Method org/apache/hadoop/hbase/procedure2/store/ProcedureStoreTracker.setDeletedIfModified:([J)V
     125: aload_1
     126: iconst_1
     127: newarray       long
     129: dup
     130: iconst_0
     131: aload_2
     132: iload_3
     133: laload
     134: lconst_1
     135: ladd
     136: lastore
     137: invokevirtual #67                 // Method org/apache/hadoop/hbase/procedure2/store/ProcedureStoreTracker.setDeletedIfModified:([J)V
     140: iinc          3, 1
     143: goto          91
     146: iconst_1
     147: invokestatic  #66                 // Method java/lang/Boolean.valueOf:(Z)Ljava/lang/Boolean;
     150: aload_1
     151: invokevirtual #4                  // Method org/apache/hadoop/hbase/procedure2/store/ProcedureStoreTracker.isEmpty:()Z
     154: invokestatic  #66                 // Method java/lang/Boolean.valueOf:(Z)Ljava/lang/Boolean;
     157: invokestatic  #9                  // Method org/junit/Assert.assertEquals:(Ljava/lang/Object;Ljava/lang/Object;)V
     160: aload_1
     161: invokevirtual #40                 // Method org/apache/hadoop/hbase/procedure2/store/ProcedureStoreTracker.reset:()V
     164: iconst_0
     165: istore_3
     166: iload_3
     167: aload_2
     168: arraylength
     169: if_icmpge     185
     172: aload_1
     173: aload_2
     174: iload_3
     175: laload
     176: invokevirtual #6                  // Method org/apache/hadoop/hbase/procedure2/store/ProcedureStoreTracker.insert:(J)V
     179: iinc          3, 1
     182: goto          166
     185: iconst_0
     186: invokestatic  #66                 // Method java/lang/Boolean.valueOf:(Z)Ljava/lang/Boolean;
     189: aload_1
     190: invokevirtual #4                  // Method org/apache/hadoop/hbase/procedure2/store/ProcedureStoreTracker.isEmpty:()Z
     193: invokestatic  #66                 // Method java/lang/Boolean.valueOf:(Z)Ljava/lang/Boolean;
     196: invokestatic  #9                  // Method org/junit/Assert.assertEquals:(Ljava/lang/Object;Ljava/lang/Object;)V
     199: aload_1
     200: aload_2
     201: invokevirtual #67                 // Method org/apache/hadoop/hbase/procedure2/store/ProcedureStoreTracker.setDeletedIfModified:([J)V
     204: iconst_1
     205: invokestatic  #66                 // Method java/lang/Boolean.valueOf:(Z)Ljava/lang/Boolean;
     208: aload_1
     209: invokevirtual #4                  // Method org/apache/hadoop/hbase/procedure2/store/ProcedureStoreTracker.isEmpty:()Z
     212: invokestatic  #66                 // Method java/lang/Boolean.valueOf:(Z)Ljava/lang/Boolean;
     215: invokestatic  #9                  // Method org/junit/Assert.assertEquals:(Ljava/lang/Object;Ljava/lang/Object;)V
     218: return

  public void testGetActiveProcIds();
    Code:
       0: new           #2                  // class org/apache/hadoop/hbase/procedure2/store/ProcedureStoreTracker
       3: dup
       4: invokespecial #3                  // Method org/apache/hadoop/hbase/procedure2/store/ProcedureStoreTracker."<init>":()V
       7: astore_1
       8: iconst_0
       9: istore_2
      10: iload_2
      11: sipush        10000
      14: if_icmpge     32
      17: aload_1
      18: iload_2
      19: bipush        10
      21: imul
      22: i2l
      23: invokevirtual #6                  // Method org/apache/hadoop/hbase/procedure2/store/ProcedureStoreTracker.insert:(J)V
      26: iinc          2, 1
      29: goto          10
      32: iconst_0
      33: istore_2
      34: iload_2
      35: sipush        10000
      38: if_icmpge     56
      41: aload_1
      42: iload_2
      43: bipush        10
      45: imul
      46: i2l
      47: invokevirtual #10                 // Method org/apache/hadoop/hbase/procedure2/store/ProcedureStoreTracker.delete:(J)V
      50: iinc          2, 2
      53: goto          34
      56: aload_1
      57: invokevirtual #68                 // Method org/apache/hadoop/hbase/procedure2/store/ProcedureStoreTracker.getAllActiveProcIds:()[J
      60: astore_2
      61: ldc2_w        #69                 // long 5000l
      64: aload_2
      65: arraylength
      66: i2l
      67: invokestatic  #71                 // Method org/junit/Assert.assertEquals:(JJ)V
      70: iconst_0
      71: istore_3
      72: iload_3
      73: sipush        5000
      76: if_icmpge     100
      79: iconst_2
      80: iload_3
      81: imul
      82: iconst_1
      83: iadd
      84: bipush        10
      86: imul
      87: i2l
      88: aload_2
      89: iload_3
      90: laload
      91: invokestatic  #71                 // Method org/junit/Assert.assertEquals:(JJ)V
      94: iinc          3, 1
      97: goto          72
     100: return

  public void testGetActiveMinProcId();
    Code:
       0: new           #2                  // class org/apache/hadoop/hbase/procedure2/store/ProcedureStoreTracker
       3: dup
       4: invokespecial #3                  // Method org/apache/hadoop/hbase/procedure2/store/ProcedureStoreTracker."<init>":()V
       7: astore_1
       8: ldc2_w        #73                 // long -1l
      11: aload_1
      12: invokevirtual #75                 // Method org/apache/hadoop/hbase/procedure2/store/ProcedureStoreTracker.getActiveMinProcId:()J
      15: invokestatic  #71                 // Method org/junit/Assert.assertEquals:(JJ)V
      18: bipush        100
      20: istore_2
      21: iload_2
      22: sipush        1000
      25: if_icmpge     43
      28: aload_1
      29: iload_2
      30: i2l
      31: invokevirtual #6                  // Method org/apache/hadoop/hbase/procedure2/store/ProcedureStoreTracker.insert:(J)V
      34: iconst_2
      35: iload_2
      36: imul
      37: iconst_1
      38: iadd
      39: istore_2
      40: goto          21
      43: bipush        100
      45: istore_2
      46: iload_2
      47: sipush        1000
      50: if_icmpge     77
      53: iload_2
      54: i2l
      55: aload_1
      56: invokevirtual #75                 // Method org/apache/hadoop/hbase/procedure2/store/ProcedureStoreTracker.getActiveMinProcId:()J
      59: invokestatic  #71                 // Method org/junit/Assert.assertEquals:(JJ)V
      62: aload_1
      63: iload_2
      64: i2l
      65: invokevirtual #10                 // Method org/apache/hadoop/hbase/procedure2/store/ProcedureStoreTracker.delete:(J)V
      68: iconst_2
      69: iload_2
      70: imul
      71: iconst_1
      72: iadd
      73: istore_2
      74: goto          46
      77: ldc2_w        #73                 // long -1l
      80: aload_1
      81: invokevirtual #75                 // Method org/apache/hadoop/hbase/procedure2/store/ProcedureStoreTracker.getActiveMinProcId:()J
      84: invokestatic  #71                 // Method org/junit/Assert.assertEquals:(JJ)V
      87: return

  static {};
    Code:
       0: ldc           #76                 // class org/apache/hadoop/hbase/procedure2/store/TestProcedureStoreTracker
       2: invokestatic  #77                 // Method org/apache/hadoop/hbase/HBaseClassTestRule.forClass:(Ljava/lang/Class;)Lorg/apache/hadoop/hbase/HBaseClassTestRule;
       5: putstatic     #78                 // Field CLASS_RULE:Lorg/apache/hadoop/hbase/HBaseClassTestRule;
       8: ldc           #76                 // class org/apache/hadoop/hbase/procedure2/store/TestProcedureStoreTracker
      10: invokestatic  #79                 // Method org/slf4j/LoggerFactory.getLogger:(Ljava/lang/Class;)Lorg/slf4j/Logger;
      13: putstatic     #41                 // Field LOG:Lorg/slf4j/Logger;
      16: return
}
