Compiled from "TestCacheConfig.java"
class org.apache.hadoop.hbase.io.hfile.TestCacheConfig$1 extends org.apache.hadoop.hbase.io.hfile.TestCacheConfig$DataCacheEntry {
  final long val$justTooBigSize;

  final org.apache.hadoop.hbase.io.hfile.TestCacheConfig this$0;

  org.apache.hadoop.hbase.io.hfile.TestCacheConfig$1(org.apache.hadoop.hbase.io.hfile.TestCacheConfig, long);
    Code:
       0: aload_0
       1: aload_1
       2: putfield      #1                  // Field this$0:Lorg/apache/hadoop/hbase/io/hfile/TestCacheConfig;
       5: aload_0
       6: lload_2
       7: putfield      #2                  // Field val$justTooBigSize:J
      10: aload_0
      11: invokespecial #3                  // Method org/apache/hadoop/hbase/io/hfile/TestCacheConfig$DataCacheEntry."<init>":()V
      14: return

  public long heapSize();
    Code:
       0: aload_0
       1: getfield      #2                  // Field val$justTooBigSize:J
       4: lreturn

  public int getSerializedLength();
    Code:
       0: aload_0
       1: invokevirtual #4                  // Method heapSize:()J
       4: l2i
       5: ireturn
}
