Compiled from "TestTimeout.java"
class org.apache.hadoop.hbase.TestTimeout$1 extends java.lang.Thread {
  final org.apache.hadoop.hbase.TestTimeout this$0;

  org.apache.hadoop.hbase.TestTimeout$1(org.apache.hadoop.hbase.TestTimeout, java.lang.String);
    Code:
       0: aload_0
       1: aload_1
       2: putfield      #1                  // Field this$0:Lorg/apache/hadoop/hbase/TestTimeout;
       5: aload_0
       6: aload_2
       7: invokespecial #2                  // Method java/lang/Thread."<init>":(Ljava/lang/String;)V
      10: return

  public void run();
    Code:
       0: aload_0
       1: dup
       2: astore_1
       3: monitorenter
       4: goto          4
       7: astore_2
       8: aload_1
       9: monitorexit
      10: aload_2
      11: athrow
    Exception table:
       from    to  target type
           4    10     7   any
}
