Compiled from "TestGetScanPartialResult.java"
public class org.apache.hadoop.hbase.client.TestGetScanPartialResult {
  public static final org.apache.hadoop.hbase.HBaseClassTestRule CLASS_RULE;

  public org.apache.hadoop.hbase.client.TestGetScanPartialResult();
    Code:
       0: aload_0
       1: invokespecial #1                  // Method java/lang/Object."<init>":()V
       4: return

  public static void setUp() throws java.lang.Exception;
    Code:
       0: getstatic     #2                  // Field TEST_UTIL:Lorg/apache/hadoop/hbase/HBaseTestingUtility;
       3: invokevirtual #3                  // Method org/apache/hadoop/hbase/HBaseTestingUtility.startMiniCluster:()Lorg/apache/hadoop/hbase/MiniHBaseCluster;
       6: pop
       7: getstatic     #2                  // Field TEST_UTIL:Lorg/apache/hadoop/hbase/HBaseTestingUtility;
      10: getstatic     #4                  // Field TABLE:Lorg/apache/hadoop/hbase/TableName;
      13: getstatic     #5                  // Field CF:[B
      16: invokevirtual #6                  // Method org/apache/hadoop/hbase/HBaseTestingUtility.createTable:(Lorg/apache/hadoop/hbase/TableName;[B)Lorg/apache/hadoop/hbase/client/Table;
      19: pop
      20: return

  public static void tearDown() throws java.lang.Exception;
    Code:
       0: getstatic     #2                  // Field TEST_UTIL:Lorg/apache/hadoop/hbase/HBaseTestingUtility;
       3: invokevirtual #7                  // Method org/apache/hadoop/hbase/HBaseTestingUtility.shutdownMiniCluster:()V
       6: return

  public void test() throws java.io.IOException;
    Code:
       0: getstatic     #2                  // Field TEST_UTIL:Lorg/apache/hadoop/hbase/HBaseTestingUtility;
       3: invokevirtual #8                  // Method org/apache/hadoop/hbase/HBaseTestingUtility.getConnection:()Lorg/apache/hadoop/hbase/client/Connection;
       6: getstatic     #4                  // Field TABLE:Lorg/apache/hadoop/hbase/TableName;
       9: invokeinterface #9,  2            // InterfaceMethod org/apache/hadoop/hbase/client/Connection.getTable:(Lorg/apache/hadoop/hbase/TableName;)Lorg/apache/hadoop/hbase/client/Table;
      14: astore_1
      15: aconst_null
      16: astore_2
      17: sipush        10000
      20: invokestatic  #11                 // Method makeLargeValue:(I)[B
      23: astore_3
      24: new           #12                 // class org/apache/hadoop/hbase/client/Put
      27: dup
      28: getstatic     #13                 // Field ROW:[B
      31: invokespecial #14                 // Method org/apache/hadoop/hbase/client/Put."<init>":([B)V
      34: astore        4
      36: iconst_0
      37: istore        5
      39: iload         5
      41: sipush        300
      44: if_icmpge     71
      47: aload         4
      49: getstatic     #5                  // Field CF:[B
      52: iload         5
      54: invokestatic  #15                 // Method java/lang/Integer.toString:(I)Ljava/lang/String;
      57: invokestatic  #16                 // Method org/apache/hadoop/hbase/util/Bytes.toBytes:(Ljava/lang/String;)[B
      60: aload_3
      61: invokevirtual #17                 // Method org/apache/hadoop/hbase/client/Put.addColumn:([B[B[B)Lorg/apache/hadoop/hbase/client/Put;
      64: pop
      65: iinc          5, 1
      68: goto          39
      71: aload_1
      72: aload         4
      74: invokeinterface #18,  2           // InterfaceMethod org/apache/hadoop/hbase/client/Table.put:(Lorg/apache/hadoop/hbase/client/Put;)V
      79: new           #19                 // class org/apache/hadoop/hbase/client/Scan
      82: dup
      83: invokespecial #20                 // Method org/apache/hadoop/hbase/client/Scan."<init>":()V
      86: astore        5
      88: aload         5
      90: getstatic     #13                 // Field ROW:[B
      93: invokevirtual #21                 // Method org/apache/hadoop/hbase/client/Scan.withStartRow:([B)Lorg/apache/hadoop/hbase/client/Scan;
      96: pop
      97: aload         5
      99: getstatic     #13                 // Field ROW:[B
     102: iconst_1
     103: invokevirtual #22                 // Method org/apache/hadoop/hbase/client/Scan.withStopRow:([BZ)Lorg/apache/hadoop/hbase/client/Scan;
     106: pop
     107: aload         5
     109: iconst_1
     110: invokevirtual #23                 // Method org/apache/hadoop/hbase/client/Scan.setAllowPartialResults:(Z)Lorg/apache/hadoop/hbase/client/Scan;
     113: pop
     114: aload         5
     116: ldc2_w        #24                 // long 2097152l
     119: invokevirtual #26                 // Method org/apache/hadoop/hbase/client/Scan.setMaxResultSize:(J)Lorg/apache/hadoop/hbase/client/Scan;
     122: pop
     123: aload         5
     125: iconst_1
     126: invokevirtual #27                 // Method org/apache/hadoop/hbase/client/Scan.readVersions:(I)Lorg/apache/hadoop/hbase/client/Scan;
     129: pop
     130: aload_1
     131: aload         5
     133: invokeinterface #28,  2           // InterfaceMethod org/apache/hadoop/hbase/client/Table.getScanner:(Lorg/apache/hadoop/hbase/client/Scan;)Lorg/apache/hadoop/hbase/client/ResultScanner;
     138: astore        6
     140: iconst_0
     141: istore        7
     143: iconst_0
     144: istore        8
     146: aload         6
     148: invokeinterface #29,  1           // InterfaceMethod org/apache/hadoop/hbase/client/ResultScanner.next:()Lorg/apache/hadoop/hbase/client/Result;
     153: astore        9
     155: aload         9
     157: ifnull        190
     160: iinc          7, 1
     163: iload         8
     165: aload         9
     167: invokevirtual #30                 // Method org/apache/hadoop/hbase/client/Result.listCells:()Ljava/util/List;
     170: invokeinterface #31,  1           // InterfaceMethod java/util/List.size:()I
     175: iadd
     176: istore        8
     178: aload         6
     180: invokeinterface #29,  1           // InterfaceMethod org/apache/hadoop/hbase/client/ResultScanner.next:()Lorg/apache/hadoop/hbase/client/Result;
     185: astore        9
     187: goto          155
     190: ldc2_w        #32                 // long 300l
     193: iload         8
     195: i2l
     196: invokestatic  #34                 // Method org/junit/Assert.assertEquals:(JJ)V
     199: iload         7
     201: iconst_5
     202: if_icmpge     209
     205: iconst_1
     206: goto          210
     209: iconst_0
     210: invokestatic  #35                 // Method org/junit/Assert.assertTrue:(Z)V
     213: aload_1
     214: ifnull        292
     217: aload_2
     218: ifnull        239
     221: aload_1
     222: invokeinterface #36,  1           // InterfaceMethod org/apache/hadoop/hbase/client/Table.close:()V
     227: goto          292
     230: astore_3
     231: aload_2
     232: aload_3
     233: invokevirtual #38                 // Method java/lang/Throwable.addSuppressed:(Ljava/lang/Throwable;)V
     236: goto          292
     239: aload_1
     240: invokeinterface #36,  1           // InterfaceMethod org/apache/hadoop/hbase/client/Table.close:()V
     245: goto          292
     248: astore_3
     249: aload_3
     250: astore_2
     251: aload_3
     252: athrow
     253: astore        10
     255: aload_1
     256: ifnull        289
     259: aload_2
     260: ifnull        283
     263: aload_1
     264: invokeinterface #36,  1           // InterfaceMethod org/apache/hadoop/hbase/client/Table.close:()V
     269: goto          289
     272: astore        11
     274: aload_2
     275: aload         11
     277: invokevirtual #38                 // Method java/lang/Throwable.addSuppressed:(Ljava/lang/Throwable;)V
     280: goto          289
     283: aload_1
     284: invokeinterface #36,  1           // InterfaceMethod org/apache/hadoop/hbase/client/Table.close:()V
     289: aload         10
     291: athrow
     292: return
    Exception table:
       from    to  target type
         221   227   230   Class java/lang/Throwable
          17   213   248   Class java/lang/Throwable
          17   213   253   any
         263   269   272   Class java/lang/Throwable
         248   255   253   any

  static {};
    Code:
       0: ldc           #10                 // class org/apache/hadoop/hbase/client/TestGetScanPartialResult
       2: invokestatic  #39                 // Method org/apache/hadoop/hbase/HBaseClassTestRule.forClass:(Ljava/lang/Class;)Lorg/apache/hadoop/hbase/HBaseClassTestRule;
       5: putstatic     #40                 // Field CLASS_RULE:Lorg/apache/hadoop/hbase/HBaseClassTestRule;
       8: new           #41                 // class org/apache/hadoop/hbase/HBaseTestingUtility
      11: dup
      12: invokespecial #42                 // Method org/apache/hadoop/hbase/HBaseTestingUtility."<init>":()V
      15: putstatic     #2                  // Field TEST_UTIL:Lorg/apache/hadoop/hbase/HBaseTestingUtility;
      18: ldc           #43                 // String table
      20: invokestatic  #44                 // Method org/apache/hadoop/hbase/TableName.valueOf:(Ljava/lang/String;)Lorg/apache/hadoop/hbase/TableName;
      23: putstatic     #4                  // Field TABLE:Lorg/apache/hadoop/hbase/TableName;
      26: iconst_2
      27: newarray       byte
      29: dup
      30: iconst_0
      31: bipush        99
      33: bastore
      34: dup
      35: iconst_1
      36: bipush        102
      38: bastore
      39: putstatic     #5                  // Field CF:[B
      42: iconst_3
      43: newarray       byte
      45: dup
      46: iconst_0
      47: bipush        114
      49: bastore
      50: dup
      51: iconst_1
      52: bipush        111
      54: bastore
      55: dup
      56: iconst_2
      57: bipush        119
      59: bastore
      60: putstatic     #13                 // Field ROW:[B
      63: return
}
