Compiled from "TestTableName.java"
class org.apache.hadoop.hbase.TestTableName$Names {
  java.lang.String ns;

  byte[] nsb;

  java.lang.String tn;

  byte[] tnb;

  java.lang.String nn;

  byte[] nnb;

  org.apache.hadoop.hbase.TestTableName$Names(java.lang.String, java.lang.String);
    Code:
       0: aload_0
       1: invokespecial #1                  // Method java/lang/Object."<init>":()V
       4: aload_0
       5: aload_1
       6: putfield      #2                  // Field ns:Ljava/lang/String;
       9: aload_0
      10: aload_1
      11: invokestatic  #3                  // Method org/apache/hadoop/hbase/util/Bytes.toBytes:(Ljava/lang/String;)[B
      14: putfield      #4                  // Field nsb:[B
      17: aload_0
      18: aload_2
      19: putfield      #5                  // Field tn:Ljava/lang/String;
      22: aload_0
      23: aload_2
      24: invokestatic  #3                  // Method org/apache/hadoop/hbase/util/Bytes.toBytes:(Ljava/lang/String;)[B
      27: putfield      #6                  // Field tnb:[B
      30: aload_0
      31: new           #7                  // class java/lang/StringBuilder
      34: dup
      35: invokespecial #8                  // Method java/lang/StringBuilder."<init>":()V
      38: aload_0
      39: getfield      #2                  // Field ns:Ljava/lang/String;
      42: invokevirtual #9                  // Method java/lang/StringBuilder.append:(Ljava/lang/String;)Ljava/lang/StringBuilder;
      45: ldc           #10                 // String :
      47: invokevirtual #9                  // Method java/lang/StringBuilder.append:(Ljava/lang/String;)Ljava/lang/StringBuilder;
      50: aload_0
      51: getfield      #5                  // Field tn:Ljava/lang/String;
      54: invokevirtual #9                  // Method java/lang/StringBuilder.append:(Ljava/lang/String;)Ljava/lang/StringBuilder;
      57: invokevirtual #11                 // Method java/lang/StringBuilder.toString:()Ljava/lang/String;
      60: putfield      #12                 // Field nn:Ljava/lang/String;
      63: aload_0
      64: aload_0
      65: getfield      #12                 // Field nn:Ljava/lang/String;
      68: invokestatic  #3                  // Method org/apache/hadoop/hbase/util/Bytes.toBytes:(Ljava/lang/String;)[B
      71: putfield      #13                 // Field nnb:[B
      74: return

  public boolean equals(java.lang.Object);
    Code:
       0: aload_0
       1: aload_1
       2: if_acmpne     7
       5: iconst_1
       6: ireturn
       7: aload_1
       8: ifnull        22
      11: aload_0
      12: invokevirtual #14                 // Method java/lang/Object.getClass:()Ljava/lang/Class;
      15: aload_1
      16: invokevirtual #14                 // Method java/lang/Object.getClass:()Ljava/lang/Class;
      19: if_acmpeq     24
      22: iconst_0
      23: ireturn
      24: aload_1
      25: checkcast     #15                 // class org/apache/hadoop/hbase/TestTableName$Names
      28: astore_2
      29: aload_0
      30: getfield      #2                  // Field ns:Ljava/lang/String;
      33: aload_2
      34: getfield      #2                  // Field ns:Ljava/lang/String;
      37: invokevirtual #16                 // Method java/lang/String.equals:(Ljava/lang/Object;)Z
      40: ifne          45
      43: iconst_0
      44: ireturn
      45: aload_0
      46: getfield      #5                  // Field tn:Ljava/lang/String;
      49: aload_2
      50: getfield      #5                  // Field tn:Ljava/lang/String;
      53: invokevirtual #16                 // Method java/lang/String.equals:(Ljava/lang/Object;)Z
      56: ifne          61
      59: iconst_0
      60: ireturn
      61: iconst_1
      62: ireturn

  public int hashCode();
    Code:
       0: aload_0
       1: getfield      #2                  // Field ns:Ljava/lang/String;
       4: invokevirtual #17                 // Method java/lang/String.hashCode:()I
       7: istore_1
       8: bipush        31
      10: iload_1
      11: imul
      12: aload_0
      13: getfield      #5                  // Field tn:Ljava/lang/String;
      16: invokevirtual #17                 // Method java/lang/String.hashCode:()I
      19: iadd
      20: istore_1
      21: iload_1
      22: ireturn
}
