Compiled from "TestCellACLs.java"
public class org.apache.hadoop.hbase.security.access.TestCellACLs extends org.apache.hadoop.hbase.security.access.SecureTestUtil {
  public static final org.apache.hadoop.hbase.HBaseClassTestRule CLASS_RULE;

  public org.apache.hadoop.hbase.TestTableName TEST_TABLE;

  public org.apache.hadoop.hbase.security.access.TestCellACLs();
    Code:
       0: aload_0
       1: invokespecial #11                 // Method org/apache/hadoop/hbase/security/access/SecureTestUtil."<init>":()V
       4: aload_0
       5: new           #12                 // class org/apache/hadoop/hbase/TestTableName
       8: dup
       9: invokespecial #13                 // Method org/apache/hadoop/hbase/TestTableName."<init>":()V
      12: putfield      #14                 // Field TEST_TABLE:Lorg/apache/hadoop/hbase/TestTableName;
      15: return

  public static void setupBeforeClass() throws java.lang.Exception;
    Code:
       0: getstatic     #15                 // Field TEST_UTIL:Lorg/apache/hadoop/hbase/HBaseTestingUtility;
       3: invokevirtual #16                 // Method org/apache/hadoop/hbase/HBaseTestingUtility.getConfiguration:()Lorg/apache/hadoop/conf/Configuration;
       6: putstatic     #10                 // Field conf:Lorg/apache/hadoop/conf/Configuration;
       9: getstatic     #10                 // Field conf:Lorg/apache/hadoop/conf/Configuration;
      12: ldc           #18                 // String hbase.regionserver.metahandler.count
      14: bipush        10
      16: invokevirtual #19                 // Method org/apache/hadoop/conf/Configuration.setInt:(Ljava/lang/String;I)V
      19: getstatic     #10                 // Field conf:Lorg/apache/hadoop/conf/Configuration;
      22: invokestatic  #20                 // Method enableSecurity:(Lorg/apache/hadoop/conf/Configuration;)V
      25: getstatic     #10                 // Field conf:Lorg/apache/hadoop/conf/Configuration;
      28: invokestatic  #21                 // Method verifyConfiguration:(Lorg/apache/hadoop/conf/Configuration;)V
      31: getstatic     #10                 // Field conf:Lorg/apache/hadoop/conf/Configuration;
      34: ldc           #23                 // String hbase.security.access.early_out
      36: iconst_0
      37: invokevirtual #24                 // Method org/apache/hadoop/conf/Configuration.setBoolean:(Ljava/lang/String;Z)V
      40: getstatic     #15                 // Field TEST_UTIL:Lorg/apache/hadoop/hbase/HBaseTestingUtility;
      43: invokevirtual #25                 // Method org/apache/hadoop/hbase/HBaseTestingUtility.startMiniCluster:()Lorg/apache/hadoop/hbase/MiniHBaseCluster;
      46: pop
      47: getstatic     #15                 // Field TEST_UTIL:Lorg/apache/hadoop/hbase/HBaseTestingUtility;
      50: invokevirtual #26                 // Method org/apache/hadoop/hbase/HBaseTestingUtility.getMiniHBaseCluster:()Lorg/apache/hadoop/hbase/MiniHBaseCluster;
      53: invokevirtual #27                 // Method org/apache/hadoop/hbase/MiniHBaseCluster.getMaster:()Lorg/apache/hadoop/hbase/master/HMaster;
      56: invokevirtual #28                 // Method org/apache/hadoop/hbase/master/HMaster.getMasterCoprocessorHost:()Lorg/apache/hadoop/hbase/master/MasterCoprocessorHost;
      59: astore_0
      60: aload_0
      61: ldc           #29                 // class org/apache/hadoop/hbase/security/access/AccessController
      63: iconst_0
      64: getstatic     #10                 // Field conf:Lorg/apache/hadoop/conf/Configuration;
      67: invokevirtual #31                 // Method org/apache/hadoop/hbase/master/MasterCoprocessorHost.load:(Ljava/lang/Class;ILorg/apache/hadoop/conf/Configuration;)V
      70: aload_0
      71: ldc           #29                 // class org/apache/hadoop/hbase/security/access/AccessController
      73: invokevirtual #32                 // Method org/apache/hadoop/hbase/master/MasterCoprocessorHost.findCoprocessor:(Ljava/lang/Class;)Lorg/apache/hadoop/hbase/Coprocessor;
      76: checkcast     #29                 // class org/apache/hadoop/hbase/security/access/AccessController
      79: astore_1
      80: aload_0
      81: aload_1
      82: iconst_0
      83: iconst_1
      84: getstatic     #10                 // Field conf:Lorg/apache/hadoop/conf/Configuration;
      87: invokevirtual #33                 // Method org/apache/hadoop/hbase/master/MasterCoprocessorHost.createEnvironment:(Lorg/apache/hadoop/hbase/coprocessor/MasterCoprocessor;IILorg/apache/hadoop/conf/Configuration;)Lorg/apache/hadoop/hbase/master/MasterCoprocessorHost$MasterEnvironment;
      90: pop
      91: getstatic     #15                 // Field TEST_UTIL:Lorg/apache/hadoop/hbase/HBaseTestingUtility;
      94: invokevirtual #26                 // Method org/apache/hadoop/hbase/HBaseTestingUtility.getMiniHBaseCluster:()Lorg/apache/hadoop/hbase/MiniHBaseCluster;
      97: iconst_0
      98: invokevirtual #34                 // Method org/apache/hadoop/hbase/MiniHBaseCluster.getRegionServer:(I)Lorg/apache/hadoop/hbase/regionserver/HRegionServer;
     101: invokevirtual #35                 // Method org/apache/hadoop/hbase/regionserver/HRegionServer.getRegionServerCoprocessorHost:()Lorg/apache/hadoop/hbase/regionserver/RegionServerCoprocessorHost;
     104: astore_2
     105: aload_2
     106: aload_1
     107: iconst_0
     108: iconst_1
     109: getstatic     #10                 // Field conf:Lorg/apache/hadoop/conf/Configuration;
     112: invokevirtual #36                 // Method org/apache/hadoop/hbase/regionserver/RegionServerCoprocessorHost.createEnvironment:(Lorg/apache/hadoop/hbase/coprocessor/RegionServerCoprocessor;IILorg/apache/hadoop/conf/Configuration;)Lorg/apache/hadoop/hbase/regionserver/RegionServerCoprocessorHost$RegionServerEnvironment;
     115: pop
     116: getstatic     #15                 // Field TEST_UTIL:Lorg/apache/hadoop/hbase/HBaseTestingUtility;
     119: getstatic     #37                 // Field org/apache/hadoop/hbase/security/access/PermissionStorage.ACL_TABLE_NAME:Lorg/apache/hadoop/hbase/TableName;
     122: invokevirtual #38                 // Method org/apache/hadoop/hbase/HBaseTestingUtility.waitTableEnabled:(Lorg/apache/hadoop/hbase/TableName;)V
     125: getstatic     #10                 // Field conf:Lorg/apache/hadoop/conf/Configuration;
     128: ldc           #39                 // String owner
     130: iconst_0
     131: anewarray     #40                 // class java/lang/String
     134: invokestatic  #41                 // Method org/apache/hadoop/hbase/security/User.createUserForTesting:(Lorg/apache/hadoop/conf/Configuration;Ljava/lang/String;[Ljava/lang/String;)Lorg/apache/hadoop/hbase/security/User;
     137: putstatic     #42                 // Field USER_OWNER:Lorg/apache/hadoop/hbase/security/User;
     140: getstatic     #10                 // Field conf:Lorg/apache/hadoop/conf/Configuration;
     143: ldc           #43                 // String other
     145: iconst_0
     146: anewarray     #40                 // class java/lang/String
     149: invokestatic  #41                 // Method org/apache/hadoop/hbase/security/User.createUserForTesting:(Lorg/apache/hadoop/conf/Configuration;Ljava/lang/String;[Ljava/lang/String;)Lorg/apache/hadoop/hbase/security/User;
     152: putstatic     #44                 // Field USER_OTHER:Lorg/apache/hadoop/hbase/security/User;
     155: getstatic     #10                 // Field conf:Lorg/apache/hadoop/conf/Configuration;
     158: ldc           #45                 // String group_user
     160: iconst_1
     161: anewarray     #40                 // class java/lang/String
     164: dup
     165: iconst_0
     166: ldc           #47                 // String group
     168: aastore
     169: invokestatic  #41                 // Method org/apache/hadoop/hbase/security/User.createUserForTesting:(Lorg/apache/hadoop/conf/Configuration;Ljava/lang/String;[Ljava/lang/String;)Lorg/apache/hadoop/hbase/security/User;
     172: putstatic     #48                 // Field GROUP_USER:Lorg/apache/hadoop/hbase/security/User;
     175: iconst_2
     176: anewarray     #40                 // class java/lang/String
     179: dup
     180: iconst_0
     181: getstatic     #44                 // Field USER_OTHER:Lorg/apache/hadoop/hbase/security/User;
     184: invokevirtual #49                 // Method org/apache/hadoop/hbase/security/User.getShortName:()Ljava/lang/String;
     187: aastore
     188: dup
     189: iconst_1
     190: ldc           #47                 // String group
     192: invokestatic  #50                 // Method org/apache/hadoop/hbase/AuthUtil.toGroupEntry:(Ljava/lang/String;)Ljava/lang/String;
     195: aastore
     196: putstatic     #5                  // Field usersAndGroups:[Ljava/lang/String;
     199: return

  public static void tearDownAfterClass() throws java.lang.Exception;
    Code:
       0: getstatic     #15                 // Field TEST_UTIL:Lorg/apache/hadoop/hbase/HBaseTestingUtility;
       3: invokevirtual #51                 // Method org/apache/hadoop/hbase/HBaseTestingUtility.shutdownMiniCluster:()V
       6: return

  public void setUp() throws java.lang.Exception;
    Code:
       0: getstatic     #15                 // Field TEST_UTIL:Lorg/apache/hadoop/hbase/HBaseTestingUtility;
       3: invokevirtual #52                 // Method org/apache/hadoop/hbase/HBaseTestingUtility.getAdmin:()Lorg/apache/hadoop/hbase/client/Admin;
       6: astore_1
       7: new           #53                 // class org/apache/hadoop/hbase/HTableDescriptor
      10: dup
      11: aload_0
      12: getfield      #14                 // Field TEST_TABLE:Lorg/apache/hadoop/hbase/TestTableName;
      15: invokevirtual #54                 // Method org/apache/hadoop/hbase/TestTableName.getTableName:()Lorg/apache/hadoop/hbase/TableName;
      18: invokespecial #55                 // Method org/apache/hadoop/hbase/HTableDescriptor."<init>":(Lorg/apache/hadoop/hbase/TableName;)V
      21: astore_2
      22: new           #56                 // class org/apache/hadoop/hbase/HColumnDescriptor
      25: dup
      26: getstatic     #9                  // Field TEST_FAMILY:[B
      29: invokespecial #57                 // Method org/apache/hadoop/hbase/HColumnDescriptor."<init>":([B)V
      32: astore_3
      33: aload_3
      34: iconst_4
      35: invokevirtual #58                 // Method org/apache/hadoop/hbase/HColumnDescriptor.setMaxVersions:(I)Lorg/apache/hadoop/hbase/HColumnDescriptor;
      38: pop
      39: aload_2
      40: getstatic     #42                 // Field USER_OWNER:Lorg/apache/hadoop/hbase/security/User;
      43: invokevirtual #59                 // Method org/apache/hadoop/hbase/HTableDescriptor.setOwner:(Lorg/apache/hadoop/hbase/security/User;)Lorg/apache/hadoop/hbase/HTableDescriptor;
      46: pop
      47: aload_2
      48: aload_3
      49: invokevirtual #60                 // Method org/apache/hadoop/hbase/HTableDescriptor.addFamily:(Lorg/apache/hadoop/hbase/HColumnDescriptor;)Lorg/apache/hadoop/hbase/HTableDescriptor;
      52: pop
      53: aload_1
      54: aload_2
      55: iconst_1
      56: anewarray     #61                 // class "[B"
      59: dup
      60: iconst_0
      61: ldc           #62                 // String s
      63: invokestatic  #63                 // Method org/apache/hadoop/hbase/util/Bytes.toBytes:(Ljava/lang/String;)[B
      66: aastore
      67: invokeinterface #64,  3           // InterfaceMethod org/apache/hadoop/hbase/client/Admin.createTable:(Lorg/apache/hadoop/hbase/client/TableDescriptor;[[B)V
      72: getstatic     #15                 // Field TEST_UTIL:Lorg/apache/hadoop/hbase/HBaseTestingUtility;
      75: aload_0
      76: getfield      #14                 // Field TEST_TABLE:Lorg/apache/hadoop/hbase/TestTableName;
      79: invokevirtual #54                 // Method org/apache/hadoop/hbase/TestTableName.getTableName:()Lorg/apache/hadoop/hbase/TableName;
      82: invokevirtual #38                 // Method org/apache/hadoop/hbase/HBaseTestingUtility.waitTableEnabled:(Lorg/apache/hadoop/hbase/TableName;)V
      85: getstatic     #65                 // Field LOG:Lorg/slf4j/Logger;
      88: ldc           #66                 // String Sleeping a second because of HBASE-12581
      90: invokeinterface #67,  2           // InterfaceMethod org/slf4j/Logger.info:(Ljava/lang/String;)V
      95: ldc2_w        #68                 // long 1000l
      98: invokestatic  #70                 // Method org/apache/hadoop/hbase/util/Threads.sleep:(J)V
     101: return

  public void testCellPermissions() throws java.lang.Exception;
    Code:
       0: new           #71                 // class org/apache/hadoop/hbase/security/access/TestCellACLs$1
       3: dup
       4: aload_0
       5: invokespecial #72                 // Method org/apache/hadoop/hbase/security/access/TestCellACLs$1."<init>":(Lorg/apache/hadoop/hbase/security/access/TestCellACLs;)V
       8: iconst_1
       9: anewarray     #73                 // class org/apache/hadoop/hbase/security/User
      12: dup
      13: iconst_0
      14: getstatic     #42                 // Field USER_OWNER:Lorg/apache/hadoop/hbase/security/User;
      17: aastore
      18: invokestatic  #74                 // Method verifyAllowed:(Lorg/apache/hadoop/hbase/security/access/SecureTestUtil$AccessTestAction;[Lorg/apache/hadoop/hbase/security/User;)V
      21: new           #75                 // class org/apache/hadoop/hbase/security/access/TestCellACLs$2
      24: dup
      25: aload_0
      26: invokespecial #76                 // Method org/apache/hadoop/hbase/security/access/TestCellACLs$2."<init>":(Lorg/apache/hadoop/hbase/security/access/TestCellACLs;)V
      29: astore_1
      30: new           #77                 // class org/apache/hadoop/hbase/security/access/TestCellACLs$3
      33: dup
      34: aload_0
      35: invokespecial #78                 // Method org/apache/hadoop/hbase/security/access/TestCellACLs$3."<init>":(Lorg/apache/hadoop/hbase/security/access/TestCellACLs;)V
      38: astore_2
      39: new           #79                 // class org/apache/hadoop/hbase/security/access/TestCellACLs$4
      42: dup
      43: aload_0
      44: invokespecial #80                 // Method org/apache/hadoop/hbase/security/access/TestCellACLs$4."<init>":(Lorg/apache/hadoop/hbase/security/access/TestCellACLs;)V
      47: astore_3
      48: new           #81                 // class org/apache/hadoop/hbase/security/access/TestCellACLs$5
      51: dup
      52: aload_0
      53: invokespecial #82                 // Method org/apache/hadoop/hbase/security/access/TestCellACLs$5."<init>":(Lorg/apache/hadoop/hbase/security/access/TestCellACLs;)V
      56: astore        4
      58: aload_1
      59: iconst_2
      60: anewarray     #73                 // class org/apache/hadoop/hbase/security/User
      63: dup
      64: iconst_0
      65: getstatic     #44                 // Field USER_OTHER:Lorg/apache/hadoop/hbase/security/User;
      68: aastore
      69: dup
      70: iconst_1
      71: getstatic     #48                 // Field GROUP_USER:Lorg/apache/hadoop/hbase/security/User;
      74: aastore
      75: invokestatic  #74                 // Method verifyAllowed:(Lorg/apache/hadoop/hbase/security/access/SecureTestUtil$AccessTestAction;[Lorg/apache/hadoop/hbase/security/User;)V
      78: aload_2
      79: iconst_2
      80: anewarray     #73                 // class org/apache/hadoop/hbase/security/User
      83: dup
      84: iconst_0
      85: getstatic     #44                 // Field USER_OTHER:Lorg/apache/hadoop/hbase/security/User;
      88: aastore
      89: dup
      90: iconst_1
      91: getstatic     #48                 // Field GROUP_USER:Lorg/apache/hadoop/hbase/security/User;
      94: aastore
      95: invokestatic  #74                 // Method verifyAllowed:(Lorg/apache/hadoop/hbase/security/access/SecureTestUtil$AccessTestAction;[Lorg/apache/hadoop/hbase/security/User;)V
      98: aload_3
      99: iconst_2
     100: anewarray     #73                 // class org/apache/hadoop/hbase/security/User
     103: dup
     104: iconst_0
     105: getstatic     #44                 // Field USER_OTHER:Lorg/apache/hadoop/hbase/security/User;
     108: aastore
     109: dup
     110: iconst_1
     111: getstatic     #48                 // Field GROUP_USER:Lorg/apache/hadoop/hbase/security/User;
     114: aastore
     115: invokestatic  #83                 // Method verifyIfNull:(Lorg/apache/hadoop/hbase/security/access/SecureTestUtil$AccessTestAction;[Lorg/apache/hadoop/hbase/security/User;)V
     118: aload         4
     120: iconst_2
     121: anewarray     #73                 // class org/apache/hadoop/hbase/security/User
     124: dup
     125: iconst_0
     126: getstatic     #44                 // Field USER_OTHER:Lorg/apache/hadoop/hbase/security/User;
     129: aastore
     130: dup
     131: iconst_1
     132: getstatic     #48                 // Field GROUP_USER:Lorg/apache/hadoop/hbase/security/User;
     135: aastore
     136: invokestatic  #83                 // Method verifyIfNull:(Lorg/apache/hadoop/hbase/security/access/SecureTestUtil$AccessTestAction;[Lorg/apache/hadoop/hbase/security/User;)V
     139: invokestatic  #84                 // Method org/apache/hbase/thirdparty/com/google/common/collect/Lists.newArrayList:()Ljava/util/ArrayList;
     142: astore        5
     144: new           #85                 // class org/apache/hadoop/hbase/security/access/TestCellACLs$6
     147: dup
     148: aload_0
     149: aload         5
     151: invokespecial #86                 // Method org/apache/hadoop/hbase/security/access/TestCellACLs$6."<init>":(Lorg/apache/hadoop/hbase/security/access/TestCellACLs;Ljava/util/List;)V
     154: astore        6
     156: aload         5
     158: invokeinterface #87,  1           // InterfaceMethod java/util/List.clear:()V
     163: aload         6
     165: iconst_1
     166: anewarray     #73                 // class org/apache/hadoop/hbase/security/User
     169: dup
     170: iconst_0
     171: getstatic     #42                 // Field USER_OWNER:Lorg/apache/hadoop/hbase/security/User;
     174: aastore
     175: invokestatic  #74                 // Method verifyAllowed:(Lorg/apache/hadoop/hbase/security/access/SecureTestUtil$AccessTestAction;[Lorg/apache/hadoop/hbase/security/User;)V
     178: ldc2_w        #88                 // long 4l
     181: aload         5
     183: invokeinterface #90,  1           // InterfaceMethod java/util/List.size:()I
     188: i2l
     189: invokestatic  #91                 // Method org/junit/Assert.assertEquals:(JJ)V
     192: aload         5
     194: invokeinterface #87,  1           // InterfaceMethod java/util/List.clear:()V
     199: aload         6
     201: iconst_1
     202: anewarray     #73                 // class org/apache/hadoop/hbase/security/User
     205: dup
     206: iconst_0
     207: getstatic     #44                 // Field USER_OTHER:Lorg/apache/hadoop/hbase/security/User;
     210: aastore
     211: invokestatic  #74                 // Method verifyAllowed:(Lorg/apache/hadoop/hbase/security/access/SecureTestUtil$AccessTestAction;[Lorg/apache/hadoop/hbase/security/User;)V
     214: ldc2_w        #92                 // long 2l
     217: aload         5
     219: invokeinterface #90,  1           // InterfaceMethod java/util/List.size:()I
     224: i2l
     225: invokestatic  #91                 // Method org/junit/Assert.assertEquals:(JJ)V
     228: aload         5
     230: invokeinterface #87,  1           // InterfaceMethod java/util/List.clear:()V
     235: aload         6
     237: iconst_1
     238: anewarray     #73                 // class org/apache/hadoop/hbase/security/User
     241: dup
     242: iconst_0
     243: getstatic     #48                 // Field GROUP_USER:Lorg/apache/hadoop/hbase/security/User;
     246: aastore
     247: invokestatic  #74                 // Method verifyAllowed:(Lorg/apache/hadoop/hbase/security/access/SecureTestUtil$AccessTestAction;[Lorg/apache/hadoop/hbase/security/User;)V
     250: ldc2_w        #92                 // long 2l
     253: aload         5
     255: invokeinterface #90,  1           // InterfaceMethod java/util/List.size:()I
     260: i2l
     261: invokestatic  #91                 // Method org/junit/Assert.assertEquals:(JJ)V
     264: new           #94                 // class org/apache/hadoop/hbase/security/access/TestCellACLs$7
     267: dup
     268: aload_0
     269: invokespecial #95                 // Method org/apache/hadoop/hbase/security/access/TestCellACLs$7."<init>":(Lorg/apache/hadoop/hbase/security/access/TestCellACLs;)V
     272: astore        7
     274: new           #96                 // class org/apache/hadoop/hbase/security/access/TestCellACLs$8
     277: dup
     278: aload_0
     279: invokespecial #97                 // Method org/apache/hadoop/hbase/security/access/TestCellACLs$8."<init>":(Lorg/apache/hadoop/hbase/security/access/TestCellACLs;)V
     282: astore        8
     284: new           #98                 // class org/apache/hadoop/hbase/security/access/TestCellACLs$9
     287: dup
     288: aload_0
     289: invokespecial #99                 // Method org/apache/hadoop/hbase/security/access/TestCellACLs$9."<init>":(Lorg/apache/hadoop/hbase/security/access/TestCellACLs;)V
     292: astore        9
     294: new           #100                // class org/apache/hadoop/hbase/security/access/TestCellACLs$10
     297: dup
     298: aload_0
     299: invokespecial #101                // Method org/apache/hadoop/hbase/security/access/TestCellACLs$10."<init>":(Lorg/apache/hadoop/hbase/security/access/TestCellACLs;)V
     302: astore        10
     304: aload         7
     306: iconst_2
     307: anewarray     #73                 // class org/apache/hadoop/hbase/security/User
     310: dup
     311: iconst_0
     312: getstatic     #44                 // Field USER_OTHER:Lorg/apache/hadoop/hbase/security/User;
     315: aastore
     316: dup
     317: iconst_1
     318: getstatic     #48                 // Field GROUP_USER:Lorg/apache/hadoop/hbase/security/User;
     321: aastore
     322: invokestatic  #102                // Method verifyDenied:(Lorg/apache/hadoop/hbase/security/access/SecureTestUtil$AccessTestAction;[Lorg/apache/hadoop/hbase/security/User;)V
     325: aload         10
     327: iconst_2
     328: anewarray     #73                 // class org/apache/hadoop/hbase/security/User
     331: dup
     332: iconst_0
     333: getstatic     #44                 // Field USER_OTHER:Lorg/apache/hadoop/hbase/security/User;
     336: aastore
     337: dup
     338: iconst_1
     339: getstatic     #48                 // Field GROUP_USER:Lorg/apache/hadoop/hbase/security/User;
     342: aastore
     343: invokestatic  #102                // Method verifyDenied:(Lorg/apache/hadoop/hbase/security/access/SecureTestUtil$AccessTestAction;[Lorg/apache/hadoop/hbase/security/User;)V
     346: aload         8
     348: iconst_2
     349: anewarray     #73                 // class org/apache/hadoop/hbase/security/User
     352: dup
     353: iconst_0
     354: getstatic     #44                 // Field USER_OTHER:Lorg/apache/hadoop/hbase/security/User;
     357: aastore
     358: dup
     359: iconst_1
     360: getstatic     #48                 // Field GROUP_USER:Lorg/apache/hadoop/hbase/security/User;
     363: aastore
     364: invokestatic  #74                 // Method verifyAllowed:(Lorg/apache/hadoop/hbase/security/access/SecureTestUtil$AccessTestAction;[Lorg/apache/hadoop/hbase/security/User;)V
     367: aload         9
     369: iconst_1
     370: anewarray     #73                 // class org/apache/hadoop/hbase/security/User
     373: dup
     374: iconst_0
     375: getstatic     #44                 // Field USER_OTHER:Lorg/apache/hadoop/hbase/security/User;
     378: aastore
     379: invokestatic  #74                 // Method verifyAllowed:(Lorg/apache/hadoop/hbase/security/access/SecureTestUtil$AccessTestAction;[Lorg/apache/hadoop/hbase/security/User;)V
     382: aload         8
     384: iconst_2
     385: anewarray     #73                 // class org/apache/hadoop/hbase/security/User
     388: dup
     389: iconst_0
     390: getstatic     #44                 // Field USER_OTHER:Lorg/apache/hadoop/hbase/security/User;
     393: aastore
     394: dup
     395: iconst_1
     396: getstatic     #48                 // Field GROUP_USER:Lorg/apache/hadoop/hbase/security/User;
     399: aastore
     400: invokestatic  #102                // Method verifyDenied:(Lorg/apache/hadoop/hbase/security/access/SecureTestUtil$AccessTestAction;[Lorg/apache/hadoop/hbase/security/User;)V
     403: new           #103                // class org/apache/hadoop/hbase/security/access/TestCellACLs$11
     406: dup
     407: aload_0
     408: invokespecial #104                // Method org/apache/hadoop/hbase/security/access/TestCellACLs$11."<init>":(Lorg/apache/hadoop/hbase/security/access/TestCellACLs;)V
     411: astore        11
     413: new           #105                // class org/apache/hadoop/hbase/security/access/TestCellACLs$12
     416: dup
     417: aload_0
     418: invokespecial #106                // Method org/apache/hadoop/hbase/security/access/TestCellACLs$12."<init>":(Lorg/apache/hadoop/hbase/security/access/TestCellACLs;)V
     421: astore        12
     423: aload         11
     425: iconst_2
     426: anewarray     #73                 // class org/apache/hadoop/hbase/security/User
     429: dup
     430: iconst_0
     431: getstatic     #44                 // Field USER_OTHER:Lorg/apache/hadoop/hbase/security/User;
     434: aastore
     435: dup
     436: iconst_1
     437: getstatic     #48                 // Field GROUP_USER:Lorg/apache/hadoop/hbase/security/User;
     440: aastore
     441: invokestatic  #102                // Method verifyDenied:(Lorg/apache/hadoop/hbase/security/access/SecureTestUtil$AccessTestAction;[Lorg/apache/hadoop/hbase/security/User;)V
     444: aload         12
     446: iconst_2
     447: anewarray     #73                 // class org/apache/hadoop/hbase/security/User
     450: dup
     451: iconst_0
     452: getstatic     #44                 // Field USER_OTHER:Lorg/apache/hadoop/hbase/security/User;
     455: aastore
     456: dup
     457: iconst_1
     458: getstatic     #48                 // Field GROUP_USER:Lorg/apache/hadoop/hbase/security/User;
     461: aastore
     462: invokestatic  #102                // Method verifyDenied:(Lorg/apache/hadoop/hbase/security/access/SecureTestUtil$AccessTestAction;[Lorg/apache/hadoop/hbase/security/User;)V
     465: aload         12
     467: iconst_1
     468: anewarray     #73                 // class org/apache/hadoop/hbase/security/User
     471: dup
     472: iconst_0
     473: getstatic     #42                 // Field USER_OWNER:Lorg/apache/hadoop/hbase/security/User;
     476: aastore
     477: invokestatic  #74                 // Method verifyAllowed:(Lorg/apache/hadoop/hbase/security/access/SecureTestUtil$AccessTestAction;[Lorg/apache/hadoop/hbase/security/User;)V
     480: return

  public void testCoveringCheck() throws java.lang.Exception;
    Code:
       0: getstatic     #15                 // Field TEST_UTIL:Lorg/apache/hadoop/hbase/HBaseTestingUtility;
       3: getstatic     #44                 // Field USER_OTHER:Lorg/apache/hadoop/hbase/security/User;
       6: invokevirtual #49                 // Method org/apache/hadoop/hbase/security/User.getShortName:()Ljava/lang/String;
       9: aload_0
      10: getfield      #14                 // Field TEST_TABLE:Lorg/apache/hadoop/hbase/TestTableName;
      13: invokevirtual #54                 // Method org/apache/hadoop/hbase/TestTableName.getTableName:()Lorg/apache/hadoop/hbase/TableName;
      16: getstatic     #9                  // Field TEST_FAMILY:[B
      19: aconst_null
      20: iconst_1
      21: anewarray     #107                // class org/apache/hadoop/hbase/security/access/Permission$Action
      24: dup
      25: iconst_0
      26: getstatic     #108                // Field org/apache/hadoop/hbase/security/access/Permission$Action.READ:Lorg/apache/hadoop/hbase/security/access/Permission$Action;
      29: aastore
      30: invokestatic  #109                // Method grantOnTable:(Lorg/apache/hadoop/hbase/HBaseTestingUtility;Ljava/lang/String;Lorg/apache/hadoop/hbase/TableName;[B[B[Lorg/apache/hadoop/hbase/security/access/Permission$Action;)V
      33: getstatic     #15                 // Field TEST_UTIL:Lorg/apache/hadoop/hbase/HBaseTestingUtility;
      36: ldc           #47                 // String group
      38: invokestatic  #50                 // Method org/apache/hadoop/hbase/AuthUtil.toGroupEntry:(Ljava/lang/String;)Ljava/lang/String;
      41: aload_0
      42: getfield      #14                 // Field TEST_TABLE:Lorg/apache/hadoop/hbase/TestTableName;
      45: invokevirtual #54                 // Method org/apache/hadoop/hbase/TestTableName.getTableName:()Lorg/apache/hadoop/hbase/TableName;
      48: getstatic     #9                  // Field TEST_FAMILY:[B
      51: aconst_null
      52: iconst_1
      53: anewarray     #107                // class org/apache/hadoop/hbase/security/access/Permission$Action
      56: dup
      57: iconst_0
      58: getstatic     #108                // Field org/apache/hadoop/hbase/security/access/Permission$Action.READ:Lorg/apache/hadoop/hbase/security/access/Permission$Action;
      61: aastore
      62: invokestatic  #109                // Method grantOnTable:(Lorg/apache/hadoop/hbase/HBaseTestingUtility;Ljava/lang/String;Lorg/apache/hadoop/hbase/TableName;[B[B[Lorg/apache/hadoop/hbase/security/access/Permission$Action;)V
      65: aload_0
      66: getstatic     #44                 // Field USER_OTHER:Lorg/apache/hadoop/hbase/security/User;
      69: getstatic     #7                  // Field ZERO:[B
      72: invokespecial #110                // Method verifyUserDeniedForWrite:(Lorg/apache/hadoop/hbase/security/User;[B)V
      75: aload_0
      76: getstatic     #48                 // Field GROUP_USER:Lorg/apache/hadoop/hbase/security/User;
      79: getstatic     #7                  // Field ZERO:[B
      82: invokespecial #110                // Method verifyUserDeniedForWrite:(Lorg/apache/hadoop/hbase/security/User;[B)V
      85: new           #111                // class org/apache/hadoop/hbase/security/access/TestCellACLs$13
      88: dup
      89: aload_0
      90: invokespecial #112                // Method org/apache/hadoop/hbase/security/access/TestCellACLs$13."<init>":(Lorg/apache/hadoop/hbase/security/access/TestCellACLs;)V
      93: iconst_1
      94: anewarray     #73                 // class org/apache/hadoop/hbase/security/User
      97: dup
      98: iconst_0
      99: getstatic     #42                 // Field USER_OWNER:Lorg/apache/hadoop/hbase/security/User;
     102: aastore
     103: invokestatic  #74                 // Method verifyAllowed:(Lorg/apache/hadoop/hbase/security/access/SecureTestUtil$AccessTestAction;[Lorg/apache/hadoop/hbase/security/User;)V
     106: aload_0
     107: getstatic     #44                 // Field USER_OTHER:Lorg/apache/hadoop/hbase/security/User;
     110: getstatic     #113                // Field ONE:[B
     113: invokespecial #110                // Method verifyUserDeniedForWrite:(Lorg/apache/hadoop/hbase/security/User;[B)V
     116: aload_0
     117: getstatic     #48                 // Field GROUP_USER:Lorg/apache/hadoop/hbase/security/User;
     120: getstatic     #113                // Field ONE:[B
     123: invokespecial #110                // Method verifyUserDeniedForWrite:(Lorg/apache/hadoop/hbase/security/User;[B)V
     126: aload_0
     127: getstatic     #44                 // Field USER_OTHER:Lorg/apache/hadoop/hbase/security/User;
     130: invokespecial #114                // Method verifyUserAllowedForRead:(Lorg/apache/hadoop/hbase/security/User;)V
     133: aload_0
     134: getstatic     #48                 // Field GROUP_USER:Lorg/apache/hadoop/hbase/security/User;
     137: invokespecial #114                // Method verifyUserAllowedForRead:(Lorg/apache/hadoop/hbase/security/User;)V
     140: return

  public void tearDown() throws java.lang.Exception;
    Code:
       0: getstatic     #15                 // Field TEST_UTIL:Lorg/apache/hadoop/hbase/HBaseTestingUtility;
       3: aload_0
       4: getfield      #14                 // Field TEST_TABLE:Lorg/apache/hadoop/hbase/TestTableName;
       7: invokevirtual #54                 // Method org/apache/hadoop/hbase/TestTableName.getTableName:()Lorg/apache/hadoop/hbase/TableName;
      10: invokevirtual #124                // Method org/apache/hadoop/hbase/HBaseTestingUtility.deleteTable:(Lorg/apache/hadoop/hbase/TableName;)V
      13: goto          50
      16: astore_1
      17: getstatic     #65                 // Field LOG:Lorg/slf4j/Logger;
      20: new           #126                // class java/lang/StringBuilder
      23: dup
      24: invokespecial #127                // Method java/lang/StringBuilder."<init>":()V
      27: ldc           #128                // String Test deleted table
      29: invokevirtual #129                // Method java/lang/StringBuilder.append:(Ljava/lang/String;)Ljava/lang/StringBuilder;
      32: aload_0
      33: getfield      #14                 // Field TEST_TABLE:Lorg/apache/hadoop/hbase/TestTableName;
      36: invokevirtual #54                 // Method org/apache/hadoop/hbase/TestTableName.getTableName:()Lorg/apache/hadoop/hbase/TableName;
      39: invokevirtual #130                // Method java/lang/StringBuilder.append:(Ljava/lang/Object;)Ljava/lang/StringBuilder;
      42: invokevirtual #131                // Method java/lang/StringBuilder.toString:()Ljava/lang/String;
      45: invokeinterface #67,  2           // InterfaceMethod org/slf4j/Logger.info:(Ljava/lang/String;)V
      50: lconst_0
      51: getstatic     #10                 // Field conf:Lorg/apache/hadoop/conf/Configuration;
      54: aload_0
      55: getfield      #14                 // Field TEST_TABLE:Lorg/apache/hadoop/hbase/TestTableName;
      58: invokevirtual #54                 // Method org/apache/hadoop/hbase/TestTableName.getTableName:()Lorg/apache/hadoop/hbase/TableName;
      61: invokestatic  #132                // Method org/apache/hadoop/hbase/security/access/PermissionStorage.getTablePermissions:(Lorg/apache/hadoop/conf/Configuration;Lorg/apache/hadoop/hbase/TableName;)Lorg/apache/hbase/thirdparty/com/google/common/collect/ListMultimap;
      64: invokeinterface #133,  1          // InterfaceMethod org/apache/hbase/thirdparty/com/google/common/collect/ListMultimap.size:()I
      69: i2l
      70: invokestatic  #91                 // Method org/junit/Assert.assertEquals:(JJ)V
      73: return
    Exception table:
       from    to  target type
           0    13    16   Class org/apache/hadoop/hbase/TableNotFoundException

  static org.apache.hadoop.conf.Configuration access$000();
    Code:
       0: getstatic     #10                 // Field conf:Lorg/apache/hadoop/conf/Configuration;
       3: areturn

  static byte[] access$100();
    Code:
       0: getstatic     #9                  // Field TEST_FAMILY:[B
       3: areturn

  static byte[] access$200();
    Code:
       0: getstatic     #8                  // Field TEST_Q1:[B
       3: areturn

  static byte[] access$300();
    Code:
       0: getstatic     #7                  // Field ZERO:[B
       3: areturn

  static byte[] access$400();
    Code:
       0: getstatic     #6                  // Field TEST_ROW:[B
       3: areturn

  static java.lang.String[] access$500();
    Code:
       0: getstatic     #5                  // Field usersAndGroups:[Ljava/lang/String;
       3: areturn

  static java.util.Map access$600(org.apache.hadoop.hbase.security.access.TestCellACLs, java.lang.String[], org.apache.hadoop.hbase.security.access.Permission$Action[]);
    Code:
       0: aload_0
       1: aload_1
       2: aload_2
       3: invokespecial #4                  // Method prepareCellPermissions:([Ljava/lang/String;[Lorg/apache/hadoop/hbase/security/access/Permission$Action;)Ljava/util/Map;
       6: areturn

  static byte[] access$700();
    Code:
       0: getstatic     #3                  // Field TEST_Q2:[B
       3: areturn

  static byte[] access$800();
    Code:
       0: getstatic     #2                  // Field TEST_Q4:[B
       3: areturn

  static byte[] access$900();
    Code:
       0: getstatic     #1                  // Field TEST_Q3:[B
       3: areturn

  static {};
    Code:
       0: ldc           #46                 // class org/apache/hadoop/hbase/security/access/TestCellACLs
       2: invokestatic  #134                // Method org/apache/hadoop/hbase/HBaseClassTestRule.forClass:(Ljava/lang/Class;)Lorg/apache/hadoop/hbase/HBaseClassTestRule;
       5: putstatic     #135                // Field CLASS_RULE:Lorg/apache/hadoop/hbase/HBaseClassTestRule;
       8: ldc           #46                 // class org/apache/hadoop/hbase/security/access/TestCellACLs
      10: invokestatic  #136                // Method org/slf4j/LoggerFactory.getLogger:(Ljava/lang/Class;)Lorg/slf4j/Logger;
      13: putstatic     #65                 // Field LOG:Lorg/slf4j/Logger;
      16: new           #137                // class org/apache/hadoop/hbase/HBaseTestingUtility
      19: dup
      20: invokespecial #138                // Method org/apache/hadoop/hbase/HBaseTestingUtility."<init>":()V
      23: putstatic     #15                 // Field TEST_UTIL:Lorg/apache/hadoop/hbase/HBaseTestingUtility;
      26: ldc           #139                // String f1
      28: invokestatic  #63                 // Method org/apache/hadoop/hbase/util/Bytes.toBytes:(Ljava/lang/String;)[B
      31: putstatic     #9                  // Field TEST_FAMILY:[B
      34: ldc           #140                // String cellpermtest
      36: invokestatic  #63                 // Method org/apache/hadoop/hbase/util/Bytes.toBytes:(Ljava/lang/String;)[B
      39: putstatic     #6                  // Field TEST_ROW:[B
      42: ldc           #141                // String q1
      44: invokestatic  #63                 // Method org/apache/hadoop/hbase/util/Bytes.toBytes:(Ljava/lang/String;)[B
      47: putstatic     #8                  // Field TEST_Q1:[B
      50: ldc           #142                // String q2
      52: invokestatic  #63                 // Method org/apache/hadoop/hbase/util/Bytes.toBytes:(Ljava/lang/String;)[B
      55: putstatic     #3                  // Field TEST_Q2:[B
      58: ldc           #143                // String q3
      60: invokestatic  #63                 // Method org/apache/hadoop/hbase/util/Bytes.toBytes:(Ljava/lang/String;)[B
      63: putstatic     #1                  // Field TEST_Q3:[B
      66: ldc           #144                // String q4
      68: invokestatic  #63                 // Method org/apache/hadoop/hbase/util/Bytes.toBytes:(Ljava/lang/String;)[B
      71: putstatic     #2                  // Field TEST_Q4:[B
      74: lconst_0
      75: invokestatic  #145                // Method org/apache/hadoop/hbase/util/Bytes.toBytes:(J)[B
      78: putstatic     #7                  // Field ZERO:[B
      81: lconst_1
      82: invokestatic  #145                // Method org/apache/hadoop/hbase/util/Bytes.toBytes:(J)[B
      85: putstatic     #113                // Field ONE:[B
      88: return
}
