Compiled from "TestTagRewriteCell.java"
public class org.apache.hadoop.hbase.TestTagRewriteCell {
  public static final org.apache.hadoop.hbase.HBaseClassTestRule CLASS_RULE;

  public org.apache.hadoop.hbase.TestTagRewriteCell();
    Code:
       0: aload_0
       1: invokespecial #1                  // Method java/lang/Object."<init>":()V
       4: return

  public void testHeapSize();
    Code:
       0: ldc           #2                  // String row
       2: invokestatic  #3                  // Method org/apache/hadoop/hbase/util/Bytes.toBytes:(Ljava/lang/String;)[B
       5: ldc           #4                  // String value
       7: invokestatic  #3                  // Method org/apache/hadoop/hbase/util/Bytes.toBytes:(Ljava/lang/String;)[B
      10: invokestatic  #5                  // Method org/apache/hadoop/hbase/CellUtil.createCell:([B[B)Lorg/apache/hadoop/hbase/Cell;
      13: astore_1
      14: bipush        10
      16: istore_2
      17: aload_1
      18: bipush        10
      20: newarray       byte
      22: invokestatic  #6                  // Method org/apache/hadoop/hbase/PrivateCellUtil.createCell:(Lorg/apache/hadoop/hbase/Cell;[B)Lorg/apache/hadoop/hbase/Cell;
      25: astore_3
      26: aload_3
      27: invokeinterface #7,  1            // InterfaceMethod org/apache/hadoop/hbase/io/HeapSize.heapSize:()J
      32: lstore        4
      34: aload_3
      35: bipush        10
      37: newarray       byte
      39: invokestatic  #6                  // Method org/apache/hadoop/hbase/PrivateCellUtil.createCell:(Lorg/apache/hadoop/hbase/Cell;[B)Lorg/apache/hadoop/hbase/Cell;
      42: astore        6
      44: ldc           #8                  // String TagRewriteCell containing a TagRewriteCell's heapsize should be larger than a single TagRewriteCell's heapsize
      46: lload         4
      48: aload         6
      50: invokeinterface #7,  1            // InterfaceMethod org/apache/hadoop/hbase/io/HeapSize.heapSize:()J
      55: lcmp
      56: ifge          63
      59: iconst_1
      60: goto          64
      63: iconst_0
      64: invokestatic  #9                  // Method org/junit/Assert.assertTrue:(Ljava/lang/String;Z)V
      67: ldc           #10                 // String TagRewriteCell should have had nulled out tags array
      69: aload_3
      70: invokeinterface #7,  1            // InterfaceMethod org/apache/hadoop/hbase/io/HeapSize.heapSize:()J
      75: lload         4
      77: lcmp
      78: ifge          85
      81: iconst_1
      82: goto          86
      85: iconst_0
      86: invokestatic  #9                  // Method org/junit/Assert.assertTrue:(Ljava/lang/String;Z)V
      89: return

  static {};
    Code:
       0: ldc           #11                 // class org/apache/hadoop/hbase/TestTagRewriteCell
       2: invokestatic  #12                 // Method org/apache/hadoop/hbase/HBaseClassTestRule.forClass:(Ljava/lang/Class;)Lorg/apache/hadoop/hbase/HBaseClassTestRule;
       5: putstatic     #13                 // Field CLASS_RULE:Lorg/apache/hadoop/hbase/HBaseClassTestRule;
       8: return
}
