Compiled from "TestColumnFamilyDescriptorBuilder.java"
public class org.apache.hadoop.hbase.client.TestColumnFamilyDescriptorBuilder {
  public static final org.apache.hadoop.hbase.HBaseClassTestRule CLASS_RULE;

  public org.junit.rules.ExpectedException expectedEx;

  public org.apache.hadoop.hbase.client.TestColumnFamilyDescriptorBuilder();
    Code:
       0: aload_0
       1: invokespecial #1                  // Method java/lang/Object."<init>":()V
       4: aload_0
       5: invokestatic  #2                  // Method org/junit/rules/ExpectedException.none:()Lorg/junit/rules/ExpectedException;
       8: putfield      #3                  // Field expectedEx:Lorg/junit/rules/ExpectedException;
      11: return

  public void testBuilder() throws org.apache.hadoop.hbase.exceptions.DeserializationException;
    Code:
       0: getstatic     #4                  // Field org/apache/hadoop/hbase/HConstants.CATALOG_FAMILY:[B
       3: invokestatic  #5                  // Method org/apache/hadoop/hbase/client/ColumnFamilyDescriptorBuilder.newBuilder:([B)Lorg/apache/hadoop/hbase/client/ColumnFamilyDescriptorBuilder;
       6: iconst_1
       7: invokevirtual #6                  // Method org/apache/hadoop/hbase/client/ColumnFamilyDescriptorBuilder.setInMemory:(Z)Lorg/apache/hadoop/hbase/client/ColumnFamilyDescriptorBuilder;
      10: iconst_0
      11: invokevirtual #8                  // Method org/apache/hadoop/hbase/client/ColumnFamilyDescriptorBuilder.setScope:(I)Lorg/apache/hadoop/hbase/client/ColumnFamilyDescriptorBuilder;
      14: getstatic     #9                  // Field org/apache/hadoop/hbase/regionserver/BloomType.NONE:Lorg/apache/hadoop/hbase/regionserver/BloomType;
      17: invokevirtual #10                 // Method org/apache/hadoop/hbase/client/ColumnFamilyDescriptorBuilder.setBloomFilterType:(Lorg/apache/hadoop/hbase/regionserver/BloomType;)Lorg/apache/hadoop/hbase/client/ColumnFamilyDescriptorBuilder;
      20: astore_1
      21: bipush        123
      23: istore_2
      24: aload_1
      25: bipush        123
      27: invokevirtual #11                 // Method org/apache/hadoop/hbase/client/ColumnFamilyDescriptorBuilder.setBlocksize:(I)Lorg/apache/hadoop/hbase/client/ColumnFamilyDescriptorBuilder;
      30: pop
      31: aload_1
      32: bipush        123
      34: invokevirtual #12                 // Method org/apache/hadoop/hbase/client/ColumnFamilyDescriptorBuilder.setTimeToLive:(I)Lorg/apache/hadoop/hbase/client/ColumnFamilyDescriptorBuilder;
      37: pop
      38: aload_1
      39: iconst_0
      40: invokevirtual #14                 // Method org/apache/hadoop/hbase/client/ColumnFamilyDescriptorBuilder.setBlockCacheEnabled:(Z)Lorg/apache/hadoop/hbase/client/ColumnFamilyDescriptorBuilder;
      43: pop
      44: aload_1
      45: ldc           #15                 // String a
      47: invokestatic  #16                 // Method org/apache/hadoop/hbase/util/Bytes.toBytes:(Ljava/lang/String;)[B
      50: ldc           #17                 // String b
      52: invokestatic  #16                 // Method org/apache/hadoop/hbase/util/Bytes.toBytes:(Ljava/lang/String;)[B
      55: invokevirtual #18                 // Method org/apache/hadoop/hbase/client/ColumnFamilyDescriptorBuilder.setValue:([B[B)Lorg/apache/hadoop/hbase/client/ColumnFamilyDescriptorBuilder;
      58: pop
      59: aload_1
      60: bipush        123
      62: invokevirtual #19                 // Method org/apache/hadoop/hbase/client/ColumnFamilyDescriptorBuilder.setMaxVersions:(I)Lorg/apache/hadoop/hbase/client/ColumnFamilyDescriptorBuilder;
      65: pop
      66: ldc2_w        #20                 // long 123l
      69: aload_1
      70: invokevirtual #22                 // Method org/apache/hadoop/hbase/client/ColumnFamilyDescriptorBuilder.build:()Lorg/apache/hadoop/hbase/client/ColumnFamilyDescriptor;
      73: invokeinterface #23,  1           // InterfaceMethod org/apache/hadoop/hbase/client/ColumnFamilyDescriptor.getMaxVersions:()I
      78: i2l
      79: invokestatic  #24                 // Method org/junit/Assert.assertEquals:(JJ)V
      82: aload_1
      83: bipush        123
      85: invokevirtual #25                 // Method org/apache/hadoop/hbase/client/ColumnFamilyDescriptorBuilder.setMinVersions:(I)Lorg/apache/hadoop/hbase/client/ColumnFamilyDescriptorBuilder;
      88: pop
      89: ldc2_w        #20                 // long 123l
      92: aload_1
      93: invokevirtual #22                 // Method org/apache/hadoop/hbase/client/ColumnFamilyDescriptorBuilder.build:()Lorg/apache/hadoop/hbase/client/ColumnFamilyDescriptor;
      96: invokeinterface #26,  1           // InterfaceMethod org/apache/hadoop/hbase/client/ColumnFamilyDescriptor.getMinVersions:()I
     101: i2l
     102: invokestatic  #24                 // Method org/junit/Assert.assertEquals:(JJ)V
     105: aload_1
     106: getstatic     #27                 // Field org/apache/hadoop/hbase/KeepDeletedCells.TRUE:Lorg/apache/hadoop/hbase/KeepDeletedCells;
     109: invokevirtual #28                 // Method org/apache/hadoop/hbase/client/ColumnFamilyDescriptorBuilder.setKeepDeletedCells:(Lorg/apache/hadoop/hbase/KeepDeletedCells;)Lorg/apache/hadoop/hbase/client/ColumnFamilyDescriptorBuilder;
     112: pop
     113: aload_1
     114: iconst_1
     115: invokevirtual #6                  // Method org/apache/hadoop/hbase/client/ColumnFamilyDescriptorBuilder.setInMemory:(Z)Lorg/apache/hadoop/hbase/client/ColumnFamilyDescriptorBuilder;
     118: pop
     119: aload_1
     120: invokevirtual #22                 // Method org/apache/hadoop/hbase/client/ColumnFamilyDescriptorBuilder.build:()Lorg/apache/hadoop/hbase/client/ColumnFamilyDescriptor;
     123: invokeinterface #29,  1           // InterfaceMethod org/apache/hadoop/hbase/client/ColumnFamilyDescriptor.isInMemory:()Z
     128: istore_3
     129: aload_1
     130: bipush        123
     132: invokevirtual #8                  // Method org/apache/hadoop/hbase/client/ColumnFamilyDescriptorBuilder.setScope:(I)Lorg/apache/hadoop/hbase/client/ColumnFamilyDescriptorBuilder;
     135: pop
     136: aload_1
     137: getstatic     #30                 // Field org/apache/hadoop/hbase/io/encoding/DataBlockEncoding.FAST_DIFF:Lorg/apache/hadoop/hbase/io/encoding/DataBlockEncoding;
     140: invokevirtual #31                 // Method org/apache/hadoop/hbase/client/ColumnFamilyDescriptorBuilder.setDataBlockEncoding:(Lorg/apache/hadoop/hbase/io/encoding/DataBlockEncoding;)Lorg/apache/hadoop/hbase/client/ColumnFamilyDescriptorBuilder;
     143: pop
     144: aload_1
     145: getstatic     #32                 // Field org/apache/hadoop/hbase/regionserver/BloomType.ROW:Lorg/apache/hadoop/hbase/regionserver/BloomType;
     148: invokevirtual #10                 // Method org/apache/hadoop/hbase/client/ColumnFamilyDescriptorBuilder.setBloomFilterType:(Lorg/apache/hadoop/hbase/regionserver/BloomType;)Lorg/apache/hadoop/hbase/client/ColumnFamilyDescriptorBuilder;
     151: pop
     152: aload_1
     153: getstatic     #33                 // Field org/apache/hadoop/hbase/io/compress/Compression$Algorithm.SNAPPY:Lorg/apache/hadoop/hbase/io/compress/Compression$Algorithm;
     156: invokevirtual #34                 // Method org/apache/hadoop/hbase/client/ColumnFamilyDescriptorBuilder.setCompressionType:(Lorg/apache/hadoop/hbase/io/compress/Compression$Algorithm;)Lorg/apache/hadoop/hbase/client/ColumnFamilyDescriptorBuilder;
     159: pop
     160: aload_1
     161: iconst_1
     162: invokevirtual #35                 // Method org/apache/hadoop/hbase/client/ColumnFamilyDescriptorBuilder.setMobEnabled:(Z)Lorg/apache/hadoop/hbase/client/ColumnFamilyDescriptorBuilder;
     165: pop
     166: aload_1
     167: ldc2_w        #36                 // long 1000l
     170: invokevirtual #38                 // Method org/apache/hadoop/hbase/client/ColumnFamilyDescriptorBuilder.setMobThreshold:(J)Lorg/apache/hadoop/hbase/client/ColumnFamilyDescriptorBuilder;
     173: pop
     174: aload_1
     175: bipush        123
     177: invokevirtual #39                 // Method org/apache/hadoop/hbase/client/ColumnFamilyDescriptorBuilder.setDFSReplication:(S)Lorg/apache/hadoop/hbase/client/ColumnFamilyDescriptorBuilder;
     180: pop
     181: aload_1
     182: invokevirtual #22                 // Method org/apache/hadoop/hbase/client/ColumnFamilyDescriptorBuilder.build:()Lorg/apache/hadoop/hbase/client/ColumnFamilyDescriptor;
     185: astore        4
     187: aload         4
     189: invokestatic  #40                 // Method org/apache/hadoop/hbase/client/ColumnFamilyDescriptorBuilder.toByteArray:(Lorg/apache/hadoop/hbase/client/ColumnFamilyDescriptor;)[B
     192: astore        5
     194: aload         5
     196: invokestatic  #41                 // Method org/apache/hadoop/hbase/client/ColumnFamilyDescriptorBuilder.parseFrom:([B)Lorg/apache/hadoop/hbase/client/ColumnFamilyDescriptor;
     199: astore        6
     201: aload         4
     203: aload         6
     205: invokevirtual #42                 // Method java/lang/Object.equals:(Ljava/lang/Object;)Z
     208: invokestatic  #43                 // Method org/junit/Assert.assertTrue:(Z)V
     211: ldc2_w        #20                 // long 123l
     214: aload         4
     216: invokeinterface #44,  1           // InterfaceMethod org/apache/hadoop/hbase/client/ColumnFamilyDescriptor.getBlocksize:()I
     221: i2l
     222: invokestatic  #24                 // Method org/junit/Assert.assertEquals:(JJ)V
     225: ldc2_w        #20                 // long 123l
     228: aload         4
     230: invokeinterface #45,  1           // InterfaceMethod org/apache/hadoop/hbase/client/ColumnFamilyDescriptor.getTimeToLive:()I
     235: i2l
     236: invokestatic  #24                 // Method org/junit/Assert.assertEquals:(JJ)V
     239: aload         4
     241: ldc           #15                 // String a
     243: invokestatic  #16                 // Method org/apache/hadoop/hbase/util/Bytes.toBytes:(Ljava/lang/String;)[B
     246: invokeinterface #46,  2           // InterfaceMethod org/apache/hadoop/hbase/client/ColumnFamilyDescriptor.getValue:([B)[B
     251: aload         6
     253: ldc           #15                 // String a
     255: invokestatic  #16                 // Method org/apache/hadoop/hbase/util/Bytes.toBytes:(Ljava/lang/String;)[B
     258: invokeinterface #46,  2           // InterfaceMethod org/apache/hadoop/hbase/client/ColumnFamilyDescriptor.getValue:([B)[B
     263: invokestatic  #47                 // Method org/apache/hadoop/hbase/util/Bytes.equals:([B[B)Z
     266: invokestatic  #43                 // Method org/junit/Assert.assertTrue:(Z)V
     269: aload         4
     271: invokeinterface #23,  1           // InterfaceMethod org/apache/hadoop/hbase/client/ColumnFamilyDescriptor.getMaxVersions:()I
     276: i2l
     277: aload         6
     279: invokeinterface #23,  1           // InterfaceMethod org/apache/hadoop/hbase/client/ColumnFamilyDescriptor.getMaxVersions:()I
     284: i2l
     285: invokestatic  #24                 // Method org/junit/Assert.assertEquals:(JJ)V
     288: aload         4
     290: invokeinterface #26,  1           // InterfaceMethod org/apache/hadoop/hbase/client/ColumnFamilyDescriptor.getMinVersions:()I
     295: i2l
     296: aload         6
     298: invokeinterface #26,  1           // InterfaceMethod org/apache/hadoop/hbase/client/ColumnFamilyDescriptor.getMinVersions:()I
     303: i2l
     304: invokestatic  #24                 // Method org/junit/Assert.assertEquals:(JJ)V
     307: aload         4
     309: invokeinterface #48,  1           // InterfaceMethod org/apache/hadoop/hbase/client/ColumnFamilyDescriptor.getKeepDeletedCells:()Lorg/apache/hadoop/hbase/KeepDeletedCells;
     314: aload         6
     316: invokeinterface #48,  1           // InterfaceMethod org/apache/hadoop/hbase/client/ColumnFamilyDescriptor.getKeepDeletedCells:()Lorg/apache/hadoop/hbase/KeepDeletedCells;
     321: invokestatic  #49                 // Method org/junit/Assert.assertEquals:(Ljava/lang/Object;Ljava/lang/Object;)V
     324: iload_3
     325: invokestatic  #50                 // Method java/lang/Boolean.valueOf:(Z)Ljava/lang/Boolean;
     328: aload         6
     330: invokeinterface #29,  1           // InterfaceMethod org/apache/hadoop/hbase/client/ColumnFamilyDescriptor.isInMemory:()Z
     335: invokestatic  #50                 // Method java/lang/Boolean.valueOf:(Z)Ljava/lang/Boolean;
     338: invokestatic  #49                 // Method org/junit/Assert.assertEquals:(Ljava/lang/Object;Ljava/lang/Object;)V
     341: aload         4
     343: invokeinterface #51,  1           // InterfaceMethod org/apache/hadoop/hbase/client/ColumnFamilyDescriptor.getScope:()I
     348: i2l
     349: aload         6
     351: invokeinterface #51,  1           // InterfaceMethod org/apache/hadoop/hbase/client/ColumnFamilyDescriptor.getScope:()I
     356: i2l
     357: invokestatic  #24                 // Method org/junit/Assert.assertEquals:(JJ)V
     360: aload         6
     362: invokeinterface #52,  1           // InterfaceMethod org/apache/hadoop/hbase/client/ColumnFamilyDescriptor.getCompressionType:()Lorg/apache/hadoop/hbase/io/compress/Compression$Algorithm;
     367: getstatic     #33                 // Field org/apache/hadoop/hbase/io/compress/Compression$Algorithm.SNAPPY:Lorg/apache/hadoop/hbase/io/compress/Compression$Algorithm;
     370: invokevirtual #53                 // Method org/apache/hadoop/hbase/io/compress/Compression$Algorithm.equals:(Ljava/lang/Object;)Z
     373: invokestatic  #43                 // Method org/junit/Assert.assertTrue:(Z)V
     376: aload         6
     378: invokeinterface #54,  1           // InterfaceMethod org/apache/hadoop/hbase/client/ColumnFamilyDescriptor.getDataBlockEncoding:()Lorg/apache/hadoop/hbase/io/encoding/DataBlockEncoding;
     383: getstatic     #30                 // Field org/apache/hadoop/hbase/io/encoding/DataBlockEncoding.FAST_DIFF:Lorg/apache/hadoop/hbase/io/encoding/DataBlockEncoding;
     386: invokevirtual #55                 // Method org/apache/hadoop/hbase/io/encoding/DataBlockEncoding.equals:(Ljava/lang/Object;)Z
     389: invokestatic  #43                 // Method org/junit/Assert.assertTrue:(Z)V
     392: aload         6
     394: invokeinterface #56,  1           // InterfaceMethod org/apache/hadoop/hbase/client/ColumnFamilyDescriptor.getBloomFilterType:()Lorg/apache/hadoop/hbase/regionserver/BloomType;
     399: getstatic     #32                 // Field org/apache/hadoop/hbase/regionserver/BloomType.ROW:Lorg/apache/hadoop/hbase/regionserver/BloomType;
     402: invokevirtual #57                 // Method org/apache/hadoop/hbase/regionserver/BloomType.equals:(Ljava/lang/Object;)Z
     405: invokestatic  #43                 // Method org/junit/Assert.assertTrue:(Z)V
     408: aload         4
     410: invokeinterface #58,  1           // InterfaceMethod org/apache/hadoop/hbase/client/ColumnFamilyDescriptor.isMobEnabled:()Z
     415: invokestatic  #50                 // Method java/lang/Boolean.valueOf:(Z)Ljava/lang/Boolean;
     418: aload         6
     420: invokeinterface #58,  1           // InterfaceMethod org/apache/hadoop/hbase/client/ColumnFamilyDescriptor.isMobEnabled:()Z
     425: invokestatic  #50                 // Method java/lang/Boolean.valueOf:(Z)Ljava/lang/Boolean;
     428: invokestatic  #49                 // Method org/junit/Assert.assertEquals:(Ljava/lang/Object;Ljava/lang/Object;)V
     431: aload         4
     433: invokeinterface #59,  1           // InterfaceMethod org/apache/hadoop/hbase/client/ColumnFamilyDescriptor.getMobThreshold:()J
     438: aload         6
     440: invokeinterface #59,  1           // InterfaceMethod org/apache/hadoop/hbase/client/ColumnFamilyDescriptor.getMobThreshold:()J
     445: invokestatic  #24                 // Method org/junit/Assert.assertEquals:(JJ)V
     448: ldc2_w        #20                 // long 123l
     451: aload         6
     453: invokeinterface #60,  1           // InterfaceMethod org/apache/hadoop/hbase/client/ColumnFamilyDescriptor.getDFSReplication:()S
     458: i2l
     459: invokestatic  #24                 // Method org/junit/Assert.assertEquals:(JJ)V
     462: return

  public void testHColumnDescriptorShouldThrowIAEWhenFamilyNameEmpty() throws java.lang.Exception;
    Code:
       0: aload_0
       1: getfield      #3                  // Field expectedEx:Lorg/junit/rules/ExpectedException;
       4: ldc           #61                 // class java/lang/IllegalArgumentException
       6: invokevirtual #62                 // Method org/junit/rules/ExpectedException.expect:(Ljava/lang/Class;)V
       9: aload_0
      10: getfield      #3                  // Field expectedEx:Lorg/junit/rules/ExpectedException;
      13: ldc           #63                 // String Column Family name can not be empty
      15: invokevirtual #64                 // Method org/junit/rules/ExpectedException.expectMessage:(Ljava/lang/String;)V
      18: ldc           #65                 // String
      20: invokestatic  #66                 // Method org/apache/hadoop/hbase/client/ColumnFamilyDescriptorBuilder.of:(Ljava/lang/String;)Lorg/apache/hadoop/hbase/client/ColumnFamilyDescriptor;
      23: pop
      24: return

  public void testAddGetRemoveConfiguration();
    Code:
       0: ldc           #67                 // String foo
       2: invokestatic  #16                 // Method org/apache/hadoop/hbase/util/Bytes.toBytes:(Ljava/lang/String;)[B
       5: invokestatic  #5                  // Method org/apache/hadoop/hbase/client/ColumnFamilyDescriptorBuilder.newBuilder:([B)Lorg/apache/hadoop/hbase/client/ColumnFamilyDescriptorBuilder;
       8: astore_1
       9: ldc           #68                 // String Some
      11: astore_2
      12: ldc           #69                 // String value
      14: astore_3
      15: aload_1
      16: aload_2
      17: aload_3
      18: invokevirtual #70                 // Method org/apache/hadoop/hbase/client/ColumnFamilyDescriptorBuilder.setConfiguration:(Ljava/lang/String;Ljava/lang/String;)Lorg/apache/hadoop/hbase/client/ColumnFamilyDescriptorBuilder;
      21: pop
      22: aload_3
      23: aload_1
      24: invokevirtual #22                 // Method org/apache/hadoop/hbase/client/ColumnFamilyDescriptorBuilder.build:()Lorg/apache/hadoop/hbase/client/ColumnFamilyDescriptor;
      27: aload_2
      28: invokeinterface #71,  2           // InterfaceMethod org/apache/hadoop/hbase/client/ColumnFamilyDescriptor.getConfigurationValue:(Ljava/lang/String;)Ljava/lang/String;
      33: invokestatic  #49                 // Method org/junit/Assert.assertEquals:(Ljava/lang/Object;Ljava/lang/Object;)V
      36: aload_1
      37: aload_2
      38: invokevirtual #72                 // Method org/apache/hadoop/hbase/client/ColumnFamilyDescriptorBuilder.removeConfiguration:(Ljava/lang/String;)Lorg/apache/hadoop/hbase/client/ColumnFamilyDescriptorBuilder;
      41: pop
      42: aconst_null
      43: aload_1
      44: invokevirtual #22                 // Method org/apache/hadoop/hbase/client/ColumnFamilyDescriptorBuilder.build:()Lorg/apache/hadoop/hbase/client/ColumnFamilyDescriptor;
      47: aload_2
      48: invokeinterface #71,  2           // InterfaceMethod org/apache/hadoop/hbase/client/ColumnFamilyDescriptor.getConfigurationValue:(Ljava/lang/String;)Ljava/lang/String;
      53: invokestatic  #49                 // Method org/junit/Assert.assertEquals:(Ljava/lang/Object;Ljava/lang/Object;)V
      56: return

  public void testMobValuesInHColumnDescriptorShouldReadable();
    Code:
       0: iconst_1
       1: istore_1
       2: ldc2_w        #36                 // long 1000l
       5: lstore_2
       6: ldc           #73                 // String weekly
       8: astore        4
      10: iload_1
      11: invokestatic  #74                 // Method java/lang/String.valueOf:(Z)Ljava/lang/String;
      14: ldc           #75                 // String IS_MOB
      16: invokestatic  #76                 // Method org/apache/hadoop/hbase/HColumnDescriptor.getUnit:(Ljava/lang/String;)Lorg/apache/hadoop/hbase/util/PrettyPrinter$Unit;
      19: invokestatic  #77                 // Method org/apache/hadoop/hbase/util/PrettyPrinter.format:(Ljava/lang/String;Lorg/apache/hadoop/hbase/util/PrettyPrinter$Unit;)Ljava/lang/String;
      22: astore        5
      24: lload_2
      25: invokestatic  #78                 // Method java/lang/String.valueOf:(J)Ljava/lang/String;
      28: ldc           #79                 // String MOB_THRESHOLD
      30: invokestatic  #76                 // Method org/apache/hadoop/hbase/HColumnDescriptor.getUnit:(Ljava/lang/String;)Lorg/apache/hadoop/hbase/util/PrettyPrinter$Unit;
      33: invokestatic  #77                 // Method org/apache/hadoop/hbase/util/PrettyPrinter.format:(Ljava/lang/String;Lorg/apache/hadoop/hbase/util/PrettyPrinter$Unit;)Ljava/lang/String;
      36: astore        6
      38: aload         4
      40: invokestatic  #16                 // Method org/apache/hadoop/hbase/util/Bytes.toBytes:(Ljava/lang/String;)[B
      43: invokestatic  #80                 // Method org/apache/hadoop/hbase/util/Bytes.toStringBinary:([B)Ljava/lang/String;
      46: ldc           #81                 // String MOB_COMPACT_PARTITION_POLICY
      48: invokestatic  #76                 // Method org/apache/hadoop/hbase/HColumnDescriptor.getUnit:(Ljava/lang/String;)Lorg/apache/hadoop/hbase/util/PrettyPrinter$Unit;
      51: invokestatic  #77                 // Method org/apache/hadoop/hbase/util/PrettyPrinter.format:(Ljava/lang/String;Lorg/apache/hadoop/hbase/util/PrettyPrinter$Unit;)Ljava/lang/String;
      54: astore        7
      56: iload_1
      57: invokestatic  #74                 // Method java/lang/String.valueOf:(Z)Ljava/lang/String;
      60: aload         5
      62: invokestatic  #49                 // Method org/junit/Assert.assertEquals:(Ljava/lang/Object;Ljava/lang/Object;)V
      65: lload_2
      66: invokestatic  #78                 // Method java/lang/String.valueOf:(J)Ljava/lang/String;
      69: aload         6
      71: invokestatic  #49                 // Method org/junit/Assert.assertEquals:(Ljava/lang/Object;Ljava/lang/Object;)V
      74: aload         4
      76: invokestatic  #82                 // Method java/lang/String.valueOf:(Ljava/lang/Object;)Ljava/lang/String;
      79: aload         7
      81: invokestatic  #49                 // Method org/junit/Assert.assertEquals:(Ljava/lang/Object;Ljava/lang/Object;)V
      84: return

  public void testClassMethodsAreBuilderStyle();
    Code:
       0: iconst_1
       1: anewarray     #83                 // class java/lang/Class
       4: dup
       5: iconst_0
       6: ldc           #84                 // class org/apache/hadoop/hbase/client/ColumnFamilyDescriptorBuilder
       8: aastore
       9: invokestatic  #85                 // Method org/apache/hadoop/hbase/util/BuilderStyleTest.assertClassesAreBuilderStyle:([Ljava/lang/Class;)V
      12: return

  public void testSetTimeToLive() throws org.apache.hadoop.hbase.exceptions.HBaseException;
    Code:
       0: ldc           #67                 // String foo
       2: invokestatic  #16                 // Method org/apache/hadoop/hbase/util/Bytes.toBytes:(Ljava/lang/String;)[B
       5: invokestatic  #5                  // Method org/apache/hadoop/hbase/client/ColumnFamilyDescriptorBuilder.newBuilder:([B)Lorg/apache/hadoop/hbase/client/ColumnFamilyDescriptorBuilder;
       8: astore_2
       9: ldc           #86                 // String 50000
      11: astore_1
      12: aload_2
      13: aload_1
      14: invokevirtual #87                 // Method org/apache/hadoop/hbase/client/ColumnFamilyDescriptorBuilder.setTimeToLive:(Ljava/lang/String;)Lorg/apache/hadoop/hbase/client/ColumnFamilyDescriptorBuilder;
      17: pop
      18: ldc2_w        #88                 // long 50000l
      21: aload_2
      22: invokevirtual #22                 // Method org/apache/hadoop/hbase/client/ColumnFamilyDescriptorBuilder.build:()Lorg/apache/hadoop/hbase/client/ColumnFamilyDescriptor;
      25: invokeinterface #45,  1           // InterfaceMethod org/apache/hadoop/hbase/client/ColumnFamilyDescriptor.getTimeToLive:()I
      30: i2l
      31: invokestatic  #24                 // Method org/junit/Assert.assertEquals:(JJ)V
      34: ldc           #90                 // String 50000 seconds
      36: astore_1
      37: aload_2
      38: aload_1
      39: invokevirtual #87                 // Method org/apache/hadoop/hbase/client/ColumnFamilyDescriptorBuilder.setTimeToLive:(Ljava/lang/String;)Lorg/apache/hadoop/hbase/client/ColumnFamilyDescriptorBuilder;
      42: pop
      43: ldc2_w        #88                 // long 50000l
      46: aload_2
      47: invokevirtual #22                 // Method org/apache/hadoop/hbase/client/ColumnFamilyDescriptorBuilder.build:()Lorg/apache/hadoop/hbase/client/ColumnFamilyDescriptor;
      50: invokeinterface #45,  1           // InterfaceMethod org/apache/hadoop/hbase/client/ColumnFamilyDescriptor.getTimeToLive:()I
      55: i2l
      56: invokestatic  #24                 // Method org/junit/Assert.assertEquals:(JJ)V
      59: ldc           #65                 // String
      61: astore_1
      62: aload_2
      63: aload_1
      64: invokevirtual #87                 // Method org/apache/hadoop/hbase/client/ColumnFamilyDescriptorBuilder.setTimeToLive:(Ljava/lang/String;)Lorg/apache/hadoop/hbase/client/ColumnFamilyDescriptorBuilder;
      67: pop
      68: lconst_0
      69: aload_2
      70: invokevirtual #22                 // Method org/apache/hadoop/hbase/client/ColumnFamilyDescriptorBuilder.build:()Lorg/apache/hadoop/hbase/client/ColumnFamilyDescriptor;
      73: invokeinterface #45,  1           // InterfaceMethod org/apache/hadoop/hbase/client/ColumnFamilyDescriptor.getTimeToLive:()I
      78: i2l
      79: invokestatic  #24                 // Method org/junit/Assert.assertEquals:(JJ)V
      82: ldc           #91                 // String FOREVER
      84: astore_1
      85: aload_2
      86: aload_1
      87: invokevirtual #87                 // Method org/apache/hadoop/hbase/client/ColumnFamilyDescriptorBuilder.setTimeToLive:(Ljava/lang/String;)Lorg/apache/hadoop/hbase/client/ColumnFamilyDescriptorBuilder;
      90: pop
      91: ldc2_w        #92                 // long 2147483647l
      94: aload_2
      95: invokevirtual #22                 // Method org/apache/hadoop/hbase/client/ColumnFamilyDescriptorBuilder.build:()Lorg/apache/hadoop/hbase/client/ColumnFamilyDescriptor;
      98: invokeinterface #45,  1           // InterfaceMethod org/apache/hadoop/hbase/client/ColumnFamilyDescriptor.getTimeToLive:()I
     103: i2l
     104: invokestatic  #24                 // Method org/junit/Assert.assertEquals:(JJ)V
     107: ldc           #94                 // String 1 HOUR 10 minutes 1 second
     109: astore_1
     110: aload_2
     111: aload_1
     112: invokevirtual #87                 // Method org/apache/hadoop/hbase/client/ColumnFamilyDescriptorBuilder.setTimeToLive:(Ljava/lang/String;)Lorg/apache/hadoop/hbase/client/ColumnFamilyDescriptorBuilder;
     115: pop
     116: ldc2_w        #95                 // long 4201l
     119: aload_2
     120: invokevirtual #22                 // Method org/apache/hadoop/hbase/client/ColumnFamilyDescriptorBuilder.build:()Lorg/apache/hadoop/hbase/client/ColumnFamilyDescriptor;
     123: invokeinterface #45,  1           // InterfaceMethod org/apache/hadoop/hbase/client/ColumnFamilyDescriptor.getTimeToLive:()I
     128: i2l
     129: invokestatic  #24                 // Method org/junit/Assert.assertEquals:(JJ)V
     132: ldc           #97                 // String 500 Days 23 HOURS
     134: astore_1
     135: aload_2
     136: aload_1
     137: invokevirtual #87                 // Method org/apache/hadoop/hbase/client/ColumnFamilyDescriptorBuilder.setTimeToLive:(Ljava/lang/String;)Lorg/apache/hadoop/hbase/client/ColumnFamilyDescriptorBuilder;
     140: pop
     141: ldc2_w        #98                 // long 43282800l
     144: aload_2
     145: invokevirtual #22                 // Method org/apache/hadoop/hbase/client/ColumnFamilyDescriptorBuilder.build:()Lorg/apache/hadoop/hbase/client/ColumnFamilyDescriptor;
     148: invokeinterface #45,  1           // InterfaceMethod org/apache/hadoop/hbase/client/ColumnFamilyDescriptor.getTimeToLive:()I
     153: i2l
     154: invokestatic  #24                 // Method org/junit/Assert.assertEquals:(JJ)V
     157: ldc           #100                // String 43282800 SECONDS (500 Days 23 hours)
     159: astore_1
     160: aload_2
     161: aload_1
     162: invokevirtual #87                 // Method org/apache/hadoop/hbase/client/ColumnFamilyDescriptorBuilder.setTimeToLive:(Ljava/lang/String;)Lorg/apache/hadoop/hbase/client/ColumnFamilyDescriptorBuilder;
     165: pop
     166: ldc2_w        #98                 // long 43282800l
     169: aload_2
     170: invokevirtual #22                 // Method org/apache/hadoop/hbase/client/ColumnFamilyDescriptorBuilder.build:()Lorg/apache/hadoop/hbase/client/ColumnFamilyDescriptor;
     173: invokeinterface #45,  1           // InterfaceMethod org/apache/hadoop/hbase/client/ColumnFamilyDescriptor.getTimeToLive:()I
     178: i2l
     179: invokestatic  #24                 // Method org/junit/Assert.assertEquals:(JJ)V
     182: return

  static {};
    Code:
       0: ldc           #101                // class org/apache/hadoop/hbase/client/TestColumnFamilyDescriptorBuilder
       2: invokestatic  #102                // Method org/apache/hadoop/hbase/HBaseClassTestRule.forClass:(Ljava/lang/Class;)Lorg/apache/hadoop/hbase/HBaseClassTestRule;
       5: putstatic     #103                // Field CLASS_RULE:Lorg/apache/hadoop/hbase/HBaseClassTestRule;
       8: return
}
