Compiled from "TestWALSplit.java"
class org.apache.hadoop.hbase.wal.TestWALSplit$8 extends org.apache.hadoop.hbase.wal.WALSplitter {
  final int val$writerSlowness;

  final int val$numFakeEdits;

  final java.util.List val$regions;

  final org.apache.hadoop.hbase.wal.TestWALSplit this$0;

  org.apache.hadoop.hbase.wal.TestWALSplit$8(org.apache.hadoop.hbase.wal.TestWALSplit, org.apache.hadoop.hbase.wal.WALFactory, org.apache.hadoop.conf.Configuration, org.apache.hadoop.fs.Path, org.apache.hadoop.fs.FileSystem, org.apache.hadoop.hbase.regionserver.LastSequenceId, org.apache.hadoop.hbase.coordination.SplitLogWorkerCoordination, int, int, java.util.List);
    Code:
       0: aload_0
       1: aload_1
       2: putfield      #1                  // Field this$0:Lorg/apache/hadoop/hbase/wal/TestWALSplit;
       5: aload_0
       6: iload         8
       8: putfield      #2                  // Field val$writerSlowness:I
      11: aload_0
      12: iload         9
      14: putfield      #3                  // Field val$numFakeEdits:I
      17: aload_0
      18: aload         10
      20: putfield      #4                  // Field val$regions:Ljava/util/List;
      23: aload_0
      24: aload_2
      25: aload_3
      26: aload         4
      28: aload         5
      30: aload         6
      32: aload         7
      34: invokespecial #5                  // Method org/apache/hadoop/hbase/wal/WALSplitter."<init>":(Lorg/apache/hadoop/hbase/wal/WALFactory;Lorg/apache/hadoop/conf/Configuration;Lorg/apache/hadoop/fs/Path;Lorg/apache/hadoop/fs/FileSystem;Lorg/apache/hadoop/hbase/regionserver/LastSequenceId;Lorg/apache/hadoop/hbase/coordination/SplitLogWorkerCoordination;)V
      37: return

  protected org.apache.hadoop.hbase.wal.WALProvider$Writer createWriter(org.apache.hadoop.fs.Path) throws java.io.IOException;
    Code:
       0: ldc           #6                  // class org/apache/hadoop/hbase/wal/WALProvider$Writer
       2: invokestatic  #7                  // Method org/mockito/Mockito.mock:(Ljava/lang/Class;)Ljava/lang/Object;
       5: checkcast     #6                  // class org/apache/hadoop/hbase/wal/WALProvider$Writer
       8: astore_2
       9: new           #8                  // class org/apache/hadoop/hbase/wal/TestWALSplit$8$1
      12: dup
      13: aload_0
      14: invokespecial #9                  // Method org/apache/hadoop/hbase/wal/TestWALSplit$8$1."<init>":(Lorg/apache/hadoop/hbase/wal/TestWALSplit$8;)V
      17: invokestatic  #10                 // Method org/mockito/Mockito.doAnswer:(Lorg/mockito/stubbing/Answer;)Lorg/mockito/stubbing/Stubber;
      20: aload_2
      21: invokeinterface #11,  2           // InterfaceMethod org/mockito/stubbing/Stubber.when:(Ljava/lang/Object;)Ljava/lang/Object;
      26: checkcast     #6                  // class org/apache/hadoop/hbase/wal/WALProvider$Writer
      29: invokestatic  #12                 // Method org/mockito/Mockito.any:()Ljava/lang/Object;
      32: checkcast     #13                 // class org/apache/hadoop/hbase/wal/WAL$Entry
      35: invokeinterface #14,  2           // InterfaceMethod org/apache/hadoop/hbase/wal/WALProvider$Writer.append:(Lorg/apache/hadoop/hbase/wal/WAL$Entry;)V
      40: aload_2
      41: areturn

  protected org.apache.hadoop.hbase.wal.WAL$Reader getReader(org.apache.hadoop.fs.Path, org.apache.hadoop.hbase.util.CancelableProgressable) throws java.io.IOException;
    Code:
       0: ldc           #15                 // class org/apache/hadoop/hbase/wal/WAL$Reader
       2: invokestatic  #7                  // Method org/mockito/Mockito.mock:(Ljava/lang/Class;)Ljava/lang/Object;
       5: checkcast     #15                 // class org/apache/hadoop/hbase/wal/WAL$Reader
       8: astore_3
       9: new           #16                 // class org/apache/hadoop/hbase/wal/TestWALSplit$8$2
      12: dup
      13: aload_0
      14: invokespecial #17                 // Method org/apache/hadoop/hbase/wal/TestWALSplit$8$2."<init>":(Lorg/apache/hadoop/hbase/wal/TestWALSplit$8;)V
      17: invokestatic  #10                 // Method org/mockito/Mockito.doAnswer:(Lorg/mockito/stubbing/Answer;)Lorg/mockito/stubbing/Stubber;
      20: aload_3
      21: invokeinterface #11,  2           // InterfaceMethod org/mockito/stubbing/Stubber.when:(Ljava/lang/Object;)Ljava/lang/Object;
      26: checkcast     #15                 // class org/apache/hadoop/hbase/wal/WAL$Reader
      29: invokeinterface #18,  1           // InterfaceMethod org/apache/hadoop/hbase/wal/WAL$Reader.next:()Lorg/apache/hadoop/hbase/wal/WAL$Entry;
      34: pop
      35: aload_3
      36: areturn
}
