Compiled from "TestReplicationEndpoint.java"
public class org.apache.hadoop.hbase.replication.TestReplicationEndpoint extends org.apache.hadoop.hbase.replication.TestReplicationBase {
  public static final org.apache.hadoop.hbase.HBaseClassTestRule CLASS_RULE;

  static int numRegionServers;

  public org.apache.hadoop.hbase.replication.TestReplicationEndpoint();
    Code:
       0: aload_0
       1: invokespecial #3                  // Method org/apache/hadoop/hbase/replication/TestReplicationBase."<init>":()V
       4: return

  public static void setUpBeforeClass() throws java.lang.Exception;
    Code:
       0: invokestatic  #4                  // Method org/apache/hadoop/hbase/replication/TestReplicationBase.setUpBeforeClass:()V
       3: getstatic     #5                  // Field UTIL1:Lorg/apache/hadoop/hbase/HBaseTestingUtility;
       6: invokevirtual #6                  // Method org/apache/hadoop/hbase/HBaseTestingUtility.getHBaseCluster:()Lorg/apache/hadoop/hbase/MiniHBaseCluster;
       9: invokevirtual #7                  // Method org/apache/hadoop/hbase/MiniHBaseCluster.getRegionServerThreads:()Ljava/util/List;
      12: invokeinterface #8,  1            // InterfaceMethod java/util/List.size:()I
      17: putstatic     #9                  // Field numRegionServers:I
      20: return

  public static void tearDownAfterClass() throws java.lang.Exception;
    Code:
       0: invokestatic  #10                 // Method org/apache/hadoop/hbase/replication/TestReplicationBase.tearDownAfterClass:()V
       3: getstatic     #11                 // Field org/apache/hadoop/hbase/replication/TestReplicationEndpoint$ReplicationEndpointForTest.stoppedCount:Ljava/util/concurrent/atomic/AtomicInteger;
       6: invokevirtual #12                 // Method java/util/concurrent/atomic/AtomicInteger.get:()I
       9: ifle          16
      12: iconst_1
      13: goto          17
      16: iconst_0
      17: invokestatic  #13                 // Method org/junit/Assert.assertTrue:(Z)V
      20: return

  public void setup() throws java.lang.Exception;
    Code:
       0: getstatic     #14                 // Field org/apache/hadoop/hbase/replication/TestReplicationEndpoint$ReplicationEndpointForTest.contructedCount:Ljava/util/concurrent/atomic/AtomicInteger;
       3: iconst_0
       4: invokevirtual #15                 // Method java/util/concurrent/atomic/AtomicInteger.set:(I)V
       7: getstatic     #16                 // Field org/apache/hadoop/hbase/replication/TestReplicationEndpoint$ReplicationEndpointForTest.startedCount:Ljava/util/concurrent/atomic/AtomicInteger;
      10: iconst_0
      11: invokevirtual #15                 // Method java/util/concurrent/atomic/AtomicInteger.set:(I)V
      14: getstatic     #17                 // Field org/apache/hadoop/hbase/replication/TestReplicationEndpoint$ReplicationEndpointForTest.replicateCount:Ljava/util/concurrent/atomic/AtomicInteger;
      17: iconst_0
      18: invokevirtual #15                 // Method java/util/concurrent/atomic/AtomicInteger.set:(I)V
      21: getstatic     #18                 // Field org/apache/hadoop/hbase/replication/TestReplicationEndpoint$ReplicationEndpointReturningFalse.replicated:Ljava/util/concurrent/atomic/AtomicBoolean;
      24: iconst_0
      25: invokevirtual #19                 // Method java/util/concurrent/atomic/AtomicBoolean.set:(Z)V
      28: aconst_null
      29: putstatic     #20                 // Field org/apache/hadoop/hbase/replication/TestReplicationEndpoint$ReplicationEndpointForTest.lastEntries:Ljava/util/List;
      32: getstatic     #5                  // Field UTIL1:Lorg/apache/hadoop/hbase/HBaseTestingUtility;
      35: invokevirtual #21                 // Method org/apache/hadoop/hbase/HBaseTestingUtility.getMiniHBaseCluster:()Lorg/apache/hadoop/hbase/MiniHBaseCluster;
      38: invokevirtual #7                  // Method org/apache/hadoop/hbase/MiniHBaseCluster.getRegionServerThreads:()Ljava/util/List;
      41: astore_1
      42: aload_1
      43: invokeinterface #22,  1           // InterfaceMethod java/util/List.iterator:()Ljava/util/Iterator;
      48: astore_2
      49: aload_2
      50: invokeinterface #23,  1           // InterfaceMethod java/util/Iterator.hasNext:()Z
      55: ifeq          89
      58: aload_2
      59: invokeinterface #24,  1           // InterfaceMethod java/util/Iterator.next:()Ljava/lang/Object;
      64: checkcast     #25                 // class org/apache/hadoop/hbase/util/JVMClusterUtil$RegionServerThread
      67: astore_3
      68: getstatic     #5                  // Field UTIL1:Lorg/apache/hadoop/hbase/HBaseTestingUtility;
      71: invokevirtual #26                 // Method org/apache/hadoop/hbase/HBaseTestingUtility.getAdmin:()Lorg/apache/hadoop/hbase/client/Admin;
      74: aload_3
      75: invokevirtual #27                 // Method org/apache/hadoop/hbase/util/JVMClusterUtil$RegionServerThread.getRegionServer:()Lorg/apache/hadoop/hbase/regionserver/HRegionServer;
      78: invokevirtual #28                 // Method org/apache/hadoop/hbase/regionserver/HRegionServer.getServerName:()Lorg/apache/hadoop/hbase/ServerName;
      81: invokeinterface #29,  2           // InterfaceMethod org/apache/hadoop/hbase/client/Admin.rollWALWriter:(Lorg/apache/hadoop/hbase/ServerName;)V
      86: goto          49
      89: getstatic     #5                  // Field UTIL1:Lorg/apache/hadoop/hbase/HBaseTestingUtility;
      92: ldc2_w        #30                 // long 3000l
      95: new           #32                 // class org/apache/hadoop/hbase/replication/TestReplicationEndpoint$1
      98: dup
      99: aload_0
     100: aload_1
     101: invokespecial #33                 // Method org/apache/hadoop/hbase/replication/TestReplicationEndpoint$1."<init>":(Lorg/apache/hadoop/hbase/replication/TestReplicationEndpoint;Ljava/util/List;)V
     104: invokevirtual #34                 // Method org/apache/hadoop/hbase/HBaseTestingUtility.waitFor:(JLorg/apache/hadoop/hbase/Waiter$Predicate;)J
     107: pop2
     108: return

  public void testCustomReplicationEndpoint() throws java.lang.Exception;
    Code:
       0: getstatic     #35                 // Field admin:Lorg/apache/hadoop/hbase/client/replication/ReplicationAdmin;
       3: ldc           #36                 // String testCustomReplicationEndpoint
       5: new           #37                 // class org/apache/hadoop/hbase/replication/ReplicationPeerConfig
       8: dup
       9: invokespecial #38                 // Method org/apache/hadoop/hbase/replication/ReplicationPeerConfig."<init>":()V
      12: getstatic     #39                 // Field CONF1:Lorg/apache/hadoop/conf/Configuration;
      15: invokestatic  #40                 // Method org/apache/hadoop/hbase/zookeeper/ZKConfig.getZooKeeperClusterKey:(Lorg/apache/hadoop/conf/Configuration;)Ljava/lang/String;
      18: invokevirtual #41                 // Method org/apache/hadoop/hbase/replication/ReplicationPeerConfig.setClusterKey:(Ljava/lang/String;)Lorg/apache/hadoop/hbase/replication/ReplicationPeerConfig;
      21: ldc           #42                 // class org/apache/hadoop/hbase/replication/TestReplicationEndpoint$ReplicationEndpointForTest
      23: invokevirtual #43                 // Method java/lang/Class.getName:()Ljava/lang/String;
      26: invokevirtual #44                 // Method org/apache/hadoop/hbase/replication/ReplicationPeerConfig.setReplicationEndpointImpl:(Ljava/lang/String;)Lorg/apache/hadoop/hbase/replication/ReplicationPeerConfig;
      29: aconst_null
      30: invokevirtual #45                 // Method org/apache/hadoop/hbase/client/replication/ReplicationAdmin.addPeer:(Ljava/lang/String;Lorg/apache/hadoop/hbase/replication/ReplicationPeerConfig;Ljava/util/Map;)V
      33: getstatic     #39                 // Field CONF1:Lorg/apache/hadoop/conf/Configuration;
      36: ldc2_w        #46                 // long 60000l
      39: new           #48                 // class org/apache/hadoop/hbase/replication/TestReplicationEndpoint$2
      42: dup
      43: aload_0
      44: invokespecial #49                 // Method org/apache/hadoop/hbase/replication/TestReplicationEndpoint$2."<init>":(Lorg/apache/hadoop/hbase/replication/TestReplicationEndpoint;)V
      47: invokestatic  #50                 // Method org/apache/hadoop/hbase/Waiter.waitFor:(Lorg/apache/hadoop/conf/Configuration;JLorg/apache/hadoop/hbase/Waiter$Predicate;)J
      50: pop2
      51: getstatic     #39                 // Field CONF1:Lorg/apache/hadoop/conf/Configuration;
      54: ldc2_w        #46                 // long 60000l
      57: new           #51                 // class org/apache/hadoop/hbase/replication/TestReplicationEndpoint$3
      60: dup
      61: aload_0
      62: invokespecial #52                 // Method org/apache/hadoop/hbase/replication/TestReplicationEndpoint$3."<init>":(Lorg/apache/hadoop/hbase/replication/TestReplicationEndpoint;)V
      65: invokestatic  #50                 // Method org/apache/hadoop/hbase/Waiter.waitFor:(Lorg/apache/hadoop/conf/Configuration;JLorg/apache/hadoop/hbase/Waiter$Predicate;)J
      68: pop2
      69: lconst_0
      70: getstatic     #17                 // Field org/apache/hadoop/hbase/replication/TestReplicationEndpoint$ReplicationEndpointForTest.replicateCount:Ljava/util/concurrent/atomic/AtomicInteger;
      73: invokevirtual #12                 // Method java/util/concurrent/atomic/AtomicInteger.get:()I
      76: i2l
      77: invokestatic  #53                 // Method org/junit/Assert.assertEquals:(JJ)V
      80: aload_0
      81: ldc           #54                 // String row42
      83: invokestatic  #55                 // Method org/apache/hadoop/hbase/util/Bytes.toBytes:(Ljava/lang/String;)[B
      86: invokespecial #56                 // Method doPut:([B)V
      89: getstatic     #39                 // Field CONF1:Lorg/apache/hadoop/conf/Configuration;
      92: ldc2_w        #46                 // long 60000l
      95: new           #57                 // class org/apache/hadoop/hbase/replication/TestReplicationEndpoint$4
      98: dup
      99: aload_0
     100: invokespecial #58                 // Method org/apache/hadoop/hbase/replication/TestReplicationEndpoint$4."<init>":(Lorg/apache/hadoop/hbase/replication/TestReplicationEndpoint;)V
     103: invokestatic  #50                 // Method org/apache/hadoop/hbase/Waiter.waitFor:(Lorg/apache/hadoop/conf/Configuration;JLorg/apache/hadoop/hbase/Waiter$Predicate;)J
     106: pop2
     107: ldc           #54                 // String row42
     109: invokestatic  #55                 // Method org/apache/hadoop/hbase/util/Bytes.toBytes:(Ljava/lang/String;)[B
     112: invokestatic  #1                  // Method doAssert:([B)V
     115: getstatic     #35                 // Field admin:Lorg/apache/hadoop/hbase/client/replication/ReplicationAdmin;
     118: ldc           #36                 // String testCustomReplicationEndpoint
     120: invokevirtual #59                 // Method org/apache/hadoop/hbase/client/replication/ReplicationAdmin.removePeer:(Ljava/lang/String;)V
     123: return

  public void testReplicationEndpointReturnsFalseOnReplicate() throws java.lang.Exception;
    Code:
       0: lconst_0
       1: getstatic     #17                 // Field org/apache/hadoop/hbase/replication/TestReplicationEndpoint$ReplicationEndpointForTest.replicateCount:Ljava/util/concurrent/atomic/AtomicInteger;
       4: invokevirtual #12                 // Method java/util/concurrent/atomic/AtomicInteger.get:()I
       7: i2l
       8: invokestatic  #53                 // Method org/junit/Assert.assertEquals:(JJ)V
      11: getstatic     #18                 // Field org/apache/hadoop/hbase/replication/TestReplicationEndpoint$ReplicationEndpointReturningFalse.replicated:Ljava/util/concurrent/atomic/AtomicBoolean;
      14: invokevirtual #60                 // Method java/util/concurrent/atomic/AtomicBoolean.get:()Z
      17: ifne          24
      20: iconst_1
      21: goto          25
      24: iconst_0
      25: invokestatic  #13                 // Method org/junit/Assert.assertTrue:(Z)V
      28: getstatic     #35                 // Field admin:Lorg/apache/hadoop/hbase/client/replication/ReplicationAdmin;
      31: invokevirtual #61                 // Method org/apache/hadoop/hbase/client/replication/ReplicationAdmin.getPeersCount:()I
      34: istore_1
      35: ldc           #62                 // String testReplicationEndpointReturnsFalseOnReplicate
      37: astore_2
      38: getstatic     #35                 // Field admin:Lorg/apache/hadoop/hbase/client/replication/ReplicationAdmin;
      41: ldc           #62                 // String testReplicationEndpointReturnsFalseOnReplicate
      43: new           #37                 // class org/apache/hadoop/hbase/replication/ReplicationPeerConfig
      46: dup
      47: invokespecial #38                 // Method org/apache/hadoop/hbase/replication/ReplicationPeerConfig."<init>":()V
      50: getstatic     #39                 // Field CONF1:Lorg/apache/hadoop/conf/Configuration;
      53: invokestatic  #40                 // Method org/apache/hadoop/hbase/zookeeper/ZKConfig.getZooKeeperClusterKey:(Lorg/apache/hadoop/conf/Configuration;)Ljava/lang/String;
      56: invokevirtual #41                 // Method org/apache/hadoop/hbase/replication/ReplicationPeerConfig.setClusterKey:(Ljava/lang/String;)Lorg/apache/hadoop/hbase/replication/ReplicationPeerConfig;
      59: ldc           #63                 // class org/apache/hadoop/hbase/replication/TestReplicationEndpoint$ReplicationEndpointReturningFalse
      61: invokevirtual #43                 // Method java/lang/Class.getName:()Ljava/lang/String;
      64: invokevirtual #44                 // Method org/apache/hadoop/hbase/replication/ReplicationPeerConfig.setReplicationEndpointImpl:(Ljava/lang/String;)Lorg/apache/hadoop/hbase/replication/ReplicationPeerConfig;
      67: aconst_null
      68: invokevirtual #45                 // Method org/apache/hadoop/hbase/client/replication/ReplicationAdmin.addPeer:(Ljava/lang/String;Lorg/apache/hadoop/hbase/replication/ReplicationPeerConfig;Ljava/util/Map;)V
      71: getstatic     #35                 // Field admin:Lorg/apache/hadoop/hbase/client/replication/ReplicationAdmin;
      74: invokevirtual #61                 // Method org/apache/hadoop/hbase/client/replication/ReplicationAdmin.getPeersCount:()I
      77: iload_1
      78: if_icmpgt     114
      81: getstatic     #2                  // Field LOG:Lorg/slf4j/Logger;
      84: new           #64                 // class java/lang/StringBuilder
      87: dup
      88: invokespecial #65                 // Method java/lang/StringBuilder."<init>":()V
      91: ldc           #66                 // String Waiting on peercount to go up from
      93: invokevirtual #67                 // Method java/lang/StringBuilder.append:(Ljava/lang/String;)Ljava/lang/StringBuilder;
      96: iload_1
      97: invokevirtual #68                 // Method java/lang/StringBuilder.append:(I)Ljava/lang/StringBuilder;
     100: invokevirtual #69                 // Method java/lang/StringBuilder.toString:()Ljava/lang/String;
     103: invokeinterface #70,  2           // InterfaceMethod org/slf4j/Logger.info:(Ljava/lang/String;)V
     108: ldc2_w        #71                 // long 100l
     111: invokestatic  #73                 // Method org/apache/hadoop/hbase/util/Threads.sleep:(J)V
     114: aload_0
     115: getstatic     #74                 // Field row:[B
     118: invokespecial #56                 // Method doPut:([B)V
     121: getstatic     #39                 // Field CONF1:Lorg/apache/hadoop/conf/Configuration;
     124: ldc2_w        #46                 // long 60000l
     127: new           #75                 // class org/apache/hadoop/hbase/replication/TestReplicationEndpoint$5
     130: dup
     131: aload_0
     132: invokespecial #76                 // Method org/apache/hadoop/hbase/replication/TestReplicationEndpoint$5."<init>":(Lorg/apache/hadoop/hbase/replication/TestReplicationEndpoint;)V
     135: invokestatic  #50                 // Method org/apache/hadoop/hbase/Waiter.waitFor:(Lorg/apache/hadoop/conf/Configuration;JLorg/apache/hadoop/hbase/Waiter$Predicate;)J
     138: pop2
     139: getstatic     #77                 // Field org/apache/hadoop/hbase/replication/TestReplicationEndpoint$ReplicationEndpointReturningFalse.ex:Ljava/util/concurrent/atomic/AtomicReference;
     142: invokevirtual #78                 // Method java/util/concurrent/atomic/AtomicReference.get:()Ljava/lang/Object;
     145: ifnull        158
     148: getstatic     #77                 // Field org/apache/hadoop/hbase/replication/TestReplicationEndpoint$ReplicationEndpointReturningFalse.ex:Ljava/util/concurrent/atomic/AtomicReference;
     151: invokevirtual #78                 // Method java/util/concurrent/atomic/AtomicReference.get:()Ljava/lang/Object;
     154: checkcast     #79                 // class java/lang/Exception
     157: athrow
     158: getstatic     #35                 // Field admin:Lorg/apache/hadoop/hbase/client/replication/ReplicationAdmin;
     161: ldc           #62                 // String testReplicationEndpointReturnsFalseOnReplicate
     163: invokevirtual #59                 // Method org/apache/hadoop/hbase/client/replication/ReplicationAdmin.removePeer:(Ljava/lang/String;)V
     166: return

  public void testInterClusterReplication() throws java.lang.Exception;
    Code:
       0: ldc           #80                 // String testInterClusterReplication
       2: astore_1
       3: getstatic     #5                  // Field UTIL1:Lorg/apache/hadoop/hbase/HBaseTestingUtility;
       6: invokevirtual #6                  // Method org/apache/hadoop/hbase/HBaseTestingUtility.getHBaseCluster:()Lorg/apache/hadoop/hbase/MiniHBaseCluster;
       9: getstatic     #81                 // Field tableName:Lorg/apache/hadoop/hbase/TableName;
      12: invokevirtual #82                 // Method org/apache/hadoop/hbase/MiniHBaseCluster.getRegions:(Lorg/apache/hadoop/hbase/TableName;)Ljava/util/List;
      15: astore_2
      16: iconst_0
      17: istore_3
      18: aload_2
      19: invokeinterface #22,  1           // InterfaceMethod java/util/List.iterator:()Ljava/util/Iterator;
      24: astore        4
      26: aload         4
      28: invokeinterface #23,  1           // InterfaceMethod java/util/Iterator.hasNext:()Z
      33: ifeq          123
      36: aload         4
      38: invokeinterface #24,  1           // InterfaceMethod java/util/Iterator.next:()Ljava/lang/Object;
      43: checkcast     #83                 // class org/apache/hadoop/hbase/regionserver/HRegion
      46: astore        5
      48: aload         5
      50: invokevirtual #84                 // Method org/apache/hadoop/hbase/regionserver/HRegion.getRegionInfo:()Lorg/apache/hadoop/hbase/client/RegionInfo;
      53: astore        6
      55: aload         6
      57: invokeinterface #85,  1           // InterfaceMethod org/apache/hadoop/hbase/client/RegionInfo.getStartKey:()[B
      62: astore        7
      64: iconst_0
      65: istore        8
      67: iload         8
      69: bipush        100
      71: if_icmpge     120
      74: aload         7
      76: arraylength
      77: ifle          114
      80: new           #86                 // class org/apache/hadoop/hbase/client/Put
      83: dup
      84: aload         7
      86: invokespecial #87                 // Method org/apache/hadoop/hbase/client/Put."<init>":([B)V
      89: astore        9
      91: aload         9
      93: getstatic     #88                 // Field famName:[B
      96: aload         7
      98: aload         7
     100: invokevirtual #89                 // Method org/apache/hadoop/hbase/client/Put.addColumn:([B[B[B)Lorg/apache/hadoop/hbase/client/Put;
     103: pop
     104: aload         5
     106: aload         9
     108: invokevirtual #90                 // Method org/apache/hadoop/hbase/regionserver/HRegion.put:(Lorg/apache/hadoop/hbase/client/Put;)V
     111: iinc          3, 1
     114: iinc          8, 1
     117: goto          67
     120: goto          26
     123: getstatic     #35                 // Field admin:Lorg/apache/hadoop/hbase/client/replication/ReplicationAdmin;
     126: ldc           #80                 // String testInterClusterReplication
     128: new           #37                 // class org/apache/hadoop/hbase/replication/ReplicationPeerConfig
     131: dup
     132: invokespecial #38                 // Method org/apache/hadoop/hbase/replication/ReplicationPeerConfig."<init>":()V
     135: getstatic     #91                 // Field CONF2:Lorg/apache/hadoop/conf/Configuration;
     138: invokestatic  #40                 // Method org/apache/hadoop/hbase/zookeeper/ZKConfig.getZooKeeperClusterKey:(Lorg/apache/hadoop/conf/Configuration;)Ljava/lang/String;
     141: invokevirtual #41                 // Method org/apache/hadoop/hbase/replication/ReplicationPeerConfig.setClusterKey:(Ljava/lang/String;)Lorg/apache/hadoop/hbase/replication/ReplicationPeerConfig;
     144: ldc           #92                 // class org/apache/hadoop/hbase/replication/TestReplicationEndpoint$InterClusterReplicationEndpointForTest
     146: invokevirtual #43                 // Method java/lang/Class.getName:()Ljava/lang/String;
     149: invokevirtual #44                 // Method org/apache/hadoop/hbase/replication/ReplicationPeerConfig.setReplicationEndpointImpl:(Ljava/lang/String;)Lorg/apache/hadoop/hbase/replication/ReplicationPeerConfig;
     152: aconst_null
     153: invokevirtual #45                 // Method org/apache/hadoop/hbase/client/replication/ReplicationAdmin.addPeer:(Ljava/lang/String;Lorg/apache/hadoop/hbase/replication/ReplicationPeerConfig;Ljava/util/Map;)V
     156: iload_3
     157: istore        4
     159: getstatic     #39                 // Field CONF1:Lorg/apache/hadoop/conf/Configuration;
     162: ldc2_w        #93                 // long 30000l
     165: new           #95                 // class org/apache/hadoop/hbase/replication/TestReplicationEndpoint$6
     168: dup
     169: aload_0
     170: iload         4
     172: invokespecial #96                 // Method org/apache/hadoop/hbase/replication/TestReplicationEndpoint$6."<init>":(Lorg/apache/hadoop/hbase/replication/TestReplicationEndpoint;I)V
     175: invokestatic  #50                 // Method org/apache/hadoop/hbase/Waiter.waitFor:(Lorg/apache/hadoop/conf/Configuration;JLorg/apache/hadoop/hbase/Waiter$Predicate;)J
     178: pop2
     179: getstatic     #35                 // Field admin:Lorg/apache/hadoop/hbase/client/replication/ReplicationAdmin;
     182: ldc           #80                 // String testInterClusterReplication
     184: invokevirtual #59                 // Method org/apache/hadoop/hbase/client/replication/ReplicationAdmin.removePeer:(Ljava/lang/String;)V
     187: getstatic     #5                  // Field UTIL1:Lorg/apache/hadoop/hbase/HBaseTestingUtility;
     190: getstatic     #81                 // Field tableName:Lorg/apache/hadoop/hbase/TableName;
     193: invokevirtual #97                 // Method org/apache/hadoop/hbase/HBaseTestingUtility.deleteTableData:(Lorg/apache/hadoop/hbase/TableName;)Lorg/apache/hadoop/hbase/client/Table;
     196: pop
     197: return

  public void testWALEntryFilterFromReplicationEndpoint() throws java.lang.Exception;
    Code:
       0: new           #37                 // class org/apache/hadoop/hbase/replication/ReplicationPeerConfig
       3: dup
       4: invokespecial #38                 // Method org/apache/hadoop/hbase/replication/ReplicationPeerConfig."<init>":()V
       7: getstatic     #39                 // Field CONF1:Lorg/apache/hadoop/conf/Configuration;
      10: invokestatic  #40                 // Method org/apache/hadoop/hbase/zookeeper/ZKConfig.getZooKeeperClusterKey:(Lorg/apache/hadoop/conf/Configuration;)Ljava/lang/String;
      13: invokevirtual #41                 // Method org/apache/hadoop/hbase/replication/ReplicationPeerConfig.setClusterKey:(Ljava/lang/String;)Lorg/apache/hadoop/hbase/replication/ReplicationPeerConfig;
      16: ldc           #98                 // class org/apache/hadoop/hbase/replication/TestReplicationEndpoint$ReplicationEndpointWithWALEntryFilter
      18: invokevirtual #43                 // Method java/lang/Class.getName:()Ljava/lang/String;
      21: invokevirtual #44                 // Method org/apache/hadoop/hbase/replication/ReplicationPeerConfig.setReplicationEndpointImpl:(Ljava/lang/String;)Lorg/apache/hadoop/hbase/replication/ReplicationPeerConfig;
      24: astore_1
      25: aload_1
      26: invokevirtual #99                 // Method org/apache/hadoop/hbase/replication/ReplicationPeerConfig.getConfiguration:()Ljava/util/Map;
      29: ldc           #101                // String hbase.replication.source.custom.walentryfilters
      31: new           #64                 // class java/lang/StringBuilder
      34: dup
      35: invokespecial #65                 // Method java/lang/StringBuilder."<init>":()V
      38: ldc           #102                // class org/apache/hadoop/hbase/replication/TestReplicationEndpoint$EverythingPassesWALEntryFilter
      40: invokevirtual #43                 // Method java/lang/Class.getName:()Ljava/lang/String;
      43: invokevirtual #67                 // Method java/lang/StringBuilder.append:(Ljava/lang/String;)Ljava/lang/StringBuilder;
      46: ldc           #103                // String ,
      48: invokevirtual #67                 // Method java/lang/StringBuilder.append:(Ljava/lang/String;)Ljava/lang/StringBuilder;
      51: ldc           #104                // class org/apache/hadoop/hbase/replication/TestReplicationEndpoint$EverythingPassesWALEntryFilterSubclass
      53: invokevirtual #43                 // Method java/lang/Class.getName:()Ljava/lang/String;
      56: invokevirtual #67                 // Method java/lang/StringBuilder.append:(Ljava/lang/String;)Ljava/lang/StringBuilder;
      59: invokevirtual #69                 // Method java/lang/StringBuilder.toString:()Ljava/lang/String;
      62: invokeinterface #105,  3          // InterfaceMethod java/util/Map.put:(Ljava/lang/Object;Ljava/lang/Object;)Ljava/lang/Object;
      67: pop
      68: getstatic     #35                 // Field admin:Lorg/apache/hadoop/hbase/client/replication/ReplicationAdmin;
      71: ldc           #106                // String testWALEntryFilterFromReplicationEndpoint
      73: aload_1
      74: invokevirtual #107                // Method org/apache/hadoop/hbase/client/replication/ReplicationAdmin.addPeer:(Ljava/lang/String;Lorg/apache/hadoop/hbase/replication/ReplicationPeerConfig;)V
      77: getstatic     #39                 // Field CONF1:Lorg/apache/hadoop/conf/Configuration;
      80: invokestatic  #108                // Method org/apache/hadoop/hbase/client/ConnectionFactory.createConnection:(Lorg/apache/hadoop/conf/Configuration;)Lorg/apache/hadoop/hbase/client/Connection;
      83: astore_2
      84: aconst_null
      85: astore_3
      86: aload_0
      87: aload_2
      88: ldc           #109                // String row1
      90: invokestatic  #55                 // Method org/apache/hadoop/hbase/util/Bytes.toBytes:(Ljava/lang/String;)[B
      93: invokespecial #110                // Method doPut:(Lorg/apache/hadoop/hbase/client/Connection;[B)V
      96: aload_0
      97: aload_2
      98: getstatic     #74                 // Field row:[B
     101: invokespecial #110                // Method doPut:(Lorg/apache/hadoop/hbase/client/Connection;[B)V
     104: aload_0
     105: aload_2
     106: ldc           #111                // String row2
     108: invokestatic  #55                 // Method org/apache/hadoop/hbase/util/Bytes.toBytes:(Ljava/lang/String;)[B
     111: invokespecial #110                // Method doPut:(Lorg/apache/hadoop/hbase/client/Connection;[B)V
     114: aload_2
     115: ifnull        198
     118: aload_3
     119: ifnull        142
     122: aload_2
     123: invokeinterface #112,  1          // InterfaceMethod org/apache/hadoop/hbase/client/Connection.close:()V
     128: goto          198
     131: astore        4
     133: aload_3
     134: aload         4
     136: invokevirtual #114                // Method java/lang/Throwable.addSuppressed:(Ljava/lang/Throwable;)V
     139: goto          198
     142: aload_2
     143: invokeinterface #112,  1          // InterfaceMethod org/apache/hadoop/hbase/client/Connection.close:()V
     148: goto          198
     151: astore        4
     153: aload         4
     155: astore_3
     156: aload         4
     158: athrow
     159: astore        5
     161: aload_2
     162: ifnull        195
     165: aload_3
     166: ifnull        189
     169: aload_2
     170: invokeinterface #112,  1          // InterfaceMethod org/apache/hadoop/hbase/client/Connection.close:()V
     175: goto          195
     178: astore        6
     180: aload_3
     181: aload         6
     183: invokevirtual #114                // Method java/lang/Throwable.addSuppressed:(Ljava/lang/Throwable;)V
     186: goto          195
     189: aload_2
     190: invokeinterface #112,  1          // InterfaceMethod org/apache/hadoop/hbase/client/Connection.close:()V
     195: aload         5
     197: athrow
     198: getstatic     #39                 // Field CONF1:Lorg/apache/hadoop/conf/Configuration;
     201: ldc2_w        #46                 // long 60000l
     204: new           #115                // class org/apache/hadoop/hbase/replication/TestReplicationEndpoint$7
     207: dup
     208: aload_0
     209: invokespecial #116                // Method org/apache/hadoop/hbase/replication/TestReplicationEndpoint$7."<init>":(Lorg/apache/hadoop/hbase/replication/TestReplicationEndpoint;)V
     212: invokestatic  #50                 // Method org/apache/hadoop/hbase/Waiter.waitFor:(Lorg/apache/hadoop/conf/Configuration;JLorg/apache/hadoop/hbase/Waiter$Predicate;)J
     215: pop2
     216: getstatic     #117                // Field org/apache/hadoop/hbase/replication/TestReplicationEndpoint$ReplicationEndpointWithWALEntryFilter.ex:Ljava/util/concurrent/atomic/AtomicReference;
     219: invokevirtual #78                 // Method java/util/concurrent/atomic/AtomicReference.get:()Ljava/lang/Object;
     222: invokestatic  #118                // Method org/junit/Assert.assertNull:(Ljava/lang/Object;)V
     225: invokestatic  #119                // Method org/apache/hadoop/hbase/replication/TestReplicationEndpoint$EverythingPassesWALEntryFilter.hasPassedAnEntry:()Z
     228: invokestatic  #13                 // Method org/junit/Assert.assertTrue:(Z)V
     231: getstatic     #35                 // Field admin:Lorg/apache/hadoop/hbase/client/replication/ReplicationAdmin;
     234: ldc           #106                // String testWALEntryFilterFromReplicationEndpoint
     236: invokevirtual #59                 // Method org/apache/hadoop/hbase/client/replication/ReplicationAdmin.removePeer:(Ljava/lang/String;)V
     239: return
    Exception table:
       from    to  target type
         122   128   131   Class java/lang/Throwable
          86   114   151   Class java/lang/Throwable
          86   114   159   any
         169   175   178   Class java/lang/Throwable
         151   161   159   any

  public void testWALEntryFilterAddValidation() throws java.lang.Exception;
    Code:
       0: new           #37                 // class org/apache/hadoop/hbase/replication/ReplicationPeerConfig
       3: dup
       4: invokespecial #38                 // Method org/apache/hadoop/hbase/replication/ReplicationPeerConfig."<init>":()V
       7: getstatic     #39                 // Field CONF1:Lorg/apache/hadoop/conf/Configuration;
      10: invokestatic  #40                 // Method org/apache/hadoop/hbase/zookeeper/ZKConfig.getZooKeeperClusterKey:(Lorg/apache/hadoop/conf/Configuration;)Ljava/lang/String;
      13: invokevirtual #41                 // Method org/apache/hadoop/hbase/replication/ReplicationPeerConfig.setClusterKey:(Ljava/lang/String;)Lorg/apache/hadoop/hbase/replication/ReplicationPeerConfig;
      16: ldc           #98                 // class org/apache/hadoop/hbase/replication/TestReplicationEndpoint$ReplicationEndpointWithWALEntryFilter
      18: invokevirtual #43                 // Method java/lang/Class.getName:()Ljava/lang/String;
      21: invokevirtual #44                 // Method org/apache/hadoop/hbase/replication/ReplicationPeerConfig.setReplicationEndpointImpl:(Ljava/lang/String;)Lorg/apache/hadoop/hbase/replication/ReplicationPeerConfig;
      24: astore_1
      25: aload_1
      26: invokevirtual #99                 // Method org/apache/hadoop/hbase/replication/ReplicationPeerConfig.getConfiguration:()Ljava/util/Map;
      29: ldc           #101                // String hbase.replication.source.custom.walentryfilters
      31: ldc           #120                // String IAmNotARealWalEntryFilter
      33: invokeinterface #105,  3          // InterfaceMethod java/util/Map.put:(Ljava/lang/Object;Ljava/lang/Object;)Ljava/lang/Object;
      38: pop
      39: getstatic     #35                 // Field admin:Lorg/apache/hadoop/hbase/client/replication/ReplicationAdmin;
      42: ldc           #121                // String testWALEntryFilterAddValidation
      44: aload_1
      45: invokevirtual #107                // Method org/apache/hadoop/hbase/client/replication/ReplicationAdmin.addPeer:(Ljava/lang/String;Lorg/apache/hadoop/hbase/replication/ReplicationPeerConfig;)V
      48: return

  public void testWALEntryFilterUpdateValidation() throws java.lang.Exception;
    Code:
       0: new           #37                 // class org/apache/hadoop/hbase/replication/ReplicationPeerConfig
       3: dup
       4: invokespecial #38                 // Method org/apache/hadoop/hbase/replication/ReplicationPeerConfig."<init>":()V
       7: getstatic     #39                 // Field CONF1:Lorg/apache/hadoop/conf/Configuration;
      10: invokestatic  #40                 // Method org/apache/hadoop/hbase/zookeeper/ZKConfig.getZooKeeperClusterKey:(Lorg/apache/hadoop/conf/Configuration;)Ljava/lang/String;
      13: invokevirtual #41                 // Method org/apache/hadoop/hbase/replication/ReplicationPeerConfig.setClusterKey:(Ljava/lang/String;)Lorg/apache/hadoop/hbase/replication/ReplicationPeerConfig;
      16: ldc           #98                 // class org/apache/hadoop/hbase/replication/TestReplicationEndpoint$ReplicationEndpointWithWALEntryFilter
      18: invokevirtual #43                 // Method java/lang/Class.getName:()Ljava/lang/String;
      21: invokevirtual #44                 // Method org/apache/hadoop/hbase/replication/ReplicationPeerConfig.setReplicationEndpointImpl:(Ljava/lang/String;)Lorg/apache/hadoop/hbase/replication/ReplicationPeerConfig;
      24: astore_1
      25: aload_1
      26: invokevirtual #99                 // Method org/apache/hadoop/hbase/replication/ReplicationPeerConfig.getConfiguration:()Ljava/util/Map;
      29: ldc           #101                // String hbase.replication.source.custom.walentryfilters
      31: ldc           #120                // String IAmNotARealWalEntryFilter
      33: invokeinterface #105,  3          // InterfaceMethod java/util/Map.put:(Ljava/lang/Object;Ljava/lang/Object;)Ljava/lang/Object;
      38: pop
      39: getstatic     #35                 // Field admin:Lorg/apache/hadoop/hbase/client/replication/ReplicationAdmin;
      42: ldc           #122                // String testWALEntryFilterUpdateValidation
      44: aload_1
      45: invokevirtual #123                // Method org/apache/hadoop/hbase/client/replication/ReplicationAdmin.updatePeerConfig:(Ljava/lang/String;Lorg/apache/hadoop/hbase/replication/ReplicationPeerConfig;)V
      48: return

  public void testMetricsSourceBaseSourcePassthrough();
    Code:
       0: ldc           #124                // String id
       2: astore_1
       3: ldc           #125                // class org/apache/hadoop/metrics2/lib/DynamicMetricsRegistry
       5: invokestatic  #126                // Method org/mockito/Mockito.mock:(Ljava/lang/Class;)Ljava/lang/Object;
       8: checkcast     #125                // class org/apache/hadoop/metrics2/lib/DynamicMetricsRegistry
      11: astore_2
      12: ldc           #127                // class org/apache/hadoop/hbase/replication/regionserver/MetricsReplicationSourceImpl
      14: invokestatic  #126                // Method org/mockito/Mockito.mock:(Ljava/lang/Class;)Ljava/lang/Object;
      17: checkcast     #127                // class org/apache/hadoop/hbase/replication/regionserver/MetricsReplicationSourceImpl
      20: astore_3
      21: aload_3
      22: invokevirtual #128                // Method org/apache/hadoop/hbase/replication/regionserver/MetricsReplicationSourceImpl.getMetricsRegistry:()Lorg/apache/hadoop/metrics2/lib/DynamicMetricsRegistry;
      25: invokestatic  #129                // Method org/mockito/Mockito.when:(Ljava/lang/Object;)Lorg/mockito/stubbing/OngoingStubbing;
      28: aload_2
      29: invokeinterface #130,  2          // InterfaceMethod org/mockito/stubbing/OngoingStubbing.thenReturn:(Ljava/lang/Object;)Lorg/mockito/stubbing/OngoingStubbing;
      34: pop
      35: ldc           #127                // class org/apache/hadoop/hbase/replication/regionserver/MetricsReplicationSourceImpl
      37: invokestatic  #126                // Method org/mockito/Mockito.mock:(Ljava/lang/Class;)Ljava/lang/Object;
      40: checkcast     #127                // class org/apache/hadoop/hbase/replication/regionserver/MetricsReplicationSourceImpl
      43: astore        4
      45: aload         4
      47: invokevirtual #128                // Method org/apache/hadoop/hbase/replication/regionserver/MetricsReplicationSourceImpl.getMetricsRegistry:()Lorg/apache/hadoop/metrics2/lib/DynamicMetricsRegistry;
      50: invokestatic  #129                // Method org/mockito/Mockito.when:(Ljava/lang/Object;)Lorg/mockito/stubbing/OngoingStubbing;
      53: aload_2
      54: invokeinterface #130,  2          // InterfaceMethod org/mockito/stubbing/OngoingStubbing.thenReturn:(Ljava/lang/Object;)Lorg/mockito/stubbing/OngoingStubbing;
      59: pop
      60: new           #131                // class org/apache/hadoop/hbase/replication/regionserver/MetricsReplicationSourceSourceImpl
      63: dup
      64: aload_3
      65: aload_1
      66: invokespecial #132                // Method org/apache/hadoop/hbase/replication/regionserver/MetricsReplicationSourceSourceImpl."<init>":(Lorg/apache/hadoop/hbase/replication/regionserver/MetricsReplicationSourceImpl;Ljava/lang/String;)V
      69: astore        5
      71: new           #133                // class org/apache/hadoop/hbase/replication/regionserver/MetricsReplicationGlobalSourceSource
      74: dup
      75: aload         4
      77: invokespecial #134                // Method org/apache/hadoop/hbase/replication/regionserver/MetricsReplicationGlobalSourceSource."<init>":(Lorg/apache/hadoop/hbase/replication/regionserver/MetricsReplicationSourceImpl;)V
      80: astore        6
      82: aload         6
      84: invokestatic  #135                // Method org/mockito/Mockito.spy:(Ljava/lang/Object;)Ljava/lang/Object;
      87: checkcast     #136                // class org/apache/hadoop/hbase/replication/regionserver/MetricsReplicationSourceSource
      90: astore        7
      92: invokestatic  #137                // Method org/mockito/Mockito.doNothing:()Lorg/mockito/stubbing/Stubber;
      95: aload         7
      97: invokeinterface #138,  2          // InterfaceMethod org/mockito/stubbing/Stubber.when:(Ljava/lang/Object;)Ljava/lang/Object;
     102: checkcast     #136                // class org/apache/hadoop/hbase/replication/regionserver/MetricsReplicationSourceSource
     105: invokeinterface #139,  1          // InterfaceMethod org/apache/hadoop/hbase/replication/regionserver/MetricsReplicationSourceSource.incrFailedRecoveryQueue:()V
     110: new           #140                // class java/util/HashMap
     113: dup
     114: invokespecial #141                // Method java/util/HashMap."<init>":()V
     117: astore        8
     119: new           #142                // class org/apache/hadoop/hbase/replication/regionserver/MetricsSource
     122: dup
     123: aload_1
     124: aload         5
     126: aload         7
     128: aload         8
     130: invokespecial #143                // Method org/apache/hadoop/hbase/replication/regionserver/MetricsSource."<init>":(Ljava/lang/String;Lorg/apache/hadoop/hbase/replication/regionserver/MetricsReplicationSourceSource;Lorg/apache/hadoop/hbase/replication/regionserver/MetricsReplicationSourceSource;Ljava/util/Map;)V
     133: astore        9
     135: ldc           #144                // String gauge
     137: astore        10
     139: new           #64                 // class java/lang/StringBuilder
     142: dup
     143: invokespecial #65                 // Method java/lang/StringBuilder."<init>":()V
     146: ldc           #145                // String source.id.
     148: invokevirtual #67                 // Method java/lang/StringBuilder.append:(Ljava/lang/String;)Ljava/lang/StringBuilder;
     151: aload         10
     153: invokevirtual #67                 // Method java/lang/StringBuilder.append:(Ljava/lang/String;)Ljava/lang/StringBuilder;
     156: invokevirtual #69                 // Method java/lang/StringBuilder.toString:()Ljava/lang/String;
     159: astore        11
     161: new           #64                 // class java/lang/StringBuilder
     164: dup
     165: invokespecial #65                 // Method java/lang/StringBuilder."<init>":()V
     168: ldc           #146                // String source.
     170: invokevirtual #67                 // Method java/lang/StringBuilder.append:(Ljava/lang/String;)Ljava/lang/StringBuilder;
     173: aload         10
     175: invokevirtual #67                 // Method java/lang/StringBuilder.append:(Ljava/lang/String;)Ljava/lang/StringBuilder;
     178: invokevirtual #69                 // Method java/lang/StringBuilder.toString:()Ljava/lang/String;
     181: astore        12
     183: lconst_1
     184: lstore        13
     186: ldc           #147                // String counter
     188: astore        15
     190: new           #64                 // class java/lang/StringBuilder
     193: dup
     194: invokespecial #65                 // Method java/lang/StringBuilder."<init>":()V
     197: ldc           #145                // String source.id.
     199: invokevirtual #67                 // Method java/lang/StringBuilder.append:(Ljava/lang/String;)Ljava/lang/StringBuilder;
     202: aload         15
     204: invokevirtual #67                 // Method java/lang/StringBuilder.append:(Ljava/lang/String;)Ljava/lang/StringBuilder;
     207: invokevirtual #69                 // Method java/lang/StringBuilder.toString:()Ljava/lang/String;
     210: astore        16
     212: new           #64                 // class java/lang/StringBuilder
     215: dup
     216: invokespecial #65                 // Method java/lang/StringBuilder."<init>":()V
     219: ldc           #146                // String source.
     221: invokevirtual #67                 // Method java/lang/StringBuilder.append:(Ljava/lang/String;)Ljava/lang/StringBuilder;
     224: aload         15
     226: invokevirtual #67                 // Method java/lang/StringBuilder.append:(Ljava/lang/String;)Ljava/lang/StringBuilder;
     229: invokevirtual #69                 // Method java/lang/StringBuilder.toString:()Ljava/lang/String;
     232: astore        17
     234: ldc2_w        #148                // long 2l
     237: lstore        18
     239: aload         9
     241: aload         10
     243: lload         13
     245: invokevirtual #150                // Method org/apache/hadoop/hbase/replication/regionserver/MetricsSource.decGauge:(Ljava/lang/String;J)V
     248: aload         9
     250: invokevirtual #151                // Method org/apache/hadoop/hbase/replication/regionserver/MetricsSource.getMetricsContext:()Ljava/lang/String;
     253: pop
     254: aload         9
     256: invokevirtual #152                // Method org/apache/hadoop/hbase/replication/regionserver/MetricsSource.getMetricsDescription:()Ljava/lang/String;
     259: pop
     260: aload         9
     262: invokevirtual #153                // Method org/apache/hadoop/hbase/replication/regionserver/MetricsSource.getMetricsJmxContext:()Ljava/lang/String;
     265: pop
     266: aload         9
     268: invokevirtual #154                // Method org/apache/hadoop/hbase/replication/regionserver/MetricsSource.getMetricsName:()Ljava/lang/String;
     271: pop
     272: aload         9
     274: aload         15
     276: lload         18
     278: invokevirtual #155                // Method org/apache/hadoop/hbase/replication/regionserver/MetricsSource.incCounters:(Ljava/lang/String;J)V
     281: aload         9
     283: aload         10
     285: lload         13
     287: invokevirtual #156                // Method org/apache/hadoop/hbase/replication/regionserver/MetricsSource.incGauge:(Ljava/lang/String;J)V
     290: aload         9
     292: invokevirtual #157                // Method org/apache/hadoop/hbase/replication/regionserver/MetricsSource.init:()V
     295: aload         9
     297: aload         10
     299: invokevirtual #158                // Method org/apache/hadoop/hbase/replication/regionserver/MetricsSource.removeMetric:(Ljava/lang/String;)V
     302: aload         9
     304: aload         10
     306: lload         13
     308: invokevirtual #159                // Method org/apache/hadoop/hbase/replication/regionserver/MetricsSource.setGauge:(Ljava/lang/String;J)V
     311: aload         9
     313: aload         15
     315: lload         18
     317: invokevirtual #160                // Method org/apache/hadoop/hbase/replication/regionserver/MetricsSource.updateHistogram:(Ljava/lang/String;J)V
     320: aload         9
     322: invokevirtual #161                // Method org/apache/hadoop/hbase/replication/regionserver/MetricsSource.incrFailedRecoveryQueue:()V
     325: aload_3
     326: invokestatic  #162                // Method org/mockito/Mockito.verify:(Ljava/lang/Object;)Ljava/lang/Object;
     329: checkcast     #127                // class org/apache/hadoop/hbase/replication/regionserver/MetricsReplicationSourceImpl
     332: aload         11
     334: lload         13
     336: invokevirtual #163                // Method org/apache/hadoop/hbase/replication/regionserver/MetricsReplicationSourceImpl.decGauge:(Ljava/lang/String;J)V
     339: aload         4
     341: invokestatic  #162                // Method org/mockito/Mockito.verify:(Ljava/lang/Object;)Ljava/lang/Object;
     344: checkcast     #127                // class org/apache/hadoop/hbase/replication/regionserver/MetricsReplicationSourceImpl
     347: aload         12
     349: lload         13
     351: invokevirtual #163                // Method org/apache/hadoop/hbase/replication/regionserver/MetricsReplicationSourceImpl.decGauge:(Ljava/lang/String;J)V
     354: aload         4
     356: invokestatic  #162                // Method org/mockito/Mockito.verify:(Ljava/lang/Object;)Ljava/lang/Object;
     359: checkcast     #127                // class org/apache/hadoop/hbase/replication/regionserver/MetricsReplicationSourceImpl
     362: invokevirtual #164                // Method org/apache/hadoop/hbase/replication/regionserver/MetricsReplicationSourceImpl.getMetricsContext:()Ljava/lang/String;
     365: pop
     366: aload         4
     368: invokestatic  #162                // Method org/mockito/Mockito.verify:(Ljava/lang/Object;)Ljava/lang/Object;
     371: checkcast     #127                // class org/apache/hadoop/hbase/replication/regionserver/MetricsReplicationSourceImpl
     374: invokevirtual #165                // Method org/apache/hadoop/hbase/replication/regionserver/MetricsReplicationSourceImpl.getMetricsJmxContext:()Ljava/lang/String;
     377: pop
     378: aload         4
     380: invokestatic  #162                // Method org/mockito/Mockito.verify:(Ljava/lang/Object;)Ljava/lang/Object;
     383: checkcast     #127                // class org/apache/hadoop/hbase/replication/regionserver/MetricsReplicationSourceImpl
     386: invokevirtual #166                // Method org/apache/hadoop/hbase/replication/regionserver/MetricsReplicationSourceImpl.getMetricsName:()Ljava/lang/String;
     389: pop
     390: aload_3
     391: invokestatic  #162                // Method org/mockito/Mockito.verify:(Ljava/lang/Object;)Ljava/lang/Object;
     394: checkcast     #127                // class org/apache/hadoop/hbase/replication/regionserver/MetricsReplicationSourceImpl
     397: aload         16
     399: lload         18
     401: invokevirtual #167                // Method org/apache/hadoop/hbase/replication/regionserver/MetricsReplicationSourceImpl.incCounters:(Ljava/lang/String;J)V
     404: aload         4
     406: invokestatic  #162                // Method org/mockito/Mockito.verify:(Ljava/lang/Object;)Ljava/lang/Object;
     409: checkcast     #127                // class org/apache/hadoop/hbase/replication/regionserver/MetricsReplicationSourceImpl
     412: aload         17
     414: lload         18
     416: invokevirtual #167                // Method org/apache/hadoop/hbase/replication/regionserver/MetricsReplicationSourceImpl.incCounters:(Ljava/lang/String;J)V
     419: aload_3
     420: invokestatic  #162                // Method org/mockito/Mockito.verify:(Ljava/lang/Object;)Ljava/lang/Object;
     423: checkcast     #127                // class org/apache/hadoop/hbase/replication/regionserver/MetricsReplicationSourceImpl
     426: aload         11
     428: lload         13
     430: invokevirtual #168                // Method org/apache/hadoop/hbase/replication/regionserver/MetricsReplicationSourceImpl.incGauge:(Ljava/lang/String;J)V
     433: aload         4
     435: invokestatic  #162                // Method org/mockito/Mockito.verify:(Ljava/lang/Object;)Ljava/lang/Object;
     438: checkcast     #127                // class org/apache/hadoop/hbase/replication/regionserver/MetricsReplicationSourceImpl
     441: aload         12
     443: lload         13
     445: invokevirtual #168                // Method org/apache/hadoop/hbase/replication/regionserver/MetricsReplicationSourceImpl.incGauge:(Ljava/lang/String;J)V
     448: aload         4
     450: invokestatic  #162                // Method org/mockito/Mockito.verify:(Ljava/lang/Object;)Ljava/lang/Object;
     453: checkcast     #127                // class org/apache/hadoop/hbase/replication/regionserver/MetricsReplicationSourceImpl
     456: invokevirtual #169                // Method org/apache/hadoop/hbase/replication/regionserver/MetricsReplicationSourceImpl.init:()V
     459: aload_3
     460: invokestatic  #162                // Method org/mockito/Mockito.verify:(Ljava/lang/Object;)Ljava/lang/Object;
     463: checkcast     #127                // class org/apache/hadoop/hbase/replication/regionserver/MetricsReplicationSourceImpl
     466: aload         11
     468: invokevirtual #170                // Method org/apache/hadoop/hbase/replication/regionserver/MetricsReplicationSourceImpl.removeMetric:(Ljava/lang/String;)V
     471: aload         4
     473: invokestatic  #162                // Method org/mockito/Mockito.verify:(Ljava/lang/Object;)Ljava/lang/Object;
     476: checkcast     #127                // class org/apache/hadoop/hbase/replication/regionserver/MetricsReplicationSourceImpl
     479: aload         12
     481: invokevirtual #170                // Method org/apache/hadoop/hbase/replication/regionserver/MetricsReplicationSourceImpl.removeMetric:(Ljava/lang/String;)V
     484: aload_3
     485: invokestatic  #162                // Method org/mockito/Mockito.verify:(Ljava/lang/Object;)Ljava/lang/Object;
     488: checkcast     #127                // class org/apache/hadoop/hbase/replication/regionserver/MetricsReplicationSourceImpl
     491: aload         11
     493: lload         13
     495: invokevirtual #171                // Method org/apache/hadoop/hbase/replication/regionserver/MetricsReplicationSourceImpl.setGauge:(Ljava/lang/String;J)V
     498: aload         4
     500: invokestatic  #162                // Method org/mockito/Mockito.verify:(Ljava/lang/Object;)Ljava/lang/Object;
     503: checkcast     #127                // class org/apache/hadoop/hbase/replication/regionserver/MetricsReplicationSourceImpl
     506: aload         12
     508: lload         13
     510: invokevirtual #171                // Method org/apache/hadoop/hbase/replication/regionserver/MetricsReplicationSourceImpl.setGauge:(Ljava/lang/String;J)V
     513: aload_3
     514: invokestatic  #162                // Method org/mockito/Mockito.verify:(Ljava/lang/Object;)Ljava/lang/Object;
     517: checkcast     #127                // class org/apache/hadoop/hbase/replication/regionserver/MetricsReplicationSourceImpl
     520: aload         16
     522: lload         18
     524: invokevirtual #172                // Method org/apache/hadoop/hbase/replication/regionserver/MetricsReplicationSourceImpl.updateHistogram:(Ljava/lang/String;J)V
     527: aload         4
     529: invokestatic  #162                // Method org/mockito/Mockito.verify:(Ljava/lang/Object;)Ljava/lang/Object;
     532: checkcast     #127                // class org/apache/hadoop/hbase/replication/regionserver/MetricsReplicationSourceImpl
     535: aload         17
     537: lload         18
     539: invokevirtual #172                // Method org/apache/hadoop/hbase/replication/regionserver/MetricsReplicationSourceImpl.updateHistogram:(Ljava/lang/String;J)V
     542: aload         7
     544: invokestatic  #162                // Method org/mockito/Mockito.verify:(Ljava/lang/Object;)Ljava/lang/Object;
     547: checkcast     #136                // class org/apache/hadoop/hbase/replication/regionserver/MetricsReplicationSourceSource
     550: invokeinterface #139,  1          // InterfaceMethod org/apache/hadoop/hbase/replication/regionserver/MetricsReplicationSourceSource.incrFailedRecoveryQueue:()V
     555: aload         9
     557: invokevirtual #173                // Method org/apache/hadoop/hbase/replication/regionserver/MetricsSource.getSingleSourceSourceByTable:()Ljava/util/Map;
     560: ldc           #174                // String RandomNewTable
     562: invokeinterface #175,  2          // InterfaceMethod java/util/Map.containsKey:(Ljava/lang/Object;)Z
     567: istore        20
     569: iconst_0
     570: invokestatic  #176                // Method java/lang/Boolean.valueOf:(Z)Ljava/lang/Boolean;
     573: iload         20
     575: invokestatic  #176                // Method java/lang/Boolean.valueOf:(Z)Ljava/lang/Boolean;
     578: invokestatic  #177                // Method org/junit/Assert.assertEquals:(Ljava/lang/Object;Ljava/lang/Object;)V
     581: aload         9
     583: ldc2_w        #178                // long 123l
     586: ldc           #174                // String RandomNewTable
     588: invokevirtual #180                // Method org/apache/hadoop/hbase/replication/regionserver/MetricsSource.setAgeOfLastShippedOpByTable:(JLjava/lang/String;)V
     591: aload         9
     593: invokevirtual #173                // Method org/apache/hadoop/hbase/replication/regionserver/MetricsSource.getSingleSourceSourceByTable:()Ljava/util/Map;
     596: ldc           #174                // String RandomNewTable
     598: invokeinterface #175,  2          // InterfaceMethod java/util/Map.containsKey:(Ljava/lang/Object;)Z
     603: istore        20
     605: iconst_1
     606: invokestatic  #176                // Method java/lang/Boolean.valueOf:(Z)Ljava/lang/Boolean;
     609: iload         20
     611: invokestatic  #176                // Method java/lang/Boolean.valueOf:(Z)Ljava/lang/Boolean;
     614: invokestatic  #177                // Method org/junit/Assert.assertEquals:(Ljava/lang/Object;Ljava/lang/Object;)V
     617: aload         9
     619: invokevirtual #173                // Method org/apache/hadoop/hbase/replication/regionserver/MetricsSource.getSingleSourceSourceByTable:()Ljava/util/Map;
     622: ldc           #174                // String RandomNewTable
     624: invokeinterface #181,  2          // InterfaceMethod java/util/Map.get:(Ljava/lang/Object;)Ljava/lang/Object;
     629: checkcast     #136                // class org/apache/hadoop/hbase/replication/regionserver/MetricsReplicationSourceSource
     632: astore        21
     634: aload         21
     636: invokeinterface #182,  1          // InterfaceMethod org/apache/hadoop/hbase/replication/regionserver/MetricsReplicationSourceSource.getLastShippedAge:()J
     641: lconst_0
     642: lcmp
     643: ifle          650
     646: iconst_1
     647: goto          651
     650: iconst_0
     651: invokestatic  #13                 // Method org/junit/Assert.assertTrue:(Z)V
     654: return

  static org.slf4j.Logger access$000();
    Code:
       0: getstatic     #2                  // Field LOG:Lorg/slf4j/Logger;
       3: areturn

  static void access$100(byte[]) throws java.lang.Exception;
    Code:
       0: aload_0
       1: invokestatic  #1                  // Method doAssert:([B)V
       4: return

  static {};
    Code:
       0: ldc           #195                // class org/apache/hadoop/hbase/replication/TestReplicationEndpoint
       2: invokestatic  #196                // Method org/apache/hadoop/hbase/HBaseClassTestRule.forClass:(Ljava/lang/Class;)Lorg/apache/hadoop/hbase/HBaseClassTestRule;
       5: putstatic     #197                // Field CLASS_RULE:Lorg/apache/hadoop/hbase/HBaseClassTestRule;
       8: ldc           #195                // class org/apache/hadoop/hbase/replication/TestReplicationEndpoint
      10: invokestatic  #198                // Method org/slf4j/LoggerFactory.getLogger:(Ljava/lang/Class;)Lorg/slf4j/Logger;
      13: putstatic     #2                  // Field LOG:Lorg/slf4j/Logger;
      16: return
}
