Compiled from "TestUnion2.java"
class org.apache.hadoop.hbase.types.TestUnion2$SampleUnion1 extends org.apache.hadoop.hbase.types.Union2<java.lang.Integer, java.lang.String> {
  public org.apache.hadoop.hbase.types.TestUnion2$SampleUnion1();
    Code:
       0: aload_0
       1: new           #1                  // class org/apache/hadoop/hbase/types/RawInteger
       4: dup
       5: invokespecial #2                  // Method org/apache/hadoop/hbase/types/RawInteger."<init>":()V
       8: new           #3                  // class org/apache/hadoop/hbase/types/RawStringTerminated
      11: dup
      12: getstatic     #4                  // Field org/apache/hadoop/hbase/util/Order.DESCENDING:Lorg/apache/hadoop/hbase/util/Order;
      15: ldc           #5                  // String .
      17: invokespecial #6                  // Method org/apache/hadoop/hbase/types/RawStringTerminated."<init>":(Lorg/apache/hadoop/hbase/util/Order;Ljava/lang/String;)V
      20: invokespecial #7                  // Method org/apache/hadoop/hbase/types/Union2."<init>":(Lorg/apache/hadoop/hbase/types/DataType;Lorg/apache/hadoop/hbase/types/DataType;)V
      23: return

  public int skip(org.apache.hadoop.hbase.util.PositionedByteRange);
    Code:
       0: aload_1
       1: invokeinterface #8,  1            // InterfaceMethod org/apache/hadoop/hbase/util/PositionedByteRange.get:()B
       6: lookupswitch  { // 2
                     0: 32
                     1: 45
               default: 58
          }
      32: iconst_1
      33: aload_0
      34: getfield      #9                  // Field typeA:Lorg/apache/hadoop/hbase/types/DataType;
      37: aload_1
      38: invokeinterface #10,  2           // InterfaceMethod org/apache/hadoop/hbase/types/DataType.skip:(Lorg/apache/hadoop/hbase/util/PositionedByteRange;)I
      43: iadd
      44: ireturn
      45: iconst_1
      46: aload_0
      47: getfield      #11                 // Field typeB:Lorg/apache/hadoop/hbase/types/DataType;
      50: aload_1
      51: invokeinterface #10,  2           // InterfaceMethod org/apache/hadoop/hbase/types/DataType.skip:(Lorg/apache/hadoop/hbase/util/PositionedByteRange;)I
      56: iadd
      57: ireturn
      58: new           #12                 // class java/lang/IllegalArgumentException
      61: dup
      62: ldc           #13                 // String Unrecognized encoding format.
      64: invokespecial #14                 // Method java/lang/IllegalArgumentException."<init>":(Ljava/lang/String;)V
      67: athrow

  public java.lang.Object decode(org.apache.hadoop.hbase.util.PositionedByteRange);
    Code:
       0: aload_1
       1: invokeinterface #8,  1            // InterfaceMethod org/apache/hadoop/hbase/util/PositionedByteRange.get:()B
       6: lookupswitch  { // 2
                     0: 32
                     1: 43
               default: 54
          }
      32: aload_0
      33: getfield      #9                  // Field typeA:Lorg/apache/hadoop/hbase/types/DataType;
      36: aload_1
      37: invokeinterface #15,  2           // InterfaceMethod org/apache/hadoop/hbase/types/DataType.decode:(Lorg/apache/hadoop/hbase/util/PositionedByteRange;)Ljava/lang/Object;
      42: areturn
      43: aload_0
      44: getfield      #11                 // Field typeB:Lorg/apache/hadoop/hbase/types/DataType;
      47: aload_1
      48: invokeinterface #15,  2           // InterfaceMethod org/apache/hadoop/hbase/types/DataType.decode:(Lorg/apache/hadoop/hbase/util/PositionedByteRange;)Ljava/lang/Object;
      53: areturn
      54: new           #12                 // class java/lang/IllegalArgumentException
      57: dup
      58: ldc           #13                 // String Unrecognized encoding format.
      60: invokespecial #14                 // Method java/lang/IllegalArgumentException."<init>":(Ljava/lang/String;)V
      63: athrow

  public int encodedLength(java.lang.Object);
    Code:
       0: aconst_null
       1: astore_2
       2: aconst_null
       3: astore_3
       4: aload_1
       5: checkcast     #16                 // class java/lang/Integer
       8: astore_2
       9: goto          14
      12: astore        4
      14: aload_1
      15: checkcast     #18                 // class java/lang/String
      18: astore_3
      19: goto          24
      22: astore        4
      24: aconst_null
      25: aload_2
      26: if_acmpeq     42
      29: iconst_1
      30: aload_0
      31: getfield      #9                  // Field typeA:Lorg/apache/hadoop/hbase/types/DataType;
      34: aload_2
      35: invokeinterface #19,  2           // InterfaceMethod org/apache/hadoop/hbase/types/DataType.encodedLength:(Ljava/lang/Object;)I
      40: iadd
      41: ireturn
      42: aconst_null
      43: aload_3
      44: if_acmpeq     60
      47: iconst_1
      48: aload_0
      49: getfield      #11                 // Field typeB:Lorg/apache/hadoop/hbase/types/DataType;
      52: aload_3
      53: invokeinterface #19,  2           // InterfaceMethod org/apache/hadoop/hbase/types/DataType.encodedLength:(Ljava/lang/Object;)I
      58: iadd
      59: ireturn
      60: new           #12                 // class java/lang/IllegalArgumentException
      63: dup
      64: ldc           #20                 // String val is not a valid member of this union.
      66: invokespecial #14                 // Method java/lang/IllegalArgumentException."<init>":(Ljava/lang/String;)V
      69: athrow
    Exception table:
       from    to  target type
           4     9    12   Class java/lang/ClassCastException
          14    19    22   Class java/lang/ClassCastException

  public int encode(org.apache.hadoop.hbase.util.PositionedByteRange, java.lang.Object);
    Code:
       0: aconst_null
       1: astore_3
       2: aconst_null
       3: astore        4
       5: aload_2
       6: checkcast     #16                 // class java/lang/Integer
       9: astore_3
      10: goto          15
      13: astore        5
      15: aload_2
      16: checkcast     #18                 // class java/lang/String
      19: astore        4
      21: goto          26
      24: astore        5
      26: aconst_null
      27: aload_3
      28: if_acmpeq     53
      31: aload_1
      32: iconst_0
      33: invokeinterface #22,  2           // InterfaceMethod org/apache/hadoop/hbase/util/PositionedByteRange.put:(B)Lorg/apache/hadoop/hbase/util/PositionedByteRange;
      38: pop
      39: iconst_1
      40: aload_0
      41: getfield      #9                  // Field typeA:Lorg/apache/hadoop/hbase/types/DataType;
      44: aload_1
      45: aload_3
      46: invokeinterface #23,  3           // InterfaceMethod org/apache/hadoop/hbase/types/DataType.encode:(Lorg/apache/hadoop/hbase/util/PositionedByteRange;Ljava/lang/Object;)I
      51: iadd
      52: ireturn
      53: aconst_null
      54: aload         4
      56: if_acmpeq     82
      59: aload_1
      60: iconst_1
      61: invokeinterface #22,  2           // InterfaceMethod org/apache/hadoop/hbase/util/PositionedByteRange.put:(B)Lorg/apache/hadoop/hbase/util/PositionedByteRange;
      66: pop
      67: iconst_1
      68: aload_0
      69: getfield      #11                 // Field typeB:Lorg/apache/hadoop/hbase/types/DataType;
      72: aload_1
      73: aload         4
      75: invokeinterface #23,  3           // InterfaceMethod org/apache/hadoop/hbase/types/DataType.encode:(Lorg/apache/hadoop/hbase/util/PositionedByteRange;Ljava/lang/Object;)I
      80: iadd
      81: ireturn
      82: new           #12                 // class java/lang/IllegalArgumentException
      85: dup
      86: ldc           #24                 // String val is not of a supported type.
      88: invokespecial #14                 // Method java/lang/IllegalArgumentException."<init>":(Ljava/lang/String;)V
      91: athrow
    Exception table:
       from    to  target type
           5    10    13   Class java/lang/ClassCastException
          15    21    24   Class java/lang/ClassCastException
}
