Compiled from "TestProcedureRecovery.java"
public class org.apache.hadoop.hbase.procedure2.TestProcedureRecovery$TestStateMachineProcedure extends org.apache.hadoop.hbase.procedure2.StateMachineProcedure<org.apache.hadoop.hbase.procedure2.TestProcedureRecovery$TestProcEnv, org.apache.hadoop.hbase.procedure2.TestProcedureRecovery$TestStateMachineProcedure$State> {
  public org.apache.hadoop.hbase.procedure2.TestProcedureRecovery$TestStateMachineProcedure();
    Code:
       0: aload_0
       1: invokespecial #1                  // Method org/apache/hadoop/hbase/procedure2/StateMachineProcedure."<init>":()V
       4: aload_0
       5: new           #2                  // class java/util/concurrent/atomic/AtomicBoolean
       8: dup
       9: iconst_0
      10: invokespecial #3                  // Method java/util/concurrent/atomic/AtomicBoolean."<init>":(Z)V
      13: putfield      #4                  // Field aborted:Ljava/util/concurrent/atomic/AtomicBoolean;
      16: aload_0
      17: iconst_0
      18: putfield      #5                  // Field iResult:I
      21: aload_0
      22: iconst_0
      23: putfield      #6                  // Field submitChildProc:Z
      26: return

  public org.apache.hadoop.hbase.procedure2.TestProcedureRecovery$TestStateMachineProcedure(boolean);
    Code:
       0: aload_0
       1: invokespecial #1                  // Method org/apache/hadoop/hbase/procedure2/StateMachineProcedure."<init>":()V
       4: aload_0
       5: new           #2                  // class java/util/concurrent/atomic/AtomicBoolean
       8: dup
       9: iconst_0
      10: invokespecial #3                  // Method java/util/concurrent/atomic/AtomicBoolean."<init>":(Z)V
      13: putfield      #4                  // Field aborted:Ljava/util/concurrent/atomic/AtomicBoolean;
      16: aload_0
      17: iconst_0
      18: putfield      #5                  // Field iResult:I
      21: aload_0
      22: iconst_0
      23: putfield      #6                  // Field submitChildProc:Z
      26: aload_0
      27: iload_1
      28: putfield      #6                  // Field submitChildProc:Z
      31: return

  protected org.apache.hadoop.hbase.procedure2.StateMachineProcedure$Flow executeFromState(org.apache.hadoop.hbase.procedure2.TestProcedureRecovery$TestProcEnv, org.apache.hadoop.hbase.procedure2.TestProcedureRecovery$TestStateMachineProcedure$State);
    Code:
       0: getstatic     #7                  // Field org/apache/hadoop/hbase/procedure2/TestProcedureRecovery$1.$SwitchMap$org$apache$hadoop$hbase$procedure2$TestProcedureRecovery$TestStateMachineProcedure$State:[I
       3: aload_2
       4: invokevirtual #8                  // Method org/apache/hadoop/hbase/procedure2/TestProcedureRecovery$TestStateMachineProcedure$State.ordinal:()I
       7: iaload
       8: tableswitch   { // 1 to 4
                     1: 40
                     2: 87
                     3: 179
                     4: 282
               default: 333
          }
      40: invokestatic  #9                  // Method org/apache/hadoop/hbase/procedure2/TestProcedureRecovery.access$100:()Lorg/slf4j/Logger;
      43: new           #10                 // class java/lang/StringBuilder
      46: dup
      47: invokespecial #11                 // Method java/lang/StringBuilder."<init>":()V
      50: ldc           #12                 // String execute step 1
      52: invokevirtual #13                 // Method java/lang/StringBuilder.append:(Ljava/lang/String;)Ljava/lang/StringBuilder;
      55: aload_0
      56: invokevirtual #14                 // Method java/lang/StringBuilder.append:(Ljava/lang/Object;)Ljava/lang/StringBuilder;
      59: invokevirtual #15                 // Method java/lang/StringBuilder.toString:()Ljava/lang/String;
      62: invokeinterface #16,  2           // InterfaceMethod org/slf4j/Logger.info:(Ljava/lang/String;)V
      67: aload_0
      68: getstatic     #17                 // Field org/apache/hadoop/hbase/procedure2/TestProcedureRecovery$TestStateMachineProcedure$State.STATE_2:Lorg/apache/hadoop/hbase/procedure2/TestProcedureRecovery$TestStateMachineProcedure$State;
      71: invokevirtual #18                 // Method setNextState:(Ljava/lang/Object;)V
      74: aload_0
      75: dup
      76: getfield      #5                  // Field iResult:I
      79: iconst_3
      80: iadd
      81: putfield      #5                  // Field iResult:I
      84: goto          341
      87: invokestatic  #9                  // Method org/apache/hadoop/hbase/procedure2/TestProcedureRecovery.access$100:()Lorg/slf4j/Logger;
      90: new           #10                 // class java/lang/StringBuilder
      93: dup
      94: invokespecial #11                 // Method java/lang/StringBuilder."<init>":()V
      97: ldc           #19                 // String execute step 2
      99: invokevirtual #13                 // Method java/lang/StringBuilder.append:(Ljava/lang/String;)Ljava/lang/StringBuilder;
     102: aload_0
     103: invokevirtual #14                 // Method java/lang/StringBuilder.append:(Ljava/lang/Object;)Ljava/lang/StringBuilder;
     106: invokevirtual #15                 // Method java/lang/StringBuilder.toString:()Ljava/lang/String;
     109: invokeinterface #16,  2           // InterfaceMethod org/slf4j/Logger.info:(Ljava/lang/String;)V
     114: aload_0
     115: getfield      #6                  // Field submitChildProc:Z
     118: ifeq          159
     121: aload_0
     122: iconst_2
     123: anewarray     #20                 // class org/apache/hadoop/hbase/procedure2/TestProcedureRecovery$TestStateMachineProcedure
     126: dup
     127: iconst_0
     128: new           #20                 // class org/apache/hadoop/hbase/procedure2/TestProcedureRecovery$TestStateMachineProcedure
     131: dup
     132: invokespecial #21                 // Method "<init>":()V
     135: aastore
     136: dup
     137: iconst_1
     138: new           #20                 // class org/apache/hadoop/hbase/procedure2/TestProcedureRecovery$TestStateMachineProcedure
     141: dup
     142: invokespecial #21                 // Method "<init>":()V
     145: aastore
     146: invokevirtual #22                 // Method addChildProcedure:([Lorg/apache/hadoop/hbase/procedure2/Procedure;)V
     149: aload_0
     150: getstatic     #23                 // Field org/apache/hadoop/hbase/procedure2/TestProcedureRecovery$TestStateMachineProcedure$State.DONE:Lorg/apache/hadoop/hbase/procedure2/TestProcedureRecovery$TestStateMachineProcedure$State;
     153: invokevirtual #18                 // Method setNextState:(Ljava/lang/Object;)V
     156: goto          166
     159: aload_0
     160: getstatic     #24                 // Field org/apache/hadoop/hbase/procedure2/TestProcedureRecovery$TestStateMachineProcedure$State.STATE_3:Lorg/apache/hadoop/hbase/procedure2/TestProcedureRecovery$TestStateMachineProcedure$State;
     163: invokevirtual #18                 // Method setNextState:(Ljava/lang/Object;)V
     166: aload_0
     167: dup
     168: getfield      #5                  // Field iResult:I
     171: iconst_5
     172: iadd
     173: putfield      #5                  // Field iResult:I
     176: goto          341
     179: invokestatic  #9                  // Method org/apache/hadoop/hbase/procedure2/TestProcedureRecovery.access$100:()Lorg/slf4j/Logger;
     182: new           #10                 // class java/lang/StringBuilder
     185: dup
     186: invokespecial #11                 // Method java/lang/StringBuilder."<init>":()V
     189: ldc           #25                 // String execute step 3
     191: invokevirtual #13                 // Method java/lang/StringBuilder.append:(Ljava/lang/String;)Ljava/lang/StringBuilder;
     194: aload_0
     195: invokevirtual #14                 // Method java/lang/StringBuilder.append:(Ljava/lang/Object;)Ljava/lang/StringBuilder;
     198: invokevirtual #15                 // Method java/lang/StringBuilder.toString:()Ljava/lang/String;
     201: invokeinterface #16,  2           // InterfaceMethod org/slf4j/Logger.info:(Ljava/lang/String;)V
     206: invokestatic  #26                 // Method org/apache/hadoop/hbase/procedure2/TestProcedureRecovery.access$300:()I
     209: i2l
     210: invokestatic  #27                 // Method org/apache/hadoop/hbase/util/Threads.sleepWithoutInterrupt:(J)V
     213: aload_0
     214: getfield      #4                  // Field aborted:Ljava/util/concurrent/atomic/AtomicBoolean;
     217: invokevirtual #28                 // Method java/util/concurrent/atomic/AtomicBoolean.get:()Z
     220: ifeq          261
     223: invokestatic  #9                  // Method org/apache/hadoop/hbase/procedure2/TestProcedureRecovery.access$100:()Lorg/slf4j/Logger;
     226: new           #10                 // class java/lang/StringBuilder
     229: dup
     230: invokespecial #11                 // Method java/lang/StringBuilder."<init>":()V
     233: ldc           #29                 // String aborted step 3
     235: invokevirtual #13                 // Method java/lang/StringBuilder.append:(Ljava/lang/String;)Ljava/lang/StringBuilder;
     238: aload_0
     239: invokevirtual #14                 // Method java/lang/StringBuilder.append:(Ljava/lang/Object;)Ljava/lang/StringBuilder;
     242: invokevirtual #15                 // Method java/lang/StringBuilder.toString:()Ljava/lang/String;
     245: invokeinterface #16,  2           // InterfaceMethod org/slf4j/Logger.info:(Ljava/lang/String;)V
     250: aload_0
     251: ldc           #30                 // String test
     253: ldc           #31                 // String aborted
     255: invokevirtual #32                 // Method setAbortFailure:(Ljava/lang/String;Ljava/lang/String;)V
     258: goto          341
     261: aload_0
     262: getstatic     #23                 // Field org/apache/hadoop/hbase/procedure2/TestProcedureRecovery$TestStateMachineProcedure$State.DONE:Lorg/apache/hadoop/hbase/procedure2/TestProcedureRecovery$TestStateMachineProcedure$State;
     265: invokevirtual #18                 // Method setNextState:(Ljava/lang/Object;)V
     268: aload_0
     269: dup
     270: getfield      #5                  // Field iResult:I
     273: bipush        7
     275: iadd
     276: putfield      #5                  // Field iResult:I
     279: goto          341
     282: aload_0
     283: getfield      #6                  // Field submitChildProc:Z
     286: ifeq          307
     289: aload_0
     290: iconst_1
     291: anewarray     #20                 // class org/apache/hadoop/hbase/procedure2/TestProcedureRecovery$TestStateMachineProcedure
     294: dup
     295: iconst_0
     296: new           #20                 // class org/apache/hadoop/hbase/procedure2/TestProcedureRecovery$TestStateMachineProcedure
     299: dup
     300: invokespecial #21                 // Method "<init>":()V
     303: aastore
     304: invokevirtual #22                 // Method addChildProcedure:([Lorg/apache/hadoop/hbase/procedure2/Procedure;)V
     307: aload_0
     308: dup
     309: getfield      #5                  // Field iResult:I
     312: bipush        11
     314: iadd
     315: putfield      #5                  // Field iResult:I
     318: aload_0
     319: aload_0
     320: getfield      #5                  // Field iResult:I
     323: invokestatic  #33                 // Method org/apache/hadoop/hbase/util/Bytes.toBytes:(I)[B
     326: invokevirtual #34                 // Method setResult:([B)V
     329: getstatic     #35                 // Field org/apache/hadoop/hbase/procedure2/StateMachineProcedure$Flow.NO_MORE_STATE:Lorg/apache/hadoop/hbase/procedure2/StateMachineProcedure$Flow;
     332: areturn
     333: new           #36                 // class java/lang/UnsupportedOperationException
     336: dup
     337: invokespecial #37                 // Method java/lang/UnsupportedOperationException."<init>":()V
     340: athrow
     341: getstatic     #38                 // Field org/apache/hadoop/hbase/procedure2/StateMachineProcedure$Flow.HAS_MORE_STATE:Lorg/apache/hadoop/hbase/procedure2/StateMachineProcedure$Flow;
     344: areturn

  protected void rollbackState(org.apache.hadoop.hbase.procedure2.TestProcedureRecovery$TestProcEnv, org.apache.hadoop.hbase.procedure2.TestProcedureRecovery$TestStateMachineProcedure$State);
    Code:
       0: getstatic     #7                  // Field org/apache/hadoop/hbase/procedure2/TestProcedureRecovery$1.$SwitchMap$org$apache$hadoop$hbase$procedure2$TestProcedureRecovery$TestStateMachineProcedure$State:[I
       3: aload_2
       4: invokevirtual #8                  // Method org/apache/hadoop/hbase/procedure2/TestProcedureRecovery$TestStateMachineProcedure$State.ordinal:()I
       7: iaload
       8: tableswitch   { // 1 to 3
                     1: 36
                     2: 66
                     3: 96
               default: 126
          }
      36: invokestatic  #9                  // Method org/apache/hadoop/hbase/procedure2/TestProcedureRecovery.access$100:()Lorg/slf4j/Logger;
      39: new           #10                 // class java/lang/StringBuilder
      42: dup
      43: invokespecial #11                 // Method java/lang/StringBuilder."<init>":()V
      46: ldc           #39                 // String rollback step 1
      48: invokevirtual #13                 // Method java/lang/StringBuilder.append:(Ljava/lang/String;)Ljava/lang/StringBuilder;
      51: aload_0
      52: invokevirtual #14                 // Method java/lang/StringBuilder.append:(Ljava/lang/Object;)Ljava/lang/StringBuilder;
      55: invokevirtual #15                 // Method java/lang/StringBuilder.toString:()Ljava/lang/String;
      58: invokeinterface #16,  2           // InterfaceMethod org/slf4j/Logger.info:(Ljava/lang/String;)V
      63: goto          134
      66: invokestatic  #9                  // Method org/apache/hadoop/hbase/procedure2/TestProcedureRecovery.access$100:()Lorg/slf4j/Logger;
      69: new           #10                 // class java/lang/StringBuilder
      72: dup
      73: invokespecial #11                 // Method java/lang/StringBuilder."<init>":()V
      76: ldc           #40                 // String rollback step 2
      78: invokevirtual #13                 // Method java/lang/StringBuilder.append:(Ljava/lang/String;)Ljava/lang/StringBuilder;
      81: aload_0
      82: invokevirtual #14                 // Method java/lang/StringBuilder.append:(Ljava/lang/Object;)Ljava/lang/StringBuilder;
      85: invokevirtual #15                 // Method java/lang/StringBuilder.toString:()Ljava/lang/String;
      88: invokeinterface #16,  2           // InterfaceMethod org/slf4j/Logger.info:(Ljava/lang/String;)V
      93: goto          134
      96: invokestatic  #9                  // Method org/apache/hadoop/hbase/procedure2/TestProcedureRecovery.access$100:()Lorg/slf4j/Logger;
      99: new           #10                 // class java/lang/StringBuilder
     102: dup
     103: invokespecial #11                 // Method java/lang/StringBuilder."<init>":()V
     106: ldc           #41                 // String rollback step 3
     108: invokevirtual #13                 // Method java/lang/StringBuilder.append:(Ljava/lang/String;)Ljava/lang/StringBuilder;
     111: aload_0
     112: invokevirtual #14                 // Method java/lang/StringBuilder.append:(Ljava/lang/Object;)Ljava/lang/StringBuilder;
     115: invokevirtual #15                 // Method java/lang/StringBuilder.toString:()Ljava/lang/String;
     118: invokeinterface #16,  2           // InterfaceMethod org/slf4j/Logger.info:(Ljava/lang/String;)V
     123: goto          134
     126: new           #36                 // class java/lang/UnsupportedOperationException
     129: dup
     130: invokespecial #37                 // Method java/lang/UnsupportedOperationException."<init>":()V
     133: athrow
     134: return

  protected org.apache.hadoop.hbase.procedure2.TestProcedureRecovery$TestStateMachineProcedure$State getState(int);
    Code:
       0: invokestatic  #42                 // Method org/apache/hadoop/hbase/procedure2/TestProcedureRecovery$TestStateMachineProcedure$State.values:()[Lorg/apache/hadoop/hbase/procedure2/TestProcedureRecovery$TestStateMachineProcedure$State;
       3: iload_1
       4: aaload
       5: areturn

  protected int getStateId(org.apache.hadoop.hbase.procedure2.TestProcedureRecovery$TestStateMachineProcedure$State);
    Code:
       0: aload_1
       1: invokevirtual #8                  // Method org/apache/hadoop/hbase/procedure2/TestProcedureRecovery$TestStateMachineProcedure$State.ordinal:()I
       4: ireturn

  protected org.apache.hadoop.hbase.procedure2.TestProcedureRecovery$TestStateMachineProcedure$State getInitialState();
    Code:
       0: getstatic     #43                 // Field org/apache/hadoop/hbase/procedure2/TestProcedureRecovery$TestStateMachineProcedure$State.STATE_1:Lorg/apache/hadoop/hbase/procedure2/TestProcedureRecovery$TestStateMachineProcedure$State;
       3: areturn

  protected boolean abort(org.apache.hadoop.hbase.procedure2.TestProcedureRecovery$TestProcEnv);
    Code:
       0: aload_0
       1: getfield      #4                  // Field aborted:Ljava/util/concurrent/atomic/AtomicBoolean;
       4: iconst_1
       5: invokevirtual #44                 // Method java/util/concurrent/atomic/AtomicBoolean.set:(Z)V
       8: iconst_1
       9: ireturn

  protected void serializeStateData(org.apache.hadoop.hbase.procedure2.ProcedureStateSerializer) throws java.io.IOException;
    Code:
       0: aload_0
       1: aload_1
       2: invokespecial #45                 // Method org/apache/hadoop/hbase/procedure2/StateMachineProcedure.serializeStateData:(Lorg/apache/hadoop/hbase/procedure2/ProcedureStateSerializer;)V
       5: invokestatic  #46                 // Method org/apache/hbase/thirdparty/com/google/protobuf/Int32Value.newBuilder:()Lorg/apache/hbase/thirdparty/com/google/protobuf/Int32Value$Builder;
       8: aload_0
       9: getfield      #5                  // Field iResult:I
      12: invokevirtual #47                 // Method org/apache/hbase/thirdparty/com/google/protobuf/Int32Value$Builder.setValue:(I)Lorg/apache/hbase/thirdparty/com/google/protobuf/Int32Value$Builder;
      15: astore_2
      16: aload_1
      17: aload_2
      18: invokevirtual #48                 // Method org/apache/hbase/thirdparty/com/google/protobuf/Int32Value$Builder.build:()Lorg/apache/hbase/thirdparty/com/google/protobuf/Int32Value;
      21: invokeinterface #49,  2           // InterfaceMethod org/apache/hadoop/hbase/procedure2/ProcedureStateSerializer.serialize:(Lorg/apache/hbase/thirdparty/com/google/protobuf/Message;)V
      26: return

  protected void deserializeStateData(org.apache.hadoop.hbase.procedure2.ProcedureStateSerializer) throws java.io.IOException;
    Code:
       0: aload_0
       1: aload_1
       2: invokespecial #50                 // Method org/apache/hadoop/hbase/procedure2/StateMachineProcedure.deserializeStateData:(Lorg/apache/hadoop/hbase/procedure2/ProcedureStateSerializer;)V
       5: aload_1
       6: ldc           #51                 // class org/apache/hbase/thirdparty/com/google/protobuf/Int32Value
       8: invokeinterface #52,  2           // InterfaceMethod org/apache/hadoop/hbase/procedure2/ProcedureStateSerializer.deserialize:(Ljava/lang/Class;)Lorg/apache/hbase/thirdparty/com/google/protobuf/Message;
      13: checkcast     #51                 // class org/apache/hbase/thirdparty/com/google/protobuf/Int32Value
      16: astore_2
      17: aload_0
      18: aload_2
      19: invokevirtual #53                 // Method org/apache/hbase/thirdparty/com/google/protobuf/Int32Value.getValue:()I
      22: putfield      #5                  // Field iResult:I
      25: return

  protected boolean abort(java.lang.Object);
    Code:
       0: aload_0
       1: aload_1
       2: checkcast     #54                 // class org/apache/hadoop/hbase/procedure2/TestProcedureRecovery$TestProcEnv
       5: invokevirtual #55                 // Method abort:(Lorg/apache/hadoop/hbase/procedure2/TestProcedureRecovery$TestProcEnv;)Z
       8: ireturn

  protected java.lang.Object getInitialState();
    Code:
       0: aload_0
       1: invokevirtual #56                 // Method getInitialState:()Lorg/apache/hadoop/hbase/procedure2/TestProcedureRecovery$TestStateMachineProcedure$State;
       4: areturn

  protected int getStateId(java.lang.Object);
    Code:
       0: aload_0
       1: aload_1
       2: checkcast     #57                 // class org/apache/hadoop/hbase/procedure2/TestProcedureRecovery$TestStateMachineProcedure$State
       5: invokevirtual #58                 // Method getStateId:(Lorg/apache/hadoop/hbase/procedure2/TestProcedureRecovery$TestStateMachineProcedure$State;)I
       8: ireturn

  protected java.lang.Object getState(int);
    Code:
       0: aload_0
       1: iload_1
       2: invokevirtual #59                 // Method getState:(I)Lorg/apache/hadoop/hbase/procedure2/TestProcedureRecovery$TestStateMachineProcedure$State;
       5: areturn

  protected void rollbackState(java.lang.Object, java.lang.Object) throws java.io.IOException, java.lang.InterruptedException;
    Code:
       0: aload_0
       1: aload_1
       2: checkcast     #54                 // class org/apache/hadoop/hbase/procedure2/TestProcedureRecovery$TestProcEnv
       5: aload_2
       6: checkcast     #57                 // class org/apache/hadoop/hbase/procedure2/TestProcedureRecovery$TestStateMachineProcedure$State
       9: invokevirtual #60                 // Method rollbackState:(Lorg/apache/hadoop/hbase/procedure2/TestProcedureRecovery$TestProcEnv;Lorg/apache/hadoop/hbase/procedure2/TestProcedureRecovery$TestStateMachineProcedure$State;)V
      12: return

  protected org.apache.hadoop.hbase.procedure2.StateMachineProcedure$Flow executeFromState(java.lang.Object, java.lang.Object) throws org.apache.hadoop.hbase.procedure2.ProcedureSuspendedException, org.apache.hadoop.hbase.procedure2.ProcedureYieldException, java.lang.InterruptedException;
    Code:
       0: aload_0
       1: aload_1
       2: checkcast     #54                 // class org/apache/hadoop/hbase/procedure2/TestProcedureRecovery$TestProcEnv
       5: aload_2
       6: checkcast     #57                 // class org/apache/hadoop/hbase/procedure2/TestProcedureRecovery$TestStateMachineProcedure$State
       9: invokevirtual #61                 // Method executeFromState:(Lorg/apache/hadoop/hbase/procedure2/TestProcedureRecovery$TestProcEnv;Lorg/apache/hadoop/hbase/procedure2/TestProcedureRecovery$TestStateMachineProcedure$State;)Lorg/apache/hadoop/hbase/procedure2/StateMachineProcedure$Flow;
      12: areturn
}
