Compiled from "TestAsyncRegistryLeak.java"
public final class org.apache.hadoop.hbase.client.TestAsyncRegistryLeak$AsyncRegistryForTest extends org.apache.hadoop.hbase.client.DoNothingAsyncRegistry {
  public org.apache.hadoop.hbase.client.TestAsyncRegistryLeak$AsyncRegistryForTest(org.apache.hadoop.conf.Configuration);
    Code:
       0: aload_0
       1: aload_1
       2: invokespecial #2                  // Method org/apache/hadoop/hbase/client/DoNothingAsyncRegistry."<init>":(Lorg/apache/hadoop/conf/Configuration;)V
       5: aload_0
       6: iconst_0
       7: putfield      #1                  // Field closed:Z
      10: invokestatic  #3                  // Method org/apache/hadoop/hbase/client/TestAsyncRegistryLeak.access$000:()Ljava/util/List;
      13: aload_0
      14: invokeinterface #4,  2            // InterfaceMethod java/util/List.add:(Ljava/lang/Object;)Z
      19: pop
      20: return

  public java.util.concurrent.CompletableFuture<java.lang.String> getClusterId();
    Code:
       0: new           #5                  // class java/io/IOException
       3: dup
       4: ldc           #6                  // String inject error
       6: invokespecial #7                  // Method java/io/IOException."<init>":(Ljava/lang/String;)V
       9: invokestatic  #8                  // Method org/apache/hadoop/hbase/util/FutureUtils.failedFuture:(Ljava/lang/Throwable;)Ljava/util/concurrent/CompletableFuture;
      12: areturn

  public void close();
    Code:
       0: aload_0
       1: iconst_1
       2: putfield      #1                  // Field closed:Z
       5: return

  public java.util.concurrent.CompletableFuture getMasterInfoPort();
    Code:
       0: aload_0
       1: invokespecial #9                  // Method org/apache/hadoop/hbase/client/DoNothingAsyncRegistry.getMasterInfoPort:()Ljava/util/concurrent/CompletableFuture;
       4: areturn

  public java.util.concurrent.CompletableFuture getMasterAddress();
    Code:
       0: aload_0
       1: invokespecial #10                 // Method org/apache/hadoop/hbase/client/DoNothingAsyncRegistry.getMasterAddress:()Ljava/util/concurrent/CompletableFuture;
       4: areturn

  public java.util.concurrent.CompletableFuture getCurrentNrHRS();
    Code:
       0: aload_0
       1: invokespecial #11                 // Method org/apache/hadoop/hbase/client/DoNothingAsyncRegistry.getCurrentNrHRS:()Ljava/util/concurrent/CompletableFuture;
       4: areturn

  public java.util.concurrent.CompletableFuture getMetaRegionLocation();
    Code:
       0: aload_0
       1: invokespecial #12                 // Method org/apache/hadoop/hbase/client/DoNothingAsyncRegistry.getMetaRegionLocation:()Ljava/util/concurrent/CompletableFuture;
       4: areturn

  static boolean access$100(org.apache.hadoop.hbase.client.TestAsyncRegistryLeak$AsyncRegistryForTest);
    Code:
       0: aload_0
       1: getfield      #1                  // Field closed:Z
       4: ireturn
}
