Compiled from "TestSnapshotClientRetries.java"
public class org.apache.hadoop.hbase.snapshot.TestSnapshotClientRetries {
  public static final org.apache.hadoop.hbase.HBaseClassTestRule CLASS_RULE;

  public org.apache.hadoop.hbase.TestTableName TEST_TABLE;

  public org.apache.hadoop.hbase.snapshot.TestSnapshotClientRetries();
    Code:
       0: aload_0
       1: invokespecial #1                  // Method java/lang/Object."<init>":()V
       4: aload_0
       5: new           #2                  // class org/apache/hadoop/hbase/TestTableName
       8: dup
       9: invokespecial #3                  // Method org/apache/hadoop/hbase/TestTableName."<init>":()V
      12: putfield      #4                  // Field TEST_TABLE:Lorg/apache/hadoop/hbase/TestTableName;
      15: return

  public void setUp() throws java.lang.Exception;
    Code:
       0: getstatic     #5                  // Field TEST_UTIL:Lorg/apache/hadoop/hbase/HBaseTestingUtility;
       3: invokevirtual #6                  // Method org/apache/hadoop/hbase/HBaseTestingUtility.getConfiguration:()Lorg/apache/hadoop/conf/Configuration;
       6: ldc           #8                  // String hbase.coprocessor.master.classes
       8: ldc           #9                  // class org/apache/hadoop/hbase/snapshot/TestSnapshotClientRetries$MasterSyncObserver
      10: invokevirtual #10                 // Method java/lang/Class.getName:()Ljava/lang/String;
      13: invokevirtual #11                 // Method org/apache/hadoop/conf/Configuration.set:(Ljava/lang/String;Ljava/lang/String;)V
      16: getstatic     #5                  // Field TEST_UTIL:Lorg/apache/hadoop/hbase/HBaseTestingUtility;
      19: iconst_1
      20: invokevirtual #12                 // Method org/apache/hadoop/hbase/HBaseTestingUtility.startMiniCluster:(I)Lorg/apache/hadoop/hbase/MiniHBaseCluster;
      23: pop
      24: return

  public void tearDown() throws java.lang.Exception;
    Code:
       0: getstatic     #5                  // Field TEST_UTIL:Lorg/apache/hadoop/hbase/HBaseTestingUtility;
       3: invokevirtual #13                 // Method org/apache/hadoop/hbase/HBaseTestingUtility.shutdownMiniCluster:()V
       6: return

  public void testSnapshotAlreadyExist() throws java.lang.Exception;
    Code:
       0: ldc           #14                 // String testSnapshotAlreadyExist
       2: astore_1
       3: getstatic     #5                  // Field TEST_UTIL:Lorg/apache/hadoop/hbase/HBaseTestingUtility;
       6: aload_0
       7: getfield      #4                  // Field TEST_TABLE:Lorg/apache/hadoop/hbase/TestTableName;
      10: invokevirtual #15                 // Method org/apache/hadoop/hbase/TestTableName.getTableName:()Lorg/apache/hadoop/hbase/TableName;
      13: ldc           #16                 // String f
      15: invokevirtual #17                 // Method org/apache/hadoop/hbase/HBaseTestingUtility.createTable:(Lorg/apache/hadoop/hbase/TableName;Ljava/lang/String;)Lorg/apache/hadoop/hbase/client/Table;
      18: pop
      19: getstatic     #5                  // Field TEST_UTIL:Lorg/apache/hadoop/hbase/HBaseTestingUtility;
      22: invokevirtual #18                 // Method org/apache/hadoop/hbase/HBaseTestingUtility.getAdmin:()Lorg/apache/hadoop/hbase/client/Admin;
      25: ldc           #14                 // String testSnapshotAlreadyExist
      27: aload_0
      28: getfield      #4                  // Field TEST_TABLE:Lorg/apache/hadoop/hbase/TestTableName;
      31: invokevirtual #15                 // Method org/apache/hadoop/hbase/TestTableName.getTableName:()Lorg/apache/hadoop/hbase/TableName;
      34: invokeinterface #19,  3           // InterfaceMethod org/apache/hadoop/hbase/client/Admin.snapshot:(Ljava/lang/String;Lorg/apache/hadoop/hbase/TableName;)V
      39: aload_0
      40: ldc           #14                 // String testSnapshotAlreadyExist
      42: aload_0
      43: getfield      #4                  // Field TEST_TABLE:Lorg/apache/hadoop/hbase/TestTableName;
      46: invokevirtual #15                 // Method org/apache/hadoop/hbase/TestTableName.getTableName:()Lorg/apache/hadoop/hbase/TableName;
      49: invokevirtual #20                 // Method snapshotAndAssertOneRetry:(Ljava/lang/String;Lorg/apache/hadoop/hbase/TableName;)V
      52: return

  public void testCloneNonExistentSnapshot() throws java.lang.Exception;
    Code:
       0: ldc           #21                 // String testCloneNonExistentSnapshot
       2: astore_1
       3: aload_0
       4: ldc           #21                 // String testCloneNonExistentSnapshot
       6: aload_0
       7: getfield      #4                  // Field TEST_TABLE:Lorg/apache/hadoop/hbase/TestTableName;
      10: invokevirtual #15                 // Method org/apache/hadoop/hbase/TestTableName.getTableName:()Lorg/apache/hadoop/hbase/TableName;
      13: invokevirtual #22                 // Method cloneAndAssertOneRetry:(Ljava/lang/String;Lorg/apache/hadoop/hbase/TableName;)V
      16: return

  public void snapshotAndAssertOneRetry(java.lang.String, org.apache.hadoop.hbase.TableName) throws java.lang.Exception;
    Code:
       0: aload_0
       1: invokespecial #23                 // Method getMasterSyncObserver:()Lorg/apache/hadoop/hbase/snapshot/TestSnapshotClientRetries$MasterSyncObserver;
       4: astore_3
       5: aload_3
       6: new           #24                 // class java/util/concurrent/atomic/AtomicInteger
       9: dup
      10: iconst_0
      11: invokespecial #25                 // Method java/util/concurrent/atomic/AtomicInteger."<init>":(I)V
      14: putfield      #26                 // Field org/apache/hadoop/hbase/snapshot/TestSnapshotClientRetries$MasterSyncObserver.snapshotCount:Ljava/util/concurrent/atomic/AtomicInteger;
      17: getstatic     #5                  // Field TEST_UTIL:Lorg/apache/hadoop/hbase/HBaseTestingUtility;
      20: invokevirtual #18                 // Method org/apache/hadoop/hbase/HBaseTestingUtility.getAdmin:()Lorg/apache/hadoop/hbase/client/Admin;
      23: aload_1
      24: aload_2
      25: invokeinterface #19,  3           // InterfaceMethod org/apache/hadoop/hbase/client/Admin.snapshot:(Ljava/lang/String;Lorg/apache/hadoop/hbase/TableName;)V
      30: lconst_1
      31: aload_3
      32: getfield      #26                 // Field org/apache/hadoop/hbase/snapshot/TestSnapshotClientRetries$MasterSyncObserver.snapshotCount:Ljava/util/concurrent/atomic/AtomicInteger;
      35: invokevirtual #27                 // Method java/util/concurrent/atomic/AtomicInteger.get:()I
      38: i2l
      39: invokestatic  #28                 // Method org/junit/Assert.assertEquals:(JJ)V
      42: return

  public void cloneAndAssertOneRetry(java.lang.String, org.apache.hadoop.hbase.TableName) throws java.lang.Exception;
    Code:
       0: aload_0
       1: invokespecial #23                 // Method getMasterSyncObserver:()Lorg/apache/hadoop/hbase/snapshot/TestSnapshotClientRetries$MasterSyncObserver;
       4: astore_3
       5: aload_3
       6: new           #24                 // class java/util/concurrent/atomic/AtomicInteger
       9: dup
      10: iconst_0
      11: invokespecial #25                 // Method java/util/concurrent/atomic/AtomicInteger."<init>":(I)V
      14: putfield      #29                 // Field org/apache/hadoop/hbase/snapshot/TestSnapshotClientRetries$MasterSyncObserver.cloneCount:Ljava/util/concurrent/atomic/AtomicInteger;
      17: getstatic     #5                  // Field TEST_UTIL:Lorg/apache/hadoop/hbase/HBaseTestingUtility;
      20: invokevirtual #18                 // Method org/apache/hadoop/hbase/HBaseTestingUtility.getAdmin:()Lorg/apache/hadoop/hbase/client/Admin;
      23: aload_1
      24: aload_2
      25: invokeinterface #30,  3           // InterfaceMethod org/apache/hadoop/hbase/client/Admin.cloneSnapshot:(Ljava/lang/String;Lorg/apache/hadoop/hbase/TableName;)V
      30: lconst_1
      31: aload_3
      32: getfield      #29                 // Field org/apache/hadoop/hbase/snapshot/TestSnapshotClientRetries$MasterSyncObserver.cloneCount:Ljava/util/concurrent/atomic/AtomicInteger;
      35: invokevirtual #27                 // Method java/util/concurrent/atomic/AtomicInteger.get:()I
      38: i2l
      39: invokestatic  #28                 // Method org/junit/Assert.assertEquals:(JJ)V
      42: return

  static {};
    Code:
       0: ldc           #35                 // class org/apache/hadoop/hbase/snapshot/TestSnapshotClientRetries
       2: invokestatic  #36                 // Method org/apache/hadoop/hbase/HBaseClassTestRule.forClass:(Ljava/lang/Class;)Lorg/apache/hadoop/hbase/HBaseClassTestRule;
       5: putstatic     #37                 // Field CLASS_RULE:Lorg/apache/hadoop/hbase/HBaseClassTestRule;
       8: new           #38                 // class org/apache/hadoop/hbase/HBaseTestingUtility
      11: dup
      12: invokespecial #39                 // Method org/apache/hadoop/hbase/HBaseTestingUtility."<init>":()V
      15: putstatic     #5                  // Field TEST_UTIL:Lorg/apache/hadoop/hbase/HBaseTestingUtility;
      18: ldc           #35                 // class org/apache/hadoop/hbase/snapshot/TestSnapshotClientRetries
      20: invokestatic  #40                 // Method org/slf4j/LoggerFactory.getLogger:(Ljava/lang/Class;)Lorg/slf4j/Logger;
      23: putstatic     #41                 // Field LOG:Lorg/slf4j/Logger;
      26: return
}
