Compiled from "TestHRegion.java"
public class org.apache.hadoop.hbase.regionserver.TestHRegion$PutThread extends java.lang.Thread {
  final org.apache.hadoop.hbase.regionserver.TestHRegion this$0;

  public void waitForFirstPut() throws java.lang.InterruptedException;
    Code:
       0: aload_0
       1: invokevirtual #10                 // Method isAlive:()Z
       4: ifeq          27
       7: aload_0
       8: getfield      #5                  // Field numPutsFinished:I
      11: ifne          27
      14: aload_0
      15: invokevirtual #11                 // Method checkNoError:()V
      18: ldc2_w        #12                 // long 50l
      21: invokestatic  #14                 // Method java/lang/Thread.sleep:(J)V
      24: goto          0
      27: return

  public void done();
    Code:
       0: aload_0
       1: iconst_1
       2: putfield      #15                 // Field done:Z
       5: aload_0
       6: dup
       7: astore_1
       8: monitorenter
       9: aload_0
      10: invokevirtual #16                 // Method interrupt:()V
      13: aload_1
      14: monitorexit
      15: goto          23
      18: astore_2
      19: aload_1
      20: monitorexit
      21: aload_2
      22: athrow
      23: return
    Exception table:
       from    to  target type
           9    15    18   any
          18    21    18   any

  public void checkNoError();
    Code:
       0: aload_0
       1: getfield      #6                  // Field error:Ljava/lang/Throwable;
       4: ifnull        14
       7: aload_0
       8: getfield      #6                  // Field error:Ljava/lang/Throwable;
      11: invokestatic  #17                 // Method org/junit/Assert.assertNull:(Ljava/lang/Object;)V
      14: return

  public void run();
    Code:
       0: aload_0
       1: iconst_0
       2: putfield      #15                 // Field done:Z
       5: aload_0
       6: getfield      #15                 // Field done:Z
       9: ifne          298
      12: iconst_0
      13: istore_1
      14: iload_1
      15: aload_0
      16: getfield      #7                  // Field numRows:I
      19: if_icmpge     260
      22: new           #18                 // class java/lang/StringBuilder
      25: dup
      26: invokespecial #19                 // Method java/lang/StringBuilder."<init>":()V
      29: ldc           #20                 // String row
      31: invokevirtual #21                 // Method java/lang/StringBuilder.append:(Ljava/lang/String;)Ljava/lang/StringBuilder;
      34: iload_1
      35: invokevirtual #22                 // Method java/lang/StringBuilder.append:(I)Ljava/lang/StringBuilder;
      38: invokevirtual #23                 // Method java/lang/StringBuilder.toString:()Ljava/lang/String;
      41: invokestatic  #24                 // Method org/apache/hadoop/hbase/util/Bytes.toBytes:(Ljava/lang/String;)[B
      44: astore_2
      45: new           #25                 // class org/apache/hadoop/hbase/client/Put
      48: dup
      49: aload_2
      50: invokespecial #26                 // Method org/apache/hadoop/hbase/client/Put."<init>":([B)V
      53: astore_3
      54: aload_3
      55: getstatic     #27                 // Field org/apache/hadoop/hbase/client/Durability.SKIP_WAL:Lorg/apache/hadoop/hbase/client/Durability;
      58: invokevirtual #28                 // Method org/apache/hadoop/hbase/client/Put.setDurability:(Lorg/apache/hadoop/hbase/client/Durability;)Lorg/apache/hadoop/hbase/client/Put;
      61: pop
      62: aload_0
      63: getfield      #5                  // Field numPutsFinished:I
      66: invokestatic  #29                 // Method java/lang/String.valueOf:(I)Ljava/lang/String;
      69: invokestatic  #24                 // Method org/apache/hadoop/hbase/util/Bytes.toBytes:(Ljava/lang/String;)[B
      72: astore        4
      74: aload_0
      75: getfield      #8                  // Field families:[[B
      78: astore        5
      80: aload         5
      82: arraylength
      83: istore        6
      85: iconst_0
      86: istore        7
      88: iload         7
      90: iload         6
      92: if_icmpge     158
      95: aload         5
      97: iload         7
      99: aaload
     100: astore        8
     102: aload_0
     103: getfield      #9                  // Field qualifiers:[[B
     106: astore        9
     108: aload         9
     110: arraylength
     111: istore        10
     113: iconst_0
     114: istore        11
     116: iload         11
     118: iload         10
     120: if_icmpge     152
     123: aload         9
     125: iload         11
     127: aaload
     128: astore        12
     130: aload_3
     131: aload         8
     133: aload         12
     135: aload_0
     136: getfield      #5                  // Field numPutsFinished:I
     139: i2l
     140: aload         4
     142: invokevirtual #30                 // Method org/apache/hadoop/hbase/client/Put.addColumn:([B[BJ[B)Lorg/apache/hadoop/hbase/client/Put;
     145: pop
     146: iinc          11, 1
     149: goto          116
     152: iinc          7, 1
     155: goto          88
     158: aload_0
     159: getfield      #2                  // Field this$0:Lorg/apache/hadoop/hbase/regionserver/TestHRegion;
     162: getfield      #31                 // Field org/apache/hadoop/hbase/regionserver/TestHRegion.region:Lorg/apache/hadoop/hbase/regionserver/HRegion;
     165: aload_3
     166: invokevirtual #32                 // Method org/apache/hadoop/hbase/regionserver/HRegion.put:(Lorg/apache/hadoop/hbase/client/Put;)V
     169: aload_0
     170: dup
     171: getfield      #5                  // Field numPutsFinished:I
     174: iconst_1
     175: iadd
     176: putfield      #5                  // Field numPutsFinished:I
     179: aload_0
     180: getfield      #5                  // Field numPutsFinished:I
     183: ifle          244
     186: aload_0
     187: getfield      #5                  // Field numPutsFinished:I
     190: bipush        47
     192: irem
     193: ifne          244
     196: invokestatic  #33                 // Method org/apache/hadoop/hbase/regionserver/TestHRegion.access$100:()Lorg/slf4j/Logger;
     199: ldc           #34                 // String put iteration = {}
     201: aload_0
     202: getfield      #5                  // Field numPutsFinished:I
     205: invokestatic  #35                 // Method java/lang/Integer.valueOf:(I)Ljava/lang/Integer;
     208: invokeinterface #36,  3           // InterfaceMethod org/slf4j/Logger.debug:(Ljava/lang/String;Ljava/lang/Object;)V
     213: new           #37                 // class org/apache/hadoop/hbase/client/Delete
     216: dup
     217: aload_2
     218: aload_0
     219: getfield      #5                  // Field numPutsFinished:I
     222: i2l
     223: ldc2_w        #38                 // long 30l
     226: lsub
     227: invokespecial #40                 // Method org/apache/hadoop/hbase/client/Delete."<init>":([BJ)V
     230: astore        5
     232: aload_0
     233: getfield      #2                  // Field this$0:Lorg/apache/hadoop/hbase/regionserver/TestHRegion;
     236: getfield      #31                 // Field org/apache/hadoop/hbase/regionserver/TestHRegion.region:Lorg/apache/hadoop/hbase/regionserver/HRegion;
     239: aload         5
     241: invokevirtual #41                 // Method org/apache/hadoop/hbase/regionserver/HRegion.delete:(Lorg/apache/hadoop/hbase/client/Delete;)V
     244: aload_0
     245: dup
     246: getfield      #5                  // Field numPutsFinished:I
     249: iconst_1
     250: iadd
     251: putfield      #5                  // Field numPutsFinished:I
     254: iinc          1, 1
     257: goto          14
     260: goto          5
     263: astore_1
     264: invokestatic  #33                 // Method org/apache/hadoop/hbase/regionserver/TestHRegion.access$100:()Lorg/slf4j/Logger;
     267: ldc           #43                 // String Interrupted
     269: aload_1
     270: invokeinterface #44,  3           // InterfaceMethod org/slf4j/Logger.info:(Ljava/lang/String;Ljava/lang/Throwable;)V
     275: goto          5
     278: astore_1
     279: invokestatic  #33                 // Method org/apache/hadoop/hbase/regionserver/TestHRegion.access$100:()Lorg/slf4j/Logger;
     282: ldc           #46                 // String Error while putting records
     284: aload_1
     285: invokeinterface #47,  3           // InterfaceMethod org/slf4j/Logger.error:(Ljava/lang/String;Ljava/lang/Throwable;)V
     290: aload_0
     291: aload_1
     292: putfield      #6                  // Field error:Ljava/lang/Throwable;
     295: goto          298
     298: return
    Exception table:
       from    to  target type
          12   260   263   Class java/io/InterruptedIOException
          12   260   278   Class java/io/IOException

  org.apache.hadoop.hbase.regionserver.TestHRegion$PutThread(org.apache.hadoop.hbase.regionserver.TestHRegion, int, byte[][], byte[][], org.apache.hadoop.hbase.regionserver.TestHRegion$1);
    Code:
       0: aload_0
       1: aload_1
       2: iload_2
       3: aload_3
       4: aload         4
       6: invokespecial #1                  // Method "<init>":(Lorg/apache/hadoop/hbase/regionserver/TestHRegion;I[[B[[B)V
       9: return
}
