Compiled from "TestHRegion.java"
class org.apache.hadoop.hbase.regionserver.TestHRegion$7 extends org.apache.hadoop.hbase.filter.FilterBase {
  final byte[] val$cf_first;

  final org.apache.hadoop.hbase.regionserver.TestHRegion this$0;

  org.apache.hadoop.hbase.regionserver.TestHRegion$7(org.apache.hadoop.hbase.regionserver.TestHRegion, byte[]);
    Code:
       0: aload_0
       1: aload_1
       2: putfield      #1                  // Field this$0:Lorg/apache/hadoop/hbase/regionserver/TestHRegion;
       5: aload_0
       6: aload_2
       7: putfield      #2                  // Field val$cf_first:[B
      10: aload_0
      11: invokespecial #3                  // Method org/apache/hadoop/hbase/filter/FilterBase."<init>":()V
      14: return

  public org.apache.hadoop.hbase.filter.Filter$ReturnCode filterCell(org.apache.hadoop.hbase.Cell) throws java.io.IOException;
    Code:
       0: getstatic     #4                  // Field org/apache/hadoop/hbase/filter/Filter$ReturnCode.INCLUDE:Lorg/apache/hadoop/hbase/filter/Filter$ReturnCode;
       3: areturn

  public boolean isFamilyEssential(byte[]);
    Code:
       0: aload_1
       1: aload_0
       2: getfield      #2                  // Field val$cf_first:[B
       5: invokestatic  #5                  // Method org/apache/hadoop/hbase/util/Bytes.equals:([B[B)Z
       8: ireturn
}
