Compiled from "TestDelayedUtil.java"
public class org.apache.hadoop.hbase.procedure2.util.TestDelayedUtil {
  public static final org.apache.hadoop.hbase.HBaseClassTestRule CLASS_RULE;

  public org.apache.hadoop.hbase.procedure2.util.TestDelayedUtil();
    Code:
       0: aload_0
       1: invokespecial #1                  // Method java/lang/Object."<init>":()V
       4: return

  public void testDelayedContainerEquals();
    Code:
       0: new           #2                  // class java/lang/Object
       3: dup
       4: invokespecial #1                  // Method java/lang/Object."<init>":()V
       7: astore_1
       8: new           #2                  // class java/lang/Object
      11: dup
      12: invokespecial #1                  // Method java/lang/Object."<init>":()V
      15: astore_2
      16: new           #3                  // class org/apache/hadoop/hbase/procedure2/util/TestDelayedUtil$ZeroDelayContainer
      19: dup
      20: aconst_null
      21: invokespecial #4                  // Method org/apache/hadoop/hbase/procedure2/util/TestDelayedUtil$ZeroDelayContainer."<init>":(Ljava/lang/Object;)V
      24: astore_3
      25: new           #3                  // class org/apache/hadoop/hbase/procedure2/util/TestDelayedUtil$ZeroDelayContainer
      28: dup
      29: ldc2_w        #5                  // long 10l
      32: invokestatic  #7                  // Method java/lang/Long.valueOf:(J)Ljava/lang/Long;
      35: invokespecial #4                  // Method org/apache/hadoop/hbase/procedure2/util/TestDelayedUtil$ZeroDelayContainer."<init>":(Ljava/lang/Object;)V
      38: astore        4
      40: new           #3                  // class org/apache/hadoop/hbase/procedure2/util/TestDelayedUtil$ZeroDelayContainer
      43: dup
      44: ldc2_w        #5                  // long 10l
      47: invokestatic  #7                  // Method java/lang/Long.valueOf:(J)Ljava/lang/Long;
      50: invokespecial #4                  // Method org/apache/hadoop/hbase/procedure2/util/TestDelayedUtil$ZeroDelayContainer."<init>":(Ljava/lang/Object;)V
      53: astore        5
      55: new           #3                  // class org/apache/hadoop/hbase/procedure2/util/TestDelayedUtil$ZeroDelayContainer
      58: dup
      59: ldc2_w        #8                  // long 15l
      62: invokestatic  #7                  // Method java/lang/Long.valueOf:(J)Ljava/lang/Long;
      65: invokespecial #4                  // Method org/apache/hadoop/hbase/procedure2/util/TestDelayedUtil$ZeroDelayContainer."<init>":(Ljava/lang/Object;)V
      68: astore        6
      70: new           #3                  // class org/apache/hadoop/hbase/procedure2/util/TestDelayedUtil$ZeroDelayContainer
      73: dup
      74: aconst_null
      75: invokespecial #4                  // Method org/apache/hadoop/hbase/procedure2/util/TestDelayedUtil$ZeroDelayContainer."<init>":(Ljava/lang/Object;)V
      78: astore        7
      80: new           #3                  // class org/apache/hadoop/hbase/procedure2/util/TestDelayedUtil$ZeroDelayContainer
      83: dup
      84: aload_1
      85: invokespecial #4                  // Method org/apache/hadoop/hbase/procedure2/util/TestDelayedUtil$ZeroDelayContainer."<init>":(Ljava/lang/Object;)V
      88: astore        8
      90: new           #3                  // class org/apache/hadoop/hbase/procedure2/util/TestDelayedUtil$ZeroDelayContainer
      93: dup
      94: aload_1
      95: invokespecial #4                  // Method org/apache/hadoop/hbase/procedure2/util/TestDelayedUtil$ZeroDelayContainer."<init>":(Ljava/lang/Object;)V
      98: astore        9
     100: new           #3                  // class org/apache/hadoop/hbase/procedure2/util/TestDelayedUtil$ZeroDelayContainer
     103: dup
     104: aload_2
     105: invokespecial #4                  // Method org/apache/hadoop/hbase/procedure2/util/TestDelayedUtil$ZeroDelayContainer."<init>":(Ljava/lang/Object;)V
     108: astore        10
     110: bipush        8
     112: anewarray     #3                  // class org/apache/hadoop/hbase/procedure2/util/TestDelayedUtil$ZeroDelayContainer
     115: dup
     116: iconst_0
     117: aload_3
     118: aastore
     119: dup
     120: iconst_1
     121: aload         4
     123: aastore
     124: dup
     125: iconst_2
     126: aload         5
     128: aastore
     129: dup
     130: iconst_3
     131: aload         6
     133: aastore
     134: dup
     135: iconst_4
     136: aload         7
     138: aastore
     139: dup
     140: iconst_5
     141: aload         8
     143: aastore
     144: dup
     145: bipush        6
     147: aload         9
     149: aastore
     150: dup
     151: bipush        7
     153: aload         10
     155: aastore
     156: astore        11
     158: aload_0
     159: aload_3
     160: aload         11
     162: iconst_2
     163: anewarray     #3                  // class org/apache/hadoop/hbase/procedure2/util/TestDelayedUtil$ZeroDelayContainer
     166: dup
     167: iconst_0
     168: aload_3
     169: aastore
     170: dup
     171: iconst_1
     172: aload         7
     174: aastore
     175: invokespecial #10                 // Method assertContainersEquals:(Lorg/apache/hadoop/hbase/procedure2/util/TestDelayedUtil$ZeroDelayContainer;[Lorg/apache/hadoop/hbase/procedure2/util/TestDelayedUtil$ZeroDelayContainer;[Lorg/apache/hadoop/hbase/procedure2/util/TestDelayedUtil$ZeroDelayContainer;)V
     178: aload_0
     179: aload         4
     181: aload         11
     183: iconst_2
     184: anewarray     #3                  // class org/apache/hadoop/hbase/procedure2/util/TestDelayedUtil$ZeroDelayContainer
     187: dup
     188: iconst_0
     189: aload         4
     191: aastore
     192: dup
     193: iconst_1
     194: aload         5
     196: aastore
     197: invokespecial #10                 // Method assertContainersEquals:(Lorg/apache/hadoop/hbase/procedure2/util/TestDelayedUtil$ZeroDelayContainer;[Lorg/apache/hadoop/hbase/procedure2/util/TestDelayedUtil$ZeroDelayContainer;[Lorg/apache/hadoop/hbase/procedure2/util/TestDelayedUtil$ZeroDelayContainer;)V
     200: aload_0
     201: aload         5
     203: aload         11
     205: iconst_2
     206: anewarray     #3                  // class org/apache/hadoop/hbase/procedure2/util/TestDelayedUtil$ZeroDelayContainer
     209: dup
     210: iconst_0
     211: aload         4
     213: aastore
     214: dup
     215: iconst_1
     216: aload         5
     218: aastore
     219: invokespecial #10                 // Method assertContainersEquals:(Lorg/apache/hadoop/hbase/procedure2/util/TestDelayedUtil$ZeroDelayContainer;[Lorg/apache/hadoop/hbase/procedure2/util/TestDelayedUtil$ZeroDelayContainer;[Lorg/apache/hadoop/hbase/procedure2/util/TestDelayedUtil$ZeroDelayContainer;)V
     222: aload_0
     223: aload         6
     225: aload         11
     227: iconst_1
     228: anewarray     #3                  // class org/apache/hadoop/hbase/procedure2/util/TestDelayedUtil$ZeroDelayContainer
     231: dup
     232: iconst_0
     233: aload         6
     235: aastore
     236: invokespecial #10                 // Method assertContainersEquals:(Lorg/apache/hadoop/hbase/procedure2/util/TestDelayedUtil$ZeroDelayContainer;[Lorg/apache/hadoop/hbase/procedure2/util/TestDelayedUtil$ZeroDelayContainer;[Lorg/apache/hadoop/hbase/procedure2/util/TestDelayedUtil$ZeroDelayContainer;)V
     239: aload_0
     240: aload         7
     242: aload         11
     244: iconst_2
     245: anewarray     #3                  // class org/apache/hadoop/hbase/procedure2/util/TestDelayedUtil$ZeroDelayContainer
     248: dup
     249: iconst_0
     250: aload_3
     251: aastore
     252: dup
     253: iconst_1
     254: aload         7
     256: aastore
     257: invokespecial #10                 // Method assertContainersEquals:(Lorg/apache/hadoop/hbase/procedure2/util/TestDelayedUtil$ZeroDelayContainer;[Lorg/apache/hadoop/hbase/procedure2/util/TestDelayedUtil$ZeroDelayContainer;[Lorg/apache/hadoop/hbase/procedure2/util/TestDelayedUtil$ZeroDelayContainer;)V
     260: aload_0
     261: aload         8
     263: aload         11
     265: iconst_2
     266: anewarray     #3                  // class org/apache/hadoop/hbase/procedure2/util/TestDelayedUtil$ZeroDelayContainer
     269: dup
     270: iconst_0
     271: aload         8
     273: aastore
     274: dup
     275: iconst_1
     276: aload         9
     278: aastore
     279: invokespecial #10                 // Method assertContainersEquals:(Lorg/apache/hadoop/hbase/procedure2/util/TestDelayedUtil$ZeroDelayContainer;[Lorg/apache/hadoop/hbase/procedure2/util/TestDelayedUtil$ZeroDelayContainer;[Lorg/apache/hadoop/hbase/procedure2/util/TestDelayedUtil$ZeroDelayContainer;)V
     282: aload_0
     283: aload         9
     285: aload         11
     287: iconst_2
     288: anewarray     #3                  // class org/apache/hadoop/hbase/procedure2/util/TestDelayedUtil$ZeroDelayContainer
     291: dup
     292: iconst_0
     293: aload         8
     295: aastore
     296: dup
     297: iconst_1
     298: aload         9
     300: aastore
     301: invokespecial #10                 // Method assertContainersEquals:(Lorg/apache/hadoop/hbase/procedure2/util/TestDelayedUtil$ZeroDelayContainer;[Lorg/apache/hadoop/hbase/procedure2/util/TestDelayedUtil$ZeroDelayContainer;[Lorg/apache/hadoop/hbase/procedure2/util/TestDelayedUtil$ZeroDelayContainer;)V
     304: aload_0
     305: aload         10
     307: aload         11
     309: iconst_1
     310: anewarray     #3                  // class org/apache/hadoop/hbase/procedure2/util/TestDelayedUtil$ZeroDelayContainer
     313: dup
     314: iconst_0
     315: aload         10
     317: aastore
     318: invokespecial #10                 // Method assertContainersEquals:(Lorg/apache/hadoop/hbase/procedure2/util/TestDelayedUtil$ZeroDelayContainer;[Lorg/apache/hadoop/hbase/procedure2/util/TestDelayedUtil$ZeroDelayContainer;[Lorg/apache/hadoop/hbase/procedure2/util/TestDelayedUtil$ZeroDelayContainer;)V
     321: return

  static {};
    Code:
       0: ldc           #21                 // class org/apache/hadoop/hbase/procedure2/util/TestDelayedUtil
       2: invokestatic  #22                 // Method org/apache/hadoop/hbase/HBaseClassTestRule.forClass:(Ljava/lang/Class;)Lorg/apache/hadoop/hbase/HBaseClassTestRule;
       5: putstatic     #23                 // Field CLASS_RULE:Lorg/apache/hadoop/hbase/HBaseClassTestRule;
       8: ldc           #21                 // class org/apache/hadoop/hbase/procedure2/util/TestDelayedUtil
      10: invokestatic  #24                 // Method org/slf4j/LoggerFactory.getLogger:(Ljava/lang/Class;)Lorg/slf4j/Logger;
      13: putstatic     #25                 // Field LOG:Lorg/slf4j/Logger;
      16: return
}
