Compiled from "TestBulkLoadCheckingViolationPolicyEnforcement.java"
public class org.apache.hadoop.hbase.quotas.policies.TestBulkLoadCheckingViolationPolicyEnforcement {
  public static final org.apache.hadoop.hbase.HBaseClassTestRule CLASS_RULE;

  org.apache.hadoop.fs.FileSystem fs;

  org.apache.hadoop.hbase.regionserver.RegionServerServices rss;

  org.apache.hadoop.hbase.TableName tableName;

  org.apache.hadoop.hbase.quotas.SpaceViolationPolicyEnforcement policy;

  public org.apache.hadoop.hbase.quotas.policies.TestBulkLoadCheckingViolationPolicyEnforcement();
    Code:
       0: aload_0
       1: invokespecial #1                  // Method java/lang/Object."<init>":()V
       4: return

  public void setup();
    Code:
       0: aload_0
       1: ldc           #2                  // class org/apache/hadoop/fs/FileSystem
       3: invokestatic  #3                  // Method org/mockito/Mockito.mock:(Ljava/lang/Class;)Ljava/lang/Object;
       6: checkcast     #2                  // class org/apache/hadoop/fs/FileSystem
       9: putfield      #4                  // Field fs:Lorg/apache/hadoop/fs/FileSystem;
      12: aload_0
      13: ldc           #5                  // class org/apache/hadoop/hbase/regionserver/RegionServerServices
      15: invokestatic  #3                  // Method org/mockito/Mockito.mock:(Ljava/lang/Class;)Ljava/lang/Object;
      18: checkcast     #5                  // class org/apache/hadoop/hbase/regionserver/RegionServerServices
      21: putfield      #6                  // Field rss:Lorg/apache/hadoop/hbase/regionserver/RegionServerServices;
      24: aload_0
      25: ldc           #7                  // String foo
      27: invokestatic  #8                  // Method org/apache/hadoop/hbase/TableName.valueOf:(Ljava/lang/String;)Lorg/apache/hadoop/hbase/TableName;
      30: putfield      #9                  // Field tableName:Lorg/apache/hadoop/hbase/TableName;
      33: aload_0
      34: new           #10                 // class org/apache/hadoop/hbase/quotas/policies/DefaultViolationPolicyEnforcement
      37: dup
      38: invokespecial #11                 // Method org/apache/hadoop/hbase/quotas/policies/DefaultViolationPolicyEnforcement."<init>":()V
      41: putfield      #12                 // Field policy:Lorg/apache/hadoop/hbase/quotas/SpaceViolationPolicyEnforcement;
      44: return

  public void testFilesUnderLimit() throws java.lang.Exception;
    Code:
       0: new           #13                 // class java/util/ArrayList
       3: dup
       4: invokespecial #14                 // Method java/util/ArrayList."<init>":()V
       7: astore_1
       8: new           #13                 // class java/util/ArrayList
      11: dup
      12: invokespecial #14                 // Method java/util/ArrayList."<init>":()V
      15: astore_2
      16: ldc2_w        #15                 // long 102400l
      19: lstore_3
      20: iconst_0
      21: istore        5
      23: iload         5
      25: iconst_5
      26: if_icmpge     156
      29: new           #17                 // class java/lang/StringBuilder
      32: dup
      33: invokespecial #18                 // Method java/lang/StringBuilder."<init>":()V
      36: ldc           #19                 // String /
      38: invokevirtual #20                 // Method java/lang/StringBuilder.append:(Ljava/lang/String;)Ljava/lang/StringBuilder;
      41: iload         5
      43: invokevirtual #21                 // Method java/lang/StringBuilder.append:(I)Ljava/lang/StringBuilder;
      46: invokevirtual #22                 // Method java/lang/StringBuilder.toString:()Ljava/lang/String;
      49: astore        6
      51: ldc           #23                 // class org/apache/hadoop/fs/FileStatus
      53: invokestatic  #3                  // Method org/mockito/Mockito.mock:(Ljava/lang/Class;)Ljava/lang/Object;
      56: checkcast     #23                 // class org/apache/hadoop/fs/FileStatus
      59: astore        7
      61: aload_0
      62: getfield      #4                  // Field fs:Lorg/apache/hadoop/fs/FileSystem;
      65: new           #24                 // class org/apache/hadoop/fs/Path
      68: dup
      69: aload         6
      71: invokespecial #25                 // Method org/apache/hadoop/fs/Path."<init>":(Ljava/lang/String;)V
      74: invokevirtual #26                 // Method org/apache/hadoop/fs/FileSystem.getFileStatus:(Lorg/apache/hadoop/fs/Path;)Lorg/apache/hadoop/fs/FileStatus;
      77: invokestatic  #27                 // Method org/mockito/Mockito.when:(Ljava/lang/Object;)Lorg/mockito/stubbing/OngoingStubbing;
      80: aload         7
      82: invokeinterface #28,  2           // InterfaceMethod org/mockito/stubbing/OngoingStubbing.thenReturn:(Ljava/lang/Object;)Lorg/mockito/stubbing/OngoingStubbing;
      87: pop
      88: aload         7
      90: invokevirtual #29                 // Method org/apache/hadoop/fs/FileStatus.getLen:()J
      93: invokestatic  #30                 // Method java/lang/Long.valueOf:(J)Ljava/lang/Long;
      96: invokestatic  #27                 // Method org/mockito/Mockito.when:(Ljava/lang/Object;)Lorg/mockito/stubbing/OngoingStubbing;
      99: ldc2_w        #15                 // long 102400l
     102: invokestatic  #30                 // Method java/lang/Long.valueOf:(J)Ljava/lang/Long;
     105: invokeinterface #28,  2           // InterfaceMethod org/mockito/stubbing/OngoingStubbing.thenReturn:(Ljava/lang/Object;)Lorg/mockito/stubbing/OngoingStubbing;
     110: pop
     111: aload         7
     113: invokevirtual #31                 // Method org/apache/hadoop/fs/FileStatus.isFile:()Z
     116: invokestatic  #32                 // Method java/lang/Boolean.valueOf:(Z)Ljava/lang/Boolean;
     119: invokestatic  #27                 // Method org/mockito/Mockito.when:(Ljava/lang/Object;)Lorg/mockito/stubbing/OngoingStubbing;
     122: iconst_1
     123: invokestatic  #32                 // Method java/lang/Boolean.valueOf:(Z)Ljava/lang/Boolean;
     126: invokeinterface #28,  2           // InterfaceMethod org/mockito/stubbing/OngoingStubbing.thenReturn:(Ljava/lang/Object;)Lorg/mockito/stubbing/OngoingStubbing;
     131: pop
     132: aload_1
     133: aload         6
     135: invokeinterface #33,  2           // InterfaceMethod java/util/List.add:(Ljava/lang/Object;)Z
     140: pop
     141: aload_2
     142: aload         7
     144: invokeinterface #33,  2           // InterfaceMethod java/util/List.add:(Ljava/lang/Object;)Z
     149: pop
     150: iinc          5, 1
     153: goto          23
     156: new           #34                 // class org/apache/hadoop/hbase/quotas/SpaceQuotaSnapshot
     159: dup
     160: invokestatic  #35                 // Method org/apache/hadoop/hbase/quotas/SpaceQuotaSnapshot$SpaceQuotaStatus.notInViolation:()Lorg/apache/hadoop/hbase/quotas/SpaceQuotaSnapshot$SpaceQuotaStatus;
     163: lconst_0
     164: ldc2_w        #36                 // long 614400l
     167: invokespecial #38                 // Method org/apache/hadoop/hbase/quotas/SpaceQuotaSnapshot."<init>":(Lorg/apache/hadoop/hbase/quotas/SpaceQuotaSnapshot$SpaceQuotaStatus;JJ)V
     170: astore        5
     172: aload_0
     173: getfield      #12                 // Field policy:Lorg/apache/hadoop/hbase/quotas/SpaceViolationPolicyEnforcement;
     176: aload_0
     177: getfield      #6                  // Field rss:Lorg/apache/hadoop/hbase/regionserver/RegionServerServices;
     180: aload_0
     181: getfield      #9                  // Field tableName:Lorg/apache/hadoop/hbase/TableName;
     184: aload         5
     186: invokeinterface #39,  4           // InterfaceMethod org/apache/hadoop/hbase/quotas/SpaceViolationPolicyEnforcement.initialize:(Lorg/apache/hadoop/hbase/regionserver/RegionServerServices;Lorg/apache/hadoop/hbase/TableName;Lorg/apache/hadoop/hbase/quotas/SpaceQuotaSnapshot;)V
     191: aload_0
     192: getfield      #12                 // Field policy:Lorg/apache/hadoop/hbase/quotas/SpaceViolationPolicyEnforcement;
     195: aload_0
     196: getfield      #4                  // Field fs:Lorg/apache/hadoop/fs/FileSystem;
     199: aload_1
     200: invokeinterface #40,  3           // InterfaceMethod org/apache/hadoop/hbase/quotas/SpaceViolationPolicyEnforcement.computeBulkLoadSize:(Lorg/apache/hadoop/fs/FileSystem;Ljava/util/List;)J
     205: pop2
     206: return

  public void testFileIsNotAFile() throws java.lang.Exception;
    Code:
       0: new           #13                 // class java/util/ArrayList
       3: dup
       4: invokespecial #14                 // Method java/util/ArrayList."<init>":()V
       7: astore_1
       8: ldc           #41                 // String /1
      10: astore_2
      11: ldc           #23                 // class org/apache/hadoop/fs/FileStatus
      13: invokestatic  #3                  // Method org/mockito/Mockito.mock:(Ljava/lang/Class;)Ljava/lang/Object;
      16: checkcast     #23                 // class org/apache/hadoop/fs/FileStatus
      19: astore_3
      20: aload_0
      21: getfield      #4                  // Field fs:Lorg/apache/hadoop/fs/FileSystem;
      24: new           #24                 // class org/apache/hadoop/fs/Path
      27: dup
      28: aload_2
      29: invokespecial #25                 // Method org/apache/hadoop/fs/Path."<init>":(Ljava/lang/String;)V
      32: invokevirtual #26                 // Method org/apache/hadoop/fs/FileSystem.getFileStatus:(Lorg/apache/hadoop/fs/Path;)Lorg/apache/hadoop/fs/FileStatus;
      35: invokestatic  #27                 // Method org/mockito/Mockito.when:(Ljava/lang/Object;)Lorg/mockito/stubbing/OngoingStubbing;
      38: aload_3
      39: invokeinterface #28,  2           // InterfaceMethod org/mockito/stubbing/OngoingStubbing.thenReturn:(Ljava/lang/Object;)Lorg/mockito/stubbing/OngoingStubbing;
      44: pop
      45: aload_3
      46: invokevirtual #29                 // Method org/apache/hadoop/fs/FileStatus.getLen:()J
      49: invokestatic  #30                 // Method java/lang/Long.valueOf:(J)Ljava/lang/Long;
      52: invokestatic  #27                 // Method org/mockito/Mockito.when:(Ljava/lang/Object;)Lorg/mockito/stubbing/OngoingStubbing;
      55: ldc2_w        #42                 // long 1000l
      58: invokestatic  #30                 // Method java/lang/Long.valueOf:(J)Ljava/lang/Long;
      61: invokeinterface #28,  2           // InterfaceMethod org/mockito/stubbing/OngoingStubbing.thenReturn:(Ljava/lang/Object;)Lorg/mockito/stubbing/OngoingStubbing;
      66: pop
      67: aload_3
      68: invokevirtual #31                 // Method org/apache/hadoop/fs/FileStatus.isFile:()Z
      71: invokestatic  #32                 // Method java/lang/Boolean.valueOf:(Z)Ljava/lang/Boolean;
      74: invokestatic  #27                 // Method org/mockito/Mockito.when:(Ljava/lang/Object;)Lorg/mockito/stubbing/OngoingStubbing;
      77: iconst_0
      78: invokestatic  #32                 // Method java/lang/Boolean.valueOf:(Z)Ljava/lang/Boolean;
      81: invokeinterface #28,  2           // InterfaceMethod org/mockito/stubbing/OngoingStubbing.thenReturn:(Ljava/lang/Object;)Lorg/mockito/stubbing/OngoingStubbing;
      86: pop
      87: aload_1
      88: aload_2
      89: invokeinterface #33,  2           // InterfaceMethod java/util/List.add:(Ljava/lang/Object;)Z
      94: pop
      95: new           #34                 // class org/apache/hadoop/hbase/quotas/SpaceQuotaSnapshot
      98: dup
      99: invokestatic  #35                 // Method org/apache/hadoop/hbase/quotas/SpaceQuotaSnapshot$SpaceQuotaStatus.notInViolation:()Lorg/apache/hadoop/hbase/quotas/SpaceQuotaSnapshot$SpaceQuotaStatus;
     102: lconst_0
     103: ldc2_w        #45                 // long 9223372036854775807l
     106: invokespecial #38                 // Method org/apache/hadoop/hbase/quotas/SpaceQuotaSnapshot."<init>":(Lorg/apache/hadoop/hbase/quotas/SpaceQuotaSnapshot$SpaceQuotaStatus;JJ)V
     109: astore        4
     111: aload_0
     112: getfield      #12                 // Field policy:Lorg/apache/hadoop/hbase/quotas/SpaceViolationPolicyEnforcement;
     115: aload_0
     116: getfield      #6                  // Field rss:Lorg/apache/hadoop/hbase/regionserver/RegionServerServices;
     119: aload_0
     120: getfield      #9                  // Field tableName:Lorg/apache/hadoop/hbase/TableName;
     123: aload         4
     125: invokeinterface #39,  4           // InterfaceMethod org/apache/hadoop/hbase/quotas/SpaceViolationPolicyEnforcement.initialize:(Lorg/apache/hadoop/hbase/regionserver/RegionServerServices;Lorg/apache/hadoop/hbase/TableName;Lorg/apache/hadoop/hbase/quotas/SpaceQuotaSnapshot;)V
     130: aload_0
     131: getfield      #12                 // Field policy:Lorg/apache/hadoop/hbase/quotas/SpaceViolationPolicyEnforcement;
     134: aload_0
     135: getfield      #4                  // Field fs:Lorg/apache/hadoop/fs/FileSystem;
     138: aload_1
     139: invokeinterface #40,  3           // InterfaceMethod org/apache/hadoop/hbase/quotas/SpaceViolationPolicyEnforcement.computeBulkLoadSize:(Lorg/apache/hadoop/fs/FileSystem;Ljava/util/List;)J
     144: pop2
     145: return

  public void testOneFileInBatchOverLimit() throws java.lang.Exception;
    Code:
       0: new           #13                 // class java/util/ArrayList
       3: dup
       4: invokespecial #14                 // Method java/util/ArrayList."<init>":()V
       7: astore_1
       8: new           #13                 // class java/util/ArrayList
      11: dup
      12: invokespecial #14                 // Method java/util/ArrayList."<init>":()V
      15: astore_2
      16: ldc2_w        #47                 // long 1024000l
      19: lstore_3
      20: iconst_0
      21: istore        5
      23: iload         5
      25: iconst_5
      26: if_icmpge     156
      29: new           #17                 // class java/lang/StringBuilder
      32: dup
      33: invokespecial #18                 // Method java/lang/StringBuilder."<init>":()V
      36: ldc           #19                 // String /
      38: invokevirtual #20                 // Method java/lang/StringBuilder.append:(Ljava/lang/String;)Ljava/lang/StringBuilder;
      41: iload         5
      43: invokevirtual #21                 // Method java/lang/StringBuilder.append:(I)Ljava/lang/StringBuilder;
      46: invokevirtual #22                 // Method java/lang/StringBuilder.toString:()Ljava/lang/String;
      49: astore        6
      51: ldc           #23                 // class org/apache/hadoop/fs/FileStatus
      53: invokestatic  #3                  // Method org/mockito/Mockito.mock:(Ljava/lang/Class;)Ljava/lang/Object;
      56: checkcast     #23                 // class org/apache/hadoop/fs/FileStatus
      59: astore        7
      61: aload_0
      62: getfield      #4                  // Field fs:Lorg/apache/hadoop/fs/FileSystem;
      65: new           #24                 // class org/apache/hadoop/fs/Path
      68: dup
      69: aload         6
      71: invokespecial #25                 // Method org/apache/hadoop/fs/Path."<init>":(Ljava/lang/String;)V
      74: invokevirtual #26                 // Method org/apache/hadoop/fs/FileSystem.getFileStatus:(Lorg/apache/hadoop/fs/Path;)Lorg/apache/hadoop/fs/FileStatus;
      77: invokestatic  #27                 // Method org/mockito/Mockito.when:(Ljava/lang/Object;)Lorg/mockito/stubbing/OngoingStubbing;
      80: aload         7
      82: invokeinterface #28,  2           // InterfaceMethod org/mockito/stubbing/OngoingStubbing.thenReturn:(Ljava/lang/Object;)Lorg/mockito/stubbing/OngoingStubbing;
      87: pop
      88: aload         7
      90: invokevirtual #29                 // Method org/apache/hadoop/fs/FileStatus.getLen:()J
      93: invokestatic  #30                 // Method java/lang/Long.valueOf:(J)Ljava/lang/Long;
      96: invokestatic  #27                 // Method org/mockito/Mockito.when:(Ljava/lang/Object;)Lorg/mockito/stubbing/OngoingStubbing;
      99: ldc2_w        #47                 // long 1024000l
     102: invokestatic  #30                 // Method java/lang/Long.valueOf:(J)Ljava/lang/Long;
     105: invokeinterface #28,  2           // InterfaceMethod org/mockito/stubbing/OngoingStubbing.thenReturn:(Ljava/lang/Object;)Lorg/mockito/stubbing/OngoingStubbing;
     110: pop
     111: aload         7
     113: invokevirtual #31                 // Method org/apache/hadoop/fs/FileStatus.isFile:()Z
     116: invokestatic  #32                 // Method java/lang/Boolean.valueOf:(Z)Ljava/lang/Boolean;
     119: invokestatic  #27                 // Method org/mockito/Mockito.when:(Ljava/lang/Object;)Lorg/mockito/stubbing/OngoingStubbing;
     122: iconst_1
     123: invokestatic  #32                 // Method java/lang/Boolean.valueOf:(Z)Ljava/lang/Boolean;
     126: invokeinterface #28,  2           // InterfaceMethod org/mockito/stubbing/OngoingStubbing.thenReturn:(Ljava/lang/Object;)Lorg/mockito/stubbing/OngoingStubbing;
     131: pop
     132: aload_1
     133: aload         6
     135: invokeinterface #33,  2           // InterfaceMethod java/util/List.add:(Ljava/lang/Object;)Z
     140: pop
     141: aload_2
     142: aload         7
     144: invokeinterface #33,  2           // InterfaceMethod java/util/List.add:(Ljava/lang/Object;)Z
     149: pop
     150: iinc          5, 1
     153: goto          23
     156: new           #34                 // class org/apache/hadoop/hbase/quotas/SpaceQuotaSnapshot
     159: dup
     160: invokestatic  #35                 // Method org/apache/hadoop/hbase/quotas/SpaceQuotaSnapshot$SpaceQuotaStatus.notInViolation:()Lorg/apache/hadoop/hbase/quotas/SpaceQuotaSnapshot$SpaceQuotaStatus;
     163: lconst_0
     164: ldc2_w        #49                 // long 1024l
     167: invokespecial #38                 // Method org/apache/hadoop/hbase/quotas/SpaceQuotaSnapshot."<init>":(Lorg/apache/hadoop/hbase/quotas/SpaceQuotaSnapshot$SpaceQuotaStatus;JJ)V
     170: astore        5
     172: aload_0
     173: getfield      #12                 // Field policy:Lorg/apache/hadoop/hbase/quotas/SpaceViolationPolicyEnforcement;
     176: aload_0
     177: getfield      #6                  // Field rss:Lorg/apache/hadoop/hbase/regionserver/RegionServerServices;
     180: aload_0
     181: getfield      #9                  // Field tableName:Lorg/apache/hadoop/hbase/TableName;
     184: aload         5
     186: invokeinterface #39,  4           // InterfaceMethod org/apache/hadoop/hbase/quotas/SpaceViolationPolicyEnforcement.initialize:(Lorg/apache/hadoop/hbase/regionserver/RegionServerServices;Lorg/apache/hadoop/hbase/TableName;Lorg/apache/hadoop/hbase/quotas/SpaceQuotaSnapshot;)V
     191: aload_0
     192: getfield      #12                 // Field policy:Lorg/apache/hadoop/hbase/quotas/SpaceViolationPolicyEnforcement;
     195: aload_0
     196: getfield      #4                  // Field fs:Lorg/apache/hadoop/fs/FileSystem;
     199: aload_1
     200: invokeinterface #40,  3           // InterfaceMethod org/apache/hadoop/hbase/quotas/SpaceViolationPolicyEnforcement.computeBulkLoadSize:(Lorg/apache/hadoop/fs/FileSystem;Ljava/util/List;)J
     205: pop2
     206: return

  public void testSumOfFilesOverLimit() throws java.lang.Exception;
    Code:
       0: new           #13                 // class java/util/ArrayList
       3: dup
       4: invokespecial #14                 // Method java/util/ArrayList."<init>":()V
       7: astore_1
       8: new           #13                 // class java/util/ArrayList
      11: dup
      12: invokespecial #14                 // Method java/util/ArrayList."<init>":()V
      15: astore_2
      16: ldc2_w        #49                 // long 1024l
      19: lstore_3
      20: iconst_0
      21: istore        5
      23: iload         5
      25: iconst_5
      26: if_icmpge     156
      29: new           #17                 // class java/lang/StringBuilder
      32: dup
      33: invokespecial #18                 // Method java/lang/StringBuilder."<init>":()V
      36: ldc           #19                 // String /
      38: invokevirtual #20                 // Method java/lang/StringBuilder.append:(Ljava/lang/String;)Ljava/lang/StringBuilder;
      41: iload         5
      43: invokevirtual #21                 // Method java/lang/StringBuilder.append:(I)Ljava/lang/StringBuilder;
      46: invokevirtual #22                 // Method java/lang/StringBuilder.toString:()Ljava/lang/String;
      49: astore        6
      51: ldc           #23                 // class org/apache/hadoop/fs/FileStatus
      53: invokestatic  #3                  // Method org/mockito/Mockito.mock:(Ljava/lang/Class;)Ljava/lang/Object;
      56: checkcast     #23                 // class org/apache/hadoop/fs/FileStatus
      59: astore        7
      61: aload_0
      62: getfield      #4                  // Field fs:Lorg/apache/hadoop/fs/FileSystem;
      65: new           #24                 // class org/apache/hadoop/fs/Path
      68: dup
      69: aload         6
      71: invokespecial #25                 // Method org/apache/hadoop/fs/Path."<init>":(Ljava/lang/String;)V
      74: invokevirtual #26                 // Method org/apache/hadoop/fs/FileSystem.getFileStatus:(Lorg/apache/hadoop/fs/Path;)Lorg/apache/hadoop/fs/FileStatus;
      77: invokestatic  #27                 // Method org/mockito/Mockito.when:(Ljava/lang/Object;)Lorg/mockito/stubbing/OngoingStubbing;
      80: aload         7
      82: invokeinterface #28,  2           // InterfaceMethod org/mockito/stubbing/OngoingStubbing.thenReturn:(Ljava/lang/Object;)Lorg/mockito/stubbing/OngoingStubbing;
      87: pop
      88: aload         7
      90: invokevirtual #29                 // Method org/apache/hadoop/fs/FileStatus.getLen:()J
      93: invokestatic  #30                 // Method java/lang/Long.valueOf:(J)Ljava/lang/Long;
      96: invokestatic  #27                 // Method org/mockito/Mockito.when:(Ljava/lang/Object;)Lorg/mockito/stubbing/OngoingStubbing;
      99: ldc2_w        #49                 // long 1024l
     102: invokestatic  #30                 // Method java/lang/Long.valueOf:(J)Ljava/lang/Long;
     105: invokeinterface #28,  2           // InterfaceMethod org/mockito/stubbing/OngoingStubbing.thenReturn:(Ljava/lang/Object;)Lorg/mockito/stubbing/OngoingStubbing;
     110: pop
     111: aload         7
     113: invokevirtual #31                 // Method org/apache/hadoop/fs/FileStatus.isFile:()Z
     116: invokestatic  #32                 // Method java/lang/Boolean.valueOf:(Z)Ljava/lang/Boolean;
     119: invokestatic  #27                 // Method org/mockito/Mockito.when:(Ljava/lang/Object;)Lorg/mockito/stubbing/OngoingStubbing;
     122: iconst_1
     123: invokestatic  #32                 // Method java/lang/Boolean.valueOf:(Z)Ljava/lang/Boolean;
     126: invokeinterface #28,  2           // InterfaceMethod org/mockito/stubbing/OngoingStubbing.thenReturn:(Ljava/lang/Object;)Lorg/mockito/stubbing/OngoingStubbing;
     131: pop
     132: aload_1
     133: aload         6
     135: invokeinterface #33,  2           // InterfaceMethod java/util/List.add:(Ljava/lang/Object;)Z
     140: pop
     141: aload_2
     142: aload         7
     144: invokeinterface #33,  2           // InterfaceMethod java/util/List.add:(Ljava/lang/Object;)Z
     149: pop
     150: iinc          5, 1
     153: goto          23
     156: new           #34                 // class org/apache/hadoop/hbase/quotas/SpaceQuotaSnapshot
     159: dup
     160: invokestatic  #35                 // Method org/apache/hadoop/hbase/quotas/SpaceQuotaSnapshot$SpaceQuotaStatus.notInViolation:()Lorg/apache/hadoop/hbase/quotas/SpaceQuotaSnapshot$SpaceQuotaStatus;
     163: lconst_0
     164: ldc2_w        #51                 // long 5000l
     167: invokespecial #38                 // Method org/apache/hadoop/hbase/quotas/SpaceQuotaSnapshot."<init>":(Lorg/apache/hadoop/hbase/quotas/SpaceQuotaSnapshot$SpaceQuotaStatus;JJ)V
     170: astore        5
     172: aload_0
     173: getfield      #12                 // Field policy:Lorg/apache/hadoop/hbase/quotas/SpaceViolationPolicyEnforcement;
     176: aload_0
     177: getfield      #6                  // Field rss:Lorg/apache/hadoop/hbase/regionserver/RegionServerServices;
     180: aload_0
     181: getfield      #9                  // Field tableName:Lorg/apache/hadoop/hbase/TableName;
     184: aload         5
     186: invokeinterface #39,  4           // InterfaceMethod org/apache/hadoop/hbase/quotas/SpaceViolationPolicyEnforcement.initialize:(Lorg/apache/hadoop/hbase/regionserver/RegionServerServices;Lorg/apache/hadoop/hbase/TableName;Lorg/apache/hadoop/hbase/quotas/SpaceQuotaSnapshot;)V
     191: aload_0
     192: getfield      #12                 // Field policy:Lorg/apache/hadoop/hbase/quotas/SpaceViolationPolicyEnforcement;
     195: aload_0
     196: getfield      #4                  // Field fs:Lorg/apache/hadoop/fs/FileSystem;
     199: aload_1
     200: invokeinterface #40,  3           // InterfaceMethod org/apache/hadoop/hbase/quotas/SpaceViolationPolicyEnforcement.computeBulkLoadSize:(Lorg/apache/hadoop/fs/FileSystem;Ljava/util/List;)J
     205: pop2
     206: return

  static {};
    Code:
       0: ldc           #53                 // class org/apache/hadoop/hbase/quotas/policies/TestBulkLoadCheckingViolationPolicyEnforcement
       2: invokestatic  #54                 // Method org/apache/hadoop/hbase/HBaseClassTestRule.forClass:(Ljava/lang/Class;)Lorg/apache/hadoop/hbase/HBaseClassTestRule;
       5: putstatic     #55                 // Field CLASS_RULE:Lorg/apache/hadoop/hbase/HBaseClassTestRule;
       8: return
}
