Compiled from "TestRegionReplicaSplit.java"
public class org.apache.hadoop.hbase.master.assignment.TestRegionReplicaSplit {
  public static final org.apache.hadoop.hbase.HBaseClassTestRule CLASS_RULE;

  public org.junit.rules.TestName name;

  public org.apache.hadoop.hbase.master.assignment.TestRegionReplicaSplit();
    Code:
       0: aload_0
       1: invokespecial #1                  // Method java/lang/Object."<init>":()V
       4: aload_0
       5: new           #2                  // class org/junit/rules/TestName
       8: dup
       9: invokespecial #3                  // Method org/junit/rules/TestName."<init>":()V
      12: putfield      #4                  // Field name:Lorg/junit/rules/TestName;
      15: return

  public static void beforeClass() throws java.lang.Exception;
    Code:
       0: getstatic     #5                  // Field HTU:Lorg/apache/hadoop/hbase/HBaseTestingUtility;
       3: invokevirtual #6                  // Method org/apache/hadoop/hbase/HBaseTestingUtility.getConfiguration:()Lorg/apache/hadoop/conf/Configuration;
       6: ldc           #7                  // String hbase.master.wait.on.regionservers.mintostart
       8: iconst_3
       9: invokevirtual #8                  // Method org/apache/hadoop/conf/Configuration.setInt:(Ljava/lang/String;I)V
      12: getstatic     #5                  // Field HTU:Lorg/apache/hadoop/hbase/HBaseTestingUtility;
      15: iconst_4
      16: invokevirtual #10                 // Method org/apache/hadoop/hbase/HBaseTestingUtility.startMiniCluster:(I)Lorg/apache/hadoop/hbase/MiniHBaseCluster;
      19: pop
      20: ldc           #9                  // class org/apache/hadoop/hbase/master/assignment/TestRegionReplicaSplit
      22: invokevirtual #11                 // Method java/lang/Class.getSimpleName:()Ljava/lang/String;
      25: invokestatic  #12                 // Method org/apache/hadoop/hbase/TableName.valueOf:(Ljava/lang/String;)Lorg/apache/hadoop/hbase/TableName;
      28: astore_0
      29: aload_0
      30: invokestatic  #13                 // Method createTable:(Lorg/apache/hadoop/hbase/TableName;)V
      33: return

  public static void afterClass() throws java.lang.Exception;
    Code:
       0: iconst_0
       1: putstatic     #33                 // Field org/apache/hadoop/hbase/regionserver/HRegionServer.TEST_SKIP_REPORTING_TRANSITION:Z
       4: getstatic     #23                 // Field table:Lorg/apache/hadoop/hbase/client/Table;
       7: invokeinterface #34,  1           // InterfaceMethod org/apache/hadoop/hbase/client/Table.close:()V
      12: getstatic     #5                  // Field HTU:Lorg/apache/hadoop/hbase/HBaseTestingUtility;
      15: invokevirtual #35                 // Method org/apache/hadoop/hbase/HBaseTestingUtility.shutdownMiniCluster:()V
      18: return

  public void testRegionReplicaSplitRegionAssignment() throws java.lang.Exception;
    Code:
       0: getstatic     #5                  // Field HTU:Lorg/apache/hadoop/hbase/HBaseTestingUtility;
       3: getstatic     #23                 // Field table:Lorg/apache/hadoop/hbase/client/Table;
       6: getstatic     #18                 // Field f:[B
       9: iconst_0
      10: iconst_3
      11: invokevirtual #36                 // Method org/apache/hadoop/hbase/HBaseTestingUtility.loadNumericRows:(Lorg/apache/hadoop/hbase/client/Table;[BII)V
      14: new           #37                 // class java/util/ArrayList
      17: dup
      18: invokespecial #38                 // Method java/util/ArrayList."<init>":()V
      21: astore_1
      22: getstatic     #5                  // Field HTU:Lorg/apache/hadoop/hbase/HBaseTestingUtility;
      25: invokevirtual #39                 // Method org/apache/hadoop/hbase/HBaseTestingUtility.getMiniHBaseCluster:()Lorg/apache/hadoop/hbase/MiniHBaseCluster;
      28: invokevirtual #40                 // Method org/apache/hadoop/hbase/MiniHBaseCluster.getRegionServerThreads:()Ljava/util/List;
      31: invokeinterface #41,  1           // InterfaceMethod java/util/List.iterator:()Ljava/util/Iterator;
      36: astore_2
      37: aload_2
      38: invokeinterface #42,  1           // InterfaceMethod java/util/Iterator.hasNext:()Z
      43: ifeq          161
      46: aload_2
      47: invokeinterface #43,  1           // InterfaceMethod java/util/Iterator.next:()Ljava/lang/Object;
      52: checkcast     #44                 // class org/apache/hadoop/hbase/util/JVMClusterUtil$RegionServerThread
      55: astore_3
      56: aload_3
      57: invokevirtual #45                 // Method org/apache/hadoop/hbase/util/JVMClusterUtil$RegionServerThread.getRegionServer:()Lorg/apache/hadoop/hbase/regionserver/HRegionServer;
      60: getstatic     #23                 // Field table:Lorg/apache/hadoop/hbase/client/Table;
      63: invokeinterface #46,  1           // InterfaceMethod org/apache/hadoop/hbase/client/Table.getName:()Lorg/apache/hadoop/hbase/TableName;
      68: invokevirtual #47                 // Method org/apache/hadoop/hbase/regionserver/HRegionServer.getRegions:(Lorg/apache/hadoop/hbase/TableName;)Ljava/util/List;
      71: invokeinterface #41,  1           // InterfaceMethod java/util/List.iterator:()Ljava/util/Iterator;
      76: astore        4
      78: aload         4
      80: invokeinterface #42,  1           // InterfaceMethod java/util/Iterator.hasNext:()Z
      85: ifeq          158
      88: aload         4
      90: invokeinterface #43,  1           // InterfaceMethod java/util/Iterator.next:()Ljava/lang/Object;
      95: checkcast     #48                 // class org/apache/hadoop/hbase/regionserver/Region
      98: astore        5
     100: getstatic     #49                 // Field java/lang/System.out:Ljava/io/PrintStream;
     103: new           #50                 // class java/lang/StringBuilder
     106: dup
     107: invokespecial #51                 // Method java/lang/StringBuilder."<init>":()V
     110: ldc           #52                 // String the region before split is is
     112: invokevirtual #53                 // Method java/lang/StringBuilder.append:(Ljava/lang/String;)Ljava/lang/StringBuilder;
     115: aload         5
     117: invokeinterface #54,  1           // InterfaceMethod org/apache/hadoop/hbase/regionserver/Region.getRegionInfo:()Lorg/apache/hadoop/hbase/client/RegionInfo;
     122: invokevirtual #55                 // Method java/lang/StringBuilder.append:(Ljava/lang/Object;)Ljava/lang/StringBuilder;
     125: aload_3
     126: invokevirtual #45                 // Method org/apache/hadoop/hbase/util/JVMClusterUtil$RegionServerThread.getRegionServer:()Lorg/apache/hadoop/hbase/regionserver/HRegionServer;
     129: invokevirtual #56                 // Method org/apache/hadoop/hbase/regionserver/HRegionServer.getServerName:()Lorg/apache/hadoop/hbase/ServerName;
     132: invokevirtual #55                 // Method java/lang/StringBuilder.append:(Ljava/lang/Object;)Ljava/lang/StringBuilder;
     135: invokevirtual #57                 // Method java/lang/StringBuilder.toString:()Ljava/lang/String;
     138: invokevirtual #58                 // Method java/io/PrintStream.println:(Ljava/lang/String;)V
     141: aload_1
     142: aload         5
     144: invokeinterface #54,  1           // InterfaceMethod org/apache/hadoop/hbase/regionserver/Region.getRegionInfo:()Lorg/apache/hadoop/hbase/client/RegionInfo;
     149: invokeinterface #59,  2           // InterfaceMethod java/util/List.add:(Ljava/lang/Object;)Z
     154: pop
     155: goto          78
     158: goto          37
     161: getstatic     #5                  // Field HTU:Lorg/apache/hadoop/hbase/HBaseTestingUtility;
     164: invokevirtual #60                 // Method org/apache/hadoop/hbase/HBaseTestingUtility.getAdmin:()Lorg/apache/hadoop/hbase/client/Admin;
     167: getstatic     #23                 // Field table:Lorg/apache/hadoop/hbase/client/Table;
     170: invokeinterface #46,  1           // InterfaceMethod org/apache/hadoop/hbase/client/Table.getName:()Lorg/apache/hadoop/hbase/TableName;
     175: iconst_1
     176: invokestatic  #61                 // Method org/apache/hadoop/hbase/util/Bytes.toBytes:(I)[B
     179: invokeinterface #62,  3           // InterfaceMethod org/apache/hadoop/hbase/client/Admin.split:(Lorg/apache/hadoop/hbase/TableName;[B)V
     184: iconst_0
     185: istore_2
     186: getstatic     #5                  // Field HTU:Lorg/apache/hadoop/hbase/HBaseTestingUtility;
     189: invokevirtual #39                 // Method org/apache/hadoop/hbase/HBaseTestingUtility.getMiniHBaseCluster:()Lorg/apache/hadoop/hbase/MiniHBaseCluster;
     192: invokevirtual #40                 // Method org/apache/hadoop/hbase/MiniHBaseCluster.getRegionServerThreads:()Ljava/util/List;
     195: invokeinterface #41,  1           // InterfaceMethod java/util/List.iterator:()Ljava/util/Iterator;
     200: astore_3
     201: aload_3
     202: invokeinterface #42,  1           // InterfaceMethod java/util/Iterator.hasNext:()Z
     207: ifeq          275
     210: aload_3
     211: invokeinterface #43,  1           // InterfaceMethod java/util/Iterator.next:()Ljava/lang/Object;
     216: checkcast     #44                 // class org/apache/hadoop/hbase/util/JVMClusterUtil$RegionServerThread
     219: astore        4
     221: aload         4
     223: invokevirtual #45                 // Method org/apache/hadoop/hbase/util/JVMClusterUtil$RegionServerThread.getRegionServer:()Lorg/apache/hadoop/hbase/regionserver/HRegionServer;
     226: getstatic     #23                 // Field table:Lorg/apache/hadoop/hbase/client/Table;
     229: invokeinterface #46,  1           // InterfaceMethod org/apache/hadoop/hbase/client/Table.getName:()Lorg/apache/hadoop/hbase/TableName;
     234: invokevirtual #47                 // Method org/apache/hadoop/hbase/regionserver/HRegionServer.getRegions:(Lorg/apache/hadoop/hbase/TableName;)Ljava/util/List;
     237: invokeinterface #41,  1           // InterfaceMethod java/util/List.iterator:()Ljava/util/Iterator;
     242: astore        5
     244: aload         5
     246: invokeinterface #42,  1           // InterfaceMethod java/util/Iterator.hasNext:()Z
     251: ifeq          272
     254: aload         5
     256: invokeinterface #43,  1           // InterfaceMethod java/util/Iterator.next:()Ljava/lang/Object;
     261: checkcast     #48                 // class org/apache/hadoop/hbase/regionserver/Region
     264: astore        6
     266: iinc          2, 1
     269: goto          244
     272: goto          201
     275: iload_2
     276: bipush        9
     278: if_icmplt     284
     281: goto          289
     284: iconst_0
     285: istore_2
     286: goto          186
     289: new           #37                 // class java/util/ArrayList
     292: dup
     293: invokespecial #38                 // Method java/util/ArrayList."<init>":()V
     296: astore_3
     297: getstatic     #5                  // Field HTU:Lorg/apache/hadoop/hbase/HBaseTestingUtility;
     300: invokevirtual #39                 // Method org/apache/hadoop/hbase/HBaseTestingUtility.getMiniHBaseCluster:()Lorg/apache/hadoop/hbase/MiniHBaseCluster;
     303: invokevirtual #40                 // Method org/apache/hadoop/hbase/MiniHBaseCluster.getRegionServerThreads:()Ljava/util/List;
     306: invokeinterface #41,  1           // InterfaceMethod java/util/List.iterator:()Ljava/util/Iterator;
     311: astore        4
     313: aload         4
     315: invokeinterface #42,  1           // InterfaceMethod java/util/Iterator.hasNext:()Z
     320: ifeq          614
     323: aload         4
     325: invokeinterface #43,  1           // InterfaceMethod java/util/Iterator.next:()Ljava/lang/Object;
     330: checkcast     #44                 // class org/apache/hadoop/hbase/util/JVMClusterUtil$RegionServerThread
     333: astore        5
     335: aconst_null
     336: astore        6
     338: aload         5
     340: invokevirtual #45                 // Method org/apache/hadoop/hbase/util/JVMClusterUtil$RegionServerThread.getRegionServer:()Lorg/apache/hadoop/hbase/regionserver/HRegionServer;
     343: getstatic     #23                 // Field table:Lorg/apache/hadoop/hbase/client/Table;
     346: invokeinterface #46,  1           // InterfaceMethod org/apache/hadoop/hbase/client/Table.getName:()Lorg/apache/hadoop/hbase/TableName;
     351: invokevirtual #47                 // Method org/apache/hadoop/hbase/regionserver/HRegionServer.getRegions:(Lorg/apache/hadoop/hbase/TableName;)Ljava/util/List;
     354: invokeinterface #41,  1           // InterfaceMethod java/util/List.iterator:()Ljava/util/Iterator;
     359: astore        7
     361: aload         7
     363: invokeinterface #42,  1           // InterfaceMethod java/util/Iterator.hasNext:()Z
     368: ifeq          611
     371: aload         7
     373: invokeinterface #43,  1           // InterfaceMethod java/util/Iterator.next:()Ljava/lang/Object;
     378: checkcast     #48                 // class org/apache/hadoop/hbase/regionserver/Region
     381: astore        8
     383: aload_1
     384: aload         8
     386: invokeinterface #54,  1           // InterfaceMethod org/apache/hadoop/hbase/regionserver/Region.getRegionInfo:()Lorg/apache/hadoop/hbase/client/RegionInfo;
     391: invokeinterface #63,  2           // InterfaceMethod java/util/List.contains:(Ljava/lang/Object;)Z
     396: ifne          608
     399: aload         8
     401: invokeinterface #54,  1           // InterfaceMethod org/apache/hadoop/hbase/regionserver/Region.getRegionInfo:()Lorg/apache/hadoop/hbase/client/RegionInfo;
     406: invokestatic  #64                 // Method org/apache/hadoop/hbase/client/RegionReplicaUtil.isDefaultReplica:(Lorg/apache/hadoop/hbase/client/RegionInfo;)Z
     409: ifne          608
     412: getstatic     #65                 // Field LOG:Lorg/slf4j/Logger;
     415: new           #50                 // class java/lang/StringBuilder
     418: dup
     419: invokespecial #51                 // Method java/lang/StringBuilder."<init>":()V
     422: ldc           #66                 // String The region is
     424: invokevirtual #53                 // Method java/lang/StringBuilder.append:(Ljava/lang/String;)Ljava/lang/StringBuilder;
     427: aload         8
     429: invokeinterface #54,  1           // InterfaceMethod org/apache/hadoop/hbase/regionserver/Region.getRegionInfo:()Lorg/apache/hadoop/hbase/client/RegionInfo;
     434: invokevirtual #55                 // Method java/lang/StringBuilder.append:(Ljava/lang/Object;)Ljava/lang/StringBuilder;
     437: ldc           #67                 // String  the location is
     439: invokevirtual #53                 // Method java/lang/StringBuilder.append:(Ljava/lang/String;)Ljava/lang/StringBuilder;
     442: aload         5
     444: invokevirtual #45                 // Method org/apache/hadoop/hbase/util/JVMClusterUtil$RegionServerThread.getRegionServer:()Lorg/apache/hadoop/hbase/regionserver/HRegionServer;
     447: invokevirtual #56                 // Method org/apache/hadoop/hbase/regionserver/HRegionServer.getServerName:()Lorg/apache/hadoop/hbase/ServerName;
     450: invokevirtual #55                 // Method java/lang/StringBuilder.append:(Ljava/lang/Object;)Ljava/lang/StringBuilder;
     453: invokevirtual #57                 // Method java/lang/StringBuilder.toString:()Ljava/lang/String;
     456: invokeinterface #68,  2           // InterfaceMethod org/slf4j/Logger.info:(Ljava/lang/String;)V
     461: aload         8
     463: invokeinterface #54,  1           // InterfaceMethod org/apache/hadoop/hbase/regionserver/Region.getRegionInfo:()Lorg/apache/hadoop/hbase/client/RegionInfo;
     468: invokestatic  #64                 // Method org/apache/hadoop/hbase/client/RegionReplicaUtil.isDefaultReplica:(Lorg/apache/hadoop/hbase/client/RegionInfo;)Z
     471: ifne          554
     474: aload_3
     475: aload         5
     477: invokevirtual #45                 // Method org/apache/hadoop/hbase/util/JVMClusterUtil$RegionServerThread.getRegionServer:()Lorg/apache/hadoop/hbase/regionserver/HRegionServer;
     480: invokevirtual #56                 // Method org/apache/hadoop/hbase/regionserver/HRegionServer.getServerName:()Lorg/apache/hadoop/hbase/ServerName;
     483: invokeinterface #63,  2           // InterfaceMethod java/util/List.contains:(Ljava/lang/Object;)Z
     488: ifeq          554
     491: aload         6
     493: ifnull        554
     496: aload         6
     498: invokeinterface #69,  1           // InterfaceMethod org/apache/hadoop/hbase/client/RegionInfo.getStartKey:()[B
     503: aload         8
     505: invokeinterface #54,  1           // InterfaceMethod org/apache/hadoop/hbase/regionserver/Region.getRegionInfo:()Lorg/apache/hadoop/hbase/client/RegionInfo;
     510: invokeinterface #69,  1           // InterfaceMethod org/apache/hadoop/hbase/client/RegionInfo.getStartKey:()[B
     515: invokestatic  #70                 // Method org/apache/hadoop/hbase/util/Bytes.equals:([B[B)Z
     518: ifeq          554
     521: aload         6
     523: invokeinterface #71,  1           // InterfaceMethod org/apache/hadoop/hbase/client/RegionInfo.getEndKey:()[B
     528: aload         8
     530: invokeinterface #54,  1           // InterfaceMethod org/apache/hadoop/hbase/regionserver/Region.getRegionInfo:()Lorg/apache/hadoop/hbase/client/RegionInfo;
     535: invokeinterface #71,  1           // InterfaceMethod org/apache/hadoop/hbase/client/RegionInfo.getEndKey:()[B
     540: invokestatic  #70                 // Method org/apache/hadoop/hbase/util/Bytes.equals:([B[B)Z
     543: ifeq          554
     546: ldc           #72                 // String Splitted regions should not be assigned to same region server
     548: invokestatic  #73                 // Method org/junit/Assert.fail:(Ljava/lang/String;)V
     551: goto          608
     554: aload         8
     556: invokeinterface #54,  1           // InterfaceMethod org/apache/hadoop/hbase/regionserver/Region.getRegionInfo:()Lorg/apache/hadoop/hbase/client/RegionInfo;
     561: astore        6
     563: aload         8
     565: invokeinterface #54,  1           // InterfaceMethod org/apache/hadoop/hbase/regionserver/Region.getRegionInfo:()Lorg/apache/hadoop/hbase/client/RegionInfo;
     570: invokestatic  #64                 // Method org/apache/hadoop/hbase/client/RegionReplicaUtil.isDefaultReplica:(Lorg/apache/hadoop/hbase/client/RegionInfo;)Z
     573: ifne          608
     576: aload_3
     577: aload         5
     579: invokevirtual #45                 // Method org/apache/hadoop/hbase/util/JVMClusterUtil$RegionServerThread.getRegionServer:()Lorg/apache/hadoop/hbase/regionserver/HRegionServer;
     582: invokevirtual #56                 // Method org/apache/hadoop/hbase/regionserver/HRegionServer.getServerName:()Lorg/apache/hadoop/hbase/ServerName;
     585: invokeinterface #63,  2           // InterfaceMethod java/util/List.contains:(Ljava/lang/Object;)Z
     590: ifne          608
     593: aload_3
     594: aload         5
     596: invokevirtual #45                 // Method org/apache/hadoop/hbase/util/JVMClusterUtil$RegionServerThread.getRegionServer:()Lorg/apache/hadoop/hbase/regionserver/HRegionServer;
     599: invokevirtual #56                 // Method org/apache/hadoop/hbase/regionserver/HRegionServer.getServerName:()Lorg/apache/hadoop/hbase/ServerName;
     602: invokeinterface #59,  2           // InterfaceMethod java/util/List.add:(Ljava/lang/Object;)Z
     607: pop
     608: goto          361
     611: goto          313
     614: ldc           #74                 // String The new regions should be assigned to 3 unique servers
     616: ldc2_w        #75                 // long 3l
     619: aload_3
     620: invokeinterface #77,  1           // InterfaceMethod java/util/List.size:()I
     625: i2l
     626: invokestatic  #78                 // Method org/junit/Assert.assertEquals:(Ljava/lang/String;JJ)V
     629: return

  static {};
    Code:
       0: ldc           #9                  // class org/apache/hadoop/hbase/master/assignment/TestRegionReplicaSplit
       2: invokestatic  #79                 // Method org/apache/hadoop/hbase/HBaseClassTestRule.forClass:(Ljava/lang/Class;)Lorg/apache/hadoop/hbase/HBaseClassTestRule;
       5: putstatic     #80                 // Field CLASS_RULE:Lorg/apache/hadoop/hbase/HBaseClassTestRule;
       8: ldc           #9                  // class org/apache/hadoop/hbase/master/assignment/TestRegionReplicaSplit
      10: invokestatic  #81                 // Method org/slf4j/LoggerFactory.getLogger:(Ljava/lang/Class;)Lorg/slf4j/Logger;
      13: putstatic     #65                 // Field LOG:Lorg/slf4j/Logger;
      16: new           #82                 // class org/apache/hadoop/hbase/HBaseTestingUtility
      19: dup
      20: invokespecial #83                 // Method org/apache/hadoop/hbase/HBaseTestingUtility."<init>":()V
      23: putstatic     #5                  // Field HTU:Lorg/apache/hadoop/hbase/HBaseTestingUtility;
      26: getstatic     #84                 // Field org/apache/hadoop/hbase/HConstants.CATALOG_FAMILY:[B
      29: putstatic     #18                 // Field f:[B
      32: return
}
