Compiled from "TestRpcServerTraceLogging.java"
public class org.apache.hadoop.hbase.ipc.TestRpcServerTraceLogging {
  public static final org.apache.hadoop.hbase.HBaseClassTestRule CLASS_RULE;

  static org.apache.log4j.Logger rpcServerLog;

  static final java.lang.String TRACE_LOG_MSG;

  static final int TRACE_LOG_LENGTH;

  static final org.apache.hadoop.hbase.ipc.RpcServer mockRpcServer;

  static final org.apache.hadoop.conf.Configuration conf;

  public org.apache.hadoop.hbase.ipc.TestRpcServerTraceLogging();
    Code:
       0: aload_0
       1: invokespecial #1                  // Method java/lang/Object."<init>":()V
       4: return

  public static void setUp();
    Code:
       0: getstatic     #2                  // Field mockRpcServer:Lorg/apache/hadoop/hbase/ipc/RpcServer;
       3: invokevirtual #3                  // Method org/apache/hadoop/hbase/ipc/RpcServer.getConf:()Lorg/apache/hadoop/conf/Configuration;
       6: invokestatic  #4                  // Method org/mockito/Mockito.when:(Ljava/lang/Object;)Lorg/mockito/stubbing/OngoingStubbing;
       9: getstatic     #5                  // Field conf:Lorg/apache/hadoop/conf/Configuration;
      12: invokeinterface #6,  2            // InterfaceMethod org/mockito/stubbing/OngoingStubbing.thenReturn:(Ljava/lang/Object;)Lorg/mockito/stubbing/OngoingStubbing;
      17: pop
      18: getstatic     #2                  // Field mockRpcServer:Lorg/apache/hadoop/hbase/ipc/RpcServer;
      21: ldc           #7                  // class java/lang/String
      23: invokestatic  #8                  // Method org/mockito/Mockito.any:(Ljava/lang/Class;)Ljava/lang/Object;
      26: checkcast     #7                  // class java/lang/String
      29: invokevirtual #9                  // Method org/apache/hadoop/hbase/ipc/RpcServer.truncateTraceLog:(Ljava/lang/String;)Ljava/lang/String;
      32: invokestatic  #4                  // Method org/mockito/Mockito.when:(Ljava/lang/Object;)Lorg/mockito/stubbing/OngoingStubbing;
      35: invokeinterface #10,  1           // InterfaceMethod org/mockito/stubbing/OngoingStubbing.thenCallRealMethod:()Lorg/mockito/stubbing/OngoingStubbing;
      40: pop
      41: return

  public void testLoggingWithTraceOff();
    Code:
       0: getstatic     #5                  // Field conf:Lorg/apache/hadoop/conf/Configuration;
       3: ldc           #11                 // String hbase.ipc.trace.log.max.length
       5: sipush        250
       8: invokevirtual #12                 // Method org/apache/hadoop/conf/Configuration.setInt:(Ljava/lang/String;I)V
      11: getstatic     #13                 // Field rpcServerLog:Lorg/apache/log4j/Logger;
      14: getstatic     #14                 // Field org/apache/log4j/Level.DEBUG:Lorg/apache/log4j/Level;
      17: invokevirtual #15                 // Method org/apache/log4j/Logger.setLevel:(Lorg/apache/log4j/Level;)V
      20: getstatic     #2                  // Field mockRpcServer:Lorg/apache/hadoop/hbase/ipc/RpcServer;
      23: ldc           #17                 // String This is dummy message for testing:: region { type: REGION_NAME value: \"hbase:meta,,1\" } scan { column { family: \"info\" } time_range { from: 0 to: 9223372036854775807 } max_versions: 1 cache_blocks: true max_result_size: 2097152 caching: 2147483647 } number_of_rows: 2147483647 close_scanner: false client_handles_partials: true client_handles_heartbeats: true track_scan_metrics: false
      25: invokevirtual #9                  // Method org/apache/hadoop/hbase/ipc/RpcServer.truncateTraceLog:(Ljava/lang/String;)Ljava/lang/String;
      28: astore_1
      29: sipush        150
      32: ldc           #19                 // String  <TRUNCATED>
      34: invokevirtual #20                 // Method java/lang/String.length:()I
      37: iadd
      38: i2l
      39: aload_1
      40: invokevirtual #20                 // Method java/lang/String.length:()I
      43: i2l
      44: invokestatic  #21                 // Method org/junit/Assert.assertEquals:(JJ)V
      47: aload_1
      48: ldc           #19                 // String  <TRUNCATED>
      50: invokevirtual #22                 // Method java/lang/String.contains:(Ljava/lang/CharSequence;)Z
      53: invokestatic  #23                 // Method org/junit/Assert.assertTrue:(Z)V
      56: return

  public void testLoggingWithTraceOn();
    Code:
       0: getstatic     #5                  // Field conf:Lorg/apache/hadoop/conf/Configuration;
       3: ldc           #11                 // String hbase.ipc.trace.log.max.length
       5: sipush        250
       8: invokevirtual #12                 // Method org/apache/hadoop/conf/Configuration.setInt:(Ljava/lang/String;I)V
      11: getstatic     #13                 // Field rpcServerLog:Lorg/apache/log4j/Logger;
      14: getstatic     #24                 // Field org/apache/log4j/Level.TRACE:Lorg/apache/log4j/Level;
      17: invokevirtual #15                 // Method org/apache/log4j/Logger.setLevel:(Lorg/apache/log4j/Level;)V
      20: getstatic     #2                  // Field mockRpcServer:Lorg/apache/hadoop/hbase/ipc/RpcServer;
      23: ldc           #17                 // String This is dummy message for testing:: region { type: REGION_NAME value: \"hbase:meta,,1\" } scan { column { family: \"info\" } time_range { from: 0 to: 9223372036854775807 } max_versions: 1 cache_blocks: true max_result_size: 2097152 caching: 2147483647 } number_of_rows: 2147483647 close_scanner: false client_handles_partials: true client_handles_heartbeats: true track_scan_metrics: false
      25: invokevirtual #9                  // Method org/apache/hadoop/hbase/ipc/RpcServer.truncateTraceLog:(Ljava/lang/String;)Ljava/lang/String;
      28: astore_1
      29: sipush        250
      32: ldc           #19                 // String  <TRUNCATED>
      34: invokevirtual #20                 // Method java/lang/String.length:()I
      37: iadd
      38: i2l
      39: aload_1
      40: invokevirtual #20                 // Method java/lang/String.length:()I
      43: i2l
      44: invokestatic  #21                 // Method org/junit/Assert.assertEquals:(JJ)V
      47: aload_1
      48: ldc           #19                 // String  <TRUNCATED>
      50: invokevirtual #22                 // Method java/lang/String.contains:(Ljava/lang/CharSequence;)Z
      53: invokestatic  #23                 // Method org/junit/Assert.assertTrue:(Z)V
      56: return

  public void testLoggingWithTraceOnLargeMax();
    Code:
       0: getstatic     #5                  // Field conf:Lorg/apache/hadoop/conf/Configuration;
       3: ldc           #11                 // String hbase.ipc.trace.log.max.length
       5: sipush        2000
       8: invokevirtual #12                 // Method org/apache/hadoop/conf/Configuration.setInt:(Ljava/lang/String;I)V
      11: getstatic     #13                 // Field rpcServerLog:Lorg/apache/log4j/Logger;
      14: getstatic     #24                 // Field org/apache/log4j/Level.TRACE:Lorg/apache/log4j/Level;
      17: invokevirtual #15                 // Method org/apache/log4j/Logger.setLevel:(Lorg/apache/log4j/Level;)V
      20: getstatic     #2                  // Field mockRpcServer:Lorg/apache/hadoop/hbase/ipc/RpcServer;
      23: ldc           #17                 // String This is dummy message for testing:: region { type: REGION_NAME value: \"hbase:meta,,1\" } scan { column { family: \"info\" } time_range { from: 0 to: 9223372036854775807 } max_versions: 1 cache_blocks: true max_result_size: 2097152 caching: 2147483647 } number_of_rows: 2147483647 close_scanner: false client_handles_partials: true client_handles_heartbeats: true track_scan_metrics: false
      25: invokevirtual #9                  // Method org/apache/hadoop/hbase/ipc/RpcServer.truncateTraceLog:(Ljava/lang/String;)Ljava/lang/String;
      28: astore_1
      29: getstatic     #25                 // Field TRACE_LOG_LENGTH:I
      32: i2l
      33: aload_1
      34: invokevirtual #20                 // Method java/lang/String.length:()I
      37: i2l
      38: invokestatic  #21                 // Method org/junit/Assert.assertEquals:(JJ)V
      41: getstatic     #2                  // Field mockRpcServer:Lorg/apache/hadoop/hbase/ipc/RpcServer;
      44: ldc           #17                 // String This is dummy message for testing:: region { type: REGION_NAME value: \"hbase:meta,,1\" } scan { column { family: \"info\" } time_range { from: 0 to: 9223372036854775807 } max_versions: 1 cache_blocks: true max_result_size: 2097152 caching: 2147483647 } number_of_rows: 2147483647 close_scanner: false client_handles_partials: true client_handles_heartbeats: true track_scan_metrics: false
      46: invokevirtual #9                  // Method org/apache/hadoop/hbase/ipc/RpcServer.truncateTraceLog:(Ljava/lang/String;)Ljava/lang/String;
      49: ldc           #19                 // String  <TRUNCATED>
      51: invokevirtual #22                 // Method java/lang/String.contains:(Ljava/lang/CharSequence;)Z
      54: invokestatic  #26                 // Method org/junit/Assert.assertFalse:(Z)V
      57: return

  static {};
    Code:
       0: ldc           #16                 // class org/apache/hadoop/hbase/ipc/TestRpcServerTraceLogging
       2: invokestatic  #27                 // Method org/apache/hadoop/hbase/HBaseClassTestRule.forClass:(Ljava/lang/Class;)Lorg/apache/hadoop/hbase/HBaseClassTestRule;
       5: putstatic     #28                 // Field CLASS_RULE:Lorg/apache/hadoop/hbase/HBaseClassTestRule;
       8: ldc           #18                 // class org/apache/hadoop/hbase/ipc/RpcServer
      10: invokestatic  #29                 // Method org/apache/log4j/Logger.getLogger:(Ljava/lang/Class;)Lorg/apache/log4j/Logger;
      13: putstatic     #13                 // Field rpcServerLog:Lorg/apache/log4j/Logger;
      16: ldc           #17                 // String This is dummy message for testing:: region { type: REGION_NAME value: \"hbase:meta,,1\" } scan { column { family: \"info\" } time_range { from: 0 to: 9223372036854775807 } max_versions: 1 cache_blocks: true max_result_size: 2097152 caching: 2147483647 } number_of_rows: 2147483647 close_scanner: false client_handles_partials: true client_handles_heartbeats: true track_scan_metrics: false
      18: invokevirtual #20                 // Method java/lang/String.length:()I
      21: putstatic     #25                 // Field TRACE_LOG_LENGTH:I
      24: ldc           #18                 // class org/apache/hadoop/hbase/ipc/RpcServer
      26: invokestatic  #30                 // Method org/mockito/Mockito.mock:(Ljava/lang/Class;)Ljava/lang/Object;
      29: checkcast     #18                 // class org/apache/hadoop/hbase/ipc/RpcServer
      32: putstatic     #2                  // Field mockRpcServer:Lorg/apache/hadoop/hbase/ipc/RpcServer;
      35: new           #31                 // class org/apache/hadoop/conf/Configuration
      38: dup
      39: iconst_0
      40: invokespecial #32                 // Method org/apache/hadoop/conf/Configuration."<init>":(Z)V
      43: putstatic     #5                  // Field conf:Lorg/apache/hadoop/conf/Configuration;
      46: return
}
