Compiled from "TestSecureIPC.java"
public class org.apache.hadoop.hbase.security.TestSecureIPC {
  public static final org.apache.hadoop.hbase.HBaseClassTestRule CLASS_RULE;

  java.lang.String krbKeytab;

  java.lang.String krbPrincipal;

  org.apache.hadoop.security.UserGroupInformation ugi;

  org.apache.hadoop.conf.Configuration clientConf;

  org.apache.hadoop.conf.Configuration serverConf;

  public org.junit.rules.ExpectedException exception;

  public java.lang.String rpcClientImpl;

  public java.lang.String rpcServerImpl;

  public org.apache.hadoop.hbase.security.TestSecureIPC();
    Code:
       0: aload_0
       1: invokespecial #1                  // Method java/lang/Object."<init>":()V
       4: aload_0
       5: invokestatic  #2                  // Method org/junit/rules/ExpectedException.none:()Lorg/junit/rules/ExpectedException;
       8: putfield      #3                  // Field exception:Lorg/junit/rules/ExpectedException;
      11: return

  public static java.util.Collection<java.lang.Object[]> parameters();
    Code:
       0: new           #4                  // class java/util/ArrayList
       3: dup
       4: invokespecial #5                  // Method java/util/ArrayList."<init>":()V
       7: astore_0
       8: iconst_2
       9: anewarray     #6                  // class java/lang/String
      12: dup
      13: iconst_0
      14: ldc           #7                  // class org/apache/hadoop/hbase/ipc/BlockingRpcClient
      16: invokevirtual #8                  // Method java/lang/Class.getName:()Ljava/lang/String;
      19: aastore
      20: dup
      21: iconst_1
      22: ldc           #9                  // class org/apache/hadoop/hbase/ipc/NettyRpcClient
      24: invokevirtual #8                  // Method java/lang/Class.getName:()Ljava/lang/String;
      27: aastore
      28: invokestatic  #10                 // Method java/util/Arrays.asList:([Ljava/lang/Object;)Ljava/util/List;
      31: astore_1
      32: iconst_2
      33: anewarray     #6                  // class java/lang/String
      36: dup
      37: iconst_0
      38: ldc           #11                 // class org/apache/hadoop/hbase/ipc/SimpleRpcServer
      40: invokevirtual #8                  // Method java/lang/Class.getName:()Ljava/lang/String;
      43: aastore
      44: dup
      45: iconst_1
      46: ldc           #12                 // class org/apache/hadoop/hbase/ipc/NettyRpcServer
      48: invokevirtual #8                  // Method java/lang/Class.getName:()Ljava/lang/String;
      51: aastore
      52: invokestatic  #10                 // Method java/util/Arrays.asList:([Ljava/lang/Object;)Ljava/util/List;
      55: astore_2
      56: aload_1
      57: invokeinterface #13,  1           // InterfaceMethod java/util/List.iterator:()Ljava/util/Iterator;
      62: astore_3
      63: aload_3
      64: invokeinterface #14,  1           // InterfaceMethod java/util/Iterator.hasNext:()Z
      69: ifeq          140
      72: aload_3
      73: invokeinterface #15,  1           // InterfaceMethod java/util/Iterator.next:()Ljava/lang/Object;
      78: checkcast     #6                  // class java/lang/String
      81: astore        4
      83: aload_2
      84: invokeinterface #13,  1           // InterfaceMethod java/util/List.iterator:()Ljava/util/Iterator;
      89: astore        5
      91: aload         5
      93: invokeinterface #14,  1           // InterfaceMethod java/util/Iterator.hasNext:()Z
      98: ifeq          137
     101: aload         5
     103: invokeinterface #15,  1           // InterfaceMethod java/util/Iterator.next:()Ljava/lang/Object;
     108: checkcast     #6                  // class java/lang/String
     111: astore        6
     113: aload_0
     114: iconst_2
     115: anewarray     #16                 // class java/lang/Object
     118: dup
     119: iconst_0
     120: aload         4
     122: aastore
     123: dup
     124: iconst_1
     125: aload         6
     127: aastore
     128: invokeinterface #17,  2           // InterfaceMethod java/util/List.add:(Ljava/lang/Object;)Z
     133: pop
     134: goto          91
     137: goto          63
     140: aload_0
     141: areturn

  public static void setUp() throws java.lang.Exception;
    Code:
       0: getstatic     #18                 // Field TEST_UTIL:Lorg/apache/hadoop/hbase/HBaseTestingUtility;
       3: getstatic     #19                 // Field KEYTAB_FILE:Ljava/io/File;
       6: invokevirtual #20                 // Method org/apache/hadoop/hbase/HBaseTestingUtility.setupMiniKdc:(Ljava/io/File;)Lorg/apache/hadoop/minikdc/MiniKdc;
       9: putstatic     #21                 // Field KDC:Lorg/apache/hadoop/minikdc/MiniKdc;
      12: new           #22                 // class java/lang/StringBuilder
      15: dup
      16: invokespecial #23                 // Method java/lang/StringBuilder."<init>":()V
      19: ldc           #24                 // String hbase/
      21: invokevirtual #25                 // Method java/lang/StringBuilder.append:(Ljava/lang/String;)Ljava/lang/StringBuilder;
      24: getstatic     #26                 // Field HOST:Ljava/lang/String;
      27: invokevirtual #25                 // Method java/lang/StringBuilder.append:(Ljava/lang/String;)Ljava/lang/StringBuilder;
      30: invokevirtual #27                 // Method java/lang/StringBuilder.toString:()Ljava/lang/String;
      33: putstatic     #28                 // Field PRINCIPAL:Ljava/lang/String;
      36: getstatic     #21                 // Field KDC:Lorg/apache/hadoop/minikdc/MiniKdc;
      39: getstatic     #19                 // Field KEYTAB_FILE:Ljava/io/File;
      42: iconst_1
      43: anewarray     #6                  // class java/lang/String
      46: dup
      47: iconst_0
      48: getstatic     #28                 // Field PRINCIPAL:Ljava/lang/String;
      51: aastore
      52: invokevirtual #29                 // Method org/apache/hadoop/minikdc/MiniKdc.createPrincipal:(Ljava/io/File;[Ljava/lang/String;)V
      55: new           #22                 // class java/lang/StringBuilder
      58: dup
      59: invokespecial #23                 // Method java/lang/StringBuilder."<init>":()V
      62: getstatic     #28                 // Field PRINCIPAL:Ljava/lang/String;
      65: invokevirtual #25                 // Method java/lang/StringBuilder.append:(Ljava/lang/String;)Ljava/lang/StringBuilder;
      68: ldc           #30                 // String @
      70: invokevirtual #25                 // Method java/lang/StringBuilder.append:(Ljava/lang/String;)Ljava/lang/StringBuilder;
      73: getstatic     #21                 // Field KDC:Lorg/apache/hadoop/minikdc/MiniKdc;
      76: invokevirtual #31                 // Method org/apache/hadoop/minikdc/MiniKdc.getRealm:()Ljava/lang/String;
      79: invokevirtual #25                 // Method java/lang/StringBuilder.append:(Ljava/lang/String;)Ljava/lang/StringBuilder;
      82: invokevirtual #27                 // Method java/lang/StringBuilder.toString:()Ljava/lang/String;
      85: invokestatic  #32                 // Method org/apache/hadoop/hbase/security/HBaseKerberosUtils.setPrincipalForTesting:(Ljava/lang/String;)V
      88: return

  public static void tearDown() throws java.io.IOException;
    Code:
       0: getstatic     #21                 // Field KDC:Lorg/apache/hadoop/minikdc/MiniKdc;
       3: ifnull        12
       6: getstatic     #21                 // Field KDC:Lorg/apache/hadoop/minikdc/MiniKdc;
       9: invokevirtual #33                 // Method org/apache/hadoop/minikdc/MiniKdc.stop:()V
      12: getstatic     #18                 // Field TEST_UTIL:Lorg/apache/hadoop/hbase/HBaseTestingUtility;
      15: invokevirtual #34                 // Method org/apache/hadoop/hbase/HBaseTestingUtility.cleanupTestDir:()Z
      18: pop
      19: return

  public void setUpTest() throws java.lang.Exception;
    Code:
       0: aload_0
       1: invokestatic  #35                 // Method org/apache/hadoop/hbase/security/HBaseKerberosUtils.getKeytabFileForTesting:()Ljava/lang/String;
       4: putfield      #36                 // Field krbKeytab:Ljava/lang/String;
       7: aload_0
       8: invokestatic  #37                 // Method org/apache/hadoop/hbase/security/HBaseKerberosUtils.getPrincipalForTesting:()Ljava/lang/String;
      11: putfield      #38                 // Field krbPrincipal:Ljava/lang/String;
      14: aload_0
      15: aload_0
      16: aload_0
      17: getfield      #36                 // Field krbKeytab:Ljava/lang/String;
      20: aload_0
      21: getfield      #38                 // Field krbPrincipal:Ljava/lang/String;
      24: invokespecial #39                 // Method loginKerberosPrincipal:(Ljava/lang/String;Ljava/lang/String;)Lorg/apache/hadoop/security/UserGroupInformation;
      27: putfield      #40                 // Field ugi:Lorg/apache/hadoop/security/UserGroupInformation;
      30: aload_0
      31: invokestatic  #41                 // Method org/apache/hadoop/hbase/security/HBaseKerberosUtils.getSecuredConfiguration:()Lorg/apache/hadoop/conf/Configuration;
      34: putfield      #42                 // Field clientConf:Lorg/apache/hadoop/conf/Configuration;
      37: aload_0
      38: getfield      #42                 // Field clientConf:Lorg/apache/hadoop/conf/Configuration;
      41: ldc           #44                 // String hbase.rpc.client.impl
      43: aload_0
      44: getfield      #45                 // Field rpcClientImpl:Ljava/lang/String;
      47: invokevirtual #46                 // Method org/apache/hadoop/conf/Configuration.set:(Ljava/lang/String;Ljava/lang/String;)V
      50: aload_0
      51: invokestatic  #41                 // Method org/apache/hadoop/hbase/security/HBaseKerberosUtils.getSecuredConfiguration:()Lorg/apache/hadoop/conf/Configuration;
      54: putfield      #47                 // Field serverConf:Lorg/apache/hadoop/conf/Configuration;
      57: aload_0
      58: getfield      #47                 // Field serverConf:Lorg/apache/hadoop/conf/Configuration;
      61: ldc           #49                 // String hbase.rpc.server.impl
      63: aload_0
      64: getfield      #50                 // Field rpcServerImpl:Ljava/lang/String;
      67: invokevirtual #46                 // Method org/apache/hadoop/conf/Configuration.set:(Ljava/lang/String;Ljava/lang/String;)V
      70: return

  public void testRpcCallWithEnabledKerberosSaslAuth() throws java.lang.Exception;
    Code:
       0: invokestatic  #51                 // Method org/apache/hadoop/security/UserGroupInformation.getCurrentUser:()Lorg/apache/hadoop/security/UserGroupInformation;
       3: astore_1
       4: aload_1
       5: aload_0
       6: getfield      #40                 // Field ugi:Lorg/apache/hadoop/security/UserGroupInformation;
       9: invokestatic  #52                 // Method org/junit/Assert.assertSame:(Ljava/lang/Object;Ljava/lang/Object;)V
      12: getstatic     #53                 // Field org/apache/hadoop/security/UserGroupInformation$AuthenticationMethod.KERBEROS:Lorg/apache/hadoop/security/UserGroupInformation$AuthenticationMethod;
      15: aload_0
      16: getfield      #40                 // Field ugi:Lorg/apache/hadoop/security/UserGroupInformation;
      19: invokevirtual #54                 // Method org/apache/hadoop/security/UserGroupInformation.getAuthenticationMethod:()Lorg/apache/hadoop/security/UserGroupInformation$AuthenticationMethod;
      22: invokestatic  #55                 // Method org/junit/Assert.assertEquals:(Ljava/lang/Object;Ljava/lang/Object;)V
      25: aload_0
      26: getfield      #38                 // Field krbPrincipal:Ljava/lang/String;
      29: aload_0
      30: getfield      #40                 // Field ugi:Lorg/apache/hadoop/security/UserGroupInformation;
      33: invokevirtual #56                 // Method org/apache/hadoop/security/UserGroupInformation.getUserName:()Ljava/lang/String;
      36: invokestatic  #55                 // Method org/junit/Assert.assertEquals:(Ljava/lang/Object;Ljava/lang/Object;)V
      39: aload_0
      40: aload_1
      41: invokestatic  #57                 // Method org/apache/hadoop/hbase/security/User.create:(Lorg/apache/hadoop/security/UserGroupInformation;)Lorg/apache/hadoop/hbase/security/User;
      44: invokespecial #58                 // Method callRpcService:(Lorg/apache/hadoop/hbase/security/User;)V
      47: return

  public void testRpcFallbackToSimpleAuth() throws java.lang.Exception;
    Code:
       0: ldc           #59                 // String testuser
       2: astore_1
       3: aload_1
       4: iconst_1
       5: anewarray     #6                  // class java/lang/String
       8: dup
       9: iconst_0
      10: aload_1
      11: aastore
      12: invokestatic  #60                 // Method org/apache/hadoop/security/UserGroupInformation.createUserForTesting:(Ljava/lang/String;[Ljava/lang/String;)Lorg/apache/hadoop/security/UserGroupInformation;
      15: astore_2
      16: aload_0
      17: getfield      #40                 // Field ugi:Lorg/apache/hadoop/security/UserGroupInformation;
      20: aload_2
      21: invokestatic  #61                 // Method org/junit/Assert.assertNotSame:(Ljava/lang/Object;Ljava/lang/Object;)V
      24: getstatic     #62                 // Field org/apache/hadoop/security/UserGroupInformation$AuthenticationMethod.SIMPLE:Lorg/apache/hadoop/security/UserGroupInformation$AuthenticationMethod;
      27: aload_2
      28: invokevirtual #54                 // Method org/apache/hadoop/security/UserGroupInformation.getAuthenticationMethod:()Lorg/apache/hadoop/security/UserGroupInformation$AuthenticationMethod;
      31: invokestatic  #55                 // Method org/junit/Assert.assertEquals:(Ljava/lang/Object;Ljava/lang/Object;)V
      34: aload_1
      35: aload_2
      36: invokevirtual #56                 // Method org/apache/hadoop/security/UserGroupInformation.getUserName:()Ljava/lang/String;
      39: invokestatic  #55                 // Method org/junit/Assert.assertEquals:(Ljava/lang/Object;Ljava/lang/Object;)V
      42: aload_0
      43: getfield      #42                 // Field clientConf:Lorg/apache/hadoop/conf/Configuration;
      46: ldc           #64                 // String hbase.security.authentication
      48: ldc           #65                 // String simple
      50: invokevirtual #46                 // Method org/apache/hadoop/conf/Configuration.set:(Ljava/lang/String;Ljava/lang/String;)V
      53: aload_0
      54: getfield      #47                 // Field serverConf:Lorg/apache/hadoop/conf/Configuration;
      57: ldc           #67                 // String hbase.ipc.server.fallback-to-simple-auth-allowed
      59: iconst_1
      60: invokevirtual #68                 // Method org/apache/hadoop/conf/Configuration.setBoolean:(Ljava/lang/String;Z)V
      63: aload_0
      64: aload_2
      65: invokestatic  #57                 // Method org/apache/hadoop/hbase/security/User.create:(Lorg/apache/hadoop/security/UserGroupInformation;)Lorg/apache/hadoop/hbase/security/User;
      68: invokespecial #58                 // Method callRpcService:(Lorg/apache/hadoop/hbase/security/User;)V
      71: return

  void setRpcProtection(java.lang.String, java.lang.String);
    Code:
       0: aload_0
       1: getfield      #42                 // Field clientConf:Lorg/apache/hadoop/conf/Configuration;
       4: ldc           #69                 // String hbase.rpc.protection
       6: aload_1
       7: invokevirtual #46                 // Method org/apache/hadoop/conf/Configuration.set:(Ljava/lang/String;Ljava/lang/String;)V
      10: aload_0
      11: getfield      #47                 // Field serverConf:Lorg/apache/hadoop/conf/Configuration;
      14: ldc           #69                 // String hbase.rpc.protection
      16: aload_2
      17: invokevirtual #46                 // Method org/apache/hadoop/conf/Configuration.set:(Ljava/lang/String;Ljava/lang/String;)V
      20: return

  public void testSaslWithCommonQop() throws java.lang.Exception;
    Code:
       0: aload_0
       1: ldc           #70                 // String privacy,authentication
       3: ldc           #71                 // String authentication
       5: invokevirtual #72                 // Method setRpcProtection:(Ljava/lang/String;Ljava/lang/String;)V
       8: aload_0
       9: aload_0
      10: getfield      #40                 // Field ugi:Lorg/apache/hadoop/security/UserGroupInformation;
      13: invokestatic  #57                 // Method org/apache/hadoop/hbase/security/User.create:(Lorg/apache/hadoop/security/UserGroupInformation;)Lorg/apache/hadoop/hbase/security/User;
      16: invokespecial #58                 // Method callRpcService:(Lorg/apache/hadoop/hbase/security/User;)V
      19: aload_0
      20: ldc           #71                 // String authentication
      22: ldc           #70                 // String privacy,authentication
      24: invokevirtual #72                 // Method setRpcProtection:(Ljava/lang/String;Ljava/lang/String;)V
      27: aload_0
      28: aload_0
      29: getfield      #40                 // Field ugi:Lorg/apache/hadoop/security/UserGroupInformation;
      32: invokestatic  #57                 // Method org/apache/hadoop/hbase/security/User.create:(Lorg/apache/hadoop/security/UserGroupInformation;)Lorg/apache/hadoop/hbase/security/User;
      35: invokespecial #58                 // Method callRpcService:(Lorg/apache/hadoop/hbase/security/User;)V
      38: aload_0
      39: ldc           #73                 // String integrity,authentication
      41: ldc           #70                 // String privacy,authentication
      43: invokevirtual #72                 // Method setRpcProtection:(Ljava/lang/String;Ljava/lang/String;)V
      46: aload_0
      47: aload_0
      48: getfield      #40                 // Field ugi:Lorg/apache/hadoop/security/UserGroupInformation;
      51: invokestatic  #57                 // Method org/apache/hadoop/hbase/security/User.create:(Lorg/apache/hadoop/security/UserGroupInformation;)Lorg/apache/hadoop/hbase/security/User;
      54: invokespecial #58                 // Method callRpcService:(Lorg/apache/hadoop/hbase/security/User;)V
      57: aload_0
      58: ldc           #73                 // String integrity,authentication
      60: ldc           #73                 // String integrity,authentication
      62: invokevirtual #72                 // Method setRpcProtection:(Ljava/lang/String;Ljava/lang/String;)V
      65: aload_0
      66: aload_0
      67: getfield      #40                 // Field ugi:Lorg/apache/hadoop/security/UserGroupInformation;
      70: invokestatic  #57                 // Method org/apache/hadoop/hbase/security/User.create:(Lorg/apache/hadoop/security/UserGroupInformation;)Lorg/apache/hadoop/hbase/security/User;
      73: invokespecial #58                 // Method callRpcService:(Lorg/apache/hadoop/hbase/security/User;)V
      76: aload_0
      77: ldc           #70                 // String privacy,authentication
      79: ldc           #70                 // String privacy,authentication
      81: invokevirtual #72                 // Method setRpcProtection:(Ljava/lang/String;Ljava/lang/String;)V
      84: aload_0
      85: aload_0
      86: getfield      #40                 // Field ugi:Lorg/apache/hadoop/security/UserGroupInformation;
      89: invokestatic  #57                 // Method org/apache/hadoop/hbase/security/User.create:(Lorg/apache/hadoop/security/UserGroupInformation;)Lorg/apache/hadoop/hbase/security/User;
      92: invokespecial #58                 // Method callRpcService:(Lorg/apache/hadoop/hbase/security/User;)V
      95: return

  public void testSaslNoCommonQop() throws java.lang.Exception;
    Code:
       0: aload_0
       1: getfield      #3                  // Field exception:Lorg/junit/rules/ExpectedException;
       4: ldc           #74                 // class javax/security/sasl/SaslException
       6: invokevirtual #75                 // Method org/junit/rules/ExpectedException.expect:(Ljava/lang/Class;)V
       9: aload_0
      10: getfield      #3                  // Field exception:Lorg/junit/rules/ExpectedException;
      13: ldc           #76                 // String No common protection layer between client and server
      15: invokevirtual #77                 // Method org/junit/rules/ExpectedException.expectMessage:(Ljava/lang/String;)V
      18: aload_0
      19: ldc           #78                 // String integrity
      21: ldc           #79                 // String privacy
      23: invokevirtual #72                 // Method setRpcProtection:(Ljava/lang/String;Ljava/lang/String;)V
      26: aload_0
      27: aload_0
      28: getfield      #40                 // Field ugi:Lorg/apache/hadoop/security/UserGroupInformation;
      31: invokestatic  #57                 // Method org/apache/hadoop/hbase/security/User.create:(Lorg/apache/hadoop/security/UserGroupInformation;)Lorg/apache/hadoop/hbase/security/User;
      34: invokespecial #58                 // Method callRpcService:(Lorg/apache/hadoop/hbase/security/User;)V
      37: return

  public void testSaslWithCryptoAES() throws java.lang.Exception;
    Code:
       0: aload_0
       1: ldc           #79                 // String privacy
       3: ldc           #79                 // String privacy
       5: invokevirtual #72                 // Method setRpcProtection:(Ljava/lang/String;Ljava/lang/String;)V
       8: aload_0
       9: ldc           #80                 // String true
      11: ldc           #80                 // String true
      13: invokevirtual #81                 // Method setCryptoAES:(Ljava/lang/String;Ljava/lang/String;)V
      16: aload_0
      17: aload_0
      18: getfield      #40                 // Field ugi:Lorg/apache/hadoop/security/UserGroupInformation;
      21: invokestatic  #57                 // Method org/apache/hadoop/hbase/security/User.create:(Lorg/apache/hadoop/security/UserGroupInformation;)Lorg/apache/hadoop/hbase/security/User;
      24: invokespecial #58                 // Method callRpcService:(Lorg/apache/hadoop/hbase/security/User;)V
      27: return

  public void testDifferentConfWithCryptoAES() throws java.lang.Exception;
    Code:
       0: aload_0
       1: ldc           #79                 // String privacy
       3: ldc           #79                 // String privacy
       5: invokevirtual #72                 // Method setRpcProtection:(Ljava/lang/String;Ljava/lang/String;)V
       8: aload_0
       9: ldc           #82                 // String false
      11: ldc           #80                 // String true
      13: invokevirtual #81                 // Method setCryptoAES:(Ljava/lang/String;Ljava/lang/String;)V
      16: aload_0
      17: aload_0
      18: getfield      #40                 // Field ugi:Lorg/apache/hadoop/security/UserGroupInformation;
      21: invokestatic  #57                 // Method org/apache/hadoop/hbase/security/User.create:(Lorg/apache/hadoop/security/UserGroupInformation;)Lorg/apache/hadoop/hbase/security/User;
      24: invokespecial #58                 // Method callRpcService:(Lorg/apache/hadoop/hbase/security/User;)V
      27: aload_0
      28: ldc           #80                 // String true
      30: ldc           #82                 // String false
      32: invokevirtual #81                 // Method setCryptoAES:(Ljava/lang/String;Ljava/lang/String;)V
      35: aload_0
      36: aload_0
      37: getfield      #40                 // Field ugi:Lorg/apache/hadoop/security/UserGroupInformation;
      40: invokestatic  #57                 // Method org/apache/hadoop/hbase/security/User.create:(Lorg/apache/hadoop/security/UserGroupInformation;)Lorg/apache/hadoop/hbase/security/User;
      43: invokespecial #58                 // Method callRpcService:(Lorg/apache/hadoop/hbase/security/User;)V
      46: ldc           #83                 // String The exception should be thrown out for the rpc timeout.
      48: invokestatic  #84                 // Method org/junit/Assert.fail:(Ljava/lang/String;)V
      51: goto          55
      54: astore_1
      55: return
    Exception table:
       from    to  target type
          35    51    54   Class java/lang/Exception

  void setCryptoAES(java.lang.String, java.lang.String);
    Code:
       0: aload_0
       1: getfield      #42                 // Field clientConf:Lorg/apache/hadoop/conf/Configuration;
       4: ldc           #86                 // String hbase.rpc.crypto.encryption.aes.enabled
       6: aload_1
       7: invokevirtual #46                 // Method org/apache/hadoop/conf/Configuration.set:(Ljava/lang/String;Ljava/lang/String;)V
      10: aload_0
      11: getfield      #47                 // Field serverConf:Lorg/apache/hadoop/conf/Configuration;
      14: ldc           #86                 // String hbase.rpc.crypto.encryption.aes.enabled
      16: aload_2
      17: invokevirtual #46                 // Method org/apache/hadoop/conf/Configuration.set:(Ljava/lang/String;Ljava/lang/String;)V
      20: return

  static {};
    Code:
       0: ldc           #133                // class org/apache/hadoop/hbase/security/TestSecureIPC
       2: invokestatic  #134                // Method org/apache/hadoop/hbase/HBaseClassTestRule.forClass:(Ljava/lang/Class;)Lorg/apache/hadoop/hbase/HBaseClassTestRule;
       5: putstatic     #135                // Field CLASS_RULE:Lorg/apache/hadoop/hbase/HBaseClassTestRule;
       8: new           #136                // class org/apache/hadoop/hbase/HBaseTestingUtility
      11: dup
      12: invokespecial #137                // Method org/apache/hadoop/hbase/HBaseTestingUtility."<init>":()V
      15: putstatic     #18                 // Field TEST_UTIL:Lorg/apache/hadoop/hbase/HBaseTestingUtility;
      18: new           #138                // class java/io/File
      21: dup
      22: getstatic     #18                 // Field TEST_UTIL:Lorg/apache/hadoop/hbase/HBaseTestingUtility;
      25: ldc           #139                // String keytab
      27: invokevirtual #140                // Method org/apache/hadoop/hbase/HBaseTestingUtility.getDataTestDir:(Ljava/lang/String;)Lorg/apache/hadoop/fs/Path;
      30: invokevirtual #141                // Method org/apache/hadoop/fs/Path.toUri:()Ljava/net/URI;
      33: invokevirtual #142                // Method java/net/URI.getPath:()Ljava/lang/String;
      36: invokespecial #143                // Method java/io/File."<init>":(Ljava/lang/String;)V
      39: putstatic     #19                 // Field KEYTAB_FILE:Ljava/io/File;
      42: ldc           #144                // String localhost
      44: putstatic     #26                 // Field HOST:Ljava/lang/String;
      47: return
}
