Compiled from "TestProcedureToString.java"
class org.apache.hadoop.hbase.procedure2.TestProcedureToString$SimpleStateMachineProcedure extends org.apache.hadoop.hbase.procedure2.StateMachineProcedure<org.apache.hadoop.hbase.procedure2.TestProcedureToString$BasicProcedureEnv, org.apache.hadoop.hbase.shaded.protobuf.generated.MasterProcedureProtos$ServerCrashState> {
  org.apache.hadoop.hbase.procedure2.TestProcedureToString$SimpleStateMachineProcedure();
    Code:
       0: aload_0
       1: invokespecial #1                  // Method org/apache/hadoop/hbase/procedure2/StateMachineProcedure."<init>":()V
       4: return

  protected org.apache.hadoop.hbase.procedure2.StateMachineProcedure$Flow executeFromState(org.apache.hadoop.hbase.procedure2.TestProcedureToString$BasicProcedureEnv, org.apache.hadoop.hbase.shaded.protobuf.generated.MasterProcedureProtos$ServerCrashState) throws org.apache.hadoop.hbase.procedure2.ProcedureYieldException, java.lang.InterruptedException;
    Code:
       0: aconst_null
       1: areturn

  protected void rollbackState(org.apache.hadoop.hbase.procedure2.TestProcedureToString$BasicProcedureEnv, org.apache.hadoop.hbase.shaded.protobuf.generated.MasterProcedureProtos$ServerCrashState) throws java.io.IOException, java.lang.InterruptedException;
    Code:
       0: return

  protected org.apache.hadoop.hbase.shaded.protobuf.generated.MasterProcedureProtos$ServerCrashState getState(int);
    Code:
       0: iload_1
       1: invokestatic  #2                  // Method org/apache/hadoop/hbase/shaded/protobuf/generated/MasterProcedureProtos$ServerCrashState.valueOf:(I)Lorg/apache/hadoop/hbase/shaded/protobuf/generated/MasterProcedureProtos$ServerCrashState;
       4: areturn

  protected int getStateId(org.apache.hadoop.hbase.shaded.protobuf.generated.MasterProcedureProtos$ServerCrashState);
    Code:
       0: aload_1
       1: invokevirtual #3                  // Method org/apache/hadoop/hbase/shaded/protobuf/generated/MasterProcedureProtos$ServerCrashState.getNumber:()I
       4: ireturn

  protected org.apache.hadoop.hbase.shaded.protobuf.generated.MasterProcedureProtos$ServerCrashState getInitialState();
    Code:
       0: aconst_null
       1: areturn

  protected boolean abort(org.apache.hadoop.hbase.procedure2.TestProcedureToString$BasicProcedureEnv);
    Code:
       0: iconst_0
       1: ireturn

  protected boolean abort(java.lang.Object);
    Code:
       0: aload_0
       1: aload_1
       2: checkcast     #4                  // class org/apache/hadoop/hbase/procedure2/TestProcedureToString$BasicProcedureEnv
       5: invokevirtual #5                  // Method abort:(Lorg/apache/hadoop/hbase/procedure2/TestProcedureToString$BasicProcedureEnv;)Z
       8: ireturn

  protected java.lang.Object getInitialState();
    Code:
       0: aload_0
       1: invokevirtual #6                  // Method getInitialState:()Lorg/apache/hadoop/hbase/shaded/protobuf/generated/MasterProcedureProtos$ServerCrashState;
       4: areturn

  protected int getStateId(java.lang.Object);
    Code:
       0: aload_0
       1: aload_1
       2: checkcast     #7                  // class org/apache/hadoop/hbase/shaded/protobuf/generated/MasterProcedureProtos$ServerCrashState
       5: invokevirtual #8                  // Method getStateId:(Lorg/apache/hadoop/hbase/shaded/protobuf/generated/MasterProcedureProtos$ServerCrashState;)I
       8: ireturn

  protected java.lang.Object getState(int);
    Code:
       0: aload_0
       1: iload_1
       2: invokevirtual #9                  // Method getState:(I)Lorg/apache/hadoop/hbase/shaded/protobuf/generated/MasterProcedureProtos$ServerCrashState;
       5: areturn

  protected void rollbackState(java.lang.Object, java.lang.Object) throws java.io.IOException, java.lang.InterruptedException;
    Code:
       0: aload_0
       1: aload_1
       2: checkcast     #4                  // class org/apache/hadoop/hbase/procedure2/TestProcedureToString$BasicProcedureEnv
       5: aload_2
       6: checkcast     #7                  // class org/apache/hadoop/hbase/shaded/protobuf/generated/MasterProcedureProtos$ServerCrashState
       9: invokevirtual #10                 // Method rollbackState:(Lorg/apache/hadoop/hbase/procedure2/TestProcedureToString$BasicProcedureEnv;Lorg/apache/hadoop/hbase/shaded/protobuf/generated/MasterProcedureProtos$ServerCrashState;)V
      12: return

  protected org.apache.hadoop.hbase.procedure2.StateMachineProcedure$Flow executeFromState(java.lang.Object, java.lang.Object) throws org.apache.hadoop.hbase.procedure2.ProcedureSuspendedException, org.apache.hadoop.hbase.procedure2.ProcedureYieldException, java.lang.InterruptedException;
    Code:
       0: aload_0
       1: aload_1
       2: checkcast     #4                  // class org/apache/hadoop/hbase/procedure2/TestProcedureToString$BasicProcedureEnv
       5: aload_2
       6: checkcast     #7                  // class org/apache/hadoop/hbase/shaded/protobuf/generated/MasterProcedureProtos$ServerCrashState
       9: invokevirtual #11                 // Method executeFromState:(Lorg/apache/hadoop/hbase/procedure2/TestProcedureToString$BasicProcedureEnv;Lorg/apache/hadoop/hbase/shaded/protobuf/generated/MasterProcedureProtos$ServerCrashState;)Lorg/apache/hadoop/hbase/procedure2/StateMachineProcedure$Flow;
      12: areturn
}
