Compiled from "TestDisabledWAL.java"
public class org.apache.hadoop.hbase.wal.TestDisabledWAL {
  public static final org.apache.hadoop.hbase.HBaseClassTestRule CLASS_RULE;

  public org.junit.rules.TestName name;

  static final org.apache.hadoop.hbase.HBaseTestingUtility TEST_UTIL;

  public org.apache.hadoop.hbase.wal.TestDisabledWAL();
    Code:
       0: aload_0
       1: invokespecial #1                  // Method java/lang/Object."<init>":()V
       4: aload_0
       5: new           #2                  // class org/junit/rules/TestName
       8: dup
       9: invokespecial #3                  // Method org/junit/rules/TestName."<init>":()V
      12: putfield      #4                  // Field name:Lorg/junit/rules/TestName;
      15: aload_0
      16: ldc           #5                  // String f1
      18: invokestatic  #6                  // Method org/apache/hadoop/hbase/util/Bytes.toBytes:(Ljava/lang/String;)[B
      21: putfield      #7                  // Field fam:[B
      24: return

  public static void beforeClass() throws java.lang.Exception;
    Code:
       0: getstatic     #8                  // Field TEST_UTIL:Lorg/apache/hadoop/hbase/HBaseTestingUtility;
       3: invokevirtual #9                  // Method org/apache/hadoop/hbase/HBaseTestingUtility.getConfiguration:()Lorg/apache/hadoop/conf/Configuration;
       6: astore_0
       7: aload_0
       8: ldc           #10                 // String hbase.regionserver.hlog.enabled
      10: iconst_0
      11: invokevirtual #11                 // Method org/apache/hadoop/conf/Configuration.setBoolean:(Ljava/lang/String;Z)V
      14: getstatic     #8                  // Field TEST_UTIL:Lorg/apache/hadoop/hbase/HBaseTestingUtility;
      17: invokevirtual #12                 // Method org/apache/hadoop/hbase/HBaseTestingUtility.startMiniCluster:()Lorg/apache/hadoop/hbase/MiniHBaseCluster;
      20: pop
      21: goto          64
      24: astore_1
      25: getstatic     #15                 // Field LOG:Lorg/slf4j/Logger;
      28: ldc           #16                 // String Master failed to start.
      30: aload_1
      31: invokeinterface #17,  3           // InterfaceMethod org/slf4j/Logger.error:(Ljava/lang/String;Ljava/lang/Throwable;)V
      36: new           #18                 // class java/lang/StringBuilder
      39: dup
      40: invokespecial #19                 // Method java/lang/StringBuilder."<init>":()V
      43: ldc           #20                 // String Failed to start cluster. Reason being:
      45: invokevirtual #21                 // Method java/lang/StringBuilder.append:(Ljava/lang/String;)Ljava/lang/StringBuilder;
      48: aload_1
      49: invokevirtual #22                 // Method java/lang/Exception.getCause:()Ljava/lang/Throwable;
      52: invokevirtual #23                 // Method java/lang/Throwable.getMessage:()Ljava/lang/String;
      55: invokevirtual #21                 // Method java/lang/StringBuilder.append:(Ljava/lang/String;)Ljava/lang/StringBuilder;
      58: invokevirtual #24                 // Method java/lang/StringBuilder.toString:()Ljava/lang/String;
      61: invokestatic  #25                 // Method org/junit/Assert.fail:(Ljava/lang/String;)V
      64: return
    Exception table:
       from    to  target type
          14    21    24   Class java/lang/RuntimeException
          14    21    24   Class java/io/IOException

  public static void afterClass() throws java.lang.Exception;
    Code:
       0: getstatic     #8                  // Field TEST_UTIL:Lorg/apache/hadoop/hbase/HBaseTestingUtility;
       3: invokevirtual #26                 // Method org/apache/hadoop/hbase/HBaseTestingUtility.shutdownMiniCluster:()V
       6: return

  public void setup() throws java.lang.Exception;
    Code:
       0: aload_0
       1: aload_0
       2: getfield      #4                  // Field name:Lorg/junit/rules/TestName;
       5: invokevirtual #27                 // Method org/junit/rules/TestName.getMethodName:()Ljava/lang/String;
       8: ldc           #28                 // String [^a-zA-Z0-9]
      10: ldc           #29                 // String _
      12: invokevirtual #30                 // Method java/lang/String.replaceAll:(Ljava/lang/String;Ljava/lang/String;)Ljava/lang/String;
      15: invokestatic  #31                 // Method org/apache/hadoop/hbase/TableName.valueOf:(Ljava/lang/String;)Lorg/apache/hadoop/hbase/TableName;
      18: putfield      #32                 // Field tableName:Lorg/apache/hadoop/hbase/TableName;
      21: getstatic     #15                 // Field LOG:Lorg/slf4j/Logger;
      24: new           #18                 // class java/lang/StringBuilder
      27: dup
      28: invokespecial #19                 // Method java/lang/StringBuilder."<init>":()V
      31: ldc           #33                 // String Creating table
      33: invokevirtual #21                 // Method java/lang/StringBuilder.append:(Ljava/lang/String;)Ljava/lang/StringBuilder;
      36: aload_0
      37: getfield      #32                 // Field tableName:Lorg/apache/hadoop/hbase/TableName;
      40: invokevirtual #34                 // Method java/lang/StringBuilder.append:(Ljava/lang/Object;)Ljava/lang/StringBuilder;
      43: invokevirtual #24                 // Method java/lang/StringBuilder.toString:()Ljava/lang/String;
      46: invokeinterface #35,  2           // InterfaceMethod org/slf4j/Logger.info:(Ljava/lang/String;)V
      51: aload_0
      52: getstatic     #8                  // Field TEST_UTIL:Lorg/apache/hadoop/hbase/HBaseTestingUtility;
      55: aload_0
      56: getfield      #32                 // Field tableName:Lorg/apache/hadoop/hbase/TableName;
      59: aload_0
      60: getfield      #7                  // Field fam:[B
      63: invokevirtual #36                 // Method org/apache/hadoop/hbase/HBaseTestingUtility.createTable:(Lorg/apache/hadoop/hbase/TableName;[B)Lorg/apache/hadoop/hbase/client/Table;
      66: putfield      #37                 // Field table:Lorg/apache/hadoop/hbase/client/Table;
      69: return

  public void cleanup() throws java.lang.Exception;
    Code:
       0: getstatic     #15                 // Field LOG:Lorg/slf4j/Logger;
       3: new           #18                 // class java/lang/StringBuilder
       6: dup
       7: invokespecial #19                 // Method java/lang/StringBuilder."<init>":()V
      10: ldc           #38                 // String Deleting table
      12: invokevirtual #21                 // Method java/lang/StringBuilder.append:(Ljava/lang/String;)Ljava/lang/StringBuilder;
      15: aload_0
      16: getfield      #32                 // Field tableName:Lorg/apache/hadoop/hbase/TableName;
      19: invokevirtual #34                 // Method java/lang/StringBuilder.append:(Ljava/lang/Object;)Ljava/lang/StringBuilder;
      22: invokevirtual #24                 // Method java/lang/StringBuilder.toString:()Ljava/lang/String;
      25: invokeinterface #35,  2           // InterfaceMethod org/slf4j/Logger.info:(Ljava/lang/String;)V
      30: getstatic     #8                  // Field TEST_UTIL:Lorg/apache/hadoop/hbase/HBaseTestingUtility;
      33: aload_0
      34: getfield      #32                 // Field tableName:Lorg/apache/hadoop/hbase/TableName;
      37: invokevirtual #39                 // Method org/apache/hadoop/hbase/HBaseTestingUtility.deleteTable:(Lorg/apache/hadoop/hbase/TableName;)V
      40: return

  public void testDisabledWAL() throws java.lang.Exception;
    Code:
       0: getstatic     #15                 // Field LOG:Lorg/slf4j/Logger;
       3: new           #18                 // class java/lang/StringBuilder
       6: dup
       7: invokespecial #19                 // Method java/lang/StringBuilder."<init>":()V
      10: ldc           #40                 // String Writing data to table
      12: invokevirtual #21                 // Method java/lang/StringBuilder.append:(Ljava/lang/String;)Ljava/lang/StringBuilder;
      15: aload_0
      16: getfield      #32                 // Field tableName:Lorg/apache/hadoop/hbase/TableName;
      19: invokevirtual #34                 // Method java/lang/StringBuilder.append:(Ljava/lang/Object;)Ljava/lang/StringBuilder;
      22: invokevirtual #24                 // Method java/lang/StringBuilder.toString:()Ljava/lang/String;
      25: invokeinterface #35,  2           // InterfaceMethod org/slf4j/Logger.info:(Ljava/lang/String;)V
      30: new           #41                 // class org/apache/hadoop/hbase/client/Put
      33: dup
      34: ldc           #42                 // String row
      36: invokestatic  #6                  // Method org/apache/hadoop/hbase/util/Bytes.toBytes:(Ljava/lang/String;)[B
      39: invokespecial #43                 // Method org/apache/hadoop/hbase/client/Put."<init>":([B)V
      42: astore_1
      43: aload_1
      44: aload_0
      45: getfield      #7                  // Field fam:[B
      48: ldc           #44                 // String qual
      50: invokestatic  #6                  // Method org/apache/hadoop/hbase/util/Bytes.toBytes:(Ljava/lang/String;)[B
      53: ldc           #45                 // String val
      55: invokestatic  #6                  // Method org/apache/hadoop/hbase/util/Bytes.toBytes:(Ljava/lang/String;)[B
      58: invokevirtual #46                 // Method org/apache/hadoop/hbase/client/Put.addColumn:([B[B[B)Lorg/apache/hadoop/hbase/client/Put;
      61: pop
      62: aload_0
      63: getfield      #37                 // Field table:Lorg/apache/hadoop/hbase/client/Table;
      66: aload_1
      67: invokeinterface #47,  2           // InterfaceMethod org/apache/hadoop/hbase/client/Table.put:(Lorg/apache/hadoop/hbase/client/Put;)V
      72: getstatic     #15                 // Field LOG:Lorg/slf4j/Logger;
      75: new           #18                 // class java/lang/StringBuilder
      78: dup
      79: invokespecial #19                 // Method java/lang/StringBuilder."<init>":()V
      82: ldc           #48                 // String Flushing table
      84: invokevirtual #21                 // Method java/lang/StringBuilder.append:(Ljava/lang/String;)Ljava/lang/StringBuilder;
      87: aload_0
      88: getfield      #32                 // Field tableName:Lorg/apache/hadoop/hbase/TableName;
      91: invokevirtual #34                 // Method java/lang/StringBuilder.append:(Ljava/lang/Object;)Ljava/lang/StringBuilder;
      94: invokevirtual #24                 // Method java/lang/StringBuilder.toString:()Ljava/lang/String;
      97: invokeinterface #35,  2           // InterfaceMethod org/slf4j/Logger.info:(Ljava/lang/String;)V
     102: getstatic     #8                  // Field TEST_UTIL:Lorg/apache/hadoop/hbase/HBaseTestingUtility;
     105: aload_0
     106: getfield      #32                 // Field tableName:Lorg/apache/hadoop/hbase/TableName;
     109: invokevirtual #49                 // Method org/apache/hadoop/hbase/HBaseTestingUtility.flush:(Lorg/apache/hadoop/hbase/TableName;)V
     112: getstatic     #15                 // Field LOG:Lorg/slf4j/Logger;
     115: new           #18                 // class java/lang/StringBuilder
     118: dup
     119: invokespecial #19                 // Method java/lang/StringBuilder."<init>":()V
     122: ldc           #50                 // String Getting data from table
     124: invokevirtual #21                 // Method java/lang/StringBuilder.append:(Ljava/lang/String;)Ljava/lang/StringBuilder;
     127: aload_0
     128: getfield      #32                 // Field tableName:Lorg/apache/hadoop/hbase/TableName;
     131: invokevirtual #34                 // Method java/lang/StringBuilder.append:(Ljava/lang/Object;)Ljava/lang/StringBuilder;
     134: invokevirtual #24                 // Method java/lang/StringBuilder.toString:()Ljava/lang/String;
     137: invokeinterface #35,  2           // InterfaceMethod org/slf4j/Logger.info:(Ljava/lang/String;)V
     142: new           #51                 // class org/apache/hadoop/hbase/client/Get
     145: dup
     146: ldc           #42                 // String row
     148: invokestatic  #6                  // Method org/apache/hadoop/hbase/util/Bytes.toBytes:(Ljava/lang/String;)[B
     151: invokespecial #52                 // Method org/apache/hadoop/hbase/client/Get."<init>":([B)V
     154: astore_2
     155: aload_0
     156: getfield      #37                 // Field table:Lorg/apache/hadoop/hbase/client/Table;
     159: aload_2
     160: invokeinterface #53,  2           // InterfaceMethod org/apache/hadoop/hbase/client/Table.get:(Lorg/apache/hadoop/hbase/client/Get;)Lorg/apache/hadoop/hbase/client/Result;
     165: astore_3
     166: aload_3
     167: aload_0
     168: getfield      #7                  // Field fam:[B
     171: ldc           #44                 // String qual
     173: invokestatic  #6                  // Method org/apache/hadoop/hbase/util/Bytes.toBytes:(Ljava/lang/String;)[B
     176: invokevirtual #54                 // Method org/apache/hadoop/hbase/client/Result.getValue:([B[B)[B
     179: invokestatic  #55                 // Method org/junit/Assert.assertNotNull:(Ljava/lang/Object;)V
     182: return

  static {};
    Code:
       0: ldc           #56                 // class org/apache/hadoop/hbase/wal/TestDisabledWAL
       2: invokestatic  #57                 // Method org/apache/hadoop/hbase/HBaseClassTestRule.forClass:(Ljava/lang/Class;)Lorg/apache/hadoop/hbase/HBaseClassTestRule;
       5: putstatic     #58                 // Field CLASS_RULE:Lorg/apache/hadoop/hbase/HBaseClassTestRule;
       8: ldc           #56                 // class org/apache/hadoop/hbase/wal/TestDisabledWAL
      10: invokestatic  #59                 // Method org/slf4j/LoggerFactory.getLogger:(Ljava/lang/Class;)Lorg/slf4j/Logger;
      13: putstatic     #15                 // Field LOG:Lorg/slf4j/Logger;
      16: new           #60                 // class org/apache/hadoop/hbase/HBaseTestingUtility
      19: dup
      20: invokespecial #61                 // Method org/apache/hadoop/hbase/HBaseTestingUtility."<init>":()V
      23: putstatic     #8                  // Field TEST_UTIL:Lorg/apache/hadoop/hbase/HBaseTestingUtility;
      26: return
}
