Compiled from "TestKeyStoreKeyProvider.java"
public class org.apache.hadoop.hbase.io.crypto.TestKeyStoreKeyProvider {
  public static final org.apache.hadoop.hbase.HBaseClassTestRule CLASS_RULE;

  static final org.apache.hadoop.hbase.HBaseCommonTestingUtility TEST_UTIL;

  static final java.lang.String ALIAS;

  static final java.lang.String PASSWORD;

  static byte[] KEY;

  static java.io.File storeFile;

  static java.io.File passwordFile;

  public org.apache.hadoop.hbase.io.crypto.TestKeyStoreKeyProvider();
    Code:
       0: aload_0
       1: invokespecial #1                  // Method java/lang/Object."<init>":()V
       4: return

  public static void setUp() throws java.lang.Exception;
    Code:
       0: ldc           #2                  // String SHA-256
       2: invokestatic  #3                  // Method java/security/MessageDigest.getInstance:(Ljava/lang/String;)Ljava/security/MessageDigest;
       5: ldc           #5                  // String test
       7: invokestatic  #6                  // Method org/apache/hadoop/hbase/util/Bytes.toBytes:(Ljava/lang/String;)[B
      10: invokevirtual #7                  // Method java/security/MessageDigest.digest:([B)[B
      13: putstatic     #8                  // Field KEY:[B
      16: ldc           #9                  // String JCEKS
      18: invokestatic  #10                 // Method java/security/KeyStore.getInstance:(Ljava/lang/String;)Ljava/security/KeyStore;
      21: astore_0
      22: aload_0
      23: aconst_null
      24: ldc           #11                 // String password
      26: invokevirtual #12                 // Method java/lang/String.toCharArray:()[C
      29: invokevirtual #13                 // Method java/security/KeyStore.load:(Ljava/io/InputStream;[C)V
      32: aload_0
      33: ldc           #5                  // String test
      35: new           #14                 // class java/security/KeyStore$SecretKeyEntry
      38: dup
      39: new           #15                 // class javax/crypto/spec/SecretKeySpec
      42: dup
      43: getstatic     #8                  // Field KEY:[B
      46: ldc           #16                 // String AES
      48: invokespecial #17                 // Method javax/crypto/spec/SecretKeySpec."<init>":([BLjava/lang/String;)V
      51: invokespecial #18                 // Method java/security/KeyStore$SecretKeyEntry."<init>":(Ljavax/crypto/SecretKey;)V
      54: new           #19                 // class java/security/KeyStore$PasswordProtection
      57: dup
      58: ldc           #11                 // String password
      60: invokevirtual #12                 // Method java/lang/String.toCharArray:()[C
      63: invokespecial #20                 // Method java/security/KeyStore$PasswordProtection."<init>":([C)V
      66: invokevirtual #21                 // Method java/security/KeyStore.setEntry:(Ljava/lang/String;Ljava/security/KeyStore$Entry;Ljava/security/KeyStore$ProtectionParameter;)V
      69: getstatic     #22                 // Field TEST_UTIL:Lorg/apache/hadoop/hbase/HBaseCommonTestingUtility;
      72: invokevirtual #23                 // Method org/apache/hadoop/hbase/HBaseCommonTestingUtility.getDataTestDir:()Lorg/apache/hadoop/fs/Path;
      75: invokevirtual #24                 // Method org/apache/hadoop/fs/Path.toString:()Ljava/lang/String;
      78: astore_1
      79: new           #25                 // class java/io/File
      82: dup
      83: aload_1
      84: invokespecial #26                 // Method java/io/File."<init>":(Ljava/lang/String;)V
      87: invokevirtual #27                 // Method java/io/File.mkdirs:()Z
      90: pop
      91: new           #25                 // class java/io/File
      94: dup
      95: aload_1
      96: ldc           #28                 // String keystore.jks
      98: invokespecial #29                 // Method java/io/File."<init>":(Ljava/lang/String;Ljava/lang/String;)V
     101: putstatic     #30                 // Field storeFile:Ljava/io/File;
     104: new           #31                 // class java/io/FileOutputStream
     107: dup
     108: getstatic     #30                 // Field storeFile:Ljava/io/File;
     111: invokespecial #32                 // Method java/io/FileOutputStream."<init>":(Ljava/io/File;)V
     114: astore_2
     115: aload_0
     116: aload_2
     117: ldc           #11                 // String password
     119: invokevirtual #12                 // Method java/lang/String.toCharArray:()[C
     122: invokevirtual #33                 // Method java/security/KeyStore.store:(Ljava/io/OutputStream;[C)V
     125: aload_2
     126: invokevirtual #34                 // Method java/io/FileOutputStream.close:()V
     129: goto          139
     132: astore_3
     133: aload_2
     134: invokevirtual #34                 // Method java/io/FileOutputStream.close:()V
     137: aload_3
     138: athrow
     139: new           #35                 // class java/util/Properties
     142: dup
     143: invokespecial #36                 // Method java/util/Properties."<init>":()V
     146: astore_3
     147: aload_3
     148: ldc           #5                  // String test
     150: ldc           #11                 // String password
     152: invokevirtual #37                 // Method java/util/Properties.setProperty:(Ljava/lang/String;Ljava/lang/String;)Ljava/lang/Object;
     155: pop
     156: new           #25                 // class java/io/File
     159: dup
     160: aload_1
     161: ldc           #38                 // String keystore.pw
     163: invokespecial #29                 // Method java/io/File."<init>":(Ljava/lang/String;Ljava/lang/String;)V
     166: putstatic     #39                 // Field passwordFile:Ljava/io/File;
     169: new           #31                 // class java/io/FileOutputStream
     172: dup
     173: getstatic     #39                 // Field passwordFile:Ljava/io/File;
     176: invokespecial #32                 // Method java/io/FileOutputStream."<init>":(Ljava/io/File;)V
     179: astore_2
     180: aload_3
     181: aload_2
     182: ldc           #40                 // String
     184: invokevirtual #41                 // Method java/util/Properties.store:(Ljava/io/OutputStream;Ljava/lang/String;)V
     187: aload_2
     188: invokevirtual #34                 // Method java/io/FileOutputStream.close:()V
     191: goto          203
     194: astore        4
     196: aload_2
     197: invokevirtual #34                 // Method java/io/FileOutputStream.close:()V
     200: aload         4
     202: athrow
     203: return
    Exception table:
       from    to  target type
         115   125   132   any
         180   187   194   any
         194   196   194   any

  public void testKeyStoreKeyProviderWithPassword() throws java.lang.Exception;
    Code:
       0: new           #42                 // class org/apache/hadoop/hbase/io/crypto/KeyStoreKeyProvider
       3: dup
       4: invokespecial #43                 // Method org/apache/hadoop/hbase/io/crypto/KeyStoreKeyProvider."<init>":()V
       7: astore_1
       8: aload_1
       9: new           #44                 // class java/lang/StringBuilder
      12: dup
      13: invokespecial #45                 // Method java/lang/StringBuilder."<init>":()V
      16: ldc           #46                 // String jceks://
      18: invokevirtual #47                 // Method java/lang/StringBuilder.append:(Ljava/lang/String;)Ljava/lang/StringBuilder;
      21: getstatic     #30                 // Field storeFile:Ljava/io/File;
      24: invokevirtual #48                 // Method java/io/File.toURI:()Ljava/net/URI;
      27: invokevirtual #49                 // Method java/net/URI.getPath:()Ljava/lang/String;
      30: invokevirtual #47                 // Method java/lang/StringBuilder.append:(Ljava/lang/String;)Ljava/lang/StringBuilder;
      33: ldc           #50                 // String ?password=
      35: invokevirtual #47                 // Method java/lang/StringBuilder.append:(Ljava/lang/String;)Ljava/lang/StringBuilder;
      38: ldc           #11                 // String password
      40: invokevirtual #47                 // Method java/lang/StringBuilder.append:(Ljava/lang/String;)Ljava/lang/StringBuilder;
      43: invokevirtual #51                 // Method java/lang/StringBuilder.toString:()Ljava/lang/String;
      46: invokeinterface #52,  2           // InterfaceMethod org/apache/hadoop/hbase/io/crypto/KeyProvider.init:(Ljava/lang/String;)V
      51: aload_1
      52: ldc           #5                  // String test
      54: invokeinterface #53,  2           // InterfaceMethod org/apache/hadoop/hbase/io/crypto/KeyProvider.getKey:(Ljava/lang/String;)Ljava/security/Key;
      59: astore_2
      60: aload_2
      61: invokestatic  #54                 // Method org/junit/Assert.assertNotNull:(Ljava/lang/Object;)V
      64: aload_2
      65: invokeinterface #55,  1           // InterfaceMethod java/security/Key.getEncoded:()[B
      70: astore_3
      71: aload_3
      72: arraylength
      73: i2l
      74: getstatic     #8                  // Field KEY:[B
      77: arraylength
      78: i2l
      79: invokestatic  #56                 // Method org/junit/Assert.assertEquals:(JJ)V
      82: iconst_0
      83: istore        4
      85: iload         4
      87: getstatic     #8                  // Field KEY:[B
      90: arraylength
      91: if_icmpge     115
      94: aload_3
      95: iload         4
      97: baload
      98: i2l
      99: getstatic     #8                  // Field KEY:[B
     102: iload         4
     104: baload
     105: i2l
     106: invokestatic  #56                 // Method org/junit/Assert.assertEquals:(JJ)V
     109: iinc          4, 1
     112: goto          85
     115: return

  public void testKeyStoreKeyProviderWithPasswordFile() throws java.lang.Exception;
    Code:
       0: new           #42                 // class org/apache/hadoop/hbase/io/crypto/KeyStoreKeyProvider
       3: dup
       4: invokespecial #43                 // Method org/apache/hadoop/hbase/io/crypto/KeyStoreKeyProvider."<init>":()V
       7: astore_1
       8: aload_1
       9: new           #44                 // class java/lang/StringBuilder
      12: dup
      13: invokespecial #45                 // Method java/lang/StringBuilder."<init>":()V
      16: ldc           #46                 // String jceks://
      18: invokevirtual #47                 // Method java/lang/StringBuilder.append:(Ljava/lang/String;)Ljava/lang/StringBuilder;
      21: getstatic     #30                 // Field storeFile:Ljava/io/File;
      24: invokevirtual #48                 // Method java/io/File.toURI:()Ljava/net/URI;
      27: invokevirtual #49                 // Method java/net/URI.getPath:()Ljava/lang/String;
      30: invokevirtual #47                 // Method java/lang/StringBuilder.append:(Ljava/lang/String;)Ljava/lang/StringBuilder;
      33: ldc           #57                 // String ?passwordFile=
      35: invokevirtual #47                 // Method java/lang/StringBuilder.append:(Ljava/lang/String;)Ljava/lang/StringBuilder;
      38: getstatic     #39                 // Field passwordFile:Ljava/io/File;
      41: invokevirtual #58                 // Method java/io/File.getAbsolutePath:()Ljava/lang/String;
      44: ldc           #59                 // String UTF-8
      46: invokestatic  #60                 // Method java/net/URLEncoder.encode:(Ljava/lang/String;Ljava/lang/String;)Ljava/lang/String;
      49: invokevirtual #47                 // Method java/lang/StringBuilder.append:(Ljava/lang/String;)Ljava/lang/StringBuilder;
      52: invokevirtual #51                 // Method java/lang/StringBuilder.toString:()Ljava/lang/String;
      55: invokeinterface #52,  2           // InterfaceMethod org/apache/hadoop/hbase/io/crypto/KeyProvider.init:(Ljava/lang/String;)V
      60: aload_1
      61: ldc           #5                  // String test
      63: invokeinterface #53,  2           // InterfaceMethod org/apache/hadoop/hbase/io/crypto/KeyProvider.getKey:(Ljava/lang/String;)Ljava/security/Key;
      68: astore_2
      69: aload_2
      70: invokestatic  #54                 // Method org/junit/Assert.assertNotNull:(Ljava/lang/Object;)V
      73: aload_2
      74: invokeinterface #55,  1           // InterfaceMethod java/security/Key.getEncoded:()[B
      79: astore_3
      80: aload_3
      81: arraylength
      82: i2l
      83: getstatic     #8                  // Field KEY:[B
      86: arraylength
      87: i2l
      88: invokestatic  #56                 // Method org/junit/Assert.assertEquals:(JJ)V
      91: iconst_0
      92: istore        4
      94: iload         4
      96: getstatic     #8                  // Field KEY:[B
      99: arraylength
     100: if_icmpge     124
     103: aload_3
     104: iload         4
     106: baload
     107: i2l
     108: getstatic     #8                  // Field KEY:[B
     111: iload         4
     113: baload
     114: i2l
     115: invokestatic  #56                 // Method org/junit/Assert.assertEquals:(JJ)V
     118: iinc          4, 1
     121: goto          94
     124: return

  static {};
    Code:
       0: ldc           #4                  // class org/apache/hadoop/hbase/io/crypto/TestKeyStoreKeyProvider
       2: invokestatic  #61                 // Method org/apache/hadoop/hbase/HBaseClassTestRule.forClass:(Ljava/lang/Class;)Lorg/apache/hadoop/hbase/HBaseClassTestRule;
       5: putstatic     #62                 // Field CLASS_RULE:Lorg/apache/hadoop/hbase/HBaseClassTestRule;
       8: ldc           #4                  // class org/apache/hadoop/hbase/io/crypto/TestKeyStoreKeyProvider
      10: invokestatic  #63                 // Method org/slf4j/LoggerFactory.getLogger:(Ljava/lang/Class;)Lorg/slf4j/Logger;
      13: putstatic     #64                 // Field LOG:Lorg/slf4j/Logger;
      16: new           #65                 // class org/apache/hadoop/hbase/HBaseCommonTestingUtility
      19: dup
      20: invokespecial #66                 // Method org/apache/hadoop/hbase/HBaseCommonTestingUtility."<init>":()V
      23: putstatic     #22                 // Field TEST_UTIL:Lorg/apache/hadoop/hbase/HBaseCommonTestingUtility;
      26: return
}
