Compiled from "TestReplicationKillRS.java"
public class org.apache.hadoop.hbase.replication.TestReplicationKillRS extends org.apache.hadoop.hbase.replication.TestReplicationBase {
  public static final org.apache.hadoop.hbase.HBaseClassTestRule CLASS_RULE;

  public org.apache.hadoop.hbase.replication.TestReplicationKillRS();
    Code:
       0: aload_0
       1: invokespecial #2                  // Method org/apache/hadoop/hbase/replication/TestReplicationBase."<init>":()V
       4: return

  public void loadTableAndKillRS(org.apache.hadoop.hbase.HBaseTestingUtility) throws java.lang.Exception;
    Code:
       0: aload_1
       1: invokevirtual #3                  // Method org/apache/hadoop/hbase/HBaseTestingUtility.getHBaseCluster:()Lorg/apache/hadoop/hbase/MiniHBaseCluster;
       4: invokevirtual #4                  // Method org/apache/hadoop/hbase/MiniHBaseCluster.getServerWithMeta:()I
       7: ifne          14
      10: iconst_1
      11: goto          15
      14: iconst_0
      15: istore_2
      16: aload_1
      17: ldc2_w        #5                  // long 5000l
      20: iload_2
      21: invokestatic  #7                  // Method killARegionServer:(Lorg/apache/hadoop/hbase/HBaseTestingUtility;JI)Ljava/lang/Thread;
      24: astore_3
      25: getstatic     #8                  // Field CONF1:Lorg/apache/hadoop/conf/Configuration;
      28: invokestatic  #9                  // Method org/apache/hadoop/hbase/client/ConnectionFactory.createConnection:(Lorg/apache/hadoop/conf/Configuration;)Lorg/apache/hadoop/hbase/client/Connection;
      31: astore        6
      33: aconst_null
      34: astore        7
      36: aload         6
      38: getstatic     #10                 // Field tableName:Lorg/apache/hadoop/hbase/TableName;
      41: invokeinterface #11,  2           // InterfaceMethod org/apache/hadoop/hbase/client/Connection.getTable:(Lorg/apache/hadoop/hbase/TableName;)Lorg/apache/hadoop/hbase/client/Table;
      46: astore        8
      48: aconst_null
      49: astore        9
      51: getstatic     #1                  // Field LOG:Lorg/slf4j/Logger;
      54: ldc           #12                 // String Start loading table
      56: invokeinterface #13,  2           // InterfaceMethod org/slf4j/Logger.info:(Ljava/lang/String;)V
      61: getstatic     #14                 // Field UTIL1:Lorg/apache/hadoop/hbase/HBaseTestingUtility;
      64: aload         8
      66: getstatic     #15                 // Field famName:[B
      69: invokevirtual #16                 // Method org/apache/hadoop/hbase/HBaseTestingUtility.loadTable:(Lorg/apache/hadoop/hbase/client/Table;[B)I
      72: istore        5
      74: getstatic     #1                  // Field LOG:Lorg/slf4j/Logger;
      77: ldc           #17                 // String Done loading table
      79: invokeinterface #13,  2           // InterfaceMethod org/slf4j/Logger.info:(Ljava/lang/String;)V
      84: aload_3
      85: ldc2_w        #5                  // long 5000l
      88: invokevirtual #18                 // Method java/lang/Thread.join:(J)V
      91: getstatic     #1                  // Field LOG:Lorg/slf4j/Logger;
      94: ldc           #19                 // String Done waiting for threads
      96: invokeinterface #13,  2           // InterfaceMethod org/slf4j/Logger.info:(Ljava/lang/String;)V
     101: aload         8
     103: new           #20                 // class org/apache/hadoop/hbase/client/Scan
     106: dup
     107: invokespecial #21                 // Method org/apache/hadoop/hbase/client/Scan."<init>":()V
     110: invokeinterface #22,  2           // InterfaceMethod org/apache/hadoop/hbase/client/Table.getScanner:(Lorg/apache/hadoop/hbase/client/Scan;)Lorg/apache/hadoop/hbase/client/ResultScanner;
     115: astore        10
     117: aconst_null
     118: astore        11
     120: aload         10
     122: iload         5
     124: invokeinterface #23,  2           // InterfaceMethod org/apache/hadoop/hbase/client/ResultScanner.next:(I)[Lorg/apache/hadoop/hbase/client/Result;
     129: astore        4
     131: aload         10
     133: ifnull        170
     136: aload         11
     138: ifnull        163
     141: aload         10
     143: invokeinterface #24,  1           // InterfaceMethod org/apache/hadoop/hbase/client/ResultScanner.close:()V
     148: goto          170
     151: astore        12
     153: aload         11
     155: aload         12
     157: invokevirtual #26                 // Method java/lang/Throwable.addSuppressed:(Ljava/lang/Throwable;)V
     160: goto          170
     163: aload         10
     165: invokeinterface #24,  1           // InterfaceMethod org/apache/hadoop/hbase/client/ResultScanner.close:()V
     170: goto          241
     173: astore        12
     175: aload         12
     177: astore        11
     179: aload         12
     181: athrow
     182: astore        13
     184: aload         10
     186: ifnull        223
     189: aload         11
     191: ifnull        216
     194: aload         10
     196: invokeinterface #24,  1           // InterfaceMethod org/apache/hadoop/hbase/client/ResultScanner.close:()V
     201: goto          223
     204: astore        14
     206: aload         11
     208: aload         14
     210: invokevirtual #26                 // Method java/lang/Throwable.addSuppressed:(Ljava/lang/Throwable;)V
     213: goto          223
     216: aload         10
     218: invokeinterface #24,  1           // InterfaceMethod org/apache/hadoop/hbase/client/ResultScanner.close:()V
     223: aload         13
     225: athrow
     226: astore        10
     228: getstatic     #1                  // Field LOG:Lorg/slf4j/Logger;
     231: ldc           #28                 // String Cluster wasn't ready yet, restarting scanner
     233: invokeinterface #13,  2           // InterfaceMethod org/slf4j/Logger.info:(Ljava/lang/String;)V
     238: goto          101
     241: aload         8
     243: ifnull        336
     246: aload         9
     248: ifnull        273
     251: aload         8
     253: invokeinterface #29,  1           // InterfaceMethod org/apache/hadoop/hbase/client/Table.close:()V
     258: goto          336
     261: astore        10
     263: aload         9
     265: aload         10
     267: invokevirtual #26                 // Method java/lang/Throwable.addSuppressed:(Ljava/lang/Throwable;)V
     270: goto          336
     273: aload         8
     275: invokeinterface #29,  1           // InterfaceMethod org/apache/hadoop/hbase/client/Table.close:()V
     280: goto          336
     283: astore        10
     285: aload         10
     287: astore        9
     289: aload         10
     291: athrow
     292: astore        15
     294: aload         8
     296: ifnull        333
     299: aload         9
     301: ifnull        326
     304: aload         8
     306: invokeinterface #29,  1           // InterfaceMethod org/apache/hadoop/hbase/client/Table.close:()V
     311: goto          333
     314: astore        16
     316: aload         9
     318: aload         16
     320: invokevirtual #26                 // Method java/lang/Throwable.addSuppressed:(Ljava/lang/Throwable;)V
     323: goto          333
     326: aload         8
     328: invokeinterface #29,  1           // InterfaceMethod org/apache/hadoop/hbase/client/Table.close:()V
     333: aload         15
     335: athrow
     336: aload         6
     338: ifnull        431
     341: aload         7
     343: ifnull        368
     346: aload         6
     348: invokeinterface #30,  1           // InterfaceMethod org/apache/hadoop/hbase/client/Connection.close:()V
     353: goto          431
     356: astore        8
     358: aload         7
     360: aload         8
     362: invokevirtual #26                 // Method java/lang/Throwable.addSuppressed:(Ljava/lang/Throwable;)V
     365: goto          431
     368: aload         6
     370: invokeinterface #30,  1           // InterfaceMethod org/apache/hadoop/hbase/client/Connection.close:()V
     375: goto          431
     378: astore        8
     380: aload         8
     382: astore        7
     384: aload         8
     386: athrow
     387: astore        17
     389: aload         6
     391: ifnull        428
     394: aload         7
     396: ifnull        421
     399: aload         6
     401: invokeinterface #30,  1           // InterfaceMethod org/apache/hadoop/hbase/client/Connection.close:()V
     406: goto          428
     409: astore        18
     411: aload         7
     413: aload         18
     415: invokevirtual #26                 // Method java/lang/Throwable.addSuppressed:(Ljava/lang/Throwable;)V
     418: goto          428
     421: aload         6
     423: invokeinterface #30,  1           // InterfaceMethod org/apache/hadoop/hbase/client/Connection.close:()V
     428: aload         17
     430: athrow
     431: aload         4
     433: arraylength
     434: iload         5
     436: if_icmpeq     454
     439: getstatic     #1                  // Field LOG:Lorg/slf4j/Logger;
     442: ldc           #31                 // String We lost some rows on the master cluster!
     444: invokeinterface #32,  2           // InterfaceMethod org/slf4j/Logger.warn:(Ljava/lang/String;)V
     449: aload         4
     451: arraylength
     452: istore        5
     454: iconst_0
     455: istore        6
     457: invokestatic  #33                 // Method java/lang/System.currentTimeMillis:()J
     460: lstore        7
     462: iconst_0
     463: istore        9
     465: getstatic     #34                 // Field CONF2:Lorg/apache/hadoop/conf/Configuration;
     468: invokestatic  #9                  // Method org/apache/hadoop/hbase/client/ConnectionFactory.createConnection:(Lorg/apache/hadoop/conf/Configuration;)Lorg/apache/hadoop/hbase/client/Connection;
     471: astore        10
     473: aconst_null
     474: astore        11
     476: aload         10
     478: getstatic     #10                 // Field tableName:Lorg/apache/hadoop/hbase/TableName;
     481: invokeinterface #11,  2           // InterfaceMethod org/apache/hadoop/hbase/client/Connection.getTable:(Lorg/apache/hadoop/hbase/TableName;)Lorg/apache/hadoop/hbase/client/Table;
     486: astore        12
     488: aconst_null
     489: astore        13
     491: iload         9
     493: bipush        49
     495: if_icmpne     530
     498: new           #36                 // class java/lang/StringBuilder
     501: dup
     502: invokespecial #37                 // Method java/lang/StringBuilder."<init>":()V
     505: ldc           #38                 // String Waited too much time for queueFailover replication. Waited
     507: invokevirtual #39                 // Method java/lang/StringBuilder.append:(Ljava/lang/String;)Ljava/lang/StringBuilder;
     510: invokestatic  #33                 // Method java/lang/System.currentTimeMillis:()J
     513: lload         7
     515: lsub
     516: invokevirtual #40                 // Method java/lang/StringBuilder.append:(J)Ljava/lang/StringBuilder;
     519: ldc           #41                 // String ms.
     521: invokevirtual #39                 // Method java/lang/StringBuilder.append:(Ljava/lang/String;)Ljava/lang/StringBuilder;
     524: invokevirtual #42                 // Method java/lang/StringBuilder.toString:()Ljava/lang/String;
     527: invokestatic  #43                 // Method org/junit/Assert.fail:(Ljava/lang/String;)V
     530: aload         12
     532: new           #20                 // class org/apache/hadoop/hbase/client/Scan
     535: dup
     536: invokespecial #21                 // Method org/apache/hadoop/hbase/client/Scan."<init>":()V
     539: invokeinterface #22,  2           // InterfaceMethod org/apache/hadoop/hbase/client/Table.getScanner:(Lorg/apache/hadoop/hbase/client/Scan;)Lorg/apache/hadoop/hbase/client/ResultScanner;
     544: astore        15
     546: aconst_null
     547: astore        16
     549: aload         15
     551: iload         5
     553: iconst_2
     554: imul
     555: invokeinterface #23,  2           // InterfaceMethod org/apache/hadoop/hbase/client/ResultScanner.next:(I)[Lorg/apache/hadoop/hbase/client/Result;
     560: astore        14
     562: aload         15
     564: ifnull        657
     567: aload         16
     569: ifnull        594
     572: aload         15
     574: invokeinterface #24,  1           // InterfaceMethod org/apache/hadoop/hbase/client/ResultScanner.close:()V
     579: goto          657
     582: astore        17
     584: aload         16
     586: aload         17
     588: invokevirtual #26                 // Method java/lang/Throwable.addSuppressed:(Ljava/lang/Throwable;)V
     591: goto          657
     594: aload         15
     596: invokeinterface #24,  1           // InterfaceMethod org/apache/hadoop/hbase/client/ResultScanner.close:()V
     601: goto          657
     604: astore        17
     606: aload         17
     608: astore        16
     610: aload         17
     612: athrow
     613: astore        19
     615: aload         15
     617: ifnull        654
     620: aload         16
     622: ifnull        647
     625: aload         15
     627: invokeinterface #24,  1           // InterfaceMethod org/apache/hadoop/hbase/client/ResultScanner.close:()V
     632: goto          654
     635: astore        20
     637: aload         16
     639: aload         20
     641: invokevirtual #26                 // Method java/lang/Throwable.addSuppressed:(Ljava/lang/Throwable;)V
     644: goto          654
     647: aload         15
     649: invokeinterface #24,  1           // InterfaceMethod org/apache/hadoop/hbase/client/ResultScanner.close:()V
     654: aload         19
     656: athrow
     657: aload         14
     659: arraylength
     660: iload         5
     662: if_icmpge     744
     665: iload         6
     667: aload         14
     669: arraylength
     670: if_icmpge     679
     673: iinc          9, -1
     676: goto          682
     679: iinc          9, 1
     682: aload         14
     684: arraylength
     685: istore        6
     687: getstatic     #1                  // Field LOG:Lorg/slf4j/Logger;
     690: new           #36                 // class java/lang/StringBuilder
     693: dup
     694: invokespecial #37                 // Method java/lang/StringBuilder."<init>":()V
     697: ldc           #44                 // String Only got
     699: invokevirtual #39                 // Method java/lang/StringBuilder.append:(Ljava/lang/String;)Ljava/lang/StringBuilder;
     702: iload         6
     704: invokevirtual #45                 // Method java/lang/StringBuilder.append:(I)Ljava/lang/StringBuilder;
     707: ldc           #46                 // String  rows instead of
     709: invokevirtual #39                 // Method java/lang/StringBuilder.append:(Ljava/lang/String;)Ljava/lang/StringBuilder;
     712: iload         5
     714: invokevirtual #45                 // Method java/lang/StringBuilder.append:(I)Ljava/lang/StringBuilder;
     717: ldc           #47                 // String  current i=
     719: invokevirtual #39                 // Method java/lang/StringBuilder.append:(Ljava/lang/String;)Ljava/lang/StringBuilder;
     722: iload         9
     724: invokevirtual #45                 // Method java/lang/StringBuilder.append:(I)Ljava/lang/StringBuilder;
     727: invokevirtual #42                 // Method java/lang/StringBuilder.toString:()Ljava/lang/String;
     730: invokeinterface #13,  2           // InterfaceMethod org/slf4j/Logger.info:(Ljava/lang/String;)V
     735: ldc2_w        #48                 // long 1000l
     738: invokestatic  #50                 // Method java/lang/Thread.sleep:(J)V
     741: goto          491
     744: aload         12
     746: ifnull        839
     749: aload         13
     751: ifnull        776
     754: aload         12
     756: invokeinterface #29,  1           // InterfaceMethod org/apache/hadoop/hbase/client/Table.close:()V
     761: goto          839
     764: astore        14
     766: aload         13
     768: aload         14
     770: invokevirtual #26                 // Method java/lang/Throwable.addSuppressed:(Ljava/lang/Throwable;)V
     773: goto          839
     776: aload         12
     778: invokeinterface #29,  1           // InterfaceMethod org/apache/hadoop/hbase/client/Table.close:()V
     783: goto          839
     786: astore        14
     788: aload         14
     790: astore        13
     792: aload         14
     794: athrow
     795: astore        21
     797: aload         12
     799: ifnull        836
     802: aload         13
     804: ifnull        829
     807: aload         12
     809: invokeinterface #29,  1           // InterfaceMethod org/apache/hadoop/hbase/client/Table.close:()V
     814: goto          836
     817: astore        22
     819: aload         13
     821: aload         22
     823: invokevirtual #26                 // Method java/lang/Throwable.addSuppressed:(Ljava/lang/Throwable;)V
     826: goto          836
     829: aload         12
     831: invokeinterface #29,  1           // InterfaceMethod org/apache/hadoop/hbase/client/Table.close:()V
     836: aload         21
     838: athrow
     839: aload         10
     841: ifnull        934
     844: aload         11
     846: ifnull        871
     849: aload         10
     851: invokeinterface #30,  1           // InterfaceMethod org/apache/hadoop/hbase/client/Connection.close:()V
     856: goto          934
     859: astore        12
     861: aload         11
     863: aload         12
     865: invokevirtual #26                 // Method java/lang/Throwable.addSuppressed:(Ljava/lang/Throwable;)V
     868: goto          934
     871: aload         10
     873: invokeinterface #30,  1           // InterfaceMethod org/apache/hadoop/hbase/client/Connection.close:()V
     878: goto          934
     881: astore        12
     883: aload         12
     885: astore        11
     887: aload         12
     889: athrow
     890: astore        23
     892: aload         10
     894: ifnull        931
     897: aload         11
     899: ifnull        924
     902: aload         10
     904: invokeinterface #30,  1           // InterfaceMethod org/apache/hadoop/hbase/client/Connection.close:()V
     909: goto          931
     912: astore        24
     914: aload         11
     916: aload         24
     918: invokevirtual #26                 // Method java/lang/Throwable.addSuppressed:(Ljava/lang/Throwable;)V
     921: goto          931
     924: aload         10
     926: invokeinterface #30,  1           // InterfaceMethod org/apache/hadoop/hbase/client/Connection.close:()V
     931: aload         23
     933: athrow
     934: return
    Exception table:
       from    to  target type
         141   148   151   Class java/lang/Throwable
         120   131   173   Class java/lang/Throwable
         120   131   182   any
         194   201   204   Class java/lang/Throwable
         173   184   182   any
         101   170   226   Class org/apache/hadoop/hbase/UnknownScannerException
         173   226   226   Class org/apache/hadoop/hbase/UnknownScannerException
         251   258   261   Class java/lang/Throwable
          51   241   283   Class java/lang/Throwable
          51   241   292   any
         304   311   314   Class java/lang/Throwable
         283   294   292   any
         346   353   356   Class java/lang/Throwable
          36   336   378   Class java/lang/Throwable
          36   336   387   any
         399   406   409   Class java/lang/Throwable
         378   389   387   any
         572   579   582   Class java/lang/Throwable
         549   562   604   Class java/lang/Throwable
         549   562   613   any
         625   632   635   Class java/lang/Throwable
         604   615   613   any
         754   761   764   Class java/lang/Throwable
         491   744   786   Class java/lang/Throwable
         491   744   795   any
         807   814   817   Class java/lang/Throwable
         786   797   795   any
         849   856   859   Class java/lang/Throwable
         476   839   881   Class java/lang/Throwable
         476   839   890   any
         902   909   912   Class java/lang/Throwable
         881   892   890   any

  static org.slf4j.Logger access$000();
    Code:
       0: getstatic     #1                  // Field LOG:Lorg/slf4j/Logger;
       3: areturn

  static {};
    Code:
       0: ldc           #55                 // class org/apache/hadoop/hbase/replication/TestReplicationKillRS
       2: invokestatic  #56                 // Method org/apache/hadoop/hbase/HBaseClassTestRule.forClass:(Ljava/lang/Class;)Lorg/apache/hadoop/hbase/HBaseClassTestRule;
       5: putstatic     #57                 // Field CLASS_RULE:Lorg/apache/hadoop/hbase/HBaseClassTestRule;
       8: ldc           #55                 // class org/apache/hadoop/hbase/replication/TestReplicationKillRS
      10: invokestatic  #58                 // Method org/slf4j/LoggerFactory.getLogger:(Ljava/lang/Class;)Lorg/slf4j/Logger;
      13: putstatic     #1                  // Field LOG:Lorg/slf4j/Logger;
      16: return
}
