Compiled from "TestRecoverStandbyProcedure.java"
public class org.apache.hadoop.hbase.replication.master.TestRecoverStandbyProcedure {
  public static final org.apache.hadoop.hbase.HBaseClassTestRule CLASS_RULE;

  public org.apache.hadoop.hbase.replication.master.TestRecoverStandbyProcedure();
    Code:
       0: aload_0
       1: invokespecial #1                  // Method java/lang/Object."<init>":()V
       4: return

  public static void setupCluster() throws java.lang.Exception;
    Code:
       0: getstatic     #2                  // Field UTIL:Lorg/apache/hadoop/hbase/HBaseTestingUtility;
       3: iconst_3
       4: invokevirtual #4                  // Method org/apache/hadoop/hbase/HBaseTestingUtility.startMiniCluster:(I)Lorg/apache/hadoop/hbase/MiniHBaseCluster;
       7: pop
       8: getstatic     #2                  // Field UTIL:Lorg/apache/hadoop/hbase/HBaseTestingUtility;
      11: invokevirtual #5                  // Method org/apache/hadoop/hbase/HBaseTestingUtility.getHBaseCluster:()Lorg/apache/hadoop/hbase/MiniHBaseCluster;
      14: invokevirtual #6                  // Method org/apache/hadoop/hbase/MiniHBaseCluster.waitForActiveAndReadyMaster:()Z
      17: pop
      18: getstatic     #2                  // Field UTIL:Lorg/apache/hadoop/hbase/HBaseTestingUtility;
      21: invokevirtual #7                  // Method org/apache/hadoop/hbase/HBaseTestingUtility.getConfiguration:()Lorg/apache/hadoop/conf/Configuration;
      24: putstatic     #8                  // Field conf:Lorg/apache/hadoop/conf/Configuration;
      27: getstatic     #2                  // Field UTIL:Lorg/apache/hadoop/hbase/HBaseTestingUtility;
      30: invokevirtual #5                  // Method org/apache/hadoop/hbase/HBaseTestingUtility.getHBaseCluster:()Lorg/apache/hadoop/hbase/MiniHBaseCluster;
      33: invokevirtual #9                  // Method org/apache/hadoop/hbase/MiniHBaseCluster.getMaster:()Lorg/apache/hadoop/hbase/master/HMaster;
      36: astore_0
      37: aload_0
      38: invokevirtual #10                 // Method org/apache/hadoop/hbase/master/HMaster.getMasterFileSystem:()Lorg/apache/hadoop/hbase/master/MasterFileSystem;
      41: invokevirtual #11                 // Method org/apache/hadoop/hbase/master/MasterFileSystem.getWALFileSystem:()Lorg/apache/hadoop/fs/FileSystem;
      44: putstatic     #12                 // Field fs:Lorg/apache/hadoop/fs/FileSystem;
      47: aload_0
      48: invokevirtual #13                 // Method org/apache/hadoop/hbase/master/HMaster.getSyncReplicationReplayWALManager:()Lorg/apache/hadoop/hbase/master/replication/SyncReplicationReplayWALManager;
      51: putstatic     #14                 // Field syncReplicationReplayWALManager:Lorg/apache/hadoop/hbase/master/replication/SyncReplicationReplayWALManager;
      54: aload_0
      55: invokevirtual #15                 // Method org/apache/hadoop/hbase/master/HMaster.getMasterProcedureExecutor:()Lorg/apache/hadoop/hbase/procedure2/ProcedureExecutor;
      58: putstatic     #16                 // Field procExec:Lorg/apache/hadoop/hbase/procedure2/ProcedureExecutor;
      61: return

  public static void cleanupTest() throws java.lang.Exception;
    Code:
       0: getstatic     #2                  // Field UTIL:Lorg/apache/hadoop/hbase/HBaseTestingUtility;
       3: invokevirtual #17                 // Method org/apache/hadoop/hbase/HBaseTestingUtility.shutdownMiniCluster:()V
       6: goto          21
       9: astore_0
      10: getstatic     #19                 // Field LOG:Lorg/slf4j/Logger;
      13: ldc           #20                 // String failure shutting down cluster
      15: aload_0
      16: invokeinterface #21,  3           // InterfaceMethod org/slf4j/Logger.warn:(Ljava/lang/String;Ljava/lang/Throwable;)V
      21: return
    Exception table:
       from    to  target type
           0     6     9   Class java/lang/Exception

  public void setupBeforeTest() throws java.io.IOException;
    Code:
       0: getstatic     #2                  // Field UTIL:Lorg/apache/hadoop/hbase/HBaseTestingUtility;
       3: getstatic     #22                 // Field tableName:Lorg/apache/hadoop/hbase/TableName;
       6: getstatic     #23                 // Field family:[B
       9: invokevirtual #24                 // Method org/apache/hadoop/hbase/HBaseTestingUtility.createTable:(Lorg/apache/hadoop/hbase/TableName;[B)Lorg/apache/hadoop/hbase/client/Table;
      12: pop
      13: return

  public void tearDownAfterTest() throws java.io.IOException;
    Code:
       0: getstatic     #2                  // Field UTIL:Lorg/apache/hadoop/hbase/HBaseTestingUtility;
       3: invokevirtual #25                 // Method org/apache/hadoop/hbase/HBaseTestingUtility.getAdmin:()Lorg/apache/hadoop/hbase/client/Admin;
       6: astore_1
       7: aconst_null
       8: astore_2
       9: aload_1
      10: getstatic     #22                 // Field tableName:Lorg/apache/hadoop/hbase/TableName;
      13: invokeinterface #26,  2           // InterfaceMethod org/apache/hadoop/hbase/client/Admin.isTableEnabled:(Lorg/apache/hadoop/hbase/TableName;)Z
      18: ifeq          30
      21: aload_1
      22: getstatic     #22                 // Field tableName:Lorg/apache/hadoop/hbase/TableName;
      25: invokeinterface #27,  2           // InterfaceMethod org/apache/hadoop/hbase/client/Admin.disableTable:(Lorg/apache/hadoop/hbase/TableName;)V
      30: aload_1
      31: getstatic     #22                 // Field tableName:Lorg/apache/hadoop/hbase/TableName;
      34: invokeinterface #28,  2           // InterfaceMethod org/apache/hadoop/hbase/client/Admin.deleteTable:(Lorg/apache/hadoop/hbase/TableName;)V
      39: aload_1
      40: ifnull        118
      43: aload_2
      44: ifnull        65
      47: aload_1
      48: invokeinterface #29,  1           // InterfaceMethod org/apache/hadoop/hbase/client/Admin.close:()V
      53: goto          118
      56: astore_3
      57: aload_2
      58: aload_3
      59: invokevirtual #31                 // Method java/lang/Throwable.addSuppressed:(Ljava/lang/Throwable;)V
      62: goto          118
      65: aload_1
      66: invokeinterface #29,  1           // InterfaceMethod org/apache/hadoop/hbase/client/Admin.close:()V
      71: goto          118
      74: astore_3
      75: aload_3
      76: astore_2
      77: aload_3
      78: athrow
      79: astore        4
      81: aload_1
      82: ifnull        115
      85: aload_2
      86: ifnull        109
      89: aload_1
      90: invokeinterface #29,  1           // InterfaceMethod org/apache/hadoop/hbase/client/Admin.close:()V
      95: goto          115
      98: astore        5
     100: aload_2
     101: aload         5
     103: invokevirtual #31                 // Method java/lang/Throwable.addSuppressed:(Ljava/lang/Throwable;)V
     106: goto          115
     109: aload_1
     110: invokeinterface #29,  1           // InterfaceMethod org/apache/hadoop/hbase/client/Admin.close:()V
     115: aload         4
     117: athrow
     118: return
    Exception table:
       from    to  target type
          47    53    56   Class java/lang/Throwable
           9    39    74   Class java/lang/Throwable
           9    39    79   any
          89    95    98   Class java/lang/Throwable
          74    81    79   any

  public void testRecoverStandby() throws java.io.IOException, org.apache.hadoop.hbase.util.CommonFSUtils$StreamLacksCapabilityException;
    Code:
       0: aload_0
       1: invokespecial #32                 // Method setupSyncReplicationWALs:()V
       4: getstatic     #16                 // Field procExec:Lorg/apache/hadoop/hbase/procedure2/ProcedureExecutor;
       7: new           #33                 // class org/apache/hadoop/hbase/master/replication/RecoverStandbyProcedure
      10: dup
      11: ldc           #34                 // String 1
      13: iconst_0
      14: invokespecial #35                 // Method org/apache/hadoop/hbase/master/replication/RecoverStandbyProcedure."<init>":(Ljava/lang/String;Z)V
      17: invokevirtual #36                 // Method org/apache/hadoop/hbase/procedure2/ProcedureExecutor.submitProcedure:(Lorg/apache/hadoop/hbase/procedure2/Procedure;)J
      20: lstore_1
      21: getstatic     #16                 // Field procExec:Lorg/apache/hadoop/hbase/procedure2/ProcedureExecutor;
      24: lload_1
      25: invokestatic  #37                 // Method org/apache/hadoop/hbase/procedure2/ProcedureTestingUtility.waitProcedure:(Lorg/apache/hadoop/hbase/procedure2/ProcedureExecutor;J)V
      28: getstatic     #16                 // Field procExec:Lorg/apache/hadoop/hbase/procedure2/ProcedureExecutor;
      31: lload_1
      32: invokestatic  #38                 // Method org/apache/hadoop/hbase/procedure2/ProcedureTestingUtility.assertProcNotFailed:(Lorg/apache/hadoop/hbase/procedure2/ProcedureExecutor;J)V
      35: getstatic     #2                  // Field UTIL:Lorg/apache/hadoop/hbase/HBaseTestingUtility;
      38: invokevirtual #39                 // Method org/apache/hadoop/hbase/HBaseTestingUtility.getConnection:()Lorg/apache/hadoop/hbase/client/Connection;
      41: getstatic     #22                 // Field tableName:Lorg/apache/hadoop/hbase/TableName;
      44: invokeinterface #40,  2           // InterfaceMethod org/apache/hadoop/hbase/client/Connection.getTable:(Lorg/apache/hadoop/hbase/TableName;)Lorg/apache/hadoop/hbase/client/Table;
      49: astore_3
      50: aconst_null
      51: astore        4
      53: iconst_0
      54: istore        5
      56: iload         5
      58: sipush        10000
      61: if_icmpge     122
      64: aload_3
      65: new           #41                 // class org/apache/hadoop/hbase/client/Get
      68: dup
      69: iload         5
      71: invokestatic  #42                 // Method org/apache/hadoop/hbase/util/Bytes.toBytes:(I)[B
      74: invokespecial #43                 // Method org/apache/hadoop/hbase/client/Get."<init>":([B)V
      77: getstatic     #44                 // Field timestamp:J
      80: invokevirtual #45                 // Method org/apache/hadoop/hbase/client/Get.setTimestamp:(J)Lorg/apache/hadoop/hbase/client/Get;
      83: invokeinterface #46,  2           // InterfaceMethod org/apache/hadoop/hbase/client/Table.get:(Lorg/apache/hadoop/hbase/client/Get;)Lorg/apache/hadoop/hbase/client/Result;
      88: astore        6
      90: aload         6
      92: invokestatic  #47                 // Method org/junit/Assert.assertNotNull:(Ljava/lang/Object;)V
      95: iload         5
      97: i2l
      98: aload         6
     100: getstatic     #23                 // Field family:[B
     103: getstatic     #48                 // Field qualifier:[B
     106: invokevirtual #49                 // Method org/apache/hadoop/hbase/client/Result.getValue:([B[B)[B
     109: invokestatic  #50                 // Method org/apache/hadoop/hbase/util/Bytes.toInt:([B)I
     112: i2l
     113: invokestatic  #51                 // Method org/junit/Assert.assertEquals:(JJ)V
     116: iinc          5, 1
     119: goto          56
     122: aload_3
     123: ifnull        211
     126: aload         4
     128: ifnull        152
     131: aload_3
     132: invokeinterface #52,  1           // InterfaceMethod org/apache/hadoop/hbase/client/Table.close:()V
     137: goto          211
     140: astore        5
     142: aload         4
     144: aload         5
     146: invokevirtual #31                 // Method java/lang/Throwable.addSuppressed:(Ljava/lang/Throwable;)V
     149: goto          211
     152: aload_3
     153: invokeinterface #52,  1           // InterfaceMethod org/apache/hadoop/hbase/client/Table.close:()V
     158: goto          211
     161: astore        5
     163: aload         5
     165: astore        4
     167: aload         5
     169: athrow
     170: astore        7
     172: aload_3
     173: ifnull        208
     176: aload         4
     178: ifnull        202
     181: aload_3
     182: invokeinterface #52,  1           // InterfaceMethod org/apache/hadoop/hbase/client/Table.close:()V
     187: goto          208
     190: astore        8
     192: aload         4
     194: aload         8
     196: invokevirtual #31                 // Method java/lang/Throwable.addSuppressed:(Ljava/lang/Throwable;)V
     199: goto          208
     202: aload_3
     203: invokeinterface #52,  1           // InterfaceMethod org/apache/hadoop/hbase/client/Table.close:()V
     208: aload         7
     210: athrow
     211: return
    Exception table:
       from    to  target type
         131   137   140   Class java/lang/Throwable
          53   122   161   Class java/lang/Throwable
          53   122   170   any
         181   187   190   Class java/lang/Throwable
         161   172   170   any

  static {};
    Code:
       0: ldc           #3                  // class org/apache/hadoop/hbase/replication/master/TestRecoverStandbyProcedure
       2: invokestatic  #97                 // Method org/apache/hadoop/hbase/HBaseClassTestRule.forClass:(Ljava/lang/Class;)Lorg/apache/hadoop/hbase/HBaseClassTestRule;
       5: putstatic     #98                 // Field CLASS_RULE:Lorg/apache/hadoop/hbase/HBaseClassTestRule;
       8: ldc           #3                  // class org/apache/hadoop/hbase/replication/master/TestRecoverStandbyProcedure
      10: invokestatic  #99                 // Method org/slf4j/LoggerFactory.getLogger:(Ljava/lang/Class;)Lorg/slf4j/Logger;
      13: putstatic     #19                 // Field LOG:Lorg/slf4j/Logger;
      16: ldc           #100                // String TestRecoverStandbyProcedure
      18: invokestatic  #101                // Method org/apache/hadoop/hbase/TableName.valueOf:(Ljava/lang/String;)Lorg/apache/hadoop/hbase/TableName;
      21: putstatic     #22                 // Field tableName:Lorg/apache/hadoop/hbase/TableName;
      24: getstatic     #22                 // Field tableName:Lorg/apache/hadoop/hbase/TableName;
      27: invokestatic  #102                // Method org/apache/hadoop/hbase/client/RegionInfoBuilder.newBuilder:(Lorg/apache/hadoop/hbase/TableName;)Lorg/apache/hadoop/hbase/client/RegionInfoBuilder;
      30: invokevirtual #103                // Method org/apache/hadoop/hbase/client/RegionInfoBuilder.build:()Lorg/apache/hadoop/hbase/client/RegionInfo;
      33: putstatic     #87                 // Field regionInfo:Lorg/apache/hadoop/hbase/client/RegionInfo;
      36: ldc           #104                // String CF
      38: invokestatic  #105                // Method org/apache/hadoop/hbase/util/Bytes.toBytes:(Ljava/lang/String;)[B
      41: putstatic     #23                 // Field family:[B
      44: ldc           #106                // String q
      46: invokestatic  #105                // Method org/apache/hadoop/hbase/util/Bytes.toBytes:(Ljava/lang/String;)[B
      49: putstatic     #48                 // Field qualifier:[B
      52: invokestatic  #107                // Method java/lang/System.currentTimeMillis:()J
      55: putstatic     #44                 // Field timestamp:J
      58: new           #108                // class org/apache/hadoop/hbase/HBaseTestingUtility
      61: dup
      62: invokespecial #109                // Method org/apache/hadoop/hbase/HBaseTestingUtility."<init>":()V
      65: putstatic     #2                  // Field UTIL:Lorg/apache/hadoop/hbase/HBaseTestingUtility;
      68: return
}
