Compiled from "TestRemoveFromSerialReplicationPeer.java"
public class org.apache.hadoop.hbase.replication.TestRemoveFromSerialReplicationPeer extends org.apache.hadoop.hbase.replication.SerialReplicationTestBase {
  public static final org.apache.hadoop.hbase.HBaseClassTestRule CLASS_RULE;

  public org.apache.hadoop.hbase.replication.TestRemoveFromSerialReplicationPeer();
    Code:
       0: aload_0
       1: invokespecial #1                  // Method org/apache/hadoop/hbase/replication/SerialReplicationTestBase."<init>":()V
       4: return

  public void setUp() throws java.io.IOException, org.apache.hadoop.hbase.util.CommonFSUtils$StreamLacksCapabilityException;
    Code:
       0: aload_0
       1: invokevirtual #2                  // Method setupWALWriter:()V
       4: return

  public void testRemoveTable() throws java.lang.Exception;
    Code:
       0: aload_0
       1: invokevirtual #13                 // Method createTable:()Lorg/apache/hadoop/hbase/TableName;
       4: astore_1
       5: invokestatic  #14                 // Method org/apache/hadoop/hbase/replication/ReplicationPeerConfig.newBuilder:()Lorg/apache/hadoop/hbase/replication/ReplicationPeerConfigBuilder;
       8: ldc           #15                 // String 127.0.0.1:2181:/hbase
      10: invokeinterface #16,  2           // InterfaceMethod org/apache/hadoop/hbase/replication/ReplicationPeerConfigBuilder.setClusterKey:(Ljava/lang/String;)Lorg/apache/hadoop/hbase/replication/ReplicationPeerConfigBuilder;
      15: ldc           #17                 // class org/apache/hadoop/hbase/replication/SerialReplicationTestBase$LocalReplicationEndpoint
      17: invokevirtual #18                 // Method java/lang/Class.getName:()Ljava/lang/String;
      20: invokeinterface #19,  2           // InterfaceMethod org/apache/hadoop/hbase/replication/ReplicationPeerConfigBuilder.setReplicationEndpointImpl:(Ljava/lang/String;)Lorg/apache/hadoop/hbase/replication/ReplicationPeerConfigBuilder;
      25: iconst_0
      26: invokeinterface #20,  2           // InterfaceMethod org/apache/hadoop/hbase/replication/ReplicationPeerConfigBuilder.setReplicateAllUserTables:(Z)Lorg/apache/hadoop/hbase/replication/ReplicationPeerConfigBuilder;
      31: aload_1
      32: invokestatic  #21                 // Method java/util/Collections.emptyList:()Ljava/util/List;
      35: invokestatic  #22                 // Method org/apache/hbase/thirdparty/com/google/common/collect/ImmutableMap.of:(Ljava/lang/Object;Ljava/lang/Object;)Lorg/apache/hbase/thirdparty/com/google/common/collect/ImmutableMap;
      38: invokeinterface #23,  2           // InterfaceMethod org/apache/hadoop/hbase/replication/ReplicationPeerConfigBuilder.setTableCFsMap:(Ljava/util/Map;)Lorg/apache/hadoop/hbase/replication/ReplicationPeerConfigBuilder;
      43: iconst_1
      44: invokeinterface #24,  2           // InterfaceMethod org/apache/hadoop/hbase/replication/ReplicationPeerConfigBuilder.setSerial:(Z)Lorg/apache/hadoop/hbase/replication/ReplicationPeerConfigBuilder;
      49: invokeinterface #25,  1           // InterfaceMethod org/apache/hadoop/hbase/replication/ReplicationPeerConfigBuilder.build:()Lorg/apache/hadoop/hbase/replication/ReplicationPeerConfig;
      54: astore_2
      55: getstatic     #3                  // Field UTIL:Lorg/apache/hadoop/hbase/HBaseTestingUtility;
      58: invokevirtual #26                 // Method org/apache/hadoop/hbase/HBaseTestingUtility.getAdmin:()Lorg/apache/hadoop/hbase/client/Admin;
      61: getstatic     #27                 // Field PEER_ID:Ljava/lang/String;
      64: aload_2
      65: iconst_1
      66: invokeinterface #28,  4           // InterfaceMethod org/apache/hadoop/hbase/client/Admin.addReplicationPeer:(Ljava/lang/String;Lorg/apache/hadoop/hbase/replication/ReplicationPeerConfig;Z)V
      71: getstatic     #3                  // Field UTIL:Lorg/apache/hadoop/hbase/HBaseTestingUtility;
      74: invokevirtual #29                 // Method org/apache/hadoop/hbase/HBaseTestingUtility.getConnection:()Lorg/apache/hadoop/hbase/client/Connection;
      77: aload_1
      78: invokeinterface #30,  2           // InterfaceMethod org/apache/hadoop/hbase/client/Connection.getTable:(Lorg/apache/hadoop/hbase/TableName;)Lorg/apache/hadoop/hbase/client/Table;
      83: astore_3
      84: aconst_null
      85: astore        4
      87: iconst_0
      88: istore        5
      90: iload         5
      92: bipush        100
      94: if_icmpge     135
      97: aload_3
      98: new           #31                 // class org/apache/hadoop/hbase/client/Put
     101: dup
     102: iload         5
     104: invokestatic  #32                 // Method org/apache/hadoop/hbase/util/Bytes.toBytes:(I)[B
     107: invokespecial #33                 // Method org/apache/hadoop/hbase/client/Put."<init>":([B)V
     110: getstatic     #34                 // Field CF:[B
     113: getstatic     #35                 // Field CQ:[B
     116: iload         5
     118: invokestatic  #32                 // Method org/apache/hadoop/hbase/util/Bytes.toBytes:(I)[B
     121: invokevirtual #36                 // Method org/apache/hadoop/hbase/client/Put.addColumn:([B[B[B)Lorg/apache/hadoop/hbase/client/Put;
     124: invokeinterface #37,  2           // InterfaceMethod org/apache/hadoop/hbase/client/Table.put:(Lorg/apache/hadoop/hbase/client/Put;)V
     129: iinc          5, 1
     132: goto          90
     135: aload_3
     136: ifnull        224
     139: aload         4
     141: ifnull        165
     144: aload_3
     145: invokeinterface #38,  1           // InterfaceMethod org/apache/hadoop/hbase/client/Table.close:()V
     150: goto          224
     153: astore        5
     155: aload         4
     157: aload         5
     159: invokevirtual #40                 // Method java/lang/Throwable.addSuppressed:(Ljava/lang/Throwable;)V
     162: goto          224
     165: aload_3
     166: invokeinterface #38,  1           // InterfaceMethod org/apache/hadoop/hbase/client/Table.close:()V
     171: goto          224
     174: astore        5
     176: aload         5
     178: astore        4
     180: aload         5
     182: athrow
     183: astore        6
     185: aload_3
     186: ifnull        221
     189: aload         4
     191: ifnull        215
     194: aload_3
     195: invokeinterface #38,  1           // InterfaceMethod org/apache/hadoop/hbase/client/Table.close:()V
     200: goto          221
     203: astore        7
     205: aload         4
     207: aload         7
     209: invokevirtual #40                 // Method java/lang/Throwable.addSuppressed:(Ljava/lang/Throwable;)V
     212: goto          221
     215: aload_3
     216: invokeinterface #38,  1           // InterfaceMethod org/apache/hadoop/hbase/client/Table.close:()V
     221: aload         6
     223: athrow
     224: getstatic     #3                  // Field UTIL:Lorg/apache/hadoop/hbase/HBaseTestingUtility;
     227: invokevirtual #4                  // Method org/apache/hadoop/hbase/HBaseTestingUtility.getMiniHBaseCluster:()Lorg/apache/hadoop/hbase/MiniHBaseCluster;
     230: aload_1
     231: invokevirtual #41                 // Method org/apache/hadoop/hbase/MiniHBaseCluster.getRegions:(Lorg/apache/hadoop/hbase/TableName;)Ljava/util/List;
     234: iconst_0
     235: invokeinterface #42,  2           // InterfaceMethod java/util/List.get:(I)Ljava/lang/Object;
     240: checkcast     #43                 // class org/apache/hadoop/hbase/regionserver/HRegion
     243: invokevirtual #44                 // Method org/apache/hadoop/hbase/regionserver/HRegion.getRegionInfo:()Lorg/apache/hadoop/hbase/client/RegionInfo;
     246: astore_3
     247: aload_0
     248: aload_3
     249: invokespecial #45                 // Method waitUntilHasLastPushedSequenceId:(Lorg/apache/hadoop/hbase/client/RegionInfo;)V
     252: getstatic     #3                  // Field UTIL:Lorg/apache/hadoop/hbase/HBaseTestingUtility;
     255: invokevirtual #26                 // Method org/apache/hadoop/hbase/HBaseTestingUtility.getAdmin:()Lorg/apache/hadoop/hbase/client/Admin;
     258: getstatic     #27                 // Field PEER_ID:Ljava/lang/String;
     261: aload_2
     262: invokestatic  #46                 // Method org/apache/hadoop/hbase/replication/ReplicationPeerConfig.newBuilder:(Lorg/apache/hadoop/hbase/replication/ReplicationPeerConfig;)Lorg/apache/hadoop/hbase/replication/ReplicationPeerConfigBuilder;
     265: invokestatic  #47                 // Method java/util/Collections.emptyMap:()Ljava/util/Map;
     268: invokeinterface #23,  2           // InterfaceMethod org/apache/hadoop/hbase/replication/ReplicationPeerConfigBuilder.setTableCFsMap:(Ljava/util/Map;)Lorg/apache/hadoop/hbase/replication/ReplicationPeerConfigBuilder;
     273: invokeinterface #25,  1           // InterfaceMethod org/apache/hadoop/hbase/replication/ReplicationPeerConfigBuilder.build:()Lorg/apache/hadoop/hbase/replication/ReplicationPeerConfig;
     278: invokeinterface #48,  3           // InterfaceMethod org/apache/hadoop/hbase/client/Admin.updateReplicationPeerConfig:(Ljava/lang/String;Lorg/apache/hadoop/hbase/replication/ReplicationPeerConfig;)V
     283: getstatic     #3                  // Field UTIL:Lorg/apache/hadoop/hbase/HBaseTestingUtility;
     286: invokevirtual #4                  // Method org/apache/hadoop/hbase/HBaseTestingUtility.getMiniHBaseCluster:()Lorg/apache/hadoop/hbase/MiniHBaseCluster;
     289: invokevirtual #5                  // Method org/apache/hadoop/hbase/MiniHBaseCluster.getMaster:()Lorg/apache/hadoop/hbase/master/HMaster;
     292: invokevirtual #6                  // Method org/apache/hadoop/hbase/master/HMaster.getReplicationPeerManager:()Lorg/apache/hadoop/hbase/master/replication/ReplicationPeerManager;
     295: invokevirtual #7                  // Method org/apache/hadoop/hbase/master/replication/ReplicationPeerManager.getQueueStorage:()Lorg/apache/hadoop/hbase/replication/ReplicationQueueStorage;
     298: astore        4
     300: ldc2_w        #50                 // long -1l
     303: aload         4
     305: aload_3
     306: invokeinterface #52,  1           // InterfaceMethod org/apache/hadoop/hbase/client/RegionInfo.getEncodedName:()Ljava/lang/String;
     311: getstatic     #27                 // Field PEER_ID:Ljava/lang/String;
     314: invokeinterface #53,  3           // InterfaceMethod org/apache/hadoop/hbase/replication/ReplicationQueueStorage.getLastSequenceId:(Ljava/lang/String;Ljava/lang/String;)J
     319: invokestatic  #54                 // Method org/junit/Assert.assertEquals:(JJ)V
     322: return
    Exception table:
       from    to  target type
         144   150   153   Class java/lang/Throwable
          87   135   174   Class java/lang/Throwable
          87   135   183   any
         194   200   203   Class java/lang/Throwable
         174   185   183   any

  public void testRemoveSerialFlag() throws java.lang.Exception;
    Code:
       0: aload_0
       1: invokevirtual #13                 // Method createTable:()Lorg/apache/hadoop/hbase/TableName;
       4: astore_1
       5: aload_0
       6: iconst_1
       7: invokevirtual #55                 // Method addPeer:(Z)V
      10: getstatic     #3                  // Field UTIL:Lorg/apache/hadoop/hbase/HBaseTestingUtility;
      13: invokevirtual #29                 // Method org/apache/hadoop/hbase/HBaseTestingUtility.getConnection:()Lorg/apache/hadoop/hbase/client/Connection;
      16: aload_1
      17: invokeinterface #30,  2           // InterfaceMethod org/apache/hadoop/hbase/client/Connection.getTable:(Lorg/apache/hadoop/hbase/TableName;)Lorg/apache/hadoop/hbase/client/Table;
      22: astore_2
      23: aconst_null
      24: astore_3
      25: iconst_0
      26: istore        4
      28: iload         4
      30: bipush        100
      32: if_icmpge     73
      35: aload_2
      36: new           #31                 // class org/apache/hadoop/hbase/client/Put
      39: dup
      40: iload         4
      42: invokestatic  #32                 // Method org/apache/hadoop/hbase/util/Bytes.toBytes:(I)[B
      45: invokespecial #33                 // Method org/apache/hadoop/hbase/client/Put."<init>":([B)V
      48: getstatic     #34                 // Field CF:[B
      51: getstatic     #35                 // Field CQ:[B
      54: iload         4
      56: invokestatic  #32                 // Method org/apache/hadoop/hbase/util/Bytes.toBytes:(I)[B
      59: invokevirtual #36                 // Method org/apache/hadoop/hbase/client/Put.addColumn:([B[B[B)Lorg/apache/hadoop/hbase/client/Put;
      62: invokeinterface #37,  2           // InterfaceMethod org/apache/hadoop/hbase/client/Table.put:(Lorg/apache/hadoop/hbase/client/Put;)V
      67: iinc          4, 1
      70: goto          28
      73: aload_2
      74: ifnull        157
      77: aload_3
      78: ifnull        101
      81: aload_2
      82: invokeinterface #38,  1           // InterfaceMethod org/apache/hadoop/hbase/client/Table.close:()V
      87: goto          157
      90: astore        4
      92: aload_3
      93: aload         4
      95: invokevirtual #40                 // Method java/lang/Throwable.addSuppressed:(Ljava/lang/Throwable;)V
      98: goto          157
     101: aload_2
     102: invokeinterface #38,  1           // InterfaceMethod org/apache/hadoop/hbase/client/Table.close:()V
     107: goto          157
     110: astore        4
     112: aload         4
     114: astore_3
     115: aload         4
     117: athrow
     118: astore        5
     120: aload_2
     121: ifnull        154
     124: aload_3
     125: ifnull        148
     128: aload_2
     129: invokeinterface #38,  1           // InterfaceMethod org/apache/hadoop/hbase/client/Table.close:()V
     134: goto          154
     137: astore        6
     139: aload_3
     140: aload         6
     142: invokevirtual #40                 // Method java/lang/Throwable.addSuppressed:(Ljava/lang/Throwable;)V
     145: goto          154
     148: aload_2
     149: invokeinterface #38,  1           // InterfaceMethod org/apache/hadoop/hbase/client/Table.close:()V
     154: aload         5
     156: athrow
     157: getstatic     #3                  // Field UTIL:Lorg/apache/hadoop/hbase/HBaseTestingUtility;
     160: invokevirtual #4                  // Method org/apache/hadoop/hbase/HBaseTestingUtility.getMiniHBaseCluster:()Lorg/apache/hadoop/hbase/MiniHBaseCluster;
     163: aload_1
     164: invokevirtual #41                 // Method org/apache/hadoop/hbase/MiniHBaseCluster.getRegions:(Lorg/apache/hadoop/hbase/TableName;)Ljava/util/List;
     167: iconst_0
     168: invokeinterface #42,  2           // InterfaceMethod java/util/List.get:(I)Ljava/lang/Object;
     173: checkcast     #43                 // class org/apache/hadoop/hbase/regionserver/HRegion
     176: invokevirtual #44                 // Method org/apache/hadoop/hbase/regionserver/HRegion.getRegionInfo:()Lorg/apache/hadoop/hbase/client/RegionInfo;
     179: astore_2
     180: aload_0
     181: aload_2
     182: invokespecial #45                 // Method waitUntilHasLastPushedSequenceId:(Lorg/apache/hadoop/hbase/client/RegionInfo;)V
     185: getstatic     #3                  // Field UTIL:Lorg/apache/hadoop/hbase/HBaseTestingUtility;
     188: invokevirtual #26                 // Method org/apache/hadoop/hbase/HBaseTestingUtility.getAdmin:()Lorg/apache/hadoop/hbase/client/Admin;
     191: getstatic     #27                 // Field PEER_ID:Ljava/lang/String;
     194: getstatic     #3                  // Field UTIL:Lorg/apache/hadoop/hbase/HBaseTestingUtility;
     197: invokevirtual #26                 // Method org/apache/hadoop/hbase/HBaseTestingUtility.getAdmin:()Lorg/apache/hadoop/hbase/client/Admin;
     200: getstatic     #27                 // Field PEER_ID:Ljava/lang/String;
     203: invokeinterface #56,  2           // InterfaceMethod org/apache/hadoop/hbase/client/Admin.getReplicationPeerConfig:(Ljava/lang/String;)Lorg/apache/hadoop/hbase/replication/ReplicationPeerConfig;
     208: invokestatic  #46                 // Method org/apache/hadoop/hbase/replication/ReplicationPeerConfig.newBuilder:(Lorg/apache/hadoop/hbase/replication/ReplicationPeerConfig;)Lorg/apache/hadoop/hbase/replication/ReplicationPeerConfigBuilder;
     211: iconst_0
     212: invokeinterface #24,  2           // InterfaceMethod org/apache/hadoop/hbase/replication/ReplicationPeerConfigBuilder.setSerial:(Z)Lorg/apache/hadoop/hbase/replication/ReplicationPeerConfigBuilder;
     217: invokeinterface #25,  1           // InterfaceMethod org/apache/hadoop/hbase/replication/ReplicationPeerConfigBuilder.build:()Lorg/apache/hadoop/hbase/replication/ReplicationPeerConfig;
     222: invokeinterface #48,  3           // InterfaceMethod org/apache/hadoop/hbase/client/Admin.updateReplicationPeerConfig:(Ljava/lang/String;Lorg/apache/hadoop/hbase/replication/ReplicationPeerConfig;)V
     227: aload_0
     228: bipush        100
     230: invokevirtual #57                 // Method waitUntilReplicationDone:(I)V
     233: getstatic     #3                  // Field UTIL:Lorg/apache/hadoop/hbase/HBaseTestingUtility;
     236: invokevirtual #4                  // Method org/apache/hadoop/hbase/HBaseTestingUtility.getMiniHBaseCluster:()Lorg/apache/hadoop/hbase/MiniHBaseCluster;
     239: invokevirtual #5                  // Method org/apache/hadoop/hbase/MiniHBaseCluster.getMaster:()Lorg/apache/hadoop/hbase/master/HMaster;
     242: invokevirtual #6                  // Method org/apache/hadoop/hbase/master/HMaster.getReplicationPeerManager:()Lorg/apache/hadoop/hbase/master/replication/ReplicationPeerManager;
     245: invokevirtual #7                  // Method org/apache/hadoop/hbase/master/replication/ReplicationPeerManager.getQueueStorage:()Lorg/apache/hadoop/hbase/replication/ReplicationQueueStorage;
     248: astore_3
     249: ldc2_w        #50                 // long -1l
     252: aload_3
     253: aload_2
     254: invokeinterface #52,  1           // InterfaceMethod org/apache/hadoop/hbase/client/RegionInfo.getEncodedName:()Ljava/lang/String;
     259: getstatic     #27                 // Field PEER_ID:Ljava/lang/String;
     262: invokeinterface #53,  3           // InterfaceMethod org/apache/hadoop/hbase/replication/ReplicationQueueStorage.getLastSequenceId:(Ljava/lang/String;Ljava/lang/String;)J
     267: invokestatic  #54                 // Method org/junit/Assert.assertEquals:(JJ)V
     270: return
    Exception table:
       from    to  target type
          81    87    90   Class java/lang/Throwable
          25    73   110   Class java/lang/Throwable
          25    73   118   any
         128   134   137   Class java/lang/Throwable
         110   120   118   any

  static {};
    Code:
       0: ldc           #58                 // class org/apache/hadoop/hbase/replication/TestRemoveFromSerialReplicationPeer
       2: invokestatic  #59                 // Method org/apache/hadoop/hbase/HBaseClassTestRule.forClass:(Ljava/lang/Class;)Lorg/apache/hadoop/hbase/HBaseClassTestRule;
       5: putstatic     #60                 // Field CLASS_RULE:Lorg/apache/hadoop/hbase/HBaseClassTestRule;
       8: return
}
