Compiled from "TestAsyncProcess.java"
class org.apache.hadoop.hbase.client.TestAsyncProcess$CountingThreadFactory implements java.util.concurrent.ThreadFactory {
  final java.util.concurrent.atomic.AtomicInteger nbThreads;

  java.util.concurrent.ThreadFactory realFactory;

  public java.lang.Thread newThread(java.lang.Runnable);
    Code:
       0: aload_0
       1: getfield      #1                  // Field nbThreads:Ljava/util/concurrent/atomic/AtomicInteger;
       4: invokevirtual #2                  // Method java/util/concurrent/atomic/AtomicInteger.incrementAndGet:()I
       7: pop
       8: aload_0
       9: getfield      #3                  // Field realFactory:Ljava/util/concurrent/ThreadFactory;
      12: aload_1
      13: invokeinterface #4,  2            // InterfaceMethod java/util/concurrent/ThreadFactory.newThread:(Ljava/lang/Runnable;)Ljava/lang/Thread;
      18: areturn

  org.apache.hadoop.hbase.client.TestAsyncProcess$CountingThreadFactory(java.util.concurrent.atomic.AtomicInteger);
    Code:
       0: aload_0
       1: invokespecial #5                  // Method java/lang/Object."<init>":()V
       4: aload_0
       5: ldc           #6                  // String test-TestAsyncProcess
       7: invokestatic  #7                  // Method org/apache/hadoop/hbase/util/Threads.newDaemonThreadFactory:(Ljava/lang/String;)Ljava/util/concurrent/ThreadFactory;
      10: putfield      #3                  // Field realFactory:Ljava/util/concurrent/ThreadFactory;
      13: aload_0
      14: aload_1
      15: putfield      #1                  // Field nbThreads:Ljava/util/concurrent/atomic/AtomicInteger;
      18: return
}
