Compiled from "TestAtomicOperation.java"
class org.apache.hadoop.hbase.regionserver.TestAtomicOperation$3 extends org.apache.hadoop.hbase.regionserver.TestAtomicOperation$AtomicOperation {
  final java.util.List val$rowsToLock;

  final org.apache.hadoop.hbase.regionserver.TestAtomicOperation this$0;

  org.apache.hadoop.hbase.regionserver.TestAtomicOperation$3(org.apache.hadoop.hbase.regionserver.TestAtomicOperation, org.apache.hadoop.hbase.regionserver.HRegion, int, java.util.concurrent.atomic.AtomicLong, java.util.concurrent.atomic.AtomicInteger, java.util.List);
    Code:
       0: aload_0
       1: aload_1
       2: putfield      #1                  // Field this$0:Lorg/apache/hadoop/hbase/regionserver/TestAtomicOperation;
       5: aload_0
       6: aload         6
       8: putfield      #2                  // Field val$rowsToLock:Ljava/util/List;
      11: aload_0
      12: aload_2
      13: iload_3
      14: aload         4
      16: aload         5
      18: invokespecial #3                  // Method org/apache/hadoop/hbase/regionserver/TestAtomicOperation$AtomicOperation."<init>":(Lorg/apache/hadoop/hbase/regionserver/HRegion;ILjava/util/concurrent/atomic/AtomicLong;Ljava/util/concurrent/atomic/AtomicInteger;)V
      21: return

  public void run();
    Code:
       0: iconst_1
       1: istore_1
       2: iconst_0
       3: istore_2
       4: iload_2
       5: aload_0
       6: getfield      #4                  // Field numOps:I
       9: if_icmpge     411
      12: iload_2
      13: bipush        10
      15: irem
      16: ifne          72
      19: aload_0
      20: getfield      #5                  // Field region:Lorg/apache/hadoop/hbase/regionserver/HRegion;
      23: dup
      24: astore_3
      25: monitorenter
      26: invokestatic  #6                  // Method org/apache/hadoop/hbase/regionserver/TestAtomicOperation.access$000:()Lorg/slf4j/Logger;
      29: ldc           #7                  // String flushing
      31: invokeinterface #8,  2            // InterfaceMethod org/slf4j/Logger.debug:(Ljava/lang/String;)V
      36: aload_0
      37: getfield      #5                  // Field region:Lorg/apache/hadoop/hbase/regionserver/HRegion;
      40: iconst_1
      41: invokevirtual #9                  // Method org/apache/hadoop/hbase/regionserver/HRegion.flush:(Z)Lorg/apache/hadoop/hbase/regionserver/HRegion$FlushResult;
      44: pop
      45: iload_2
      46: bipush        100
      48: irem
      49: ifne          60
      52: aload_0
      53: getfield      #5                  // Field region:Lorg/apache/hadoop/hbase/regionserver/HRegion;
      56: iconst_0
      57: invokevirtual #10                 // Method org/apache/hadoop/hbase/regionserver/HRegion.compact:(Z)V
      60: aload_3
      61: monitorexit
      62: goto          72
      65: astore        4
      67: aload_3
      68: monitorexit
      69: aload         4
      71: athrow
      72: aload_0
      73: getfield      #11                 // Field timeStamps:Ljava/util/concurrent/atomic/AtomicLong;
      76: invokevirtual #12                 // Method java/util/concurrent/atomic/AtomicLong.incrementAndGet:()J
      79: lstore_3
      80: new           #13                 // class java/util/ArrayList
      83: dup
      84: invokespecial #14                 // Method java/util/ArrayList."<init>":()V
      87: astore        5
      89: iload_1
      90: ifeq          187
      93: new           #15                 // class org/apache/hadoop/hbase/client/Put
      96: dup
      97: getstatic     #16                 // Field org/apache/hadoop/hbase/regionserver/TestAtomicOperation.row2:[B
     100: lload_3
     101: invokespecial #17                 // Method org/apache/hadoop/hbase/client/Put."<init>":([BJ)V
     104: astore        6
     106: aload         6
     108: getstatic     #18                 // Field org/apache/hadoop/hbase/HBaseTestingUtility.fam1:[B
     111: getstatic     #19                 // Field org/apache/hadoop/hbase/regionserver/TestAtomicOperation.qual1:[B
     114: getstatic     #20                 // Field org/apache/hadoop/hbase/regionserver/TestAtomicOperation.value1:[B
     117: invokevirtual #21                 // Method org/apache/hadoop/hbase/client/Put.addColumn:([B[B[B)Lorg/apache/hadoop/hbase/client/Put;
     120: pop
     121: aload         6
     123: getstatic     #22                 // Field org/apache/hadoop/hbase/client/Durability.ASYNC_WAL:Lorg/apache/hadoop/hbase/client/Durability;
     126: invokevirtual #23                 // Method org/apache/hadoop/hbase/client/Put.setDurability:(Lorg/apache/hadoop/hbase/client/Durability;)Lorg/apache/hadoop/hbase/client/Put;
     129: pop
     130: aload         5
     132: aload         6
     134: invokeinterface #24,  2           // InterfaceMethod java/util/List.add:(Ljava/lang/Object;)Z
     139: pop
     140: new           #25                 // class org/apache/hadoop/hbase/client/Delete
     143: dup
     144: getstatic     #26                 // Field org/apache/hadoop/hbase/regionserver/TestAtomicOperation.row:[B
     147: invokespecial #27                 // Method org/apache/hadoop/hbase/client/Delete."<init>":([B)V
     150: astore        7
     152: aload         7
     154: getstatic     #18                 // Field org/apache/hadoop/hbase/HBaseTestingUtility.fam1:[B
     157: getstatic     #19                 // Field org/apache/hadoop/hbase/regionserver/TestAtomicOperation.qual1:[B
     160: lload_3
     161: invokevirtual #28                 // Method org/apache/hadoop/hbase/client/Delete.addColumns:([B[BJ)Lorg/apache/hadoop/hbase/client/Delete;
     164: pop
     165: aload         7
     167: getstatic     #22                 // Field org/apache/hadoop/hbase/client/Durability.ASYNC_WAL:Lorg/apache/hadoop/hbase/client/Durability;
     170: invokevirtual #29                 // Method org/apache/hadoop/hbase/client/Delete.setDurability:(Lorg/apache/hadoop/hbase/client/Durability;)Lorg/apache/hadoop/hbase/client/Delete;
     173: pop
     174: aload         5
     176: aload         7
     178: invokeinterface #24,  2           // InterfaceMethod java/util/List.add:(Ljava/lang/Object;)Z
     183: pop
     184: goto          278
     187: new           #25                 // class org/apache/hadoop/hbase/client/Delete
     190: dup
     191: getstatic     #16                 // Field org/apache/hadoop/hbase/regionserver/TestAtomicOperation.row2:[B
     194: invokespecial #27                 // Method org/apache/hadoop/hbase/client/Delete."<init>":([B)V
     197: astore        6
     199: aload         6
     201: getstatic     #18                 // Field org/apache/hadoop/hbase/HBaseTestingUtility.fam1:[B
     204: getstatic     #19                 // Field org/apache/hadoop/hbase/regionserver/TestAtomicOperation.qual1:[B
     207: lload_3
     208: invokevirtual #28                 // Method org/apache/hadoop/hbase/client/Delete.addColumns:([B[BJ)Lorg/apache/hadoop/hbase/client/Delete;
     211: pop
     212: aload         6
     214: getstatic     #22                 // Field org/apache/hadoop/hbase/client/Durability.ASYNC_WAL:Lorg/apache/hadoop/hbase/client/Durability;
     217: invokevirtual #29                 // Method org/apache/hadoop/hbase/client/Delete.setDurability:(Lorg/apache/hadoop/hbase/client/Durability;)Lorg/apache/hadoop/hbase/client/Delete;
     220: pop
     221: aload         5
     223: aload         6
     225: invokeinterface #24,  2           // InterfaceMethod java/util/List.add:(Ljava/lang/Object;)Z
     230: pop
     231: new           #15                 // class org/apache/hadoop/hbase/client/Put
     234: dup
     235: getstatic     #26                 // Field org/apache/hadoop/hbase/regionserver/TestAtomicOperation.row:[B
     238: lload_3
     239: invokespecial #17                 // Method org/apache/hadoop/hbase/client/Put."<init>":([BJ)V
     242: astore        7
     244: aload         7
     246: getstatic     #22                 // Field org/apache/hadoop/hbase/client/Durability.ASYNC_WAL:Lorg/apache/hadoop/hbase/client/Durability;
     249: invokevirtual #23                 // Method org/apache/hadoop/hbase/client/Put.setDurability:(Lorg/apache/hadoop/hbase/client/Durability;)Lorg/apache/hadoop/hbase/client/Put;
     252: pop
     253: aload         7
     255: getstatic     #18                 // Field org/apache/hadoop/hbase/HBaseTestingUtility.fam1:[B
     258: getstatic     #19                 // Field org/apache/hadoop/hbase/regionserver/TestAtomicOperation.qual1:[B
     261: getstatic     #30                 // Field org/apache/hadoop/hbase/regionserver/TestAtomicOperation.value2:[B
     264: invokevirtual #21                 // Method org/apache/hadoop/hbase/client/Put.addColumn:([B[B[B)Lorg/apache/hadoop/hbase/client/Put;
     267: pop
     268: aload         5
     270: aload         7
     272: invokeinterface #24,  2           // InterfaceMethod java/util/List.add:(Ljava/lang/Object;)Z
     277: pop
     278: aload_0
     279: getfield      #5                  // Field region:Lorg/apache/hadoop/hbase/regionserver/HRegion;
     282: aload         5
     284: aload_0
     285: getfield      #2                  // Field val$rowsToLock:Ljava/util/List;
     288: lconst_0
     289: lconst_0
     290: invokevirtual #32                 // Method org/apache/hadoop/hbase/regionserver/HRegion.mutateRowsWithLocks:(Ljava/util/Collection;Ljava/util/Collection;JJ)V
     293: iload_1
     294: iconst_1
     295: ixor
     296: istore_1
     297: new           #33                 // class org/apache/hadoop/hbase/client/Scan
     300: dup
     301: getstatic     #26                 // Field org/apache/hadoop/hbase/regionserver/TestAtomicOperation.row:[B
     304: invokespecial #34                 // Method org/apache/hadoop/hbase/client/Scan."<init>":([B)V
     307: astore        6
     309: aload_0
     310: getfield      #5                  // Field region:Lorg/apache/hadoop/hbase/regionserver/HRegion;
     313: aload         6
     315: invokevirtual #35                 // Method org/apache/hadoop/hbase/regionserver/HRegion.getScanner:(Lorg/apache/hadoop/hbase/client/Scan;)Lorg/apache/hadoop/hbase/regionserver/HRegion$RegionScannerImpl;
     318: astore        7
     320: new           #13                 // class java/util/ArrayList
     323: dup
     324: invokespecial #14                 // Method java/util/ArrayList."<init>":()V
     327: astore        8
     329: aload         7
     331: aload         8
     333: invokeinterface #36,  2           // InterfaceMethod org/apache/hadoop/hbase/regionserver/RegionScanner.next:(Ljava/util/List;)Z
     338: ifeq          344
     341: goto          329
     344: aload         7
     346: invokeinterface #37,  1           // InterfaceMethod org/apache/hadoop/hbase/regionserver/RegionScanner.close:()V
     351: aload         8
     353: invokeinterface #38,  1           // InterfaceMethod java/util/List.size:()I
     358: iconst_1
     359: if_icmpeq     386
     362: invokestatic  #6                  // Method org/apache/hadoop/hbase/regionserver/TestAtomicOperation.access$000:()Lorg/slf4j/Logger;
     365: aload         8
     367: invokestatic  #39                 // Method java/util/Objects.toString:(Ljava/lang/Object;)Ljava/lang/String;
     370: invokeinterface #8,  2            // InterfaceMethod org/slf4j/Logger.debug:(Ljava/lang/String;)V
     375: aload_0
     376: getfield      #40                 // Field failures:Ljava/util/concurrent/atomic/AtomicInteger;
     379: invokevirtual #41                 // Method java/util/concurrent/atomic/AtomicInteger.incrementAndGet:()I
     382: pop
     383: invokestatic  #42                 // Method org/junit/Assert.fail:()V
     386: goto          405
     389: astore_3
     390: aload_3
     391: invokevirtual #44                 // Method java/io/IOException.printStackTrace:()V
     394: aload_0
     395: getfield      #40                 // Field failures:Ljava/util/concurrent/atomic/AtomicInteger;
     398: invokevirtual #41                 // Method java/util/concurrent/atomic/AtomicInteger.incrementAndGet:()I
     401: pop
     402: invokestatic  #42                 // Method org/junit/Assert.fail:()V
     405: iinc          2, 1
     408: goto          4
     411: return
    Exception table:
       from    to  target type
          26    62    65   any
          65    69    65   any
          12   386   389   Class java/io/IOException
}
