Compiled from "TestSnapshotClientRetries.java"
public class org.apache.hadoop.hbase.snapshot.TestSnapshotClientRetries$MasterSyncObserver implements org.apache.hadoop.hbase.coprocessor.MasterCoprocessor,org.apache.hadoop.hbase.coprocessor.MasterObserver {
  volatile java.util.concurrent.atomic.AtomicInteger snapshotCount;

  volatile java.util.concurrent.atomic.AtomicInteger cloneCount;

  public org.apache.hadoop.hbase.snapshot.TestSnapshotClientRetries$MasterSyncObserver();
    Code:
       0: aload_0
       1: invokespecial #1                  // Method java/lang/Object."<init>":()V
       4: aload_0
       5: aconst_null
       6: putfield      #2                  // Field snapshotCount:Ljava/util/concurrent/atomic/AtomicInteger;
       9: aload_0
      10: aconst_null
      11: putfield      #3                  // Field cloneCount:Ljava/util/concurrent/atomic/AtomicInteger;
      14: return

  public java.util.Optional<org.apache.hadoop.hbase.coprocessor.MasterObserver> getMasterObserver();
    Code:
       0: aload_0
       1: invokestatic  #4                  // Method java/util/Optional.of:(Ljava/lang/Object;)Ljava/util/Optional;
       4: areturn

  public void preSnapshot(org.apache.hadoop.hbase.coprocessor.ObserverContext<org.apache.hadoop.hbase.coprocessor.MasterCoprocessorEnvironment>, org.apache.hadoop.hbase.client.SnapshotDescription, org.apache.hadoop.hbase.client.TableDescriptor) throws java.io.IOException;
    Code:
       0: aload_0
       1: getfield      #2                  // Field snapshotCount:Ljava/util/concurrent/atomic/AtomicInteger;
       4: ifnull        15
       7: aload_0
       8: getfield      #2                  // Field snapshotCount:Ljava/util/concurrent/atomic/AtomicInteger;
      11: invokevirtual #5                  // Method java/util/concurrent/atomic/AtomicInteger.incrementAndGet:()I
      14: pop
      15: return

  public void preCloneSnapshot(org.apache.hadoop.hbase.coprocessor.ObserverContext<org.apache.hadoop.hbase.coprocessor.MasterCoprocessorEnvironment>, org.apache.hadoop.hbase.client.SnapshotDescription, org.apache.hadoop.hbase.client.TableDescriptor) throws java.io.IOException;
    Code:
       0: aload_0
       1: getfield      #3                  // Field cloneCount:Ljava/util/concurrent/atomic/AtomicInteger;
       4: ifnull        15
       7: aload_0
       8: getfield      #3                  // Field cloneCount:Ljava/util/concurrent/atomic/AtomicInteger;
      11: invokevirtual #5                  // Method java/util/concurrent/atomic/AtomicInteger.incrementAndGet:()I
      14: pop
      15: return
}
