Compiled from "TestTagCompressionContext.java"
public class org.apache.hadoop.hbase.io.TestTagCompressionContext {
  public static final org.apache.hadoop.hbase.HBaseClassTestRule CLASS_RULE;

  public org.apache.hadoop.hbase.io.TestTagCompressionContext();
    Code:
       0: aload_0
       1: invokespecial #1                  // Method java/lang/Object."<init>":()V
       4: return

  public void testCompressUncompressTags1() throws java.lang.Exception;
    Code:
       0: new           #2                  // class org/apache/hadoop/hbase/io/ByteArrayOutputStream
       3: dup
       4: invokespecial #3                  // Method org/apache/hadoop/hbase/io/ByteArrayOutputStream."<init>":()V
       7: astore_1
       8: new           #4                  // class org/apache/hadoop/hbase/io/TagCompressionContext
      11: dup
      12: ldc           #5                  // class org/apache/hadoop/hbase/io/util/LRUDictionary
      14: bipush        127
      16: invokespecial #7                  // Method org/apache/hadoop/hbase/io/TagCompressionContext."<init>":(Ljava/lang/Class;I)V
      19: astore_2
      20: aload_0
      21: iconst_2
      22: invokespecial #8                  // Method createKVWithTags:(I)Lorg/apache/hadoop/hbase/KeyValue;
      25: astore_3
      26: aload_3
      27: invokevirtual #9                  // Method org/apache/hadoop/hbase/KeyValue.getTagsLength:()I
      30: istore        4
      32: aload_3
      33: invokevirtual #10                 // Method org/apache/hadoop/hbase/KeyValue.getTagsArray:()[B
      36: invokestatic  #11                 // Method java/nio/ByteBuffer.wrap:([B)Ljava/nio/ByteBuffer;
      39: astore        5
      41: aload_2
      42: aload_1
      43: aload         5
      45: aload_3
      46: invokevirtual #12                 // Method org/apache/hadoop/hbase/KeyValue.getTagsOffset:()I
      49: iload         4
      51: invokevirtual #13                 // Method org/apache/hadoop/hbase/io/TagCompressionContext.compressTags:(Ljava/io/OutputStream;Ljava/nio/ByteBuffer;II)V
      54: aload_0
      55: iconst_3
      56: invokespecial #8                  // Method createKVWithTags:(I)Lorg/apache/hadoop/hbase/KeyValue;
      59: astore        6
      61: aload         6
      63: invokevirtual #9                  // Method org/apache/hadoop/hbase/KeyValue.getTagsLength:()I
      66: istore        7
      68: aload         6
      70: invokevirtual #10                 // Method org/apache/hadoop/hbase/KeyValue.getTagsArray:()[B
      73: invokestatic  #11                 // Method java/nio/ByteBuffer.wrap:([B)Ljava/nio/ByteBuffer;
      76: astore        5
      78: aload_2
      79: aload_1
      80: aload         5
      82: aload         6
      84: invokevirtual #12                 // Method org/apache/hadoop/hbase/KeyValue.getTagsOffset:()I
      87: iload         7
      89: invokevirtual #13                 // Method org/apache/hadoop/hbase/io/TagCompressionContext.compressTags:(Ljava/io/OutputStream;Ljava/nio/ByteBuffer;II)V
      92: aload_2
      93: invokevirtual #14                 // Method org/apache/hadoop/hbase/io/TagCompressionContext.clear:()V
      96: iload         4
      98: newarray       byte
     100: astore        8
     102: aload_1
     103: invokevirtual #15                 // Method org/apache/hadoop/hbase/io/ByteArrayOutputStream.toByteArray:()[B
     106: invokestatic  #11                 // Method java/nio/ByteBuffer.wrap:([B)Ljava/nio/ByteBuffer;
     109: astore        9
     111: aload_2
     112: new           #16                 // class org/apache/hadoop/hbase/nio/SingleByteBuff
     115: dup
     116: aload         9
     118: invokespecial #17                 // Method org/apache/hadoop/hbase/nio/SingleByteBuff."<init>":(Ljava/nio/ByteBuffer;)V
     121: aload         8
     123: iconst_0
     124: iload         4
     126: invokevirtual #18                 // Method org/apache/hadoop/hbase/io/TagCompressionContext.uncompressTags:(Lorg/apache/hadoop/hbase/nio/ByteBuff;[BII)I
     129: pop
     130: aload_3
     131: invokevirtual #10                 // Method org/apache/hadoop/hbase/KeyValue.getTagsArray:()[B
     134: aload_3
     135: invokevirtual #12                 // Method org/apache/hadoop/hbase/KeyValue.getTagsOffset:()I
     138: iload         4
     140: aload         8
     142: iconst_0
     143: iload         4
     145: invokestatic  #19                 // Method org/apache/hadoop/hbase/util/Bytes.equals:([BII[BII)Z
     148: invokestatic  #20                 // Method org/junit/Assert.assertTrue:(Z)V
     151: iload         7
     153: newarray       byte
     155: astore        8
     157: aload_2
     158: new           #16                 // class org/apache/hadoop/hbase/nio/SingleByteBuff
     161: dup
     162: aload         9
     164: invokespecial #17                 // Method org/apache/hadoop/hbase/nio/SingleByteBuff."<init>":(Ljava/nio/ByteBuffer;)V
     167: aload         8
     169: iconst_0
     170: iload         7
     172: invokevirtual #18                 // Method org/apache/hadoop/hbase/io/TagCompressionContext.uncompressTags:(Lorg/apache/hadoop/hbase/nio/ByteBuff;[BII)I
     175: pop
     176: aload         6
     178: invokevirtual #10                 // Method org/apache/hadoop/hbase/KeyValue.getTagsArray:()[B
     181: aload         6
     183: invokevirtual #12                 // Method org/apache/hadoop/hbase/KeyValue.getTagsOffset:()I
     186: iload         7
     188: aload         8
     190: iconst_0
     191: iload         7
     193: invokestatic  #19                 // Method org/apache/hadoop/hbase/util/Bytes.equals:([BII[BII)Z
     196: invokestatic  #20                 // Method org/junit/Assert.assertTrue:(Z)V
     199: return

  public void testCompressUncompressTagsWithOffheapKeyValue1() throws java.lang.Exception;
    Code:
       0: new           #2                  // class org/apache/hadoop/hbase/io/ByteArrayOutputStream
       3: dup
       4: invokespecial #3                  // Method org/apache/hadoop/hbase/io/ByteArrayOutputStream."<init>":()V
       7: astore_1
       8: new           #21                 // class org/apache/hadoop/hbase/io/ByteBufferWriterDataOutputStream
      11: dup
      12: aload_1
      13: invokespecial #22                 // Method org/apache/hadoop/hbase/io/ByteBufferWriterDataOutputStream."<init>":(Ljava/io/OutputStream;)V
      16: astore_2
      17: new           #4                  // class org/apache/hadoop/hbase/io/TagCompressionContext
      20: dup
      21: ldc           #5                  // class org/apache/hadoop/hbase/io/util/LRUDictionary
      23: bipush        127
      25: invokespecial #7                  // Method org/apache/hadoop/hbase/io/TagCompressionContext."<init>":(Ljava/lang/Class;I)V
      28: astore_3
      29: aload_0
      30: iconst_2
      31: invokespecial #23                 // Method createOffheapKVWithTags:(I)Lorg/apache/hadoop/hbase/Cell;
      34: checkcast     #24                 // class org/apache/hadoop/hbase/ByteBufferExtendedCell
      37: astore        4
      39: aload         4
      41: invokevirtual #25                 // Method org/apache/hadoop/hbase/ByteBufferExtendedCell.getTagsLength:()I
      44: istore        5
      46: aload_3
      47: aload_2
      48: aload         4
      50: invokevirtual #26                 // Method org/apache/hadoop/hbase/ByteBufferExtendedCell.getTagsByteBuffer:()Ljava/nio/ByteBuffer;
      53: aload         4
      55: invokevirtual #27                 // Method org/apache/hadoop/hbase/ByteBufferExtendedCell.getTagsPosition:()I
      58: iload         5
      60: invokevirtual #13                 // Method org/apache/hadoop/hbase/io/TagCompressionContext.compressTags:(Ljava/io/OutputStream;Ljava/nio/ByteBuffer;II)V
      63: aload_0
      64: iconst_3
      65: invokespecial #23                 // Method createOffheapKVWithTags:(I)Lorg/apache/hadoop/hbase/Cell;
      68: checkcast     #24                 // class org/apache/hadoop/hbase/ByteBufferExtendedCell
      71: astore        6
      73: aload         6
      75: invokevirtual #25                 // Method org/apache/hadoop/hbase/ByteBufferExtendedCell.getTagsLength:()I
      78: istore        7
      80: aload_3
      81: aload_2
      82: aload         6
      84: invokevirtual #26                 // Method org/apache/hadoop/hbase/ByteBufferExtendedCell.getTagsByteBuffer:()Ljava/nio/ByteBuffer;
      87: aload         6
      89: invokevirtual #27                 // Method org/apache/hadoop/hbase/ByteBufferExtendedCell.getTagsPosition:()I
      92: iload         7
      94: invokevirtual #13                 // Method org/apache/hadoop/hbase/io/TagCompressionContext.compressTags:(Ljava/io/OutputStream;Ljava/nio/ByteBuffer;II)V
      97: aload_3
      98: invokevirtual #14                 // Method org/apache/hadoop/hbase/io/TagCompressionContext.clear:()V
     101: iload         5
     103: newarray       byte
     105: astore        8
     107: aload_1
     108: invokevirtual #28                 // Method org/apache/hadoop/hbase/io/ByteArrayOutputStream.getBuffer:()[B
     111: invokestatic  #11                 // Method java/nio/ByteBuffer.wrap:([B)Ljava/nio/ByteBuffer;
     114: astore        9
     116: aload_3
     117: new           #16                 // class org/apache/hadoop/hbase/nio/SingleByteBuff
     120: dup
     121: aload         9
     123: invokespecial #17                 // Method org/apache/hadoop/hbase/nio/SingleByteBuff."<init>":(Ljava/nio/ByteBuffer;)V
     126: aload         8
     128: iconst_0
     129: iload         5
     131: invokevirtual #18                 // Method org/apache/hadoop/hbase/io/TagCompressionContext.uncompressTags:(Lorg/apache/hadoop/hbase/nio/ByteBuff;[BII)I
     134: pop
     135: aload         4
     137: invokevirtual #29                 // Method org/apache/hadoop/hbase/ByteBufferExtendedCell.getTagsArray:()[B
     140: aload         4
     142: invokevirtual #30                 // Method org/apache/hadoop/hbase/ByteBufferExtendedCell.getTagsOffset:()I
     145: iload         5
     147: aload         8
     149: iconst_0
     150: iload         5
     152: invokestatic  #19                 // Method org/apache/hadoop/hbase/util/Bytes.equals:([BII[BII)Z
     155: invokestatic  #20                 // Method org/junit/Assert.assertTrue:(Z)V
     158: iload         7
     160: newarray       byte
     162: astore        8
     164: aload_3
     165: new           #16                 // class org/apache/hadoop/hbase/nio/SingleByteBuff
     168: dup
     169: aload         9
     171: invokespecial #17                 // Method org/apache/hadoop/hbase/nio/SingleByteBuff."<init>":(Ljava/nio/ByteBuffer;)V
     174: aload         8
     176: iconst_0
     177: iload         7
     179: invokevirtual #18                 // Method org/apache/hadoop/hbase/io/TagCompressionContext.uncompressTags:(Lorg/apache/hadoop/hbase/nio/ByteBuff;[BII)I
     182: pop
     183: aload         6
     185: invokevirtual #29                 // Method org/apache/hadoop/hbase/ByteBufferExtendedCell.getTagsArray:()[B
     188: aload         6
     190: invokevirtual #30                 // Method org/apache/hadoop/hbase/ByteBufferExtendedCell.getTagsOffset:()I
     193: iload         7
     195: aload         8
     197: iconst_0
     198: iload         7
     200: invokestatic  #19                 // Method org/apache/hadoop/hbase/util/Bytes.equals:([BII[BII)Z
     203: invokestatic  #20                 // Method org/junit/Assert.assertTrue:(Z)V
     206: return

  public void testCompressUncompressTags2() throws java.lang.Exception;
    Code:
       0: new           #2                  // class org/apache/hadoop/hbase/io/ByteArrayOutputStream
       3: dup
       4: invokespecial #3                  // Method org/apache/hadoop/hbase/io/ByteArrayOutputStream."<init>":()V
       7: astore_1
       8: new           #4                  // class org/apache/hadoop/hbase/io/TagCompressionContext
      11: dup
      12: ldc           #5                  // class org/apache/hadoop/hbase/io/util/LRUDictionary
      14: bipush        127
      16: invokespecial #7                  // Method org/apache/hadoop/hbase/io/TagCompressionContext."<init>":(Ljava/lang/Class;I)V
      19: astore_2
      20: aload_0
      21: iconst_1
      22: invokespecial #8                  // Method createKVWithTags:(I)Lorg/apache/hadoop/hbase/KeyValue;
      25: astore_3
      26: aload_3
      27: invokevirtual #9                  // Method org/apache/hadoop/hbase/KeyValue.getTagsLength:()I
      30: istore        4
      32: aload_2
      33: aload_1
      34: aload_3
      35: invokevirtual #10                 // Method org/apache/hadoop/hbase/KeyValue.getTagsArray:()[B
      38: aload_3
      39: invokevirtual #12                 // Method org/apache/hadoop/hbase/KeyValue.getTagsOffset:()I
      42: iload         4
      44: invokevirtual #31                 // Method org/apache/hadoop/hbase/io/TagCompressionContext.compressTags:(Ljava/io/OutputStream;[BII)V
      47: aload_0
      48: iconst_3
      49: invokespecial #8                  // Method createKVWithTags:(I)Lorg/apache/hadoop/hbase/KeyValue;
      52: astore        5
      54: aload         5
      56: invokevirtual #9                  // Method org/apache/hadoop/hbase/KeyValue.getTagsLength:()I
      59: istore        6
      61: aload_2
      62: aload_1
      63: aload         5
      65: invokevirtual #10                 // Method org/apache/hadoop/hbase/KeyValue.getTagsArray:()[B
      68: aload         5
      70: invokevirtual #12                 // Method org/apache/hadoop/hbase/KeyValue.getTagsOffset:()I
      73: iload         6
      75: invokevirtual #31                 // Method org/apache/hadoop/hbase/io/TagCompressionContext.compressTags:(Ljava/io/OutputStream;[BII)V
      78: aload_2
      79: invokevirtual #14                 // Method org/apache/hadoop/hbase/io/TagCompressionContext.clear:()V
      82: new           #32                 // class java/io/ByteArrayInputStream
      85: dup
      86: aload_1
      87: invokevirtual #28                 // Method org/apache/hadoop/hbase/io/ByteArrayOutputStream.getBuffer:()[B
      90: invokespecial #33                 // Method java/io/ByteArrayInputStream."<init>":([B)V
      93: astore        7
      95: iload         4
      97: newarray       byte
      99: astore        8
     101: aload_2
     102: aload         7
     104: aload         8
     106: iconst_0
     107: iload         4
     109: invokevirtual #34                 // Method org/apache/hadoop/hbase/io/TagCompressionContext.uncompressTags:(Ljava/io/InputStream;[BII)V
     112: aload_3
     113: invokevirtual #10                 // Method org/apache/hadoop/hbase/KeyValue.getTagsArray:()[B
     116: aload_3
     117: invokevirtual #12                 // Method org/apache/hadoop/hbase/KeyValue.getTagsOffset:()I
     120: iload         4
     122: aload         8
     124: iconst_0
     125: iload         4
     127: invokestatic  #19                 // Method org/apache/hadoop/hbase/util/Bytes.equals:([BII[BII)Z
     130: invokestatic  #20                 // Method org/junit/Assert.assertTrue:(Z)V
     133: iload         6
     135: newarray       byte
     137: astore        8
     139: aload_2
     140: aload         7
     142: aload         8
     144: iconst_0
     145: iload         6
     147: invokevirtual #34                 // Method org/apache/hadoop/hbase/io/TagCompressionContext.uncompressTags:(Ljava/io/InputStream;[BII)V
     150: aload         5
     152: invokevirtual #10                 // Method org/apache/hadoop/hbase/KeyValue.getTagsArray:()[B
     155: aload         5
     157: invokevirtual #12                 // Method org/apache/hadoop/hbase/KeyValue.getTagsOffset:()I
     160: iload         6
     162: aload         8
     164: iconst_0
     165: iload         6
     167: invokestatic  #19                 // Method org/apache/hadoop/hbase/util/Bytes.equals:([BII[BII)Z
     170: invokestatic  #20                 // Method org/junit/Assert.assertTrue:(Z)V
     173: return

  public void testCompressUncompressTagsWithOffheapKeyValue2() throws java.lang.Exception;
    Code:
       0: new           #2                  // class org/apache/hadoop/hbase/io/ByteArrayOutputStream
       3: dup
       4: invokespecial #3                  // Method org/apache/hadoop/hbase/io/ByteArrayOutputStream."<init>":()V
       7: astore_1
       8: new           #21                 // class org/apache/hadoop/hbase/io/ByteBufferWriterDataOutputStream
      11: dup
      12: aload_1
      13: invokespecial #22                 // Method org/apache/hadoop/hbase/io/ByteBufferWriterDataOutputStream."<init>":(Ljava/io/OutputStream;)V
      16: astore_2
      17: new           #4                  // class org/apache/hadoop/hbase/io/TagCompressionContext
      20: dup
      21: ldc           #5                  // class org/apache/hadoop/hbase/io/util/LRUDictionary
      23: bipush        127
      25: invokespecial #7                  // Method org/apache/hadoop/hbase/io/TagCompressionContext."<init>":(Ljava/lang/Class;I)V
      28: astore_3
      29: aload_0
      30: iconst_1
      31: invokespecial #23                 // Method createOffheapKVWithTags:(I)Lorg/apache/hadoop/hbase/Cell;
      34: checkcast     #24                 // class org/apache/hadoop/hbase/ByteBufferExtendedCell
      37: astore        4
      39: aload         4
      41: invokevirtual #25                 // Method org/apache/hadoop/hbase/ByteBufferExtendedCell.getTagsLength:()I
      44: istore        5
      46: aload_3
      47: aload_2
      48: aload         4
      50: invokevirtual #26                 // Method org/apache/hadoop/hbase/ByteBufferExtendedCell.getTagsByteBuffer:()Ljava/nio/ByteBuffer;
      53: aload         4
      55: invokevirtual #27                 // Method org/apache/hadoop/hbase/ByteBufferExtendedCell.getTagsPosition:()I
      58: iload         5
      60: invokevirtual #13                 // Method org/apache/hadoop/hbase/io/TagCompressionContext.compressTags:(Ljava/io/OutputStream;Ljava/nio/ByteBuffer;II)V
      63: aload_0
      64: iconst_3
      65: invokespecial #23                 // Method createOffheapKVWithTags:(I)Lorg/apache/hadoop/hbase/Cell;
      68: checkcast     #24                 // class org/apache/hadoop/hbase/ByteBufferExtendedCell
      71: astore        6
      73: aload         6
      75: invokevirtual #25                 // Method org/apache/hadoop/hbase/ByteBufferExtendedCell.getTagsLength:()I
      78: istore        7
      80: aload_3
      81: aload_2
      82: aload         6
      84: invokevirtual #26                 // Method org/apache/hadoop/hbase/ByteBufferExtendedCell.getTagsByteBuffer:()Ljava/nio/ByteBuffer;
      87: aload         6
      89: invokevirtual #27                 // Method org/apache/hadoop/hbase/ByteBufferExtendedCell.getTagsPosition:()I
      92: iload         7
      94: invokevirtual #13                 // Method org/apache/hadoop/hbase/io/TagCompressionContext.compressTags:(Ljava/io/OutputStream;Ljava/nio/ByteBuffer;II)V
      97: aload_3
      98: invokevirtual #14                 // Method org/apache/hadoop/hbase/io/TagCompressionContext.clear:()V
     101: new           #32                 // class java/io/ByteArrayInputStream
     104: dup
     105: aload_1
     106: invokevirtual #28                 // Method org/apache/hadoop/hbase/io/ByteArrayOutputStream.getBuffer:()[B
     109: invokespecial #33                 // Method java/io/ByteArrayInputStream."<init>":([B)V
     112: astore        8
     114: iload         5
     116: newarray       byte
     118: astore        9
     120: aload_3
     121: aload         8
     123: aload         9
     125: iconst_0
     126: iload         5
     128: invokevirtual #34                 // Method org/apache/hadoop/hbase/io/TagCompressionContext.uncompressTags:(Ljava/io/InputStream;[BII)V
     131: aload         4
     133: invokevirtual #29                 // Method org/apache/hadoop/hbase/ByteBufferExtendedCell.getTagsArray:()[B
     136: aload         4
     138: invokevirtual #30                 // Method org/apache/hadoop/hbase/ByteBufferExtendedCell.getTagsOffset:()I
     141: iload         5
     143: aload         9
     145: iconst_0
     146: iload         5
     148: invokestatic  #19                 // Method org/apache/hadoop/hbase/util/Bytes.equals:([BII[BII)Z
     151: invokestatic  #20                 // Method org/junit/Assert.assertTrue:(Z)V
     154: iload         7
     156: newarray       byte
     158: astore        9
     160: aload_3
     161: aload         8
     163: aload         9
     165: iconst_0
     166: iload         7
     168: invokevirtual #34                 // Method org/apache/hadoop/hbase/io/TagCompressionContext.uncompressTags:(Ljava/io/InputStream;[BII)V
     171: aload         6
     173: invokevirtual #29                 // Method org/apache/hadoop/hbase/ByteBufferExtendedCell.getTagsArray:()[B
     176: aload         6
     178: invokevirtual #30                 // Method org/apache/hadoop/hbase/ByteBufferExtendedCell.getTagsOffset:()I
     181: iload         7
     183: aload         9
     185: iconst_0
     186: iload         7
     188: invokestatic  #19                 // Method org/apache/hadoop/hbase/util/Bytes.equals:([BII[BII)Z
     191: invokestatic  #20                 // Method org/junit/Assert.assertTrue:(Z)V
     194: return

  static {};
    Code:
       0: ldc           #59                 // class org/apache/hadoop/hbase/io/TestTagCompressionContext
       2: invokestatic  #60                 // Method org/apache/hadoop/hbase/HBaseClassTestRule.forClass:(Ljava/lang/Class;)Lorg/apache/hadoop/hbase/HBaseClassTestRule;
       5: putstatic     #61                 // Field CLASS_RULE:Lorg/apache/hadoop/hbase/HBaseClassTestRule;
       8: ldc           #62                 // String r1
      10: invokestatic  #63                 // Method org/apache/hadoop/hbase/util/Bytes.toBytes:(Ljava/lang/String;)[B
      13: putstatic     #47                 // Field ROW:[B
      16: ldc           #64                 // String f
      18: invokestatic  #63                 // Method org/apache/hadoop/hbase/util/Bytes.toBytes:(Ljava/lang/String;)[B
      21: putstatic     #48                 // Field CF:[B
      24: ldc           #65                 // String q
      26: invokestatic  #63                 // Method org/apache/hadoop/hbase/util/Bytes.toBytes:(Ljava/lang/String;)[B
      29: putstatic     #49                 // Field Q:[B
      32: ldc           #66                 // String v
      34: invokestatic  #63                 // Method org/apache/hadoop/hbase/util/Bytes.toBytes:(Ljava/lang/String;)[B
      37: putstatic     #52                 // Field V:[B
      40: return
}
