Compiled from "TestWALProcedureStore.java"
class org.apache.hadoop.hbase.procedure2.store.wal.TestWALProcedureStore$1 implements java.util.Comparator<org.apache.hadoop.fs.FileStatus> {
  final org.apache.hadoop.hbase.procedure2.store.wal.TestWALProcedureStore this$0;

  org.apache.hadoop.hbase.procedure2.store.wal.TestWALProcedureStore$1(org.apache.hadoop.hbase.procedure2.store.wal.TestWALProcedureStore);
    Code:
       0: aload_0
       1: aload_1
       2: putfield      #1                  // Field this$0:Lorg/apache/hadoop/hbase/procedure2/store/wal/TestWALProcedureStore;
       5: aload_0
       6: invokespecial #2                  // Method java/lang/Object."<init>":()V
       9: return

  public int compare(org.apache.hadoop.fs.FileStatus, org.apache.hadoop.fs.FileStatus);
    Code:
       0: aload_1
       1: invokevirtual #3                  // Method org/apache/hadoop/fs/FileStatus.getPath:()Lorg/apache/hadoop/fs/Path;
       4: invokevirtual #4                  // Method org/apache/hadoop/fs/Path.getName:()Ljava/lang/String;
       7: aload_2
       8: invokevirtual #3                  // Method org/apache/hadoop/fs/FileStatus.getPath:()Lorg/apache/hadoop/fs/Path;
      11: invokevirtual #4                  // Method org/apache/hadoop/fs/Path.getName:()Ljava/lang/String;
      14: invokevirtual #5                  // Method java/lang/String.compareTo:(Ljava/lang/String;)I
      17: ireturn

  public int compare(java.lang.Object, java.lang.Object);
    Code:
       0: aload_0
       1: aload_1
       2: checkcast     #6                  // class org/apache/hadoop/fs/FileStatus
       5: aload_2
       6: checkcast     #6                  // class org/apache/hadoop/fs/FileStatus
       9: invokevirtual #7                  // Method compare:(Lorg/apache/hadoop/fs/FileStatus;Lorg/apache/hadoop/fs/FileStatus;)I
      12: ireturn
}
