Compiled from "TestStochasticLoadBalancerRegionReplicaWithRacks.java"
class org.apache.hadoop.hbase.master.balancer.TestStochasticLoadBalancerRegionReplicaWithRacks$ForTestRackManager extends org.apache.hadoop.hbase.master.RackManager {
  int numRacks;

  public org.apache.hadoop.hbase.master.balancer.TestStochasticLoadBalancerRegionReplicaWithRacks$ForTestRackManager(int);
    Code:
       0: aload_0
       1: invokespecial #1                  // Method org/apache/hadoop/hbase/master/RackManager."<init>":()V
       4: aload_0
       5: iload_1
       6: putfield      #2                  // Field numRacks:I
       9: return

  public java.lang.String getRack(org.apache.hadoop.hbase.ServerName);
    Code:
       0: new           #3                  // class java/lang/StringBuilder
       3: dup
       4: invokespecial #4                  // Method java/lang/StringBuilder."<init>":()V
       7: ldc           #5                  // String rack_
       9: invokevirtual #6                  // Method java/lang/StringBuilder.append:(Ljava/lang/String;)Ljava/lang/StringBuilder;
      12: aload_1
      13: invokevirtual #7                  // Method org/apache/hadoop/hbase/ServerName.hashCode:()I
      16: aload_0
      17: getfield      #2                  // Field numRacks:I
      20: irem
      21: invokevirtual #8                  // Method java/lang/StringBuilder.append:(I)Ljava/lang/StringBuilder;
      24: invokevirtual #9                  // Method java/lang/StringBuilder.toString:()Ljava/lang/String;
      27: areturn
}
