Compiled from "TestProcedureBypass.java"
public final class org.apache.hadoop.hbase.procedure2.TestProcedureBypass$StuckStateMachineState extends java.lang.Enum<org.apache.hadoop.hbase.procedure2.TestProcedureBypass$StuckStateMachineState> {
  public static final org.apache.hadoop.hbase.procedure2.TestProcedureBypass$StuckStateMachineState START;

  public static final org.apache.hadoop.hbase.procedure2.TestProcedureBypass$StuckStateMachineState THEN;

  public static final org.apache.hadoop.hbase.procedure2.TestProcedureBypass$StuckStateMachineState END;

  public static org.apache.hadoop.hbase.procedure2.TestProcedureBypass$StuckStateMachineState[] values();
    Code:
       0: getstatic     #1                  // Field $VALUES:[Lorg/apache/hadoop/hbase/procedure2/TestProcedureBypass$StuckStateMachineState;
       3: invokevirtual #2                  // Method "[Lorg/apache/hadoop/hbase/procedure2/TestProcedureBypass$StuckStateMachineState;".clone:()Ljava/lang/Object;
       6: checkcast     #3                  // class "[Lorg/apache/hadoop/hbase/procedure2/TestProcedureBypass$StuckStateMachineState;"
       9: areturn

  public static org.apache.hadoop.hbase.procedure2.TestProcedureBypass$StuckStateMachineState valueOf(java.lang.String);
    Code:
       0: ldc           #4                  // class org/apache/hadoop/hbase/procedure2/TestProcedureBypass$StuckStateMachineState
       2: aload_0
       3: invokestatic  #5                  // Method java/lang/Enum.valueOf:(Ljava/lang/Class;Ljava/lang/String;)Ljava/lang/Enum;
       6: checkcast     #4                  // class org/apache/hadoop/hbase/procedure2/TestProcedureBypass$StuckStateMachineState
       9: areturn

  static {};
    Code:
       0: new           #4                  // class org/apache/hadoop/hbase/procedure2/TestProcedureBypass$StuckStateMachineState
       3: dup
       4: ldc           #7                  // String START
       6: iconst_0
       7: invokespecial #8                  // Method "<init>":(Ljava/lang/String;I)V
      10: putstatic     #9                  // Field START:Lorg/apache/hadoop/hbase/procedure2/TestProcedureBypass$StuckStateMachineState;
      13: new           #4                  // class org/apache/hadoop/hbase/procedure2/TestProcedureBypass$StuckStateMachineState
      16: dup
      17: ldc           #10                 // String THEN
      19: iconst_1
      20: invokespecial #8                  // Method "<init>":(Ljava/lang/String;I)V
      23: putstatic     #11                 // Field THEN:Lorg/apache/hadoop/hbase/procedure2/TestProcedureBypass$StuckStateMachineState;
      26: new           #4                  // class org/apache/hadoop/hbase/procedure2/TestProcedureBypass$StuckStateMachineState
      29: dup
      30: ldc           #12                 // String END
      32: iconst_2
      33: invokespecial #8                  // Method "<init>":(Ljava/lang/String;I)V
      36: putstatic     #13                 // Field END:Lorg/apache/hadoop/hbase/procedure2/TestProcedureBypass$StuckStateMachineState;
      39: iconst_3
      40: anewarray     #4                  // class org/apache/hadoop/hbase/procedure2/TestProcedureBypass$StuckStateMachineState
      43: dup
      44: iconst_0
      45: getstatic     #9                  // Field START:Lorg/apache/hadoop/hbase/procedure2/TestProcedureBypass$StuckStateMachineState;
      48: aastore
      49: dup
      50: iconst_1
      51: getstatic     #11                 // Field THEN:Lorg/apache/hadoop/hbase/procedure2/TestProcedureBypass$StuckStateMachineState;
      54: aastore
      55: dup
      56: iconst_2
      57: getstatic     #13                 // Field END:Lorg/apache/hadoop/hbase/procedure2/TestProcedureBypass$StuckStateMachineState;
      60: aastore
      61: putstatic     #1                  // Field $VALUES:[Lorg/apache/hadoop/hbase/procedure2/TestProcedureBypass$StuckStateMachineState;
      64: return
}
