Compiled from "TestRegionObserverPreFlushAndPreCompact.java"
public class org.apache.hadoop.hbase.coprocessor.TestRegionObserverPreFlushAndPreCompact$TestRegionObserver implements org.apache.hadoop.hbase.coprocessor.RegionObserver,org.apache.hadoop.hbase.coprocessor.RegionCoprocessor {
  public org.apache.hadoop.hbase.coprocessor.TestRegionObserverPreFlushAndPreCompact$TestRegionObserver();
    Code:
       0: aload_0
       1: invokespecial #1                  // Method java/lang/Object."<init>":()V
       4: return

  public org.apache.hadoop.hbase.regionserver.InternalScanner preFlush(org.apache.hadoop.hbase.coprocessor.ObserverContext<org.apache.hadoop.hbase.coprocessor.RegionCoprocessorEnvironment>, org.apache.hadoop.hbase.regionserver.Store, org.apache.hadoop.hbase.regionserver.InternalScanner, org.apache.hadoop.hbase.regionserver.FlushLifeCycleTracker) throws java.io.IOException;
    Code:
       0: aconst_null
       1: areturn

  public org.apache.hadoop.hbase.regionserver.InternalScanner preCompact(org.apache.hadoop.hbase.coprocessor.ObserverContext<org.apache.hadoop.hbase.coprocessor.RegionCoprocessorEnvironment>, org.apache.hadoop.hbase.regionserver.Store, org.apache.hadoop.hbase.regionserver.InternalScanner, org.apache.hadoop.hbase.regionserver.ScanType, org.apache.hadoop.hbase.regionserver.compactions.CompactionLifeCycleTracker, org.apache.hadoop.hbase.regionserver.compactions.CompactionRequest) throws java.io.IOException;
    Code:
       0: aconst_null
       1: areturn

  public java.util.Optional<org.apache.hadoop.hbase.coprocessor.RegionObserver> getRegionObserver();
    Code:
       0: aload_0
       1: invokestatic  #2                  // Method java/util/Optional.of:(Ljava/lang/Object;)Ljava/util/Optional;
       4: areturn
}
