Compiled from "TestScanWithBloomError.java"
class org.apache.hadoop.hbase.regionserver.TestScanWithBloomError$1 implements java.util.Comparator<org.apache.hadoop.hbase.regionserver.StoreFileScanner> {
  final org.apache.hadoop.hbase.regionserver.TestScanWithBloomError this$0;

  org.apache.hadoop.hbase.regionserver.TestScanWithBloomError$1(org.apache.hadoop.hbase.regionserver.TestScanWithBloomError);
    Code:
       0: aload_0
       1: aload_1
       2: putfield      #1                  // Field this$0:Lorg/apache/hadoop/hbase/regionserver/TestScanWithBloomError;
       5: aload_0
       6: invokespecial #2                  // Method java/lang/Object."<init>":()V
       9: return

  public int compare(org.apache.hadoop.hbase.regionserver.StoreFileScanner, org.apache.hadoop.hbase.regionserver.StoreFileScanner);
    Code:
       0: aload_1
       1: invokevirtual #3                  // Method org/apache/hadoop/hbase/regionserver/StoreFileScanner.getReader:()Lorg/apache/hadoop/hbase/regionserver/StoreFileReader;
       4: invokevirtual #4                  // Method org/apache/hadoop/hbase/regionserver/StoreFileReader.getHFileReader:()Lorg/apache/hadoop/hbase/io/hfile/HFile$Reader;
       7: invokeinterface #5,  1            // InterfaceMethod org/apache/hadoop/hbase/io/hfile/HFile$Reader.getPath:()Lorg/apache/hadoop/fs/Path;
      12: astore_3
      13: aload_2
      14: invokevirtual #3                  // Method org/apache/hadoop/hbase/regionserver/StoreFileScanner.getReader:()Lorg/apache/hadoop/hbase/regionserver/StoreFileReader;
      17: invokevirtual #4                  // Method org/apache/hadoop/hbase/regionserver/StoreFileReader.getHFileReader:()Lorg/apache/hadoop/hbase/io/hfile/HFile$Reader;
      20: invokeinterface #5,  1            // InterfaceMethod org/apache/hadoop/hbase/io/hfile/HFile$Reader.getPath:()Lorg/apache/hadoop/fs/Path;
      25: astore        4
      27: aload_0
      28: getfield      #1                  // Field this$0:Lorg/apache/hadoop/hbase/regionserver/TestScanWithBloomError;
      31: invokestatic  #6                  // Method org/apache/hadoop/hbase/regionserver/TestScanWithBloomError.access$000:(Lorg/apache/hadoop/hbase/regionserver/TestScanWithBloomError;)Lorg/apache/hadoop/fs/FileSystem;
      34: aload_3
      35: invokevirtual #7                  // Method org/apache/hadoop/fs/FileSystem.getFileStatus:(Lorg/apache/hadoop/fs/Path;)Lorg/apache/hadoop/fs/FileStatus;
      38: invokevirtual #8                  // Method org/apache/hadoop/fs/FileStatus.getModificationTime:()J
      41: lstore        5
      43: aload_0
      44: getfield      #1                  // Field this$0:Lorg/apache/hadoop/hbase/regionserver/TestScanWithBloomError;
      47: invokestatic  #6                  // Method org/apache/hadoop/hbase/regionserver/TestScanWithBloomError.access$000:(Lorg/apache/hadoop/hbase/regionserver/TestScanWithBloomError;)Lorg/apache/hadoop/fs/FileSystem;
      50: aload         4
      52: invokevirtual #7                  // Method org/apache/hadoop/fs/FileSystem.getFileStatus:(Lorg/apache/hadoop/fs/Path;)Lorg/apache/hadoop/fs/FileStatus;
      55: invokevirtual #8                  // Method org/apache/hadoop/fs/FileStatus.getModificationTime:()J
      58: lstore        7
      60: goto          75
      63: astore        9
      65: new           #10                 // class java/lang/RuntimeException
      68: dup
      69: aload         9
      71: invokespecial #11                 // Method java/lang/RuntimeException."<init>":(Ljava/lang/Throwable;)V
      74: athrow
      75: lload         5
      77: lload         7
      79: lcmp
      80: ifge          87
      83: iconst_m1
      84: goto          100
      87: lload         5
      89: lload         7
      91: lcmp
      92: ifne          99
      95: iconst_1
      96: goto          100
      99: iconst_0
     100: ireturn
    Exception table:
       from    to  target type
          27    60    63   Class java/io/IOException

  public int compare(java.lang.Object, java.lang.Object);
    Code:
       0: aload_0
       1: aload_1
       2: checkcast     #12                 // class org/apache/hadoop/hbase/regionserver/StoreFileScanner
       5: aload_2
       6: checkcast     #12                 // class org/apache/hadoop/hbase/regionserver/StoreFileScanner
       9: invokevirtual #13                 // Method compare:(Lorg/apache/hadoop/hbase/regionserver/StoreFileScanner;Lorg/apache/hadoop/hbase/regionserver/StoreFileScanner;)I
      12: ireturn
}
