Compiled from "TestReplicationSink.java"
public class org.apache.hadoop.hbase.replication.regionserver.TestReplicationSink {
  public static final org.apache.hadoop.hbase.HBaseClassTestRule CLASS_RULE;

  protected static final org.apache.hadoop.hbase.HBaseTestingUtility TEST_UTIL;

  protected static org.apache.hadoop.hbase.replication.regionserver.ReplicationSink SINK;

  protected static final org.apache.hadoop.hbase.TableName TABLE_NAME1;

  protected static final org.apache.hadoop.hbase.TableName TABLE_NAME2;

  protected static final byte[] FAM_NAME1;

  protected static final byte[] FAM_NAME2;

  protected static org.apache.hadoop.hbase.client.Table table1;

  protected static org.apache.hadoop.hbase.Stoppable STOPPABLE;

  protected static org.apache.hadoop.hbase.client.Table table2;

  protected static java.lang.String baseNamespaceDir;

  protected static java.lang.String hfileArchiveDir;

  protected static java.lang.String replicationClusterId;

  public org.apache.hadoop.hbase.replication.regionserver.TestReplicationSink();
    Code:
       0: aload_0
       1: invokespecial #2                  // Method java/lang/Object."<init>":()V
       4: return

  public static void setUpBeforeClass() throws java.lang.Exception;
    Code:
       0: getstatic     #3                  // Field TEST_UTIL:Lorg/apache/hadoop/hbase/HBaseTestingUtility;
       3: invokevirtual #4                  // Method org/apache/hadoop/hbase/HBaseTestingUtility.getConfiguration:()Lorg/apache/hadoop/conf/Configuration;
       6: ldc           #5                  // String hbase.replication.source.fs.conf.provider
       8: ldc           #6                  // class org/apache/hadoop/hbase/replication/regionserver/TestSourceFSConfigurationProvider
      10: invokevirtual #7                  // Method java/lang/Class.getCanonicalName:()Ljava/lang/String;
      13: invokevirtual #8                  // Method org/apache/hadoop/conf/Configuration.set:(Ljava/lang/String;Ljava/lang/String;)V
      16: getstatic     #3                  // Field TEST_UTIL:Lorg/apache/hadoop/hbase/HBaseTestingUtility;
      19: iconst_3
      20: invokevirtual #9                  // Method org/apache/hadoop/hbase/HBaseTestingUtility.startMiniCluster:(I)Lorg/apache/hadoop/hbase/MiniHBaseCluster;
      23: pop
      24: new           #10                 // class org/apache/hadoop/hbase/replication/regionserver/ReplicationSink
      27: dup
      28: new           #11                 // class org/apache/hadoop/conf/Configuration
      31: dup
      32: getstatic     #3                  // Field TEST_UTIL:Lorg/apache/hadoop/hbase/HBaseTestingUtility;
      35: invokevirtual #4                  // Method org/apache/hadoop/hbase/HBaseTestingUtility.getConfiguration:()Lorg/apache/hadoop/conf/Configuration;
      38: invokespecial #12                 // Method org/apache/hadoop/conf/Configuration."<init>":(Lorg/apache/hadoop/conf/Configuration;)V
      41: getstatic     #13                 // Field STOPPABLE:Lorg/apache/hadoop/hbase/Stoppable;
      44: invokespecial #14                 // Method org/apache/hadoop/hbase/replication/regionserver/ReplicationSink."<init>":(Lorg/apache/hadoop/conf/Configuration;Lorg/apache/hadoop/hbase/Stoppable;)V
      47: putstatic     #15                 // Field SINK:Lorg/apache/hadoop/hbase/replication/regionserver/ReplicationSink;
      50: getstatic     #3                  // Field TEST_UTIL:Lorg/apache/hadoop/hbase/HBaseTestingUtility;
      53: getstatic     #16                 // Field TABLE_NAME1:Lorg/apache/hadoop/hbase/TableName;
      56: getstatic     #17                 // Field FAM_NAME1:[B
      59: invokevirtual #18                 // Method org/apache/hadoop/hbase/HBaseTestingUtility.createTable:(Lorg/apache/hadoop/hbase/TableName;[B)Lorg/apache/hadoop/hbase/client/Table;
      62: putstatic     #19                 // Field table1:Lorg/apache/hadoop/hbase/client/Table;
      65: getstatic     #3                  // Field TEST_UTIL:Lorg/apache/hadoop/hbase/HBaseTestingUtility;
      68: getstatic     #20                 // Field TABLE_NAME2:Lorg/apache/hadoop/hbase/TableName;
      71: getstatic     #21                 // Field FAM_NAME2:[B
      74: invokevirtual #18                 // Method org/apache/hadoop/hbase/HBaseTestingUtility.createTable:(Lorg/apache/hadoop/hbase/TableName;[B)Lorg/apache/hadoop/hbase/client/Table;
      77: putstatic     #22                 // Field table2:Lorg/apache/hadoop/hbase/client/Table;
      80: getstatic     #3                  // Field TEST_UTIL:Lorg/apache/hadoop/hbase/HBaseTestingUtility;
      83: invokevirtual #4                  // Method org/apache/hadoop/hbase/HBaseTestingUtility.getConfiguration:()Lorg/apache/hadoop/conf/Configuration;
      86: invokestatic  #23                 // Method org/apache/hadoop/hbase/util/FSUtils.getRootDir:(Lorg/apache/hadoop/conf/Configuration;)Lorg/apache/hadoop/fs/Path;
      89: astore_0
      90: new           #24                 // class org/apache/hadoop/fs/Path
      93: dup
      94: aload_0
      95: new           #24                 // class org/apache/hadoop/fs/Path
      98: dup
      99: ldc           #26                 // String data
     101: invokespecial #27                 // Method org/apache/hadoop/fs/Path."<init>":(Ljava/lang/String;)V
     104: invokespecial #28                 // Method org/apache/hadoop/fs/Path."<init>":(Lorg/apache/hadoop/fs/Path;Lorg/apache/hadoop/fs/Path;)V
     107: invokevirtual #29                 // Method org/apache/hadoop/fs/Path.toString:()Ljava/lang/String;
     110: putstatic     #30                 // Field baseNamespaceDir:Ljava/lang/String;
     113: new           #24                 // class org/apache/hadoop/fs/Path
     116: dup
     117: aload_0
     118: new           #24                 // class org/apache/hadoop/fs/Path
     121: dup
     122: ldc           #31                 // String archive
     124: invokespecial #27                 // Method org/apache/hadoop/fs/Path."<init>":(Ljava/lang/String;)V
     127: invokespecial #28                 // Method org/apache/hadoop/fs/Path."<init>":(Lorg/apache/hadoop/fs/Path;Lorg/apache/hadoop/fs/Path;)V
     130: invokevirtual #29                 // Method org/apache/hadoop/fs/Path.toString:()Ljava/lang/String;
     133: putstatic     #32                 // Field hfileArchiveDir:Ljava/lang/String;
     136: ldc           #33                 // String 12345
     138: putstatic     #34                 // Field replicationClusterId:Ljava/lang/String;
     141: return

  public static void tearDownAfterClass() throws java.lang.Exception;
    Code:
       0: getstatic     #13                 // Field STOPPABLE:Lorg/apache/hadoop/hbase/Stoppable;
       3: ldc           #35                 // String Shutting down
       5: invokeinterface #36,  2           // InterfaceMethod org/apache/hadoop/hbase/Stoppable.stop:(Ljava/lang/String;)V
      10: getstatic     #3                  // Field TEST_UTIL:Lorg/apache/hadoop/hbase/HBaseTestingUtility;
      13: invokevirtual #37                 // Method org/apache/hadoop/hbase/HBaseTestingUtility.shutdownMiniCluster:()V
      16: return

  public void setUp() throws java.lang.Exception;
    Code:
       0: getstatic     #3                  // Field TEST_UTIL:Lorg/apache/hadoop/hbase/HBaseTestingUtility;
       3: getstatic     #16                 // Field TABLE_NAME1:Lorg/apache/hadoop/hbase/TableName;
       6: invokevirtual #38                 // Method org/apache/hadoop/hbase/HBaseTestingUtility.deleteTableData:(Lorg/apache/hadoop/hbase/TableName;)Lorg/apache/hadoop/hbase/client/Table;
       9: putstatic     #19                 // Field table1:Lorg/apache/hadoop/hbase/client/Table;
      12: getstatic     #3                  // Field TEST_UTIL:Lorg/apache/hadoop/hbase/HBaseTestingUtility;
      15: getstatic     #20                 // Field TABLE_NAME2:Lorg/apache/hadoop/hbase/TableName;
      18: invokevirtual #38                 // Method org/apache/hadoop/hbase/HBaseTestingUtility.deleteTableData:(Lorg/apache/hadoop/hbase/TableName;)Lorg/apache/hadoop/hbase/client/Table;
      21: putstatic     #22                 // Field table2:Lorg/apache/hadoop/hbase/client/Table;
      24: return

  public void testBatchSink() throws java.lang.Exception;
    Code:
       0: new           #39                 // class java/util/ArrayList
       3: dup
       4: bipush        10
       6: invokespecial #41                 // Method java/util/ArrayList."<init>":(I)V
       9: astore_1
      10: new           #39                 // class java/util/ArrayList
      13: dup
      14: invokespecial #42                 // Method java/util/ArrayList."<init>":()V
      17: astore_2
      18: iconst_0
      19: istore_3
      20: iload_3
      21: bipush        10
      23: if_icmpge     51
      26: aload_1
      27: aload_0
      28: getstatic     #16                 // Field TABLE_NAME1:Lorg/apache/hadoop/hbase/TableName;
      31: iload_3
      32: getstatic     #43                 // Field org/apache/hadoop/hbase/KeyValue$Type.Put:Lorg/apache/hadoop/hbase/KeyValue$Type;
      35: aload_2
      36: invokespecial #44                 // Method createEntry:(Lorg/apache/hadoop/hbase/TableName;ILorg/apache/hadoop/hbase/KeyValue$Type;Ljava/util/List;)Lorg/apache/hadoop/hbase/shaded/protobuf/generated/AdminProtos$WALEntry;
      39: invokeinterface #45,  2           // InterfaceMethod java/util/List.add:(Ljava/lang/Object;)Z
      44: pop
      45: iinc          3, 1
      48: goto          20
      51: getstatic     #15                 // Field SINK:Lorg/apache/hadoop/hbase/replication/regionserver/ReplicationSink;
      54: aload_1
      55: aload_2
      56: invokeinterface #46,  1           // InterfaceMethod java/util/List.iterator:()Ljava/util/Iterator;
      61: invokestatic  #47                 // Method org/apache/hadoop/hbase/CellUtil.createCellScanner:(Ljava/util/Iterator;)Lorg/apache/hadoop/hbase/CellScanner;
      64: getstatic     #34                 // Field replicationClusterId:Ljava/lang/String;
      67: getstatic     #30                 // Field baseNamespaceDir:Ljava/lang/String;
      70: getstatic     #32                 // Field hfileArchiveDir:Ljava/lang/String;
      73: invokevirtual #48                 // Method org/apache/hadoop/hbase/replication/regionserver/ReplicationSink.replicateEntries:(Ljava/util/List;Lorg/apache/hadoop/hbase/CellScanner;Ljava/lang/String;Ljava/lang/String;Ljava/lang/String;)V
      76: new           #49                 // class org/apache/hadoop/hbase/client/Scan
      79: dup
      80: invokespecial #50                 // Method org/apache/hadoop/hbase/client/Scan."<init>":()V
      83: astore_3
      84: getstatic     #19                 // Field table1:Lorg/apache/hadoop/hbase/client/Table;
      87: aload_3
      88: invokeinterface #51,  2           // InterfaceMethod org/apache/hadoop/hbase/client/Table.getScanner:(Lorg/apache/hadoop/hbase/client/Scan;)Lorg/apache/hadoop/hbase/client/ResultScanner;
      93: astore        4
      95: ldc2_w        #52                 // long 10l
      98: aload         4
     100: bipush        10
     102: invokeinterface #54,  2           // InterfaceMethod org/apache/hadoop/hbase/client/ResultScanner.next:(I)[Lorg/apache/hadoop/hbase/client/Result;
     107: arraylength
     108: i2l
     109: invokestatic  #55                 // Method org/junit/Assert.assertEquals:(JJ)V
     112: return

  public void testMixedPutDelete() throws java.lang.Exception;
    Code:
       0: new           #39                 // class java/util/ArrayList
       3: dup
       4: iconst_5
       5: invokespecial #41                 // Method java/util/ArrayList."<init>":(I)V
       8: astore_1
       9: new           #39                 // class java/util/ArrayList
      12: dup
      13: invokespecial #42                 // Method java/util/ArrayList."<init>":()V
      16: astore_2
      17: iconst_0
      18: istore_3
      19: iload_3
      20: iconst_5
      21: if_icmpge     49
      24: aload_1
      25: aload_0
      26: getstatic     #16                 // Field TABLE_NAME1:Lorg/apache/hadoop/hbase/TableName;
      29: iload_3
      30: getstatic     #43                 // Field org/apache/hadoop/hbase/KeyValue$Type.Put:Lorg/apache/hadoop/hbase/KeyValue$Type;
      33: aload_2
      34: invokespecial #44                 // Method createEntry:(Lorg/apache/hadoop/hbase/TableName;ILorg/apache/hadoop/hbase/KeyValue$Type;Ljava/util/List;)Lorg/apache/hadoop/hbase/shaded/protobuf/generated/AdminProtos$WALEntry;
      37: invokeinterface #45,  2           // InterfaceMethod java/util/List.add:(Ljava/lang/Object;)Z
      42: pop
      43: iinc          3, 1
      46: goto          19
      49: getstatic     #15                 // Field SINK:Lorg/apache/hadoop/hbase/replication/regionserver/ReplicationSink;
      52: aload_1
      53: aload_2
      54: invokestatic  #56                 // Method org/apache/hadoop/hbase/CellUtil.createCellScanner:(Ljava/lang/Iterable;)Lorg/apache/hadoop/hbase/CellScanner;
      57: getstatic     #34                 // Field replicationClusterId:Ljava/lang/String;
      60: getstatic     #30                 // Field baseNamespaceDir:Ljava/lang/String;
      63: getstatic     #32                 // Field hfileArchiveDir:Ljava/lang/String;
      66: invokevirtual #48                 // Method org/apache/hadoop/hbase/replication/regionserver/ReplicationSink.replicateEntries:(Ljava/util/List;Lorg/apache/hadoop/hbase/CellScanner;Ljava/lang/String;Ljava/lang/String;Ljava/lang/String;)V
      69: new           #39                 // class java/util/ArrayList
      72: dup
      73: bipush        10
      75: invokespecial #41                 // Method java/util/ArrayList."<init>":(I)V
      78: astore_1
      79: new           #39                 // class java/util/ArrayList
      82: dup
      83: invokespecial #42                 // Method java/util/ArrayList."<init>":()V
      86: astore_2
      87: iconst_0
      88: istore_3
      89: iload_3
      90: bipush        10
      92: if_icmpge     132
      95: aload_1
      96: aload_0
      97: getstatic     #16                 // Field TABLE_NAME1:Lorg/apache/hadoop/hbase/TableName;
     100: iload_3
     101: iload_3
     102: iconst_2
     103: irem
     104: ifeq          113
     107: getstatic     #43                 // Field org/apache/hadoop/hbase/KeyValue$Type.Put:Lorg/apache/hadoop/hbase/KeyValue$Type;
     110: goto          116
     113: getstatic     #57                 // Field org/apache/hadoop/hbase/KeyValue$Type.DeleteColumn:Lorg/apache/hadoop/hbase/KeyValue$Type;
     116: aload_2
     117: invokespecial #44                 // Method createEntry:(Lorg/apache/hadoop/hbase/TableName;ILorg/apache/hadoop/hbase/KeyValue$Type;Ljava/util/List;)Lorg/apache/hadoop/hbase/shaded/protobuf/generated/AdminProtos$WALEntry;
     120: invokeinterface #45,  2           // InterfaceMethod java/util/List.add:(Ljava/lang/Object;)Z
     125: pop
     126: iinc          3, 1
     129: goto          89
     132: getstatic     #15                 // Field SINK:Lorg/apache/hadoop/hbase/replication/regionserver/ReplicationSink;
     135: aload_1
     136: aload_2
     137: invokeinterface #46,  1           // InterfaceMethod java/util/List.iterator:()Ljava/util/Iterator;
     142: invokestatic  #47                 // Method org/apache/hadoop/hbase/CellUtil.createCellScanner:(Ljava/util/Iterator;)Lorg/apache/hadoop/hbase/CellScanner;
     145: getstatic     #34                 // Field replicationClusterId:Ljava/lang/String;
     148: getstatic     #30                 // Field baseNamespaceDir:Ljava/lang/String;
     151: getstatic     #32                 // Field hfileArchiveDir:Ljava/lang/String;
     154: invokevirtual #48                 // Method org/apache/hadoop/hbase/replication/regionserver/ReplicationSink.replicateEntries:(Ljava/util/List;Lorg/apache/hadoop/hbase/CellScanner;Ljava/lang/String;Ljava/lang/String;Ljava/lang/String;)V
     157: new           #49                 // class org/apache/hadoop/hbase/client/Scan
     160: dup
     161: invokespecial #50                 // Method org/apache/hadoop/hbase/client/Scan."<init>":()V
     164: astore_3
     165: getstatic     #19                 // Field table1:Lorg/apache/hadoop/hbase/client/Table;
     168: aload_3
     169: invokeinterface #51,  2           // InterfaceMethod org/apache/hadoop/hbase/client/Table.getScanner:(Lorg/apache/hadoop/hbase/client/Scan;)Lorg/apache/hadoop/hbase/client/ResultScanner;
     174: astore        4
     176: ldc2_w        #58                 // long 5l
     179: aload         4
     181: bipush        10
     183: invokeinterface #54,  2           // InterfaceMethod org/apache/hadoop/hbase/client/ResultScanner.next:(I)[Lorg/apache/hadoop/hbase/client/Result;
     188: arraylength
     189: i2l
     190: invokestatic  #55                 // Method org/junit/Assert.assertEquals:(JJ)V
     193: return

  public void testMixedPutTables() throws java.lang.Exception;
    Code:
       0: new           #39                 // class java/util/ArrayList
       3: dup
       4: iconst_5
       5: invokespecial #41                 // Method java/util/ArrayList."<init>":(I)V
       8: astore_1
       9: new           #39                 // class java/util/ArrayList
      12: dup
      13: invokespecial #42                 // Method java/util/ArrayList."<init>":()V
      16: astore_2
      17: iconst_0
      18: istore_3
      19: iload_3
      20: bipush        10
      22: if_icmpge     62
      25: aload_1
      26: aload_0
      27: iload_3
      28: iconst_2
      29: irem
      30: ifne          39
      33: getstatic     #20                 // Field TABLE_NAME2:Lorg/apache/hadoop/hbase/TableName;
      36: goto          42
      39: getstatic     #16                 // Field TABLE_NAME1:Lorg/apache/hadoop/hbase/TableName;
      42: iload_3
      43: getstatic     #43                 // Field org/apache/hadoop/hbase/KeyValue$Type.Put:Lorg/apache/hadoop/hbase/KeyValue$Type;
      46: aload_2
      47: invokespecial #44                 // Method createEntry:(Lorg/apache/hadoop/hbase/TableName;ILorg/apache/hadoop/hbase/KeyValue$Type;Ljava/util/List;)Lorg/apache/hadoop/hbase/shaded/protobuf/generated/AdminProtos$WALEntry;
      50: invokeinterface #45,  2           // InterfaceMethod java/util/List.add:(Ljava/lang/Object;)Z
      55: pop
      56: iinc          3, 1
      59: goto          19
      62: getstatic     #15                 // Field SINK:Lorg/apache/hadoop/hbase/replication/regionserver/ReplicationSink;
      65: aload_1
      66: aload_2
      67: invokeinterface #46,  1           // InterfaceMethod java/util/List.iterator:()Ljava/util/Iterator;
      72: invokestatic  #47                 // Method org/apache/hadoop/hbase/CellUtil.createCellScanner:(Ljava/util/Iterator;)Lorg/apache/hadoop/hbase/CellScanner;
      75: getstatic     #34                 // Field replicationClusterId:Ljava/lang/String;
      78: getstatic     #30                 // Field baseNamespaceDir:Ljava/lang/String;
      81: getstatic     #32                 // Field hfileArchiveDir:Ljava/lang/String;
      84: invokevirtual #48                 // Method org/apache/hadoop/hbase/replication/regionserver/ReplicationSink.replicateEntries:(Ljava/util/List;Lorg/apache/hadoop/hbase/CellScanner;Ljava/lang/String;Ljava/lang/String;Ljava/lang/String;)V
      87: new           #49                 // class org/apache/hadoop/hbase/client/Scan
      90: dup
      91: invokespecial #50                 // Method org/apache/hadoop/hbase/client/Scan."<init>":()V
      94: astore_3
      95: getstatic     #22                 // Field table2:Lorg/apache/hadoop/hbase/client/Table;
      98: aload_3
      99: invokeinterface #51,  2           // InterfaceMethod org/apache/hadoop/hbase/client/Table.getScanner:(Lorg/apache/hadoop/hbase/client/Scan;)Lorg/apache/hadoop/hbase/client/ResultScanner;
     104: astore        4
     106: aload         4
     108: invokeinterface #60,  1           // InterfaceMethod org/apache/hadoop/hbase/client/ResultScanner.iterator:()Ljava/util/Iterator;
     113: astore        5
     115: aload         5
     117: invokeinterface #61,  1           // InterfaceMethod java/util/Iterator.hasNext:()Z
     122: ifeq          161
     125: aload         5
     127: invokeinterface #62,  1           // InterfaceMethod java/util/Iterator.next:()Ljava/lang/Object;
     132: checkcast     #63                 // class org/apache/hadoop/hbase/client/Result
     135: astore        6
     137: aload         6
     139: invokevirtual #64                 // Method org/apache/hadoop/hbase/client/Result.getRow:()[B
     142: invokestatic  #65                 // Method org/apache/hadoop/hbase/util/Bytes.toInt:([B)I
     145: iconst_2
     146: irem
     147: ifne          154
     150: iconst_1
     151: goto          155
     154: iconst_0
     155: invokestatic  #66                 // Method org/junit/Assert.assertTrue:(Z)V
     158: goto          115
     161: return

  public void testMixedDeletes() throws java.lang.Exception;
    Code:
       0: new           #39                 // class java/util/ArrayList
       3: dup
       4: iconst_3
       5: invokespecial #41                 // Method java/util/ArrayList."<init>":(I)V
       8: astore_1
       9: new           #39                 // class java/util/ArrayList
      12: dup
      13: invokespecial #42                 // Method java/util/ArrayList."<init>":()V
      16: astore_2
      17: iconst_0
      18: istore_3
      19: iload_3
      20: iconst_3
      21: if_icmpge     49
      24: aload_1
      25: aload_0
      26: getstatic     #16                 // Field TABLE_NAME1:Lorg/apache/hadoop/hbase/TableName;
      29: iload_3
      30: getstatic     #43                 // Field org/apache/hadoop/hbase/KeyValue$Type.Put:Lorg/apache/hadoop/hbase/KeyValue$Type;
      33: aload_2
      34: invokespecial #44                 // Method createEntry:(Lorg/apache/hadoop/hbase/TableName;ILorg/apache/hadoop/hbase/KeyValue$Type;Ljava/util/List;)Lorg/apache/hadoop/hbase/shaded/protobuf/generated/AdminProtos$WALEntry;
      37: invokeinterface #45,  2           // InterfaceMethod java/util/List.add:(Ljava/lang/Object;)Z
      42: pop
      43: iinc          3, 1
      46: goto          19
      49: getstatic     #15                 // Field SINK:Lorg/apache/hadoop/hbase/replication/regionserver/ReplicationSink;
      52: aload_1
      53: aload_2
      54: invokeinterface #46,  1           // InterfaceMethod java/util/List.iterator:()Ljava/util/Iterator;
      59: invokestatic  #47                 // Method org/apache/hadoop/hbase/CellUtil.createCellScanner:(Ljava/util/Iterator;)Lorg/apache/hadoop/hbase/CellScanner;
      62: getstatic     #34                 // Field replicationClusterId:Ljava/lang/String;
      65: getstatic     #30                 // Field baseNamespaceDir:Ljava/lang/String;
      68: getstatic     #32                 // Field hfileArchiveDir:Ljava/lang/String;
      71: invokevirtual #48                 // Method org/apache/hadoop/hbase/replication/regionserver/ReplicationSink.replicateEntries:(Ljava/util/List;Lorg/apache/hadoop/hbase/CellScanner;Ljava/lang/String;Ljava/lang/String;Ljava/lang/String;)V
      74: new           #39                 // class java/util/ArrayList
      77: dup
      78: iconst_3
      79: invokespecial #41                 // Method java/util/ArrayList."<init>":(I)V
      82: astore_1
      83: new           #39                 // class java/util/ArrayList
      86: dup
      87: invokespecial #42                 // Method java/util/ArrayList."<init>":()V
      90: astore_2
      91: aload_1
      92: aload_0
      93: getstatic     #16                 // Field TABLE_NAME1:Lorg/apache/hadoop/hbase/TableName;
      96: iconst_0
      97: getstatic     #57                 // Field org/apache/hadoop/hbase/KeyValue$Type.DeleteColumn:Lorg/apache/hadoop/hbase/KeyValue$Type;
     100: aload_2
     101: invokespecial #44                 // Method createEntry:(Lorg/apache/hadoop/hbase/TableName;ILorg/apache/hadoop/hbase/KeyValue$Type;Ljava/util/List;)Lorg/apache/hadoop/hbase/shaded/protobuf/generated/AdminProtos$WALEntry;
     104: invokeinterface #45,  2           // InterfaceMethod java/util/List.add:(Ljava/lang/Object;)Z
     109: pop
     110: aload_1
     111: aload_0
     112: getstatic     #16                 // Field TABLE_NAME1:Lorg/apache/hadoop/hbase/TableName;
     115: iconst_1
     116: getstatic     #67                 // Field org/apache/hadoop/hbase/KeyValue$Type.DeleteFamily:Lorg/apache/hadoop/hbase/KeyValue$Type;
     119: aload_2
     120: invokespecial #44                 // Method createEntry:(Lorg/apache/hadoop/hbase/TableName;ILorg/apache/hadoop/hbase/KeyValue$Type;Ljava/util/List;)Lorg/apache/hadoop/hbase/shaded/protobuf/generated/AdminProtos$WALEntry;
     123: invokeinterface #45,  2           // InterfaceMethod java/util/List.add:(Ljava/lang/Object;)Z
     128: pop
     129: aload_1
     130: aload_0
     131: getstatic     #16                 // Field TABLE_NAME1:Lorg/apache/hadoop/hbase/TableName;
     134: iconst_2
     135: getstatic     #57                 // Field org/apache/hadoop/hbase/KeyValue$Type.DeleteColumn:Lorg/apache/hadoop/hbase/KeyValue$Type;
     138: aload_2
     139: invokespecial #44                 // Method createEntry:(Lorg/apache/hadoop/hbase/TableName;ILorg/apache/hadoop/hbase/KeyValue$Type;Ljava/util/List;)Lorg/apache/hadoop/hbase/shaded/protobuf/generated/AdminProtos$WALEntry;
     142: invokeinterface #45,  2           // InterfaceMethod java/util/List.add:(Ljava/lang/Object;)Z
     147: pop
     148: getstatic     #15                 // Field SINK:Lorg/apache/hadoop/hbase/replication/regionserver/ReplicationSink;
     151: aload_1
     152: aload_2
     153: invokeinterface #46,  1           // InterfaceMethod java/util/List.iterator:()Ljava/util/Iterator;
     158: invokestatic  #47                 // Method org/apache/hadoop/hbase/CellUtil.createCellScanner:(Ljava/util/Iterator;)Lorg/apache/hadoop/hbase/CellScanner;
     161: getstatic     #34                 // Field replicationClusterId:Ljava/lang/String;
     164: getstatic     #30                 // Field baseNamespaceDir:Ljava/lang/String;
     167: getstatic     #32                 // Field hfileArchiveDir:Ljava/lang/String;
     170: invokevirtual #48                 // Method org/apache/hadoop/hbase/replication/regionserver/ReplicationSink.replicateEntries:(Ljava/util/List;Lorg/apache/hadoop/hbase/CellScanner;Ljava/lang/String;Ljava/lang/String;Ljava/lang/String;)V
     173: new           #49                 // class org/apache/hadoop/hbase/client/Scan
     176: dup
     177: invokespecial #50                 // Method org/apache/hadoop/hbase/client/Scan."<init>":()V
     180: astore_3
     181: getstatic     #19                 // Field table1:Lorg/apache/hadoop/hbase/client/Table;
     184: aload_3
     185: invokeinterface #51,  2           // InterfaceMethod org/apache/hadoop/hbase/client/Table.getScanner:(Lorg/apache/hadoop/hbase/client/Scan;)Lorg/apache/hadoop/hbase/client/ResultScanner;
     190: astore        4
     192: lconst_0
     193: aload         4
     195: iconst_3
     196: invokeinterface #54,  2           // InterfaceMethod org/apache/hadoop/hbase/client/ResultScanner.next:(I)[Lorg/apache/hadoop/hbase/client/Result;
     201: arraylength
     202: i2l
     203: invokestatic  #55                 // Method org/junit/Assert.assertEquals:(JJ)V
     206: return

  public void testApplyDeleteBeforePut() throws java.lang.Exception;
    Code:
       0: new           #39                 // class java/util/ArrayList
       3: dup
       4: iconst_5
       5: invokespecial #41                 // Method java/util/ArrayList."<init>":(I)V
       8: astore_1
       9: new           #39                 // class java/util/ArrayList
      12: dup
      13: invokespecial #42                 // Method java/util/ArrayList."<init>":()V
      16: astore_2
      17: iconst_0
      18: istore_3
      19: iload_3
      20: iconst_2
      21: if_icmpge     49
      24: aload_1
      25: aload_0
      26: getstatic     #16                 // Field TABLE_NAME1:Lorg/apache/hadoop/hbase/TableName;
      29: iload_3
      30: getstatic     #43                 // Field org/apache/hadoop/hbase/KeyValue$Type.Put:Lorg/apache/hadoop/hbase/KeyValue$Type;
      33: aload_2
      34: invokespecial #44                 // Method createEntry:(Lorg/apache/hadoop/hbase/TableName;ILorg/apache/hadoop/hbase/KeyValue$Type;Ljava/util/List;)Lorg/apache/hadoop/hbase/shaded/protobuf/generated/AdminProtos$WALEntry;
      37: invokeinterface #45,  2           // InterfaceMethod java/util/List.add:(Ljava/lang/Object;)Z
      42: pop
      43: iinc          3, 1
      46: goto          19
      49: aload_1
      50: aload_0
      51: getstatic     #16                 // Field TABLE_NAME1:Lorg/apache/hadoop/hbase/TableName;
      54: iconst_1
      55: getstatic     #67                 // Field org/apache/hadoop/hbase/KeyValue$Type.DeleteFamily:Lorg/apache/hadoop/hbase/KeyValue$Type;
      58: aload_2
      59: invokespecial #44                 // Method createEntry:(Lorg/apache/hadoop/hbase/TableName;ILorg/apache/hadoop/hbase/KeyValue$Type;Ljava/util/List;)Lorg/apache/hadoop/hbase/shaded/protobuf/generated/AdminProtos$WALEntry;
      62: invokeinterface #45,  2           // InterfaceMethod java/util/List.add:(Ljava/lang/Object;)Z
      67: pop
      68: iconst_3
      69: istore_3
      70: iload_3
      71: iconst_5
      72: if_icmpge     100
      75: aload_1
      76: aload_0
      77: getstatic     #16                 // Field TABLE_NAME1:Lorg/apache/hadoop/hbase/TableName;
      80: iload_3
      81: getstatic     #43                 // Field org/apache/hadoop/hbase/KeyValue$Type.Put:Lorg/apache/hadoop/hbase/KeyValue$Type;
      84: aload_2
      85: invokespecial #44                 // Method createEntry:(Lorg/apache/hadoop/hbase/TableName;ILorg/apache/hadoop/hbase/KeyValue$Type;Ljava/util/List;)Lorg/apache/hadoop/hbase/shaded/protobuf/generated/AdminProtos$WALEntry;
      88: invokeinterface #45,  2           // InterfaceMethod java/util/List.add:(Ljava/lang/Object;)Z
      93: pop
      94: iinc          3, 1
      97: goto          70
     100: getstatic     #15                 // Field SINK:Lorg/apache/hadoop/hbase/replication/regionserver/ReplicationSink;
     103: aload_1
     104: aload_2
     105: invokeinterface #46,  1           // InterfaceMethod java/util/List.iterator:()Ljava/util/Iterator;
     110: invokestatic  #47                 // Method org/apache/hadoop/hbase/CellUtil.createCellScanner:(Ljava/util/Iterator;)Lorg/apache/hadoop/hbase/CellScanner;
     113: getstatic     #34                 // Field replicationClusterId:Ljava/lang/String;
     116: getstatic     #30                 // Field baseNamespaceDir:Ljava/lang/String;
     119: getstatic     #32                 // Field hfileArchiveDir:Ljava/lang/String;
     122: invokevirtual #48                 // Method org/apache/hadoop/hbase/replication/regionserver/ReplicationSink.replicateEntries:(Ljava/util/List;Lorg/apache/hadoop/hbase/CellScanner;Ljava/lang/String;Ljava/lang/String;Ljava/lang/String;)V
     125: new           #68                 // class org/apache/hadoop/hbase/client/Get
     128: dup
     129: iconst_1
     130: invokestatic  #69                 // Method org/apache/hadoop/hbase/util/Bytes.toBytes:(I)[B
     133: invokespecial #70                 // Method org/apache/hadoop/hbase/client/Get."<init>":([B)V
     136: astore_3
     137: getstatic     #19                 // Field table1:Lorg/apache/hadoop/hbase/client/Table;
     140: aload_3
     141: invokeinterface #71,  2           // InterfaceMethod org/apache/hadoop/hbase/client/Table.get:(Lorg/apache/hadoop/hbase/client/Get;)Lorg/apache/hadoop/hbase/client/Result;
     146: astore        4
     148: lconst_0
     149: aload         4
     151: invokevirtual #72                 // Method org/apache/hadoop/hbase/client/Result.size:()I
     154: i2l
     155: invokestatic  #55                 // Method org/junit/Assert.assertEquals:(JJ)V
     158: return

  public void testRethrowRetriesExhaustedWithDetailsException() throws java.lang.Exception;
    Code:
       0: ldc           #73                 // String notExistTable
       2: invokestatic  #74                 // Method org/apache/hadoop/hbase/TableName.valueOf:(Ljava/lang/String;)Lorg/apache/hadoop/hbase/TableName;
       5: astore_1
       6: new           #39                 // class java/util/ArrayList
       9: dup
      10: invokespecial #42                 // Method java/util/ArrayList."<init>":()V
      13: astore_2
      14: new           #39                 // class java/util/ArrayList
      17: dup
      18: invokespecial #42                 // Method java/util/ArrayList."<init>":()V
      21: astore_3
      22: iconst_0
      23: istore        4
      25: iload         4
      27: bipush        10
      29: if_icmpge     56
      32: aload_2
      33: aload_0
      34: aload_1
      35: iload         4
      37: getstatic     #43                 // Field org/apache/hadoop/hbase/KeyValue$Type.Put:Lorg/apache/hadoop/hbase/KeyValue$Type;
      40: aload_3
      41: invokespecial #44                 // Method createEntry:(Lorg/apache/hadoop/hbase/TableName;ILorg/apache/hadoop/hbase/KeyValue$Type;Ljava/util/List;)Lorg/apache/hadoop/hbase/shaded/protobuf/generated/AdminProtos$WALEntry;
      44: invokeinterface #45,  2           // InterfaceMethod java/util/List.add:(Ljava/lang/Object;)Z
      49: pop
      50: iinc          4, 1
      53: goto          25
      56: getstatic     #15                 // Field SINK:Lorg/apache/hadoop/hbase/replication/regionserver/ReplicationSink;
      59: aload_2
      60: aload_3
      61: invokeinterface #46,  1           // InterfaceMethod java/util/List.iterator:()Ljava/util/Iterator;
      66: invokestatic  #47                 // Method org/apache/hadoop/hbase/CellUtil.createCellScanner:(Ljava/util/Iterator;)Lorg/apache/hadoop/hbase/CellScanner;
      69: getstatic     #34                 // Field replicationClusterId:Ljava/lang/String;
      72: getstatic     #30                 // Field baseNamespaceDir:Ljava/lang/String;
      75: getstatic     #32                 // Field hfileArchiveDir:Ljava/lang/String;
      78: invokevirtual #48                 // Method org/apache/hadoop/hbase/replication/regionserver/ReplicationSink.replicateEntries:(Ljava/util/List;Lorg/apache/hadoop/hbase/CellScanner;Ljava/lang/String;Ljava/lang/String;Ljava/lang/String;)V
      81: ldc           #75                 // String Should re-throw TableNotFoundException.
      83: invokestatic  #76                 // Method org/junit/Assert.fail:(Ljava/lang/String;)V
      86: goto          91
      89: astore        4
      91: aload_2
      92: invokeinterface #78,  1           // InterfaceMethod java/util/List.clear:()V
      97: aload_3
      98: invokeinterface #78,  1           // InterfaceMethod java/util/List.clear:()V
     103: iconst_0
     104: istore        4
     106: iload         4
     108: bipush        10
     110: if_icmpge     139
     113: aload_2
     114: aload_0
     115: getstatic     #16                 // Field TABLE_NAME1:Lorg/apache/hadoop/hbase/TableName;
     118: iload         4
     120: getstatic     #43                 // Field org/apache/hadoop/hbase/KeyValue$Type.Put:Lorg/apache/hadoop/hbase/KeyValue$Type;
     123: aload_3
     124: invokespecial #44                 // Method createEntry:(Lorg/apache/hadoop/hbase/TableName;ILorg/apache/hadoop/hbase/KeyValue$Type;Ljava/util/List;)Lorg/apache/hadoop/hbase/shaded/protobuf/generated/AdminProtos$WALEntry;
     127: invokeinterface #45,  2           // InterfaceMethod java/util/List.add:(Ljava/lang/Object;)Z
     132: pop
     133: iinc          4, 1
     136: goto          106
     139: getstatic     #3                  // Field TEST_UTIL:Lorg/apache/hadoop/hbase/HBaseTestingUtility;
     142: invokevirtual #4                  // Method org/apache/hadoop/hbase/HBaseTestingUtility.getConfiguration:()Lorg/apache/hadoop/conf/Configuration;
     145: invokestatic  #79                 // Method org/apache/hadoop/hbase/client/ConnectionFactory.createConnection:(Lorg/apache/hadoop/conf/Configuration;)Lorg/apache/hadoop/hbase/client/Connection;
     148: astore        4
     150: aconst_null
     151: astore        5
     153: aload         4
     155: invokeinterface #80,  1           // InterfaceMethod org/apache/hadoop/hbase/client/Connection.getAdmin:()Lorg/apache/hadoop/hbase/client/Admin;
     160: astore        6
     162: aconst_null
     163: astore        7
     165: aload         6
     167: getstatic     #16                 // Field TABLE_NAME1:Lorg/apache/hadoop/hbase/TableName;
     170: invokeinterface #81,  2           // InterfaceMethod org/apache/hadoop/hbase/client/Admin.disableTable:(Lorg/apache/hadoop/hbase/TableName;)V
     175: getstatic     #15                 // Field SINK:Lorg/apache/hadoop/hbase/replication/regionserver/ReplicationSink;
     178: aload_2
     179: aload_3
     180: invokeinterface #46,  1           // InterfaceMethod java/util/List.iterator:()Ljava/util/Iterator;
     185: invokestatic  #47                 // Method org/apache/hadoop/hbase/CellUtil.createCellScanner:(Ljava/util/Iterator;)Lorg/apache/hadoop/hbase/CellScanner;
     188: getstatic     #34                 // Field replicationClusterId:Ljava/lang/String;
     191: getstatic     #30                 // Field baseNamespaceDir:Ljava/lang/String;
     194: getstatic     #32                 // Field hfileArchiveDir:Ljava/lang/String;
     197: invokevirtual #48                 // Method org/apache/hadoop/hbase/replication/regionserver/ReplicationSink.replicateEntries:(Ljava/util/List;Lorg/apache/hadoop/hbase/CellScanner;Ljava/lang/String;Ljava/lang/String;Ljava/lang/String;)V
     200: ldc           #82                 // String Should re-throw RetriesExhaustedWithDetailsException.
     202: invokestatic  #76                 // Method org/junit/Assert.fail:(Ljava/lang/String;)V
     205: aload         6
     207: getstatic     #16                 // Field TABLE_NAME1:Lorg/apache/hadoop/hbase/TableName;
     210: invokeinterface #83,  2           // InterfaceMethod org/apache/hadoop/hbase/client/Admin.enableTable:(Lorg/apache/hadoop/hbase/TableName;)V
     215: goto          248
     218: astore        8
     220: aload         6
     222: getstatic     #16                 // Field TABLE_NAME1:Lorg/apache/hadoop/hbase/TableName;
     225: invokeinterface #83,  2           // InterfaceMethod org/apache/hadoop/hbase/client/Admin.enableTable:(Lorg/apache/hadoop/hbase/TableName;)V
     230: goto          248
     233: astore        9
     235: aload         6
     237: getstatic     #16                 // Field TABLE_NAME1:Lorg/apache/hadoop/hbase/TableName;
     240: invokeinterface #83,  2           // InterfaceMethod org/apache/hadoop/hbase/client/Admin.enableTable:(Lorg/apache/hadoop/hbase/TableName;)V
     245: aload         9
     247: athrow
     248: aload         6
     250: ifnull        343
     253: aload         7
     255: ifnull        280
     258: aload         6
     260: invokeinterface #85,  1           // InterfaceMethod org/apache/hadoop/hbase/client/Admin.close:()V
     265: goto          343
     268: astore        8
     270: aload         7
     272: aload         8
     274: invokevirtual #87                 // Method java/lang/Throwable.addSuppressed:(Ljava/lang/Throwable;)V
     277: goto          343
     280: aload         6
     282: invokeinterface #85,  1           // InterfaceMethod org/apache/hadoop/hbase/client/Admin.close:()V
     287: goto          343
     290: astore        8
     292: aload         8
     294: astore        7
     296: aload         8
     298: athrow
     299: astore        10
     301: aload         6
     303: ifnull        340
     306: aload         7
     308: ifnull        333
     311: aload         6
     313: invokeinterface #85,  1           // InterfaceMethod org/apache/hadoop/hbase/client/Admin.close:()V
     318: goto          340
     321: astore        11
     323: aload         7
     325: aload         11
     327: invokevirtual #87                 // Method java/lang/Throwable.addSuppressed:(Ljava/lang/Throwable;)V
     330: goto          340
     333: aload         6
     335: invokeinterface #85,  1           // InterfaceMethod org/apache/hadoop/hbase/client/Admin.close:()V
     340: aload         10
     342: athrow
     343: aload         4
     345: ifnull        438
     348: aload         5
     350: ifnull        375
     353: aload         4
     355: invokeinterface #88,  1           // InterfaceMethod org/apache/hadoop/hbase/client/Connection.close:()V
     360: goto          438
     363: astore        6
     365: aload         5
     367: aload         6
     369: invokevirtual #87                 // Method java/lang/Throwable.addSuppressed:(Ljava/lang/Throwable;)V
     372: goto          438
     375: aload         4
     377: invokeinterface #88,  1           // InterfaceMethod org/apache/hadoop/hbase/client/Connection.close:()V
     382: goto          438
     385: astore        6
     387: aload         6
     389: astore        5
     391: aload         6
     393: athrow
     394: astore        12
     396: aload         4
     398: ifnull        435
     401: aload         5
     403: ifnull        428
     406: aload         4
     408: invokeinterface #88,  1           // InterfaceMethod org/apache/hadoop/hbase/client/Connection.close:()V
     413: goto          435
     416: astore        13
     418: aload         5
     420: aload         13
     422: invokevirtual #87                 // Method java/lang/Throwable.addSuppressed:(Ljava/lang/Throwable;)V
     425: goto          435
     428: aload         4
     430: invokeinterface #88,  1           // InterfaceMethod org/apache/hadoop/hbase/client/Connection.close:()V
     435: aload         12
     437: athrow
     438: return
    Exception table:
       from    to  target type
          56    86    89   Class org/apache/hadoop/hbase/TableNotFoundException
         175   205   218   Class org/apache/hadoop/hbase/client/RetriesExhaustedWithDetailsException
         175   205   233   any
         218   220   233   any
         233   235   233   any
         258   265   268   Class java/lang/Throwable
         165   248   290   Class java/lang/Throwable
         165   248   299   any
         311   318   321   Class java/lang/Throwable
         290   301   299   any
         353   360   363   Class java/lang/Throwable
         153   343   385   Class java/lang/Throwable
         153   343   394   any
         406   413   416   Class java/lang/Throwable
         385   396   394   any

  public void testReplicateEntriesForHFiles() throws java.lang.Exception;
    Code:
       0: getstatic     #3                  // Field TEST_UTIL:Lorg/apache/hadoop/hbase/HBaseTestingUtility;
       3: ldc           #89                 // String testReplicateEntries
       5: invokevirtual #90                 // Method org/apache/hadoop/hbase/HBaseTestingUtility.getDataTestDirOnTestFS:(Ljava/lang/String;)Lorg/apache/hadoop/fs/Path;
       8: astore_1
       9: new           #24                 // class org/apache/hadoop/fs/Path
      12: dup
      13: aload_1
      14: getstatic     #17                 // Field FAM_NAME1:[B
      17: invokestatic  #91                 // Method org/apache/hadoop/hbase/util/Bytes.toString:([B)Ljava/lang/String;
      20: invokespecial #92                 // Method org/apache/hadoop/fs/Path."<init>":(Lorg/apache/hadoop/fs/Path;Ljava/lang/String;)V
      23: astore_2
      24: bipush        10
      26: istore_3
      27: new           #39                 // class java/util/ArrayList
      30: dup
      31: iconst_1
      32: invokespecial #41                 // Method java/util/ArrayList."<init>":(I)V
      35: astore        4
      37: ldc           #93                 // String hfile-
      39: astore        5
      41: new           #94                 // class java/security/SecureRandom
      44: dup
      45: invokespecial #95                 // Method java/security/SecureRandom."<init>":()V
      48: astore        6
      50: new           #96                 // class java/util/HashSet
      53: dup
      54: invokespecial #97                 // Method java/util/HashSet."<init>":()V
      57: astore        7
      59: aload         7
      61: invokeinterface #98,  1           // InterfaceMethod java/util/Set.size:()I
      66: bipush        50
      68: if_icmpge     93
      71: aload         7
      73: aload         6
      75: sipush        1000
      78: invokevirtual #99                 // Method java/util/Random.nextInt:(I)I
      81: invokestatic  #100                // Method java/lang/Integer.valueOf:(I)Ljava/lang/Integer;
      84: invokeinterface #101,  2          // InterfaceMethod java/util/Set.add:(Ljava/lang/Object;)Z
      89: pop
      90: goto          59
      93: new           #39                 // class java/util/ArrayList
      96: dup
      97: aload         7
      99: invokespecial #102                // Method java/util/ArrayList."<init>":(Ljava/util/Collection;)V
     102: astore        8
     104: aload         8
     106: invokestatic  #103                // Method java/util/Collections.sort:(Ljava/util/List;)V
     109: new           #104                // class java/util/HashMap
     112: dup
     113: iconst_1
     114: invokespecial #105                // Method java/util/HashMap."<init>":(I)V
     117: astore        9
     119: getstatic     #3                  // Field TEST_UTIL:Lorg/apache/hadoop/hbase/HBaseTestingUtility;
     122: invokevirtual #4                  // Method org/apache/hadoop/hbase/HBaseTestingUtility.getConfiguration:()Lorg/apache/hadoop/conf/Configuration;
     125: astore        10
     127: aload_1
     128: aload         10
     130: invokevirtual #106                // Method org/apache/hadoop/fs/Path.getFileSystem:(Lorg/apache/hadoop/conf/Configuration;)Lorg/apache/hadoop/fs/FileSystem;
     133: astore        11
     135: aload         8
     137: invokeinterface #46,  1           // InterfaceMethod java/util/List.iterator:()Ljava/util/Iterator;
     142: astore        12
     144: iconst_0
     145: istore        13
     147: iload         13
     149: bipush        25
     151: if_icmpge     274
     154: new           #24                 // class org/apache/hadoop/fs/Path
     157: dup
     158: aload_2
     159: new           #107                // class java/lang/StringBuilder
     162: dup
     163: invokespecial #108                // Method java/lang/StringBuilder."<init>":()V
     166: ldc           #93                 // String hfile-
     168: invokevirtual #109                // Method java/lang/StringBuilder.append:(Ljava/lang/String;)Ljava/lang/StringBuilder;
     171: iload         13
     173: invokevirtual #110                // Method java/lang/StringBuilder.append:(I)Ljava/lang/StringBuilder;
     176: invokevirtual #111                // Method java/lang/StringBuilder.toString:()Ljava/lang/String;
     179: invokespecial #92                 // Method org/apache/hadoop/fs/Path."<init>":(Lorg/apache/hadoop/fs/Path;Ljava/lang/String;)V
     182: astore        14
     184: aload         10
     186: aload         11
     188: aload         14
     190: getstatic     #17                 // Field FAM_NAME1:[B
     193: getstatic     #17                 // Field FAM_NAME1:[B
     196: aload         12
     198: invokeinterface #62,  1           // InterfaceMethod java/util/Iterator.next:()Ljava/lang/Object;
     203: checkcast     #112                // class java/lang/Integer
     206: invokevirtual #113                // Method java/lang/Integer.intValue:()I
     209: invokestatic  #69                 // Method org/apache/hadoop/hbase/util/Bytes.toBytes:(I)[B
     212: aload         12
     214: invokeinterface #62,  1           // InterfaceMethod java/util/Iterator.next:()Ljava/lang/Object;
     219: checkcast     #112                // class java/lang/Integer
     222: invokevirtual #113                // Method java/lang/Integer.intValue:()I
     225: invokestatic  #69                 // Method org/apache/hadoop/hbase/util/Bytes.toBytes:(I)[B
     228: iload_3
     229: invokestatic  #114                // Method org/apache/hadoop/hbase/util/HFileTestUtil.createHFile:(Lorg/apache/hadoop/conf/Configuration;Lorg/apache/hadoop/fs/FileSystem;Lorg/apache/hadoop/fs/Path;[B[B[B[BI)V
     232: aload         4
     234: aload         14
     236: invokeinterface #45,  2           // InterfaceMethod java/util/List.add:(Ljava/lang/Object;)Z
     241: pop
     242: aload         9
     244: aload         14
     246: invokevirtual #115                // Method org/apache/hadoop/fs/Path.getName:()Ljava/lang/String;
     249: aload         11
     251: aload         14
     253: invokevirtual #116                // Method org/apache/hadoop/fs/FileSystem.getFileStatus:(Lorg/apache/hadoop/fs/Path;)Lorg/apache/hadoop/fs/FileStatus;
     256: invokevirtual #117                // Method org/apache/hadoop/fs/FileStatus.getLen:()J
     259: invokestatic  #118                // Method java/lang/Long.valueOf:(J)Ljava/lang/Long;
     262: invokeinterface #119,  3          // InterfaceMethod java/util/Map.put:(Ljava/lang/Object;Ljava/lang/Object;)Ljava/lang/Object;
     267: pop
     268: iinc          13, 1
     271: goto          147
     274: new           #104                // class java/util/HashMap
     277: dup
     278: iconst_1
     279: invokespecial #105                // Method java/util/HashMap."<init>":(I)V
     282: astore        13
     284: aload         13
     286: getstatic     #17                 // Field FAM_NAME1:[B
     289: aload         4
     291: invokeinterface #119,  3          // InterfaceMethod java/util/Map.put:(Ljava/lang/Object;Ljava/lang/Object;)Ljava/lang/Object;
     296: pop
     297: aconst_null
     298: astore        14
     300: aconst_null
     301: astore        15
     303: aload         10
     305: invokestatic  #79                 // Method org/apache/hadoop/hbase/client/ConnectionFactory.createConnection:(Lorg/apache/hadoop/conf/Configuration;)Lorg/apache/hadoop/hbase/client/Connection;
     308: astore        16
     310: aconst_null
     311: astore        17
     313: aload         16
     315: getstatic     #16                 // Field TABLE_NAME1:Lorg/apache/hadoop/hbase/TableName;
     318: invokeinterface #120,  2          // InterfaceMethod org/apache/hadoop/hbase/client/Connection.getRegionLocator:(Lorg/apache/hadoop/hbase/TableName;)Lorg/apache/hadoop/hbase/client/RegionLocator;
     323: astore        18
     325: aconst_null
     326: astore        19
     328: aload         18
     330: invokeinterface #121,  1          // InterfaceMethod org/apache/hadoop/hbase/client/RegionLocator.getAllRegionLocations:()Ljava/util/List;
     335: iconst_0
     336: invokeinterface #122,  2          // InterfaceMethod java/util/List.get:(I)Ljava/lang/Object;
     341: checkcast     #123                // class org/apache/hadoop/hbase/HRegionLocation
     344: invokevirtual #124                // Method org/apache/hadoop/hbase/HRegionLocation.getRegionInfo:()Lorg/apache/hadoop/hbase/HRegionInfo;
     347: astore        20
     349: getstatic     #16                 // Field TABLE_NAME1:Lorg/apache/hadoop/hbase/TableName;
     352: aload         20
     354: invokevirtual #125                // Method org/apache/hadoop/hbase/HRegionInfo.getEncodedNameAsBytes:()[B
     357: invokestatic  #126                // Method org/apache/hbase/thirdparty/com/google/protobuf/UnsafeByteOperations.unsafeWrap:([B)Lorg/apache/hbase/thirdparty/com/google/protobuf/ByteString;
     360: aload         13
     362: aload         9
     364: lconst_1
     365: invokestatic  #127                // Method org/apache/hadoop/hbase/shaded/protobuf/ProtobufUtil.toBulkLoadDescriptor:(Lorg/apache/hadoop/hbase/TableName;Lorg/apache/hbase/thirdparty/com/google/protobuf/ByteString;Ljava/util/Map;Ljava/util/Map;J)Lorg/apache/hadoop/hbase/shaded/protobuf/generated/WALProtos$BulkLoadDescriptor;
     368: astore        15
     370: aload         20
     372: aload         15
     374: invokestatic  #128                // Method org/apache/hadoop/hbase/wal/WALEdit.createBulkLoadEvent:(Lorg/apache/hadoop/hbase/client/RegionInfo;Lorg/apache/hadoop/hbase/shaded/protobuf/generated/WALProtos$BulkLoadDescriptor;)Lorg/apache/hadoop/hbase/wal/WALEdit;
     377: astore        14
     379: aload         18
     381: ifnull        474
     384: aload         19
     386: ifnull        411
     389: aload         18
     391: invokeinterface #129,  1          // InterfaceMethod org/apache/hadoop/hbase/client/RegionLocator.close:()V
     396: goto          474
     399: astore        20
     401: aload         19
     403: aload         20
     405: invokevirtual #87                 // Method java/lang/Throwable.addSuppressed:(Ljava/lang/Throwable;)V
     408: goto          474
     411: aload         18
     413: invokeinterface #129,  1          // InterfaceMethod org/apache/hadoop/hbase/client/RegionLocator.close:()V
     418: goto          474
     421: astore        20
     423: aload         20
     425: astore        19
     427: aload         20
     429: athrow
     430: astore        21
     432: aload         18
     434: ifnull        471
     437: aload         19
     439: ifnull        464
     442: aload         18
     444: invokeinterface #129,  1          // InterfaceMethod org/apache/hadoop/hbase/client/RegionLocator.close:()V
     449: goto          471
     452: astore        22
     454: aload         19
     456: aload         22
     458: invokevirtual #87                 // Method java/lang/Throwable.addSuppressed:(Ljava/lang/Throwable;)V
     461: goto          471
     464: aload         18
     466: invokeinterface #129,  1          // InterfaceMethod org/apache/hadoop/hbase/client/RegionLocator.close:()V
     471: aload         21
     473: athrow
     474: aload         16
     476: ifnull        569
     479: aload         17
     481: ifnull        506
     484: aload         16
     486: invokeinterface #88,  1           // InterfaceMethod org/apache/hadoop/hbase/client/Connection.close:()V
     491: goto          569
     494: astore        18
     496: aload         17
     498: aload         18
     500: invokevirtual #87                 // Method java/lang/Throwable.addSuppressed:(Ljava/lang/Throwable;)V
     503: goto          569
     506: aload         16
     508: invokeinterface #88,  1           // InterfaceMethod org/apache/hadoop/hbase/client/Connection.close:()V
     513: goto          569
     516: astore        18
     518: aload         18
     520: astore        17
     522: aload         18
     524: athrow
     525: astore        23
     527: aload         16
     529: ifnull        566
     532: aload         17
     534: ifnull        559
     537: aload         16
     539: invokeinterface #88,  1           // InterfaceMethod org/apache/hadoop/hbase/client/Connection.close:()V
     544: goto          566
     547: astore        24
     549: aload         17
     551: aload         24
     553: invokevirtual #87                 // Method java/lang/Throwable.addSuppressed:(Ljava/lang/Throwable;)V
     556: goto          566
     559: aload         16
     561: invokeinterface #88,  1           // InterfaceMethod org/apache/hadoop/hbase/client/Connection.close:()V
     566: aload         23
     568: athrow
     569: new           #39                 // class java/util/ArrayList
     572: dup
     573: iconst_1
     574: invokespecial #41                 // Method java/util/ArrayList."<init>":(I)V
     577: astore        16
     579: getstatic     #16                 // Field TABLE_NAME1:Lorg/apache/hadoop/hbase/TableName;
     582: invokestatic  #130                // Method createWALEntryBuilder:(Lorg/apache/hadoop/hbase/TableName;)Lorg/apache/hadoop/hbase/shaded/protobuf/generated/AdminProtos$WALEntry$Builder;
     585: astore        17
     587: iconst_0
     588: istore        18
     590: iload         18
     592: bipush        25
     594: if_icmpge     767
     597: new           #107                // class java/lang/StringBuilder
     600: dup
     601: bipush        100
     603: invokespecial #131                // Method java/lang/StringBuilder."<init>":(I)V
     606: getstatic     #16                 // Field TABLE_NAME1:Lorg/apache/hadoop/hbase/TableName;
     609: invokevirtual #132                // Method org/apache/hadoop/hbase/TableName.getNamespaceAsString:()Ljava/lang/String;
     612: invokevirtual #109                // Method java/lang/StringBuilder.append:(Ljava/lang/String;)Ljava/lang/StringBuilder;
     615: ldc           #133                // String /
     617: invokevirtual #109                // Method java/lang/StringBuilder.append:(Ljava/lang/String;)Ljava/lang/StringBuilder;
     620: getstatic     #16                 // Field TABLE_NAME1:Lorg/apache/hadoop/hbase/TableName;
     623: invokevirtual #134                // Method org/apache/hadoop/hbase/TableName.getName:()[B
     626: invokestatic  #91                 // Method org/apache/hadoop/hbase/util/Bytes.toString:([B)Ljava/lang/String;
     629: invokevirtual #109                // Method java/lang/StringBuilder.append:(Ljava/lang/String;)Ljava/lang/StringBuilder;
     632: ldc           #133                // String /
     634: invokevirtual #109                // Method java/lang/StringBuilder.append:(Ljava/lang/String;)Ljava/lang/StringBuilder;
     637: aload         15
     639: invokevirtual #135                // Method org/apache/hadoop/hbase/shaded/protobuf/generated/WALProtos$BulkLoadDescriptor.getEncodedRegionName:()Lorg/apache/hbase/thirdparty/com/google/protobuf/ByteString;
     642: invokevirtual #136                // Method org/apache/hbase/thirdparty/com/google/protobuf/ByteString.toByteArray:()[B
     645: invokestatic  #91                 // Method org/apache/hadoop/hbase/util/Bytes.toString:([B)Ljava/lang/String;
     648: invokevirtual #109                // Method java/lang/StringBuilder.append:(Ljava/lang/String;)Ljava/lang/StringBuilder;
     651: ldc           #133                // String /
     653: invokevirtual #109                // Method java/lang/StringBuilder.append:(Ljava/lang/String;)Ljava/lang/StringBuilder;
     656: getstatic     #17                 // Field FAM_NAME1:[B
     659: invokestatic  #91                 // Method org/apache/hadoop/hbase/util/Bytes.toString:([B)Ljava/lang/String;
     662: invokevirtual #109                // Method java/lang/StringBuilder.append:(Ljava/lang/String;)Ljava/lang/StringBuilder;
     665: ldc           #133                // String /
     667: invokevirtual #109                // Method java/lang/StringBuilder.append:(Ljava/lang/String;)Ljava/lang/StringBuilder;
     670: new           #107                // class java/lang/StringBuilder
     673: dup
     674: invokespecial #108                // Method java/lang/StringBuilder."<init>":()V
     677: ldc           #93                 // String hfile-
     679: invokevirtual #109                // Method java/lang/StringBuilder.append:(Ljava/lang/String;)Ljava/lang/StringBuilder;
     682: iload         18
     684: invokevirtual #110                // Method java/lang/StringBuilder.append:(I)Ljava/lang/StringBuilder;
     687: invokevirtual #111                // Method java/lang/StringBuilder.toString:()Ljava/lang/String;
     690: invokevirtual #109                // Method java/lang/StringBuilder.append:(Ljava/lang/String;)Ljava/lang/StringBuilder;
     693: invokevirtual #111                // Method java/lang/StringBuilder.toString:()Ljava/lang/String;
     696: astore        19
     698: new           #107                // class java/lang/StringBuilder
     701: dup
     702: invokespecial #108                // Method java/lang/StringBuilder."<init>":()V
     705: getstatic     #30                 // Field baseNamespaceDir:Ljava/lang/String;
     708: invokevirtual #109                // Method java/lang/StringBuilder.append:(Ljava/lang/String;)Ljava/lang/StringBuilder;
     711: ldc           #133                // String /
     713: invokevirtual #109                // Method java/lang/StringBuilder.append:(Ljava/lang/String;)Ljava/lang/StringBuilder;
     716: aload         19
     718: invokevirtual #109                // Method java/lang/StringBuilder.append:(Ljava/lang/String;)Ljava/lang/StringBuilder;
     721: invokevirtual #111                // Method java/lang/StringBuilder.toString:()Ljava/lang/String;
     724: astore        20
     726: new           #24                 // class org/apache/hadoop/fs/Path
     729: dup
     730: aload         20
     732: invokespecial #27                 // Method org/apache/hadoop/fs/Path."<init>":(Ljava/lang/String;)V
     735: astore        21
     737: aload         11
     739: aload         4
     741: iconst_0
     742: invokeinterface #122,  2          // InterfaceMethod java/util/List.get:(I)Ljava/lang/Object;
     747: checkcast     #24                 // class org/apache/hadoop/fs/Path
     750: aload         11
     752: aload         21
     754: iconst_0
     755: aload         10
     757: invokestatic  #137                // Method org/apache/hadoop/fs/FileUtil.copy:(Lorg/apache/hadoop/fs/FileSystem;Lorg/apache/hadoop/fs/Path;Lorg/apache/hadoop/fs/FileSystem;Lorg/apache/hadoop/fs/Path;ZLorg/apache/hadoop/conf/Configuration;)Z
     760: pop
     761: iinc          18, 1
     764: goto          590
     767: aload         16
     769: aload         17
     771: invokevirtual #138                // Method org/apache/hadoop/hbase/shaded/protobuf/generated/AdminProtos$WALEntry$Builder.build:()Lorg/apache/hadoop/hbase/shaded/protobuf/generated/AdminProtos$WALEntry;
     774: invokeinterface #45,  2           // InterfaceMethod java/util/List.add:(Ljava/lang/Object;)Z
     779: pop
     780: getstatic     #19                 // Field table1:Lorg/apache/hadoop/hbase/client/Table;
     783: new           #49                 // class org/apache/hadoop/hbase/client/Scan
     786: dup
     787: invokespecial #50                 // Method org/apache/hadoop/hbase/client/Scan."<init>":()V
     790: invokeinterface #51,  2           // InterfaceMethod org/apache/hadoop/hbase/client/Table.getScanner:(Lorg/apache/hadoop/hbase/client/Scan;)Lorg/apache/hadoop/hbase/client/ResultScanner;
     795: astore        18
     797: aconst_null
     798: astore        19
     800: lconst_0
     801: aload         18
     803: iload_3
     804: invokeinterface #54,  2           // InterfaceMethod org/apache/hadoop/hbase/client/ResultScanner.next:(I)[Lorg/apache/hadoop/hbase/client/Result;
     809: arraylength
     810: i2l
     811: invokestatic  #55                 // Method org/junit/Assert.assertEquals:(JJ)V
     814: aload         18
     816: ifnull        909
     819: aload         19
     821: ifnull        846
     824: aload         18
     826: invokeinterface #139,  1          // InterfaceMethod org/apache/hadoop/hbase/client/ResultScanner.close:()V
     831: goto          909
     834: astore        20
     836: aload         19
     838: aload         20
     840: invokevirtual #87                 // Method java/lang/Throwable.addSuppressed:(Ljava/lang/Throwable;)V
     843: goto          909
     846: aload         18
     848: invokeinterface #139,  1          // InterfaceMethod org/apache/hadoop/hbase/client/ResultScanner.close:()V
     853: goto          909
     856: astore        20
     858: aload         20
     860: astore        19
     862: aload         20
     864: athrow
     865: astore        25
     867: aload         18
     869: ifnull        906
     872: aload         19
     874: ifnull        899
     877: aload         18
     879: invokeinterface #139,  1          // InterfaceMethod org/apache/hadoop/hbase/client/ResultScanner.close:()V
     884: goto          906
     887: astore        26
     889: aload         19
     891: aload         26
     893: invokevirtual #87                 // Method java/lang/Throwable.addSuppressed:(Ljava/lang/Throwable;)V
     896: goto          906
     899: aload         18
     901: invokeinterface #139,  1          // InterfaceMethod org/apache/hadoop/hbase/client/ResultScanner.close:()V
     906: aload         25
     908: athrow
     909: getstatic     #15                 // Field SINK:Lorg/apache/hadoop/hbase/replication/regionserver/ReplicationSink;
     912: aload         16
     914: aload         14
     916: invokevirtual #140                // Method org/apache/hadoop/hbase/wal/WALEdit.getCells:()Ljava/util/ArrayList;
     919: invokevirtual #141                // Method java/util/ArrayList.iterator:()Ljava/util/Iterator;
     922: invokestatic  #47                 // Method org/apache/hadoop/hbase/CellUtil.createCellScanner:(Ljava/util/Iterator;)Lorg/apache/hadoop/hbase/CellScanner;
     925: getstatic     #34                 // Field replicationClusterId:Ljava/lang/String;
     928: getstatic     #30                 // Field baseNamespaceDir:Ljava/lang/String;
     931: getstatic     #32                 // Field hfileArchiveDir:Ljava/lang/String;
     934: invokevirtual #48                 // Method org/apache/hadoop/hbase/replication/regionserver/ReplicationSink.replicateEntries:(Ljava/util/List;Lorg/apache/hadoop/hbase/CellScanner;Ljava/lang/String;Ljava/lang/String;Ljava/lang/String;)V
     937: getstatic     #19                 // Field table1:Lorg/apache/hadoop/hbase/client/Table;
     940: new           #49                 // class org/apache/hadoop/hbase/client/Scan
     943: dup
     944: invokespecial #50                 // Method org/apache/hadoop/hbase/client/Scan."<init>":()V
     947: invokeinterface #51,  2           // InterfaceMethod org/apache/hadoop/hbase/client/Table.getScanner:(Lorg/apache/hadoop/hbase/client/Scan;)Lorg/apache/hadoop/hbase/client/ResultScanner;
     952: astore        18
     954: aconst_null
     955: astore        19
     957: iload_3
     958: i2l
     959: aload         18
     961: iload_3
     962: invokeinterface #54,  2           // InterfaceMethod org/apache/hadoop/hbase/client/ResultScanner.next:(I)[Lorg/apache/hadoop/hbase/client/Result;
     967: arraylength
     968: i2l
     969: invokestatic  #55                 // Method org/junit/Assert.assertEquals:(JJ)V
     972: aload         18
     974: ifnull        1067
     977: aload         19
     979: ifnull        1004
     982: aload         18
     984: invokeinterface #139,  1          // InterfaceMethod org/apache/hadoop/hbase/client/ResultScanner.close:()V
     989: goto          1067
     992: astore        20
     994: aload         19
     996: aload         20
     998: invokevirtual #87                 // Method java/lang/Throwable.addSuppressed:(Ljava/lang/Throwable;)V
    1001: goto          1067
    1004: aload         18
    1006: invokeinterface #139,  1          // InterfaceMethod org/apache/hadoop/hbase/client/ResultScanner.close:()V
    1011: goto          1067
    1014: astore        20
    1016: aload         20
    1018: astore        19
    1020: aload         20
    1022: athrow
    1023: astore        27
    1025: aload         18
    1027: ifnull        1064
    1030: aload         19
    1032: ifnull        1057
    1035: aload         18
    1037: invokeinterface #139,  1          // InterfaceMethod org/apache/hadoop/hbase/client/ResultScanner.close:()V
    1042: goto          1064
    1045: astore        28
    1047: aload         19
    1049: aload         28
    1051: invokevirtual #87                 // Method java/lang/Throwable.addSuppressed:(Ljava/lang/Throwable;)V
    1054: goto          1064
    1057: aload         18
    1059: invokeinterface #139,  1          // InterfaceMethod org/apache/hadoop/hbase/client/ResultScanner.close:()V
    1064: aload         27
    1066: athrow
    1067: return
    Exception table:
       from    to  target type
         389   396   399   Class java/lang/Throwable
         328   379   421   Class java/lang/Throwable
         328   379   430   any
         442   449   452   Class java/lang/Throwable
         421   432   430   any
         484   491   494   Class java/lang/Throwable
         313   474   516   Class java/lang/Throwable
         313   474   525   any
         537   544   547   Class java/lang/Throwable
         516   527   525   any
         824   831   834   Class java/lang/Throwable
         800   814   856   Class java/lang/Throwable
         800   814   865   any
         877   884   887   Class java/lang/Throwable
         856   867   865   any
         982   989   992   Class java/lang/Throwable
         957   972  1014   Class java/lang/Throwable
         957   972  1023   any
        1035  1042  1045   Class java/lang/Throwable
        1014  1025  1023   any

  public static org.apache.hadoop.hbase.shaded.protobuf.generated.AdminProtos$WALEntry$Builder createWALEntryBuilder(org.apache.hadoop.hbase.TableName);
    Code:
       0: invokestatic  #152                // Method org/apache/hadoop/hbase/shaded/protobuf/generated/AdminProtos$WALEntry.newBuilder:()Lorg/apache/hadoop/hbase/shaded/protobuf/generated/AdminProtos$WALEntry$Builder;
       3: astore_1
       4: aload_1
       5: iconst_1
       6: invokevirtual #153                // Method org/apache/hadoop/hbase/shaded/protobuf/generated/AdminProtos$WALEntry$Builder.setAssociatedCellCount:(I)Lorg/apache/hadoop/hbase/shaded/protobuf/generated/AdminProtos$WALEntry$Builder;
       9: pop
      10: invokestatic  #154                // Method org/apache/hadoop/hbase/shaded/protobuf/generated/WALProtos$WALKey.newBuilder:()Lorg/apache/hadoop/hbase/shaded/protobuf/generated/WALProtos$WALKey$Builder;
      13: astore_2
      14: invokestatic  #155                // Method org/apache/hadoop/hbase/shaded/protobuf/generated/HBaseProtos$UUID.newBuilder:()Lorg/apache/hadoop/hbase/shaded/protobuf/generated/HBaseProtos$UUID$Builder;
      17: astore_3
      18: aload_3
      19: getstatic     #156                // Field org/apache/hadoop/hbase/HConstants.DEFAULT_CLUSTER_ID:Ljava/util/UUID;
      22: invokevirtual #157                // Method java/util/UUID.getLeastSignificantBits:()J
      25: invokevirtual #158                // Method org/apache/hadoop/hbase/shaded/protobuf/generated/HBaseProtos$UUID$Builder.setLeastSigBits:(J)Lorg/apache/hadoop/hbase/shaded/protobuf/generated/HBaseProtos$UUID$Builder;
      28: pop
      29: aload_3
      30: getstatic     #156                // Field org/apache/hadoop/hbase/HConstants.DEFAULT_CLUSTER_ID:Ljava/util/UUID;
      33: invokevirtual #159                // Method java/util/UUID.getMostSignificantBits:()J
      36: invokevirtual #160                // Method org/apache/hadoop/hbase/shaded/protobuf/generated/HBaseProtos$UUID$Builder.setMostSigBits:(J)Lorg/apache/hadoop/hbase/shaded/protobuf/generated/HBaseProtos$UUID$Builder;
      39: pop
      40: aload_2
      41: aload_3
      42: invokevirtual #161                // Method org/apache/hadoop/hbase/shaded/protobuf/generated/HBaseProtos$UUID$Builder.build:()Lorg/apache/hadoop/hbase/shaded/protobuf/generated/HBaseProtos$UUID;
      45: invokevirtual #162                // Method org/apache/hadoop/hbase/shaded/protobuf/generated/WALProtos$WALKey$Builder.setClusterId:(Lorg/apache/hadoop/hbase/shaded/protobuf/generated/HBaseProtos$UUID;)Lorg/apache/hadoop/hbase/shaded/protobuf/generated/WALProtos$WALKey$Builder;
      48: pop
      49: aload_2
      50: aload_0
      51: invokevirtual #134                // Method org/apache/hadoop/hbase/TableName.getName:()[B
      54: invokestatic  #126                // Method org/apache/hbase/thirdparty/com/google/protobuf/UnsafeByteOperations.unsafeWrap:([B)Lorg/apache/hbase/thirdparty/com/google/protobuf/ByteString;
      57: invokevirtual #163                // Method org/apache/hadoop/hbase/shaded/protobuf/generated/WALProtos$WALKey$Builder.setTableName:(Lorg/apache/hbase/thirdparty/com/google/protobuf/ByteString;)Lorg/apache/hadoop/hbase/shaded/protobuf/generated/WALProtos$WALKey$Builder;
      60: pop
      61: aload_2
      62: invokestatic  #147                // Method java/lang/System.currentTimeMillis:()J
      65: invokevirtual #164                // Method org/apache/hadoop/hbase/shaded/protobuf/generated/WALProtos$WALKey$Builder.setWriteTime:(J)Lorg/apache/hadoop/hbase/shaded/protobuf/generated/WALProtos$WALKey$Builder;
      68: pop
      69: aload_2
      70: getstatic     #165                // Field org/apache/hadoop/hbase/HConstants.EMPTY_BYTE_ARRAY:[B
      73: invokestatic  #126                // Method org/apache/hbase/thirdparty/com/google/protobuf/UnsafeByteOperations.unsafeWrap:([B)Lorg/apache/hbase/thirdparty/com/google/protobuf/ByteString;
      76: invokevirtual #166                // Method org/apache/hadoop/hbase/shaded/protobuf/generated/WALProtos$WALKey$Builder.setEncodedRegionName:(Lorg/apache/hbase/thirdparty/com/google/protobuf/ByteString;)Lorg/apache/hadoop/hbase/shaded/protobuf/generated/WALProtos$WALKey$Builder;
      79: pop
      80: aload_2
      81: ldc2_w        #167                // long -1l
      84: invokevirtual #169                // Method org/apache/hadoop/hbase/shaded/protobuf/generated/WALProtos$WALKey$Builder.setLogSequenceNumber:(J)Lorg/apache/hadoop/hbase/shaded/protobuf/generated/WALProtos$WALKey$Builder;
      87: pop
      88: aload_1
      89: aload_2
      90: invokevirtual #170                // Method org/apache/hadoop/hbase/shaded/protobuf/generated/WALProtos$WALKey$Builder.build:()Lorg/apache/hadoop/hbase/shaded/protobuf/generated/WALProtos$WALKey;
      93: invokevirtual #171                // Method org/apache/hadoop/hbase/shaded/protobuf/generated/AdminProtos$WALEntry$Builder.setKey:(Lorg/apache/hadoop/hbase/shaded/protobuf/generated/WALProtos$WALKey;)Lorg/apache/hadoop/hbase/shaded/protobuf/generated/AdminProtos$WALEntry$Builder;
      96: pop
      97: aload_1
      98: areturn

  static org.slf4j.Logger access$000();
    Code:
       0: getstatic     #1                  // Field LOG:Lorg/slf4j/Logger;
       3: areturn

  static {};
    Code:
       0: ldc           #40                 // class org/apache/hadoop/hbase/replication/regionserver/TestReplicationSink
       2: invokestatic  #172                // Method org/apache/hadoop/hbase/HBaseClassTestRule.forClass:(Ljava/lang/Class;)Lorg/apache/hadoop/hbase/HBaseClassTestRule;
       5: putstatic     #173                // Field CLASS_RULE:Lorg/apache/hadoop/hbase/HBaseClassTestRule;
       8: ldc           #40                 // class org/apache/hadoop/hbase/replication/regionserver/TestReplicationSink
      10: invokestatic  #174                // Method org/slf4j/LoggerFactory.getLogger:(Ljava/lang/Class;)Lorg/slf4j/Logger;
      13: putstatic     #1                  // Field LOG:Lorg/slf4j/Logger;
      16: new           #175                // class org/apache/hadoop/hbase/HBaseTestingUtility
      19: dup
      20: invokespecial #176                // Method org/apache/hadoop/hbase/HBaseTestingUtility."<init>":()V
      23: putstatic     #3                  // Field TEST_UTIL:Lorg/apache/hadoop/hbase/HBaseTestingUtility;
      26: ldc           #177                // String table1
      28: invokestatic  #74                 // Method org/apache/hadoop/hbase/TableName.valueOf:(Ljava/lang/String;)Lorg/apache/hadoop/hbase/TableName;
      31: putstatic     #16                 // Field TABLE_NAME1:Lorg/apache/hadoop/hbase/TableName;
      34: ldc           #178                // String table2
      36: invokestatic  #74                 // Method org/apache/hadoop/hbase/TableName.valueOf:(Ljava/lang/String;)Lorg/apache/hadoop/hbase/TableName;
      39: putstatic     #20                 // Field TABLE_NAME2:Lorg/apache/hadoop/hbase/TableName;
      42: ldc           #179                // String info1
      44: invokestatic  #180                // Method org/apache/hadoop/hbase/util/Bytes.toBytes:(Ljava/lang/String;)[B
      47: putstatic     #17                 // Field FAM_NAME1:[B
      50: ldc           #181                // String info2
      52: invokestatic  #180                // Method org/apache/hadoop/hbase/util/Bytes.toBytes:(Ljava/lang/String;)[B
      55: putstatic     #21                 // Field FAM_NAME2:[B
      58: new           #182                // class org/apache/hadoop/hbase/replication/regionserver/TestReplicationSink$1
      61: dup
      62: invokespecial #183                // Method org/apache/hadoop/hbase/replication/regionserver/TestReplicationSink$1."<init>":()V
      65: putstatic     #13                 // Field STOPPABLE:Lorg/apache/hadoop/hbase/Stoppable;
      68: return
}
