Compiled from "TestFuzzyRowFilter.java"
public class org.apache.hadoop.hbase.filter.TestFuzzyRowFilter {
  public static final org.apache.hadoop.hbase.HBaseClassTestRule CLASS_RULE;

  public org.apache.hadoop.hbase.filter.TestFuzzyRowFilter();
    Code:
       0: aload_0
       1: invokespecial #1                  // Method java/lang/Object."<init>":()V
       4: return

  public void testSatisfiesNoUnsafeForward();
    Code:
       0: getstatic     #2                  // Field org/apache/hadoop/hbase/filter/FuzzyRowFilter$SatisfiesCode.YES:Lorg/apache/hadoop/hbase/filter/FuzzyRowFilter$SatisfiesCode;
       3: iconst_0
       4: iconst_5
       5: newarray       byte
       7: dup
       8: iconst_0
       9: iconst_1
      10: bastore
      11: dup
      12: iconst_1
      13: bipush        -128
      15: bastore
      16: dup
      17: iconst_2
      18: iconst_1
      19: bastore
      20: dup
      21: iconst_3
      22: iconst_0
      23: bastore
      24: dup
      25: iconst_4
      26: iconst_1
      27: bastore
      28: iconst_0
      29: iconst_5
      30: iconst_3
      31: newarray       byte
      33: dup
      34: iconst_0
      35: iconst_1
      36: bastore
      37: dup
      38: iconst_1
      39: iconst_0
      40: bastore
      41: dup
      42: iconst_2
      43: iconst_1
      44: bastore
      45: iconst_3
      46: newarray       byte
      48: dup
      49: iconst_0
      50: iconst_0
      51: bastore
      52: dup
      53: iconst_1
      54: iconst_1
      55: bastore
      56: dup
      57: iconst_2
      58: iconst_0
      59: bastore
      60: invokestatic  #3                  // Method org/apache/hadoop/hbase/filter/FuzzyRowFilter.satisfiesNoUnsafe:(Z[BII[B[B)Lorg/apache/hadoop/hbase/filter/FuzzyRowFilter$SatisfiesCode;
      63: invokestatic  #4                  // Method org/junit/Assert.assertEquals:(Ljava/lang/Object;Ljava/lang/Object;)V
      66: getstatic     #5                  // Field org/apache/hadoop/hbase/filter/FuzzyRowFilter$SatisfiesCode.NEXT_EXISTS:Lorg/apache/hadoop/hbase/filter/FuzzyRowFilter$SatisfiesCode;
      69: iconst_0
      70: iconst_5
      71: newarray       byte
      73: dup
      74: iconst_0
      75: iconst_1
      76: bastore
      77: dup
      78: iconst_1
      79: bipush        -128
      81: bastore
      82: dup
      83: iconst_2
      84: iconst_2
      85: bastore
      86: dup
      87: iconst_3
      88: iconst_0
      89: bastore
      90: dup
      91: iconst_4
      92: iconst_1
      93: bastore
      94: iconst_0
      95: iconst_5
      96: iconst_3
      97: newarray       byte
      99: dup
     100: iconst_0
     101: iconst_1
     102: bastore
     103: dup
     104: iconst_1
     105: iconst_0
     106: bastore
     107: dup
     108: iconst_2
     109: iconst_1
     110: bastore
     111: iconst_3
     112: newarray       byte
     114: dup
     115: iconst_0
     116: iconst_0
     117: bastore
     118: dup
     119: iconst_1
     120: iconst_1
     121: bastore
     122: dup
     123: iconst_2
     124: iconst_0
     125: bastore
     126: invokestatic  #3                  // Method org/apache/hadoop/hbase/filter/FuzzyRowFilter.satisfiesNoUnsafe:(Z[BII[B[B)Lorg/apache/hadoop/hbase/filter/FuzzyRowFilter$SatisfiesCode;
     129: invokestatic  #4                  // Method org/junit/Assert.assertEquals:(Ljava/lang/Object;Ljava/lang/Object;)V
     132: getstatic     #2                  // Field org/apache/hadoop/hbase/filter/FuzzyRowFilter$SatisfiesCode.YES:Lorg/apache/hadoop/hbase/filter/FuzzyRowFilter$SatisfiesCode;
     135: iconst_0
     136: iconst_5
     137: newarray       byte
     139: dup
     140: iconst_0
     141: iconst_1
     142: bastore
     143: dup
     144: iconst_1
     145: iconst_2
     146: bastore
     147: dup
     148: iconst_2
     149: iconst_1
     150: bastore
     151: dup
     152: iconst_3
     153: iconst_3
     154: bastore
     155: dup
     156: iconst_4
     157: iconst_3
     158: bastore
     159: iconst_0
     160: iconst_5
     161: iconst_4
     162: newarray       byte
     164: dup
     165: iconst_0
     166: iconst_1
     167: bastore
     168: dup
     169: iconst_1
     170: iconst_2
     171: bastore
     172: dup
     173: iconst_2
     174: iconst_0
     175: bastore
     176: dup
     177: iconst_3
     178: iconst_3
     179: bastore
     180: iconst_4
     181: newarray       byte
     183: dup
     184: iconst_0
     185: iconst_0
     186: bastore
     187: dup
     188: iconst_1
     189: iconst_0
     190: bastore
     191: dup
     192: iconst_2
     193: iconst_1
     194: bastore
     195: dup
     196: iconst_3
     197: iconst_0
     198: bastore
     199: invokestatic  #3                  // Method org/apache/hadoop/hbase/filter/FuzzyRowFilter.satisfiesNoUnsafe:(Z[BII[B[B)Lorg/apache/hadoop/hbase/filter/FuzzyRowFilter$SatisfiesCode;
     202: invokestatic  #4                  // Method org/junit/Assert.assertEquals:(Ljava/lang/Object;Ljava/lang/Object;)V
     205: getstatic     #5                  // Field org/apache/hadoop/hbase/filter/FuzzyRowFilter$SatisfiesCode.NEXT_EXISTS:Lorg/apache/hadoop/hbase/filter/FuzzyRowFilter$SatisfiesCode;
     208: iconst_0
     209: iconst_5
     210: newarray       byte
     212: dup
     213: iconst_0
     214: iconst_1
     215: bastore
     216: dup
     217: iconst_1
     218: iconst_1
     219: bastore
     220: dup
     221: iconst_2
     222: iconst_1
     223: bastore
     224: dup
     225: iconst_3
     226: iconst_3
     227: bastore
     228: dup
     229: iconst_4
     230: iconst_0
     231: bastore
     232: iconst_0
     233: iconst_5
     234: iconst_4
     235: newarray       byte
     237: dup
     238: iconst_0
     239: iconst_1
     240: bastore
     241: dup
     242: iconst_1
     243: iconst_2
     244: bastore
     245: dup
     246: iconst_2
     247: iconst_0
     248: bastore
     249: dup
     250: iconst_3
     251: iconst_3
     252: bastore
     253: iconst_4
     254: newarray       byte
     256: dup
     257: iconst_0
     258: iconst_0
     259: bastore
     260: dup
     261: iconst_1
     262: iconst_0
     263: bastore
     264: dup
     265: iconst_2
     266: iconst_1
     267: bastore
     268: dup
     269: iconst_3
     270: iconst_0
     271: bastore
     272: invokestatic  #3                  // Method org/apache/hadoop/hbase/filter/FuzzyRowFilter.satisfiesNoUnsafe:(Z[BII[B[B)Lorg/apache/hadoop/hbase/filter/FuzzyRowFilter$SatisfiesCode;
     275: invokestatic  #4                  // Method org/junit/Assert.assertEquals:(Ljava/lang/Object;Ljava/lang/Object;)V
     278: getstatic     #5                  // Field org/apache/hadoop/hbase/filter/FuzzyRowFilter$SatisfiesCode.NEXT_EXISTS:Lorg/apache/hadoop/hbase/filter/FuzzyRowFilter$SatisfiesCode;
     281: iconst_0
     282: iconst_5
     283: newarray       byte
     285: dup
     286: iconst_0
     287: iconst_1
     288: bastore
     289: dup
     290: iconst_1
     291: iconst_1
     292: bastore
     293: dup
     294: iconst_2
     295: iconst_1
     296: bastore
     297: dup
     298: iconst_3
     299: iconst_3
     300: bastore
     301: dup
     302: iconst_4
     303: iconst_0
     304: bastore
     305: iconst_0
     306: iconst_5
     307: iconst_4
     308: newarray       byte
     310: dup
     311: iconst_0
     312: iconst_1
     313: bastore
     314: dup
     315: iconst_1
     316: bipush        -11
     318: bastore
     319: dup
     320: iconst_2
     321: iconst_0
     322: bastore
     323: dup
     324: iconst_3
     325: iconst_3
     326: bastore
     327: iconst_4
     328: newarray       byte
     330: dup
     331: iconst_0
     332: iconst_0
     333: bastore
     334: dup
     335: iconst_1
     336: iconst_0
     337: bastore
     338: dup
     339: iconst_2
     340: iconst_1
     341: bastore
     342: dup
     343: iconst_3
     344: iconst_0
     345: bastore
     346: invokestatic  #3                  // Method org/apache/hadoop/hbase/filter/FuzzyRowFilter.satisfiesNoUnsafe:(Z[BII[B[B)Lorg/apache/hadoop/hbase/filter/FuzzyRowFilter$SatisfiesCode;
     349: invokestatic  #4                  // Method org/junit/Assert.assertEquals:(Ljava/lang/Object;Ljava/lang/Object;)V
     352: getstatic     #5                  // Field org/apache/hadoop/hbase/filter/FuzzyRowFilter$SatisfiesCode.NEXT_EXISTS:Lorg/apache/hadoop/hbase/filter/FuzzyRowFilter$SatisfiesCode;
     355: iconst_0
     356: iconst_5
     357: newarray       byte
     359: dup
     360: iconst_0
     361: iconst_1
     362: bastore
     363: dup
     364: iconst_1
     365: iconst_2
     366: bastore
     367: dup
     368: iconst_2
     369: iconst_1
     370: bastore
     371: dup
     372: iconst_3
     373: iconst_0
     374: bastore
     375: dup
     376: iconst_4
     377: iconst_1
     378: bastore
     379: iconst_0
     380: iconst_5
     381: iconst_3
     382: newarray       byte
     384: dup
     385: iconst_0
     386: iconst_0
     387: bastore
     388: dup
     389: iconst_1
     390: iconst_1
     391: bastore
     392: dup
     393: iconst_2
     394: iconst_2
     395: bastore
     396: iconst_3
     397: newarray       byte
     399: dup
     400: iconst_0
     401: iconst_1
     402: bastore
     403: dup
     404: iconst_1
     405: iconst_0
     406: bastore
     407: dup
     408: iconst_2
     409: iconst_0
     410: bastore
     411: invokestatic  #3                  // Method org/apache/hadoop/hbase/filter/FuzzyRowFilter.satisfiesNoUnsafe:(Z[BII[B[B)Lorg/apache/hadoop/hbase/filter/FuzzyRowFilter$SatisfiesCode;
     414: invokestatic  #4                  // Method org/junit/Assert.assertEquals:(Ljava/lang/Object;Ljava/lang/Object;)V
     417: return

  public void testSatisfiesForward();
    Code:
       0: getstatic     #2                  // Field org/apache/hadoop/hbase/filter/FuzzyRowFilter$SatisfiesCode.YES:Lorg/apache/hadoop/hbase/filter/FuzzyRowFilter$SatisfiesCode;
       3: iconst_0
       4: iconst_5
       5: newarray       byte
       7: dup
       8: iconst_0
       9: iconst_1
      10: bastore
      11: dup
      12: iconst_1
      13: bipush        -128
      15: bastore
      16: dup
      17: iconst_2
      18: iconst_1
      19: bastore
      20: dup
      21: iconst_3
      22: iconst_0
      23: bastore
      24: dup
      25: iconst_4
      26: iconst_1
      27: bastore
      28: iconst_3
      29: newarray       byte
      31: dup
      32: iconst_0
      33: iconst_1
      34: bastore
      35: dup
      36: iconst_1
      37: iconst_0
      38: bastore
      39: dup
      40: iconst_2
      41: iconst_1
      42: bastore
      43: iconst_3
      44: newarray       byte
      46: dup
      47: iconst_0
      48: iconst_m1
      49: bastore
      50: dup
      51: iconst_1
      52: iconst_0
      53: bastore
      54: dup
      55: iconst_2
      56: iconst_m1
      57: bastore
      58: invokestatic  #6                  // Method org/apache/hadoop/hbase/filter/FuzzyRowFilter.satisfies:(Z[B[B[B)Lorg/apache/hadoop/hbase/filter/FuzzyRowFilter$SatisfiesCode;
      61: invokestatic  #4                  // Method org/junit/Assert.assertEquals:(Ljava/lang/Object;Ljava/lang/Object;)V
      64: getstatic     #5                  // Field org/apache/hadoop/hbase/filter/FuzzyRowFilter$SatisfiesCode.NEXT_EXISTS:Lorg/apache/hadoop/hbase/filter/FuzzyRowFilter$SatisfiesCode;
      67: iconst_0
      68: iconst_5
      69: newarray       byte
      71: dup
      72: iconst_0
      73: iconst_1
      74: bastore
      75: dup
      76: iconst_1
      77: bipush        -128
      79: bastore
      80: dup
      81: iconst_2
      82: iconst_2
      83: bastore
      84: dup
      85: iconst_3
      86: iconst_0
      87: bastore
      88: dup
      89: iconst_4
      90: iconst_1
      91: bastore
      92: iconst_3
      93: newarray       byte
      95: dup
      96: iconst_0
      97: iconst_1
      98: bastore
      99: dup
     100: iconst_1
     101: iconst_0
     102: bastore
     103: dup
     104: iconst_2
     105: iconst_1
     106: bastore
     107: iconst_3
     108: newarray       byte
     110: dup
     111: iconst_0
     112: iconst_m1
     113: bastore
     114: dup
     115: iconst_1
     116: iconst_0
     117: bastore
     118: dup
     119: iconst_2
     120: iconst_m1
     121: bastore
     122: invokestatic  #6                  // Method org/apache/hadoop/hbase/filter/FuzzyRowFilter.satisfies:(Z[B[B[B)Lorg/apache/hadoop/hbase/filter/FuzzyRowFilter$SatisfiesCode;
     125: invokestatic  #4                  // Method org/junit/Assert.assertEquals:(Ljava/lang/Object;Ljava/lang/Object;)V
     128: getstatic     #2                  // Field org/apache/hadoop/hbase/filter/FuzzyRowFilter$SatisfiesCode.YES:Lorg/apache/hadoop/hbase/filter/FuzzyRowFilter$SatisfiesCode;
     131: iconst_0
     132: iconst_5
     133: newarray       byte
     135: dup
     136: iconst_0
     137: iconst_1
     138: bastore
     139: dup
     140: iconst_1
     141: iconst_2
     142: bastore
     143: dup
     144: iconst_2
     145: iconst_1
     146: bastore
     147: dup
     148: iconst_3
     149: iconst_3
     150: bastore
     151: dup
     152: iconst_4
     153: iconst_3
     154: bastore
     155: iconst_4
     156: newarray       byte
     158: dup
     159: iconst_0
     160: iconst_1
     161: bastore
     162: dup
     163: iconst_1
     164: iconst_2
     165: bastore
     166: dup
     167: iconst_2
     168: iconst_0
     169: bastore
     170: dup
     171: iconst_3
     172: iconst_3
     173: bastore
     174: iconst_4
     175: newarray       byte
     177: dup
     178: iconst_0
     179: iconst_m1
     180: bastore
     181: dup
     182: iconst_1
     183: iconst_m1
     184: bastore
     185: dup
     186: iconst_2
     187: iconst_0
     188: bastore
     189: dup
     190: iconst_3
     191: iconst_m1
     192: bastore
     193: invokestatic  #6                  // Method org/apache/hadoop/hbase/filter/FuzzyRowFilter.satisfies:(Z[B[B[B)Lorg/apache/hadoop/hbase/filter/FuzzyRowFilter$SatisfiesCode;
     196: invokestatic  #4                  // Method org/junit/Assert.assertEquals:(Ljava/lang/Object;Ljava/lang/Object;)V
     199: getstatic     #5                  // Field org/apache/hadoop/hbase/filter/FuzzyRowFilter$SatisfiesCode.NEXT_EXISTS:Lorg/apache/hadoop/hbase/filter/FuzzyRowFilter$SatisfiesCode;
     202: iconst_0
     203: iconst_5
     204: newarray       byte
     206: dup
     207: iconst_0
     208: iconst_1
     209: bastore
     210: dup
     211: iconst_1
     212: iconst_1
     213: bastore
     214: dup
     215: iconst_2
     216: iconst_1
     217: bastore
     218: dup
     219: iconst_3
     220: iconst_3
     221: bastore
     222: dup
     223: iconst_4
     224: iconst_0
     225: bastore
     226: iconst_4
     227: newarray       byte
     229: dup
     230: iconst_0
     231: iconst_1
     232: bastore
     233: dup
     234: iconst_1
     235: iconst_2
     236: bastore
     237: dup
     238: iconst_2
     239: iconst_0
     240: bastore
     241: dup
     242: iconst_3
     243: iconst_3
     244: bastore
     245: iconst_4
     246: newarray       byte
     248: dup
     249: iconst_0
     250: iconst_m1
     251: bastore
     252: dup
     253: iconst_1
     254: iconst_m1
     255: bastore
     256: dup
     257: iconst_2
     258: iconst_0
     259: bastore
     260: dup
     261: iconst_3
     262: iconst_m1
     263: bastore
     264: invokestatic  #6                  // Method org/apache/hadoop/hbase/filter/FuzzyRowFilter.satisfies:(Z[B[B[B)Lorg/apache/hadoop/hbase/filter/FuzzyRowFilter$SatisfiesCode;
     267: invokestatic  #4                  // Method org/junit/Assert.assertEquals:(Ljava/lang/Object;Ljava/lang/Object;)V
     270: getstatic     #5                  // Field org/apache/hadoop/hbase/filter/FuzzyRowFilter$SatisfiesCode.NEXT_EXISTS:Lorg/apache/hadoop/hbase/filter/FuzzyRowFilter$SatisfiesCode;
     273: iconst_0
     274: iconst_5
     275: newarray       byte
     277: dup
     278: iconst_0
     279: iconst_1
     280: bastore
     281: dup
     282: iconst_1
     283: iconst_1
     284: bastore
     285: dup
     286: iconst_2
     287: iconst_1
     288: bastore
     289: dup
     290: iconst_3
     291: iconst_3
     292: bastore
     293: dup
     294: iconst_4
     295: iconst_0
     296: bastore
     297: iconst_4
     298: newarray       byte
     300: dup
     301: iconst_0
     302: iconst_1
     303: bastore
     304: dup
     305: iconst_1
     306: bipush        -11
     308: bastore
     309: dup
     310: iconst_2
     311: iconst_0
     312: bastore
     313: dup
     314: iconst_3
     315: iconst_3
     316: bastore
     317: iconst_4
     318: newarray       byte
     320: dup
     321: iconst_0
     322: iconst_m1
     323: bastore
     324: dup
     325: iconst_1
     326: iconst_m1
     327: bastore
     328: dup
     329: iconst_2
     330: iconst_0
     331: bastore
     332: dup
     333: iconst_3
     334: iconst_m1
     335: bastore
     336: invokestatic  #6                  // Method org/apache/hadoop/hbase/filter/FuzzyRowFilter.satisfies:(Z[B[B[B)Lorg/apache/hadoop/hbase/filter/FuzzyRowFilter$SatisfiesCode;
     339: invokestatic  #4                  // Method org/junit/Assert.assertEquals:(Ljava/lang/Object;Ljava/lang/Object;)V
     342: getstatic     #5                  // Field org/apache/hadoop/hbase/filter/FuzzyRowFilter$SatisfiesCode.NEXT_EXISTS:Lorg/apache/hadoop/hbase/filter/FuzzyRowFilter$SatisfiesCode;
     345: iconst_0
     346: iconst_5
     347: newarray       byte
     349: dup
     350: iconst_0
     351: iconst_1
     352: bastore
     353: dup
     354: iconst_1
     355: iconst_2
     356: bastore
     357: dup
     358: iconst_2
     359: iconst_1
     360: bastore
     361: dup
     362: iconst_3
     363: iconst_0
     364: bastore
     365: dup
     366: iconst_4
     367: iconst_1
     368: bastore
     369: iconst_3
     370: newarray       byte
     372: dup
     373: iconst_0
     374: iconst_0
     375: bastore
     376: dup
     377: iconst_1
     378: iconst_1
     379: bastore
     380: dup
     381: iconst_2
     382: iconst_2
     383: bastore
     384: iconst_3
     385: newarray       byte
     387: dup
     388: iconst_0
     389: iconst_0
     390: bastore
     391: dup
     392: iconst_1
     393: iconst_m1
     394: bastore
     395: dup
     396: iconst_2
     397: iconst_m1
     398: bastore
     399: invokestatic  #6                  // Method org/apache/hadoop/hbase/filter/FuzzyRowFilter.satisfies:(Z[B[B[B)Lorg/apache/hadoop/hbase/filter/FuzzyRowFilter$SatisfiesCode;
     402: invokestatic  #4                  // Method org/junit/Assert.assertEquals:(Ljava/lang/Object;Ljava/lang/Object;)V
     405: return

  public void testSatisfiesReverse();
    Code:
       0: getstatic     #2                  // Field org/apache/hadoop/hbase/filter/FuzzyRowFilter$SatisfiesCode.YES:Lorg/apache/hadoop/hbase/filter/FuzzyRowFilter$SatisfiesCode;
       3: iconst_1
       4: iconst_5
       5: newarray       byte
       7: dup
       8: iconst_0
       9: iconst_1
      10: bastore
      11: dup
      12: iconst_1
      13: bipush        -128
      15: bastore
      16: dup
      17: iconst_2
      18: iconst_1
      19: bastore
      20: dup
      21: iconst_3
      22: iconst_0
      23: bastore
      24: dup
      25: iconst_4
      26: iconst_1
      27: bastore
      28: iconst_3
      29: newarray       byte
      31: dup
      32: iconst_0
      33: iconst_1
      34: bastore
      35: dup
      36: iconst_1
      37: iconst_0
      38: bastore
      39: dup
      40: iconst_2
      41: iconst_1
      42: bastore
      43: iconst_3
      44: newarray       byte
      46: dup
      47: iconst_0
      48: iconst_m1
      49: bastore
      50: dup
      51: iconst_1
      52: iconst_0
      53: bastore
      54: dup
      55: iconst_2
      56: iconst_m1
      57: bastore
      58: invokestatic  #6                  // Method org/apache/hadoop/hbase/filter/FuzzyRowFilter.satisfies:(Z[B[B[B)Lorg/apache/hadoop/hbase/filter/FuzzyRowFilter$SatisfiesCode;
      61: invokestatic  #4                  // Method org/junit/Assert.assertEquals:(Ljava/lang/Object;Ljava/lang/Object;)V
      64: getstatic     #5                  // Field org/apache/hadoop/hbase/filter/FuzzyRowFilter$SatisfiesCode.NEXT_EXISTS:Lorg/apache/hadoop/hbase/filter/FuzzyRowFilter$SatisfiesCode;
      67: iconst_1
      68: iconst_5
      69: newarray       byte
      71: dup
      72: iconst_0
      73: iconst_1
      74: bastore
      75: dup
      76: iconst_1
      77: bipush        -128
      79: bastore
      80: dup
      81: iconst_2
      82: iconst_2
      83: bastore
      84: dup
      85: iconst_3
      86: iconst_0
      87: bastore
      88: dup
      89: iconst_4
      90: iconst_1
      91: bastore
      92: iconst_3
      93: newarray       byte
      95: dup
      96: iconst_0
      97: iconst_1
      98: bastore
      99: dup
     100: iconst_1
     101: iconst_0
     102: bastore
     103: dup
     104: iconst_2
     105: iconst_1
     106: bastore
     107: iconst_3
     108: newarray       byte
     110: dup
     111: iconst_0
     112: iconst_m1
     113: bastore
     114: dup
     115: iconst_1
     116: iconst_0
     117: bastore
     118: dup
     119: iconst_2
     120: iconst_m1
     121: bastore
     122: invokestatic  #6                  // Method org/apache/hadoop/hbase/filter/FuzzyRowFilter.satisfies:(Z[B[B[B)Lorg/apache/hadoop/hbase/filter/FuzzyRowFilter$SatisfiesCode;
     125: invokestatic  #4                  // Method org/junit/Assert.assertEquals:(Ljava/lang/Object;Ljava/lang/Object;)V
     128: getstatic     #5                  // Field org/apache/hadoop/hbase/filter/FuzzyRowFilter$SatisfiesCode.NEXT_EXISTS:Lorg/apache/hadoop/hbase/filter/FuzzyRowFilter$SatisfiesCode;
     131: iconst_1
     132: iconst_5
     133: newarray       byte
     135: dup
     136: iconst_0
     137: iconst_2
     138: bastore
     139: dup
     140: iconst_1
     141: iconst_3
     142: bastore
     143: dup
     144: iconst_2
     145: iconst_1
     146: bastore
     147: dup
     148: iconst_3
     149: iconst_1
     150: bastore
     151: dup
     152: iconst_4
     153: iconst_1
     154: bastore
     155: iconst_3
     156: newarray       byte
     158: dup
     159: iconst_0
     160: iconst_1
     161: bastore
     162: dup
     163: iconst_1
     164: iconst_0
     165: bastore
     166: dup
     167: iconst_2
     168: iconst_1
     169: bastore
     170: iconst_3
     171: newarray       byte
     173: dup
     174: iconst_0
     175: iconst_m1
     176: bastore
     177: dup
     178: iconst_1
     179: iconst_0
     180: bastore
     181: dup
     182: iconst_2
     183: iconst_m1
     184: bastore
     185: invokestatic  #6                  // Method org/apache/hadoop/hbase/filter/FuzzyRowFilter.satisfies:(Z[B[B[B)Lorg/apache/hadoop/hbase/filter/FuzzyRowFilter$SatisfiesCode;
     188: invokestatic  #4                  // Method org/junit/Assert.assertEquals:(Ljava/lang/Object;Ljava/lang/Object;)V
     191: getstatic     #2                  // Field org/apache/hadoop/hbase/filter/FuzzyRowFilter$SatisfiesCode.YES:Lorg/apache/hadoop/hbase/filter/FuzzyRowFilter$SatisfiesCode;
     194: iconst_1
     195: iconst_5
     196: newarray       byte
     198: dup
     199: iconst_0
     200: iconst_1
     201: bastore
     202: dup
     203: iconst_1
     204: iconst_2
     205: bastore
     206: dup
     207: iconst_2
     208: iconst_1
     209: bastore
     210: dup
     211: iconst_3
     212: iconst_3
     213: bastore
     214: dup
     215: iconst_4
     216: iconst_3
     217: bastore
     218: iconst_4
     219: newarray       byte
     221: dup
     222: iconst_0
     223: iconst_1
     224: bastore
     225: dup
     226: iconst_1
     227: iconst_2
     228: bastore
     229: dup
     230: iconst_2
     231: iconst_0
     232: bastore
     233: dup
     234: iconst_3
     235: iconst_3
     236: bastore
     237: iconst_4
     238: newarray       byte
     240: dup
     241: iconst_0
     242: iconst_m1
     243: bastore
     244: dup
     245: iconst_1
     246: iconst_m1
     247: bastore
     248: dup
     249: iconst_2
     250: iconst_0
     251: bastore
     252: dup
     253: iconst_3
     254: iconst_m1
     255: bastore
     256: invokestatic  #6                  // Method org/apache/hadoop/hbase/filter/FuzzyRowFilter.satisfies:(Z[B[B[B)Lorg/apache/hadoop/hbase/filter/FuzzyRowFilter$SatisfiesCode;
     259: invokestatic  #4                  // Method org/junit/Assert.assertEquals:(Ljava/lang/Object;Ljava/lang/Object;)V
     262: getstatic     #5                  // Field org/apache/hadoop/hbase/filter/FuzzyRowFilter$SatisfiesCode.NEXT_EXISTS:Lorg/apache/hadoop/hbase/filter/FuzzyRowFilter$SatisfiesCode;
     265: iconst_1
     266: iconst_5
     267: newarray       byte
     269: dup
     270: iconst_0
     271: iconst_1
     272: bastore
     273: dup
     274: iconst_1
     275: bipush        -11
     277: bastore
     278: dup
     279: iconst_2
     280: iconst_1
     281: bastore
     282: dup
     283: iconst_3
     284: iconst_3
     285: bastore
     286: dup
     287: iconst_4
     288: iconst_0
     289: bastore
     290: iconst_4
     291: newarray       byte
     293: dup
     294: iconst_0
     295: iconst_1
     296: bastore
     297: dup
     298: iconst_1
     299: iconst_1
     300: bastore
     301: dup
     302: iconst_2
     303: iconst_0
     304: bastore
     305: dup
     306: iconst_3
     307: iconst_3
     308: bastore
     309: iconst_4
     310: newarray       byte
     312: dup
     313: iconst_0
     314: iconst_m1
     315: bastore
     316: dup
     317: iconst_1
     318: iconst_m1
     319: bastore
     320: dup
     321: iconst_2
     322: iconst_0
     323: bastore
     324: dup
     325: iconst_3
     326: iconst_m1
     327: bastore
     328: invokestatic  #6                  // Method org/apache/hadoop/hbase/filter/FuzzyRowFilter.satisfies:(Z[B[B[B)Lorg/apache/hadoop/hbase/filter/FuzzyRowFilter$SatisfiesCode;
     331: invokestatic  #4                  // Method org/junit/Assert.assertEquals:(Ljava/lang/Object;Ljava/lang/Object;)V
     334: getstatic     #5                  // Field org/apache/hadoop/hbase/filter/FuzzyRowFilter$SatisfiesCode.NEXT_EXISTS:Lorg/apache/hadoop/hbase/filter/FuzzyRowFilter$SatisfiesCode;
     337: iconst_1
     338: iconst_5
     339: newarray       byte
     341: dup
     342: iconst_0
     343: iconst_1
     344: bastore
     345: dup
     346: iconst_1
     347: iconst_3
     348: bastore
     349: dup
     350: iconst_2
     351: iconst_1
     352: bastore
     353: dup
     354: iconst_3
     355: iconst_3
     356: bastore
     357: dup
     358: iconst_4
     359: iconst_0
     360: bastore
     361: iconst_4
     362: newarray       byte
     364: dup
     365: iconst_0
     366: iconst_1
     367: bastore
     368: dup
     369: iconst_1
     370: iconst_2
     371: bastore
     372: dup
     373: iconst_2
     374: iconst_0
     375: bastore
     376: dup
     377: iconst_3
     378: iconst_3
     379: bastore
     380: iconst_4
     381: newarray       byte
     383: dup
     384: iconst_0
     385: iconst_m1
     386: bastore
     387: dup
     388: iconst_1
     389: iconst_m1
     390: bastore
     391: dup
     392: iconst_2
     393: iconst_0
     394: bastore
     395: dup
     396: iconst_3
     397: iconst_m1
     398: bastore
     399: invokestatic  #6                  // Method org/apache/hadoop/hbase/filter/FuzzyRowFilter.satisfies:(Z[B[B[B)Lorg/apache/hadoop/hbase/filter/FuzzyRowFilter$SatisfiesCode;
     402: invokestatic  #4                  // Method org/junit/Assert.assertEquals:(Ljava/lang/Object;Ljava/lang/Object;)V
     405: getstatic     #5                  // Field org/apache/hadoop/hbase/filter/FuzzyRowFilter$SatisfiesCode.NEXT_EXISTS:Lorg/apache/hadoop/hbase/filter/FuzzyRowFilter$SatisfiesCode;
     408: iconst_1
     409: iconst_5
     410: newarray       byte
     412: dup
     413: iconst_0
     414: iconst_2
     415: bastore
     416: dup
     417: iconst_1
     418: iconst_1
     419: bastore
     420: dup
     421: iconst_2
     422: iconst_1
     423: bastore
     424: dup
     425: iconst_3
     426: iconst_1
     427: bastore
     428: dup
     429: iconst_4
     430: iconst_0
     431: bastore
     432: iconst_4
     433: newarray       byte
     435: dup
     436: iconst_0
     437: iconst_1
     438: bastore
     439: dup
     440: iconst_1
     441: iconst_2
     442: bastore
     443: dup
     444: iconst_2
     445: iconst_0
     446: bastore
     447: dup
     448: iconst_3
     449: iconst_3
     450: bastore
     451: iconst_4
     452: newarray       byte
     454: dup
     455: iconst_0
     456: iconst_m1
     457: bastore
     458: dup
     459: iconst_1
     460: iconst_m1
     461: bastore
     462: dup
     463: iconst_2
     464: iconst_0
     465: bastore
     466: dup
     467: iconst_3
     468: iconst_m1
     469: bastore
     470: invokestatic  #6                  // Method org/apache/hadoop/hbase/filter/FuzzyRowFilter.satisfies:(Z[B[B[B)Lorg/apache/hadoop/hbase/filter/FuzzyRowFilter$SatisfiesCode;
     473: invokestatic  #4                  // Method org/junit/Assert.assertEquals:(Ljava/lang/Object;Ljava/lang/Object;)V
     476: getstatic     #5                  // Field org/apache/hadoop/hbase/filter/FuzzyRowFilter$SatisfiesCode.NEXT_EXISTS:Lorg/apache/hadoop/hbase/filter/FuzzyRowFilter$SatisfiesCode;
     479: iconst_1
     480: iconst_5
     481: newarray       byte
     483: dup
     484: iconst_0
     485: iconst_1
     486: bastore
     487: dup
     488: iconst_1
     489: iconst_2
     490: bastore
     491: dup
     492: iconst_2
     493: iconst_1
     494: bastore
     495: dup
     496: iconst_3
     497: iconst_0
     498: bastore
     499: dup
     500: iconst_4
     501: iconst_1
     502: bastore
     503: iconst_3
     504: newarray       byte
     506: dup
     507: iconst_0
     508: iconst_0
     509: bastore
     510: dup
     511: iconst_1
     512: iconst_1
     513: bastore
     514: dup
     515: iconst_2
     516: iconst_2
     517: bastore
     518: iconst_3
     519: newarray       byte
     521: dup
     522: iconst_0
     523: iconst_0
     524: bastore
     525: dup
     526: iconst_1
     527: iconst_m1
     528: bastore
     529: dup
     530: iconst_2
     531: iconst_m1
     532: bastore
     533: invokestatic  #6                  // Method org/apache/hadoop/hbase/filter/FuzzyRowFilter.satisfies:(Z[B[B[B)Lorg/apache/hadoop/hbase/filter/FuzzyRowFilter$SatisfiesCode;
     536: invokestatic  #4                  // Method org/junit/Assert.assertEquals:(Ljava/lang/Object;Ljava/lang/Object;)V
     539: return

  public void testSatisfiesNoUnsafeReverse();
    Code:
       0: getstatic     #2                  // Field org/apache/hadoop/hbase/filter/FuzzyRowFilter$SatisfiesCode.YES:Lorg/apache/hadoop/hbase/filter/FuzzyRowFilter$SatisfiesCode;
       3: iconst_1
       4: iconst_5
       5: newarray       byte
       7: dup
       8: iconst_0
       9: iconst_1
      10: bastore
      11: dup
      12: iconst_1
      13: bipush        -128
      15: bastore
      16: dup
      17: iconst_2
      18: iconst_1
      19: bastore
      20: dup
      21: iconst_3
      22: iconst_0
      23: bastore
      24: dup
      25: iconst_4
      26: iconst_1
      27: bastore
      28: iconst_0
      29: iconst_5
      30: iconst_3
      31: newarray       byte
      33: dup
      34: iconst_0
      35: iconst_1
      36: bastore
      37: dup
      38: iconst_1
      39: iconst_0
      40: bastore
      41: dup
      42: iconst_2
      43: iconst_1
      44: bastore
      45: iconst_3
      46: newarray       byte
      48: dup
      49: iconst_0
      50: iconst_0
      51: bastore
      52: dup
      53: iconst_1
      54: iconst_1
      55: bastore
      56: dup
      57: iconst_2
      58: iconst_0
      59: bastore
      60: invokestatic  #3                  // Method org/apache/hadoop/hbase/filter/FuzzyRowFilter.satisfiesNoUnsafe:(Z[BII[B[B)Lorg/apache/hadoop/hbase/filter/FuzzyRowFilter$SatisfiesCode;
      63: invokestatic  #4                  // Method org/junit/Assert.assertEquals:(Ljava/lang/Object;Ljava/lang/Object;)V
      66: getstatic     #5                  // Field org/apache/hadoop/hbase/filter/FuzzyRowFilter$SatisfiesCode.NEXT_EXISTS:Lorg/apache/hadoop/hbase/filter/FuzzyRowFilter$SatisfiesCode;
      69: iconst_1
      70: iconst_5
      71: newarray       byte
      73: dup
      74: iconst_0
      75: iconst_1
      76: bastore
      77: dup
      78: iconst_1
      79: bipush        -128
      81: bastore
      82: dup
      83: iconst_2
      84: iconst_2
      85: bastore
      86: dup
      87: iconst_3
      88: iconst_0
      89: bastore
      90: dup
      91: iconst_4
      92: iconst_1
      93: bastore
      94: iconst_0
      95: iconst_5
      96: iconst_3
      97: newarray       byte
      99: dup
     100: iconst_0
     101: iconst_1
     102: bastore
     103: dup
     104: iconst_1
     105: iconst_0
     106: bastore
     107: dup
     108: iconst_2
     109: iconst_1
     110: bastore
     111: iconst_3
     112: newarray       byte
     114: dup
     115: iconst_0
     116: iconst_0
     117: bastore
     118: dup
     119: iconst_1
     120: iconst_1
     121: bastore
     122: dup
     123: iconst_2
     124: iconst_0
     125: bastore
     126: invokestatic  #3                  // Method org/apache/hadoop/hbase/filter/FuzzyRowFilter.satisfiesNoUnsafe:(Z[BII[B[B)Lorg/apache/hadoop/hbase/filter/FuzzyRowFilter$SatisfiesCode;
     129: invokestatic  #4                  // Method org/junit/Assert.assertEquals:(Ljava/lang/Object;Ljava/lang/Object;)V
     132: getstatic     #5                  // Field org/apache/hadoop/hbase/filter/FuzzyRowFilter$SatisfiesCode.NEXT_EXISTS:Lorg/apache/hadoop/hbase/filter/FuzzyRowFilter$SatisfiesCode;
     135: iconst_1
     136: iconst_5
     137: newarray       byte
     139: dup
     140: iconst_0
     141: iconst_2
     142: bastore
     143: dup
     144: iconst_1
     145: iconst_3
     146: bastore
     147: dup
     148: iconst_2
     149: iconst_1
     150: bastore
     151: dup
     152: iconst_3
     153: iconst_1
     154: bastore
     155: dup
     156: iconst_4
     157: iconst_1
     158: bastore
     159: iconst_0
     160: iconst_5
     161: iconst_3
     162: newarray       byte
     164: dup
     165: iconst_0
     166: iconst_1
     167: bastore
     168: dup
     169: iconst_1
     170: iconst_0
     171: bastore
     172: dup
     173: iconst_2
     174: iconst_1
     175: bastore
     176: iconst_3
     177: newarray       byte
     179: dup
     180: iconst_0
     181: iconst_0
     182: bastore
     183: dup
     184: iconst_1
     185: iconst_1
     186: bastore
     187: dup
     188: iconst_2
     189: iconst_0
     190: bastore
     191: invokestatic  #3                  // Method org/apache/hadoop/hbase/filter/FuzzyRowFilter.satisfiesNoUnsafe:(Z[BII[B[B)Lorg/apache/hadoop/hbase/filter/FuzzyRowFilter$SatisfiesCode;
     194: invokestatic  #4                  // Method org/junit/Assert.assertEquals:(Ljava/lang/Object;Ljava/lang/Object;)V
     197: getstatic     #2                  // Field org/apache/hadoop/hbase/filter/FuzzyRowFilter$SatisfiesCode.YES:Lorg/apache/hadoop/hbase/filter/FuzzyRowFilter$SatisfiesCode;
     200: iconst_1
     201: iconst_5
     202: newarray       byte
     204: dup
     205: iconst_0
     206: iconst_1
     207: bastore
     208: dup
     209: iconst_1
     210: iconst_2
     211: bastore
     212: dup
     213: iconst_2
     214: iconst_1
     215: bastore
     216: dup
     217: iconst_3
     218: iconst_3
     219: bastore
     220: dup
     221: iconst_4
     222: iconst_3
     223: bastore
     224: iconst_0
     225: iconst_5
     226: iconst_4
     227: newarray       byte
     229: dup
     230: iconst_0
     231: iconst_1
     232: bastore
     233: dup
     234: iconst_1
     235: iconst_2
     236: bastore
     237: dup
     238: iconst_2
     239: iconst_0
     240: bastore
     241: dup
     242: iconst_3
     243: iconst_3
     244: bastore
     245: iconst_4
     246: newarray       byte
     248: dup
     249: iconst_0
     250: iconst_0
     251: bastore
     252: dup
     253: iconst_1
     254: iconst_0
     255: bastore
     256: dup
     257: iconst_2
     258: iconst_1
     259: bastore
     260: dup
     261: iconst_3
     262: iconst_0
     263: bastore
     264: invokestatic  #3                  // Method org/apache/hadoop/hbase/filter/FuzzyRowFilter.satisfiesNoUnsafe:(Z[BII[B[B)Lorg/apache/hadoop/hbase/filter/FuzzyRowFilter$SatisfiesCode;
     267: invokestatic  #4                  // Method org/junit/Assert.assertEquals:(Ljava/lang/Object;Ljava/lang/Object;)V
     270: getstatic     #5                  // Field org/apache/hadoop/hbase/filter/FuzzyRowFilter$SatisfiesCode.NEXT_EXISTS:Lorg/apache/hadoop/hbase/filter/FuzzyRowFilter$SatisfiesCode;
     273: iconst_1
     274: iconst_5
     275: newarray       byte
     277: dup
     278: iconst_0
     279: iconst_1
     280: bastore
     281: dup
     282: iconst_1
     283: bipush        -11
     285: bastore
     286: dup
     287: iconst_2
     288: iconst_1
     289: bastore
     290: dup
     291: iconst_3
     292: iconst_3
     293: bastore
     294: dup
     295: iconst_4
     296: iconst_0
     297: bastore
     298: iconst_0
     299: iconst_5
     300: iconst_4
     301: newarray       byte
     303: dup
     304: iconst_0
     305: iconst_1
     306: bastore
     307: dup
     308: iconst_1
     309: iconst_1
     310: bastore
     311: dup
     312: iconst_2
     313: iconst_0
     314: bastore
     315: dup
     316: iconst_3
     317: iconst_3
     318: bastore
     319: iconst_4
     320: newarray       byte
     322: dup
     323: iconst_0
     324: iconst_0
     325: bastore
     326: dup
     327: iconst_1
     328: iconst_0
     329: bastore
     330: dup
     331: iconst_2
     332: iconst_1
     333: bastore
     334: dup
     335: iconst_3
     336: iconst_0
     337: bastore
     338: invokestatic  #3                  // Method org/apache/hadoop/hbase/filter/FuzzyRowFilter.satisfiesNoUnsafe:(Z[BII[B[B)Lorg/apache/hadoop/hbase/filter/FuzzyRowFilter$SatisfiesCode;
     341: invokestatic  #4                  // Method org/junit/Assert.assertEquals:(Ljava/lang/Object;Ljava/lang/Object;)V
     344: getstatic     #5                  // Field org/apache/hadoop/hbase/filter/FuzzyRowFilter$SatisfiesCode.NEXT_EXISTS:Lorg/apache/hadoop/hbase/filter/FuzzyRowFilter$SatisfiesCode;
     347: iconst_1
     348: iconst_5
     349: newarray       byte
     351: dup
     352: iconst_0
     353: iconst_1
     354: bastore
     355: dup
     356: iconst_1
     357: iconst_3
     358: bastore
     359: dup
     360: iconst_2
     361: iconst_1
     362: bastore
     363: dup
     364: iconst_3
     365: iconst_3
     366: bastore
     367: dup
     368: iconst_4
     369: iconst_0
     370: bastore
     371: iconst_0
     372: iconst_5
     373: iconst_4
     374: newarray       byte
     376: dup
     377: iconst_0
     378: iconst_1
     379: bastore
     380: dup
     381: iconst_1
     382: iconst_2
     383: bastore
     384: dup
     385: iconst_2
     386: iconst_0
     387: bastore
     388: dup
     389: iconst_3
     390: iconst_3
     391: bastore
     392: iconst_4
     393: newarray       byte
     395: dup
     396: iconst_0
     397: iconst_0
     398: bastore
     399: dup
     400: iconst_1
     401: iconst_0
     402: bastore
     403: dup
     404: iconst_2
     405: iconst_1
     406: bastore
     407: dup
     408: iconst_3
     409: iconst_0
     410: bastore
     411: invokestatic  #3                  // Method org/apache/hadoop/hbase/filter/FuzzyRowFilter.satisfiesNoUnsafe:(Z[BII[B[B)Lorg/apache/hadoop/hbase/filter/FuzzyRowFilter$SatisfiesCode;
     414: invokestatic  #4                  // Method org/junit/Assert.assertEquals:(Ljava/lang/Object;Ljava/lang/Object;)V
     417: getstatic     #5                  // Field org/apache/hadoop/hbase/filter/FuzzyRowFilter$SatisfiesCode.NEXT_EXISTS:Lorg/apache/hadoop/hbase/filter/FuzzyRowFilter$SatisfiesCode;
     420: iconst_1
     421: iconst_5
     422: newarray       byte
     424: dup
     425: iconst_0
     426: iconst_2
     427: bastore
     428: dup
     429: iconst_1
     430: iconst_1
     431: bastore
     432: dup
     433: iconst_2
     434: iconst_1
     435: bastore
     436: dup
     437: iconst_3
     438: iconst_1
     439: bastore
     440: dup
     441: iconst_4
     442: iconst_0
     443: bastore
     444: iconst_0
     445: iconst_5
     446: iconst_4
     447: newarray       byte
     449: dup
     450: iconst_0
     451: iconst_1
     452: bastore
     453: dup
     454: iconst_1
     455: iconst_2
     456: bastore
     457: dup
     458: iconst_2
     459: iconst_0
     460: bastore
     461: dup
     462: iconst_3
     463: iconst_3
     464: bastore
     465: iconst_4
     466: newarray       byte
     468: dup
     469: iconst_0
     470: iconst_0
     471: bastore
     472: dup
     473: iconst_1
     474: iconst_0
     475: bastore
     476: dup
     477: iconst_2
     478: iconst_1
     479: bastore
     480: dup
     481: iconst_3
     482: iconst_0
     483: bastore
     484: invokestatic  #3                  // Method org/apache/hadoop/hbase/filter/FuzzyRowFilter.satisfiesNoUnsafe:(Z[BII[B[B)Lorg/apache/hadoop/hbase/filter/FuzzyRowFilter$SatisfiesCode;
     487: invokestatic  #4                  // Method org/junit/Assert.assertEquals:(Ljava/lang/Object;Ljava/lang/Object;)V
     490: getstatic     #5                  // Field org/apache/hadoop/hbase/filter/FuzzyRowFilter$SatisfiesCode.NEXT_EXISTS:Lorg/apache/hadoop/hbase/filter/FuzzyRowFilter$SatisfiesCode;
     493: iconst_1
     494: iconst_5
     495: newarray       byte
     497: dup
     498: iconst_0
     499: iconst_1
     500: bastore
     501: dup
     502: iconst_1
     503: iconst_2
     504: bastore
     505: dup
     506: iconst_2
     507: iconst_1
     508: bastore
     509: dup
     510: iconst_3
     511: iconst_0
     512: bastore
     513: dup
     514: iconst_4
     515: iconst_1
     516: bastore
     517: iconst_0
     518: iconst_5
     519: iconst_3
     520: newarray       byte
     522: dup
     523: iconst_0
     524: iconst_0
     525: bastore
     526: dup
     527: iconst_1
     528: iconst_1
     529: bastore
     530: dup
     531: iconst_2
     532: iconst_2
     533: bastore
     534: iconst_3
     535: newarray       byte
     537: dup
     538: iconst_0
     539: iconst_1
     540: bastore
     541: dup
     542: iconst_1
     543: iconst_0
     544: bastore
     545: dup
     546: iconst_2
     547: iconst_0
     548: bastore
     549: invokestatic  #3                  // Method org/apache/hadoop/hbase/filter/FuzzyRowFilter.satisfiesNoUnsafe:(Z[BII[B[B)Lorg/apache/hadoop/hbase/filter/FuzzyRowFilter$SatisfiesCode;
     552: invokestatic  #4                  // Method org/junit/Assert.assertEquals:(Ljava/lang/Object;Ljava/lang/Object;)V
     555: return

  public void testGetNextForFuzzyRuleForward();
    Code:
       0: iconst_0
       1: iconst_3
       2: newarray       byte
       4: dup
       5: iconst_0
       6: iconst_0
       7: bastore
       8: dup
       9: iconst_1
      10: iconst_1
      11: bastore
      12: dup
      13: iconst_2
      14: iconst_2
      15: bastore
      16: iconst_3
      17: newarray       byte
      19: dup
      20: iconst_0
      21: iconst_0
      22: bastore
      23: dup
      24: iconst_1
      25: iconst_m1
      26: bastore
      27: dup
      28: iconst_2
      29: iconst_m1
      30: bastore
      31: iconst_5
      32: newarray       byte
      34: dup
      35: iconst_0
      36: iconst_1
      37: bastore
      38: dup
      39: iconst_1
      40: iconst_2
      41: bastore
      42: dup
      43: iconst_2
      44: iconst_1
      45: bastore
      46: dup
      47: iconst_3
      48: iconst_0
      49: bastore
      50: dup
      51: iconst_4
      52: iconst_1
      53: bastore
      54: iconst_3
      55: newarray       byte
      57: dup
      58: iconst_0
      59: iconst_2
      60: bastore
      61: dup
      62: iconst_1
      63: iconst_1
      64: bastore
      65: dup
      66: iconst_2
      67: iconst_2
      68: bastore
      69: invokestatic  #7                  // Method assertNext:(Z[B[B[B[B)V
      72: iconst_0
      73: iconst_3
      74: newarray       byte
      76: dup
      77: iconst_0
      78: iconst_0
      79: bastore
      80: dup
      81: iconst_1
      82: iconst_1
      83: bastore
      84: dup
      85: iconst_2
      86: iconst_2
      87: bastore
      88: iconst_3
      89: newarray       byte
      91: dup
      92: iconst_0
      93: iconst_0
      94: bastore
      95: dup
      96: iconst_1
      97: iconst_m1
      98: bastore
      99: dup
     100: iconst_2
     101: iconst_m1
     102: bastore
     103: iconst_5
     104: newarray       byte
     106: dup
     107: iconst_0
     108: iconst_1
     109: bastore
     110: dup
     111: iconst_1
     112: iconst_1
     113: bastore
     114: dup
     115: iconst_2
     116: iconst_2
     117: bastore
     118: dup
     119: iconst_3
     120: iconst_0
     121: bastore
     122: dup
     123: iconst_4
     124: iconst_1
     125: bastore
     126: iconst_5
     127: newarray       byte
     129: dup
     130: iconst_0
     131: iconst_1
     132: bastore
     133: dup
     134: iconst_1
     135: iconst_1
     136: bastore
     137: dup
     138: iconst_2
     139: iconst_2
     140: bastore
     141: dup
     142: iconst_3
     143: iconst_0
     144: bastore
     145: dup
     146: iconst_4
     147: iconst_2
     148: bastore
     149: invokestatic  #7                  // Method assertNext:(Z[B[B[B[B)V
     152: iconst_0
     153: iconst_5
     154: newarray       byte
     156: dup
     157: iconst_0
     158: iconst_0
     159: bastore
     160: dup
     161: iconst_1
     162: iconst_1
     163: bastore
     164: dup
     165: iconst_2
     166: iconst_0
     167: bastore
     168: dup
     169: iconst_3
     170: iconst_2
     171: bastore
     172: dup
     173: iconst_4
     174: iconst_0
     175: bastore
     176: iconst_5
     177: newarray       byte
     179: dup
     180: iconst_0
     181: iconst_0
     182: bastore
     183: dup
     184: iconst_1
     185: iconst_m1
     186: bastore
     187: dup
     188: iconst_2
     189: iconst_0
     190: bastore
     191: dup
     192: iconst_3
     193: iconst_m1
     194: bastore
     195: dup
     196: iconst_4
     197: iconst_0
     198: bastore
     199: iconst_5
     200: newarray       byte
     202: dup
     203: iconst_0
     204: iconst_1
     205: bastore
     206: dup
     207: iconst_1
     208: iconst_0
     209: bastore
     210: dup
     211: iconst_2
     212: iconst_2
     213: bastore
     214: dup
     215: iconst_3
     216: iconst_0
     217: bastore
     218: dup
     219: iconst_4
     220: iconst_1
     221: bastore
     222: iconst_4
     223: newarray       byte
     225: dup
     226: iconst_0
     227: iconst_1
     228: bastore
     229: dup
     230: iconst_1
     231: iconst_1
     232: bastore
     233: dup
     234: iconst_2
     235: iconst_0
     236: bastore
     237: dup
     238: iconst_3
     239: iconst_2
     240: bastore
     241: invokestatic  #7                  // Method assertNext:(Z[B[B[B[B)V
     244: iconst_0
     245: iconst_3
     246: newarray       byte
     248: dup
     249: iconst_0
     250: iconst_1
     251: bastore
     252: dup
     253: iconst_1
     254: iconst_0
     255: bastore
     256: dup
     257: iconst_2
     258: iconst_1
     259: bastore
     260: iconst_3
     261: newarray       byte
     263: dup
     264: iconst_0
     265: iconst_m1
     266: bastore
     267: dup
     268: iconst_1
     269: iconst_0
     270: bastore
     271: dup
     272: iconst_2
     273: iconst_m1
     274: bastore
     275: iconst_5
     276: newarray       byte
     278: dup
     279: iconst_0
     280: iconst_1
     281: bastore
     282: dup
     283: iconst_1
     284: bipush        -128
     286: bastore
     287: dup
     288: iconst_2
     289: iconst_2
     290: bastore
     291: dup
     292: iconst_3
     293: iconst_0
     294: bastore
     295: dup
     296: iconst_4
     297: iconst_1
     298: bastore
     299: iconst_3
     300: newarray       byte
     302: dup
     303: iconst_0
     304: iconst_1
     305: bastore
     306: dup
     307: iconst_1
     308: bipush        -127
     310: bastore
     311: dup
     312: iconst_2
     313: iconst_1
     314: bastore
     315: invokestatic  #7                  // Method assertNext:(Z[B[B[B[B)V
     318: iconst_0
     319: iconst_4
     320: newarray       byte
     322: dup
     323: iconst_0
     324: iconst_0
     325: bastore
     326: dup
     327: iconst_1
     328: iconst_1
     329: bastore
     330: dup
     331: iconst_2
     332: iconst_0
     333: bastore
     334: dup
     335: iconst_3
     336: iconst_1
     337: bastore
     338: iconst_4
     339: newarray       byte
     341: dup
     342: iconst_0
     343: iconst_0
     344: bastore
     345: dup
     346: iconst_1
     347: iconst_m1
     348: bastore
     349: dup
     350: iconst_2
     351: iconst_0
     352: bastore
     353: dup
     354: iconst_3
     355: iconst_m1
     356: bastore
     357: iconst_4
     358: newarray       byte
     360: dup
     361: iconst_0
     362: iconst_5
     363: bastore
     364: dup
     365: iconst_1
     366: iconst_1
     367: bastore
     368: dup
     369: iconst_2
     370: iconst_0
     371: bastore
     372: dup
     373: iconst_3
     374: iconst_1
     375: bastore
     376: iconst_4
     377: newarray       byte
     379: dup
     380: iconst_0
     381: iconst_5
     382: bastore
     383: dup
     384: iconst_1
     385: iconst_1
     386: bastore
     387: dup
     388: iconst_2
     389: iconst_1
     390: bastore
     391: dup
     392: iconst_3
     393: iconst_1
     394: bastore
     395: invokestatic  #7                  // Method assertNext:(Z[B[B[B[B)V
     398: iconst_0
     399: iconst_4
     400: newarray       byte
     402: dup
     403: iconst_0
     404: iconst_0
     405: bastore
     406: dup
     407: iconst_1
     408: iconst_1
     409: bastore
     410: dup
     411: iconst_2
     412: iconst_0
     413: bastore
     414: dup
     415: iconst_3
     416: iconst_1
     417: bastore
     418: iconst_4
     419: newarray       byte
     421: dup
     422: iconst_0
     423: iconst_0
     424: bastore
     425: dup
     426: iconst_1
     427: iconst_m1
     428: bastore
     429: dup
     430: iconst_2
     431: iconst_0
     432: bastore
     433: dup
     434: iconst_3
     435: iconst_m1
     436: bastore
     437: iconst_5
     438: newarray       byte
     440: dup
     441: iconst_0
     442: iconst_5
     443: bastore
     444: dup
     445: iconst_1
     446: iconst_1
     447: bastore
     448: dup
     449: iconst_2
     450: iconst_0
     451: bastore
     452: dup
     453: iconst_3
     454: iconst_1
     455: bastore
     456: dup
     457: iconst_4
     458: iconst_1
     459: bastore
     460: iconst_5
     461: newarray       byte
     463: dup
     464: iconst_0
     465: iconst_5
     466: bastore
     467: dup
     468: iconst_1
     469: iconst_1
     470: bastore
     471: dup
     472: iconst_2
     473: iconst_0
     474: bastore
     475: dup
     476: iconst_3
     477: iconst_1
     478: bastore
     479: dup
     480: iconst_4
     481: iconst_2
     482: bastore
     483: invokestatic  #7                  // Method assertNext:(Z[B[B[B[B)V
     486: iconst_0
     487: iconst_4
     488: newarray       byte
     490: dup
     491: iconst_0
     492: iconst_0
     493: bastore
     494: dup
     495: iconst_1
     496: iconst_1
     497: bastore
     498: dup
     499: iconst_2
     500: iconst_0
     501: bastore
     502: dup
     503: iconst_3
     504: iconst_0
     505: bastore
     506: iconst_4
     507: newarray       byte
     509: dup
     510: iconst_0
     511: iconst_0
     512: bastore
     513: dup
     514: iconst_1
     515: iconst_m1
     516: bastore
     517: dup
     518: iconst_2
     519: iconst_0
     520: bastore
     521: dup
     522: iconst_3
     523: iconst_0
     524: bastore
     525: iconst_4
     526: newarray       byte
     528: dup
     529: iconst_0
     530: iconst_5
     531: bastore
     532: dup
     533: iconst_1
     534: iconst_1
     535: bastore
     536: dup
     537: iconst_2
     538: iconst_m1
     539: bastore
     540: dup
     541: iconst_3
     542: iconst_1
     543: bastore
     544: iconst_4
     545: newarray       byte
     547: dup
     548: iconst_0
     549: iconst_5
     550: bastore
     551: dup
     552: iconst_1
     553: iconst_1
     554: bastore
     555: dup
     556: iconst_2
     557: iconst_m1
     558: bastore
     559: dup
     560: iconst_3
     561: iconst_2
     562: bastore
     563: invokestatic  #7                  // Method assertNext:(Z[B[B[B[B)V
     566: iconst_0
     567: iconst_4
     568: newarray       byte
     570: dup
     571: iconst_0
     572: iconst_0
     573: bastore
     574: dup
     575: iconst_1
     576: iconst_1
     577: bastore
     578: dup
     579: iconst_2
     580: iconst_0
     581: bastore
     582: dup
     583: iconst_3
     584: iconst_1
     585: bastore
     586: iconst_4
     587: newarray       byte
     589: dup
     590: iconst_0
     591: iconst_0
     592: bastore
     593: dup
     594: iconst_1
     595: iconst_m1
     596: bastore
     597: dup
     598: iconst_2
     599: iconst_0
     600: bastore
     601: dup
     602: iconst_3
     603: iconst_m1
     604: bastore
     605: iconst_4
     606: newarray       byte
     608: dup
     609: iconst_0
     610: iconst_5
     611: bastore
     612: dup
     613: iconst_1
     614: iconst_1
     615: bastore
     616: dup
     617: iconst_2
     618: iconst_m1
     619: bastore
     620: dup
     621: iconst_3
     622: iconst_1
     623: bastore
     624: iconst_4
     625: newarray       byte
     627: dup
     628: iconst_0
     629: bipush        6
     631: bastore
     632: dup
     633: iconst_1
     634: iconst_1
     635: bastore
     636: dup
     637: iconst_2
     638: iconst_0
     639: bastore
     640: dup
     641: iconst_3
     642: iconst_1
     643: bastore
     644: invokestatic  #7                  // Method assertNext:(Z[B[B[B[B)V
     647: iconst_0
     648: iconst_4
     649: newarray       byte
     651: dup
     652: iconst_0
     653: iconst_0
     654: bastore
     655: dup
     656: iconst_1
     657: iconst_1
     658: bastore
     659: dup
     660: iconst_2
     661: iconst_0
     662: bastore
     663: dup
     664: iconst_3
     665: iconst_1
     666: bastore
     667: iconst_4
     668: newarray       byte
     670: dup
     671: iconst_0
     672: iconst_0
     673: bastore
     674: dup
     675: iconst_1
     676: iconst_m1
     677: bastore
     678: dup
     679: iconst_2
     680: iconst_0
     681: bastore
     682: dup
     683: iconst_3
     684: iconst_m1
     685: bastore
     686: iconst_4
     687: newarray       byte
     689: dup
     690: iconst_0
     691: iconst_5
     692: bastore
     693: dup
     694: iconst_1
     695: iconst_1
     696: bastore
     697: dup
     698: iconst_2
     699: iconst_m1
     700: bastore
     701: dup
     702: iconst_3
     703: iconst_0
     704: bastore
     705: iconst_4
     706: newarray       byte
     708: dup
     709: iconst_0
     710: iconst_5
     711: bastore
     712: dup
     713: iconst_1
     714: iconst_1
     715: bastore
     716: dup
     717: iconst_2
     718: iconst_m1
     719: bastore
     720: dup
     721: iconst_3
     722: iconst_1
     723: bastore
     724: invokestatic  #7                  // Method assertNext:(Z[B[B[B[B)V
     727: iconst_0
     728: iconst_4
     729: newarray       byte
     731: dup
     732: iconst_0
     733: iconst_5
     734: bastore
     735: dup
     736: iconst_1
     737: iconst_1
     738: bastore
     739: dup
     740: iconst_2
     741: iconst_1
     742: bastore
     743: dup
     744: iconst_3
     745: iconst_0
     746: bastore
     747: iconst_4
     748: newarray       byte
     750: dup
     751: iconst_0
     752: iconst_m1
     753: bastore
     754: dup
     755: iconst_1
     756: iconst_m1
     757: bastore
     758: dup
     759: iconst_2
     760: iconst_0
     761: bastore
     762: dup
     763: iconst_3
     764: iconst_0
     765: bastore
     766: iconst_4
     767: newarray       byte
     769: dup
     770: iconst_0
     771: iconst_5
     772: bastore
     773: dup
     774: iconst_1
     775: iconst_1
     776: bastore
     777: dup
     778: iconst_2
     779: iconst_m1
     780: bastore
     781: dup
     782: iconst_3
     783: iconst_1
     784: bastore
     785: iconst_4
     786: newarray       byte
     788: dup
     789: iconst_0
     790: iconst_5
     791: bastore
     792: dup
     793: iconst_1
     794: iconst_1
     795: bastore
     796: dup
     797: iconst_2
     798: iconst_m1
     799: bastore
     800: dup
     801: iconst_3
     802: iconst_2
     803: bastore
     804: invokestatic  #7                  // Method assertNext:(Z[B[B[B[B)V
     807: iconst_0
     808: iconst_4
     809: newarray       byte
     811: dup
     812: iconst_0
     813: iconst_1
     814: bastore
     815: dup
     816: iconst_1
     817: iconst_1
     818: bastore
     819: dup
     820: iconst_2
     821: iconst_1
     822: bastore
     823: dup
     824: iconst_3
     825: iconst_1
     826: bastore
     827: iconst_4
     828: newarray       byte
     830: dup
     831: iconst_0
     832: iconst_m1
     833: bastore
     834: dup
     835: iconst_1
     836: iconst_m1
     837: bastore
     838: dup
     839: iconst_2
     840: iconst_0
     841: bastore
     842: dup
     843: iconst_3
     844: iconst_0
     845: bastore
     846: iconst_4
     847: newarray       byte
     849: dup
     850: iconst_0
     851: iconst_1
     852: bastore
     853: dup
     854: iconst_1
     855: iconst_1
     856: bastore
     857: dup
     858: iconst_2
     859: iconst_2
     860: bastore
     861: dup
     862: iconst_3
     863: iconst_2
     864: bastore
     865: iconst_4
     866: newarray       byte
     868: dup
     869: iconst_0
     870: iconst_1
     871: bastore
     872: dup
     873: iconst_1
     874: iconst_1
     875: bastore
     876: dup
     877: iconst_2
     878: iconst_2
     879: bastore
     880: dup
     881: iconst_3
     882: iconst_3
     883: bastore
     884: invokestatic  #7                  // Method assertNext:(Z[B[B[B[B)V
     887: iconst_0
     888: iconst_4
     889: newarray       byte
     891: dup
     892: iconst_0
     893: iconst_1
     894: bastore
     895: dup
     896: iconst_1
     897: iconst_1
     898: bastore
     899: dup
     900: iconst_2
     901: iconst_1
     902: bastore
     903: dup
     904: iconst_3
     905: iconst_1
     906: bastore
     907: iconst_4
     908: newarray       byte
     910: dup
     911: iconst_0
     912: iconst_m1
     913: bastore
     914: dup
     915: iconst_1
     916: iconst_m1
     917: bastore
     918: dup
     919: iconst_2
     920: iconst_0
     921: bastore
     922: dup
     923: iconst_3
     924: iconst_0
     925: bastore
     926: iconst_4
     927: newarray       byte
     929: dup
     930: iconst_0
     931: iconst_1
     932: bastore
     933: dup
     934: iconst_1
     935: iconst_1
     936: bastore
     937: dup
     938: iconst_2
     939: iconst_3
     940: bastore
     941: dup
     942: iconst_3
     943: iconst_2
     944: bastore
     945: iconst_4
     946: newarray       byte
     948: dup
     949: iconst_0
     950: iconst_1
     951: bastore
     952: dup
     953: iconst_1
     954: iconst_1
     955: bastore
     956: dup
     957: iconst_2
     958: iconst_3
     959: bastore
     960: dup
     961: iconst_3
     962: iconst_3
     963: bastore
     964: invokestatic  #7                  // Method assertNext:(Z[B[B[B[B)V
     967: iconst_0
     968: iconst_4
     969: newarray       byte
     971: dup
     972: iconst_0
     973: iconst_1
     974: bastore
     975: dup
     976: iconst_1
     977: iconst_1
     978: bastore
     979: dup
     980: iconst_2
     981: iconst_1
     982: bastore
     983: dup
     984: iconst_3
     985: iconst_1
     986: bastore
     987: iconst_4
     988: newarray       byte
     990: dup
     991: iconst_0
     992: iconst_0
     993: bastore
     994: dup
     995: iconst_1
     996: iconst_0
     997: bastore
     998: dup
     999: iconst_2
    1000: iconst_0
    1001: bastore
    1002: dup
    1003: iconst_3
    1004: iconst_0
    1005: bastore
    1006: iconst_4
    1007: newarray       byte
    1009: dup
    1010: iconst_0
    1011: iconst_1
    1012: bastore
    1013: dup
    1014: iconst_1
    1015: iconst_1
    1016: bastore
    1017: dup
    1018: iconst_2
    1019: iconst_2
    1020: bastore
    1021: dup
    1022: iconst_3
    1023: iconst_3
    1024: bastore
    1025: iconst_4
    1026: newarray       byte
    1028: dup
    1029: iconst_0
    1030: iconst_1
    1031: bastore
    1032: dup
    1033: iconst_1
    1034: iconst_1
    1035: bastore
    1036: dup
    1037: iconst_2
    1038: iconst_2
    1039: bastore
    1040: dup
    1041: iconst_3
    1042: iconst_4
    1043: bastore
    1044: invokestatic  #7                  // Method assertNext:(Z[B[B[B[B)V
    1047: iconst_0
    1048: iconst_4
    1049: newarray       byte
    1051: dup
    1052: iconst_0
    1053: iconst_1
    1054: bastore
    1055: dup
    1056: iconst_1
    1057: iconst_1
    1058: bastore
    1059: dup
    1060: iconst_2
    1061: iconst_1
    1062: bastore
    1063: dup
    1064: iconst_3
    1065: iconst_1
    1066: bastore
    1067: iconst_4
    1068: newarray       byte
    1070: dup
    1071: iconst_0
    1072: iconst_0
    1073: bastore
    1074: dup
    1075: iconst_1
    1076: iconst_0
    1077: bastore
    1078: dup
    1079: iconst_2
    1080: iconst_0
    1081: bastore
    1082: dup
    1083: iconst_3
    1084: iconst_0
    1085: bastore
    1086: iconst_4
    1087: newarray       byte
    1089: dup
    1090: iconst_0
    1091: iconst_1
    1092: bastore
    1093: dup
    1094: iconst_1
    1095: iconst_1
    1096: bastore
    1097: dup
    1098: iconst_2
    1099: iconst_3
    1100: bastore
    1101: dup
    1102: iconst_3
    1103: iconst_2
    1104: bastore
    1105: iconst_4
    1106: newarray       byte
    1108: dup
    1109: iconst_0
    1110: iconst_1
    1111: bastore
    1112: dup
    1113: iconst_1
    1114: iconst_1
    1115: bastore
    1116: dup
    1117: iconst_2
    1118: iconst_3
    1119: bastore
    1120: dup
    1121: iconst_3
    1122: iconst_3
    1123: bastore
    1124: invokestatic  #7                  // Method assertNext:(Z[B[B[B[B)V
    1127: iconst_0
    1128: iconst_4
    1129: newarray       byte
    1131: dup
    1132: iconst_0
    1133: iconst_1
    1134: bastore
    1135: dup
    1136: iconst_1
    1137: iconst_1
    1138: bastore
    1139: dup
    1140: iconst_2
    1141: iconst_0
    1142: bastore
    1143: dup
    1144: iconst_3
    1145: iconst_0
    1146: bastore
    1147: iconst_4
    1148: newarray       byte
    1150: dup
    1151: iconst_0
    1152: iconst_m1
    1153: bastore
    1154: dup
    1155: iconst_1
    1156: iconst_m1
    1157: bastore
    1158: dup
    1159: iconst_2
    1160: iconst_0
    1161: bastore
    1162: dup
    1163: iconst_3
    1164: iconst_0
    1165: bastore
    1166: iconst_4
    1167: newarray       byte
    1169: dup
    1170: iconst_0
    1171: iconst_0
    1172: bastore
    1173: dup
    1174: iconst_1
    1175: iconst_1
    1176: bastore
    1177: dup
    1178: iconst_2
    1179: iconst_3
    1180: bastore
    1181: dup
    1182: iconst_3
    1183: iconst_2
    1184: bastore
    1185: iconst_2
    1186: newarray       byte
    1188: dup
    1189: iconst_0
    1190: iconst_1
    1191: bastore
    1192: dup
    1193: iconst_1
    1194: iconst_1
    1195: bastore
    1196: invokestatic  #7                  // Method assertNext:(Z[B[B[B[B)V
    1199: iconst_5
    1200: newarray       byte
    1202: dup
    1203: iconst_0
    1204: iconst_2
    1205: bastore
    1206: dup
    1207: iconst_1
    1208: iconst_3
    1209: bastore
    1210: dup
    1211: iconst_2
    1212: iconst_1
    1213: bastore
    1214: dup
    1215: iconst_3
    1216: iconst_1
    1217: bastore
    1218: dup
    1219: iconst_4
    1220: iconst_1
    1221: bastore
    1222: iconst_3
    1223: newarray       byte
    1225: dup
    1226: iconst_0
    1227: iconst_1
    1228: bastore
    1229: dup
    1230: iconst_1
    1231: iconst_0
    1232: bastore
    1233: dup
    1234: iconst_2
    1235: iconst_1
    1236: bastore
    1237: iconst_3
    1238: newarray       byte
    1240: dup
    1241: iconst_0
    1242: iconst_m1
    1243: bastore
    1244: dup
    1245: iconst_1
    1246: iconst_0
    1247: bastore
    1248: dup
    1249: iconst_2
    1250: iconst_m1
    1251: bastore
    1252: invokestatic  #8                  // Method org/apache/hadoop/hbase/filter/FuzzyRowFilter.getNextForFuzzyRule:([B[B[B)[B
    1255: invokestatic  #9                  // Method org/junit/Assert.assertNull:(Ljava/lang/Object;)V
    1258: iconst_5
    1259: newarray       byte
    1261: dup
    1262: iconst_0
    1263: iconst_1
    1264: bastore
    1265: dup
    1266: iconst_1
    1267: bipush        -11
    1269: bastore
    1270: dup
    1271: iconst_2
    1272: iconst_1
    1273: bastore
    1274: dup
    1275: iconst_3
    1276: iconst_3
    1277: bastore
    1278: dup
    1279: iconst_4
    1280: iconst_0
    1281: bastore
    1282: iconst_4
    1283: newarray       byte
    1285: dup
    1286: iconst_0
    1287: iconst_1
    1288: bastore
    1289: dup
    1290: iconst_1
    1291: iconst_1
    1292: bastore
    1293: dup
    1294: iconst_2
    1295: iconst_0
    1296: bastore
    1297: dup
    1298: iconst_3
    1299: iconst_3
    1300: bastore
    1301: iconst_4
    1302: newarray       byte
    1304: dup
    1305: iconst_0
    1306: iconst_m1
    1307: bastore
    1308: dup
    1309: iconst_1
    1310: iconst_m1
    1311: bastore
    1312: dup
    1313: iconst_2
    1314: iconst_0
    1315: bastore
    1316: dup
    1317: iconst_3
    1318: iconst_m1
    1319: bastore
    1320: invokestatic  #8                  // Method org/apache/hadoop/hbase/filter/FuzzyRowFilter.getNextForFuzzyRule:([B[B[B)[B
    1323: invokestatic  #9                  // Method org/junit/Assert.assertNull:(Ljava/lang/Object;)V
    1326: iconst_5
    1327: newarray       byte
    1329: dup
    1330: iconst_0
    1331: iconst_1
    1332: bastore
    1333: dup
    1334: iconst_1
    1335: iconst_3
    1336: bastore
    1337: dup
    1338: iconst_2
    1339: iconst_1
    1340: bastore
    1341: dup
    1342: iconst_3
    1343: iconst_3
    1344: bastore
    1345: dup
    1346: iconst_4
    1347: iconst_0
    1348: bastore
    1349: iconst_4
    1350: newarray       byte
    1352: dup
    1353: iconst_0
    1354: iconst_1
    1355: bastore
    1356: dup
    1357: iconst_1
    1358: iconst_2
    1359: bastore
    1360: dup
    1361: iconst_2
    1362: iconst_0
    1363: bastore
    1364: dup
    1365: iconst_3
    1366: iconst_3
    1367: bastore
    1368: iconst_4
    1369: newarray       byte
    1371: dup
    1372: iconst_0
    1373: iconst_m1
    1374: bastore
    1375: dup
    1376: iconst_1
    1377: iconst_m1
    1378: bastore
    1379: dup
    1380: iconst_2
    1381: iconst_0
    1382: bastore
    1383: dup
    1384: iconst_3
    1385: iconst_m1
    1386: bastore
    1387: invokestatic  #8                  // Method org/apache/hadoop/hbase/filter/FuzzyRowFilter.getNextForFuzzyRule:([B[B[B)[B
    1390: invokestatic  #9                  // Method org/junit/Assert.assertNull:(Ljava/lang/Object;)V
    1393: iconst_5
    1394: newarray       byte
    1396: dup
    1397: iconst_0
    1398: iconst_2
    1399: bastore
    1400: dup
    1401: iconst_1
    1402: iconst_1
    1403: bastore
    1404: dup
    1405: iconst_2
    1406: iconst_1
    1407: bastore
    1408: dup
    1409: iconst_3
    1410: iconst_1
    1411: bastore
    1412: dup
    1413: iconst_4
    1414: iconst_0
    1415: bastore
    1416: iconst_4
    1417: newarray       byte
    1419: dup
    1420: iconst_0
    1421: iconst_1
    1422: bastore
    1423: dup
    1424: iconst_1
    1425: iconst_2
    1426: bastore
    1427: dup
    1428: iconst_2
    1429: iconst_0
    1430: bastore
    1431: dup
    1432: iconst_3
    1433: iconst_3
    1434: bastore
    1435: iconst_4
    1436: newarray       byte
    1438: dup
    1439: iconst_0
    1440: iconst_m1
    1441: bastore
    1442: dup
    1443: iconst_1
    1444: iconst_m1
    1445: bastore
    1446: dup
    1447: iconst_2
    1448: iconst_0
    1449: bastore
    1450: dup
    1451: iconst_3
    1452: iconst_m1
    1453: bastore
    1454: invokestatic  #8                  // Method org/apache/hadoop/hbase/filter/FuzzyRowFilter.getNextForFuzzyRule:([B[B[B)[B
    1457: invokestatic  #9                  // Method org/junit/Assert.assertNull:(Ljava/lang/Object;)V
    1460: return

  public void testGetNextForFuzzyRuleReverse();
    Code:
       0: iconst_1
       1: iconst_3
       2: newarray       byte
       4: dup
       5: iconst_0
       6: iconst_0
       7: bastore
       8: dup
       9: iconst_1
      10: iconst_1
      11: bastore
      12: dup
      13: iconst_2
      14: iconst_2
      15: bastore
      16: iconst_3
      17: newarray       byte
      19: dup
      20: iconst_0
      21: iconst_0
      22: bastore
      23: dup
      24: iconst_1
      25: iconst_m1
      26: bastore
      27: dup
      28: iconst_2
      29: iconst_m1
      30: bastore
      31: iconst_5
      32: newarray       byte
      34: dup
      35: iconst_0
      36: iconst_1
      37: bastore
      38: dup
      39: iconst_1
      40: iconst_2
      41: bastore
      42: dup
      43: iconst_2
      44: iconst_1
      45: bastore
      46: dup
      47: iconst_3
      48: iconst_0
      49: bastore
      50: dup
      51: iconst_4
      52: iconst_1
      53: bastore
      54: iconst_5
      55: newarray       byte
      57: dup
      58: iconst_0
      59: iconst_1
      60: bastore
      61: dup
      62: iconst_1
      63: iconst_1
      64: bastore
      65: dup
      66: iconst_2
      67: iconst_2
      68: bastore
      69: dup
      70: iconst_3
      71: iconst_m1
      72: bastore
      73: dup
      74: iconst_4
      75: iconst_m1
      76: bastore
      77: invokestatic  #7                  // Method assertNext:(Z[B[B[B[B)V
      80: iconst_1
      81: iconst_5
      82: newarray       byte
      84: dup
      85: iconst_0
      86: iconst_0
      87: bastore
      88: dup
      89: iconst_1
      90: iconst_1
      91: bastore
      92: dup
      93: iconst_2
      94: iconst_0
      95: bastore
      96: dup
      97: iconst_3
      98: iconst_2
      99: bastore
     100: dup
     101: iconst_4
     102: iconst_0
     103: bastore
     104: iconst_5
     105: newarray       byte
     107: dup
     108: iconst_0
     109: iconst_0
     110: bastore
     111: dup
     112: iconst_1
     113: iconst_m1
     114: bastore
     115: dup
     116: iconst_2
     117: iconst_0
     118: bastore
     119: dup
     120: iconst_3
     121: iconst_m1
     122: bastore
     123: dup
     124: iconst_4
     125: iconst_0
     126: bastore
     127: iconst_5
     128: newarray       byte
     130: dup
     131: iconst_0
     132: iconst_1
     133: bastore
     134: dup
     135: iconst_1
     136: iconst_2
     137: bastore
     138: dup
     139: iconst_2
     140: iconst_1
     141: bastore
     142: dup
     143: iconst_3
     144: iconst_3
     145: bastore
     146: dup
     147: iconst_4
     148: iconst_1
     149: bastore
     150: iconst_5
     151: newarray       byte
     153: dup
     154: iconst_0
     155: iconst_1
     156: bastore
     157: dup
     158: iconst_1
     159: iconst_1
     160: bastore
     161: dup
     162: iconst_2
     163: iconst_0
     164: bastore
     165: dup
     166: iconst_3
     167: iconst_2
     168: bastore
     169: dup
     170: iconst_4
     171: iconst_0
     172: bastore
     173: invokestatic  #7                  // Method assertNext:(Z[B[B[B[B)V
     176: iconst_1
     177: iconst_3
     178: newarray       byte
     180: dup
     181: iconst_0
     182: iconst_1
     183: bastore
     184: dup
     185: iconst_1
     186: iconst_0
     187: bastore
     188: dup
     189: iconst_2
     190: iconst_1
     191: bastore
     192: iconst_3
     193: newarray       byte
     195: dup
     196: iconst_0
     197: iconst_m1
     198: bastore
     199: dup
     200: iconst_1
     201: iconst_0
     202: bastore
     203: dup
     204: iconst_2
     205: iconst_m1
     206: bastore
     207: iconst_5
     208: newarray       byte
     210: dup
     211: iconst_0
     212: iconst_1
     213: bastore
     214: dup
     215: iconst_1
     216: bipush        -128
     218: bastore
     219: dup
     220: iconst_2
     221: iconst_2
     222: bastore
     223: dup
     224: iconst_3
     225: iconst_0
     226: bastore
     227: dup
     228: iconst_4
     229: iconst_1
     230: bastore
     231: iconst_5
     232: newarray       byte
     234: dup
     235: iconst_0
     236: iconst_1
     237: bastore
     238: dup
     239: iconst_1
     240: bipush        -128
     242: bastore
     243: dup
     244: iconst_2
     245: iconst_1
     246: bastore
     247: dup
     248: iconst_3
     249: iconst_m1
     250: bastore
     251: dup
     252: iconst_4
     253: iconst_m1
     254: bastore
     255: invokestatic  #7                  // Method assertNext:(Z[B[B[B[B)V
     258: iconst_1
     259: iconst_4
     260: newarray       byte
     262: dup
     263: iconst_0
     264: iconst_0
     265: bastore
     266: dup
     267: iconst_1
     268: iconst_1
     269: bastore
     270: dup
     271: iconst_2
     272: iconst_0
     273: bastore
     274: dup
     275: iconst_3
     276: iconst_1
     277: bastore
     278: iconst_4
     279: newarray       byte
     281: dup
     282: iconst_0
     283: iconst_0
     284: bastore
     285: dup
     286: iconst_1
     287: iconst_m1
     288: bastore
     289: dup
     290: iconst_2
     291: iconst_0
     292: bastore
     293: dup
     294: iconst_3
     295: iconst_m1
     296: bastore
     297: iconst_5
     298: newarray       byte
     300: dup
     301: iconst_0
     302: iconst_5
     303: bastore
     304: dup
     305: iconst_1
     306: iconst_1
     307: bastore
     308: dup
     309: iconst_2
     310: iconst_0
     311: bastore
     312: dup
     313: iconst_3
     314: iconst_2
     315: bastore
     316: dup
     317: iconst_4
     318: iconst_1
     319: bastore
     320: iconst_5
     321: newarray       byte
     323: dup
     324: iconst_0
     325: iconst_5
     326: bastore
     327: dup
     328: iconst_1
     329: iconst_1
     330: bastore
     331: dup
     332: iconst_2
     333: iconst_0
     334: bastore
     335: dup
     336: iconst_3
     337: iconst_1
     338: bastore
     339: dup
     340: iconst_4
     341: iconst_m1
     342: bastore
     343: invokestatic  #7                  // Method assertNext:(Z[B[B[B[B)V
     346: iconst_1
     347: iconst_4
     348: newarray       byte
     350: dup
     351: iconst_0
     352: iconst_0
     353: bastore
     354: dup
     355: iconst_1
     356: iconst_1
     357: bastore
     358: dup
     359: iconst_2
     360: iconst_0
     361: bastore
     362: dup
     363: iconst_3
     364: iconst_0
     365: bastore
     366: iconst_4
     367: newarray       byte
     369: dup
     370: iconst_0
     371: iconst_0
     372: bastore
     373: dup
     374: iconst_1
     375: iconst_m1
     376: bastore
     377: dup
     378: iconst_2
     379: iconst_0
     380: bastore
     381: dup
     382: iconst_3
     383: iconst_0
     384: bastore
     385: iconst_4
     386: newarray       byte
     388: dup
     389: iconst_0
     390: iconst_5
     391: bastore
     392: dup
     393: iconst_1
     394: iconst_1
     395: bastore
     396: dup
     397: iconst_2
     398: iconst_m1
     399: bastore
     400: dup
     401: iconst_3
     402: iconst_1
     403: bastore
     404: iconst_4
     405: newarray       byte
     407: dup
     408: iconst_0
     409: iconst_5
     410: bastore
     411: dup
     412: iconst_1
     413: iconst_1
     414: bastore
     415: dup
     416: iconst_2
     417: iconst_m1
     418: bastore
     419: dup
     420: iconst_3
     421: iconst_0
     422: bastore
     423: invokestatic  #7                  // Method assertNext:(Z[B[B[B[B)V
     426: iconst_1
     427: iconst_4
     428: newarray       byte
     430: dup
     431: iconst_0
     432: iconst_0
     433: bastore
     434: dup
     435: iconst_1
     436: iconst_1
     437: bastore
     438: dup
     439: iconst_2
     440: iconst_0
     441: bastore
     442: dup
     443: iconst_3
     444: iconst_1
     445: bastore
     446: iconst_4
     447: newarray       byte
     449: dup
     450: iconst_0
     451: iconst_0
     452: bastore
     453: dup
     454: iconst_1
     455: iconst_m1
     456: bastore
     457: dup
     458: iconst_2
     459: iconst_0
     460: bastore
     461: dup
     462: iconst_3
     463: iconst_m1
     464: bastore
     465: iconst_4
     466: newarray       byte
     468: dup
     469: iconst_0
     470: iconst_5
     471: bastore
     472: dup
     473: iconst_1
     474: iconst_1
     475: bastore
     476: dup
     477: iconst_2
     478: iconst_0
     479: bastore
     480: dup
     481: iconst_3
     482: iconst_1
     483: bastore
     484: iconst_4
     485: newarray       byte
     487: dup
     488: iconst_0
     489: iconst_4
     490: bastore
     491: dup
     492: iconst_1
     493: iconst_1
     494: bastore
     495: dup
     496: iconst_2
     497: iconst_m1
     498: bastore
     499: dup
     500: iconst_3
     501: iconst_1
     502: bastore
     503: invokestatic  #7                  // Method assertNext:(Z[B[B[B[B)V
     506: iconst_1
     507: iconst_4
     508: newarray       byte
     510: dup
     511: iconst_0
     512: iconst_0
     513: bastore
     514: dup
     515: iconst_1
     516: iconst_1
     517: bastore
     518: dup
     519: iconst_2
     520: iconst_0
     521: bastore
     522: dup
     523: iconst_3
     524: iconst_1
     525: bastore
     526: iconst_4
     527: newarray       byte
     529: dup
     530: iconst_0
     531: iconst_0
     532: bastore
     533: dup
     534: iconst_1
     535: iconst_m1
     536: bastore
     537: dup
     538: iconst_2
     539: iconst_0
     540: bastore
     541: dup
     542: iconst_3
     543: iconst_m1
     544: bastore
     545: iconst_4
     546: newarray       byte
     548: dup
     549: iconst_0
     550: iconst_5
     551: bastore
     552: dup
     553: iconst_1
     554: iconst_1
     555: bastore
     556: dup
     557: iconst_2
     558: iconst_m1
     559: bastore
     560: dup
     561: iconst_3
     562: iconst_0
     563: bastore
     564: iconst_4
     565: newarray       byte
     567: dup
     568: iconst_0
     569: iconst_5
     570: bastore
     571: dup
     572: iconst_1
     573: iconst_1
     574: bastore
     575: dup
     576: iconst_2
     577: bipush        -2
     579: bastore
     580: dup
     581: iconst_3
     582: iconst_1
     583: bastore
     584: invokestatic  #7                  // Method assertNext:(Z[B[B[B[B)V
     587: iconst_1
     588: iconst_4
     589: newarray       byte
     591: dup
     592: iconst_0
     593: iconst_1
     594: bastore
     595: dup
     596: iconst_1
     597: iconst_1
     598: bastore
     599: dup
     600: iconst_2
     601: iconst_0
     602: bastore
     603: dup
     604: iconst_3
     605: iconst_0
     606: bastore
     607: iconst_4
     608: newarray       byte
     610: dup
     611: iconst_0
     612: iconst_m1
     613: bastore
     614: dup
     615: iconst_1
     616: iconst_m1
     617: bastore
     618: dup
     619: iconst_2
     620: iconst_0
     621: bastore
     622: dup
     623: iconst_3
     624: iconst_0
     625: bastore
     626: iconst_4
     627: newarray       byte
     629: dup
     630: iconst_0
     631: iconst_2
     632: bastore
     633: dup
     634: iconst_1
     635: iconst_1
     636: bastore
     637: dup
     638: iconst_2
     639: iconst_3
     640: bastore
     641: dup
     642: iconst_3
     643: iconst_2
     644: bastore
     645: iconst_4
     646: newarray       byte
     648: dup
     649: iconst_0
     650: iconst_1
     651: bastore
     652: dup
     653: iconst_1
     654: iconst_1
     655: bastore
     656: dup
     657: iconst_2
     658: iconst_0
     659: bastore
     660: dup
     661: iconst_3
     662: iconst_0
     663: bastore
     664: invokestatic  #7                  // Method assertNext:(Z[B[B[B[B)V
     667: iconst_1
     668: iconst_3
     669: newarray       byte
     671: dup
     672: iconst_0
     673: iconst_1
     674: bastore
     675: dup
     676: iconst_1
     677: iconst_0
     678: bastore
     679: dup
     680: iconst_2
     681: iconst_1
     682: bastore
     683: iconst_3
     684: newarray       byte
     686: dup
     687: iconst_0
     688: iconst_m1
     689: bastore
     690: dup
     691: iconst_1
     692: iconst_0
     693: bastore
     694: dup
     695: iconst_2
     696: iconst_m1
     697: bastore
     698: iconst_5
     699: newarray       byte
     701: dup
     702: iconst_0
     703: iconst_2
     704: bastore
     705: dup
     706: iconst_1
     707: iconst_3
     708: bastore
     709: dup
     710: iconst_2
     711: iconst_1
     712: bastore
     713: dup
     714: iconst_3
     715: iconst_1
     716: bastore
     717: dup
     718: iconst_4
     719: iconst_1
     720: bastore
     721: iconst_5
     722: newarray       byte
     724: dup
     725: iconst_0
     726: iconst_1
     727: bastore
     728: dup
     729: iconst_1
     730: iconst_0
     731: bastore
     732: dup
     733: iconst_2
     734: iconst_1
     735: bastore
     736: dup
     737: iconst_3
     738: iconst_m1
     739: bastore
     740: dup
     741: iconst_4
     742: iconst_m1
     743: bastore
     744: invokestatic  #7                  // Method assertNext:(Z[B[B[B[B)V
     747: iconst_1
     748: iconst_4
     749: newarray       byte
     751: dup
     752: iconst_0
     753: iconst_1
     754: bastore
     755: dup
     756: iconst_1
     757: iconst_1
     758: bastore
     759: dup
     760: iconst_2
     761: iconst_0
     762: bastore
     763: dup
     764: iconst_3
     765: iconst_3
     766: bastore
     767: iconst_4
     768: newarray       byte
     770: dup
     771: iconst_0
     772: iconst_m1
     773: bastore
     774: dup
     775: iconst_1
     776: iconst_m1
     777: bastore
     778: dup
     779: iconst_2
     780: iconst_0
     781: bastore
     782: dup
     783: iconst_3
     784: iconst_m1
     785: bastore
     786: iconst_5
     787: newarray       byte
     789: dup
     790: iconst_0
     791: iconst_1
     792: bastore
     793: dup
     794: iconst_1
     795: bipush        -11
     797: bastore
     798: dup
     799: iconst_2
     800: iconst_1
     801: bastore
     802: dup
     803: iconst_3
     804: iconst_3
     805: bastore
     806: dup
     807: iconst_4
     808: iconst_0
     809: bastore
     810: iconst_5
     811: newarray       byte
     813: dup
     814: iconst_0
     815: iconst_1
     816: bastore
     817: dup
     818: iconst_1
     819: iconst_1
     820: bastore
     821: dup
     822: iconst_2
     823: iconst_0
     824: bastore
     825: dup
     826: iconst_3
     827: iconst_3
     828: bastore
     829: dup
     830: iconst_4
     831: iconst_m1
     832: bastore
     833: invokestatic  #7                  // Method assertNext:(Z[B[B[B[B)V
     836: iconst_1
     837: iconst_4
     838: newarray       byte
     840: dup
     841: iconst_0
     842: iconst_1
     843: bastore
     844: dup
     845: iconst_1
     846: iconst_2
     847: bastore
     848: dup
     849: iconst_2
     850: iconst_0
     851: bastore
     852: dup
     853: iconst_3
     854: iconst_3
     855: bastore
     856: iconst_4
     857: newarray       byte
     859: dup
     860: iconst_0
     861: iconst_m1
     862: bastore
     863: dup
     864: iconst_1
     865: iconst_m1
     866: bastore
     867: dup
     868: iconst_2
     869: iconst_0
     870: bastore
     871: dup
     872: iconst_3
     873: iconst_m1
     874: bastore
     875: iconst_5
     876: newarray       byte
     878: dup
     879: iconst_0
     880: iconst_1
     881: bastore
     882: dup
     883: iconst_1
     884: iconst_3
     885: bastore
     886: dup
     887: iconst_2
     888: iconst_1
     889: bastore
     890: dup
     891: iconst_3
     892: iconst_3
     893: bastore
     894: dup
     895: iconst_4
     896: iconst_0
     897: bastore
     898: iconst_5
     899: newarray       byte
     901: dup
     902: iconst_0
     903: iconst_1
     904: bastore
     905: dup
     906: iconst_1
     907: iconst_2
     908: bastore
     909: dup
     910: iconst_2
     911: iconst_0
     912: bastore
     913: dup
     914: iconst_3
     915: iconst_3
     916: bastore
     917: dup
     918: iconst_4
     919: iconst_m1
     920: bastore
     921: invokestatic  #7                  // Method assertNext:(Z[B[B[B[B)V
     924: iconst_1
     925: iconst_4
     926: newarray       byte
     928: dup
     929: iconst_0
     930: iconst_1
     931: bastore
     932: dup
     933: iconst_1
     934: iconst_2
     935: bastore
     936: dup
     937: iconst_2
     938: iconst_0
     939: bastore
     940: dup
     941: iconst_3
     942: iconst_3
     943: bastore
     944: iconst_4
     945: newarray       byte
     947: dup
     948: iconst_0
     949: iconst_m1
     950: bastore
     951: dup
     952: iconst_1
     953: iconst_m1
     954: bastore
     955: dup
     956: iconst_2
     957: iconst_0
     958: bastore
     959: dup
     960: iconst_3
     961: iconst_m1
     962: bastore
     963: iconst_5
     964: newarray       byte
     966: dup
     967: iconst_0
     968: iconst_2
     969: bastore
     970: dup
     971: iconst_1
     972: iconst_1
     973: bastore
     974: dup
     975: iconst_2
     976: iconst_1
     977: bastore
     978: dup
     979: iconst_3
     980: iconst_1
     981: bastore
     982: dup
     983: iconst_4
     984: iconst_0
     985: bastore
     986: iconst_5
     987: newarray       byte
     989: dup
     990: iconst_0
     991: iconst_1
     992: bastore
     993: dup
     994: iconst_1
     995: iconst_2
     996: bastore
     997: dup
     998: iconst_2
     999: iconst_0
    1000: bastore
    1001: dup
    1002: iconst_3
    1003: iconst_3
    1004: bastore
    1005: dup
    1006: iconst_4
    1007: iconst_m1
    1008: bastore
    1009: invokestatic  #7                  // Method assertNext:(Z[B[B[B[B)V
    1012: iconst_1
    1013: iconst_3
    1014: newarray       byte
    1016: dup
    1017: iconst_0
    1018: iconst_1
    1019: bastore
    1020: dup
    1021: iconst_1
    1022: iconst_0
    1023: bastore
    1024: dup
    1025: iconst_2
    1026: iconst_1
    1027: bastore
    1028: iconst_3
    1029: newarray       byte
    1031: dup
    1032: iconst_0
    1033: iconst_m1
    1034: bastore
    1035: dup
    1036: iconst_1
    1037: iconst_0
    1038: bastore
    1039: dup
    1040: iconst_2
    1041: iconst_m1
    1042: bastore
    1043: iconst_3
    1044: newarray       byte
    1046: dup
    1047: iconst_0
    1048: iconst_1
    1049: bastore
    1050: dup
    1051: iconst_1
    1052: bipush        -128
    1054: bastore
    1055: dup
    1056: iconst_2
    1057: iconst_2
    1058: bastore
    1059: iconst_3
    1060: newarray       byte
    1062: dup
    1063: iconst_0
    1064: iconst_1
    1065: bastore
    1066: dup
    1067: iconst_1
    1068: bipush        -128
    1070: bastore
    1071: dup
    1072: iconst_2
    1073: iconst_1
    1074: bastore
    1075: invokestatic  #7                  // Method assertNext:(Z[B[B[B[B)V
    1078: iconst_1
    1079: iconst_4
    1080: newarray       byte
    1082: dup
    1083: iconst_0
    1084: iconst_0
    1085: bastore
    1086: dup
    1087: iconst_1
    1088: iconst_1
    1089: bastore
    1090: dup
    1091: iconst_2
    1092: iconst_0
    1093: bastore
    1094: dup
    1095: iconst_3
    1096: iconst_1
    1097: bastore
    1098: iconst_4
    1099: newarray       byte
    1101: dup
    1102: iconst_0
    1103: iconst_0
    1104: bastore
    1105: dup
    1106: iconst_1
    1107: iconst_m1
    1108: bastore
    1109: dup
    1110: iconst_2
    1111: iconst_0
    1112: bastore
    1113: dup
    1114: iconst_3
    1115: iconst_m1
    1116: bastore
    1117: iconst_4
    1118: newarray       byte
    1120: dup
    1121: iconst_0
    1122: iconst_5
    1123: bastore
    1124: dup
    1125: iconst_1
    1126: iconst_1
    1127: bastore
    1128: dup
    1129: iconst_2
    1130: iconst_0
    1131: bastore
    1132: dup
    1133: iconst_3
    1134: iconst_2
    1135: bastore
    1136: iconst_4
    1137: newarray       byte
    1139: dup
    1140: iconst_0
    1141: iconst_5
    1142: bastore
    1143: dup
    1144: iconst_1
    1145: iconst_1
    1146: bastore
    1147: dup
    1148: iconst_2
    1149: iconst_0
    1150: bastore
    1151: dup
    1152: iconst_3
    1153: iconst_1
    1154: bastore
    1155: invokestatic  #7                  // Method assertNext:(Z[B[B[B[B)V
    1158: iconst_1
    1159: iconst_4
    1160: newarray       byte
    1162: dup
    1163: iconst_0
    1164: iconst_5
    1165: bastore
    1166: dup
    1167: iconst_1
    1168: iconst_1
    1169: bastore
    1170: dup
    1171: iconst_2
    1172: iconst_1
    1173: bastore
    1174: dup
    1175: iconst_3
    1176: iconst_0
    1177: bastore
    1178: iconst_4
    1179: newarray       byte
    1181: dup
    1182: iconst_0
    1183: iconst_m1
    1184: bastore
    1185: dup
    1186: iconst_1
    1187: iconst_m1
    1188: bastore
    1189: dup
    1190: iconst_2
    1191: iconst_0
    1192: bastore
    1193: dup
    1194: iconst_3
    1195: iconst_0
    1196: bastore
    1197: iconst_4
    1198: newarray       byte
    1200: dup
    1201: iconst_0
    1202: iconst_5
    1203: bastore
    1204: dup
    1205: iconst_1
    1206: iconst_1
    1207: bastore
    1208: dup
    1209: iconst_2
    1210: iconst_m1
    1211: bastore
    1212: dup
    1213: iconst_3
    1214: iconst_1
    1215: bastore
    1216: iconst_4
    1217: newarray       byte
    1219: dup
    1220: iconst_0
    1221: iconst_5
    1222: bastore
    1223: dup
    1224: iconst_1
    1225: iconst_1
    1226: bastore
    1227: dup
    1228: iconst_2
    1229: iconst_m1
    1230: bastore
    1231: dup
    1232: iconst_3
    1233: iconst_0
    1234: bastore
    1235: invokestatic  #7                  // Method assertNext:(Z[B[B[B[B)V
    1238: iconst_1
    1239: iconst_4
    1240: newarray       byte
    1242: dup
    1243: iconst_0
    1244: iconst_1
    1245: bastore
    1246: dup
    1247: iconst_1
    1248: iconst_1
    1249: bastore
    1250: dup
    1251: iconst_2
    1252: iconst_1
    1253: bastore
    1254: dup
    1255: iconst_3
    1256: iconst_1
    1257: bastore
    1258: iconst_4
    1259: newarray       byte
    1261: dup
    1262: iconst_0
    1263: iconst_m1
    1264: bastore
    1265: dup
    1266: iconst_1
    1267: iconst_m1
    1268: bastore
    1269: dup
    1270: iconst_2
    1271: iconst_0
    1272: bastore
    1273: dup
    1274: iconst_3
    1275: iconst_0
    1276: bastore
    1277: iconst_4
    1278: newarray       byte
    1280: dup
    1281: iconst_0
    1282: iconst_1
    1283: bastore
    1284: dup
    1285: iconst_1
    1286: iconst_1
    1287: bastore
    1288: dup
    1289: iconst_2
    1290: iconst_2
    1291: bastore
    1292: dup
    1293: iconst_3
    1294: iconst_2
    1295: bastore
    1296: iconst_4
    1297: newarray       byte
    1299: dup
    1300: iconst_0
    1301: iconst_1
    1302: bastore
    1303: dup
    1304: iconst_1
    1305: iconst_1
    1306: bastore
    1307: dup
    1308: iconst_2
    1309: iconst_2
    1310: bastore
    1311: dup
    1312: iconst_3
    1313: iconst_1
    1314: bastore
    1315: invokestatic  #7                  // Method assertNext:(Z[B[B[B[B)V
    1318: iconst_1
    1319: iconst_4
    1320: newarray       byte
    1322: dup
    1323: iconst_0
    1324: iconst_1
    1325: bastore
    1326: dup
    1327: iconst_1
    1328: iconst_1
    1329: bastore
    1330: dup
    1331: iconst_2
    1332: iconst_1
    1333: bastore
    1334: dup
    1335: iconst_3
    1336: iconst_1
    1337: bastore
    1338: iconst_4
    1339: newarray       byte
    1341: dup
    1342: iconst_0
    1343: iconst_0
    1344: bastore
    1345: dup
    1346: iconst_1
    1347: iconst_0
    1348: bastore
    1349: dup
    1350: iconst_2
    1351: iconst_0
    1352: bastore
    1353: dup
    1354: iconst_3
    1355: iconst_0
    1356: bastore
    1357: iconst_4
    1358: newarray       byte
    1360: dup
    1361: iconst_0
    1362: iconst_1
    1363: bastore
    1364: dup
    1365: iconst_1
    1366: iconst_1
    1367: bastore
    1368: dup
    1369: iconst_2
    1370: iconst_2
    1371: bastore
    1372: dup
    1373: iconst_3
    1374: iconst_3
    1375: bastore
    1376: iconst_4
    1377: newarray       byte
    1379: dup
    1380: iconst_0
    1381: iconst_1
    1382: bastore
    1383: dup
    1384: iconst_1
    1385: iconst_1
    1386: bastore
    1387: dup
    1388: iconst_2
    1389: iconst_2
    1390: bastore
    1391: dup
    1392: iconst_3
    1393: iconst_2
    1394: bastore
    1395: invokestatic  #7                  // Method assertNext:(Z[B[B[B[B)V
    1398: iconst_1
    1399: iconst_5
    1400: newarray       byte
    1402: dup
    1403: iconst_0
    1404: iconst_1
    1405: bastore
    1406: dup
    1407: iconst_1
    1408: iconst_1
    1409: bastore
    1410: dup
    1411: iconst_2
    1412: iconst_1
    1413: bastore
    1414: dup
    1415: iconst_3
    1416: iconst_3
    1417: bastore
    1418: dup
    1419: iconst_4
    1420: iconst_0
    1421: bastore
    1422: iconst_4
    1423: newarray       byte
    1425: dup
    1426: iconst_0
    1427: iconst_1
    1428: bastore
    1429: dup
    1430: iconst_1
    1431: iconst_2
    1432: bastore
    1433: dup
    1434: iconst_2
    1435: iconst_0
    1436: bastore
    1437: dup
    1438: iconst_3
    1439: iconst_3
    1440: bastore
    1441: iconst_4
    1442: newarray       byte
    1444: dup
    1445: iconst_0
    1446: iconst_m1
    1447: bastore
    1448: dup
    1449: iconst_1
    1450: iconst_m1
    1451: bastore
    1452: dup
    1453: iconst_2
    1454: iconst_0
    1455: bastore
    1456: dup
    1457: iconst_3
    1458: iconst_m1
    1459: bastore
    1460: invokestatic  #10                 // Method org/apache/hadoop/hbase/filter/FuzzyRowFilter.getNextForFuzzyRule:(Z[B[B[B)[B
    1463: invokestatic  #9                  // Method org/junit/Assert.assertNull:(Ljava/lang/Object;)V
    1466: return

  static {};
    Code:
       0: ldc           #17                 // class org/apache/hadoop/hbase/filter/TestFuzzyRowFilter
       2: invokestatic  #18                 // Method org/apache/hadoop/hbase/HBaseClassTestRule.forClass:(Ljava/lang/Class;)Lorg/apache/hadoop/hbase/HBaseClassTestRule;
       5: putstatic     #19                 // Field CLASS_RULE:Lorg/apache/hadoop/hbase/HBaseClassTestRule;
       8: return
}
