Compiled from "TestSimpleRpcScheduler.java"
final class org.apache.hadoop.hbase.ipc.TestSimpleRpcScheduler$CoDelEnvironmentEdge implements org.apache.hadoop.hbase.util.EnvironmentEdge {
  public long currentTime();
    Code:
       0: aload_0
       1: getfield      #3                  // Field threadNamePrefixs:Ljava/util/Set;
       4: invokeinterface #10,  1           // InterfaceMethod java/util/Set.iterator:()Ljava/util/Iterator;
       9: astore_1
      10: aload_1
      11: invokeinterface #11,  1           // InterfaceMethod java/util/Iterator.hasNext:()Z
      16: ifeq          68
      19: aload_1
      20: invokeinterface #12,  1           // InterfaceMethod java/util/Iterator.next:()Ljava/lang/Object;
      25: checkcast     #13                 // class java/lang/String
      28: astore_2
      29: invokestatic  #14                 // Method java/lang/Thread.currentThread:()Ljava/lang/Thread;
      32: invokevirtual #15                 // Method java/lang/Thread.getName:()Ljava/lang/String;
      35: astore_3
      36: aload_3
      37: aload_2
      38: invokevirtual #16                 // Method java/lang/String.startsWith:(Ljava/lang/String;)Z
      41: ifeq          65
      44: aload_0
      45: getfield      #1                  // Field timeQ:Ljava/util/concurrent/BlockingQueue;
      48: invokeinterface #17,  1           // InterfaceMethod java/util/concurrent/BlockingQueue.poll:()Ljava/lang/Object;
      53: checkcast     #18                 // class java/lang/Long
      56: invokevirtual #19                 // Method java/lang/Long.longValue:()J
      59: aload_0
      60: getfield      #2                  // Field offset:J
      63: ladd
      64: lreturn
      65: goto          10
      68: invokestatic  #20                 // Method java/lang/System.currentTimeMillis:()J
      71: lreturn

  org.apache.hadoop.hbase.ipc.TestSimpleRpcScheduler$CoDelEnvironmentEdge(org.apache.hadoop.hbase.ipc.TestSimpleRpcScheduler$1);
    Code:
       0: aload_0
       1: invokespecial #4                  // Method "<init>":()V
       4: return

  static java.util.Set access$100(org.apache.hadoop.hbase.ipc.TestSimpleRpcScheduler$CoDelEnvironmentEdge);
    Code:
       0: aload_0
       1: getfield      #3                  // Field threadNamePrefixs:Ljava/util/Set;
       4: areturn

  static long access$202(org.apache.hadoop.hbase.ipc.TestSimpleRpcScheduler$CoDelEnvironmentEdge, long);
    Code:
       0: aload_0
       1: lload_1
       2: dup2_x1
       3: putfield      #2                  // Field offset:J
       6: lreturn

  static java.util.concurrent.BlockingQueue access$300(org.apache.hadoop.hbase.ipc.TestSimpleRpcScheduler$CoDelEnvironmentEdge);
    Code:
       0: aload_0
       1: getfield      #1                  // Field timeQ:Ljava/util/concurrent/BlockingQueue;
       4: areturn
}
