Compiled from "TestServerLoad.java"
public class org.apache.hadoop.hbase.TestServerLoad {
  public static final org.apache.hadoop.hbase.HBaseClassTestRule CLASS_RULE;

  public org.apache.hadoop.hbase.TestServerLoad();
    Code:
       0: aload_0
       1: invokespecial #1                  // Method java/lang/Object."<init>":()V
       4: return

  public void testRegionLoadAggregation();
    Code:
       0: new           #2                  // class org/apache/hadoop/hbase/ServerLoad
       3: dup
       4: ldc           #3                  // String localhost,1,1
       6: invokestatic  #4                  // Method org/apache/hadoop/hbase/ServerName.valueOf:(Ljava/lang/String;)Lorg/apache/hadoop/hbase/ServerName;
       9: aload_0
      10: invokespecial #5                  // Method createServerLoadProto:()Lorg/apache/hadoop/hbase/shaded/protobuf/generated/ClusterStatusProtos$ServerLoad;
      13: invokespecial #6                  // Method org/apache/hadoop/hbase/ServerLoad."<init>":(Lorg/apache/hadoop/hbase/ServerName;Lorg/apache/hadoop/hbase/shaded/protobuf/generated/ClusterStatusProtos$ServerLoad;)V
      16: astore_1
      17: ldc2_w        #7                  // long 13l
      20: aload_1
      21: invokevirtual #9                  // Method org/apache/hadoop/hbase/ServerLoad.getStores:()I
      24: i2l
      25: invokestatic  #10                 // Method org/junit/Assert.assertEquals:(JJ)V
      28: ldc2_w        #11                 // long 114l
      31: aload_1
      32: invokevirtual #13                 // Method org/apache/hadoop/hbase/ServerLoad.getStorefiles:()I
      35: i2l
      36: invokestatic  #10                 // Method org/junit/Assert.assertEquals:(JJ)V
      39: ldc2_w        #14                 // long 129l
      42: aload_1
      43: invokevirtual #16                 // Method org/apache/hadoop/hbase/ServerLoad.getStoreUncompressedSizeMB:()I
      46: i2l
      47: invokestatic  #10                 // Method org/junit/Assert.assertEquals:(JJ)V
      50: ldc2_w        #17                 // long 504l
      53: aload_1
      54: invokevirtual #19                 // Method org/apache/hadoop/hbase/ServerLoad.getRootIndexSizeKB:()I
      57: i2l
      58: invokestatic  #10                 // Method org/junit/Assert.assertEquals:(JJ)V
      61: ldc2_w        #20                 // long 820l
      64: aload_1
      65: invokevirtual #22                 // Method org/apache/hadoop/hbase/ServerLoad.getStorefileSizeMB:()I
      68: i2l
      69: invokestatic  #10                 // Method org/junit/Assert.assertEquals:(JJ)V
      72: ldc2_w        #23                 // long 82l
      75: aload_1
      76: invokevirtual #25                 // Method org/apache/hadoop/hbase/ServerLoad.getStorefileIndexSizeKB:()J
      79: invokestatic  #10                 // Method org/junit/Assert.assertEquals:(JJ)V
      82: ldc2_w        #27                 // long 4294967294l
      85: aload_1
      86: invokevirtual #29                 // Method org/apache/hadoop/hbase/ServerLoad.getReadRequestsCount:()J
      89: invokestatic  #10                 // Method org/junit/Assert.assertEquals:(JJ)V
      92: ldc2_w        #30                 // long 300l
      95: aload_1
      96: invokevirtual #32                 // Method org/apache/hadoop/hbase/ServerLoad.getFilteredReadRequestsCount:()J
      99: invokestatic  #10                 // Method org/junit/Assert.assertEquals:(JJ)V
     102: return

  public void testToString();
    Code:
       0: new           #2                  // class org/apache/hadoop/hbase/ServerLoad
       3: dup
       4: ldc           #3                  // String localhost,1,1
       6: invokestatic  #4                  // Method org/apache/hadoop/hbase/ServerName.valueOf:(Ljava/lang/String;)Lorg/apache/hadoop/hbase/ServerName;
       9: aload_0
      10: invokespecial #5                  // Method createServerLoadProto:()Lorg/apache/hadoop/hbase/shaded/protobuf/generated/ClusterStatusProtos$ServerLoad;
      13: invokespecial #6                  // Method org/apache/hadoop/hbase/ServerLoad."<init>":(Lorg/apache/hadoop/hbase/ServerName;Lorg/apache/hadoop/hbase/shaded/protobuf/generated/ClusterStatusProtos$ServerLoad;)V
      16: astore_1
      17: aload_1
      18: invokevirtual #33                 // Method org/apache/hadoop/hbase/ServerLoad.toString:()Ljava/lang/String;
      21: astore_2
      22: aload_1
      23: invokevirtual #34                 // Method org/apache/hadoop/hbase/ServerLoad.obtainServerLoadPB:()Lorg/apache/hadoop/hbase/shaded/protobuf/generated/ClusterStatusProtos$ServerLoad;
      26: invokestatic  #35                 // Method org/junit/Assert.assertNotNull:(Ljava/lang/Object;)V
      29: aload_2
      30: ldc           #36                 // String numberOfStores=13
      32: invokevirtual #37                 // Method java/lang/String.contains:(Ljava/lang/CharSequence;)Z
      35: invokestatic  #38                 // Method org/junit/Assert.assertTrue:(Z)V
      38: aload_2
      39: ldc           #39                 // String numberOfStorefiles=114
      41: invokevirtual #37                 // Method java/lang/String.contains:(Ljava/lang/CharSequence;)Z
      44: invokestatic  #38                 // Method org/junit/Assert.assertTrue:(Z)V
      47: aload_2
      48: ldc           #40                 // String storefileUncompressedSizeMB=129
      50: invokevirtual #37                 // Method java/lang/String.contains:(Ljava/lang/CharSequence;)Z
      53: invokestatic  #38                 // Method org/junit/Assert.assertTrue:(Z)V
      56: aload_2
      57: ldc           #41                 // String storefileSizeMB=820
      59: invokevirtual #37                 // Method java/lang/String.contains:(Ljava/lang/CharSequence;)Z
      62: invokestatic  #38                 // Method org/junit/Assert.assertTrue:(Z)V
      65: aload_2
      66: ldc           #42                 // String rootIndexSizeKB=504
      68: invokevirtual #37                 // Method java/lang/String.contains:(Ljava/lang/CharSequence;)Z
      71: invokestatic  #38                 // Method org/junit/Assert.assertTrue:(Z)V
      74: aload_2
      75: ldc           #43                 // String coprocessors=[]
      77: invokevirtual #37                 // Method java/lang/String.contains:(Ljava/lang/CharSequence;)Z
      80: invokestatic  #38                 // Method org/junit/Assert.assertTrue:(Z)V
      83: aload_2
      84: ldc           #44                 // String filteredReadRequestsCount=300
      86: invokevirtual #37                 // Method java/lang/String.contains:(Ljava/lang/CharSequence;)Z
      89: invokestatic  #38                 // Method org/junit/Assert.assertTrue:(Z)V
      92: return

  public void testRegionLoadWrapAroundAggregation();
    Code:
       0: new           #2                  // class org/apache/hadoop/hbase/ServerLoad
       3: dup
       4: ldc           #3                  // String localhost,1,1
       6: invokestatic  #4                  // Method org/apache/hadoop/hbase/ServerName.valueOf:(Ljava/lang/String;)Lorg/apache/hadoop/hbase/ServerName;
       9: aload_0
      10: invokespecial #5                  // Method createServerLoadProto:()Lorg/apache/hadoop/hbase/shaded/protobuf/generated/ClusterStatusProtos$ServerLoad;
      13: invokespecial #6                  // Method org/apache/hadoop/hbase/ServerLoad."<init>":(Lorg/apache/hadoop/hbase/ServerName;Lorg/apache/hadoop/hbase/shaded/protobuf/generated/ClusterStatusProtos$ServerLoad;)V
      16: astore_1
      17: aload_1
      18: invokevirtual #34                 // Method org/apache/hadoop/hbase/ServerLoad.obtainServerLoadPB:()Lorg/apache/hadoop/hbase/shaded/protobuf/generated/ClusterStatusProtos$ServerLoad;
      21: invokestatic  #35                 // Method org/junit/Assert.assertNotNull:(Ljava/lang/Object;)V
      24: ldc2_w        #27                 // long 4294967294l
      27: lstore_2
      28: lload_2
      29: aload_1
      30: invokevirtual #29                 // Method org/apache/hadoop/hbase/ServerLoad.getReadRequestsCount:()J
      33: invokestatic  #10                 // Method org/junit/Assert.assertEquals:(JJ)V
      36: lload_2
      37: aload_1
      38: invokevirtual #45                 // Method org/apache/hadoop/hbase/ServerLoad.getWriteRequestsCount:()J
      41: invokestatic  #10                 // Method org/junit/Assert.assertEquals:(JJ)V
      44: return

  static {};
    Code:
       0: ldc           #79                 // class org/apache/hadoop/hbase/TestServerLoad
       2: invokestatic  #80                 // Method org/apache/hadoop/hbase/HBaseClassTestRule.forClass:(Ljava/lang/Class;)Lorg/apache/hadoop/hbase/HBaseClassTestRule;
       5: putstatic     #81                 // Field CLASS_RULE:Lorg/apache/hadoop/hbase/HBaseClassTestRule;
       8: return
}
