Compiled from "TestHStore.java"
public class org.apache.hadoop.hbase.regionserver.TestHStore$MyCompactingMemStore extends org.apache.hadoop.hbase.regionserver.CompactingMemStore {
  public org.apache.hadoop.hbase.regionserver.TestHStore$MyCompactingMemStore(org.apache.hadoop.conf.Configuration, org.apache.hadoop.hbase.CellComparatorImpl, org.apache.hadoop.hbase.regionserver.HStore, org.apache.hadoop.hbase.regionserver.RegionServicesForStores, org.apache.hadoop.hbase.MemoryCompactionPolicy) throws java.io.IOException;
    Code:
       0: aload_0
       1: aload_1
       2: aload_2
       3: aload_3
       4: aload         4
       6: aload         5
       8: invokespecial #2                  // Method org/apache/hadoop/hbase/regionserver/CompactingMemStore."<init>":(Lorg/apache/hadoop/conf/Configuration;Lorg/apache/hadoop/hbase/CellComparator;Lorg/apache/hadoop/hbase/regionserver/HStore;Lorg/apache/hadoop/hbase/regionserver/RegionServicesForStores;Lorg/apache/hadoop/hbase/MemoryCompactionPolicy;)V
      11: aload_0
      12: new           #3                  // class java/util/concurrent/CountDownLatch
      15: dup
      16: iconst_1
      17: invokespecial #4                  // Method java/util/concurrent/CountDownLatch."<init>":(I)V
      20: putfield      #5                  // Field getScannerLatch:Ljava/util/concurrent/CountDownLatch;
      23: aload_0
      24: new           #3                  // class java/util/concurrent/CountDownLatch
      27: dup
      28: iconst_1
      29: invokespecial #4                  // Method java/util/concurrent/CountDownLatch."<init>":(I)V
      32: putfield      #6                  // Field snapshotLatch:Ljava/util/concurrent/CountDownLatch;
      35: return

  protected java.util.List<org.apache.hadoop.hbase.regionserver.KeyValueScanner> createList(int);
    Code:
       0: getstatic     #1                  // Field START_TEST:Ljava/util/concurrent/atomic/AtomicBoolean;
       3: invokevirtual #7                  // Method java/util/concurrent/atomic/AtomicBoolean.get:()Z
       6: ifeq          36
       9: aload_0
      10: getfield      #5                  // Field getScannerLatch:Ljava/util/concurrent/CountDownLatch;
      13: invokevirtual #8                  // Method java/util/concurrent/CountDownLatch.countDown:()V
      16: aload_0
      17: getfield      #6                  // Field snapshotLatch:Ljava/util/concurrent/CountDownLatch;
      20: invokevirtual #9                  // Method java/util/concurrent/CountDownLatch.await:()V
      23: goto          36
      26: astore_2
      27: new           #11                 // class java/lang/RuntimeException
      30: dup
      31: aload_2
      32: invokespecial #12                 // Method java/lang/RuntimeException."<init>":(Ljava/lang/Throwable;)V
      35: athrow
      36: new           #13                 // class java/util/ArrayList
      39: dup
      40: iload_1
      41: invokespecial #14                 // Method java/util/ArrayList."<init>":(I)V
      44: areturn
    Exception table:
       from    to  target type
           9    23    26   Class java/lang/InterruptedException

  protected void pushActiveToPipeline(org.apache.hadoop.hbase.regionserver.MutableSegment);
    Code:
       0: getstatic     #1                  // Field START_TEST:Ljava/util/concurrent/atomic/AtomicBoolean;
       3: invokevirtual #7                  // Method java/util/concurrent/atomic/AtomicBoolean.get:()Z
       6: ifeq          29
       9: aload_0
      10: getfield      #5                  // Field getScannerLatch:Ljava/util/concurrent/CountDownLatch;
      13: invokevirtual #9                  // Method java/util/concurrent/CountDownLatch.await:()V
      16: goto          29
      19: astore_2
      20: new           #11                 // class java/lang/RuntimeException
      23: dup
      24: aload_2
      25: invokespecial #12                 // Method java/lang/RuntimeException."<init>":(Ljava/lang/Throwable;)V
      28: athrow
      29: aload_0
      30: aload_1
      31: invokespecial #15                 // Method org/apache/hadoop/hbase/regionserver/CompactingMemStore.pushActiveToPipeline:(Lorg/apache/hadoop/hbase/regionserver/MutableSegment;)V
      34: getstatic     #1                  // Field START_TEST:Ljava/util/concurrent/atomic/AtomicBoolean;
      37: invokevirtual #7                  // Method java/util/concurrent/atomic/AtomicBoolean.get:()Z
      40: ifeq          50
      43: aload_0
      44: getfield      #6                  // Field snapshotLatch:Ljava/util/concurrent/CountDownLatch;
      47: invokevirtual #8                  // Method java/util/concurrent/CountDownLatch.countDown:()V
      50: return
    Exception table:
       from    to  target type
           9    16    19   Class java/lang/InterruptedException

  static java.util.concurrent.atomic.AtomicBoolean access$500();
    Code:
       0: getstatic     #1                  // Field START_TEST:Ljava/util/concurrent/atomic/AtomicBoolean;
       3: areturn

  static {};
    Code:
       0: new           #16                 // class java/util/concurrent/atomic/AtomicBoolean
       3: dup
       4: iconst_0
       5: invokespecial #17                 // Method java/util/concurrent/atomic/AtomicBoolean."<init>":(Z)V
       8: putstatic     #1                  // Field START_TEST:Ljava/util/concurrent/atomic/AtomicBoolean;
      11: return
}
