Compiled from "TestColumnPrefixFilter.java"
public class org.apache.hadoop.hbase.filter.TestColumnPrefixFilter {
  public static final org.apache.hadoop.hbase.HBaseClassTestRule CLASS_RULE;

  public org.junit.rules.TestName name;

  public org.apache.hadoop.hbase.filter.TestColumnPrefixFilter();
    Code:
       0: aload_0
       1: invokespecial #1                  // Method java/lang/Object."<init>":()V
       4: aload_0
       5: new           #2                  // class org/junit/rules/TestName
       8: dup
       9: invokespecial #3                  // Method org/junit/rules/TestName."<init>":()V
      12: putfield      #4                  // Field name:Lorg/junit/rules/TestName;
      15: return

  public void testColumnPrefixFilter() throws java.io.IOException;
    Code:
       0: ldc           #5                  // String Family
       2: astore_1
       3: new           #6                  // class org/apache/hadoop/hbase/HTableDescriptor
       6: dup
       7: aload_0
       8: getfield      #4                  // Field name:Lorg/junit/rules/TestName;
      11: invokevirtual #7                  // Method org/junit/rules/TestName.getMethodName:()Ljava/lang/String;
      14: invokestatic  #8                  // Method org/apache/hadoop/hbase/TableName.valueOf:(Ljava/lang/String;)Lorg/apache/hadoop/hbase/TableName;
      17: invokespecial #9                  // Method org/apache/hadoop/hbase/HTableDescriptor."<init>":(Lorg/apache/hadoop/hbase/TableName;)V
      20: astore_2
      21: aload_2
      22: new           #10                 // class org/apache/hadoop/hbase/HColumnDescriptor
      25: dup
      26: aload_1
      27: invokespecial #11                 // Method org/apache/hadoop/hbase/HColumnDescriptor."<init>":(Ljava/lang/String;)V
      30: iconst_3
      31: invokevirtual #12                 // Method org/apache/hadoop/hbase/HColumnDescriptor.setMaxVersions:(I)Lorg/apache/hadoop/hbase/HColumnDescriptor;
      34: invokevirtual #13                 // Method org/apache/hadoop/hbase/HTableDescriptor.addFamily:(Lorg/apache/hadoop/hbase/HColumnDescriptor;)Lorg/apache/hadoop/hbase/HTableDescriptor;
      37: pop
      38: new           #14                 // class org/apache/hadoop/hbase/HRegionInfo
      41: dup
      42: aload_2
      43: invokevirtual #15                 // Method org/apache/hadoop/hbase/HTableDescriptor.getTableName:()Lorg/apache/hadoop/hbase/TableName;
      46: aconst_null
      47: aconst_null
      48: iconst_0
      49: invokespecial #16                 // Method org/apache/hadoop/hbase/HRegionInfo."<init>":(Lorg/apache/hadoop/hbase/TableName;[B[BZ)V
      52: astore_3
      53: aload_3
      54: getstatic     #17                 // Field TEST_UTIL:Lorg/apache/hadoop/hbase/HBaseTestingUtility;
      57: invokevirtual #18                 // Method org/apache/hadoop/hbase/HBaseTestingUtility.getDataTestDir:()Lorg/apache/hadoop/fs/Path;
      60: getstatic     #17                 // Field TEST_UTIL:Lorg/apache/hadoop/hbase/HBaseTestingUtility;
      63: invokevirtual #19                 // Method org/apache/hadoop/hbase/HBaseTestingUtility.getConfiguration:()Lorg/apache/hadoop/conf/Configuration;
      66: aload_2
      67: invokestatic  #20                 // Method org/apache/hadoop/hbase/HBaseTestingUtility.createRegionAndWAL:(Lorg/apache/hadoop/hbase/client/RegionInfo;Lorg/apache/hadoop/fs/Path;Lorg/apache/hadoop/conf/Configuration;Lorg/apache/hadoop/hbase/client/TableDescriptor;)Lorg/apache/hadoop/hbase/regionserver/HRegion;
      70: astore        4
      72: aload_0
      73: bipush        100
      75: ldc           #21                 // String row
      77: invokevirtual #22                 // Method generateRandomWords:(ILjava/lang/String;)Ljava/util/List;
      80: astore        5
      82: aload_0
      83: sipush        10000
      86: ldc           #23                 // String column
      88: invokevirtual #22                 // Method generateRandomWords:(ILjava/lang/String;)Ljava/util/List;
      91: astore        6
      93: ldc2_w        #24                 // long 2l
      96: lstore        7
      98: new           #26                 // class java/util/ArrayList
     101: dup
     102: invokespecial #27                 // Method java/util/ArrayList."<init>":()V
     105: astore        9
     107: new           #28                 // class java/util/HashMap
     110: dup
     111: invokespecial #29                 // Method java/util/HashMap."<init>":()V
     114: astore        10
     116: aload         10
     118: ldc           #30                 // String p
     120: new           #26                 // class java/util/ArrayList
     123: dup
     124: invokespecial #27                 // Method java/util/ArrayList."<init>":()V
     127: invokeinterface #31,  3           // InterfaceMethod java/util/Map.put:(Ljava/lang/Object;Ljava/lang/Object;)Ljava/lang/Object;
     132: pop
     133: aload         10
     135: ldc           #32                 // String s
     137: new           #26                 // class java/util/ArrayList
     140: dup
     141: invokespecial #27                 // Method java/util/ArrayList."<init>":()V
     144: invokeinterface #31,  3           // InterfaceMethod java/util/Map.put:(Ljava/lang/Object;Ljava/lang/Object;)Ljava/lang/Object;
     149: pop
     150: ldc           #33                 // String ValueString
     152: astore        11
     154: aload         5
     156: invokeinterface #34,  1           // InterfaceMethod java/util/List.iterator:()Ljava/util/Iterator;
     161: astore        12
     163: aload         12
     165: invokeinterface #35,  1           // InterfaceMethod java/util/Iterator.hasNext:()Z
     170: ifeq          373
     173: aload         12
     175: invokeinterface #36,  1           // InterfaceMethod java/util/Iterator.next:()Ljava/lang/Object;
     180: checkcast     #37                 // class java/lang/String
     183: astore        13
     185: new           #38                 // class org/apache/hadoop/hbase/client/Put
     188: dup
     189: aload         13
     191: invokestatic  #39                 // Method org/apache/hadoop/hbase/util/Bytes.toBytes:(Ljava/lang/String;)[B
     194: invokespecial #40                 // Method org/apache/hadoop/hbase/client/Put."<init>":([B)V
     197: astore        14
     199: aload         14
     201: getstatic     #41                 // Field org/apache/hadoop/hbase/client/Durability.SKIP_WAL:Lorg/apache/hadoop/hbase/client/Durability;
     204: invokevirtual #42                 // Method org/apache/hadoop/hbase/client/Put.setDurability:(Lorg/apache/hadoop/hbase/client/Durability;)Lorg/apache/hadoop/hbase/client/Put;
     207: pop
     208: aload         6
     210: invokeinterface #34,  1           // InterfaceMethod java/util/List.iterator:()Ljava/util/Iterator;
     215: astore        15
     217: aload         15
     219: invokeinterface #35,  1           // InterfaceMethod java/util/Iterator.hasNext:()Z
     224: ifeq          363
     227: aload         15
     229: invokeinterface #36,  1           // InterfaceMethod java/util/Iterator.next:()Ljava/lang/Object;
     234: checkcast     #37                 // class java/lang/String
     237: astore        16
     239: lconst_1
     240: lstore        17
     242: lload         17
     244: lload         7
     246: lcmp
     247: ifgt          360
     250: aload         13
     252: aload_1
     253: aload         16
     255: lload         17
     257: aload         11
     259: invokestatic  #43                 // Method org/apache/hadoop/hbase/KeyValueTestUtil.create:(Ljava/lang/String;Ljava/lang/String;Ljava/lang/String;JLjava/lang/String;)Lorg/apache/hadoop/hbase/KeyValue;
     262: astore        19
     264: aload         14
     266: aload         19
     268: invokevirtual #44                 // Method org/apache/hadoop/hbase/client/Put.add:(Lorg/apache/hadoop/hbase/Cell;)Lorg/apache/hadoop/hbase/client/Put;
     271: pop
     272: aload         9
     274: aload         19
     276: invokeinterface #45,  2           // InterfaceMethod java/util/List.add:(Ljava/lang/Object;)Z
     281: pop
     282: aload         10
     284: invokeinterface #46,  1           // InterfaceMethod java/util/Map.keySet:()Ljava/util/Set;
     289: invokeinterface #47,  1           // InterfaceMethod java/util/Set.iterator:()Ljava/util/Iterator;
     294: astore        20
     296: aload         20
     298: invokeinterface #35,  1           // InterfaceMethod java/util/Iterator.hasNext:()Z
     303: ifeq          351
     306: aload         20
     308: invokeinterface #36,  1           // InterfaceMethod java/util/Iterator.next:()Ljava/lang/Object;
     313: checkcast     #37                 // class java/lang/String
     316: astore        21
     318: aload         16
     320: aload         21
     322: invokevirtual #48                 // Method java/lang/String.startsWith:(Ljava/lang/String;)Z
     325: ifeq          348
     328: aload         10
     330: aload         21
     332: invokeinterface #49,  2           // InterfaceMethod java/util/Map.get:(Ljava/lang/Object;)Ljava/lang/Object;
     337: checkcast     #50                 // class java/util/List
     340: aload         19
     342: invokeinterface #45,  2           // InterfaceMethod java/util/List.add:(Ljava/lang/Object;)Z
     347: pop
     348: goto          296
     351: lload         17
     353: lconst_1
     354: ladd
     355: lstore        17
     357: goto          242
     360: goto          217
     363: aload         4
     365: aload         14
     367: invokevirtual #51                 // Method org/apache/hadoop/hbase/regionserver/HRegion.put:(Lorg/apache/hadoop/hbase/client/Put;)V
     370: goto          163
     373: new           #52                 // class org/apache/hadoop/hbase/client/Scan
     376: dup
     377: invokespecial #53                 // Method org/apache/hadoop/hbase/client/Scan."<init>":()V
     380: astore        13
     382: aload         13
     384: invokevirtual #54                 // Method org/apache/hadoop/hbase/client/Scan.setMaxVersions:()Lorg/apache/hadoop/hbase/client/Scan;
     387: pop
     388: aload         10
     390: invokeinterface #46,  1           // InterfaceMethod java/util/Map.keySet:()Ljava/util/Set;
     395: invokeinterface #47,  1           // InterfaceMethod java/util/Set.iterator:()Ljava/util/Iterator;
     400: astore        14
     402: aload         14
     404: invokeinterface #35,  1           // InterfaceMethod java/util/Iterator.hasNext:()Z
     409: ifeq          511
     412: aload         14
     414: invokeinterface #36,  1           // InterfaceMethod java/util/Iterator.next:()Ljava/lang/Object;
     419: checkcast     #37                 // class java/lang/String
     422: astore        15
     424: new           #55                 // class org/apache/hadoop/hbase/filter/ColumnPrefixFilter
     427: dup
     428: aload         15
     430: invokestatic  #39                 // Method org/apache/hadoop/hbase/util/Bytes.toBytes:(Ljava/lang/String;)[B
     433: invokespecial #56                 // Method org/apache/hadoop/hbase/filter/ColumnPrefixFilter."<init>":([B)V
     436: astore        12
     438: aload         13
     440: aload         12
     442: invokevirtual #57                 // Method org/apache/hadoop/hbase/client/Scan.setFilter:(Lorg/apache/hadoop/hbase/filter/Filter;)Lorg/apache/hadoop/hbase/client/Scan;
     445: pop
     446: aload         4
     448: aload         13
     450: invokevirtual #58                 // Method org/apache/hadoop/hbase/regionserver/HRegion.getScanner:(Lorg/apache/hadoop/hbase/client/Scan;)Lorg/apache/hadoop/hbase/regionserver/HRegion$RegionScannerImpl;
     453: astore        16
     455: new           #26                 // class java/util/ArrayList
     458: dup
     459: invokespecial #27                 // Method java/util/ArrayList."<init>":()V
     462: astore        17
     464: aload         16
     466: aload         17
     468: invokeinterface #59,  2           // InterfaceMethod org/apache/hadoop/hbase/regionserver/InternalScanner.next:(Ljava/util/List;)Z
     473: ifeq          479
     476: goto          464
     479: aload         10
     481: aload         15
     483: invokeinterface #49,  2           // InterfaceMethod java/util/Map.get:(Ljava/lang/Object;)Ljava/lang/Object;
     488: checkcast     #50                 // class java/util/List
     491: invokeinterface #60,  1           // InterfaceMethod java/util/List.size:()I
     496: i2l
     497: aload         17
     499: invokeinterface #60,  1           // InterfaceMethod java/util/List.size:()I
     504: i2l
     505: invokestatic  #61                 // Method org/junit/Assert.assertEquals:(JJ)V
     508: goto          402
     511: aload         4
     513: invokestatic  #62                 // Method org/apache/hadoop/hbase/HBaseTestingUtility.closeRegionAndWAL:(Lorg/apache/hadoop/hbase/regionserver/HRegion;)V
     516: goto          529
     519: astore        22
     521: aload         4
     523: invokestatic  #62                 // Method org/apache/hadoop/hbase/HBaseTestingUtility.closeRegionAndWAL:(Lorg/apache/hadoop/hbase/regionserver/HRegion;)V
     526: aload         22
     528: athrow
     529: aload         4
     531: invokestatic  #62                 // Method org/apache/hadoop/hbase/HBaseTestingUtility.closeRegionAndWAL:(Lorg/apache/hadoop/hbase/regionserver/HRegion;)V
     534: return
    Exception table:
       from    to  target type
          72   511   519   any
         519   521   519   any

  public void testColumnPrefixFilterWithFilterList() throws java.io.IOException;
    Code:
       0: ldc           #5                  // String Family
       2: astore_1
       3: new           #6                  // class org/apache/hadoop/hbase/HTableDescriptor
       6: dup
       7: aload_0
       8: getfield      #4                  // Field name:Lorg/junit/rules/TestName;
      11: invokevirtual #7                  // Method org/junit/rules/TestName.getMethodName:()Ljava/lang/String;
      14: invokestatic  #8                  // Method org/apache/hadoop/hbase/TableName.valueOf:(Ljava/lang/String;)Lorg/apache/hadoop/hbase/TableName;
      17: invokespecial #9                  // Method org/apache/hadoop/hbase/HTableDescriptor."<init>":(Lorg/apache/hadoop/hbase/TableName;)V
      20: astore_2
      21: aload_2
      22: new           #10                 // class org/apache/hadoop/hbase/HColumnDescriptor
      25: dup
      26: aload_1
      27: invokespecial #11                 // Method org/apache/hadoop/hbase/HColumnDescriptor."<init>":(Ljava/lang/String;)V
      30: iconst_3
      31: invokevirtual #12                 // Method org/apache/hadoop/hbase/HColumnDescriptor.setMaxVersions:(I)Lorg/apache/hadoop/hbase/HColumnDescriptor;
      34: invokevirtual #13                 // Method org/apache/hadoop/hbase/HTableDescriptor.addFamily:(Lorg/apache/hadoop/hbase/HColumnDescriptor;)Lorg/apache/hadoop/hbase/HTableDescriptor;
      37: pop
      38: new           #14                 // class org/apache/hadoop/hbase/HRegionInfo
      41: dup
      42: aload_2
      43: invokevirtual #15                 // Method org/apache/hadoop/hbase/HTableDescriptor.getTableName:()Lorg/apache/hadoop/hbase/TableName;
      46: aconst_null
      47: aconst_null
      48: iconst_0
      49: invokespecial #16                 // Method org/apache/hadoop/hbase/HRegionInfo."<init>":(Lorg/apache/hadoop/hbase/TableName;[B[BZ)V
      52: astore_3
      53: aload_3
      54: getstatic     #17                 // Field TEST_UTIL:Lorg/apache/hadoop/hbase/HBaseTestingUtility;
      57: invokevirtual #18                 // Method org/apache/hadoop/hbase/HBaseTestingUtility.getDataTestDir:()Lorg/apache/hadoop/fs/Path;
      60: getstatic     #17                 // Field TEST_UTIL:Lorg/apache/hadoop/hbase/HBaseTestingUtility;
      63: invokevirtual #19                 // Method org/apache/hadoop/hbase/HBaseTestingUtility.getConfiguration:()Lorg/apache/hadoop/conf/Configuration;
      66: aload_2
      67: invokestatic  #20                 // Method org/apache/hadoop/hbase/HBaseTestingUtility.createRegionAndWAL:(Lorg/apache/hadoop/hbase/client/RegionInfo;Lorg/apache/hadoop/fs/Path;Lorg/apache/hadoop/conf/Configuration;Lorg/apache/hadoop/hbase/client/TableDescriptor;)Lorg/apache/hadoop/hbase/regionserver/HRegion;
      70: astore        4
      72: aload_0
      73: bipush        100
      75: ldc           #21                 // String row
      77: invokevirtual #22                 // Method generateRandomWords:(ILjava/lang/String;)Ljava/util/List;
      80: astore        5
      82: aload_0
      83: sipush        10000
      86: ldc           #23                 // String column
      88: invokevirtual #22                 // Method generateRandomWords:(ILjava/lang/String;)Ljava/util/List;
      91: astore        6
      93: ldc2_w        #24                 // long 2l
      96: lstore        7
      98: new           #26                 // class java/util/ArrayList
     101: dup
     102: invokespecial #27                 // Method java/util/ArrayList."<init>":()V
     105: astore        9
     107: new           #28                 // class java/util/HashMap
     110: dup
     111: invokespecial #29                 // Method java/util/HashMap."<init>":()V
     114: astore        10
     116: aload         10
     118: ldc           #30                 // String p
     120: new           #26                 // class java/util/ArrayList
     123: dup
     124: invokespecial #27                 // Method java/util/ArrayList."<init>":()V
     127: invokeinterface #31,  3           // InterfaceMethod java/util/Map.put:(Ljava/lang/Object;Ljava/lang/Object;)Ljava/lang/Object;
     132: pop
     133: aload         10
     135: ldc           #32                 // String s
     137: new           #26                 // class java/util/ArrayList
     140: dup
     141: invokespecial #27                 // Method java/util/ArrayList."<init>":()V
     144: invokeinterface #31,  3           // InterfaceMethod java/util/Map.put:(Ljava/lang/Object;Ljava/lang/Object;)Ljava/lang/Object;
     149: pop
     150: ldc           #33                 // String ValueString
     152: astore        11
     154: aload         5
     156: invokeinterface #34,  1           // InterfaceMethod java/util/List.iterator:()Ljava/util/Iterator;
     161: astore        12
     163: aload         12
     165: invokeinterface #35,  1           // InterfaceMethod java/util/Iterator.hasNext:()Z
     170: ifeq          373
     173: aload         12
     175: invokeinterface #36,  1           // InterfaceMethod java/util/Iterator.next:()Ljava/lang/Object;
     180: checkcast     #37                 // class java/lang/String
     183: astore        13
     185: new           #38                 // class org/apache/hadoop/hbase/client/Put
     188: dup
     189: aload         13
     191: invokestatic  #39                 // Method org/apache/hadoop/hbase/util/Bytes.toBytes:(Ljava/lang/String;)[B
     194: invokespecial #40                 // Method org/apache/hadoop/hbase/client/Put."<init>":([B)V
     197: astore        14
     199: aload         14
     201: getstatic     #41                 // Field org/apache/hadoop/hbase/client/Durability.SKIP_WAL:Lorg/apache/hadoop/hbase/client/Durability;
     204: invokevirtual #42                 // Method org/apache/hadoop/hbase/client/Put.setDurability:(Lorg/apache/hadoop/hbase/client/Durability;)Lorg/apache/hadoop/hbase/client/Put;
     207: pop
     208: aload         6
     210: invokeinterface #34,  1           // InterfaceMethod java/util/List.iterator:()Ljava/util/Iterator;
     215: astore        15
     217: aload         15
     219: invokeinterface #35,  1           // InterfaceMethod java/util/Iterator.hasNext:()Z
     224: ifeq          363
     227: aload         15
     229: invokeinterface #36,  1           // InterfaceMethod java/util/Iterator.next:()Ljava/lang/Object;
     234: checkcast     #37                 // class java/lang/String
     237: astore        16
     239: lconst_1
     240: lstore        17
     242: lload         17
     244: lload         7
     246: lcmp
     247: ifgt          360
     250: aload         13
     252: aload_1
     253: aload         16
     255: lload         17
     257: aload         11
     259: invokestatic  #43                 // Method org/apache/hadoop/hbase/KeyValueTestUtil.create:(Ljava/lang/String;Ljava/lang/String;Ljava/lang/String;JLjava/lang/String;)Lorg/apache/hadoop/hbase/KeyValue;
     262: astore        19
     264: aload         14
     266: aload         19
     268: invokevirtual #44                 // Method org/apache/hadoop/hbase/client/Put.add:(Lorg/apache/hadoop/hbase/Cell;)Lorg/apache/hadoop/hbase/client/Put;
     271: pop
     272: aload         9
     274: aload         19
     276: invokeinterface #45,  2           // InterfaceMethod java/util/List.add:(Ljava/lang/Object;)Z
     281: pop
     282: aload         10
     284: invokeinterface #46,  1           // InterfaceMethod java/util/Map.keySet:()Ljava/util/Set;
     289: invokeinterface #47,  1           // InterfaceMethod java/util/Set.iterator:()Ljava/util/Iterator;
     294: astore        20
     296: aload         20
     298: invokeinterface #35,  1           // InterfaceMethod java/util/Iterator.hasNext:()Z
     303: ifeq          351
     306: aload         20
     308: invokeinterface #36,  1           // InterfaceMethod java/util/Iterator.next:()Ljava/lang/Object;
     313: checkcast     #37                 // class java/lang/String
     316: astore        21
     318: aload         16
     320: aload         21
     322: invokevirtual #48                 // Method java/lang/String.startsWith:(Ljava/lang/String;)Z
     325: ifeq          348
     328: aload         10
     330: aload         21
     332: invokeinterface #49,  2           // InterfaceMethod java/util/Map.get:(Ljava/lang/Object;)Ljava/lang/Object;
     337: checkcast     #50                 // class java/util/List
     340: aload         19
     342: invokeinterface #45,  2           // InterfaceMethod java/util/List.add:(Ljava/lang/Object;)Z
     347: pop
     348: goto          296
     351: lload         17
     353: lconst_1
     354: ladd
     355: lstore        17
     357: goto          242
     360: goto          217
     363: aload         4
     365: aload         14
     367: invokevirtual #51                 // Method org/apache/hadoop/hbase/regionserver/HRegion.put:(Lorg/apache/hadoop/hbase/client/Put;)V
     370: goto          163
     373: new           #52                 // class org/apache/hadoop/hbase/client/Scan
     376: dup
     377: invokespecial #53                 // Method org/apache/hadoop/hbase/client/Scan."<init>":()V
     380: astore        13
     382: aload         13
     384: invokevirtual #54                 // Method org/apache/hadoop/hbase/client/Scan.setMaxVersions:()Lorg/apache/hadoop/hbase/client/Scan;
     387: pop
     388: aload         10
     390: invokeinterface #46,  1           // InterfaceMethod java/util/Map.keySet:()Ljava/util/Set;
     395: invokeinterface #47,  1           // InterfaceMethod java/util/Set.iterator:()Ljava/util/Iterator;
     400: astore        14
     402: aload         14
     404: invokeinterface #35,  1           // InterfaceMethod java/util/Iterator.hasNext:()Z
     409: ifeq          530
     412: aload         14
     414: invokeinterface #36,  1           // InterfaceMethod java/util/Iterator.next:()Ljava/lang/Object;
     419: checkcast     #37                 // class java/lang/String
     422: astore        15
     424: new           #55                 // class org/apache/hadoop/hbase/filter/ColumnPrefixFilter
     427: dup
     428: aload         15
     430: invokestatic  #39                 // Method org/apache/hadoop/hbase/util/Bytes.toBytes:(Ljava/lang/String;)[B
     433: invokespecial #56                 // Method org/apache/hadoop/hbase/filter/ColumnPrefixFilter."<init>":([B)V
     436: astore        12
     438: new           #63                 // class org/apache/hadoop/hbase/filter/FilterList
     441: dup
     442: getstatic     #64                 // Field org/apache/hadoop/hbase/filter/FilterList$Operator.MUST_PASS_ALL:Lorg/apache/hadoop/hbase/filter/FilterList$Operator;
     445: invokespecial #65                 // Method org/apache/hadoop/hbase/filter/FilterList."<init>":(Lorg/apache/hadoop/hbase/filter/FilterList$Operator;)V
     448: astore        16
     450: aload         16
     452: aload         12
     454: invokevirtual #66                 // Method org/apache/hadoop/hbase/filter/FilterList.addFilter:(Lorg/apache/hadoop/hbase/filter/Filter;)V
     457: aload         13
     459: aload         16
     461: invokevirtual #57                 // Method org/apache/hadoop/hbase/client/Scan.setFilter:(Lorg/apache/hadoop/hbase/filter/Filter;)Lorg/apache/hadoop/hbase/client/Scan;
     464: pop
     465: aload         4
     467: aload         13
     469: invokevirtual #58                 // Method org/apache/hadoop/hbase/regionserver/HRegion.getScanner:(Lorg/apache/hadoop/hbase/client/Scan;)Lorg/apache/hadoop/hbase/regionserver/HRegion$RegionScannerImpl;
     472: astore        17
     474: new           #26                 // class java/util/ArrayList
     477: dup
     478: invokespecial #27                 // Method java/util/ArrayList."<init>":()V
     481: astore        18
     483: aload         17
     485: aload         18
     487: invokeinterface #59,  2           // InterfaceMethod org/apache/hadoop/hbase/regionserver/InternalScanner.next:(Ljava/util/List;)Z
     492: ifeq          498
     495: goto          483
     498: aload         10
     500: aload         15
     502: invokeinterface #49,  2           // InterfaceMethod java/util/Map.get:(Ljava/lang/Object;)Ljava/lang/Object;
     507: checkcast     #50                 // class java/util/List
     510: invokeinterface #60,  1           // InterfaceMethod java/util/List.size:()I
     515: i2l
     516: aload         18
     518: invokeinterface #60,  1           // InterfaceMethod java/util/List.size:()I
     523: i2l
     524: invokestatic  #61                 // Method org/junit/Assert.assertEquals:(JJ)V
     527: goto          402
     530: aload         4
     532: invokestatic  #62                 // Method org/apache/hadoop/hbase/HBaseTestingUtility.closeRegionAndWAL:(Lorg/apache/hadoop/hbase/regionserver/HRegion;)V
     535: goto          548
     538: astore        22
     540: aload         4
     542: invokestatic  #62                 // Method org/apache/hadoop/hbase/HBaseTestingUtility.closeRegionAndWAL:(Lorg/apache/hadoop/hbase/regionserver/HRegion;)V
     545: aload         22
     547: athrow
     548: aload         4
     550: invokestatic  #62                 // Method org/apache/hadoop/hbase/HBaseTestingUtility.closeRegionAndWAL:(Lorg/apache/hadoop/hbase/regionserver/HRegion;)V
     553: return
    Exception table:
       from    to  target type
          72   530   538   any
         538   540   538   any

  java.util.List<java.lang.String> generateRandomWords(int, java.lang.String);
    Code:
       0: new           #67                 // class java/util/HashSet
       3: dup
       4: invokespecial #68                 // Method java/util/HashSet."<init>":()V
       7: astore_3
       8: iconst_0
       9: istore        4
      11: iload         4
      13: iload_1
      14: if_icmpge     131
      17: invokestatic  #69                 // Method java/lang/Math.random:()D
      20: ldc2_w        #70                 // double 2.0d
      23: dmul
      24: d2i
      25: iconst_1
      26: iadd
      27: istore        5
      29: iload         5
      31: newarray       char
      33: astore        6
      35: iconst_0
      36: istore        7
      38: iload         7
      40: aload         6
      42: arraylength
      43: if_icmpge     70
      46: aload         6
      48: iload         7
      50: invokestatic  #69                 // Method java/lang/Math.random:()D
      53: ldc2_w        #72                 // double 26.0d
      56: dmul
      57: ldc2_w        #74                 // double 97.0d
      60: dadd
      61: d2i
      62: i2c
      63: castore
      64: iinc          7, 1
      67: goto          38
      70: aload_2
      71: ifnonnull     88
      74: new           #37                 // class java/lang/String
      77: dup
      78: aload         6
      80: invokespecial #76                 // Method java/lang/String."<init>":([C)V
      83: astore        7
      85: goto          116
      88: new           #77                 // class java/lang/StringBuilder
      91: dup
      92: invokespecial #78                 // Method java/lang/StringBuilder."<init>":()V
      95: new           #37                 // class java/lang/String
      98: dup
      99: aload         6
     101: invokespecial #76                 // Method java/lang/String."<init>":([C)V
     104: invokevirtual #79                 // Method java/lang/StringBuilder.append:(Ljava/lang/String;)Ljava/lang/StringBuilder;
     107: aload_2
     108: invokevirtual #79                 // Method java/lang/StringBuilder.append:(Ljava/lang/String;)Ljava/lang/StringBuilder;
     111: invokevirtual #80                 // Method java/lang/StringBuilder.toString:()Ljava/lang/String;
     114: astore        7
     116: aload_3
     117: aload         7
     119: invokeinterface #81,  2           // InterfaceMethod java/util/Set.add:(Ljava/lang/Object;)Z
     124: pop
     125: iinc          4, 1
     128: goto          11
     131: new           #26                 // class java/util/ArrayList
     134: dup
     135: aload_3
     136: invokespecial #82                 // Method java/util/ArrayList."<init>":(Ljava/util/Collection;)V
     139: astore        4
     141: aload         4
     143: areturn

  static {};
    Code:
       0: ldc           #83                 // class org/apache/hadoop/hbase/filter/TestColumnPrefixFilter
       2: invokestatic  #84                 // Method org/apache/hadoop/hbase/HBaseClassTestRule.forClass:(Ljava/lang/Class;)Lorg/apache/hadoop/hbase/HBaseClassTestRule;
       5: putstatic     #85                 // Field CLASS_RULE:Lorg/apache/hadoop/hbase/HBaseClassTestRule;
       8: new           #86                 // class org/apache/hadoop/hbase/HBaseTestingUtility
      11: dup
      12: invokespecial #87                 // Method org/apache/hadoop/hbase/HBaseTestingUtility."<init>":()V
      15: putstatic     #17                 // Field TEST_UTIL:Lorg/apache/hadoop/hbase/HBaseTestingUtility;
      18: return
}
