Compiled from "TestAssignmentManagerBase.java"
public class org.apache.hadoop.hbase.master.assignment.TestAssignmentManagerBase$ServerNotYetRunningRsExecutor implements org.apache.hadoop.hbase.master.assignment.TestAssignmentManagerBase$MockRSExecutor {
  protected org.apache.hadoop.hbase.master.assignment.TestAssignmentManagerBase$ServerNotYetRunningRsExecutor();
    Code:
       0: aload_0
       1: invokespecial #1                  // Method java/lang/Object."<init>":()V
       4: return

  public org.apache.hadoop.hbase.shaded.protobuf.generated.AdminProtos$ExecuteProceduresResponse sendRequest(org.apache.hadoop.hbase.ServerName, org.apache.hadoop.hbase.shaded.protobuf.generated.AdminProtos$ExecuteProceduresRequest) throws java.io.IOException;
    Code:
       0: new           #2                  // class org/apache/hadoop/hbase/ipc/ServerNotRunningYetException
       3: dup
       4: ldc           #3                  // String wait on server startup
       6: invokespecial #4                  // Method org/apache/hadoop/hbase/ipc/ServerNotRunningYetException."<init>":(Ljava/lang/String;)V
       9: athrow
}
