Compiled from "TestCompactionState.java"
public class org.apache.hadoop.hbase.regionserver.TestCompactionState {
  public static final org.apache.hadoop.hbase.HBaseClassTestRule CLASS_RULE;

  public org.junit.rules.TestName name;

  public org.apache.hadoop.hbase.regionserver.TestCompactionState();
    Code:
       0: aload_0
       1: invokespecial #1                  // Method java/lang/Object."<init>":()V
       4: aload_0
       5: new           #2                  // class org/junit/rules/TestName
       8: dup
       9: invokespecial #3                  // Method org/junit/rules/TestName."<init>":()V
      12: putfield      #4                  // Field name:Lorg/junit/rules/TestName;
      15: return

  public static void setUpBeforeClass() throws java.lang.Exception;
    Code:
       0: getstatic     #5                  // Field TEST_UTIL:Lorg/apache/hadoop/hbase/HBaseTestingUtility;
       3: invokevirtual #6                  // Method org/apache/hadoop/hbase/HBaseTestingUtility.startMiniCluster:()Lorg/apache/hadoop/hbase/MiniHBaseCluster;
       6: pop
       7: return

  public static void tearDownAfterClass() throws java.lang.Exception;
    Code:
       0: getstatic     #5                  // Field TEST_UTIL:Lorg/apache/hadoop/hbase/HBaseTestingUtility;
       3: invokevirtual #7                  // Method org/apache/hadoop/hbase/HBaseTestingUtility.shutdownMiniCluster:()V
       6: return

  public void testMajorCompaction() throws java.io.IOException, java.lang.InterruptedException;
    Code:
       0: aload_0
       1: aload_0
       2: getfield      #4                  // Field name:Lorg/junit/rules/TestName;
       5: invokevirtual #8                  // Method org/junit/rules/TestName.getMethodName:()Ljava/lang/String;
       8: bipush        8
      10: getstatic     #9                  // Field org/apache/hadoop/hbase/client/CompactionState.MAJOR:Lorg/apache/hadoop/hbase/client/CompactionState;
      13: iconst_0
      14: invokespecial #10                 // Method compaction:(Ljava/lang/String;ILorg/apache/hadoop/hbase/client/CompactionState;Z)V
      17: return

  public void testMinorCompaction() throws java.io.IOException, java.lang.InterruptedException;
    Code:
       0: aload_0
       1: aload_0
       2: getfield      #4                  // Field name:Lorg/junit/rules/TestName;
       5: invokevirtual #8                  // Method org/junit/rules/TestName.getMethodName:()Ljava/lang/String;
       8: bipush        15
      10: getstatic     #11                 // Field org/apache/hadoop/hbase/client/CompactionState.MINOR:Lorg/apache/hadoop/hbase/client/CompactionState;
      13: iconst_0
      14: invokespecial #10                 // Method compaction:(Ljava/lang/String;ILorg/apache/hadoop/hbase/client/CompactionState;Z)V
      17: return

  public void testMajorCompactionOnFamily() throws java.io.IOException, java.lang.InterruptedException;
    Code:
       0: aload_0
       1: aload_0
       2: getfield      #4                  // Field name:Lorg/junit/rules/TestName;
       5: invokevirtual #8                  // Method org/junit/rules/TestName.getMethodName:()Ljava/lang/String;
       8: bipush        8
      10: getstatic     #9                  // Field org/apache/hadoop/hbase/client/CompactionState.MAJOR:Lorg/apache/hadoop/hbase/client/CompactionState;
      13: iconst_1
      14: invokespecial #10                 // Method compaction:(Ljava/lang/String;ILorg/apache/hadoop/hbase/client/CompactionState;Z)V
      17: return

  public void testMinorCompactionOnFamily() throws java.io.IOException, java.lang.InterruptedException;
    Code:
       0: aload_0
       1: aload_0
       2: getfield      #4                  // Field name:Lorg/junit/rules/TestName;
       5: invokevirtual #8                  // Method org/junit/rules/TestName.getMethodName:()Ljava/lang/String;
       8: bipush        15
      10: getstatic     #11                 // Field org/apache/hadoop/hbase/client/CompactionState.MINOR:Lorg/apache/hadoop/hbase/client/CompactionState;
      13: iconst_1
      14: invokespecial #10                 // Method compaction:(Ljava/lang/String;ILorg/apache/hadoop/hbase/client/CompactionState;Z)V
      17: return

  public void testInvalidColumnFamily() throws java.io.IOException, java.lang.InterruptedException;
    Code:
       0: aload_0
       1: getfield      #4                  // Field name:Lorg/junit/rules/TestName;
       4: invokevirtual #8                  // Method org/junit/rules/TestName.getMethodName:()Ljava/lang/String;
       7: invokestatic  #12                 // Method org/apache/hadoop/hbase/TableName.valueOf:(Ljava/lang/String;)Lorg/apache/hadoop/hbase/TableName;
      10: astore_1
      11: ldc           #13                 // String family
      13: invokestatic  #14                 // Method org/apache/hadoop/hbase/util/Bytes.toBytes:(Ljava/lang/String;)[B
      16: astore_2
      17: ldc           #15                 // String fakecf
      19: invokestatic  #14                 // Method org/apache/hadoop/hbase/util/Bytes.toBytes:(Ljava/lang/String;)[B
      22: astore_3
      23: iconst_0
      24: istore        4
      26: iconst_0
      27: istore        5
      29: aconst_null
      30: astore        6
      32: getstatic     #5                  // Field TEST_UTIL:Lorg/apache/hadoop/hbase/HBaseTestingUtility;
      35: aload_1
      36: aload_2
      37: invokevirtual #16                 // Method org/apache/hadoop/hbase/HBaseTestingUtility.createTable:(Lorg/apache/hadoop/hbase/TableName;[B)Lorg/apache/hadoop/hbase/client/Table;
      40: astore        6
      42: getstatic     #5                  // Field TEST_UTIL:Lorg/apache/hadoop/hbase/HBaseTestingUtility;
      45: invokevirtual #17                 // Method org/apache/hadoop/hbase/HBaseTestingUtility.getAdmin:()Lorg/apache/hadoop/hbase/client/Admin;
      48: astore        7
      50: aload         7
      52: aload_1
      53: aload_3
      54: invokeinterface #18,  3           // InterfaceMethod org/apache/hadoop/hbase/client/Admin.compact:(Lorg/apache/hadoop/hbase/TableName;[B)V
      59: goto          67
      62: astore        8
      64: iconst_1
      65: istore        4
      67: aload         7
      69: aload_1
      70: aload_3
      71: invokeinterface #20,  3           // InterfaceMethod org/apache/hadoop/hbase/client/Admin.majorCompact:(Lorg/apache/hadoop/hbase/TableName;[B)V
      76: goto          84
      79: astore        8
      81: iconst_1
      82: istore        5
      84: aload         6
      86: ifnull        96
      89: getstatic     #5                  // Field TEST_UTIL:Lorg/apache/hadoop/hbase/HBaseTestingUtility;
      92: aload_1
      93: invokevirtual #21                 // Method org/apache/hadoop/hbase/HBaseTestingUtility.deleteTable:(Lorg/apache/hadoop/hbase/TableName;)V
      96: iload         4
      98: invokestatic  #22                 // Method org/junit/Assert.assertTrue:(Z)V
     101: iload         5
     103: invokestatic  #22                 // Method org/junit/Assert.assertTrue:(Z)V
     106: goto          136
     109: astore        9
     111: aload         6
     113: ifnull        123
     116: getstatic     #5                  // Field TEST_UTIL:Lorg/apache/hadoop/hbase/HBaseTestingUtility;
     119: aload_1
     120: invokevirtual #21                 // Method org/apache/hadoop/hbase/HBaseTestingUtility.deleteTable:(Lorg/apache/hadoop/hbase/TableName;)V
     123: iload         4
     125: invokestatic  #22                 // Method org/junit/Assert.assertTrue:(Z)V
     128: iload         5
     130: invokestatic  #22                 // Method org/junit/Assert.assertTrue:(Z)V
     133: aload         9
     135: athrow
     136: return
    Exception table:
       from    to  target type
          50    59    62   Class java/io/IOException
          67    76    79   Class java/io/IOException
          32    84   109   any
         109   111   109   any

  static {};
    Code:
       0: ldc           #68                 // class org/apache/hadoop/hbase/regionserver/TestCompactionState
       2: invokestatic  #69                 // Method org/apache/hadoop/hbase/HBaseClassTestRule.forClass:(Ljava/lang/Class;)Lorg/apache/hadoop/hbase/HBaseClassTestRule;
       5: putstatic     #70                 // Field CLASS_RULE:Lorg/apache/hadoop/hbase/HBaseClassTestRule;
       8: ldc           #68                 // class org/apache/hadoop/hbase/regionserver/TestCompactionState
      10: invokestatic  #71                 // Method org/slf4j/LoggerFactory.getLogger:(Ljava/lang/Class;)Lorg/slf4j/Logger;
      13: putstatic     #72                 // Field LOG:Lorg/slf4j/Logger;
      16: new           #73                 // class org/apache/hadoop/hbase/HBaseTestingUtility
      19: dup
      20: invokespecial #74                 // Method org/apache/hadoop/hbase/HBaseTestingUtility."<init>":()V
      23: putstatic     #5                  // Field TEST_UTIL:Lorg/apache/hadoop/hbase/HBaseTestingUtility;
      26: new           #75                 // class java/util/Random
      29: dup
      30: invokespecial #76                 // Method java/util/Random."<init>":()V
      33: putstatic     #58                 // Field random:Ljava/util/Random;
      36: return
}
