Compiled from "TestHStore.java"
public class org.apache.hadoop.hbase.regionserver.TestHStore$DummyStoreEngine extends org.apache.hadoop.hbase.regionserver.DefaultStoreEngine {
  public static org.apache.hadoop.hbase.regionserver.compactions.DefaultCompactor lastCreatedCompactor;

  public org.apache.hadoop.hbase.regionserver.TestHStore$DummyStoreEngine();
    Code:
       0: aload_0
       1: invokespecial #1                  // Method org/apache/hadoop/hbase/regionserver/DefaultStoreEngine."<init>":()V
       4: return

  protected void createComponents(org.apache.hadoop.conf.Configuration, org.apache.hadoop.hbase.regionserver.HStore, org.apache.hadoop.hbase.CellComparator) throws java.io.IOException;
    Code:
       0: aload_0
       1: aload_1
       2: aload_2
       3: aload_3
       4: invokespecial #2                  // Method org/apache/hadoop/hbase/regionserver/DefaultStoreEngine.createComponents:(Lorg/apache/hadoop/conf/Configuration;Lorg/apache/hadoop/hbase/regionserver/HStore;Lorg/apache/hadoop/hbase/CellComparator;)V
       7: aload_0
       8: getfield      #3                  // Field compactor:Lorg/apache/hadoop/hbase/regionserver/compactions/Compactor;
      11: checkcast     #4                  // class org/apache/hadoop/hbase/regionserver/compactions/DefaultCompactor
      14: putstatic     #5                  // Field lastCreatedCompactor:Lorg/apache/hadoop/hbase/regionserver/compactions/DefaultCompactor;
      17: return

  static {};
    Code:
       0: aconst_null
       1: putstatic     #5                  // Field lastCreatedCompactor:Lorg/apache/hadoop/hbase/regionserver/compactions/DefaultCompactor;
       4: return
}
