Compiled from "TestSpaceQuotasWithSnapshots.java"
class org.apache.hadoop.hbase.quotas.TestSpaceQuotasWithSnapshots$11 extends org.apache.hadoop.hbase.quotas.SpaceQuotaHelperForTests$SpaceQuotaSnapshotPredicate {
  final long val$actualInitialSize;

  final org.apache.hadoop.hbase.quotas.TestSpaceQuotasWithSnapshots this$0;

  org.apache.hadoop.hbase.quotas.TestSpaceQuotasWithSnapshots$11(org.apache.hadoop.hbase.quotas.TestSpaceQuotasWithSnapshots, org.apache.hadoop.hbase.client.Connection, org.apache.hadoop.hbase.TableName, long);
    Code:
       0: aload_0
       1: aload_1
       2: putfield      #1                  // Field this$0:Lorg/apache/hadoop/hbase/quotas/TestSpaceQuotasWithSnapshots;
       5: aload_0
       6: lload         4
       8: putfield      #2                  // Field val$actualInitialSize:J
      11: aload_0
      12: aload_2
      13: aload_3
      14: invokespecial #3                  // Method org/apache/hadoop/hbase/quotas/SpaceQuotaHelperForTests$SpaceQuotaSnapshotPredicate."<init>":(Lorg/apache/hadoop/hbase/client/Connection;Lorg/apache/hadoop/hbase/TableName;)V
      17: return

  boolean evaluate(org.apache.hadoop.hbase.quotas.SpaceQuotaSnapshot) throws java.lang.Exception;
    Code:
       0: aload_1
       1: invokevirtual #4                  // Method org/apache/hadoop/hbase/quotas/SpaceQuotaSnapshot.getUsage:()J
       4: aload_0
       5: getfield      #2                  // Field val$actualInitialSize:J
       8: ldc2_w        #5                  // long 2l
      11: lmul
      12: lcmp
      13: iflt          20
      16: iconst_1
      17: goto          21
      20: iconst_0
      21: ireturn
}
