Compiled from "TestCheckAndMutate.java"
public class org.apache.hadoop.hbase.client.TestCheckAndMutate {
  public static final org.apache.hadoop.hbase.HBaseClassTestRule CLASS_RULE;

  public org.junit.rules.TestName name;

  public org.apache.hadoop.hbase.client.TestCheckAndMutate();
    Code:
       0: aload_0
       1: invokespecial #1                  // Method java/lang/Object."<init>":()V
       4: aload_0
       5: new           #2                  // class org/junit/rules/TestName
       8: dup
       9: invokespecial #3                  // Method org/junit/rules/TestName."<init>":()V
      12: putfield      #4                  // Field name:Lorg/junit/rules/TestName;
      15: return

  public static void setUpBeforeClass() throws java.lang.Exception;
    Code:
       0: getstatic     #5                  // Field TEST_UTIL:Lorg/apache/hadoop/hbase/HBaseTestingUtility;
       3: invokevirtual #6                  // Method org/apache/hadoop/hbase/HBaseTestingUtility.startMiniCluster:()Lorg/apache/hadoop/hbase/MiniHBaseCluster;
       6: pop
       7: return

  public static void tearDownAfterClass() throws java.lang.Exception;
    Code:
       0: getstatic     #5                  // Field TEST_UTIL:Lorg/apache/hadoop/hbase/HBaseTestingUtility;
       3: invokevirtual #7                  // Method org/apache/hadoop/hbase/HBaseTestingUtility.shutdownMiniCluster:()V
       6: return

  public void testCheckAndMutate() throws java.lang.Throwable;
    Code:
       0: aload_0
       1: invokespecial #47                 // Method createTable:()Lorg/apache/hadoop/hbase/client/Table;
       4: astore_1
       5: aconst_null
       6: astore_2
       7: aload_0
       8: aload_1
       9: invokespecial #48                 // Method putOneRow:(Lorg/apache/hadoop/hbase/client/Table;)V
      12: aload_0
      13: aload_1
      14: invokespecial #49                 // Method getOneRowAndAssertAllExist:(Lorg/apache/hadoop/hbase/client/Table;)V
      17: aload_0
      18: invokespecial #50                 // Method makeRowMutationsWithColumnCDeleted:()Lorg/apache/hadoop/hbase/client/RowMutations;
      21: astore_3
      22: aload_1
      23: getstatic     #17                 // Field ROWKEY:[B
      26: getstatic     #10                 // Field FAMILY:[B
      29: invokeinterface #51,  3           // InterfaceMethod org/apache/hadoop/hbase/client/Table.checkAndMutate:([B[B)Lorg/apache/hadoop/hbase/client/Table$CheckAndMutateBuilder;
      34: ldc           #19                 // String A
      36: invokestatic  #20                 // Method org/apache/hadoop/hbase/util/Bytes.toBytes:(Ljava/lang/String;)[B
      39: invokeinterface #52,  2           // InterfaceMethod org/apache/hadoop/hbase/client/Table$CheckAndMutateBuilder.qualifier:([B)Lorg/apache/hadoop/hbase/client/Table$CheckAndMutateBuilder;
      44: ldc           #21                 // String a
      46: invokestatic  #20                 // Method org/apache/hadoop/hbase/util/Bytes.toBytes:(Ljava/lang/String;)[B
      49: invokeinterface #53,  2           // InterfaceMethod org/apache/hadoop/hbase/client/Table$CheckAndMutateBuilder.ifEquals:([B)Lorg/apache/hadoop/hbase/client/Table$CheckAndMutateBuilder;
      54: aload_3
      55: invokeinterface #54,  2           // InterfaceMethod org/apache/hadoop/hbase/client/Table$CheckAndMutateBuilder.thenMutate:(Lorg/apache/hadoop/hbase/client/RowMutations;)Z
      60: istore        4
      62: iload         4
      64: invokestatic  #55                 // Method org/junit/Assert.assertTrue:(Z)V
      67: aload_0
      68: aload_1
      69: invokespecial #56                 // Method getOneRowAndAssertAllButCExist:(Lorg/apache/hadoop/hbase/client/Table;)V
      72: aload_0
      73: invokespecial #57                 // Method getBogusRowMutations:()Lorg/apache/hadoop/hbase/client/RowMutations;
      76: astore_3
      77: aload_1
      78: getstatic     #17                 // Field ROWKEY:[B
      81: getstatic     #10                 // Field FAMILY:[B
      84: invokeinterface #51,  3           // InterfaceMethod org/apache/hadoop/hbase/client/Table.checkAndMutate:([B[B)Lorg/apache/hadoop/hbase/client/Table$CheckAndMutateBuilder;
      89: ldc           #19                 // String A
      91: invokestatic  #20                 // Method org/apache/hadoop/hbase/util/Bytes.toBytes:(Ljava/lang/String;)[B
      94: invokeinterface #52,  2           // InterfaceMethod org/apache/hadoop/hbase/client/Table$CheckAndMutateBuilder.qualifier:([B)Lorg/apache/hadoop/hbase/client/Table$CheckAndMutateBuilder;
      99: ldc           #21                 // String a
     101: invokestatic  #20                 // Method org/apache/hadoop/hbase/util/Bytes.toBytes:(Ljava/lang/String;)[B
     104: invokeinterface #53,  2           // InterfaceMethod org/apache/hadoop/hbase/client/Table$CheckAndMutateBuilder.ifEquals:([B)Lorg/apache/hadoop/hbase/client/Table$CheckAndMutateBuilder;
     109: aload_3
     110: invokeinterface #54,  2           // InterfaceMethod org/apache/hadoop/hbase/client/Table$CheckAndMutateBuilder.thenMutate:(Lorg/apache/hadoop/hbase/client/RowMutations;)Z
     115: pop
     116: ldc           #58                 // String Expected NoSuchColumnFamilyException
     118: invokestatic  #59                 // Method org/junit/Assert.fail:(Ljava/lang/String;)V
     121: goto          135
     124: astore        5
     126: aload         5
     128: iconst_0
     129: invokevirtual #61                 // Method org/apache/hadoop/hbase/client/RetriesExhaustedWithDetailsException.getCause:(I)Ljava/lang/Throwable;
     132: athrow
     133: astore        6
     135: aload_1
     136: ifnull        214
     139: aload_2
     140: ifnull        161
     143: aload_1
     144: invokeinterface #63,  1           // InterfaceMethod org/apache/hadoop/hbase/client/Table.close:()V
     149: goto          214
     152: astore_3
     153: aload_2
     154: aload_3
     155: invokevirtual #65                 // Method java/lang/Throwable.addSuppressed:(Ljava/lang/Throwable;)V
     158: goto          214
     161: aload_1
     162: invokeinterface #63,  1           // InterfaceMethod org/apache/hadoop/hbase/client/Table.close:()V
     167: goto          214
     170: astore_3
     171: aload_3
     172: astore_2
     173: aload_3
     174: athrow
     175: astore        7
     177: aload_1
     178: ifnull        211
     181: aload_2
     182: ifnull        205
     185: aload_1
     186: invokeinterface #63,  1           // InterfaceMethod org/apache/hadoop/hbase/client/Table.close:()V
     191: goto          211
     194: astore        8
     196: aload_2
     197: aload         8
     199: invokevirtual #65                 // Method java/lang/Throwable.addSuppressed:(Ljava/lang/Throwable;)V
     202: goto          211
     205: aload_1
     206: invokeinterface #63,  1           // InterfaceMethod org/apache/hadoop/hbase/client/Table.close:()V
     211: aload         7
     213: athrow
     214: return
    Exception table:
       from    to  target type
          72   121   124   Class org/apache/hadoop/hbase/client/RetriesExhaustedWithDetailsException
         126   133   133   Class org/apache/hadoop/hbase/regionserver/NoSuchColumnFamilyException
         143   149   152   Class java/lang/Throwable
           7   135   170   Class java/lang/Throwable
           7   135   175   any
         185   191   194   Class java/lang/Throwable
         170   177   175   any

  public void testCheckAndMutateWithBuilder() throws java.lang.Throwable;
    Code:
       0: aload_0
       1: invokespecial #47                 // Method createTable:()Lorg/apache/hadoop/hbase/client/Table;
       4: astore_1
       5: aconst_null
       6: astore_2
       7: aload_0
       8: aload_1
       9: invokespecial #48                 // Method putOneRow:(Lorg/apache/hadoop/hbase/client/Table;)V
      12: aload_0
      13: aload_1
      14: invokespecial #49                 // Method getOneRowAndAssertAllExist:(Lorg/apache/hadoop/hbase/client/Table;)V
      17: aload_0
      18: invokespecial #50                 // Method makeRowMutationsWithColumnCDeleted:()Lorg/apache/hadoop/hbase/client/RowMutations;
      21: astore_3
      22: aload_1
      23: getstatic     #17                 // Field ROWKEY:[B
      26: getstatic     #10                 // Field FAMILY:[B
      29: invokeinterface #51,  3           // InterfaceMethod org/apache/hadoop/hbase/client/Table.checkAndMutate:([B[B)Lorg/apache/hadoop/hbase/client/Table$CheckAndMutateBuilder;
      34: ldc           #19                 // String A
      36: invokestatic  #20                 // Method org/apache/hadoop/hbase/util/Bytes.toBytes:(Ljava/lang/String;)[B
      39: invokeinterface #52,  2           // InterfaceMethod org/apache/hadoop/hbase/client/Table$CheckAndMutateBuilder.qualifier:([B)Lorg/apache/hadoop/hbase/client/Table$CheckAndMutateBuilder;
      44: ldc           #21                 // String a
      46: invokestatic  #20                 // Method org/apache/hadoop/hbase/util/Bytes.toBytes:(Ljava/lang/String;)[B
      49: invokeinterface #53,  2           // InterfaceMethod org/apache/hadoop/hbase/client/Table$CheckAndMutateBuilder.ifEquals:([B)Lorg/apache/hadoop/hbase/client/Table$CheckAndMutateBuilder;
      54: aload_3
      55: invokeinterface #54,  2           // InterfaceMethod org/apache/hadoop/hbase/client/Table$CheckAndMutateBuilder.thenMutate:(Lorg/apache/hadoop/hbase/client/RowMutations;)Z
      60: istore        4
      62: iload         4
      64: invokestatic  #55                 // Method org/junit/Assert.assertTrue:(Z)V
      67: aload_0
      68: aload_1
      69: invokespecial #56                 // Method getOneRowAndAssertAllButCExist:(Lorg/apache/hadoop/hbase/client/Table;)V
      72: aload_0
      73: invokespecial #57                 // Method getBogusRowMutations:()Lorg/apache/hadoop/hbase/client/RowMutations;
      76: astore_3
      77: aload_1
      78: getstatic     #17                 // Field ROWKEY:[B
      81: getstatic     #10                 // Field FAMILY:[B
      84: invokeinterface #51,  3           // InterfaceMethod org/apache/hadoop/hbase/client/Table.checkAndMutate:([B[B)Lorg/apache/hadoop/hbase/client/Table$CheckAndMutateBuilder;
      89: ldc           #19                 // String A
      91: invokestatic  #20                 // Method org/apache/hadoop/hbase/util/Bytes.toBytes:(Ljava/lang/String;)[B
      94: invokeinterface #52,  2           // InterfaceMethod org/apache/hadoop/hbase/client/Table$CheckAndMutateBuilder.qualifier:([B)Lorg/apache/hadoop/hbase/client/Table$CheckAndMutateBuilder;
      99: ldc           #21                 // String a
     101: invokestatic  #20                 // Method org/apache/hadoop/hbase/util/Bytes.toBytes:(Ljava/lang/String;)[B
     104: invokeinterface #53,  2           // InterfaceMethod org/apache/hadoop/hbase/client/Table$CheckAndMutateBuilder.ifEquals:([B)Lorg/apache/hadoop/hbase/client/Table$CheckAndMutateBuilder;
     109: aload_3
     110: invokeinterface #54,  2           // InterfaceMethod org/apache/hadoop/hbase/client/Table$CheckAndMutateBuilder.thenMutate:(Lorg/apache/hadoop/hbase/client/RowMutations;)Z
     115: pop
     116: ldc           #58                 // String Expected NoSuchColumnFamilyException
     118: invokestatic  #59                 // Method org/junit/Assert.fail:(Ljava/lang/String;)V
     121: goto          135
     124: astore        5
     126: aload         5
     128: iconst_0
     129: invokevirtual #61                 // Method org/apache/hadoop/hbase/client/RetriesExhaustedWithDetailsException.getCause:(I)Ljava/lang/Throwable;
     132: athrow
     133: astore        6
     135: aload_1
     136: ifnull        214
     139: aload_2
     140: ifnull        161
     143: aload_1
     144: invokeinterface #63,  1           // InterfaceMethod org/apache/hadoop/hbase/client/Table.close:()V
     149: goto          214
     152: astore_3
     153: aload_2
     154: aload_3
     155: invokevirtual #65                 // Method java/lang/Throwable.addSuppressed:(Ljava/lang/Throwable;)V
     158: goto          214
     161: aload_1
     162: invokeinterface #63,  1           // InterfaceMethod org/apache/hadoop/hbase/client/Table.close:()V
     167: goto          214
     170: astore_3
     171: aload_3
     172: astore_2
     173: aload_3
     174: athrow
     175: astore        7
     177: aload_1
     178: ifnull        211
     181: aload_2
     182: ifnull        205
     185: aload_1
     186: invokeinterface #63,  1           // InterfaceMethod org/apache/hadoop/hbase/client/Table.close:()V
     191: goto          211
     194: astore        8
     196: aload_2
     197: aload         8
     199: invokevirtual #65                 // Method java/lang/Throwable.addSuppressed:(Ljava/lang/Throwable;)V
     202: goto          211
     205: aload_1
     206: invokeinterface #63,  1           // InterfaceMethod org/apache/hadoop/hbase/client/Table.close:()V
     211: aload         7
     213: athrow
     214: return
    Exception table:
       from    to  target type
          72   121   124   Class org/apache/hadoop/hbase/client/RetriesExhaustedWithDetailsException
         126   133   133   Class org/apache/hadoop/hbase/regionserver/NoSuchColumnFamilyException
         143   149   152   Class java/lang/Throwable
           7   135   170   Class java/lang/Throwable
           7   135   175   any
         185   191   194   Class java/lang/Throwable
         170   177   175   any

  static {};
    Code:
       0: ldc           #66                 // class org/apache/hadoop/hbase/client/TestCheckAndMutate
       2: invokestatic  #67                 // Method org/apache/hadoop/hbase/HBaseClassTestRule.forClass:(Ljava/lang/Class;)Lorg/apache/hadoop/hbase/HBaseClassTestRule;
       5: putstatic     #68                 // Field CLASS_RULE:Lorg/apache/hadoop/hbase/HBaseClassTestRule;
       8: new           #69                 // class org/apache/hadoop/hbase/HBaseTestingUtility
      11: dup
      12: invokespecial #70                 // Method org/apache/hadoop/hbase/HBaseTestingUtility."<init>":()V
      15: putstatic     #5                  // Field TEST_UTIL:Lorg/apache/hadoop/hbase/HBaseTestingUtility;
      18: ldc           #71                 // String 12345
      20: invokestatic  #20                 // Method org/apache/hadoop/hbase/util/Bytes.toBytes:(Ljava/lang/String;)[B
      23: putstatic     #17                 // Field ROWKEY:[B
      26: ldc           #72                 // String cf
      28: invokestatic  #20                 // Method org/apache/hadoop/hbase/util/Bytes.toBytes:(Ljava/lang/String;)[B
      31: putstatic     #10                 // Field FAMILY:[B
      34: return
}
