Compiled from "TestProcedureInMemoryChore.java"
public class org.apache.hadoop.hbase.procedure2.TestProcedureInMemoryChore$TestLatchChore extends org.apache.hadoop.hbase.procedure2.ProcedureInMemoryChore<org.apache.hadoop.hbase.procedure2.TestProcedureInMemoryChore$TestProcEnv> {
  public org.apache.hadoop.hbase.procedure2.TestProcedureInMemoryChore$TestLatchChore(int, java.util.concurrent.CountDownLatch);
    Code:
       0: aload_0
       1: iload_1
       2: invokespecial #1                  // Method org/apache/hadoop/hbase/procedure2/ProcedureInMemoryChore."<init>":(I)V
       5: aload_0
       6: aload_2
       7: invokevirtual #2                  // Method setLatch:(Ljava/util/concurrent/CountDownLatch;)V
      10: return

  public void setLatch(java.util.concurrent.CountDownLatch);
    Code:
       0: aload_0
       1: aload_1
       2: putfield      #3                  // Field latch:Ljava/util/concurrent/CountDownLatch;
       5: return

  protected void periodicExecute(org.apache.hadoop.hbase.procedure2.TestProcedureInMemoryChore$TestProcEnv);
    Code:
       0: invokestatic  #4                  // Method org/apache/hadoop/hbase/procedure2/TestProcedureInMemoryChore.access$100:()Lorg/slf4j/Logger;
       3: new           #5                  // class java/lang/StringBuilder
       6: dup
       7: invokespecial #6                  // Method java/lang/StringBuilder."<init>":()V
      10: ldc           #7                  // String periodic execute
      12: invokevirtual #8                  // Method java/lang/StringBuilder.append:(Ljava/lang/String;)Ljava/lang/StringBuilder;
      15: aload_0
      16: invokevirtual #9                  // Method java/lang/StringBuilder.append:(Ljava/lang/Object;)Ljava/lang/StringBuilder;
      19: invokevirtual #10                 // Method java/lang/StringBuilder.toString:()Ljava/lang/String;
      22: invokeinterface #11,  2           // InterfaceMethod org/slf4j/Logger.info:(Ljava/lang/String;)V
      27: aload_0
      28: getfield      #3                  // Field latch:Ljava/util/concurrent/CountDownLatch;
      31: invokevirtual #12                 // Method java/util/concurrent/CountDownLatch.countDown:()V
      34: return

  protected void periodicExecute(java.lang.Object);
    Code:
       0: aload_0
       1: aload_1
       2: checkcast     #13                 // class org/apache/hadoop/hbase/procedure2/TestProcedureInMemoryChore$TestProcEnv
       5: invokevirtual #14                 // Method periodicExecute:(Lorg/apache/hadoop/hbase/procedure2/TestProcedureInMemoryChore$TestProcEnv;)V
       8: return
}
