Compiled from "TestProcedureRecovery.java"
final class org.apache.hadoop.hbase.procedure2.TestProcedureRecovery$TestStateMachineProcedure$State extends java.lang.Enum<org.apache.hadoop.hbase.procedure2.TestProcedureRecovery$TestStateMachineProcedure$State> {
  public static final org.apache.hadoop.hbase.procedure2.TestProcedureRecovery$TestStateMachineProcedure$State STATE_1;

  public static final org.apache.hadoop.hbase.procedure2.TestProcedureRecovery$TestStateMachineProcedure$State STATE_2;

  public static final org.apache.hadoop.hbase.procedure2.TestProcedureRecovery$TestStateMachineProcedure$State STATE_3;

  public static final org.apache.hadoop.hbase.procedure2.TestProcedureRecovery$TestStateMachineProcedure$State DONE;

  public static org.apache.hadoop.hbase.procedure2.TestProcedureRecovery$TestStateMachineProcedure$State[] values();
    Code:
       0: getstatic     #1                  // Field $VALUES:[Lorg/apache/hadoop/hbase/procedure2/TestProcedureRecovery$TestStateMachineProcedure$State;
       3: invokevirtual #2                  // Method "[Lorg/apache/hadoop/hbase/procedure2/TestProcedureRecovery$TestStateMachineProcedure$State;".clone:()Ljava/lang/Object;
       6: checkcast     #3                  // class "[Lorg/apache/hadoop/hbase/procedure2/TestProcedureRecovery$TestStateMachineProcedure$State;"
       9: areturn

  public static org.apache.hadoop.hbase.procedure2.TestProcedureRecovery$TestStateMachineProcedure$State valueOf(java.lang.String);
    Code:
       0: ldc           #4                  // class org/apache/hadoop/hbase/procedure2/TestProcedureRecovery$TestStateMachineProcedure$State
       2: aload_0
       3: invokestatic  #5                  // Method java/lang/Enum.valueOf:(Ljava/lang/Class;Ljava/lang/String;)Ljava/lang/Enum;
       6: checkcast     #4                  // class org/apache/hadoop/hbase/procedure2/TestProcedureRecovery$TestStateMachineProcedure$State
       9: areturn

  static {};
    Code:
       0: new           #4                  // class org/apache/hadoop/hbase/procedure2/TestProcedureRecovery$TestStateMachineProcedure$State
       3: dup
       4: ldc           #7                  // String STATE_1
       6: iconst_0
       7: invokespecial #8                  // Method "<init>":(Ljava/lang/String;I)V
      10: putstatic     #9                  // Field STATE_1:Lorg/apache/hadoop/hbase/procedure2/TestProcedureRecovery$TestStateMachineProcedure$State;
      13: new           #4                  // class org/apache/hadoop/hbase/procedure2/TestProcedureRecovery$TestStateMachineProcedure$State
      16: dup
      17: ldc           #10                 // String STATE_2
      19: iconst_1
      20: invokespecial #8                  // Method "<init>":(Ljava/lang/String;I)V
      23: putstatic     #11                 // Field STATE_2:Lorg/apache/hadoop/hbase/procedure2/TestProcedureRecovery$TestStateMachineProcedure$State;
      26: new           #4                  // class org/apache/hadoop/hbase/procedure2/TestProcedureRecovery$TestStateMachineProcedure$State
      29: dup
      30: ldc           #12                 // String STATE_3
      32: iconst_2
      33: invokespecial #8                  // Method "<init>":(Ljava/lang/String;I)V
      36: putstatic     #13                 // Field STATE_3:Lorg/apache/hadoop/hbase/procedure2/TestProcedureRecovery$TestStateMachineProcedure$State;
      39: new           #4                  // class org/apache/hadoop/hbase/procedure2/TestProcedureRecovery$TestStateMachineProcedure$State
      42: dup
      43: ldc           #14                 // String DONE
      45: iconst_3
      46: invokespecial #8                  // Method "<init>":(Ljava/lang/String;I)V
      49: putstatic     #15                 // Field DONE:Lorg/apache/hadoop/hbase/procedure2/TestProcedureRecovery$TestStateMachineProcedure$State;
      52: iconst_4
      53: anewarray     #4                  // class org/apache/hadoop/hbase/procedure2/TestProcedureRecovery$TestStateMachineProcedure$State
      56: dup
      57: iconst_0
      58: getstatic     #9                  // Field STATE_1:Lorg/apache/hadoop/hbase/procedure2/TestProcedureRecovery$TestStateMachineProcedure$State;
      61: aastore
      62: dup
      63: iconst_1
      64: getstatic     #11                 // Field STATE_2:Lorg/apache/hadoop/hbase/procedure2/TestProcedureRecovery$TestStateMachineProcedure$State;
      67: aastore
      68: dup
      69: iconst_2
      70: getstatic     #13                 // Field STATE_3:Lorg/apache/hadoop/hbase/procedure2/TestProcedureRecovery$TestStateMachineProcedure$State;
      73: aastore
      74: dup
      75: iconst_3
      76: getstatic     #15                 // Field DONE:Lorg/apache/hadoop/hbase/procedure2/TestProcedureRecovery$TestStateMachineProcedure$State;
      79: aastore
      80: putstatic     #1                  // Field $VALUES:[Lorg/apache/hadoop/hbase/procedure2/TestProcedureRecovery$TestStateMachineProcedure$State;
      83: return
}
