Compiled from "TestRegionServerAbort.java"
public class org.apache.hadoop.hbase.regionserver.TestRegionServerAbort$StopBlockingRegionObserver implements org.apache.hadoop.hbase.coprocessor.RegionServerCoprocessor,org.apache.hadoop.hbase.coprocessor.RegionCoprocessor,org.apache.hadoop.hbase.coprocessor.RegionServerObserver,org.apache.hadoop.hbase.coprocessor.RegionObserver {
  public static final java.lang.String DO_ABORT;

  public org.apache.hadoop.hbase.regionserver.TestRegionServerAbort$StopBlockingRegionObserver();
    Code:
       0: aload_0
       1: invokespecial #1                  // Method java/lang/Object."<init>":()V
       4: return

  public java.util.Optional<org.apache.hadoop.hbase.coprocessor.RegionObserver> getRegionObserver();
    Code:
       0: aload_0
       1: invokestatic  #2                  // Method java/util/Optional.of:(Ljava/lang/Object;)Ljava/util/Optional;
       4: areturn

  public java.util.Optional<org.apache.hadoop.hbase.coprocessor.RegionServerObserver> getRegionServerObserver();
    Code:
       0: aload_0
       1: invokestatic  #2                  // Method java/util/Optional.of:(Ljava/lang/Object;)Ljava/util/Optional;
       4: areturn

  public void prePut(org.apache.hadoop.hbase.coprocessor.ObserverContext<org.apache.hadoop.hbase.coprocessor.RegionCoprocessorEnvironment>, org.apache.hadoop.hbase.client.Put, org.apache.hadoop.hbase.wal.WALEdit, org.apache.hadoop.hbase.client.Durability) throws java.io.IOException;
    Code:
       0: aload_2
       1: ldc           #4                  // String DO_ABORT
       3: invokevirtual #5                  // Method org/apache/hadoop/hbase/client/Put.getAttribute:(Ljava/lang/String;)[B
       6: ifnull        85
       9: aload_1
      10: invokeinterface #6,  1            // InterfaceMethod org/apache/hadoop/hbase/coprocessor/ObserverContext.getEnvironment:()Lorg/apache/hadoop/hbase/CoprocessorEnvironment;
      15: checkcast     #7                  // class org/apache/hadoop/hbase/coprocessor/HasRegionServerServices
      18: invokeinterface #8,  1            // InterfaceMethod org/apache/hadoop/hbase/coprocessor/HasRegionServerServices.getRegionServerServices:()Lorg/apache/hadoop/hbase/regionserver/RegionServerServices;
      23: astore        5
      25: ldc           #9                  // String Aborting for test
      27: astore        6
      29: invokestatic  #10                 // Method org/apache/hadoop/hbase/regionserver/TestRegionServerAbort.access$000:()Lorg/slf4j/Logger;
      32: new           #11                 // class java/lang/StringBuilder
      35: dup
      36: invokespecial #12                 // Method java/lang/StringBuilder."<init>":()V
      39: aload         6
      41: invokevirtual #13                 // Method java/lang/StringBuilder.append:(Ljava/lang/String;)Ljava/lang/StringBuilder;
      44: ldc           #14                 // String
      46: invokevirtual #13                 // Method java/lang/StringBuilder.append:(Ljava/lang/String;)Ljava/lang/StringBuilder;
      49: aload         5
      51: invokeinterface #15,  1           // InterfaceMethod org/apache/hadoop/hbase/regionserver/RegionServerServices.getServerName:()Lorg/apache/hadoop/hbase/ServerName;
      56: invokevirtual #16                 // Method java/lang/StringBuilder.append:(Ljava/lang/Object;)Ljava/lang/StringBuilder;
      59: invokevirtual #17                 // Method java/lang/StringBuilder.toString:()Ljava/lang/String;
      62: invokeinterface #18,  2           // InterfaceMethod org/slf4j/Logger.info:(Ljava/lang/String;)V
      67: aload         5
      69: aload         6
      71: new           #19                 // class java/lang/Throwable
      74: dup
      75: aload         6
      77: invokespecial #20                 // Method java/lang/Throwable."<init>":(Ljava/lang/String;)V
      80: invokeinterface #21,  3           // InterfaceMethod org/apache/hadoop/hbase/regionserver/RegionServerServices.abort:(Ljava/lang/String;Ljava/lang/Throwable;)V
      85: return

  public void preStopRegionServer(org.apache.hadoop.hbase.coprocessor.ObserverContext<org.apache.hadoop.hbase.coprocessor.RegionServerCoprocessorEnvironment>) throws java.io.IOException;
    Code:
       0: aload_0
       1: getfield      #22                 // Field stopAllowed:Z
       4: ifne          17
       7: new           #23                 // class java/io/IOException
      10: dup
      11: ldc           #24                 // String Stop not allowed
      13: invokespecial #25                 // Method java/io/IOException."<init>":(Ljava/lang/String;)V
      16: athrow
      17: return

  public void setStopAllowed(boolean);
    Code:
       0: aload_0
       1: iload_1
       2: putfield      #22                 // Field stopAllowed:Z
       5: return
}
