Compiled from "TestProcedureMember.java"
class org.apache.hadoop.hbase.procedure.TestProcedureMember$1 implements org.mockito.stubbing.Answer<java.lang.Void> {
  final org.apache.hadoop.hbase.procedure.TestProcedureMember this$0;

  org.apache.hadoop.hbase.procedure.TestProcedureMember$1(org.apache.hadoop.hbase.procedure.TestProcedureMember);
    Code:
       0: aload_0
       1: aload_1
       2: putfield      #2                  // Field this$0:Lorg/apache/hadoop/hbase/procedure/TestProcedureMember;
       5: aload_0
       6: invokespecial #3                  // Method java/lang/Object."<init>":()V
       9: return

  public java.lang.Void answer(org.mockito.invocation.InvocationOnMock) throws java.lang.Throwable;
    Code:
       0: aload_0
       1: getfield      #2                  // Field this$0:Lorg/apache/hadoop/hbase/procedure/TestProcedureMember;
       4: invokestatic  #4                  // Method org/apache/hadoop/hbase/procedure/TestProcedureMember.access$000:(Lorg/apache/hadoop/hbase/procedure/TestProcedureMember;)Lorg/apache/hadoop/hbase/procedure/ProcedureMember;
       7: ldc           #5                  // String some op
       9: invokevirtual #6                  // Method org/apache/hadoop/hbase/procedure/ProcedureMember.receivedReachedGlobalBarrier:(Ljava/lang/String;)V
      12: aconst_null
      13: areturn

  public java.lang.Object answer(org.mockito.invocation.InvocationOnMock) throws java.lang.Throwable;
    Code:
       0: aload_0
       1: aload_1
       2: invokevirtual #7                  // Method answer:(Lorg/mockito/invocation/InvocationOnMock;)Ljava/lang/Void;
       5: areturn
}
