Compiled from "TestWALObserver.java"
class org.apache.hadoop.hbase.coprocessor.TestWALObserver$1 implements java.security.PrivilegedExceptionAction<java.lang.Void> {
  final org.apache.hadoop.conf.Configuration val$newConf;

  final org.apache.hadoop.hbase.client.RegionInfo val$hri;

  final org.apache.hadoop.hbase.client.TableDescriptor val$htd;

  final org.apache.hadoop.hbase.coprocessor.TestWALObserver this$0;

  org.apache.hadoop.hbase.coprocessor.TestWALObserver$1(org.apache.hadoop.hbase.coprocessor.TestWALObserver, org.apache.hadoop.conf.Configuration, org.apache.hadoop.hbase.client.RegionInfo, org.apache.hadoop.hbase.client.TableDescriptor);
    Code:
       0: aload_0
       1: aload_1
       2: putfield      #1                  // Field this$0:Lorg/apache/hadoop/hbase/coprocessor/TestWALObserver;
       5: aload_0
       6: aload_2
       7: putfield      #2                  // Field val$newConf:Lorg/apache/hadoop/conf/Configuration;
      10: aload_0
      11: aload_3
      12: putfield      #3                  // Field val$hri:Lorg/apache/hadoop/hbase/client/RegionInfo;
      15: aload_0
      16: aload         4
      18: putfield      #4                  // Field val$htd:Lorg/apache/hadoop/hbase/client/TableDescriptor;
      21: aload_0
      22: invokespecial #5                  // Method java/lang/Object."<init>":()V
      25: return

  public java.lang.Void run() throws java.lang.Exception;
    Code:
       0: aload_0
       1: getfield      #1                  // Field this$0:Lorg/apache/hadoop/hbase/coprocessor/TestWALObserver;
       4: aload_0
       5: getfield      #2                  // Field val$newConf:Lorg/apache/hadoop/conf/Configuration;
       8: invokestatic  #6                  // Method org/apache/hadoop/hbase/coprocessor/TestWALObserver.access$000:(Lorg/apache/hadoop/hbase/coprocessor/TestWALObserver;Lorg/apache/hadoop/conf/Configuration;)Lorg/apache/hadoop/fs/Path;
      11: astore_1
      12: invokestatic  #7                  // Method org/apache/hadoop/hbase/coprocessor/TestWALObserver.access$100:()Lorg/slf4j/Logger;
      15: new           #8                  // class java/lang/StringBuilder
      18: dup
      19: invokespecial #9                  // Method java/lang/StringBuilder."<init>":()V
      22: ldc           #10                 // String WALSplit path ==
      24: invokevirtual #11                 // Method java/lang/StringBuilder.append:(Ljava/lang/String;)Ljava/lang/StringBuilder;
      27: aload_1
      28: invokevirtual #12                 // Method java/lang/StringBuilder.append:(Ljava/lang/Object;)Ljava/lang/StringBuilder;
      31: invokevirtual #13                 // Method java/lang/StringBuilder.toString:()Ljava/lang/String;
      34: invokeinterface #14,  2           // InterfaceMethod org/slf4j/Logger.info:(Ljava/lang/String;)V
      39: new           #15                 // class org/apache/hadoop/hbase/wal/WALFactory
      42: dup
      43: aload_0
      44: getfield      #1                  // Field this$0:Lorg/apache/hadoop/hbase/coprocessor/TestWALObserver;
      47: invokestatic  #16                 // Method org/apache/hadoop/hbase/coprocessor/TestWALObserver.access$200:(Lorg/apache/hadoop/hbase/coprocessor/TestWALObserver;)Lorg/apache/hadoop/conf/Configuration;
      50: new           #8                  // class java/lang/StringBuilder
      53: dup
      54: invokespecial #9                  // Method java/lang/StringBuilder."<init>":()V
      57: aload_0
      58: getfield      #1                  // Field this$0:Lorg/apache/hadoop/hbase/coprocessor/TestWALObserver;
      61: getfield      #17                 // Field org/apache/hadoop/hbase/coprocessor/TestWALObserver.currentTest:Lorg/junit/rules/TestName;
      64: invokevirtual #18                 // Method org/junit/rules/TestName.getMethodName:()Ljava/lang/String;
      67: invokevirtual #11                 // Method java/lang/StringBuilder.append:(Ljava/lang/String;)Ljava/lang/StringBuilder;
      70: ldc           #19                 // String 2
      72: invokevirtual #11                 // Method java/lang/StringBuilder.append:(Ljava/lang/String;)Ljava/lang/StringBuilder;
      75: invokevirtual #13                 // Method java/lang/StringBuilder.toString:()Ljava/lang/String;
      78: sipush        16010
      81: invokestatic  #20                 // Method java/lang/System.currentTimeMillis:()J
      84: invokestatic  #21                 // Method org/apache/hadoop/hbase/ServerName.valueOf:(Ljava/lang/String;IJ)Lorg/apache/hadoop/hbase/ServerName;
      87: invokevirtual #22                 // Method org/apache/hadoop/hbase/ServerName.toString:()Ljava/lang/String;
      90: invokespecial #23                 // Method org/apache/hadoop/hbase/wal/WALFactory."<init>":(Lorg/apache/hadoop/conf/Configuration;Ljava/lang/String;)V
      93: astore_2
      94: aload_2
      95: aconst_null
      96: invokevirtual #24                 // Method org/apache/hadoop/hbase/wal/WALFactory.getWAL:(Lorg/apache/hadoop/hbase/client/RegionInfo;)Lorg/apache/hadoop/hbase/wal/WAL;
      99: astore_3
     100: aload_0
     101: getfield      #2                  // Field val$newConf:Lorg/apache/hadoop/conf/Configuration;
     104: aload_0
     105: getfield      #2                  // Field val$newConf:Lorg/apache/hadoop/conf/Configuration;
     108: invokestatic  #25                 // Method org/apache/hadoop/fs/FileSystem.get:(Lorg/apache/hadoop/conf/Configuration;)Lorg/apache/hadoop/fs/FileSystem;
     111: aload_0
     112: getfield      #1                  // Field this$0:Lorg/apache/hadoop/hbase/coprocessor/TestWALObserver;
     115: invokestatic  #26                 // Method org/apache/hadoop/hbase/coprocessor/TestWALObserver.access$300:(Lorg/apache/hadoop/hbase/coprocessor/TestWALObserver;)Lorg/apache/hadoop/fs/Path;
     118: aload_0
     119: getfield      #3                  // Field val$hri:Lorg/apache/hadoop/hbase/client/RegionInfo;
     122: aload_0
     123: getfield      #4                  // Field val$htd:Lorg/apache/hadoop/hbase/client/TableDescriptor;
     126: aload_3
     127: invokestatic  #27                 // Method org/apache/hadoop/hbase/coprocessor/TestWALObserver.access$400:()Lorg/apache/hadoop/hbase/HBaseTestingUtility;
     130: invokevirtual #28                 // Method org/apache/hadoop/hbase/HBaseTestingUtility.getHBaseCluster:()Lorg/apache/hadoop/hbase/MiniHBaseCluster;
     133: iconst_0
     134: invokevirtual #29                 // Method org/apache/hadoop/hbase/MiniHBaseCluster.getRegionServer:(I)Lorg/apache/hadoop/hbase/regionserver/HRegionServer;
     137: aconst_null
     138: invokestatic  #30                 // Method org/apache/hadoop/hbase/regionserver/HRegion.openHRegion:(Lorg/apache/hadoop/conf/Configuration;Lorg/apache/hadoop/fs/FileSystem;Lorg/apache/hadoop/fs/Path;Lorg/apache/hadoop/hbase/client/RegionInfo;Lorg/apache/hadoop/hbase/client/TableDescriptor;Lorg/apache/hadoop/hbase/wal/WAL;Lorg/apache/hadoop/hbase/regionserver/RegionServerServices;Lorg/apache/hadoop/hbase/util/CancelableProgressable;)Lorg/apache/hadoop/hbase/regionserver/HRegion;
     141: astore        4
     143: aload         4
     145: invokevirtual #31                 // Method org/apache/hadoop/hbase/regionserver/HRegion.getCoprocessorHost:()Lorg/apache/hadoop/hbase/regionserver/RegionCoprocessorHost;
     148: ldc           #32                 // class org/apache/hadoop/hbase/coprocessor/SampleRegionWALCoprocessor
     150: invokevirtual #33                 // Method org/apache/hadoop/hbase/regionserver/RegionCoprocessorHost.findCoprocessor:(Ljava/lang/Class;)Lorg/apache/hadoop/hbase/Coprocessor;
     153: checkcast     #32                 // class org/apache/hadoop/hbase/coprocessor/SampleRegionWALCoprocessor
     156: astore        5
     158: aload         5
     160: invokestatic  #34                 // Method org/junit/Assert.assertNotNull:(Ljava/lang/Object;)V
     163: aload         5
     165: invokevirtual #35                 // Method org/apache/hadoop/hbase/coprocessor/SampleRegionWALCoprocessor.isPreWALRestoreCalled:()Z
     168: invokestatic  #36                 // Method org/junit/Assert.assertTrue:(Z)V
     171: aload         5
     173: invokevirtual #37                 // Method org/apache/hadoop/hbase/coprocessor/SampleRegionWALCoprocessor.isPostWALRestoreCalled:()Z
     176: invokestatic  #36                 // Method org/junit/Assert.assertTrue:(Z)V
     179: aload         4
     181: invokevirtual #38                 // Method org/apache/hadoop/hbase/regionserver/HRegion.close:()Ljava/util/Map;
     184: pop
     185: aload_2
     186: invokevirtual #39                 // Method org/apache/hadoop/hbase/wal/WALFactory.close:()V
     189: aconst_null
     190: areturn

  public java.lang.Object run() throws java.lang.Exception;
    Code:
       0: aload_0
       1: invokevirtual #40                 // Method run:()Ljava/lang/Void;
       4: areturn
}
