Compiled from "TestCompoundConfiguration.java"
public class org.apache.hadoop.hbase.TestCompoundConfiguration {
  public static final org.apache.hadoop.hbase.HBaseClassTestRule CLASS_RULE;

  public org.apache.hadoop.hbase.TestCompoundConfiguration();
    Code:
       0: aload_0
       1: invokespecial #1                  // Method java/lang/Object."<init>":()V
       4: return

  public void setUp() throws java.lang.Exception;
    Code:
       0: aload_0
       1: new           #2                  // class org/apache/hadoop/conf/Configuration
       4: dup
       5: invokespecial #3                  // Method org/apache/hadoop/conf/Configuration."<init>":()V
       8: putfield      #4                  // Field baseConf:Lorg/apache/hadoop/conf/Configuration;
      11: aload_0
      12: getfield      #4                  // Field baseConf:Lorg/apache/hadoop/conf/Configuration;
      15: ldc           #5                  // String A
      17: ldc           #6                  // String 1
      19: invokevirtual #7                  // Method org/apache/hadoop/conf/Configuration.set:(Ljava/lang/String;Ljava/lang/String;)V
      22: aload_0
      23: getfield      #4                  // Field baseConf:Lorg/apache/hadoop/conf/Configuration;
      26: ldc           #8                  // String B
      28: iconst_2
      29: invokevirtual #9                  // Method org/apache/hadoop/conf/Configuration.setInt:(Ljava/lang/String;I)V
      32: aload_0
      33: getfield      #4                  // Field baseConf:Lorg/apache/hadoop/conf/Configuration;
      36: ldc           #10                 // String C
      38: ldc           #11                 // String 3
      40: invokevirtual #7                  // Method org/apache/hadoop/conf/Configuration.set:(Ljava/lang/String;Ljava/lang/String;)V
      43: aload_0
      44: aload_0
      45: getfield      #4                  // Field baseConf:Lorg/apache/hadoop/conf/Configuration;
      48: invokevirtual #12                 // Method org/apache/hadoop/conf/Configuration.size:()I
      51: putfield      #13                 // Field baseConfSize:I
      54: return

  public void testBasicFunctionality() throws java.lang.ClassNotFoundException;
    Code:
       0: new           #14                 // class org/apache/hadoop/hbase/CompoundConfiguration
       3: dup
       4: invokespecial #15                 // Method org/apache/hadoop/hbase/CompoundConfiguration."<init>":()V
       7: aload_0
       8: getfield      #4                  // Field baseConf:Lorg/apache/hadoop/conf/Configuration;
      11: invokevirtual #16                 // Method org/apache/hadoop/hbase/CompoundConfiguration.add:(Lorg/apache/hadoop/conf/Configuration;)Lorg/apache/hadoop/hbase/CompoundConfiguration;
      14: astore_1
      15: ldc           #6                  // String 1
      17: aload_1
      18: ldc           #5                  // String A
      20: invokevirtual #17                 // Method org/apache/hadoop/hbase/CompoundConfiguration.get:(Ljava/lang/String;)Ljava/lang/String;
      23: invokestatic  #18                 // Method org/junit/Assert.assertEquals:(Ljava/lang/Object;Ljava/lang/Object;)V
      26: ldc2_w        #19                 // long 2l
      29: aload_1
      30: ldc           #8                  // String B
      32: iconst_0
      33: invokevirtual #21                 // Method org/apache/hadoop/hbase/CompoundConfiguration.getInt:(Ljava/lang/String;I)I
      36: i2l
      37: invokestatic  #22                 // Method org/junit/Assert.assertEquals:(JJ)V
      40: ldc2_w        #23                 // long 3l
      43: aload_1
      44: ldc           #10                 // String C
      46: iconst_0
      47: invokevirtual #21                 // Method org/apache/hadoop/hbase/CompoundConfiguration.getInt:(Ljava/lang/String;I)I
      50: i2l
      51: invokestatic  #22                 // Method org/junit/Assert.assertEquals:(JJ)V
      54: lconst_0
      55: aload_1
      56: ldc           #25                 // String D
      58: iconst_0
      59: invokevirtual #21                 // Method org/apache/hadoop/hbase/CompoundConfiguration.getInt:(Ljava/lang/String;I)I
      62: i2l
      63: invokestatic  #22                 // Method org/junit/Assert.assertEquals:(JJ)V
      66: ldc           #14                 // class org/apache/hadoop/hbase/CompoundConfiguration
      68: aload_1
      69: ldc           #14                 // class org/apache/hadoop/hbase/CompoundConfiguration
      71: invokevirtual #26                 // Method java/lang/Class.getName:()Ljava/lang/String;
      74: invokevirtual #27                 // Method org/apache/hadoop/hbase/CompoundConfiguration.getClassByName:(Ljava/lang/String;)Ljava/lang/Class;
      77: invokestatic  #18                 // Method org/junit/Assert.assertEquals:(Ljava/lang/Object;Ljava/lang/Object;)V
      80: aload_1
      81: ldc           #28                 // String bad_class_name
      83: invokevirtual #27                 // Method org/apache/hadoop/hbase/CompoundConfiguration.getClassByName:(Ljava/lang/String;)Ljava/lang/Class;
      86: pop
      87: ldc           #29                 // String Trying to load bad_class_name should throw an exception
      89: invokestatic  #30                 // Method org/junit/Assert.fail:(Ljava/lang/String;)V
      92: goto          96
      95: astore_2
      96: return
    Exception table:
       from    to  target type
          80    92    95   Class java/lang/ClassNotFoundException

  public void testPut();
    Code:
       0: new           #14                 // class org/apache/hadoop/hbase/CompoundConfiguration
       3: dup
       4: invokespecial #15                 // Method org/apache/hadoop/hbase/CompoundConfiguration."<init>":()V
       7: aload_0
       8: getfield      #4                  // Field baseConf:Lorg/apache/hadoop/conf/Configuration;
      11: invokevirtual #16                 // Method org/apache/hadoop/hbase/CompoundConfiguration.add:(Lorg/apache/hadoop/conf/Configuration;)Lorg/apache/hadoop/hbase/CompoundConfiguration;
      14: astore_1
      15: ldc           #6                  // String 1
      17: aload_1
      18: ldc           #5                  // String A
      20: invokevirtual #17                 // Method org/apache/hadoop/hbase/CompoundConfiguration.get:(Ljava/lang/String;)Ljava/lang/String;
      23: invokestatic  #18                 // Method org/junit/Assert.assertEquals:(Ljava/lang/Object;Ljava/lang/Object;)V
      26: ldc2_w        #19                 // long 2l
      29: aload_1
      30: ldc           #8                  // String B
      32: iconst_0
      33: invokevirtual #21                 // Method org/apache/hadoop/hbase/CompoundConfiguration.getInt:(Ljava/lang/String;I)I
      36: i2l
      37: invokestatic  #22                 // Method org/junit/Assert.assertEquals:(JJ)V
      40: ldc2_w        #23                 // long 3l
      43: aload_1
      44: ldc           #10                 // String C
      46: iconst_0
      47: invokevirtual #21                 // Method org/apache/hadoop/hbase/CompoundConfiguration.getInt:(Ljava/lang/String;I)I
      50: i2l
      51: invokestatic  #22                 // Method org/junit/Assert.assertEquals:(JJ)V
      54: lconst_0
      55: aload_1
      56: ldc           #25                 // String D
      58: iconst_0
      59: invokevirtual #21                 // Method org/apache/hadoop/hbase/CompoundConfiguration.getInt:(Ljava/lang/String;I)I
      62: i2l
      63: invokestatic  #22                 // Method org/junit/Assert.assertEquals:(JJ)V
      66: aload_1
      67: ldc           #5                  // String A
      69: ldc           #32                 // String 1337
      71: invokevirtual #33                 // Method org/apache/hadoop/hbase/CompoundConfiguration.set:(Ljava/lang/String;Ljava/lang/String;)V
      74: aload_1
      75: ldc           #34                 // String string
      77: ldc           #35                 // String stringvalue
      79: invokevirtual #33                 // Method org/apache/hadoop/hbase/CompoundConfiguration.set:(Ljava/lang/String;Ljava/lang/String;)V
      82: ldc2_w        #36                 // long 1337l
      85: aload_1
      86: ldc           #5                  // String A
      88: iconst_0
      89: invokevirtual #21                 // Method org/apache/hadoop/hbase/CompoundConfiguration.getInt:(Ljava/lang/String;I)I
      92: i2l
      93: invokestatic  #22                 // Method org/junit/Assert.assertEquals:(JJ)V
      96: ldc           #35                 // String stringvalue
      98: aload_1
      99: ldc           #34                 // String string
     101: invokevirtual #17                 // Method org/apache/hadoop/hbase/CompoundConfiguration.get:(Ljava/lang/String;)Ljava/lang/String;
     104: invokestatic  #18                 // Method org/junit/Assert.assertEquals:(Ljava/lang/Object;Ljava/lang/Object;)V
     107: ldc           #6                  // String 1
     109: aload_0
     110: getfield      #4                  // Field baseConf:Lorg/apache/hadoop/conf/Configuration;
     113: ldc           #5                  // String A
     115: invokevirtual #38                 // Method org/apache/hadoop/conf/Configuration.get:(Ljava/lang/String;)Ljava/lang/String;
     118: invokestatic  #18                 // Method org/junit/Assert.assertEquals:(Ljava/lang/Object;Ljava/lang/Object;)V
     121: aload_0
     122: getfield      #4                  // Field baseConf:Lorg/apache/hadoop/conf/Configuration;
     125: ldc           #34                 // String string
     127: invokevirtual #38                 // Method org/apache/hadoop/conf/Configuration.get:(Ljava/lang/String;)Ljava/lang/String;
     130: invokestatic  #39                 // Method org/junit/Assert.assertNull:(Ljava/lang/Object;)V
     133: aload_0
     134: getfield      #4                  // Field baseConf:Lorg/apache/hadoop/conf/Configuration;
     137: ldc           #40                 // String setInParent
     139: ldc           #41                 // String fromParent
     141: invokevirtual #7                  // Method org/apache/hadoop/conf/Configuration.set:(Ljava/lang/String;Ljava/lang/String;)V
     144: ldc           #41                 // String fromParent
     146: aload_1
     147: ldc           #40                 // String setInParent
     149: invokevirtual #17                 // Method org/apache/hadoop/hbase/CompoundConfiguration.get:(Ljava/lang/String;)Ljava/lang/String;
     152: invokestatic  #18                 // Method org/junit/Assert.assertEquals:(Ljava/lang/Object;Ljava/lang/Object;)V
     155: return

  public void testWithConfig();
    Code:
       0: new           #2                  // class org/apache/hadoop/conf/Configuration
       3: dup
       4: invokespecial #3                  // Method org/apache/hadoop/conf/Configuration."<init>":()V
       7: astore_1
       8: aload_1
       9: ldc           #8                  // String B
      11: ldc           #42                 // String 2b
      13: invokevirtual #7                  // Method org/apache/hadoop/conf/Configuration.set:(Ljava/lang/String;Ljava/lang/String;)V
      16: aload_1
      17: ldc           #10                 // String C
      19: ldc           #43                 // String 33
      21: invokevirtual #7                  // Method org/apache/hadoop/conf/Configuration.set:(Ljava/lang/String;Ljava/lang/String;)V
      24: aload_1
      25: ldc           #25                 // String D
      27: ldc           #44                 // String 4
      29: invokevirtual #7                  // Method org/apache/hadoop/conf/Configuration.set:(Ljava/lang/String;Ljava/lang/String;)V
      32: new           #14                 // class org/apache/hadoop/hbase/CompoundConfiguration
      35: dup
      36: invokespecial #15                 // Method org/apache/hadoop/hbase/CompoundConfiguration."<init>":()V
      39: aload_0
      40: getfield      #4                  // Field baseConf:Lorg/apache/hadoop/conf/Configuration;
      43: invokevirtual #16                 // Method org/apache/hadoop/hbase/CompoundConfiguration.add:(Lorg/apache/hadoop/conf/Configuration;)Lorg/apache/hadoop/hbase/CompoundConfiguration;
      46: aload_1
      47: invokevirtual #16                 // Method org/apache/hadoop/hbase/CompoundConfiguration.add:(Lorg/apache/hadoop/conf/Configuration;)Lorg/apache/hadoop/hbase/CompoundConfiguration;
      50: astore_2
      51: ldc           #6                  // String 1
      53: aload_2
      54: ldc           #5                  // String A
      56: invokevirtual #17                 // Method org/apache/hadoop/hbase/CompoundConfiguration.get:(Ljava/lang/String;)Ljava/lang/String;
      59: invokestatic  #18                 // Method org/junit/Assert.assertEquals:(Ljava/lang/Object;Ljava/lang/Object;)V
      62: ldc           #42                 // String 2b
      64: aload_2
      65: ldc           #8                  // String B
      67: invokevirtual #17                 // Method org/apache/hadoop/hbase/CompoundConfiguration.get:(Ljava/lang/String;)Ljava/lang/String;
      70: invokestatic  #18                 // Method org/junit/Assert.assertEquals:(Ljava/lang/Object;Ljava/lang/Object;)V
      73: ldc2_w        #45                 // long 33l
      76: aload_2
      77: ldc           #10                 // String C
      79: iconst_0
      80: invokevirtual #21                 // Method org/apache/hadoop/hbase/CompoundConfiguration.getInt:(Ljava/lang/String;I)I
      83: i2l
      84: invokestatic  #22                 // Method org/junit/Assert.assertEquals:(JJ)V
      87: ldc           #44                 // String 4
      89: aload_2
      90: ldc           #25                 // String D
      92: invokevirtual #17                 // Method org/apache/hadoop/hbase/CompoundConfiguration.get:(Ljava/lang/String;)Ljava/lang/String;
      95: invokestatic  #18                 // Method org/junit/Assert.assertEquals:(Ljava/lang/Object;Ljava/lang/Object;)V
      98: ldc2_w        #47                 // long 4l
     101: aload_2
     102: ldc           #25                 // String D
     104: iconst_0
     105: invokevirtual #21                 // Method org/apache/hadoop/hbase/CompoundConfiguration.getInt:(Ljava/lang/String;I)I
     108: i2l
     109: invokestatic  #22                 // Method org/junit/Assert.assertEquals:(JJ)V
     112: aload_2
     113: ldc           #49                 // String E
     115: invokevirtual #17                 // Method org/apache/hadoop/hbase/CompoundConfiguration.get:(Ljava/lang/String;)Ljava/lang/String;
     118: invokestatic  #39                 // Method org/junit/Assert.assertNull:(Ljava/lang/Object;)V
     121: ldc2_w        #50                 // long 6l
     124: aload_2
     125: ldc           #52                 // String F
     127: bipush        6
     129: invokevirtual #21                 // Method org/apache/hadoop/hbase/CompoundConfiguration.getInt:(Ljava/lang/String;I)I
     132: i2l
     133: invokestatic  #22                 // Method org/junit/Assert.assertEquals:(JJ)V
     136: iconst_0
     137: istore_3
     138: aload_2
     139: invokevirtual #53                 // Method org/apache/hadoop/hbase/CompoundConfiguration.iterator:()Ljava/util/Iterator;
     142: astore        4
     144: aload         4
     146: invokeinterface #54,  1           // InterfaceMethod java/util/Iterator.hasNext:()Z
     151: ifeq          233
     154: aload         4
     156: invokeinterface #55,  1           // InterfaceMethod java/util/Iterator.next:()Ljava/lang/Object;
     161: checkcast     #56                 // class java/util/Map$Entry
     164: astore        5
     166: iinc          3, 1
     169: aload         5
     171: invokeinterface #57,  1           // InterfaceMethod java/util/Map$Entry.getKey:()Ljava/lang/Object;
     176: checkcast     #58                 // class java/lang/String
     179: ldc           #8                  // String B
     181: invokevirtual #59                 // Method java/lang/String.equals:(Ljava/lang/Object;)Z
     184: ifeq          202
     187: ldc           #42                 // String 2b
     189: aload         5
     191: invokeinterface #60,  1           // InterfaceMethod java/util/Map$Entry.getValue:()Ljava/lang/Object;
     196: invokestatic  #18                 // Method org/junit/Assert.assertEquals:(Ljava/lang/Object;Ljava/lang/Object;)V
     199: goto          230
     202: aload         5
     204: invokeinterface #57,  1           // InterfaceMethod java/util/Map$Entry.getKey:()Ljava/lang/Object;
     209: checkcast     #58                 // class java/lang/String
     212: ldc           #61                 // String G
     214: invokevirtual #59                 // Method java/lang/String.equals:(Ljava/lang/Object;)Z
     217: ifeq          230
     220: aload         5
     222: invokeinterface #60,  1           // InterfaceMethod java/util/Map$Entry.getValue:()Ljava/lang/Object;
     227: invokestatic  #39                 // Method org/junit/Assert.assertNull:(Ljava/lang/Object;)V
     230: goto          144
     233: aload_0
     234: getfield      #13                 // Field baseConfSize:I
     237: iconst_1
     238: iadd
     239: i2l
     240: iload_3
     241: i2l
     242: invokestatic  #22                 // Method org/junit/Assert.assertEquals:(JJ)V
     245: return

  public void testWithIbwMap();
    Code:
       0: new           #65                 // class java/util/HashMap
       3: dup
       4: invokespecial #66                 // Method java/util/HashMap."<init>":()V
       7: astore_1
       8: aload_1
       9: aload_0
      10: ldc           #8                  // String B
      12: invokespecial #67                 // Method strToIb:(Ljava/lang/String;)Lorg/apache/hadoop/hbase/util/Bytes;
      15: aload_0
      16: ldc           #42                 // String 2b
      18: invokespecial #67                 // Method strToIb:(Ljava/lang/String;)Lorg/apache/hadoop/hbase/util/Bytes;
      21: invokeinterface #68,  3           // InterfaceMethod java/util/Map.put:(Ljava/lang/Object;Ljava/lang/Object;)Ljava/lang/Object;
      26: pop
      27: aload_1
      28: aload_0
      29: ldc           #10                 // String C
      31: invokespecial #67                 // Method strToIb:(Ljava/lang/String;)Lorg/apache/hadoop/hbase/util/Bytes;
      34: aload_0
      35: ldc           #43                 // String 33
      37: invokespecial #67                 // Method strToIb:(Ljava/lang/String;)Lorg/apache/hadoop/hbase/util/Bytes;
      40: invokeinterface #68,  3           // InterfaceMethod java/util/Map.put:(Ljava/lang/Object;Ljava/lang/Object;)Ljava/lang/Object;
      45: pop
      46: aload_1
      47: aload_0
      48: ldc           #25                 // String D
      50: invokespecial #67                 // Method strToIb:(Ljava/lang/String;)Lorg/apache/hadoop/hbase/util/Bytes;
      53: aload_0
      54: ldc           #44                 // String 4
      56: invokespecial #67                 // Method strToIb:(Ljava/lang/String;)Lorg/apache/hadoop/hbase/util/Bytes;
      59: invokeinterface #68,  3           // InterfaceMethod java/util/Map.put:(Ljava/lang/Object;Ljava/lang/Object;)Ljava/lang/Object;
      64: pop
      65: aload_1
      66: aload_0
      67: ldc           #61                 // String G
      69: invokespecial #67                 // Method strToIb:(Ljava/lang/String;)Lorg/apache/hadoop/hbase/util/Bytes;
      72: aconst_null
      73: invokeinterface #68,  3           // InterfaceMethod java/util/Map.put:(Ljava/lang/Object;Ljava/lang/Object;)Ljava/lang/Object;
      78: pop
      79: new           #14                 // class org/apache/hadoop/hbase/CompoundConfiguration
      82: dup
      83: invokespecial #15                 // Method org/apache/hadoop/hbase/CompoundConfiguration."<init>":()V
      86: aload_0
      87: getfield      #4                  // Field baseConf:Lorg/apache/hadoop/conf/Configuration;
      90: invokevirtual #16                 // Method org/apache/hadoop/hbase/CompoundConfiguration.add:(Lorg/apache/hadoop/conf/Configuration;)Lorg/apache/hadoop/hbase/CompoundConfiguration;
      93: aload_1
      94: invokevirtual #69                 // Method org/apache/hadoop/hbase/CompoundConfiguration.addBytesMap:(Ljava/util/Map;)Lorg/apache/hadoop/hbase/CompoundConfiguration;
      97: astore_2
      98: ldc           #6                  // String 1
     100: aload_2
     101: ldc           #5                  // String A
     103: invokevirtual #17                 // Method org/apache/hadoop/hbase/CompoundConfiguration.get:(Ljava/lang/String;)Ljava/lang/String;
     106: invokestatic  #18                 // Method org/junit/Assert.assertEquals:(Ljava/lang/Object;Ljava/lang/Object;)V
     109: ldc           #42                 // String 2b
     111: aload_2
     112: ldc           #8                  // String B
     114: invokevirtual #17                 // Method org/apache/hadoop/hbase/CompoundConfiguration.get:(Ljava/lang/String;)Ljava/lang/String;
     117: invokestatic  #18                 // Method org/junit/Assert.assertEquals:(Ljava/lang/Object;Ljava/lang/Object;)V
     120: ldc2_w        #45                 // long 33l
     123: aload_2
     124: ldc           #10                 // String C
     126: iconst_0
     127: invokevirtual #21                 // Method org/apache/hadoop/hbase/CompoundConfiguration.getInt:(Ljava/lang/String;I)I
     130: i2l
     131: invokestatic  #22                 // Method org/junit/Assert.assertEquals:(JJ)V
     134: ldc           #44                 // String 4
     136: aload_2
     137: ldc           #25                 // String D
     139: invokevirtual #17                 // Method org/apache/hadoop/hbase/CompoundConfiguration.get:(Ljava/lang/String;)Ljava/lang/String;
     142: invokestatic  #18                 // Method org/junit/Assert.assertEquals:(Ljava/lang/Object;Ljava/lang/Object;)V
     145: ldc2_w        #47                 // long 4l
     148: aload_2
     149: ldc           #25                 // String D
     151: iconst_0
     152: invokevirtual #21                 // Method org/apache/hadoop/hbase/CompoundConfiguration.getInt:(Ljava/lang/String;I)I
     155: i2l
     156: invokestatic  #22                 // Method org/junit/Assert.assertEquals:(JJ)V
     159: aload_2
     160: ldc           #49                 // String E
     162: invokevirtual #17                 // Method org/apache/hadoop/hbase/CompoundConfiguration.get:(Ljava/lang/String;)Ljava/lang/String;
     165: invokestatic  #39                 // Method org/junit/Assert.assertNull:(Ljava/lang/Object;)V
     168: ldc2_w        #50                 // long 6l
     171: aload_2
     172: ldc           #52                 // String F
     174: bipush        6
     176: invokevirtual #21                 // Method org/apache/hadoop/hbase/CompoundConfiguration.getInt:(Ljava/lang/String;I)I
     179: i2l
     180: invokestatic  #22                 // Method org/junit/Assert.assertEquals:(JJ)V
     183: aload_2
     184: ldc           #61                 // String G
     186: invokevirtual #17                 // Method org/apache/hadoop/hbase/CompoundConfiguration.get:(Ljava/lang/String;)Ljava/lang/String;
     189: invokestatic  #39                 // Method org/junit/Assert.assertNull:(Ljava/lang/Object;)V
     192: iconst_0
     193: istore_3
     194: aload_2
     195: invokevirtual #53                 // Method org/apache/hadoop/hbase/CompoundConfiguration.iterator:()Ljava/util/Iterator;
     198: astore        4
     200: aload         4
     202: invokeinterface #54,  1           // InterfaceMethod java/util/Iterator.hasNext:()Z
     207: ifeq          289
     210: aload         4
     212: invokeinterface #55,  1           // InterfaceMethod java/util/Iterator.next:()Ljava/lang/Object;
     217: checkcast     #56                 // class java/util/Map$Entry
     220: astore        5
     222: iinc          3, 1
     225: aload         5
     227: invokeinterface #57,  1           // InterfaceMethod java/util/Map$Entry.getKey:()Ljava/lang/Object;
     232: checkcast     #58                 // class java/lang/String
     235: ldc           #8                  // String B
     237: invokevirtual #59                 // Method java/lang/String.equals:(Ljava/lang/Object;)Z
     240: ifeq          258
     243: ldc           #42                 // String 2b
     245: aload         5
     247: invokeinterface #60,  1           // InterfaceMethod java/util/Map$Entry.getValue:()Ljava/lang/Object;
     252: invokestatic  #18                 // Method org/junit/Assert.assertEquals:(Ljava/lang/Object;Ljava/lang/Object;)V
     255: goto          286
     258: aload         5
     260: invokeinterface #57,  1           // InterfaceMethod java/util/Map$Entry.getKey:()Ljava/lang/Object;
     265: checkcast     #58                 // class java/lang/String
     268: ldc           #61                 // String G
     270: invokevirtual #59                 // Method java/lang/String.equals:(Ljava/lang/Object;)Z
     273: ifeq          286
     276: aload         5
     278: invokeinterface #60,  1           // InterfaceMethod java/util/Map$Entry.getValue:()Ljava/lang/Object;
     283: invokestatic  #39                 // Method org/junit/Assert.assertNull:(Ljava/lang/Object;)V
     286: goto          200
     289: aload_0
     290: getfield      #13                 // Field baseConfSize:I
     293: iconst_2
     294: iadd
     295: i2l
     296: iload_3
     297: i2l
     298: invokestatic  #22                 // Method org/junit/Assert.assertEquals:(JJ)V
     301: new           #14                 // class org/apache/hadoop/hbase/CompoundConfiguration
     304: dup
     305: invokespecial #15                 // Method org/apache/hadoop/hbase/CompoundConfiguration."<init>":()V
     308: astore        4
     310: aload         4
     312: ldc           #70                 // String X
     314: ldc           #71                 // String modification
     316: invokevirtual #33                 // Method org/apache/hadoop/hbase/CompoundConfiguration.set:(Ljava/lang/String;Ljava/lang/String;)V
     319: aload         4
     321: ldc           #25                 // String D
     323: ldc           #72                 // String not4
     325: invokevirtual #33                 // Method org/apache/hadoop/hbase/CompoundConfiguration.set:(Ljava/lang/String;Ljava/lang/String;)V
     328: ldc           #71                 // String modification
     330: aload         4
     332: ldc           #70                 // String X
     334: invokevirtual #17                 // Method org/apache/hadoop/hbase/CompoundConfiguration.get:(Ljava/lang/String;)Ljava/lang/String;
     337: invokestatic  #18                 // Method org/junit/Assert.assertEquals:(Ljava/lang/Object;Ljava/lang/Object;)V
     340: ldc           #72                 // String not4
     342: aload         4
     344: ldc           #25                 // String D
     346: invokevirtual #17                 // Method org/apache/hadoop/hbase/CompoundConfiguration.get:(Ljava/lang/String;)Ljava/lang/String;
     349: invokestatic  #18                 // Method org/junit/Assert.assertEquals:(Ljava/lang/Object;Ljava/lang/Object;)V
     352: aload         4
     354: aload_1
     355: invokevirtual #69                 // Method org/apache/hadoop/hbase/CompoundConfiguration.addBytesMap:(Ljava/util/Map;)Lorg/apache/hadoop/hbase/CompoundConfiguration;
     358: pop
     359: ldc           #44                 // String 4
     361: aload         4
     363: ldc           #25                 // String D
     365: invokevirtual #17                 // Method org/apache/hadoop/hbase/CompoundConfiguration.get:(Ljava/lang/String;)Ljava/lang/String;
     368: invokestatic  #18                 // Method org/junit/Assert.assertEquals:(Ljava/lang/Object;Ljava/lang/Object;)V
     371: return

  public void testWithStringMap();
    Code:
       0: new           #65                 // class java/util/HashMap
       3: dup
       4: invokespecial #66                 // Method java/util/HashMap."<init>":()V
       7: astore_1
       8: aload_1
       9: ldc           #8                  // String B
      11: ldc           #42                 // String 2b
      13: invokeinterface #68,  3           // InterfaceMethod java/util/Map.put:(Ljava/lang/Object;Ljava/lang/Object;)Ljava/lang/Object;
      18: pop
      19: aload_1
      20: ldc           #10                 // String C
      22: ldc           #43                 // String 33
      24: invokeinterface #68,  3           // InterfaceMethod java/util/Map.put:(Ljava/lang/Object;Ljava/lang/Object;)Ljava/lang/Object;
      29: pop
      30: aload_1
      31: ldc           #25                 // String D
      33: ldc           #44                 // String 4
      35: invokeinterface #68,  3           // InterfaceMethod java/util/Map.put:(Ljava/lang/Object;Ljava/lang/Object;)Ljava/lang/Object;
      40: pop
      41: aload_1
      42: ldc           #61                 // String G
      44: aconst_null
      45: invokeinterface #68,  3           // InterfaceMethod java/util/Map.put:(Ljava/lang/Object;Ljava/lang/Object;)Ljava/lang/Object;
      50: pop
      51: new           #14                 // class org/apache/hadoop/hbase/CompoundConfiguration
      54: dup
      55: invokespecial #15                 // Method org/apache/hadoop/hbase/CompoundConfiguration."<init>":()V
      58: aload_1
      59: invokevirtual #73                 // Method org/apache/hadoop/hbase/CompoundConfiguration.addStringMap:(Ljava/util/Map;)Lorg/apache/hadoop/hbase/CompoundConfiguration;
      62: astore_2
      63: ldc           #42                 // String 2b
      65: aload_2
      66: ldc           #8                  // String B
      68: invokevirtual #17                 // Method org/apache/hadoop/hbase/CompoundConfiguration.get:(Ljava/lang/String;)Ljava/lang/String;
      71: invokestatic  #18                 // Method org/junit/Assert.assertEquals:(Ljava/lang/Object;Ljava/lang/Object;)V
      74: ldc2_w        #45                 // long 33l
      77: aload_2
      78: ldc           #10                 // String C
      80: iconst_0
      81: invokevirtual #21                 // Method org/apache/hadoop/hbase/CompoundConfiguration.getInt:(Ljava/lang/String;I)I
      84: i2l
      85: invokestatic  #22                 // Method org/junit/Assert.assertEquals:(JJ)V
      88: ldc           #44                 // String 4
      90: aload_2
      91: ldc           #25                 // String D
      93: invokevirtual #17                 // Method org/apache/hadoop/hbase/CompoundConfiguration.get:(Ljava/lang/String;)Ljava/lang/String;
      96: invokestatic  #18                 // Method org/junit/Assert.assertEquals:(Ljava/lang/Object;Ljava/lang/Object;)V
      99: ldc2_w        #47                 // long 4l
     102: aload_2
     103: ldc           #25                 // String D
     105: iconst_0
     106: invokevirtual #21                 // Method org/apache/hadoop/hbase/CompoundConfiguration.getInt:(Ljava/lang/String;I)I
     109: i2l
     110: invokestatic  #22                 // Method org/junit/Assert.assertEquals:(JJ)V
     113: aload_2
     114: ldc           #49                 // String E
     116: invokevirtual #17                 // Method org/apache/hadoop/hbase/CompoundConfiguration.get:(Ljava/lang/String;)Ljava/lang/String;
     119: invokestatic  #39                 // Method org/junit/Assert.assertNull:(Ljava/lang/Object;)V
     122: ldc2_w        #50                 // long 6l
     125: aload_2
     126: ldc           #52                 // String F
     128: bipush        6
     130: invokevirtual #21                 // Method org/apache/hadoop/hbase/CompoundConfiguration.getInt:(Ljava/lang/String;I)I
     133: i2l
     134: invokestatic  #22                 // Method org/junit/Assert.assertEquals:(JJ)V
     137: aload_2
     138: ldc           #61                 // String G
     140: invokevirtual #17                 // Method org/apache/hadoop/hbase/CompoundConfiguration.get:(Ljava/lang/String;)Ljava/lang/String;
     143: invokestatic  #39                 // Method org/junit/Assert.assertNull:(Ljava/lang/Object;)V
     146: iconst_0
     147: istore_3
     148: aload_2
     149: invokevirtual #53                 // Method org/apache/hadoop/hbase/CompoundConfiguration.iterator:()Ljava/util/Iterator;
     152: astore        4
     154: aload         4
     156: invokeinterface #54,  1           // InterfaceMethod java/util/Iterator.hasNext:()Z
     161: ifeq          243
     164: aload         4
     166: invokeinterface #55,  1           // InterfaceMethod java/util/Iterator.next:()Ljava/lang/Object;
     171: checkcast     #56                 // class java/util/Map$Entry
     174: astore        5
     176: iinc          3, 1
     179: aload         5
     181: invokeinterface #57,  1           // InterfaceMethod java/util/Map$Entry.getKey:()Ljava/lang/Object;
     186: checkcast     #58                 // class java/lang/String
     189: ldc           #8                  // String B
     191: invokevirtual #59                 // Method java/lang/String.equals:(Ljava/lang/Object;)Z
     194: ifeq          212
     197: ldc           #42                 // String 2b
     199: aload         5
     201: invokeinterface #60,  1           // InterfaceMethod java/util/Map$Entry.getValue:()Ljava/lang/Object;
     206: invokestatic  #18                 // Method org/junit/Assert.assertEquals:(Ljava/lang/Object;Ljava/lang/Object;)V
     209: goto          240
     212: aload         5
     214: invokeinterface #57,  1           // InterfaceMethod java/util/Map$Entry.getKey:()Ljava/lang/Object;
     219: checkcast     #58                 // class java/lang/String
     222: ldc           #61                 // String G
     224: invokevirtual #59                 // Method java/lang/String.equals:(Ljava/lang/Object;)Z
     227: ifeq          240
     230: aload         5
     232: invokeinterface #60,  1           // InterfaceMethod java/util/Map$Entry.getValue:()Ljava/lang/Object;
     237: invokestatic  #39                 // Method org/junit/Assert.assertNull:(Ljava/lang/Object;)V
     240: goto          154
     243: ldc2_w        #47                 // long 4l
     246: iload_3
     247: i2l
     248: invokestatic  #22                 // Method org/junit/Assert.assertEquals:(JJ)V
     251: new           #14                 // class org/apache/hadoop/hbase/CompoundConfiguration
     254: dup
     255: invokespecial #15                 // Method org/apache/hadoop/hbase/CompoundConfiguration."<init>":()V
     258: astore        4
     260: aload         4
     262: ldc           #70                 // String X
     264: ldc           #71                 // String modification
     266: invokevirtual #33                 // Method org/apache/hadoop/hbase/CompoundConfiguration.set:(Ljava/lang/String;Ljava/lang/String;)V
     269: aload         4
     271: ldc           #25                 // String D
     273: ldc           #72                 // String not4
     275: invokevirtual #33                 // Method org/apache/hadoop/hbase/CompoundConfiguration.set:(Ljava/lang/String;Ljava/lang/String;)V
     278: ldc           #71                 // String modification
     280: aload         4
     282: ldc           #70                 // String X
     284: invokevirtual #17                 // Method org/apache/hadoop/hbase/CompoundConfiguration.get:(Ljava/lang/String;)Ljava/lang/String;
     287: invokestatic  #18                 // Method org/junit/Assert.assertEquals:(Ljava/lang/Object;Ljava/lang/Object;)V
     290: ldc           #72                 // String not4
     292: aload         4
     294: ldc           #25                 // String D
     296: invokevirtual #17                 // Method org/apache/hadoop/hbase/CompoundConfiguration.get:(Ljava/lang/String;)Ljava/lang/String;
     299: invokestatic  #18                 // Method org/junit/Assert.assertEquals:(Ljava/lang/Object;Ljava/lang/Object;)V
     302: aload         4
     304: aload_1
     305: invokevirtual #73                 // Method org/apache/hadoop/hbase/CompoundConfiguration.addStringMap:(Ljava/util/Map;)Lorg/apache/hadoop/hbase/CompoundConfiguration;
     308: pop
     309: ldc           #44                 // String 4
     311: aload         4
     313: ldc           #25                 // String D
     315: invokevirtual #17                 // Method org/apache/hadoop/hbase/CompoundConfiguration.get:(Ljava/lang/String;)Ljava/lang/String;
     318: invokestatic  #18                 // Method org/junit/Assert.assertEquals:(Ljava/lang/Object;Ljava/lang/Object;)V
     321: return

  public void testLaterConfigsOverrideEarlier();
    Code:
       0: new           #65                 // class java/util/HashMap
       3: dup
       4: invokespecial #66                 // Method java/util/HashMap."<init>":()V
       7: astore_1
       8: aload_1
       9: ldc           #5                  // String A
      11: ldc           #74                 // String 2
      13: invokeinterface #68,  3           // InterfaceMethod java/util/Map.put:(Ljava/lang/Object;Ljava/lang/Object;)Ljava/lang/Object;
      18: pop
      19: aload_1
      20: ldc           #25                 // String D
      22: ldc           #75                 // String 5
      24: invokeinterface #68,  3           // InterfaceMethod java/util/Map.put:(Ljava/lang/Object;Ljava/lang/Object;)Ljava/lang/Object;
      29: pop
      30: new           #65                 // class java/util/HashMap
      33: dup
      34: invokespecial #66                 // Method java/util/HashMap."<init>":()V
      37: astore_2
      38: ldc           #11                 // String 3
      40: astore_3
      41: ldc           #44                 // String 4
      43: astore        4
      45: aload_2
      46: ldc           #5                  // String A
      48: aload_3
      49: invokeinterface #68,  3           // InterfaceMethod java/util/Map.put:(Ljava/lang/Object;Ljava/lang/Object;)Ljava/lang/Object;
      54: pop
      55: aload_2
      56: ldc           #8                  // String B
      58: aload         4
      60: invokeinterface #68,  3           // InterfaceMethod java/util/Map.put:(Ljava/lang/Object;Ljava/lang/Object;)Ljava/lang/Object;
      65: pop
      66: new           #14                 // class org/apache/hadoop/hbase/CompoundConfiguration
      69: dup
      70: invokespecial #15                 // Method org/apache/hadoop/hbase/CompoundConfiguration."<init>":()V
      73: aload_1
      74: invokevirtual #73                 // Method org/apache/hadoop/hbase/CompoundConfiguration.addStringMap:(Ljava/util/Map;)Lorg/apache/hadoop/hbase/CompoundConfiguration;
      77: aload_0
      78: getfield      #4                  // Field baseConf:Lorg/apache/hadoop/conf/Configuration;
      81: invokevirtual #16                 // Method org/apache/hadoop/hbase/CompoundConfiguration.add:(Lorg/apache/hadoop/conf/Configuration;)Lorg/apache/hadoop/hbase/CompoundConfiguration;
      84: astore        5
      86: ldc           #6                  // String 1
      88: aload         5
      90: ldc           #5                  // String A
      92: invokevirtual #17                 // Method org/apache/hadoop/hbase/CompoundConfiguration.get:(Ljava/lang/String;)Ljava/lang/String;
      95: invokestatic  #18                 // Method org/junit/Assert.assertEquals:(Ljava/lang/Object;Ljava/lang/Object;)V
      98: ldc           #75                 // String 5
     100: aload         5
     102: ldc           #25                 // String D
     104: invokevirtual #17                 // Method org/apache/hadoop/hbase/CompoundConfiguration.get:(Ljava/lang/String;)Ljava/lang/String;
     107: invokestatic  #18                 // Method org/junit/Assert.assertEquals:(Ljava/lang/Object;Ljava/lang/Object;)V
     110: aload         5
     112: aload_2
     113: invokevirtual #73                 // Method org/apache/hadoop/hbase/CompoundConfiguration.addStringMap:(Ljava/util/Map;)Lorg/apache/hadoop/hbase/CompoundConfiguration;
     116: pop
     117: aload_3
     118: aload         5
     120: ldc           #5                  // String A
     122: invokevirtual #17                 // Method org/apache/hadoop/hbase/CompoundConfiguration.get:(Ljava/lang/String;)Ljava/lang/String;
     125: invokestatic  #18                 // Method org/junit/Assert.assertEquals:(Ljava/lang/Object;Ljava/lang/Object;)V
     128: aload         4
     130: aload         5
     132: ldc           #8                  // String B
     134: invokevirtual #17                 // Method org/apache/hadoop/hbase/CompoundConfiguration.get:(Ljava/lang/String;)Ljava/lang/String;
     137: invokestatic  #18                 // Method org/junit/Assert.assertEquals:(Ljava/lang/Object;Ljava/lang/Object;)V
     140: ldc           #75                 // String 5
     142: aload         5
     144: ldc           #25                 // String D
     146: invokevirtual #17                 // Method org/apache/hadoop/hbase/CompoundConfiguration.get:(Ljava/lang/String;)Ljava/lang/String;
     149: invokestatic  #18                 // Method org/junit/Assert.assertEquals:(Ljava/lang/Object;Ljava/lang/Object;)V
     152: iconst_0
     153: istore        6
     155: aload         5
     157: invokevirtual #53                 // Method org/apache/hadoop/hbase/CompoundConfiguration.iterator:()Ljava/util/Iterator;
     160: astore        7
     162: aload         7
     164: invokeinterface #54,  1           // InterfaceMethod java/util/Iterator.hasNext:()Z
     169: ifeq          252
     172: aload         7
     174: invokeinterface #55,  1           // InterfaceMethod java/util/Iterator.next:()Ljava/lang/Object;
     179: checkcast     #56                 // class java/util/Map$Entry
     182: astore        8
     184: iinc          6, 1
     187: aload         8
     189: invokeinterface #57,  1           // InterfaceMethod java/util/Map$Entry.getKey:()Ljava/lang/Object;
     194: checkcast     #58                 // class java/lang/String
     197: ldc           #5                  // String A
     199: invokevirtual #59                 // Method java/lang/String.equals:(Ljava/lang/Object;)Z
     202: ifeq          219
     205: aload_3
     206: aload         8
     208: invokeinterface #60,  1           // InterfaceMethod java/util/Map$Entry.getValue:()Ljava/lang/Object;
     213: invokestatic  #18                 // Method org/junit/Assert.assertEquals:(Ljava/lang/Object;Ljava/lang/Object;)V
     216: goto          249
     219: aload         8
     221: invokeinterface #57,  1           // InterfaceMethod java/util/Map$Entry.getKey:()Ljava/lang/Object;
     226: checkcast     #58                 // class java/lang/String
     229: ldc           #8                  // String B
     231: invokevirtual #59                 // Method java/lang/String.equals:(Ljava/lang/Object;)Z
     234: ifeq          249
     237: aload         4
     239: aload         8
     241: invokeinterface #60,  1           // InterfaceMethod java/util/Map$Entry.getValue:()Ljava/lang/Object;
     246: invokestatic  #18                 // Method org/junit/Assert.assertEquals:(Ljava/lang/Object;Ljava/lang/Object;)V
     249: goto          162
     252: aload_0
     253: getfield      #13                 // Field baseConfSize:I
     256: iconst_1
     257: iadd
     258: i2l
     259: iload         6
     261: i2l
     262: invokestatic  #22                 // Method org/junit/Assert.assertEquals:(JJ)V
     265: return

  static {};
    Code:
       0: ldc           #76                 // class org/apache/hadoop/hbase/TestCompoundConfiguration
       2: invokestatic  #77                 // Method org/apache/hadoop/hbase/HBaseClassTestRule.forClass:(Ljava/lang/Class;)Lorg/apache/hadoop/hbase/HBaseClassTestRule;
       5: putstatic     #78                 // Field CLASS_RULE:Lorg/apache/hadoop/hbase/HBaseClassTestRule;
       8: return
}
