Compiled from "TestSecureLoadIncrementalHFiles.java"
public class org.apache.hadoop.hbase.tool.TestSecureLoadIncrementalHFiles extends org.apache.hadoop.hbase.tool.TestLoadIncrementalHFiles {
  public static final org.apache.hadoop.hbase.HBaseClassTestRule CLASS_RULE;

  public org.apache.hadoop.hbase.tool.TestSecureLoadIncrementalHFiles();
    Code:
       0: aload_0
       1: invokespecial #1                  // Method org/apache/hadoop/hbase/tool/TestLoadIncrementalHFiles."<init>":()V
       4: return

  public static void setUpBeforeClass() throws java.lang.Exception;
    Code:
       0: getstatic     #2                  // Field util:Lorg/apache/hadoop/hbase/HBaseTestingUtility;
       3: invokevirtual #3                  // Method org/apache/hadoop/hbase/HBaseTestingUtility.getConfiguration:()Lorg/apache/hadoop/conf/Configuration;
       6: ldc           #4                  // class org/apache/hadoop/hbase/security/HadoopSecurityEnabledUserProviderForTesting
       8: invokestatic  #5                  // Method org/apache/hadoop/hbase/security/UserProvider.setUserProviderForTesting:(Lorg/apache/hadoop/conf/Configuration;Ljava/lang/Class;)V
      11: getstatic     #2                  // Field util:Lorg/apache/hadoop/hbase/HBaseTestingUtility;
      14: invokevirtual #3                  // Method org/apache/hadoop/hbase/HBaseTestingUtility.getConfiguration:()Lorg/apache/hadoop/conf/Configuration;
      17: invokestatic  #6                  // Method org/apache/hadoop/hbase/security/access/SecureTestUtil.enableSecurity:(Lorg/apache/hadoop/conf/Configuration;)V
      20: getstatic     #2                  // Field util:Lorg/apache/hadoop/hbase/HBaseTestingUtility;
      23: invokevirtual #3                  // Method org/apache/hadoop/hbase/HBaseTestingUtility.getConfiguration:()Lorg/apache/hadoop/conf/Configuration;
      26: ldc           #8                  // String hbase.mapreduce.bulkload.max.hfiles.perRegion.perFamily
      28: iconst_4
      29: invokevirtual #10                 // Method org/apache/hadoop/conf/Configuration.setInt:(Ljava/lang/String;I)V
      32: getstatic     #2                  // Field util:Lorg/apache/hadoop/hbase/HBaseTestingUtility;
      35: invokevirtual #3                  // Method org/apache/hadoop/hbase/HBaseTestingUtility.getConfiguration:()Lorg/apache/hadoop/conf/Configuration;
      38: ldc           #12                 // String hbase.client.rpc.codec
      40: ldc           #13                 // class org/apache/hadoop/hbase/codec/KeyValueCodecWithTags
      42: invokevirtual #14                 // Method java/lang/Class.getCanonicalName:()Ljava/lang/String;
      45: invokevirtual #15                 // Method org/apache/hadoop/conf/Configuration.set:(Ljava/lang/String;Ljava/lang/String;)V
      48: getstatic     #2                  // Field util:Lorg/apache/hadoop/hbase/HBaseTestingUtility;
      51: invokevirtual #16                 // Method org/apache/hadoop/hbase/HBaseTestingUtility.startMiniCluster:()Lorg/apache/hadoop/hbase/MiniHBaseCluster;
      54: pop
      55: getstatic     #2                  // Field util:Lorg/apache/hadoop/hbase/HBaseTestingUtility;
      58: getstatic     #17                 // Field org/apache/hadoop/hbase/security/access/PermissionStorage.ACL_TABLE_NAME:Lorg/apache/hadoop/hbase/TableName;
      61: invokevirtual #18                 // Method org/apache/hadoop/hbase/HBaseTestingUtility.waitTableEnabled:(Lorg/apache/hadoop/hbase/TableName;)V
      64: invokestatic  #19                 // Method setupNamespace:()V
      67: return

  static {};
    Code:
       0: ldc           #20                 // class org/apache/hadoop/hbase/tool/TestSecureLoadIncrementalHFiles
       2: invokestatic  #21                 // Method org/apache/hadoop/hbase/HBaseClassTestRule.forClass:(Ljava/lang/Class;)Lorg/apache/hadoop/hbase/HBaseClassTestRule;
       5: putstatic     #22                 // Field CLASS_RULE:Lorg/apache/hadoop/hbase/HBaseClassTestRule;
       8: return
}
