Compiled from "TestHFileCleaner.java"
class org.apache.hadoop.hbase.master.cleaner.TestHFileCleaner$DummyServer implements org.apache.hadoop.hbase.Server {
  org.apache.hadoop.hbase.master.cleaner.TestHFileCleaner$DummyServer();
    Code:
       0: aload_0
       1: invokespecial #1                  // Method java/lang/Object."<init>":()V
       4: return

  public org.apache.hadoop.conf.Configuration getConfiguration();
    Code:
       0: invokestatic  #2                  // Method org/apache/hadoop/hbase/master/cleaner/TestHFileCleaner.access$000:()Lorg/apache/hadoop/hbase/HBaseTestingUtility;
       3: invokevirtual #3                  // Method org/apache/hadoop/hbase/HBaseTestingUtility.getConfiguration:()Lorg/apache/hadoop/conf/Configuration;
       6: areturn

  public org.apache.hadoop.hbase.zookeeper.ZKWatcher getZooKeeper();
    Code:
       0: new           #4                  // class org/apache/hadoop/hbase/zookeeper/ZKWatcher
       3: dup
       4: aload_0
       5: invokevirtual #5                  // Method getConfiguration:()Lorg/apache/hadoop/conf/Configuration;
       8: ldc           #6                  // String dummy server
      10: aload_0
      11: invokespecial #7                  // Method org/apache/hadoop/hbase/zookeeper/ZKWatcher."<init>":(Lorg/apache/hadoop/conf/Configuration;Ljava/lang/String;Lorg/apache/hadoop/hbase/Abortable;)V
      14: areturn
      15: astore_1
      16: aload_1
      17: invokevirtual #9                  // Method java/io/IOException.printStackTrace:()V
      20: aconst_null
      21: areturn
    Exception table:
       from    to  target type
           0    14    15   Class java/io/IOException

  public org.apache.hadoop.hbase.CoordinatedStateManager getCoordinatedStateManager();
    Code:
       0: aconst_null
       1: areturn

  public org.apache.hadoop.hbase.client.ClusterConnection getConnection();
    Code:
       0: aconst_null
       1: areturn

  public org.apache.hadoop.hbase.ServerName getServerName();
    Code:
       0: ldc           #10                 // String regionserver,60020,000000
       2: invokestatic  #11                 // Method org/apache/hadoop/hbase/ServerName.valueOf:(Ljava/lang/String;)Lorg/apache/hadoop/hbase/ServerName;
       5: areturn

  public void abort(java.lang.String, java.lang.Throwable);
    Code:
       0: return

  public boolean isAborted();
    Code:
       0: iconst_0
       1: ireturn

  public void stop(java.lang.String);
    Code:
       0: return

  public boolean isStopped();
    Code:
       0: iconst_0
       1: ireturn

  public org.apache.hadoop.hbase.ChoreService getChoreService();
    Code:
       0: aconst_null
       1: areturn

  public org.apache.hadoop.hbase.client.ClusterConnection getClusterConnection();
    Code:
       0: aconst_null
       1: areturn

  public org.apache.hadoop.fs.FileSystem getFileSystem();
    Code:
       0: aconst_null
       1: areturn

  public boolean isStopping();
    Code:
       0: iconst_0
       1: ireturn

  public org.apache.hadoop.hbase.client.Connection createConnection(org.apache.hadoop.conf.Configuration) throws java.io.IOException;
    Code:
       0: aconst_null
       1: areturn

  public org.apache.hadoop.hbase.client.Connection getConnection();
    Code:
       0: aload_0
       1: invokevirtual #12                 // Method getConnection:()Lorg/apache/hadoop/hbase/client/ClusterConnection;
       4: areturn
}
