Compiled from "TestRegionReplicas.java"
class org.apache.hadoop.hbase.regionserver.TestRegionReplicas$3 implements java.lang.Runnable {
  java.util.Random random;

  final java.util.concurrent.atomic.AtomicBoolean val$running;

  final java.util.concurrent.atomic.AtomicReference[] val$exceptions;

  final org.apache.hadoop.hbase.regionserver.TestRegionReplicas this$0;

  org.apache.hadoop.hbase.regionserver.TestRegionReplicas$3(org.apache.hadoop.hbase.regionserver.TestRegionReplicas, java.util.concurrent.atomic.AtomicBoolean, java.util.concurrent.atomic.AtomicReference[]);
    Code:
       0: aload_0
       1: aload_1
       2: putfield      #1                  // Field this$0:Lorg/apache/hadoop/hbase/regionserver/TestRegionReplicas;
       5: aload_0
       6: aload_2
       7: putfield      #2                  // Field val$running:Ljava/util/concurrent/atomic/AtomicBoolean;
      10: aload_0
      11: aload_3
      12: putfield      #3                  // Field val$exceptions:[Ljava/util/concurrent/atomic/AtomicReference;
      15: aload_0
      16: invokespecial #4                  // Method java/lang/Object."<init>":()V
      19: aload_0
      20: new           #5                  // class java/util/Random
      23: dup
      24: invokespecial #6                  // Method java/util/Random."<init>":()V
      27: putfield      #7                  // Field random:Ljava/util/Random;
      30: return

  public void run();
    Code:
       0: aload_0
       1: getfield      #2                  // Field val$running:Ljava/util/concurrent/atomic/AtomicBoolean;
       4: invokevirtual #8                  // Method java/util/concurrent/atomic/AtomicBoolean.get:()Z
       7: ifeq          196
      10: aload_0
      11: getfield      #7                  // Field random:Ljava/util/Random;
      14: bipush        10
      16: invokevirtual #9                  // Method java/util/Random.nextInt:(I)I
      19: ifne          168
      22: invokestatic  #10                 // Method org/apache/hadoop/hbase/regionserver/TestRegionReplicas.access$300:()Lorg/apache/hadoop/hbase/HBaseTestingUtility;
      25: aload_0
      26: getfield      #1                  // Field this$0:Lorg/apache/hadoop/hbase/regionserver/TestRegionReplicas;
      29: invokestatic  #11                 // Method org/apache/hadoop/hbase/regionserver/TestRegionReplicas.access$500:(Lorg/apache/hadoop/hbase/regionserver/TestRegionReplicas;)Lorg/apache/hadoop/hbase/regionserver/HRegionServer;
      32: invokestatic  #12                 // Method org/apache/hadoop/hbase/regionserver/TestRegionReplicas.access$600:()Lorg/apache/hadoop/hbase/HRegionInfo;
      35: invokestatic  #13                 // Method org/apache/hadoop/hbase/regionserver/TestRegionServerNoMaster.closeRegion:(Lorg/apache/hadoop/hbase/HBaseTestingUtility;Lorg/apache/hadoop/hbase/regionserver/HRegionServer;Lorg/apache/hadoop/hbase/HRegionInfo;)V
      38: goto          95
      41: astore_1
      42: invokestatic  #15                 // Method org/apache/hadoop/hbase/regionserver/TestRegionReplicas.access$200:()Lorg/slf4j/Logger;
      45: new           #16                 // class java/lang/StringBuilder
      48: dup
      49: invokespecial #17                 // Method java/lang/StringBuilder."<init>":()V
      52: ldc           #18                 // String Failed closing the region
      54: invokevirtual #19                 // Method java/lang/StringBuilder.append:(Ljava/lang/String;)Ljava/lang/StringBuilder;
      57: invokestatic  #12                 // Method org/apache/hadoop/hbase/regionserver/TestRegionReplicas.access$600:()Lorg/apache/hadoop/hbase/HRegionInfo;
      60: invokevirtual #20                 // Method java/lang/StringBuilder.append:(Ljava/lang/Object;)Ljava/lang/StringBuilder;
      63: ldc           #21                 // String
      65: invokevirtual #19                 // Method java/lang/StringBuilder.append:(Ljava/lang/String;)Ljava/lang/StringBuilder;
      68: aload_1
      69: invokestatic  #22                 // Method org/apache/hadoop/util/StringUtils.stringifyException:(Ljava/lang/Throwable;)Ljava/lang/String;
      72: invokevirtual #19                 // Method java/lang/StringBuilder.append:(Ljava/lang/String;)Ljava/lang/StringBuilder;
      75: invokevirtual #23                 // Method java/lang/StringBuilder.toString:()Ljava/lang/String;
      78: invokeinterface #24,  2           // InterfaceMethod org/slf4j/Logger.warn:(Ljava/lang/String;)V
      83: aload_0
      84: getfield      #3                  // Field val$exceptions:[Ljava/util/concurrent/atomic/AtomicReference;
      87: iconst_2
      88: aaload
      89: aconst_null
      90: aload_1
      91: invokevirtual #25                 // Method java/util/concurrent/atomic/AtomicReference.compareAndSet:(Ljava/lang/Object;Ljava/lang/Object;)Z
      94: pop
      95: invokestatic  #10                 // Method org/apache/hadoop/hbase/regionserver/TestRegionReplicas.access$300:()Lorg/apache/hadoop/hbase/HBaseTestingUtility;
      98: aload_0
      99: getfield      #1                  // Field this$0:Lorg/apache/hadoop/hbase/regionserver/TestRegionReplicas;
     102: invokestatic  #11                 // Method org/apache/hadoop/hbase/regionserver/TestRegionReplicas.access$500:(Lorg/apache/hadoop/hbase/regionserver/TestRegionReplicas;)Lorg/apache/hadoop/hbase/regionserver/HRegionServer;
     105: invokestatic  #12                 // Method org/apache/hadoop/hbase/regionserver/TestRegionReplicas.access$600:()Lorg/apache/hadoop/hbase/HRegionInfo;
     108: invokestatic  #26                 // Method org/apache/hadoop/hbase/regionserver/TestRegionServerNoMaster.openRegion:(Lorg/apache/hadoop/hbase/HBaseTestingUtility;Lorg/apache/hadoop/hbase/regionserver/HRegionServer;Lorg/apache/hadoop/hbase/HRegionInfo;)V
     111: goto          168
     114: astore_1
     115: invokestatic  #15                 // Method org/apache/hadoop/hbase/regionserver/TestRegionReplicas.access$200:()Lorg/slf4j/Logger;
     118: new           #16                 // class java/lang/StringBuilder
     121: dup
     122: invokespecial #17                 // Method java/lang/StringBuilder."<init>":()V
     125: ldc           #27                 // String Failed opening the region
     127: invokevirtual #19                 // Method java/lang/StringBuilder.append:(Ljava/lang/String;)Ljava/lang/StringBuilder;
     130: invokestatic  #12                 // Method org/apache/hadoop/hbase/regionserver/TestRegionReplicas.access$600:()Lorg/apache/hadoop/hbase/HRegionInfo;
     133: invokevirtual #20                 // Method java/lang/StringBuilder.append:(Ljava/lang/Object;)Ljava/lang/StringBuilder;
     136: ldc           #21                 // String
     138: invokevirtual #19                 // Method java/lang/StringBuilder.append:(Ljava/lang/String;)Ljava/lang/StringBuilder;
     141: aload_1
     142: invokestatic  #22                 // Method org/apache/hadoop/util/StringUtils.stringifyException:(Ljava/lang/Throwable;)Ljava/lang/String;
     145: invokevirtual #19                 // Method java/lang/StringBuilder.append:(Ljava/lang/String;)Ljava/lang/StringBuilder;
     148: invokevirtual #23                 // Method java/lang/StringBuilder.toString:()Ljava/lang/String;
     151: invokeinterface #24,  2           // InterfaceMethod org/slf4j/Logger.warn:(Ljava/lang/String;)V
     156: aload_0
     157: getfield      #3                  // Field val$exceptions:[Ljava/util/concurrent/atomic/AtomicReference;
     160: iconst_2
     161: aaload
     162: aconst_null
     163: aload_1
     164: invokevirtual #25                 // Method java/util/concurrent/atomic/AtomicReference.compareAndSet:(Ljava/lang/Object;Ljava/lang/Object;)Z
     167: pop
     168: aload_0
     169: getfield      #7                  // Field random:Ljava/util/Random;
     172: sipush        1000
     175: invokevirtual #9                  // Method java/util/Random.nextInt:(I)I
     178: iconst_0
     179: iadd
     180: istore_1
     181: aload_0
     182: getfield      #1                  // Field this$0:Lorg/apache/hadoop/hbase/regionserver/TestRegionReplicas;
     185: invokestatic  #12                 // Method org/apache/hadoop/hbase/regionserver/TestRegionReplicas.access$600:()Lorg/apache/hadoop/hbase/HRegionInfo;
     188: iload_1
     189: iconst_1
     190: invokestatic  #28                 // Method org/apache/hadoop/hbase/regionserver/TestRegionReplicas.access$700:(Lorg/apache/hadoop/hbase/regionserver/TestRegionReplicas;Lorg/apache/hadoop/hbase/HRegionInfo;IZ)V
     193: goto          0
     196: goto          253
     199: astore_1
     200: invokestatic  #15                 // Method org/apache/hadoop/hbase/regionserver/TestRegionReplicas.access$200:()Lorg/slf4j/Logger;
     203: new           #16                 // class java/lang/StringBuilder
     206: dup
     207: invokespecial #17                 // Method java/lang/StringBuilder."<init>":()V
     210: ldc           #29                 // String Failed getting the value in the region
     212: invokevirtual #19                 // Method java/lang/StringBuilder.append:(Ljava/lang/String;)Ljava/lang/StringBuilder;
     215: invokestatic  #12                 // Method org/apache/hadoop/hbase/regionserver/TestRegionReplicas.access$600:()Lorg/apache/hadoop/hbase/HRegionInfo;
     218: invokevirtual #20                 // Method java/lang/StringBuilder.append:(Ljava/lang/Object;)Ljava/lang/StringBuilder;
     221: ldc           #21                 // String
     223: invokevirtual #19                 // Method java/lang/StringBuilder.append:(Ljava/lang/String;)Ljava/lang/StringBuilder;
     226: aload_1
     227: invokestatic  #22                 // Method org/apache/hadoop/util/StringUtils.stringifyException:(Ljava/lang/Throwable;)Ljava/lang/String;
     230: invokevirtual #19                 // Method java/lang/StringBuilder.append:(Ljava/lang/String;)Ljava/lang/StringBuilder;
     233: invokevirtual #23                 // Method java/lang/StringBuilder.toString:()Ljava/lang/String;
     236: invokeinterface #24,  2           // InterfaceMethod org/slf4j/Logger.warn:(Ljava/lang/String;)V
     241: aload_0
     242: getfield      #3                  // Field val$exceptions:[Ljava/util/concurrent/atomic/AtomicReference;
     245: iconst_2
     246: aaload
     247: aconst_null
     248: aload_1
     249: invokevirtual #25                 // Method java/util/concurrent/atomic/AtomicReference.compareAndSet:(Ljava/lang/Object;Ljava/lang/Object;)Z
     252: pop
     253: return
    Exception table:
       from    to  target type
          22    38    41   Class java/lang/Exception
          95   111   114   Class java/lang/Exception
           0   196   199   Class java/lang/Exception
}
