Compiled from "TestActiveMasterManager.java"
public class org.apache.hadoop.hbase.master.TestActiveMasterManager$WaitToBeMasterThread extends java.lang.Thread {
  org.apache.hadoop.hbase.master.ActiveMasterManager manager;

  org.apache.hadoop.hbase.master.TestActiveMasterManager$DummyMaster dummyMaster;

  boolean isActiveMaster;

  public org.apache.hadoop.hbase.master.TestActiveMasterManager$WaitToBeMasterThread(org.apache.hadoop.hbase.zookeeper.ZKWatcher, org.apache.hadoop.hbase.ServerName);
    Code:
       0: aload_0
       1: invokespecial #1                  // Method java/lang/Thread."<init>":()V
       4: aload_0
       5: new           #2                  // class org/apache/hadoop/hbase/master/TestActiveMasterManager$DummyMaster
       8: dup
       9: aload_1
      10: aload_2
      11: invokespecial #3                  // Method org/apache/hadoop/hbase/master/TestActiveMasterManager$DummyMaster."<init>":(Lorg/apache/hadoop/hbase/zookeeper/ZKWatcher;Lorg/apache/hadoop/hbase/ServerName;)V
      14: putfield      #4                  // Field dummyMaster:Lorg/apache/hadoop/hbase/master/TestActiveMasterManager$DummyMaster;
      17: aload_0
      18: aload_0
      19: getfield      #4                  // Field dummyMaster:Lorg/apache/hadoop/hbase/master/TestActiveMasterManager$DummyMaster;
      22: invokevirtual #5                  // Method org/apache/hadoop/hbase/master/TestActiveMasterManager$DummyMaster.getActiveMasterManager:()Lorg/apache/hadoop/hbase/master/ActiveMasterManager;
      25: putfield      #6                  // Field manager:Lorg/apache/hadoop/hbase/master/ActiveMasterManager;
      28: aload_0
      29: iconst_0
      30: putfield      #7                  // Field isActiveMaster:Z
      33: return

  public void run();
    Code:
       0: aload_0
       1: getfield      #6                  // Field manager:Lorg/apache/hadoop/hbase/master/ActiveMasterManager;
       4: bipush        100
       6: ldc           #8                  // class org/apache/hadoop/hbase/monitoring/MonitoredTask
       8: invokestatic  #9                  // Method org/mockito/Mockito.mock:(Ljava/lang/Class;)Ljava/lang/Object;
      11: checkcast     #8                  // class org/apache/hadoop/hbase/monitoring/MonitoredTask
      14: invokevirtual #10                 // Method org/apache/hadoop/hbase/master/ActiveMasterManager.blockUntilBecomingActiveMaster:(ILorg/apache/hadoop/hbase/monitoring/MonitoredTask;)Z
      17: pop
      18: invokestatic  #11                 // Method org/apache/hadoop/hbase/master/TestActiveMasterManager.access$000:()Lorg/slf4j/Logger;
      21: ldc           #12                 // String Second master has become the active master!
      23: invokeinterface #13,  2           // InterfaceMethod org/slf4j/Logger.info:(Ljava/lang/String;)V
      28: aload_0
      29: iconst_1
      30: putfield      #7                  // Field isActiveMaster:Z
      33: return
}
