Compiled from "TestHeapMemoryManager.java"
class org.apache.hadoop.hbase.regionserver.TestHeapMemoryManager$BlockCacheStub implements org.apache.hadoop.hbase.io.hfile.ResizableBlockCache {
  org.apache.hadoop.hbase.io.hfile.CacheStats stats;

  long maxSize;

  public org.apache.hadoop.hbase.regionserver.TestHeapMemoryManager$BlockCacheStub(long);
    Code:
       0: aload_0
       1: invokespecial #1                  // Method java/lang/Object."<init>":()V
       4: aload_0
       5: new           #2                  // class org/apache/hadoop/hbase/io/hfile/CacheStats
       8: dup
       9: ldc           #3                  // String test
      11: invokespecial #4                  // Method org/apache/hadoop/hbase/io/hfile/CacheStats."<init>":(Ljava/lang/String;)V
      14: putfield      #5                  // Field stats:Lorg/apache/hadoop/hbase/io/hfile/CacheStats;
      17: aload_0
      18: lconst_0
      19: putfield      #6                  // Field maxSize:J
      22: aload_0
      23: lconst_0
      24: putfield      #7                  // Field testBlockSize:J
      27: aload_0
      28: lload_1
      29: putfield      #6                  // Field maxSize:J
      32: return

  public void cacheBlock(org.apache.hadoop.hbase.io.hfile.BlockCacheKey, org.apache.hadoop.hbase.io.hfile.Cacheable, boolean);
    Code:
       0: return

  public void cacheBlock(org.apache.hadoop.hbase.io.hfile.BlockCacheKey, org.apache.hadoop.hbase.io.hfile.Cacheable);
    Code:
       0: return

  public org.apache.hadoop.hbase.io.hfile.Cacheable getBlock(org.apache.hadoop.hbase.io.hfile.BlockCacheKey, boolean, boolean, boolean);
    Code:
       0: aconst_null
       1: areturn

  public boolean evictBlock(org.apache.hadoop.hbase.io.hfile.BlockCacheKey);
    Code:
       0: aload_0
       1: getfield      #5                  // Field stats:Lorg/apache/hadoop/hbase/io/hfile/CacheStats;
       4: lconst_0
       5: aload_1
       6: ifnull        16
       9: aload_1
      10: invokevirtual #8                  // Method org/apache/hadoop/hbase/io/hfile/BlockCacheKey.isPrimary:()Z
      13: goto          17
      16: iconst_1
      17: invokevirtual #9                  // Method org/apache/hadoop/hbase/io/hfile/CacheStats.evicted:(JZ)V
      20: iconst_0
      21: ireturn

  public int evictBlocksByHfileName(java.lang.String);
    Code:
       0: aload_0
       1: getfield      #5                  // Field stats:Lorg/apache/hadoop/hbase/io/hfile/CacheStats;
       4: lconst_0
       5: iconst_1
       6: invokevirtual #9                  // Method org/apache/hadoop/hbase/io/hfile/CacheStats.evicted:(JZ)V
       9: iconst_0
      10: ireturn

  public org.apache.hadoop.hbase.io.hfile.CacheStats getStats();
    Code:
       0: aload_0
       1: getfield      #5                  // Field stats:Lorg/apache/hadoop/hbase/io/hfile/CacheStats;
       4: areturn

  public void shutdown();
    Code:
       0: return

  public long size();
    Code:
       0: lconst_0
       1: lreturn

  public long getMaxSize();
    Code:
       0: lconst_0
       1: lreturn

  public long getFreeSize();
    Code:
       0: lconst_0
       1: lreturn

  public long getCurrentSize();
    Code:
       0: aload_0
       1: getfield      #7                  // Field testBlockSize:J
       4: lreturn

  public long getCurrentDataSize();
    Code:
       0: lconst_0
       1: lreturn

  public long getBlockCount();
    Code:
       0: lconst_0
       1: lreturn

  public long getDataBlockCount();
    Code:
       0: lconst_0
       1: lreturn

  public void setMaxSize(long);
    Code:
       0: aload_0
       1: lload_1
       2: putfield      #6                  // Field maxSize:J
       5: return

  public java.util.Iterator<org.apache.hadoop.hbase.io.hfile.CachedBlock> iterator();
    Code:
       0: aconst_null
       1: areturn

  public org.apache.hadoop.hbase.io.hfile.BlockCache[] getBlockCaches();
    Code:
       0: aconst_null
       1: areturn

  public void returnBlock(org.apache.hadoop.hbase.io.hfile.BlockCacheKey, org.apache.hadoop.hbase.io.hfile.Cacheable);
    Code:
       0: return

  public void setTestBlockSize(long);
    Code:
       0: aload_0
       1: lload_1
       2: putfield      #7                  // Field testBlockSize:J
       5: return
}
