Compiled from "TestQuotaStatusRPCs.java"
class org.apache.hadoop.hbase.quotas.TestQuotaStatusRPCs$3 implements org.apache.hadoop.hbase.Waiter$Predicate<java.lang.Exception> {
  final org.apache.hadoop.hbase.quotas.RegionServerSpaceQuotaManager val$manager;

  final org.apache.hadoop.hbase.TableName val$tn;

  final org.apache.hadoop.hbase.quotas.TestQuotaStatusRPCs this$0;

  org.apache.hadoop.hbase.quotas.TestQuotaStatusRPCs$3(org.apache.hadoop.hbase.quotas.TestQuotaStatusRPCs, org.apache.hadoop.hbase.quotas.RegionServerSpaceQuotaManager, org.apache.hadoop.hbase.TableName);
    Code:
       0: aload_0
       1: aload_1
       2: putfield      #1                  // Field this$0:Lorg/apache/hadoop/hbase/quotas/TestQuotaStatusRPCs;
       5: aload_0
       6: aload_2
       7: putfield      #2                  // Field val$manager:Lorg/apache/hadoop/hbase/quotas/RegionServerSpaceQuotaManager;
      10: aload_0
      11: aload_3
      12: putfield      #3                  // Field val$tn:Lorg/apache/hadoop/hbase/TableName;
      15: aload_0
      16: invokespecial #4                  // Method java/lang/Object."<init>":()V
      19: return

  public boolean evaluate() throws java.lang.Exception;
    Code:
       0: aload_0
       1: getfield      #2                  // Field val$manager:Lorg/apache/hadoop/hbase/quotas/RegionServerSpaceQuotaManager;
       4: invokevirtual #5                  // Method org/apache/hadoop/hbase/quotas/RegionServerSpaceQuotaManager.getActiveEnforcements:()Lorg/apache/hadoop/hbase/quotas/ActivePolicyEnforcement;
       7: astore_1
       8: aload_1
       9: aload_0
      10: getfield      #3                  // Field val$tn:Lorg/apache/hadoop/hbase/TableName;
      13: invokevirtual #6                  // Method org/apache/hadoop/hbase/quotas/ActivePolicyEnforcement.getPolicyEnforcement:(Lorg/apache/hadoop/hbase/TableName;)Lorg/apache/hadoop/hbase/quotas/SpaceViolationPolicyEnforcement;
      16: astore_2
      17: aload_2
      18: instanceof    #7                  // class org/apache/hadoop/hbase/quotas/policies/MissingSnapshotViolationPolicyEnforcement
      21: ifeq          26
      24: iconst_0
      25: ireturn
      26: aload_2
      27: invokeinterface #8,  1            // InterfaceMethod org/apache/hadoop/hbase/quotas/SpaceViolationPolicyEnforcement.getQuotaSnapshot:()Lorg/apache/hadoop/hbase/quotas/SpaceQuotaSnapshot;
      32: invokevirtual #9                  // Method org/apache/hadoop/hbase/quotas/SpaceQuotaSnapshot.getQuotaStatus:()Lorg/apache/hadoop/hbase/quotas/SpaceQuotaSnapshot$SpaceQuotaStatus;
      35: invokevirtual #10                 // Method org/apache/hadoop/hbase/quotas/SpaceQuotaSnapshot$SpaceQuotaStatus.isInViolation:()Z
      38: ireturn
}
