Compiled from "TestAsyncTableRpcPriority.java"
class org.apache.hadoop.hbase.client.TestAsyncTableRpcPriority$1 implements org.mockito.stubbing.Answer<java.lang.Void> {
  final java.util.concurrent.atomic.AtomicInteger val$scanNextCalled;

  final org.apache.hadoop.hbase.client.TestAsyncTableRpcPriority this$0;

  org.apache.hadoop.hbase.client.TestAsyncTableRpcPriority$1(org.apache.hadoop.hbase.client.TestAsyncTableRpcPriority, java.util.concurrent.atomic.AtomicInteger);
    Code:
       0: aload_0
       1: aload_1
       2: putfield      #1                  // Field this$0:Lorg/apache/hadoop/hbase/client/TestAsyncTableRpcPriority;
       5: aload_0
       6: aload_2
       7: putfield      #2                  // Field val$scanNextCalled:Ljava/util/concurrent/atomic/AtomicInteger;
      10: aload_0
      11: invokespecial #3                  // Method java/lang/Object."<init>":()V
      14: return

  public java.lang.Void answer(org.mockito.invocation.InvocationOnMock) throws java.lang.Throwable;
    Code:
       0: aload_1
       1: iconst_1
       2: invokeinterface #4,  2            // InterfaceMethod org/mockito/invocation/InvocationOnMock.getArgument:(I)Ljava/lang/Object;
       7: checkcast     #5                  // class org/apache/hadoop/hbase/shaded/protobuf/generated/ClientProtos$ScanRequest
      10: astore_2
      11: aload_1
      12: iconst_2
      13: invokeinterface #4,  2            // InterfaceMethod org/mockito/invocation/InvocationOnMock.getArgument:(I)Ljava/lang/Object;
      18: checkcast     #6                  // class org/apache/hbase/thirdparty/com/google/protobuf/RpcCallback
      21: astore_3
      22: aload_2
      23: invokevirtual #7                  // Method org/apache/hadoop/hbase/shaded/protobuf/generated/ClientProtos$ScanRequest.hasScannerId:()Z
      26: ifne          62
      29: aload_3
      30: invokestatic  #8                  // Method org/apache/hadoop/hbase/shaded/protobuf/generated/ClientProtos$ScanResponse.newBuilder:()Lorg/apache/hadoop/hbase/shaded/protobuf/generated/ClientProtos$ScanResponse$Builder;
      33: lconst_1
      34: invokevirtual #9                  // Method org/apache/hadoop/hbase/shaded/protobuf/generated/ClientProtos$ScanResponse$Builder.setScannerId:(J)Lorg/apache/hadoop/hbase/shaded/protobuf/generated/ClientProtos$ScanResponse$Builder;
      37: sipush        800
      40: invokevirtual #10                 // Method org/apache/hadoop/hbase/shaded/protobuf/generated/ClientProtos$ScanResponse$Builder.setTtl:(I)Lorg/apache/hadoop/hbase/shaded/protobuf/generated/ClientProtos$ScanResponse$Builder;
      43: iconst_1
      44: invokevirtual #11                 // Method org/apache/hadoop/hbase/shaded/protobuf/generated/ClientProtos$ScanResponse$Builder.setMoreResultsInRegion:(Z)Lorg/apache/hadoop/hbase/shaded/protobuf/generated/ClientProtos$ScanResponse$Builder;
      47: iconst_1
      48: invokevirtual #12                 // Method org/apache/hadoop/hbase/shaded/protobuf/generated/ClientProtos$ScanResponse$Builder.setMoreResults:(Z)Lorg/apache/hadoop/hbase/shaded/protobuf/generated/ClientProtos$ScanResponse$Builder;
      51: invokevirtual #13                 // Method org/apache/hadoop/hbase/shaded/protobuf/generated/ClientProtos$ScanResponse$Builder.build:()Lorg/apache/hadoop/hbase/shaded/protobuf/generated/ClientProtos$ScanResponse;
      54: invokeinterface #14,  2           // InterfaceMethod org/apache/hbase/thirdparty/com/google/protobuf/RpcCallback.run:(Ljava/lang/Object;)V
      59: goto          209
      62: aload_2
      63: invokevirtual #15                 // Method org/apache/hadoop/hbase/shaded/protobuf/generated/ClientProtos$ScanRequest.hasCloseScanner:()Z
      66: ifeq          88
      69: aload_2
      70: invokevirtual #16                 // Method org/apache/hadoop/hbase/shaded/protobuf/generated/ClientProtos$ScanRequest.getCloseScanner:()Z
      73: ifeq          88
      76: aload_3
      77: invokestatic  #17                 // Method org/apache/hadoop/hbase/shaded/protobuf/generated/ClientProtos$ScanResponse.getDefaultInstance:()Lorg/apache/hadoop/hbase/shaded/protobuf/generated/ClientProtos$ScanResponse;
      80: invokeinterface #14,  2           // InterfaceMethod org/apache/hbase/thirdparty/com/google/protobuf/RpcCallback.run:(Ljava/lang/Object;)V
      85: goto          209
      88: getstatic     #18                 // Field org/apache/hadoop/hbase/CellBuilderType.SHALLOW_COPY:Lorg/apache/hadoop/hbase/CellBuilderType;
      91: invokestatic  #19                 // Method org/apache/hadoop/hbase/CellBuilderFactory.create:(Lorg/apache/hadoop/hbase/CellBuilderType;)Lorg/apache/hadoop/hbase/CellBuilder;
      94: getstatic     #20                 // Field org/apache/hadoop/hbase/Cell$Type.Put:Lorg/apache/hadoop/hbase/Cell$Type;
      97: invokeinterface #21,  2           // InterfaceMethod org/apache/hadoop/hbase/CellBuilder.setType:(Lorg/apache/hadoop/hbase/Cell$Type;)Lorg/apache/hadoop/hbase/CellBuilder;
     102: aload_0
     103: getfield      #2                  // Field val$scanNextCalled:Ljava/util/concurrent/atomic/AtomicInteger;
     106: invokevirtual #22                 // Method java/util/concurrent/atomic/AtomicInteger.incrementAndGet:()I
     109: invokestatic  #23                 // Method org/apache/hadoop/hbase/util/Bytes.toBytes:(I)[B
     112: invokeinterface #24,  2           // InterfaceMethod org/apache/hadoop/hbase/CellBuilder.setRow:([B)Lorg/apache/hadoop/hbase/CellBuilder;
     117: ldc           #25                 // String cf
     119: invokestatic  #26                 // Method org/apache/hadoop/hbase/util/Bytes.toBytes:(Ljava/lang/String;)[B
     122: invokeinterface #27,  2           // InterfaceMethod org/apache/hadoop/hbase/CellBuilder.setFamily:([B)Lorg/apache/hadoop/hbase/CellBuilder;
     127: ldc           #28                 // String cq
     129: invokestatic  #26                 // Method org/apache/hadoop/hbase/util/Bytes.toBytes:(Ljava/lang/String;)[B
     132: invokeinterface #29,  2           // InterfaceMethod org/apache/hadoop/hbase/CellBuilder.setQualifier:([B)Lorg/apache/hadoop/hbase/CellBuilder;
     137: ldc           #30                 // String v
     139: invokestatic  #26                 // Method org/apache/hadoop/hbase/util/Bytes.toBytes:(Ljava/lang/String;)[B
     142: invokeinterface #31,  2           // InterfaceMethod org/apache/hadoop/hbase/CellBuilder.setValue:([B)Lorg/apache/hadoop/hbase/CellBuilder;
     147: invokeinterface #32,  1           // InterfaceMethod org/apache/hadoop/hbase/CellBuilder.build:()Lorg/apache/hadoop/hbase/Cell;
     152: astore        4
     154: iconst_1
     155: anewarray     #33                 // class org/apache/hadoop/hbase/Cell
     158: dup
     159: iconst_0
     160: aload         4
     162: aastore
     163: invokestatic  #34                 // Method java/util/Arrays.asList:([Ljava/lang/Object;)Ljava/util/List;
     166: invokestatic  #35                 // Method org/apache/hadoop/hbase/client/Result.create:(Ljava/util/List;)Lorg/apache/hadoop/hbase/client/Result;
     169: astore        5
     171: aload_3
     172: invokestatic  #8                  // Method org/apache/hadoop/hbase/shaded/protobuf/generated/ClientProtos$ScanResponse.newBuilder:()Lorg/apache/hadoop/hbase/shaded/protobuf/generated/ClientProtos$ScanResponse$Builder;
     175: lconst_1
     176: invokevirtual #9                  // Method org/apache/hadoop/hbase/shaded/protobuf/generated/ClientProtos$ScanResponse$Builder.setScannerId:(J)Lorg/apache/hadoop/hbase/shaded/protobuf/generated/ClientProtos$ScanResponse$Builder;
     179: sipush        800
     182: invokevirtual #10                 // Method org/apache/hadoop/hbase/shaded/protobuf/generated/ClientProtos$ScanResponse$Builder.setTtl:(I)Lorg/apache/hadoop/hbase/shaded/protobuf/generated/ClientProtos$ScanResponse$Builder;
     185: iconst_1
     186: invokevirtual #11                 // Method org/apache/hadoop/hbase/shaded/protobuf/generated/ClientProtos$ScanResponse$Builder.setMoreResultsInRegion:(Z)Lorg/apache/hadoop/hbase/shaded/protobuf/generated/ClientProtos$ScanResponse$Builder;
     189: iconst_1
     190: invokevirtual #12                 // Method org/apache/hadoop/hbase/shaded/protobuf/generated/ClientProtos$ScanResponse$Builder.setMoreResults:(Z)Lorg/apache/hadoop/hbase/shaded/protobuf/generated/ClientProtos$ScanResponse$Builder;
     193: aload         5
     195: invokestatic  #36                 // Method org/apache/hadoop/hbase/shaded/protobuf/ProtobufUtil.toResult:(Lorg/apache/hadoop/hbase/client/Result;)Lorg/apache/hadoop/hbase/shaded/protobuf/generated/ClientProtos$Result;
     198: invokevirtual #37                 // Method org/apache/hadoop/hbase/shaded/protobuf/generated/ClientProtos$ScanResponse$Builder.addResults:(Lorg/apache/hadoop/hbase/shaded/protobuf/generated/ClientProtos$Result;)Lorg/apache/hadoop/hbase/shaded/protobuf/generated/ClientProtos$ScanResponse$Builder;
     201: invokevirtual #13                 // Method org/apache/hadoop/hbase/shaded/protobuf/generated/ClientProtos$ScanResponse$Builder.build:()Lorg/apache/hadoop/hbase/shaded/protobuf/generated/ClientProtos$ScanResponse;
     204: invokeinterface #14,  2           // InterfaceMethod org/apache/hbase/thirdparty/com/google/protobuf/RpcCallback.run:(Ljava/lang/Object;)V
     209: aconst_null
     210: areturn

  public java.lang.Object answer(org.mockito.invocation.InvocationOnMock) throws java.lang.Throwable;
    Code:
       0: aload_0
       1: aload_1
       2: invokevirtual #38                 // Method answer:(Lorg/mockito/invocation/InvocationOnMock;)Ljava/lang/Void;
       5: areturn
}
