Compiled from "TestCleanerChore.java"
class org.apache.hadoop.hbase.master.cleaner.TestCleanerChore$AllValidPaths extends org.apache.hadoop.hbase.master.cleaner.CleanerChore<org.apache.hadoop.hbase.master.cleaner.BaseHFileCleanerDelegate> {
  public org.apache.hadoop.hbase.master.cleaner.TestCleanerChore$AllValidPaths(java.lang.String, org.apache.hadoop.hbase.Stoppable, org.apache.hadoop.conf.Configuration, org.apache.hadoop.fs.FileSystem, org.apache.hadoop.fs.Path, java.lang.String);
    Code:
       0: aload_0
       1: aload_1
       2: ldc           #2                  // int 2147483647
       4: aload_2
       5: aload_3
       6: aload         4
       8: aload         5
      10: aload         6
      12: invokespecial #3                  // Method org/apache/hadoop/hbase/master/cleaner/CleanerChore."<init>":(Ljava/lang/String;ILorg/apache/hadoop/hbase/Stoppable;Lorg/apache/hadoop/conf/Configuration;Lorg/apache/hadoop/fs/FileSystem;Lorg/apache/hadoop/fs/Path;Ljava/lang/String;)V
      15: return

  protected boolean validate(org.apache.hadoop.fs.Path);
    Code:
       0: iconst_1
       1: ireturn
}
