Compiled from "TestTablesWithQuotas.java"
public class org.apache.hadoop.hbase.quotas.TestTablesWithQuotas {
  public static final org.apache.hadoop.hbase.HBaseClassTestRule CLASS_RULE;

  public org.apache.hadoop.hbase.quotas.TestTablesWithQuotas();
    Code:
       0: aload_0
       1: invokespecial #1                  // Method java/lang/Object."<init>":()V
       4: return

  public void setup() throws java.lang.Exception;
    Code:
       0: aload_0
       1: ldc           #2                  // class org/apache/hadoop/hbase/client/Connection
       3: invokestatic  #3                  // Method org/mockito/Mockito.mock:(Ljava/lang/Class;)Ljava/lang/Object;
       6: checkcast     #2                  // class org/apache/hadoop/hbase/client/Connection
       9: putfield      #4                  // Field conn:Lorg/apache/hadoop/hbase/client/Connection;
      12: aload_0
      13: invokestatic  #5                  // Method org/apache/hadoop/hbase/HBaseConfiguration.create:()Lorg/apache/hadoop/conf/Configuration;
      16: putfield      #6                  // Field conf:Lorg/apache/hadoop/conf/Configuration;
      19: return

  public void testImmutableGetters();
    Code:
       0: new           #7                  // class java/util/HashSet
       3: dup
       4: invokespecial #8                  // Method java/util/HashSet."<init>":()V
       7: astore_1
       8: new           #7                  // class java/util/HashSet
      11: dup
      12: invokespecial #8                  // Method java/util/HashSet."<init>":()V
      15: astore_2
      16: new           #9                  // class org/apache/hadoop/hbase/quotas/QuotaObserverChore$TablesWithQuotas
      19: dup
      20: aload_0
      21: getfield      #4                  // Field conn:Lorg/apache/hadoop/hbase/client/Connection;
      24: aload_0
      25: getfield      #6                  // Field conf:Lorg/apache/hadoop/conf/Configuration;
      28: invokespecial #10                 // Method org/apache/hadoop/hbase/quotas/QuotaObserverChore$TablesWithQuotas."<init>":(Lorg/apache/hadoop/hbase/client/Connection;Lorg/apache/hadoop/conf/Configuration;)V
      31: astore_3
      32: iconst_0
      33: istore        4
      35: iload         4
      37: iconst_5
      38: if_icmpge     87
      41: new           #11                 // class java/lang/StringBuilder
      44: dup
      45: invokespecial #12                 // Method java/lang/StringBuilder."<init>":()V
      48: ldc           #13                 // String tn
      50: invokevirtual #14                 // Method java/lang/StringBuilder.append:(Ljava/lang/String;)Ljava/lang/StringBuilder;
      53: iload         4
      55: invokevirtual #15                 // Method java/lang/StringBuilder.append:(I)Ljava/lang/StringBuilder;
      58: invokevirtual #16                 // Method java/lang/StringBuilder.toString:()Ljava/lang/String;
      61: invokestatic  #17                 // Method org/apache/hadoop/hbase/TableName.valueOf:(Ljava/lang/String;)Lorg/apache/hadoop/hbase/TableName;
      64: astore        5
      66: aload_1
      67: aload         5
      69: invokeinterface #18,  2           // InterfaceMethod java/util/Set.add:(Ljava/lang/Object;)Z
      74: pop
      75: aload_3
      76: aload         5
      78: invokevirtual #19                 // Method org/apache/hadoop/hbase/quotas/QuotaObserverChore$TablesWithQuotas.addTableQuotaTable:(Lorg/apache/hadoop/hbase/TableName;)V
      81: iinc          4, 1
      84: goto          35
      87: iconst_0
      88: istore        4
      90: iload         4
      92: iconst_3
      93: if_icmpge     142
      96: new           #11                 // class java/lang/StringBuilder
      99: dup
     100: invokespecial #12                 // Method java/lang/StringBuilder."<init>":()V
     103: ldc           #20                 // String tn_ns
     105: invokevirtual #14                 // Method java/lang/StringBuilder.append:(Ljava/lang/String;)Ljava/lang/StringBuilder;
     108: iload         4
     110: invokevirtual #15                 // Method java/lang/StringBuilder.append:(I)Ljava/lang/StringBuilder;
     113: invokevirtual #16                 // Method java/lang/StringBuilder.toString:()Ljava/lang/String;
     116: invokestatic  #17                 // Method org/apache/hadoop/hbase/TableName.valueOf:(Ljava/lang/String;)Lorg/apache/hadoop/hbase/TableName;
     119: astore        5
     121: aload_2
     122: aload         5
     124: invokeinterface #18,  2           // InterfaceMethod java/util/Set.add:(Ljava/lang/Object;)Z
     129: pop
     130: aload_3
     131: aload         5
     133: invokevirtual #21                 // Method org/apache/hadoop/hbase/quotas/QuotaObserverChore$TablesWithQuotas.addNamespaceQuotaTable:(Lorg/apache/hadoop/hbase/TableName;)V
     136: iinc          4, 1
     139: goto          90
     142: aload_3
     143: invokevirtual #22                 // Method org/apache/hadoop/hbase/quotas/QuotaObserverChore$TablesWithQuotas.getTableQuotaTables:()Ljava/util/Set;
     146: astore        4
     148: aload_3
     149: invokevirtual #23                 // Method org/apache/hadoop/hbase/quotas/QuotaObserverChore$TablesWithQuotas.getNamespaceQuotaTables:()Ljava/util/Set;
     152: astore        5
     154: aload_1
     155: aload         4
     157: invokestatic  #24                 // Method org/junit/Assert.assertEquals:(Ljava/lang/Object;Ljava/lang/Object;)V
     160: aload_2
     161: aload         5
     163: invokestatic  #24                 // Method org/junit/Assert.assertEquals:(Ljava/lang/Object;Ljava/lang/Object;)V
     166: aload         4
     168: aconst_null
     169: invokeinterface #18,  2           // InterfaceMethod java/util/Set.add:(Ljava/lang/Object;)Z
     174: pop
     175: ldc           #25                 // String Should not be able to add an element
     177: invokestatic  #26                 // Method org/junit/Assert.fail:(Ljava/lang/String;)V
     180: goto          185
     183: astore        6
     185: aload         5
     187: aconst_null
     188: invokeinterface #18,  2           // InterfaceMethod java/util/Set.add:(Ljava/lang/Object;)Z
     193: pop
     194: ldc           #25                 // String Should not be able to add an element
     196: invokestatic  #26                 // Method org/junit/Assert.fail:(Ljava/lang/String;)V
     199: goto          204
     202: astore        6
     204: return
    Exception table:
       from    to  target type
         166   180   183   Class java/lang/UnsupportedOperationException
         185   199   202   Class java/lang/UnsupportedOperationException

  public void testInsufficientlyReportedTableFiltering() throws java.lang.Exception;
    Code:
       0: new           #28                 // class java/util/HashMap
       3: dup
       4: invokespecial #29                 // Method java/util/HashMap."<init>":()V
       7: astore_1
       8: new           #28                 // class java/util/HashMap
      11: dup
      12: invokespecial #29                 // Method java/util/HashMap."<init>":()V
      15: astore_2
      16: invokestatic  #5                  // Method org/apache/hadoop/hbase/HBaseConfiguration.create:()Lorg/apache/hadoop/conf/Configuration;
      19: astore_3
      20: aload_3
      21: ldc           #31                 // String hbase.master.quotas.observer.report.percent
      23: ldc2_w        #32                 // double 0.95d
      26: invokevirtual #34                 // Method org/apache/hadoop/conf/Configuration.setDouble:(Ljava/lang/String;D)V
      29: ldc           #35                 // String tn1
      31: invokestatic  #17                 // Method org/apache/hadoop/hbase/TableName.valueOf:(Ljava/lang/String;)Lorg/apache/hadoop/hbase/TableName;
      34: astore        4
      36: ldc           #36                 // String tn2
      38: invokestatic  #17                 // Method org/apache/hadoop/hbase/TableName.valueOf:(Ljava/lang/String;)Lorg/apache/hadoop/hbase/TableName;
      41: astore        5
      43: ldc           #37                 // String ns1
      45: ldc           #36                 // String tn2
      47: invokestatic  #38                 // Method org/apache/hadoop/hbase/TableName.valueOf:(Ljava/lang/String;Ljava/lang/String;)Lorg/apache/hadoop/hbase/TableName;
      50: astore        6
      52: ldc           #37                 // String ns1
      54: ldc           #36                 // String tn2
      56: invokestatic  #38                 // Method org/apache/hadoop/hbase/TableName.valueOf:(Ljava/lang/String;Ljava/lang/String;)Lorg/apache/hadoop/hbase/TableName;
      59: astore        7
      61: new           #39                 // class org/apache/hadoop/hbase/quotas/TestTablesWithQuotas$1
      64: dup
      65: aload_0
      66: aload_0
      67: getfield      #4                  // Field conn:Lorg/apache/hadoop/hbase/client/Connection;
      70: aload_3
      71: aload_3
      72: aload_2
      73: aload_1
      74: invokespecial #40                 // Method org/apache/hadoop/hbase/quotas/TestTablesWithQuotas$1."<init>":(Lorg/apache/hadoop/hbase/quotas/TestTablesWithQuotas;Lorg/apache/hadoop/hbase/client/Connection;Lorg/apache/hadoop/conf/Configuration;Lorg/apache/hadoop/conf/Configuration;Ljava/util/Map;Ljava/util/Map;)V
      77: astore        8
      79: aload         8
      81: aload         4
      83: invokevirtual #19                 // Method org/apache/hadoop/hbase/quotas/QuotaObserverChore$TablesWithQuotas.addTableQuotaTable:(Lorg/apache/hadoop/hbase/TableName;)V
      86: aload         8
      88: aload         5
      90: invokevirtual #19                 // Method org/apache/hadoop/hbase/quotas/QuotaObserverChore$TablesWithQuotas.addTableQuotaTable:(Lorg/apache/hadoop/hbase/TableName;)V
      93: aload         8
      95: aload         6
      97: invokevirtual #21                 // Method org/apache/hadoop/hbase/quotas/QuotaObserverChore$TablesWithQuotas.addNamespaceQuotaTable:(Lorg/apache/hadoop/hbase/TableName;)V
     100: aload         8
     102: aload         7
     104: invokevirtual #21                 // Method org/apache/hadoop/hbase/quotas/QuotaObserverChore$TablesWithQuotas.addNamespaceQuotaTable:(Lorg/apache/hadoop/hbase/TableName;)V
     107: aload_1
     108: aload         4
     110: iconst_5
     111: invokestatic  #41                 // Method java/lang/Integer.valueOf:(I)Ljava/lang/Integer;
     114: invokeinterface #42,  3           // InterfaceMethod java/util/Map.put:(Ljava/lang/Object;Ljava/lang/Object;)Ljava/lang/Object;
     119: pop
     120: aload_2
     121: aload         4
     123: bipush        10
     125: invokestatic  #41                 // Method java/lang/Integer.valueOf:(I)Ljava/lang/Integer;
     128: invokeinterface #42,  3           // InterfaceMethod java/util/Map.put:(Ljava/lang/Object;Ljava/lang/Object;)Ljava/lang/Object;
     133: pop
     134: aload_1
     135: aload         5
     137: bipush        19
     139: invokestatic  #41                 // Method java/lang/Integer.valueOf:(I)Ljava/lang/Integer;
     142: invokeinterface #42,  3           // InterfaceMethod java/util/Map.put:(Ljava/lang/Object;Ljava/lang/Object;)Ljava/lang/Object;
     147: pop
     148: aload_2
     149: aload         5
     151: bipush        20
     153: invokestatic  #41                 // Method java/lang/Integer.valueOf:(I)Ljava/lang/Integer;
     156: invokeinterface #42,  3           // InterfaceMethod java/util/Map.put:(Ljava/lang/Object;Ljava/lang/Object;)Ljava/lang/Object;
     161: pop
     162: aload_1
     163: aload         6
     165: bipush        9
     167: invokestatic  #41                 // Method java/lang/Integer.valueOf:(I)Ljava/lang/Integer;
     170: invokeinterface #42,  3           // InterfaceMethod java/util/Map.put:(Ljava/lang/Object;Ljava/lang/Object;)Ljava/lang/Object;
     175: pop
     176: aload_2
     177: aload         6
     179: bipush        10
     181: invokestatic  #41                 // Method java/lang/Integer.valueOf:(I)Ljava/lang/Integer;
     184: invokeinterface #42,  3           // InterfaceMethod java/util/Map.put:(Ljava/lang/Object;Ljava/lang/Object;)Ljava/lang/Object;
     189: pop
     190: aload_1
     191: aload         7
     193: bipush        98
     195: invokestatic  #41                 // Method java/lang/Integer.valueOf:(I)Ljava/lang/Integer;
     198: invokeinterface #42,  3           // InterfaceMethod java/util/Map.put:(Ljava/lang/Object;Ljava/lang/Object;)Ljava/lang/Object;
     203: pop
     204: aload_2
     205: aload         7
     207: bipush        100
     209: invokestatic  #41                 // Method java/lang/Integer.valueOf:(I)Ljava/lang/Integer;
     212: invokeinterface #42,  3           // InterfaceMethod java/util/Map.put:(Ljava/lang/Object;Ljava/lang/Object;)Ljava/lang/Object;
     217: pop
     218: aload         8
     220: aconst_null
     221: invokevirtual #43                 // Method org/apache/hadoop/hbase/quotas/QuotaObserverChore$TablesWithQuotas.filterInsufficientlyReportedTables:(Lorg/apache/hadoop/hbase/quotas/QuotaSnapshotStore;)Ljava/util/Set;
     224: pop
     225: aload         8
     227: invokevirtual #22                 // Method org/apache/hadoop/hbase/quotas/QuotaObserverChore$TablesWithQuotas.getTableQuotaTables:()Ljava/util/Set;
     230: astore        9
     232: aload         5
     234: invokestatic  #44                 // Method java/util/Collections.singleton:(Ljava/lang/Object;)Ljava/util/Set;
     237: aload         9
     239: invokestatic  #24                 // Method org/junit/Assert.assertEquals:(Ljava/lang/Object;Ljava/lang/Object;)V
     242: aload         8
     244: invokevirtual #23                 // Method org/apache/hadoop/hbase/quotas/QuotaObserverChore$TablesWithQuotas.getNamespaceQuotaTables:()Ljava/util/Set;
     247: astore        10
     249: aload         7
     251: invokestatic  #44                 // Method java/util/Collections.singleton:(Ljava/lang/Object;)Ljava/util/Set;
     254: aload         10
     256: invokestatic  #24                 // Method org/junit/Assert.assertEquals:(Ljava/lang/Object;Ljava/lang/Object;)V
     259: return

  public void testGetTablesByNamespace();
    Code:
       0: new           #9                  // class org/apache/hadoop/hbase/quotas/QuotaObserverChore$TablesWithQuotas
       3: dup
       4: aload_0
       5: getfield      #4                  // Field conn:Lorg/apache/hadoop/hbase/client/Connection;
       8: aload_0
       9: getfield      #6                  // Field conf:Lorg/apache/hadoop/conf/Configuration;
      12: invokespecial #10                 // Method org/apache/hadoop/hbase/quotas/QuotaObserverChore$TablesWithQuotas."<init>":(Lorg/apache/hadoop/hbase/client/Connection;Lorg/apache/hadoop/conf/Configuration;)V
      15: astore_1
      16: aload_1
      17: ldc           #45                 // String ignored1
      19: invokestatic  #17                 // Method org/apache/hadoop/hbase/TableName.valueOf:(Ljava/lang/String;)Lorg/apache/hadoop/hbase/TableName;
      22: invokevirtual #19                 // Method org/apache/hadoop/hbase/quotas/QuotaObserverChore$TablesWithQuotas.addTableQuotaTable:(Lorg/apache/hadoop/hbase/TableName;)V
      25: aload_1
      26: ldc           #46                 // String ignored2
      28: invokestatic  #17                 // Method org/apache/hadoop/hbase/TableName.valueOf:(Ljava/lang/String;)Lorg/apache/hadoop/hbase/TableName;
      31: invokevirtual #19                 // Method org/apache/hadoop/hbase/quotas/QuotaObserverChore$TablesWithQuotas.addTableQuotaTable:(Lorg/apache/hadoop/hbase/TableName;)V
      34: aload_1
      35: ldc           #37                 // String ns1
      37: ldc           #47                 // String t1
      39: invokestatic  #38                 // Method org/apache/hadoop/hbase/TableName.valueOf:(Ljava/lang/String;Ljava/lang/String;)Lorg/apache/hadoop/hbase/TableName;
      42: invokevirtual #21                 // Method org/apache/hadoop/hbase/quotas/QuotaObserverChore$TablesWithQuotas.addNamespaceQuotaTable:(Lorg/apache/hadoop/hbase/TableName;)V
      45: aload_1
      46: ldc           #37                 // String ns1
      48: ldc           #48                 // String t2
      50: invokestatic  #38                 // Method org/apache/hadoop/hbase/TableName.valueOf:(Ljava/lang/String;Ljava/lang/String;)Lorg/apache/hadoop/hbase/TableName;
      53: invokevirtual #21                 // Method org/apache/hadoop/hbase/quotas/QuotaObserverChore$TablesWithQuotas.addNamespaceQuotaTable:(Lorg/apache/hadoop/hbase/TableName;)V
      56: aload_1
      57: ldc           #37                 // String ns1
      59: ldc           #49                 // String t3
      61: invokestatic  #38                 // Method org/apache/hadoop/hbase/TableName.valueOf:(Ljava/lang/String;Ljava/lang/String;)Lorg/apache/hadoop/hbase/TableName;
      64: invokevirtual #21                 // Method org/apache/hadoop/hbase/quotas/QuotaObserverChore$TablesWithQuotas.addNamespaceQuotaTable:(Lorg/apache/hadoop/hbase/TableName;)V
      67: aload_1
      68: ldc           #50                 // String ns2
      70: ldc           #47                 // String t1
      72: invokestatic  #38                 // Method org/apache/hadoop/hbase/TableName.valueOf:(Ljava/lang/String;Ljava/lang/String;)Lorg/apache/hadoop/hbase/TableName;
      75: invokevirtual #21                 // Method org/apache/hadoop/hbase/quotas/QuotaObserverChore$TablesWithQuotas.addNamespaceQuotaTable:(Lorg/apache/hadoop/hbase/TableName;)V
      78: aload_1
      79: ldc           #50                 // String ns2
      81: ldc           #48                 // String t2
      83: invokestatic  #38                 // Method org/apache/hadoop/hbase/TableName.valueOf:(Ljava/lang/String;Ljava/lang/String;)Lorg/apache/hadoop/hbase/TableName;
      86: invokevirtual #21                 // Method org/apache/hadoop/hbase/quotas/QuotaObserverChore$TablesWithQuotas.addNamespaceQuotaTable:(Lorg/apache/hadoop/hbase/TableName;)V
      89: aload_1
      90: invokevirtual #51                 // Method org/apache/hadoop/hbase/quotas/QuotaObserverChore$TablesWithQuotas.getTablesByNamespace:()Lorg/apache/hbase/thirdparty/com/google/common/collect/Multimap;
      93: astore_2
      94: aload_2
      95: ldc           #37                 // String ns1
      97: invokeinterface #52,  2           // InterfaceMethod org/apache/hbase/thirdparty/com/google/common/collect/Multimap.get:(Ljava/lang/Object;)Ljava/util/Collection;
     102: astore_3
     103: ldc2_w        #53                 // long 3l
     106: aload_3
     107: invokeinterface #55,  1           // InterfaceMethod java/util/Collection.size:()I
     112: i2l
     113: invokestatic  #56                 // Method org/junit/Assert.assertEquals:(JJ)V
     116: new           #11                 // class java/lang/StringBuilder
     119: dup
     120: invokespecial #12                 // Method java/lang/StringBuilder."<init>":()V
     123: ldc           #57                 // String Unexpected results for ns1:
     125: invokevirtual #14                 // Method java/lang/StringBuilder.append:(Ljava/lang/String;)Ljava/lang/StringBuilder;
     128: aload_3
     129: invokevirtual #58                 // Method java/lang/StringBuilder.append:(Ljava/lang/Object;)Ljava/lang/StringBuilder;
     132: invokevirtual #16                 // Method java/lang/StringBuilder.toString:()Ljava/lang/String;
     135: aload_3
     136: iconst_3
     137: anewarray     #59                 // class org/apache/hadoop/hbase/TableName
     140: dup
     141: iconst_0
     142: ldc           #37                 // String ns1
     144: ldc           #47                 // String t1
     146: invokestatic  #38                 // Method org/apache/hadoop/hbase/TableName.valueOf:(Ljava/lang/String;Ljava/lang/String;)Lorg/apache/hadoop/hbase/TableName;
     149: aastore
     150: dup
     151: iconst_1
     152: ldc           #37                 // String ns1
     154: ldc           #48                 // String t2
     156: invokestatic  #38                 // Method org/apache/hadoop/hbase/TableName.valueOf:(Ljava/lang/String;Ljava/lang/String;)Lorg/apache/hadoop/hbase/TableName;
     159: aastore
     160: dup
     161: iconst_2
     162: ldc           #37                 // String ns1
     164: ldc           #49                 // String t3
     166: invokestatic  #38                 // Method org/apache/hadoop/hbase/TableName.valueOf:(Ljava/lang/String;Ljava/lang/String;)Lorg/apache/hadoop/hbase/TableName;
     169: aastore
     170: invokestatic  #60                 // Method java/util/Arrays.asList:([Ljava/lang/Object;)Ljava/util/List;
     173: invokeinterface #61,  2           // InterfaceMethod java/util/Collection.containsAll:(Ljava/util/Collection;)Z
     178: invokestatic  #62                 // Method org/junit/Assert.assertTrue:(Ljava/lang/String;Z)V
     181: aload_2
     182: ldc           #50                 // String ns2
     184: invokeinterface #52,  2           // InterfaceMethod org/apache/hbase/thirdparty/com/google/common/collect/Multimap.get:(Ljava/lang/Object;)Ljava/util/Collection;
     189: astore_3
     190: ldc2_w        #63                 // long 2l
     193: aload_3
     194: invokeinterface #55,  1           // InterfaceMethod java/util/Collection.size:()I
     199: i2l
     200: invokestatic  #56                 // Method org/junit/Assert.assertEquals:(JJ)V
     203: new           #11                 // class java/lang/StringBuilder
     206: dup
     207: invokespecial #12                 // Method java/lang/StringBuilder."<init>":()V
     210: ldc           #65                 // String Unexpected results for ns2:
     212: invokevirtual #14                 // Method java/lang/StringBuilder.append:(Ljava/lang/String;)Ljava/lang/StringBuilder;
     215: aload_3
     216: invokevirtual #58                 // Method java/lang/StringBuilder.append:(Ljava/lang/Object;)Ljava/lang/StringBuilder;
     219: invokevirtual #16                 // Method java/lang/StringBuilder.toString:()Ljava/lang/String;
     222: aload_3
     223: iconst_2
     224: anewarray     #59                 // class org/apache/hadoop/hbase/TableName
     227: dup
     228: iconst_0
     229: ldc           #50                 // String ns2
     231: ldc           #47                 // String t1
     233: invokestatic  #38                 // Method org/apache/hadoop/hbase/TableName.valueOf:(Ljava/lang/String;Ljava/lang/String;)Lorg/apache/hadoop/hbase/TableName;
     236: aastore
     237: dup
     238: iconst_1
     239: ldc           #50                 // String ns2
     241: ldc           #48                 // String t2
     243: invokestatic  #38                 // Method org/apache/hadoop/hbase/TableName.valueOf:(Ljava/lang/String;Ljava/lang/String;)Lorg/apache/hadoop/hbase/TableName;
     246: aastore
     247: invokestatic  #60                 // Method java/util/Arrays.asList:([Ljava/lang/Object;)Ljava/util/List;
     250: invokeinterface #61,  2           // InterfaceMethod java/util/Collection.containsAll:(Ljava/util/Collection;)Z
     255: invokestatic  #62                 // Method org/junit/Assert.assertTrue:(Ljava/lang/String;Z)V
     258: return

  public void testFilteringMissingTables() throws java.lang.Exception;
    Code:
       0: ldc           #66                 // String doesNotExist
       2: invokestatic  #17                 // Method org/apache/hadoop/hbase/TableName.valueOf:(Ljava/lang/String;)Lorg/apache/hadoop/hbase/TableName;
       5: astore_1
       6: ldc           #67                 // class org/apache/hadoop/hbase/client/Admin
       8: invokestatic  #3                  // Method org/mockito/Mockito.mock:(Ljava/lang/Class;)Ljava/lang/Object;
      11: checkcast     #67                 // class org/apache/hadoop/hbase/client/Admin
      14: astore_2
      15: aload_0
      16: getfield      #4                  // Field conn:Lorg/apache/hadoop/hbase/client/Connection;
      19: invokeinterface #68,  1           // InterfaceMethod org/apache/hadoop/hbase/client/Connection.getAdmin:()Lorg/apache/hadoop/hbase/client/Admin;
      24: invokestatic  #69                 // Method org/mockito/Mockito.when:(Ljava/lang/Object;)Lorg/mockito/stubbing/OngoingStubbing;
      27: aload_2
      28: invokeinterface #70,  2           // InterfaceMethod org/mockito/stubbing/OngoingStubbing.thenReturn:(Ljava/lang/Object;)Lorg/mockito/stubbing/OngoingStubbing;
      33: pop
      34: aload_2
      35: aload_1
      36: invokeinterface #71,  2           // InterfaceMethod org/apache/hadoop/hbase/client/Admin.getRegions:(Lorg/apache/hadoop/hbase/TableName;)Ljava/util/List;
      41: invokestatic  #69                 // Method org/mockito/Mockito.when:(Ljava/lang/Object;)Lorg/mockito/stubbing/OngoingStubbing;
      44: aconst_null
      45: invokeinterface #70,  2           // InterfaceMethod org/mockito/stubbing/OngoingStubbing.thenReturn:(Ljava/lang/Object;)Lorg/mockito/stubbing/OngoingStubbing;
      50: pop
      51: ldc           #30                 // class org/apache/hadoop/hbase/quotas/QuotaObserverChore
      53: invokestatic  #3                  // Method org/mockito/Mockito.mock:(Ljava/lang/Class;)Ljava/lang/Object;
      56: checkcast     #30                 // class org/apache/hadoop/hbase/quotas/QuotaObserverChore
      59: astore_3
      60: new           #28                 // class java/util/HashMap
      63: dup
      64: invokespecial #29                 // Method java/util/HashMap."<init>":()V
      67: astore        4
      69: new           #72                 // class org/apache/hadoop/hbase/quotas/TableQuotaSnapshotStore
      72: dup
      73: aload_0
      74: getfield      #4                  // Field conn:Lorg/apache/hadoop/hbase/client/Connection;
      77: aload_3
      78: aload         4
      80: invokespecial #73                 // Method org/apache/hadoop/hbase/quotas/TableQuotaSnapshotStore."<init>":(Lorg/apache/hadoop/hbase/client/Connection;Lorg/apache/hadoop/hbase/quotas/QuotaObserverChore;Ljava/util/Map;)V
      83: astore        5
      85: new           #74                 // class org/apache/hadoop/hbase/quotas/TestTablesWithQuotas$2
      88: dup
      89: aload_0
      90: aload_0
      91: getfield      #4                  // Field conn:Lorg/apache/hadoop/hbase/client/Connection;
      94: aload_0
      95: getfield      #6                  // Field conf:Lorg/apache/hadoop/conf/Configuration;
      98: invokespecial #75                 // Method org/apache/hadoop/hbase/quotas/TestTablesWithQuotas$2."<init>":(Lorg/apache/hadoop/hbase/quotas/TestTablesWithQuotas;Lorg/apache/hadoop/hbase/client/Connection;Lorg/apache/hadoop/conf/Configuration;)V
     101: astore        6
     103: aload         6
     105: aload_1
     106: invokevirtual #19                 // Method org/apache/hadoop/hbase/quotas/QuotaObserverChore$TablesWithQuotas.addTableQuotaTable:(Lorg/apache/hadoop/hbase/TableName;)V
     109: aload         6
     111: aload         5
     113: invokevirtual #43                 // Method org/apache/hadoop/hbase/quotas/QuotaObserverChore$TablesWithQuotas.filterInsufficientlyReportedTables:(Lorg/apache/hadoop/hbase/quotas/QuotaSnapshotStore;)Ljava/util/Set;
     116: pop
     117: aload         6
     119: invokevirtual #22                 // Method org/apache/hadoop/hbase/quotas/QuotaObserverChore$TablesWithQuotas.getTableQuotaTables:()Ljava/util/Set;
     122: astore        7
     124: new           #11                 // class java/lang/StringBuilder
     127: dup
     128: invokespecial #12                 // Method java/lang/StringBuilder."<init>":()V
     131: ldc           #76                 // String Expected to find no tables, but found
     133: invokevirtual #14                 // Method java/lang/StringBuilder.append:(Ljava/lang/String;)Ljava/lang/StringBuilder;
     136: aload         7
     138: invokevirtual #58                 // Method java/lang/StringBuilder.append:(Ljava/lang/Object;)Ljava/lang/StringBuilder;
     141: invokevirtual #16                 // Method java/lang/StringBuilder.toString:()Ljava/lang/String;
     144: aload         7
     146: invokeinterface #77,  1           // InterfaceMethod java/util/Set.isEmpty:()Z
     151: invokestatic  #62                 // Method org/junit/Assert.assertTrue:(Ljava/lang/String;Z)V
     154: return

  static {};
    Code:
       0: ldc           #78                 // class org/apache/hadoop/hbase/quotas/TestTablesWithQuotas
       2: invokestatic  #79                 // Method org/apache/hadoop/hbase/HBaseClassTestRule.forClass:(Ljava/lang/Class;)Lorg/apache/hadoop/hbase/HBaseClassTestRule;
       5: putstatic     #80                 // Field CLASS_RULE:Lorg/apache/hadoop/hbase/HBaseClassTestRule;
       8: return
}
