Compiled from "TestMasterObserverToModifyTableSchema.java"
public class org.apache.hadoop.hbase.coprocessor.TestMasterObserverToModifyTableSchema {
  public static final org.apache.hadoop.hbase.HBaseClassTestRule CLASS_RULE;

  public org.junit.rules.TestName name;

  public org.apache.hadoop.hbase.coprocessor.TestMasterObserverToModifyTableSchema();
    Code:
       0: aload_0
       1: invokespecial #1                  // Method java/lang/Object."<init>":()V
       4: aload_0
       5: new           #2                  // class org/junit/rules/TestName
       8: dup
       9: invokespecial #3                  // Method org/junit/rules/TestName."<init>":()V
      12: putfield      #4                  // Field name:Lorg/junit/rules/TestName;
      15: return

  public static void setupBeforeClass() throws java.lang.Exception;
    Code:
       0: getstatic     #5                  // Field UTIL:Lorg/apache/hadoop/hbase/HBaseTestingUtility;
       3: invokevirtual #6                  // Method org/apache/hadoop/hbase/HBaseTestingUtility.getConfiguration:()Lorg/apache/hadoop/conf/Configuration;
       6: astore_0
       7: aload_0
       8: ldc           #8                  // String hbase.coprocessor.master.classes
      10: ldc           #9                  // class org/apache/hadoop/hbase/coprocessor/TestMasterObserverToModifyTableSchema$OnlyOneVersionAllowedMasterObserver
      12: invokevirtual #10                 // Method java/lang/Class.getName:()Ljava/lang/String;
      15: invokevirtual #11                 // Method org/apache/hadoop/conf/Configuration.set:(Ljava/lang/String;Ljava/lang/String;)V
      18: getstatic     #5                  // Field UTIL:Lorg/apache/hadoop/hbase/HBaseTestingUtility;
      21: iconst_1
      22: invokevirtual #12                 // Method org/apache/hadoop/hbase/HBaseTestingUtility.startMiniCluster:(I)Lorg/apache/hadoop/hbase/MiniHBaseCluster;
      25: pop
      26: return

  public static void tearDownAfterClass() throws java.lang.Exception;
    Code:
       0: getstatic     #5                  // Field UTIL:Lorg/apache/hadoop/hbase/HBaseTestingUtility;
       3: invokevirtual #13                 // Method org/apache/hadoop/hbase/HBaseTestingUtility.shutdownMiniCluster:()V
       6: return

  public void testMasterObserverToModifyTableSchema() throws java.io.IOException;
    Code:
       0: getstatic     #14                 // Field TABLENAME:Lorg/apache/hadoop/hbase/TableName;
       3: invokestatic  #15                 // Method org/apache/hadoop/hbase/client/TableDescriptorBuilder.newBuilder:(Lorg/apache/hadoop/hbase/TableName;)Lorg/apache/hadoop/hbase/client/TableDescriptorBuilder;
       6: astore_1
       7: iconst_1
       8: istore_2
       9: iload_2
      10: iconst_3
      11: if_icmpgt     57
      14: aload_1
      15: new           #16                 // class java/lang/StringBuilder
      18: dup
      19: invokespecial #17                 // Method java/lang/StringBuilder."<init>":()V
      22: ldc           #18                 // String cf
      24: invokevirtual #19                 // Method java/lang/StringBuilder.append:(Ljava/lang/String;)Ljava/lang/StringBuilder;
      27: iload_2
      28: invokevirtual #20                 // Method java/lang/StringBuilder.append:(I)Ljava/lang/StringBuilder;
      31: invokevirtual #21                 // Method java/lang/StringBuilder.toString:()Ljava/lang/String;
      34: invokestatic  #22                 // Method org/apache/hadoop/hbase/util/Bytes.toBytes:(Ljava/lang/String;)[B
      37: invokestatic  #23                 // Method org/apache/hadoop/hbase/client/ColumnFamilyDescriptorBuilder.newBuilder:([B)Lorg/apache/hadoop/hbase/client/ColumnFamilyDescriptorBuilder;
      40: iload_2
      41: invokevirtual #24                 // Method org/apache/hadoop/hbase/client/ColumnFamilyDescriptorBuilder.setMaxVersions:(I)Lorg/apache/hadoop/hbase/client/ColumnFamilyDescriptorBuilder;
      44: invokevirtual #25                 // Method org/apache/hadoop/hbase/client/ColumnFamilyDescriptorBuilder.build:()Lorg/apache/hadoop/hbase/client/ColumnFamilyDescriptor;
      47: invokevirtual #26                 // Method org/apache/hadoop/hbase/client/TableDescriptorBuilder.setColumnFamily:(Lorg/apache/hadoop/hbase/client/ColumnFamilyDescriptor;)Lorg/apache/hadoop/hbase/client/TableDescriptorBuilder;
      50: pop
      51: iinc          2, 1
      54: goto          9
      57: getstatic     #5                  // Field UTIL:Lorg/apache/hadoop/hbase/HBaseTestingUtility;
      60: invokevirtual #27                 // Method org/apache/hadoop/hbase/HBaseTestingUtility.getAdmin:()Lorg/apache/hadoop/hbase/client/Admin;
      63: astore_2
      64: aconst_null
      65: astore_3
      66: aload_2
      67: aload_1
      68: invokevirtual #28                 // Method org/apache/hadoop/hbase/client/TableDescriptorBuilder.build:()Lorg/apache/hadoop/hbase/client/TableDescriptor;
      71: invokeinterface #29,  2           // InterfaceMethod org/apache/hadoop/hbase/client/Admin.createTable:(Lorg/apache/hadoop/hbase/client/TableDescriptor;)V
      76: aload_0
      77: aload_2
      78: getstatic     #14                 // Field TABLENAME:Lorg/apache/hadoop/hbase/TableName;
      81: invokeinterface #30,  2           // InterfaceMethod org/apache/hadoop/hbase/client/Admin.getDescriptor:(Lorg/apache/hadoop/hbase/TableName;)Lorg/apache/hadoop/hbase/client/TableDescriptor;
      86: invokespecial #31                 // Method assertOneVersion:(Lorg/apache/hadoop/hbase/client/TableDescriptor;)V
      89: aload_1
      90: ldc           #32                 // String cf1
      92: invokestatic  #22                 // Method org/apache/hadoop/hbase/util/Bytes.toBytes:(Ljava/lang/String;)[B
      95: invokestatic  #23                 // Method org/apache/hadoop/hbase/client/ColumnFamilyDescriptorBuilder.newBuilder:([B)Lorg/apache/hadoop/hbase/client/ColumnFamilyDescriptorBuilder;
      98: ldc           #34                 // int 2147483647
     100: invokevirtual #24                 // Method org/apache/hadoop/hbase/client/ColumnFamilyDescriptorBuilder.setMaxVersions:(I)Lorg/apache/hadoop/hbase/client/ColumnFamilyDescriptorBuilder;
     103: invokevirtual #25                 // Method org/apache/hadoop/hbase/client/ColumnFamilyDescriptorBuilder.build:()Lorg/apache/hadoop/hbase/client/ColumnFamilyDescriptor;
     106: invokevirtual #35                 // Method org/apache/hadoop/hbase/client/TableDescriptorBuilder.modifyColumnFamily:(Lorg/apache/hadoop/hbase/client/ColumnFamilyDescriptor;)Lorg/apache/hadoop/hbase/client/TableDescriptorBuilder;
     109: pop
     110: aload_2
     111: aload_1
     112: invokevirtual #28                 // Method org/apache/hadoop/hbase/client/TableDescriptorBuilder.build:()Lorg/apache/hadoop/hbase/client/TableDescriptor;
     115: invokeinterface #36,  2           // InterfaceMethod org/apache/hadoop/hbase/client/Admin.modifyTable:(Lorg/apache/hadoop/hbase/client/TableDescriptor;)V
     120: aload_0
     121: aload_2
     122: getstatic     #14                 // Field TABLENAME:Lorg/apache/hadoop/hbase/TableName;
     125: invokeinterface #30,  2           // InterfaceMethod org/apache/hadoop/hbase/client/Admin.getDescriptor:(Lorg/apache/hadoop/hbase/TableName;)Lorg/apache/hadoop/hbase/client/TableDescriptor;
     130: invokespecial #31                 // Method assertOneVersion:(Lorg/apache/hadoop/hbase/client/TableDescriptor;)V
     133: aload_2
     134: ifnull        217
     137: aload_3
     138: ifnull        161
     141: aload_2
     142: invokeinterface #37,  1           // InterfaceMethod org/apache/hadoop/hbase/client/Admin.close:()V
     147: goto          217
     150: astore        4
     152: aload_3
     153: aload         4
     155: invokevirtual #39                 // Method java/lang/Throwable.addSuppressed:(Ljava/lang/Throwable;)V
     158: goto          217
     161: aload_2
     162: invokeinterface #37,  1           // InterfaceMethod org/apache/hadoop/hbase/client/Admin.close:()V
     167: goto          217
     170: astore        4
     172: aload         4
     174: astore_3
     175: aload         4
     177: athrow
     178: astore        5
     180: aload_2
     181: ifnull        214
     184: aload_3
     185: ifnull        208
     188: aload_2
     189: invokeinterface #37,  1           // InterfaceMethod org/apache/hadoop/hbase/client/Admin.close:()V
     194: goto          214
     197: astore        6
     199: aload_3
     200: aload         6
     202: invokevirtual #39                 // Method java/lang/Throwable.addSuppressed:(Ljava/lang/Throwable;)V
     205: goto          214
     208: aload_2
     209: invokeinterface #37,  1           // InterfaceMethod org/apache/hadoop/hbase/client/Admin.close:()V
     214: aload         5
     216: athrow
     217: return
    Exception table:
       from    to  target type
         141   147   150   Class java/lang/Throwable
          66   133   170   Class java/lang/Throwable
          66   133   178   any
         188   194   197   Class java/lang/Throwable
         170   180   178   any

  static {};
    Code:
       0: ldc           #43                 // class org/apache/hadoop/hbase/coprocessor/TestMasterObserverToModifyTableSchema
       2: invokestatic  #44                 // Method org/apache/hadoop/hbase/HBaseClassTestRule.forClass:(Ljava/lang/Class;)Lorg/apache/hadoop/hbase/HBaseClassTestRule;
       5: putstatic     #45                 // Field CLASS_RULE:Lorg/apache/hadoop/hbase/HBaseClassTestRule;
       8: new           #46                 // class org/apache/hadoop/hbase/HBaseTestingUtility
      11: dup
      12: invokespecial #47                 // Method org/apache/hadoop/hbase/HBaseTestingUtility."<init>":()V
      15: putstatic     #5                  // Field UTIL:Lorg/apache/hadoop/hbase/HBaseTestingUtility;
      18: ldc           #48                 // String TestTable
      20: invokestatic  #49                 // Method org/apache/hadoop/hbase/TableName.valueOf:(Ljava/lang/String;)Lorg/apache/hadoop/hbase/TableName;
      23: putstatic     #14                 // Field TABLENAME:Lorg/apache/hadoop/hbase/TableName;
      26: return
}
