Compiled from "TestHRegion.java"
class org.apache.hadoop.hbase.regionserver.TestHRegion$8 extends org.apache.hadoop.hbase.MultithreadedTestUtil$RepeatingTestThread {
  final org.apache.hadoop.hbase.regionserver.TestHRegion this$0;

  org.apache.hadoop.hbase.regionserver.TestHRegion$8(org.apache.hadoop.hbase.regionserver.TestHRegion, org.apache.hadoop.hbase.MultithreadedTestUtil$TestContext);
    Code:
       0: aload_0
       1: aload_1
       2: putfield      #1                  // Field this$0:Lorg/apache/hadoop/hbase/regionserver/TestHRegion;
       5: aload_0
       6: aload_2
       7: invokespecial #2                  // Method org/apache/hadoop/hbase/MultithreadedTestUtil$RepeatingTestThread."<init>":(Lorg/apache/hadoop/hbase/MultithreadedTestUtil$TestContext;)V
      10: return

  public void doAnAction() throws java.lang.Exception;
    Code:
       0: aload_0
       1: getfield      #1                  // Field this$0:Lorg/apache/hadoop/hbase/regionserver/TestHRegion;
       4: getfield      #3                  // Field org/apache/hadoop/hbase/regionserver/TestHRegion.region:Lorg/apache/hadoop/hbase/regionserver/HRegion;
       7: iconst_1
       8: invokevirtual #4                  // Method org/apache/hadoop/hbase/regionserver/HRegion.flush:(Z)Lorg/apache/hadoop/hbase/regionserver/HRegion$FlushResult;
      11: pop
      12: aload_0
      13: getfield      #1                  // Field this$0:Lorg/apache/hadoop/hbase/regionserver/TestHRegion;
      16: getfield      #3                  // Field org/apache/hadoop/hbase/regionserver/TestHRegion.region:Lorg/apache/hadoop/hbase/regionserver/HRegion;
      19: iconst_0
      20: invokevirtual #5                  // Method org/apache/hadoop/hbase/regionserver/HRegion.compact:(Z)V
      23: aload_0
      24: getfield      #1                  // Field this$0:Lorg/apache/hadoop/hbase/regionserver/TestHRegion;
      27: getfield      #3                  // Field org/apache/hadoop/hbase/regionserver/TestHRegion.region:Lorg/apache/hadoop/hbase/regionserver/HRegion;
      30: invokevirtual #6                  // Method org/apache/hadoop/hbase/regionserver/HRegion.getStores:()Ljava/util/List;
      33: invokeinterface #7,  1            // InterfaceMethod java/util/List.iterator:()Ljava/util/Iterator;
      38: astore_1
      39: aload_1
      40: invokeinterface #8,  1            // InterfaceMethod java/util/Iterator.hasNext:()Z
      45: ifeq          65
      48: aload_1
      49: invokeinterface #9,  1            // InterfaceMethod java/util/Iterator.next:()Ljava/lang/Object;
      54: checkcast     #10                 // class org/apache/hadoop/hbase/regionserver/HStore
      57: astore_2
      58: aload_2
      59: invokevirtual #11                 // Method org/apache/hadoop/hbase/regionserver/HStore.closeAndArchiveCompactedFiles:()V
      62: goto          39
      65: return
}
