Compiled from "TestHRegion.java"
class org.apache.hadoop.hbase.regionserver.TestHRegion$11 implements org.apache.hadoop.hbase.Waiter$Predicate<java.lang.Exception> {
  final boolean val$expectSync;

  final org.apache.hadoop.hbase.wal.WAL val$wal;

  final boolean val$expectSyncFromLogSyncer;

  final org.apache.hadoop.hbase.regionserver.TestHRegion this$0;

  org.apache.hadoop.hbase.regionserver.TestHRegion$11(org.apache.hadoop.hbase.regionserver.TestHRegion, boolean, org.apache.hadoop.hbase.wal.WAL, boolean);
    Code:
       0: aload_0
       1: aload_1
       2: putfield      #1                  // Field this$0:Lorg/apache/hadoop/hbase/regionserver/TestHRegion;
       5: aload_0
       6: iload_2
       7: putfield      #2                  // Field val$expectSync:Z
      10: aload_0
      11: aload_3
      12: putfield      #3                  // Field val$wal:Lorg/apache/hadoop/hbase/wal/WAL;
      15: aload_0
      16: iload         4
      18: putfield      #4                  // Field val$expectSyncFromLogSyncer:Z
      21: aload_0
      22: invokespecial #5                  // Method java/lang/Object."<init>":()V
      25: return

  public boolean evaluate() throws java.lang.Exception;
    Code:
       0: aload_0
       1: getfield      #2                  // Field val$expectSync:Z
       4: ifeq          32
       7: aload_0
       8: getfield      #3                  // Field val$wal:Lorg/apache/hadoop/hbase/wal/WAL;
      11: iconst_1
      12: invokestatic  #6                  // Method org/mockito/Mockito.times:(I)Lorg/mockito/verification/VerificationMode;
      15: invokestatic  #7                  // Method org/mockito/Mockito.verify:(Ljava/lang/Object;Lorg/mockito/verification/VerificationMode;)Ljava/lang/Object;
      18: checkcast     #8                  // class org/apache/hadoop/hbase/wal/WAL
      21: invokestatic  #9                  // Method org/mockito/ArgumentMatchers.anyLong:()J
      24: invokeinterface #10,  3           // InterfaceMethod org/apache/hadoop/hbase/wal/WAL.sync:(J)V
      29: goto          58
      32: aload_0
      33: getfield      #4                  // Field val$expectSyncFromLogSyncer:Z
      36: ifeq          58
      39: aload_0
      40: getfield      #3                  // Field val$wal:Lorg/apache/hadoop/hbase/wal/WAL;
      43: iconst_1
      44: invokestatic  #6                  // Method org/mockito/Mockito.times:(I)Lorg/mockito/verification/VerificationMode;
      47: invokestatic  #7                  // Method org/mockito/Mockito.verify:(Ljava/lang/Object;Lorg/mockito/verification/VerificationMode;)Ljava/lang/Object;
      50: checkcast     #8                  // class org/apache/hadoop/hbase/wal/WAL
      53: invokeinterface #11,  1           // InterfaceMethod org/apache/hadoop/hbase/wal/WAL.sync:()V
      58: goto          62
      61: astore_1
      62: iconst_1
      63: ireturn
    Exception table:
       from    to  target type
           0    58    61   Class java/lang/Throwable
}
