Compiled from "TestCleanerChore.java"
public class org.apache.hadoop.hbase.master.cleaner.TestCleanerChore {
  public static final org.apache.hadoop.hbase.HBaseClassTestRule CLASS_RULE;

  public org.apache.hadoop.hbase.master.cleaner.TestCleanerChore();
    Code:
       0: aload_0
       1: invokespecial #2                  // Method java/lang/Object."<init>":()V
       4: return

  public static void setup();
    Code:
       0: getstatic     #3                  // Field UTIL:Lorg/apache/hadoop/hbase/HBaseTestingUtility;
       3: invokevirtual #4                  // Method org/apache/hadoop/hbase/HBaseTestingUtility.getConfiguration:()Lorg/apache/hadoop/conf/Configuration;
       6: invokestatic  #5                  // Method org/apache/hadoop/hbase/master/cleaner/CleanerChore.initChorePool:(Lorg/apache/hadoop/conf/Configuration;)V
       9: return

  public static void cleanup() throws java.lang.Exception;
    Code:
       0: getstatic     #3                  // Field UTIL:Lorg/apache/hadoop/hbase/HBaseTestingUtility;
       3: invokevirtual #6                  // Method org/apache/hadoop/hbase/HBaseTestingUtility.cleanupTestDir:()Z
       6: pop
       7: invokestatic  #7                  // Method org/apache/hadoop/hbase/master/cleaner/CleanerChore.shutDownChorePool:()V
      10: return

  public void testSavesFilesOnRequest() throws java.lang.Exception;
    Code:
       0: new           #8                  // class org/apache/hadoop/hbase/util/StoppableImplementation
       3: dup
       4: invokespecial #9                  // Method org/apache/hadoop/hbase/util/StoppableImplementation."<init>":()V
       7: astore_1
       8: getstatic     #3                  // Field UTIL:Lorg/apache/hadoop/hbase/HBaseTestingUtility;
      11: invokevirtual #4                  // Method org/apache/hadoop/hbase/HBaseTestingUtility.getConfiguration:()Lorg/apache/hadoop/conf/Configuration;
      14: astore_2
      15: getstatic     #3                  // Field UTIL:Lorg/apache/hadoop/hbase/HBaseTestingUtility;
      18: invokevirtual #10                 // Method org/apache/hadoop/hbase/HBaseTestingUtility.getDataTestDir:()Lorg/apache/hadoop/fs/Path;
      21: astore_3
      22: getstatic     #3                  // Field UTIL:Lorg/apache/hadoop/hbase/HBaseTestingUtility;
      25: invokevirtual #11                 // Method org/apache/hadoop/hbase/HBaseTestingUtility.getTestFileSystem:()Lorg/apache/hadoop/fs/FileSystem;
      28: astore        4
      30: ldc           #12                 // String hbase.test.cleaner.delegates
      32: astore        5
      34: aload_2
      35: aload         5
      37: ldc           #13                 // class org/apache/hadoop/hbase/master/cleaner/TestCleanerChore$NeverDelete
      39: invokevirtual #14                 // Method java/lang/Class.getName:()Ljava/lang/String;
      42: invokevirtual #15                 // Method org/apache/hadoop/conf/Configuration.set:(Ljava/lang/String;Ljava/lang/String;)V
      45: new           #16                 // class org/apache/hadoop/hbase/master/cleaner/TestCleanerChore$AllValidPaths
      48: dup
      49: ldc           #17                 // String test-file-cleaner
      51: aload_1
      52: aload_2
      53: aload         4
      55: aload_3
      56: aload         5
      58: invokespecial #18                 // Method org/apache/hadoop/hbase/master/cleaner/TestCleanerChore$AllValidPaths."<init>":(Ljava/lang/String;Lorg/apache/hadoop/hbase/Stoppable;Lorg/apache/hadoop/conf/Configuration;Lorg/apache/hadoop/fs/FileSystem;Lorg/apache/hadoop/fs/Path;Ljava/lang/String;)V
      61: astore        6
      63: new           #19                 // class org/apache/hadoop/fs/Path
      66: dup
      67: aload_3
      68: ldc           #20                 // String parent
      70: invokespecial #21                 // Method org/apache/hadoop/fs/Path."<init>":(Lorg/apache/hadoop/fs/Path;Ljava/lang/String;)V
      73: astore        7
      75: new           #19                 // class org/apache/hadoop/fs/Path
      78: dup
      79: aload         7
      81: ldc           #22                 // String someFile
      83: invokespecial #21                 // Method org/apache/hadoop/fs/Path."<init>":(Lorg/apache/hadoop/fs/Path;Ljava/lang/String;)V
      86: astore        8
      88: aload         4
      90: aload         7
      92: invokevirtual #23                 // Method org/apache/hadoop/fs/FileSystem.mkdirs:(Lorg/apache/hadoop/fs/Path;)Z
      95: pop
      96: aload         4
      98: aload         8
     100: invokevirtual #24                 // Method org/apache/hadoop/fs/FileSystem.create:(Lorg/apache/hadoop/fs/Path;)Lorg/apache/hadoop/fs/FSDataOutputStream;
     103: invokevirtual #25                 // Method org/apache/hadoop/fs/FSDataOutputStream.close:()V
     106: ldc           #26                 // String Test file didn't get created.
     108: aload         4
     110: aload         8
     112: invokevirtual #27                 // Method org/apache/hadoop/fs/FileSystem.exists:(Lorg/apache/hadoop/fs/Path;)Z
     115: invokestatic  #28                 // Method org/junit/Assert.assertTrue:(Ljava/lang/String;Z)V
     118: aload         6
     120: invokevirtual #29                 // Method org/apache/hadoop/hbase/master/cleaner/TestCleanerChore$AllValidPaths.chore:()V
     123: ldc           #30                 // String File shouldn't have been deleted
     125: aload         4
     127: aload         8
     129: invokevirtual #27                 // Method org/apache/hadoop/fs/FileSystem.exists:(Lorg/apache/hadoop/fs/Path;)Z
     132: invokestatic  #28                 // Method org/junit/Assert.assertTrue:(Ljava/lang/String;Z)V
     135: ldc           #31                 // String directory shouldn't have been deleted
     137: aload         4
     139: aload         7
     141: invokevirtual #27                 // Method org/apache/hadoop/fs/FileSystem.exists:(Lorg/apache/hadoop/fs/Path;)Z
     144: invokestatic  #28                 // Method org/junit/Assert.assertTrue:(Ljava/lang/String;Z)V
     147: return

  public void retriesIOExceptionInStatus() throws java.lang.Exception;
    Code:
       0: new           #8                  // class org/apache/hadoop/hbase/util/StoppableImplementation
       3: dup
       4: invokespecial #9                  // Method org/apache/hadoop/hbase/util/StoppableImplementation."<init>":()V
       7: astore_1
       8: getstatic     #3                  // Field UTIL:Lorg/apache/hadoop/hbase/HBaseTestingUtility;
      11: invokevirtual #4                  // Method org/apache/hadoop/hbase/HBaseTestingUtility.getConfiguration:()Lorg/apache/hadoop/conf/Configuration;
      14: astore_2
      15: getstatic     #3                  // Field UTIL:Lorg/apache/hadoop/hbase/HBaseTestingUtility;
      18: invokevirtual #10                 // Method org/apache/hadoop/hbase/HBaseTestingUtility.getDataTestDir:()Lorg/apache/hadoop/fs/Path;
      21: astore_3
      22: getstatic     #3                  // Field UTIL:Lorg/apache/hadoop/hbase/HBaseTestingUtility;
      25: invokevirtual #11                 // Method org/apache/hadoop/hbase/HBaseTestingUtility.getTestFileSystem:()Lorg/apache/hadoop/fs/FileSystem;
      28: astore        4
      30: ldc           #12                 // String hbase.test.cleaner.delegates
      32: astore        5
      34: new           #19                 // class org/apache/hadoop/fs/Path
      37: dup
      38: aload_3
      39: ldc           #32                 // String child
      41: invokespecial #21                 // Method org/apache/hadoop/fs/Path."<init>":(Lorg/apache/hadoop/fs/Path;Ljava/lang/String;)V
      44: astore        6
      46: new           #19                 // class org/apache/hadoop/fs/Path
      49: dup
      50: aload         6
      52: ldc           #33                 // String file
      54: invokespecial #21                 // Method org/apache/hadoop/fs/Path."<init>":(Lorg/apache/hadoop/fs/Path;Ljava/lang/String;)V
      57: astore        7
      59: aload         4
      61: aload         6
      63: invokevirtual #23                 // Method org/apache/hadoop/fs/FileSystem.mkdirs:(Lorg/apache/hadoop/fs/Path;)Z
      66: pop
      67: aload         4
      69: aload         7
      71: invokevirtual #24                 // Method org/apache/hadoop/fs/FileSystem.create:(Lorg/apache/hadoop/fs/Path;)Lorg/apache/hadoop/fs/FSDataOutputStream;
      74: invokevirtual #25                 // Method org/apache/hadoop/fs/FSDataOutputStream.close:()V
      77: ldc           #34                 // String test file didn't get created.
      79: aload         4
      81: aload         7
      83: invokevirtual #27                 // Method org/apache/hadoop/fs/FileSystem.exists:(Lorg/apache/hadoop/fs/Path;)Z
      86: invokestatic  #28                 // Method org/junit/Assert.assertTrue:(Ljava/lang/String;Z)V
      89: new           #35                 // class java/util/concurrent/atomic/AtomicBoolean
      92: dup
      93: iconst_1
      94: invokespecial #36                 // Method java/util/concurrent/atomic/AtomicBoolean."<init>":(Z)V
      97: astore        8
      99: new           #37                 // class org/apache/hadoop/hbase/master/cleaner/TestCleanerChore$1
     102: dup
     103: aload_0
     104: aload         4
     106: aload         8
     108: invokespecial #38                 // Method org/apache/hadoop/hbase/master/cleaner/TestCleanerChore$1."<init>":(Lorg/apache/hadoop/hbase/master/cleaner/TestCleanerChore;Lorg/apache/hadoop/fs/FileSystem;Ljava/util/concurrent/atomic/AtomicBoolean;)V
     111: astore        9
     113: new           #16                 // class org/apache/hadoop/hbase/master/cleaner/TestCleanerChore$AllValidPaths
     116: dup
     117: ldc           #39                 // String test-retry-ioe
     119: aload_1
     120: aload_2
     121: aload         9
     123: aload_3
     124: aload         5
     126: invokespecial #18                 // Method org/apache/hadoop/hbase/master/cleaner/TestCleanerChore$AllValidPaths."<init>":(Ljava/lang/String;Lorg/apache/hadoop/hbase/Stoppable;Lorg/apache/hadoop/conf/Configuration;Lorg/apache/hadoop/fs/FileSystem;Lorg/apache/hadoop/fs/Path;Ljava/lang/String;)V
     129: astore        10
     131: aload         10
     133: invokevirtual #40                 // Method org/apache/hadoop/hbase/master/cleaner/TestCleanerChore$AllValidPaths.runCleaner:()Ljava/lang/Boolean;
     136: astore        11
     138: ldc           #41                 // String test rig failed to inject failure.
     140: aload         4
     142: aload         7
     144: invokevirtual #27                 // Method org/apache/hadoop/fs/FileSystem.exists:(Lorg/apache/hadoop/fs/Path;)Z
     147: invokestatic  #28                 // Method org/junit/Assert.assertTrue:(Ljava/lang/String;Z)V
     150: ldc           #41                 // String test rig failed to inject failure.
     152: aload         4
     154: aload         6
     156: invokevirtual #27                 // Method org/apache/hadoop/fs/FileSystem.exists:(Lorg/apache/hadoop/fs/Path;)Z
     159: invokestatic  #28                 // Method org/junit/Assert.assertTrue:(Ljava/lang/String;Z)V
     162: ldc           #42                 // String chore should report that it failed.
     164: aload         11
     166: invokevirtual #43                 // Method java/lang/Boolean.booleanValue:()Z
     169: invokestatic  #44                 // Method org/junit/Assert.assertFalse:(Ljava/lang/String;Z)V
     172: aload         8
     174: iconst_0
     175: invokevirtual #45                 // Method java/util/concurrent/atomic/AtomicBoolean.set:(Z)V
     178: aload         10
     180: invokevirtual #40                 // Method org/apache/hadoop/hbase/master/cleaner/TestCleanerChore$AllValidPaths.runCleaner:()Ljava/lang/Boolean;
     183: astore        11
     185: ldc           #46                 // String file should have been destroyed.
     187: aload         4
     189: aload         7
     191: invokevirtual #27                 // Method org/apache/hadoop/fs/FileSystem.exists:(Lorg/apache/hadoop/fs/Path;)Z
     194: invokestatic  #44                 // Method org/junit/Assert.assertFalse:(Ljava/lang/String;Z)V
     197: ldc           #47                 // String directory should have been destroyed.
     199: aload         4
     201: aload         6
     203: invokevirtual #27                 // Method org/apache/hadoop/fs/FileSystem.exists:(Lorg/apache/hadoop/fs/Path;)Z
     206: invokestatic  #44                 // Method org/junit/Assert.assertFalse:(Ljava/lang/String;Z)V
     209: ldc           #48                 // String chore should claim it succeeded.
     211: aload         11
     213: invokevirtual #43                 // Method java/lang/Boolean.booleanValue:()Z
     216: invokestatic  #28                 // Method org/junit/Assert.assertTrue:(Ljava/lang/String;Z)V
     219: return

  public void testDeletesEmptyDirectories() throws java.lang.Exception;
    Code:
       0: new           #8                  // class org/apache/hadoop/hbase/util/StoppableImplementation
       3: dup
       4: invokespecial #9                  // Method org/apache/hadoop/hbase/util/StoppableImplementation."<init>":()V
       7: astore_1
       8: getstatic     #3                  // Field UTIL:Lorg/apache/hadoop/hbase/HBaseTestingUtility;
      11: invokevirtual #4                  // Method org/apache/hadoop/hbase/HBaseTestingUtility.getConfiguration:()Lorg/apache/hadoop/conf/Configuration;
      14: astore_2
      15: getstatic     #3                  // Field UTIL:Lorg/apache/hadoop/hbase/HBaseTestingUtility;
      18: invokevirtual #10                 // Method org/apache/hadoop/hbase/HBaseTestingUtility.getDataTestDir:()Lorg/apache/hadoop/fs/Path;
      21: astore_3
      22: getstatic     #3                  // Field UTIL:Lorg/apache/hadoop/hbase/HBaseTestingUtility;
      25: invokevirtual #11                 // Method org/apache/hadoop/hbase/HBaseTestingUtility.getTestFileSystem:()Lorg/apache/hadoop/fs/FileSystem;
      28: astore        4
      30: ldc           #12                 // String hbase.test.cleaner.delegates
      32: astore        5
      34: aload_2
      35: aload         5
      37: ldc           #49                 // class org/apache/hadoop/hbase/master/cleaner/TestCleanerChore$AlwaysDelete
      39: invokevirtual #14                 // Method java/lang/Class.getName:()Ljava/lang/String;
      42: invokevirtual #15                 // Method org/apache/hadoop/conf/Configuration.set:(Ljava/lang/String;Ljava/lang/String;)V
      45: new           #16                 // class org/apache/hadoop/hbase/master/cleaner/TestCleanerChore$AllValidPaths
      48: dup
      49: ldc           #17                 // String test-file-cleaner
      51: aload_1
      52: aload_2
      53: aload         4
      55: aload_3
      56: aload         5
      58: invokespecial #18                 // Method org/apache/hadoop/hbase/master/cleaner/TestCleanerChore$AllValidPaths."<init>":(Ljava/lang/String;Lorg/apache/hadoop/hbase/Stoppable;Lorg/apache/hadoop/conf/Configuration;Lorg/apache/hadoop/fs/FileSystem;Lorg/apache/hadoop/fs/Path;Ljava/lang/String;)V
      61: astore        6
      63: new           #19                 // class org/apache/hadoop/fs/Path
      66: dup
      67: aload_3
      68: ldc           #20                 // String parent
      70: invokespecial #21                 // Method org/apache/hadoop/fs/Path."<init>":(Lorg/apache/hadoop/fs/Path;Ljava/lang/String;)V
      73: astore        7
      75: new           #19                 // class org/apache/hadoop/fs/Path
      78: dup
      79: aload         7
      81: ldc           #32                 // String child
      83: invokespecial #21                 // Method org/apache/hadoop/fs/Path."<init>":(Lorg/apache/hadoop/fs/Path;Ljava/lang/String;)V
      86: astore        8
      88: new           #19                 // class org/apache/hadoop/fs/Path
      91: dup
      92: aload         7
      94: ldc           #50                 // String emptyChild
      96: invokespecial #21                 // Method org/apache/hadoop/fs/Path."<init>":(Lorg/apache/hadoop/fs/Path;Ljava/lang/String;)V
      99: astore        9
     101: new           #19                 // class org/apache/hadoop/fs/Path
     104: dup
     105: aload         8
     107: ldc           #22                 // String someFile
     109: invokespecial #21                 // Method org/apache/hadoop/fs/Path."<init>":(Lorg/apache/hadoop/fs/Path;Ljava/lang/String;)V
     112: astore        10
     114: aload         4
     116: aload         8
     118: invokevirtual #23                 // Method org/apache/hadoop/fs/FileSystem.mkdirs:(Lorg/apache/hadoop/fs/Path;)Z
     121: pop
     122: aload         4
     124: aload         9
     126: invokevirtual #23                 // Method org/apache/hadoop/fs/FileSystem.mkdirs:(Lorg/apache/hadoop/fs/Path;)Z
     129: pop
     130: aload         4
     132: aload         10
     134: invokevirtual #24                 // Method org/apache/hadoop/fs/FileSystem.create:(Lorg/apache/hadoop/fs/Path;)Lorg/apache/hadoop/fs/FSDataOutputStream;
     137: invokevirtual #25                 // Method org/apache/hadoop/fs/FSDataOutputStream.close:()V
     140: new           #19                 // class org/apache/hadoop/fs/Path
     143: dup
     144: aload_3
     145: ldc           #51                 // String topFile
     147: invokespecial #21                 // Method org/apache/hadoop/fs/Path."<init>":(Lorg/apache/hadoop/fs/Path;Ljava/lang/String;)V
     150: astore        11
     152: aload         4
     154: aload         11
     156: invokevirtual #24                 // Method org/apache/hadoop/fs/FileSystem.create:(Lorg/apache/hadoop/fs/Path;)Lorg/apache/hadoop/fs/FSDataOutputStream;
     159: invokevirtual #25                 // Method org/apache/hadoop/fs/FSDataOutputStream.close:()V
     162: ldc           #26                 // String Test file didn't get created.
     164: aload         4
     166: aload         10
     168: invokevirtual #27                 // Method org/apache/hadoop/fs/FileSystem.exists:(Lorg/apache/hadoop/fs/Path;)Z
     171: invokestatic  #28                 // Method org/junit/Assert.assertTrue:(Ljava/lang/String;Z)V
     174: ldc           #26                 // String Test file didn't get created.
     176: aload         4
     178: aload         11
     180: invokevirtual #27                 // Method org/apache/hadoop/fs/FileSystem.exists:(Lorg/apache/hadoop/fs/Path;)Z
     183: invokestatic  #28                 // Method org/junit/Assert.assertTrue:(Ljava/lang/String;Z)V
     186: aload         6
     188: invokevirtual #29                 // Method org/apache/hadoop/hbase/master/cleaner/TestCleanerChore$AllValidPaths.chore:()V
     191: ldc           #52                 // String File didn't get deleted
     193: aload         4
     195: aload         11
     197: invokevirtual #27                 // Method org/apache/hadoop/fs/FileSystem.exists:(Lorg/apache/hadoop/fs/Path;)Z
     200: invokestatic  #44                 // Method org/junit/Assert.assertFalse:(Ljava/lang/String;Z)V
     203: ldc           #52                 // String File didn't get deleted
     205: aload         4
     207: aload         10
     209: invokevirtual #27                 // Method org/apache/hadoop/fs/FileSystem.exists:(Lorg/apache/hadoop/fs/Path;)Z
     212: invokestatic  #44                 // Method org/junit/Assert.assertFalse:(Ljava/lang/String;Z)V
     215: ldc           #53                 // String Empty directory didn't get deleted
     217: aload         4
     219: aload         8
     221: invokevirtual #27                 // Method org/apache/hadoop/fs/FileSystem.exists:(Lorg/apache/hadoop/fs/Path;)Z
     224: invokestatic  #44                 // Method org/junit/Assert.assertFalse:(Ljava/lang/String;Z)V
     227: ldc           #53                 // String Empty directory didn't get deleted
     229: aload         4
     231: aload         7
     233: invokevirtual #27                 // Method org/apache/hadoop/fs/FileSystem.exists:(Lorg/apache/hadoop/fs/Path;)Z
     236: invokestatic  #44                 // Method org/junit/Assert.assertFalse:(Ljava/lang/String;Z)V
     239: return

  public void testDoesNotCheckDirectories() throws java.lang.Exception;
    Code:
       0: new           #8                  // class org/apache/hadoop/hbase/util/StoppableImplementation
       3: dup
       4: invokespecial #9                  // Method org/apache/hadoop/hbase/util/StoppableImplementation."<init>":()V
       7: astore_1
       8: getstatic     #3                  // Field UTIL:Lorg/apache/hadoop/hbase/HBaseTestingUtility;
      11: invokevirtual #4                  // Method org/apache/hadoop/hbase/HBaseTestingUtility.getConfiguration:()Lorg/apache/hadoop/conf/Configuration;
      14: astore_2
      15: getstatic     #3                  // Field UTIL:Lorg/apache/hadoop/hbase/HBaseTestingUtility;
      18: invokevirtual #10                 // Method org/apache/hadoop/hbase/HBaseTestingUtility.getDataTestDir:()Lorg/apache/hadoop/fs/Path;
      21: astore_3
      22: getstatic     #3                  // Field UTIL:Lorg/apache/hadoop/hbase/HBaseTestingUtility;
      25: invokevirtual #11                 // Method org/apache/hadoop/hbase/HBaseTestingUtility.getTestFileSystem:()Lorg/apache/hadoop/fs/FileSystem;
      28: astore        4
      30: ldc           #12                 // String hbase.test.cleaner.delegates
      32: astore        5
      34: aload_2
      35: aload         5
      37: ldc           #49                 // class org/apache/hadoop/hbase/master/cleaner/TestCleanerChore$AlwaysDelete
      39: invokevirtual #14                 // Method java/lang/Class.getName:()Ljava/lang/String;
      42: invokevirtual #15                 // Method org/apache/hadoop/conf/Configuration.set:(Ljava/lang/String;Ljava/lang/String;)V
      45: new           #16                 // class org/apache/hadoop/hbase/master/cleaner/TestCleanerChore$AllValidPaths
      48: dup
      49: ldc           #17                 // String test-file-cleaner
      51: aload_1
      52: aload_2
      53: aload         4
      55: aload_3
      56: aload         5
      58: invokespecial #18                 // Method org/apache/hadoop/hbase/master/cleaner/TestCleanerChore$AllValidPaths."<init>":(Ljava/lang/String;Lorg/apache/hadoop/hbase/Stoppable;Lorg/apache/hadoop/conf/Configuration;Lorg/apache/hadoop/fs/FileSystem;Lorg/apache/hadoop/fs/Path;Ljava/lang/String;)V
      61: astore        6
      63: aload         6
      65: getfield      #54                 // Field org/apache/hadoop/hbase/master/cleaner/TestCleanerChore$AllValidPaths.cleanersChain:Ljava/util/List;
      68: iconst_0
      69: invokeinterface #55,  2           // InterfaceMethod java/util/List.get:(I)Ljava/lang/Object;
      74: checkcast     #49                 // class org/apache/hadoop/hbase/master/cleaner/TestCleanerChore$AlwaysDelete
      77: astore        7
      79: aload         7
      81: invokestatic  #56                 // Method org/mockito/Mockito.spy:(Ljava/lang/Object;)Ljava/lang/Object;
      84: checkcast     #49                 // class org/apache/hadoop/hbase/master/cleaner/TestCleanerChore$AlwaysDelete
      87: astore        8
      89: aload         6
      91: getfield      #54                 // Field org/apache/hadoop/hbase/master/cleaner/TestCleanerChore$AllValidPaths.cleanersChain:Ljava/util/List;
      94: iconst_0
      95: aload         8
      97: invokeinterface #57,  3           // InterfaceMethod java/util/List.set:(ILjava/lang/Object;)Ljava/lang/Object;
     102: pop
     103: new           #19                 // class org/apache/hadoop/fs/Path
     106: dup
     107: aload_3
     108: ldc           #20                 // String parent
     110: invokespecial #21                 // Method org/apache/hadoop/fs/Path."<init>":(Lorg/apache/hadoop/fs/Path;Ljava/lang/String;)V
     113: astore        9
     115: new           #19                 // class org/apache/hadoop/fs/Path
     118: dup
     119: aload         9
     121: ldc           #22                 // String someFile
     123: invokespecial #21                 // Method org/apache/hadoop/fs/Path."<init>":(Lorg/apache/hadoop/fs/Path;Ljava/lang/String;)V
     126: astore        10
     128: aload         4
     130: aload         9
     132: invokevirtual #23                 // Method org/apache/hadoop/fs/FileSystem.mkdirs:(Lorg/apache/hadoop/fs/Path;)Z
     135: pop
     136: ldc           #58                 // String Test parent didn't get created.
     138: aload         4
     140: aload         9
     142: invokevirtual #27                 // Method org/apache/hadoop/fs/FileSystem.exists:(Lorg/apache/hadoop/fs/Path;)Z
     145: invokestatic  #28                 // Method org/junit/Assert.assertTrue:(Ljava/lang/String;Z)V
     148: aload         4
     150: aload         10
     152: invokevirtual #24                 // Method org/apache/hadoop/fs/FileSystem.create:(Lorg/apache/hadoop/fs/Path;)Lorg/apache/hadoop/fs/FSDataOutputStream;
     155: invokevirtual #25                 // Method org/apache/hadoop/fs/FSDataOutputStream.close:()V
     158: ldc           #26                 // String Test file didn't get created.
     160: aload         4
     162: aload         10
     164: invokevirtual #27                 // Method org/apache/hadoop/fs/FileSystem.exists:(Lorg/apache/hadoop/fs/Path;)Z
     167: invokestatic  #28                 // Method org/junit/Assert.assertTrue:(Ljava/lang/String;Z)V
     170: aload         4
     172: aload         9
     174: invokevirtual #59                 // Method org/apache/hadoop/fs/FileSystem.getFileStatus:(Lorg/apache/hadoop/fs/Path;)Lorg/apache/hadoop/fs/FileStatus;
     177: astore        11
     179: aload         6
     181: invokevirtual #29                 // Method org/apache/hadoop/hbase/master/cleaner/TestCleanerChore$AllValidPaths.chore:()V
     184: aload         8
     186: invokestatic  #60                 // Method org/mockito/Mockito.never:()Lorg/mockito/verification/VerificationMode;
     189: invokestatic  #61                 // Method org/mockito/Mockito.verify:(Ljava/lang/Object;Lorg/mockito/verification/VerificationMode;)Ljava/lang/Object;
     192: checkcast     #49                 // class org/apache/hadoop/hbase/master/cleaner/TestCleanerChore$AlwaysDelete
     195: aload         11
     197: invokevirtual #62                 // Method org/apache/hadoop/hbase/master/cleaner/TestCleanerChore$AlwaysDelete.isFileDeletable:(Lorg/apache/hadoop/fs/FileStatus;)Z
     200: pop
     201: iconst_1
     202: anewarray     #49                 // class org/apache/hadoop/hbase/master/cleaner/TestCleanerChore$AlwaysDelete
     205: dup
     206: iconst_0
     207: aload         8
     209: aastore
     210: invokestatic  #63                 // Method org/mockito/Mockito.reset:([Ljava/lang/Object;)V
     213: return

  public void testStoppedCleanerDoesNotDeleteFiles() throws java.lang.Exception;
    Code:
       0: new           #8                  // class org/apache/hadoop/hbase/util/StoppableImplementation
       3: dup
       4: invokespecial #9                  // Method org/apache/hadoop/hbase/util/StoppableImplementation."<init>":()V
       7: astore_1
       8: getstatic     #3                  // Field UTIL:Lorg/apache/hadoop/hbase/HBaseTestingUtility;
      11: invokevirtual #4                  // Method org/apache/hadoop/hbase/HBaseTestingUtility.getConfiguration:()Lorg/apache/hadoop/conf/Configuration;
      14: astore_2
      15: getstatic     #3                  // Field UTIL:Lorg/apache/hadoop/hbase/HBaseTestingUtility;
      18: invokevirtual #10                 // Method org/apache/hadoop/hbase/HBaseTestingUtility.getDataTestDir:()Lorg/apache/hadoop/fs/Path;
      21: astore_3
      22: getstatic     #3                  // Field UTIL:Lorg/apache/hadoop/hbase/HBaseTestingUtility;
      25: invokevirtual #11                 // Method org/apache/hadoop/hbase/HBaseTestingUtility.getTestFileSystem:()Lorg/apache/hadoop/fs/FileSystem;
      28: astore        4
      30: ldc           #12                 // String hbase.test.cleaner.delegates
      32: astore        5
      34: aload_2
      35: aload         5
      37: ldc           #49                 // class org/apache/hadoop/hbase/master/cleaner/TestCleanerChore$AlwaysDelete
      39: invokevirtual #14                 // Method java/lang/Class.getName:()Ljava/lang/String;
      42: invokevirtual #15                 // Method org/apache/hadoop/conf/Configuration.set:(Ljava/lang/String;Ljava/lang/String;)V
      45: new           #16                 // class org/apache/hadoop/hbase/master/cleaner/TestCleanerChore$AllValidPaths
      48: dup
      49: ldc           #17                 // String test-file-cleaner
      51: aload_1
      52: aload_2
      53: aload         4
      55: aload_3
      56: aload         5
      58: invokespecial #18                 // Method org/apache/hadoop/hbase/master/cleaner/TestCleanerChore$AllValidPaths."<init>":(Ljava/lang/String;Lorg/apache/hadoop/hbase/Stoppable;Lorg/apache/hadoop/conf/Configuration;Lorg/apache/hadoop/fs/FileSystem;Lorg/apache/hadoop/fs/Path;Ljava/lang/String;)V
      61: astore        6
      63: new           #19                 // class org/apache/hadoop/fs/Path
      66: dup
      67: aload_3
      68: ldc           #51                 // String topFile
      70: invokespecial #21                 // Method org/apache/hadoop/fs/Path."<init>":(Lorg/apache/hadoop/fs/Path;Ljava/lang/String;)V
      73: astore        7
      75: aload         4
      77: aload         7
      79: invokevirtual #24                 // Method org/apache/hadoop/fs/FileSystem.create:(Lorg/apache/hadoop/fs/Path;)Lorg/apache/hadoop/fs/FSDataOutputStream;
      82: invokevirtual #25                 // Method org/apache/hadoop/fs/FSDataOutputStream.close:()V
      85: ldc           #26                 // String Test file didn't get created.
      87: aload         4
      89: aload         7
      91: invokevirtual #27                 // Method org/apache/hadoop/fs/FileSystem.exists:(Lorg/apache/hadoop/fs/Path;)Z
      94: invokestatic  #28                 // Method org/junit/Assert.assertTrue:(Ljava/lang/String;Z)V
      97: aload_1
      98: ldc           #64                 // String testing stop
     100: invokeinterface #65,  2           // InterfaceMethod org/apache/hadoop/hbase/Stoppable.stop:(Ljava/lang/String;)V
     105: aload         6
     107: invokevirtual #29                 // Method org/apache/hadoop/hbase/master/cleaner/TestCleanerChore$AllValidPaths.chore:()V
     110: ldc           #66                 // String File got deleted while chore was stopped
     112: aload         4
     114: aload         7
     116: invokevirtual #27                 // Method org/apache/hadoop/fs/FileSystem.exists:(Lorg/apache/hadoop/fs/Path;)Z
     119: invokestatic  #28                 // Method org/junit/Assert.assertTrue:(Ljava/lang/String;Z)V
     122: return

  public void testCleanerDoesNotDeleteDirectoryWithLateAddedFiles() throws java.io.IOException;
    Code:
       0: new           #8                  // class org/apache/hadoop/hbase/util/StoppableImplementation
       3: dup
       4: invokespecial #9                  // Method org/apache/hadoop/hbase/util/StoppableImplementation."<init>":()V
       7: astore_1
       8: getstatic     #3                  // Field UTIL:Lorg/apache/hadoop/hbase/HBaseTestingUtility;
      11: invokevirtual #4                  // Method org/apache/hadoop/hbase/HBaseTestingUtility.getConfiguration:()Lorg/apache/hadoop/conf/Configuration;
      14: astore_2
      15: getstatic     #3                  // Field UTIL:Lorg/apache/hadoop/hbase/HBaseTestingUtility;
      18: invokevirtual #10                 // Method org/apache/hadoop/hbase/HBaseTestingUtility.getDataTestDir:()Lorg/apache/hadoop/fs/Path;
      21: astore_3
      22: getstatic     #3                  // Field UTIL:Lorg/apache/hadoop/hbase/HBaseTestingUtility;
      25: invokevirtual #11                 // Method org/apache/hadoop/hbase/HBaseTestingUtility.getTestFileSystem:()Lorg/apache/hadoop/fs/FileSystem;
      28: astore        4
      30: ldc           #12                 // String hbase.test.cleaner.delegates
      32: astore        5
      34: aload_2
      35: aload         5
      37: ldc           #49                 // class org/apache/hadoop/hbase/master/cleaner/TestCleanerChore$AlwaysDelete
      39: invokevirtual #14                 // Method java/lang/Class.getName:()Ljava/lang/String;
      42: invokevirtual #15                 // Method org/apache/hadoop/conf/Configuration.set:(Ljava/lang/String;Ljava/lang/String;)V
      45: new           #16                 // class org/apache/hadoop/hbase/master/cleaner/TestCleanerChore$AllValidPaths
      48: dup
      49: ldc           #17                 // String test-file-cleaner
      51: aload_1
      52: aload_2
      53: aload         4
      55: aload_3
      56: aload         5
      58: invokespecial #18                 // Method org/apache/hadoop/hbase/master/cleaner/TestCleanerChore$AllValidPaths."<init>":(Ljava/lang/String;Lorg/apache/hadoop/hbase/Stoppable;Lorg/apache/hadoop/conf/Configuration;Lorg/apache/hadoop/fs/FileSystem;Lorg/apache/hadoop/fs/Path;Ljava/lang/String;)V
      61: astore        6
      63: aload         6
      65: getfield      #54                 // Field org/apache/hadoop/hbase/master/cleaner/TestCleanerChore$AllValidPaths.cleanersChain:Ljava/util/List;
      68: iconst_0
      69: invokeinterface #55,  2           // InterfaceMethod java/util/List.get:(I)Ljava/lang/Object;
      74: checkcast     #49                 // class org/apache/hadoop/hbase/master/cleaner/TestCleanerChore$AlwaysDelete
      77: astore        7
      79: aload         7
      81: invokestatic  #56                 // Method org/mockito/Mockito.spy:(Ljava/lang/Object;)Ljava/lang/Object;
      84: checkcast     #49                 // class org/apache/hadoop/hbase/master/cleaner/TestCleanerChore$AlwaysDelete
      87: astore        8
      89: aload         6
      91: getfield      #54                 // Field org/apache/hadoop/hbase/master/cleaner/TestCleanerChore$AllValidPaths.cleanersChain:Ljava/util/List;
      94: iconst_0
      95: aload         8
      97: invokeinterface #57,  3           // InterfaceMethod java/util/List.set:(ILjava/lang/Object;)Ljava/lang/Object;
     102: pop
     103: new           #19                 // class org/apache/hadoop/fs/Path
     106: dup
     107: aload_3
     108: ldc           #20                 // String parent
     110: invokespecial #21                 // Method org/apache/hadoop/fs/Path."<init>":(Lorg/apache/hadoop/fs/Path;Ljava/lang/String;)V
     113: astore        9
     115: new           #19                 // class org/apache/hadoop/fs/Path
     118: dup
     119: aload         9
     121: ldc           #22                 // String someFile
     123: invokespecial #21                 // Method org/apache/hadoop/fs/Path."<init>":(Lorg/apache/hadoop/fs/Path;Ljava/lang/String;)V
     126: astore        10
     128: aload         4
     130: aload         9
     132: invokevirtual #23                 // Method org/apache/hadoop/fs/FileSystem.mkdirs:(Lorg/apache/hadoop/fs/Path;)Z
     135: pop
     136: aload         4
     138: aload         10
     140: invokevirtual #24                 // Method org/apache/hadoop/fs/FileSystem.create:(Lorg/apache/hadoop/fs/Path;)Lorg/apache/hadoop/fs/FSDataOutputStream;
     143: invokevirtual #25                 // Method org/apache/hadoop/fs/FSDataOutputStream.close:()V
     146: ldc           #26                 // String Test file didn't get created.
     148: aload         4
     150: aload         10
     152: invokevirtual #27                 // Method org/apache/hadoop/fs/FileSystem.exists:(Lorg/apache/hadoop/fs/Path;)Z
     155: invokestatic  #28                 // Method org/junit/Assert.assertTrue:(Ljava/lang/String;Z)V
     158: new           #19                 // class org/apache/hadoop/fs/Path
     161: dup
     162: aload         9
     164: ldc           #67                 // String addedFile
     166: invokespecial #21                 // Method org/apache/hadoop/fs/Path."<init>":(Lorg/apache/hadoop/fs/Path;Ljava/lang/String;)V
     169: astore        11
     171: new           #68                 // class org/apache/hadoop/hbase/master/cleaner/TestCleanerChore$2
     174: dup
     175: aload_0
     176: aload         4
     178: aload         11
     180: aload_3
     181: invokespecial #69                 // Method org/apache/hadoop/hbase/master/cleaner/TestCleanerChore$2."<init>":(Lorg/apache/hadoop/hbase/master/cleaner/TestCleanerChore;Lorg/apache/hadoop/fs/FileSystem;Lorg/apache/hadoop/fs/Path;Lorg/apache/hadoop/fs/Path;)V
     184: invokestatic  #70                 // Method org/mockito/Mockito.doAnswer:(Lorg/mockito/stubbing/Answer;)Lorg/mockito/stubbing/Stubber;
     187: aload         8
     189: invokeinterface #71,  2           // InterfaceMethod org/mockito/stubbing/Stubber.when:(Ljava/lang/Object;)Ljava/lang/Object;
     194: checkcast     #49                 // class org/apache/hadoop/hbase/master/cleaner/TestCleanerChore$AlwaysDelete
     197: invokestatic  #72                 // Method org/mockito/Mockito.any:()Ljava/lang/Object;
     200: checkcast     #73                 // class org/apache/hadoop/fs/FileStatus
     203: invokevirtual #62                 // Method org/apache/hadoop/hbase/master/cleaner/TestCleanerChore$AlwaysDelete.isFileDeletable:(Lorg/apache/hadoop/fs/FileStatus;)Z
     206: pop
     207: aload         6
     209: invokevirtual #29                 // Method org/apache/hadoop/hbase/master/cleaner/TestCleanerChore$AllValidPaths.chore:()V
     212: ldc           #74                 // String Added file unexpectedly deleted
     214: aload         4
     216: aload         11
     218: invokevirtual #27                 // Method org/apache/hadoop/fs/FileSystem.exists:(Lorg/apache/hadoop/fs/Path;)Z
     221: invokestatic  #28                 // Method org/junit/Assert.assertTrue:(Ljava/lang/String;Z)V
     224: ldc           #75                 // String Parent directory deleted unexpectedly
     226: aload         4
     228: aload         9
     230: invokevirtual #27                 // Method org/apache/hadoop/fs/FileSystem.exists:(Lorg/apache/hadoop/fs/Path;)Z
     233: invokestatic  #28                 // Method org/junit/Assert.assertTrue:(Ljava/lang/String;Z)V
     236: ldc           #76                 // String Original file unexpectedly retained
     238: aload         4
     240: aload         10
     242: invokevirtual #27                 // Method org/apache/hadoop/fs/FileSystem.exists:(Lorg/apache/hadoop/fs/Path;)Z
     245: invokestatic  #44                 // Method org/junit/Assert.assertFalse:(Ljava/lang/String;Z)V
     248: aload         8
     250: iconst_1
     251: invokestatic  #77                 // Method org/mockito/Mockito.times:(I)Lorg/mockito/verification/VerificationMode;
     254: invokestatic  #61                 // Method org/mockito/Mockito.verify:(Ljava/lang/Object;Lorg/mockito/verification/VerificationMode;)Ljava/lang/Object;
     257: checkcast     #49                 // class org/apache/hadoop/hbase/master/cleaner/TestCleanerChore$AlwaysDelete
     260: invokestatic  #72                 // Method org/mockito/Mockito.any:()Ljava/lang/Object;
     263: checkcast     #73                 // class org/apache/hadoop/fs/FileStatus
     266: invokevirtual #62                 // Method org/apache/hadoop/hbase/master/cleaner/TestCleanerChore$AlwaysDelete.isFileDeletable:(Lorg/apache/hadoop/fs/FileStatus;)Z
     269: pop
     270: iconst_1
     271: anewarray     #49                 // class org/apache/hadoop/hbase/master/cleaner/TestCleanerChore$AlwaysDelete
     274: dup
     275: iconst_0
     276: aload         8
     278: aastore
     279: invokestatic  #63                 // Method org/mockito/Mockito.reset:([Ljava/lang/Object;)V
     282: return

  public void testNoExceptionFromDirectoryWithRacyChildren() throws java.lang.Exception;
    Code:
       0: getstatic     #3                  // Field UTIL:Lorg/apache/hadoop/hbase/HBaseTestingUtility;
       3: invokevirtual #6                  // Method org/apache/hadoop/hbase/HBaseTestingUtility.cleanupTestDir:()Z
       6: pop
       7: new           #8                  // class org/apache/hadoop/hbase/util/StoppableImplementation
      10: dup
      11: invokespecial #9                  // Method org/apache/hadoop/hbase/util/StoppableImplementation."<init>":()V
      14: astore_1
      15: new           #78                 // class org/apache/hadoop/hbase/HBaseTestingUtility
      18: dup
      19: invokespecial #79                 // Method org/apache/hadoop/hbase/HBaseTestingUtility."<init>":()V
      22: astore_2
      23: aload_2
      24: invokevirtual #4                  // Method org/apache/hadoop/hbase/HBaseTestingUtility.getConfiguration:()Lorg/apache/hadoop/conf/Configuration;
      27: astore_3
      28: getstatic     #3                  // Field UTIL:Lorg/apache/hadoop/hbase/HBaseTestingUtility;
      31: invokevirtual #10                 // Method org/apache/hadoop/hbase/HBaseTestingUtility.getDataTestDir:()Lorg/apache/hadoop/fs/Path;
      34: astore        4
      36: getstatic     #3                  // Field UTIL:Lorg/apache/hadoop/hbase/HBaseTestingUtility;
      39: invokevirtual #11                 // Method org/apache/hadoop/hbase/HBaseTestingUtility.getTestFileSystem:()Lorg/apache/hadoop/fs/FileSystem;
      42: astore        5
      44: getstatic     #1                  // Field LOG:Lorg/slf4j/Logger;
      47: new           #80                 // class java/lang/StringBuilder
      50: dup
      51: invokespecial #81                 // Method java/lang/StringBuilder."<init>":()V
      54: ldc           #82                 // String Writing test data to:
      56: invokevirtual #83                 // Method java/lang/StringBuilder.append:(Ljava/lang/String;)Ljava/lang/StringBuilder;
      59: aload         4
      61: invokevirtual #84                 // Method java/lang/StringBuilder.append:(Ljava/lang/Object;)Ljava/lang/StringBuilder;
      64: invokevirtual #85                 // Method java/lang/StringBuilder.toString:()Ljava/lang/String;
      67: invokeinterface #86,  2           // InterfaceMethod org/slf4j/Logger.debug:(Ljava/lang/String;)V
      72: ldc           #12                 // String hbase.test.cleaner.delegates
      74: astore        6
      76: aload_3
      77: aload         6
      79: ldc           #49                 // class org/apache/hadoop/hbase/master/cleaner/TestCleanerChore$AlwaysDelete
      81: invokevirtual #14                 // Method java/lang/Class.getName:()Ljava/lang/String;
      84: invokevirtual #15                 // Method org/apache/hadoop/conf/Configuration.set:(Ljava/lang/String;Ljava/lang/String;)V
      87: new           #16                 // class org/apache/hadoop/hbase/master/cleaner/TestCleanerChore$AllValidPaths
      90: dup
      91: ldc           #17                 // String test-file-cleaner
      93: aload_1
      94: aload_3
      95: aload         5
      97: aload         4
      99: aload         6
     101: invokespecial #18                 // Method org/apache/hadoop/hbase/master/cleaner/TestCleanerChore$AllValidPaths."<init>":(Ljava/lang/String;Lorg/apache/hadoop/hbase/Stoppable;Lorg/apache/hadoop/conf/Configuration;Lorg/apache/hadoop/fs/FileSystem;Lorg/apache/hadoop/fs/Path;Ljava/lang/String;)V
     104: astore        7
     106: aload         7
     108: getfield      #54                 // Field org/apache/hadoop/hbase/master/cleaner/TestCleanerChore$AllValidPaths.cleanersChain:Ljava/util/List;
     111: iconst_0
     112: invokeinterface #55,  2           // InterfaceMethod java/util/List.get:(I)Ljava/lang/Object;
     117: checkcast     #49                 // class org/apache/hadoop/hbase/master/cleaner/TestCleanerChore$AlwaysDelete
     120: astore        8
     122: aload         8
     124: invokestatic  #56                 // Method org/mockito/Mockito.spy:(Ljava/lang/Object;)Ljava/lang/Object;
     127: checkcast     #49                 // class org/apache/hadoop/hbase/master/cleaner/TestCleanerChore$AlwaysDelete
     130: astore        9
     132: aload         7
     134: getfield      #54                 // Field org/apache/hadoop/hbase/master/cleaner/TestCleanerChore$AllValidPaths.cleanersChain:Ljava/util/List;
     137: iconst_0
     138: aload         9
     140: invokeinterface #57,  3           // InterfaceMethod java/util/List.set:(ILjava/lang/Object;)Ljava/lang/Object;
     145: pop
     146: new           #19                 // class org/apache/hadoop/fs/Path
     149: dup
     150: aload         4
     152: ldc           #20                 // String parent
     154: invokespecial #21                 // Method org/apache/hadoop/fs/Path."<init>":(Lorg/apache/hadoop/fs/Path;Ljava/lang/String;)V
     157: astore        10
     159: new           #19                 // class org/apache/hadoop/fs/Path
     162: dup
     163: aload         10
     165: ldc           #22                 // String someFile
     167: invokespecial #21                 // Method org/apache/hadoop/fs/Path."<init>":(Lorg/apache/hadoop/fs/Path;Ljava/lang/String;)V
     170: astore        11
     172: aload         5
     174: aload         10
     176: invokevirtual #23                 // Method org/apache/hadoop/fs/FileSystem.mkdirs:(Lorg/apache/hadoop/fs/Path;)Z
     179: pop
     180: aload         5
     182: aload         11
     184: invokevirtual #24                 // Method org/apache/hadoop/fs/FileSystem.create:(Lorg/apache/hadoop/fs/Path;)Lorg/apache/hadoop/fs/FSDataOutputStream;
     187: invokevirtual #25                 // Method org/apache/hadoop/fs/FSDataOutputStream.close:()V
     190: ldc           #26                 // String Test file didn't get created.
     192: aload         5
     194: aload         11
     196: invokevirtual #27                 // Method org/apache/hadoop/fs/FileSystem.exists:(Lorg/apache/hadoop/fs/Path;)Z
     199: invokestatic  #28                 // Method org/junit/Assert.assertTrue:(Ljava/lang/String;Z)V
     202: new           #19                 // class org/apache/hadoop/fs/Path
     205: dup
     206: aload         10
     208: ldc           #67                 // String addedFile
     210: invokespecial #21                 // Method org/apache/hadoop/fs/Path."<init>":(Lorg/apache/hadoop/fs/Path;Ljava/lang/String;)V
     213: astore        12
     215: new           #87                 // class org/apache/hadoop/hbase/master/cleaner/TestCleanerChore$3
     218: dup
     219: aload_0
     220: aload         5
     222: aload         12
     224: aload         4
     226: invokespecial #88                 // Method org/apache/hadoop/hbase/master/cleaner/TestCleanerChore$3."<init>":(Lorg/apache/hadoop/hbase/master/cleaner/TestCleanerChore;Lorg/apache/hadoop/fs/FileSystem;Lorg/apache/hadoop/fs/Path;Lorg/apache/hadoop/fs/Path;)V
     229: invokestatic  #70                 // Method org/mockito/Mockito.doAnswer:(Lorg/mockito/stubbing/Answer;)Lorg/mockito/stubbing/Stubber;
     232: aload         9
     234: invokeinterface #71,  2           // InterfaceMethod org/mockito/stubbing/Stubber.when:(Ljava/lang/Object;)Ljava/lang/Object;
     239: checkcast     #49                 // class org/apache/hadoop/hbase/master/cleaner/TestCleanerChore$AlwaysDelete
     242: invokestatic  #72                 // Method org/mockito/Mockito.any:()Ljava/lang/Object;
     245: checkcast     #73                 // class org/apache/hadoop/fs/FileStatus
     248: invokevirtual #62                 // Method org/apache/hadoop/hbase/master/cleaner/TestCleanerChore$AlwaysDelete.isFileDeletable:(Lorg/apache/hadoop/fs/FileStatus;)Z
     251: pop
     252: aload         7
     254: invokevirtual #29                 // Method org/apache/hadoop/hbase/master/cleaner/TestCleanerChore$AllValidPaths.chore:()V
     257: ldc           #74                 // String Added file unexpectedly deleted
     259: aload         5
     261: aload         12
     263: invokevirtual #27                 // Method org/apache/hadoop/fs/FileSystem.exists:(Lorg/apache/hadoop/fs/Path;)Z
     266: invokestatic  #28                 // Method org/junit/Assert.assertTrue:(Ljava/lang/String;Z)V
     269: ldc           #75                 // String Parent directory deleted unexpectedly
     271: aload         5
     273: aload         10
     275: invokevirtual #27                 // Method org/apache/hadoop/fs/FileSystem.exists:(Lorg/apache/hadoop/fs/Path;)Z
     278: invokestatic  #28                 // Method org/junit/Assert.assertTrue:(Ljava/lang/String;Z)V
     281: ldc           #76                 // String Original file unexpectedly retained
     283: aload         5
     285: aload         11
     287: invokevirtual #27                 // Method org/apache/hadoop/fs/FileSystem.exists:(Lorg/apache/hadoop/fs/Path;)Z
     290: invokestatic  #44                 // Method org/junit/Assert.assertFalse:(Ljava/lang/String;Z)V
     293: aload         9
     295: iconst_1
     296: invokestatic  #77                 // Method org/mockito/Mockito.times:(I)Lorg/mockito/verification/VerificationMode;
     299: invokestatic  #61                 // Method org/mockito/Mockito.verify:(Ljava/lang/Object;Lorg/mockito/verification/VerificationMode;)Ljava/lang/Object;
     302: checkcast     #49                 // class org/apache/hadoop/hbase/master/cleaner/TestCleanerChore$AlwaysDelete
     305: invokestatic  #72                 // Method org/mockito/Mockito.any:()Ljava/lang/Object;
     308: checkcast     #73                 // class org/apache/hadoop/fs/FileStatus
     311: invokevirtual #62                 // Method org/apache/hadoop/hbase/master/cleaner/TestCleanerChore$AlwaysDelete.isFileDeletable:(Lorg/apache/hadoop/fs/FileStatus;)Z
     314: pop
     315: return

  public void testDeleteFileWithCleanerEnabled() throws java.lang.Exception;
    Code:
       0: new           #8                  // class org/apache/hadoop/hbase/util/StoppableImplementation
       3: dup
       4: invokespecial #9                  // Method org/apache/hadoop/hbase/util/StoppableImplementation."<init>":()V
       7: astore_1
       8: getstatic     #3                  // Field UTIL:Lorg/apache/hadoop/hbase/HBaseTestingUtility;
      11: invokevirtual #4                  // Method org/apache/hadoop/hbase/HBaseTestingUtility.getConfiguration:()Lorg/apache/hadoop/conf/Configuration;
      14: astore_2
      15: getstatic     #3                  // Field UTIL:Lorg/apache/hadoop/hbase/HBaseTestingUtility;
      18: invokevirtual #10                 // Method org/apache/hadoop/hbase/HBaseTestingUtility.getDataTestDir:()Lorg/apache/hadoop/fs/Path;
      21: astore_3
      22: getstatic     #3                  // Field UTIL:Lorg/apache/hadoop/hbase/HBaseTestingUtility;
      25: invokevirtual #11                 // Method org/apache/hadoop/hbase/HBaseTestingUtility.getTestFileSystem:()Lorg/apache/hadoop/fs/FileSystem;
      28: astore        4
      30: ldc           #12                 // String hbase.test.cleaner.delegates
      32: astore        5
      34: aload_2
      35: aload         5
      37: ldc           #49                 // class org/apache/hadoop/hbase/master/cleaner/TestCleanerChore$AlwaysDelete
      39: invokevirtual #14                 // Method java/lang/Class.getName:()Ljava/lang/String;
      42: invokevirtual #15                 // Method org/apache/hadoop/conf/Configuration.set:(Ljava/lang/String;Ljava/lang/String;)V
      45: new           #16                 // class org/apache/hadoop/hbase/master/cleaner/TestCleanerChore$AllValidPaths
      48: dup
      49: ldc           #17                 // String test-file-cleaner
      51: aload_1
      52: aload_2
      53: aload         4
      55: aload_3
      56: aload         5
      58: invokespecial #18                 // Method org/apache/hadoop/hbase/master/cleaner/TestCleanerChore$AllValidPaths."<init>":(Ljava/lang/String;Lorg/apache/hadoop/hbase/Stoppable;Lorg/apache/hadoop/conf/Configuration;Lorg/apache/hadoop/fs/FileSystem;Lorg/apache/hadoop/fs/Path;Ljava/lang/String;)V
      61: astore        6
      63: aload         6
      65: iconst_1
      66: invokevirtual #89                 // Method org/apache/hadoop/hbase/master/cleaner/TestCleanerChore$AllValidPaths.setEnabled:(Z)Z
      69: pop
      70: new           #19                 // class org/apache/hadoop/fs/Path
      73: dup
      74: aload_3
      75: ldc           #20                 // String parent
      77: invokespecial #21                 // Method org/apache/hadoop/fs/Path."<init>":(Lorg/apache/hadoop/fs/Path;Ljava/lang/String;)V
      80: astore        7
      82: new           #19                 // class org/apache/hadoop/fs/Path
      85: dup
      86: aload         7
      88: ldc           #32                 // String child
      90: invokespecial #21                 // Method org/apache/hadoop/fs/Path."<init>":(Lorg/apache/hadoop/fs/Path;Ljava/lang/String;)V
      93: astore        8
      95: new           #19                 // class org/apache/hadoop/fs/Path
      98: dup
      99: aload         8
     101: ldc           #22                 // String someFile
     103: invokespecial #21                 // Method org/apache/hadoop/fs/Path."<init>":(Lorg/apache/hadoop/fs/Path;Ljava/lang/String;)V
     106: astore        9
     108: aload         4
     110: aload         8
     112: invokevirtual #23                 // Method org/apache/hadoop/fs/FileSystem.mkdirs:(Lorg/apache/hadoop/fs/Path;)Z
     115: pop
     116: aload         4
     118: aload         9
     120: invokevirtual #24                 // Method org/apache/hadoop/fs/FileSystem.create:(Lorg/apache/hadoop/fs/Path;)Lorg/apache/hadoop/fs/FSDataOutputStream;
     123: invokevirtual #25                 // Method org/apache/hadoop/fs/FSDataOutputStream.close:()V
     126: ldc           #26                 // String Test file didn't get created.
     128: aload         4
     130: aload         9
     132: invokevirtual #27                 // Method org/apache/hadoop/fs/FileSystem.exists:(Lorg/apache/hadoop/fs/Path;)Z
     135: invokestatic  #28                 // Method org/junit/Assert.assertTrue:(Ljava/lang/String;Z)V
     138: aload         6
     140: invokevirtual #29                 // Method org/apache/hadoop/hbase/master/cleaner/TestCleanerChore$AllValidPaths.chore:()V
     143: ldc           #52                 // String File didn't get deleted
     145: aload         4
     147: aload         9
     149: invokevirtual #27                 // Method org/apache/hadoop/fs/FileSystem.exists:(Lorg/apache/hadoop/fs/Path;)Z
     152: invokestatic  #44                 // Method org/junit/Assert.assertFalse:(Ljava/lang/String;Z)V
     155: ldc           #53                 // String Empty directory didn't get deleted
     157: aload         4
     159: aload         8
     161: invokevirtual #27                 // Method org/apache/hadoop/fs/FileSystem.exists:(Lorg/apache/hadoop/fs/Path;)Z
     164: invokestatic  #44                 // Method org/junit/Assert.assertFalse:(Ljava/lang/String;Z)V
     167: ldc           #53                 // String Empty directory didn't get deleted
     169: aload         4
     171: aload         7
     173: invokevirtual #27                 // Method org/apache/hadoop/fs/FileSystem.exists:(Lorg/apache/hadoop/fs/Path;)Z
     176: invokestatic  #44                 // Method org/junit/Assert.assertFalse:(Ljava/lang/String;Z)V
     179: return

  public void testDeleteFileWithCleanerDisabled() throws java.lang.Exception;
    Code:
       0: new           #8                  // class org/apache/hadoop/hbase/util/StoppableImplementation
       3: dup
       4: invokespecial #9                  // Method org/apache/hadoop/hbase/util/StoppableImplementation."<init>":()V
       7: astore_1
       8: getstatic     #3                  // Field UTIL:Lorg/apache/hadoop/hbase/HBaseTestingUtility;
      11: invokevirtual #4                  // Method org/apache/hadoop/hbase/HBaseTestingUtility.getConfiguration:()Lorg/apache/hadoop/conf/Configuration;
      14: astore_2
      15: getstatic     #3                  // Field UTIL:Lorg/apache/hadoop/hbase/HBaseTestingUtility;
      18: invokevirtual #10                 // Method org/apache/hadoop/hbase/HBaseTestingUtility.getDataTestDir:()Lorg/apache/hadoop/fs/Path;
      21: astore_3
      22: getstatic     #3                  // Field UTIL:Lorg/apache/hadoop/hbase/HBaseTestingUtility;
      25: invokevirtual #11                 // Method org/apache/hadoop/hbase/HBaseTestingUtility.getTestFileSystem:()Lorg/apache/hadoop/fs/FileSystem;
      28: astore        4
      30: ldc           #12                 // String hbase.test.cleaner.delegates
      32: astore        5
      34: aload_2
      35: aload         5
      37: ldc           #49                 // class org/apache/hadoop/hbase/master/cleaner/TestCleanerChore$AlwaysDelete
      39: invokevirtual #14                 // Method java/lang/Class.getName:()Ljava/lang/String;
      42: invokevirtual #15                 // Method org/apache/hadoop/conf/Configuration.set:(Ljava/lang/String;Ljava/lang/String;)V
      45: new           #16                 // class org/apache/hadoop/hbase/master/cleaner/TestCleanerChore$AllValidPaths
      48: dup
      49: ldc           #17                 // String test-file-cleaner
      51: aload_1
      52: aload_2
      53: aload         4
      55: aload_3
      56: aload         5
      58: invokespecial #18                 // Method org/apache/hadoop/hbase/master/cleaner/TestCleanerChore$AllValidPaths."<init>":(Ljava/lang/String;Lorg/apache/hadoop/hbase/Stoppable;Lorg/apache/hadoop/conf/Configuration;Lorg/apache/hadoop/fs/FileSystem;Lorg/apache/hadoop/fs/Path;Ljava/lang/String;)V
      61: astore        6
      63: aload         6
      65: iconst_0
      66: invokevirtual #89                 // Method org/apache/hadoop/hbase/master/cleaner/TestCleanerChore$AllValidPaths.setEnabled:(Z)Z
      69: pop
      70: new           #19                 // class org/apache/hadoop/fs/Path
      73: dup
      74: aload_3
      75: ldc           #20                 // String parent
      77: invokespecial #21                 // Method org/apache/hadoop/fs/Path."<init>":(Lorg/apache/hadoop/fs/Path;Ljava/lang/String;)V
      80: astore        7
      82: new           #19                 // class org/apache/hadoop/fs/Path
      85: dup
      86: aload         7
      88: ldc           #32                 // String child
      90: invokespecial #21                 // Method org/apache/hadoop/fs/Path."<init>":(Lorg/apache/hadoop/fs/Path;Ljava/lang/String;)V
      93: astore        8
      95: new           #19                 // class org/apache/hadoop/fs/Path
      98: dup
      99: aload         8
     101: ldc           #22                 // String someFile
     103: invokespecial #21                 // Method org/apache/hadoop/fs/Path."<init>":(Lorg/apache/hadoop/fs/Path;Ljava/lang/String;)V
     106: astore        9
     108: aload         4
     110: aload         8
     112: invokevirtual #23                 // Method org/apache/hadoop/fs/FileSystem.mkdirs:(Lorg/apache/hadoop/fs/Path;)Z
     115: pop
     116: aload         4
     118: aload         9
     120: invokevirtual #24                 // Method org/apache/hadoop/fs/FileSystem.create:(Lorg/apache/hadoop/fs/Path;)Lorg/apache/hadoop/fs/FSDataOutputStream;
     123: invokevirtual #25                 // Method org/apache/hadoop/fs/FSDataOutputStream.close:()V
     126: ldc           #26                 // String Test file didn't get created.
     128: aload         4
     130: aload         9
     132: invokevirtual #27                 // Method org/apache/hadoop/fs/FileSystem.exists:(Lorg/apache/hadoop/fs/Path;)Z
     135: invokestatic  #28                 // Method org/junit/Assert.assertTrue:(Ljava/lang/String;Z)V
     138: aload         6
     140: invokevirtual #29                 // Method org/apache/hadoop/hbase/master/cleaner/TestCleanerChore$AllValidPaths.chore:()V
     143: ldc           #90                 // String File got deleted with cleaner disabled
     145: aload         4
     147: aload         9
     149: invokevirtual #27                 // Method org/apache/hadoop/fs/FileSystem.exists:(Lorg/apache/hadoop/fs/Path;)Z
     152: invokestatic  #28                 // Method org/junit/Assert.assertTrue:(Ljava/lang/String;Z)V
     155: ldc           #91                 // String Directory got deleted
     157: aload         4
     159: aload         8
     161: invokevirtual #27                 // Method org/apache/hadoop/fs/FileSystem.exists:(Lorg/apache/hadoop/fs/Path;)Z
     164: invokestatic  #28                 // Method org/junit/Assert.assertTrue:(Ljava/lang/String;Z)V
     167: ldc           #91                 // String Directory got deleted
     169: aload         4
     171: aload         7
     173: invokevirtual #27                 // Method org/apache/hadoop/fs/FileSystem.exists:(Lorg/apache/hadoop/fs/Path;)Z
     176: invokestatic  #28                 // Method org/junit/Assert.assertTrue:(Ljava/lang/String;Z)V
     179: return

  public void testOnConfigurationChange() throws java.lang.Exception;
    Code:
       0: invokestatic  #92                 // Method java/lang/Runtime.getRuntime:()Ljava/lang/Runtime;
       3: invokevirtual #93                 // Method java/lang/Runtime.availableProcessors:()I
       6: istore_1
       7: iload_1
       8: iconst_1
       9: if_icmpne     13
      12: return
      13: iload_1
      14: iconst_2
      15: idiv
      16: istore_2
      17: iload_1
      18: istore_3
      19: new           #8                  // class org/apache/hadoop/hbase/util/StoppableImplementation
      22: dup
      23: invokespecial #9                  // Method org/apache/hadoop/hbase/util/StoppableImplementation."<init>":()V
      26: astore        4
      28: getstatic     #3                  // Field UTIL:Lorg/apache/hadoop/hbase/HBaseTestingUtility;
      31: invokevirtual #4                  // Method org/apache/hadoop/hbase/HBaseTestingUtility.getConfiguration:()Lorg/apache/hadoop/conf/Configuration;
      34: astore        5
      36: getstatic     #3                  // Field UTIL:Lorg/apache/hadoop/hbase/HBaseTestingUtility;
      39: invokevirtual #10                 // Method org/apache/hadoop/hbase/HBaseTestingUtility.getDataTestDir:()Lorg/apache/hadoop/fs/Path;
      42: astore        6
      44: getstatic     #3                  // Field UTIL:Lorg/apache/hadoop/hbase/HBaseTestingUtility;
      47: invokevirtual #11                 // Method org/apache/hadoop/hbase/HBaseTestingUtility.getTestFileSystem:()Lorg/apache/hadoop/fs/FileSystem;
      50: astore        7
      52: ldc           #12                 // String hbase.test.cleaner.delegates
      54: astore        8
      56: aload         5
      58: aload         8
      60: ldc           #49                 // class org/apache/hadoop/hbase/master/cleaner/TestCleanerChore$AlwaysDelete
      62: invokevirtual #14                 // Method java/lang/Class.getName:()Ljava/lang/String;
      65: invokevirtual #15                 // Method org/apache/hadoop/conf/Configuration.set:(Ljava/lang/String;Ljava/lang/String;)V
      68: aload         5
      70: ldc           #95                 // String hbase.cleaner.scan.dir.concurrent.size
      72: iload_2
      73: invokestatic  #96                 // Method java/lang/String.valueOf:(I)Ljava/lang/String;
      76: invokevirtual #15                 // Method org/apache/hadoop/conf/Configuration.set:(Ljava/lang/String;Ljava/lang/String;)V
      79: new           #16                 // class org/apache/hadoop/hbase/master/cleaner/TestCleanerChore$AllValidPaths
      82: dup
      83: ldc           #17                 // String test-file-cleaner
      85: aload         4
      87: aload         5
      89: aload         7
      91: aload         6
      93: aload         8
      95: invokespecial #18                 // Method org/apache/hadoop/hbase/master/cleaner/TestCleanerChore$AllValidPaths."<init>":(Ljava/lang/String;Lorg/apache/hadoop/hbase/Stoppable;Lorg/apache/hadoop/conf/Configuration;Lorg/apache/hadoop/fs/FileSystem;Lorg/apache/hadoop/fs/Path;Ljava/lang/String;)V
      98: astore        9
     100: aload         9
     102: iconst_1
     103: invokevirtual #89                 // Method org/apache/hadoop/hbase/master/cleaner/TestCleanerChore$AllValidPaths.setEnabled:(Z)Z
     106: pop
     107: bipush        6
     109: istore        10
     111: iload         10
     113: anewarray     #19                 // class org/apache/hadoop/fs/Path
     116: astore        11
     118: iconst_0
     119: istore        12
     121: iload         12
     123: iload         10
     125: if_icmpge     179
     128: aload         11
     130: iload         12
     132: new           #19                 // class org/apache/hadoop/fs/Path
     135: dup
     136: aload         6
     138: new           #80                 // class java/lang/StringBuilder
     141: dup
     142: invokespecial #81                 // Method java/lang/StringBuilder."<init>":()V
     145: ldc           #97                 // String subdir-
     147: invokevirtual #83                 // Method java/lang/StringBuilder.append:(Ljava/lang/String;)Ljava/lang/StringBuilder;
     150: iload         12
     152: invokevirtual #98                 // Method java/lang/StringBuilder.append:(I)Ljava/lang/StringBuilder;
     155: invokevirtual #85                 // Method java/lang/StringBuilder.toString:()Ljava/lang/String;
     158: invokespecial #21                 // Method org/apache/hadoop/fs/Path."<init>":(Lorg/apache/hadoop/fs/Path;Ljava/lang/String;)V
     161: aastore
     162: aload         7
     164: aload         11
     166: iload         12
     168: aaload
     169: invokevirtual #23                 // Method org/apache/hadoop/fs/FileSystem.mkdirs:(Lorg/apache/hadoop/fs/Path;)Z
     172: pop
     173: iinc          12, 1
     176: goto          121
     179: aload         11
     181: astore        12
     183: aload         12
     185: arraylength
     186: istore        13
     188: iconst_0
     189: istore        14
     191: iload         14
     193: iload         13
     195: if_icmpge     221
     198: aload         12
     200: iload         14
     202: aaload
     203: astore        15
     205: aload_0
     206: aload         7
     208: aload         15
     210: bipush        6
     212: invokespecial #99                 // Method createFiles:(Lorg/apache/hadoop/fs/FileSystem;Lorg/apache/hadoop/fs/Path;I)V
     215: iinc          14, 1
     218: goto          191
     221: new           #100                // class java/lang/Thread
     224: dup
     225: aload         9
     227: invokedynamic #101,  0            // InvokeDynamic #0:run:(Lorg/apache/hadoop/hbase/master/cleaner/TestCleanerChore$AllValidPaths;)Ljava/lang/Runnable;
     232: invokespecial #102                // Method java/lang/Thread."<init>":(Ljava/lang/Runnable;)V
     235: astore        12
     237: aload         12
     239: iconst_1
     240: invokevirtual #103                // Method java/lang/Thread.setDaemon:(Z)V
     243: aload         12
     245: invokevirtual #104                // Method java/lang/Thread.start:()V
     248: aload         5
     250: ldc           #95                 // String hbase.cleaner.scan.dir.concurrent.size
     252: iload_3
     253: invokestatic  #96                 // Method java/lang/String.valueOf:(I)Ljava/lang/String;
     256: invokevirtual #15                 // Method org/apache/hadoop/conf/Configuration.set:(Ljava/lang/String;Ljava/lang/String;)V
     259: aload         9
     261: aload         5
     263: invokevirtual #105                // Method org/apache/hadoop/hbase/master/cleaner/TestCleanerChore$AllValidPaths.onConfigurationChange:(Lorg/apache/hadoop/conf/Configuration;)V
     266: iload_3
     267: i2l
     268: aload         9
     270: invokevirtual #106                // Method org/apache/hadoop/hbase/master/cleaner/TestCleanerChore$AllValidPaths.getChorePoolSize:()I
     273: i2l
     274: invokestatic  #107                // Method org/junit/Assert.assertEquals:(JJ)V
     277: aload         12
     279: invokevirtual #108                // Method java/lang/Thread.join:()V
     282: return

  public void testMinimumNumberOfThreads() throws java.lang.Exception;
    Code:
       0: new           #8                  // class org/apache/hadoop/hbase/util/StoppableImplementation
       3: dup
       4: invokespecial #9                  // Method org/apache/hadoop/hbase/util/StoppableImplementation."<init>":()V
       7: astore_1
       8: getstatic     #3                  // Field UTIL:Lorg/apache/hadoop/hbase/HBaseTestingUtility;
      11: invokevirtual #4                  // Method org/apache/hadoop/hbase/HBaseTestingUtility.getConfiguration:()Lorg/apache/hadoop/conf/Configuration;
      14: astore_2
      15: getstatic     #3                  // Field UTIL:Lorg/apache/hadoop/hbase/HBaseTestingUtility;
      18: invokevirtual #10                 // Method org/apache/hadoop/hbase/HBaseTestingUtility.getDataTestDir:()Lorg/apache/hadoop/fs/Path;
      21: astore_3
      22: getstatic     #3                  // Field UTIL:Lorg/apache/hadoop/hbase/HBaseTestingUtility;
      25: invokevirtual #11                 // Method org/apache/hadoop/hbase/HBaseTestingUtility.getTestFileSystem:()Lorg/apache/hadoop/fs/FileSystem;
      28: astore        4
      30: ldc           #12                 // String hbase.test.cleaner.delegates
      32: astore        5
      34: aload_2
      35: aload         5
      37: ldc           #49                 // class org/apache/hadoop/hbase/master/cleaner/TestCleanerChore$AlwaysDelete
      39: invokevirtual #14                 // Method java/lang/Class.getName:()Ljava/lang/String;
      42: invokevirtual #15                 // Method org/apache/hadoop/conf/Configuration.set:(Ljava/lang/String;Ljava/lang/String;)V
      45: aload_2
      46: ldc           #95                 // String hbase.cleaner.scan.dir.concurrent.size
      48: ldc           #109                // String 2
      50: invokevirtual #15                 // Method org/apache/hadoop/conf/Configuration.set:(Ljava/lang/String;Ljava/lang/String;)V
      53: new           #16                 // class org/apache/hadoop/hbase/master/cleaner/TestCleanerChore$AllValidPaths
      56: dup
      57: ldc           #17                 // String test-file-cleaner
      59: aload_1
      60: aload_2
      61: aload         4
      63: aload_3
      64: aload         5
      66: invokespecial #18                 // Method org/apache/hadoop/hbase/master/cleaner/TestCleanerChore$AllValidPaths."<init>":(Ljava/lang/String;Lorg/apache/hadoop/hbase/Stoppable;Lorg/apache/hadoop/conf/Configuration;Lorg/apache/hadoop/fs/FileSystem;Lorg/apache/hadoop/fs/Path;Ljava/lang/String;)V
      69: astore        6
      71: invokestatic  #92                 // Method java/lang/Runtime.getRuntime:()Ljava/lang/Runtime;
      74: invokevirtual #93                 // Method java/lang/Runtime.availableProcessors:()I
      77: istore        7
      79: iload         7
      81: i2l
      82: aload         6
      84: pop
      85: iload         7
      87: invokestatic  #110                // Method java/lang/Integer.toString:(I)Ljava/lang/String;
      90: invokestatic  #111                // Method org/apache/hadoop/hbase/master/cleaner/TestCleanerChore$AllValidPaths.calculatePoolSize:(Ljava/lang/String;)I
      93: i2l
      94: invokestatic  #107                // Method org/junit/Assert.assertEquals:(JJ)V
      97: iload         7
      99: i2l
     100: aload         6
     102: pop
     103: iload         7
     105: iconst_2
     106: iadd
     107: invokestatic  #110                // Method java/lang/Integer.toString:(I)Ljava/lang/String;
     110: invokestatic  #111                // Method org/apache/hadoop/hbase/master/cleaner/TestCleanerChore$AllValidPaths.calculatePoolSize:(Ljava/lang/String;)I
     113: i2l
     114: invokestatic  #107                // Method org/junit/Assert.assertEquals:(JJ)V
     117: lconst_1
     118: aload         6
     120: pop
     121: ldc           #112                // String 0.0
     123: invokestatic  #111                // Method org/apache/hadoop/hbase/master/cleaner/TestCleanerChore$AllValidPaths.calculatePoolSize:(Ljava/lang/String;)I
     126: i2l
     127: invokestatic  #107                // Method org/junit/Assert.assertEquals:(JJ)V
     130: return

  static org.slf4j.Logger access$000();
    Code:
       0: getstatic     #1                  // Field LOG:Lorg/slf4j/Logger;
       3: areturn

  static {};
    Code:
       0: ldc           #122                // class org/apache/hadoop/hbase/master/cleaner/TestCleanerChore
       2: invokestatic  #123                // Method org/apache/hadoop/hbase/HBaseClassTestRule.forClass:(Ljava/lang/Class;)Lorg/apache/hadoop/hbase/HBaseClassTestRule;
       5: putstatic     #124                // Field CLASS_RULE:Lorg/apache/hadoop/hbase/HBaseClassTestRule;
       8: ldc           #122                // class org/apache/hadoop/hbase/master/cleaner/TestCleanerChore
      10: invokestatic  #125                // Method org/slf4j/LoggerFactory.getLogger:(Ljava/lang/Class;)Lorg/slf4j/Logger;
      13: putstatic     #1                  // Field LOG:Lorg/slf4j/Logger;
      16: new           #78                 // class org/apache/hadoop/hbase/HBaseTestingUtility
      19: dup
      20: invokespecial #79                 // Method org/apache/hadoop/hbase/HBaseTestingUtility."<init>":()V
      23: putstatic     #3                  // Field UTIL:Lorg/apache/hadoop/hbase/HBaseTestingUtility;
      26: return
}
