Compiled from "TestConnectionCache.java"
public class org.apache.hadoop.hbase.util.TestConnectionCache extends junit.framework.TestCase {
  public static final org.apache.hadoop.hbase.HBaseClassTestRule CLASS_RULE;

  public org.apache.hadoop.hbase.util.TestConnectionCache();
    Code:
       0: aload_0
       1: invokespecial #1                  // Method junit/framework/TestCase."<init>":()V
       4: return

  public void testConnectionChore() throws java.lang.Exception;
    Code:
       0: getstatic     #2                  // Field UTIL:Lorg/apache/hadoop/hbase/HBaseTestingUtility;
       3: invokevirtual #3                  // Method org/apache/hadoop/hbase/HBaseTestingUtility.startMiniCluster:()Lorg/apache/hadoop/hbase/MiniHBaseCluster;
       6: pop
       7: new           #4                  // class org/apache/hadoop/hbase/util/ConnectionCache
      10: dup
      11: getstatic     #2                  // Field UTIL:Lorg/apache/hadoop/hbase/HBaseTestingUtility;
      14: invokevirtual #5                  // Method org/apache/hadoop/hbase/HBaseTestingUtility.getConfiguration:()Lorg/apache/hadoop/conf/Configuration;
      17: getstatic     #2                  // Field UTIL:Lorg/apache/hadoop/hbase/HBaseTestingUtility;
      20: invokevirtual #5                  // Method org/apache/hadoop/hbase/HBaseTestingUtility.getConfiguration:()Lorg/apache/hadoop/conf/Configuration;
      23: invokestatic  #6                  // Method org/apache/hadoop/hbase/security/UserProvider.instantiate:(Lorg/apache/hadoop/conf/Configuration;)Lorg/apache/hadoop/hbase/security/UserProvider;
      26: sipush        1000
      29: sipush        5000
      32: invokespecial #7                  // Method org/apache/hadoop/hbase/util/ConnectionCache."<init>":(Lorg/apache/hadoop/conf/Configuration;Lorg/apache/hadoop/hbase/security/UserProvider;II)V
      35: astore_1
      36: aload_1
      37: invokevirtual #8                  // Method org/apache/hadoop/hbase/util/ConnectionCache.getCurrentConnection:()Lorg/apache/hadoop/hbase/util/ConnectionCache$ConnectionInfo;
      40: astore_2
      41: iconst_0
      42: aload_2
      43: getfield      #9                  // Field org/apache/hadoop/hbase/util/ConnectionCache$ConnectionInfo.connection:Lorg/apache/hadoop/hbase/client/Connection;
      46: invokeinterface #10,  1           // InterfaceMethod org/apache/hadoop/hbase/client/Connection.isClosed:()Z
      51: invokestatic  #11                 // Method assertEquals:(ZZ)V
      54: ldc2_w        #12                 // long 7000l
      57: invokestatic  #14                 // Method java/lang/Thread.sleep:(J)V
      60: iconst_1
      61: aload_2
      62: getfield      #9                  // Field org/apache/hadoop/hbase/util/ConnectionCache$ConnectionInfo.connection:Lorg/apache/hadoop/hbase/client/Connection;
      65: invokeinterface #10,  1           // InterfaceMethod org/apache/hadoop/hbase/client/Connection.isClosed:()Z
      70: invokestatic  #11                 // Method assertEquals:(ZZ)V
      73: getstatic     #2                  // Field UTIL:Lorg/apache/hadoop/hbase/HBaseTestingUtility;
      76: invokevirtual #15                 // Method org/apache/hadoop/hbase/HBaseTestingUtility.shutdownMiniCluster:()V
      79: return

  static {};
    Code:
       0: ldc           #16                 // class org/apache/hadoop/hbase/util/TestConnectionCache
       2: invokestatic  #17                 // Method org/apache/hadoop/hbase/HBaseClassTestRule.forClass:(Ljava/lang/Class;)Lorg/apache/hadoop/hbase/HBaseClassTestRule;
       5: putstatic     #18                 // Field CLASS_RULE:Lorg/apache/hadoop/hbase/HBaseClassTestRule;
       8: new           #19                 // class org/apache/hadoop/hbase/HBaseTestingUtility
      11: dup
      12: invokespecial #20                 // Method org/apache/hadoop/hbase/HBaseTestingUtility."<init>":()V
      15: putstatic     #2                  // Field UTIL:Lorg/apache/hadoop/hbase/HBaseTestingUtility;
      18: return
}
