Compiled from "TestBlockEvictionFromClient.java"
class org.apache.hadoop.hbase.client.TestBlockEvictionFromClient$MultiGetThread extends java.lang.Thread {
  public org.apache.hadoop.hbase.client.TestBlockEvictionFromClient$MultiGetThread(org.apache.hadoop.hbase.client.Table);
    Code:
       0: aload_0
       1: invokespecial #1                  // Method java/lang/Thread."<init>":()V
       4: aload_0
       5: new           #2                  // class java/util/ArrayList
       8: dup
       9: invokespecial #3                  // Method java/util/ArrayList."<init>":()V
      12: putfield      #4                  // Field gets:Ljava/util/List;
      15: aload_0
      16: aload_1
      17: putfield      #5                  // Field table:Lorg/apache/hadoop/hbase/client/Table;
      20: return

  public void run();
    Code:
       0: aload_0
       1: getfield      #4                  // Field gets:Ljava/util/List;
       4: new           #6                  // class org/apache/hadoop/hbase/client/Get
       7: dup
       8: invokestatic  #7                  // Method org/apache/hadoop/hbase/client/TestBlockEvictionFromClient.access$000:()[B
      11: invokespecial #8                  // Method org/apache/hadoop/hbase/client/Get."<init>":([B)V
      14: invokeinterface #9,  2            // InterfaceMethod java/util/List.add:(Ljava/lang/Object;)Z
      19: pop
      20: aload_0
      21: getfield      #4                  // Field gets:Ljava/util/List;
      24: new           #6                  // class org/apache/hadoop/hbase/client/Get
      27: dup
      28: invokestatic  #10                 // Method org/apache/hadoop/hbase/client/TestBlockEvictionFromClient.access$100:()[B
      31: invokespecial #8                  // Method org/apache/hadoop/hbase/client/Get."<init>":([B)V
      34: invokeinterface #9,  2            // InterfaceMethod java/util/List.add:(Ljava/lang/Object;)Z
      39: pop
      40: invokestatic  #11                 // Method org/apache/hadoop/hbase/client/TestBlockEvictionFromClient$CustomInnerRegionObserver.getCdl:()Ljava/util/concurrent/atomic/AtomicReference;
      43: invokestatic  #12                 // Method org/apache/hadoop/hbase/client/TestBlockEvictionFromClient.access$200:()Ljava/util/concurrent/CountDownLatch;
      46: invokevirtual #13                 // Method java/util/concurrent/atomic/AtomicReference.set:(Ljava/lang/Object;)V
      49: aload_0
      50: getfield      #5                  // Field table:Lorg/apache/hadoop/hbase/client/Table;
      53: aload_0
      54: getfield      #4                  // Field gets:Ljava/util/List;
      57: invokeinterface #14,  2           // InterfaceMethod org/apache/hadoop/hbase/client/Table.get:(Ljava/util/List;)[Lorg/apache/hadoop/hbase/client/Result;
      62: astore_1
      63: aload_1
      64: iconst_0
      65: aaload
      66: invokevirtual #15                 // Method org/apache/hadoop/hbase/client/Result.getRow:()[B
      69: invokestatic  #7                  // Method org/apache/hadoop/hbase/client/TestBlockEvictionFromClient.access$000:()[B
      72: invokestatic  #16                 // Method org/apache/hadoop/hbase/util/Bytes.equals:([B[B)Z
      75: invokestatic  #17                 // Method org/junit/Assert.assertTrue:(Z)V
      78: aload_1
      79: iconst_1
      80: aaload
      81: invokevirtual #15                 // Method org/apache/hadoop/hbase/client/Result.getRow:()[B
      84: invokestatic  #10                 // Method org/apache/hadoop/hbase/client/TestBlockEvictionFromClient.access$100:()[B
      87: invokestatic  #16                 // Method org/apache/hadoop/hbase/util/Bytes.equals:([B[B)Z
      90: invokestatic  #17                 // Method org/junit/Assert.assertTrue:(Z)V
      93: goto          97
      96: astore_1
      97: return
    Exception table:
       from    to  target type
          40    93    96   Class java/io/IOException
}
