Compiled from "TestFirstKeyValueMatchingQualifiersFilter.java"
public class org.apache.hadoop.hbase.filter.TestFirstKeyValueMatchingQualifiersFilter extends junit.framework.TestCase {
  public static final org.apache.hadoop.hbase.HBaseClassTestRule CLASS_RULE;

  public org.apache.hadoop.hbase.filter.TestFirstKeyValueMatchingQualifiersFilter();
    Code:
       0: aload_0
       1: invokespecial #1                  // Method junit/framework/TestCase."<init>":()V
       4: return

  public void testFirstKeyMatchingQualifierFilter() throws java.lang.Exception;
    Code:
       0: new           #2                  // class java/util/TreeSet
       3: dup
       4: getstatic     #3                  // Field org/apache/hadoop/hbase/util/Bytes.BYTES_COMPARATOR:Ljava/util/Comparator;
       7: invokespecial #4                  // Method java/util/TreeSet."<init>":(Ljava/util/Comparator;)V
      10: astore_1
      11: aload_1
      12: getstatic     #5                  // Field COLUMN_QUALIFIER_1:[B
      15: invokeinterface #6,  2            // InterfaceMethod java/util/Set.add:(Ljava/lang/Object;)Z
      20: pop
      21: aload_1
      22: getstatic     #7                  // Field COLUMN_QUALIFIER_2:[B
      25: invokeinterface #6,  2            // InterfaceMethod java/util/Set.add:(Ljava/lang/Object;)Z
      30: pop
      31: new           #8                  // class org/apache/hadoop/hbase/filter/FirstKeyValueMatchingQualifiersFilter
      34: dup
      35: aload_1
      36: invokespecial #9                  // Method org/apache/hadoop/hbase/filter/FirstKeyValueMatchingQualifiersFilter."<init>":(Ljava/util/Set;)V
      39: astore_2
      40: new           #10                 // class org/apache/hadoop/hbase/KeyValue
      43: dup
      44: getstatic     #11                 // Field ROW:[B
      47: getstatic     #12                 // Field COLUMN_FAMILY:[B
      50: getstatic     #5                  // Field COLUMN_QUALIFIER_1:[B
      53: getstatic     #13                 // Field VAL_1:[B
      56: invokespecial #14                 // Method org/apache/hadoop/hbase/KeyValue."<init>":([B[B[B[B)V
      59: astore_3
      60: ldc           #15                 // String includeAndSetFlag
      62: aload_2
      63: aload_3
      64: invokevirtual #16                 // Method org/apache/hadoop/hbase/filter/Filter.filterCell:(Lorg/apache/hadoop/hbase/Cell;)Lorg/apache/hadoop/hbase/filter/Filter$ReturnCode;
      67: getstatic     #17                 // Field org/apache/hadoop/hbase/filter/Filter$ReturnCode.INCLUDE:Lorg/apache/hadoop/hbase/filter/Filter$ReturnCode;
      70: if_acmpne     77
      73: iconst_1
      74: goto          78
      77: iconst_0
      78: invokestatic  #18                 // Method assertTrue:(Ljava/lang/String;Z)V
      81: new           #10                 // class org/apache/hadoop/hbase/KeyValue
      84: dup
      85: getstatic     #11                 // Field ROW:[B
      88: getstatic     #12                 // Field COLUMN_FAMILY:[B
      91: getstatic     #7                  // Field COLUMN_QUALIFIER_2:[B
      94: getstatic     #13                 // Field VAL_1:[B
      97: invokespecial #14                 // Method org/apache/hadoop/hbase/KeyValue."<init>":([B[B[B[B)V
     100: astore_3
     101: ldc           #19                 // String flagIsSetSkipToNextRow
     103: aload_2
     104: aload_3
     105: invokevirtual #16                 // Method org/apache/hadoop/hbase/filter/Filter.filterCell:(Lorg/apache/hadoop/hbase/Cell;)Lorg/apache/hadoop/hbase/filter/Filter$ReturnCode;
     108: getstatic     #20                 // Field org/apache/hadoop/hbase/filter/Filter$ReturnCode.NEXT_ROW:Lorg/apache/hadoop/hbase/filter/Filter$ReturnCode;
     111: if_acmpne     118
     114: iconst_1
     115: goto          119
     118: iconst_0
     119: invokestatic  #18                 // Method assertTrue:(Ljava/lang/String;Z)V
     122: aload_2
     123: invokevirtual #21                 // Method org/apache/hadoop/hbase/filter/Filter.reset:()V
     126: new           #10                 // class org/apache/hadoop/hbase/KeyValue
     129: dup
     130: getstatic     #11                 // Field ROW:[B
     133: getstatic     #12                 // Field COLUMN_FAMILY:[B
     136: getstatic     #22                 // Field COLUMN_QUALIFIER_3:[B
     139: getstatic     #13                 // Field VAL_1:[B
     142: invokespecial #14                 // Method org/apache/hadoop/hbase/KeyValue."<init>":([B[B[B[B)V
     145: astore_3
     146: getstatic     #23                 // Field java/lang/System.out:Ljava/io/PrintStream;
     149: aload_2
     150: aload_3
     151: invokevirtual #16                 // Method org/apache/hadoop/hbase/filter/Filter.filterCell:(Lorg/apache/hadoop/hbase/Cell;)Lorg/apache/hadoop/hbase/filter/Filter$ReturnCode;
     154: invokevirtual #24                 // Method java/io/PrintStream.println:(Ljava/lang/Object;)V
     157: ldc           #25                 // String includeFlagIsUnset
     159: aload_2
     160: aload_3
     161: invokevirtual #16                 // Method org/apache/hadoop/hbase/filter/Filter.filterCell:(Lorg/apache/hadoop/hbase/Cell;)Lorg/apache/hadoop/hbase/filter/Filter$ReturnCode;
     164: getstatic     #17                 // Field org/apache/hadoop/hbase/filter/Filter$ReturnCode.INCLUDE:Lorg/apache/hadoop/hbase/filter/Filter$ReturnCode;
     167: if_acmpne     174
     170: iconst_1
     171: goto          175
     174: iconst_0
     175: invokestatic  #18                 // Method assertTrue:(Ljava/lang/String;Z)V
     178: new           #10                 // class org/apache/hadoop/hbase/KeyValue
     181: dup
     182: getstatic     #11                 // Field ROW:[B
     185: getstatic     #12                 // Field COLUMN_FAMILY:[B
     188: getstatic     #7                  // Field COLUMN_QUALIFIER_2:[B
     191: getstatic     #13                 // Field VAL_1:[B
     194: invokespecial #14                 // Method org/apache/hadoop/hbase/KeyValue."<init>":([B[B[B[B)V
     197: astore_3
     198: ldc           #15                 // String includeAndSetFlag
     200: aload_2
     201: aload_3
     202: invokevirtual #16                 // Method org/apache/hadoop/hbase/filter/Filter.filterCell:(Lorg/apache/hadoop/hbase/Cell;)Lorg/apache/hadoop/hbase/filter/Filter$ReturnCode;
     205: getstatic     #17                 // Field org/apache/hadoop/hbase/filter/Filter$ReturnCode.INCLUDE:Lorg/apache/hadoop/hbase/filter/Filter$ReturnCode;
     208: if_acmpne     215
     211: iconst_1
     212: goto          216
     215: iconst_0
     216: invokestatic  #18                 // Method assertTrue:(Ljava/lang/String;Z)V
     219: new           #10                 // class org/apache/hadoop/hbase/KeyValue
     222: dup
     223: getstatic     #11                 // Field ROW:[B
     226: getstatic     #12                 // Field COLUMN_FAMILY:[B
     229: getstatic     #5                  // Field COLUMN_QUALIFIER_1:[B
     232: getstatic     #13                 // Field VAL_1:[B
     235: invokespecial #14                 // Method org/apache/hadoop/hbase/KeyValue."<init>":([B[B[B[B)V
     238: astore_3
     239: ldc           #19                 // String flagIsSetSkipToNextRow
     241: aload_2
     242: aload_3
     243: invokevirtual #16                 // Method org/apache/hadoop/hbase/filter/Filter.filterCell:(Lorg/apache/hadoop/hbase/Cell;)Lorg/apache/hadoop/hbase/filter/Filter$ReturnCode;
     246: getstatic     #20                 // Field org/apache/hadoop/hbase/filter/Filter$ReturnCode.NEXT_ROW:Lorg/apache/hadoop/hbase/filter/Filter$ReturnCode;
     249: if_acmpne     256
     252: iconst_1
     253: goto          257
     256: iconst_0
     257: invokestatic  #18                 // Method assertTrue:(Ljava/lang/String;Z)V
     260: return

  static {};
    Code:
       0: ldc           #26                 // class org/apache/hadoop/hbase/filter/TestFirstKeyValueMatchingQualifiersFilter
       2: invokestatic  #27                 // Method org/apache/hadoop/hbase/HBaseClassTestRule.forClass:(Ljava/lang/Class;)Lorg/apache/hadoop/hbase/HBaseClassTestRule;
       5: putstatic     #28                 // Field CLASS_RULE:Lorg/apache/hadoop/hbase/HBaseClassTestRule;
       8: ldc           #29                 // String test
      10: invokestatic  #30                 // Method org/apache/hadoop/hbase/util/Bytes.toBytes:(Ljava/lang/String;)[B
      13: putstatic     #11                 // Field ROW:[B
      16: ldc           #29                 // String test
      18: invokestatic  #30                 // Method org/apache/hadoop/hbase/util/Bytes.toBytes:(Ljava/lang/String;)[B
      21: putstatic     #12                 // Field COLUMN_FAMILY:[B
      24: ldc           #31                 // String foo
      26: invokestatic  #30                 // Method org/apache/hadoop/hbase/util/Bytes.toBytes:(Ljava/lang/String;)[B
      29: putstatic     #5                  // Field COLUMN_QUALIFIER_1:[B
      32: ldc           #32                 // String foo_2
      34: invokestatic  #30                 // Method org/apache/hadoop/hbase/util/Bytes.toBytes:(Ljava/lang/String;)[B
      37: putstatic     #7                  // Field COLUMN_QUALIFIER_2:[B
      40: ldc           #33                 // String foo_3
      42: invokestatic  #30                 // Method org/apache/hadoop/hbase/util/Bytes.toBytes:(Ljava/lang/String;)[B
      45: putstatic     #22                 // Field COLUMN_QUALIFIER_3:[B
      48: ldc           #34                 // String a
      50: invokestatic  #30                 // Method org/apache/hadoop/hbase/util/Bytes.toBytes:(Ljava/lang/String;)[B
      53: putstatic     #13                 // Field VAL_1:[B
      56: return
}
