Compiled from "TestRegionLocations.java"
public class org.apache.hadoop.hbase.TestRegionLocations {
  public static final org.apache.hadoop.hbase.HBaseClassTestRule CLASS_RULE;

  org.apache.hadoop.hbase.ServerName sn0;

  org.apache.hadoop.hbase.ServerName sn1;

  org.apache.hadoop.hbase.ServerName sn2;

  org.apache.hadoop.hbase.ServerName sn3;

  org.apache.hadoop.hbase.HRegionInfo info0;

  org.apache.hadoop.hbase.HRegionInfo info1;

  org.apache.hadoop.hbase.HRegionInfo info2;

  org.apache.hadoop.hbase.HRegionInfo info9;

  long regionId1;

  long regionId2;

  public org.apache.hadoop.hbase.TestRegionLocations();
    Code:
       0: aload_0
       1: invokespecial #1                  // Method java/lang/Object."<init>":()V
       4: aload_0
       5: ldc           #2                  // String host0
       7: bipush        10
       9: ldc2_w        #3                  // long 10l
      12: invokestatic  #5                  // Method org/apache/hadoop/hbase/ServerName.valueOf:(Ljava/lang/String;IJ)Lorg/apache/hadoop/hbase/ServerName;
      15: putfield      #6                  // Field sn0:Lorg/apache/hadoop/hbase/ServerName;
      18: aload_0
      19: ldc           #7                  // String host1
      21: bipush        10
      23: ldc2_w        #3                  // long 10l
      26: invokestatic  #5                  // Method org/apache/hadoop/hbase/ServerName.valueOf:(Ljava/lang/String;IJ)Lorg/apache/hadoop/hbase/ServerName;
      29: putfield      #8                  // Field sn1:Lorg/apache/hadoop/hbase/ServerName;
      32: aload_0
      33: ldc           #9                  // String host2
      35: bipush        10
      37: ldc2_w        #3                  // long 10l
      40: invokestatic  #5                  // Method org/apache/hadoop/hbase/ServerName.valueOf:(Ljava/lang/String;IJ)Lorg/apache/hadoop/hbase/ServerName;
      43: putfield      #10                 // Field sn2:Lorg/apache/hadoop/hbase/ServerName;
      46: aload_0
      47: ldc           #11                 // String host3
      49: bipush        10
      51: ldc2_w        #3                  // long 10l
      54: invokestatic  #5                  // Method org/apache/hadoop/hbase/ServerName.valueOf:(Ljava/lang/String;IJ)Lorg/apache/hadoop/hbase/ServerName;
      57: putfield      #12                 // Field sn3:Lorg/apache/hadoop/hbase/ServerName;
      60: aload_0
      61: aload_0
      62: iconst_0
      63: invokespecial #13                 // Method hri:(I)Lorg/apache/hadoop/hbase/HRegionInfo;
      66: putfield      #14                 // Field info0:Lorg/apache/hadoop/hbase/HRegionInfo;
      69: aload_0
      70: aload_0
      71: iconst_1
      72: invokespecial #13                 // Method hri:(I)Lorg/apache/hadoop/hbase/HRegionInfo;
      75: putfield      #15                 // Field info1:Lorg/apache/hadoop/hbase/HRegionInfo;
      78: aload_0
      79: aload_0
      80: iconst_2
      81: invokespecial #13                 // Method hri:(I)Lorg/apache/hadoop/hbase/HRegionInfo;
      84: putfield      #16                 // Field info2:Lorg/apache/hadoop/hbase/HRegionInfo;
      87: aload_0
      88: aload_0
      89: bipush        9
      91: invokespecial #13                 // Method hri:(I)Lorg/apache/hadoop/hbase/HRegionInfo;
      94: putfield      #17                 // Field info9:Lorg/apache/hadoop/hbase/HRegionInfo;
      97: aload_0
      98: ldc2_w        #18                 // long 1000l
     101: putfield      #20                 // Field regionId1:J
     104: aload_0
     105: ldc2_w        #21                 // long 2000l
     108: putfield      #23                 // Field regionId2:J
     111: return

  public void testSizeMethods();
    Code:
       0: new           #24                 // class org/apache/hadoop/hbase/RegionLocations
       3: dup
       4: iconst_0
       5: anewarray     #25                 // class org/apache/hadoop/hbase/HRegionLocation
       8: invokespecial #26                 // Method org/apache/hadoop/hbase/RegionLocations."<init>":([Lorg/apache/hadoop/hbase/HRegionLocation;)V
      11: astore_1
      12: aload_1
      13: invokevirtual #27                 // Method org/apache/hadoop/hbase/RegionLocations.isEmpty:()Z
      16: invokestatic  #28                 // Method org/junit/Assert.assertTrue:(Z)V
      19: lconst_0
      20: aload_1
      21: invokevirtual #29                 // Method org/apache/hadoop/hbase/RegionLocations.size:()I
      24: i2l
      25: invokestatic  #30                 // Method org/junit/Assert.assertEquals:(JJ)V
      28: lconst_0
      29: aload_1
      30: invokevirtual #31                 // Method org/apache/hadoop/hbase/RegionLocations.numNonNullElements:()I
      33: i2l
      34: invokestatic  #30                 // Method org/junit/Assert.assertEquals:(JJ)V
      37: aload_0
      38: iconst_1
      39: anewarray     #25                 // class org/apache/hadoop/hbase/HRegionLocation
      42: dup
      43: iconst_0
      44: aconst_null
      45: checkcast     #25                 // class org/apache/hadoop/hbase/HRegionLocation
      48: aastore
      49: invokespecial #32                 // Method hrll:([Lorg/apache/hadoop/hbase/HRegionLocation;)Lorg/apache/hadoop/hbase/RegionLocations;
      52: astore_1
      53: aload_1
      54: invokevirtual #27                 // Method org/apache/hadoop/hbase/RegionLocations.isEmpty:()Z
      57: invokestatic  #28                 // Method org/junit/Assert.assertTrue:(Z)V
      60: lconst_1
      61: aload_1
      62: invokevirtual #29                 // Method org/apache/hadoop/hbase/RegionLocations.size:()I
      65: i2l
      66: invokestatic  #30                 // Method org/junit/Assert.assertEquals:(JJ)V
      69: lconst_0
      70: aload_1
      71: invokevirtual #31                 // Method org/apache/hadoop/hbase/RegionLocations.numNonNullElements:()I
      74: i2l
      75: invokestatic  #30                 // Method org/junit/Assert.assertEquals:(JJ)V
      78: aload_0
      79: iconst_0
      80: invokespecial #13                 // Method hri:(I)Lorg/apache/hadoop/hbase/HRegionInfo;
      83: astore_2
      84: aload_0
      85: iconst_1
      86: anewarray     #25                 // class org/apache/hadoop/hbase/HRegionLocation
      89: dup
      90: iconst_0
      91: aload_0
      92: aload_2
      93: aconst_null
      94: invokespecial #33                 // Method hrl:(Lorg/apache/hadoop/hbase/HRegionInfo;Lorg/apache/hadoop/hbase/ServerName;)Lorg/apache/hadoop/hbase/HRegionLocation;
      97: aastore
      98: invokespecial #32                 // Method hrll:([Lorg/apache/hadoop/hbase/HRegionLocation;)Lorg/apache/hadoop/hbase/RegionLocations;
     101: astore_1
     102: aload_1
     103: invokevirtual #27                 // Method org/apache/hadoop/hbase/RegionLocations.isEmpty:()Z
     106: invokestatic  #28                 // Method org/junit/Assert.assertTrue:(Z)V
     109: lconst_1
     110: aload_1
     111: invokevirtual #29                 // Method org/apache/hadoop/hbase/RegionLocations.size:()I
     114: i2l
     115: invokestatic  #30                 // Method org/junit/Assert.assertEquals:(JJ)V
     118: lconst_0
     119: aload_1
     120: invokevirtual #31                 // Method org/apache/hadoop/hbase/RegionLocations.numNonNullElements:()I
     123: i2l
     124: invokestatic  #30                 // Method org/junit/Assert.assertEquals:(JJ)V
     127: aload_0
     128: bipush        9
     130: invokespecial #13                 // Method hri:(I)Lorg/apache/hadoop/hbase/HRegionInfo;
     133: astore_3
     134: aload_0
     135: iconst_1
     136: anewarray     #25                 // class org/apache/hadoop/hbase/HRegionLocation
     139: dup
     140: iconst_0
     141: aload_0
     142: aload_3
     143: aconst_null
     144: invokespecial #33                 // Method hrl:(Lorg/apache/hadoop/hbase/HRegionInfo;Lorg/apache/hadoop/hbase/ServerName;)Lorg/apache/hadoop/hbase/HRegionLocation;
     147: aastore
     148: invokespecial #32                 // Method hrll:([Lorg/apache/hadoop/hbase/HRegionLocation;)Lorg/apache/hadoop/hbase/RegionLocations;
     151: astore_1
     152: aload_1
     153: invokevirtual #27                 // Method org/apache/hadoop/hbase/RegionLocations.isEmpty:()Z
     156: invokestatic  #28                 // Method org/junit/Assert.assertTrue:(Z)V
     159: ldc2_w        #3                  // long 10l
     162: aload_1
     163: invokevirtual #29                 // Method org/apache/hadoop/hbase/RegionLocations.size:()I
     166: i2l
     167: invokestatic  #30                 // Method org/junit/Assert.assertEquals:(JJ)V
     170: lconst_0
     171: aload_1
     172: invokevirtual #31                 // Method org/apache/hadoop/hbase/RegionLocations.numNonNullElements:()I
     175: i2l
     176: invokestatic  #30                 // Method org/junit/Assert.assertEquals:(JJ)V
     179: aload_0
     180: iconst_2
     181: anewarray     #25                 // class org/apache/hadoop/hbase/HRegionLocation
     184: dup
     185: iconst_0
     186: aload_0
     187: aload_2
     188: aconst_null
     189: invokespecial #33                 // Method hrl:(Lorg/apache/hadoop/hbase/HRegionInfo;Lorg/apache/hadoop/hbase/ServerName;)Lorg/apache/hadoop/hbase/HRegionLocation;
     192: aastore
     193: dup
     194: iconst_1
     195: aload_0
     196: aload_3
     197: aconst_null
     198: invokespecial #33                 // Method hrl:(Lorg/apache/hadoop/hbase/HRegionInfo;Lorg/apache/hadoop/hbase/ServerName;)Lorg/apache/hadoop/hbase/HRegionLocation;
     201: aastore
     202: invokespecial #32                 // Method hrll:([Lorg/apache/hadoop/hbase/HRegionLocation;)Lorg/apache/hadoop/hbase/RegionLocations;
     205: astore_1
     206: aload_1
     207: invokevirtual #27                 // Method org/apache/hadoop/hbase/RegionLocations.isEmpty:()Z
     210: invokestatic  #28                 // Method org/junit/Assert.assertTrue:(Z)V
     213: ldc2_w        #3                  // long 10l
     216: aload_1
     217: invokevirtual #29                 // Method org/apache/hadoop/hbase/RegionLocations.size:()I
     220: i2l
     221: invokestatic  #30                 // Method org/junit/Assert.assertEquals:(JJ)V
     224: lconst_0
     225: aload_1
     226: invokevirtual #31                 // Method org/apache/hadoop/hbase/RegionLocations.numNonNullElements:()I
     229: i2l
     230: invokestatic  #30                 // Method org/junit/Assert.assertEquals:(JJ)V
     233: return

  public void testRemoveByServer();
    Code:
       0: new           #24                 // class org/apache/hadoop/hbase/RegionLocations
       3: dup
       4: iconst_0
       5: anewarray     #25                 // class org/apache/hadoop/hbase/HRegionLocation
       8: invokespecial #26                 // Method org/apache/hadoop/hbase/RegionLocations."<init>":([Lorg/apache/hadoop/hbase/HRegionLocation;)V
      11: astore_1
      12: aload_1
      13: aload_1
      14: aload_0
      15: getfield      #6                  // Field sn0:Lorg/apache/hadoop/hbase/ServerName;
      18: invokevirtual #43                 // Method org/apache/hadoop/hbase/RegionLocations.removeByServer:(Lorg/apache/hadoop/hbase/ServerName;)Lorg/apache/hadoop/hbase/RegionLocations;
      21: if_acmpne     28
      24: iconst_1
      25: goto          29
      28: iconst_0
      29: invokestatic  #28                 // Method org/junit/Assert.assertTrue:(Z)V
      32: aload_0
      33: iconst_1
      34: anewarray     #25                 // class org/apache/hadoop/hbase/HRegionLocation
      37: dup
      38: iconst_0
      39: aload_0
      40: aload_0
      41: getfield      #14                 // Field info0:Lorg/apache/hadoop/hbase/HRegionInfo;
      44: aload_0
      45: getfield      #6                  // Field sn0:Lorg/apache/hadoop/hbase/ServerName;
      48: invokespecial #33                 // Method hrl:(Lorg/apache/hadoop/hbase/HRegionInfo;Lorg/apache/hadoop/hbase/ServerName;)Lorg/apache/hadoop/hbase/HRegionLocation;
      51: aastore
      52: invokespecial #32                 // Method hrll:([Lorg/apache/hadoop/hbase/HRegionLocation;)Lorg/apache/hadoop/hbase/RegionLocations;
      55: astore_1
      56: aload_1
      57: aload_1
      58: aload_0
      59: getfield      #8                  // Field sn1:Lorg/apache/hadoop/hbase/ServerName;
      62: invokevirtual #43                 // Method org/apache/hadoop/hbase/RegionLocations.removeByServer:(Lorg/apache/hadoop/hbase/ServerName;)Lorg/apache/hadoop/hbase/RegionLocations;
      65: if_acmpne     72
      68: iconst_1
      69: goto          73
      72: iconst_0
      73: invokestatic  #28                 // Method org/junit/Assert.assertTrue:(Z)V
      76: aload_1
      77: aload_0
      78: getfield      #6                  // Field sn0:Lorg/apache/hadoop/hbase/ServerName;
      81: invokevirtual #43                 // Method org/apache/hadoop/hbase/RegionLocations.removeByServer:(Lorg/apache/hadoop/hbase/ServerName;)Lorg/apache/hadoop/hbase/RegionLocations;
      84: astore_1
      85: lconst_0
      86: aload_1
      87: invokevirtual #31                 // Method org/apache/hadoop/hbase/RegionLocations.numNonNullElements:()I
      90: i2l
      91: invokestatic  #30                 // Method org/junit/Assert.assertEquals:(JJ)V
      94: aload_0
      95: iconst_4
      96: anewarray     #25                 // class org/apache/hadoop/hbase/HRegionLocation
      99: dup
     100: iconst_0
     101: aload_0
     102: aload_0
     103: getfield      #14                 // Field info0:Lorg/apache/hadoop/hbase/HRegionInfo;
     106: aload_0
     107: getfield      #6                  // Field sn0:Lorg/apache/hadoop/hbase/ServerName;
     110: invokespecial #33                 // Method hrl:(Lorg/apache/hadoop/hbase/HRegionInfo;Lorg/apache/hadoop/hbase/ServerName;)Lorg/apache/hadoop/hbase/HRegionLocation;
     113: aastore
     114: dup
     115: iconst_1
     116: aload_0
     117: aload_0
     118: getfield      #15                 // Field info1:Lorg/apache/hadoop/hbase/HRegionInfo;
     121: aload_0
     122: getfield      #8                  // Field sn1:Lorg/apache/hadoop/hbase/ServerName;
     125: invokespecial #33                 // Method hrl:(Lorg/apache/hadoop/hbase/HRegionInfo;Lorg/apache/hadoop/hbase/ServerName;)Lorg/apache/hadoop/hbase/HRegionLocation;
     128: aastore
     129: dup
     130: iconst_2
     131: aload_0
     132: aload_0
     133: getfield      #16                 // Field info2:Lorg/apache/hadoop/hbase/HRegionInfo;
     136: aload_0
     137: getfield      #10                 // Field sn2:Lorg/apache/hadoop/hbase/ServerName;
     140: invokespecial #33                 // Method hrl:(Lorg/apache/hadoop/hbase/HRegionInfo;Lorg/apache/hadoop/hbase/ServerName;)Lorg/apache/hadoop/hbase/HRegionLocation;
     143: aastore
     144: dup
     145: iconst_3
     146: aload_0
     147: aload_0
     148: getfield      #17                 // Field info9:Lorg/apache/hadoop/hbase/HRegionInfo;
     151: aload_0
     152: getfield      #10                 // Field sn2:Lorg/apache/hadoop/hbase/ServerName;
     155: invokespecial #33                 // Method hrl:(Lorg/apache/hadoop/hbase/HRegionInfo;Lorg/apache/hadoop/hbase/ServerName;)Lorg/apache/hadoop/hbase/HRegionLocation;
     158: aastore
     159: invokespecial #32                 // Method hrll:([Lorg/apache/hadoop/hbase/HRegionLocation;)Lorg/apache/hadoop/hbase/RegionLocations;
     162: astore_1
     163: aload_1
     164: aload_1
     165: aload_0
     166: getfield      #12                 // Field sn3:Lorg/apache/hadoop/hbase/ServerName;
     169: invokevirtual #43                 // Method org/apache/hadoop/hbase/RegionLocations.removeByServer:(Lorg/apache/hadoop/hbase/ServerName;)Lorg/apache/hadoop/hbase/RegionLocations;
     172: if_acmpne     179
     175: iconst_1
     176: goto          180
     179: iconst_0
     180: invokestatic  #28                 // Method org/junit/Assert.assertTrue:(Z)V
     183: aload_1
     184: aload_0
     185: getfield      #6                  // Field sn0:Lorg/apache/hadoop/hbase/ServerName;
     188: invokevirtual #43                 // Method org/apache/hadoop/hbase/RegionLocations.removeByServer:(Lorg/apache/hadoop/hbase/ServerName;)Lorg/apache/hadoop/hbase/RegionLocations;
     191: astore_1
     192: aload_1
     193: iconst_0
     194: invokevirtual #44                 // Method org/apache/hadoop/hbase/RegionLocations.getRegionLocation:(I)Lorg/apache/hadoop/hbase/HRegionLocation;
     197: invokestatic  #45                 // Method org/junit/Assert.assertNull:(Ljava/lang/Object;)V
     200: aload_0
     201: getfield      #8                  // Field sn1:Lorg/apache/hadoop/hbase/ServerName;
     204: aload_1
     205: iconst_1
     206: invokevirtual #44                 // Method org/apache/hadoop/hbase/RegionLocations.getRegionLocation:(I)Lorg/apache/hadoop/hbase/HRegionLocation;
     209: invokevirtual #46                 // Method org/apache/hadoop/hbase/HRegionLocation.getServerName:()Lorg/apache/hadoop/hbase/ServerName;
     212: invokestatic  #47                 // Method org/junit/Assert.assertEquals:(Ljava/lang/Object;Ljava/lang/Object;)V
     215: aload_0
     216: getfield      #10                 // Field sn2:Lorg/apache/hadoop/hbase/ServerName;
     219: aload_1
     220: iconst_2
     221: invokevirtual #44                 // Method org/apache/hadoop/hbase/RegionLocations.getRegionLocation:(I)Lorg/apache/hadoop/hbase/HRegionLocation;
     224: invokevirtual #46                 // Method org/apache/hadoop/hbase/HRegionLocation.getServerName:()Lorg/apache/hadoop/hbase/ServerName;
     227: invokestatic  #47                 // Method org/junit/Assert.assertEquals:(Ljava/lang/Object;Ljava/lang/Object;)V
     230: aload_1
     231: iconst_5
     232: invokevirtual #44                 // Method org/apache/hadoop/hbase/RegionLocations.getRegionLocation:(I)Lorg/apache/hadoop/hbase/HRegionLocation;
     235: invokestatic  #45                 // Method org/junit/Assert.assertNull:(Ljava/lang/Object;)V
     238: aload_0
     239: getfield      #10                 // Field sn2:Lorg/apache/hadoop/hbase/ServerName;
     242: aload_1
     243: bipush        9
     245: invokevirtual #44                 // Method org/apache/hadoop/hbase/RegionLocations.getRegionLocation:(I)Lorg/apache/hadoop/hbase/HRegionLocation;
     248: invokevirtual #46                 // Method org/apache/hadoop/hbase/HRegionLocation.getServerName:()Lorg/apache/hadoop/hbase/ServerName;
     251: invokestatic  #47                 // Method org/junit/Assert.assertEquals:(Ljava/lang/Object;Ljava/lang/Object;)V
     254: aload_0
     255: iconst_4
     256: anewarray     #25                 // class org/apache/hadoop/hbase/HRegionLocation
     259: dup
     260: iconst_0
     261: aload_0
     262: aload_0
     263: getfield      #14                 // Field info0:Lorg/apache/hadoop/hbase/HRegionInfo;
     266: aload_0
     267: getfield      #8                  // Field sn1:Lorg/apache/hadoop/hbase/ServerName;
     270: invokespecial #33                 // Method hrl:(Lorg/apache/hadoop/hbase/HRegionInfo;Lorg/apache/hadoop/hbase/ServerName;)Lorg/apache/hadoop/hbase/HRegionLocation;
     273: aastore
     274: dup
     275: iconst_1
     276: aload_0
     277: aload_0
     278: getfield      #15                 // Field info1:Lorg/apache/hadoop/hbase/HRegionInfo;
     281: aload_0
     282: getfield      #8                  // Field sn1:Lorg/apache/hadoop/hbase/ServerName;
     285: invokespecial #33                 // Method hrl:(Lorg/apache/hadoop/hbase/HRegionInfo;Lorg/apache/hadoop/hbase/ServerName;)Lorg/apache/hadoop/hbase/HRegionLocation;
     288: aastore
     289: dup
     290: iconst_2
     291: aload_0
     292: aload_0
     293: getfield      #16                 // Field info2:Lorg/apache/hadoop/hbase/HRegionInfo;
     296: aload_0
     297: getfield      #6                  // Field sn0:Lorg/apache/hadoop/hbase/ServerName;
     300: invokespecial #33                 // Method hrl:(Lorg/apache/hadoop/hbase/HRegionInfo;Lorg/apache/hadoop/hbase/ServerName;)Lorg/apache/hadoop/hbase/HRegionLocation;
     303: aastore
     304: dup
     305: iconst_3
     306: aload_0
     307: aload_0
     308: getfield      #17                 // Field info9:Lorg/apache/hadoop/hbase/HRegionInfo;
     311: aload_0
     312: getfield      #6                  // Field sn0:Lorg/apache/hadoop/hbase/ServerName;
     315: invokespecial #33                 // Method hrl:(Lorg/apache/hadoop/hbase/HRegionInfo;Lorg/apache/hadoop/hbase/ServerName;)Lorg/apache/hadoop/hbase/HRegionLocation;
     318: aastore
     319: invokespecial #32                 // Method hrll:([Lorg/apache/hadoop/hbase/HRegionLocation;)Lorg/apache/hadoop/hbase/RegionLocations;
     322: astore_1
     323: aload_1
     324: aload_0
     325: getfield      #6                  // Field sn0:Lorg/apache/hadoop/hbase/ServerName;
     328: invokevirtual #43                 // Method org/apache/hadoop/hbase/RegionLocations.removeByServer:(Lorg/apache/hadoop/hbase/ServerName;)Lorg/apache/hadoop/hbase/RegionLocations;
     331: astore_1
     332: aload_0
     333: getfield      #8                  // Field sn1:Lorg/apache/hadoop/hbase/ServerName;
     336: aload_1
     337: iconst_0
     338: invokevirtual #44                 // Method org/apache/hadoop/hbase/RegionLocations.getRegionLocation:(I)Lorg/apache/hadoop/hbase/HRegionLocation;
     341: invokevirtual #46                 // Method org/apache/hadoop/hbase/HRegionLocation.getServerName:()Lorg/apache/hadoop/hbase/ServerName;
     344: invokestatic  #47                 // Method org/junit/Assert.assertEquals:(Ljava/lang/Object;Ljava/lang/Object;)V
     347: aload_0
     348: getfield      #8                  // Field sn1:Lorg/apache/hadoop/hbase/ServerName;
     351: aload_1
     352: iconst_1
     353: invokevirtual #44                 // Method org/apache/hadoop/hbase/RegionLocations.getRegionLocation:(I)Lorg/apache/hadoop/hbase/HRegionLocation;
     356: invokevirtual #46                 // Method org/apache/hadoop/hbase/HRegionLocation.getServerName:()Lorg/apache/hadoop/hbase/ServerName;
     359: invokestatic  #47                 // Method org/junit/Assert.assertEquals:(Ljava/lang/Object;Ljava/lang/Object;)V
     362: aload_1
     363: iconst_2
     364: invokevirtual #44                 // Method org/apache/hadoop/hbase/RegionLocations.getRegionLocation:(I)Lorg/apache/hadoop/hbase/HRegionLocation;
     367: invokestatic  #45                 // Method org/junit/Assert.assertNull:(Ljava/lang/Object;)V
     370: aload_1
     371: iconst_5
     372: invokevirtual #44                 // Method org/apache/hadoop/hbase/RegionLocations.getRegionLocation:(I)Lorg/apache/hadoop/hbase/HRegionLocation;
     375: invokestatic  #45                 // Method org/junit/Assert.assertNull:(Ljava/lang/Object;)V
     378: aload_1
     379: bipush        9
     381: invokevirtual #44                 // Method org/apache/hadoop/hbase/RegionLocations.getRegionLocation:(I)Lorg/apache/hadoop/hbase/HRegionLocation;
     384: invokestatic  #45                 // Method org/junit/Assert.assertNull:(Ljava/lang/Object;)V
     387: return

  public void testRemove();
    Code:
       0: new           #24                 // class org/apache/hadoop/hbase/RegionLocations
       3: dup
       4: iconst_0
       5: anewarray     #25                 // class org/apache/hadoop/hbase/HRegionLocation
       8: invokespecial #26                 // Method org/apache/hadoop/hbase/RegionLocations."<init>":([Lorg/apache/hadoop/hbase/HRegionLocation;)V
      11: astore_1
      12: aload_1
      13: aload_1
      14: aload_0
      15: aload_0
      16: getfield      #14                 // Field info0:Lorg/apache/hadoop/hbase/HRegionInfo;
      19: aload_0
      20: getfield      #6                  // Field sn0:Lorg/apache/hadoop/hbase/ServerName;
      23: invokespecial #33                 // Method hrl:(Lorg/apache/hadoop/hbase/HRegionInfo;Lorg/apache/hadoop/hbase/ServerName;)Lorg/apache/hadoop/hbase/HRegionLocation;
      26: invokevirtual #48                 // Method org/apache/hadoop/hbase/RegionLocations.remove:(Lorg/apache/hadoop/hbase/HRegionLocation;)Lorg/apache/hadoop/hbase/RegionLocations;
      29: if_acmpne     36
      32: iconst_1
      33: goto          37
      36: iconst_0
      37: invokestatic  #28                 // Method org/junit/Assert.assertTrue:(Z)V
      40: aload_0
      41: iconst_1
      42: anewarray     #25                 // class org/apache/hadoop/hbase/HRegionLocation
      45: dup
      46: iconst_0
      47: aload_0
      48: aload_0
      49: getfield      #14                 // Field info0:Lorg/apache/hadoop/hbase/HRegionInfo;
      52: aload_0
      53: getfield      #6                  // Field sn0:Lorg/apache/hadoop/hbase/ServerName;
      56: invokespecial #33                 // Method hrl:(Lorg/apache/hadoop/hbase/HRegionInfo;Lorg/apache/hadoop/hbase/ServerName;)Lorg/apache/hadoop/hbase/HRegionLocation;
      59: aastore
      60: invokespecial #32                 // Method hrll:([Lorg/apache/hadoop/hbase/HRegionLocation;)Lorg/apache/hadoop/hbase/RegionLocations;
      63: astore_1
      64: aload_1
      65: aload_1
      66: aload_0
      67: aload_0
      68: getfield      #14                 // Field info0:Lorg/apache/hadoop/hbase/HRegionInfo;
      71: aload_0
      72: getfield      #8                  // Field sn1:Lorg/apache/hadoop/hbase/ServerName;
      75: invokespecial #33                 // Method hrl:(Lorg/apache/hadoop/hbase/HRegionInfo;Lorg/apache/hadoop/hbase/ServerName;)Lorg/apache/hadoop/hbase/HRegionLocation;
      78: invokevirtual #48                 // Method org/apache/hadoop/hbase/RegionLocations.remove:(Lorg/apache/hadoop/hbase/HRegionLocation;)Lorg/apache/hadoop/hbase/RegionLocations;
      81: if_acmpne     88
      84: iconst_1
      85: goto          89
      88: iconst_0
      89: invokestatic  #28                 // Method org/junit/Assert.assertTrue:(Z)V
      92: aload_1
      93: aload_0
      94: aload_0
      95: getfield      #14                 // Field info0:Lorg/apache/hadoop/hbase/HRegionInfo;
      98: aload_0
      99: getfield      #6                  // Field sn0:Lorg/apache/hadoop/hbase/ServerName;
     102: invokespecial #33                 // Method hrl:(Lorg/apache/hadoop/hbase/HRegionInfo;Lorg/apache/hadoop/hbase/ServerName;)Lorg/apache/hadoop/hbase/HRegionLocation;
     105: invokevirtual #48                 // Method org/apache/hadoop/hbase/RegionLocations.remove:(Lorg/apache/hadoop/hbase/HRegionLocation;)Lorg/apache/hadoop/hbase/RegionLocations;
     108: astore_1
     109: aload_1
     110: invokevirtual #27                 // Method org/apache/hadoop/hbase/RegionLocations.isEmpty:()Z
     113: invokestatic  #28                 // Method org/junit/Assert.assertTrue:(Z)V
     116: aload_0
     117: iconst_4
     118: anewarray     #25                 // class org/apache/hadoop/hbase/HRegionLocation
     121: dup
     122: iconst_0
     123: aload_0
     124: aload_0
     125: getfield      #14                 // Field info0:Lorg/apache/hadoop/hbase/HRegionInfo;
     128: aload_0
     129: getfield      #6                  // Field sn0:Lorg/apache/hadoop/hbase/ServerName;
     132: invokespecial #33                 // Method hrl:(Lorg/apache/hadoop/hbase/HRegionInfo;Lorg/apache/hadoop/hbase/ServerName;)Lorg/apache/hadoop/hbase/HRegionLocation;
     135: aastore
     136: dup
     137: iconst_1
     138: aload_0
     139: aload_0
     140: getfield      #15                 // Field info1:Lorg/apache/hadoop/hbase/HRegionInfo;
     143: aload_0
     144: getfield      #8                  // Field sn1:Lorg/apache/hadoop/hbase/ServerName;
     147: invokespecial #33                 // Method hrl:(Lorg/apache/hadoop/hbase/HRegionInfo;Lorg/apache/hadoop/hbase/ServerName;)Lorg/apache/hadoop/hbase/HRegionLocation;
     150: aastore
     151: dup
     152: iconst_2
     153: aload_0
     154: aload_0
     155: getfield      #16                 // Field info2:Lorg/apache/hadoop/hbase/HRegionInfo;
     158: aload_0
     159: getfield      #10                 // Field sn2:Lorg/apache/hadoop/hbase/ServerName;
     162: invokespecial #33                 // Method hrl:(Lorg/apache/hadoop/hbase/HRegionInfo;Lorg/apache/hadoop/hbase/ServerName;)Lorg/apache/hadoop/hbase/HRegionLocation;
     165: aastore
     166: dup
     167: iconst_3
     168: aload_0
     169: aload_0
     170: getfield      #17                 // Field info9:Lorg/apache/hadoop/hbase/HRegionInfo;
     173: aload_0
     174: getfield      #10                 // Field sn2:Lorg/apache/hadoop/hbase/ServerName;
     177: invokespecial #33                 // Method hrl:(Lorg/apache/hadoop/hbase/HRegionInfo;Lorg/apache/hadoop/hbase/ServerName;)Lorg/apache/hadoop/hbase/HRegionLocation;
     180: aastore
     181: invokespecial #32                 // Method hrll:([Lorg/apache/hadoop/hbase/HRegionLocation;)Lorg/apache/hadoop/hbase/RegionLocations;
     184: astore_1
     185: aload_1
     186: aload_1
     187: aload_0
     188: aload_0
     189: getfield      #15                 // Field info1:Lorg/apache/hadoop/hbase/HRegionInfo;
     192: aload_0
     193: getfield      #12                 // Field sn3:Lorg/apache/hadoop/hbase/ServerName;
     196: invokespecial #33                 // Method hrl:(Lorg/apache/hadoop/hbase/HRegionInfo;Lorg/apache/hadoop/hbase/ServerName;)Lorg/apache/hadoop/hbase/HRegionLocation;
     199: invokevirtual #48                 // Method org/apache/hadoop/hbase/RegionLocations.remove:(Lorg/apache/hadoop/hbase/HRegionLocation;)Lorg/apache/hadoop/hbase/RegionLocations;
     202: if_acmpne     209
     205: iconst_1
     206: goto          210
     209: iconst_0
     210: invokestatic  #28                 // Method org/junit/Assert.assertTrue:(Z)V
     213: aload_1
     214: aload_0
     215: aload_0
     216: getfield      #14                 // Field info0:Lorg/apache/hadoop/hbase/HRegionInfo;
     219: aload_0
     220: getfield      #6                  // Field sn0:Lorg/apache/hadoop/hbase/ServerName;
     223: invokespecial #33                 // Method hrl:(Lorg/apache/hadoop/hbase/HRegionInfo;Lorg/apache/hadoop/hbase/ServerName;)Lorg/apache/hadoop/hbase/HRegionLocation;
     226: invokevirtual #48                 // Method org/apache/hadoop/hbase/RegionLocations.remove:(Lorg/apache/hadoop/hbase/HRegionLocation;)Lorg/apache/hadoop/hbase/RegionLocations;
     229: astore_1
     230: aload_1
     231: iconst_0
     232: invokevirtual #44                 // Method org/apache/hadoop/hbase/RegionLocations.getRegionLocation:(I)Lorg/apache/hadoop/hbase/HRegionLocation;
     235: invokestatic  #45                 // Method org/junit/Assert.assertNull:(Ljava/lang/Object;)V
     238: aload_0
     239: getfield      #8                  // Field sn1:Lorg/apache/hadoop/hbase/ServerName;
     242: aload_1
     243: iconst_1
     244: invokevirtual #44                 // Method org/apache/hadoop/hbase/RegionLocations.getRegionLocation:(I)Lorg/apache/hadoop/hbase/HRegionLocation;
     247: invokevirtual #46                 // Method org/apache/hadoop/hbase/HRegionLocation.getServerName:()Lorg/apache/hadoop/hbase/ServerName;
     250: invokestatic  #47                 // Method org/junit/Assert.assertEquals:(Ljava/lang/Object;Ljava/lang/Object;)V
     253: aload_0
     254: getfield      #10                 // Field sn2:Lorg/apache/hadoop/hbase/ServerName;
     257: aload_1
     258: iconst_2
     259: invokevirtual #44                 // Method org/apache/hadoop/hbase/RegionLocations.getRegionLocation:(I)Lorg/apache/hadoop/hbase/HRegionLocation;
     262: invokevirtual #46                 // Method org/apache/hadoop/hbase/HRegionLocation.getServerName:()Lorg/apache/hadoop/hbase/ServerName;
     265: invokestatic  #47                 // Method org/junit/Assert.assertEquals:(Ljava/lang/Object;Ljava/lang/Object;)V
     268: aload_1
     269: iconst_5
     270: invokevirtual #44                 // Method org/apache/hadoop/hbase/RegionLocations.getRegionLocation:(I)Lorg/apache/hadoop/hbase/HRegionLocation;
     273: invokestatic  #45                 // Method org/junit/Assert.assertNull:(Ljava/lang/Object;)V
     276: aload_0
     277: getfield      #10                 // Field sn2:Lorg/apache/hadoop/hbase/ServerName;
     280: aload_1
     281: bipush        9
     283: invokevirtual #44                 // Method org/apache/hadoop/hbase/RegionLocations.getRegionLocation:(I)Lorg/apache/hadoop/hbase/HRegionLocation;
     286: invokevirtual #46                 // Method org/apache/hadoop/hbase/HRegionLocation.getServerName:()Lorg/apache/hadoop/hbase/ServerName;
     289: invokestatic  #47                 // Method org/junit/Assert.assertEquals:(Ljava/lang/Object;Ljava/lang/Object;)V
     292: aload_1
     293: aload_0
     294: aload_0
     295: getfield      #17                 // Field info9:Lorg/apache/hadoop/hbase/HRegionInfo;
     298: aload_0
     299: getfield      #10                 // Field sn2:Lorg/apache/hadoop/hbase/ServerName;
     302: invokespecial #33                 // Method hrl:(Lorg/apache/hadoop/hbase/HRegionInfo;Lorg/apache/hadoop/hbase/ServerName;)Lorg/apache/hadoop/hbase/HRegionLocation;
     305: invokevirtual #48                 // Method org/apache/hadoop/hbase/RegionLocations.remove:(Lorg/apache/hadoop/hbase/HRegionLocation;)Lorg/apache/hadoop/hbase/RegionLocations;
     308: astore_1
     309: aload_1
     310: iconst_0
     311: invokevirtual #44                 // Method org/apache/hadoop/hbase/RegionLocations.getRegionLocation:(I)Lorg/apache/hadoop/hbase/HRegionLocation;
     314: invokestatic  #45                 // Method org/junit/Assert.assertNull:(Ljava/lang/Object;)V
     317: aload_0
     318: getfield      #8                  // Field sn1:Lorg/apache/hadoop/hbase/ServerName;
     321: aload_1
     322: iconst_1
     323: invokevirtual #44                 // Method org/apache/hadoop/hbase/RegionLocations.getRegionLocation:(I)Lorg/apache/hadoop/hbase/HRegionLocation;
     326: invokevirtual #46                 // Method org/apache/hadoop/hbase/HRegionLocation.getServerName:()Lorg/apache/hadoop/hbase/ServerName;
     329: invokestatic  #47                 // Method org/junit/Assert.assertEquals:(Ljava/lang/Object;Ljava/lang/Object;)V
     332: aload_0
     333: getfield      #10                 // Field sn2:Lorg/apache/hadoop/hbase/ServerName;
     336: aload_1
     337: iconst_2
     338: invokevirtual #44                 // Method org/apache/hadoop/hbase/RegionLocations.getRegionLocation:(I)Lorg/apache/hadoop/hbase/HRegionLocation;
     341: invokevirtual #46                 // Method org/apache/hadoop/hbase/HRegionLocation.getServerName:()Lorg/apache/hadoop/hbase/ServerName;
     344: invokestatic  #47                 // Method org/junit/Assert.assertEquals:(Ljava/lang/Object;Ljava/lang/Object;)V
     347: aload_1
     348: iconst_5
     349: invokevirtual #44                 // Method org/apache/hadoop/hbase/RegionLocations.getRegionLocation:(I)Lorg/apache/hadoop/hbase/HRegionLocation;
     352: invokestatic  #45                 // Method org/junit/Assert.assertNull:(Ljava/lang/Object;)V
     355: aload_1
     356: bipush        9
     358: invokevirtual #44                 // Method org/apache/hadoop/hbase/RegionLocations.getRegionLocation:(I)Lorg/apache/hadoop/hbase/HRegionLocation;
     361: invokestatic  #45                 // Method org/junit/Assert.assertNull:(Ljava/lang/Object;)V
     364: aload_0
     365: iconst_4
     366: anewarray     #25                 // class org/apache/hadoop/hbase/HRegionLocation
     369: dup
     370: iconst_0
     371: aload_0
     372: aload_0
     373: getfield      #14                 // Field info0:Lorg/apache/hadoop/hbase/HRegionInfo;
     376: aload_0
     377: getfield      #8                  // Field sn1:Lorg/apache/hadoop/hbase/ServerName;
     380: invokespecial #33                 // Method hrl:(Lorg/apache/hadoop/hbase/HRegionInfo;Lorg/apache/hadoop/hbase/ServerName;)Lorg/apache/hadoop/hbase/HRegionLocation;
     383: aastore
     384: dup
     385: iconst_1
     386: aload_0
     387: aload_0
     388: getfield      #15                 // Field info1:Lorg/apache/hadoop/hbase/HRegionInfo;
     391: aload_0
     392: getfield      #8                  // Field sn1:Lorg/apache/hadoop/hbase/ServerName;
     395: invokespecial #33                 // Method hrl:(Lorg/apache/hadoop/hbase/HRegionInfo;Lorg/apache/hadoop/hbase/ServerName;)Lorg/apache/hadoop/hbase/HRegionLocation;
     398: aastore
     399: dup
     400: iconst_2
     401: aload_0
     402: aload_0
     403: getfield      #16                 // Field info2:Lorg/apache/hadoop/hbase/HRegionInfo;
     406: aload_0
     407: getfield      #6                  // Field sn0:Lorg/apache/hadoop/hbase/ServerName;
     410: invokespecial #33                 // Method hrl:(Lorg/apache/hadoop/hbase/HRegionInfo;Lorg/apache/hadoop/hbase/ServerName;)Lorg/apache/hadoop/hbase/HRegionLocation;
     413: aastore
     414: dup
     415: iconst_3
     416: aload_0
     417: aload_0
     418: getfield      #17                 // Field info9:Lorg/apache/hadoop/hbase/HRegionInfo;
     421: aload_0
     422: getfield      #6                  // Field sn0:Lorg/apache/hadoop/hbase/ServerName;
     425: invokespecial #33                 // Method hrl:(Lorg/apache/hadoop/hbase/HRegionInfo;Lorg/apache/hadoop/hbase/ServerName;)Lorg/apache/hadoop/hbase/HRegionLocation;
     428: aastore
     429: invokespecial #32                 // Method hrll:([Lorg/apache/hadoop/hbase/HRegionLocation;)Lorg/apache/hadoop/hbase/RegionLocations;
     432: astore_1
     433: aload_1
     434: aload_0
     435: aload_0
     436: getfield      #17                 // Field info9:Lorg/apache/hadoop/hbase/HRegionInfo;
     439: aload_0
     440: getfield      #6                  // Field sn0:Lorg/apache/hadoop/hbase/ServerName;
     443: invokespecial #33                 // Method hrl:(Lorg/apache/hadoop/hbase/HRegionInfo;Lorg/apache/hadoop/hbase/ServerName;)Lorg/apache/hadoop/hbase/HRegionLocation;
     446: invokevirtual #48                 // Method org/apache/hadoop/hbase/RegionLocations.remove:(Lorg/apache/hadoop/hbase/HRegionLocation;)Lorg/apache/hadoop/hbase/RegionLocations;
     449: astore_1
     450: aload_0
     451: getfield      #8                  // Field sn1:Lorg/apache/hadoop/hbase/ServerName;
     454: aload_1
     455: iconst_0
     456: invokevirtual #44                 // Method org/apache/hadoop/hbase/RegionLocations.getRegionLocation:(I)Lorg/apache/hadoop/hbase/HRegionLocation;
     459: invokevirtual #46                 // Method org/apache/hadoop/hbase/HRegionLocation.getServerName:()Lorg/apache/hadoop/hbase/ServerName;
     462: invokestatic  #47                 // Method org/junit/Assert.assertEquals:(Ljava/lang/Object;Ljava/lang/Object;)V
     465: aload_0
     466: getfield      #8                  // Field sn1:Lorg/apache/hadoop/hbase/ServerName;
     469: aload_1
     470: iconst_1
     471: invokevirtual #44                 // Method org/apache/hadoop/hbase/RegionLocations.getRegionLocation:(I)Lorg/apache/hadoop/hbase/HRegionLocation;
     474: invokevirtual #46                 // Method org/apache/hadoop/hbase/HRegionLocation.getServerName:()Lorg/apache/hadoop/hbase/ServerName;
     477: invokestatic  #47                 // Method org/junit/Assert.assertEquals:(Ljava/lang/Object;Ljava/lang/Object;)V
     480: aload_0
     481: getfield      #6                  // Field sn0:Lorg/apache/hadoop/hbase/ServerName;
     484: aload_1
     485: iconst_2
     486: invokevirtual #44                 // Method org/apache/hadoop/hbase/RegionLocations.getRegionLocation:(I)Lorg/apache/hadoop/hbase/HRegionLocation;
     489: invokevirtual #46                 // Method org/apache/hadoop/hbase/HRegionLocation.getServerName:()Lorg/apache/hadoop/hbase/ServerName;
     492: invokestatic  #47                 // Method org/junit/Assert.assertEquals:(Ljava/lang/Object;Ljava/lang/Object;)V
     495: aload_1
     496: iconst_5
     497: invokevirtual #44                 // Method org/apache/hadoop/hbase/RegionLocations.getRegionLocation:(I)Lorg/apache/hadoop/hbase/HRegionLocation;
     500: invokestatic  #45                 // Method org/junit/Assert.assertNull:(Ljava/lang/Object;)V
     503: aload_1
     504: bipush        9
     506: invokevirtual #44                 // Method org/apache/hadoop/hbase/RegionLocations.getRegionLocation:(I)Lorg/apache/hadoop/hbase/HRegionLocation;
     509: invokestatic  #45                 // Method org/junit/Assert.assertNull:(Ljava/lang/Object;)V
     512: return

  public void testUpdateLocation();
    Code:
       0: new           #24                 // class org/apache/hadoop/hbase/RegionLocations
       3: dup
       4: iconst_0
       5: anewarray     #25                 // class org/apache/hadoop/hbase/HRegionLocation
       8: invokespecial #26                 // Method org/apache/hadoop/hbase/RegionLocations."<init>":([Lorg/apache/hadoop/hbase/HRegionLocation;)V
      11: astore_1
      12: aload_1
      13: aload_0
      14: aload_0
      15: getfield      #14                 // Field info0:Lorg/apache/hadoop/hbase/HRegionInfo;
      18: aload_0
      19: getfield      #8                  // Field sn1:Lorg/apache/hadoop/hbase/ServerName;
      22: invokespecial #33                 // Method hrl:(Lorg/apache/hadoop/hbase/HRegionInfo;Lorg/apache/hadoop/hbase/ServerName;)Lorg/apache/hadoop/hbase/HRegionLocation;
      25: iconst_0
      26: iconst_0
      27: invokevirtual #49                 // Method org/apache/hadoop/hbase/RegionLocations.updateLocation:(Lorg/apache/hadoop/hbase/HRegionLocation;ZZ)Lorg/apache/hadoop/hbase/RegionLocations;
      30: astore_1
      31: aload_0
      32: getfield      #8                  // Field sn1:Lorg/apache/hadoop/hbase/ServerName;
      35: aload_1
      36: iconst_0
      37: invokevirtual #44                 // Method org/apache/hadoop/hbase/RegionLocations.getRegionLocation:(I)Lorg/apache/hadoop/hbase/HRegionLocation;
      40: invokevirtual #46                 // Method org/apache/hadoop/hbase/HRegionLocation.getServerName:()Lorg/apache/hadoop/hbase/ServerName;
      43: invokestatic  #47                 // Method org/junit/Assert.assertEquals:(Ljava/lang/Object;Ljava/lang/Object;)V
      46: aload_1
      47: aload_0
      48: aload_0
      49: getfield      #17                 // Field info9:Lorg/apache/hadoop/hbase/HRegionInfo;
      52: aload_0
      53: getfield      #12                 // Field sn3:Lorg/apache/hadoop/hbase/ServerName;
      56: ldc2_w        #3                  // long 10l
      59: invokespecial #50                 // Method hrl:(Lorg/apache/hadoop/hbase/HRegionInfo;Lorg/apache/hadoop/hbase/ServerName;J)Lorg/apache/hadoop/hbase/HRegionLocation;
      62: iconst_0
      63: iconst_0
      64: invokevirtual #49                 // Method org/apache/hadoop/hbase/RegionLocations.updateLocation:(Lorg/apache/hadoop/hbase/HRegionLocation;ZZ)Lorg/apache/hadoop/hbase/RegionLocations;
      67: astore_1
      68: aload_0
      69: getfield      #12                 // Field sn3:Lorg/apache/hadoop/hbase/ServerName;
      72: aload_1
      73: bipush        9
      75: invokevirtual #44                 // Method org/apache/hadoop/hbase/RegionLocations.getRegionLocation:(I)Lorg/apache/hadoop/hbase/HRegionLocation;
      78: invokevirtual #46                 // Method org/apache/hadoop/hbase/HRegionLocation.getServerName:()Lorg/apache/hadoop/hbase/ServerName;
      81: invokestatic  #47                 // Method org/junit/Assert.assertEquals:(Ljava/lang/Object;Ljava/lang/Object;)V
      84: ldc2_w        #3                  // long 10l
      87: aload_1
      88: invokevirtual #29                 // Method org/apache/hadoop/hbase/RegionLocations.size:()I
      91: i2l
      92: invokestatic  #30                 // Method org/junit/Assert.assertEquals:(JJ)V
      95: aload_1
      96: aload_0
      97: aload_0
      98: getfield      #16                 // Field info2:Lorg/apache/hadoop/hbase/HRegionInfo;
     101: aload_0
     102: getfield      #10                 // Field sn2:Lorg/apache/hadoop/hbase/ServerName;
     105: ldc2_w        #3                  // long 10l
     108: invokespecial #50                 // Method hrl:(Lorg/apache/hadoop/hbase/HRegionInfo;Lorg/apache/hadoop/hbase/ServerName;J)Lorg/apache/hadoop/hbase/HRegionLocation;
     111: iconst_0
     112: iconst_0
     113: invokevirtual #49                 // Method org/apache/hadoop/hbase/RegionLocations.updateLocation:(Lorg/apache/hadoop/hbase/HRegionLocation;ZZ)Lorg/apache/hadoop/hbase/RegionLocations;
     116: astore_1
     117: aload_0
     118: getfield      #10                 // Field sn2:Lorg/apache/hadoop/hbase/ServerName;
     121: aload_1
     122: iconst_2
     123: invokevirtual #44                 // Method org/apache/hadoop/hbase/RegionLocations.getRegionLocation:(I)Lorg/apache/hadoop/hbase/HRegionLocation;
     126: invokevirtual #46                 // Method org/apache/hadoop/hbase/HRegionLocation.getServerName:()Lorg/apache/hadoop/hbase/ServerName;
     129: invokestatic  #47                 // Method org/junit/Assert.assertEquals:(Ljava/lang/Object;Ljava/lang/Object;)V
     132: ldc2_w        #3                  // long 10l
     135: aload_1
     136: invokevirtual #29                 // Method org/apache/hadoop/hbase/RegionLocations.size:()I
     139: i2l
     140: invokestatic  #30                 // Method org/junit/Assert.assertEquals:(JJ)V
     143: aload_1
     144: aload_0
     145: aload_0
     146: getfield      #16                 // Field info2:Lorg/apache/hadoop/hbase/HRegionInfo;
     149: aload_0
     150: getfield      #12                 // Field sn3:Lorg/apache/hadoop/hbase/ServerName;
     153: ldc2_w        #51                 // long 11l
     156: invokespecial #50                 // Method hrl:(Lorg/apache/hadoop/hbase/HRegionInfo;Lorg/apache/hadoop/hbase/ServerName;J)Lorg/apache/hadoop/hbase/HRegionLocation;
     159: iconst_0
     160: iconst_0
     161: invokevirtual #49                 // Method org/apache/hadoop/hbase/RegionLocations.updateLocation:(Lorg/apache/hadoop/hbase/HRegionLocation;ZZ)Lorg/apache/hadoop/hbase/RegionLocations;
     164: astore_1
     165: aload_0
     166: getfield      #12                 // Field sn3:Lorg/apache/hadoop/hbase/ServerName;
     169: aload_1
     170: iconst_2
     171: invokevirtual #44                 // Method org/apache/hadoop/hbase/RegionLocations.getRegionLocation:(I)Lorg/apache/hadoop/hbase/HRegionLocation;
     174: invokevirtual #46                 // Method org/apache/hadoop/hbase/HRegionLocation.getServerName:()Lorg/apache/hadoop/hbase/ServerName;
     177: invokestatic  #47                 // Method org/junit/Assert.assertEquals:(Ljava/lang/Object;Ljava/lang/Object;)V
     180: aload_0
     181: getfield      #12                 // Field sn3:Lorg/apache/hadoop/hbase/ServerName;
     184: aload_1
     185: bipush        9
     187: invokevirtual #44                 // Method org/apache/hadoop/hbase/RegionLocations.getRegionLocation:(I)Lorg/apache/hadoop/hbase/HRegionLocation;
     190: invokevirtual #46                 // Method org/apache/hadoop/hbase/HRegionLocation.getServerName:()Lorg/apache/hadoop/hbase/ServerName;
     193: invokestatic  #47                 // Method org/junit/Assert.assertEquals:(Ljava/lang/Object;Ljava/lang/Object;)V
     196: aload_1
     197: aload_0
     198: aload_0
     199: getfield      #16                 // Field info2:Lorg/apache/hadoop/hbase/HRegionInfo;
     202: aload_0
     203: getfield      #8                  // Field sn1:Lorg/apache/hadoop/hbase/ServerName;
     206: ldc2_w        #51                 // long 11l
     209: invokespecial #50                 // Method hrl:(Lorg/apache/hadoop/hbase/HRegionInfo;Lorg/apache/hadoop/hbase/ServerName;J)Lorg/apache/hadoop/hbase/HRegionLocation;
     212: iconst_0
     213: iconst_0
     214: invokevirtual #49                 // Method org/apache/hadoop/hbase/RegionLocations.updateLocation:(Lorg/apache/hadoop/hbase/HRegionLocation;ZZ)Lorg/apache/hadoop/hbase/RegionLocations;
     217: astore_1
     218: aload_0
     219: getfield      #12                 // Field sn3:Lorg/apache/hadoop/hbase/ServerName;
     222: aload_1
     223: iconst_2
     224: invokevirtual #44                 // Method org/apache/hadoop/hbase/RegionLocations.getRegionLocation:(I)Lorg/apache/hadoop/hbase/HRegionLocation;
     227: invokevirtual #46                 // Method org/apache/hadoop/hbase/HRegionLocation.getServerName:()Lorg/apache/hadoop/hbase/ServerName;
     230: invokestatic  #47                 // Method org/junit/Assert.assertEquals:(Ljava/lang/Object;Ljava/lang/Object;)V
     233: aload_0
     234: getfield      #12                 // Field sn3:Lorg/apache/hadoop/hbase/ServerName;
     237: aload_1
     238: bipush        9
     240: invokevirtual #44                 // Method org/apache/hadoop/hbase/RegionLocations.getRegionLocation:(I)Lorg/apache/hadoop/hbase/HRegionLocation;
     243: invokevirtual #46                 // Method org/apache/hadoop/hbase/HRegionLocation.getServerName:()Lorg/apache/hadoop/hbase/ServerName;
     246: invokestatic  #47                 // Method org/junit/Assert.assertEquals:(Ljava/lang/Object;Ljava/lang/Object;)V
     249: aload_1
     250: aload_0
     251: aload_0
     252: getfield      #16                 // Field info2:Lorg/apache/hadoop/hbase/HRegionInfo;
     255: aload_0
     256: getfield      #8                  // Field sn1:Lorg/apache/hadoop/hbase/ServerName;
     259: ldc2_w        #51                 // long 11l
     262: invokespecial #50                 // Method hrl:(Lorg/apache/hadoop/hbase/HRegionInfo;Lorg/apache/hadoop/hbase/ServerName;J)Lorg/apache/hadoop/hbase/HRegionLocation;
     265: iconst_1
     266: iconst_0
     267: invokevirtual #49                 // Method org/apache/hadoop/hbase/RegionLocations.updateLocation:(Lorg/apache/hadoop/hbase/HRegionLocation;ZZ)Lorg/apache/hadoop/hbase/RegionLocations;
     270: astore_1
     271: aload_0
     272: getfield      #8                  // Field sn1:Lorg/apache/hadoop/hbase/ServerName;
     275: aload_1
     276: iconst_2
     277: invokevirtual #44                 // Method org/apache/hadoop/hbase/RegionLocations.getRegionLocation:(I)Lorg/apache/hadoop/hbase/HRegionLocation;
     280: invokevirtual #46                 // Method org/apache/hadoop/hbase/HRegionLocation.getServerName:()Lorg/apache/hadoop/hbase/ServerName;
     283: invokestatic  #47                 // Method org/junit/Assert.assertEquals:(Ljava/lang/Object;Ljava/lang/Object;)V
     286: aload_0
     287: getfield      #12                 // Field sn3:Lorg/apache/hadoop/hbase/ServerName;
     290: aload_1
     291: bipush        9
     293: invokevirtual #44                 // Method org/apache/hadoop/hbase/RegionLocations.getRegionLocation:(I)Lorg/apache/hadoop/hbase/HRegionLocation;
     296: invokevirtual #46                 // Method org/apache/hadoop/hbase/HRegionLocation.getServerName:()Lorg/apache/hadoop/hbase/ServerName;
     299: invokestatic  #47                 // Method org/junit/Assert.assertEquals:(Ljava/lang/Object;Ljava/lang/Object;)V
     302: aload_1
     303: aload_0
     304: aload_0
     305: getfield      #16                 // Field info2:Lorg/apache/hadoop/hbase/HRegionInfo;
     308: aload_0
     309: getfield      #10                 // Field sn2:Lorg/apache/hadoop/hbase/ServerName;
     312: ldc2_w        #53                 // long 9l
     315: invokespecial #50                 // Method hrl:(Lorg/apache/hadoop/hbase/HRegionInfo;Lorg/apache/hadoop/hbase/ServerName;J)Lorg/apache/hadoop/hbase/HRegionLocation;
     318: iconst_0
     319: iconst_1
     320: invokevirtual #49                 // Method org/apache/hadoop/hbase/RegionLocations.updateLocation:(Lorg/apache/hadoop/hbase/HRegionLocation;ZZ)Lorg/apache/hadoop/hbase/RegionLocations;
     323: astore_1
     324: aload_0
     325: getfield      #10                 // Field sn2:Lorg/apache/hadoop/hbase/ServerName;
     328: aload_1
     329: iconst_2
     330: invokevirtual #44                 // Method org/apache/hadoop/hbase/RegionLocations.getRegionLocation:(I)Lorg/apache/hadoop/hbase/HRegionLocation;
     333: invokevirtual #46                 // Method org/apache/hadoop/hbase/HRegionLocation.getServerName:()Lorg/apache/hadoop/hbase/ServerName;
     336: invokestatic  #47                 // Method org/junit/Assert.assertEquals:(Ljava/lang/Object;Ljava/lang/Object;)V
     339: aload_0
     340: getfield      #12                 // Field sn3:Lorg/apache/hadoop/hbase/ServerName;
     343: aload_1
     344: bipush        9
     346: invokevirtual #44                 // Method org/apache/hadoop/hbase/RegionLocations.getRegionLocation:(I)Lorg/apache/hadoop/hbase/HRegionLocation;
     349: invokevirtual #46                 // Method org/apache/hadoop/hbase/HRegionLocation.getServerName:()Lorg/apache/hadoop/hbase/ServerName;
     352: invokestatic  #47                 // Method org/junit/Assert.assertEquals:(Ljava/lang/Object;Ljava/lang/Object;)V
     355: return

  public void testMergeLocations();
    Code:
       0: new           #24                 // class org/apache/hadoop/hbase/RegionLocations
       3: dup
       4: iconst_0
       5: anewarray     #25                 // class org/apache/hadoop/hbase/HRegionLocation
       8: invokespecial #26                 // Method org/apache/hadoop/hbase/RegionLocations."<init>":([Lorg/apache/hadoop/hbase/HRegionLocation;)V
      11: astore_1
      12: new           #24                 // class org/apache/hadoop/hbase/RegionLocations
      15: dup
      16: iconst_0
      17: anewarray     #25                 // class org/apache/hadoop/hbase/HRegionLocation
      20: invokespecial #26                 // Method org/apache/hadoop/hbase/RegionLocations."<init>":([Lorg/apache/hadoop/hbase/HRegionLocation;)V
      23: astore_2
      24: aload_1
      25: aload_1
      26: aload_2
      27: invokevirtual #55                 // Method org/apache/hadoop/hbase/RegionLocations.mergeLocations:(Lorg/apache/hadoop/hbase/RegionLocations;)Lorg/apache/hadoop/hbase/RegionLocations;
      30: if_acmpne     37
      33: iconst_1
      34: goto          38
      37: iconst_0
      38: invokestatic  #28                 // Method org/junit/Assert.assertTrue:(Z)V
      41: aload_0
      42: iconst_1
      43: anewarray     #25                 // class org/apache/hadoop/hbase/HRegionLocation
      46: dup
      47: iconst_0
      48: aload_0
      49: aload_0
      50: getfield      #14                 // Field info0:Lorg/apache/hadoop/hbase/HRegionInfo;
      53: aload_0
      54: getfield      #6                  // Field sn0:Lorg/apache/hadoop/hbase/ServerName;
      57: invokespecial #33                 // Method hrl:(Lorg/apache/hadoop/hbase/HRegionInfo;Lorg/apache/hadoop/hbase/ServerName;)Lorg/apache/hadoop/hbase/HRegionLocation;
      60: aastore
      61: invokespecial #32                 // Method hrll:([Lorg/apache/hadoop/hbase/HRegionLocation;)Lorg/apache/hadoop/hbase/RegionLocations;
      64: astore_2
      65: aload_1
      66: aload_2
      67: invokevirtual #55                 // Method org/apache/hadoop/hbase/RegionLocations.mergeLocations:(Lorg/apache/hadoop/hbase/RegionLocations;)Lorg/apache/hadoop/hbase/RegionLocations;
      70: astore_1
      71: aload_0
      72: getfield      #6                  // Field sn0:Lorg/apache/hadoop/hbase/ServerName;
      75: aload_1
      76: iconst_0
      77: invokevirtual #44                 // Method org/apache/hadoop/hbase/RegionLocations.getRegionLocation:(I)Lorg/apache/hadoop/hbase/HRegionLocation;
      80: invokevirtual #46                 // Method org/apache/hadoop/hbase/HRegionLocation.getServerName:()Lorg/apache/hadoop/hbase/ServerName;
      83: invokestatic  #47                 // Method org/junit/Assert.assertEquals:(Ljava/lang/Object;Ljava/lang/Object;)V
      86: aload_0
      87: iconst_0
      88: anewarray     #25                 // class org/apache/hadoop/hbase/HRegionLocation
      91: invokespecial #32                 // Method hrll:([Lorg/apache/hadoop/hbase/HRegionLocation;)Lorg/apache/hadoop/hbase/RegionLocations;
      94: astore_1
      95: aload_2
      96: aload_1
      97: invokevirtual #55                 // Method org/apache/hadoop/hbase/RegionLocations.mergeLocations:(Lorg/apache/hadoop/hbase/RegionLocations;)Lorg/apache/hadoop/hbase/RegionLocations;
     100: astore_1
     101: aload_0
     102: getfield      #6                  // Field sn0:Lorg/apache/hadoop/hbase/ServerName;
     105: aload_1
     106: iconst_0
     107: invokevirtual #44                 // Method org/apache/hadoop/hbase/RegionLocations.getRegionLocation:(I)Lorg/apache/hadoop/hbase/HRegionLocation;
     110: invokevirtual #46                 // Method org/apache/hadoop/hbase/HRegionLocation.getServerName:()Lorg/apache/hadoop/hbase/ServerName;
     113: invokestatic  #47                 // Method org/junit/Assert.assertEquals:(Ljava/lang/Object;Ljava/lang/Object;)V
     116: aload_0
     117: iconst_2
     118: anewarray     #25                 // class org/apache/hadoop/hbase/HRegionLocation
     121: dup
     122: iconst_0
     123: aload_0
     124: aload_0
     125: getfield      #14                 // Field info0:Lorg/apache/hadoop/hbase/HRegionInfo;
     128: aload_0
     129: getfield      #6                  // Field sn0:Lorg/apache/hadoop/hbase/ServerName;
     132: invokespecial #33                 // Method hrl:(Lorg/apache/hadoop/hbase/HRegionInfo;Lorg/apache/hadoop/hbase/ServerName;)Lorg/apache/hadoop/hbase/HRegionLocation;
     135: aastore
     136: dup
     137: iconst_1
     138: aload_0
     139: aload_0
     140: getfield      #15                 // Field info1:Lorg/apache/hadoop/hbase/HRegionInfo;
     143: aload_0
     144: getfield      #8                  // Field sn1:Lorg/apache/hadoop/hbase/ServerName;
     147: invokespecial #33                 // Method hrl:(Lorg/apache/hadoop/hbase/HRegionInfo;Lorg/apache/hadoop/hbase/ServerName;)Lorg/apache/hadoop/hbase/HRegionLocation;
     150: aastore
     151: invokespecial #32                 // Method hrll:([Lorg/apache/hadoop/hbase/HRegionLocation;)Lorg/apache/hadoop/hbase/RegionLocations;
     154: astore_1
     155: aload_0
     156: iconst_1
     157: anewarray     #25                 // class org/apache/hadoop/hbase/HRegionLocation
     160: dup
     161: iconst_0
     162: aload_0
     163: aload_0
     164: getfield      #16                 // Field info2:Lorg/apache/hadoop/hbase/HRegionInfo;
     167: aload_0
     168: getfield      #10                 // Field sn2:Lorg/apache/hadoop/hbase/ServerName;
     171: invokespecial #33                 // Method hrl:(Lorg/apache/hadoop/hbase/HRegionInfo;Lorg/apache/hadoop/hbase/ServerName;)Lorg/apache/hadoop/hbase/HRegionLocation;
     174: aastore
     175: invokespecial #32                 // Method hrll:([Lorg/apache/hadoop/hbase/HRegionLocation;)Lorg/apache/hadoop/hbase/RegionLocations;
     178: astore_2
     179: aload_2
     180: aload_1
     181: invokevirtual #55                 // Method org/apache/hadoop/hbase/RegionLocations.mergeLocations:(Lorg/apache/hadoop/hbase/RegionLocations;)Lorg/apache/hadoop/hbase/RegionLocations;
     184: astore_1
     185: aload_0
     186: getfield      #6                  // Field sn0:Lorg/apache/hadoop/hbase/ServerName;
     189: aload_1
     190: iconst_0
     191: invokevirtual #44                 // Method org/apache/hadoop/hbase/RegionLocations.getRegionLocation:(I)Lorg/apache/hadoop/hbase/HRegionLocation;
     194: invokevirtual #46                 // Method org/apache/hadoop/hbase/HRegionLocation.getServerName:()Lorg/apache/hadoop/hbase/ServerName;
     197: invokestatic  #47                 // Method org/junit/Assert.assertEquals:(Ljava/lang/Object;Ljava/lang/Object;)V
     200: aload_0
     201: getfield      #8                  // Field sn1:Lorg/apache/hadoop/hbase/ServerName;
     204: aload_1
     205: iconst_1
     206: invokevirtual #44                 // Method org/apache/hadoop/hbase/RegionLocations.getRegionLocation:(I)Lorg/apache/hadoop/hbase/HRegionLocation;
     209: invokevirtual #46                 // Method org/apache/hadoop/hbase/HRegionLocation.getServerName:()Lorg/apache/hadoop/hbase/ServerName;
     212: invokestatic  #47                 // Method org/junit/Assert.assertEquals:(Ljava/lang/Object;Ljava/lang/Object;)V
     215: ldc2_w        #56                 // long 2l
     218: aload_1
     219: invokevirtual #29                 // Method org/apache/hadoop/hbase/RegionLocations.size:()I
     222: i2l
     223: invokestatic  #30                 // Method org/junit/Assert.assertEquals:(JJ)V
     226: aload_0
     227: iconst_2
     228: anewarray     #25                 // class org/apache/hadoop/hbase/HRegionLocation
     231: dup
     232: iconst_0
     233: aload_0
     234: aload_0
     235: getfield      #14                 // Field info0:Lorg/apache/hadoop/hbase/HRegionInfo;
     238: aload_0
     239: getfield      #6                  // Field sn0:Lorg/apache/hadoop/hbase/ServerName;
     242: invokespecial #33                 // Method hrl:(Lorg/apache/hadoop/hbase/HRegionInfo;Lorg/apache/hadoop/hbase/ServerName;)Lorg/apache/hadoop/hbase/HRegionLocation;
     245: aastore
     246: dup
     247: iconst_1
     248: aload_0
     249: aload_0
     250: getfield      #15                 // Field info1:Lorg/apache/hadoop/hbase/HRegionInfo;
     253: aload_0
     254: getfield      #8                  // Field sn1:Lorg/apache/hadoop/hbase/ServerName;
     257: invokespecial #33                 // Method hrl:(Lorg/apache/hadoop/hbase/HRegionInfo;Lorg/apache/hadoop/hbase/ServerName;)Lorg/apache/hadoop/hbase/HRegionLocation;
     260: aastore
     261: invokespecial #32                 // Method hrll:([Lorg/apache/hadoop/hbase/HRegionLocation;)Lorg/apache/hadoop/hbase/RegionLocations;
     264: astore_1
     265: aload_0
     266: iconst_1
     267: anewarray     #25                 // class org/apache/hadoop/hbase/HRegionLocation
     270: dup
     271: iconst_0
     272: aload_0
     273: aload_0
     274: getfield      #16                 // Field info2:Lorg/apache/hadoop/hbase/HRegionInfo;
     277: aload_0
     278: getfield      #10                 // Field sn2:Lorg/apache/hadoop/hbase/ServerName;
     281: invokespecial #33                 // Method hrl:(Lorg/apache/hadoop/hbase/HRegionInfo;Lorg/apache/hadoop/hbase/ServerName;)Lorg/apache/hadoop/hbase/HRegionLocation;
     284: aastore
     285: invokespecial #32                 // Method hrll:([Lorg/apache/hadoop/hbase/HRegionLocation;)Lorg/apache/hadoop/hbase/RegionLocations;
     288: astore_2
     289: aload_1
     290: aload_2
     291: invokevirtual #55                 // Method org/apache/hadoop/hbase/RegionLocations.mergeLocations:(Lorg/apache/hadoop/hbase/RegionLocations;)Lorg/apache/hadoop/hbase/RegionLocations;
     294: astore_1
     295: aload_0
     296: getfield      #6                  // Field sn0:Lorg/apache/hadoop/hbase/ServerName;
     299: aload_1
     300: iconst_0
     301: invokevirtual #44                 // Method org/apache/hadoop/hbase/RegionLocations.getRegionLocation:(I)Lorg/apache/hadoop/hbase/HRegionLocation;
     304: invokevirtual #46                 // Method org/apache/hadoop/hbase/HRegionLocation.getServerName:()Lorg/apache/hadoop/hbase/ServerName;
     307: invokestatic  #47                 // Method org/junit/Assert.assertEquals:(Ljava/lang/Object;Ljava/lang/Object;)V
     310: aload_0
     311: getfield      #8                  // Field sn1:Lorg/apache/hadoop/hbase/ServerName;
     314: aload_1
     315: iconst_1
     316: invokevirtual #44                 // Method org/apache/hadoop/hbase/RegionLocations.getRegionLocation:(I)Lorg/apache/hadoop/hbase/HRegionLocation;
     319: invokevirtual #46                 // Method org/apache/hadoop/hbase/HRegionLocation.getServerName:()Lorg/apache/hadoop/hbase/ServerName;
     322: invokestatic  #47                 // Method org/junit/Assert.assertEquals:(Ljava/lang/Object;Ljava/lang/Object;)V
     325: aload_0
     326: getfield      #10                 // Field sn2:Lorg/apache/hadoop/hbase/ServerName;
     329: aload_1
     330: iconst_2
     331: invokevirtual #44                 // Method org/apache/hadoop/hbase/RegionLocations.getRegionLocation:(I)Lorg/apache/hadoop/hbase/HRegionLocation;
     334: invokevirtual #46                 // Method org/apache/hadoop/hbase/HRegionLocation.getServerName:()Lorg/apache/hadoop/hbase/ServerName;
     337: invokestatic  #47                 // Method org/junit/Assert.assertEquals:(Ljava/lang/Object;Ljava/lang/Object;)V
     340: aload_0
     341: iconst_2
     342: anewarray     #25                 // class org/apache/hadoop/hbase/HRegionLocation
     345: dup
     346: iconst_0
     347: aload_0
     348: aload_0
     349: getfield      #14                 // Field info0:Lorg/apache/hadoop/hbase/HRegionInfo;
     352: aload_0
     353: getfield      #6                  // Field sn0:Lorg/apache/hadoop/hbase/ServerName;
     356: invokespecial #33                 // Method hrl:(Lorg/apache/hadoop/hbase/HRegionInfo;Lorg/apache/hadoop/hbase/ServerName;)Lorg/apache/hadoop/hbase/HRegionLocation;
     359: aastore
     360: dup
     361: iconst_1
     362: aload_0
     363: aload_0
     364: getfield      #15                 // Field info1:Lorg/apache/hadoop/hbase/HRegionInfo;
     367: aload_0
     368: getfield      #8                  // Field sn1:Lorg/apache/hadoop/hbase/ServerName;
     371: invokespecial #33                 // Method hrl:(Lorg/apache/hadoop/hbase/HRegionInfo;Lorg/apache/hadoop/hbase/ServerName;)Lorg/apache/hadoop/hbase/HRegionLocation;
     374: aastore
     375: invokespecial #32                 // Method hrll:([Lorg/apache/hadoop/hbase/HRegionLocation;)Lorg/apache/hadoop/hbase/RegionLocations;
     378: astore_1
     379: aload_0
     380: iconst_3
     381: anewarray     #25                 // class org/apache/hadoop/hbase/HRegionLocation
     384: dup
     385: iconst_0
     386: aload_0
     387: aload_0
     388: getfield      #14                 // Field info0:Lorg/apache/hadoop/hbase/HRegionInfo;
     391: aload_0
     392: getfield      #10                 // Field sn2:Lorg/apache/hadoop/hbase/ServerName;
     395: invokespecial #33                 // Method hrl:(Lorg/apache/hadoop/hbase/HRegionInfo;Lorg/apache/hadoop/hbase/ServerName;)Lorg/apache/hadoop/hbase/HRegionLocation;
     398: aastore
     399: dup
     400: iconst_1
     401: aload_0
     402: aload_0
     403: getfield      #15                 // Field info1:Lorg/apache/hadoop/hbase/HRegionInfo;
     406: aload_0
     407: getfield      #10                 // Field sn2:Lorg/apache/hadoop/hbase/ServerName;
     410: invokespecial #33                 // Method hrl:(Lorg/apache/hadoop/hbase/HRegionInfo;Lorg/apache/hadoop/hbase/ServerName;)Lorg/apache/hadoop/hbase/HRegionLocation;
     413: aastore
     414: dup
     415: iconst_2
     416: aload_0
     417: aload_0
     418: getfield      #17                 // Field info9:Lorg/apache/hadoop/hbase/HRegionInfo;
     421: aload_0
     422: getfield      #12                 // Field sn3:Lorg/apache/hadoop/hbase/ServerName;
     425: invokespecial #33                 // Method hrl:(Lorg/apache/hadoop/hbase/HRegionInfo;Lorg/apache/hadoop/hbase/ServerName;)Lorg/apache/hadoop/hbase/HRegionLocation;
     428: aastore
     429: invokespecial #32                 // Method hrll:([Lorg/apache/hadoop/hbase/HRegionLocation;)Lorg/apache/hadoop/hbase/RegionLocations;
     432: astore_2
     433: aload_2
     434: aload_1
     435: invokevirtual #55                 // Method org/apache/hadoop/hbase/RegionLocations.mergeLocations:(Lorg/apache/hadoop/hbase/RegionLocations;)Lorg/apache/hadoop/hbase/RegionLocations;
     438: astore_1
     439: ldc2_w        #56                 // long 2l
     442: aload_1
     443: invokevirtual #29                 // Method org/apache/hadoop/hbase/RegionLocations.size:()I
     446: i2l
     447: invokestatic  #30                 // Method org/junit/Assert.assertEquals:(JJ)V
     450: aload_0
     451: getfield      #6                  // Field sn0:Lorg/apache/hadoop/hbase/ServerName;
     454: aload_1
     455: iconst_0
     456: invokevirtual #44                 // Method org/apache/hadoop/hbase/RegionLocations.getRegionLocation:(I)Lorg/apache/hadoop/hbase/HRegionLocation;
     459: invokevirtual #46                 // Method org/apache/hadoop/hbase/HRegionLocation.getServerName:()Lorg/apache/hadoop/hbase/ServerName;
     462: invokestatic  #47                 // Method org/junit/Assert.assertEquals:(Ljava/lang/Object;Ljava/lang/Object;)V
     465: aload_0
     466: getfield      #8                  // Field sn1:Lorg/apache/hadoop/hbase/ServerName;
     469: aload_1
     470: iconst_1
     471: invokevirtual #44                 // Method org/apache/hadoop/hbase/RegionLocations.getRegionLocation:(I)Lorg/apache/hadoop/hbase/HRegionLocation;
     474: invokevirtual #46                 // Method org/apache/hadoop/hbase/HRegionLocation.getServerName:()Lorg/apache/hadoop/hbase/ServerName;
     477: invokestatic  #47                 // Method org/junit/Assert.assertEquals:(Ljava/lang/Object;Ljava/lang/Object;)V
     480: aload_0
     481: iconst_2
     482: anewarray     #25                 // class org/apache/hadoop/hbase/HRegionLocation
     485: dup
     486: iconst_0
     487: aload_0
     488: aload_0
     489: getfield      #14                 // Field info0:Lorg/apache/hadoop/hbase/HRegionInfo;
     492: aload_0
     493: getfield      #6                  // Field sn0:Lorg/apache/hadoop/hbase/ServerName;
     496: invokespecial #33                 // Method hrl:(Lorg/apache/hadoop/hbase/HRegionInfo;Lorg/apache/hadoop/hbase/ServerName;)Lorg/apache/hadoop/hbase/HRegionLocation;
     499: aastore
     500: dup
     501: iconst_1
     502: aload_0
     503: aload_0
     504: getfield      #15                 // Field info1:Lorg/apache/hadoop/hbase/HRegionInfo;
     507: aload_0
     508: getfield      #8                  // Field sn1:Lorg/apache/hadoop/hbase/ServerName;
     511: invokespecial #33                 // Method hrl:(Lorg/apache/hadoop/hbase/HRegionInfo;Lorg/apache/hadoop/hbase/ServerName;)Lorg/apache/hadoop/hbase/HRegionLocation;
     514: aastore
     515: invokespecial #32                 // Method hrll:([Lorg/apache/hadoop/hbase/HRegionLocation;)Lorg/apache/hadoop/hbase/RegionLocations;
     518: astore_1
     519: aload_0
     520: iconst_3
     521: anewarray     #25                 // class org/apache/hadoop/hbase/HRegionLocation
     524: dup
     525: iconst_0
     526: aload_0
     527: aload_0
     528: getfield      #14                 // Field info0:Lorg/apache/hadoop/hbase/HRegionInfo;
     531: aload_0
     532: getfield      #10                 // Field sn2:Lorg/apache/hadoop/hbase/ServerName;
     535: invokespecial #33                 // Method hrl:(Lorg/apache/hadoop/hbase/HRegionInfo;Lorg/apache/hadoop/hbase/ServerName;)Lorg/apache/hadoop/hbase/HRegionLocation;
     538: aastore
     539: dup
     540: iconst_1
     541: aload_0
     542: aload_0
     543: getfield      #15                 // Field info1:Lorg/apache/hadoop/hbase/HRegionInfo;
     546: aload_0
     547: getfield      #10                 // Field sn2:Lorg/apache/hadoop/hbase/ServerName;
     550: invokespecial #33                 // Method hrl:(Lorg/apache/hadoop/hbase/HRegionInfo;Lorg/apache/hadoop/hbase/ServerName;)Lorg/apache/hadoop/hbase/HRegionLocation;
     553: aastore
     554: dup
     555: iconst_2
     556: aload_0
     557: aload_0
     558: getfield      #17                 // Field info9:Lorg/apache/hadoop/hbase/HRegionInfo;
     561: aload_0
     562: getfield      #12                 // Field sn3:Lorg/apache/hadoop/hbase/ServerName;
     565: invokespecial #33                 // Method hrl:(Lorg/apache/hadoop/hbase/HRegionInfo;Lorg/apache/hadoop/hbase/ServerName;)Lorg/apache/hadoop/hbase/HRegionLocation;
     568: aastore
     569: invokespecial #32                 // Method hrll:([Lorg/apache/hadoop/hbase/HRegionLocation;)Lorg/apache/hadoop/hbase/RegionLocations;
     572: astore_2
     573: aload_1
     574: aload_2
     575: invokevirtual #55                 // Method org/apache/hadoop/hbase/RegionLocations.mergeLocations:(Lorg/apache/hadoop/hbase/RegionLocations;)Lorg/apache/hadoop/hbase/RegionLocations;
     578: astore_1
     579: ldc2_w        #3                  // long 10l
     582: aload_1
     583: invokevirtual #29                 // Method org/apache/hadoop/hbase/RegionLocations.size:()I
     586: i2l
     587: invokestatic  #30                 // Method org/junit/Assert.assertEquals:(JJ)V
     590: aload_0
     591: getfield      #10                 // Field sn2:Lorg/apache/hadoop/hbase/ServerName;
     594: aload_1
     595: iconst_0
     596: invokevirtual #44                 // Method org/apache/hadoop/hbase/RegionLocations.getRegionLocation:(I)Lorg/apache/hadoop/hbase/HRegionLocation;
     599: invokevirtual #46                 // Method org/apache/hadoop/hbase/HRegionLocation.getServerName:()Lorg/apache/hadoop/hbase/ServerName;
     602: invokestatic  #47                 // Method org/junit/Assert.assertEquals:(Ljava/lang/Object;Ljava/lang/Object;)V
     605: aload_0
     606: getfield      #10                 // Field sn2:Lorg/apache/hadoop/hbase/ServerName;
     609: aload_1
     610: iconst_1
     611: invokevirtual #44                 // Method org/apache/hadoop/hbase/RegionLocations.getRegionLocation:(I)Lorg/apache/hadoop/hbase/HRegionLocation;
     614: invokevirtual #46                 // Method org/apache/hadoop/hbase/HRegionLocation.getServerName:()Lorg/apache/hadoop/hbase/ServerName;
     617: invokestatic  #47                 // Method org/junit/Assert.assertEquals:(Ljava/lang/Object;Ljava/lang/Object;)V
     620: aload_0
     621: getfield      #12                 // Field sn3:Lorg/apache/hadoop/hbase/ServerName;
     624: aload_1
     625: bipush        9
     627: invokevirtual #44                 // Method org/apache/hadoop/hbase/RegionLocations.getRegionLocation:(I)Lorg/apache/hadoop/hbase/HRegionLocation;
     630: invokevirtual #46                 // Method org/apache/hadoop/hbase/HRegionLocation.getServerName:()Lorg/apache/hadoop/hbase/ServerName;
     633: invokestatic  #47                 // Method org/junit/Assert.assertEquals:(Ljava/lang/Object;Ljava/lang/Object;)V
     636: aload_0
     637: iconst_2
     638: anewarray     #25                 // class org/apache/hadoop/hbase/HRegionLocation
     641: dup
     642: iconst_0
     643: aload_0
     644: aload_0
     645: getfield      #14                 // Field info0:Lorg/apache/hadoop/hbase/HRegionInfo;
     648: aload_0
     649: getfield      #6                  // Field sn0:Lorg/apache/hadoop/hbase/ServerName;
     652: ldc2_w        #3                  // long 10l
     655: invokespecial #50                 // Method hrl:(Lorg/apache/hadoop/hbase/HRegionInfo;Lorg/apache/hadoop/hbase/ServerName;J)Lorg/apache/hadoop/hbase/HRegionLocation;
     658: aastore
     659: dup
     660: iconst_1
     661: aload_0
     662: aload_0
     663: getfield      #15                 // Field info1:Lorg/apache/hadoop/hbase/HRegionInfo;
     666: aload_0
     667: getfield      #8                  // Field sn1:Lorg/apache/hadoop/hbase/ServerName;
     670: ldc2_w        #3                  // long 10l
     673: invokespecial #50                 // Method hrl:(Lorg/apache/hadoop/hbase/HRegionInfo;Lorg/apache/hadoop/hbase/ServerName;J)Lorg/apache/hadoop/hbase/HRegionLocation;
     676: aastore
     677: invokespecial #32                 // Method hrll:([Lorg/apache/hadoop/hbase/HRegionLocation;)Lorg/apache/hadoop/hbase/RegionLocations;
     680: astore_1
     681: aload_0
     682: iconst_3
     683: anewarray     #25                 // class org/apache/hadoop/hbase/HRegionLocation
     686: dup
     687: iconst_0
     688: aload_0
     689: aload_0
     690: getfield      #14                 // Field info0:Lorg/apache/hadoop/hbase/HRegionInfo;
     693: aload_0
     694: getfield      #10                 // Field sn2:Lorg/apache/hadoop/hbase/ServerName;
     697: ldc2_w        #51                 // long 11l
     700: invokespecial #50                 // Method hrl:(Lorg/apache/hadoop/hbase/HRegionInfo;Lorg/apache/hadoop/hbase/ServerName;J)Lorg/apache/hadoop/hbase/HRegionLocation;
     703: aastore
     704: dup
     705: iconst_1
     706: aload_0
     707: aload_0
     708: getfield      #15                 // Field info1:Lorg/apache/hadoop/hbase/HRegionInfo;
     711: aload_0
     712: getfield      #10                 // Field sn2:Lorg/apache/hadoop/hbase/ServerName;
     715: ldc2_w        #51                 // long 11l
     718: invokespecial #50                 // Method hrl:(Lorg/apache/hadoop/hbase/HRegionInfo;Lorg/apache/hadoop/hbase/ServerName;J)Lorg/apache/hadoop/hbase/HRegionLocation;
     721: aastore
     722: dup
     723: iconst_2
     724: aload_0
     725: aload_0
     726: getfield      #17                 // Field info9:Lorg/apache/hadoop/hbase/HRegionInfo;
     729: aload_0
     730: getfield      #12                 // Field sn3:Lorg/apache/hadoop/hbase/ServerName;
     733: ldc2_w        #51                 // long 11l
     736: invokespecial #50                 // Method hrl:(Lorg/apache/hadoop/hbase/HRegionInfo;Lorg/apache/hadoop/hbase/ServerName;J)Lorg/apache/hadoop/hbase/HRegionLocation;
     739: aastore
     740: invokespecial #32                 // Method hrll:([Lorg/apache/hadoop/hbase/HRegionLocation;)Lorg/apache/hadoop/hbase/RegionLocations;
     743: astore_2
     744: aload_1
     745: aload_2
     746: invokevirtual #55                 // Method org/apache/hadoop/hbase/RegionLocations.mergeLocations:(Lorg/apache/hadoop/hbase/RegionLocations;)Lorg/apache/hadoop/hbase/RegionLocations;
     749: astore_1
     750: ldc2_w        #3                  // long 10l
     753: aload_1
     754: invokevirtual #29                 // Method org/apache/hadoop/hbase/RegionLocations.size:()I
     757: i2l
     758: invokestatic  #30                 // Method org/junit/Assert.assertEquals:(JJ)V
     761: aload_0
     762: getfield      #10                 // Field sn2:Lorg/apache/hadoop/hbase/ServerName;
     765: aload_1
     766: iconst_0
     767: invokevirtual #44                 // Method org/apache/hadoop/hbase/RegionLocations.getRegionLocation:(I)Lorg/apache/hadoop/hbase/HRegionLocation;
     770: invokevirtual #46                 // Method org/apache/hadoop/hbase/HRegionLocation.getServerName:()Lorg/apache/hadoop/hbase/ServerName;
     773: invokestatic  #47                 // Method org/junit/Assert.assertEquals:(Ljava/lang/Object;Ljava/lang/Object;)V
     776: aload_0
     777: getfield      #10                 // Field sn2:Lorg/apache/hadoop/hbase/ServerName;
     780: aload_1
     781: iconst_1
     782: invokevirtual #44                 // Method org/apache/hadoop/hbase/RegionLocations.getRegionLocation:(I)Lorg/apache/hadoop/hbase/HRegionLocation;
     785: invokevirtual #46                 // Method org/apache/hadoop/hbase/HRegionLocation.getServerName:()Lorg/apache/hadoop/hbase/ServerName;
     788: invokestatic  #47                 // Method org/junit/Assert.assertEquals:(Ljava/lang/Object;Ljava/lang/Object;)V
     791: aload_0
     792: getfield      #12                 // Field sn3:Lorg/apache/hadoop/hbase/ServerName;
     795: aload_1
     796: bipush        9
     798: invokevirtual #44                 // Method org/apache/hadoop/hbase/RegionLocations.getRegionLocation:(I)Lorg/apache/hadoop/hbase/HRegionLocation;
     801: invokevirtual #46                 // Method org/apache/hadoop/hbase/HRegionLocation.getServerName:()Lorg/apache/hadoop/hbase/ServerName;
     804: invokestatic  #47                 // Method org/junit/Assert.assertEquals:(Ljava/lang/Object;Ljava/lang/Object;)V
     807: aload_0
     808: iconst_2
     809: anewarray     #25                 // class org/apache/hadoop/hbase/HRegionLocation
     812: dup
     813: iconst_0
     814: aload_0
     815: aload_0
     816: getfield      #14                 // Field info0:Lorg/apache/hadoop/hbase/HRegionInfo;
     819: aload_0
     820: getfield      #6                  // Field sn0:Lorg/apache/hadoop/hbase/ServerName;
     823: ldc2_w        #3                  // long 10l
     826: invokespecial #50                 // Method hrl:(Lorg/apache/hadoop/hbase/HRegionInfo;Lorg/apache/hadoop/hbase/ServerName;J)Lorg/apache/hadoop/hbase/HRegionLocation;
     829: aastore
     830: dup
     831: iconst_1
     832: aload_0
     833: aload_0
     834: getfield      #15                 // Field info1:Lorg/apache/hadoop/hbase/HRegionInfo;
     837: aload_0
     838: getfield      #8                  // Field sn1:Lorg/apache/hadoop/hbase/ServerName;
     841: ldc2_w        #3                  // long 10l
     844: invokespecial #50                 // Method hrl:(Lorg/apache/hadoop/hbase/HRegionInfo;Lorg/apache/hadoop/hbase/ServerName;J)Lorg/apache/hadoop/hbase/HRegionLocation;
     847: aastore
     848: invokespecial #32                 // Method hrll:([Lorg/apache/hadoop/hbase/HRegionLocation;)Lorg/apache/hadoop/hbase/RegionLocations;
     851: astore_1
     852: aload_0
     853: iconst_3
     854: anewarray     #25                 // class org/apache/hadoop/hbase/HRegionLocation
     857: dup
     858: iconst_0
     859: aload_0
     860: aload_0
     861: getfield      #14                 // Field info0:Lorg/apache/hadoop/hbase/HRegionInfo;
     864: aload_0
     865: getfield      #10                 // Field sn2:Lorg/apache/hadoop/hbase/ServerName;
     868: ldc2_w        #51                 // long 11l
     871: invokespecial #50                 // Method hrl:(Lorg/apache/hadoop/hbase/HRegionInfo;Lorg/apache/hadoop/hbase/ServerName;J)Lorg/apache/hadoop/hbase/HRegionLocation;
     874: aastore
     875: dup
     876: iconst_1
     877: aload_0
     878: aload_0
     879: getfield      #15                 // Field info1:Lorg/apache/hadoop/hbase/HRegionInfo;
     882: aload_0
     883: getfield      #10                 // Field sn2:Lorg/apache/hadoop/hbase/ServerName;
     886: ldc2_w        #51                 // long 11l
     889: invokespecial #50                 // Method hrl:(Lorg/apache/hadoop/hbase/HRegionInfo;Lorg/apache/hadoop/hbase/ServerName;J)Lorg/apache/hadoop/hbase/HRegionLocation;
     892: aastore
     893: dup
     894: iconst_2
     895: aload_0
     896: aload_0
     897: getfield      #17                 // Field info9:Lorg/apache/hadoop/hbase/HRegionInfo;
     900: aload_0
     901: getfield      #12                 // Field sn3:Lorg/apache/hadoop/hbase/ServerName;
     904: ldc2_w        #51                 // long 11l
     907: invokespecial #50                 // Method hrl:(Lorg/apache/hadoop/hbase/HRegionInfo;Lorg/apache/hadoop/hbase/ServerName;J)Lorg/apache/hadoop/hbase/HRegionLocation;
     910: aastore
     911: invokespecial #32                 // Method hrll:([Lorg/apache/hadoop/hbase/HRegionLocation;)Lorg/apache/hadoop/hbase/RegionLocations;
     914: astore_2
     915: aload_1
     916: aload_2
     917: invokevirtual #55                 // Method org/apache/hadoop/hbase/RegionLocations.mergeLocations:(Lorg/apache/hadoop/hbase/RegionLocations;)Lorg/apache/hadoop/hbase/RegionLocations;
     920: astore_1
     921: ldc2_w        #3                  // long 10l
     924: aload_1
     925: invokevirtual #29                 // Method org/apache/hadoop/hbase/RegionLocations.size:()I
     928: i2l
     929: invokestatic  #30                 // Method org/junit/Assert.assertEquals:(JJ)V
     932: aload_0
     933: getfield      #10                 // Field sn2:Lorg/apache/hadoop/hbase/ServerName;
     936: aload_1
     937: iconst_0
     938: invokevirtual #44                 // Method org/apache/hadoop/hbase/RegionLocations.getRegionLocation:(I)Lorg/apache/hadoop/hbase/HRegionLocation;
     941: invokevirtual #46                 // Method org/apache/hadoop/hbase/HRegionLocation.getServerName:()Lorg/apache/hadoop/hbase/ServerName;
     944: invokestatic  #47                 // Method org/junit/Assert.assertEquals:(Ljava/lang/Object;Ljava/lang/Object;)V
     947: aload_0
     948: getfield      #10                 // Field sn2:Lorg/apache/hadoop/hbase/ServerName;
     951: aload_1
     952: iconst_1
     953: invokevirtual #44                 // Method org/apache/hadoop/hbase/RegionLocations.getRegionLocation:(I)Lorg/apache/hadoop/hbase/HRegionLocation;
     956: invokevirtual #46                 // Method org/apache/hadoop/hbase/HRegionLocation.getServerName:()Lorg/apache/hadoop/hbase/ServerName;
     959: invokestatic  #47                 // Method org/junit/Assert.assertEquals:(Ljava/lang/Object;Ljava/lang/Object;)V
     962: aload_0
     963: getfield      #12                 // Field sn3:Lorg/apache/hadoop/hbase/ServerName;
     966: aload_1
     967: bipush        9
     969: invokevirtual #44                 // Method org/apache/hadoop/hbase/RegionLocations.getRegionLocation:(I)Lorg/apache/hadoop/hbase/HRegionLocation;
     972: invokevirtual #46                 // Method org/apache/hadoop/hbase/HRegionLocation.getServerName:()Lorg/apache/hadoop/hbase/ServerName;
     975: invokestatic  #47                 // Method org/junit/Assert.assertEquals:(Ljava/lang/Object;Ljava/lang/Object;)V
     978: return

  public void testMergeLocationsWithDifferentRegionId();
    Code:
       0: aload_0
       1: aload_0
       2: getfield      #20                 // Field regionId1:J
       5: iconst_0
       6: invokespecial #34                 // Method hri:(JI)Lorg/apache/hadoop/hbase/HRegionInfo;
       9: astore_3
      10: aload_0
      11: aload_0
      12: getfield      #20                 // Field regionId1:J
      15: iconst_1
      16: invokespecial #34                 // Method hri:(JI)Lorg/apache/hadoop/hbase/HRegionInfo;
      19: astore        4
      21: aload_0
      22: aload_0
      23: getfield      #23                 // Field regionId2:J
      26: iconst_2
      27: invokespecial #34                 // Method hri:(JI)Lorg/apache/hadoop/hbase/HRegionInfo;
      30: astore        5
      32: aload_0
      33: iconst_1
      34: anewarray     #25                 // class org/apache/hadoop/hbase/HRegionLocation
      37: dup
      38: iconst_0
      39: aload_0
      40: aload         5
      42: aload_0
      43: getfield      #8                  // Field sn1:Lorg/apache/hadoop/hbase/ServerName;
      46: invokespecial #33                 // Method hrl:(Lorg/apache/hadoop/hbase/HRegionInfo;Lorg/apache/hadoop/hbase/ServerName;)Lorg/apache/hadoop/hbase/HRegionLocation;
      49: aastore
      50: invokespecial #32                 // Method hrll:([Lorg/apache/hadoop/hbase/HRegionLocation;)Lorg/apache/hadoop/hbase/RegionLocations;
      53: astore_1
      54: aload_0
      55: iconst_2
      56: anewarray     #25                 // class org/apache/hadoop/hbase/HRegionLocation
      59: dup
      60: iconst_0
      61: aload_0
      62: aload_3
      63: aload_0
      64: getfield      #10                 // Field sn2:Lorg/apache/hadoop/hbase/ServerName;
      67: invokespecial #33                 // Method hrl:(Lorg/apache/hadoop/hbase/HRegionInfo;Lorg/apache/hadoop/hbase/ServerName;)Lorg/apache/hadoop/hbase/HRegionLocation;
      70: aastore
      71: dup
      72: iconst_1
      73: aload_0
      74: aload         4
      76: aload_0
      77: getfield      #10                 // Field sn2:Lorg/apache/hadoop/hbase/ServerName;
      80: invokespecial #33                 // Method hrl:(Lorg/apache/hadoop/hbase/HRegionInfo;Lorg/apache/hadoop/hbase/ServerName;)Lorg/apache/hadoop/hbase/HRegionLocation;
      83: aastore
      84: invokespecial #32                 // Method hrll:([Lorg/apache/hadoop/hbase/HRegionLocation;)Lorg/apache/hadoop/hbase/RegionLocations;
      87: astore_2
      88: aload_2
      89: aload_1
      90: invokevirtual #55                 // Method org/apache/hadoop/hbase/RegionLocations.mergeLocations:(Lorg/apache/hadoop/hbase/RegionLocations;)Lorg/apache/hadoop/hbase/RegionLocations;
      93: astore_1
      94: aload_1
      95: iconst_0
      96: invokevirtual #44                 // Method org/apache/hadoop/hbase/RegionLocations.getRegionLocation:(I)Lorg/apache/hadoop/hbase/HRegionLocation;
      99: invokestatic  #45                 // Method org/junit/Assert.assertNull:(Ljava/lang/Object;)V
     102: aload_1
     103: iconst_1
     104: invokevirtual #44                 // Method org/apache/hadoop/hbase/RegionLocations.getRegionLocation:(I)Lorg/apache/hadoop/hbase/HRegionLocation;
     107: invokestatic  #45                 // Method org/junit/Assert.assertNull:(Ljava/lang/Object;)V
     110: aload_1
     111: iconst_2
     112: invokevirtual #44                 // Method org/apache/hadoop/hbase/RegionLocations.getRegionLocation:(I)Lorg/apache/hadoop/hbase/HRegionLocation;
     115: invokestatic  #58                 // Method org/junit/Assert.assertNotNull:(Ljava/lang/Object;)V
     118: aload_0
     119: getfield      #8                  // Field sn1:Lorg/apache/hadoop/hbase/ServerName;
     122: aload_1
     123: iconst_2
     124: invokevirtual #44                 // Method org/apache/hadoop/hbase/RegionLocations.getRegionLocation:(I)Lorg/apache/hadoop/hbase/HRegionLocation;
     127: invokevirtual #46                 // Method org/apache/hadoop/hbase/HRegionLocation.getServerName:()Lorg/apache/hadoop/hbase/ServerName;
     130: invokestatic  #47                 // Method org/junit/Assert.assertEquals:(Ljava/lang/Object;Ljava/lang/Object;)V
     133: ldc2_w        #59                 // long 3l
     136: aload_1
     137: invokevirtual #29                 // Method org/apache/hadoop/hbase/RegionLocations.size:()I
     140: i2l
     141: invokestatic  #30                 // Method org/junit/Assert.assertEquals:(JJ)V
     144: aload_0
     145: iconst_1
     146: anewarray     #25                 // class org/apache/hadoop/hbase/HRegionLocation
     149: dup
     150: iconst_0
     151: aload_0
     152: aload         5
     154: aload_0
     155: getfield      #8                  // Field sn1:Lorg/apache/hadoop/hbase/ServerName;
     158: invokespecial #33                 // Method hrl:(Lorg/apache/hadoop/hbase/HRegionInfo;Lorg/apache/hadoop/hbase/ServerName;)Lorg/apache/hadoop/hbase/HRegionLocation;
     161: aastore
     162: invokespecial #32                 // Method hrll:([Lorg/apache/hadoop/hbase/HRegionLocation;)Lorg/apache/hadoop/hbase/RegionLocations;
     165: astore_1
     166: aload_0
     167: iconst_2
     168: anewarray     #25                 // class org/apache/hadoop/hbase/HRegionLocation
     171: dup
     172: iconst_0
     173: aload_0
     174: aload_3
     175: aload_0
     176: getfield      #10                 // Field sn2:Lorg/apache/hadoop/hbase/ServerName;
     179: invokespecial #33                 // Method hrl:(Lorg/apache/hadoop/hbase/HRegionInfo;Lorg/apache/hadoop/hbase/ServerName;)Lorg/apache/hadoop/hbase/HRegionLocation;
     182: aastore
     183: dup
     184: iconst_1
     185: aload_0
     186: aload         4
     188: aload_0
     189: getfield      #10                 // Field sn2:Lorg/apache/hadoop/hbase/ServerName;
     192: invokespecial #33                 // Method hrl:(Lorg/apache/hadoop/hbase/HRegionInfo;Lorg/apache/hadoop/hbase/ServerName;)Lorg/apache/hadoop/hbase/HRegionLocation;
     195: aastore
     196: invokespecial #32                 // Method hrll:([Lorg/apache/hadoop/hbase/HRegionLocation;)Lorg/apache/hadoop/hbase/RegionLocations;
     199: astore_2
     200: aload_1
     201: aload_2
     202: invokevirtual #55                 // Method org/apache/hadoop/hbase/RegionLocations.mergeLocations:(Lorg/apache/hadoop/hbase/RegionLocations;)Lorg/apache/hadoop/hbase/RegionLocations;
     205: astore_2
     206: aload_2
     207: iconst_0
     208: invokevirtual #44                 // Method org/apache/hadoop/hbase/RegionLocations.getRegionLocation:(I)Lorg/apache/hadoop/hbase/HRegionLocation;
     211: invokestatic  #58                 // Method org/junit/Assert.assertNotNull:(Ljava/lang/Object;)V
     214: aload_2
     215: iconst_1
     216: invokevirtual #44                 // Method org/apache/hadoop/hbase/RegionLocations.getRegionLocation:(I)Lorg/apache/hadoop/hbase/HRegionLocation;
     219: invokestatic  #58                 // Method org/junit/Assert.assertNotNull:(Ljava/lang/Object;)V
     222: aload_2
     223: iconst_2
     224: invokevirtual #44                 // Method org/apache/hadoop/hbase/RegionLocations.getRegionLocation:(I)Lorg/apache/hadoop/hbase/HRegionLocation;
     227: invokestatic  #45                 // Method org/junit/Assert.assertNull:(Ljava/lang/Object;)V
     230: return

  public void testUpdateLocationWithDifferentRegionId();
    Code:
       0: aload_0
       1: aload_0
       2: getfield      #20                 // Field regionId1:J
       5: iconst_0
       6: invokespecial #34                 // Method hri:(JI)Lorg/apache/hadoop/hbase/HRegionInfo;
       9: astore_2
      10: aload_0
      11: aload_0
      12: getfield      #23                 // Field regionId2:J
      15: iconst_1
      16: invokespecial #34                 // Method hri:(JI)Lorg/apache/hadoop/hbase/HRegionInfo;
      19: astore_3
      20: aload_0
      21: aload_0
      22: getfield      #20                 // Field regionId1:J
      25: iconst_2
      26: invokespecial #34                 // Method hri:(JI)Lorg/apache/hadoop/hbase/HRegionInfo;
      29: astore        4
      31: new           #24                 // class org/apache/hadoop/hbase/RegionLocations
      34: dup
      35: iconst_2
      36: anewarray     #25                 // class org/apache/hadoop/hbase/HRegionLocation
      39: dup
      40: iconst_0
      41: aload_0
      42: aload_2
      43: aload_0
      44: getfield      #8                  // Field sn1:Lorg/apache/hadoop/hbase/ServerName;
      47: invokespecial #33                 // Method hrl:(Lorg/apache/hadoop/hbase/HRegionInfo;Lorg/apache/hadoop/hbase/ServerName;)Lorg/apache/hadoop/hbase/HRegionLocation;
      50: aastore
      51: dup
      52: iconst_1
      53: aload_0
      54: aload         4
      56: aload_0
      57: getfield      #8                  // Field sn1:Lorg/apache/hadoop/hbase/ServerName;
      60: invokespecial #33                 // Method hrl:(Lorg/apache/hadoop/hbase/HRegionInfo;Lorg/apache/hadoop/hbase/ServerName;)Lorg/apache/hadoop/hbase/HRegionLocation;
      63: aastore
      64: invokespecial #26                 // Method org/apache/hadoop/hbase/RegionLocations."<init>":([Lorg/apache/hadoop/hbase/HRegionLocation;)V
      67: astore_1
      68: aload_1
      69: aload_0
      70: aload_3
      71: aload_0
      72: getfield      #10                 // Field sn2:Lorg/apache/hadoop/hbase/ServerName;
      75: invokespecial #33                 // Method hrl:(Lorg/apache/hadoop/hbase/HRegionInfo;Lorg/apache/hadoop/hbase/ServerName;)Lorg/apache/hadoop/hbase/HRegionLocation;
      78: iconst_0
      79: iconst_1
      80: invokevirtual #49                 // Method org/apache/hadoop/hbase/RegionLocations.updateLocation:(Lorg/apache/hadoop/hbase/HRegionLocation;ZZ)Lorg/apache/hadoop/hbase/RegionLocations;
      83: astore_1
      84: aload_1
      85: iconst_0
      86: invokevirtual #44                 // Method org/apache/hadoop/hbase/RegionLocations.getRegionLocation:(I)Lorg/apache/hadoop/hbase/HRegionLocation;
      89: invokestatic  #45                 // Method org/junit/Assert.assertNull:(Ljava/lang/Object;)V
      92: aload_1
      93: iconst_1
      94: invokevirtual #44                 // Method org/apache/hadoop/hbase/RegionLocations.getRegionLocation:(I)Lorg/apache/hadoop/hbase/HRegionLocation;
      97: invokestatic  #58                 // Method org/junit/Assert.assertNotNull:(Ljava/lang/Object;)V
     100: aload_1
     101: iconst_2
     102: invokevirtual #44                 // Method org/apache/hadoop/hbase/RegionLocations.getRegionLocation:(I)Lorg/apache/hadoop/hbase/HRegionLocation;
     105: invokestatic  #45                 // Method org/junit/Assert.assertNull:(Ljava/lang/Object;)V
     108: aload_0
     109: getfield      #10                 // Field sn2:Lorg/apache/hadoop/hbase/ServerName;
     112: aload_1
     113: iconst_1
     114: invokevirtual #44                 // Method org/apache/hadoop/hbase/RegionLocations.getRegionLocation:(I)Lorg/apache/hadoop/hbase/HRegionLocation;
     117: invokevirtual #46                 // Method org/apache/hadoop/hbase/HRegionLocation.getServerName:()Lorg/apache/hadoop/hbase/ServerName;
     120: invokestatic  #47                 // Method org/junit/Assert.assertEquals:(Ljava/lang/Object;Ljava/lang/Object;)V
     123: ldc2_w        #59                 // long 3l
     126: aload_1
     127: invokevirtual #29                 // Method org/apache/hadoop/hbase/RegionLocations.size:()I
     130: i2l
     131: invokestatic  #30                 // Method org/junit/Assert.assertEquals:(JJ)V
     134: return

  public void testConstructWithNullElements();
    Code:
       0: new           #24                 // class org/apache/hadoop/hbase/RegionLocations
       3: dup
       4: iconst_1
       5: anewarray     #25                 // class org/apache/hadoop/hbase/HRegionLocation
       8: dup
       9: iconst_0
      10: aconst_null
      11: checkcast     #25                 // class org/apache/hadoop/hbase/HRegionLocation
      14: aastore
      15: invokespecial #26                 // Method org/apache/hadoop/hbase/RegionLocations."<init>":([Lorg/apache/hadoop/hbase/HRegionLocation;)V
      18: astore_1
      19: aload_1
      20: invokevirtual #27                 // Method org/apache/hadoop/hbase/RegionLocations.isEmpty:()Z
      23: invokestatic  #28                 // Method org/junit/Assert.assertTrue:(Z)V
      26: lconst_1
      27: aload_1
      28: invokevirtual #29                 // Method org/apache/hadoop/hbase/RegionLocations.size:()I
      31: i2l
      32: invokestatic  #30                 // Method org/junit/Assert.assertEquals:(JJ)V
      35: lconst_0
      36: aload_1
      37: invokevirtual #31                 // Method org/apache/hadoop/hbase/RegionLocations.numNonNullElements:()I
      40: i2l
      41: invokestatic  #30                 // Method org/junit/Assert.assertEquals:(JJ)V
      44: new           #24                 // class org/apache/hadoop/hbase/RegionLocations
      47: dup
      48: iconst_2
      49: anewarray     #25                 // class org/apache/hadoop/hbase/HRegionLocation
      52: dup
      53: iconst_0
      54: aconst_null
      55: aastore
      56: dup
      57: iconst_1
      58: aload_0
      59: aload_0
      60: getfield      #15                 // Field info1:Lorg/apache/hadoop/hbase/HRegionInfo;
      63: aload_0
      64: getfield      #6                  // Field sn0:Lorg/apache/hadoop/hbase/ServerName;
      67: invokespecial #33                 // Method hrl:(Lorg/apache/hadoop/hbase/HRegionInfo;Lorg/apache/hadoop/hbase/ServerName;)Lorg/apache/hadoop/hbase/HRegionLocation;
      70: aastore
      71: invokespecial #26                 // Method org/apache/hadoop/hbase/RegionLocations."<init>":([Lorg/apache/hadoop/hbase/HRegionLocation;)V
      74: astore_1
      75: aload_1
      76: invokevirtual #27                 // Method org/apache/hadoop/hbase/RegionLocations.isEmpty:()Z
      79: invokestatic  #61                 // Method org/junit/Assert.assertFalse:(Z)V
      82: ldc2_w        #56                 // long 2l
      85: aload_1
      86: invokevirtual #29                 // Method org/apache/hadoop/hbase/RegionLocations.size:()I
      89: i2l
      90: invokestatic  #30                 // Method org/junit/Assert.assertEquals:(JJ)V
      93: lconst_1
      94: aload_1
      95: invokevirtual #31                 // Method org/apache/hadoop/hbase/RegionLocations.numNonNullElements:()I
      98: i2l
      99: invokestatic  #30                 // Method org/junit/Assert.assertEquals:(JJ)V
     102: new           #24                 // class org/apache/hadoop/hbase/RegionLocations
     105: dup
     106: iconst_2
     107: anewarray     #25                 // class org/apache/hadoop/hbase/HRegionLocation
     110: dup
     111: iconst_0
     112: aload_0
     113: aload_0
     114: getfield      #14                 // Field info0:Lorg/apache/hadoop/hbase/HRegionInfo;
     117: aload_0
     118: getfield      #6                  // Field sn0:Lorg/apache/hadoop/hbase/ServerName;
     121: invokespecial #33                 // Method hrl:(Lorg/apache/hadoop/hbase/HRegionInfo;Lorg/apache/hadoop/hbase/ServerName;)Lorg/apache/hadoop/hbase/HRegionLocation;
     124: aastore
     125: dup
     126: iconst_1
     127: aconst_null
     128: aastore
     129: invokespecial #26                 // Method org/apache/hadoop/hbase/RegionLocations."<init>":([Lorg/apache/hadoop/hbase/HRegionLocation;)V
     132: astore_1
     133: ldc2_w        #56                 // long 2l
     136: aload_1
     137: invokevirtual #29                 // Method org/apache/hadoop/hbase/RegionLocations.size:()I
     140: i2l
     141: invokestatic  #30                 // Method org/junit/Assert.assertEquals:(JJ)V
     144: lconst_1
     145: aload_1
     146: invokevirtual #31                 // Method org/apache/hadoop/hbase/RegionLocations.numNonNullElements:()I
     149: i2l
     150: invokestatic  #30                 // Method org/junit/Assert.assertEquals:(JJ)V
     153: new           #24                 // class org/apache/hadoop/hbase/RegionLocations
     156: dup
     157: iconst_4
     158: anewarray     #25                 // class org/apache/hadoop/hbase/HRegionLocation
     161: dup
     162: iconst_0
     163: aconst_null
     164: aastore
     165: dup
     166: iconst_1
     167: aload_0
     168: aload_0
     169: getfield      #16                 // Field info2:Lorg/apache/hadoop/hbase/HRegionInfo;
     172: aload_0
     173: getfield      #6                  // Field sn0:Lorg/apache/hadoop/hbase/ServerName;
     176: invokespecial #33                 // Method hrl:(Lorg/apache/hadoop/hbase/HRegionInfo;Lorg/apache/hadoop/hbase/ServerName;)Lorg/apache/hadoop/hbase/HRegionLocation;
     179: aastore
     180: dup
     181: iconst_2
     182: aconst_null
     183: aastore
     184: dup
     185: iconst_3
     186: aload_0
     187: aload_0
     188: getfield      #17                 // Field info9:Lorg/apache/hadoop/hbase/HRegionInfo;
     191: aload_0
     192: getfield      #6                  // Field sn0:Lorg/apache/hadoop/hbase/ServerName;
     195: invokespecial #33                 // Method hrl:(Lorg/apache/hadoop/hbase/HRegionInfo;Lorg/apache/hadoop/hbase/ServerName;)Lorg/apache/hadoop/hbase/HRegionLocation;
     198: aastore
     199: invokespecial #26                 // Method org/apache/hadoop/hbase/RegionLocations."<init>":([Lorg/apache/hadoop/hbase/HRegionLocation;)V
     202: astore_1
     203: ldc2_w        #3                  // long 10l
     206: aload_1
     207: invokevirtual #29                 // Method org/apache/hadoop/hbase/RegionLocations.size:()I
     210: i2l
     211: invokestatic  #30                 // Method org/junit/Assert.assertEquals:(JJ)V
     214: ldc2_w        #56                 // long 2l
     217: aload_1
     218: invokevirtual #31                 // Method org/apache/hadoop/hbase/RegionLocations.numNonNullElements:()I
     221: i2l
     222: invokestatic  #30                 // Method org/junit/Assert.assertEquals:(JJ)V
     225: new           #24                 // class org/apache/hadoop/hbase/RegionLocations
     228: dup
     229: iconst_5
     230: anewarray     #25                 // class org/apache/hadoop/hbase/HRegionLocation
     233: dup
     234: iconst_0
     235: aconst_null
     236: aastore
     237: dup
     238: iconst_1
     239: aload_0
     240: aload_0
     241: getfield      #16                 // Field info2:Lorg/apache/hadoop/hbase/HRegionInfo;
     244: aload_0
     245: getfield      #6                  // Field sn0:Lorg/apache/hadoop/hbase/ServerName;
     248: invokespecial #33                 // Method hrl:(Lorg/apache/hadoop/hbase/HRegionInfo;Lorg/apache/hadoop/hbase/ServerName;)Lorg/apache/hadoop/hbase/HRegionLocation;
     251: aastore
     252: dup
     253: iconst_2
     254: aconst_null
     255: aastore
     256: dup
     257: iconst_3
     258: aload_0
     259: aload_0
     260: getfield      #17                 // Field info9:Lorg/apache/hadoop/hbase/HRegionInfo;
     263: aload_0
     264: getfield      #6                  // Field sn0:Lorg/apache/hadoop/hbase/ServerName;
     267: invokespecial #33                 // Method hrl:(Lorg/apache/hadoop/hbase/HRegionInfo;Lorg/apache/hadoop/hbase/ServerName;)Lorg/apache/hadoop/hbase/HRegionLocation;
     270: aastore
     271: dup
     272: iconst_4
     273: aconst_null
     274: aastore
     275: invokespecial #26                 // Method org/apache/hadoop/hbase/RegionLocations."<init>":([Lorg/apache/hadoop/hbase/HRegionLocation;)V
     278: astore_1
     279: ldc2_w        #51                 // long 11l
     282: aload_1
     283: invokevirtual #29                 // Method org/apache/hadoop/hbase/RegionLocations.size:()I
     286: i2l
     287: invokestatic  #30                 // Method org/junit/Assert.assertEquals:(JJ)V
     290: ldc2_w        #56                 // long 2l
     293: aload_1
     294: invokevirtual #31                 // Method org/apache/hadoop/hbase/RegionLocations.numNonNullElements:()I
     297: i2l
     298: invokestatic  #30                 // Method org/junit/Assert.assertEquals:(JJ)V
     301: new           #24                 // class org/apache/hadoop/hbase/RegionLocations
     304: dup
     305: bipush        6
     307: anewarray     #25                 // class org/apache/hadoop/hbase/HRegionLocation
     310: dup
     311: iconst_0
     312: aconst_null
     313: aastore
     314: dup
     315: iconst_1
     316: aload_0
     317: aload_0
     318: getfield      #16                 // Field info2:Lorg/apache/hadoop/hbase/HRegionInfo;
     321: aload_0
     322: getfield      #6                  // Field sn0:Lorg/apache/hadoop/hbase/ServerName;
     325: invokespecial #33                 // Method hrl:(Lorg/apache/hadoop/hbase/HRegionInfo;Lorg/apache/hadoop/hbase/ServerName;)Lorg/apache/hadoop/hbase/HRegionLocation;
     328: aastore
     329: dup
     330: iconst_2
     331: aconst_null
     332: aastore
     333: dup
     334: iconst_3
     335: aload_0
     336: aload_0
     337: getfield      #17                 // Field info9:Lorg/apache/hadoop/hbase/HRegionInfo;
     340: aload_0
     341: getfield      #6                  // Field sn0:Lorg/apache/hadoop/hbase/ServerName;
     344: invokespecial #33                 // Method hrl:(Lorg/apache/hadoop/hbase/HRegionInfo;Lorg/apache/hadoop/hbase/ServerName;)Lorg/apache/hadoop/hbase/HRegionLocation;
     347: aastore
     348: dup
     349: iconst_4
     350: aconst_null
     351: aastore
     352: dup
     353: iconst_5
     354: aconst_null
     355: aastore
     356: invokespecial #26                 // Method org/apache/hadoop/hbase/RegionLocations."<init>":([Lorg/apache/hadoop/hbase/HRegionLocation;)V
     359: astore_1
     360: ldc2_w        #62                 // long 12l
     363: aload_1
     364: invokevirtual #29                 // Method org/apache/hadoop/hbase/RegionLocations.size:()I
     367: i2l
     368: invokestatic  #30                 // Method org/junit/Assert.assertEquals:(JJ)V
     371: ldc2_w        #56                 // long 2l
     374: aload_1
     375: invokevirtual #31                 // Method org/apache/hadoop/hbase/RegionLocations.numNonNullElements:()I
     378: i2l
     379: invokestatic  #30                 // Method org/junit/Assert.assertEquals:(JJ)V
     382: return

  static {};
    Code:
       0: ldc           #64                 // class org/apache/hadoop/hbase/TestRegionLocations
       2: invokestatic  #65                 // Method org/apache/hadoop/hbase/HBaseClassTestRule.forClass:(Ljava/lang/Class;)Lorg/apache/hadoop/hbase/HBaseClassTestRule;
       5: putstatic     #66                 // Field CLASS_RULE:Lorg/apache/hadoop/hbase/HBaseClassTestRule;
       8: return
}
