Compiled from "TestFlushLifeCycleTracker.java"
public class org.apache.hadoop.hbase.regionserver.TestFlushLifeCycleTracker {
  public static final org.apache.hadoop.hbase.HBaseClassTestRule CLASS_RULE;

  public org.apache.hadoop.hbase.regionserver.TestFlushLifeCycleTracker();
    Code:
       0: aload_0
       1: invokespecial #4                  // Method java/lang/Object."<init>":()V
       4: return

  public static void setUpBeforeClass() throws java.lang.Exception;
    Code:
       0: getstatic     #5                  // Field UTIL:Lorg/apache/hadoop/hbase/HBaseTestingUtility;
       3: iconst_3
       4: invokevirtual #6                  // Method org/apache/hadoop/hbase/HBaseTestingUtility.startMiniCluster:(I)Lorg/apache/hadoop/hbase/MiniHBaseCluster;
       7: pop
       8: return

  public static void tearDownAfterClass() throws java.lang.Exception;
    Code:
       0: getstatic     #5                  // Field UTIL:Lorg/apache/hadoop/hbase/HBaseTestingUtility;
       3: invokevirtual #7                  // Method org/apache/hadoop/hbase/HBaseTestingUtility.shutdownMiniCluster:()V
       6: return

  public void setUp() throws java.io.IOException;
    Code:
       0: getstatic     #5                  // Field UTIL:Lorg/apache/hadoop/hbase/HBaseTestingUtility;
       3: invokevirtual #8                  // Method org/apache/hadoop/hbase/HBaseTestingUtility.getAdmin:()Lorg/apache/hadoop/hbase/client/Admin;
       6: getstatic     #9                  // Field NAME:Lorg/apache/hadoop/hbase/TableName;
       9: invokestatic  #10                 // Method org/apache/hadoop/hbase/client/TableDescriptorBuilder.newBuilder:(Lorg/apache/hadoop/hbase/TableName;)Lorg/apache/hadoop/hbase/client/TableDescriptorBuilder;
      12: getstatic     #11                 // Field CF:[B
      15: invokestatic  #12                 // Method org/apache/hadoop/hbase/client/ColumnFamilyDescriptorBuilder.of:([B)Lorg/apache/hadoop/hbase/client/ColumnFamilyDescriptor;
      18: invokevirtual #13                 // Method org/apache/hadoop/hbase/client/TableDescriptorBuilder.setColumnFamily:(Lorg/apache/hadoop/hbase/client/ColumnFamilyDescriptor;)Lorg/apache/hadoop/hbase/client/TableDescriptorBuilder;
      21: ldc           #14                 // class org/apache/hadoop/hbase/regionserver/TestFlushLifeCycleTracker$FlushObserver
      23: invokevirtual #15                 // Method java/lang/Class.getName:()Ljava/lang/String;
      26: invokevirtual #16                 // Method org/apache/hadoop/hbase/client/TableDescriptorBuilder.setCoprocessor:(Ljava/lang/String;)Lorg/apache/hadoop/hbase/client/TableDescriptorBuilder;
      29: invokevirtual #17                 // Method org/apache/hadoop/hbase/client/TableDescriptorBuilder.build:()Lorg/apache/hadoop/hbase/client/TableDescriptor;
      32: invokeinterface #18,  2           // InterfaceMethod org/apache/hadoop/hbase/client/Admin.createTable:(Lorg/apache/hadoop/hbase/client/TableDescriptor;)V
      37: aload_0
      38: getstatic     #5                  // Field UTIL:Lorg/apache/hadoop/hbase/HBaseTestingUtility;
      41: invokevirtual #19                 // Method org/apache/hadoop/hbase/HBaseTestingUtility.getHBaseCluster:()Lorg/apache/hadoop/hbase/MiniHBaseCluster;
      44: getstatic     #9                  // Field NAME:Lorg/apache/hadoop/hbase/TableName;
      47: invokevirtual #20                 // Method org/apache/hadoop/hbase/MiniHBaseCluster.getRegions:(Lorg/apache/hadoop/hbase/TableName;)Ljava/util/List;
      50: iconst_0
      51: invokeinterface #21,  2           // InterfaceMethod java/util/List.get:(I)Ljava/lang/Object;
      56: checkcast     #22                 // class org/apache/hadoop/hbase/regionserver/HRegion
      59: putfield      #23                 // Field region:Lorg/apache/hadoop/hbase/regionserver/HRegion;
      62: return

  public void tearDown() throws java.io.IOException;
    Code:
       0: aload_0
       1: aconst_null
       2: putfield      #23                 // Field region:Lorg/apache/hadoop/hbase/regionserver/HRegion;
       5: aconst_null
       6: putstatic     #3                  // Field TRACKER:Lorg/apache/hadoop/hbase/regionserver/FlushLifeCycleTracker;
       9: getstatic     #5                  // Field UTIL:Lorg/apache/hadoop/hbase/HBaseTestingUtility;
      12: getstatic     #9                  // Field NAME:Lorg/apache/hadoop/hbase/TableName;
      15: invokevirtual #24                 // Method org/apache/hadoop/hbase/HBaseTestingUtility.deleteTable:(Lorg/apache/hadoop/hbase/TableName;)V
      18: return

  public void test() throws java.io.IOException, java.lang.InterruptedException;
    Code:
       0: getstatic     #5                  // Field UTIL:Lorg/apache/hadoop/hbase/HBaseTestingUtility;
       3: invokevirtual #25                 // Method org/apache/hadoop/hbase/HBaseTestingUtility.getConnection:()Lorg/apache/hadoop/hbase/client/Connection;
       6: getstatic     #9                  // Field NAME:Lorg/apache/hadoop/hbase/TableName;
       9: invokeinterface #26,  2           // InterfaceMethod org/apache/hadoop/hbase/client/Connection.getTable:(Lorg/apache/hadoop/hbase/TableName;)Lorg/apache/hadoop/hbase/client/Table;
      14: astore_1
      15: aconst_null
      16: astore_2
      17: iconst_0
      18: istore_3
      19: iload_3
      20: bipush        100
      22: if_icmpge     115
      25: iload_3
      26: invokestatic  #27                 // Method org/apache/hadoop/hbase/util/Bytes.toBytes:(I)[B
      29: astore        4
      31: aload_1
      32: new           #28                 // class org/apache/hadoop/hbase/client/Put
      35: dup
      36: aload         4
      38: iconst_1
      39: invokespecial #29                 // Method org/apache/hadoop/hbase/client/Put."<init>":([BZ)V
      42: getstatic     #30                 // Field org/apache/hadoop/hbase/CellBuilderType.SHALLOW_COPY:Lorg/apache/hadoop/hbase/CellBuilderType;
      45: invokestatic  #31                 // Method org/apache/hadoop/hbase/CellBuilderFactory.create:(Lorg/apache/hadoop/hbase/CellBuilderType;)Lorg/apache/hadoop/hbase/CellBuilder;
      48: aload         4
      50: invokeinterface #32,  2           // InterfaceMethod org/apache/hadoop/hbase/CellBuilder.setRow:([B)Lorg/apache/hadoop/hbase/CellBuilder;
      55: getstatic     #11                 // Field CF:[B
      58: invokeinterface #33,  2           // InterfaceMethod org/apache/hadoop/hbase/CellBuilder.setFamily:([B)Lorg/apache/hadoop/hbase/CellBuilder;
      63: getstatic     #34                 // Field QUALIFIER:[B
      66: invokeinterface #35,  2           // InterfaceMethod org/apache/hadoop/hbase/CellBuilder.setQualifier:([B)Lorg/apache/hadoop/hbase/CellBuilder;
      71: ldc2_w        #37                 // long 9223372036854775807l
      74: invokeinterface #39,  3           // InterfaceMethod org/apache/hadoop/hbase/CellBuilder.setTimestamp:(J)Lorg/apache/hadoop/hbase/CellBuilder;
      79: getstatic     #40                 // Field org/apache/hadoop/hbase/Cell$Type.Put:Lorg/apache/hadoop/hbase/Cell$Type;
      82: invokeinterface #41,  2           // InterfaceMethod org/apache/hadoop/hbase/CellBuilder.setType:(Lorg/apache/hadoop/hbase/Cell$Type;)Lorg/apache/hadoop/hbase/CellBuilder;
      87: iload_3
      88: invokestatic  #27                 // Method org/apache/hadoop/hbase/util/Bytes.toBytes:(I)[B
      91: invokeinterface #42,  2           // InterfaceMethod org/apache/hadoop/hbase/CellBuilder.setValue:([B)Lorg/apache/hadoop/hbase/CellBuilder;
      96: invokeinterface #43,  1           // InterfaceMethod org/apache/hadoop/hbase/CellBuilder.build:()Lorg/apache/hadoop/hbase/Cell;
     101: invokevirtual #44                 // Method org/apache/hadoop/hbase/client/Put.add:(Lorg/apache/hadoop/hbase/Cell;)Lorg/apache/hadoop/hbase/client/Put;
     104: invokeinterface #45,  2           // InterfaceMethod org/apache/hadoop/hbase/client/Table.put:(Lorg/apache/hadoop/hbase/client/Put;)V
     109: iinc          3, 1
     112: goto          19
     115: aload_1
     116: ifnull        194
     119: aload_2
     120: ifnull        141
     123: aload_1
     124: invokeinterface #46,  1           // InterfaceMethod org/apache/hadoop/hbase/client/Table.close:()V
     129: goto          194
     132: astore_3
     133: aload_2
     134: aload_3
     135: invokevirtual #48                 // Method java/lang/Throwable.addSuppressed:(Ljava/lang/Throwable;)V
     138: goto          194
     141: aload_1
     142: invokeinterface #46,  1           // InterfaceMethod org/apache/hadoop/hbase/client/Table.close:()V
     147: goto          194
     150: astore_3
     151: aload_3
     152: astore_2
     153: aload_3
     154: athrow
     155: astore        5
     157: aload_1
     158: ifnull        191
     161: aload_2
     162: ifnull        185
     165: aload_1
     166: invokeinterface #46,  1           // InterfaceMethod org/apache/hadoop/hbase/client/Table.close:()V
     171: goto          191
     174: astore        6
     176: aload_2
     177: aload         6
     179: invokevirtual #48                 // Method java/lang/Throwable.addSuppressed:(Ljava/lang/Throwable;)V
     182: goto          191
     185: aload_1
     186: invokeinterface #46,  1           // InterfaceMethod org/apache/hadoop/hbase/client/Table.close:()V
     191: aload         5
     193: athrow
     194: new           #49                 // class org/apache/hadoop/hbase/regionserver/TestFlushLifeCycleTracker$Tracker
     197: dup
     198: aconst_null
     199: invokespecial #50                 // Method org/apache/hadoop/hbase/regionserver/TestFlushLifeCycleTracker$Tracker."<init>":(Lorg/apache/hadoop/hbase/regionserver/TestFlushLifeCycleTracker$1;)V
     202: astore_1
     203: aload_1
     204: putstatic     #3                  // Field TRACKER:Lorg/apache/hadoop/hbase/regionserver/FlushLifeCycleTracker;
     207: aload_0
     208: getfield      #23                 // Field region:Lorg/apache/hadoop/hbase/regionserver/HRegion;
     211: aload_1
     212: invokevirtual #51                 // Method org/apache/hadoop/hbase/regionserver/HRegion.requestFlush:(Lorg/apache/hadoop/hbase/regionserver/FlushLifeCycleTracker;)V
     215: aload_1
     216: invokevirtual #52                 // Method org/apache/hadoop/hbase/regionserver/TestFlushLifeCycleTracker$Tracker.await:()V
     219: aload_1
     220: invokestatic  #53                 // Method org/apache/hadoop/hbase/regionserver/TestFlushLifeCycleTracker$Tracker.access$400:(Lorg/apache/hadoop/hbase/regionserver/TestFlushLifeCycleTracker$Tracker;)Ljava/lang/String;
     223: invokestatic  #54                 // Method org/junit/Assert.assertNull:(Ljava/lang/Object;)V
     226: aload_1
     227: invokestatic  #55                 // Method org/apache/hadoop/hbase/regionserver/TestFlushLifeCycleTracker$Tracker.access$500:(Lorg/apache/hadoop/hbase/regionserver/TestFlushLifeCycleTracker$Tracker;)Z
     230: invokestatic  #56                 // Method org/junit/Assert.assertTrue:(Z)V
     233: aload_1
     234: invokestatic  #57                 // Method org/apache/hadoop/hbase/regionserver/TestFlushLifeCycleTracker$Tracker.access$600:(Lorg/apache/hadoop/hbase/regionserver/TestFlushLifeCycleTracker$Tracker;)Z
     237: invokestatic  #56                 // Method org/junit/Assert.assertTrue:(Z)V
     240: new           #49                 // class org/apache/hadoop/hbase/regionserver/TestFlushLifeCycleTracker$Tracker
     243: dup
     244: aconst_null
     245: invokespecial #50                 // Method org/apache/hadoop/hbase/regionserver/TestFlushLifeCycleTracker$Tracker."<init>":(Lorg/apache/hadoop/hbase/regionserver/TestFlushLifeCycleTracker$1;)V
     248: astore_1
     249: aload_1
     250: putstatic     #3                  // Field TRACKER:Lorg/apache/hadoop/hbase/regionserver/FlushLifeCycleTracker;
     253: aload_0
     254: getfield      #23                 // Field region:Lorg/apache/hadoop/hbase/regionserver/HRegion;
     257: aload_1
     258: invokevirtual #51                 // Method org/apache/hadoop/hbase/regionserver/HRegion.requestFlush:(Lorg/apache/hadoop/hbase/regionserver/FlushLifeCycleTracker;)V
     261: aload_1
     262: invokevirtual #52                 // Method org/apache/hadoop/hbase/regionserver/TestFlushLifeCycleTracker$Tracker.await:()V
     265: aload_1
     266: invokestatic  #53                 // Method org/apache/hadoop/hbase/regionserver/TestFlushLifeCycleTracker$Tracker.access$400:(Lorg/apache/hadoop/hbase/regionserver/TestFlushLifeCycleTracker$Tracker;)Ljava/lang/String;
     269: invokestatic  #54                 // Method org/junit/Assert.assertNull:(Ljava/lang/Object;)V
     272: aload_1
     273: invokestatic  #55                 // Method org/apache/hadoop/hbase/regionserver/TestFlushLifeCycleTracker$Tracker.access$500:(Lorg/apache/hadoop/hbase/regionserver/TestFlushLifeCycleTracker$Tracker;)Z
     276: invokestatic  #56                 // Method org/junit/Assert.assertTrue:(Z)V
     279: aload_1
     280: invokestatic  #57                 // Method org/apache/hadoop/hbase/regionserver/TestFlushLifeCycleTracker$Tracker.access$600:(Lorg/apache/hadoop/hbase/regionserver/TestFlushLifeCycleTracker$Tracker;)Z
     283: invokestatic  #56                 // Method org/junit/Assert.assertTrue:(Z)V
     286: return
    Exception table:
       from    to  target type
         123   129   132   Class java/lang/Throwable
          17   115   150   Class java/lang/Throwable
          17   115   155   any
         165   171   174   Class java/lang/Throwable
         150   157   155   any

  public void testNotExecuted() throws java.io.IOException, java.lang.InterruptedException;
    Code:
       0: getstatic     #5                  // Field UTIL:Lorg/apache/hadoop/hbase/HBaseTestingUtility;
       3: invokevirtual #25                 // Method org/apache/hadoop/hbase/HBaseTestingUtility.getConnection:()Lorg/apache/hadoop/hbase/client/Connection;
       6: getstatic     #9                  // Field NAME:Lorg/apache/hadoop/hbase/TableName;
       9: invokeinterface #26,  2           // InterfaceMethod org/apache/hadoop/hbase/client/Connection.getTable:(Lorg/apache/hadoop/hbase/TableName;)Lorg/apache/hadoop/hbase/client/Table;
      14: astore_1
      15: aconst_null
      16: astore_2
      17: iconst_0
      18: istore_3
      19: iload_3
      20: bipush        100
      22: if_icmpge     115
      25: iload_3
      26: invokestatic  #27                 // Method org/apache/hadoop/hbase/util/Bytes.toBytes:(I)[B
      29: astore        4
      31: aload_1
      32: new           #28                 // class org/apache/hadoop/hbase/client/Put
      35: dup
      36: aload         4
      38: iconst_1
      39: invokespecial #29                 // Method org/apache/hadoop/hbase/client/Put."<init>":([BZ)V
      42: getstatic     #30                 // Field org/apache/hadoop/hbase/CellBuilderType.SHALLOW_COPY:Lorg/apache/hadoop/hbase/CellBuilderType;
      45: invokestatic  #31                 // Method org/apache/hadoop/hbase/CellBuilderFactory.create:(Lorg/apache/hadoop/hbase/CellBuilderType;)Lorg/apache/hadoop/hbase/CellBuilder;
      48: aload         4
      50: invokeinterface #32,  2           // InterfaceMethod org/apache/hadoop/hbase/CellBuilder.setRow:([B)Lorg/apache/hadoop/hbase/CellBuilder;
      55: getstatic     #11                 // Field CF:[B
      58: invokeinterface #33,  2           // InterfaceMethod org/apache/hadoop/hbase/CellBuilder.setFamily:([B)Lorg/apache/hadoop/hbase/CellBuilder;
      63: getstatic     #34                 // Field QUALIFIER:[B
      66: invokeinterface #35,  2           // InterfaceMethod org/apache/hadoop/hbase/CellBuilder.setQualifier:([B)Lorg/apache/hadoop/hbase/CellBuilder;
      71: ldc2_w        #37                 // long 9223372036854775807l
      74: invokeinterface #39,  3           // InterfaceMethod org/apache/hadoop/hbase/CellBuilder.setTimestamp:(J)Lorg/apache/hadoop/hbase/CellBuilder;
      79: getstatic     #40                 // Field org/apache/hadoop/hbase/Cell$Type.Put:Lorg/apache/hadoop/hbase/Cell$Type;
      82: invokeinterface #41,  2           // InterfaceMethod org/apache/hadoop/hbase/CellBuilder.setType:(Lorg/apache/hadoop/hbase/Cell$Type;)Lorg/apache/hadoop/hbase/CellBuilder;
      87: iload_3
      88: invokestatic  #27                 // Method org/apache/hadoop/hbase/util/Bytes.toBytes:(I)[B
      91: invokeinterface #42,  2           // InterfaceMethod org/apache/hadoop/hbase/CellBuilder.setValue:([B)Lorg/apache/hadoop/hbase/CellBuilder;
      96: invokeinterface #43,  1           // InterfaceMethod org/apache/hadoop/hbase/CellBuilder.build:()Lorg/apache/hadoop/hbase/Cell;
     101: invokevirtual #44                 // Method org/apache/hadoop/hbase/client/Put.add:(Lorg/apache/hadoop/hbase/Cell;)Lorg/apache/hadoop/hbase/client/Put;
     104: invokeinterface #45,  2           // InterfaceMethod org/apache/hadoop/hbase/client/Table.put:(Lorg/apache/hadoop/hbase/client/Put;)V
     109: iinc          3, 1
     112: goto          19
     115: aload_1
     116: ifnull        194
     119: aload_2
     120: ifnull        141
     123: aload_1
     124: invokeinterface #46,  1           // InterfaceMethod org/apache/hadoop/hbase/client/Table.close:()V
     129: goto          194
     132: astore_3
     133: aload_2
     134: aload_3
     135: invokevirtual #48                 // Method java/lang/Throwable.addSuppressed:(Ljava/lang/Throwable;)V
     138: goto          194
     141: aload_1
     142: invokeinterface #46,  1           // InterfaceMethod org/apache/hadoop/hbase/client/Table.close:()V
     147: goto          194
     150: astore_3
     151: aload_3
     152: astore_2
     153: aload_3
     154: athrow
     155: astore        5
     157: aload_1
     158: ifnull        191
     161: aload_2
     162: ifnull        185
     165: aload_1
     166: invokeinterface #46,  1           // InterfaceMethod org/apache/hadoop/hbase/client/Table.close:()V
     171: goto          191
     174: astore        6
     176: aload_2
     177: aload         6
     179: invokevirtual #48                 // Method java/lang/Throwable.addSuppressed:(Ljava/lang/Throwable;)V
     182: goto          191
     185: aload_1
     186: invokeinterface #46,  1           // InterfaceMethod org/apache/hadoop/hbase/client/Table.close:()V
     191: aload         5
     193: athrow
     194: new           #49                 // class org/apache/hadoop/hbase/regionserver/TestFlushLifeCycleTracker$Tracker
     197: dup
     198: aconst_null
     199: invokespecial #50                 // Method org/apache/hadoop/hbase/regionserver/TestFlushLifeCycleTracker$Tracker."<init>":(Lorg/apache/hadoop/hbase/regionserver/TestFlushLifeCycleTracker$1;)V
     202: astore_1
     203: new           #58                 // class java/util/concurrent/CountDownLatch
     206: dup
     207: iconst_1
     208: invokespecial #59                 // Method java/util/concurrent/CountDownLatch."<init>":(I)V
     211: putstatic     #2                  // Field ARRIVE:Ljava/util/concurrent/CountDownLatch;
     214: new           #58                 // class java/util/concurrent/CountDownLatch
     217: dup
     218: iconst_1
     219: invokespecial #59                 // Method java/util/concurrent/CountDownLatch."<init>":(I)V
     222: putstatic     #1                  // Field BLOCK:Ljava/util/concurrent/CountDownLatch;
     225: aload_0
     226: getfield      #23                 // Field region:Lorg/apache/hadoop/hbase/regionserver/HRegion;
     229: aload_1
     230: invokevirtual #51                 // Method org/apache/hadoop/hbase/regionserver/HRegion.requestFlush:(Lorg/apache/hadoop/hbase/regionserver/FlushLifeCycleTracker;)V
     233: getstatic     #2                  // Field ARRIVE:Ljava/util/concurrent/CountDownLatch;
     236: invokevirtual #60                 // Method java/util/concurrent/CountDownLatch.await:()V
     239: new           #49                 // class org/apache/hadoop/hbase/regionserver/TestFlushLifeCycleTracker$Tracker
     242: dup
     243: aconst_null
     244: invokespecial #50                 // Method org/apache/hadoop/hbase/regionserver/TestFlushLifeCycleTracker$Tracker."<init>":(Lorg/apache/hadoop/hbase/regionserver/TestFlushLifeCycleTracker$1;)V
     247: astore_2
     248: aload_0
     249: getfield      #23                 // Field region:Lorg/apache/hadoop/hbase/regionserver/HRegion;
     252: aload_2
     253: invokevirtual #51                 // Method org/apache/hadoop/hbase/regionserver/HRegion.requestFlush:(Lorg/apache/hadoop/hbase/regionserver/FlushLifeCycleTracker;)V
     256: aload_2
     257: invokevirtual #52                 // Method org/apache/hadoop/hbase/regionserver/TestFlushLifeCycleTracker$Tracker.await:()V
     260: aload_2
     261: invokestatic  #53                 // Method org/apache/hadoop/hbase/regionserver/TestFlushLifeCycleTracker$Tracker.access$400:(Lorg/apache/hadoop/hbase/regionserver/TestFlushLifeCycleTracker$Tracker;)Ljava/lang/String;
     264: invokestatic  #61                 // Method org/junit/Assert.assertNotNull:(Ljava/lang/Object;)V
     267: aload_2
     268: invokestatic  #55                 // Method org/apache/hadoop/hbase/regionserver/TestFlushLifeCycleTracker$Tracker.access$500:(Lorg/apache/hadoop/hbase/regionserver/TestFlushLifeCycleTracker$Tracker;)Z
     271: invokestatic  #62                 // Method org/junit/Assert.assertFalse:(Z)V
     274: aload_2
     275: invokestatic  #57                 // Method org/apache/hadoop/hbase/regionserver/TestFlushLifeCycleTracker$Tracker.access$600:(Lorg/apache/hadoop/hbase/regionserver/TestFlushLifeCycleTracker$Tracker;)Z
     278: invokestatic  #62                 // Method org/junit/Assert.assertFalse:(Z)V
     281: getstatic     #1                  // Field BLOCK:Ljava/util/concurrent/CountDownLatch;
     284: invokevirtual #63                 // Method java/util/concurrent/CountDownLatch.countDown:()V
     287: aload_1
     288: invokevirtual #52                 // Method org/apache/hadoop/hbase/regionserver/TestFlushLifeCycleTracker$Tracker.await:()V
     291: aload_1
     292: invokestatic  #53                 // Method org/apache/hadoop/hbase/regionserver/TestFlushLifeCycleTracker$Tracker.access$400:(Lorg/apache/hadoop/hbase/regionserver/TestFlushLifeCycleTracker$Tracker;)Ljava/lang/String;
     295: invokestatic  #54                 // Method org/junit/Assert.assertNull:(Ljava/lang/Object;)V
     298: aload_1
     299: invokestatic  #55                 // Method org/apache/hadoop/hbase/regionserver/TestFlushLifeCycleTracker$Tracker.access$500:(Lorg/apache/hadoop/hbase/regionserver/TestFlushLifeCycleTracker$Tracker;)Z
     302: invokestatic  #56                 // Method org/junit/Assert.assertTrue:(Z)V
     305: aload_1
     306: invokestatic  #57                 // Method org/apache/hadoop/hbase/regionserver/TestFlushLifeCycleTracker$Tracker.access$600:(Lorg/apache/hadoop/hbase/regionserver/TestFlushLifeCycleTracker$Tracker;)Z
     309: invokestatic  #56                 // Method org/junit/Assert.assertTrue:(Z)V
     312: return
    Exception table:
       from    to  target type
         123   129   132   Class java/lang/Throwable
          17   115   150   Class java/lang/Throwable
          17   115   155   any
         165   171   174   Class java/lang/Throwable
         150   157   155   any

  static org.apache.hadoop.hbase.regionserver.FlushLifeCycleTracker access$000();
    Code:
       0: getstatic     #3                  // Field TRACKER:Lorg/apache/hadoop/hbase/regionserver/FlushLifeCycleTracker;
       3: areturn

  static java.util.concurrent.CountDownLatch access$100();
    Code:
       0: getstatic     #2                  // Field ARRIVE:Ljava/util/concurrent/CountDownLatch;
       3: areturn

  static java.util.concurrent.CountDownLatch access$200();
    Code:
       0: getstatic     #1                  // Field BLOCK:Ljava/util/concurrent/CountDownLatch;
       3: areturn

  static {};
    Code:
       0: ldc           #64                 // class org/apache/hadoop/hbase/regionserver/TestFlushLifeCycleTracker
       2: invokestatic  #65                 // Method org/apache/hadoop/hbase/HBaseClassTestRule.forClass:(Ljava/lang/Class;)Lorg/apache/hadoop/hbase/HBaseClassTestRule;
       5: putstatic     #66                 // Field CLASS_RULE:Lorg/apache/hadoop/hbase/HBaseClassTestRule;
       8: new           #67                 // class org/apache/hadoop/hbase/HBaseTestingUtility
      11: dup
      12: invokespecial #68                 // Method org/apache/hadoop/hbase/HBaseTestingUtility."<init>":()V
      15: putstatic     #5                  // Field UTIL:Lorg/apache/hadoop/hbase/HBaseTestingUtility;
      18: ldc           #64                 // class org/apache/hadoop/hbase/regionserver/TestFlushLifeCycleTracker
      20: invokevirtual #69                 // Method java/lang/Class.getSimpleName:()Ljava/lang/String;
      23: invokestatic  #70                 // Method org/apache/hadoop/hbase/TableName.valueOf:(Ljava/lang/String;)Lorg/apache/hadoop/hbase/TableName;
      26: putstatic     #9                  // Field NAME:Lorg/apache/hadoop/hbase/TableName;
      29: ldc           #71                 // String CF
      31: invokestatic  #72                 // Method org/apache/hadoop/hbase/util/Bytes.toBytes:(Ljava/lang/String;)[B
      34: putstatic     #11                 // Field CF:[B
      37: ldc           #73                 // String CQ
      39: invokestatic  #72                 // Method org/apache/hadoop/hbase/util/Bytes.toBytes:(Ljava/lang/String;)[B
      42: putstatic     #34                 // Field QUALIFIER:[B
      45: return
}
