Compiled from "TestScannersFromClientSide.java"
public class org.apache.hadoop.hbase.client.TestScannersFromClientSide {
  public static final org.apache.hadoop.hbase.HBaseClassTestRule CLASS_RULE;

  public org.junit.rules.TestName name;

  static final boolean $assertionsDisabled;

  public org.apache.hadoop.hbase.client.TestScannersFromClientSide();
    Code:
       0: aload_0
       1: invokespecial #3                  // Method java/lang/Object."<init>":()V
       4: aload_0
       5: new           #4                  // class org/junit/rules/TestName
       8: dup
       9: invokespecial #5                  // Method org/junit/rules/TestName."<init>":()V
      12: putfield      #6                  // Field name:Lorg/junit/rules/TestName;
      15: return

  public static void setUpBeforeClass() throws java.lang.Exception;
    Code:
       0: getstatic     #7                  // Field TEST_UTIL:Lorg/apache/hadoop/hbase/HBaseTestingUtility;
       3: invokevirtual #8                  // Method org/apache/hadoop/hbase/HBaseTestingUtility.getConfiguration:()Lorg/apache/hadoop/conf/Configuration;
       6: astore_0
       7: aload_0
       8: ldc           #9                  // String hbase.client.scanner.max.result.size
      10: ldc2_w        #10                 // long 10485760l
      13: invokevirtual #12                 // Method org/apache/hadoop/conf/Configuration.setLong:(Ljava/lang/String;J)V
      16: getstatic     #7                  // Field TEST_UTIL:Lorg/apache/hadoop/hbase/HBaseTestingUtility;
      19: iconst_3
      20: invokevirtual #13                 // Method org/apache/hadoop/hbase/HBaseTestingUtility.startMiniCluster:(I)Lorg/apache/hadoop/hbase/MiniHBaseCluster;
      23: pop
      24: return

  public static void tearDownAfterClass() throws java.lang.Exception;
    Code:
       0: getstatic     #7                  // Field TEST_UTIL:Lorg/apache/hadoop/hbase/HBaseTestingUtility;
       3: invokevirtual #14                 // Method org/apache/hadoop/hbase/HBaseTestingUtility.shutdownMiniCluster:()V
       6: return

  public void setUp() throws java.lang.Exception;
    Code:
       0: return

  public void tearDown() throws java.lang.Exception;
    Code:
       0: return

  public void testScanBatch() throws java.lang.Exception;
    Code:
       0: aload_0
       1: getfield      #6                  // Field name:Lorg/junit/rules/TestName;
       4: invokevirtual #15                 // Method org/junit/rules/TestName.getMethodName:()Ljava/lang/String;
       7: invokestatic  #16                 // Method org/apache/hadoop/hbase/TableName.valueOf:(Ljava/lang/String;)Lorg/apache/hadoop/hbase/TableName;
      10: astore_1
      11: getstatic     #17                 // Field QUALIFIER:[B
      14: bipush        8
      16: invokestatic  #18                 // Method org/apache/hadoop/hbase/HTestConst.makeNAscii:([BI)[[B
      19: astore_2
      20: getstatic     #7                  // Field TEST_UTIL:Lorg/apache/hadoop/hbase/HBaseTestingUtility;
      23: aload_1
      24: getstatic     #19                 // Field FAMILY:[B
      27: invokevirtual #20                 // Method org/apache/hadoop/hbase/HBaseTestingUtility.createTable:(Lorg/apache/hadoop/hbase/TableName;[B)Lorg/apache/hadoop/hbase/client/Table;
      30: astore_3
      31: iconst_1
      32: istore        9
      34: new           #21                 // class org/apache/hadoop/hbase/client/Put
      37: dup
      38: getstatic     #22                 // Field ROW:[B
      41: invokespecial #23                 // Method org/apache/hadoop/hbase/client/Put."<init>":([B)V
      44: astore        4
      46: iconst_0
      47: istore        11
      49: iload         11
      51: aload_2
      52: arraylength
      53: if_icmpge     95
      56: new           #24                 // class org/apache/hadoop/hbase/KeyValue
      59: dup
      60: getstatic     #22                 // Field ROW:[B
      63: getstatic     #19                 // Field FAMILY:[B
      66: aload_2
      67: iload         11
      69: aaload
      70: iload         11
      72: i2l
      73: getstatic     #25                 // Field VALUE:[B
      76: invokespecial #26                 // Method org/apache/hadoop/hbase/KeyValue."<init>":([B[B[BJ[B)V
      79: astore        12
      81: aload         4
      83: aload         12
      85: invokevirtual #27                 // Method org/apache/hadoop/hbase/client/Put.add:(Lorg/apache/hadoop/hbase/Cell;)Lorg/apache/hadoop/hbase/client/Put;
      88: pop
      89: iinc          11, 1
      92: goto          49
      95: aload_3
      96: aload         4
      98: invokeinterface #28,  2           // InterfaceMethod org/apache/hadoop/hbase/client/Table.put:(Lorg/apache/hadoop/hbase/client/Put;)V
     103: new           #21                 // class org/apache/hadoop/hbase/client/Put
     106: dup
     107: getstatic     #22                 // Field ROW:[B
     110: invokespecial #23                 // Method org/apache/hadoop/hbase/client/Put."<init>":([B)V
     113: astore        4
     115: new           #24                 // class org/apache/hadoop/hbase/KeyValue
     118: dup
     119: getstatic     #22                 // Field ROW:[B
     122: getstatic     #19                 // Field FAMILY:[B
     125: aload_2
     126: bipush        6
     128: aaload
     129: ldc2_w        #29                 // long 2l
     132: getstatic     #25                 // Field VALUE:[B
     135: invokespecial #26                 // Method org/apache/hadoop/hbase/KeyValue."<init>":([B[B[BJ[B)V
     138: astore        11
     140: aload         4
     142: aload         11
     144: invokevirtual #27                 // Method org/apache/hadoop/hbase/client/Put.add:(Lorg/apache/hadoop/hbase/Cell;)Lorg/apache/hadoop/hbase/client/Put;
     147: pop
     148: aload_3
     149: aload         4
     151: invokeinterface #28,  2           // InterfaceMethod org/apache/hadoop/hbase/client/Table.put:(Lorg/apache/hadoop/hbase/client/Put;)V
     156: new           #31                 // class org/apache/hadoop/hbase/client/Delete
     159: dup
     160: getstatic     #22                 // Field ROW:[B
     163: invokespecial #32                 // Method org/apache/hadoop/hbase/client/Delete."<init>":([B)V
     166: astore        6
     168: aload         6
     170: getstatic     #19                 // Field FAMILY:[B
     173: ldc2_w        #33                 // long 3l
     176: invokevirtual #35                 // Method org/apache/hadoop/hbase/client/Delete.addFamily:([BJ)Lorg/apache/hadoop/hbase/client/Delete;
     179: pop
     180: aload_3
     181: aload         6
     183: invokeinterface #36,  2           // InterfaceMethod org/apache/hadoop/hbase/client/Table.delete:(Lorg/apache/hadoop/hbase/client/Delete;)V
     188: new           #37                 // class org/apache/hadoop/hbase/client/Scan
     191: dup
     192: invokespecial #38                 // Method org/apache/hadoop/hbase/client/Scan."<init>":()V
     195: getstatic     #22                 // Field ROW:[B
     198: invokevirtual #39                 // Method org/apache/hadoop/hbase/client/Scan.withStartRow:([B)Lorg/apache/hadoop/hbase/client/Scan;
     201: astore        5
     203: aload         5
     205: invokevirtual #40                 // Method org/apache/hadoop/hbase/client/Scan.setMaxVersions:()Lorg/apache/hadoop/hbase/client/Scan;
     208: pop
     209: aload_3
     210: aload         5
     212: invokeinterface #41,  2           // InterfaceMethod org/apache/hadoop/hbase/client/Table.getScanner:(Lorg/apache/hadoop/hbase/client/Scan;)Lorg/apache/hadoop/hbase/client/ResultScanner;
     217: astore        8
     219: new           #42                 // class java/util/ArrayList
     222: dup
     223: invokespecial #43                 // Method java/util/ArrayList."<init>":()V
     226: astore        10
     228: aload         10
     230: new           #24                 // class org/apache/hadoop/hbase/KeyValue
     233: dup
     234: getstatic     #22                 // Field ROW:[B
     237: getstatic     #19                 // Field FAMILY:[B
     240: aload_2
     241: iconst_4
     242: aaload
     243: ldc2_w        #44                 // long 4l
     246: getstatic     #25                 // Field VALUE:[B
     249: invokespecial #26                 // Method org/apache/hadoop/hbase/KeyValue."<init>":([B[B[BJ[B)V
     252: invokeinterface #46,  2           // InterfaceMethod java/util/List.add:(Ljava/lang/Object;)Z
     257: pop
     258: aload         10
     260: new           #24                 // class org/apache/hadoop/hbase/KeyValue
     263: dup
     264: getstatic     #22                 // Field ROW:[B
     267: getstatic     #19                 // Field FAMILY:[B
     270: aload_2
     271: iconst_5
     272: aaload
     273: ldc2_w        #47                 // long 5l
     276: getstatic     #25                 // Field VALUE:[B
     279: invokespecial #26                 // Method org/apache/hadoop/hbase/KeyValue."<init>":([B[B[BJ[B)V
     282: invokeinterface #46,  2           // InterfaceMethod java/util/List.add:(Ljava/lang/Object;)Z
     287: pop
     288: aload         10
     290: new           #24                 // class org/apache/hadoop/hbase/KeyValue
     293: dup
     294: getstatic     #22                 // Field ROW:[B
     297: getstatic     #19                 // Field FAMILY:[B
     300: aload_2
     301: bipush        6
     303: aaload
     304: ldc2_w        #49                 // long 6l
     307: getstatic     #25                 // Field VALUE:[B
     310: invokespecial #26                 // Method org/apache/hadoop/hbase/KeyValue."<init>":([B[B[BJ[B)V
     313: invokeinterface #46,  2           // InterfaceMethod java/util/List.add:(Ljava/lang/Object;)Z
     318: pop
     319: aload         10
     321: new           #24                 // class org/apache/hadoop/hbase/KeyValue
     324: dup
     325: getstatic     #22                 // Field ROW:[B
     328: getstatic     #19                 // Field FAMILY:[B
     331: aload_2
     332: bipush        7
     334: aaload
     335: ldc2_w        #51                 // long 7l
     338: getstatic     #25                 // Field VALUE:[B
     341: invokespecial #26                 // Method org/apache/hadoop/hbase/KeyValue."<init>":([B[B[BJ[B)V
     344: invokeinterface #46,  2           // InterfaceMethod java/util/List.add:(Ljava/lang/Object;)Z
     349: pop
     350: aload         8
     352: invokeinterface #53,  1           // InterfaceMethod org/apache/hadoop/hbase/client/ResultScanner.next:()Lorg/apache/hadoop/hbase/client/Result;
     357: astore        7
     359: aload         7
     361: aload         10
     363: iload         9
     365: ldc           #54                 // String Testing first batch of scan
     367: invokestatic  #55                 // Method verifyResult:(Lorg/apache/hadoop/hbase/client/Result;Ljava/util/List;ZLjava/lang/String;)V
     370: new           #37                 // class org/apache/hadoop/hbase/client/Scan
     373: dup
     374: invokespecial #38                 // Method org/apache/hadoop/hbase/client/Scan."<init>":()V
     377: getstatic     #22                 // Field ROW:[B
     380: invokevirtual #39                 // Method org/apache/hadoop/hbase/client/Scan.withStartRow:([B)Lorg/apache/hadoop/hbase/client/Scan;
     383: astore        5
     385: aload         5
     387: invokevirtual #40                 // Method org/apache/hadoop/hbase/client/Scan.setMaxVersions:()Lorg/apache/hadoop/hbase/client/Scan;
     390: pop
     391: aload         5
     393: iconst_2
     394: invokevirtual #56                 // Method org/apache/hadoop/hbase/client/Scan.setBatch:(I)Lorg/apache/hadoop/hbase/client/Scan;
     397: pop
     398: aload_3
     399: aload         5
     401: invokeinterface #41,  2           // InterfaceMethod org/apache/hadoop/hbase/client/Table.getScanner:(Lorg/apache/hadoop/hbase/client/Scan;)Lorg/apache/hadoop/hbase/client/ResultScanner;
     406: astore        8
     408: new           #42                 // class java/util/ArrayList
     411: dup
     412: invokespecial #43                 // Method java/util/ArrayList."<init>":()V
     415: astore        10
     417: aload         10
     419: new           #24                 // class org/apache/hadoop/hbase/KeyValue
     422: dup
     423: getstatic     #22                 // Field ROW:[B
     426: getstatic     #19                 // Field FAMILY:[B
     429: aload_2
     430: iconst_4
     431: aaload
     432: ldc2_w        #44                 // long 4l
     435: getstatic     #25                 // Field VALUE:[B
     438: invokespecial #26                 // Method org/apache/hadoop/hbase/KeyValue."<init>":([B[B[BJ[B)V
     441: invokeinterface #46,  2           // InterfaceMethod java/util/List.add:(Ljava/lang/Object;)Z
     446: pop
     447: aload         10
     449: new           #24                 // class org/apache/hadoop/hbase/KeyValue
     452: dup
     453: getstatic     #22                 // Field ROW:[B
     456: getstatic     #19                 // Field FAMILY:[B
     459: aload_2
     460: iconst_5
     461: aaload
     462: ldc2_w        #47                 // long 5l
     465: getstatic     #25                 // Field VALUE:[B
     468: invokespecial #26                 // Method org/apache/hadoop/hbase/KeyValue."<init>":([B[B[BJ[B)V
     471: invokeinterface #46,  2           // InterfaceMethod java/util/List.add:(Ljava/lang/Object;)Z
     476: pop
     477: aload         8
     479: invokeinterface #53,  1           // InterfaceMethod org/apache/hadoop/hbase/client/ResultScanner.next:()Lorg/apache/hadoop/hbase/client/Result;
     484: astore        7
     486: aload         7
     488: aload         10
     490: iload         9
     492: ldc           #54                 // String Testing first batch of scan
     494: invokestatic  #55                 // Method verifyResult:(Lorg/apache/hadoop/hbase/client/Result;Ljava/util/List;ZLjava/lang/String;)V
     497: new           #42                 // class java/util/ArrayList
     500: dup
     501: invokespecial #43                 // Method java/util/ArrayList."<init>":()V
     504: astore        10
     506: aload         10
     508: new           #24                 // class org/apache/hadoop/hbase/KeyValue
     511: dup
     512: getstatic     #22                 // Field ROW:[B
     515: getstatic     #19                 // Field FAMILY:[B
     518: aload_2
     519: bipush        6
     521: aaload
     522: ldc2_w        #49                 // long 6l
     525: getstatic     #25                 // Field VALUE:[B
     528: invokespecial #26                 // Method org/apache/hadoop/hbase/KeyValue."<init>":([B[B[BJ[B)V
     531: invokeinterface #46,  2           // InterfaceMethod java/util/List.add:(Ljava/lang/Object;)Z
     536: pop
     537: aload         10
     539: new           #24                 // class org/apache/hadoop/hbase/KeyValue
     542: dup
     543: getstatic     #22                 // Field ROW:[B
     546: getstatic     #19                 // Field FAMILY:[B
     549: aload_2
     550: bipush        7
     552: aaload
     553: ldc2_w        #51                 // long 7l
     556: getstatic     #25                 // Field VALUE:[B
     559: invokespecial #26                 // Method org/apache/hadoop/hbase/KeyValue."<init>":([B[B[BJ[B)V
     562: invokeinterface #46,  2           // InterfaceMethod java/util/List.add:(Ljava/lang/Object;)Z
     567: pop
     568: aload         8
     570: invokeinterface #53,  1           // InterfaceMethod org/apache/hadoop/hbase/client/ResultScanner.next:()Lorg/apache/hadoop/hbase/client/Result;
     575: astore        7
     577: aload         7
     579: aload         10
     581: iload         9
     583: ldc           #57                 // String Testing second batch of scan
     585: invokestatic  #55                 // Method verifyResult:(Lorg/apache/hadoop/hbase/client/Result;Ljava/util/List;ZLjava/lang/String;)V
     588: return

  public void testMaxResultSizeIsSetToDefault() throws java.lang.Exception;
    Code:
       0: aload_0
       1: getfield      #6                  // Field name:Lorg/junit/rules/TestName;
       4: invokevirtual #15                 // Method org/junit/rules/TestName.getMethodName:()Ljava/lang/String;
       7: invokestatic  #16                 // Method org/apache/hadoop/hbase/TableName.valueOf:(Ljava/lang/String;)Lorg/apache/hadoop/hbase/TableName;
      10: astore_1
      11: getstatic     #7                  // Field TEST_UTIL:Lorg/apache/hadoop/hbase/HBaseTestingUtility;
      14: aload_1
      15: getstatic     #19                 // Field FAMILY:[B
      18: invokevirtual #20                 // Method org/apache/hadoop/hbase/HBaseTestingUtility.createTable:(Lorg/apache/hadoop/hbase/TableName;[B)Lorg/apache/hadoop/hbase/client/Table;
      21: astore_2
      22: getstatic     #7                  // Field TEST_UTIL:Lorg/apache/hadoop/hbase/HBaseTestingUtility;
      25: invokevirtual #8                  // Method org/apache/hadoop/hbase/HBaseTestingUtility.getConfiguration:()Lorg/apache/hadoop/conf/Configuration;
      28: ldc           #9                  // String hbase.client.scanner.max.result.size
      30: ldc2_w        #58                 // long 2097152l
      33: invokevirtual #60                 // Method org/apache/hadoop/conf/Configuration.getLong:(Ljava/lang/String;J)J
      36: lstore_3
      37: iconst_5
      38: istore        5
      40: getstatic     #22                 // Field ROW:[B
      43: iload         5
      45: invokestatic  #18                 // Method org/apache/hadoop/hbase/HTestConst.makeNAscii:([BI)[[B
      48: astore        6
      50: bipush        10
      52: istore        7
      54: getstatic     #17                 // Field QUALIFIER:[B
      57: iload         7
      59: invokestatic  #18                 // Method org/apache/hadoop/hbase/HTestConst.makeNAscii:([BI)[[B
      62: astore        8
      64: lload_3
      65: iload         7
      67: iconst_1
      68: isub
      69: i2l
      70: ldiv
      71: l2i
      72: istore        9
      74: iload         9
      76: invokestatic  #61                 // Method org/apache/hadoop/hbase/util/Bytes.createMaxByteArray:(I)[B
      79: astore        10
      81: new           #42                 // class java/util/ArrayList
      84: dup
      85: invokespecial #43                 // Method java/util/ArrayList."<init>":()V
      88: astore        12
      90: iconst_0
      91: istore        13
      93: iload         13
      95: aload         6
      97: arraylength
      98: if_icmpge     180
     101: new           #21                 // class org/apache/hadoop/hbase/client/Put
     104: dup
     105: aload         6
     107: iload         13
     109: aaload
     110: invokespecial #23                 // Method org/apache/hadoop/hbase/client/Put."<init>":([B)V
     113: astore        11
     115: iconst_0
     116: istore        14
     118: iload         14
     120: aload         8
     122: arraylength
     123: if_icmpge     164
     126: new           #24                 // class org/apache/hadoop/hbase/KeyValue
     129: dup
     130: aload         6
     132: iload         13
     134: aaload
     135: getstatic     #19                 // Field FAMILY:[B
     138: aload         8
     140: iload         14
     142: aaload
     143: aload         10
     145: invokespecial #62                 // Method org/apache/hadoop/hbase/KeyValue."<init>":([B[B[B[B)V
     148: astore        15
     150: aload         11
     152: aload         15
     154: invokevirtual #27                 // Method org/apache/hadoop/hbase/client/Put.add:(Lorg/apache/hadoop/hbase/Cell;)Lorg/apache/hadoop/hbase/client/Put;
     157: pop
     158: iinc          14, 1
     161: goto          118
     164: aload         12
     166: aload         11
     168: invokeinterface #46,  2           // InterfaceMethod java/util/List.add:(Ljava/lang/Object;)Z
     173: pop
     174: iinc          13, 1
     177: goto          93
     180: aload_2
     181: aload         12
     183: invokeinterface #63,  2           // InterfaceMethod org/apache/hadoop/hbase/client/Table.put:(Ljava/util/List;)V
     188: new           #37                 // class org/apache/hadoop/hbase/client/Scan
     191: dup
     192: invokespecial #38                 // Method org/apache/hadoop/hbase/client/Scan."<init>":()V
     195: astore        13
     197: aload_2
     198: aload         13
     200: invokeinterface #41,  2           // InterfaceMethod org/apache/hadoop/hbase/client/Table.getScanner:(Lorg/apache/hadoop/hbase/client/Scan;)Lorg/apache/hadoop/hbase/client/ResultScanner;
     205: astore        14
     207: aload         14
     209: instanceof    #64                 // class org/apache/hadoop/hbase/client/ClientScanner
     212: invokestatic  #65                 // Method org/junit/Assert.assertTrue:(Z)V
     215: aload         14
     217: checkcast     #64                 // class org/apache/hadoop/hbase/client/ClientScanner
     220: astore        15
     222: aload         14
     224: invokeinterface #53,  1           // InterfaceMethod org/apache/hadoop/hbase/client/ResultScanner.next:()Lorg/apache/hadoop/hbase/client/Result;
     229: pop
     230: new           #66                 // class java/lang/StringBuilder
     233: dup
     234: invokespecial #67                 // Method java/lang/StringBuilder."<init>":()V
     237: ldc           #68                 // String The cache contains:
     239: invokevirtual #69                 // Method java/lang/StringBuilder.append:(Ljava/lang/String;)Ljava/lang/StringBuilder;
     242: aload         15
     244: invokevirtual #70                 // Method org/apache/hadoop/hbase/client/ClientScanner.getCacheSize:()I
     247: invokevirtual #71                 // Method java/lang/StringBuilder.append:(I)Ljava/lang/StringBuilder;
     250: ldc           #72                 // String  results
     252: invokevirtual #69                 // Method java/lang/StringBuilder.append:(Ljava/lang/String;)Ljava/lang/StringBuilder;
     255: invokevirtual #73                 // Method java/lang/StringBuilder.toString:()Ljava/lang/String;
     258: aload         15
     260: invokevirtual #70                 // Method org/apache/hadoop/hbase/client/ClientScanner.getCacheSize:()I
     263: iconst_1
     264: if_icmpgt     271
     267: iconst_1
     268: goto          272
     271: iconst_0
     272: invokestatic  #74                 // Method org/junit/Assert.assertTrue:(Ljava/lang/String;Z)V
     275: return

  public void testScannerForNotExistingTable();
    Code:
       0: iconst_4
       1: anewarray     #75                 // class java/lang/String
       4: dup
       5: iconst_0
       6: ldc           #76                 // String A
       8: aastore
       9: dup
      10: iconst_1
      11: ldc           #77                 // String Z
      13: aastore
      14: dup
      15: iconst_2
      16: ldc           #78                 // String A:A
      18: aastore
      19: dup
      20: iconst_3
      21: ldc           #79                 // String Z:Z
      23: aastore
      24: astore_1
      25: aload_1
      26: astore_2
      27: aload_2
      28: arraylength
      29: istore_3
      30: iconst_0
      31: istore        4
      33: iload         4
      35: iload_3
      36: if_icmpge     129
      39: aload_2
      40: iload         4
      42: aaload
      43: astore        5
      45: getstatic     #7                  // Field TEST_UTIL:Lorg/apache/hadoop/hbase/HBaseTestingUtility;
      48: invokevirtual #80                 // Method org/apache/hadoop/hbase/HBaseTestingUtility.getConnection:()Lorg/apache/hadoop/hbase/client/Connection;
      51: aload         5
      53: invokestatic  #16                 // Method org/apache/hadoop/hbase/TableName.valueOf:(Ljava/lang/String;)Lorg/apache/hadoop/hbase/TableName;
      56: invokeinterface #81,  2           // InterfaceMethod org/apache/hadoop/hbase/client/Connection.getTable:(Lorg/apache/hadoop/hbase/TableName;)Lorg/apache/hadoop/hbase/client/Table;
      61: astore        6
      63: aload_0
      64: aload         6
      66: iconst_1
      67: iconst_1
      68: iconst_5
      69: invokespecial #82                 // Method testSmallScan:(Lorg/apache/hadoop/hbase/client/Table;ZII)V
      72: ldc           #83                 // String TableNotFoundException was not thrown
      74: invokestatic  #84                 // Method org/junit/Assert.fail:(Ljava/lang/String;)V
      77: goto          123
      80: astore        6
      82: aload         6
      84: invokevirtual #86                 // Method org/apache/hadoop/hbase/TableNotFoundException.getMessage:()Ljava/lang/String;
      87: aload         5
      89: invokestatic  #87                 // Method org/junit/Assert.assertEquals:(Ljava/lang/Object;Ljava/lang/Object;)V
      92: goto          123
      95: astore        6
      97: new           #66                 // class java/lang/StringBuilder
     100: dup
     101: invokespecial #67                 // Method java/lang/StringBuilder."<init>":()V
     104: ldc           #89                 // String Unexpected exception
     106: invokevirtual #69                 // Method java/lang/StringBuilder.append:(Ljava/lang/String;)Ljava/lang/StringBuilder;
     109: aload         6
     111: invokevirtual #90                 // Method java/lang/Exception.getMessage:()Ljava/lang/String;
     114: invokevirtual #69                 // Method java/lang/StringBuilder.append:(Ljava/lang/String;)Ljava/lang/StringBuilder;
     117: invokevirtual #73                 // Method java/lang/StringBuilder.toString:()Ljava/lang/String;
     120: invokestatic  #84                 // Method org/junit/Assert.fail:(Ljava/lang/String;)V
     123: iinc          4, 1
     126: goto          33
     129: return
    Exception table:
       from    to  target type
          45    77    80   Class org/apache/hadoop/hbase/TableNotFoundException
          45    77    95   Class java/lang/Exception

  public void testSmallScan() throws java.lang.Exception;
    Code:
       0: aload_0
       1: getfield      #6                  // Field name:Lorg/junit/rules/TestName;
       4: invokevirtual #15                 // Method org/junit/rules/TestName.getMethodName:()Ljava/lang/String;
       7: invokestatic  #16                 // Method org/apache/hadoop/hbase/TableName.valueOf:(Ljava/lang/String;)Lorg/apache/hadoop/hbase/TableName;
      10: astore_1
      11: bipush        10
      13: istore_2
      14: getstatic     #22                 // Field ROW:[B
      17: iload_2
      18: invokestatic  #18                 // Method org/apache/hadoop/hbase/HTestConst.makeNAscii:([BI)[[B
      21: astore_3
      22: bipush        10
      24: istore        4
      26: getstatic     #17                 // Field QUALIFIER:[B
      29: iload         4
      31: invokestatic  #18                 // Method org/apache/hadoop/hbase/HTestConst.makeNAscii:([BI)[[B
      34: astore        5
      36: getstatic     #7                  // Field TEST_UTIL:Lorg/apache/hadoop/hbase/HBaseTestingUtility;
      39: aload_1
      40: getstatic     #19                 // Field FAMILY:[B
      43: invokevirtual #20                 // Method org/apache/hadoop/hbase/HBaseTestingUtility.createTable:(Lorg/apache/hadoop/hbase/TableName;[B)Lorg/apache/hadoop/hbase/client/Table;
      46: astore        6
      48: new           #42                 // class java/util/ArrayList
      51: dup
      52: invokespecial #43                 // Method java/util/ArrayList."<init>":()V
      55: astore        8
      57: iconst_0
      58: istore        9
      60: iload         9
      62: aload_3
      63: arraylength
      64: if_icmpge     145
      67: new           #21                 // class org/apache/hadoop/hbase/client/Put
      70: dup
      71: aload_3
      72: iload         9
      74: aaload
      75: invokespecial #23                 // Method org/apache/hadoop/hbase/client/Put."<init>":([B)V
      78: astore        7
      80: iconst_0
      81: istore        10
      83: iload         10
      85: aload         5
      87: arraylength
      88: if_icmpge     129
      91: new           #24                 // class org/apache/hadoop/hbase/KeyValue
      94: dup
      95: aload_3
      96: iload         9
      98: aaload
      99: getstatic     #19                 // Field FAMILY:[B
     102: aload         5
     104: iload         10
     106: aaload
     107: getstatic     #25                 // Field VALUE:[B
     110: invokespecial #62                 // Method org/apache/hadoop/hbase/KeyValue."<init>":([B[B[B[B)V
     113: astore        11
     115: aload         7
     117: aload         11
     119: invokevirtual #27                 // Method org/apache/hadoop/hbase/client/Put.add:(Lorg/apache/hadoop/hbase/Cell;)Lorg/apache/hadoop/hbase/client/Put;
     122: pop
     123: iinc          10, 1
     126: goto          83
     129: aload         8
     131: aload         7
     133: invokeinterface #46,  2           // InterfaceMethod java/util/List.add:(Ljava/lang/Object;)Z
     138: pop
     139: iinc          9, 1
     142: goto          60
     145: aload         6
     147: aload         8
     149: invokeinterface #63,  2           // InterfaceMethod org/apache/hadoop/hbase/client/Table.put:(Ljava/util/List;)V
     154: iload_2
     155: istore        9
     157: iload_2
     158: iload         4
     160: imul
     161: istore        10
     163: aload_0
     164: aload         6
     166: iconst_1
     167: iload         9
     169: iload         10
     171: invokespecial #82                 // Method testSmallScan:(Lorg/apache/hadoop/hbase/client/Table;ZII)V
     174: aload_0
     175: aload         6
     177: iconst_0
     178: iload         9
     180: iload         10
     182: invokespecial #82                 // Method testSmallScan:(Lorg/apache/hadoop/hbase/client/Table;ZII)V
     185: return

  public void testGetMaxResults() throws java.lang.Exception;
    Code:
       0: aload_0
       1: getfield      #6                  // Field name:Lorg/junit/rules/TestName;
       4: invokevirtual #15                 // Method org/junit/rules/TestName.getMethodName:()Ljava/lang/String;
       7: invokestatic  #16                 // Method org/apache/hadoop/hbase/TableName.valueOf:(Ljava/lang/String;)Lorg/apache/hadoop/hbase/TableName;
      10: astore_1
      11: getstatic     #19                 // Field FAMILY:[B
      14: iconst_3
      15: invokestatic  #18                 // Method org/apache/hadoop/hbase/HTestConst.makeNAscii:([BI)[[B
      18: astore_2
      19: getstatic     #17                 // Field QUALIFIER:[B
      22: bipush        20
      24: invokestatic  #18                 // Method org/apache/hadoop/hbase/HTestConst.makeNAscii:([BI)[[B
      27: astore_3
      28: getstatic     #7                  // Field TEST_UTIL:Lorg/apache/hadoop/hbase/HBaseTestingUtility;
      31: aload_1
      32: aload_2
      33: invokevirtual #105                // Method org/apache/hadoop/hbase/HBaseTestingUtility.createTable:(Lorg/apache/hadoop/hbase/TableName;[[B)Lorg/apache/hadoop/hbase/client/Table;
      36: astore        4
      38: iconst_1
      39: istore        8
      41: new           #42                 // class java/util/ArrayList
      44: dup
      45: invokespecial #43                 // Method java/util/ArrayList."<init>":()V
      48: astore        9
      50: new           #21                 // class org/apache/hadoop/hbase/client/Put
      53: dup
      54: getstatic     #22                 // Field ROW:[B
      57: invokespecial #23                 // Method org/apache/hadoop/hbase/client/Put."<init>":([B)V
      60: astore        6
      62: iconst_0
      63: istore        10
      65: iload         10
      67: bipush        10
      69: if_icmpge     119
      72: new           #24                 // class org/apache/hadoop/hbase/KeyValue
      75: dup
      76: getstatic     #22                 // Field ROW:[B
      79: aload_2
      80: iconst_0
      81: aaload
      82: aload_3
      83: iload         10
      85: aaload
      86: lconst_1
      87: getstatic     #25                 // Field VALUE:[B
      90: invokespecial #26                 // Method org/apache/hadoop/hbase/KeyValue."<init>":([B[B[BJ[B)V
      93: astore        11
      95: aload         6
      97: aload         11
      99: invokevirtual #27                 // Method org/apache/hadoop/hbase/client/Put.add:(Lorg/apache/hadoop/hbase/Cell;)Lorg/apache/hadoop/hbase/client/Put;
     102: pop
     103: aload         9
     105: aload         11
     107: invokeinterface #46,  2           // InterfaceMethod java/util/List.add:(Ljava/lang/Object;)Z
     112: pop
     113: iinc          10, 1
     116: goto          65
     119: aload         4
     121: aload         6
     123: invokeinterface #28,  2           // InterfaceMethod org/apache/hadoop/hbase/client/Table.put:(Lorg/apache/hadoop/hbase/client/Put;)V
     128: new           #106                // class org/apache/hadoop/hbase/client/Get
     131: dup
     132: getstatic     #22                 // Field ROW:[B
     135: invokespecial #107                // Method org/apache/hadoop/hbase/client/Get."<init>":([B)V
     138: astore        5
     140: aload         4
     142: aload         5
     144: invokeinterface #108,  2          // InterfaceMethod org/apache/hadoop/hbase/client/Table.get:(Lorg/apache/hadoop/hbase/client/Get;)Lorg/apache/hadoop/hbase/client/Result;
     149: astore        7
     151: aload         7
     153: aload         9
     155: iload         8
     157: ldc           #109                // String Testing without setting maxResults
     159: invokestatic  #55                 // Method verifyResult:(Lorg/apache/hadoop/hbase/client/Result;Ljava/util/List;ZLjava/lang/String;)V
     162: new           #106                // class org/apache/hadoop/hbase/client/Get
     165: dup
     166: getstatic     #22                 // Field ROW:[B
     169: invokespecial #107                // Method org/apache/hadoop/hbase/client/Get."<init>":([B)V
     172: astore        5
     174: aload         5
     176: iconst_2
     177: invokevirtual #110                // Method org/apache/hadoop/hbase/client/Get.setMaxResultsPerColumnFamily:(I)Lorg/apache/hadoop/hbase/client/Get;
     180: pop
     181: aload         4
     183: aload         5
     185: invokeinterface #108,  2          // InterfaceMethod org/apache/hadoop/hbase/client/Table.get:(Lorg/apache/hadoop/hbase/client/Get;)Lorg/apache/hadoop/hbase/client/Result;
     190: astore        7
     192: new           #42                 // class java/util/ArrayList
     195: dup
     196: invokespecial #43                 // Method java/util/ArrayList."<init>":()V
     199: astore        9
     201: aload         9
     203: new           #24                 // class org/apache/hadoop/hbase/KeyValue
     206: dup
     207: getstatic     #22                 // Field ROW:[B
     210: aload_2
     211: iconst_0
     212: aaload
     213: aload_3
     214: iconst_0
     215: aaload
     216: lconst_1
     217: getstatic     #25                 // Field VALUE:[B
     220: invokespecial #26                 // Method org/apache/hadoop/hbase/KeyValue."<init>":([B[B[BJ[B)V
     223: invokeinterface #46,  2           // InterfaceMethod java/util/List.add:(Ljava/lang/Object;)Z
     228: pop
     229: aload         9
     231: new           #24                 // class org/apache/hadoop/hbase/KeyValue
     234: dup
     235: getstatic     #22                 // Field ROW:[B
     238: aload_2
     239: iconst_0
     240: aaload
     241: aload_3
     242: iconst_1
     243: aaload
     244: lconst_1
     245: getstatic     #25                 // Field VALUE:[B
     248: invokespecial #26                 // Method org/apache/hadoop/hbase/KeyValue."<init>":([B[B[BJ[B)V
     251: invokeinterface #46,  2           // InterfaceMethod java/util/List.add:(Ljava/lang/Object;)Z
     256: pop
     257: aload         7
     259: aload         9
     261: iload         8
     263: ldc           #111                // String Testing basic setMaxResults
     265: invokestatic  #55                 // Method verifyResult:(Lorg/apache/hadoop/hbase/client/Result;Ljava/util/List;ZLjava/lang/String;)V
     268: new           #106                // class org/apache/hadoop/hbase/client/Get
     271: dup
     272: getstatic     #22                 // Field ROW:[B
     275: invokespecial #107                // Method org/apache/hadoop/hbase/client/Get."<init>":([B)V
     278: astore        5
     280: aload         5
     282: iconst_5
     283: invokevirtual #110                // Method org/apache/hadoop/hbase/client/Get.setMaxResultsPerColumnFamily:(I)Lorg/apache/hadoop/hbase/client/Get;
     286: pop
     287: aload         5
     289: new           #112                // class org/apache/hadoop/hbase/filter/ColumnRangeFilter
     292: dup
     293: aload_3
     294: iconst_2
     295: aaload
     296: iconst_1
     297: aload_3
     298: iconst_5
     299: aaload
     300: iconst_1
     301: invokespecial #113                // Method org/apache/hadoop/hbase/filter/ColumnRangeFilter."<init>":([BZ[BZ)V
     304: invokevirtual #114                // Method org/apache/hadoop/hbase/client/Get.setFilter:(Lorg/apache/hadoop/hbase/filter/Filter;)Lorg/apache/hadoop/hbase/client/Get;
     307: pop
     308: aload         4
     310: aload         5
     312: invokeinterface #108,  2          // InterfaceMethod org/apache/hadoop/hbase/client/Table.get:(Lorg/apache/hadoop/hbase/client/Get;)Lorg/apache/hadoop/hbase/client/Result;
     317: astore        7
     319: new           #42                 // class java/util/ArrayList
     322: dup
     323: invokespecial #43                 // Method java/util/ArrayList."<init>":()V
     326: astore        9
     328: aload         9
     330: new           #24                 // class org/apache/hadoop/hbase/KeyValue
     333: dup
     334: getstatic     #22                 // Field ROW:[B
     337: aload_2
     338: iconst_0
     339: aaload
     340: aload_3
     341: iconst_2
     342: aaload
     343: lconst_1
     344: getstatic     #25                 // Field VALUE:[B
     347: invokespecial #26                 // Method org/apache/hadoop/hbase/KeyValue."<init>":([B[B[BJ[B)V
     350: invokeinterface #46,  2           // InterfaceMethod java/util/List.add:(Ljava/lang/Object;)Z
     355: pop
     356: aload         9
     358: new           #24                 // class org/apache/hadoop/hbase/KeyValue
     361: dup
     362: getstatic     #22                 // Field ROW:[B
     365: aload_2
     366: iconst_0
     367: aaload
     368: aload_3
     369: iconst_3
     370: aaload
     371: lconst_1
     372: getstatic     #25                 // Field VALUE:[B
     375: invokespecial #26                 // Method org/apache/hadoop/hbase/KeyValue."<init>":([B[B[BJ[B)V
     378: invokeinterface #46,  2           // InterfaceMethod java/util/List.add:(Ljava/lang/Object;)Z
     383: pop
     384: aload         9
     386: new           #24                 // class org/apache/hadoop/hbase/KeyValue
     389: dup
     390: getstatic     #22                 // Field ROW:[B
     393: aload_2
     394: iconst_0
     395: aaload
     396: aload_3
     397: iconst_4
     398: aaload
     399: lconst_1
     400: getstatic     #25                 // Field VALUE:[B
     403: invokespecial #26                 // Method org/apache/hadoop/hbase/KeyValue."<init>":([B[B[BJ[B)V
     406: invokeinterface #46,  2           // InterfaceMethod java/util/List.add:(Ljava/lang/Object;)Z
     411: pop
     412: aload         9
     414: new           #24                 // class org/apache/hadoop/hbase/KeyValue
     417: dup
     418: getstatic     #22                 // Field ROW:[B
     421: aload_2
     422: iconst_0
     423: aaload
     424: aload_3
     425: iconst_5
     426: aaload
     427: lconst_1
     428: getstatic     #25                 // Field VALUE:[B
     431: invokespecial #26                 // Method org/apache/hadoop/hbase/KeyValue."<init>":([B[B[BJ[B)V
     434: invokeinterface #46,  2           // InterfaceMethod java/util/List.add:(Ljava/lang/Object;)Z
     439: pop
     440: aload         7
     442: aload         9
     444: iload         8
     446: ldc           #115                // String Testing single CF with CRF
     448: invokestatic  #55                 // Method verifyResult:(Lorg/apache/hadoop/hbase/client/Result;Ljava/util/List;ZLjava/lang/String;)V
     451: new           #21                 // class org/apache/hadoop/hbase/client/Put
     454: dup
     455: getstatic     #22                 // Field ROW:[B
     458: invokespecial #23                 // Method org/apache/hadoop/hbase/client/Put."<init>":([B)V
     461: astore        6
     463: iconst_0
     464: istore        10
     466: iload         10
     468: aload_3
     469: arraylength
     470: if_icmpge     510
     473: new           #24                 // class org/apache/hadoop/hbase/KeyValue
     476: dup
     477: getstatic     #22                 // Field ROW:[B
     480: aload_2
     481: iconst_2
     482: aaload
     483: aload_3
     484: iload         10
     486: aaload
     487: lconst_1
     488: getstatic     #25                 // Field VALUE:[B
     491: invokespecial #26                 // Method org/apache/hadoop/hbase/KeyValue."<init>":([B[B[BJ[B)V
     494: astore        11
     496: aload         6
     498: aload         11
     500: invokevirtual #27                 // Method org/apache/hadoop/hbase/client/Put.add:(Lorg/apache/hadoop/hbase/Cell;)Lorg/apache/hadoop/hbase/client/Put;
     503: pop
     504: iinc          10, 1
     507: goto          466
     510: aload         4
     512: aload         6
     514: invokeinterface #28,  2           // InterfaceMethod org/apache/hadoop/hbase/client/Table.put:(Lorg/apache/hadoop/hbase/client/Put;)V
     519: new           #21                 // class org/apache/hadoop/hbase/client/Put
     522: dup
     523: getstatic     #22                 // Field ROW:[B
     526: invokespecial #23                 // Method org/apache/hadoop/hbase/client/Put."<init>":([B)V
     529: astore        6
     531: iconst_0
     532: istore        10
     534: iload         10
     536: bipush        10
     538: if_icmpge     578
     541: new           #24                 // class org/apache/hadoop/hbase/KeyValue
     544: dup
     545: getstatic     #22                 // Field ROW:[B
     548: aload_2
     549: iconst_1
     550: aaload
     551: aload_3
     552: iload         10
     554: aaload
     555: lconst_1
     556: getstatic     #25                 // Field VALUE:[B
     559: invokespecial #26                 // Method org/apache/hadoop/hbase/KeyValue."<init>":([B[B[BJ[B)V
     562: astore        11
     564: aload         6
     566: aload         11
     568: invokevirtual #27                 // Method org/apache/hadoop/hbase/client/Put.add:(Lorg/apache/hadoop/hbase/Cell;)Lorg/apache/hadoop/hbase/client/Put;
     571: pop
     572: iinc          10, 1
     575: goto          534
     578: aload         4
     580: aload         6
     582: invokeinterface #28,  2           // InterfaceMethod org/apache/hadoop/hbase/client/Table.put:(Lorg/apache/hadoop/hbase/client/Put;)V
     587: new           #106                // class org/apache/hadoop/hbase/client/Get
     590: dup
     591: getstatic     #22                 // Field ROW:[B
     594: invokespecial #107                // Method org/apache/hadoop/hbase/client/Get."<init>":([B)V
     597: astore        5
     599: aload         5
     601: bipush        12
     603: invokevirtual #110                // Method org/apache/hadoop/hbase/client/Get.setMaxResultsPerColumnFamily:(I)Lorg/apache/hadoop/hbase/client/Get;
     606: pop
     607: aload         5
     609: aload_2
     610: iconst_1
     611: aaload
     612: invokevirtual #116                // Method org/apache/hadoop/hbase/client/Get.addFamily:([B)Lorg/apache/hadoop/hbase/client/Get;
     615: pop
     616: aload         5
     618: aload_2
     619: iconst_2
     620: aaload
     621: invokevirtual #116                // Method org/apache/hadoop/hbase/client/Get.addFamily:([B)Lorg/apache/hadoop/hbase/client/Get;
     624: pop
     625: aload         4
     627: aload         5
     629: invokeinterface #108,  2          // InterfaceMethod org/apache/hadoop/hbase/client/Table.get:(Lorg/apache/hadoop/hbase/client/Get;)Lorg/apache/hadoop/hbase/client/Result;
     634: astore        7
     636: new           #42                 // class java/util/ArrayList
     639: dup
     640: invokespecial #43                 // Method java/util/ArrayList."<init>":()V
     643: astore        9
     645: iconst_0
     646: istore        10
     648: iload         10
     650: bipush        10
     652: if_icmpge     690
     655: aload         9
     657: new           #24                 // class org/apache/hadoop/hbase/KeyValue
     660: dup
     661: getstatic     #22                 // Field ROW:[B
     664: aload_2
     665: iconst_1
     666: aaload
     667: aload_3
     668: iload         10
     670: aaload
     671: lconst_1
     672: getstatic     #25                 // Field VALUE:[B
     675: invokespecial #26                 // Method org/apache/hadoop/hbase/KeyValue."<init>":([B[B[BJ[B)V
     678: invokeinterface #46,  2           // InterfaceMethod java/util/List.add:(Ljava/lang/Object;)Z
     683: pop
     684: iinc          10, 1
     687: goto          648
     690: iconst_0
     691: istore        10
     693: iload         10
     695: iconst_2
     696: if_icmpge     734
     699: aload         9
     701: new           #24                 // class org/apache/hadoop/hbase/KeyValue
     704: dup
     705: getstatic     #22                 // Field ROW:[B
     708: aload_2
     709: iconst_2
     710: aaload
     711: aload_3
     712: iload         10
     714: aaload
     715: lconst_1
     716: getstatic     #25                 // Field VALUE:[B
     719: invokespecial #26                 // Method org/apache/hadoop/hbase/KeyValue."<init>":([B[B[BJ[B)V
     722: invokeinterface #46,  2           // InterfaceMethod java/util/List.add:(Ljava/lang/Object;)Z
     727: pop
     728: iinc          10, 1
     731: goto          693
     734: bipush        10
     736: istore        10
     738: iload         10
     740: bipush        20
     742: if_icmpge     780
     745: aload         9
     747: new           #24                 // class org/apache/hadoop/hbase/KeyValue
     750: dup
     751: getstatic     #22                 // Field ROW:[B
     754: aload_2
     755: iconst_2
     756: aaload
     757: aload_3
     758: iload         10
     760: aaload
     761: lconst_1
     762: getstatic     #25                 // Field VALUE:[B
     765: invokespecial #26                 // Method org/apache/hadoop/hbase/KeyValue."<init>":([B[B[BJ[B)V
     768: invokeinterface #46,  2           // InterfaceMethod java/util/List.add:(Ljava/lang/Object;)Z
     773: pop
     774: iinc          10, 1
     777: goto          738
     780: aload         7
     782: aload         9
     784: iload         8
     786: ldc           #117                // String Testing multiple CFs
     788: invokestatic  #55                 // Method verifyResult:(Lorg/apache/hadoop/hbase/client/Result;Ljava/util/List;ZLjava/lang/String;)V
     791: new           #106                // class org/apache/hadoop/hbase/client/Get
     794: dup
     795: getstatic     #22                 // Field ROW:[B
     798: invokespecial #107                // Method org/apache/hadoop/hbase/client/Get."<init>":([B)V
     801: astore        5
     803: aload         5
     805: iconst_3
     806: invokevirtual #110                // Method org/apache/hadoop/hbase/client/Get.setMaxResultsPerColumnFamily:(I)Lorg/apache/hadoop/hbase/client/Get;
     809: pop
     810: aload         5
     812: new           #112                // class org/apache/hadoop/hbase/filter/ColumnRangeFilter
     815: dup
     816: aload_3
     817: iconst_2
     818: aaload
     819: iconst_1
     820: aconst_null
     821: iconst_1
     822: invokespecial #113                // Method org/apache/hadoop/hbase/filter/ColumnRangeFilter."<init>":([BZ[BZ)V
     825: invokevirtual #114                // Method org/apache/hadoop/hbase/client/Get.setFilter:(Lorg/apache/hadoop/hbase/filter/Filter;)Lorg/apache/hadoop/hbase/client/Get;
     828: pop
     829: aload         4
     831: aload         5
     833: invokeinterface #108,  2          // InterfaceMethod org/apache/hadoop/hbase/client/Table.get:(Lorg/apache/hadoop/hbase/client/Get;)Lorg/apache/hadoop/hbase/client/Result;
     838: astore        7
     840: new           #42                 // class java/util/ArrayList
     843: dup
     844: invokespecial #43                 // Method java/util/ArrayList."<init>":()V
     847: astore        9
     849: iconst_2
     850: istore        10
     852: iload         10
     854: iconst_5
     855: if_icmpge     893
     858: aload         9
     860: new           #24                 // class org/apache/hadoop/hbase/KeyValue
     863: dup
     864: getstatic     #22                 // Field ROW:[B
     867: aload_2
     868: iconst_0
     869: aaload
     870: aload_3
     871: iload         10
     873: aaload
     874: lconst_1
     875: getstatic     #25                 // Field VALUE:[B
     878: invokespecial #26                 // Method org/apache/hadoop/hbase/KeyValue."<init>":([B[B[BJ[B)V
     881: invokeinterface #46,  2           // InterfaceMethod java/util/List.add:(Ljava/lang/Object;)Z
     886: pop
     887: iinc          10, 1
     890: goto          852
     893: iconst_2
     894: istore        10
     896: iload         10
     898: iconst_5
     899: if_icmpge     937
     902: aload         9
     904: new           #24                 // class org/apache/hadoop/hbase/KeyValue
     907: dup
     908: getstatic     #22                 // Field ROW:[B
     911: aload_2
     912: iconst_1
     913: aaload
     914: aload_3
     915: iload         10
     917: aaload
     918: lconst_1
     919: getstatic     #25                 // Field VALUE:[B
     922: invokespecial #26                 // Method org/apache/hadoop/hbase/KeyValue."<init>":([B[B[BJ[B)V
     925: invokeinterface #46,  2           // InterfaceMethod java/util/List.add:(Ljava/lang/Object;)Z
     930: pop
     931: iinc          10, 1
     934: goto          896
     937: iconst_2
     938: istore        10
     940: iload         10
     942: iconst_5
     943: if_icmpge     981
     946: aload         9
     948: new           #24                 // class org/apache/hadoop/hbase/KeyValue
     951: dup
     952: getstatic     #22                 // Field ROW:[B
     955: aload_2
     956: iconst_2
     957: aaload
     958: aload_3
     959: iload         10
     961: aaload
     962: lconst_1
     963: getstatic     #25                 // Field VALUE:[B
     966: invokespecial #26                 // Method org/apache/hadoop/hbase/KeyValue."<init>":([B[B[BJ[B)V
     969: invokeinterface #46,  2           // InterfaceMethod java/util/List.add:(Ljava/lang/Object;)Z
     974: pop
     975: iinc          10, 1
     978: goto          940
     981: aload         7
     983: aload         9
     985: iload         8
     987: ldc           #118                // String Testing multiple CFs + CRF
     989: invokestatic  #55                 // Method verifyResult:(Lorg/apache/hadoop/hbase/client/Result;Ljava/util/List;ZLjava/lang/String;)V
     992: new           #106                // class org/apache/hadoop/hbase/client/Get
     995: dup
     996: getstatic     #22                 // Field ROW:[B
     999: invokespecial #107                // Method org/apache/hadoop/hbase/client/Get."<init>":([B)V
    1002: astore        5
    1004: aload         5
    1006: bipush        7
    1008: invokevirtual #110                // Method org/apache/hadoop/hbase/client/Get.setMaxResultsPerColumnFamily:(I)Lorg/apache/hadoop/hbase/client/Get;
    1011: pop
    1012: aload         5
    1014: new           #119                // class org/apache/hadoop/hbase/filter/ColumnPrefixFilter
    1017: dup
    1018: aload_3
    1019: iconst_1
    1020: aaload
    1021: invokespecial #120                // Method org/apache/hadoop/hbase/filter/ColumnPrefixFilter."<init>":([B)V
    1024: invokevirtual #114                // Method org/apache/hadoop/hbase/client/Get.setFilter:(Lorg/apache/hadoop/hbase/filter/Filter;)Lorg/apache/hadoop/hbase/client/Get;
    1027: pop
    1028: aload         4
    1030: aload         5
    1032: invokeinterface #108,  2          // InterfaceMethod org/apache/hadoop/hbase/client/Table.get:(Lorg/apache/hadoop/hbase/client/Get;)Lorg/apache/hadoop/hbase/client/Result;
    1037: astore        7
    1039: new           #42                 // class java/util/ArrayList
    1042: dup
    1043: invokespecial #43                 // Method java/util/ArrayList."<init>":()V
    1046: astore        9
    1048: aload         9
    1050: new           #24                 // class org/apache/hadoop/hbase/KeyValue
    1053: dup
    1054: getstatic     #22                 // Field ROW:[B
    1057: aload_2
    1058: iconst_0
    1059: aaload
    1060: aload_3
    1061: iconst_1
    1062: aaload
    1063: lconst_1
    1064: getstatic     #25                 // Field VALUE:[B
    1067: invokespecial #26                 // Method org/apache/hadoop/hbase/KeyValue."<init>":([B[B[BJ[B)V
    1070: invokeinterface #46,  2           // InterfaceMethod java/util/List.add:(Ljava/lang/Object;)Z
    1075: pop
    1076: aload         9
    1078: new           #24                 // class org/apache/hadoop/hbase/KeyValue
    1081: dup
    1082: getstatic     #22                 // Field ROW:[B
    1085: aload_2
    1086: iconst_1
    1087: aaload
    1088: aload_3
    1089: iconst_1
    1090: aaload
    1091: lconst_1
    1092: getstatic     #25                 // Field VALUE:[B
    1095: invokespecial #26                 // Method org/apache/hadoop/hbase/KeyValue."<init>":([B[B[BJ[B)V
    1098: invokeinterface #46,  2           // InterfaceMethod java/util/List.add:(Ljava/lang/Object;)Z
    1103: pop
    1104: aload         9
    1106: new           #24                 // class org/apache/hadoop/hbase/KeyValue
    1109: dup
    1110: getstatic     #22                 // Field ROW:[B
    1113: aload_2
    1114: iconst_2
    1115: aaload
    1116: aload_3
    1117: iconst_1
    1118: aaload
    1119: lconst_1
    1120: getstatic     #25                 // Field VALUE:[B
    1123: invokespecial #26                 // Method org/apache/hadoop/hbase/KeyValue."<init>":([B[B[BJ[B)V
    1126: invokeinterface #46,  2           // InterfaceMethod java/util/List.add:(Ljava/lang/Object;)Z
    1131: pop
    1132: bipush        10
    1134: istore        10
    1136: iload         10
    1138: bipush        16
    1140: if_icmpge     1178
    1143: aload         9
    1145: new           #24                 // class org/apache/hadoop/hbase/KeyValue
    1148: dup
    1149: getstatic     #22                 // Field ROW:[B
    1152: aload_2
    1153: iconst_2
    1154: aaload
    1155: aload_3
    1156: iload         10
    1158: aaload
    1159: lconst_1
    1160: getstatic     #25                 // Field VALUE:[B
    1163: invokespecial #26                 // Method org/apache/hadoop/hbase/KeyValue."<init>":([B[B[BJ[B)V
    1166: invokeinterface #46,  2           // InterfaceMethod java/util/List.add:(Ljava/lang/Object;)Z
    1171: pop
    1172: iinc          10, 1
    1175: goto          1136
    1178: aload         7
    1180: aload         9
    1182: iload         8
    1184: ldc           #121                // String Testing multiple CFs + PFF
    1186: invokestatic  #55                 // Method verifyResult:(Lorg/apache/hadoop/hbase/client/Result;Ljava/util/List;ZLjava/lang/String;)V
    1189: return

  public void testScanMaxResults() throws java.lang.Exception;
    Code:
       0: aload_0
       1: getfield      #6                  // Field name:Lorg/junit/rules/TestName;
       4: invokevirtual #15                 // Method org/junit/rules/TestName.getMethodName:()Ljava/lang/String;
       7: invokestatic  #16                 // Method org/apache/hadoop/hbase/TableName.valueOf:(Ljava/lang/String;)Lorg/apache/hadoop/hbase/TableName;
      10: astore_1
      11: getstatic     #22                 // Field ROW:[B
      14: iconst_2
      15: invokestatic  #18                 // Method org/apache/hadoop/hbase/HTestConst.makeNAscii:([BI)[[B
      18: astore_2
      19: getstatic     #19                 // Field FAMILY:[B
      22: iconst_3
      23: invokestatic  #18                 // Method org/apache/hadoop/hbase/HTestConst.makeNAscii:([BI)[[B
      26: astore_3
      27: getstatic     #17                 // Field QUALIFIER:[B
      30: bipush        10
      32: invokestatic  #18                 // Method org/apache/hadoop/hbase/HTestConst.makeNAscii:([BI)[[B
      35: astore        4
      37: getstatic     #7                  // Field TEST_UTIL:Lorg/apache/hadoop/hbase/HBaseTestingUtility;
      40: aload_1
      41: aload_3
      42: invokevirtual #105                // Method org/apache/hadoop/hbase/HBaseTestingUtility.createTable:(Lorg/apache/hadoop/hbase/TableName;[[B)Lorg/apache/hadoop/hbase/client/Table;
      45: astore        5
      47: iconst_1
      48: istore        9
      50: new           #42                 // class java/util/ArrayList
      53: dup
      54: invokespecial #43                 // Method java/util/ArrayList."<init>":()V
      57: astore        10
      59: iconst_0
      60: istore        12
      62: iload         12
      64: aload_2
      65: arraylength
      66: if_icmpge     180
      69: new           #21                 // class org/apache/hadoop/hbase/client/Put
      72: dup
      73: aload_2
      74: iload         12
      76: aaload
      77: invokespecial #23                 // Method org/apache/hadoop/hbase/client/Put."<init>":([B)V
      80: astore        6
      82: iconst_0
      83: istore        13
      85: iload         13
      87: aload_3
      88: arraylength
      89: if_icmpge     165
      92: iconst_0
      93: istore        14
      95: iload         14
      97: aload         4
      99: arraylength
     100: if_icmpge     159
     103: new           #24                 // class org/apache/hadoop/hbase/KeyValue
     106: dup
     107: aload_2
     108: iload         12
     110: aaload
     111: aload_3
     112: iload         13
     114: aaload
     115: aload         4
     117: iload         14
     119: aaload
     120: lconst_1
     121: getstatic     #25                 // Field VALUE:[B
     124: invokespecial #26                 // Method org/apache/hadoop/hbase/KeyValue."<init>":([B[B[BJ[B)V
     127: astore        15
     129: aload         6
     131: aload         15
     133: invokevirtual #27                 // Method org/apache/hadoop/hbase/client/Put.add:(Lorg/apache/hadoop/hbase/Cell;)Lorg/apache/hadoop/hbase/client/Put;
     136: pop
     137: iload         14
     139: iconst_4
     140: if_icmpge     153
     143: aload         10
     145: aload         15
     147: invokeinterface #46,  2           // InterfaceMethod java/util/List.add:(Ljava/lang/Object;)Z
     152: pop
     153: iinc          14, 1
     156: goto          95
     159: iinc          13, 1
     162: goto          85
     165: aload         5
     167: aload         6
     169: invokeinterface #28,  2           // InterfaceMethod org/apache/hadoop/hbase/client/Table.put:(Lorg/apache/hadoop/hbase/client/Put;)V
     174: iinc          12, 1
     177: goto          62
     180: new           #37                 // class org/apache/hadoop/hbase/client/Scan
     183: dup
     184: invokespecial #38                 // Method org/apache/hadoop/hbase/client/Scan."<init>":()V
     187: astore        7
     189: aload         7
     191: iconst_4
     192: invokevirtual #122                // Method org/apache/hadoop/hbase/client/Scan.setMaxResultsPerColumnFamily:(I)Lorg/apache/hadoop/hbase/client/Scan;
     195: pop
     196: aload         5
     198: aload         7
     200: invokeinterface #41,  2           // InterfaceMethod org/apache/hadoop/hbase/client/Table.getScanner:(Lorg/apache/hadoop/hbase/client/Scan;)Lorg/apache/hadoop/hbase/client/ResultScanner;
     205: astore        12
     207: new           #42                 // class java/util/ArrayList
     210: dup
     211: invokespecial #43                 // Method java/util/ArrayList."<init>":()V
     214: astore        11
     216: aload         12
     218: invokeinterface #53,  1           // InterfaceMethod org/apache/hadoop/hbase/client/ResultScanner.next:()Lorg/apache/hadoop/hbase/client/Result;
     223: dup
     224: astore        8
     226: ifnull        279
     229: aload         8
     231: invokevirtual #123                // Method org/apache/hadoop/hbase/client/Result.listCells:()Ljava/util/List;
     234: invokeinterface #124,  1          // InterfaceMethod java/util/List.iterator:()Ljava/util/Iterator;
     239: astore        13
     241: aload         13
     243: invokeinterface #125,  1          // InterfaceMethod java/util/Iterator.hasNext:()Z
     248: ifeq          276
     251: aload         13
     253: invokeinterface #126,  1          // InterfaceMethod java/util/Iterator.next:()Ljava/lang/Object;
     258: checkcast     #127                // class org/apache/hadoop/hbase/Cell
     261: astore        14
     263: aload         11
     265: aload         14
     267: invokeinterface #46,  2           // InterfaceMethod java/util/List.add:(Ljava/lang/Object;)Z
     272: pop
     273: goto          241
     276: goto          216
     279: aload         11
     281: invokestatic  #128                // Method org/apache/hadoop/hbase/client/Result.create:(Ljava/util/List;)Lorg/apache/hadoop/hbase/client/Result;
     284: astore        8
     286: aload         8
     288: aload         10
     290: iload         9
     292: ldc           #129                // String Testing scan with maxResults
     294: invokestatic  #55                 // Method verifyResult:(Lorg/apache/hadoop/hbase/client/Result;Ljava/util/List;ZLjava/lang/String;)V
     297: return

  public void testGetRowOffset() throws java.lang.Exception;
    Code:
       0: aload_0
       1: getfield      #6                  // Field name:Lorg/junit/rules/TestName;
       4: invokevirtual #15                 // Method org/junit/rules/TestName.getMethodName:()Ljava/lang/String;
       7: invokestatic  #16                 // Method org/apache/hadoop/hbase/TableName.valueOf:(Ljava/lang/String;)Lorg/apache/hadoop/hbase/TableName;
      10: astore_1
      11: getstatic     #19                 // Field FAMILY:[B
      14: iconst_3
      15: invokestatic  #18                 // Method org/apache/hadoop/hbase/HTestConst.makeNAscii:([BI)[[B
      18: astore_2
      19: getstatic     #17                 // Field QUALIFIER:[B
      22: bipush        20
      24: invokestatic  #18                 // Method org/apache/hadoop/hbase/HTestConst.makeNAscii:([BI)[[B
      27: astore_3
      28: getstatic     #7                  // Field TEST_UTIL:Lorg/apache/hadoop/hbase/HBaseTestingUtility;
      31: aload_1
      32: aload_2
      33: invokevirtual #105                // Method org/apache/hadoop/hbase/HBaseTestingUtility.createTable:(Lorg/apache/hadoop/hbase/TableName;[[B)Lorg/apache/hadoop/hbase/client/Table;
      36: astore        4
      38: iconst_1
      39: istore        8
      41: new           #42                 // class java/util/ArrayList
      44: dup
      45: invokespecial #43                 // Method java/util/ArrayList."<init>":()V
      48: astore        9
      50: new           #21                 // class org/apache/hadoop/hbase/client/Put
      53: dup
      54: getstatic     #22                 // Field ROW:[B
      57: invokespecial #23                 // Method org/apache/hadoop/hbase/client/Put."<init>":([B)V
      60: astore        6
      62: iconst_0
      63: istore        10
      65: iload         10
      67: bipush        10
      69: if_icmpge     128
      72: new           #24                 // class org/apache/hadoop/hbase/KeyValue
      75: dup
      76: getstatic     #22                 // Field ROW:[B
      79: aload_2
      80: iconst_0
      81: aaload
      82: aload_3
      83: iload         10
      85: aaload
      86: lconst_1
      87: getstatic     #25                 // Field VALUE:[B
      90: invokespecial #26                 // Method org/apache/hadoop/hbase/KeyValue."<init>":([B[B[BJ[B)V
      93: astore        11
      95: aload         6
      97: aload         11
      99: invokevirtual #27                 // Method org/apache/hadoop/hbase/client/Put.add:(Lorg/apache/hadoop/hbase/Cell;)Lorg/apache/hadoop/hbase/client/Put;
     102: pop
     103: iload         10
     105: iconst_2
     106: if_icmpge     112
     109: goto          122
     112: aload         9
     114: aload         11
     116: invokeinterface #46,  2           // InterfaceMethod java/util/List.add:(Ljava/lang/Object;)Z
     121: pop
     122: iinc          10, 1
     125: goto          65
     128: aload         4
     130: aload         6
     132: invokeinterface #28,  2           // InterfaceMethod org/apache/hadoop/hbase/client/Table.put:(Lorg/apache/hadoop/hbase/client/Put;)V
     137: new           #106                // class org/apache/hadoop/hbase/client/Get
     140: dup
     141: getstatic     #22                 // Field ROW:[B
     144: invokespecial #107                // Method org/apache/hadoop/hbase/client/Get."<init>":([B)V
     147: astore        5
     149: aload         5
     151: iconst_2
     152: invokevirtual #130                // Method org/apache/hadoop/hbase/client/Get.setRowOffsetPerColumnFamily:(I)Lorg/apache/hadoop/hbase/client/Get;
     155: pop
     156: aload         4
     158: aload         5
     160: invokeinterface #108,  2          // InterfaceMethod org/apache/hadoop/hbase/client/Table.get:(Lorg/apache/hadoop/hbase/client/Get;)Lorg/apache/hadoop/hbase/client/Result;
     165: astore        7
     167: aload         7
     169: aload         9
     171: iload         8
     173: ldc           #131                // String Testing basic setRowOffset
     175: invokestatic  #55                 // Method verifyResult:(Lorg/apache/hadoop/hbase/client/Result;Ljava/util/List;ZLjava/lang/String;)V
     178: new           #106                // class org/apache/hadoop/hbase/client/Get
     181: dup
     182: getstatic     #22                 // Field ROW:[B
     185: invokespecial #107                // Method org/apache/hadoop/hbase/client/Get."<init>":([B)V
     188: astore        5
     190: aload         5
     192: bipush        20
     194: invokevirtual #130                // Method org/apache/hadoop/hbase/client/Get.setRowOffsetPerColumnFamily:(I)Lorg/apache/hadoop/hbase/client/Get;
     197: pop
     198: aload         4
     200: aload         5
     202: invokeinterface #108,  2          // InterfaceMethod org/apache/hadoop/hbase/client/Table.get:(Lorg/apache/hadoop/hbase/client/Get;)Lorg/apache/hadoop/hbase/client/Result;
     207: astore        7
     209: new           #42                 // class java/util/ArrayList
     212: dup
     213: invokespecial #43                 // Method java/util/ArrayList."<init>":()V
     216: astore        9
     218: aload         7
     220: aload         9
     222: iload         8
     224: ldc           #132                // String Testing offset > #kvs
     226: invokestatic  #55                 // Method verifyResult:(Lorg/apache/hadoop/hbase/client/Result;Ljava/util/List;ZLjava/lang/String;)V
     229: new           #106                // class org/apache/hadoop/hbase/client/Get
     232: dup
     233: getstatic     #22                 // Field ROW:[B
     236: invokespecial #107                // Method org/apache/hadoop/hbase/client/Get."<init>":([B)V
     239: astore        5
     241: aload         5
     243: iconst_4
     244: invokevirtual #130                // Method org/apache/hadoop/hbase/client/Get.setRowOffsetPerColumnFamily:(I)Lorg/apache/hadoop/hbase/client/Get;
     247: pop
     248: aload         5
     250: iconst_5
     251: invokevirtual #110                // Method org/apache/hadoop/hbase/client/Get.setMaxResultsPerColumnFamily:(I)Lorg/apache/hadoop/hbase/client/Get;
     254: pop
     255: aload         4
     257: aload         5
     259: invokeinterface #108,  2          // InterfaceMethod org/apache/hadoop/hbase/client/Table.get:(Lorg/apache/hadoop/hbase/client/Get;)Lorg/apache/hadoop/hbase/client/Result;
     264: astore        7
     266: new           #42                 // class java/util/ArrayList
     269: dup
     270: invokespecial #43                 // Method java/util/ArrayList."<init>":()V
     273: astore        9
     275: iconst_4
     276: istore        10
     278: iload         10
     280: bipush        9
     282: if_icmpge     320
     285: aload         9
     287: new           #24                 // class org/apache/hadoop/hbase/KeyValue
     290: dup
     291: getstatic     #22                 // Field ROW:[B
     294: aload_2
     295: iconst_0
     296: aaload
     297: aload_3
     298: iload         10
     300: aaload
     301: lconst_1
     302: getstatic     #25                 // Field VALUE:[B
     305: invokespecial #26                 // Method org/apache/hadoop/hbase/KeyValue."<init>":([B[B[BJ[B)V
     308: invokeinterface #46,  2           // InterfaceMethod java/util/List.add:(Ljava/lang/Object;)Z
     313: pop
     314: iinc          10, 1
     317: goto          278
     320: aload         7
     322: aload         9
     324: iload         8
     326: ldc           #133                // String Testing offset + setMaxResultsPerCF
     328: invokestatic  #55                 // Method verifyResult:(Lorg/apache/hadoop/hbase/client/Result;Ljava/util/List;ZLjava/lang/String;)V
     331: new           #106                // class org/apache/hadoop/hbase/client/Get
     334: dup
     335: getstatic     #22                 // Field ROW:[B
     338: invokespecial #107                // Method org/apache/hadoop/hbase/client/Get."<init>":([B)V
     341: astore        5
     343: aload         5
     345: iconst_1
     346: invokevirtual #130                // Method org/apache/hadoop/hbase/client/Get.setRowOffsetPerColumnFamily:(I)Lorg/apache/hadoop/hbase/client/Get;
     349: pop
     350: aload         5
     352: new           #112                // class org/apache/hadoop/hbase/filter/ColumnRangeFilter
     355: dup
     356: aload_3
     357: iconst_2
     358: aaload
     359: iconst_1
     360: aload_3
     361: iconst_5
     362: aaload
     363: iconst_1
     364: invokespecial #113                // Method org/apache/hadoop/hbase/filter/ColumnRangeFilter."<init>":([BZ[BZ)V
     367: invokevirtual #114                // Method org/apache/hadoop/hbase/client/Get.setFilter:(Lorg/apache/hadoop/hbase/filter/Filter;)Lorg/apache/hadoop/hbase/client/Get;
     370: pop
     371: aload         4
     373: aload         5
     375: invokeinterface #108,  2          // InterfaceMethod org/apache/hadoop/hbase/client/Table.get:(Lorg/apache/hadoop/hbase/client/Get;)Lorg/apache/hadoop/hbase/client/Result;
     380: astore        7
     382: new           #42                 // class java/util/ArrayList
     385: dup
     386: invokespecial #43                 // Method java/util/ArrayList."<init>":()V
     389: astore        9
     391: aload         9
     393: new           #24                 // class org/apache/hadoop/hbase/KeyValue
     396: dup
     397: getstatic     #22                 // Field ROW:[B
     400: aload_2
     401: iconst_0
     402: aaload
     403: aload_3
     404: iconst_3
     405: aaload
     406: lconst_1
     407: getstatic     #25                 // Field VALUE:[B
     410: invokespecial #26                 // Method org/apache/hadoop/hbase/KeyValue."<init>":([B[B[BJ[B)V
     413: invokeinterface #46,  2           // InterfaceMethod java/util/List.add:(Ljava/lang/Object;)Z
     418: pop
     419: aload         9
     421: new           #24                 // class org/apache/hadoop/hbase/KeyValue
     424: dup
     425: getstatic     #22                 // Field ROW:[B
     428: aload_2
     429: iconst_0
     430: aaload
     431: aload_3
     432: iconst_4
     433: aaload
     434: lconst_1
     435: getstatic     #25                 // Field VALUE:[B
     438: invokespecial #26                 // Method org/apache/hadoop/hbase/KeyValue."<init>":([B[B[BJ[B)V
     441: invokeinterface #46,  2           // InterfaceMethod java/util/List.add:(Ljava/lang/Object;)Z
     446: pop
     447: aload         9
     449: new           #24                 // class org/apache/hadoop/hbase/KeyValue
     452: dup
     453: getstatic     #22                 // Field ROW:[B
     456: aload_2
     457: iconst_0
     458: aaload
     459: aload_3
     460: iconst_5
     461: aaload
     462: lconst_1
     463: getstatic     #25                 // Field VALUE:[B
     466: invokespecial #26                 // Method org/apache/hadoop/hbase/KeyValue."<init>":([B[B[BJ[B)V
     469: invokeinterface #46,  2           // InterfaceMethod java/util/List.add:(Ljava/lang/Object;)Z
     474: pop
     475: aload         7
     477: aload         9
     479: iload         8
     481: ldc           #134                // String Testing offset with CRF
     483: invokestatic  #55                 // Method verifyResult:(Lorg/apache/hadoop/hbase/client/Result;Ljava/util/List;ZLjava/lang/String;)V
     486: iconst_2
     487: istore        10
     489: iload         10
     491: ifle          569
     494: new           #21                 // class org/apache/hadoop/hbase/client/Put
     497: dup
     498: getstatic     #22                 // Field ROW:[B
     501: invokespecial #23                 // Method org/apache/hadoop/hbase/client/Put."<init>":([B)V
     504: astore        6
     506: iconst_0
     507: istore        11
     509: iload         11
     511: bipush        10
     513: if_icmpge     554
     516: new           #24                 // class org/apache/hadoop/hbase/KeyValue
     519: dup
     520: getstatic     #22                 // Field ROW:[B
     523: aload_2
     524: iload         10
     526: aaload
     527: aload_3
     528: iload         11
     530: aaload
     531: lconst_1
     532: getstatic     #25                 // Field VALUE:[B
     535: invokespecial #26                 // Method org/apache/hadoop/hbase/KeyValue."<init>":([B[B[BJ[B)V
     538: astore        12
     540: aload         6
     542: aload         12
     544: invokevirtual #27                 // Method org/apache/hadoop/hbase/client/Put.add:(Lorg/apache/hadoop/hbase/Cell;)Lorg/apache/hadoop/hbase/client/Put;
     547: pop
     548: iinc          11, 1
     551: goto          509
     554: aload         4
     556: aload         6
     558: invokeinterface #28,  2           // InterfaceMethod org/apache/hadoop/hbase/client/Table.put:(Lorg/apache/hadoop/hbase/client/Put;)V
     563: iinc          10, -1
     566: goto          489
     569: new           #106                // class org/apache/hadoop/hbase/client/Get
     572: dup
     573: getstatic     #22                 // Field ROW:[B
     576: invokespecial #107                // Method org/apache/hadoop/hbase/client/Get."<init>":([B)V
     579: astore        5
     581: aload         5
     583: iconst_4
     584: invokevirtual #130                // Method org/apache/hadoop/hbase/client/Get.setRowOffsetPerColumnFamily:(I)Lorg/apache/hadoop/hbase/client/Get;
     587: pop
     588: aload         5
     590: iconst_2
     591: invokevirtual #110                // Method org/apache/hadoop/hbase/client/Get.setMaxResultsPerColumnFamily:(I)Lorg/apache/hadoop/hbase/client/Get;
     594: pop
     595: aload         5
     597: aload_2
     598: iconst_1
     599: aaload
     600: invokevirtual #116                // Method org/apache/hadoop/hbase/client/Get.addFamily:([B)Lorg/apache/hadoop/hbase/client/Get;
     603: pop
     604: aload         5
     606: aload_2
     607: iconst_2
     608: aaload
     609: invokevirtual #116                // Method org/apache/hadoop/hbase/client/Get.addFamily:([B)Lorg/apache/hadoop/hbase/client/Get;
     612: pop
     613: aload         4
     615: aload         5
     617: invokeinterface #108,  2          // InterfaceMethod org/apache/hadoop/hbase/client/Table.get:(Lorg/apache/hadoop/hbase/client/Get;)Lorg/apache/hadoop/hbase/client/Result;
     622: astore        7
     624: new           #42                 // class java/util/ArrayList
     627: dup
     628: invokespecial #43                 // Method java/util/ArrayList."<init>":()V
     631: astore        9
     633: aload         9
     635: new           #24                 // class org/apache/hadoop/hbase/KeyValue
     638: dup
     639: getstatic     #22                 // Field ROW:[B
     642: aload_2
     643: iconst_1
     644: aaload
     645: aload_3
     646: iconst_4
     647: aaload
     648: lconst_1
     649: getstatic     #25                 // Field VALUE:[B
     652: invokespecial #26                 // Method org/apache/hadoop/hbase/KeyValue."<init>":([B[B[BJ[B)V
     655: invokeinterface #46,  2           // InterfaceMethod java/util/List.add:(Ljava/lang/Object;)Z
     660: pop
     661: aload         9
     663: new           #24                 // class org/apache/hadoop/hbase/KeyValue
     666: dup
     667: getstatic     #22                 // Field ROW:[B
     670: aload_2
     671: iconst_1
     672: aaload
     673: aload_3
     674: iconst_5
     675: aaload
     676: lconst_1
     677: getstatic     #25                 // Field VALUE:[B
     680: invokespecial #26                 // Method org/apache/hadoop/hbase/KeyValue."<init>":([B[B[BJ[B)V
     683: invokeinterface #46,  2           // InterfaceMethod java/util/List.add:(Ljava/lang/Object;)Z
     688: pop
     689: aload         9
     691: new           #24                 // class org/apache/hadoop/hbase/KeyValue
     694: dup
     695: getstatic     #22                 // Field ROW:[B
     698: aload_2
     699: iconst_2
     700: aaload
     701: aload_3
     702: iconst_4
     703: aaload
     704: lconst_1
     705: getstatic     #25                 // Field VALUE:[B
     708: invokespecial #26                 // Method org/apache/hadoop/hbase/KeyValue."<init>":([B[B[BJ[B)V
     711: invokeinterface #46,  2           // InterfaceMethod java/util/List.add:(Ljava/lang/Object;)Z
     716: pop
     717: aload         9
     719: new           #24                 // class org/apache/hadoop/hbase/KeyValue
     722: dup
     723: getstatic     #22                 // Field ROW:[B
     726: aload_2
     727: iconst_2
     728: aaload
     729: aload_3
     730: iconst_5
     731: aaload
     732: lconst_1
     733: getstatic     #25                 // Field VALUE:[B
     736: invokespecial #26                 // Method org/apache/hadoop/hbase/KeyValue."<init>":([B[B[BJ[B)V
     739: invokeinterface #46,  2           // InterfaceMethod java/util/List.add:(Ljava/lang/Object;)Z
     744: pop
     745: aload         7
     747: aload         9
     749: iload         8
     751: ldc           #135                // String Testing offset + multiple CFs + maxResults
     753: invokestatic  #55                 // Method verifyResult:(Lorg/apache/hadoop/hbase/client/Result;Ljava/util/List;ZLjava/lang/String;)V
     756: return

  public void testScanRawDeleteFamilyVersion() throws java.lang.Exception;
    Code:
       0: aload_0
       1: getfield      #6                  // Field name:Lorg/junit/rules/TestName;
       4: invokevirtual #15                 // Method org/junit/rules/TestName.getMethodName:()Ljava/lang/String;
       7: invokestatic  #16                 // Method org/apache/hadoop/hbase/TableName.valueOf:(Ljava/lang/String;)Lorg/apache/hadoop/hbase/TableName;
      10: astore_1
      11: getstatic     #7                  // Field TEST_UTIL:Lorg/apache/hadoop/hbase/HBaseTestingUtility;
      14: aload_1
      15: getstatic     #19                 // Field FAMILY:[B
      18: invokevirtual #20                 // Method org/apache/hadoop/hbase/HBaseTestingUtility.createTable:(Lorg/apache/hadoop/hbase/TableName;[B)Lorg/apache/hadoop/hbase/client/Table;
      21: pop
      22: new           #136                // class org/apache/hadoop/conf/Configuration
      25: dup
      26: getstatic     #7                  // Field TEST_UTIL:Lorg/apache/hadoop/hbase/HBaseTestingUtility;
      29: invokevirtual #8                  // Method org/apache/hadoop/hbase/HBaseTestingUtility.getConfiguration:()Lorg/apache/hadoop/conf/Configuration;
      32: invokespecial #137                // Method org/apache/hadoop/conf/Configuration."<init>":(Lorg/apache/hadoop/conf/Configuration;)V
      35: astore_2
      36: aload_2
      37: ldc           #138                // String hbase.client.rpc.codec
      39: ldc           #139                // String
      41: invokevirtual #140                // Method org/apache/hadoop/conf/Configuration.set:(Ljava/lang/String;Ljava/lang/String;)V
      44: aload_2
      45: ldc           #141                // String hbase.client.default.rpc.codec
      47: ldc           #139                // String
      49: invokevirtual #140                // Method org/apache/hadoop/conf/Configuration.set:(Ljava/lang/String;Ljava/lang/String;)V
      52: aload_2
      53: invokestatic  #142                // Method org/apache/hadoop/hbase/client/ConnectionFactory.createConnection:(Lorg/apache/hadoop/conf/Configuration;)Lorg/apache/hadoop/hbase/client/Connection;
      56: astore_3
      57: aconst_null
      58: astore        4
      60: aload_3
      61: aload_1
      62: invokeinterface #81,  2           // InterfaceMethod org/apache/hadoop/hbase/client/Connection.getTable:(Lorg/apache/hadoop/hbase/TableName;)Lorg/apache/hadoop/hbase/client/Table;
      67: astore        5
      69: aconst_null
      70: astore        6
      72: new           #31                 // class org/apache/hadoop/hbase/client/Delete
      75: dup
      76: getstatic     #22                 // Field ROW:[B
      79: invokespecial #32                 // Method org/apache/hadoop/hbase/client/Delete."<init>":([B)V
      82: astore        7
      84: aload         7
      86: getstatic     #19                 // Field FAMILY:[B
      89: lconst_0
      90: invokevirtual #143                // Method org/apache/hadoop/hbase/client/Delete.addFamilyVersion:([BJ)Lorg/apache/hadoop/hbase/client/Delete;
      93: pop
      94: aload         5
      96: aload         7
      98: invokeinterface #36,  2           // InterfaceMethod org/apache/hadoop/hbase/client/Table.delete:(Lorg/apache/hadoop/hbase/client/Delete;)V
     103: new           #37                 // class org/apache/hadoop/hbase/client/Scan
     106: dup
     107: getstatic     #22                 // Field ROW:[B
     110: invokespecial #144                // Method org/apache/hadoop/hbase/client/Scan."<init>":([B)V
     113: iconst_1
     114: invokevirtual #145                // Method org/apache/hadoop/hbase/client/Scan.setRaw:(Z)Lorg/apache/hadoop/hbase/client/Scan;
     117: astore        8
     119: aload         5
     121: aload         8
     123: invokeinterface #41,  2           // InterfaceMethod org/apache/hadoop/hbase/client/Table.getScanner:(Lorg/apache/hadoop/hbase/client/Scan;)Lorg/apache/hadoop/hbase/client/ResultScanner;
     128: astore        9
     130: iconst_0
     131: istore        10
     133: aload         9
     135: invokeinterface #53,  1           // InterfaceMethod org/apache/hadoop/hbase/client/ResultScanner.next:()Lorg/apache/hadoop/hbase/client/Result;
     140: ifnull        149
     143: iinc          10, 1
     146: goto          133
     149: lconst_1
     150: iload         10
     152: i2l
     153: invokestatic  #146                // Method org/junit/Assert.assertEquals:(JJ)V
     156: aload         5
     158: ifnull        251
     161: aload         6
     163: ifnull        188
     166: aload         5
     168: invokeinterface #147,  1          // InterfaceMethod org/apache/hadoop/hbase/client/Table.close:()V
     173: goto          251
     176: astore        7
     178: aload         6
     180: aload         7
     182: invokevirtual #149                // Method java/lang/Throwable.addSuppressed:(Ljava/lang/Throwable;)V
     185: goto          251
     188: aload         5
     190: invokeinterface #147,  1          // InterfaceMethod org/apache/hadoop/hbase/client/Table.close:()V
     195: goto          251
     198: astore        7
     200: aload         7
     202: astore        6
     204: aload         7
     206: athrow
     207: astore        11
     209: aload         5
     211: ifnull        248
     214: aload         6
     216: ifnull        241
     219: aload         5
     221: invokeinterface #147,  1          // InterfaceMethod org/apache/hadoop/hbase/client/Table.close:()V
     226: goto          248
     229: astore        12
     231: aload         6
     233: aload         12
     235: invokevirtual #149                // Method java/lang/Throwable.addSuppressed:(Ljava/lang/Throwable;)V
     238: goto          248
     241: aload         5
     243: invokeinterface #147,  1          // InterfaceMethod org/apache/hadoop/hbase/client/Table.close:()V
     248: aload         11
     250: athrow
     251: aload_3
     252: ifnull        340
     255: aload         4
     257: ifnull        281
     260: aload_3
     261: invokeinterface #150,  1          // InterfaceMethod org/apache/hadoop/hbase/client/Connection.close:()V
     266: goto          340
     269: astore        5
     271: aload         4
     273: aload         5
     275: invokevirtual #149                // Method java/lang/Throwable.addSuppressed:(Ljava/lang/Throwable;)V
     278: goto          340
     281: aload_3
     282: invokeinterface #150,  1          // InterfaceMethod org/apache/hadoop/hbase/client/Connection.close:()V
     287: goto          340
     290: astore        5
     292: aload         5
     294: astore        4
     296: aload         5
     298: athrow
     299: astore        13
     301: aload_3
     302: ifnull        337
     305: aload         4
     307: ifnull        331
     310: aload_3
     311: invokeinterface #150,  1          // InterfaceMethod org/apache/hadoop/hbase/client/Connection.close:()V
     316: goto          337
     319: astore        14
     321: aload         4
     323: aload         14
     325: invokevirtual #149                // Method java/lang/Throwable.addSuppressed:(Ljava/lang/Throwable;)V
     328: goto          337
     331: aload_3
     332: invokeinterface #150,  1          // InterfaceMethod org/apache/hadoop/hbase/client/Connection.close:()V
     337: aload         13
     339: athrow
     340: getstatic     #7                  // Field TEST_UTIL:Lorg/apache/hadoop/hbase/HBaseTestingUtility;
     343: aload_1
     344: invokevirtual #151                // Method org/apache/hadoop/hbase/HBaseTestingUtility.deleteTable:(Lorg/apache/hadoop/hbase/TableName;)V
     347: goto          362
     350: astore        15
     352: getstatic     #7                  // Field TEST_UTIL:Lorg/apache/hadoop/hbase/HBaseTestingUtility;
     355: aload_1
     356: invokevirtual #151                // Method org/apache/hadoop/hbase/HBaseTestingUtility.deleteTable:(Lorg/apache/hadoop/hbase/TableName;)V
     359: aload         15
     361: athrow
     362: return
    Exception table:
       from    to  target type
         166   173   176   Class java/lang/Throwable
          72   156   198   Class java/lang/Throwable
          72   156   207   any
         219   226   229   Class java/lang/Throwable
         198   209   207   any
         260   266   269   Class java/lang/Throwable
          60   251   290   Class java/lang/Throwable
          60   251   299   any
         310   316   319   Class java/lang/Throwable
         290   301   299   any
          52   340   350   any
         350   352   350   any

  public void testScanOnReopenedRegion() throws java.lang.Exception;
    Code:
       0: aload_0
       1: getfield      #6                  // Field name:Lorg/junit/rules/TestName;
       4: invokevirtual #15                 // Method org/junit/rules/TestName.getMethodName:()Ljava/lang/String;
       7: invokestatic  #16                 // Method org/apache/hadoop/hbase/TableName.valueOf:(Ljava/lang/String;)Lorg/apache/hadoop/hbase/TableName;
      10: astore_1
      11: getstatic     #17                 // Field QUALIFIER:[B
      14: iconst_2
      15: invokestatic  #18                 // Method org/apache/hadoop/hbase/HTestConst.makeNAscii:([BI)[[B
      18: astore_2
      19: getstatic     #7                  // Field TEST_UTIL:Lorg/apache/hadoop/hbase/HBaseTestingUtility;
      22: aload_1
      23: getstatic     #19                 // Field FAMILY:[B
      26: invokevirtual #20                 // Method org/apache/hadoop/hbase/HBaseTestingUtility.createTable:(Lorg/apache/hadoop/hbase/TableName;[B)Lorg/apache/hadoop/hbase/client/Table;
      29: astore_3
      30: iconst_0
      31: istore        8
      33: new           #21                 // class org/apache/hadoop/hbase/client/Put
      36: dup
      37: getstatic     #22                 // Field ROW:[B
      40: invokespecial #23                 // Method org/apache/hadoop/hbase/client/Put."<init>":([B)V
      43: astore        4
      45: iconst_0
      46: istore        10
      48: iload         10
      50: aload_2
      51: arraylength
      52: if_icmpge     94
      55: new           #24                 // class org/apache/hadoop/hbase/KeyValue
      58: dup
      59: getstatic     #22                 // Field ROW:[B
      62: getstatic     #19                 // Field FAMILY:[B
      65: aload_2
      66: iload         10
      68: aaload
      69: iload         10
      71: i2l
      72: getstatic     #25                 // Field VALUE:[B
      75: invokespecial #26                 // Method org/apache/hadoop/hbase/KeyValue."<init>":([B[B[BJ[B)V
      78: astore        11
      80: aload         4
      82: aload         11
      84: invokevirtual #27                 // Method org/apache/hadoop/hbase/client/Put.add:(Lorg/apache/hadoop/hbase/Cell;)Lorg/apache/hadoop/hbase/client/Put;
      87: pop
      88: iinc          10, 1
      91: goto          48
      94: aload_3
      95: aload         4
      97: invokeinterface #28,  2           // InterfaceMethod org/apache/hadoop/hbase/client/Table.put:(Lorg/apache/hadoop/hbase/client/Put;)V
     102: new           #37                 // class org/apache/hadoop/hbase/client/Scan
     105: dup
     106: invokespecial #38                 // Method org/apache/hadoop/hbase/client/Scan."<init>":()V
     109: getstatic     #22                 // Field ROW:[B
     112: invokevirtual #39                 // Method org/apache/hadoop/hbase/client/Scan.withStartRow:([B)Lorg/apache/hadoop/hbase/client/Scan;
     115: astore        5
     117: aload_3
     118: aload         5
     120: invokeinterface #41,  2           // InterfaceMethod org/apache/hadoop/hbase/client/Table.getScanner:(Lorg/apache/hadoop/hbase/client/Scan;)Lorg/apache/hadoop/hbase/client/ResultScanner;
     125: astore        7
     127: getstatic     #7                  // Field TEST_UTIL:Lorg/apache/hadoop/hbase/HBaseTestingUtility;
     130: invokevirtual #80                 // Method org/apache/hadoop/hbase/HBaseTestingUtility.getConnection:()Lorg/apache/hadoop/hbase/client/Connection;
     133: aload_1
     134: invokeinterface #152,  2          // InterfaceMethod org/apache/hadoop/hbase/client/Connection.getRegionLocator:(Lorg/apache/hadoop/hbase/TableName;)Lorg/apache/hadoop/hbase/client/RegionLocator;
     139: astore        11
     141: aconst_null
     142: astore        12
     144: aload         11
     146: getstatic     #22                 // Field ROW:[B
     149: invokeinterface #153,  2          // InterfaceMethod org/apache/hadoop/hbase/client/RegionLocator.getRegionLocation:([B)Lorg/apache/hadoop/hbase/HRegionLocation;
     154: astore        10
     156: aload         11
     158: ifnull        251
     161: aload         12
     163: ifnull        188
     166: aload         11
     168: invokeinterface #154,  1          // InterfaceMethod org/apache/hadoop/hbase/client/RegionLocator.close:()V
     173: goto          251
     176: astore        13
     178: aload         12
     180: aload         13
     182: invokevirtual #149                // Method java/lang/Throwable.addSuppressed:(Ljava/lang/Throwable;)V
     185: goto          251
     188: aload         11
     190: invokeinterface #154,  1          // InterfaceMethod org/apache/hadoop/hbase/client/RegionLocator.close:()V
     195: goto          251
     198: astore        13
     200: aload         13
     202: astore        12
     204: aload         13
     206: athrow
     207: astore        14
     209: aload         11
     211: ifnull        248
     214: aload         12
     216: ifnull        241
     219: aload         11
     221: invokeinterface #154,  1          // InterfaceMethod org/apache/hadoop/hbase/client/RegionLocator.close:()V
     226: goto          248
     229: astore        15
     231: aload         12
     233: aload         15
     235: invokevirtual #149                // Method java/lang/Throwable.addSuppressed:(Ljava/lang/Throwable;)V
     238: goto          248
     241: aload         11
     243: invokeinterface #154,  1          // InterfaceMethod org/apache/hadoop/hbase/client/RegionLocator.close:()V
     248: aload         14
     250: athrow
     251: aload         10
     253: invokevirtual #155                // Method org/apache/hadoop/hbase/HRegionLocation.getRegionInfo:()Lorg/apache/hadoop/hbase/HRegionInfo;
     256: astore        11
     258: getstatic     #7                  // Field TEST_UTIL:Lorg/apache/hadoop/hbase/HBaseTestingUtility;
     261: invokevirtual #156                // Method org/apache/hadoop/hbase/HBaseTestingUtility.getMiniHBaseCluster:()Lorg/apache/hadoop/hbase/MiniHBaseCluster;
     264: astore        12
     266: aload         11
     268: invokevirtual #157                // Method org/apache/hadoop/hbase/HRegionInfo.getRegionName:()[B
     271: astore        13
     273: aload         12
     275: aload         13
     277: invokevirtual #158                // Method org/apache/hadoop/hbase/MiniHBaseCluster.getServerWith:([B)I
     280: istore        14
     282: aload         12
     284: iload         14
     286: invokevirtual #159                // Method org/apache/hadoop/hbase/MiniHBaseCluster.getRegionServer:(I)Lorg/apache/hadoop/hbase/regionserver/HRegionServer;
     289: astore        15
     291: getstatic     #160                // Field LOG:Lorg/slf4j/Logger;
     294: new           #66                 // class java/lang/StringBuilder
     297: dup
     298: invokespecial #67                 // Method java/lang/StringBuilder."<init>":()V
     301: ldc           #161                // String Unassigning
     303: invokevirtual #69                 // Method java/lang/StringBuilder.append:(Ljava/lang/String;)Ljava/lang/StringBuilder;
     306: aload         11
     308: invokevirtual #162                // Method java/lang/StringBuilder.append:(Ljava/lang/Object;)Ljava/lang/StringBuilder;
     311: invokevirtual #73                 // Method java/lang/StringBuilder.toString:()Ljava/lang/String;
     314: invokeinterface #163,  2          // InterfaceMethod org/slf4j/Logger.info:(Ljava/lang/String;)V
     319: getstatic     #7                  // Field TEST_UTIL:Lorg/apache/hadoop/hbase/HBaseTestingUtility;
     322: invokevirtual #164                // Method org/apache/hadoop/hbase/HBaseTestingUtility.getAdmin:()Lorg/apache/hadoop/hbase/client/Admin;
     325: aload         11
     327: invokevirtual #157                // Method org/apache/hadoop/hbase/HRegionInfo.getRegionName:()[B
     330: iconst_1
     331: invokeinterface #165,  3          // InterfaceMethod org/apache/hadoop/hbase/client/Admin.unassign:([BZ)V
     336: invokestatic  #166                // Method org/apache/hadoop/hbase/util/EnvironmentEdgeManager.currentTime:()J
     339: lstore        16
     341: ldc2_w        #167                // long 10000l
     344: lstore        18
     346: iconst_0
     347: istore        20
     349: aload         15
     351: aload         13
     353: invokevirtual #169                // Method org/apache/hadoop/hbase/regionserver/HRegionServer.getOnlineRegion:([B)Lorg/apache/hadoop/hbase/regionserver/HRegion;
     356: ifnonnull     365
     359: iconst_1
     360: istore        20
     362: goto          390
     365: ldc           #170                // String Timed out in closing the testing region
     367: invokestatic  #166                // Method org/apache/hadoop/hbase/util/EnvironmentEdgeManager.currentTime:()J
     370: lload         16
     372: lload         18
     374: ladd
     375: lcmp
     376: ifge          383
     379: iconst_1
     380: goto          384
     383: iconst_0
     384: invokestatic  #74                 // Method org/junit/Assert.assertTrue:(Ljava/lang/String;Z)V
     387: goto          349
     390: iload         20
     392: invokestatic  #65                 // Method org/junit/Assert.assertTrue:(Z)V
     395: getstatic     #160                // Field LOG:Lorg/slf4j/Logger;
     398: new           #66                 // class java/lang/StringBuilder
     401: dup
     402: invokespecial #67                 // Method java/lang/StringBuilder."<init>":()V
     405: ldc           #171                // String Assigning
     407: invokevirtual #69                 // Method java/lang/StringBuilder.append:(Ljava/lang/String;)Ljava/lang/StringBuilder;
     410: aload         11
     412: invokevirtual #162                // Method java/lang/StringBuilder.append:(Ljava/lang/Object;)Ljava/lang/StringBuilder;
     415: invokevirtual #73                 // Method java/lang/StringBuilder.toString:()Ljava/lang/String;
     418: invokeinterface #163,  2          // InterfaceMethod org/slf4j/Logger.info:(Ljava/lang/String;)V
     423: getstatic     #7                  // Field TEST_UTIL:Lorg/apache/hadoop/hbase/HBaseTestingUtility;
     426: invokevirtual #164                // Method org/apache/hadoop/hbase/HBaseTestingUtility.getAdmin:()Lorg/apache/hadoop/hbase/client/Admin;
     429: aload         11
     431: invokevirtual #157                // Method org/apache/hadoop/hbase/HRegionInfo.getRegionName:()[B
     434: invokeinterface #172,  2          // InterfaceMethod org/apache/hadoop/hbase/client/Admin.assign:([B)V
     439: invokestatic  #166                // Method org/apache/hadoop/hbase/util/EnvironmentEdgeManager.currentTime:()J
     442: lstore        16
     444: aload         12
     446: aload         12
     448: aload         13
     450: invokevirtual #158                // Method org/apache/hadoop/hbase/MiniHBaseCluster.getServerWith:([B)I
     453: invokevirtual #159                // Method org/apache/hadoop/hbase/MiniHBaseCluster.getRegionServer:(I)Lorg/apache/hadoop/hbase/regionserver/HRegionServer;
     456: astore        15
     458: aload         15
     460: ifnull        479
     463: aload         15
     465: aload         13
     467: invokevirtual #169                // Method org/apache/hadoop/hbase/regionserver/HRegionServer.getOnlineRegion:([B)Lorg/apache/hadoop/hbase/regionserver/HRegion;
     470: ifnull        479
     473: iconst_0
     474: istore        20
     476: goto          504
     479: ldc           #173                // String Timed out in open the testing region
     481: invokestatic  #166                // Method org/apache/hadoop/hbase/util/EnvironmentEdgeManager.currentTime:()J
     484: lload         16
     486: lload         18
     488: ladd
     489: lcmp
     490: ifge          497
     493: iconst_1
     494: goto          498
     497: iconst_0
     498: invokestatic  #74                 // Method org/junit/Assert.assertTrue:(Ljava/lang/String;Z)V
     501: goto          444
     504: iload         20
     506: invokestatic  #174                // Method org/junit/Assert.assertFalse:(Z)V
     509: new           #42                 // class java/util/ArrayList
     512: dup
     513: invokespecial #43                 // Method java/util/ArrayList."<init>":()V
     516: astore        9
     518: aload         9
     520: new           #24                 // class org/apache/hadoop/hbase/KeyValue
     523: dup
     524: getstatic     #22                 // Field ROW:[B
     527: getstatic     #19                 // Field FAMILY:[B
     530: aload_2
     531: iconst_0
     532: aaload
     533: lconst_0
     534: getstatic     #25                 // Field VALUE:[B
     537: invokespecial #26                 // Method org/apache/hadoop/hbase/KeyValue."<init>":([B[B[BJ[B)V
     540: invokeinterface #46,  2           // InterfaceMethod java/util/List.add:(Ljava/lang/Object;)Z
     545: pop
     546: aload         9
     548: new           #24                 // class org/apache/hadoop/hbase/KeyValue
     551: dup
     552: getstatic     #22                 // Field ROW:[B
     555: getstatic     #19                 // Field FAMILY:[B
     558: aload_2
     559: iconst_1
     560: aaload
     561: lconst_1
     562: getstatic     #25                 // Field VALUE:[B
     565: invokespecial #26                 // Method org/apache/hadoop/hbase/KeyValue."<init>":([B[B[BJ[B)V
     568: invokeinterface #46,  2           // InterfaceMethod java/util/List.add:(Ljava/lang/Object;)Z
     573: pop
     574: aload         7
     576: invokeinterface #53,  1           // InterfaceMethod org/apache/hadoop/hbase/client/ResultScanner.next:()Lorg/apache/hadoop/hbase/client/Result;
     581: astore        6
     583: aload         6
     585: aload         9
     587: iload         8
     589: ldc           #175                // String Testing scan on re-opened region
     591: invokestatic  #55                 // Method verifyResult:(Lorg/apache/hadoop/hbase/client/Result;Ljava/util/List;ZLjava/lang/String;)V
     594: return
    Exception table:
       from    to  target type
         166   173   176   Class java/lang/Throwable
         144   156   198   Class java/lang/Throwable
         144   156   207   any
         219   226   229   Class java/lang/Throwable
         198   209   207   any

  public void testAsyncScannerWithSmallData() throws java.lang.Exception;
    Code:
       0: aload_0
       1: aload_0
       2: getfield      #6                  // Field name:Lorg/junit/rules/TestName;
       5: invokevirtual #15                 // Method org/junit/rules/TestName.getMethodName:()Ljava/lang/String;
       8: invokestatic  #16                 // Method org/apache/hadoop/hbase/TableName.valueOf:(Ljava/lang/String;)Lorg/apache/hadoop/hbase/TableName;
      11: iconst_2
      12: iconst_3
      13: bipush        10
      15: iconst_m1
      16: aconst_null
      17: invokespecial #176                // Method testAsyncScanner:(Lorg/apache/hadoop/hbase/TableName;IIIILjava/util/function/Consumer;)V
      20: return

  public void testAsyncScannerWithManyRows() throws java.lang.Exception;
    Code:
       0: aload_0
       1: aload_0
       2: getfield      #6                  // Field name:Lorg/junit/rules/TestName;
       5: invokevirtual #15                 // Method org/junit/rules/TestName.getMethodName:()Ljava/lang/String;
       8: invokestatic  #16                 // Method org/apache/hadoop/hbase/TableName.valueOf:(Ljava/lang/String;)Lorg/apache/hadoop/hbase/TableName;
      11: sipush        30000
      14: iconst_1
      15: iconst_1
      16: iconst_m1
      17: aconst_null
      18: invokespecial #176                // Method testAsyncScanner:(Lorg/apache/hadoop/hbase/TableName;IIIILjava/util/function/Consumer;)V
      21: return

  public void testAsyncScannerWithoutCaching() throws java.lang.Exception;
    Code:
       0: aload_0
       1: aload_0
       2: getfield      #6                  // Field name:Lorg/junit/rules/TestName;
       5: invokevirtual #15                 // Method org/junit/rules/TestName.getMethodName:()Ljava/lang/String;
       8: invokestatic  #16                 // Method org/apache/hadoop/hbase/TableName.valueOf:(Ljava/lang/String;)Lorg/apache/hadoop/hbase/TableName;
      11: iconst_5
      12: iconst_1
      13: iconst_1
      14: iconst_1
      15: invokedynamic #177,  0            // InvokeDynamic #0:accept:()Ljava/util/function/Consumer;
      20: invokespecial #176                // Method testAsyncScanner:(Lorg/apache/hadoop/hbase/TableName;IIIILjava/util/function/Consumer;)V
      23: return

  static void verifyResult(org.apache.hadoop.hbase.client.Result, java.util.List<org.apache.hadoop.hbase.Cell>, boolean, java.lang.String);
    Code:
       0: getstatic     #160                // Field LOG:Lorg/slf4j/Logger;
       3: aload_3
       4: invokeinterface #163,  2          // InterfaceMethod org/slf4j/Logger.info:(Ljava/lang/String;)V
       9: getstatic     #160                // Field LOG:Lorg/slf4j/Logger;
      12: new           #66                 // class java/lang/StringBuilder
      15: dup
      16: invokespecial #67                 // Method java/lang/StringBuilder."<init>":()V
      19: ldc           #204                // String Expected count:
      21: invokevirtual #69                 // Method java/lang/StringBuilder.append:(Ljava/lang/String;)Ljava/lang/StringBuilder;
      24: aload_1
      25: invokeinterface #186,  1          // InterfaceMethod java/util/List.size:()I
      30: invokevirtual #71                 // Method java/lang/StringBuilder.append:(I)Ljava/lang/StringBuilder;
      33: invokevirtual #73                 // Method java/lang/StringBuilder.toString:()Ljava/lang/String;
      36: invokeinterface #163,  2          // InterfaceMethod org/slf4j/Logger.info:(Ljava/lang/String;)V
      41: getstatic     #160                // Field LOG:Lorg/slf4j/Logger;
      44: new           #66                 // class java/lang/StringBuilder
      47: dup
      48: invokespecial #67                 // Method java/lang/StringBuilder."<init>":()V
      51: ldc           #205                // String Actual count:
      53: invokevirtual #69                 // Method java/lang/StringBuilder.append:(Ljava/lang/String;)Ljava/lang/StringBuilder;
      56: aload_0
      57: invokevirtual #206                // Method org/apache/hadoop/hbase/client/Result.size:()I
      60: invokevirtual #71                 // Method java/lang/StringBuilder.append:(I)Ljava/lang/StringBuilder;
      63: invokevirtual #73                 // Method java/lang/StringBuilder.toString:()Ljava/lang/String;
      66: invokeinterface #163,  2          // InterfaceMethod org/slf4j/Logger.info:(Ljava/lang/String;)V
      71: aload_1
      72: invokeinterface #188,  1          // InterfaceMethod java/util/List.isEmpty:()Z
      77: ifeq          81
      80: return
      81: iconst_0
      82: istore        4
      84: aload_0
      85: invokevirtual #99                 // Method org/apache/hadoop/hbase/client/Result.rawCells:()[Lorg/apache/hadoop/hbase/Cell;
      88: astore        5
      90: aload         5
      92: arraylength
      93: istore        6
      95: iconst_0
      96: istore        7
      98: iload         7
     100: iload         6
     102: if_icmpge     226
     105: aload         5
     107: iload         7
     109: aaload
     110: astore        8
     112: iload         4
     114: aload_1
     115: invokeinterface #186,  1          // InterfaceMethod java/util/List.size:()I
     120: if_icmplt     126
     123: goto          226
     126: aload_1
     127: iload         4
     129: iinc          4, 1
     132: invokeinterface #207,  2          // InterfaceMethod java/util/List.get:(I)Ljava/lang/Object;
     137: checkcast     #127                // class org/apache/hadoop/hbase/Cell
     140: astore        9
     142: iload_2
     143: ifeq          208
     146: getstatic     #160                // Field LOG:Lorg/slf4j/Logger;
     149: new           #66                 // class java/lang/StringBuilder
     152: dup
     153: invokespecial #67                 // Method java/lang/StringBuilder."<init>":()V
     156: ldc           #208                // String get kv is:
     158: invokevirtual #69                 // Method java/lang/StringBuilder.append:(Ljava/lang/String;)Ljava/lang/StringBuilder;
     161: aload         8
     163: invokevirtual #209                // Method java/lang/Object.toString:()Ljava/lang/String;
     166: invokevirtual #69                 // Method java/lang/StringBuilder.append:(Ljava/lang/String;)Ljava/lang/StringBuilder;
     169: invokevirtual #73                 // Method java/lang/StringBuilder.toString:()Ljava/lang/String;
     172: invokeinterface #163,  2          // InterfaceMethod org/slf4j/Logger.info:(Ljava/lang/String;)V
     177: getstatic     #160                // Field LOG:Lorg/slf4j/Logger;
     180: new           #66                 // class java/lang/StringBuilder
     183: dup
     184: invokespecial #67                 // Method java/lang/StringBuilder."<init>":()V
     187: ldc           #210                // String exp kv is:
     189: invokevirtual #69                 // Method java/lang/StringBuilder.append:(Ljava/lang/String;)Ljava/lang/StringBuilder;
     192: aload         9
     194: invokevirtual #209                // Method java/lang/Object.toString:()Ljava/lang/String;
     197: invokevirtual #69                 // Method java/lang/StringBuilder.append:(Ljava/lang/String;)Ljava/lang/StringBuilder;
     200: invokevirtual #73                 // Method java/lang/StringBuilder.toString:()Ljava/lang/String;
     203: invokeinterface #163,  2          // InterfaceMethod org/slf4j/Logger.info:(Ljava/lang/String;)V
     208: ldc           #211                // String Not equal
     210: aload         9
     212: aload         8
     214: invokevirtual #212                // Method java/lang/Object.equals:(Ljava/lang/Object;)Z
     217: invokestatic  #74                 // Method org/junit/Assert.assertTrue:(Ljava/lang/String;Z)V
     220: iinc          7, 1
     223: goto          98
     226: aload_1
     227: invokeinterface #186,  1          // InterfaceMethod java/util/List.size:()I
     232: i2l
     233: aload_0
     234: invokevirtual #206                // Method org/apache/hadoop/hbase/client/Result.size:()I
     237: i2l
     238: invokestatic  #146                // Method org/junit/Assert.assertEquals:(JJ)V
     241: return

  public void testReadExpiredDataForRawScan() throws java.io.IOException;
    Code:
       0: aload_0
       1: getfield      #6                  // Field name:Lorg/junit/rules/TestName;
       4: invokevirtual #15                 // Method org/junit/rules/TestName.getMethodName:()Ljava/lang/String;
       7: invokestatic  #16                 // Method org/apache/hadoop/hbase/TableName.valueOf:(Ljava/lang/String;)Lorg/apache/hadoop/hbase/TableName;
      10: astore_1
      11: invokestatic  #213                // Method java/lang/System.currentTimeMillis:()J
      14: ldc2_w        #167                // long 10000l
      17: lsub
      18: lstore_2
      19: ldc           #214                // String expired
      21: invokestatic  #182                // Method org/apache/hadoop/hbase/util/Bytes.toBytes:(Ljava/lang/String;)[B
      24: astore        4
      26: getstatic     #7                  // Field TEST_UTIL:Lorg/apache/hadoop/hbase/HBaseTestingUtility;
      29: aload_1
      30: getstatic     #19                 // Field FAMILY:[B
      33: invokevirtual #20                 // Method org/apache/hadoop/hbase/HBaseTestingUtility.createTable:(Lorg/apache/hadoop/hbase/TableName;[B)Lorg/apache/hadoop/hbase/client/Table;
      36: astore        5
      38: aconst_null
      39: astore        6
      41: aload         5
      43: new           #21                 // class org/apache/hadoop/hbase/client/Put
      46: dup
      47: getstatic     #22                 // Field ROW:[B
      50: invokespecial #23                 // Method org/apache/hadoop/hbase/client/Put."<init>":([B)V
      53: getstatic     #19                 // Field FAMILY:[B
      56: getstatic     #17                 // Field QUALIFIER:[B
      59: lload_2
      60: aload         4
      62: invokevirtual #215                // Method org/apache/hadoop/hbase/client/Put.addColumn:([B[BJ[B)Lorg/apache/hadoop/hbase/client/Put;
      65: invokeinterface #28,  2           // InterfaceMethod org/apache/hadoop/hbase/client/Table.put:(Lorg/apache/hadoop/hbase/client/Put;)V
      70: aload         4
      72: aload         5
      74: new           #106                // class org/apache/hadoop/hbase/client/Get
      77: dup
      78: getstatic     #22                 // Field ROW:[B
      81: invokespecial #107                // Method org/apache/hadoop/hbase/client/Get."<init>":([B)V
      84: invokeinterface #108,  2          // InterfaceMethod org/apache/hadoop/hbase/client/Table.get:(Lorg/apache/hadoop/hbase/client/Get;)Lorg/apache/hadoop/hbase/client/Result;
      89: getstatic     #19                 // Field FAMILY:[B
      92: getstatic     #17                 // Field QUALIFIER:[B
      95: invokevirtual #216                // Method org/apache/hadoop/hbase/client/Result.getValue:([B[B)[B
      98: invokestatic  #217                // Method org/junit/Assert.assertArrayEquals:([B[B)V
     101: getstatic     #7                  // Field TEST_UTIL:Lorg/apache/hadoop/hbase/HBaseTestingUtility;
     104: invokevirtual #164                // Method org/apache/hadoop/hbase/HBaseTestingUtility.getAdmin:()Lorg/apache/hadoop/hbase/client/Admin;
     107: aload_1
     108: new           #218                // class org/apache/hadoop/hbase/HColumnDescriptor
     111: dup
     112: getstatic     #19                 // Field FAMILY:[B
     115: invokespecial #219                // Method org/apache/hadoop/hbase/HColumnDescriptor."<init>":([B)V
     118: iconst_5
     119: invokevirtual #220                // Method org/apache/hadoop/hbase/HColumnDescriptor.setTimeToLive:(I)Lorg/apache/hadoop/hbase/HColumnDescriptor;
     122: invokeinterface #221,  3          // InterfaceMethod org/apache/hadoop/hbase/client/Admin.modifyColumnFamily:(Lorg/apache/hadoop/hbase/TableName;Lorg/apache/hadoop/hbase/client/ColumnFamilyDescriptor;)V
     127: aload         5
     129: getstatic     #19                 // Field FAMILY:[B
     132: invokeinterface #222,  2          // InterfaceMethod org/apache/hadoop/hbase/client/Table.getScanner:([B)Lorg/apache/hadoop/hbase/client/ResultScanner;
     137: astore        7
     139: aconst_null
     140: astore        8
     142: aload         7
     144: invokeinterface #53,  1           // InterfaceMethod org/apache/hadoop/hbase/client/ResultScanner.next:()Lorg/apache/hadoop/hbase/client/Result;
     149: invokestatic  #223                // Method org/junit/Assert.assertNull:(Ljava/lang/Object;)V
     152: aload         7
     154: ifnull        247
     157: aload         8
     159: ifnull        184
     162: aload         7
     164: invokeinterface #104,  1          // InterfaceMethod org/apache/hadoop/hbase/client/ResultScanner.close:()V
     169: goto          247
     172: astore        9
     174: aload         8
     176: aload         9
     178: invokevirtual #149                // Method java/lang/Throwable.addSuppressed:(Ljava/lang/Throwable;)V
     181: goto          247
     184: aload         7
     186: invokeinterface #104,  1          // InterfaceMethod org/apache/hadoop/hbase/client/ResultScanner.close:()V
     191: goto          247
     194: astore        9
     196: aload         9
     198: astore        8
     200: aload         9
     202: athrow
     203: astore        10
     205: aload         7
     207: ifnull        244
     210: aload         8
     212: ifnull        237
     215: aload         7
     217: invokeinterface #104,  1          // InterfaceMethod org/apache/hadoop/hbase/client/ResultScanner.close:()V
     222: goto          244
     225: astore        11
     227: aload         8
     229: aload         11
     231: invokevirtual #149                // Method java/lang/Throwable.addSuppressed:(Ljava/lang/Throwable;)V
     234: goto          244
     237: aload         7
     239: invokeinterface #104,  1          // InterfaceMethod org/apache/hadoop/hbase/client/ResultScanner.close:()V
     244: aload         10
     246: athrow
     247: aload         5
     249: new           #37                 // class org/apache/hadoop/hbase/client/Scan
     252: dup
     253: invokespecial #38                 // Method org/apache/hadoop/hbase/client/Scan."<init>":()V
     256: iconst_1
     257: invokevirtual #145                // Method org/apache/hadoop/hbase/client/Scan.setRaw:(Z)Lorg/apache/hadoop/hbase/client/Scan;
     260: invokeinterface #41,  2           // InterfaceMethod org/apache/hadoop/hbase/client/Table.getScanner:(Lorg/apache/hadoop/hbase/client/Scan;)Lorg/apache/hadoop/hbase/client/ResultScanner;
     265: astore        7
     267: aconst_null
     268: astore        8
     270: aload         4
     272: aload         7
     274: invokeinterface #53,  1           // InterfaceMethod org/apache/hadoop/hbase/client/ResultScanner.next:()Lorg/apache/hadoop/hbase/client/Result;
     279: getstatic     #19                 // Field FAMILY:[B
     282: getstatic     #17                 // Field QUALIFIER:[B
     285: invokevirtual #216                // Method org/apache/hadoop/hbase/client/Result.getValue:([B[B)[B
     288: invokestatic  #217                // Method org/junit/Assert.assertArrayEquals:([B[B)V
     291: aload         7
     293: invokeinterface #53,  1           // InterfaceMethod org/apache/hadoop/hbase/client/ResultScanner.next:()Lorg/apache/hadoop/hbase/client/Result;
     298: invokestatic  #223                // Method org/junit/Assert.assertNull:(Ljava/lang/Object;)V
     301: aload         7
     303: ifnull        396
     306: aload         8
     308: ifnull        333
     311: aload         7
     313: invokeinterface #104,  1          // InterfaceMethod org/apache/hadoop/hbase/client/ResultScanner.close:()V
     318: goto          396
     321: astore        9
     323: aload         8
     325: aload         9
     327: invokevirtual #149                // Method java/lang/Throwable.addSuppressed:(Ljava/lang/Throwable;)V
     330: goto          396
     333: aload         7
     335: invokeinterface #104,  1          // InterfaceMethod org/apache/hadoop/hbase/client/ResultScanner.close:()V
     340: goto          396
     343: astore        9
     345: aload         9
     347: astore        8
     349: aload         9
     351: athrow
     352: astore        12
     354: aload         7
     356: ifnull        393
     359: aload         8
     361: ifnull        386
     364: aload         7
     366: invokeinterface #104,  1          // InterfaceMethod org/apache/hadoop/hbase/client/ResultScanner.close:()V
     371: goto          393
     374: astore        13
     376: aload         8
     378: aload         13
     380: invokevirtual #149                // Method java/lang/Throwable.addSuppressed:(Ljava/lang/Throwable;)V
     383: goto          393
     386: aload         7
     388: invokeinterface #104,  1          // InterfaceMethod org/apache/hadoop/hbase/client/ResultScanner.close:()V
     393: aload         12
     395: athrow
     396: aload         5
     398: ifnull        491
     401: aload         6
     403: ifnull        428
     406: aload         5
     408: invokeinterface #147,  1          // InterfaceMethod org/apache/hadoop/hbase/client/Table.close:()V
     413: goto          491
     416: astore        7
     418: aload         6
     420: aload         7
     422: invokevirtual #149                // Method java/lang/Throwable.addSuppressed:(Ljava/lang/Throwable;)V
     425: goto          491
     428: aload         5
     430: invokeinterface #147,  1          // InterfaceMethod org/apache/hadoop/hbase/client/Table.close:()V
     435: goto          491
     438: astore        7
     440: aload         7
     442: astore        6
     444: aload         7
     446: athrow
     447: astore        14
     449: aload         5
     451: ifnull        488
     454: aload         6
     456: ifnull        481
     459: aload         5
     461: invokeinterface #147,  1          // InterfaceMethod org/apache/hadoop/hbase/client/Table.close:()V
     466: goto          488
     469: astore        15
     471: aload         6
     473: aload         15
     475: invokevirtual #149                // Method java/lang/Throwable.addSuppressed:(Ljava/lang/Throwable;)V
     478: goto          488
     481: aload         5
     483: invokeinterface #147,  1          // InterfaceMethod org/apache/hadoop/hbase/client/Table.close:()V
     488: aload         14
     490: athrow
     491: return
    Exception table:
       from    to  target type
         162   169   172   Class java/lang/Throwable
         142   152   194   Class java/lang/Throwable
         142   152   203   any
         215   222   225   Class java/lang/Throwable
         194   205   203   any
         311   318   321   Class java/lang/Throwable
         270   301   343   Class java/lang/Throwable
         270   301   352   any
         364   371   374   Class java/lang/Throwable
         343   354   352   any
         406   413   416   Class java/lang/Throwable
          41   396   438   Class java/lang/Throwable
          41   396   447   any
         459   466   469   Class java/lang/Throwable
         438   449   447   any

  public void testScanWithColumnsAndFilterAndVersion() throws java.io.IOException;
    Code:
       0: aload_0
       1: getfield      #6                  // Field name:Lorg/junit/rules/TestName;
       4: invokevirtual #15                 // Method org/junit/rules/TestName.getMethodName:()Ljava/lang/String;
       7: invokestatic  #16                 // Method org/apache/hadoop/hbase/TableName.valueOf:(Ljava/lang/String;)Lorg/apache/hadoop/hbase/TableName;
      10: astore_1
      11: getstatic     #7                  // Field TEST_UTIL:Lorg/apache/hadoop/hbase/HBaseTestingUtility;
      14: aload_1
      15: getstatic     #19                 // Field FAMILY:[B
      18: iconst_4
      19: invokevirtual #224                // Method org/apache/hadoop/hbase/HBaseTestingUtility.createTable:(Lorg/apache/hadoop/hbase/TableName;[BI)Lorg/apache/hadoop/hbase/client/Table;
      22: astore_2
      23: aconst_null
      24: astore_3
      25: iconst_0
      26: istore        4
      28: iload         4
      30: iconst_4
      31: if_icmpge     75
      34: new           #21                 // class org/apache/hadoop/hbase/client/Put
      37: dup
      38: getstatic     #22                 // Field ROW:[B
      41: invokespecial #23                 // Method org/apache/hadoop/hbase/client/Put."<init>":([B)V
      44: astore        5
      46: aload         5
      48: getstatic     #19                 // Field FAMILY:[B
      51: getstatic     #17                 // Field QUALIFIER:[B
      54: getstatic     #25                 // Field VALUE:[B
      57: invokevirtual #225                // Method org/apache/hadoop/hbase/client/Put.addColumn:([B[B[B)Lorg/apache/hadoop/hbase/client/Put;
      60: pop
      61: aload_2
      62: aload         5
      64: invokeinterface #28,  2           // InterfaceMethod org/apache/hadoop/hbase/client/Table.put:(Lorg/apache/hadoop/hbase/client/Put;)V
      69: iinc          4, 1
      72: goto          28
      75: new           #37                 // class org/apache/hadoop/hbase/client/Scan
      78: dup
      79: invokespecial #38                 // Method org/apache/hadoop/hbase/client/Scan."<init>":()V
      82: astore        4
      84: aload         4
      86: getstatic     #19                 // Field FAMILY:[B
      89: getstatic     #17                 // Field QUALIFIER:[B
      92: invokevirtual #226                // Method org/apache/hadoop/hbase/client/Scan.addColumn:([B[B)Lorg/apache/hadoop/hbase/client/Scan;
      95: pop
      96: aload         4
      98: new           #227                // class org/apache/hadoop/hbase/filter/QualifierFilter
     101: dup
     102: getstatic     #228                // Field org/apache/hadoop/hbase/CompareOperator.EQUAL:Lorg/apache/hadoop/hbase/CompareOperator;
     105: new           #229                // class org/apache/hadoop/hbase/filter/BinaryComparator
     108: dup
     109: getstatic     #17                 // Field QUALIFIER:[B
     112: invokespecial #230                // Method org/apache/hadoop/hbase/filter/BinaryComparator."<init>":([B)V
     115: invokespecial #231                // Method org/apache/hadoop/hbase/filter/QualifierFilter."<init>":(Lorg/apache/hadoop/hbase/CompareOperator;Lorg/apache/hadoop/hbase/filter/ByteArrayComparable;)V
     118: invokevirtual #232                // Method org/apache/hadoop/hbase/client/Scan.setFilter:(Lorg/apache/hadoop/hbase/filter/Filter;)Lorg/apache/hadoop/hbase/client/Scan;
     121: pop
     122: aload         4
     124: iconst_3
     125: invokevirtual #233                // Method org/apache/hadoop/hbase/client/Scan.readVersions:(I)Lorg/apache/hadoop/hbase/client/Scan;
     128: pop
     129: aload_2
     130: aload         4
     132: invokeinterface #41,  2           // InterfaceMethod org/apache/hadoop/hbase/client/Table.getScanner:(Lorg/apache/hadoop/hbase/client/Scan;)Lorg/apache/hadoop/hbase/client/ResultScanner;
     137: astore        5
     139: aconst_null
     140: astore        6
     142: aload         5
     144: invokeinterface #53,  1           // InterfaceMethod org/apache/hadoop/hbase/client/ResultScanner.next:()Lorg/apache/hadoop/hbase/client/Result;
     149: astore        7
     151: ldc2_w        #33                 // long 3l
     154: aload         7
     156: invokevirtual #206                // Method org/apache/hadoop/hbase/client/Result.size:()I
     159: i2l
     160: invokestatic  #146                // Method org/junit/Assert.assertEquals:(JJ)V
     163: aload         5
     165: ifnull        258
     168: aload         6
     170: ifnull        195
     173: aload         5
     175: invokeinterface #104,  1          // InterfaceMethod org/apache/hadoop/hbase/client/ResultScanner.close:()V
     180: goto          258
     183: astore        7
     185: aload         6
     187: aload         7
     189: invokevirtual #149                // Method java/lang/Throwable.addSuppressed:(Ljava/lang/Throwable;)V
     192: goto          258
     195: aload         5
     197: invokeinterface #104,  1          // InterfaceMethod org/apache/hadoop/hbase/client/ResultScanner.close:()V
     202: goto          258
     205: astore        7
     207: aload         7
     209: astore        6
     211: aload         7
     213: athrow
     214: astore        8
     216: aload         5
     218: ifnull        255
     221: aload         6
     223: ifnull        248
     226: aload         5
     228: invokeinterface #104,  1          // InterfaceMethod org/apache/hadoop/hbase/client/ResultScanner.close:()V
     233: goto          255
     236: astore        9
     238: aload         6
     240: aload         9
     242: invokevirtual #149                // Method java/lang/Throwable.addSuppressed:(Ljava/lang/Throwable;)V
     245: goto          255
     248: aload         5
     250: invokeinterface #104,  1          // InterfaceMethod org/apache/hadoop/hbase/client/ResultScanner.close:()V
     255: aload         8
     257: athrow
     258: aload_2
     259: ifnull        342
     262: aload_3
     263: ifnull        286
     266: aload_2
     267: invokeinterface #147,  1          // InterfaceMethod org/apache/hadoop/hbase/client/Table.close:()V
     272: goto          342
     275: astore        4
     277: aload_3
     278: aload         4
     280: invokevirtual #149                // Method java/lang/Throwable.addSuppressed:(Ljava/lang/Throwable;)V
     283: goto          342
     286: aload_2
     287: invokeinterface #147,  1          // InterfaceMethod org/apache/hadoop/hbase/client/Table.close:()V
     292: goto          342
     295: astore        4
     297: aload         4
     299: astore_3
     300: aload         4
     302: athrow
     303: astore        10
     305: aload_2
     306: ifnull        339
     309: aload_3
     310: ifnull        333
     313: aload_2
     314: invokeinterface #147,  1          // InterfaceMethod org/apache/hadoop/hbase/client/Table.close:()V
     319: goto          339
     322: astore        11
     324: aload_3
     325: aload         11
     327: invokevirtual #149                // Method java/lang/Throwable.addSuppressed:(Ljava/lang/Throwable;)V
     330: goto          339
     333: aload_2
     334: invokeinterface #147,  1          // InterfaceMethod org/apache/hadoop/hbase/client/Table.close:()V
     339: aload         10
     341: athrow
     342: return
    Exception table:
       from    to  target type
         173   180   183   Class java/lang/Throwable
         142   163   205   Class java/lang/Throwable
         142   163   214   any
         226   233   236   Class java/lang/Throwable
         205   216   214   any
         266   272   275   Class java/lang/Throwable
          25   258   295   Class java/lang/Throwable
          25   258   303   any
         313   319   322   Class java/lang/Throwable
         295   305   303   any

  public void testScanWithSameStartRowStopRow() throws java.io.IOException;
    Code:
       0: aload_0
       1: getfield      #6                  // Field name:Lorg/junit/rules/TestName;
       4: invokevirtual #15                 // Method org/junit/rules/TestName.getMethodName:()Ljava/lang/String;
       7: invokestatic  #16                 // Method org/apache/hadoop/hbase/TableName.valueOf:(Ljava/lang/String;)Lorg/apache/hadoop/hbase/TableName;
      10: astore_1
      11: getstatic     #7                  // Field TEST_UTIL:Lorg/apache/hadoop/hbase/HBaseTestingUtility;
      14: aload_1
      15: getstatic     #19                 // Field FAMILY:[B
      18: invokevirtual #20                 // Method org/apache/hadoop/hbase/HBaseTestingUtility.createTable:(Lorg/apache/hadoop/hbase/TableName;[B)Lorg/apache/hadoop/hbase/client/Table;
      21: astore_2
      22: aconst_null
      23: astore_3
      24: aload_2
      25: new           #21                 // class org/apache/hadoop/hbase/client/Put
      28: dup
      29: getstatic     #22                 // Field ROW:[B
      32: invokespecial #23                 // Method org/apache/hadoop/hbase/client/Put."<init>":([B)V
      35: getstatic     #19                 // Field FAMILY:[B
      38: getstatic     #17                 // Field QUALIFIER:[B
      41: getstatic     #25                 // Field VALUE:[B
      44: invokevirtual #225                // Method org/apache/hadoop/hbase/client/Put.addColumn:([B[B[B)Lorg/apache/hadoop/hbase/client/Put;
      47: invokeinterface #28,  2           // InterfaceMethod org/apache/hadoop/hbase/client/Table.put:(Lorg/apache/hadoop/hbase/client/Put;)V
      52: new           #37                 // class org/apache/hadoop/hbase/client/Scan
      55: dup
      56: invokespecial #38                 // Method org/apache/hadoop/hbase/client/Scan."<init>":()V
      59: getstatic     #22                 // Field ROW:[B
      62: invokevirtual #39                 // Method org/apache/hadoop/hbase/client/Scan.withStartRow:([B)Lorg/apache/hadoop/hbase/client/Scan;
      65: getstatic     #22                 // Field ROW:[B
      68: invokevirtual #234                // Method org/apache/hadoop/hbase/client/Scan.withStopRow:([B)Lorg/apache/hadoop/hbase/client/Scan;
      71: astore        4
      73: aload_2
      74: aload         4
      76: invokeinterface #41,  2           // InterfaceMethod org/apache/hadoop/hbase/client/Table.getScanner:(Lorg/apache/hadoop/hbase/client/Scan;)Lorg/apache/hadoop/hbase/client/ResultScanner;
      81: astore        5
      83: aconst_null
      84: astore        6
      86: aload         5
      88: invokeinterface #53,  1           // InterfaceMethod org/apache/hadoop/hbase/client/ResultScanner.next:()Lorg/apache/hadoop/hbase/client/Result;
      93: invokestatic  #223                // Method org/junit/Assert.assertNull:(Ljava/lang/Object;)V
      96: aload         5
      98: ifnull        191
     101: aload         6
     103: ifnull        128
     106: aload         5
     108: invokeinterface #104,  1          // InterfaceMethod org/apache/hadoop/hbase/client/ResultScanner.close:()V
     113: goto          191
     116: astore        7
     118: aload         6
     120: aload         7
     122: invokevirtual #149                // Method java/lang/Throwable.addSuppressed:(Ljava/lang/Throwable;)V
     125: goto          191
     128: aload         5
     130: invokeinterface #104,  1          // InterfaceMethod org/apache/hadoop/hbase/client/ResultScanner.close:()V
     135: goto          191
     138: astore        7
     140: aload         7
     142: astore        6
     144: aload         7
     146: athrow
     147: astore        8
     149: aload         5
     151: ifnull        188
     154: aload         6
     156: ifnull        181
     159: aload         5
     161: invokeinterface #104,  1          // InterfaceMethod org/apache/hadoop/hbase/client/ResultScanner.close:()V
     166: goto          188
     169: astore        9
     171: aload         6
     173: aload         9
     175: invokevirtual #149                // Method java/lang/Throwable.addSuppressed:(Ljava/lang/Throwable;)V
     178: goto          188
     181: aload         5
     183: invokeinterface #104,  1          // InterfaceMethod org/apache/hadoop/hbase/client/ResultScanner.close:()V
     188: aload         8
     190: athrow
     191: new           #37                 // class org/apache/hadoop/hbase/client/Scan
     194: dup
     195: invokespecial #38                 // Method org/apache/hadoop/hbase/client/Scan."<init>":()V
     198: getstatic     #22                 // Field ROW:[B
     201: iconst_1
     202: invokevirtual #235                // Method org/apache/hadoop/hbase/client/Scan.withStartRow:([BZ)Lorg/apache/hadoop/hbase/client/Scan;
     205: getstatic     #22                 // Field ROW:[B
     208: iconst_1
     209: invokevirtual #236                // Method org/apache/hadoop/hbase/client/Scan.withStopRow:([BZ)Lorg/apache/hadoop/hbase/client/Scan;
     212: astore        4
     214: aload_2
     215: aload         4
     217: invokeinterface #41,  2           // InterfaceMethod org/apache/hadoop/hbase/client/Table.getScanner:(Lorg/apache/hadoop/hbase/client/Scan;)Lorg/apache/hadoop/hbase/client/ResultScanner;
     222: astore        5
     224: aconst_null
     225: astore        6
     227: aload         5
     229: invokeinterface #53,  1           // InterfaceMethod org/apache/hadoop/hbase/client/ResultScanner.next:()Lorg/apache/hadoop/hbase/client/Result;
     234: astore        7
     236: aload         7
     238: invokestatic  #237                // Method org/junit/Assert.assertNotNull:(Ljava/lang/Object;)V
     241: getstatic     #22                 // Field ROW:[B
     244: aload         7
     246: invokevirtual #238                // Method org/apache/hadoop/hbase/client/Result.getRow:()[B
     249: invokestatic  #217                // Method org/junit/Assert.assertArrayEquals:([B[B)V
     252: getstatic     #25                 // Field VALUE:[B
     255: aload         7
     257: getstatic     #19                 // Field FAMILY:[B
     260: getstatic     #17                 // Field QUALIFIER:[B
     263: invokevirtual #216                // Method org/apache/hadoop/hbase/client/Result.getValue:([B[B)[B
     266: invokestatic  #217                // Method org/junit/Assert.assertArrayEquals:([B[B)V
     269: aload         5
     271: invokeinterface #53,  1           // InterfaceMethod org/apache/hadoop/hbase/client/ResultScanner.next:()Lorg/apache/hadoop/hbase/client/Result;
     276: invokestatic  #223                // Method org/junit/Assert.assertNull:(Ljava/lang/Object;)V
     279: aload         5
     281: ifnull        374
     284: aload         6
     286: ifnull        311
     289: aload         5
     291: invokeinterface #104,  1          // InterfaceMethod org/apache/hadoop/hbase/client/ResultScanner.close:()V
     296: goto          374
     299: astore        7
     301: aload         6
     303: aload         7
     305: invokevirtual #149                // Method java/lang/Throwable.addSuppressed:(Ljava/lang/Throwable;)V
     308: goto          374
     311: aload         5
     313: invokeinterface #104,  1          // InterfaceMethod org/apache/hadoop/hbase/client/ResultScanner.close:()V
     318: goto          374
     321: astore        7
     323: aload         7
     325: astore        6
     327: aload         7
     329: athrow
     330: astore        10
     332: aload         5
     334: ifnull        371
     337: aload         6
     339: ifnull        364
     342: aload         5
     344: invokeinterface #104,  1          // InterfaceMethod org/apache/hadoop/hbase/client/ResultScanner.close:()V
     349: goto          371
     352: astore        11
     354: aload         6
     356: aload         11
     358: invokevirtual #149                // Method java/lang/Throwable.addSuppressed:(Ljava/lang/Throwable;)V
     361: goto          371
     364: aload         5
     366: invokeinterface #104,  1          // InterfaceMethod org/apache/hadoop/hbase/client/ResultScanner.close:()V
     371: aload         10
     373: athrow
     374: new           #37                 // class org/apache/hadoop/hbase/client/Scan
     377: dup
     378: invokespecial #38                 // Method org/apache/hadoop/hbase/client/Scan."<init>":()V
     381: getstatic     #22                 // Field ROW:[B
     384: iconst_1
     385: invokevirtual #235                // Method org/apache/hadoop/hbase/client/Scan.withStartRow:([BZ)Lorg/apache/hadoop/hbase/client/Scan;
     388: getstatic     #22                 // Field ROW:[B
     391: iconst_0
     392: invokevirtual #236                // Method org/apache/hadoop/hbase/client/Scan.withStopRow:([BZ)Lorg/apache/hadoop/hbase/client/Scan;
     395: astore        4
     397: aload_2
     398: aload         4
     400: invokeinterface #41,  2           // InterfaceMethod org/apache/hadoop/hbase/client/Table.getScanner:(Lorg/apache/hadoop/hbase/client/Scan;)Lorg/apache/hadoop/hbase/client/ResultScanner;
     405: astore        5
     407: aconst_null
     408: astore        6
     410: aload         5
     412: invokeinterface #53,  1           // InterfaceMethod org/apache/hadoop/hbase/client/ResultScanner.next:()Lorg/apache/hadoop/hbase/client/Result;
     417: invokestatic  #223                // Method org/junit/Assert.assertNull:(Ljava/lang/Object;)V
     420: aload         5
     422: ifnull        515
     425: aload         6
     427: ifnull        452
     430: aload         5
     432: invokeinterface #104,  1          // InterfaceMethod org/apache/hadoop/hbase/client/ResultScanner.close:()V
     437: goto          515
     440: astore        7
     442: aload         6
     444: aload         7
     446: invokevirtual #149                // Method java/lang/Throwable.addSuppressed:(Ljava/lang/Throwable;)V
     449: goto          515
     452: aload         5
     454: invokeinterface #104,  1          // InterfaceMethod org/apache/hadoop/hbase/client/ResultScanner.close:()V
     459: goto          515
     462: astore        7
     464: aload         7
     466: astore        6
     468: aload         7
     470: athrow
     471: astore        12
     473: aload         5
     475: ifnull        512
     478: aload         6
     480: ifnull        505
     483: aload         5
     485: invokeinterface #104,  1          // InterfaceMethod org/apache/hadoop/hbase/client/ResultScanner.close:()V
     490: goto          512
     493: astore        13
     495: aload         6
     497: aload         13
     499: invokevirtual #149                // Method java/lang/Throwable.addSuppressed:(Ljava/lang/Throwable;)V
     502: goto          512
     505: aload         5
     507: invokeinterface #104,  1          // InterfaceMethod org/apache/hadoop/hbase/client/ResultScanner.close:()V
     512: aload         12
     514: athrow
     515: new           #37                 // class org/apache/hadoop/hbase/client/Scan
     518: dup
     519: invokespecial #38                 // Method org/apache/hadoop/hbase/client/Scan."<init>":()V
     522: getstatic     #22                 // Field ROW:[B
     525: iconst_0
     526: invokevirtual #235                // Method org/apache/hadoop/hbase/client/Scan.withStartRow:([BZ)Lorg/apache/hadoop/hbase/client/Scan;
     529: getstatic     #22                 // Field ROW:[B
     532: iconst_0
     533: invokevirtual #236                // Method org/apache/hadoop/hbase/client/Scan.withStopRow:([BZ)Lorg/apache/hadoop/hbase/client/Scan;
     536: astore        4
     538: aload_2
     539: aload         4
     541: invokeinterface #41,  2           // InterfaceMethod org/apache/hadoop/hbase/client/Table.getScanner:(Lorg/apache/hadoop/hbase/client/Scan;)Lorg/apache/hadoop/hbase/client/ResultScanner;
     546: astore        5
     548: aconst_null
     549: astore        6
     551: aload         5
     553: invokeinterface #53,  1           // InterfaceMethod org/apache/hadoop/hbase/client/ResultScanner.next:()Lorg/apache/hadoop/hbase/client/Result;
     558: invokestatic  #223                // Method org/junit/Assert.assertNull:(Ljava/lang/Object;)V
     561: aload         5
     563: ifnull        656
     566: aload         6
     568: ifnull        593
     571: aload         5
     573: invokeinterface #104,  1          // InterfaceMethod org/apache/hadoop/hbase/client/ResultScanner.close:()V
     578: goto          656
     581: astore        7
     583: aload         6
     585: aload         7
     587: invokevirtual #149                // Method java/lang/Throwable.addSuppressed:(Ljava/lang/Throwable;)V
     590: goto          656
     593: aload         5
     595: invokeinterface #104,  1          // InterfaceMethod org/apache/hadoop/hbase/client/ResultScanner.close:()V
     600: goto          656
     603: astore        7
     605: aload         7
     607: astore        6
     609: aload         7
     611: athrow
     612: astore        14
     614: aload         5
     616: ifnull        653
     619: aload         6
     621: ifnull        646
     624: aload         5
     626: invokeinterface #104,  1          // InterfaceMethod org/apache/hadoop/hbase/client/ResultScanner.close:()V
     631: goto          653
     634: astore        15
     636: aload         6
     638: aload         15
     640: invokevirtual #149                // Method java/lang/Throwable.addSuppressed:(Ljava/lang/Throwable;)V
     643: goto          653
     646: aload         5
     648: invokeinterface #104,  1          // InterfaceMethod org/apache/hadoop/hbase/client/ResultScanner.close:()V
     653: aload         14
     655: athrow
     656: new           #37                 // class org/apache/hadoop/hbase/client/Scan
     659: dup
     660: invokespecial #38                 // Method org/apache/hadoop/hbase/client/Scan."<init>":()V
     663: getstatic     #22                 // Field ROW:[B
     666: iconst_0
     667: invokevirtual #235                // Method org/apache/hadoop/hbase/client/Scan.withStartRow:([BZ)Lorg/apache/hadoop/hbase/client/Scan;
     670: getstatic     #22                 // Field ROW:[B
     673: iconst_1
     674: invokevirtual #236                // Method org/apache/hadoop/hbase/client/Scan.withStopRow:([BZ)Lorg/apache/hadoop/hbase/client/Scan;
     677: astore        4
     679: aload_2
     680: aload         4
     682: invokeinterface #41,  2           // InterfaceMethod org/apache/hadoop/hbase/client/Table.getScanner:(Lorg/apache/hadoop/hbase/client/Scan;)Lorg/apache/hadoop/hbase/client/ResultScanner;
     687: astore        5
     689: aconst_null
     690: astore        6
     692: aload         5
     694: invokeinterface #53,  1           // InterfaceMethod org/apache/hadoop/hbase/client/ResultScanner.next:()Lorg/apache/hadoop/hbase/client/Result;
     699: invokestatic  #223                // Method org/junit/Assert.assertNull:(Ljava/lang/Object;)V
     702: aload         5
     704: ifnull        797
     707: aload         6
     709: ifnull        734
     712: aload         5
     714: invokeinterface #104,  1          // InterfaceMethod org/apache/hadoop/hbase/client/ResultScanner.close:()V
     719: goto          797
     722: astore        7
     724: aload         6
     726: aload         7
     728: invokevirtual #149                // Method java/lang/Throwable.addSuppressed:(Ljava/lang/Throwable;)V
     731: goto          797
     734: aload         5
     736: invokeinterface #104,  1          // InterfaceMethod org/apache/hadoop/hbase/client/ResultScanner.close:()V
     741: goto          797
     744: astore        7
     746: aload         7
     748: astore        6
     750: aload         7
     752: athrow
     753: astore        16
     755: aload         5
     757: ifnull        794
     760: aload         6
     762: ifnull        787
     765: aload         5
     767: invokeinterface #104,  1          // InterfaceMethod org/apache/hadoop/hbase/client/ResultScanner.close:()V
     772: goto          794
     775: astore        17
     777: aload         6
     779: aload         17
     781: invokevirtual #149                // Method java/lang/Throwable.addSuppressed:(Ljava/lang/Throwable;)V
     784: goto          794
     787: aload         5
     789: invokeinterface #104,  1          // InterfaceMethod org/apache/hadoop/hbase/client/ResultScanner.close:()V
     794: aload         16
     796: athrow
     797: aload_2
     798: ifnull        881
     801: aload_3
     802: ifnull        825
     805: aload_2
     806: invokeinterface #147,  1          // InterfaceMethod org/apache/hadoop/hbase/client/Table.close:()V
     811: goto          881
     814: astore        4
     816: aload_3
     817: aload         4
     819: invokevirtual #149                // Method java/lang/Throwable.addSuppressed:(Ljava/lang/Throwable;)V
     822: goto          881
     825: aload_2
     826: invokeinterface #147,  1          // InterfaceMethod org/apache/hadoop/hbase/client/Table.close:()V
     831: goto          881
     834: astore        4
     836: aload         4
     838: astore_3
     839: aload         4
     841: athrow
     842: astore        18
     844: aload_2
     845: ifnull        878
     848: aload_3
     849: ifnull        872
     852: aload_2
     853: invokeinterface #147,  1          // InterfaceMethod org/apache/hadoop/hbase/client/Table.close:()V
     858: goto          878
     861: astore        19
     863: aload_3
     864: aload         19
     866: invokevirtual #149                // Method java/lang/Throwable.addSuppressed:(Ljava/lang/Throwable;)V
     869: goto          878
     872: aload_2
     873: invokeinterface #147,  1          // InterfaceMethod org/apache/hadoop/hbase/client/Table.close:()V
     878: aload         18
     880: athrow
     881: return
    Exception table:
       from    to  target type
         106   113   116   Class java/lang/Throwable
          86    96   138   Class java/lang/Throwable
          86    96   147   any
         159   166   169   Class java/lang/Throwable
         138   149   147   any
         289   296   299   Class java/lang/Throwable
         227   279   321   Class java/lang/Throwable
         227   279   330   any
         342   349   352   Class java/lang/Throwable
         321   332   330   any
         430   437   440   Class java/lang/Throwable
         410   420   462   Class java/lang/Throwable
         410   420   471   any
         483   490   493   Class java/lang/Throwable
         462   473   471   any
         571   578   581   Class java/lang/Throwable
         551   561   603   Class java/lang/Throwable
         551   561   612   any
         624   631   634   Class java/lang/Throwable
         603   614   612   any
         712   719   722   Class java/lang/Throwable
         692   702   744   Class java/lang/Throwable
         692   702   753   any
         765   772   775   Class java/lang/Throwable
         744   755   753   any
         805   811   814   Class java/lang/Throwable
          24   797   834   Class java/lang/Throwable
          24   797   842   any
         852   858   861   Class java/lang/Throwable
         834   844   842   any

  public void testReverseScanWithFlush() throws java.lang.Exception;
    Code:
       0: aload_0
       1: getfield      #6                  // Field name:Lorg/junit/rules/TestName;
       4: invokevirtual #15                 // Method org/junit/rules/TestName.getMethodName:()Ljava/lang/String;
       7: invokestatic  #16                 // Method org/apache/hadoop/hbase/TableName.valueOf:(Ljava/lang/String;)Lorg/apache/hadoop/hbase/TableName;
      10: astore_1
      11: bipush        10
      13: istore_2
      14: bipush        100
      16: istore_3
      17: ldc           #239                // int 131072
      19: invokestatic  #240                // Method org/apache/hadoop/hbase/client/TestFromClientSide3.generateHugeValue:(I)[B
      22: astore        4
      24: getstatic     #7                  // Field TEST_UTIL:Lorg/apache/hadoop/hbase/HBaseTestingUtility;
      27: aload_1
      28: getstatic     #19                 // Field FAMILY:[B
      31: invokevirtual #20                 // Method org/apache/hadoop/hbase/HBaseTestingUtility.createTable:(Lorg/apache/hadoop/hbase/TableName;[B)Lorg/apache/hadoop/hbase/client/Table;
      34: astore        5
      36: aconst_null
      37: astore        6
      39: getstatic     #7                  // Field TEST_UTIL:Lorg/apache/hadoop/hbase/HBaseTestingUtility;
      42: invokevirtual #164                // Method org/apache/hadoop/hbase/HBaseTestingUtility.getAdmin:()Lorg/apache/hadoop/hbase/client/Admin;
      45: astore        7
      47: aconst_null
      48: astore        8
      50: new           #42                 // class java/util/ArrayList
      53: dup
      54: invokespecial #43                 // Method java/util/ArrayList."<init>":()V
      57: astore        9
      59: lconst_0
      60: lstore        10
      62: lload         10
      64: ldc2_w        #241                // long 100l
      67: lcmp
      68: ifge          154
      71: new           #21                 // class org/apache/hadoop/hbase/client/Put
      74: dup
      75: lload         10
      77: invokestatic  #243                // Method org/apache/hadoop/hbase/util/Bytes.toBytes:(J)[B
      80: invokespecial #23                 // Method org/apache/hadoop/hbase/client/Put."<init>":([B)V
      83: astore        12
      85: aload         12
      87: getstatic     #19                 // Field FAMILY:[B
      90: getstatic     #17                 // Field QUALIFIER:[B
      93: aload         4
      95: invokevirtual #225                // Method org/apache/hadoop/hbase/client/Put.addColumn:([B[B[B)Lorg/apache/hadoop/hbase/client/Put;
      98: pop
      99: aload         9
     101: aload         12
     103: invokeinterface #46,  2           // InterfaceMethod java/util/List.add:(Ljava/lang/Object;)Z
     108: pop
     109: aload         9
     111: invokeinterface #186,  1          // InterfaceMethod java/util/List.size:()I
     116: bipush        10
     118: if_icmplt     145
     121: aload         5
     123: aload         9
     125: invokeinterface #63,  2           // InterfaceMethod org/apache/hadoop/hbase/client/Table.put:(Ljava/util/List;)V
     130: aload         7
     132: aload_1
     133: invokeinterface #244,  2          // InterfaceMethod org/apache/hadoop/hbase/client/Admin.flush:(Lorg/apache/hadoop/hbase/TableName;)V
     138: aload         9
     140: invokeinterface #187,  1          // InterfaceMethod java/util/List.clear:()V
     145: lload         10
     147: lconst_1
     148: ladd
     149: lstore        10
     151: goto          62
     154: aload         9
     156: invokeinterface #188,  1          // InterfaceMethod java/util/List.isEmpty:()Z
     161: ifne          188
     164: aload         5
     166: aload         9
     168: invokeinterface #63,  2           // InterfaceMethod org/apache/hadoop/hbase/client/Table.put:(Ljava/util/List;)V
     173: aload         7
     175: aload_1
     176: invokeinterface #244,  2          // InterfaceMethod org/apache/hadoop/hbase/client/Admin.flush:(Lorg/apache/hadoop/hbase/TableName;)V
     181: aload         9
     183: invokeinterface #187,  1          // InterfaceMethod java/util/List.clear:()V
     188: new           #37                 // class org/apache/hadoop/hbase/client/Scan
     191: dup
     192: invokespecial #38                 // Method org/apache/hadoop/hbase/client/Scan."<init>":()V
     195: astore        10
     197: aload         10
     199: iconst_1
     200: invokevirtual #91                 // Method org/apache/hadoop/hbase/client/Scan.setReversed:(Z)Lorg/apache/hadoop/hbase/client/Scan;
     203: pop
     204: iconst_0
     205: istore        11
     207: aload         5
     209: aload         10
     211: invokeinterface #41,  2           // InterfaceMethod org/apache/hadoop/hbase/client/Table.getScanner:(Lorg/apache/hadoop/hbase/client/Scan;)Lorg/apache/hadoop/hbase/client/ResultScanner;
     216: astore        12
     218: aconst_null
     219: astore        13
     221: aload         12
     223: invokeinterface #245,  1          // InterfaceMethod org/apache/hadoop/hbase/client/ResultScanner.iterator:()Ljava/util/Iterator;
     228: astore        14
     230: aload         14
     232: invokeinterface #125,  1          // InterfaceMethod java/util/Iterator.hasNext:()Z
     237: ifeq          258
     240: aload         14
     242: invokeinterface #126,  1          // InterfaceMethod java/util/Iterator.next:()Ljava/lang/Object;
     247: checkcast     #246                // class org/apache/hadoop/hbase/client/Result
     250: astore        15
     252: iinc          11, 1
     255: goto          230
     258: aload         12
     260: ifnull        353
     263: aload         13
     265: ifnull        290
     268: aload         12
     270: invokeinterface #104,  1          // InterfaceMethod org/apache/hadoop/hbase/client/ResultScanner.close:()V
     275: goto          353
     278: astore        14
     280: aload         13
     282: aload         14
     284: invokevirtual #149                // Method java/lang/Throwable.addSuppressed:(Ljava/lang/Throwable;)V
     287: goto          353
     290: aload         12
     292: invokeinterface #104,  1          // InterfaceMethod org/apache/hadoop/hbase/client/ResultScanner.close:()V
     297: goto          353
     300: astore        14
     302: aload         14
     304: astore        13
     306: aload         14
     308: athrow
     309: astore        16
     311: aload         12
     313: ifnull        350
     316: aload         13
     318: ifnull        343
     321: aload         12
     323: invokeinterface #104,  1          // InterfaceMethod org/apache/hadoop/hbase/client/ResultScanner.close:()V
     328: goto          350
     331: astore        17
     333: aload         13
     335: aload         17
     337: invokevirtual #149                // Method java/lang/Throwable.addSuppressed:(Ljava/lang/Throwable;)V
     340: goto          350
     343: aload         12
     345: invokeinterface #104,  1          // InterfaceMethod org/apache/hadoop/hbase/client/ResultScanner.close:()V
     350: aload         16
     352: athrow
     353: new           #66                 // class java/lang/StringBuilder
     356: dup
     357: invokespecial #67                 // Method java/lang/StringBuilder."<init>":()V
     360: ldc           #247                // String Expected 100 rows in the table but it is
     362: invokevirtual #69                 // Method java/lang/StringBuilder.append:(Ljava/lang/String;)Ljava/lang/StringBuilder;
     365: iload         11
     367: invokevirtual #71                 // Method java/lang/StringBuilder.append:(I)Ljava/lang/StringBuilder;
     370: invokevirtual #73                 // Method java/lang/StringBuilder.toString:()Ljava/lang/String;
     373: ldc2_w        #241                // long 100l
     376: iload         11
     378: i2l
     379: invokestatic  #248                // Method org/junit/Assert.assertEquals:(Ljava/lang/String;JJ)V
     382: aload         7
     384: ifnull        477
     387: aload         8
     389: ifnull        414
     392: aload         7
     394: invokeinterface #249,  1          // InterfaceMethod org/apache/hadoop/hbase/client/Admin.close:()V
     399: goto          477
     402: astore        9
     404: aload         8
     406: aload         9
     408: invokevirtual #149                // Method java/lang/Throwable.addSuppressed:(Ljava/lang/Throwable;)V
     411: goto          477
     414: aload         7
     416: invokeinterface #249,  1          // InterfaceMethod org/apache/hadoop/hbase/client/Admin.close:()V
     421: goto          477
     424: astore        9
     426: aload         9
     428: astore        8
     430: aload         9
     432: athrow
     433: astore        18
     435: aload         7
     437: ifnull        474
     440: aload         8
     442: ifnull        467
     445: aload         7
     447: invokeinterface #249,  1          // InterfaceMethod org/apache/hadoop/hbase/client/Admin.close:()V
     452: goto          474
     455: astore        19
     457: aload         8
     459: aload         19
     461: invokevirtual #149                // Method java/lang/Throwable.addSuppressed:(Ljava/lang/Throwable;)V
     464: goto          474
     467: aload         7
     469: invokeinterface #249,  1          // InterfaceMethod org/apache/hadoop/hbase/client/Admin.close:()V
     474: aload         18
     476: athrow
     477: aload         5
     479: ifnull        572
     482: aload         6
     484: ifnull        509
     487: aload         5
     489: invokeinterface #147,  1          // InterfaceMethod org/apache/hadoop/hbase/client/Table.close:()V
     494: goto          572
     497: astore        7
     499: aload         6
     501: aload         7
     503: invokevirtual #149                // Method java/lang/Throwable.addSuppressed:(Ljava/lang/Throwable;)V
     506: goto          572
     509: aload         5
     511: invokeinterface #147,  1          // InterfaceMethod org/apache/hadoop/hbase/client/Table.close:()V
     516: goto          572
     519: astore        7
     521: aload         7
     523: astore        6
     525: aload         7
     527: athrow
     528: astore        20
     530: aload         5
     532: ifnull        569
     535: aload         6
     537: ifnull        562
     540: aload         5
     542: invokeinterface #147,  1          // InterfaceMethod org/apache/hadoop/hbase/client/Table.close:()V
     547: goto          569
     550: astore        21
     552: aload         6
     554: aload         21
     556: invokevirtual #149                // Method java/lang/Throwable.addSuppressed:(Ljava/lang/Throwable;)V
     559: goto          569
     562: aload         5
     564: invokeinterface #147,  1          // InterfaceMethod org/apache/hadoop/hbase/client/Table.close:()V
     569: aload         20
     571: athrow
     572: return
    Exception table:
       from    to  target type
         268   275   278   Class java/lang/Throwable
         221   258   300   Class java/lang/Throwable
         221   258   309   any
         321   328   331   Class java/lang/Throwable
         300   311   309   any
         392   399   402   Class java/lang/Throwable
          50   382   424   Class java/lang/Throwable
          50   382   433   any
         445   452   455   Class java/lang/Throwable
         424   435   433   any
         487   494   497   Class java/lang/Throwable
          39   477   519   Class java/lang/Throwable
          39   477   528   any
         540   547   550   Class java/lang/Throwable
         519   530   528   any

  static {};
    Code:
       0: ldc_w         #256                // class org/apache/hadoop/hbase/client/TestScannersFromClientSide
       3: invokevirtual #257                // Method java/lang/Class.desiredAssertionStatus:()Z
       6: ifne          13
       9: iconst_1
      10: goto          14
      13: iconst_0
      14: putstatic     #178                // Field $assertionsDisabled:Z
      17: ldc_w         #256                // class org/apache/hadoop/hbase/client/TestScannersFromClientSide
      20: invokestatic  #258                // Method org/apache/hadoop/hbase/HBaseClassTestRule.forClass:(Ljava/lang/Class;)Lorg/apache/hadoop/hbase/HBaseClassTestRule;
      23: putstatic     #259                // Field CLASS_RULE:Lorg/apache/hadoop/hbase/HBaseClassTestRule;
      26: ldc_w         #256                // class org/apache/hadoop/hbase/client/TestScannersFromClientSide
      29: invokestatic  #260                // Method org/slf4j/LoggerFactory.getLogger:(Ljava/lang/Class;)Lorg/slf4j/Logger;
      32: putstatic     #160                // Field LOG:Lorg/slf4j/Logger;
      35: new           #261                // class org/apache/hadoop/hbase/HBaseTestingUtility
      38: dup
      39: invokespecial #262                // Method org/apache/hadoop/hbase/HBaseTestingUtility."<init>":()V
      42: putstatic     #7                  // Field TEST_UTIL:Lorg/apache/hadoop/hbase/HBaseTestingUtility;
      45: ldc_w         #263                // String testRow
      48: invokestatic  #182                // Method org/apache/hadoop/hbase/util/Bytes.toBytes:(Ljava/lang/String;)[B
      51: putstatic     #22                 // Field ROW:[B
      54: ldc_w         #264                // String testFamily
      57: invokestatic  #182                // Method org/apache/hadoop/hbase/util/Bytes.toBytes:(Ljava/lang/String;)[B
      60: putstatic     #19                 // Field FAMILY:[B
      63: ldc_w         #265                // String testQualifier
      66: invokestatic  #182                // Method org/apache/hadoop/hbase/util/Bytes.toBytes:(Ljava/lang/String;)[B
      69: putstatic     #17                 // Field QUALIFIER:[B
      72: ldc_w         #266                // String testValue
      75: invokestatic  #182                // Method org/apache/hadoop/hbase/util/Bytes.toBytes:(Ljava/lang/String;)[B
      78: putstatic     #25                 // Field VALUE:[B
      81: return
}
