Compiled from "TestHStore.java"
abstract class org.apache.hadoop.hbase.regionserver.TestHStore$MyStoreHook {
  void getScanners(org.apache.hadoop.hbase.regionserver.TestHStore$MyStore) throws java.io.IOException;
    Code:
       0: return

  long getSmallestReadPoint(org.apache.hadoop.hbase.regionserver.HStore);
    Code:
       0: aload_1
       1: invokevirtual #3                  // Method org/apache/hadoop/hbase/regionserver/HStore.getHRegion:()Lorg/apache/hadoop/hbase/regionserver/HRegion;
       4: invokevirtual #4                  // Method org/apache/hadoop/hbase/regionserver/HRegion.getSmallestReadPoint:()J
       7: lreturn

  org.apache.hadoop.hbase.regionserver.TestHStore$MyStoreHook(org.apache.hadoop.hbase.regionserver.TestHStore$1);
    Code:
       0: aload_0
       1: invokespecial #1                  // Method "<init>":()V
       4: return
}
