Compiled from "TestMetricsTableSourceImpl.java"
public class org.apache.hadoop.hbase.regionserver.TestMetricsTableSourceImpl {
  public static final org.apache.hadoop.hbase.HBaseClassTestRule CLASS_RULE;

  public org.apache.hadoop.hbase.regionserver.TestMetricsTableSourceImpl();
    Code:
       0: aload_0
       1: invokespecial #1                  // Method java/lang/Object."<init>":()V
       4: return

  public void testCompareToHashCode() throws java.lang.Exception;
    Code:
       0: ldc           #2                  // class org/apache/hadoop/hbase/regionserver/MetricsRegionServerSourceFactory
       2: invokestatic  #3                  // Method org/apache/hadoop/hbase/CompatibilitySingletonFactory.getInstance:(Ljava/lang/Class;)Ljava/lang/Object;
       5: checkcast     #2                  // class org/apache/hadoop/hbase/regionserver/MetricsRegionServerSourceFactory
       8: astore_1
       9: aload_1
      10: ldc           #4                  // String ONETABLE
      12: new           #5                  // class org/apache/hadoop/hbase/regionserver/MetricsTableWrapperStub
      15: dup
      16: ldc           #4                  // String ONETABLE
      18: invokespecial #6                  // Method org/apache/hadoop/hbase/regionserver/MetricsTableWrapperStub."<init>":(Ljava/lang/String;)V
      21: invokeinterface #7,  3            // InterfaceMethod org/apache/hadoop/hbase/regionserver/MetricsRegionServerSourceFactory.createTable:(Ljava/lang/String;Lorg/apache/hadoop/hbase/regionserver/MetricsTableWrapperAggregate;)Lorg/apache/hadoop/hbase/regionserver/MetricsTableSource;
      26: astore_2
      27: aload_1
      28: ldc           #4                  // String ONETABLE
      30: new           #5                  // class org/apache/hadoop/hbase/regionserver/MetricsTableWrapperStub
      33: dup
      34: ldc           #4                  // String ONETABLE
      36: invokespecial #6                  // Method org/apache/hadoop/hbase/regionserver/MetricsTableWrapperStub."<init>":(Ljava/lang/String;)V
      39: invokeinterface #7,  3            // InterfaceMethod org/apache/hadoop/hbase/regionserver/MetricsRegionServerSourceFactory.createTable:(Ljava/lang/String;Lorg/apache/hadoop/hbase/regionserver/MetricsTableWrapperAggregate;)Lorg/apache/hadoop/hbase/regionserver/MetricsTableSource;
      44: astore_3
      45: aload_1
      46: ldc           #8                  // String TWOTABLE
      48: new           #5                  // class org/apache/hadoop/hbase/regionserver/MetricsTableWrapperStub
      51: dup
      52: ldc           #8                  // String TWOTABLE
      54: invokespecial #6                  // Method org/apache/hadoop/hbase/regionserver/MetricsTableWrapperStub."<init>":(Ljava/lang/String;)V
      57: invokeinterface #7,  3            // InterfaceMethod org/apache/hadoop/hbase/regionserver/MetricsRegionServerSourceFactory.createTable:(Ljava/lang/String;Lorg/apache/hadoop/hbase/regionserver/MetricsTableWrapperAggregate;)Lorg/apache/hadoop/hbase/regionserver/MetricsTableSource;
      62: astore        4
      64: lconst_0
      65: aload_2
      66: aload_3
      67: invokeinterface #9,  2            // InterfaceMethod org/apache/hadoop/hbase/regionserver/MetricsTableSource.compareTo:(Ljava/lang/Object;)I
      72: i2l
      73: invokestatic  #10                 // Method org/junit/Assert.assertEquals:(JJ)V
      76: aload_2
      77: invokevirtual #11                 // Method java/lang/Object.hashCode:()I
      80: i2l
      81: aload_3
      82: invokevirtual #11                 // Method java/lang/Object.hashCode:()I
      85: i2l
      86: invokestatic  #10                 // Method org/junit/Assert.assertEquals:(JJ)V
      89: aload_2
      90: aload         4
      92: invokestatic  #12                 // Method org/junit/Assert.assertNotEquals:(Ljava/lang/Object;Ljava/lang/Object;)V
      95: aload_2
      96: aload         4
      98: invokeinterface #9,  2            // InterfaceMethod org/apache/hadoop/hbase/regionserver/MetricsTableSource.compareTo:(Ljava/lang/Object;)I
     103: ifeq          110
     106: iconst_1
     107: goto          111
     110: iconst_0
     111: invokestatic  #13                 // Method org/junit/Assert.assertTrue:(Z)V
     114: aload         4
     116: aload_2
     117: invokeinterface #9,  2            // InterfaceMethod org/apache/hadoop/hbase/regionserver/MetricsTableSource.compareTo:(Ljava/lang/Object;)I
     122: ifeq          129
     125: iconst_1
     126: goto          130
     129: iconst_0
     130: invokestatic  #13                 // Method org/junit/Assert.assertTrue:(Z)V
     133: aload         4
     135: aload_2
     136: invokeinterface #9,  2            // InterfaceMethod org/apache/hadoop/hbase/regionserver/MetricsTableSource.compareTo:(Ljava/lang/Object;)I
     141: aload_2
     142: aload         4
     144: invokeinterface #9,  2            // InterfaceMethod org/apache/hadoop/hbase/regionserver/MetricsTableSource.compareTo:(Ljava/lang/Object;)I
     149: if_icmpeq     156
     152: iconst_1
     153: goto          157
     156: iconst_0
     157: invokestatic  #13                 // Method org/junit/Assert.assertTrue:(Z)V
     160: aload         4
     162: aload         4
     164: invokeinterface #9,  2            // InterfaceMethod org/apache/hadoop/hbase/regionserver/MetricsTableSource.compareTo:(Ljava/lang/Object;)I
     169: ifne          176
     172: iconst_1
     173: goto          177
     176: iconst_0
     177: invokestatic  #13                 // Method org/junit/Assert.assertTrue:(Z)V
     180: return

  public void testNoGetTableMetricsSourceImpl();
    Code:
       0: ldc           #14                 // class org/apache/hadoop/hbase/regionserver/MetricsTableSourceImpl
       2: invokestatic  #3                  // Method org/apache/hadoop/hbase/CompatibilitySingletonFactory.getInstance:(Ljava/lang/Class;)Ljava/lang/Object;
       5: pop
       6: return

  public void testGetTableMetrics();
    Code:
       0: ldc           #2                  // class org/apache/hadoop/hbase/regionserver/MetricsRegionServerSourceFactory
       2: invokestatic  #3                  // Method org/apache/hadoop/hbase/CompatibilitySingletonFactory.getInstance:(Ljava/lang/Class;)Ljava/lang/Object;
       5: checkcast     #2                  // class org/apache/hadoop/hbase/regionserver/MetricsRegionServerSourceFactory
       8: ldc           #4                  // String ONETABLE
      10: new           #5                  // class org/apache/hadoop/hbase/regionserver/MetricsTableWrapperStub
      13: dup
      14: ldc           #4                  // String ONETABLE
      16: invokespecial #6                  // Method org/apache/hadoop/hbase/regionserver/MetricsTableWrapperStub."<init>":(Ljava/lang/String;)V
      19: invokeinterface #7,  3            // InterfaceMethod org/apache/hadoop/hbase/regionserver/MetricsRegionServerSourceFactory.createTable:(Ljava/lang/String;Lorg/apache/hadoop/hbase/regionserver/MetricsTableWrapperAggregate;)Lorg/apache/hadoop/hbase/regionserver/MetricsTableSource;
      24: astore_1
      25: ldc           #4                  // String ONETABLE
      27: aload_1
      28: invokeinterface #15,  1           // InterfaceMethod org/apache/hadoop/hbase/regionserver/MetricsTableSource.getTableName:()Ljava/lang/String;
      33: invokestatic  #16                 // Method org/junit/Assert.assertEquals:(Ljava/lang/Object;Ljava/lang/Object;)V
      36: return

  static {};
    Code:
       0: ldc           #17                 // class org/apache/hadoop/hbase/regionserver/TestMetricsTableSourceImpl
       2: invokestatic  #18                 // Method org/apache/hadoop/hbase/HBaseClassTestRule.forClass:(Ljava/lang/Class;)Lorg/apache/hadoop/hbase/HBaseClassTestRule;
       5: putstatic     #19                 // Field CLASS_RULE:Lorg/apache/hadoop/hbase/HBaseClassTestRule;
       8: return
}
