Compiled from "TestFuzzyRowFilterEndToEnd.java"
public class org.apache.hadoop.hbase.filter.TestFuzzyRowFilterEndToEnd {
  public static final org.apache.hadoop.hbase.HBaseClassTestRule CLASS_RULE;

  public org.junit.rules.TestName name;

  public org.apache.hadoop.hbase.filter.TestFuzzyRowFilterEndToEnd();
    Code:
       0: aload_0
       1: invokespecial #1                  // Method java/lang/Object."<init>":()V
       4: aload_0
       5: new           #2                  // class org/junit/rules/TestName
       8: dup
       9: invokespecial #3                  // Method org/junit/rules/TestName."<init>":()V
      12: putfield      #4                  // Field name:Lorg/junit/rules/TestName;
      15: return

  public static void setUpBeforeClass() throws java.lang.Exception;
    Code:
       0: getstatic     #5                  // Field TEST_UTIL:Lorg/apache/hadoop/hbase/HBaseTestingUtility;
       3: invokevirtual #6                  // Method org/apache/hadoop/hbase/HBaseTestingUtility.getConfiguration:()Lorg/apache/hadoop/conf/Configuration;
       6: astore_0
       7: aload_0
       8: ldc           #7                  // String hbase.client.scanner.caching
      10: sipush        1000
      13: invokevirtual #8                  // Method org/apache/hadoop/conf/Configuration.setInt:(Ljava/lang/String;I)V
      16: aload_0
      17: ldc           #10                 // String hbase.regionserver.region.split.policy
      19: ldc           #11                 // class org/apache/hadoop/hbase/regionserver/ConstantSizeRegionSplitPolicy
      21: invokevirtual #12                 // Method java/lang/Class.getName:()Ljava/lang/String;
      24: invokevirtual #13                 // Method org/apache/hadoop/conf/Configuration.set:(Ljava/lang/String;Ljava/lang/String;)V
      27: aload_0
      28: ldc           #14                 // String hbase.hregion.max.filesize
      30: ldc2_w        #15                 // long 10737418240l
      33: invokevirtual #17                 // Method org/apache/hadoop/conf/Configuration.setLong:(Ljava/lang/String;J)V
      36: getstatic     #5                  // Field TEST_UTIL:Lorg/apache/hadoop/hbase/HBaseTestingUtility;
      39: invokevirtual #18                 // Method org/apache/hadoop/hbase/HBaseTestingUtility.startMiniCluster:()Lorg/apache/hadoop/hbase/MiniHBaseCluster;
      42: pop
      43: return

  public static void tearDownAfterClass() throws java.lang.Exception;
    Code:
       0: getstatic     #5                  // Field TEST_UTIL:Lorg/apache/hadoop/hbase/HBaseTestingUtility;
       3: invokevirtual #19                 // Method org/apache/hadoop/hbase/HBaseTestingUtility.shutdownMiniCluster:()V
       6: return

  public void setUp() throws java.lang.Exception;
    Code:
       0: return

  public void tearDown() throws java.lang.Exception;
    Code:
       0: return

  public void testAllFixedBits() throws java.io.IOException;
    Code:
       0: ldc           #20                 // String f
       2: astore_1
       3: ldc           #21                 // String q
       5: astore_2
       6: getstatic     #5                  // Field TEST_UTIL:Lorg/apache/hadoop/hbase/HBaseTestingUtility;
       9: aload_0
      10: getfield      #4                  // Field name:Lorg/junit/rules/TestName;
      13: invokevirtual #22                 // Method org/junit/rules/TestName.getMethodName:()Ljava/lang/String;
      16: invokestatic  #23                 // Method org/apache/hadoop/hbase/TableName.valueOf:(Ljava/lang/String;)Lorg/apache/hadoop/hbase/TableName;
      19: aload_1
      20: invokestatic  #24                 // Method org/apache/hadoop/hbase/util/Bytes.toBytes:(Ljava/lang/String;)[B
      23: ldc           #26                 // int 2147483647
      25: invokevirtual #27                 // Method org/apache/hadoop/hbase/HBaseTestingUtility.createTable:(Lorg/apache/hadoop/hbase/TableName;[BI)Lorg/apache/hadoop/hbase/client/Table;
      28: astore_3
      29: bipush        7
      31: anewarray     #28                 // class java/lang/String
      34: dup
      35: iconst_0
      36: ldc           #29                 // String \x9C\x00\x044\x00\x00\x00\x00
      38: aastore
      39: dup
      40: iconst_1
      41: ldc           #30                 // String \x9C\x00\x044\x01\x00\x00\x00
      43: aastore
      44: dup
      45: iconst_2
      46: ldc           #31                 // String \x9C\x00\x044\x00\x01\x00\x00
      48: aastore
      49: dup
      50: iconst_3
      51: ldc           #32                 // String \x9B\x00\x044e\x9B\x02\xBB
      53: aastore
      54: dup
      55: iconst_4
      56: ldc           #33                 // String \x9C\x00\x044\x00\x00\x01\x00
      58: aastore
      59: dup
      60: iconst_5
      61: ldc           #34                 // String \x9C\x00\x044\x00\x01\x00\x01
      63: aastore
      64: dup
      65: bipush        6
      67: ldc           #35                 // String \x9B\x00\x044e\xBB\xB2\xBB
      69: aastore
      70: astore        4
      72: iconst_0
      73: istore        5
      75: iload         5
      77: aload         4
      79: arraylength
      80: if_icmpge     133
      83: new           #36                 // class org/apache/hadoop/hbase/client/Put
      86: dup
      87: aload         4
      89: iload         5
      91: aaload
      92: invokestatic  #37                 // Method org/apache/hadoop/hbase/util/Bytes.toBytesBinary:(Ljava/lang/String;)[B
      95: invokespecial #38                 // Method org/apache/hadoop/hbase/client/Put."<init>":([B)V
      98: astore        6
     100: aload         6
     102: aload_1
     103: invokestatic  #24                 // Method org/apache/hadoop/hbase/util/Bytes.toBytes:(Ljava/lang/String;)[B
     106: aload_2
     107: invokestatic  #24                 // Method org/apache/hadoop/hbase/util/Bytes.toBytes:(Ljava/lang/String;)[B
     110: ldc           #39                 // String value
     112: invokestatic  #24                 // Method org/apache/hadoop/hbase/util/Bytes.toBytes:(Ljava/lang/String;)[B
     115: invokevirtual #40                 // Method org/apache/hadoop/hbase/client/Put.addColumn:([B[B[B)Lorg/apache/hadoop/hbase/client/Put;
     118: pop
     119: aload_3
     120: aload         6
     122: invokeinterface #41,  2           // InterfaceMethod org/apache/hadoop/hbase/client/Table.put:(Lorg/apache/hadoop/hbase/client/Put;)V
     127: iinc          5, 1
     130: goto          75
     133: getstatic     #5                  // Field TEST_UTIL:Lorg/apache/hadoop/hbase/HBaseTestingUtility;
     136: invokevirtual #42                 // Method org/apache/hadoop/hbase/HBaseTestingUtility.flush:()V
     139: new           #43                 // class java/util/ArrayList
     142: dup
     143: invokespecial #44                 // Method java/util/ArrayList."<init>":()V
     146: astore        5
     148: ldc           #45                 // String \x9B\x00\x044e
     150: invokestatic  #37                 // Method org/apache/hadoop/hbase/util/Bytes.toBytesBinary:(Ljava/lang/String;)[B
     153: astore        6
     155: iconst_5
     156: newarray       byte
     158: dup
     159: iconst_0
     160: iconst_0
     161: bastore
     162: dup
     163: iconst_1
     164: iconst_0
     165: bastore
     166: dup
     167: iconst_2
     168: iconst_0
     169: bastore
     170: dup
     171: iconst_3
     172: iconst_0
     173: bastore
     174: dup
     175: iconst_4
     176: iconst_0
     177: bastore
     178: astore        7
     180: aload         6
     182: aload         6
     184: arraylength
     185: invokestatic  #46                 // Method java/util/Arrays.copyOf:([BI)[B
     188: astore        8
     190: aload         7
     192: aload         7
     194: arraylength
     195: invokestatic  #46                 // Method java/util/Arrays.copyOf:([BI)[B
     198: astore        9
     200: aload         5
     202: new           #47                 // class org/apache/hadoop/hbase/util/Pair
     205: dup
     206: aload         6
     208: aload         7
     210: invokespecial #48                 // Method org/apache/hadoop/hbase/util/Pair."<init>":(Ljava/lang/Object;Ljava/lang/Object;)V
     213: invokeinterface #49,  2           // InterfaceMethod java/util/List.add:(Ljava/lang/Object;)Z
     218: pop
     219: new           #50                 // class org/apache/hadoop/hbase/filter/FuzzyRowFilter
     222: dup
     223: aload         5
     225: invokespecial #51                 // Method org/apache/hadoop/hbase/filter/FuzzyRowFilter."<init>":(Ljava/util/List;)V
     228: astore        10
     230: new           #52                 // class org/apache/hadoop/hbase/client/Scan
     233: dup
     234: invokespecial #53                 // Method org/apache/hadoop/hbase/client/Scan."<init>":()V
     237: astore        11
     239: aload         11
     241: aload         10
     243: invokevirtual #54                 // Method org/apache/hadoop/hbase/client/Scan.setFilter:(Lorg/apache/hadoop/hbase/filter/Filter;)Lorg/apache/hadoop/hbase/client/Scan;
     246: pop
     247: aload_3
     248: aload         11
     250: invokeinterface #55,  2           // InterfaceMethod org/apache/hadoop/hbase/client/Table.getScanner:(Lorg/apache/hadoop/hbase/client/Scan;)Lorg/apache/hadoop/hbase/client/ResultScanner;
     255: astore        12
     257: iconst_0
     258: istore        13
     260: aload         12
     262: invokeinterface #56,  1           // InterfaceMethod org/apache/hadoop/hbase/client/ResultScanner.next:()Lorg/apache/hadoop/hbase/client/Result;
     267: ifnull        276
     270: iinc          13, 1
     273: goto          260
     276: ldc2_w        #57                 // long 2l
     279: iload         13
     281: i2l
     282: invokestatic  #59                 // Method org/junit/Assert.assertEquals:(JJ)V
     285: iconst_1
     286: invokestatic  #60                 // Method java/lang/Boolean.valueOf:(Z)Ljava/lang/Boolean;
     289: aload         8
     291: aload         6
     293: invokestatic  #61                 // Method java/util/Arrays.equals:([B[B)Z
     296: invokestatic  #60                 // Method java/lang/Boolean.valueOf:(Z)Ljava/lang/Boolean;
     299: invokestatic  #62                 // Method org/junit/Assert.assertEquals:(Ljava/lang/Object;Ljava/lang/Object;)V
     302: iconst_1
     303: invokestatic  #60                 // Method java/lang/Boolean.valueOf:(Z)Ljava/lang/Boolean;
     306: aload         9
     308: aload         7
     310: invokestatic  #61                 // Method java/util/Arrays.equals:([B[B)Z
     313: invokestatic  #60                 // Method java/lang/Boolean.valueOf:(Z)Ljava/lang/Boolean;
     316: invokestatic  #62                 // Method org/junit/Assert.assertEquals:(Ljava/lang/Object;Ljava/lang/Object;)V
     319: getstatic     #5                  // Field TEST_UTIL:Lorg/apache/hadoop/hbase/HBaseTestingUtility;
     322: aload_0
     323: getfield      #4                  // Field name:Lorg/junit/rules/TestName;
     326: invokevirtual #22                 // Method org/junit/rules/TestName.getMethodName:()Ljava/lang/String;
     329: invokestatic  #23                 // Method org/apache/hadoop/hbase/TableName.valueOf:(Ljava/lang/String;)Lorg/apache/hadoop/hbase/TableName;
     332: invokevirtual #63                 // Method org/apache/hadoop/hbase/HBaseTestingUtility.deleteTable:(Lorg/apache/hadoop/hbase/TableName;)V
     335: return

  public void testHBASE14782() throws java.io.IOException;
    Code:
       0: ldc           #20                 // String f
       2: astore_1
       3: ldc           #21                 // String q
       5: astore_2
       6: getstatic     #5                  // Field TEST_UTIL:Lorg/apache/hadoop/hbase/HBaseTestingUtility;
       9: aload_0
      10: getfield      #4                  // Field name:Lorg/junit/rules/TestName;
      13: invokevirtual #22                 // Method org/junit/rules/TestName.getMethodName:()Ljava/lang/String;
      16: invokestatic  #23                 // Method org/apache/hadoop/hbase/TableName.valueOf:(Ljava/lang/String;)Lorg/apache/hadoop/hbase/TableName;
      19: aload_1
      20: invokestatic  #24                 // Method org/apache/hadoop/hbase/util/Bytes.toBytes:(Ljava/lang/String;)[B
      23: ldc           #26                 // int 2147483647
      25: invokevirtual #27                 // Method org/apache/hadoop/hbase/HBaseTestingUtility.createTable:(Lorg/apache/hadoop/hbase/TableName;[BI)Lorg/apache/hadoop/hbase/client/Table;
      28: astore_3
      29: bipush        6
      31: anewarray     #28                 // class java/lang/String
      34: dup
      35: iconst_0
      36: ldc           #29                 // String \x9C\x00\x044\x00\x00\x00\x00
      38: aastore
      39: dup
      40: iconst_1
      41: ldc           #30                 // String \x9C\x00\x044\x01\x00\x00\x00
      43: aastore
      44: dup
      45: iconst_2
      46: ldc           #31                 // String \x9C\x00\x044\x00\x01\x00\x00
      48: aastore
      49: dup
      50: iconst_3
      51: ldc           #33                 // String \x9C\x00\x044\x00\x00\x01\x00
      53: aastore
      54: dup
      55: iconst_4
      56: ldc           #34                 // String \x9C\x00\x044\x00\x01\x00\x01
      58: aastore
      59: dup
      60: iconst_5
      61: ldc           #35                 // String \x9B\x00\x044e\xBB\xB2\xBB
      63: aastore
      64: astore        4
      66: ldc           #64                 // String \x9C\x00\x03\xE9e\xBB{X\x1Fwts\x1F\x15vRX
      68: astore        5
      70: iconst_0
      71: istore        6
      73: iload         6
      75: aload         4
      77: arraylength
      78: if_icmpge     131
      81: new           #36                 // class org/apache/hadoop/hbase/client/Put
      84: dup
      85: aload         4
      87: iload         6
      89: aaload
      90: invokestatic  #37                 // Method org/apache/hadoop/hbase/util/Bytes.toBytesBinary:(Ljava/lang/String;)[B
      93: invokespecial #38                 // Method org/apache/hadoop/hbase/client/Put."<init>":([B)V
      96: astore        7
      98: aload         7
     100: aload_1
     101: invokestatic  #24                 // Method org/apache/hadoop/hbase/util/Bytes.toBytes:(Ljava/lang/String;)[B
     104: aload_2
     105: invokestatic  #24                 // Method org/apache/hadoop/hbase/util/Bytes.toBytes:(Ljava/lang/String;)[B
     108: ldc           #39                 // String value
     110: invokestatic  #24                 // Method org/apache/hadoop/hbase/util/Bytes.toBytes:(Ljava/lang/String;)[B
     113: invokevirtual #40                 // Method org/apache/hadoop/hbase/client/Put.addColumn:([B[B[B)Lorg/apache/hadoop/hbase/client/Put;
     116: pop
     117: aload_3
     118: aload         7
     120: invokeinterface #41,  2           // InterfaceMethod org/apache/hadoop/hbase/client/Table.put:(Lorg/apache/hadoop/hbase/client/Put;)V
     125: iinc          6, 1
     128: goto          73
     131: new           #36                 // class org/apache/hadoop/hbase/client/Put
     134: dup
     135: aload         5
     137: invokestatic  #37                 // Method org/apache/hadoop/hbase/util/Bytes.toBytesBinary:(Ljava/lang/String;)[B
     140: invokespecial #38                 // Method org/apache/hadoop/hbase/client/Put."<init>":([B)V
     143: astore        6
     145: aload         6
     147: aload_1
     148: invokestatic  #24                 // Method org/apache/hadoop/hbase/util/Bytes.toBytes:(Ljava/lang/String;)[B
     151: aload_2
     152: invokestatic  #24                 // Method org/apache/hadoop/hbase/util/Bytes.toBytes:(Ljava/lang/String;)[B
     155: ldc           #39                 // String value
     157: invokestatic  #24                 // Method org/apache/hadoop/hbase/util/Bytes.toBytes:(Ljava/lang/String;)[B
     160: invokevirtual #40                 // Method org/apache/hadoop/hbase/client/Put.addColumn:([B[B[B)Lorg/apache/hadoop/hbase/client/Put;
     163: pop
     164: aload_3
     165: aload         6
     167: invokeinterface #41,  2           // InterfaceMethod org/apache/hadoop/hbase/client/Table.put:(Lorg/apache/hadoop/hbase/client/Put;)V
     172: getstatic     #5                  // Field TEST_UTIL:Lorg/apache/hadoop/hbase/HBaseTestingUtility;
     175: invokevirtual #42                 // Method org/apache/hadoop/hbase/HBaseTestingUtility.flush:()V
     178: new           #43                 // class java/util/ArrayList
     181: dup
     182: invokespecial #44                 // Method java/util/ArrayList."<init>":()V
     185: astore        7
     187: ldc           #65                 // String \x00\x00\x044
     189: invokestatic  #37                 // Method org/apache/hadoop/hbase/util/Bytes.toBytesBinary:(Ljava/lang/String;)[B
     192: astore        8
     194: iconst_4
     195: newarray       byte
     197: dup
     198: iconst_0
     199: iconst_1
     200: bastore
     201: dup
     202: iconst_1
     203: iconst_0
     204: bastore
     205: dup
     206: iconst_2
     207: iconst_0
     208: bastore
     209: dup
     210: iconst_3
     211: iconst_0
     212: bastore
     213: astore        9
     215: aload         7
     217: new           #47                 // class org/apache/hadoop/hbase/util/Pair
     220: dup
     221: aload         8
     223: aload         9
     225: invokespecial #48                 // Method org/apache/hadoop/hbase/util/Pair."<init>":(Ljava/lang/Object;Ljava/lang/Object;)V
     228: invokeinterface #49,  2           // InterfaceMethod java/util/List.add:(Ljava/lang/Object;)Z
     233: pop
     234: new           #50                 // class org/apache/hadoop/hbase/filter/FuzzyRowFilter
     237: dup
     238: aload         7
     240: invokespecial #51                 // Method org/apache/hadoop/hbase/filter/FuzzyRowFilter."<init>":(Ljava/util/List;)V
     243: astore        10
     245: new           #52                 // class org/apache/hadoop/hbase/client/Scan
     248: dup
     249: invokespecial #53                 // Method org/apache/hadoop/hbase/client/Scan."<init>":()V
     252: astore        11
     254: aload         11
     256: aload         10
     258: invokevirtual #54                 // Method org/apache/hadoop/hbase/client/Scan.setFilter:(Lorg/apache/hadoop/hbase/filter/Filter;)Lorg/apache/hadoop/hbase/client/Scan;
     261: pop
     262: aload_3
     263: aload         11
     265: invokeinterface #55,  2           // InterfaceMethod org/apache/hadoop/hbase/client/Table.getScanner:(Lorg/apache/hadoop/hbase/client/Scan;)Lorg/apache/hadoop/hbase/client/ResultScanner;
     270: astore        12
     272: iconst_0
     273: istore        13
     275: aload         12
     277: invokeinterface #56,  1           // InterfaceMethod org/apache/hadoop/hbase/client/ResultScanner.next:()Lorg/apache/hadoop/hbase/client/Result;
     282: ifnull        291
     285: iinc          13, 1
     288: goto          275
     291: aload         4
     293: arraylength
     294: i2l
     295: iload         13
     297: i2l
     298: invokestatic  #59                 // Method org/junit/Assert.assertEquals:(JJ)V
     301: getstatic     #5                  // Field TEST_UTIL:Lorg/apache/hadoop/hbase/HBaseTestingUtility;
     304: aload_0
     305: getfield      #4                  // Field name:Lorg/junit/rules/TestName;
     308: invokevirtual #22                 // Method org/junit/rules/TestName.getMethodName:()Ljava/lang/String;
     311: invokestatic  #23                 // Method org/apache/hadoop/hbase/TableName.valueOf:(Ljava/lang/String;)Lorg/apache/hadoop/hbase/TableName;
     314: invokevirtual #63                 // Method org/apache/hadoop/hbase/HBaseTestingUtility.deleteTable:(Lorg/apache/hadoop/hbase/TableName;)V
     317: return

  public void testEndToEnd() throws java.lang.Exception;
    Code:
       0: ldc           #20                 // String f
       2: astore_1
       3: getstatic     #5                  // Field TEST_UTIL:Lorg/apache/hadoop/hbase/HBaseTestingUtility;
       6: getstatic     #66                 // Field table:Ljava/lang/String;
       9: invokestatic  #23                 // Method org/apache/hadoop/hbase/TableName.valueOf:(Ljava/lang/String;)Lorg/apache/hadoop/hbase/TableName;
      12: aload_1
      13: invokestatic  #24                 // Method org/apache/hadoop/hbase/util/Bytes.toBytes:(Ljava/lang/String;)[B
      16: ldc           #26                 // int 2147483647
      18: invokevirtual #27                 // Method org/apache/hadoop/hbase/HBaseTestingUtility.createTable:(Lorg/apache/hadoop/hbase/TableName;[BI)Lorg/apache/hadoop/hbase/client/Table;
      21: astore_2
      22: iconst_0
      23: istore_3
      24: iload_3
      25: getstatic     #67                 // Field firstPartCardinality:I
      28: if_icmpge     195
      31: iconst_0
      32: istore        4
      34: iload         4
      36: getstatic     #68                 // Field secondPartCardinality:I
      39: if_icmpge     189
      42: iconst_0
      43: istore        5
      45: iload         5
      47: getstatic     #69                 // Field thirdPartCardinality:I
      50: if_icmpge     183
      53: bipush        10
      55: newarray       byte
      57: astore        6
      59: aload         6
      61: invokestatic  #70                 // Method java/nio/ByteBuffer.wrap:([B)Ljava/nio/ByteBuffer;
      64: astore        7
      66: aload         7
      68: invokevirtual #71                 // Method java/nio/ByteBuffer.clear:()Ljava/nio/Buffer;
      71: pop
      72: aload         7
      74: iload_3
      75: i2s
      76: invokevirtual #72                 // Method java/nio/ByteBuffer.putShort:(S)Ljava/nio/ByteBuffer;
      79: pop
      80: aload         7
      82: iload         4
      84: invokevirtual #73                 // Method java/nio/ByteBuffer.putInt:(I)Ljava/nio/ByteBuffer;
      87: pop
      88: aload         7
      90: iload         5
      92: invokevirtual #73                 // Method java/nio/ByteBuffer.putInt:(I)Ljava/nio/ByteBuffer;
      95: pop
      96: iconst_0
      97: istore        8
      99: iload         8
     101: getstatic     #74                 // Field colQualifiersTotal:I
     104: if_icmpge     177
     107: iconst_4
     108: newarray       byte
     110: astore        9
     112: aload         9
     114: iconst_0
     115: iload         8
     117: invokestatic  #75                 // Method org/apache/hadoop/hbase/util/Bytes.toBytes:(I)[B
     120: iconst_0
     121: iconst_4
     122: invokestatic  #76                 // Method org/apache/hadoop/hbase/util/Bytes.putBytes:([BI[BII)I
     125: pop
     126: new           #36                 // class org/apache/hadoop/hbase/client/Put
     129: dup
     130: aload         6
     132: invokespecial #38                 // Method org/apache/hadoop/hbase/client/Put."<init>":([B)V
     135: astore        10
     137: aload         10
     139: getstatic     #77                 // Field org/apache/hadoop/hbase/client/Durability.SKIP_WAL:Lorg/apache/hadoop/hbase/client/Durability;
     142: invokevirtual #78                 // Method org/apache/hadoop/hbase/client/Put.setDurability:(Lorg/apache/hadoop/hbase/client/Durability;)Lorg/apache/hadoop/hbase/client/Put;
     145: pop
     146: aload         10
     148: aload_1
     149: invokestatic  #24                 // Method org/apache/hadoop/hbase/util/Bytes.toBytes:(Ljava/lang/String;)[B
     152: aload         9
     154: iload         8
     156: invokestatic  #75                 // Method org/apache/hadoop/hbase/util/Bytes.toBytes:(I)[B
     159: invokevirtual #40                 // Method org/apache/hadoop/hbase/client/Put.addColumn:([B[B[B)Lorg/apache/hadoop/hbase/client/Put;
     162: pop
     163: aload_2
     164: aload         10
     166: invokeinterface #41,  2           // InterfaceMethod org/apache/hadoop/hbase/client/Table.put:(Lorg/apache/hadoop/hbase/client/Put;)V
     171: iinc          8, 1
     174: goto          99
     177: iinc          5, 1
     180: goto          45
     183: iinc          4, 1
     186: goto          34
     189: iinc          3, 1
     192: goto          24
     195: getstatic     #5                  // Field TEST_UTIL:Lorg/apache/hadoop/hbase/HBaseTestingUtility;
     198: invokevirtual #42                 // Method org/apache/hadoop/hbase/HBaseTestingUtility.flush:()V
     201: aload_0
     202: aload_2
     203: invokespecial #79                 // Method runTest1:(Lorg/apache/hadoop/hbase/client/Table;)V
     206: aload_0
     207: aload_2
     208: invokespecial #80                 // Method runTest2:(Lorg/apache/hadoop/hbase/client/Table;)V
     211: return

  public void testFilterList() throws java.lang.Exception;
    Code:
       0: ldc           #20                 // String f
       2: astore_1
       3: getstatic     #5                  // Field TEST_UTIL:Lorg/apache/hadoop/hbase/HBaseTestingUtility;
       6: aload_0
       7: getfield      #4                  // Field name:Lorg/junit/rules/TestName;
      10: invokevirtual #22                 // Method org/junit/rules/TestName.getMethodName:()Ljava/lang/String;
      13: invokestatic  #23                 // Method org/apache/hadoop/hbase/TableName.valueOf:(Ljava/lang/String;)Lorg/apache/hadoop/hbase/TableName;
      16: aload_1
      17: invokestatic  #24                 // Method org/apache/hadoop/hbase/util/Bytes.toBytes:(Ljava/lang/String;)[B
      20: ldc           #26                 // int 2147483647
      22: invokevirtual #27                 // Method org/apache/hadoop/hbase/HBaseTestingUtility.createTable:(Lorg/apache/hadoop/hbase/TableName;[BI)Lorg/apache/hadoop/hbase/client/Table;
      25: astore_2
      26: iconst_0
      27: istore_3
      28: iload_3
      29: iconst_5
      30: if_icmpge     218
      33: iconst_0
      34: istore        4
      36: iload         4
      38: iconst_5
      39: if_icmpge     212
      42: bipush        10
      44: newarray       byte
      46: astore        5
      48: aload         5
      50: invokestatic  #70                 // Method java/nio/ByteBuffer.wrap:([B)Ljava/nio/ByteBuffer;
      53: astore        6
      55: aload         6
      57: invokevirtual #71                 // Method java/nio/ByteBuffer.clear:()Ljava/nio/Buffer;
      60: pop
      61: aload         6
      63: iconst_2
      64: invokevirtual #72                 // Method java/nio/ByteBuffer.putShort:(S)Ljava/nio/ByteBuffer;
      67: pop
      68: aload         6
      70: iload_3
      71: invokevirtual #73                 // Method java/nio/ByteBuffer.putInt:(I)Ljava/nio/ByteBuffer;
      74: pop
      75: aload         6
      77: iload         4
      79: invokevirtual #73                 // Method java/nio/ByteBuffer.putInt:(I)Ljava/nio/ByteBuffer;
      82: pop
      83: iconst_0
      84: istore        7
      86: iload         7
      88: iconst_5
      89: if_icmpge     206
      92: iconst_4
      93: newarray       byte
      95: astore        8
      97: aload         8
      99: iconst_0
     100: iload         7
     102: invokestatic  #75                 // Method org/apache/hadoop/hbase/util/Bytes.toBytes:(I)[B
     105: iconst_0
     106: iconst_4
     107: invokestatic  #76                 // Method org/apache/hadoop/hbase/util/Bytes.putBytes:([BI[BII)I
     110: pop
     111: new           #36                 // class org/apache/hadoop/hbase/client/Put
     114: dup
     115: aload         5
     117: invokespecial #38                 // Method org/apache/hadoop/hbase/client/Put."<init>":([B)V
     120: astore        9
     122: aload         9
     124: getstatic     #77                 // Field org/apache/hadoop/hbase/client/Durability.SKIP_WAL:Lorg/apache/hadoop/hbase/client/Durability;
     127: invokevirtual #78                 // Method org/apache/hadoop/hbase/client/Put.setDurability:(Lorg/apache/hadoop/hbase/client/Durability;)Lorg/apache/hadoop/hbase/client/Put;
     130: pop
     131: aload         9
     133: aload_1
     134: invokestatic  #24                 // Method org/apache/hadoop/hbase/util/Bytes.toBytes:(Ljava/lang/String;)[B
     137: aload         8
     139: iload         7
     141: invokestatic  #75                 // Method org/apache/hadoop/hbase/util/Bytes.toBytes:(I)[B
     144: invokevirtual #40                 // Method org/apache/hadoop/hbase/client/Put.addColumn:([B[B[B)Lorg/apache/hadoop/hbase/client/Put;
     147: pop
     148: aload_2
     149: aload         9
     151: invokeinterface #41,  2           // InterfaceMethod org/apache/hadoop/hbase/client/Table.put:(Lorg/apache/hadoop/hbase/client/Put;)V
     156: getstatic     #96                 // Field LOG:Lorg/slf4j/Logger;
     159: new           #97                 // class java/lang/StringBuilder
     162: dup
     163: invokespecial #98                 // Method java/lang/StringBuilder."<init>":()V
     166: ldc           #108                // String Inserting: rk:
     168: invokevirtual #100                // Method java/lang/StringBuilder.append:(Ljava/lang/String;)Ljava/lang/StringBuilder;
     171: aload         5
     173: invokestatic  #109                // Method org/apache/hadoop/hbase/util/Bytes.toStringBinary:([B)Ljava/lang/String;
     176: invokevirtual #100                // Method java/lang/StringBuilder.append:(Ljava/lang/String;)Ljava/lang/StringBuilder;
     179: ldc           #110                // String  cq:
     181: invokevirtual #100                // Method java/lang/StringBuilder.append:(Ljava/lang/String;)Ljava/lang/StringBuilder;
     184: aload         8
     186: invokestatic  #109                // Method org/apache/hadoop/hbase/util/Bytes.toStringBinary:([B)Ljava/lang/String;
     189: invokevirtual #100                // Method java/lang/StringBuilder.append:(Ljava/lang/String;)Ljava/lang/StringBuilder;
     192: invokevirtual #103                // Method java/lang/StringBuilder.toString:()Ljava/lang/String;
     195: invokeinterface #104,  2          // InterfaceMethod org/slf4j/Logger.info:(Ljava/lang/String;)V
     200: iinc          7, 1
     203: goto          86
     206: iinc          4, 1
     209: goto          36
     212: iinc          3, 1
     215: goto          28
     218: getstatic     #5                  // Field TEST_UTIL:Lorg/apache/hadoop/hbase/HBaseTestingUtility;
     221: invokevirtual #42                 // Method org/apache/hadoop/hbase/HBaseTestingUtility.flush:()V
     224: aload_0
     225: aload_2
     226: iconst_5
     227: invokespecial #111                // Method runTest:(Lorg/apache/hadoop/hbase/client/Table;I)V
     230: return

  static {};
    Code:
       0: ldc           #82                 // class org/apache/hadoop/hbase/filter/TestFuzzyRowFilterEndToEnd
       2: invokestatic  #129                // Method org/apache/hadoop/hbase/HBaseClassTestRule.forClass:(Ljava/lang/Class;)Lorg/apache/hadoop/hbase/HBaseClassTestRule;
       5: putstatic     #130                // Field CLASS_RULE:Lorg/apache/hadoop/hbase/HBaseClassTestRule;
       8: new           #131                // class org/apache/hadoop/hbase/HBaseTestingUtility
      11: dup
      12: invokespecial #132                // Method org/apache/hadoop/hbase/HBaseTestingUtility."<init>":()V
      15: putstatic     #5                  // Field TEST_UTIL:Lorg/apache/hadoop/hbase/HBaseTestingUtility;
      18: ldc           #82                 // class org/apache/hadoop/hbase/filter/TestFuzzyRowFilterEndToEnd
      20: invokestatic  #133                // Method org/slf4j/LoggerFactory.getLogger:(Ljava/lang/Class;)Lorg/slf4j/Logger;
      23: putstatic     #96                 // Field LOG:Lorg/slf4j/Logger;
      26: bipush        50
      28: putstatic     #67                 // Field firstPartCardinality:I
      31: bipush        50
      33: putstatic     #68                 // Field secondPartCardinality:I
      36: bipush        50
      38: putstatic     #69                 // Field thirdPartCardinality:I
      41: iconst_5
      42: putstatic     #74                 // Field colQualifiersTotal:I
      45: getstatic     #69                 // Field thirdPartCardinality:I
      48: iconst_2
      49: idiv
      50: putstatic     #81                 // Field totalFuzzyKeys:I
      53: ldc           #134                // String TestFuzzyRowFilterEndToEnd
      55: putstatic     #66                 // Field table:Ljava/lang/String;
      58: return
}
