Compiled from "TestRegionState.java"
public class org.apache.hadoop.hbase.master.TestRegionState {
  public static final org.apache.hadoop.hbase.HBaseClassTestRule CLASS_RULE;

  public org.junit.rules.TestName name;

  public org.apache.hadoop.hbase.master.TestRegionState();
    Code:
       0: aload_0
       1: invokespecial #1                  // Method java/lang/Object."<init>":()V
       4: aload_0
       5: new           #2                  // class org/junit/rules/TestName
       8: dup
       9: invokespecial #3                  // Method org/junit/rules/TestName."<init>":()V
      12: putfield      #4                  // Field name:Lorg/junit/rules/TestName;
      15: return

  public void testSerializeDeserialize();
    Code:
       0: ldc           #5                  // String testtb
       2: invokestatic  #6                  // Method org/apache/hadoop/hbase/TableName.valueOf:(Ljava/lang/String;)Lorg/apache/hadoop/hbase/TableName;
       5: astore_1
       6: invokestatic  #7                  // Method org/apache/hadoop/hbase/master/RegionState$State.values:()[Lorg/apache/hadoop/hbase/master/RegionState$State;
       9: astore_2
      10: aload_2
      11: arraylength
      12: istore_3
      13: iconst_0
      14: istore        4
      16: iload         4
      18: iload_3
      19: if_icmpge     41
      22: aload_2
      23: iload         4
      25: aaload
      26: astore        5
      28: aload_0
      29: aload_1
      30: aload         5
      32: invokespecial #8                  // Method testSerializeDeserialize:(Lorg/apache/hadoop/hbase/TableName;Lorg/apache/hadoop/hbase/master/RegionState$State;)V
      35: iinc          4, 1
      38: goto          16
      41: return

  static {};
    Code:
       0: ldc           #22                 // class org/apache/hadoop/hbase/master/TestRegionState
       2: invokestatic  #23                 // Method org/apache/hadoop/hbase/HBaseClassTestRule.forClass:(Ljava/lang/Class;)Lorg/apache/hadoop/hbase/HBaseClassTestRule;
       5: putstatic     #24                 // Field CLASS_RULE:Lorg/apache/hadoop/hbase/HBaseClassTestRule;
       8: return
}
