Compiled from "TestFromClientSideScanExcpetion.java"
class org.apache.hadoop.hbase.client.TestFromClientSideScanExcpetion$MyStoreScanner$1 extends org.apache.hadoop.hbase.regionserver.DelegatingKeyValueScanner {
  final org.apache.hadoop.hbase.client.TestFromClientSideScanExcpetion$MyStoreScanner this$0;

  org.apache.hadoop.hbase.client.TestFromClientSideScanExcpetion$MyStoreScanner$1(org.apache.hadoop.hbase.client.TestFromClientSideScanExcpetion$MyStoreScanner, org.apache.hadoop.hbase.regionserver.KeyValueScanner);
    Code:
       0: aload_0
       1: aload_1
       2: putfield      #1                  // Field this$0:Lorg/apache/hadoop/hbase/client/TestFromClientSideScanExcpetion$MyStoreScanner;
       5: aload_0
       6: aload_2
       7: invokespecial #2                  // Method org/apache/hadoop/hbase/regionserver/DelegatingKeyValueScanner."<init>":(Lorg/apache/hadoop/hbase/regionserver/KeyValueScanner;)V
      10: return

  public boolean reseek(org.apache.hadoop.hbase.Cell) throws java.io.IOException;
    Code:
       0: invokestatic  #3                  // Method org/apache/hadoop/hbase/client/TestFromClientSideScanExcpetion.access$000:()Ljava/util/concurrent/atomic/AtomicBoolean;
       3: invokevirtual #4                  // Method java/util/concurrent/atomic/AtomicBoolean.get:()Z
       6: ifeq          65
       9: invokestatic  #5                  // Method org/apache/hadoop/hbase/client/TestFromClientSideScanExcpetion.access$100:()Ljava/util/concurrent/atomic/AtomicLong;
      12: invokevirtual #6                  // Method java/util/concurrent/atomic/AtomicLong.incrementAndGet:()J
      15: pop2
      16: invokestatic  #7                  // Method org/apache/hadoop/hbase/client/TestFromClientSideScanExcpetion.access$200:()Ljava/util/concurrent/atomic/AtomicBoolean;
      19: invokevirtual #4                  // Method java/util/concurrent/atomic/AtomicBoolean.get:()Z
      22: ifeq          36
      25: invokestatic  #5                  // Method org/apache/hadoop/hbase/client/TestFromClientSideScanExcpetion.access$100:()Ljava/util/concurrent/atomic/AtomicLong;
      28: invokevirtual #8                  // Method java/util/concurrent/atomic/AtomicLong.get:()J
      31: lconst_1
      32: lcmp
      33: ifne          65
      36: invokestatic  #9                  // Method org/apache/hadoop/hbase/client/TestFromClientSideScanExcpetion.access$300:()Ljava/util/concurrent/atomic/AtomicBoolean;
      39: invokevirtual #4                  // Method java/util/concurrent/atomic/AtomicBoolean.get:()Z
      42: ifeq          55
      45: new           #10                 // class org/apache/hadoop/hbase/DoNotRetryIOException
      48: dup
      49: ldc           #11                 // String Injected exception
      51: invokespecial #12                 // Method org/apache/hadoop/hbase/DoNotRetryIOException."<init>":(Ljava/lang/String;)V
      54: athrow
      55: new           #13                 // class java/io/IOException
      58: dup
      59: ldc           #11                 // String Injected exception
      61: invokespecial #14                 // Method java/io/IOException."<init>":(Ljava/lang/String;)V
      64: athrow
      65: aload_0
      66: aload_1
      67: invokespecial #15                 // Method org/apache/hadoop/hbase/regionserver/DelegatingKeyValueScanner.reseek:(Lorg/apache/hadoop/hbase/Cell;)Z
      70: ireturn
}
