Compiled from "TestAsyncNonMetaRegionLocator.java"
class org.apache.hadoop.hbase.client.TestAsyncNonMetaRegionLocator$2 implements org.apache.hadoop.hbase.client.RegionReplicaTestHelper$Locator {
  final org.apache.hadoop.hbase.client.TestAsyncNonMetaRegionLocator this$0;

  org.apache.hadoop.hbase.client.TestAsyncNonMetaRegionLocator$2(org.apache.hadoop.hbase.client.TestAsyncNonMetaRegionLocator);
    Code:
       0: aload_0
       1: aload_1
       2: putfield      #1                  // Field this$0:Lorg/apache/hadoop/hbase/client/TestAsyncNonMetaRegionLocator;
       5: aload_0
       6: invokespecial #2                  // Method java/lang/Object."<init>":()V
       9: return

  public void updateCachedLocationOnError(org.apache.hadoop.hbase.HRegionLocation, java.lang.Throwable) throws java.lang.Exception;
    Code:
       0: invokestatic  #3                  // Method org/apache/hadoop/hbase/client/TestAsyncNonMetaRegionLocator.access$200:()Lorg/apache/hadoop/hbase/client/AsyncNonMetaRegionLocator;
       3: aload_1
       4: aload_2
       5: invokevirtual #4                  // Method org/apache/hadoop/hbase/client/AsyncNonMetaRegionLocator.updateCachedLocationOnError:(Lorg/apache/hadoop/hbase/HRegionLocation;Ljava/lang/Throwable;)V
       8: return

  public org.apache.hadoop.hbase.RegionLocations getRegionLocations(org.apache.hadoop.hbase.TableName, int, boolean) throws java.lang.Exception;
    Code:
       0: invokestatic  #3                  // Method org/apache/hadoop/hbase/client/TestAsyncNonMetaRegionLocator.access$200:()Lorg/apache/hadoop/hbase/client/AsyncNonMetaRegionLocator;
       3: aload_1
       4: getstatic     #5                  // Field org/apache/hadoop/hbase/HConstants.EMPTY_START_ROW:[B
       7: iload_2
       8: getstatic     #6                  // Field org/apache/hadoop/hbase/client/RegionLocateType.CURRENT:Lorg/apache/hadoop/hbase/client/RegionLocateType;
      11: iload_3
      12: invokevirtual #7                  // Method org/apache/hadoop/hbase/client/AsyncNonMetaRegionLocator.getRegionLocations:(Lorg/apache/hadoop/hbase/TableName;[BILorg/apache/hadoop/hbase/client/RegionLocateType;Z)Ljava/util/concurrent/CompletableFuture;
      15: invokevirtual #8                  // Method java/util/concurrent/CompletableFuture.get:()Ljava/lang/Object;
      18: checkcast     #9                  // class org/apache/hadoop/hbase/RegionLocations
      21: areturn
}
