Compiled from "TestMasterRepairMode.java"
public class org.apache.hadoop.hbase.master.TestMasterRepairMode {
  public static final org.apache.hadoop.hbase.HBaseClassTestRule CLASS_RULE;

  public org.junit.rules.TestName name;

  public org.apache.hadoop.hbase.master.TestMasterRepairMode();
    Code:
       0: aload_0
       1: invokespecial #1                  // Method java/lang/Object."<init>":()V
       4: aload_0
       5: new           #2                  // class org/junit/rules/TestName
       8: dup
       9: invokespecial #3                  // Method org/junit/rules/TestName."<init>":()V
      12: putfield      #4                  // Field name:Lorg/junit/rules/TestName;
      15: return

  public void setUp() throws java.lang.Exception;
    Code:
       0: new           #5                  // class org/apache/hadoop/hbase/HBaseTestingUtility
       3: dup
       4: invokespecial #6                  // Method org/apache/hadoop/hbase/HBaseTestingUtility."<init>":()V
       7: putstatic     #7                  // Field TEST_UTIL:Lorg/apache/hadoop/hbase/HBaseTestingUtility;
      10: return

  public void tearDown() throws java.lang.Exception;
    Code:
       0: getstatic     #7                  // Field TEST_UTIL:Lorg/apache/hadoop/hbase/HBaseTestingUtility;
       3: invokevirtual #8                  // Method org/apache/hadoop/hbase/HBaseTestingUtility.shutdownMiniCluster:()V
       6: return

  public void testNewCluster() throws java.lang.Exception;
    Code:
       0: aload_0
       1: invokespecial #15                 // Method enableMaintenanceMode:()V
       4: getstatic     #7                  // Field TEST_UTIL:Lorg/apache/hadoop/hbase/HBaseTestingUtility;
       7: invokestatic  #16                 // Method org/apache/hadoop/hbase/StartMiniClusterOption.builder:()Lorg/apache/hadoop/hbase/StartMiniClusterOption$Builder;
      10: iconst_0
      11: invokevirtual #17                 // Method org/apache/hadoop/hbase/StartMiniClusterOption$Builder.numRegionServers:(I)Lorg/apache/hadoop/hbase/StartMiniClusterOption$Builder;
      14: iconst_3
      15: invokevirtual #18                 // Method org/apache/hadoop/hbase/StartMiniClusterOption$Builder.numDataNodes:(I)Lorg/apache/hadoop/hbase/StartMiniClusterOption$Builder;
      18: invokevirtual #19                 // Method org/apache/hadoop/hbase/StartMiniClusterOption$Builder.build:()Lorg/apache/hadoop/hbase/StartMiniClusterOption;
      21: invokevirtual #20                 // Method org/apache/hadoop/hbase/HBaseTestingUtility.startMiniCluster:(Lorg/apache/hadoop/hbase/StartMiniClusterOption;)Lorg/apache/hadoop/hbase/MiniHBaseCluster;
      24: pop
      25: getstatic     #7                  // Field TEST_UTIL:Lorg/apache/hadoop/hbase/HBaseTestingUtility;
      28: invokevirtual #21                 // Method org/apache/hadoop/hbase/HBaseTestingUtility.getConnection:()Lorg/apache/hadoop/hbase/client/Connection;
      31: astore_1
      32: aload_1
      33: invokeinterface #22,  1           // InterfaceMethod org/apache/hadoop/hbase/client/Connection.getAdmin:()Lorg/apache/hadoop/hbase/client/Admin;
      38: invokeinterface #23,  1           // InterfaceMethod org/apache/hadoop/hbase/client/Admin.isMasterInMaintenanceMode:()Z
      43: invokestatic  #24                 // Method org/junit/Assert.assertTrue:(Z)V
      46: aload_1
      47: getstatic     #25                 // Field org/apache/hadoop/hbase/TableName.META_TABLE_NAME:Lorg/apache/hadoop/hbase/TableName;
      50: invokeinterface #26,  2           // InterfaceMethod org/apache/hadoop/hbase/client/Connection.getTable:(Lorg/apache/hadoop/hbase/TableName;)Lorg/apache/hadoop/hbase/client/Table;
      55: astore_2
      56: aconst_null
      57: astore_3
      58: aload_2
      59: new           #27                 // class org/apache/hadoop/hbase/client/Scan
      62: dup
      63: invokespecial #28                 // Method org/apache/hadoop/hbase/client/Scan."<init>":()V
      66: invokeinterface #29,  2           // InterfaceMethod org/apache/hadoop/hbase/client/Table.getScanner:(Lorg/apache/hadoop/hbase/client/Scan;)Lorg/apache/hadoop/hbase/client/ResultScanner;
      71: astore        4
      73: aconst_null
      74: astore        5
      76: ldc           #30                 // String Could not read meta.
      78: aload         4
      80: invokeinterface #31,  1           // InterfaceMethod org/apache/hadoop/hbase/client/ResultScanner.next:()Lorg/apache/hadoop/hbase/client/Result;
      85: invokestatic  #32                 // Method org/junit/Assert.assertNotNull:(Ljava/lang/String;Ljava/lang/Object;)V
      88: aload         4
      90: ifnull        183
      93: aload         5
      95: ifnull        120
      98: aload         4
     100: invokeinterface #33,  1           // InterfaceMethod org/apache/hadoop/hbase/client/ResultScanner.close:()V
     105: goto          183
     108: astore        6
     110: aload         5
     112: aload         6
     114: invokevirtual #35                 // Method java/lang/Throwable.addSuppressed:(Ljava/lang/Throwable;)V
     117: goto          183
     120: aload         4
     122: invokeinterface #33,  1           // InterfaceMethod org/apache/hadoop/hbase/client/ResultScanner.close:()V
     127: goto          183
     130: astore        6
     132: aload         6
     134: astore        5
     136: aload         6
     138: athrow
     139: astore        7
     141: aload         4
     143: ifnull        180
     146: aload         5
     148: ifnull        173
     151: aload         4
     153: invokeinterface #33,  1           // InterfaceMethod org/apache/hadoop/hbase/client/ResultScanner.close:()V
     158: goto          180
     161: astore        8
     163: aload         5
     165: aload         8
     167: invokevirtual #35                 // Method java/lang/Throwable.addSuppressed:(Ljava/lang/Throwable;)V
     170: goto          180
     173: aload         4
     175: invokeinterface #33,  1           // InterfaceMethod org/apache/hadoop/hbase/client/ResultScanner.close:()V
     180: aload         7
     182: athrow
     183: aload_2
     184: ifnull        267
     187: aload_3
     188: ifnull        211
     191: aload_2
     192: invokeinterface #36,  1           // InterfaceMethod org/apache/hadoop/hbase/client/Table.close:()V
     197: goto          267
     200: astore        4
     202: aload_3
     203: aload         4
     205: invokevirtual #35                 // Method java/lang/Throwable.addSuppressed:(Ljava/lang/Throwable;)V
     208: goto          267
     211: aload_2
     212: invokeinterface #36,  1           // InterfaceMethod org/apache/hadoop/hbase/client/Table.close:()V
     217: goto          267
     220: astore        4
     222: aload         4
     224: astore_3
     225: aload         4
     227: athrow
     228: astore        9
     230: aload_2
     231: ifnull        264
     234: aload_3
     235: ifnull        258
     238: aload_2
     239: invokeinterface #36,  1           // InterfaceMethod org/apache/hadoop/hbase/client/Table.close:()V
     244: goto          264
     247: astore        10
     249: aload_3
     250: aload         10
     252: invokevirtual #35                 // Method java/lang/Throwable.addSuppressed:(Ljava/lang/Throwable;)V
     255: goto          264
     258: aload_2
     259: invokeinterface #36,  1           // InterfaceMethod org/apache/hadoop/hbase/client/Table.close:()V
     264: aload         9
     266: athrow
     267: return
    Exception table:
       from    to  target type
          98   105   108   Class java/lang/Throwable
          76    88   130   Class java/lang/Throwable
          76    88   139   any
         151   158   161   Class java/lang/Throwable
         130   141   139   any
         191   197   200   Class java/lang/Throwable
          58   183   220   Class java/lang/Throwable
          58   183   228   any
         238   244   247   Class java/lang/Throwable
         220   230   228   any

  public void testExistingCluster() throws java.lang.Exception;
    Code:
       0: aload_0
       1: getfield      #4                  // Field name:Lorg/junit/rules/TestName;
       4: invokevirtual #37                 // Method org/junit/rules/TestName.getMethodName:()Ljava/lang/String;
       7: invokestatic  #38                 // Method org/apache/hadoop/hbase/TableName.valueOf:(Ljava/lang/String;)Lorg/apache/hadoop/hbase/TableName;
      10: astore_1
      11: getstatic     #7                  // Field TEST_UTIL:Lorg/apache/hadoop/hbase/HBaseTestingUtility;
      14: invokevirtual #39                 // Method org/apache/hadoop/hbase/HBaseTestingUtility.startMiniCluster:()Lorg/apache/hadoop/hbase/MiniHBaseCluster;
      17: pop
      18: getstatic     #7                  // Field TEST_UTIL:Lorg/apache/hadoop/hbase/HBaseTestingUtility;
      21: aload_1
      22: getstatic     #40                 // Field FAMILYNAME:[B
      25: invokevirtual #41                 // Method org/apache/hadoop/hbase/HBaseTestingUtility.createTable:(Lorg/apache/hadoop/hbase/TableName;[B)Lorg/apache/hadoop/hbase/client/Table;
      28: astore_2
      29: new           #42                 // class org/apache/hadoop/hbase/client/Put
      32: dup
      33: ldc           #43                 // String r
      35: invokestatic  #44                 // Method org/apache/hadoop/hbase/util/Bytes.toBytes:(Ljava/lang/String;)[B
      38: invokespecial #45                 // Method org/apache/hadoop/hbase/client/Put."<init>":([B)V
      41: astore_3
      42: aload_3
      43: getstatic     #40                 // Field FAMILYNAME:[B
      46: ldc           #46                 // String c
      48: invokestatic  #44                 // Method org/apache/hadoop/hbase/util/Bytes.toBytes:(Ljava/lang/String;)[B
      51: iconst_0
      52: newarray       byte
      54: invokevirtual #47                 // Method org/apache/hadoop/hbase/client/Put.addColumn:([B[B[B)Lorg/apache/hadoop/hbase/client/Put;
      57: pop
      58: aload_2
      59: aload_3
      60: invokeinterface #48,  2           // InterfaceMethod org/apache/hadoop/hbase/client/Table.put:(Lorg/apache/hadoop/hbase/client/Put;)V
      65: getstatic     #7                  // Field TEST_UTIL:Lorg/apache/hadoop/hbase/HBaseTestingUtility;
      68: invokevirtual #49                 // Method org/apache/hadoop/hbase/HBaseTestingUtility.shutdownMiniHBaseCluster:()V
      71: getstatic     #50                 // Field LOG:Lorg/slf4j/Logger;
      74: ldc           #51                 // String Starting master-only
      76: invokeinterface #52,  2           // InterfaceMethod org/slf4j/Logger.info:(Ljava/lang/String;)V
      81: aload_0
      82: invokespecial #15                 // Method enableMaintenanceMode:()V
      85: getstatic     #7                  // Field TEST_UTIL:Lorg/apache/hadoop/hbase/HBaseTestingUtility;
      88: invokestatic  #16                 // Method org/apache/hadoop/hbase/StartMiniClusterOption.builder:()Lorg/apache/hadoop/hbase/StartMiniClusterOption$Builder;
      91: iconst_0
      92: invokevirtual #17                 // Method org/apache/hadoop/hbase/StartMiniClusterOption$Builder.numRegionServers:(I)Lorg/apache/hadoop/hbase/StartMiniClusterOption$Builder;
      95: iconst_0
      96: invokevirtual #53                 // Method org/apache/hadoop/hbase/StartMiniClusterOption$Builder.createRootDir:(Z)Lorg/apache/hadoop/hbase/StartMiniClusterOption$Builder;
      99: invokevirtual #19                 // Method org/apache/hadoop/hbase/StartMiniClusterOption$Builder.build:()Lorg/apache/hadoop/hbase/StartMiniClusterOption;
     102: invokevirtual #54                 // Method org/apache/hadoop/hbase/HBaseTestingUtility.startMiniHBaseCluster:(Lorg/apache/hadoop/hbase/StartMiniClusterOption;)Lorg/apache/hadoop/hbase/MiniHBaseCluster;
     105: pop
     106: getstatic     #7                  // Field TEST_UTIL:Lorg/apache/hadoop/hbase/HBaseTestingUtility;
     109: invokevirtual #21                 // Method org/apache/hadoop/hbase/HBaseTestingUtility.getConnection:()Lorg/apache/hadoop/hbase/client/Connection;
     112: astore        4
     114: aload         4
     116: invokeinterface #22,  1           // InterfaceMethod org/apache/hadoop/hbase/client/Connection.getAdmin:()Lorg/apache/hadoop/hbase/client/Admin;
     121: invokeinterface #23,  1           // InterfaceMethod org/apache/hadoop/hbase/client/Admin.isMasterInMaintenanceMode:()Z
     126: invokestatic  #24                 // Method org/junit/Assert.assertTrue:(Z)V
     129: aload         4
     131: getstatic     #25                 // Field org/apache/hadoop/hbase/TableName.META_TABLE_NAME:Lorg/apache/hadoop/hbase/TableName;
     134: invokeinterface #26,  2           // InterfaceMethod org/apache/hadoop/hbase/client/Connection.getTable:(Lorg/apache/hadoop/hbase/TableName;)Lorg/apache/hadoop/hbase/client/Table;
     139: astore        5
     141: aconst_null
     142: astore        6
     144: aload         5
     146: getstatic     #55                 // Field org/apache/hadoop/hbase/HConstants.TABLE_FAMILY:[B
     149: invokeinterface #56,  2           // InterfaceMethod org/apache/hadoop/hbase/client/Table.getScanner:([B)Lorg/apache/hadoop/hbase/client/ResultScanner;
     154: astore        7
     156: aconst_null
     157: astore        8
     159: aload         7
     161: invokeinterface #57,  1           // InterfaceMethod org/apache/hadoop/hbase/client/ResultScanner.spliterator:()Ljava/util/Spliterator;
     166: iconst_0
     167: invokestatic  #58                 // Method java/util/stream/StreamSupport.stream:(Ljava/util/Spliterator;Z)Ljava/util/stream/Stream;
     170: astore        9
     172: aconst_null
     173: astore        10
     175: ldc           #59                 // String Did not find user table records while reading hbase:meta
     177: aload         9
     179: aload_1
     180: invokedynamic #60,  0             // InvokeDynamic #0:test:(Lorg/apache/hadoop/hbase/TableName;)Ljava/util/function/Predicate;
     185: invokeinterface #61,  2           // InterfaceMethod java/util/stream/Stream.anyMatch:(Ljava/util/function/Predicate;)Z
     190: invokestatic  #62                 // Method org/junit/Assert.assertTrue:(Ljava/lang/String;Z)V
     193: aload         9
     195: ifnull        288
     198: aload         10
     200: ifnull        225
     203: aload         9
     205: invokeinterface #63,  1           // InterfaceMethod java/util/stream/Stream.close:()V
     210: goto          288
     213: astore        11
     215: aload         10
     217: aload         11
     219: invokevirtual #35                 // Method java/lang/Throwable.addSuppressed:(Ljava/lang/Throwable;)V
     222: goto          288
     225: aload         9
     227: invokeinterface #63,  1           // InterfaceMethod java/util/stream/Stream.close:()V
     232: goto          288
     235: astore        11
     237: aload         11
     239: astore        10
     241: aload         11
     243: athrow
     244: astore        12
     246: aload         9
     248: ifnull        285
     251: aload         10
     253: ifnull        278
     256: aload         9
     258: invokeinterface #63,  1           // InterfaceMethod java/util/stream/Stream.close:()V
     263: goto          285
     266: astore        13
     268: aload         10
     270: aload         13
     272: invokevirtual #35                 // Method java/lang/Throwable.addSuppressed:(Ljava/lang/Throwable;)V
     275: goto          285
     278: aload         9
     280: invokeinterface #63,  1           // InterfaceMethod java/util/stream/Stream.close:()V
     285: aload         12
     287: athrow
     288: aload         7
     290: ifnull        383
     293: aload         8
     295: ifnull        320
     298: aload         7
     300: invokeinterface #33,  1           // InterfaceMethod org/apache/hadoop/hbase/client/ResultScanner.close:()V
     305: goto          383
     308: astore        9
     310: aload         8
     312: aload         9
     314: invokevirtual #35                 // Method java/lang/Throwable.addSuppressed:(Ljava/lang/Throwable;)V
     317: goto          383
     320: aload         7
     322: invokeinterface #33,  1           // InterfaceMethod org/apache/hadoop/hbase/client/ResultScanner.close:()V
     327: goto          383
     330: astore        9
     332: aload         9
     334: astore        8
     336: aload         9
     338: athrow
     339: astore        14
     341: aload         7
     343: ifnull        380
     346: aload         8
     348: ifnull        373
     351: aload         7
     353: invokeinterface #33,  1           // InterfaceMethod org/apache/hadoop/hbase/client/ResultScanner.close:()V
     358: goto          380
     361: astore        15
     363: aload         8
     365: aload         15
     367: invokevirtual #35                 // Method java/lang/Throwable.addSuppressed:(Ljava/lang/Throwable;)V
     370: goto          380
     373: aload         7
     375: invokeinterface #33,  1           // InterfaceMethod org/apache/hadoop/hbase/client/ResultScanner.close:()V
     380: aload         14
     382: athrow
     383: aload         5
     385: ifnull        478
     388: aload         6
     390: ifnull        415
     393: aload         5
     395: invokeinterface #36,  1           // InterfaceMethod org/apache/hadoop/hbase/client/Table.close:()V
     400: goto          478
     403: astore        7
     405: aload         6
     407: aload         7
     409: invokevirtual #35                 // Method java/lang/Throwable.addSuppressed:(Ljava/lang/Throwable;)V
     412: goto          478
     415: aload         5
     417: invokeinterface #36,  1           // InterfaceMethod org/apache/hadoop/hbase/client/Table.close:()V
     422: goto          478
     425: astore        7
     427: aload         7
     429: astore        6
     431: aload         7
     433: athrow
     434: astore        16
     436: aload         5
     438: ifnull        475
     441: aload         6
     443: ifnull        468
     446: aload         5
     448: invokeinterface #36,  1           // InterfaceMethod org/apache/hadoop/hbase/client/Table.close:()V
     453: goto          475
     456: astore        17
     458: aload         6
     460: aload         17
     462: invokevirtual #35                 // Method java/lang/Throwable.addSuppressed:(Ljava/lang/Throwable;)V
     465: goto          475
     468: aload         5
     470: invokeinterface #36,  1           // InterfaceMethod org/apache/hadoop/hbase/client/Table.close:()V
     475: aload         16
     477: athrow
     478: aload         4
     480: aload_1
     481: invokeinterface #26,  2           // InterfaceMethod org/apache/hadoop/hbase/client/Connection.getTable:(Lorg/apache/hadoop/hbase/TableName;)Lorg/apache/hadoop/hbase/client/Table;
     486: astore        5
     488: aconst_null
     489: astore        6
     491: aload         5
     493: new           #27                 // class org/apache/hadoop/hbase/client/Scan
     496: dup
     497: invokespecial #28                 // Method org/apache/hadoop/hbase/client/Scan."<init>":()V
     500: invokeinterface #29,  2           // InterfaceMethod org/apache/hadoop/hbase/client/Table.getScanner:(Lorg/apache/hadoop/hbase/client/Scan;)Lorg/apache/hadoop/hbase/client/ResultScanner;
     505: astore        7
     507: aconst_null
     508: astore        8
     510: aload         7
     512: invokeinterface #31,  1           // InterfaceMethod org/apache/hadoop/hbase/client/ResultScanner.next:()Lorg/apache/hadoop/hbase/client/Result;
     517: pop
     518: ldc           #64                 // String Should not be able to access user-space tables in repair mode.
     520: invokestatic  #65                 // Method org/junit/Assert.fail:(Ljava/lang/String;)V
     523: aload         7
     525: ifnull        618
     528: aload         8
     530: ifnull        555
     533: aload         7
     535: invokeinterface #33,  1           // InterfaceMethod org/apache/hadoop/hbase/client/ResultScanner.close:()V
     540: goto          618
     543: astore        9
     545: aload         8
     547: aload         9
     549: invokevirtual #35                 // Method java/lang/Throwable.addSuppressed:(Ljava/lang/Throwable;)V
     552: goto          618
     555: aload         7
     557: invokeinterface #33,  1           // InterfaceMethod org/apache/hadoop/hbase/client/ResultScanner.close:()V
     562: goto          618
     565: astore        9
     567: aload         9
     569: astore        8
     571: aload         9
     573: athrow
     574: astore        18
     576: aload         7
     578: ifnull        615
     581: aload         8
     583: ifnull        608
     586: aload         7
     588: invokeinterface #33,  1           // InterfaceMethod org/apache/hadoop/hbase/client/ResultScanner.close:()V
     593: goto          615
     596: astore        19
     598: aload         8
     600: aload         19
     602: invokevirtual #35                 // Method java/lang/Throwable.addSuppressed:(Ljava/lang/Throwable;)V
     605: goto          615
     608: aload         7
     610: invokeinterface #33,  1           // InterfaceMethod org/apache/hadoop/hbase/client/ResultScanner.close:()V
     615: aload         18
     617: athrow
     618: aload         5
     620: ifnull        713
     623: aload         6
     625: ifnull        650
     628: aload         5
     630: invokeinterface #36,  1           // InterfaceMethod org/apache/hadoop/hbase/client/Table.close:()V
     635: goto          713
     638: astore        7
     640: aload         6
     642: aload         7
     644: invokevirtual #35                 // Method java/lang/Throwable.addSuppressed:(Ljava/lang/Throwable;)V
     647: goto          713
     650: aload         5
     652: invokeinterface #36,  1           // InterfaceMethod org/apache/hadoop/hbase/client/Table.close:()V
     657: goto          713
     660: astore        7
     662: aload         7
     664: astore        6
     666: aload         7
     668: athrow
     669: astore        20
     671: aload         5
     673: ifnull        710
     676: aload         6
     678: ifnull        703
     681: aload         5
     683: invokeinterface #36,  1           // InterfaceMethod org/apache/hadoop/hbase/client/Table.close:()V
     688: goto          710
     691: astore        21
     693: aload         6
     695: aload         21
     697: invokevirtual #35                 // Method java/lang/Throwable.addSuppressed:(Ljava/lang/Throwable;)V
     700: goto          710
     703: aload         5
     705: invokeinterface #36,  1           // InterfaceMethod org/apache/hadoop/hbase/client/Table.close:()V
     710: aload         20
     712: athrow
     713: goto          718
     716: astore        5
     718: return
    Exception table:
       from    to  target type
         203   210   213   Class java/lang/Throwable
         175   193   235   Class java/lang/Throwable
         175   193   244   any
         256   263   266   Class java/lang/Throwable
         235   246   244   any
         298   305   308   Class java/lang/Throwable
         159   288   330   Class java/lang/Throwable
         159   288   339   any
         351   358   361   Class java/lang/Throwable
         330   341   339   any
         393   400   403   Class java/lang/Throwable
         144   383   425   Class java/lang/Throwable
         144   383   434   any
         446   453   456   Class java/lang/Throwable
         425   436   434   any
         533   540   543   Class java/lang/Throwable
         510   523   565   Class java/lang/Throwable
         510   523   574   any
         586   593   596   Class java/lang/Throwable
         565   576   574   any
         628   635   638   Class java/lang/Throwable
         491   618   660   Class java/lang/Throwable
         491   618   669   any
         681   688   691   Class java/lang/Throwable
         660   671   669   any
         478   713   716   Class java/lang/Exception

  static {};
    Code:
       0: ldc           #70                 // class org/apache/hadoop/hbase/master/TestMasterRepairMode
       2: invokestatic  #71                 // Method org/apache/hadoop/hbase/HBaseClassTestRule.forClass:(Ljava/lang/Class;)Lorg/apache/hadoop/hbase/HBaseClassTestRule;
       5: putstatic     #72                 // Field CLASS_RULE:Lorg/apache/hadoop/hbase/HBaseClassTestRule;
       8: ldc           #70                 // class org/apache/hadoop/hbase/master/TestMasterRepairMode
      10: invokestatic  #73                 // Method org/slf4j/LoggerFactory.getLogger:(Ljava/lang/Class;)Lorg/slf4j/Logger;
      13: putstatic     #50                 // Field LOG:Lorg/slf4j/Logger;
      16: ldc           #74                 // String fam
      18: invokestatic  #44                 // Method org/apache/hadoop/hbase/util/Bytes.toBytes:(Ljava/lang/String;)[B
      21: putstatic     #40                 // Field FAMILYNAME:[B
      24: return
}
