Compiled from "TestRpcSchedulerFactory.java"
public class org.apache.hadoop.hbase.regionserver.TestRpcSchedulerFactory {
  public static final org.apache.hadoop.hbase.HBaseClassTestRule CLASS_RULE;

  public org.junit.rules.TestName testName;

  public org.apache.hadoop.hbase.regionserver.TestRpcSchedulerFactory();
    Code:
       0: aload_0
       1: invokespecial #1                  // Method java/lang/Object."<init>":()V
       4: aload_0
       5: new           #2                  // class org/junit/rules/TestName
       8: dup
       9: invokespecial #3                  // Method org/junit/rules/TestName."<init>":()V
      12: putfield      #4                  // Field testName:Lorg/junit/rules/TestName;
      15: return

  public void setUp() throws java.lang.Exception;
    Code:
       0: aload_0
       1: invokestatic  #5                  // Method org/apache/hadoop/hbase/HBaseConfiguration.create:()Lorg/apache/hadoop/conf/Configuration;
       4: putfield      #6                  // Field conf:Lorg/apache/hadoop/conf/Configuration;
       7: return

  public void testRWQ();
    Code:
       0: aload_0
       1: getfield      #6                  // Field conf:Lorg/apache/hadoop/conf/Configuration;
       4: ldc           #8                  // String hbase.ipc.server.callqueue.read.ratio
       6: ldc2_w        #9                  // double 0.5d
       9: invokevirtual #11                 // Method org/apache/hadoop/conf/Configuration.setDouble:(Ljava/lang/String;D)V
      12: aload_0
      13: getfield      #6                  // Field conf:Lorg/apache/hadoop/conf/Configuration;
      16: ldc           #13                 // String hbase.ipc.server.callqueue.handler.factor
      18: ldc2_w        #9                  // double 0.5d
      21: invokevirtual #11                 // Method org/apache/hadoop/conf/Configuration.setDouble:(Ljava/lang/String;D)V
      24: aload_0
      25: getfield      #6                  // Field conf:Lorg/apache/hadoop/conf/Configuration;
      28: ldc           #14                 // String hbase.ipc.server.callqueue.scan.ratio
      30: ldc2_w        #9                  // double 0.5d
      33: invokevirtual #11                 // Method org/apache/hadoop/conf/Configuration.setDouble:(Ljava/lang/String;D)V
      36: new           #15                 // class org/apache/hadoop/hbase/regionserver/SimpleRpcSchedulerFactory
      39: dup
      40: invokespecial #16                 // Method org/apache/hadoop/hbase/regionserver/SimpleRpcSchedulerFactory."<init>":()V
      43: astore_1
      44: aload_1
      45: aload_0
      46: getfield      #6                  // Field conf:Lorg/apache/hadoop/conf/Configuration;
      49: aconst_null
      50: aconst_null
      51: invokeinterface #17,  4           // InterfaceMethod org/apache/hadoop/hbase/regionserver/RpcSchedulerFactory.create:(Lorg/apache/hadoop/conf/Configuration;Lorg/apache/hadoop/hbase/ipc/PriorityFunction;Lorg/apache/hadoop/hbase/Abortable;)Lorg/apache/hadoop/hbase/ipc/RpcScheduler;
      56: astore_2
      57: aload_2
      58: invokevirtual #18                 // Method java/lang/Object.getClass:()Ljava/lang/Class;
      61: ldc           #19                 // class org/apache/hadoop/hbase/ipc/SimpleRpcScheduler
      63: invokevirtual #20                 // Method java/lang/Object.equals:(Ljava/lang/Object;)Z
      66: invokestatic  #21                 // Method org/junit/Assert.assertTrue:(Z)V
      69: return

  public void testFifo();
    Code:
       0: new           #22                 // class org/apache/hadoop/hbase/regionserver/FifoRpcSchedulerFactory
       3: dup
       4: invokespecial #23                 // Method org/apache/hadoop/hbase/regionserver/FifoRpcSchedulerFactory."<init>":()V
       7: astore_1
       8: aload_1
       9: aload_0
      10: getfield      #6                  // Field conf:Lorg/apache/hadoop/conf/Configuration;
      13: aconst_null
      14: aconst_null
      15: invokeinterface #17,  4           // InterfaceMethod org/apache/hadoop/hbase/regionserver/RpcSchedulerFactory.create:(Lorg/apache/hadoop/conf/Configuration;Lorg/apache/hadoop/hbase/ipc/PriorityFunction;Lorg/apache/hadoop/hbase/Abortable;)Lorg/apache/hadoop/hbase/ipc/RpcScheduler;
      20: astore_2
      21: aload_2
      22: invokevirtual #18                 // Method java/lang/Object.getClass:()Ljava/lang/Class;
      25: ldc           #24                 // class org/apache/hadoop/hbase/ipc/FifoRpcScheduler
      27: invokevirtual #20                 // Method java/lang/Object.equals:(Ljava/lang/Object;)Z
      30: invokestatic  #21                 // Method org/junit/Assert.assertTrue:(Z)V
      33: return

  static {};
    Code:
       0: ldc           #25                 // class org/apache/hadoop/hbase/regionserver/TestRpcSchedulerFactory
       2: invokestatic  #26                 // Method org/apache/hadoop/hbase/HBaseClassTestRule.forClass:(Ljava/lang/Class;)Lorg/apache/hadoop/hbase/HBaseClassTestRule;
       5: putstatic     #27                 // Field CLASS_RULE:Lorg/apache/hadoop/hbase/HBaseClassTestRule;
       8: return
}
