Compiled from "TestHttpRequestLogAppender.java"
public class org.apache.hadoop.hbase.http.TestHttpRequestLogAppender {
  public static final org.apache.hadoop.hbase.HBaseClassTestRule CLASS_RULE;

  public org.apache.hadoop.hbase.http.TestHttpRequestLogAppender();
    Code:
       0: aload_0
       1: invokespecial #1                  // Method java/lang/Object."<init>":()V
       4: return

  public void testParameterPropagation();
    Code:
       0: new           #2                  // class org/apache/hadoop/hbase/http/HttpRequestLogAppender
       3: dup
       4: invokespecial #3                  // Method org/apache/hadoop/hbase/http/HttpRequestLogAppender."<init>":()V
       7: astore_1
       8: aload_1
       9: ldc           #4                  // String jetty-namenode-yyyy_mm_dd.log
      11: invokevirtual #5                  // Method org/apache/hadoop/hbase/http/HttpRequestLogAppender.setFilename:(Ljava/lang/String;)V
      14: aload_1
      15: bipush        17
      17: invokevirtual #6                  // Method org/apache/hadoop/hbase/http/HttpRequestLogAppender.setRetainDays:(I)V
      20: ldc           #7                  // String Filename mismatch
      22: ldc           #4                  // String jetty-namenode-yyyy_mm_dd.log
      24: aload_1
      25: invokevirtual #8                  // Method org/apache/hadoop/hbase/http/HttpRequestLogAppender.getFilename:()Ljava/lang/String;
      28: invokestatic  #9                  // Method org/junit/Assert.assertEquals:(Ljava/lang/String;Ljava/lang/Object;Ljava/lang/Object;)V
      31: ldc           #10                 // String Retain days mismatch
      33: ldc2_w        #11                 // long 17l
      36: aload_1
      37: invokevirtual #13                 // Method org/apache/hadoop/hbase/http/HttpRequestLogAppender.getRetainDays:()I
      40: i2l
      41: invokestatic  #14                 // Method org/junit/Assert.assertEquals:(Ljava/lang/String;JJ)V
      44: return

  static {};
    Code:
       0: ldc           #15                 // class org/apache/hadoop/hbase/http/TestHttpRequestLogAppender
       2: invokestatic  #16                 // Method org/apache/hadoop/hbase/HBaseClassTestRule.forClass:(Ljava/lang/Class;)Lorg/apache/hadoop/hbase/HBaseClassTestRule;
       5: putstatic     #17                 // Field CLASS_RULE:Lorg/apache/hadoop/hbase/HBaseClassTestRule;
       8: return
}
