Compiled from "TestByteBufferArray.java"
public class org.apache.hadoop.hbase.util.TestByteBufferArray {
  public static final org.apache.hadoop.hbase.HBaseClassTestRule CLASS_RULE;

  public org.apache.hadoop.hbase.util.TestByteBufferArray();
    Code:
       0: aload_0
       1: invokespecial #1                  // Method java/lang/Object."<init>":()V
       4: return

  public void testAsSubBufferWhenEndOffsetLandInLastBuffer() throws java.lang.Exception;
    Code:
       0: ldc           #2                  // int 4194304
       2: istore_1
       3: new           #3                  // class org/apache/hadoop/hbase/util/TestByteBufferArray$1
       6: dup
       7: aload_0
       8: invokespecial #4                  // Method org/apache/hadoop/hbase/util/TestByteBufferArray$1."<init>":(Lorg/apache/hadoop/hbase/util/TestByteBufferArray;)V
      11: astore_2
      12: new           #5                  // class org/apache/hadoop/hbase/util/ByteBufferArray
      15: dup
      16: iload_1
      17: i2l
      18: aload_2
      19: invokespecial #6                  // Method org/apache/hadoop/hbase/util/ByteBufferArray."<init>":(JLorg/apache/hadoop/hbase/util/ByteBufferAllocator;)V
      22: astore_3
      23: aload_3
      24: lconst_0
      25: iload_1
      26: invokevirtual #7                  // Method org/apache/hadoop/hbase/util/ByteBufferArray.asSubByteBuff:(JI)Lorg/apache/hadoop/hbase/nio/ByteBuff;
      29: astore        4
      31: aload         4
      33: iload_1
      34: iconst_1
      35: isub
      36: invokevirtual #8                  // Method org/apache/hadoop/hbase/nio/ByteBuff.position:(I)Lorg/apache/hadoop/hbase/nio/ByteBuff;
      39: pop
      40: aload         4
      42: invokevirtual #9                  // Method org/apache/hadoop/hbase/nio/ByteBuff.hasRemaining:()Z
      45: invokestatic  #10                 // Method org/junit/Assert.assertTrue:(Z)V
      48: aload         4
      50: invokevirtual #11                 // Method org/apache/hadoop/hbase/nio/ByteBuff.get:()B
      53: pop
      54: aload         4
      56: invokevirtual #9                  // Method org/apache/hadoop/hbase/nio/ByteBuff.hasRemaining:()Z
      59: invokestatic  #12                 // Method org/junit/Assert.assertFalse:(Z)V
      62: return

  public void testByteBufferCreation() throws java.lang.Exception;
    Code:
       0: ldc           #13                 // int 490907010
       2: istore_1
       3: new           #14                 // class org/apache/hadoop/hbase/util/TestByteBufferArray$2
       6: dup
       7: aload_0
       8: invokespecial #15                 // Method org/apache/hadoop/hbase/util/TestByteBufferArray$2."<init>":(Lorg/apache/hadoop/hbase/util/TestByteBufferArray;)V
      11: astore_2
      12: new           #5                  // class org/apache/hadoop/hbase/util/ByteBufferArray
      15: dup
      16: iload_1
      17: i2l
      18: aload_2
      19: invokespecial #6                  // Method org/apache/hadoop/hbase/util/ByteBufferArray."<init>":(JLorg/apache/hadoop/hbase/util/ByteBufferAllocator;)V
      22: astore_3
      23: ldc2_w        #16                 // long 119l
      26: aload_3
      27: getfield      #18                 // Field org/apache/hadoop/hbase/util/ByteBufferArray.buffers:[Ljava/nio/ByteBuffer;
      30: arraylength
      31: i2l
      32: invokestatic  #19                 // Method org/junit/Assert.assertEquals:(JJ)V
      35: iconst_0
      36: istore        4
      38: iload         4
      40: aload_3
      41: getfield      #18                 // Field org/apache/hadoop/hbase/util/ByteBufferArray.buffers:[Ljava/nio/ByteBuffer;
      44: arraylength
      45: if_icmpge     101
      48: iload         4
      50: aload_3
      51: getfield      #18                 // Field org/apache/hadoop/hbase/util/ByteBufferArray.buffers:[Ljava/nio/ByteBuffer;
      54: arraylength
      55: iconst_1
      56: isub
      57: if_icmpne     78
      60: lconst_0
      61: aload_3
      62: getfield      #18                 // Field org/apache/hadoop/hbase/util/ByteBufferArray.buffers:[Ljava/nio/ByteBuffer;
      65: iload         4
      67: aaload
      68: invokevirtual #20                 // Method java/nio/ByteBuffer.capacity:()I
      71: i2l
      72: invokestatic  #19                 // Method org/junit/Assert.assertEquals:(JJ)V
      75: goto          95
      78: ldc2_w        #21                 // long 4194304l
      81: aload_3
      82: getfield      #18                 // Field org/apache/hadoop/hbase/util/ByteBufferArray.buffers:[Ljava/nio/ByteBuffer;
      85: iload         4
      87: aaload
      88: invokevirtual #20                 // Method java/nio/ByteBuffer.capacity:()I
      91: i2l
      92: invokestatic  #19                 // Method org/junit/Assert.assertEquals:(JJ)V
      95: iinc          4, 1
      98: goto          38
     101: return

  public void testByteBufferCreation1() throws java.lang.Exception;
    Code:
       0: new           #23                 // class org/apache/hadoop/hbase/util/TestByteBufferArray$3
       3: dup
       4: aload_0
       5: invokespecial #24                 // Method org/apache/hadoop/hbase/util/TestByteBufferArray$3."<init>":(Lorg/apache/hadoop/hbase/util/TestByteBufferArray;)V
       8: astore_1
       9: new           #25                 // class org/apache/hadoop/hbase/util/TestByteBufferArray$DummyByteBufferArray
      12: dup
      13: ldc2_w        #26                 // long 7340032l
      16: aload_1
      17: invokespecial #28                 // Method org/apache/hadoop/hbase/util/TestByteBufferArray$DummyByteBufferArray."<init>":(JLorg/apache/hadoop/hbase/util/ByteBufferAllocator;)V
      20: astore_2
      21: aload_2
      22: bipush        25
      24: putfield      #29                 // Field org/apache/hadoop/hbase/util/ByteBufferArray.bufferCount:I
      27: aload_2
      28: aload_2
      29: getfield      #29                 // Field org/apache/hadoop/hbase/util/ByteBufferArray.bufferCount:I
      32: iconst_1
      33: iadd
      34: anewarray     #30                 // class java/nio/ByteBuffer
      37: putfield      #18                 // Field org/apache/hadoop/hbase/util/ByteBufferArray.buffers:[Ljava/nio/ByteBuffer;
      40: aload_2
      41: aload_1
      42: invokevirtual #31                 // Method org/apache/hadoop/hbase/util/ByteBufferArray.createBuffers:(Lorg/apache/hadoop/hbase/util/ByteBufferAllocator;)V
      45: iconst_0
      46: istore_3
      47: iload_3
      48: aload_2
      49: getfield      #18                 // Field org/apache/hadoop/hbase/util/ByteBufferArray.buffers:[Ljava/nio/ByteBuffer;
      52: arraylength
      53: if_icmpge     106
      56: iload_3
      57: aload_2
      58: getfield      #18                 // Field org/apache/hadoop/hbase/util/ByteBufferArray.buffers:[Ljava/nio/ByteBuffer;
      61: arraylength
      62: iconst_1
      63: isub
      64: if_icmpne     84
      67: lconst_0
      68: aload_2
      69: getfield      #18                 // Field org/apache/hadoop/hbase/util/ByteBufferArray.buffers:[Ljava/nio/ByteBuffer;
      72: iload_3
      73: aaload
      74: invokevirtual #20                 // Method java/nio/ByteBuffer.capacity:()I
      77: i2l
      78: invokestatic  #19                 // Method org/junit/Assert.assertEquals:(JJ)V
      81: goto          100
      84: ldc2_w        #32                 // long 458752l
      87: aload_2
      88: getfield      #18                 // Field org/apache/hadoop/hbase/util/ByteBufferArray.buffers:[Ljava/nio/ByteBuffer;
      91: iload_3
      92: aaload
      93: invokevirtual #20                 // Method java/nio/ByteBuffer.capacity:()I
      96: i2l
      97: invokestatic  #19                 // Method org/junit/Assert.assertEquals:(JJ)V
     100: iinc          3, 1
     103: goto          47
     106: return

  static {};
    Code:
       0: ldc           #34                 // class org/apache/hadoop/hbase/util/TestByteBufferArray
       2: invokestatic  #35                 // Method org/apache/hadoop/hbase/HBaseClassTestRule.forClass:(Ljava/lang/Class;)Lorg/apache/hadoop/hbase/HBaseClassTestRule;
       5: putstatic     #36                 // Field CLASS_RULE:Lorg/apache/hadoop/hbase/HBaseClassTestRule;
       8: return
}
