Compiled from "TestClientScannerRPCTimeout.java"
class org.apache.hadoop.hbase.client.TestClientScannerRPCTimeout$RSRpcServicesWithScanTimeout extends org.apache.hadoop.hbase.regionserver.RSRpcServices {
  public org.apache.hadoop.hbase.client.TestClientScannerRPCTimeout$RSRpcServicesWithScanTimeout(org.apache.hadoop.hbase.regionserver.HRegionServer) throws java.io.IOException;
    Code:
       0: aload_0
       1: aload_1
       2: invokespecial #5                  // Method org/apache/hadoop/hbase/regionserver/RSRpcServices."<init>":(Lorg/apache/hadoop/hbase/regionserver/HRegionServer;)V
       5: return

  public org.apache.hadoop.hbase.shaded.protobuf.generated.ClientProtos$ScanResponse scan(org.apache.hbase.thirdparty.com.google.protobuf.RpcController, org.apache.hadoop.hbase.shaded.protobuf.generated.ClientProtos$ScanRequest) throws org.apache.hbase.thirdparty.com.google.protobuf.ServiceException;
    Code:
       0: aload_2
       1: invokevirtual #6                  // Method org/apache/hadoop/hbase/shaded/protobuf/generated/ClientProtos$ScanRequest.hasScannerId:()Z
       4: ifeq          98
       7: aload_0
       8: aload_1
       9: aload_2
      10: invokespecial #7                  // Method org/apache/hadoop/hbase/regionserver/RSRpcServices.scan:(Lorg/apache/hbase/thirdparty/com/google/protobuf/RpcController;Lorg/apache/hadoop/hbase/shaded/protobuf/generated/ClientProtos$ScanRequest;)Lorg/apache/hadoop/hbase/shaded/protobuf/generated/ClientProtos$ScanResponse;
      13: astore_3
      14: aload_0
      15: getfield      #8                  // Field tableScannerId:J
      18: aload_2
      19: invokevirtual #9                  // Method org/apache/hadoop/hbase/shaded/protobuf/generated/ClientProtos$ScanRequest.getScannerId:()J
      22: lcmp
      23: ifne          96
      26: getstatic     #3                  // Field sleepAlways:Z
      29: ifne          50
      32: aload_0
      33: getfield      #10                 // Field slept:Z
      36: ifne          96
      39: getstatic     #4                  // Field seqNoToSleepOn:J
      42: aload_2
      43: invokevirtual #11                 // Method org/apache/hadoop/hbase/shaded/protobuf/generated/ClientProtos$ScanRequest.getNextCallSeq:()J
      46: lcmp
      47: ifne          96
      50: getstatic     #12                 // Field LOG:Lorg/slf4j/Logger;
      53: ldc           #13                 // String SLEEPING 2500
      55: invokeinterface #14,  2           // InterfaceMethod org/slf4j/Logger.info:(Ljava/lang/String;)V
      60: ldc2_w        #15                 // long 2500l
      63: invokestatic  #17                 // Method java/lang/Thread.sleep:(J)V
      66: goto          71
      69: astore        4
      71: aload_0
      72: iconst_1
      73: putfield      #10                 // Field slept:Z
      76: getstatic     #2                  // Field tryNumber:I
      79: iconst_1
      80: iadd
      81: putstatic     #2                  // Field tryNumber:I
      84: getstatic     #2                  // Field tryNumber:I
      87: bipush        6
      89: if_icmple     96
      92: iconst_0
      93: putstatic     #3                  // Field sleepAlways:Z
      96: aload_3
      97: areturn
      98: aload_0
      99: aload_1
     100: aload_2
     101: invokespecial #7                  // Method org/apache/hadoop/hbase/regionserver/RSRpcServices.scan:(Lorg/apache/hbase/thirdparty/com/google/protobuf/RpcController;Lorg/apache/hadoop/hbase/shaded/protobuf/generated/ClientProtos$ScanRequest;)Lorg/apache/hadoop/hbase/shaded/protobuf/generated/ClientProtos$ScanResponse;
     104: astore_3
     105: aload_2
     106: invokevirtual #19                 // Method org/apache/hadoop/hbase/shaded/protobuf/generated/ClientProtos$ScanRequest.getRegion:()Lorg/apache/hadoop/hbase/shaded/protobuf/generated/HBaseProtos$RegionSpecifier;
     109: invokevirtual #20                 // Method org/apache/hadoop/hbase/shaded/protobuf/generated/HBaseProtos$RegionSpecifier.getValue:()Lorg/apache/hbase/thirdparty/com/google/protobuf/ByteString;
     112: invokevirtual #21                 // Method org/apache/hbase/thirdparty/com/google/protobuf/ByteString.toByteArray:()[B
     115: invokestatic  #22                 // Method org/apache/hadoop/hbase/util/Bytes.toString:([B)Ljava/lang/String;
     118: astore        4
     120: aload         4
     122: getstatic     #23                 // Field org/apache/hadoop/hbase/TableName.META_TABLE_NAME:Lorg/apache/hadoop/hbase/TableName;
     125: invokevirtual #24                 // Method org/apache/hadoop/hbase/TableName.getNameAsString:()Ljava/lang/String;
     128: invokevirtual #25                 // Method java/lang/String.contains:(Ljava/lang/CharSequence;)Z
     131: ifne          142
     134: aload_0
     135: aload_3
     136: invokevirtual #26                 // Method org/apache/hadoop/hbase/shaded/protobuf/generated/ClientProtos$ScanResponse.getScannerId:()J
     139: putfield      #8                  // Field tableScannerId:J
     142: aload_3
     143: areturn
    Exception table:
       from    to  target type
          50    66    69   Class java/lang/InterruptedException

  static long access$002(long);
    Code:
       0: lload_0
       1: dup2
       2: putstatic     #4                  // Field seqNoToSleepOn:J
       5: lreturn

  static boolean access$102(boolean);
    Code:
       0: iload_0
       1: dup
       2: putstatic     #3                  // Field sleepAlways:Z
       5: ireturn

  static int access$202(int);
    Code:
       0: iload_0
       1: dup
       2: putstatic     #2                  // Field tryNumber:I
       5: ireturn

  static int access$200();
    Code:
       0: getstatic     #2                  // Field tryNumber:I
       3: ireturn

  static {};
    Code:
       0: ldc2_w        #27                 // long -1l
       3: putstatic     #4                  // Field seqNoToSleepOn:J
       6: iconst_0
       7: putstatic     #3                  // Field sleepAlways:Z
      10: iconst_0
      11: putstatic     #2                  // Field tryNumber:I
      14: return
}
