Compiled from "TestWeakObjectPool.java"
public class org.apache.hadoop.hbase.util.TestWeakObjectPool {
  public static final org.apache.hadoop.hbase.HBaseClassTestRule CLASS_RULE;

  org.apache.hadoop.hbase.util.ObjectPool<java.lang.String, java.lang.Object> pool;

  public org.apache.hadoop.hbase.util.TestWeakObjectPool();
    Code:
       0: aload_0
       1: invokespecial #1                  // Method java/lang/Object."<init>":()V
       4: return

  public void setUp();
    Code:
       0: aload_0
       1: new           #2                  // class org/apache/hadoop/hbase/util/WeakObjectPool
       4: dup
       5: new           #3                  // class org/apache/hadoop/hbase/util/TestWeakObjectPool$1
       8: dup
       9: aload_0
      10: invokespecial #4                  // Method org/apache/hadoop/hbase/util/TestWeakObjectPool$1."<init>":(Lorg/apache/hadoop/hbase/util/TestWeakObjectPool;)V
      13: invokespecial #5                  // Method org/apache/hadoop/hbase/util/WeakObjectPool."<init>":(Lorg/apache/hadoop/hbase/util/ObjectPool$ObjectFactory;)V
      16: putfield      #6                  // Field pool:Lorg/apache/hadoop/hbase/util/ObjectPool;
      19: return

  public void testKeys();
    Code:
       0: aload_0
       1: getfield      #6                  // Field pool:Lorg/apache/hadoop/hbase/util/ObjectPool;
       4: ldc           #7                  // String a
       6: invokevirtual #8                  // Method org/apache/hadoop/hbase/util/ObjectPool.get:(Ljava/lang/Object;)Ljava/lang/Object;
       9: astore_1
      10: aload_0
      11: getfield      #6                  // Field pool:Lorg/apache/hadoop/hbase/util/ObjectPool;
      14: new           #9                  // class java/lang/String
      17: dup
      18: ldc           #7                  // String a
      20: invokespecial #10                 // Method java/lang/String."<init>":(Ljava/lang/String;)V
      23: invokevirtual #8                  // Method org/apache/hadoop/hbase/util/ObjectPool.get:(Ljava/lang/Object;)Ljava/lang/Object;
      26: astore_2
      27: aload_1
      28: aload_2
      29: invokestatic  #11                 // Method org/junit/Assert.assertSame:(Ljava/lang/Object;Ljava/lang/Object;)V
      32: aload_0
      33: getfield      #6                  // Field pool:Lorg/apache/hadoop/hbase/util/ObjectPool;
      36: ldc           #12                 // String b
      38: invokevirtual #8                  // Method org/apache/hadoop/hbase/util/ObjectPool.get:(Ljava/lang/Object;)Ljava/lang/Object;
      41: astore_3
      42: aload_1
      43: aload_3
      44: invokestatic  #13                 // Method org/junit/Assert.assertNotSame:(Ljava/lang/Object;Ljava/lang/Object;)V
      47: return

  public void testWeakReference() throws java.lang.Exception;
    Code:
       0: aload_0
       1: getfield      #6                  // Field pool:Lorg/apache/hadoop/hbase/util/ObjectPool;
       4: ldc           #7                  // String a
       6: invokevirtual #8                  // Method org/apache/hadoop/hbase/util/ObjectPool.get:(Ljava/lang/Object;)Ljava/lang/Object;
       9: astore_1
      10: aload_1
      11: invokestatic  #14                 // Method java/lang/System.identityHashCode:(Ljava/lang/Object;)I
      14: istore_2
      15: invokestatic  #15                 // Method java/lang/System.gc:()V
      18: invokestatic  #15                 // Method java/lang/System.gc:()V
      21: invokestatic  #15                 // Method java/lang/System.gc:()V
      24: ldc2_w        #16                 // long 10l
      27: invokestatic  #18                 // Method java/lang/Thread.sleep:(J)V
      30: aload_0
      31: getfield      #6                  // Field pool:Lorg/apache/hadoop/hbase/util/ObjectPool;
      34: invokevirtual #19                 // Method org/apache/hadoop/hbase/util/ObjectPool.purge:()V
      37: lconst_1
      38: aload_0
      39: getfield      #6                  // Field pool:Lorg/apache/hadoop/hbase/util/ObjectPool;
      42: invokevirtual #20                 // Method org/apache/hadoop/hbase/util/ObjectPool.size:()I
      45: i2l
      46: invokestatic  #21                 // Method org/junit/Assert.assertEquals:(JJ)V
      49: aload_0
      50: getfield      #6                  // Field pool:Lorg/apache/hadoop/hbase/util/ObjectPool;
      53: ldc           #7                  // String a
      55: invokevirtual #8                  // Method org/apache/hadoop/hbase/util/ObjectPool.get:(Ljava/lang/Object;)Ljava/lang/Object;
      58: astore_3
      59: aload_1
      60: aload_3
      61: invokestatic  #11                 // Method org/junit/Assert.assertSame:(Ljava/lang/Object;Ljava/lang/Object;)V
      64: aconst_null
      65: astore_1
      66: aconst_null
      67: astore_3
      68: invokestatic  #15                 // Method java/lang/System.gc:()V
      71: invokestatic  #15                 // Method java/lang/System.gc:()V
      74: invokestatic  #15                 // Method java/lang/System.gc:()V
      77: ldc2_w        #16                 // long 10l
      80: invokestatic  #18                 // Method java/lang/Thread.sleep:(J)V
      83: aload_0
      84: getfield      #6                  // Field pool:Lorg/apache/hadoop/hbase/util/ObjectPool;
      87: invokevirtual #19                 // Method org/apache/hadoop/hbase/util/ObjectPool.purge:()V
      90: lconst_0
      91: aload_0
      92: getfield      #6                  // Field pool:Lorg/apache/hadoop/hbase/util/ObjectPool;
      95: invokevirtual #20                 // Method org/apache/hadoop/hbase/util/ObjectPool.size:()I
      98: i2l
      99: invokestatic  #21                 // Method org/junit/Assert.assertEquals:(JJ)V
     102: aload_0
     103: getfield      #6                  // Field pool:Lorg/apache/hadoop/hbase/util/ObjectPool;
     106: ldc           #7                  // String a
     108: invokevirtual #8                  // Method org/apache/hadoop/hbase/util/ObjectPool.get:(Ljava/lang/Object;)Ljava/lang/Object;
     111: astore        4
     113: iload_2
     114: i2l
     115: aload         4
     117: invokestatic  #14                 // Method java/lang/System.identityHashCode:(Ljava/lang/Object;)I
     120: i2l
     121: invokestatic  #22                 // Method org/junit/Assert.assertNotEquals:(JJ)V
     124: return

  public void testCongestion() throws java.lang.Exception;
    Code:
       0: bipush        100
       2: istore_1
       3: new           #23                 // class java/util/concurrent/atomic/AtomicBoolean
       6: dup
       7: invokespecial #24                 // Method java/util/concurrent/atomic/AtomicBoolean."<init>":()V
      10: astore_2
      11: new           #25                 // class java/util/concurrent/atomic/AtomicReference
      14: dup
      15: invokespecial #26                 // Method java/util/concurrent/atomic/AtomicReference."<init>":()V
      18: astore_3
      19: new           #27                 // class java/util/concurrent/CountDownLatch
      22: dup
      23: bipush        100
      25: invokespecial #28                 // Method java/util/concurrent/CountDownLatch."<init>":(I)V
      28: astore        4
      30: new           #27                 // class java/util/concurrent/CountDownLatch
      33: dup
      34: iconst_1
      35: invokespecial #28                 // Method java/util/concurrent/CountDownLatch."<init>":(I)V
      38: astore        5
      40: new           #27                 // class java/util/concurrent/CountDownLatch
      43: dup
      44: bipush        100
      46: invokespecial #28                 // Method java/util/concurrent/CountDownLatch."<init>":(I)V
      49: astore        6
      51: iconst_0
      52: istore        7
      54: iload         7
      56: bipush        100
      58: if_icmpge     86
      61: new           #29                 // class org/apache/hadoop/hbase/util/TestWeakObjectPool$2
      64: dup
      65: aload_0
      66: aload         4
      68: aload         5
      70: aload_3
      71: aload_2
      72: aload         6
      74: invokespecial #30                 // Method org/apache/hadoop/hbase/util/TestWeakObjectPool$2."<init>":(Lorg/apache/hadoop/hbase/util/TestWeakObjectPool;Ljava/util/concurrent/CountDownLatch;Ljava/util/concurrent/CountDownLatch;Ljava/util/concurrent/atomic/AtomicReference;Ljava/util/concurrent/atomic/AtomicBoolean;Ljava/util/concurrent/CountDownLatch;)V
      77: invokevirtual #31                 // Method org/apache/hadoop/hbase/util/TestWeakObjectPool$2.start:()V
      80: iinc          7, 1
      83: goto          54
      86: aload         4
      88: invokevirtual #32                 // Method java/util/concurrent/CountDownLatch.await:()V
      91: aload         5
      93: invokevirtual #33                 // Method java/util/concurrent/CountDownLatch.countDown:()V
      96: aload         6
      98: invokevirtual #32                 // Method java/util/concurrent/CountDownLatch.await:()V
     101: aload_2
     102: invokevirtual #34                 // Method java/util/concurrent/atomic/AtomicBoolean.get:()Z
     105: ifeq          111
     108: invokestatic  #35                 // Method org/junit/Assert.fail:()V
     111: return

  static {};
    Code:
       0: ldc           #36                 // class org/apache/hadoop/hbase/util/TestWeakObjectPool
       2: invokestatic  #37                 // Method org/apache/hadoop/hbase/HBaseClassTestRule.forClass:(Ljava/lang/Class;)Lorg/apache/hadoop/hbase/HBaseClassTestRule;
       5: putstatic     #38                 // Field CLASS_RULE:Lorg/apache/hadoop/hbase/HBaseClassTestRule;
       8: return
}
