Compiled from "TestTableFavoredNodes.java"
class org.apache.hadoop.hbase.client.TestTableFavoredNodes$1 implements org.apache.hadoop.hbase.Waiter$Predicate<java.lang.Exception> {
  final org.apache.hadoop.hbase.TableName val$tableName;

  final int val$numRegions;

  final org.apache.hadoop.hbase.client.TestTableFavoredNodes this$0;

  org.apache.hadoop.hbase.client.TestTableFavoredNodes$1(org.apache.hadoop.hbase.client.TestTableFavoredNodes, org.apache.hadoop.hbase.TableName, int);
    Code:
       0: aload_0
       1: aload_1
       2: putfield      #1                  // Field this$0:Lorg/apache/hadoop/hbase/client/TestTableFavoredNodes;
       5: aload_0
       6: aload_2
       7: putfield      #2                  // Field val$tableName:Lorg/apache/hadoop/hbase/TableName;
      10: aload_0
      11: iload_3
      12: putfield      #3                  // Field val$numRegions:I
      15: aload_0
      16: invokespecial #4                  // Method java/lang/Object."<init>":()V
      19: return

  public boolean evaluate() throws java.lang.Exception;
    Code:
       0: invokestatic  #5                  // Method org/apache/hadoop/hbase/client/TestTableFavoredNodes.access$000:()Lorg/apache/hadoop/hbase/HBaseTestingUtility;
       3: invokevirtual #6                  // Method org/apache/hadoop/hbase/HBaseTestingUtility.getConfiguration:()Lorg/apache/hadoop/conf/Configuration;
       6: aload_0
       7: getfield      #2                  // Field val$tableName:Lorg/apache/hadoop/hbase/TableName;
      10: invokestatic  #7                  // Method org/apache/hadoop/hbase/MetaTableAccessor.getRegionCount:(Lorg/apache/hadoop/conf/Configuration;Lorg/apache/hadoop/hbase/TableName;)I
      13: aload_0
      14: getfield      #3                  // Field val$numRegions:I
      17: if_icmpne     24
      20: iconst_1
      21: goto          25
      24: iconst_0
      25: ireturn
}
