Compiled from "ThroughputControlUtil.java"
public final class org.apache.hadoop.hbase.regionserver.throttle.ThroughputControlUtil {
  public static java.lang.String getNameForThrottling(org.apache.hadoop.hbase.regionserver.HStore, java.lang.String);
    Code:
       0: getstatic     #2                  // Field NAME_COUNTER:Ljava/util/concurrent/atomic/AtomicInteger;
       3: invokevirtual #3                  // Method java/util/concurrent/atomic/AtomicInteger.get:()I
       6: istore_2
       7: iload_2
       8: ldc           #5                  // int 2147483647
      10: if_icmpne     17
      13: iconst_0
      14: goto          20
      17: iload_2
      18: iconst_1
      19: iadd
      20: istore_3
      21: getstatic     #2                  // Field NAME_COUNTER:Ljava/util/concurrent/atomic/AtomicInteger;
      24: iload_2
      25: iload_3
      26: invokevirtual #6                  // Method java/util/concurrent/atomic/AtomicInteger.compareAndSet:(II)Z
      29: ifeq          35
      32: goto          38
      35: goto          0
      38: new           #7                  // class java/lang/StringBuilder
      41: dup
      42: invokespecial #8                  // Method java/lang/StringBuilder."<init>":()V
      45: aload_0
      46: invokevirtual #9                  // Method org/apache/hadoop/hbase/regionserver/HStore.getRegionInfo:()Lorg/apache/hadoop/hbase/client/RegionInfo;
      49: invokeinterface #10,  1           // InterfaceMethod org/apache/hadoop/hbase/client/RegionInfo.getEncodedName:()Ljava/lang/String;
      54: invokevirtual #11                 // Method java/lang/StringBuilder.append:(Ljava/lang/String;)Ljava/lang/StringBuilder;
      57: ldc           #13                 // String #
      59: invokevirtual #11                 // Method java/lang/StringBuilder.append:(Ljava/lang/String;)Ljava/lang/StringBuilder;
      62: aload_0
      63: invokevirtual #14                 // Method org/apache/hadoop/hbase/regionserver/HStore.getColumnFamilyDescriptor:()Lorg/apache/hadoop/hbase/client/ColumnFamilyDescriptor;
      66: invokeinterface #15,  1           // InterfaceMethod org/apache/hadoop/hbase/client/ColumnFamilyDescriptor.getNameAsString:()Ljava/lang/String;
      71: invokevirtual #11                 // Method java/lang/StringBuilder.append:(Ljava/lang/String;)Ljava/lang/StringBuilder;
      74: ldc           #13                 // String #
      76: invokevirtual #11                 // Method java/lang/StringBuilder.append:(Ljava/lang/String;)Ljava/lang/StringBuilder;
      79: aload_1
      80: invokevirtual #11                 // Method java/lang/StringBuilder.append:(Ljava/lang/String;)Ljava/lang/StringBuilder;
      83: ldc           #13                 // String #
      85: invokevirtual #11                 // Method java/lang/StringBuilder.append:(Ljava/lang/String;)Ljava/lang/StringBuilder;
      88: iload_2
      89: invokevirtual #16                 // Method java/lang/StringBuilder.append:(I)Ljava/lang/StringBuilder;
      92: invokevirtual #17                 // Method java/lang/StringBuilder.toString:()Ljava/lang/String;
      95: areturn

  static {};
    Code:
       0: new           #18                 // class java/util/concurrent/atomic/AtomicInteger
       3: dup
       4: iconst_0
       5: invokespecial #19                 // Method java/util/concurrent/atomic/AtomicInteger."<init>":(I)V
       8: putstatic     #2                  // Field NAME_COUNTER:Ljava/util/concurrent/atomic/AtomicInteger;
      11: return
}
