Compiled from "ThrottleType.java"
public final class org.apache.hadoop.hbase.quotas.ThrottleType extends java.lang.Enum<org.apache.hadoop.hbase.quotas.ThrottleType> {
  public static final org.apache.hadoop.hbase.quotas.ThrottleType REQUEST_NUMBER;

  public static final org.apache.hadoop.hbase.quotas.ThrottleType REQUEST_SIZE;

  public static final org.apache.hadoop.hbase.quotas.ThrottleType WRITE_NUMBER;

  public static final org.apache.hadoop.hbase.quotas.ThrottleType WRITE_SIZE;

  public static final org.apache.hadoop.hbase.quotas.ThrottleType READ_NUMBER;

  public static final org.apache.hadoop.hbase.quotas.ThrottleType READ_SIZE;

  public static final org.apache.hadoop.hbase.quotas.ThrottleType REQUEST_CAPACITY_UNIT;

  public static final org.apache.hadoop.hbase.quotas.ThrottleType WRITE_CAPACITY_UNIT;

  public static final org.apache.hadoop.hbase.quotas.ThrottleType READ_CAPACITY_UNIT;

  public static org.apache.hadoop.hbase.quotas.ThrottleType[] values();
    Code:
       0: getstatic     #1                  // Field $VALUES:[Lorg/apache/hadoop/hbase/quotas/ThrottleType;
       3: invokevirtual #2                  // Method "[Lorg/apache/hadoop/hbase/quotas/ThrottleType;".clone:()Ljava/lang/Object;
       6: checkcast     #3                  // class "[Lorg/apache/hadoop/hbase/quotas/ThrottleType;"
       9: areturn

  public static org.apache.hadoop.hbase.quotas.ThrottleType valueOf(java.lang.String);
    Code:
       0: ldc           #4                  // class org/apache/hadoop/hbase/quotas/ThrottleType
       2: aload_0
       3: invokestatic  #5                  // Method java/lang/Enum.valueOf:(Ljava/lang/Class;Ljava/lang/String;)Ljava/lang/Enum;
       6: checkcast     #4                  // class org/apache/hadoop/hbase/quotas/ThrottleType
       9: areturn

  static {};
    Code:
       0: new           #4                  // class org/apache/hadoop/hbase/quotas/ThrottleType
       3: dup
       4: ldc           #7                  // String REQUEST_NUMBER
       6: iconst_0
       7: invokespecial #8                  // Method "<init>":(Ljava/lang/String;I)V
      10: putstatic     #9                  // Field REQUEST_NUMBER:Lorg/apache/hadoop/hbase/quotas/ThrottleType;
      13: new           #4                  // class org/apache/hadoop/hbase/quotas/ThrottleType
      16: dup
      17: ldc           #10                 // String REQUEST_SIZE
      19: iconst_1
      20: invokespecial #8                  // Method "<init>":(Ljava/lang/String;I)V
      23: putstatic     #11                 // Field REQUEST_SIZE:Lorg/apache/hadoop/hbase/quotas/ThrottleType;
      26: new           #4                  // class org/apache/hadoop/hbase/quotas/ThrottleType
      29: dup
      30: ldc           #12                 // String WRITE_NUMBER
      32: iconst_2
      33: invokespecial #8                  // Method "<init>":(Ljava/lang/String;I)V
      36: putstatic     #13                 // Field WRITE_NUMBER:Lorg/apache/hadoop/hbase/quotas/ThrottleType;
      39: new           #4                  // class org/apache/hadoop/hbase/quotas/ThrottleType
      42: dup
      43: ldc           #14                 // String WRITE_SIZE
      45: iconst_3
      46: invokespecial #8                  // Method "<init>":(Ljava/lang/String;I)V
      49: putstatic     #15                 // Field WRITE_SIZE:Lorg/apache/hadoop/hbase/quotas/ThrottleType;
      52: new           #4                  // class org/apache/hadoop/hbase/quotas/ThrottleType
      55: dup
      56: ldc           #16                 // String READ_NUMBER
      58: iconst_4
      59: invokespecial #8                  // Method "<init>":(Ljava/lang/String;I)V
      62: putstatic     #17                 // Field READ_NUMBER:Lorg/apache/hadoop/hbase/quotas/ThrottleType;
      65: new           #4                  // class org/apache/hadoop/hbase/quotas/ThrottleType
      68: dup
      69: ldc           #18                 // String READ_SIZE
      71: iconst_5
      72: invokespecial #8                  // Method "<init>":(Ljava/lang/String;I)V
      75: putstatic     #19                 // Field READ_SIZE:Lorg/apache/hadoop/hbase/quotas/ThrottleType;
      78: new           #4                  // class org/apache/hadoop/hbase/quotas/ThrottleType
      81: dup
      82: ldc           #20                 // String REQUEST_CAPACITY_UNIT
      84: bipush        6
      86: invokespecial #8                  // Method "<init>":(Ljava/lang/String;I)V
      89: putstatic     #21                 // Field REQUEST_CAPACITY_UNIT:Lorg/apache/hadoop/hbase/quotas/ThrottleType;
      92: new           #4                  // class org/apache/hadoop/hbase/quotas/ThrottleType
      95: dup
      96: ldc           #22                 // String WRITE_CAPACITY_UNIT
      98: bipush        7
     100: invokespecial #8                  // Method "<init>":(Ljava/lang/String;I)V
     103: putstatic     #23                 // Field WRITE_CAPACITY_UNIT:Lorg/apache/hadoop/hbase/quotas/ThrottleType;
     106: new           #4                  // class org/apache/hadoop/hbase/quotas/ThrottleType
     109: dup
     110: ldc           #24                 // String READ_CAPACITY_UNIT
     112: bipush        8
     114: invokespecial #8                  // Method "<init>":(Ljava/lang/String;I)V
     117: putstatic     #25                 // Field READ_CAPACITY_UNIT:Lorg/apache/hadoop/hbase/quotas/ThrottleType;
     120: bipush        9
     122: anewarray     #4                  // class org/apache/hadoop/hbase/quotas/ThrottleType
     125: dup
     126: iconst_0
     127: getstatic     #9                  // Field REQUEST_NUMBER:Lorg/apache/hadoop/hbase/quotas/ThrottleType;
     130: aastore
     131: dup
     132: iconst_1
     133: getstatic     #11                 // Field REQUEST_SIZE:Lorg/apache/hadoop/hbase/quotas/ThrottleType;
     136: aastore
     137: dup
     138: iconst_2
     139: getstatic     #13                 // Field WRITE_NUMBER:Lorg/apache/hadoop/hbase/quotas/ThrottleType;
     142: aastore
     143: dup
     144: iconst_3
     145: getstatic     #15                 // Field WRITE_SIZE:Lorg/apache/hadoop/hbase/quotas/ThrottleType;
     148: aastore
     149: dup
     150: iconst_4
     151: getstatic     #17                 // Field READ_NUMBER:Lorg/apache/hadoop/hbase/quotas/ThrottleType;
     154: aastore
     155: dup
     156: iconst_5
     157: getstatic     #19                 // Field READ_SIZE:Lorg/apache/hadoop/hbase/quotas/ThrottleType;
     160: aastore
     161: dup
     162: bipush        6
     164: getstatic     #21                 // Field REQUEST_CAPACITY_UNIT:Lorg/apache/hadoop/hbase/quotas/ThrottleType;
     167: aastore
     168: dup
     169: bipush        7
     171: getstatic     #23                 // Field WRITE_CAPACITY_UNIT:Lorg/apache/hadoop/hbase/quotas/ThrottleType;
     174: aastore
     175: dup
     176: bipush        8
     178: getstatic     #25                 // Field READ_CAPACITY_UNIT:Lorg/apache/hadoop/hbase/quotas/ThrottleType;
     181: aastore
     182: putstatic     #1                  // Field $VALUES:[Lorg/apache/hadoop/hbase/quotas/ThrottleType;
     185: return
}
