Compiled from "TinyLfuBlockCache.java"
final class org.apache.hadoop.hbase.io.hfile.TinyLfuBlockCache$CachedBlockView implements org.apache.hadoop.hbase.io.hfile.CachedBlock {
  public org.apache.hadoop.hbase.io.hfile.TinyLfuBlockCache$CachedBlockView(org.apache.hadoop.hbase.io.hfile.BlockCacheKey, org.apache.hadoop.hbase.io.hfile.Cacheable, long);
    Code:
       0: aload_0
       1: invokespecial #1                  // Method java/lang/Object."<init>":()V
       4: aload_0
       5: lload_3
       6: putfield      #2                  // Field now:J
       9: aload_0
      10: aload_1
      11: putfield      #3                  // Field key:Lorg/apache/hadoop/hbase/io/hfile/BlockCacheKey;
      14: aload_0
      15: aload_2
      16: putfield      #4                  // Field value:Lorg/apache/hadoop/hbase/io/hfile/Cacheable;
      19: return

  public org.apache.hadoop.hbase.io.hfile.BlockPriority getBlockPriority();
    Code:
       0: getstatic     #5                  // Field org/apache/hadoop/hbase/io/hfile/BlockPriority.MEMORY:Lorg/apache/hadoop/hbase/io/hfile/BlockPriority;
       3: areturn

  public org.apache.hadoop.hbase.io.hfile.BlockType getBlockType();
    Code:
       0: aload_0
       1: getfield      #4                  // Field value:Lorg/apache/hadoop/hbase/io/hfile/Cacheable;
       4: invokeinterface #6,  1            // InterfaceMethod org/apache/hadoop/hbase/io/hfile/Cacheable.getBlockType:()Lorg/apache/hadoop/hbase/io/hfile/BlockType;
       9: areturn

  public long getOffset();
    Code:
       0: aload_0
       1: getfield      #3                  // Field key:Lorg/apache/hadoop/hbase/io/hfile/BlockCacheKey;
       4: invokevirtual #7                  // Method org/apache/hadoop/hbase/io/hfile/BlockCacheKey.getOffset:()J
       7: lreturn

  public long getSize();
    Code:
       0: aload_0
       1: getfield      #4                  // Field value:Lorg/apache/hadoop/hbase/io/hfile/Cacheable;
       4: invokeinterface #8,  1            // InterfaceMethod org/apache/hadoop/hbase/io/hfile/Cacheable.heapSize:()J
       9: lreturn

  public long getCachedTime();
    Code:
       0: lconst_0
       1: lreturn

  public java.lang.String getFilename();
    Code:
       0: aload_0
       1: getfield      #3                  // Field key:Lorg/apache/hadoop/hbase/io/hfile/BlockCacheKey;
       4: invokevirtual #9                  // Method org/apache/hadoop/hbase/io/hfile/BlockCacheKey.getHfileName:()Ljava/lang/String;
       7: areturn

  public int compareTo(org.apache.hadoop.hbase.io.hfile.CachedBlock);
    Code:
       0: getstatic     #10                 // Field COMPARATOR:Ljava/util/Comparator;
       3: aload_0
       4: aload_1
       5: invokeinterface #11,  3           // InterfaceMethod java/util/Comparator.compare:(Ljava/lang/Object;Ljava/lang/Object;)I
      10: ireturn

  public boolean equals(java.lang.Object);
    Code:
       0: aload_1
       1: aload_0
       2: if_acmpne     7
       5: iconst_1
       6: ireturn
       7: aload_1
       8: instanceof    #12                 // class org/apache/hadoop/hbase/io/hfile/CachedBlock
      11: ifne          16
      14: iconst_0
      15: ireturn
      16: aload_1
      17: checkcast     #12                 // class org/apache/hadoop/hbase/io/hfile/CachedBlock
      20: astore_2
      21: aload_0
      22: aload_2
      23: invokevirtual #13                 // Method compareTo:(Lorg/apache/hadoop/hbase/io/hfile/CachedBlock;)I
      26: ifne          33
      29: iconst_1
      30: goto          34
      33: iconst_0
      34: ireturn

  public int hashCode();
    Code:
       0: aload_0
       1: getfield      #3                  // Field key:Lorg/apache/hadoop/hbase/io/hfile/BlockCacheKey;
       4: invokevirtual #14                 // Method org/apache/hadoop/hbase/io/hfile/BlockCacheKey.hashCode:()I
       7: ireturn

  public java.lang.String toString();
    Code:
       0: aload_0
       1: aload_0
       2: getfield      #2                  // Field now:J
       5: invokestatic  #15                 // Method org/apache/hadoop/hbase/io/hfile/BlockCacheUtil.toString:(Lorg/apache/hadoop/hbase/io/hfile/CachedBlock;J)Ljava/lang/String;
       8: areturn

  public int compareTo(java.lang.Object);
    Code:
       0: aload_0
       1: aload_1
       2: checkcast     #12                 // class org/apache/hadoop/hbase/io/hfile/CachedBlock
       5: invokevirtual #13                 // Method compareTo:(Lorg/apache/hadoop/hbase/io/hfile/CachedBlock;)I
       8: ireturn

  static {};
    Code:
       0: invokedynamic #16,  0             // InvokeDynamic #0:apply:()Ljava/util/function/Function;
       5: invokestatic  #17                 // InterfaceMethod java/util/Comparator.comparing:(Ljava/util/function/Function;)Ljava/util/Comparator;
       8: invokedynamic #18,  0             // InvokeDynamic #1:apply:()Ljava/util/function/Function;
      13: invokeinterface #19,  2           // InterfaceMethod java/util/Comparator.thenComparing:(Ljava/util/function/Function;)Ljava/util/Comparator;
      18: invokedynamic #20,  0             // InvokeDynamic #2:apply:()Ljava/util/function/Function;
      23: invokeinterface #19,  2           // InterfaceMethod java/util/Comparator.thenComparing:(Ljava/util/function/Function;)Ljava/util/Comparator;
      28: putstatic     #10                 // Field COMPARATOR:Ljava/util/Comparator;
      31: return
}
