Compiled from "TokenUtil.java"
public class org.apache.hadoop.hbase.security.token.TokenUtil {
  public org.apache.hadoop.hbase.security.token.TokenUtil();
    Code:
       0: aload_0
       1: invokespecial #1                  // Method java/lang/Object."<init>":()V
       4: return

  public static org.apache.hadoop.security.token.Token<org.apache.hadoop.hbase.security.token.AuthenticationTokenIdentifier> obtainToken(org.apache.hadoop.hbase.client.Connection) throws java.io.IOException;
    Code:
       0: aconst_null
       1: astore_1
       2: invokestatic  #3                  // Method injectFault:()V
       5: aload_0
       6: getstatic     #4                  // Field org/apache/hadoop/hbase/TableName.META_TABLE_NAME:Lorg/apache/hadoop/hbase/TableName;
       9: invokeinterface #5,  2            // InterfaceMethod org/apache/hadoop/hbase/client/Connection.getTable:(Lorg/apache/hadoop/hbase/TableName;)Lorg/apache/hadoop/hbase/client/Table;
      14: astore_1
      15: aload_1
      16: getstatic     #6                  // Field org/apache/hadoop/hbase/HConstants.EMPTY_START_ROW:[B
      19: invokeinterface #7,  2            // InterfaceMethod org/apache/hadoop/hbase/client/Table.coprocessorService:([B)Lorg/apache/hadoop/hbase/ipc/CoprocessorRpcChannel;
      24: astore_2
      25: aload_2
      26: invokestatic  #8                  // Method org/apache/hadoop/hbase/protobuf/generated/AuthenticationProtos$AuthenticationService.newBlockingStub:(Lcom/google/protobuf/BlockingRpcChannel;)Lorg/apache/hadoop/hbase/protobuf/generated/AuthenticationProtos$AuthenticationService$BlockingInterface;
      29: astore_3
      30: aload_3
      31: aconst_null
      32: invokestatic  #9                  // Method org/apache/hadoop/hbase/protobuf/generated/AuthenticationProtos$GetAuthenticationTokenRequest.getDefaultInstance:()Lorg/apache/hadoop/hbase/protobuf/generated/AuthenticationProtos$GetAuthenticationTokenRequest;
      35: invokeinterface #10,  3           // InterfaceMethod org/apache/hadoop/hbase/protobuf/generated/AuthenticationProtos$AuthenticationService$BlockingInterface.getAuthenticationToken:(Lcom/google/protobuf/RpcController;Lorg/apache/hadoop/hbase/protobuf/generated/AuthenticationProtos$GetAuthenticationTokenRequest;)Lorg/apache/hadoop/hbase/protobuf/generated/AuthenticationProtos$GetAuthenticationTokenResponse;
      40: astore        4
      42: aload         4
      44: invokevirtual #11                 // Method org/apache/hadoop/hbase/protobuf/generated/AuthenticationProtos$GetAuthenticationTokenResponse.getToken:()Lorg/apache/hadoop/hbase/protobuf/generated/AuthenticationProtos$Token;
      47: invokestatic  #12                 // Method toToken:(Lorg/apache/hadoop/hbase/protobuf/generated/AuthenticationProtos$Token;)Lorg/apache/hadoop/security/token/Token;
      50: astore        5
      52: aload_1
      53: ifnull        62
      56: aload_1
      57: invokeinterface #13,  1           // InterfaceMethod org/apache/hadoop/hbase/client/Table.close:()V
      62: aload         5
      64: areturn
      65: astore_2
      66: aload_2
      67: invokestatic  #15                 // Method org/apache/hadoop/hbase/shaded/protobuf/ProtobufUtil.handleRemoteException:(Ljava/lang/Exception;)Ljava/io/IOException;
      70: athrow
      71: astore        6
      73: aload_1
      74: ifnull        83
      77: aload_1
      78: invokeinterface #13,  1           // InterfaceMethod org/apache/hadoop/hbase/client/Table.close:()V
      83: aload         6
      85: athrow
    Exception table:
       from    to  target type
           2    52    65   Class com/google/protobuf/ServiceException
           2    52    71   any
          65    73    71   any

  public static org.apache.hadoop.hbase.protobuf.generated.AuthenticationProtos$Token toToken(org.apache.hadoop.security.token.Token<org.apache.hadoop.hbase.security.token.AuthenticationTokenIdentifier>);
    Code:
       0: invokestatic  #16                 // Method org/apache/hadoop/hbase/protobuf/generated/AuthenticationProtos$Token.newBuilder:()Lorg/apache/hadoop/hbase/protobuf/generated/AuthenticationProtos$Token$Builder;
       3: astore_1
       4: aload_1
       5: aload_0
       6: invokevirtual #17                 // Method org/apache/hadoop/security/token/Token.getIdentifier:()[B
       9: invokestatic  #18                 // Method com/google/protobuf/ByteString.copyFrom:([B)Lcom/google/protobuf/ByteString;
      12: invokevirtual #19                 // Method org/apache/hadoop/hbase/protobuf/generated/AuthenticationProtos$Token$Builder.setIdentifier:(Lcom/google/protobuf/ByteString;)Lorg/apache/hadoop/hbase/protobuf/generated/AuthenticationProtos$Token$Builder;
      15: pop
      16: aload_1
      17: aload_0
      18: invokevirtual #20                 // Method org/apache/hadoop/security/token/Token.getPassword:()[B
      21: invokestatic  #18                 // Method com/google/protobuf/ByteString.copyFrom:([B)Lcom/google/protobuf/ByteString;
      24: invokevirtual #21                 // Method org/apache/hadoop/hbase/protobuf/generated/AuthenticationProtos$Token$Builder.setPassword:(Lcom/google/protobuf/ByteString;)Lorg/apache/hadoop/hbase/protobuf/generated/AuthenticationProtos$Token$Builder;
      27: pop
      28: aload_0
      29: invokevirtual #22                 // Method org/apache/hadoop/security/token/Token.getService:()Lorg/apache/hadoop/io/Text;
      32: ifnull        50
      35: aload_1
      36: aload_0
      37: invokevirtual #22                 // Method org/apache/hadoop/security/token/Token.getService:()Lorg/apache/hadoop/io/Text;
      40: invokevirtual #23                 // Method org/apache/hadoop/io/Text.toString:()Ljava/lang/String;
      43: invokestatic  #24                 // Method com/google/protobuf/ByteString.copyFromUtf8:(Ljava/lang/String;)Lcom/google/protobuf/ByteString;
      46: invokevirtual #25                 // Method org/apache/hadoop/hbase/protobuf/generated/AuthenticationProtos$Token$Builder.setService:(Lcom/google/protobuf/ByteString;)Lorg/apache/hadoop/hbase/protobuf/generated/AuthenticationProtos$Token$Builder;
      49: pop
      50: aload_1
      51: invokevirtual #26                 // Method org/apache/hadoop/hbase/protobuf/generated/AuthenticationProtos$Token$Builder.build:()Lorg/apache/hadoop/hbase/protobuf/generated/AuthenticationProtos$Token;
      54: areturn

  public static org.apache.hadoop.security.token.Token<org.apache.hadoop.hbase.security.token.AuthenticationTokenIdentifier> obtainToken(org.apache.hadoop.hbase.client.Connection, org.apache.hadoop.hbase.security.User) throws java.io.IOException, java.lang.InterruptedException;
    Code:
       0: aload_1
       1: new           #27                 // class org/apache/hadoop/hbase/security/token/TokenUtil$1
       4: dup
       5: aload_0
       6: invokespecial #28                 // Method org/apache/hadoop/hbase/security/token/TokenUtil$1."<init>":(Lorg/apache/hadoop/hbase/client/Connection;)V
       9: invokevirtual #29                 // Method org/apache/hadoop/hbase/security/User.runAs:(Ljava/security/PrivilegedExceptionAction;)Ljava/lang/Object;
      12: checkcast     #30                 // class org/apache/hadoop/security/token/Token
      15: areturn

  public static void obtainAndCacheToken(org.apache.hadoop.hbase.client.Connection, org.apache.hadoop.hbase.security.User) throws java.io.IOException, java.lang.InterruptedException;
    Code:
       0: aload_0
       1: aload_1
       2: invokestatic  #34                 // Method obtainToken:(Lorg/apache/hadoop/hbase/client/Connection;Lorg/apache/hadoop/hbase/security/User;)Lorg/apache/hadoop/security/token/Token;
       5: astore_2
       6: aload_2
       7: ifnonnull     40
      10: new           #35                 // class java/io/IOException
      13: dup
      14: new           #36                 // class java/lang/StringBuilder
      17: dup
      18: invokespecial #37                 // Method java/lang/StringBuilder."<init>":()V
      21: ldc           #38                 // String No token returned for user
      23: invokevirtual #39                 // Method java/lang/StringBuilder.append:(Ljava/lang/String;)Ljava/lang/StringBuilder;
      26: aload_1
      27: invokevirtual #40                 // Method org/apache/hadoop/hbase/security/User.getName:()Ljava/lang/String;
      30: invokevirtual #39                 // Method java/lang/StringBuilder.append:(Ljava/lang/String;)Ljava/lang/StringBuilder;
      33: invokevirtual #41                 // Method java/lang/StringBuilder.toString:()Ljava/lang/String;
      36: invokespecial #42                 // Method java/io/IOException."<init>":(Ljava/lang/String;)V
      39: athrow
      40: getstatic     #43                 // Field LOG:Lorg/slf4j/Logger;
      43: invokeinterface #44,  1           // InterfaceMethod org/slf4j/Logger.isDebugEnabled:()Z
      48: ifeq          96
      51: getstatic     #43                 // Field LOG:Lorg/slf4j/Logger;
      54: new           #36                 // class java/lang/StringBuilder
      57: dup
      58: invokespecial #37                 // Method java/lang/StringBuilder."<init>":()V
      61: ldc           #45                 // String Obtained token
      63: invokevirtual #39                 // Method java/lang/StringBuilder.append:(Ljava/lang/String;)Ljava/lang/StringBuilder;
      66: aload_2
      67: invokevirtual #46                 // Method org/apache/hadoop/security/token/Token.getKind:()Lorg/apache/hadoop/io/Text;
      70: invokevirtual #23                 // Method org/apache/hadoop/io/Text.toString:()Ljava/lang/String;
      73: invokevirtual #39                 // Method java/lang/StringBuilder.append:(Ljava/lang/String;)Ljava/lang/StringBuilder;
      76: ldc           #47                 // String  for user
      78: invokevirtual #39                 // Method java/lang/StringBuilder.append:(Ljava/lang/String;)Ljava/lang/StringBuilder;
      81: aload_1
      82: invokevirtual #40                 // Method org/apache/hadoop/hbase/security/User.getName:()Ljava/lang/String;
      85: invokevirtual #39                 // Method java/lang/StringBuilder.append:(Ljava/lang/String;)Ljava/lang/StringBuilder;
      88: invokevirtual #41                 // Method java/lang/StringBuilder.toString:()Ljava/lang/String;
      91: invokeinterface #48,  2           // InterfaceMethod org/slf4j/Logger.debug:(Ljava/lang/String;)V
      96: aload_1
      97: aload_2
      98: invokevirtual #49                 // Method org/apache/hadoop/hbase/security/User.addToken:(Lorg/apache/hadoop/security/token/Token;)V
     101: goto          145
     104: astore_2
     105: aload_2
     106: athrow
     107: astore_2
     108: aload_2
     109: athrow
     110: astore_2
     111: aload_2
     112: athrow
     113: astore_2
     114: new           #53                 // class java/lang/reflect/UndeclaredThrowableException
     117: dup
     118: aload_2
     119: new           #36                 // class java/lang/StringBuilder
     122: dup
     123: invokespecial #37                 // Method java/lang/StringBuilder."<init>":()V
     126: ldc           #54                 // String Unexpected exception obtaining token for user
     128: invokevirtual #39                 // Method java/lang/StringBuilder.append:(Ljava/lang/String;)Ljava/lang/StringBuilder;
     131: aload_1
     132: invokevirtual #40                 // Method org/apache/hadoop/hbase/security/User.getName:()Ljava/lang/String;
     135: invokevirtual #39                 // Method java/lang/StringBuilder.append:(Ljava/lang/String;)Ljava/lang/StringBuilder;
     138: invokevirtual #41                 // Method java/lang/StringBuilder.toString:()Ljava/lang/String;
     141: invokespecial #55                 // Method java/lang/reflect/UndeclaredThrowableException."<init>":(Ljava/lang/Throwable;Ljava/lang/String;)V
     144: athrow
     145: return
    Exception table:
       from    to  target type
           0   101   104   Class java/io/IOException
           0   101   107   Class java/lang/InterruptedException
           0   101   110   Class java/lang/RuntimeException
           0   101   113   Class java/lang/Exception

  public static void obtainTokenForJob(org.apache.hadoop.hbase.client.Connection, org.apache.hadoop.hbase.security.User, org.apache.hadoop.mapreduce.Job) throws java.io.IOException, java.lang.InterruptedException;
    Code:
       0: aload_0
       1: aload_1
       2: invokestatic  #34                 // Method obtainToken:(Lorg/apache/hadoop/hbase/client/Connection;Lorg/apache/hadoop/hbase/security/User;)Lorg/apache/hadoop/security/token/Token;
       5: astore_3
       6: aload_3
       7: ifnonnull     40
      10: new           #35                 // class java/io/IOException
      13: dup
      14: new           #36                 // class java/lang/StringBuilder
      17: dup
      18: invokespecial #37                 // Method java/lang/StringBuilder."<init>":()V
      21: ldc           #38                 // String No token returned for user
      23: invokevirtual #39                 // Method java/lang/StringBuilder.append:(Ljava/lang/String;)Ljava/lang/StringBuilder;
      26: aload_1
      27: invokevirtual #40                 // Method org/apache/hadoop/hbase/security/User.getName:()Ljava/lang/String;
      30: invokevirtual #39                 // Method java/lang/StringBuilder.append:(Ljava/lang/String;)Ljava/lang/StringBuilder;
      33: invokevirtual #41                 // Method java/lang/StringBuilder.toString:()Ljava/lang/String;
      36: invokespecial #42                 // Method java/io/IOException."<init>":(Ljava/lang/String;)V
      39: athrow
      40: aload_3
      41: invokestatic  #56                 // Method getClusterId:(Lorg/apache/hadoop/security/token/Token;)Lorg/apache/hadoop/io/Text;
      44: astore        4
      46: getstatic     #43                 // Field LOG:Lorg/slf4j/Logger;
      49: invokeinterface #44,  1           // InterfaceMethod org/slf4j/Logger.isDebugEnabled:()Z
      54: ifeq          115
      57: getstatic     #43                 // Field LOG:Lorg/slf4j/Logger;
      60: new           #36                 // class java/lang/StringBuilder
      63: dup
      64: invokespecial #37                 // Method java/lang/StringBuilder."<init>":()V
      67: ldc           #45                 // String Obtained token
      69: invokevirtual #39                 // Method java/lang/StringBuilder.append:(Ljava/lang/String;)Ljava/lang/StringBuilder;
      72: aload_3
      73: invokevirtual #46                 // Method org/apache/hadoop/security/token/Token.getKind:()Lorg/apache/hadoop/io/Text;
      76: invokevirtual #23                 // Method org/apache/hadoop/io/Text.toString:()Ljava/lang/String;
      79: invokevirtual #39                 // Method java/lang/StringBuilder.append:(Ljava/lang/String;)Ljava/lang/StringBuilder;
      82: ldc           #47                 // String  for user
      84: invokevirtual #39                 // Method java/lang/StringBuilder.append:(Ljava/lang/String;)Ljava/lang/StringBuilder;
      87: aload_1
      88: invokevirtual #40                 // Method org/apache/hadoop/hbase/security/User.getName:()Ljava/lang/String;
      91: invokevirtual #39                 // Method java/lang/StringBuilder.append:(Ljava/lang/String;)Ljava/lang/StringBuilder;
      94: ldc           #57                 // String  on cluster
      96: invokevirtual #39                 // Method java/lang/StringBuilder.append:(Ljava/lang/String;)Ljava/lang/StringBuilder;
      99: aload         4
     101: invokevirtual #23                 // Method org/apache/hadoop/io/Text.toString:()Ljava/lang/String;
     104: invokevirtual #39                 // Method java/lang/StringBuilder.append:(Ljava/lang/String;)Ljava/lang/StringBuilder;
     107: invokevirtual #41                 // Method java/lang/StringBuilder.toString:()Ljava/lang/String;
     110: invokeinterface #48,  2           // InterfaceMethod org/slf4j/Logger.debug:(Ljava/lang/String;)V
     115: aload_2
     116: invokevirtual #58                 // Method org/apache/hadoop/mapreduce/Job.getCredentials:()Lorg/apache/hadoop/security/Credentials;
     119: aload         4
     121: aload_3
     122: invokevirtual #59                 // Method org/apache/hadoop/security/Credentials.addToken:(Lorg/apache/hadoop/io/Text;Lorg/apache/hadoop/security/token/Token;)V
     125: goto          169
     128: astore_3
     129: aload_3
     130: athrow
     131: astore_3
     132: aload_3
     133: athrow
     134: astore_3
     135: aload_3
     136: athrow
     137: astore_3
     138: new           #53                 // class java/lang/reflect/UndeclaredThrowableException
     141: dup
     142: aload_3
     143: new           #36                 // class java/lang/StringBuilder
     146: dup
     147: invokespecial #37                 // Method java/lang/StringBuilder."<init>":()V
     150: ldc           #54                 // String Unexpected exception obtaining token for user
     152: invokevirtual #39                 // Method java/lang/StringBuilder.append:(Ljava/lang/String;)Ljava/lang/StringBuilder;
     155: aload_1
     156: invokevirtual #40                 // Method org/apache/hadoop/hbase/security/User.getName:()Ljava/lang/String;
     159: invokevirtual #39                 // Method java/lang/StringBuilder.append:(Ljava/lang/String;)Ljava/lang/StringBuilder;
     162: invokevirtual #41                 // Method java/lang/StringBuilder.toString:()Ljava/lang/String;
     165: invokespecial #55                 // Method java/lang/reflect/UndeclaredThrowableException."<init>":(Ljava/lang/Throwable;Ljava/lang/String;)V
     168: athrow
     169: return
    Exception table:
       from    to  target type
           0   125   128   Class java/io/IOException
           0   125   131   Class java/lang/InterruptedException
           0   125   134   Class java/lang/RuntimeException
           0   125   137   Class java/lang/Exception

  public static void obtainTokenForJob(org.apache.hadoop.hbase.client.Connection, org.apache.hadoop.mapred.JobConf, org.apache.hadoop.hbase.security.User) throws java.io.IOException, java.lang.InterruptedException;
    Code:
       0: aload_0
       1: aload_2
       2: invokestatic  #34                 // Method obtainToken:(Lorg/apache/hadoop/hbase/client/Connection;Lorg/apache/hadoop/hbase/security/User;)Lorg/apache/hadoop/security/token/Token;
       5: astore_3
       6: aload_3
       7: ifnonnull     40
      10: new           #35                 // class java/io/IOException
      13: dup
      14: new           #36                 // class java/lang/StringBuilder
      17: dup
      18: invokespecial #37                 // Method java/lang/StringBuilder."<init>":()V
      21: ldc           #38                 // String No token returned for user
      23: invokevirtual #39                 // Method java/lang/StringBuilder.append:(Ljava/lang/String;)Ljava/lang/StringBuilder;
      26: aload_2
      27: invokevirtual #40                 // Method org/apache/hadoop/hbase/security/User.getName:()Ljava/lang/String;
      30: invokevirtual #39                 // Method java/lang/StringBuilder.append:(Ljava/lang/String;)Ljava/lang/StringBuilder;
      33: invokevirtual #41                 // Method java/lang/StringBuilder.toString:()Ljava/lang/String;
      36: invokespecial #42                 // Method java/io/IOException."<init>":(Ljava/lang/String;)V
      39: athrow
      40: aload_3
      41: invokestatic  #56                 // Method getClusterId:(Lorg/apache/hadoop/security/token/Token;)Lorg/apache/hadoop/io/Text;
      44: astore        4
      46: getstatic     #43                 // Field LOG:Lorg/slf4j/Logger;
      49: invokeinterface #44,  1           // InterfaceMethod org/slf4j/Logger.isDebugEnabled:()Z
      54: ifeq          115
      57: getstatic     #43                 // Field LOG:Lorg/slf4j/Logger;
      60: new           #36                 // class java/lang/StringBuilder
      63: dup
      64: invokespecial #37                 // Method java/lang/StringBuilder."<init>":()V
      67: ldc           #45                 // String Obtained token
      69: invokevirtual #39                 // Method java/lang/StringBuilder.append:(Ljava/lang/String;)Ljava/lang/StringBuilder;
      72: aload_3
      73: invokevirtual #46                 // Method org/apache/hadoop/security/token/Token.getKind:()Lorg/apache/hadoop/io/Text;
      76: invokevirtual #23                 // Method org/apache/hadoop/io/Text.toString:()Ljava/lang/String;
      79: invokevirtual #39                 // Method java/lang/StringBuilder.append:(Ljava/lang/String;)Ljava/lang/StringBuilder;
      82: ldc           #47                 // String  for user
      84: invokevirtual #39                 // Method java/lang/StringBuilder.append:(Ljava/lang/String;)Ljava/lang/StringBuilder;
      87: aload_2
      88: invokevirtual #40                 // Method org/apache/hadoop/hbase/security/User.getName:()Ljava/lang/String;
      91: invokevirtual #39                 // Method java/lang/StringBuilder.append:(Ljava/lang/String;)Ljava/lang/StringBuilder;
      94: ldc           #57                 // String  on cluster
      96: invokevirtual #39                 // Method java/lang/StringBuilder.append:(Ljava/lang/String;)Ljava/lang/StringBuilder;
      99: aload         4
     101: invokevirtual #23                 // Method org/apache/hadoop/io/Text.toString:()Ljava/lang/String;
     104: invokevirtual #39                 // Method java/lang/StringBuilder.append:(Ljava/lang/String;)Ljava/lang/StringBuilder;
     107: invokevirtual #41                 // Method java/lang/StringBuilder.toString:()Ljava/lang/String;
     110: invokeinterface #48,  2           // InterfaceMethod org/slf4j/Logger.debug:(Ljava/lang/String;)V
     115: aload_1
     116: invokevirtual #60                 // Method org/apache/hadoop/mapred/JobConf.getCredentials:()Lorg/apache/hadoop/security/Credentials;
     119: aload         4
     121: aload_3
     122: invokevirtual #59                 // Method org/apache/hadoop/security/Credentials.addToken:(Lorg/apache/hadoop/io/Text;Lorg/apache/hadoop/security/token/Token;)V
     125: goto          169
     128: astore_3
     129: aload_3
     130: athrow
     131: astore_3
     132: aload_3
     133: athrow
     134: astore_3
     135: aload_3
     136: athrow
     137: astore_3
     138: new           #53                 // class java/lang/reflect/UndeclaredThrowableException
     141: dup
     142: aload_3
     143: new           #36                 // class java/lang/StringBuilder
     146: dup
     147: invokespecial #37                 // Method java/lang/StringBuilder."<init>":()V
     150: ldc           #54                 // String Unexpected exception obtaining token for user
     152: invokevirtual #39                 // Method java/lang/StringBuilder.append:(Ljava/lang/String;)Ljava/lang/StringBuilder;
     155: aload_2
     156: invokevirtual #40                 // Method org/apache/hadoop/hbase/security/User.getName:()Ljava/lang/String;
     159: invokevirtual #39                 // Method java/lang/StringBuilder.append:(Ljava/lang/String;)Ljava/lang/StringBuilder;
     162: invokevirtual #41                 // Method java/lang/StringBuilder.toString:()Ljava/lang/String;
     165: invokespecial #55                 // Method java/lang/reflect/UndeclaredThrowableException."<init>":(Ljava/lang/Throwable;Ljava/lang/String;)V
     168: athrow
     169: return
    Exception table:
       from    to  target type
           0   125   128   Class java/io/IOException
           0   125   131   Class java/lang/InterruptedException
           0   125   134   Class java/lang/RuntimeException
           0   125   137   Class java/lang/Exception

  public static void addTokenForJob(org.apache.hadoop.hbase.client.Connection, org.apache.hadoop.mapred.JobConf, org.apache.hadoop.hbase.security.User) throws java.io.IOException, java.lang.InterruptedException;
    Code:
       0: aload_0
       1: invokeinterface #61,  1           // InterfaceMethod org/apache/hadoop/hbase/client/Connection.getConfiguration:()Lorg/apache/hadoop/conf/Configuration;
       6: aload_2
       7: invokestatic  #62                 // Method getAuthToken:(Lorg/apache/hadoop/conf/Configuration;Lorg/apache/hadoop/hbase/security/User;)Lorg/apache/hadoop/security/token/Token;
      10: astore_3
      11: aload_3
      12: ifnonnull     21
      15: aload_0
      16: aload_2
      17: invokestatic  #34                 // Method obtainToken:(Lorg/apache/hadoop/hbase/client/Connection;Lorg/apache/hadoop/hbase/security/User;)Lorg/apache/hadoop/security/token/Token;
      20: astore_3
      21: aload_1
      22: invokevirtual #60                 // Method org/apache/hadoop/mapred/JobConf.getCredentials:()Lorg/apache/hadoop/security/Credentials;
      25: aload_3
      26: invokevirtual #22                 // Method org/apache/hadoop/security/token/Token.getService:()Lorg/apache/hadoop/io/Text;
      29: aload_3
      30: invokevirtual #59                 // Method org/apache/hadoop/security/Credentials.addToken:(Lorg/apache/hadoop/io/Text;Lorg/apache/hadoop/security/token/Token;)V
      33: return

  public static void addTokenForJob(org.apache.hadoop.hbase.client.Connection, org.apache.hadoop.hbase.security.User, org.apache.hadoop.mapreduce.Job) throws java.io.IOException, java.lang.InterruptedException;
    Code:
       0: aload_0
       1: invokeinterface #61,  1           // InterfaceMethod org/apache/hadoop/hbase/client/Connection.getConfiguration:()Lorg/apache/hadoop/conf/Configuration;
       6: aload_1
       7: invokestatic  #62                 // Method getAuthToken:(Lorg/apache/hadoop/conf/Configuration;Lorg/apache/hadoop/hbase/security/User;)Lorg/apache/hadoop/security/token/Token;
      10: astore_3
      11: aload_3
      12: ifnonnull     21
      15: aload_0
      16: aload_1
      17: invokestatic  #34                 // Method obtainToken:(Lorg/apache/hadoop/hbase/client/Connection;Lorg/apache/hadoop/hbase/security/User;)Lorg/apache/hadoop/security/token/Token;
      20: astore_3
      21: aload_2
      22: invokevirtual #58                 // Method org/apache/hadoop/mapreduce/Job.getCredentials:()Lorg/apache/hadoop/security/Credentials;
      25: aload_3
      26: invokevirtual #22                 // Method org/apache/hadoop/security/token/Token.getService:()Lorg/apache/hadoop/io/Text;
      29: aload_3
      30: invokevirtual #59                 // Method org/apache/hadoop/security/Credentials.addToken:(Lorg/apache/hadoop/io/Text;Lorg/apache/hadoop/security/token/Token;)V
      33: return

  public static boolean addTokenIfMissing(org.apache.hadoop.hbase.client.Connection, org.apache.hadoop.hbase.security.User) throws java.io.IOException, java.lang.InterruptedException;
    Code:
       0: aload_0
       1: invokeinterface #61,  1           // InterfaceMethod org/apache/hadoop/hbase/client/Connection.getConfiguration:()Lorg/apache/hadoop/conf/Configuration;
       6: aload_1
       7: invokestatic  #62                 // Method getAuthToken:(Lorg/apache/hadoop/conf/Configuration;Lorg/apache/hadoop/hbase/security/User;)Lorg/apache/hadoop/security/token/Token;
      10: astore_2
      11: aload_2
      12: ifnonnull     36
      15: aload_0
      16: aload_1
      17: invokestatic  #34                 // Method obtainToken:(Lorg/apache/hadoop/hbase/client/Connection;Lorg/apache/hadoop/hbase/security/User;)Lorg/apache/hadoop/security/token/Token;
      20: astore_2
      21: aload_1
      22: invokevirtual #63                 // Method org/apache/hadoop/hbase/security/User.getUGI:()Lorg/apache/hadoop/security/UserGroupInformation;
      25: aload_2
      26: invokevirtual #22                 // Method org/apache/hadoop/security/token/Token.getService:()Lorg/apache/hadoop/io/Text;
      29: aload_2
      30: invokevirtual #64                 // Method org/apache/hadoop/security/UserGroupInformation.addToken:(Lorg/apache/hadoop/io/Text;Lorg/apache/hadoop/security/token/Token;)Z
      33: pop
      34: iconst_1
      35: ireturn
      36: iconst_0
      37: ireturn

  public static org.apache.hadoop.security.token.Token<org.apache.hadoop.hbase.security.token.AuthenticationTokenIdentifier> toToken(org.apache.hadoop.hbase.protobuf.generated.AuthenticationProtos$Token);
    Code:
       0: new           #30                 // class org/apache/hadoop/security/token/Token
       3: dup
       4: aload_0
       5: invokevirtual #77                 // Method org/apache/hadoop/hbase/protobuf/generated/AuthenticationProtos$Token.hasIdentifier:()Z
       8: ifeq          21
      11: aload_0
      12: invokevirtual #78                 // Method org/apache/hadoop/hbase/protobuf/generated/AuthenticationProtos$Token.getIdentifier:()Lcom/google/protobuf/ByteString;
      15: invokevirtual #79                 // Method com/google/protobuf/ByteString.toByteArray:()[B
      18: goto          22
      21: aconst_null
      22: aload_0
      23: invokevirtual #80                 // Method org/apache/hadoop/hbase/protobuf/generated/AuthenticationProtos$Token.hasPassword:()Z
      26: ifeq          39
      29: aload_0
      30: invokevirtual #81                 // Method org/apache/hadoop/hbase/protobuf/generated/AuthenticationProtos$Token.getPassword:()Lcom/google/protobuf/ByteString;
      33: invokevirtual #79                 // Method com/google/protobuf/ByteString.toByteArray:()[B
      36: goto          40
      39: aconst_null
      40: getstatic     #82                 // Field org/apache/hadoop/hbase/security/token/AuthenticationTokenIdentifier.AUTH_TOKEN_TYPE:Lorg/apache/hadoop/io/Text;
      43: aload_0
      44: invokevirtual #83                 // Method org/apache/hadoop/hbase/protobuf/generated/AuthenticationProtos$Token.hasService:()Z
      47: ifeq          67
      50: new           #31                 // class org/apache/hadoop/io/Text
      53: dup
      54: aload_0
      55: invokevirtual #84                 // Method org/apache/hadoop/hbase/protobuf/generated/AuthenticationProtos$Token.getService:()Lcom/google/protobuf/ByteString;
      58: invokevirtual #85                 // Method com/google/protobuf/ByteString.toStringUtf8:()Ljava/lang/String;
      61: invokespecial #33                 // Method org/apache/hadoop/io/Text."<init>":(Ljava/lang/String;)V
      64: goto          68
      67: aconst_null
      68: invokespecial #86                 // Method org/apache/hadoop/security/token/Token."<init>":([B[BLorg/apache/hadoop/io/Text;Lorg/apache/hadoop/io/Text;)V
      71: areturn

  static {};
    Code:
       0: ldc           #87                 // class org/apache/hadoop/hbase/security/token/TokenUtil
       2: invokestatic  #88                 // Method org/slf4j/LoggerFactory.getLogger:(Ljava/lang/Class;)Lorg/slf4j/Logger;
       5: putstatic     #43                 // Field LOG:Lorg/slf4j/Logger;
       8: return
}
