Compiled from "TransitRegionStateProcedure.java"
class org.apache.hadoop.hbase.master.assignment.TransitRegionStateProcedure$1 {
  static final int[] $SwitchMap$org$apache$hadoop$hbase$master$assignment$TransitRegionStateProcedure$TransitionType;

  static final int[] $SwitchMap$org$apache$hadoop$hbase$shaded$protobuf$generated$MasterProcedureProtos$RegionStateTransitionState;

  static final int[] $SwitchMap$org$apache$hadoop$hbase$shaded$protobuf$generated$MasterProcedureProtos$RegionTransitionType;

  static {};
    Code:
       0: invokestatic  #1                  // Method org/apache/hadoop/hbase/shaded/protobuf/generated/MasterProcedureProtos$RegionTransitionType.values:()[Lorg/apache/hadoop/hbase/shaded/protobuf/generated/MasterProcedureProtos$RegionTransitionType;
       3: arraylength
       4: newarray       int
       6: putstatic     #2                  // Field $SwitchMap$org$apache$hadoop$hbase$shaded$protobuf$generated$MasterProcedureProtos$RegionTransitionType:[I
       9: getstatic     #2                  // Field $SwitchMap$org$apache$hadoop$hbase$shaded$protobuf$generated$MasterProcedureProtos$RegionTransitionType:[I
      12: getstatic     #3                  // Field org/apache/hadoop/hbase/shaded/protobuf/generated/MasterProcedureProtos$RegionTransitionType.ASSIGN:Lorg/apache/hadoop/hbase/shaded/protobuf/generated/MasterProcedureProtos$RegionTransitionType;
      15: invokevirtual #4                  // Method org/apache/hadoop/hbase/shaded/protobuf/generated/MasterProcedureProtos$RegionTransitionType.ordinal:()I
      18: iconst_1
      19: iastore
      20: goto          24
      23: astore_0
      24: getstatic     #2                  // Field $SwitchMap$org$apache$hadoop$hbase$shaded$protobuf$generated$MasterProcedureProtos$RegionTransitionType:[I
      27: getstatic     #6                  // Field org/apache/hadoop/hbase/shaded/protobuf/generated/MasterProcedureProtos$RegionTransitionType.UNASSIGN:Lorg/apache/hadoop/hbase/shaded/protobuf/generated/MasterProcedureProtos$RegionTransitionType;
      30: invokevirtual #4                  // Method org/apache/hadoop/hbase/shaded/protobuf/generated/MasterProcedureProtos$RegionTransitionType.ordinal:()I
      33: iconst_2
      34: iastore
      35: goto          39
      38: astore_0
      39: getstatic     #2                  // Field $SwitchMap$org$apache$hadoop$hbase$shaded$protobuf$generated$MasterProcedureProtos$RegionTransitionType:[I
      42: getstatic     #7                  // Field org/apache/hadoop/hbase/shaded/protobuf/generated/MasterProcedureProtos$RegionTransitionType.MOVE:Lorg/apache/hadoop/hbase/shaded/protobuf/generated/MasterProcedureProtos$RegionTransitionType;
      45: invokevirtual #4                  // Method org/apache/hadoop/hbase/shaded/protobuf/generated/MasterProcedureProtos$RegionTransitionType.ordinal:()I
      48: iconst_3
      49: iastore
      50: goto          54
      53: astore_0
      54: getstatic     #2                  // Field $SwitchMap$org$apache$hadoop$hbase$shaded$protobuf$generated$MasterProcedureProtos$RegionTransitionType:[I
      57: getstatic     #8                  // Field org/apache/hadoop/hbase/shaded/protobuf/generated/MasterProcedureProtos$RegionTransitionType.REOPEN:Lorg/apache/hadoop/hbase/shaded/protobuf/generated/MasterProcedureProtos$RegionTransitionType;
      60: invokevirtual #4                  // Method org/apache/hadoop/hbase/shaded/protobuf/generated/MasterProcedureProtos$RegionTransitionType.ordinal:()I
      63: iconst_4
      64: iastore
      65: goto          69
      68: astore_0
      69: invokestatic  #9                  // Method org/apache/hadoop/hbase/shaded/protobuf/generated/MasterProcedureProtos$RegionStateTransitionState.values:()[Lorg/apache/hadoop/hbase/shaded/protobuf/generated/MasterProcedureProtos$RegionStateTransitionState;
      72: arraylength
      73: newarray       int
      75: putstatic     #10                 // Field $SwitchMap$org$apache$hadoop$hbase$shaded$protobuf$generated$MasterProcedureProtos$RegionStateTransitionState:[I
      78: getstatic     #10                 // Field $SwitchMap$org$apache$hadoop$hbase$shaded$protobuf$generated$MasterProcedureProtos$RegionStateTransitionState:[I
      81: getstatic     #11                 // Field org/apache/hadoop/hbase/shaded/protobuf/generated/MasterProcedureProtos$RegionStateTransitionState.REGION_STATE_TRANSITION_GET_ASSIGN_CANDIDATE:Lorg/apache/hadoop/hbase/shaded/protobuf/generated/MasterProcedureProtos$RegionStateTransitionState;
      84: invokevirtual #12                 // Method org/apache/hadoop/hbase/shaded/protobuf/generated/MasterProcedureProtos$RegionStateTransitionState.ordinal:()I
      87: iconst_1
      88: iastore
      89: goto          93
      92: astore_0
      93: getstatic     #10                 // Field $SwitchMap$org$apache$hadoop$hbase$shaded$protobuf$generated$MasterProcedureProtos$RegionStateTransitionState:[I
      96: getstatic     #13                 // Field org/apache/hadoop/hbase/shaded/protobuf/generated/MasterProcedureProtos$RegionStateTransitionState.REGION_STATE_TRANSITION_OPEN:Lorg/apache/hadoop/hbase/shaded/protobuf/generated/MasterProcedureProtos$RegionStateTransitionState;
      99: invokevirtual #12                 // Method org/apache/hadoop/hbase/shaded/protobuf/generated/MasterProcedureProtos$RegionStateTransitionState.ordinal:()I
     102: iconst_2
     103: iastore
     104: goto          108
     107: astore_0
     108: getstatic     #10                 // Field $SwitchMap$org$apache$hadoop$hbase$shaded$protobuf$generated$MasterProcedureProtos$RegionStateTransitionState:[I
     111: getstatic     #14                 // Field org/apache/hadoop/hbase/shaded/protobuf/generated/MasterProcedureProtos$RegionStateTransitionState.REGION_STATE_TRANSITION_CONFIRM_OPENED:Lorg/apache/hadoop/hbase/shaded/protobuf/generated/MasterProcedureProtos$RegionStateTransitionState;
     114: invokevirtual #12                 // Method org/apache/hadoop/hbase/shaded/protobuf/generated/MasterProcedureProtos$RegionStateTransitionState.ordinal:()I
     117: iconst_3
     118: iastore
     119: goto          123
     122: astore_0
     123: getstatic     #10                 // Field $SwitchMap$org$apache$hadoop$hbase$shaded$protobuf$generated$MasterProcedureProtos$RegionStateTransitionState:[I
     126: getstatic     #15                 // Field org/apache/hadoop/hbase/shaded/protobuf/generated/MasterProcedureProtos$RegionStateTransitionState.REGION_STATE_TRANSITION_CLOSE:Lorg/apache/hadoop/hbase/shaded/protobuf/generated/MasterProcedureProtos$RegionStateTransitionState;
     129: invokevirtual #12                 // Method org/apache/hadoop/hbase/shaded/protobuf/generated/MasterProcedureProtos$RegionStateTransitionState.ordinal:()I
     132: iconst_4
     133: iastore
     134: goto          138
     137: astore_0
     138: getstatic     #10                 // Field $SwitchMap$org$apache$hadoop$hbase$shaded$protobuf$generated$MasterProcedureProtos$RegionStateTransitionState:[I
     141: getstatic     #16                 // Field org/apache/hadoop/hbase/shaded/protobuf/generated/MasterProcedureProtos$RegionStateTransitionState.REGION_STATE_TRANSITION_CONFIRM_CLOSED:Lorg/apache/hadoop/hbase/shaded/protobuf/generated/MasterProcedureProtos$RegionStateTransitionState;
     144: invokevirtual #12                 // Method org/apache/hadoop/hbase/shaded/protobuf/generated/MasterProcedureProtos$RegionStateTransitionState.ordinal:()I
     147: iconst_5
     148: iastore
     149: goto          153
     152: astore_0
     153: invokestatic  #17                 // Method org/apache/hadoop/hbase/master/assignment/TransitRegionStateProcedure$TransitionType.values:()[Lorg/apache/hadoop/hbase/master/assignment/TransitRegionStateProcedure$TransitionType;
     156: arraylength
     157: newarray       int
     159: putstatic     #18                 // Field $SwitchMap$org$apache$hadoop$hbase$master$assignment$TransitRegionStateProcedure$TransitionType:[I
     162: getstatic     #18                 // Field $SwitchMap$org$apache$hadoop$hbase$master$assignment$TransitRegionStateProcedure$TransitionType:[I
     165: getstatic     #19                 // Field org/apache/hadoop/hbase/master/assignment/TransitRegionStateProcedure$TransitionType.ASSIGN:Lorg/apache/hadoop/hbase/master/assignment/TransitRegionStateProcedure$TransitionType;
     168: invokevirtual #20                 // Method org/apache/hadoop/hbase/master/assignment/TransitRegionStateProcedure$TransitionType.ordinal:()I
     171: iconst_1
     172: iastore
     173: goto          177
     176: astore_0
     177: getstatic     #18                 // Field $SwitchMap$org$apache$hadoop$hbase$master$assignment$TransitRegionStateProcedure$TransitionType:[I
     180: getstatic     #21                 // Field org/apache/hadoop/hbase/master/assignment/TransitRegionStateProcedure$TransitionType.UNASSIGN:Lorg/apache/hadoop/hbase/master/assignment/TransitRegionStateProcedure$TransitionType;
     183: invokevirtual #20                 // Method org/apache/hadoop/hbase/master/assignment/TransitRegionStateProcedure$TransitionType.ordinal:()I
     186: iconst_2
     187: iastore
     188: goto          192
     191: astore_0
     192: getstatic     #18                 // Field $SwitchMap$org$apache$hadoop$hbase$master$assignment$TransitRegionStateProcedure$TransitionType:[I
     195: getstatic     #22                 // Field org/apache/hadoop/hbase/master/assignment/TransitRegionStateProcedure$TransitionType.MOVE:Lorg/apache/hadoop/hbase/master/assignment/TransitRegionStateProcedure$TransitionType;
     198: invokevirtual #20                 // Method org/apache/hadoop/hbase/master/assignment/TransitRegionStateProcedure$TransitionType.ordinal:()I
     201: iconst_3
     202: iastore
     203: goto          207
     206: astore_0
     207: getstatic     #18                 // Field $SwitchMap$org$apache$hadoop$hbase$master$assignment$TransitRegionStateProcedure$TransitionType:[I
     210: getstatic     #23                 // Field org/apache/hadoop/hbase/master/assignment/TransitRegionStateProcedure$TransitionType.REOPEN:Lorg/apache/hadoop/hbase/master/assignment/TransitRegionStateProcedure$TransitionType;
     213: invokevirtual #20                 // Method org/apache/hadoop/hbase/master/assignment/TransitRegionStateProcedure$TransitionType.ordinal:()I
     216: iconst_4
     217: iastore
     218: goto          222
     221: astore_0
     222: return
    Exception table:
       from    to  target type
           9    20    23   Class java/lang/NoSuchFieldError
          24    35    38   Class java/lang/NoSuchFieldError
          39    50    53   Class java/lang/NoSuchFieldError
          54    65    68   Class java/lang/NoSuchFieldError
          78    89    92   Class java/lang/NoSuchFieldError
          93   104   107   Class java/lang/NoSuchFieldError
         108   119   122   Class java/lang/NoSuchFieldError
         123   134   137   Class java/lang/NoSuchFieldError
         138   149   152   Class java/lang/NoSuchFieldError
         162   173   176   Class java/lang/NoSuchFieldError
         177   188   191   Class java/lang/NoSuchFieldError
         192   203   206   Class java/lang/NoSuchFieldError
         207   218   221   Class java/lang/NoSuchFieldError
}
