Compiled from "TruncateTableProcedure.java"
class org.apache.hadoop.hbase.master.procedure.TruncateTableProcedure$1 {
  static final int[] $SwitchMap$org$apache$hadoop$hbase$shaded$protobuf$generated$MasterProcedureProtos$TruncateTableState;

  static {};
    Code:
       0: invokestatic  #1                  // Method org/apache/hadoop/hbase/shaded/protobuf/generated/MasterProcedureProtos$TruncateTableState.values:()[Lorg/apache/hadoop/hbase/shaded/protobuf/generated/MasterProcedureProtos$TruncateTableState;
       3: arraylength
       4: newarray       int
       6: putstatic     #2                  // Field $SwitchMap$org$apache$hadoop$hbase$shaded$protobuf$generated$MasterProcedureProtos$TruncateTableState:[I
       9: getstatic     #2                  // Field $SwitchMap$org$apache$hadoop$hbase$shaded$protobuf$generated$MasterProcedureProtos$TruncateTableState:[I
      12: getstatic     #3                  // Field org/apache/hadoop/hbase/shaded/protobuf/generated/MasterProcedureProtos$TruncateTableState.TRUNCATE_TABLE_PRE_OPERATION:Lorg/apache/hadoop/hbase/shaded/protobuf/generated/MasterProcedureProtos$TruncateTableState;
      15: invokevirtual #4                  // Method org/apache/hadoop/hbase/shaded/protobuf/generated/MasterProcedureProtos$TruncateTableState.ordinal:()I
      18: iconst_1
      19: iastore
      20: goto          24
      23: astore_0
      24: getstatic     #2                  // Field $SwitchMap$org$apache$hadoop$hbase$shaded$protobuf$generated$MasterProcedureProtos$TruncateTableState:[I
      27: getstatic     #6                  // Field org/apache/hadoop/hbase/shaded/protobuf/generated/MasterProcedureProtos$TruncateTableState.TRUNCATE_TABLE_REMOVE_FROM_META:Lorg/apache/hadoop/hbase/shaded/protobuf/generated/MasterProcedureProtos$TruncateTableState;
      30: invokevirtual #4                  // Method org/apache/hadoop/hbase/shaded/protobuf/generated/MasterProcedureProtos$TruncateTableState.ordinal:()I
      33: iconst_2
      34: iastore
      35: goto          39
      38: astore_0
      39: getstatic     #2                  // Field $SwitchMap$org$apache$hadoop$hbase$shaded$protobuf$generated$MasterProcedureProtos$TruncateTableState:[I
      42: getstatic     #7                  // Field org/apache/hadoop/hbase/shaded/protobuf/generated/MasterProcedureProtos$TruncateTableState.TRUNCATE_TABLE_CLEAR_FS_LAYOUT:Lorg/apache/hadoop/hbase/shaded/protobuf/generated/MasterProcedureProtos$TruncateTableState;
      45: invokevirtual #4                  // Method org/apache/hadoop/hbase/shaded/protobuf/generated/MasterProcedureProtos$TruncateTableState.ordinal:()I
      48: iconst_3
      49: iastore
      50: goto          54
      53: astore_0
      54: getstatic     #2                  // Field $SwitchMap$org$apache$hadoop$hbase$shaded$protobuf$generated$MasterProcedureProtos$TruncateTableState:[I
      57: getstatic     #8                  // Field org/apache/hadoop/hbase/shaded/protobuf/generated/MasterProcedureProtos$TruncateTableState.TRUNCATE_TABLE_CREATE_FS_LAYOUT:Lorg/apache/hadoop/hbase/shaded/protobuf/generated/MasterProcedureProtos$TruncateTableState;
      60: invokevirtual #4                  // Method org/apache/hadoop/hbase/shaded/protobuf/generated/MasterProcedureProtos$TruncateTableState.ordinal:()I
      63: iconst_4
      64: iastore
      65: goto          69
      68: astore_0
      69: getstatic     #2                  // Field $SwitchMap$org$apache$hadoop$hbase$shaded$protobuf$generated$MasterProcedureProtos$TruncateTableState:[I
      72: getstatic     #9                  // Field org/apache/hadoop/hbase/shaded/protobuf/generated/MasterProcedureProtos$TruncateTableState.TRUNCATE_TABLE_ADD_TO_META:Lorg/apache/hadoop/hbase/shaded/protobuf/generated/MasterProcedureProtos$TruncateTableState;
      75: invokevirtual #4                  // Method org/apache/hadoop/hbase/shaded/protobuf/generated/MasterProcedureProtos$TruncateTableState.ordinal:()I
      78: iconst_5
      79: iastore
      80: goto          84
      83: astore_0
      84: getstatic     #2                  // Field $SwitchMap$org$apache$hadoop$hbase$shaded$protobuf$generated$MasterProcedureProtos$TruncateTableState:[I
      87: getstatic     #10                 // Field org/apache/hadoop/hbase/shaded/protobuf/generated/MasterProcedureProtos$TruncateTableState.TRUNCATE_TABLE_ASSIGN_REGIONS:Lorg/apache/hadoop/hbase/shaded/protobuf/generated/MasterProcedureProtos$TruncateTableState;
      90: invokevirtual #4                  // Method org/apache/hadoop/hbase/shaded/protobuf/generated/MasterProcedureProtos$TruncateTableState.ordinal:()I
      93: bipush        6
      95: iastore
      96: goto          100
      99: astore_0
     100: getstatic     #2                  // Field $SwitchMap$org$apache$hadoop$hbase$shaded$protobuf$generated$MasterProcedureProtos$TruncateTableState:[I
     103: getstatic     #11                 // Field org/apache/hadoop/hbase/shaded/protobuf/generated/MasterProcedureProtos$TruncateTableState.TRUNCATE_TABLE_POST_OPERATION:Lorg/apache/hadoop/hbase/shaded/protobuf/generated/MasterProcedureProtos$TruncateTableState;
     106: invokevirtual #4                  // Method org/apache/hadoop/hbase/shaded/protobuf/generated/MasterProcedureProtos$TruncateTableState.ordinal:()I
     109: bipush        7
     111: iastore
     112: goto          116
     115: astore_0
     116: return
    Exception table:
       from    to  target type
           9    20    23   Class java/lang/NoSuchFieldError
          24    35    38   Class java/lang/NoSuchFieldError
          39    50    53   Class java/lang/NoSuchFieldError
          54    65    68   Class java/lang/NoSuchFieldError
          69    80    83   Class java/lang/NoSuchFieldError
          84    96    99   Class java/lang/NoSuchFieldError
         100   112   115   Class java/lang/NoSuchFieldError
}
