Compiled from "TruncateTableProcedure.java"
public class org.apache.hadoop.hbase.master.procedure.TruncateTableProcedure extends org.apache.hadoop.hbase.master.procedure.AbstractStateMachineTableProcedure<org.apache.hadoop.hbase.shaded.protobuf.generated.MasterProcedureProtos$TruncateTableState> {
  static final boolean $assertionsDisabled;

  public org.apache.hadoop.hbase.master.procedure.TruncateTableProcedure();
    Code:
       0: aload_0
       1: invokespecial #1                  // Method org/apache/hadoop/hbase/master/procedure/AbstractStateMachineTableProcedure."<init>":()V
       4: return

  public org.apache.hadoop.hbase.master.procedure.TruncateTableProcedure(org.apache.hadoop.hbase.master.procedure.MasterProcedureEnv, org.apache.hadoop.hbase.TableName, boolean) throws org.apache.hadoop.hbase.HBaseIOException;
    Code:
       0: aload_0
       1: aload_1
       2: aload_2
       3: iload_3
       4: aconst_null
       5: invokespecial #2                  // Method "<init>":(Lorg/apache/hadoop/hbase/master/procedure/MasterProcedureEnv;Lorg/apache/hadoop/hbase/TableName;ZLorg/apache/hadoop/hbase/master/procedure/ProcedurePrepareLatch;)V
       8: return

  public org.apache.hadoop.hbase.master.procedure.TruncateTableProcedure(org.apache.hadoop.hbase.master.procedure.MasterProcedureEnv, org.apache.hadoop.hbase.TableName, boolean, org.apache.hadoop.hbase.master.procedure.ProcedurePrepareLatch) throws org.apache.hadoop.hbase.HBaseIOException;
    Code:
       0: aload_0
       1: aload_1
       2: aload         4
       4: invokespecial #3                  // Method org/apache/hadoop/hbase/master/procedure/AbstractStateMachineTableProcedure."<init>":(Lorg/apache/hadoop/hbase/master/procedure/MasterProcedureEnv;Lorg/apache/hadoop/hbase/master/procedure/ProcedurePrepareLatch;)V
       7: aload_0
       8: aload_2
       9: putfield      #4                  // Field tableName:Lorg/apache/hadoop/hbase/TableName;
      12: aload_0
      13: aload_1
      14: iconst_0
      15: invokestatic  #5                  // Method java/lang/Boolean.valueOf:(Z)Ljava/lang/Boolean;
      18: invokevirtual #6                  // Method preflightChecks:(Lorg/apache/hadoop/hbase/master/procedure/MasterProcedureEnv;Ljava/lang/Boolean;)V
      21: aload_0
      22: iload_3
      23: putfield      #7                  // Field preserveSplits:Z
      26: return

  protected org.apache.hadoop.hbase.procedure2.StateMachineProcedure$Flow executeFromState(org.apache.hadoop.hbase.master.procedure.MasterProcedureEnv, org.apache.hadoop.hbase.shaded.protobuf.generated.MasterProcedureProtos$TruncateTableState) throws java.lang.InterruptedException;
    Code:
       0: getstatic     #8                  // Field LOG:Lorg/slf4j/Logger;
       3: invokeinterface #9,  1            // InterfaceMethod org/slf4j/Logger.isTraceEnabled:()Z
       8: ifeq          42
      11: getstatic     #8                  // Field LOG:Lorg/slf4j/Logger;
      14: new           #10                 // class java/lang/StringBuilder
      17: dup
      18: invokespecial #11                 // Method java/lang/StringBuilder."<init>":()V
      21: aload_0
      22: invokevirtual #12                 // Method java/lang/StringBuilder.append:(Ljava/lang/Object;)Ljava/lang/StringBuilder;
      25: ldc           #13                 // String  execute state=
      27: invokevirtual #14                 // Method java/lang/StringBuilder.append:(Ljava/lang/String;)Ljava/lang/StringBuilder;
      30: aload_2
      31: invokevirtual #12                 // Method java/lang/StringBuilder.append:(Ljava/lang/Object;)Ljava/lang/StringBuilder;
      34: invokevirtual #15                 // Method java/lang/StringBuilder.toString:()Ljava/lang/String;
      37: invokeinterface #16,  2           // InterfaceMethod org/slf4j/Logger.trace:(Ljava/lang/String;)V
      42: getstatic     #17                 // Field org/apache/hadoop/hbase/master/procedure/TruncateTableProcedure$1.$SwitchMap$org$apache$hadoop$hbase$shaded$protobuf$generated$MasterProcedureProtos$TruncateTableState:[I
      45: aload_2
      46: invokevirtual #18                 // Method org/apache/hadoop/hbase/shaded/protobuf/generated/MasterProcedureProtos$TruncateTableState.ordinal:()I
      49: iaload
      50: tableswitch   { // 1 to 7
                     1: 92
                     2: 246
                     3: 298
                     4: 360
                     5: 407
                     6: 433
                     7: 476
               default: 528
          }
      92: aload_0
      93: aload_1
      94: invokespecial #19                 // Method prepareTruncate:(Lorg/apache/hadoop/hbase/master/procedure/MasterProcedureEnv;)Z
      97: ifne          127
     100: getstatic     #20                 // Field $assertionsDisabled:Z
     103: ifne          123
     106: aload_0
     107: invokevirtual #21                 // Method isFailed:()Z
     110: ifne          123
     113: new           #22                 // class java/lang/AssertionError
     116: dup
     117: ldc           #23                 // String the truncate should have an exception here
     119: invokespecial #24                 // Method java/lang/AssertionError."<init>":(Ljava/lang/Object;)V
     122: athrow
     123: getstatic     #25                 // Field org/apache/hadoop/hbase/procedure2/StateMachineProcedure$Flow.NO_MORE_STATE:Lorg/apache/hadoop/hbase/procedure2/StateMachineProcedure$Flow;
     126: areturn
     127: getstatic     #8                  // Field LOG:Lorg/slf4j/Logger;
     130: new           #10                 // class java/lang/StringBuilder
     133: dup
     134: invokespecial #11                 // Method java/lang/StringBuilder."<init>":()V
     137: ldc           #26                 // String waiting for '
     139: invokevirtual #14                 // Method java/lang/StringBuilder.append:(Ljava/lang/String;)Ljava/lang/StringBuilder;
     142: aload_0
     143: invokevirtual #27                 // Method getTableName:()Lorg/apache/hadoop/hbase/TableName;
     146: invokevirtual #12                 // Method java/lang/StringBuilder.append:(Ljava/lang/Object;)Ljava/lang/StringBuilder;
     149: ldc           #28                 // String ' regions in transition
     151: invokevirtual #14                 // Method java/lang/StringBuilder.append:(Ljava/lang/String;)Ljava/lang/StringBuilder;
     154: invokevirtual #15                 // Method java/lang/StringBuilder.toString:()Ljava/lang/String;
     157: invokeinterface #29,  2           // InterfaceMethod org/slf4j/Logger.debug:(Ljava/lang/String;)V
     162: aload_0
     163: aload_1
     164: invokevirtual #30                 // Method org/apache/hadoop/hbase/master/procedure/MasterProcedureEnv.getAssignmentManager:()Lorg/apache/hadoop/hbase/master/assignment/AssignmentManager;
     167: invokevirtual #31                 // Method org/apache/hadoop/hbase/master/assignment/AssignmentManager.getRegionStates:()Lorg/apache/hadoop/hbase/master/assignment/RegionStates;
     170: aload_0
     171: invokevirtual #27                 // Method getTableName:()Lorg/apache/hadoop/hbase/TableName;
     174: invokevirtual #32                 // Method org/apache/hadoop/hbase/master/assignment/RegionStates.getRegionsOfTable:(Lorg/apache/hadoop/hbase/TableName;)Ljava/util/List;
     177: putfield      #33                 // Field regions:Ljava/util/List;
     180: aload_0
     181: getfield      #33                 // Field regions:Ljava/util/List;
     184: invokestatic  #34                 // Method org/apache/hadoop/hbase/client/RegionReplicaUtil.removeNonDefaultRegions:(Ljava/util/Collection;)V
     187: getstatic     #20                 // Field $assertionsDisabled:Z
     190: ifne          222
     193: aload_0
     194: getfield      #33                 // Field regions:Ljava/util/List;
     197: ifnull        212
     200: aload_0
     201: getfield      #33                 // Field regions:Ljava/util/List;
     204: invokeinterface #35,  1           // InterfaceMethod java/util/List.isEmpty:()Z
     209: ifeq          222
     212: new           #22                 // class java/lang/AssertionError
     215: dup
     216: ldc           #36                 // String unexpected 0 regions
     218: invokespecial #24                 // Method java/lang/AssertionError."<init>":(Ljava/lang/Object;)V
     221: athrow
     222: aload_1
     223: aload_0
     224: getfield      #33                 // Field regions:Ljava/util/List;
     227: invokestatic  #37                 // Method org/apache/hadoop/hbase/master/procedure/ProcedureSyncWait.waitRegionInTransition:(Lorg/apache/hadoop/hbase/master/procedure/MasterProcedureEnv;Ljava/util/List;)V
     230: aload_0
     231: aload_1
     232: invokespecial #38                 // Method preTruncate:(Lorg/apache/hadoop/hbase/master/procedure/MasterProcedureEnv;)Z
     235: pop
     236: aload_0
     237: getstatic     #39                 // Field org/apache/hadoop/hbase/shaded/protobuf/generated/MasterProcedureProtos$TruncateTableState.TRUNCATE_TABLE_REMOVE_FROM_META:Lorg/apache/hadoop/hbase/shaded/protobuf/generated/MasterProcedureProtos$TruncateTableState;
     240: invokevirtual #40                 // Method setNextState:(Ljava/lang/Object;)V
     243: goto          555
     246: aload_0
     247: aload_1
     248: invokevirtual #41                 // Method org/apache/hadoop/hbase/master/procedure/MasterProcedureEnv.getMasterServices:()Lorg/apache/hadoop/hbase/master/MasterServices;
     251: invokeinterface #42,  1           // InterfaceMethod org/apache/hadoop/hbase/master/MasterServices.getTableDescriptors:()Lorg/apache/hadoop/hbase/TableDescriptors;
     256: aload_0
     257: getfield      #4                  // Field tableName:Lorg/apache/hadoop/hbase/TableName;
     260: invokeinterface #43,  2           // InterfaceMethod org/apache/hadoop/hbase/TableDescriptors.get:(Lorg/apache/hadoop/hbase/TableName;)Lorg/apache/hadoop/hbase/client/TableDescriptor;
     265: putfield      #44                 // Field tableDescriptor:Lorg/apache/hadoop/hbase/client/TableDescriptor;
     268: aload_1
     269: aload_0
     270: invokevirtual #27                 // Method getTableName:()Lorg/apache/hadoop/hbase/TableName;
     273: aload_0
     274: getfield      #33                 // Field regions:Ljava/util/List;
     277: invokestatic  #45                 // Method org/apache/hadoop/hbase/master/procedure/DeleteTableProcedure.deleteFromMeta:(Lorg/apache/hadoop/hbase/master/procedure/MasterProcedureEnv;Lorg/apache/hadoop/hbase/TableName;Ljava/util/List;)V
     280: aload_1
     281: aload_0
     282: invokevirtual #27                 // Method getTableName:()Lorg/apache/hadoop/hbase/TableName;
     285: invokestatic  #46                 // Method org/apache/hadoop/hbase/master/procedure/DeleteTableProcedure.deleteAssignmentState:(Lorg/apache/hadoop/hbase/master/procedure/MasterProcedureEnv;Lorg/apache/hadoop/hbase/TableName;)V
     288: aload_0
     289: getstatic     #47                 // Field org/apache/hadoop/hbase/shaded/protobuf/generated/MasterProcedureProtos$TruncateTableState.TRUNCATE_TABLE_CLEAR_FS_LAYOUT:Lorg/apache/hadoop/hbase/shaded/protobuf/generated/MasterProcedureProtos$TruncateTableState;
     292: invokevirtual #40                 // Method setNextState:(Ljava/lang/Object;)V
     295: goto          555
     298: aload_1
     299: aload_0
     300: invokevirtual #27                 // Method getTableName:()Lorg/apache/hadoop/hbase/TableName;
     303: aload_0
     304: getfield      #33                 // Field regions:Ljava/util/List;
     307: iconst_1
     308: invokestatic  #48                 // Method org/apache/hadoop/hbase/master/procedure/DeleteTableProcedure.deleteFromFs:(Lorg/apache/hadoop/hbase/master/procedure/MasterProcedureEnv;Lorg/apache/hadoop/hbase/TableName;Ljava/util/List;Z)V
     311: aload_0
     312: getfield      #7                  // Field preserveSplits:Z
     315: ifne          339
     318: aload_0
     319: aload_0
     320: getfield      #44                 // Field tableDescriptor:Lorg/apache/hadoop/hbase/client/TableDescriptor;
     323: aconst_null
     324: checkcast     #49                 // class "[[B"
     327: invokestatic  #50                 // Method org/apache/hadoop/hbase/util/ModifyRegionUtils.createRegionInfos:(Lorg/apache/hadoop/hbase/client/TableDescriptor;[[B)[Lorg/apache/hadoop/hbase/client/RegionInfo;
     330: invokestatic  #51                 // Method java/util/Arrays.asList:([Ljava/lang/Object;)Ljava/util/List;
     333: putfield      #33                 // Field regions:Ljava/util/List;
     336: goto          350
     339: aload_0
     340: aload_0
     341: getfield      #33                 // Field regions:Ljava/util/List;
     344: invokestatic  #52                 // Method recreateRegionInfo:(Ljava/util/List;)Ljava/util/List;
     347: putfield      #33                 // Field regions:Ljava/util/List;
     350: aload_0
     351: getstatic     #53                 // Field org/apache/hadoop/hbase/shaded/protobuf/generated/MasterProcedureProtos$TruncateTableState.TRUNCATE_TABLE_CREATE_FS_LAYOUT:Lorg/apache/hadoop/hbase/shaded/protobuf/generated/MasterProcedureProtos$TruncateTableState;
     354: invokevirtual #40                 // Method setNextState:(Ljava/lang/Object;)V
     357: goto          555
     360: aload_1
     361: aload_0
     362: invokevirtual #27                 // Method getTableName:()Lorg/apache/hadoop/hbase/TableName;
     365: aload_0
     366: getfield      #33                 // Field regions:Ljava/util/List;
     369: iconst_1
     370: invokestatic  #48                 // Method org/apache/hadoop/hbase/master/procedure/DeleteTableProcedure.deleteFromFs:(Lorg/apache/hadoop/hbase/master/procedure/MasterProcedureEnv;Lorg/apache/hadoop/hbase/TableName;Ljava/util/List;Z)V
     373: aload_0
     374: aload_1
     375: aload_0
     376: getfield      #44                 // Field tableDescriptor:Lorg/apache/hadoop/hbase/client/TableDescriptor;
     379: aload_0
     380: getfield      #33                 // Field regions:Ljava/util/List;
     383: invokestatic  #54                 // Method org/apache/hadoop/hbase/master/procedure/CreateTableProcedure.createFsLayout:(Lorg/apache/hadoop/hbase/master/procedure/MasterProcedureEnv;Lorg/apache/hadoop/hbase/client/TableDescriptor;Ljava/util/List;)Ljava/util/List;
     386: putfield      #33                 // Field regions:Ljava/util/List;
     389: aload_1
     390: aload_0
     391: invokevirtual #27                 // Method getTableName:()Lorg/apache/hadoop/hbase/TableName;
     394: invokestatic  #55                 // Method org/apache/hadoop/hbase/master/procedure/CreateTableProcedure.updateTableDescCache:(Lorg/apache/hadoop/hbase/master/procedure/MasterProcedureEnv;Lorg/apache/hadoop/hbase/TableName;)V
     397: aload_0
     398: getstatic     #56                 // Field org/apache/hadoop/hbase/shaded/protobuf/generated/MasterProcedureProtos$TruncateTableState.TRUNCATE_TABLE_ADD_TO_META:Lorg/apache/hadoop/hbase/shaded/protobuf/generated/MasterProcedureProtos$TruncateTableState;
     401: invokevirtual #40                 // Method setNextState:(Ljava/lang/Object;)V
     404: goto          555
     407: aload_0
     408: aload_1
     409: aload_0
     410: getfield      #44                 // Field tableDescriptor:Lorg/apache/hadoop/hbase/client/TableDescriptor;
     413: aload_0
     414: getfield      #33                 // Field regions:Ljava/util/List;
     417: invokestatic  #57                 // Method org/apache/hadoop/hbase/master/procedure/CreateTableProcedure.addTableToMeta:(Lorg/apache/hadoop/hbase/master/procedure/MasterProcedureEnv;Lorg/apache/hadoop/hbase/client/TableDescriptor;Ljava/util/List;)Ljava/util/List;
     420: putfield      #33                 // Field regions:Ljava/util/List;
     423: aload_0
     424: getstatic     #58                 // Field org/apache/hadoop/hbase/shaded/protobuf/generated/MasterProcedureProtos$TruncateTableState.TRUNCATE_TABLE_ASSIGN_REGIONS:Lorg/apache/hadoop/hbase/shaded/protobuf/generated/MasterProcedureProtos$TruncateTableState;
     427: invokevirtual #40                 // Method setNextState:(Ljava/lang/Object;)V
     430: goto          555
     433: aload_1
     434: aload_0
     435: invokevirtual #27                 // Method getTableName:()Lorg/apache/hadoop/hbase/TableName;
     438: invokestatic  #59                 // Method org/apache/hadoop/hbase/master/procedure/CreateTableProcedure.setEnablingState:(Lorg/apache/hadoop/hbase/master/procedure/MasterProcedureEnv;Lorg/apache/hadoop/hbase/TableName;)V
     441: aload_0
     442: aload_1
     443: invokevirtual #30                 // Method org/apache/hadoop/hbase/master/procedure/MasterProcedureEnv.getAssignmentManager:()Lorg/apache/hadoop/hbase/master/assignment/AssignmentManager;
     446: aload_0
     447: getfield      #33                 // Field regions:Ljava/util/List;
     450: invokevirtual #60                 // Method org/apache/hadoop/hbase/master/assignment/AssignmentManager.createRoundRobinAssignProcedures:(Ljava/util/List;)[Lorg/apache/hadoop/hbase/master/assignment/TransitRegionStateProcedure;
     453: invokevirtual #61                 // Method addChildProcedure:([Lorg/apache/hadoop/hbase/procedure2/Procedure;)V
     456: aload_0
     457: getstatic     #62                 // Field org/apache/hadoop/hbase/shaded/protobuf/generated/MasterProcedureProtos$TruncateTableState.TRUNCATE_TABLE_POST_OPERATION:Lorg/apache/hadoop/hbase/shaded/protobuf/generated/MasterProcedureProtos$TruncateTableState;
     460: invokevirtual #40                 // Method setNextState:(Ljava/lang/Object;)V
     463: aload_0
     464: aconst_null
     465: putfield      #44                 // Field tableDescriptor:Lorg/apache/hadoop/hbase/client/TableDescriptor;
     468: aload_0
     469: aconst_null
     470: putfield      #33                 // Field regions:Ljava/util/List;
     473: goto          555
     476: aload_1
     477: aload_0
     478: invokevirtual #27                 // Method getTableName:()Lorg/apache/hadoop/hbase/TableName;
     481: invokestatic  #63                 // Method org/apache/hadoop/hbase/master/procedure/CreateTableProcedure.setEnabledState:(Lorg/apache/hadoop/hbase/master/procedure/MasterProcedureEnv;Lorg/apache/hadoop/hbase/TableName;)V
     484: aload_0
     485: aload_1
     486: invokespecial #64                 // Method postTruncate:(Lorg/apache/hadoop/hbase/master/procedure/MasterProcedureEnv;)V
     489: getstatic     #8                  // Field LOG:Lorg/slf4j/Logger;
     492: new           #10                 // class java/lang/StringBuilder
     495: dup
     496: invokespecial #11                 // Method java/lang/StringBuilder."<init>":()V
     499: ldc           #65                 // String truncate '
     501: invokevirtual #14                 // Method java/lang/StringBuilder.append:(Ljava/lang/String;)Ljava/lang/StringBuilder;
     504: aload_0
     505: invokevirtual #27                 // Method getTableName:()Lorg/apache/hadoop/hbase/TableName;
     508: invokevirtual #12                 // Method java/lang/StringBuilder.append:(Ljava/lang/Object;)Ljava/lang/StringBuilder;
     511: ldc           #66                 // String ' completed
     513: invokevirtual #14                 // Method java/lang/StringBuilder.append:(Ljava/lang/String;)Ljava/lang/StringBuilder;
     516: invokevirtual #15                 // Method java/lang/StringBuilder.toString:()Ljava/lang/String;
     519: invokeinterface #29,  2           // InterfaceMethod org/slf4j/Logger.debug:(Ljava/lang/String;)V
     524: getstatic     #25                 // Field org/apache/hadoop/hbase/procedure2/StateMachineProcedure$Flow.NO_MORE_STATE:Lorg/apache/hadoop/hbase/procedure2/StateMachineProcedure$Flow;
     527: areturn
     528: new           #67                 // class java/lang/UnsupportedOperationException
     531: dup
     532: new           #10                 // class java/lang/StringBuilder
     535: dup
     536: invokespecial #11                 // Method java/lang/StringBuilder."<init>":()V
     539: ldc           #68                 // String unhandled state=
     541: invokevirtual #14                 // Method java/lang/StringBuilder.append:(Ljava/lang/String;)Ljava/lang/StringBuilder;
     544: aload_2
     545: invokevirtual #12                 // Method java/lang/StringBuilder.append:(Ljava/lang/Object;)Ljava/lang/StringBuilder;
     548: invokevirtual #15                 // Method java/lang/StringBuilder.toString:()Ljava/lang/String;
     551: invokespecial #69                 // Method java/lang/UnsupportedOperationException."<init>":(Ljava/lang/String;)V
     554: athrow
     555: goto          617
     558: astore_3
     559: aload_0
     560: aload_2
     561: invokevirtual #71                 // Method isRollbackSupported:(Lorg/apache/hadoop/hbase/shaded/protobuf/generated/MasterProcedureProtos$TruncateTableState;)Z
     564: ifeq          577
     567: aload_0
     568: ldc           #72                 // String master-truncate-table
     570: aload_3
     571: invokevirtual #73                 // Method setFailure:(Ljava/lang/String;Ljava/lang/Throwable;)V
     574: goto          617
     577: getstatic     #8                  // Field LOG:Lorg/slf4j/Logger;
     580: new           #10                 // class java/lang/StringBuilder
     583: dup
     584: invokespecial #11                 // Method java/lang/StringBuilder."<init>":()V
     587: ldc           #74                 // String Retriable error trying to truncate table=
     589: invokevirtual #14                 // Method java/lang/StringBuilder.append:(Ljava/lang/String;)Ljava/lang/StringBuilder;
     592: aload_0
     593: invokevirtual #27                 // Method getTableName:()Lorg/apache/hadoop/hbase/TableName;
     596: invokevirtual #12                 // Method java/lang/StringBuilder.append:(Ljava/lang/Object;)Ljava/lang/StringBuilder;
     599: ldc           #75                 // String  state=
     601: invokevirtual #14                 // Method java/lang/StringBuilder.append:(Ljava/lang/String;)Ljava/lang/StringBuilder;
     604: aload_2
     605: invokevirtual #12                 // Method java/lang/StringBuilder.append:(Ljava/lang/Object;)Ljava/lang/StringBuilder;
     608: invokevirtual #15                 // Method java/lang/StringBuilder.toString:()Ljava/lang/String;
     611: aload_3
     612: invokeinterface #76,  3           // InterfaceMethod org/slf4j/Logger.warn:(Ljava/lang/String;Ljava/lang/Throwable;)V
     617: getstatic     #77                 // Field org/apache/hadoop/hbase/procedure2/StateMachineProcedure$Flow.HAS_MORE_STATE:Lorg/apache/hadoop/hbase/procedure2/StateMachineProcedure$Flow;
     620: areturn
    Exception table:
       from    to  target type
          42   126   558   Class java/io/IOException
         127   527   558   Class java/io/IOException
         528   555   558   Class java/io/IOException

  protected void rollbackState(org.apache.hadoop.hbase.master.procedure.MasterProcedureEnv, org.apache.hadoop.hbase.shaded.protobuf.generated.MasterProcedureProtos$TruncateTableState);
    Code:
       0: aload_2
       1: getstatic     #78                 // Field org/apache/hadoop/hbase/shaded/protobuf/generated/MasterProcedureProtos$TruncateTableState.TRUNCATE_TABLE_PRE_OPERATION:Lorg/apache/hadoop/hbase/shaded/protobuf/generated/MasterProcedureProtos$TruncateTableState;
       4: if_acmpne     8
       7: return
       8: new           #67                 // class java/lang/UnsupportedOperationException
      11: dup
      12: new           #10                 // class java/lang/StringBuilder
      15: dup
      16: invokespecial #11                 // Method java/lang/StringBuilder."<init>":()V
      19: ldc           #68                 // String unhandled state=
      21: invokevirtual #14                 // Method java/lang/StringBuilder.append:(Ljava/lang/String;)Ljava/lang/StringBuilder;
      24: aload_2
      25: invokevirtual #12                 // Method java/lang/StringBuilder.append:(Ljava/lang/Object;)Ljava/lang/StringBuilder;
      28: invokevirtual #15                 // Method java/lang/StringBuilder.toString:()Ljava/lang/String;
      31: invokespecial #69                 // Method java/lang/UnsupportedOperationException."<init>":(Ljava/lang/String;)V
      34: athrow

  protected void completionCleanup(org.apache.hadoop.hbase.master.procedure.MasterProcedureEnv);
    Code:
       0: aload_0
       1: invokevirtual #79                 // Method releaseSyncLatch:()V
       4: return

  protected boolean isRollbackSupported(org.apache.hadoop.hbase.shaded.protobuf.generated.MasterProcedureProtos$TruncateTableState);
    Code:
       0: getstatic     #17                 // Field org/apache/hadoop/hbase/master/procedure/TruncateTableProcedure$1.$SwitchMap$org$apache$hadoop$hbase$shaded$protobuf$generated$MasterProcedureProtos$TruncateTableState:[I
       3: aload_1
       4: invokevirtual #18                 // Method org/apache/hadoop/hbase/shaded/protobuf/generated/MasterProcedureProtos$TruncateTableState.ordinal:()I
       7: iaload
       8: lookupswitch  { // 1
                     1: 28
               default: 30
          }
      28: iconst_1
      29: ireturn
      30: iconst_0
      31: ireturn

  protected org.apache.hadoop.hbase.shaded.protobuf.generated.MasterProcedureProtos$TruncateTableState getState(int);
    Code:
       0: iload_1
       1: invokestatic  #80                 // Method org/apache/hadoop/hbase/shaded/protobuf/generated/MasterProcedureProtos$TruncateTableState.forNumber:(I)Lorg/apache/hadoop/hbase/shaded/protobuf/generated/MasterProcedureProtos$TruncateTableState;
       4: areturn

  protected int getStateId(org.apache.hadoop.hbase.shaded.protobuf.generated.MasterProcedureProtos$TruncateTableState);
    Code:
       0: aload_1
       1: invokevirtual #81                 // Method org/apache/hadoop/hbase/shaded/protobuf/generated/MasterProcedureProtos$TruncateTableState.getNumber:()I
       4: ireturn

  protected org.apache.hadoop.hbase.shaded.protobuf.generated.MasterProcedureProtos$TruncateTableState getInitialState();
    Code:
       0: getstatic     #78                 // Field org/apache/hadoop/hbase/shaded/protobuf/generated/MasterProcedureProtos$TruncateTableState.TRUNCATE_TABLE_PRE_OPERATION:Lorg/apache/hadoop/hbase/shaded/protobuf/generated/MasterProcedureProtos$TruncateTableState;
       3: areturn

  protected boolean holdLock(org.apache.hadoop.hbase.master.procedure.MasterProcedureEnv);
    Code:
       0: iconst_1
       1: ireturn

  public org.apache.hadoop.hbase.TableName getTableName();
    Code:
       0: aload_0
       1: getfield      #4                  // Field tableName:Lorg/apache/hadoop/hbase/TableName;
       4: areturn

  public org.apache.hadoop.hbase.master.procedure.TableProcedureInterface$TableOperationType getTableOperationType();
    Code:
       0: getstatic     #82                 // Field org/apache/hadoop/hbase/master/procedure/TableProcedureInterface$TableOperationType.EDIT:Lorg/apache/hadoop/hbase/master/procedure/TableProcedureInterface$TableOperationType;
       3: areturn

  public void toStringClassDetails(java.lang.StringBuilder);
    Code:
       0: aload_1
       1: aload_0
       2: invokevirtual #83                 // Method java/lang/Object.getClass:()Ljava/lang/Class;
       5: invokevirtual #84                 // Method java/lang/Class.getSimpleName:()Ljava/lang/String;
       8: invokevirtual #14                 // Method java/lang/StringBuilder.append:(Ljava/lang/String;)Ljava/lang/StringBuilder;
      11: pop
      12: aload_1
      13: ldc           #85                 // String  (table=
      15: invokevirtual #14                 // Method java/lang/StringBuilder.append:(Ljava/lang/String;)Ljava/lang/StringBuilder;
      18: pop
      19: aload_1
      20: aload_0
      21: invokevirtual #27                 // Method getTableName:()Lorg/apache/hadoop/hbase/TableName;
      24: invokevirtual #12                 // Method java/lang/StringBuilder.append:(Ljava/lang/Object;)Ljava/lang/StringBuilder;
      27: pop
      28: aload_1
      29: ldc           #86                 // String  preserveSplits=
      31: invokevirtual #14                 // Method java/lang/StringBuilder.append:(Ljava/lang/String;)Ljava/lang/StringBuilder;
      34: pop
      35: aload_1
      36: aload_0
      37: getfield      #7                  // Field preserveSplits:Z
      40: invokevirtual #87                 // Method java/lang/StringBuilder.append:(Z)Ljava/lang/StringBuilder;
      43: pop
      44: aload_1
      45: ldc           #88                 // String )
      47: invokevirtual #14                 // Method java/lang/StringBuilder.append:(Ljava/lang/String;)Ljava/lang/StringBuilder;
      50: pop
      51: return

  protected void serializeStateData(org.apache.hadoop.hbase.procedure2.ProcedureStateSerializer) throws java.io.IOException;
    Code:
       0: aload_0
       1: aload_1
       2: invokespecial #89                 // Method org/apache/hadoop/hbase/master/procedure/AbstractStateMachineTableProcedure.serializeStateData:(Lorg/apache/hadoop/hbase/procedure2/ProcedureStateSerializer;)V
       5: invokestatic  #90                 // Method org/apache/hadoop/hbase/shaded/protobuf/generated/MasterProcedureProtos$TruncateTableStateData.newBuilder:()Lorg/apache/hadoop/hbase/shaded/protobuf/generated/MasterProcedureProtos$TruncateTableStateData$Builder;
       8: aload_0
       9: invokevirtual #91                 // Method getUser:()Lorg/apache/hadoop/hbase/security/User;
      12: invokestatic  #92                 // Method org/apache/hadoop/hbase/master/procedure/MasterProcedureUtil.toProtoUserInfo:(Lorg/apache/hadoop/hbase/security/User;)Lorg/apache/hadoop/hbase/shaded/protobuf/generated/RPCProtos$UserInformation;
      15: invokevirtual #93                 // Method org/apache/hadoop/hbase/shaded/protobuf/generated/MasterProcedureProtos$TruncateTableStateData$Builder.setUserInfo:(Lorg/apache/hadoop/hbase/shaded/protobuf/generated/RPCProtos$UserInformation;)Lorg/apache/hadoop/hbase/shaded/protobuf/generated/MasterProcedureProtos$TruncateTableStateData$Builder;
      18: aload_0
      19: getfield      #7                  // Field preserveSplits:Z
      22: invokevirtual #94                 // Method org/apache/hadoop/hbase/shaded/protobuf/generated/MasterProcedureProtos$TruncateTableStateData$Builder.setPreserveSplits:(Z)Lorg/apache/hadoop/hbase/shaded/protobuf/generated/MasterProcedureProtos$TruncateTableStateData$Builder;
      25: astore_2
      26: aload_0
      27: getfield      #44                 // Field tableDescriptor:Lorg/apache/hadoop/hbase/client/TableDescriptor;
      30: ifnull        48
      33: aload_2
      34: aload_0
      35: getfield      #44                 // Field tableDescriptor:Lorg/apache/hadoop/hbase/client/TableDescriptor;
      38: invokestatic  #95                 // Method org/apache/hadoop/hbase/shaded/protobuf/ProtobufUtil.toTableSchema:(Lorg/apache/hadoop/hbase/client/TableDescriptor;)Lorg/apache/hadoop/hbase/shaded/protobuf/generated/HBaseProtos$TableSchema;
      41: invokevirtual #96                 // Method org/apache/hadoop/hbase/shaded/protobuf/generated/MasterProcedureProtos$TruncateTableStateData$Builder.setTableSchema:(Lorg/apache/hadoop/hbase/shaded/protobuf/generated/HBaseProtos$TableSchema;)Lorg/apache/hadoop/hbase/shaded/protobuf/generated/MasterProcedureProtos$TruncateTableStateData$Builder;
      44: pop
      45: goto          60
      48: aload_2
      49: aload_0
      50: getfield      #4                  // Field tableName:Lorg/apache/hadoop/hbase/TableName;
      53: invokestatic  #97                 // Method org/apache/hadoop/hbase/shaded/protobuf/ProtobufUtil.toProtoTableName:(Lorg/apache/hadoop/hbase/TableName;)Lorg/apache/hadoop/hbase/shaded/protobuf/generated/HBaseProtos$TableName;
      56: invokevirtual #98                 // Method org/apache/hadoop/hbase/shaded/protobuf/generated/MasterProcedureProtos$TruncateTableStateData$Builder.setTableName:(Lorg/apache/hadoop/hbase/shaded/protobuf/generated/HBaseProtos$TableName;)Lorg/apache/hadoop/hbase/shaded/protobuf/generated/MasterProcedureProtos$TruncateTableStateData$Builder;
      59: pop
      60: aload_0
      61: getfield      #33                 // Field regions:Ljava/util/List;
      64: ifnull        110
      67: aload_0
      68: getfield      #33                 // Field regions:Ljava/util/List;
      71: invokeinterface #99,  1           // InterfaceMethod java/util/List.iterator:()Ljava/util/Iterator;
      76: astore_3
      77: aload_3
      78: invokeinterface #100,  1          // InterfaceMethod java/util/Iterator.hasNext:()Z
      83: ifeq          110
      86: aload_3
      87: invokeinterface #101,  1          // InterfaceMethod java/util/Iterator.next:()Ljava/lang/Object;
      92: checkcast     #102                // class org/apache/hadoop/hbase/client/RegionInfo
      95: astore        4
      97: aload_2
      98: aload         4
     100: invokestatic  #103                // Method org/apache/hadoop/hbase/shaded/protobuf/ProtobufUtil.toRegionInfo:(Lorg/apache/hadoop/hbase/client/RegionInfo;)Lorg/apache/hadoop/hbase/shaded/protobuf/generated/HBaseProtos$RegionInfo;
     103: invokevirtual #104                // Method org/apache/hadoop/hbase/shaded/protobuf/generated/MasterProcedureProtos$TruncateTableStateData$Builder.addRegionInfo:(Lorg/apache/hadoop/hbase/shaded/protobuf/generated/HBaseProtos$RegionInfo;)Lorg/apache/hadoop/hbase/shaded/protobuf/generated/MasterProcedureProtos$TruncateTableStateData$Builder;
     106: pop
     107: goto          77
     110: aload_1
     111: aload_2
     112: invokevirtual #105                // Method org/apache/hadoop/hbase/shaded/protobuf/generated/MasterProcedureProtos$TruncateTableStateData$Builder.build:()Lorg/apache/hadoop/hbase/shaded/protobuf/generated/MasterProcedureProtos$TruncateTableStateData;
     115: invokeinterface #106,  2          // InterfaceMethod org/apache/hadoop/hbase/procedure2/ProcedureStateSerializer.serialize:(Lorg/apache/hbase/thirdparty/com/google/protobuf/Message;)V
     120: return

  protected void deserializeStateData(org.apache.hadoop.hbase.procedure2.ProcedureStateSerializer) throws java.io.IOException;
    Code:
       0: aload_0
       1: aload_1
       2: invokespecial #107                // Method org/apache/hadoop/hbase/master/procedure/AbstractStateMachineTableProcedure.deserializeStateData:(Lorg/apache/hadoop/hbase/procedure2/ProcedureStateSerializer;)V
       5: aload_1
       6: ldc           #108                // class org/apache/hadoop/hbase/shaded/protobuf/generated/MasterProcedureProtos$TruncateTableStateData
       8: invokeinterface #109,  2          // InterfaceMethod org/apache/hadoop/hbase/procedure2/ProcedureStateSerializer.deserialize:(Ljava/lang/Class;)Lorg/apache/hbase/thirdparty/com/google/protobuf/Message;
      13: checkcast     #108                // class org/apache/hadoop/hbase/shaded/protobuf/generated/MasterProcedureProtos$TruncateTableStateData
      16: astore_2
      17: aload_0
      18: aload_2
      19: invokevirtual #110                // Method org/apache/hadoop/hbase/shaded/protobuf/generated/MasterProcedureProtos$TruncateTableStateData.getUserInfo:()Lorg/apache/hadoop/hbase/shaded/protobuf/generated/RPCProtos$UserInformation;
      22: invokestatic  #111                // Method org/apache/hadoop/hbase/master/procedure/MasterProcedureUtil.toUserInfo:(Lorg/apache/hadoop/hbase/shaded/protobuf/generated/RPCProtos$UserInformation;)Lorg/apache/hadoop/hbase/security/User;
      25: invokevirtual #112                // Method setUser:(Lorg/apache/hadoop/hbase/security/User;)V
      28: aload_2
      29: invokevirtual #113                // Method org/apache/hadoop/hbase/shaded/protobuf/generated/MasterProcedureProtos$TruncateTableStateData.hasTableSchema:()Z
      32: ifeq          62
      35: aload_0
      36: aload_2
      37: invokevirtual #114                // Method org/apache/hadoop/hbase/shaded/protobuf/generated/MasterProcedureProtos$TruncateTableStateData.getTableSchema:()Lorg/apache/hadoop/hbase/shaded/protobuf/generated/HBaseProtos$TableSchema;
      40: invokestatic  #115                // Method org/apache/hadoop/hbase/shaded/protobuf/ProtobufUtil.toTableDescriptor:(Lorg/apache/hadoop/hbase/shaded/protobuf/generated/HBaseProtos$TableSchema;)Lorg/apache/hadoop/hbase/client/TableDescriptor;
      43: putfield      #44                 // Field tableDescriptor:Lorg/apache/hadoop/hbase/client/TableDescriptor;
      46: aload_0
      47: aload_0
      48: getfield      #44                 // Field tableDescriptor:Lorg/apache/hadoop/hbase/client/TableDescriptor;
      51: invokeinterface #116,  1          // InterfaceMethod org/apache/hadoop/hbase/client/TableDescriptor.getTableName:()Lorg/apache/hadoop/hbase/TableName;
      56: putfield      #4                  // Field tableName:Lorg/apache/hadoop/hbase/TableName;
      59: goto          73
      62: aload_0
      63: aload_2
      64: invokevirtual #117                // Method org/apache/hadoop/hbase/shaded/protobuf/generated/MasterProcedureProtos$TruncateTableStateData.getTableName:()Lorg/apache/hadoop/hbase/shaded/protobuf/generated/HBaseProtos$TableName;
      67: invokestatic  #118                // Method org/apache/hadoop/hbase/shaded/protobuf/ProtobufUtil.toTableName:(Lorg/apache/hadoop/hbase/shaded/protobuf/generated/HBaseProtos$TableName;)Lorg/apache/hadoop/hbase/TableName;
      70: putfield      #4                  // Field tableName:Lorg/apache/hadoop/hbase/TableName;
      73: aload_0
      74: aload_2
      75: invokevirtual #119                // Method org/apache/hadoop/hbase/shaded/protobuf/generated/MasterProcedureProtos$TruncateTableStateData.getPreserveSplits:()Z
      78: putfield      #7                  // Field preserveSplits:Z
      81: aload_2
      82: invokevirtual #120                // Method org/apache/hadoop/hbase/shaded/protobuf/generated/MasterProcedureProtos$TruncateTableStateData.getRegionInfoCount:()I
      85: ifne          96
      88: aload_0
      89: aconst_null
      90: putfield      #33                 // Field regions:Ljava/util/List;
      93: goto          159
      96: aload_0
      97: new           #121                // class java/util/ArrayList
     100: dup
     101: aload_2
     102: invokevirtual #120                // Method org/apache/hadoop/hbase/shaded/protobuf/generated/MasterProcedureProtos$TruncateTableStateData.getRegionInfoCount:()I
     105: invokespecial #122                // Method java/util/ArrayList."<init>":(I)V
     108: putfield      #33                 // Field regions:Ljava/util/List;
     111: aload_2
     112: invokevirtual #123                // Method org/apache/hadoop/hbase/shaded/protobuf/generated/MasterProcedureProtos$TruncateTableStateData.getRegionInfoList:()Ljava/util/List;
     115: invokeinterface #99,  1           // InterfaceMethod java/util/List.iterator:()Ljava/util/Iterator;
     120: astore_3
     121: aload_3
     122: invokeinterface #100,  1          // InterfaceMethod java/util/Iterator.hasNext:()Z
     127: ifeq          159
     130: aload_3
     131: invokeinterface #101,  1          // InterfaceMethod java/util/Iterator.next:()Ljava/lang/Object;
     136: checkcast     #124                // class org/apache/hadoop/hbase/shaded/protobuf/generated/HBaseProtos$RegionInfo
     139: astore        4
     141: aload_0
     142: getfield      #33                 // Field regions:Ljava/util/List;
     145: aload         4
     147: invokestatic  #125                // Method org/apache/hadoop/hbase/shaded/protobuf/ProtobufUtil.toRegionInfo:(Lorg/apache/hadoop/hbase/shaded/protobuf/generated/HBaseProtos$RegionInfo;)Lorg/apache/hadoop/hbase/client/RegionInfo;
     150: invokeinterface #126,  2          // InterfaceMethod java/util/List.add:(Ljava/lang/Object;)Z
     155: pop
     156: goto          121
     159: return

  org.apache.hadoop.hbase.client.RegionInfo getFirstRegionInfo();
    Code:
       0: aload_0
       1: getfield      #33                 // Field regions:Ljava/util/List;
       4: ifnull        19
       7: aload_0
       8: getfield      #33                 // Field regions:Ljava/util/List;
      11: invokeinterface #35,  1           // InterfaceMethod java/util/List.isEmpty:()Z
      16: ifeq          21
      19: aconst_null
      20: areturn
      21: aload_0
      22: getfield      #33                 // Field regions:Ljava/util/List;
      25: iconst_0
      26: invokeinterface #142,  2          // InterfaceMethod java/util/List.get:(I)Ljava/lang/Object;
      31: checkcast     #102                // class org/apache/hadoop/hbase/client/RegionInfo
      34: areturn

  protected boolean isRollbackSupported(java.lang.Object);
    Code:
       0: aload_0
       1: aload_1
       2: checkcast     #143                // class org/apache/hadoop/hbase/shaded/protobuf/generated/MasterProcedureProtos$TruncateTableState
       5: invokevirtual #71                 // Method isRollbackSupported:(Lorg/apache/hadoop/hbase/shaded/protobuf/generated/MasterProcedureProtos$TruncateTableState;)Z
       8: ireturn

  protected java.lang.Object getInitialState();
    Code:
       0: aload_0
       1: invokevirtual #144                // Method getInitialState:()Lorg/apache/hadoop/hbase/shaded/protobuf/generated/MasterProcedureProtos$TruncateTableState;
       4: areturn

  protected int getStateId(java.lang.Object);
    Code:
       0: aload_0
       1: aload_1
       2: checkcast     #143                // class org/apache/hadoop/hbase/shaded/protobuf/generated/MasterProcedureProtos$TruncateTableState
       5: invokevirtual #145                // Method getStateId:(Lorg/apache/hadoop/hbase/shaded/protobuf/generated/MasterProcedureProtos$TruncateTableState;)I
       8: ireturn

  protected java.lang.Object getState(int);
    Code:
       0: aload_0
       1: iload_1
       2: invokevirtual #146                // Method getState:(I)Lorg/apache/hadoop/hbase/shaded/protobuf/generated/MasterProcedureProtos$TruncateTableState;
       5: areturn

  protected void rollbackState(java.lang.Object, java.lang.Object) throws java.io.IOException, java.lang.InterruptedException;
    Code:
       0: aload_0
       1: aload_1
       2: checkcast     #147                // class org/apache/hadoop/hbase/master/procedure/MasterProcedureEnv
       5: aload_2
       6: checkcast     #143                // class org/apache/hadoop/hbase/shaded/protobuf/generated/MasterProcedureProtos$TruncateTableState
       9: invokevirtual #148                // Method rollbackState:(Lorg/apache/hadoop/hbase/master/procedure/MasterProcedureEnv;Lorg/apache/hadoop/hbase/shaded/protobuf/generated/MasterProcedureProtos$TruncateTableState;)V
      12: return

  protected org.apache.hadoop.hbase.procedure2.StateMachineProcedure$Flow executeFromState(java.lang.Object, java.lang.Object) throws org.apache.hadoop.hbase.procedure2.ProcedureSuspendedException, org.apache.hadoop.hbase.procedure2.ProcedureYieldException, java.lang.InterruptedException;
    Code:
       0: aload_0
       1: aload_1
       2: checkcast     #147                // class org/apache/hadoop/hbase/master/procedure/MasterProcedureEnv
       5: aload_2
       6: checkcast     #143                // class org/apache/hadoop/hbase/shaded/protobuf/generated/MasterProcedureProtos$TruncateTableState
       9: invokevirtual #149                // Method executeFromState:(Lorg/apache/hadoop/hbase/master/procedure/MasterProcedureEnv;Lorg/apache/hadoop/hbase/shaded/protobuf/generated/MasterProcedureProtos$TruncateTableState;)Lorg/apache/hadoop/hbase/procedure2/StateMachineProcedure$Flow;
      12: areturn

  protected void completionCleanup(java.lang.Object);
    Code:
       0: aload_0
       1: aload_1
       2: checkcast     #147                // class org/apache/hadoop/hbase/master/procedure/MasterProcedureEnv
       5: invokevirtual #150                // Method completionCleanup:(Lorg/apache/hadoop/hbase/master/procedure/MasterProcedureEnv;)V
       8: return

  protected boolean holdLock(java.lang.Object);
    Code:
       0: aload_0
       1: aload_1
       2: checkcast     #147                // class org/apache/hadoop/hbase/master/procedure/MasterProcedureEnv
       5: invokevirtual #151                // Method holdLock:(Lorg/apache/hadoop/hbase/master/procedure/MasterProcedureEnv;)Z
       8: ireturn

  static {};
    Code:
       0: ldc           #152                // class org/apache/hadoop/hbase/master/procedure/TruncateTableProcedure
       2: invokevirtual #153                // Method java/lang/Class.desiredAssertionStatus:()Z
       5: ifne          12
       8: iconst_1
       9: goto          13
      12: iconst_0
      13: putstatic     #20                 // Field $assertionsDisabled:Z
      16: ldc           #152                // class org/apache/hadoop/hbase/master/procedure/TruncateTableProcedure
      18: invokestatic  #154                // Method org/slf4j/LoggerFactory.getLogger:(Ljava/lang/Class;)Lorg/slf4j/Logger;
      21: putstatic     #8                  // Field LOG:Lorg/slf4j/Logger;
      24: return
}
