Compiled from "Union4.java"
public abstract class org.apache.hadoop.hbase.types.Union4<A, B, C, D> extends org.apache.hadoop.hbase.types.Union3<A, B, C> {
  protected final org.apache.hadoop.hbase.types.DataType<D> typeD;

  public org.apache.hadoop.hbase.types.Union4(org.apache.hadoop.hbase.types.DataType<A>, org.apache.hadoop.hbase.types.DataType<B>, org.apache.hadoop.hbase.types.DataType<C>, org.apache.hadoop.hbase.types.DataType<D>);
    Code:
       0: aload_0
       1: aload_1
       2: aload_2
       3: aload_3
       4: invokespecial #1                  // Method org/apache/hadoop/hbase/types/Union3."<init>":(Lorg/apache/hadoop/hbase/types/DataType;Lorg/apache/hadoop/hbase/types/DataType;Lorg/apache/hadoop/hbase/types/DataType;)V
       7: aload_0
       8: aload         4
      10: putfield      #2                  // Field typeD:Lorg/apache/hadoop/hbase/types/DataType;
      13: return

  public boolean isOrderPreserving();
    Code:
       0: aload_0
       1: invokespecial #3                  // Method org/apache/hadoop/hbase/types/Union3.isOrderPreserving:()Z
       4: ifeq          23
       7: aload_0
       8: getfield      #2                  // Field typeD:Lorg/apache/hadoop/hbase/types/DataType;
      11: invokeinterface #4,  1            // InterfaceMethod org/apache/hadoop/hbase/types/DataType.isOrderPreserving:()Z
      16: ifeq          23
      19: iconst_1
      20: goto          24
      23: iconst_0
      24: ireturn

  public org.apache.hadoop.hbase.util.Order getOrder();
    Code:
       0: aconst_null
       1: areturn

  public boolean isNullable();
    Code:
       0: aload_0
       1: invokespecial #5                  // Method org/apache/hadoop/hbase/types/Union3.isNullable:()Z
       4: ifeq          23
       7: aload_0
       8: getfield      #2                  // Field typeD:Lorg/apache/hadoop/hbase/types/DataType;
      11: invokeinterface #6,  1            // InterfaceMethod org/apache/hadoop/hbase/types/DataType.isNullable:()Z
      16: ifeq          23
      19: iconst_1
      20: goto          24
      23: iconst_0
      24: ireturn

  public boolean isSkippable();
    Code:
       0: aload_0
       1: invokespecial #7                  // Method org/apache/hadoop/hbase/types/Union3.isSkippable:()Z
       4: ifeq          23
       7: aload_0
       8: getfield      #2                  // Field typeD:Lorg/apache/hadoop/hbase/types/DataType;
      11: invokeinterface #8,  1            // InterfaceMethod org/apache/hadoop/hbase/types/DataType.isSkippable:()Z
      16: ifeq          23
      19: iconst_1
      20: goto          24
      23: iconst_0
      24: ireturn

  public D decodeD(org.apache.hadoop.hbase.util.PositionedByteRange);
    Code:
       0: aload_0
       1: aload_1
       2: invokevirtual #9                  // Method decode:(Lorg/apache/hadoop/hbase/util/PositionedByteRange;)Ljava/lang/Object;
       5: areturn
}
