Compiled from "UserQuotaState.java"
public class org.apache.hadoop.hbase.quotas.UserQuotaState extends org.apache.hadoop.hbase.quotas.QuotaState {
  public org.apache.hadoop.hbase.quotas.UserQuotaState();
    Code:
       0: aload_0
       1: invokespecial #1                  // Method org/apache/hadoop/hbase/quotas/QuotaState."<init>":()V
       4: aload_0
       5: aconst_null
       6: putfield      #2                  // Field namespaceLimiters:Ljava/util/Map;
       9: aload_0
      10: aconst_null
      11: putfield      #3                  // Field tableLimiters:Ljava/util/Map;
      14: aload_0
      15: iconst_0
      16: putfield      #4                  // Field bypassGlobals:Z
      19: return

  public org.apache.hadoop.hbase.quotas.UserQuotaState(long);
    Code:
       0: aload_0
       1: lload_1
       2: invokespecial #5                  // Method org/apache/hadoop/hbase/quotas/QuotaState."<init>":(J)V
       5: aload_0
       6: aconst_null
       7: putfield      #2                  // Field namespaceLimiters:Ljava/util/Map;
      10: aload_0
      11: aconst_null
      12: putfield      #3                  // Field tableLimiters:Ljava/util/Map;
      15: aload_0
      16: iconst_0
      17: putfield      #4                  // Field bypassGlobals:Z
      20: return

  public synchronized java.lang.String toString();
    Code:
       0: new           #6                  // class java/lang/StringBuilder
       3: dup
       4: invokespecial #7                  // Method java/lang/StringBuilder."<init>":()V
       7: astore_1
       8: aload_1
       9: new           #6                  // class java/lang/StringBuilder
      12: dup
      13: invokespecial #7                  // Method java/lang/StringBuilder."<init>":()V
      16: ldc           #8                  // String UserQuotaState(ts=
      18: invokevirtual #9                  // Method java/lang/StringBuilder.append:(Ljava/lang/String;)Ljava/lang/StringBuilder;
      21: aload_0
      22: invokevirtual #10                 // Method getLastUpdate:()J
      25: invokevirtual #11                 // Method java/lang/StringBuilder.append:(J)Ljava/lang/StringBuilder;
      28: invokevirtual #12                 // Method java/lang/StringBuilder.toString:()Ljava/lang/String;
      31: invokevirtual #9                  // Method java/lang/StringBuilder.append:(Ljava/lang/String;)Ljava/lang/StringBuilder;
      34: pop
      35: aload_0
      36: getfield      #4                  // Field bypassGlobals:Z
      39: ifeq          49
      42: aload_1
      43: ldc           #13                 // String  bypass-globals
      45: invokevirtual #9                  // Method java/lang/StringBuilder.append:(Ljava/lang/String;)Ljava/lang/StringBuilder;
      48: pop
      49: aload_0
      50: invokevirtual #14                 // Method isBypass:()Z
      53: ifeq          66
      56: aload_1
      57: ldc           #15                 // String  bypass
      59: invokevirtual #9                  // Method java/lang/StringBuilder.append:(Ljava/lang/String;)Ljava/lang/StringBuilder;
      62: pop
      63: goto          271
      66: aload_0
      67: invokevirtual #16                 // Method getGlobalLimiterWithoutUpdatingLastQuery:()Lorg/apache/hadoop/hbase/quotas/QuotaLimiter;
      70: invokestatic  #17                 // Method org/apache/hadoop/hbase/quotas/NoopQuotaLimiter.get:()Lorg/apache/hadoop/hbase/quotas/QuotaLimiter;
      73: if_acmpeq     83
      76: aload_1
      77: ldc           #18                 // String  global-limiter
      79: invokevirtual #9                  // Method java/lang/StringBuilder.append:(Ljava/lang/String;)Ljava/lang/StringBuilder;
      82: pop
      83: aload_0
      84: getfield      #3                  // Field tableLimiters:Ljava/util/Map;
      87: ifnull        177
      90: aload_0
      91: getfield      #3                  // Field tableLimiters:Ljava/util/Map;
      94: invokeinterface #19,  1           // InterfaceMethod java/util/Map.isEmpty:()Z
      99: ifne          177
     102: aload_1
     103: ldc           #20                 // String  [
     105: invokevirtual #9                  // Method java/lang/StringBuilder.append:(Ljava/lang/String;)Ljava/lang/StringBuilder;
     108: pop
     109: aload_0
     110: getfield      #3                  // Field tableLimiters:Ljava/util/Map;
     113: invokeinterface #21,  1           // InterfaceMethod java/util/Map.keySet:()Ljava/util/Set;
     118: invokeinterface #22,  1           // InterfaceMethod java/util/Set.iterator:()Ljava/util/Iterator;
     123: astore_2
     124: aload_2
     125: invokeinterface #23,  1           // InterfaceMethod java/util/Iterator.hasNext:()Z
     130: ifeq          170
     133: aload_2
     134: invokeinterface #24,  1           // InterfaceMethod java/util/Iterator.next:()Ljava/lang/Object;
     139: checkcast     #25                 // class org/apache/hadoop/hbase/TableName
     142: astore_3
     143: aload_1
     144: new           #6                  // class java/lang/StringBuilder
     147: dup
     148: invokespecial #7                  // Method java/lang/StringBuilder."<init>":()V
     151: ldc           #26                 // String
     153: invokevirtual #9                  // Method java/lang/StringBuilder.append:(Ljava/lang/String;)Ljava/lang/StringBuilder;
     156: aload_3
     157: invokevirtual #27                 // Method java/lang/StringBuilder.append:(Ljava/lang/Object;)Ljava/lang/StringBuilder;
     160: invokevirtual #12                 // Method java/lang/StringBuilder.toString:()Ljava/lang/String;
     163: invokevirtual #9                  // Method java/lang/StringBuilder.append:(Ljava/lang/String;)Ljava/lang/StringBuilder;
     166: pop
     167: goto          124
     170: aload_1
     171: ldc           #28                 // String  ]
     173: invokevirtual #9                  // Method java/lang/StringBuilder.append:(Ljava/lang/String;)Ljava/lang/StringBuilder;
     176: pop
     177: aload_0
     178: getfield      #2                  // Field namespaceLimiters:Ljava/util/Map;
     181: ifnull        271
     184: aload_0
     185: getfield      #2                  // Field namespaceLimiters:Ljava/util/Map;
     188: invokeinterface #19,  1           // InterfaceMethod java/util/Map.isEmpty:()Z
     193: ifne          271
     196: aload_1
     197: ldc           #20                 // String  [
     199: invokevirtual #9                  // Method java/lang/StringBuilder.append:(Ljava/lang/String;)Ljava/lang/StringBuilder;
     202: pop
     203: aload_0
     204: getfield      #2                  // Field namespaceLimiters:Ljava/util/Map;
     207: invokeinterface #21,  1           // InterfaceMethod java/util/Map.keySet:()Ljava/util/Set;
     212: invokeinterface #22,  1           // InterfaceMethod java/util/Set.iterator:()Ljava/util/Iterator;
     217: astore_2
     218: aload_2
     219: invokeinterface #23,  1           // InterfaceMethod java/util/Iterator.hasNext:()Z
     224: ifeq          264
     227: aload_2
     228: invokeinterface #24,  1           // InterfaceMethod java/util/Iterator.next:()Ljava/lang/Object;
     233: checkcast     #29                 // class java/lang/String
     236: astore_3
     237: aload_1
     238: new           #6                  // class java/lang/StringBuilder
     241: dup
     242: invokespecial #7                  // Method java/lang/StringBuilder."<init>":()V
     245: ldc           #26                 // String
     247: invokevirtual #9                  // Method java/lang/StringBuilder.append:(Ljava/lang/String;)Ljava/lang/StringBuilder;
     250: aload_3
     251: invokevirtual #9                  // Method java/lang/StringBuilder.append:(Ljava/lang/String;)Ljava/lang/StringBuilder;
     254: invokevirtual #12                 // Method java/lang/StringBuilder.toString:()Ljava/lang/String;
     257: invokevirtual #9                  // Method java/lang/StringBuilder.append:(Ljava/lang/String;)Ljava/lang/StringBuilder;
     260: pop
     261: goto          218
     264: aload_1
     265: ldc           #28                 // String  ]
     267: invokevirtual #9                  // Method java/lang/StringBuilder.append:(Ljava/lang/String;)Ljava/lang/StringBuilder;
     270: pop
     271: aload_1
     272: bipush        41
     274: invokevirtual #30                 // Method java/lang/StringBuilder.append:(C)Ljava/lang/StringBuilder;
     277: pop
     278: aload_1
     279: invokevirtual #12                 // Method java/lang/StringBuilder.toString:()Ljava/lang/String;
     282: areturn

  public synchronized boolean isBypass();
    Code:
       0: aload_0
       1: getfield      #4                  // Field bypassGlobals:Z
       4: ifne          59
       7: aload_0
       8: invokevirtual #16                 // Method getGlobalLimiterWithoutUpdatingLastQuery:()Lorg/apache/hadoop/hbase/quotas/QuotaLimiter;
      11: invokestatic  #17                 // Method org/apache/hadoop/hbase/quotas/NoopQuotaLimiter.get:()Lorg/apache/hadoop/hbase/quotas/QuotaLimiter;
      14: if_acmpne     59
      17: aload_0
      18: getfield      #3                  // Field tableLimiters:Ljava/util/Map;
      21: ifnull        36
      24: aload_0
      25: getfield      #3                  // Field tableLimiters:Ljava/util/Map;
      28: invokeinterface #19,  1           // InterfaceMethod java/util/Map.isEmpty:()Z
      33: ifeq          59
      36: aload_0
      37: getfield      #2                  // Field namespaceLimiters:Ljava/util/Map;
      40: ifnull        55
      43: aload_0
      44: getfield      #2                  // Field namespaceLimiters:Ljava/util/Map;
      47: invokeinterface #19,  1           // InterfaceMethod java/util/Map.isEmpty:()Z
      52: ifeq          59
      55: iconst_1
      56: goto          60
      59: iconst_0
      60: ireturn

  public synchronized boolean hasBypassGlobals();
    Code:
       0: aload_0
       1: getfield      #4                  // Field bypassGlobals:Z
       4: ireturn

  public synchronized void setQuotas(org.apache.hadoop.hbase.shaded.protobuf.generated.QuotaProtos$Quotas);
    Code:
       0: aload_0
       1: aload_1
       2: invokespecial #31                 // Method org/apache/hadoop/hbase/quotas/QuotaState.setQuotas:(Lorg/apache/hadoop/hbase/shaded/protobuf/generated/QuotaProtos$Quotas;)V
       5: aload_0
       6: aload_1
       7: invokevirtual #32                 // Method org/apache/hadoop/hbase/shaded/protobuf/generated/QuotaProtos$Quotas.getBypassGlobals:()Z
      10: putfield      #4                  // Field bypassGlobals:Z
      13: return

  public synchronized void setQuotas(org.apache.hadoop.hbase.TableName, org.apache.hadoop.hbase.shaded.protobuf.generated.QuotaProtos$Quotas);
    Code:
       0: aload_0
       1: aload_0
       2: aload_0
       3: getfield      #3                  // Field tableLimiters:Ljava/util/Map;
       6: aload_1
       7: aload_2
       8: invokespecial #33                 // Method setLimiter:(Ljava/util/Map;Ljava/lang/Object;Lorg/apache/hadoop/hbase/shaded/protobuf/generated/QuotaProtos$Quotas;)Ljava/util/Map;
      11: putfield      #3                  // Field tableLimiters:Ljava/util/Map;
      14: return

  public void setQuotas(java.lang.String, org.apache.hadoop.hbase.shaded.protobuf.generated.QuotaProtos$Quotas);
    Code:
       0: aload_0
       1: aload_0
       2: aload_0
       3: getfield      #2                  // Field namespaceLimiters:Ljava/util/Map;
       6: aload_1
       7: aload_2
       8: invokespecial #33                 // Method setLimiter:(Ljava/util/Map;Ljava/lang/Object;Lorg/apache/hadoop/hbase/shaded/protobuf/generated/QuotaProtos$Quotas;)Ljava/util/Map;
      11: putfield      #2                  // Field namespaceLimiters:Ljava/util/Map;
      14: return

  public synchronized void update(org.apache.hadoop.hbase.quotas.QuotaState);
    Code:
       0: aload_0
       1: aload_1
       2: invokespecial #42                 // Method org/apache/hadoop/hbase/quotas/QuotaState.update:(Lorg/apache/hadoop/hbase/quotas/QuotaState;)V
       5: aload_1
       6: instanceof    #43                 // class org/apache/hadoop/hbase/quotas/UserQuotaState
       9: ifeq          58
      12: aload_1
      13: checkcast     #43                 // class org/apache/hadoop/hbase/quotas/UserQuotaState
      16: astore_2
      17: aload_0
      18: aload_0
      19: getfield      #3                  // Field tableLimiters:Ljava/util/Map;
      22: aload_2
      23: getfield      #3                  // Field tableLimiters:Ljava/util/Map;
      26: invokestatic  #44                 // Method updateLimiters:(Ljava/util/Map;Ljava/util/Map;)Ljava/util/Map;
      29: putfield      #3                  // Field tableLimiters:Ljava/util/Map;
      32: aload_0
      33: aload_0
      34: getfield      #2                  // Field namespaceLimiters:Ljava/util/Map;
      37: aload_2
      38: getfield      #2                  // Field namespaceLimiters:Ljava/util/Map;
      41: invokestatic  #44                 // Method updateLimiters:(Ljava/util/Map;Ljava/util/Map;)Ljava/util/Map;
      44: putfield      #2                  // Field namespaceLimiters:Ljava/util/Map;
      47: aload_0
      48: aload_2
      49: getfield      #4                  // Field bypassGlobals:Z
      52: putfield      #4                  // Field bypassGlobals:Z
      55: goto          73
      58: aload_0
      59: aconst_null
      60: putfield      #3                  // Field tableLimiters:Ljava/util/Map;
      63: aload_0
      64: aconst_null
      65: putfield      #2                  // Field namespaceLimiters:Ljava/util/Map;
      68: aload_0
      69: iconst_0
      70: putfield      #4                  // Field bypassGlobals:Z
      73: return

  public synchronized org.apache.hadoop.hbase.quotas.QuotaLimiter getTableLimiter(org.apache.hadoop.hbase.TableName);
    Code:
       0: aload_0
       1: invokestatic  #55                 // Method org/apache/hadoop/hbase/util/EnvironmentEdgeManager.currentTime:()J
       4: putfield      #56                 // Field lastQuery:J
       7: aload_0
       8: getfield      #3                  // Field tableLimiters:Ljava/util/Map;
      11: ifnull        34
      14: aload_0
      15: getfield      #3                  // Field tableLimiters:Ljava/util/Map;
      18: aload_1
      19: invokeinterface #51,  2           // InterfaceMethod java/util/Map.get:(Ljava/lang/Object;)Ljava/lang/Object;
      24: checkcast     #52                 // class org/apache/hadoop/hbase/quotas/QuotaLimiter
      27: astore_2
      28: aload_2
      29: ifnull        34
      32: aload_2
      33: areturn
      34: aload_0
      35: getfield      #2                  // Field namespaceLimiters:Ljava/util/Map;
      38: ifnull        64
      41: aload_0
      42: getfield      #2                  // Field namespaceLimiters:Ljava/util/Map;
      45: aload_1
      46: invokevirtual #57                 // Method org/apache/hadoop/hbase/TableName.getNamespaceAsString:()Ljava/lang/String;
      49: invokeinterface #51,  2           // InterfaceMethod java/util/Map.get:(Ljava/lang/Object;)Ljava/lang/Object;
      54: checkcast     #52                 // class org/apache/hadoop/hbase/quotas/QuotaLimiter
      57: astore_2
      58: aload_2
      59: ifnull        64
      62: aload_2
      63: areturn
      64: aload_0
      65: invokevirtual #16                 // Method getGlobalLimiterWithoutUpdatingLastQuery:()Lorg/apache/hadoop/hbase/quotas/QuotaLimiter;
      68: areturn
}
