Compiled from "UserProvider.java"
public class org.apache.hadoop.hbase.security.UserProvider extends org.apache.hadoop.hbase.BaseConfigurable {
  static org.apache.hadoop.security.Groups groups;

  public org.apache.hadoop.hbase.security.UserProvider();
    Code:
       0: aload_0
       1: invokespecial #2                  // Method org/apache/hadoop/hbase/BaseConfigurable."<init>":()V
       4: aload_0
       5: aconst_null
       6: putfield      #3                  // Field groupCache:Lorg/apache/hbase/thirdparty/com/google/common/cache/LoadingCache;
       9: return

  public static org.apache.hadoop.security.Groups getGroups();
    Code:
       0: getstatic     #4                  // Field groups:Lorg/apache/hadoop/security/Groups;
       3: areturn

  public static void setGroups(org.apache.hadoop.security.Groups);
    Code:
       0: aload_0
       1: putstatic     #4                  // Field groups:Lorg/apache/hadoop/security/Groups;
       4: return

  public void setConf(org.apache.hadoop.conf.Configuration);
    Code:
       0: aload_0
       1: aload_1
       2: invokespecial #5                  // Method org/apache/hadoop/hbase/BaseConfigurable.setConf:(Lorg/apache/hadoop/conf/Configuration;)V
       5: ldc           #6                  // class org/apache/hadoop/hbase/security/UserProvider
       7: dup
       8: astore_2
       9: monitorenter
      10: getstatic     #4                  // Field groups:Lorg/apache/hadoop/security/Groups;
      13: instanceof    #7                  // class org/apache/hadoop/hbase/security/User$TestingGroups
      16: ifne          26
      19: aload_1
      20: invokestatic  #8                  // Method org/apache/hadoop/security/Groups.getUserToGroupsMappingService:(Lorg/apache/hadoop/conf/Configuration;)Lorg/apache/hadoop/security/Groups;
      23: putstatic     #4                  // Field groups:Lorg/apache/hadoop/security/Groups;
      26: aload_2
      27: monitorexit
      28: goto          36
      31: astore_3
      32: aload_2
      33: monitorexit
      34: aload_3
      35: athrow
      36: aload_0
      37: invokevirtual #9                  // Method getConf:()Lorg/apache/hadoop/conf/Configuration;
      40: ldc           #11                 // String hadoop.security.groups.cache.secs
      42: ldc2_w        #12                 // long 300l
      45: invokevirtual #14                 // Method org/apache/hadoop/conf/Configuration.getLong:(Ljava/lang/String;J)J
      48: ldc2_w        #15                 // long 1000l
      51: lmul
      52: lstore_2
      53: aload_0
      54: invokestatic  #17                 // Method org/apache/hbase/thirdparty/com/google/common/cache/CacheBuilder.newBuilder:()Lorg/apache/hbase/thirdparty/com/google/common/cache/CacheBuilder;
      57: lload_2
      58: getstatic     #18                 // Field java/util/concurrent/TimeUnit.MILLISECONDS:Ljava/util/concurrent/TimeUnit;
      61: invokevirtual #19                 // Method org/apache/hbase/thirdparty/com/google/common/cache/CacheBuilder.refreshAfterWrite:(JLjava/util/concurrent/TimeUnit;)Lorg/apache/hbase/thirdparty/com/google/common/cache/CacheBuilder;
      64: ldc2_w        #20                 // long 10l
      67: lload_2
      68: lmul
      69: getstatic     #18                 // Field java/util/concurrent/TimeUnit.MILLISECONDS:Ljava/util/concurrent/TimeUnit;
      72: invokevirtual #22                 // Method org/apache/hbase/thirdparty/com/google/common/cache/CacheBuilder.expireAfterWrite:(JLjava/util/concurrent/TimeUnit;)Lorg/apache/hbase/thirdparty/com/google/common/cache/CacheBuilder;
      75: bipush        20
      77: invokevirtual #23                 // Method org/apache/hbase/thirdparty/com/google/common/cache/CacheBuilder.concurrencyLevel:(I)Lorg/apache/hbase/thirdparty/com/google/common/cache/CacheBuilder;
      80: new           #24                 // class org/apache/hadoop/hbase/security/UserProvider$1
      83: dup
      84: aload_0
      85: invokespecial #25                 // Method org/apache/hadoop/hbase/security/UserProvider$1."<init>":(Lorg/apache/hadoop/hbase/security/UserProvider;)V
      88: invokevirtual #26                 // Method org/apache/hbase/thirdparty/com/google/common/cache/CacheBuilder.build:(Lorg/apache/hbase/thirdparty/com/google/common/cache/CacheLoader;)Lorg/apache/hbase/thirdparty/com/google/common/cache/LoadingCache;
      91: putfield      #3                  // Field groupCache:Lorg/apache/hbase/thirdparty/com/google/common/cache/LoadingCache;
      94: return
    Exception table:
       from    to  target type
          10    28    31   any
          31    34    31   any

  public static org.apache.hadoop.hbase.security.UserProvider instantiate(org.apache.hadoop.conf.Configuration);
    Code:
       0: aload_0
       1: ldc           #27                 // String hbase.client.userprovider.class
       3: ldc           #6                  // class org/apache/hadoop/hbase/security/UserProvider
       5: ldc           #6                  // class org/apache/hadoop/hbase/security/UserProvider
       7: invokevirtual #28                 // Method org/apache/hadoop/conf/Configuration.getClass:(Ljava/lang/String;Ljava/lang/Class;Ljava/lang/Class;)Ljava/lang/Class;
      10: astore_1
      11: aload_1
      12: aload_0
      13: invokestatic  #29                 // Method org/apache/hadoop/util/ReflectionUtils.newInstance:(Ljava/lang/Class;Lorg/apache/hadoop/conf/Configuration;)Ljava/lang/Object;
      16: checkcast     #6                  // class org/apache/hadoop/hbase/security/UserProvider
      19: areturn

  public static void setUserProviderForTesting(org.apache.hadoop.conf.Configuration, java.lang.Class<? extends org.apache.hadoop.hbase.security.UserProvider>);
    Code:
       0: aload_0
       1: ldc           #27                 // String hbase.client.userprovider.class
       3: aload_1
       4: invokevirtual #30                 // Method java/lang/Class.getName:()Ljava/lang/String;
       7: invokevirtual #31                 // Method org/apache/hadoop/conf/Configuration.set:(Ljava/lang/String;Ljava/lang/String;)V
      10: return

  public java.lang.String getCurrentUserName() throws java.io.IOException;
    Code:
       0: aload_0
       1: invokevirtual #32                 // Method getCurrent:()Lorg/apache/hadoop/hbase/security/User;
       4: astore_1
       5: aload_1
       6: ifnonnull     13
       9: aconst_null
      10: goto          17
      13: aload_1
      14: invokevirtual #33                 // Method org/apache/hadoop/hbase/security/User.getName:()Ljava/lang/String;
      17: areturn

  public boolean isHBaseSecurityEnabled();
    Code:
       0: aload_0
       1: invokevirtual #9                  // Method getConf:()Lorg/apache/hadoop/conf/Configuration;
       4: invokestatic  #34                 // Method org/apache/hadoop/hbase/security/User.isHBaseSecurityEnabled:(Lorg/apache/hadoop/conf/Configuration;)Z
       7: ireturn

  public boolean isHadoopSecurityEnabled();
    Code:
       0: invokestatic  #35                 // Method org/apache/hadoop/hbase/security/User.isSecurityEnabled:()Z
       3: ireturn

  public boolean shouldLoginFromKeytab();
    Code:
       0: aload_0
       1: invokevirtual #9                  // Method getConf:()Lorg/apache/hadoop/conf/Configuration;
       4: invokestatic  #36                 // Method org/apache/hadoop/hbase/security/User.shouldLoginFromKeytab:(Lorg/apache/hadoop/conf/Configuration;)Z
       7: ireturn

  public org.apache.hadoop.hbase.security.User getCurrent() throws java.io.IOException;
    Code:
       0: invokestatic  #37                 // Method org/apache/hadoop/hbase/security/User.getCurrent:()Lorg/apache/hadoop/hbase/security/User;
       3: areturn

  public org.apache.hadoop.hbase.security.User create(org.apache.hadoop.security.UserGroupInformation);
    Code:
       0: aload_1
       1: ifnonnull     6
       4: aconst_null
       5: areturn
       6: new           #38                 // class org/apache/hadoop/hbase/security/User$SecureHadoopUser
       9: dup
      10: aload_1
      11: aload_0
      12: getfield      #3                  // Field groupCache:Lorg/apache/hbase/thirdparty/com/google/common/cache/LoadingCache;
      15: invokespecial #39                 // Method org/apache/hadoop/hbase/security/User$SecureHadoopUser."<init>":(Lorg/apache/hadoop/security/UserGroupInformation;Lorg/apache/hbase/thirdparty/com/google/common/cache/LoadingCache;)V
      18: areturn

  public void login(java.lang.String, java.lang.String, java.lang.String) throws java.io.IOException;
    Code:
       0: aload_0
       1: invokevirtual #9                  // Method getConf:()Lorg/apache/hadoop/conf/Configuration;
       4: aload_1
       5: aload_2
       6: aload_3
       7: invokestatic  #40                 // Method org/apache/hadoop/hbase/security/User.login:(Lorg/apache/hadoop/conf/Configuration;Ljava/lang/String;Ljava/lang/String;Ljava/lang/String;)V
      10: return

  public void login(java.lang.String, java.lang.String) throws java.io.IOException;
    Code:
       0: aload_0
       1: invokevirtual #9                  // Method getConf:()Lorg/apache/hadoop/conf/Configuration;
       4: aload_1
       5: invokevirtual #41                 // Method org/apache/hadoop/conf/Configuration.get:(Ljava/lang/String;)Ljava/lang/String;
       8: aload_0
       9: invokevirtual #9                  // Method getConf:()Lorg/apache/hadoop/conf/Configuration;
      12: aload_2
      13: invokevirtual #41                 // Method org/apache/hadoop/conf/Configuration.get:(Ljava/lang/String;)Ljava/lang/String;
      16: invokestatic  #42                 // Method org/apache/hadoop/hbase/security/User.login:(Ljava/lang/String;Ljava/lang/String;)V
      19: return

  static org.apache.hbase.thirdparty.com.google.common.util.concurrent.ListeningExecutorService access$100();
    Code:
       0: getstatic     #1                  // Field executor:Lorg/apache/hbase/thirdparty/com/google/common/util/concurrent/ListeningExecutorService;
       3: areturn

  static {};
    Code:
       0: iconst_1
       1: new           #43                 // class org/apache/hbase/thirdparty/com/google/common/util/concurrent/ThreadFactoryBuilder
       4: dup
       5: invokespecial #44                 // Method org/apache/hbase/thirdparty/com/google/common/util/concurrent/ThreadFactoryBuilder."<init>":()V
       8: iconst_1
       9: invokevirtual #45                 // Method org/apache/hbase/thirdparty/com/google/common/util/concurrent/ThreadFactoryBuilder.setDaemon:(Z)Lorg/apache/hbase/thirdparty/com/google/common/util/concurrent/ThreadFactoryBuilder;
      12: ldc           #46                 // String group-cache-%d
      14: invokevirtual #47                 // Method org/apache/hbase/thirdparty/com/google/common/util/concurrent/ThreadFactoryBuilder.setNameFormat:(Ljava/lang/String;)Lorg/apache/hbase/thirdparty/com/google/common/util/concurrent/ThreadFactoryBuilder;
      17: invokevirtual #48                 // Method org/apache/hbase/thirdparty/com/google/common/util/concurrent/ThreadFactoryBuilder.build:()Ljava/util/concurrent/ThreadFactory;
      20: invokestatic  #49                 // Method java/util/concurrent/Executors.newScheduledThreadPool:(ILjava/util/concurrent/ThreadFactory;)Ljava/util/concurrent/ScheduledExecutorService;
      23: invokestatic  #50                 // Method org/apache/hbase/thirdparty/com/google/common/util/concurrent/MoreExecutors.listeningDecorator:(Ljava/util/concurrent/ScheduledExecutorService;)Lorg/apache/hbase/thirdparty/com/google/common/util/concurrent/ListeningScheduledExecutorService;
      26: putstatic     #1                  // Field executor:Lorg/apache/hbase/thirdparty/com/google/common/util/concurrent/ListeningExecutorService;
      29: invokestatic  #51                 // Method org/apache/hadoop/security/Groups.getUserToGroupsMappingService:()Lorg/apache/hadoop/security/Groups;
      32: putstatic     #4                  // Field groups:Lorg/apache/hadoop/security/Groups;
      35: return
}
