Compiled from "VisibilityLabelsWithDeletesTestBase.java"
class org.apache.hadoop.hbase.security.visibility.VisibilityLabelsWithDeletesTestBase$2 implements java.security.PrivilegedExceptionAction<org.apache.hadoop.hbase.protobuf.generated.VisibilityLabelsProtos$VisibilityLabelsResponse> {
  final org.apache.hadoop.hbase.security.visibility.VisibilityLabelsWithDeletesTestBase this$0;

  org.apache.hadoop.hbase.security.visibility.VisibilityLabelsWithDeletesTestBase$2(org.apache.hadoop.hbase.security.visibility.VisibilityLabelsWithDeletesTestBase);
    Code:
       0: aload_0
       1: aload_1
       2: putfield      #2                  // Field this$0:Lorg/apache/hadoop/hbase/security/visibility/VisibilityLabelsWithDeletesTestBase;
       5: aload_0
       6: invokespecial #3                  // Method java/lang/Object."<init>":()V
       9: return

  public org.apache.hadoop.hbase.protobuf.generated.VisibilityLabelsProtos$VisibilityLabelsResponse run() throws java.lang.Exception;
    Code:
       0: getstatic     #4                  // Field org/apache/hadoop/hbase/security/visibility/VisibilityLabelsWithDeletesTestBase.conf:Lorg/apache/hadoop/conf/Configuration;
       3: invokestatic  #5                  // Method org/apache/hadoop/hbase/client/ConnectionFactory.createConnection:(Lorg/apache/hadoop/conf/Configuration;)Lorg/apache/hadoop/hbase/client/Connection;
       6: astore_1
       7: aconst_null
       8: astore_2
       9: aload_1
      10: iconst_4
      11: anewarray     #6                  // class java/lang/String
      14: dup
      15: iconst_0
      16: ldc           #7                  // String CONFIDENTIAL
      18: aastore
      19: dup
      20: iconst_1
      21: ldc           #8                  // String PRIVATE
      23: aastore
      24: dup
      25: iconst_2
      26: ldc           #9                  // String SECRET
      28: aastore
      29: dup
      30: iconst_3
      31: ldc           #10                 // String TOPSECRET
      33: aastore
      34: getstatic     #11                 // Field org/apache/hadoop/hbase/security/visibility/VisibilityLabelsWithDeletesTestBase.SUPERUSER:Lorg/apache/hadoop/hbase/security/User;
      37: invokevirtual #12                 // Method org/apache/hadoop/hbase/security/User.getShortName:()Ljava/lang/String;
      40: invokestatic  #13                 // Method org/apache/hadoop/hbase/security/visibility/VisibilityClient.setAuths:(Lorg/apache/hadoop/hbase/client/Connection;[Ljava/lang/String;Ljava/lang/String;)Lorg/apache/hadoop/hbase/protobuf/generated/VisibilityLabelsProtos$VisibilityLabelsResponse;
      43: astore_3
      44: aload_1
      45: ifnull        78
      48: aload_2
      49: ifnull        72
      52: aload_1
      53: invokeinterface #14,  1           // InterfaceMethod org/apache/hadoop/hbase/client/Connection.close:()V
      58: goto          78
      61: astore        4
      63: aload_2
      64: aload         4
      66: invokevirtual #16                 // Method java/lang/Throwable.addSuppressed:(Ljava/lang/Throwable;)V
      69: goto          78
      72: aload_1
      73: invokeinterface #14,  1           // InterfaceMethod org/apache/hadoop/hbase/client/Connection.close:()V
      78: aload_3
      79: areturn
      80: astore_3
      81: aload_3
      82: astore_2
      83: aload_3
      84: athrow
      85: astore        5
      87: aload_1
      88: ifnull        121
      91: aload_2
      92: ifnull        115
      95: aload_1
      96: invokeinterface #14,  1           // InterfaceMethod org/apache/hadoop/hbase/client/Connection.close:()V
     101: goto          121
     104: astore        6
     106: aload_2
     107: aload         6
     109: invokevirtual #16                 // Method java/lang/Throwable.addSuppressed:(Ljava/lang/Throwable;)V
     112: goto          121
     115: aload_1
     116: invokeinterface #14,  1           // InterfaceMethod org/apache/hadoop/hbase/client/Connection.close:()V
     121: aload         5
     123: athrow
     124: astore_1
     125: aconst_null
     126: areturn
    Exception table:
       from    to  target type
          52    58    61   Class java/lang/Throwable
           9    44    80   Class java/lang/Throwable
           9    44    85   any
          95   101   104   Class java/lang/Throwable
          80    87    85   any
           0    78   124   Class java/lang/Throwable
          80   124   124   Class java/lang/Throwable

  public java.lang.Object run() throws java.lang.Exception;
    Code:
       0: aload_0
       1: invokevirtual #17                 // Method run:()Lorg/apache/hadoop/hbase/protobuf/generated/VisibilityLabelsProtos$VisibilityLabelsResponse;
       4: areturn
}
