Compiled from "VisibilityNewVersionBehaivorTracker.java"
class org.apache.hadoop.hbase.security.visibility.VisibilityNewVersionBehaivorTracker$VisibilityDeleteVersionsNode extends org.apache.hadoop.hbase.regionserver.querymatcher.NewVersionBehaviorTracker$DeleteVersionsNode {
  final org.apache.hadoop.hbase.security.visibility.VisibilityNewVersionBehaivorTracker this$0;

  protected org.apache.hadoop.hbase.security.visibility.VisibilityNewVersionBehaivorTracker$VisibilityDeleteVersionsNode(org.apache.hadoop.hbase.security.visibility.VisibilityNewVersionBehaivorTracker, long, long, org.apache.hadoop.hbase.security.visibility.VisibilityNewVersionBehaivorTracker$TagInfo);
    Code:
       0: aload_0
       1: aload_1
       2: putfield      #4                  // Field this$0:Lorg/apache/hadoop/hbase/security/visibility/VisibilityNewVersionBehaivorTracker;
       5: aload_0
       6: aload_1
       7: invokespecial #5                  // Method org/apache/hadoop/hbase/regionserver/querymatcher/NewVersionBehaviorTracker$DeleteVersionsNode."<init>":(Lorg/apache/hadoop/hbase/regionserver/querymatcher/NewVersionBehaviorTracker;)V
      10: aload_0
      11: new           #6                  // class java/util/HashMap
      14: dup
      15: invokespecial #7                  // Method java/util/HashMap."<init>":()V
      18: putfield      #3                  // Field deletesMap:Ljava/util/Map;
      21: aload_0
      22: new           #8                  // class java/util/TreeMap
      25: dup
      26: invokespecial #9                  // Method java/util/TreeMap."<init>":()V
      29: putfield      #2                  // Field mvccCountingMap:Ljava/util/NavigableMap;
      32: aload_0
      33: aload         6
      35: putfield      #1                  // Field tagInfo:Lorg/apache/hadoop/hbase/security/visibility/VisibilityNewVersionBehaivorTracker$TagInfo;
      38: aload_0
      39: lload_2
      40: putfield      #10                 // Field ts:J
      43: aload_0
      44: lload         4
      46: putfield      #11                 // Field mvcc:J
      49: aload_0
      50: getfield      #2                  // Field mvccCountingMap:Ljava/util/NavigableMap;
      53: ldc2_w        #13                 // long 9223372036854775807l
      56: invokestatic  #15                 // Method java/lang/Long.valueOf:(J)Ljava/lang/Long;
      59: new           #16                 // class java/util/TreeSet
      62: dup
      63: invokespecial #17                 // Method java/util/TreeSet."<init>":()V
      66: invokeinterface #18,  3           // InterfaceMethod java/util/NavigableMap.put:(Ljava/lang/Object;Ljava/lang/Object;)Ljava/lang/Object;
      71: pop
      72: return

  protected org.apache.hadoop.hbase.security.visibility.VisibilityNewVersionBehaivorTracker$VisibilityDeleteVersionsNode getDeepCopy();
    Code:
       0: new           #19                 // class org/apache/hadoop/hbase/security/visibility/VisibilityNewVersionBehaivorTracker$VisibilityDeleteVersionsNode
       3: dup
       4: aload_0
       5: getfield      #4                  // Field this$0:Lorg/apache/hadoop/hbase/security/visibility/VisibilityNewVersionBehaivorTracker;
       8: aload_0
       9: getfield      #10                 // Field ts:J
      12: aload_0
      13: getfield      #11                 // Field mvcc:J
      16: aload_0
      17: getfield      #1                  // Field tagInfo:Lorg/apache/hadoop/hbase/security/visibility/VisibilityNewVersionBehaivorTracker$TagInfo;
      20: invokespecial #20                 // Method "<init>":(Lorg/apache/hadoop/hbase/security/visibility/VisibilityNewVersionBehaivorTracker;JJLorg/apache/hadoop/hbase/security/visibility/VisibilityNewVersionBehaivorTracker$TagInfo;)V
      23: astore_1
      24: aload_0
      25: getfield      #3                  // Field deletesMap:Ljava/util/Map;
      28: invokeinterface #21,  1           // InterfaceMethod java/util/Map.entrySet:()Ljava/util/Set;
      33: invokeinterface #22,  1           // InterfaceMethod java/util/Set.iterator:()Ljava/util/Iterator;
      38: astore_2
      39: aload_2
      40: invokeinterface #23,  1           // InterfaceMethod java/util/Iterator.hasNext:()Z
      45: ifeq          93
      48: aload_2
      49: invokeinterface #24,  1           // InterfaceMethod java/util/Iterator.next:()Ljava/lang/Object;
      54: checkcast     #25                 // class java/util/Map$Entry
      57: astore_3
      58: aload_1
      59: getfield      #3                  // Field deletesMap:Ljava/util/Map;
      62: aload_3
      63: invokeinterface #26,  1           // InterfaceMethod java/util/Map$Entry.getKey:()Ljava/lang/Object;
      68: new           #8                  // class java/util/TreeMap
      71: dup
      72: aload_3
      73: invokeinterface #27,  1           // InterfaceMethod java/util/Map$Entry.getValue:()Ljava/lang/Object;
      78: checkcast     #28                 // class java/util/SortedMap
      81: invokespecial #29                 // Method java/util/TreeMap."<init>":(Ljava/util/SortedMap;)V
      84: invokeinterface #30,  3           // InterfaceMethod java/util/Map.put:(Ljava/lang/Object;Ljava/lang/Object;)Ljava/lang/Object;
      89: pop
      90: goto          39
      93: aload_0
      94: getfield      #2                  // Field mvccCountingMap:Ljava/util/NavigableMap;
      97: invokeinterface #31,  1           // InterfaceMethod java/util/NavigableMap.entrySet:()Ljava/util/Set;
     102: invokeinterface #22,  1           // InterfaceMethod java/util/Set.iterator:()Ljava/util/Iterator;
     107: astore_2
     108: aload_2
     109: invokeinterface #23,  1           // InterfaceMethod java/util/Iterator.hasNext:()Z
     114: ifeq          162
     117: aload_2
     118: invokeinterface #24,  1           // InterfaceMethod java/util/Iterator.next:()Ljava/lang/Object;
     123: checkcast     #25                 // class java/util/Map$Entry
     126: astore_3
     127: aload_1
     128: getfield      #2                  // Field mvccCountingMap:Ljava/util/NavigableMap;
     131: aload_3
     132: invokeinterface #26,  1           // InterfaceMethod java/util/Map$Entry.getKey:()Ljava/lang/Object;
     137: new           #16                 // class java/util/TreeSet
     140: dup
     141: aload_3
     142: invokeinterface #27,  1           // InterfaceMethod java/util/Map$Entry.getValue:()Ljava/lang/Object;
     147: checkcast     #32                 // class java/util/SortedSet
     150: invokespecial #33                 // Method java/util/TreeSet."<init>":(Ljava/util/SortedSet;)V
     153: invokeinterface #18,  3           // InterfaceMethod java/util/NavigableMap.put:(Ljava/lang/Object;Ljava/lang/Object;)Ljava/lang/Object;
     158: pop
     159: goto          108
     162: aload_1
     163: areturn

  public void addVersionDelete(org.apache.hadoop.hbase.Cell);
    Code:
       0: aload_0
       1: getfield      #3                  // Field deletesMap:Ljava/util/Map;
       4: aload_1
       5: invokeinterface #34,  1           // InterfaceMethod org/apache/hadoop/hbase/Cell.getTimestamp:()J
      10: invokestatic  #15                 // Method java/lang/Long.valueOf:(J)Ljava/lang/Long;
      13: invokeinterface #35,  2           // InterfaceMethod java/util/Map.get:(Ljava/lang/Object;)Ljava/lang/Object;
      18: checkcast     #28                 // class java/util/SortedMap
      21: astore_2
      22: aload_2
      23: ifnonnull     54
      26: new           #8                  // class java/util/TreeMap
      29: dup
      30: invokespecial #9                  // Method java/util/TreeMap."<init>":()V
      33: astore_2
      34: aload_0
      35: getfield      #3                  // Field deletesMap:Ljava/util/Map;
      38: aload_1
      39: invokeinterface #34,  1           // InterfaceMethod org/apache/hadoop/hbase/Cell.getTimestamp:()J
      44: invokestatic  #15                 // Method java/lang/Long.valueOf:(J)Ljava/lang/Long;
      47: aload_2
      48: invokeinterface #30,  3           // InterfaceMethod java/util/Map.put:(Ljava/lang/Object;Ljava/lang/Object;)Ljava/lang/Object;
      53: pop
      54: aload_2
      55: aload_1
      56: invokeinterface #36,  1           // InterfaceMethod org/apache/hadoop/hbase/Cell.getSequenceId:()J
      61: invokestatic  #15                 // Method java/lang/Long.valueOf:(J)Ljava/lang/Long;
      64: new           #37                 // class org/apache/hadoop/hbase/security/visibility/VisibilityNewVersionBehaivorTracker$TagInfo
      67: dup
      68: aload_1
      69: aconst_null
      70: invokespecial #38                 // Method org/apache/hadoop/hbase/security/visibility/VisibilityNewVersionBehaivorTracker$TagInfo."<init>":(Lorg/apache/hadoop/hbase/Cell;Lorg/apache/hadoop/hbase/security/visibility/VisibilityNewVersionBehaivorTracker$1;)V
      73: invokeinterface #39,  3           // InterfaceMethod java/util/SortedMap.put:(Ljava/lang/Object;Ljava/lang/Object;)Ljava/lang/Object;
      78: pop
      79: aload_0
      80: getfield      #2                  // Field mvccCountingMap:Ljava/util/NavigableMap;
      83: aload_1
      84: invokeinterface #36,  1           // InterfaceMethod org/apache/hadoop/hbase/Cell.getSequenceId:()J
      89: invokestatic  #15                 // Method java/lang/Long.valueOf:(J)Ljava/lang/Long;
      92: invokeinterface #40,  2           // InterfaceMethod java/util/NavigableMap.ceilingEntry:(Ljava/lang/Object;)Ljava/util/Map$Entry;
      97: invokeinterface #27,  1           // InterfaceMethod java/util/Map$Entry.getValue:()Ljava/lang/Object;
     102: checkcast     #32                 // class java/util/SortedSet
     105: astore_3
     106: new           #16                 // class java/util/TreeSet
     109: dup
     110: aload_3
     111: aload_1
     112: invokeinterface #36,  1           // InterfaceMethod org/apache/hadoop/hbase/Cell.getSequenceId:()J
     117: invokestatic  #15                 // Method java/lang/Long.valueOf:(J)Ljava/lang/Long;
     120: invokeinterface #41,  2           // InterfaceMethod java/util/SortedSet.headSet:(Ljava/lang/Object;)Ljava/util/SortedSet;
     125: invokespecial #33                 // Method java/util/TreeSet."<init>":(Ljava/util/SortedSet;)V
     128: astore        4
     130: aload_0
     131: getfield      #2                  // Field mvccCountingMap:Ljava/util/NavigableMap;
     134: aload_1
     135: invokeinterface #36,  1           // InterfaceMethod org/apache/hadoop/hbase/Cell.getSequenceId:()J
     140: invokestatic  #15                 // Method java/lang/Long.valueOf:(J)Ljava/lang/Long;
     143: aload         4
     145: invokeinterface #18,  3           // InterfaceMethod java/util/NavigableMap.put:(Ljava/lang/Object;Ljava/lang/Object;)Ljava/lang/Object;
     150: pop
     151: return

  protected org.apache.hadoop.hbase.regionserver.querymatcher.NewVersionBehaviorTracker$DeleteVersionsNode getDeepCopy();
    Code:
       0: aload_0
       1: invokevirtual #42                 // Method getDeepCopy:()Lorg/apache/hadoop/hbase/security/visibility/VisibilityNewVersionBehaivorTracker$VisibilityDeleteVersionsNode;
       4: areturn

  static java.util.Map access$100(org.apache.hadoop.hbase.security.visibility.VisibilityNewVersionBehaivorTracker$VisibilityDeleteVersionsNode);
    Code:
       0: aload_0
       1: getfield      #3                  // Field deletesMap:Ljava/util/Map;
       4: areturn

  static java.util.NavigableMap access$200(org.apache.hadoop.hbase.security.visibility.VisibilityNewVersionBehaivorTracker$VisibilityDeleteVersionsNode);
    Code:
       0: aload_0
       1: getfield      #2                  // Field mvccCountingMap:Ljava/util/NavigableMap;
       4: areturn

  static org.apache.hadoop.hbase.security.visibility.VisibilityNewVersionBehaivorTracker$TagInfo access$300(org.apache.hadoop.hbase.security.visibility.VisibilityNewVersionBehaivorTracker$VisibilityDeleteVersionsNode);
    Code:
       0: aload_0
       1: getfield      #1                  // Field tagInfo:Lorg/apache/hadoop/hbase/security/visibility/VisibilityNewVersionBehaivorTracker$TagInfo;
       4: areturn
}
