Compiled from "VisibilityConstants.java"
public final class org.apache.hadoop.hbase.security.visibility.VisibilityConstants {
  public static final java.lang.String VISIBILITY_LABELS_ATTR_KEY;

  public static final org.apache.hadoop.hbase.TableName LABELS_TABLE_NAME;

  public static final byte[] LABELS_TABLE_FAMILY;

  public static final byte[] LABEL_QUALIFIER;

  public static final byte SORTED_ORDINAL_SERIALIZATION_FORMAT;

  public static final byte[] SORTED_ORDINAL_SERIALIZATION_FORMAT_TAG_VAL;

  public static final java.lang.String CHECK_AUTHS_FOR_MUTATION;

  public static final java.lang.String NOT_OPERATOR;

  public static final java.lang.String AND_OPERATOR;

  public static final java.lang.String OR_OPERATOR;

  public static final java.lang.String OPEN_PARAN;

  public static final java.lang.String CLOSED_PARAN;

  public static final int NON_EXIST_LABEL_ORDINAL;

  public org.apache.hadoop.hbase.security.visibility.VisibilityConstants();
    Code:
       0: aload_0
       1: invokespecial #1                  // Method java/lang/Object."<init>":()V
       4: return

  static {};
    Code:
       0: getstatic     #2                  // Field org/apache/hadoop/hbase/NamespaceDescriptor.SYSTEM_NAMESPACE_NAME_STR:Ljava/lang/String;
       3: ldc           #3                  // String labels
       5: invokestatic  #4                  // Method org/apache/hadoop/hbase/TableName.valueOf:(Ljava/lang/String;Ljava/lang/String;)Lorg/apache/hadoop/hbase/TableName;
       8: putstatic     #5                  // Field LABELS_TABLE_NAME:Lorg/apache/hadoop/hbase/TableName;
      11: ldc           #6                  // String f
      13: invokestatic  #7                  // Method org/apache/hadoop/hbase/util/Bytes.toBytes:(Ljava/lang/String;)[B
      16: putstatic     #8                  // Field LABELS_TABLE_FAMILY:[B
      19: iconst_1
      20: newarray       byte
      22: putstatic     #9                  // Field LABEL_QUALIFIER:[B
      25: iconst_1
      26: newarray       byte
      28: dup
      29: iconst_0
      30: iconst_1
      31: bastore
      32: putstatic     #11                 // Field SORTED_ORDINAL_SERIALIZATION_FORMAT_TAG_VAL:[B
      35: return
}
