Compiled from "VisibilityController.java"
class org.apache.hadoop.hbase.security.visibility.VisibilityController$DeleteVersionVisibilityExpressionFilter extends org.apache.hadoop.hbase.filter.FilterBase {
  public org.apache.hadoop.hbase.security.visibility.VisibilityController$DeleteVersionVisibilityExpressionFilter(java.util.List<org.apache.hadoop.hbase.Tag>, java.lang.Byte);
    Code:
       0: aload_0
       1: invokespecial #1                  // Method org/apache/hadoop/hbase/filter/FilterBase."<init>":()V
       4: aload_0
       5: aload_1
       6: putfield      #2                  // Field deleteCellVisTags:Ljava/util/List;
       9: aload_0
      10: aload_2
      11: putfield      #3                  // Field deleteCellVisTagsFormat:Ljava/lang/Byte;
      14: return

  public boolean filterRowKey(org.apache.hadoop.hbase.Cell) throws java.io.IOException;
    Code:
       0: iconst_0
       1: ireturn

  public org.apache.hadoop.hbase.filter.Filter$ReturnCode filterCell(org.apache.hadoop.hbase.Cell) throws java.io.IOException;
    Code:
       0: new           #4                  // class java/util/ArrayList
       3: dup
       4: invokespecial #5                  // Method java/util/ArrayList."<init>":()V
       7: astore_2
       8: aload_1
       9: aload_2
      10: invokestatic  #6                  // Method org/apache/hadoop/hbase/security/visibility/VisibilityUtils.extractVisibilityTags:(Lorg/apache/hadoop/hbase/Cell;Ljava/util/List;)Ljava/lang/Byte;
      13: astore_3
      14: aload_2
      15: invokeinterface #7,  1            // InterfaceMethod java/util/List.isEmpty:()Z
      20: ifeq          39
      23: aload_0
      24: getfield      #2                  // Field deleteCellVisTags:Ljava/util/List;
      27: invokeinterface #7,  1            // InterfaceMethod java/util/List.isEmpty:()Z
      32: ifeq          39
      35: getstatic     #8                  // Field org/apache/hadoop/hbase/filter/Filter$ReturnCode.INCLUDE:Lorg/apache/hadoop/hbase/filter/Filter$ReturnCode;
      38: areturn
      39: invokestatic  #9                  // Method org/apache/hadoop/hbase/security/visibility/VisibilityLabelServiceManager.getInstance:()Lorg/apache/hadoop/hbase/security/visibility/VisibilityLabelServiceManager;
      42: invokevirtual #10                 // Method org/apache/hadoop/hbase/security/visibility/VisibilityLabelServiceManager.getVisibilityLabelService:()Lorg/apache/hadoop/hbase/security/visibility/VisibilityLabelService;
      45: aload_2
      46: aload_3
      47: aload_0
      48: getfield      #2                  // Field deleteCellVisTags:Ljava/util/List;
      51: aload_0
      52: getfield      #3                  // Field deleteCellVisTagsFormat:Ljava/lang/Byte;
      55: invokeinterface #11,  5           // InterfaceMethod org/apache/hadoop/hbase/security/visibility/VisibilityLabelService.matchVisibility:(Ljava/util/List;Ljava/lang/Byte;Ljava/util/List;Ljava/lang/Byte;)Z
      60: istore        4
      62: iload         4
      64: ifeq          73
      67: getstatic     #8                  // Field org/apache/hadoop/hbase/filter/Filter$ReturnCode.INCLUDE:Lorg/apache/hadoop/hbase/filter/Filter$ReturnCode;
      70: goto          76
      73: getstatic     #12                 // Field org/apache/hadoop/hbase/filter/Filter$ReturnCode.SKIP:Lorg/apache/hadoop/hbase/filter/Filter$ReturnCode;
      76: areturn

  public boolean equals(java.lang.Object);
    Code:
       0: aload_1
       1: instanceof    #13                 // class org/apache/hadoop/hbase/security/visibility/VisibilityController$DeleteVersionVisibilityExpressionFilter
       4: ifne          9
       7: iconst_0
       8: ireturn
       9: aload_0
      10: aload_1
      11: if_acmpne     16
      14: iconst_1
      15: ireturn
      16: aload_1
      17: checkcast     #13                 // class org/apache/hadoop/hbase/security/visibility/VisibilityController$DeleteVersionVisibilityExpressionFilter
      20: astore_2
      21: aload_0
      22: getfield      #2                  // Field deleteCellVisTags:Ljava/util/List;
      25: aload_2
      26: getfield      #2                  // Field deleteCellVisTags:Ljava/util/List;
      29: invokeinterface #14,  2           // InterfaceMethod java/util/List.equals:(Ljava/lang/Object;)Z
      34: ifeq          55
      37: aload_0
      38: getfield      #3                  // Field deleteCellVisTagsFormat:Ljava/lang/Byte;
      41: aload_2
      42: getfield      #3                  // Field deleteCellVisTagsFormat:Ljava/lang/Byte;
      45: invokevirtual #15                 // Method java/lang/Byte.equals:(Ljava/lang/Object;)Z
      48: ifeq          55
      51: iconst_1
      52: goto          56
      55: iconst_0
      56: ireturn

  public int hashCode();
    Code:
       0: iconst_2
       1: anewarray     #16                 // class java/lang/Object
       4: dup
       5: iconst_0
       6: aload_0
       7: getfield      #2                  // Field deleteCellVisTags:Ljava/util/List;
      10: aastore
      11: dup
      12: iconst_1
      13: aload_0
      14: getfield      #3                  // Field deleteCellVisTagsFormat:Ljava/lang/Byte;
      17: aastore
      18: invokestatic  #17                 // Method java/util/Objects.hash:([Ljava/lang/Object;)I
      21: ireturn
}
