Compiled from "Waiter.java"
public final class org.apache.hadoop.hbase.Waiter {
  public static final java.lang.String HBASE_TEST_WAIT_FOR_RATIO;

  public static float getWaitForRatio(org.apache.hadoop.conf.Configuration);
    Code:
       0: getstatic     #2                  // Field waitForRatio:F
       3: fconst_0
       4: fcmpg
       5: ifge          42
       8: ldc           #4                  // String hbase.test.wait.for.ratio
      10: invokestatic  #5                  // Method java/lang/System.getProperty:(Ljava/lang/String;)Ljava/lang/String;
      13: ifnull        30
      16: ldc           #4                  // String hbase.test.wait.for.ratio
      18: invokestatic  #5                  // Method java/lang/System.getProperty:(Ljava/lang/String;)Ljava/lang/String;
      21: invokestatic  #6                  // Method java/lang/Float.parseFloat:(Ljava/lang/String;)F
      24: putstatic     #2                  // Field waitForRatio:F
      27: goto          42
      30: aload_0
      31: ldc           #4                  // String hbase.test.wait.for.ratio
      33: getstatic     #7                  // Field HBASE_WAIT_FOR_RATIO_DEFAULT:F
      36: invokevirtual #8                  // Method org/apache/hadoop/conf/Configuration.getFloat:(Ljava/lang/String;F)F
      39: putstatic     #2                  // Field waitForRatio:F
      42: getstatic     #2                  // Field waitForRatio:F
      45: freturn

  public static void sleep(org.apache.hadoop.conf.Configuration, long);
    Code:
       0: aload_0
       1: invokestatic  #9                  // Method getWaitForRatio:(Lorg/apache/hadoop/conf/Configuration;)F
       4: lload_1
       5: l2f
       6: fmul
       7: f2l
       8: invokestatic  #10                 // Method java/lang/Thread.sleep:(J)V
      11: goto          39
      14: astore_3
      15: getstatic     #12                 // Field LOG:Lorg/slf4j/Logger;
      18: ldc           #13                 // String Sleep interrupted, {0}
      20: iconst_1
      21: anewarray     #14                 // class java/lang/Object
      24: dup
      25: iconst_0
      26: aload_3
      27: invokevirtual #15                 // Method java/lang/InterruptedException.toString:()Ljava/lang/String;
      30: aastore
      31: invokestatic  #16                 // Method java/text/MessageFormat.format:(Ljava/lang/String;[Ljava/lang/Object;)Ljava/lang/String;
      34: invokeinterface #17,  2           // InterfaceMethod org/slf4j/Logger.warn:(Ljava/lang/String;)V
      39: return
    Exception table:
       from    to  target type
           0    11    14   Class java/lang/InterruptedException

  public static <E extends java.lang.Exception> long waitFor(org.apache.hadoop.conf.Configuration, long, org.apache.hadoop.hbase.Waiter$Predicate<E>) throws E;
    Code:
       0: aload_0
       1: lload_1
       2: ldc2_w        #18                 // long 100l
       5: iconst_1
       6: aload_3
       7: invokestatic  #20                 // Method waitFor:(Lorg/apache/hadoop/conf/Configuration;JJZLorg/apache/hadoop/hbase/Waiter$Predicate;)J
      10: lreturn

  public static <E extends java.lang.Exception> long waitFor(org.apache.hadoop.conf.Configuration, long, long, org.apache.hadoop.hbase.Waiter$Predicate<E>) throws E;
    Code:
       0: aload_0
       1: lload_1
       2: lload_3
       3: iconst_1
       4: aload         5
       6: invokestatic  #20                 // Method waitFor:(Lorg/apache/hadoop/conf/Configuration;JJZLorg/apache/hadoop/hbase/Waiter$Predicate;)J
       9: lreturn

  public static <E extends java.lang.Exception> long waitFor(org.apache.hadoop.conf.Configuration, long, long, boolean, org.apache.hadoop.hbase.Waiter$Predicate<E>) throws E;
    Code:
       0: invokestatic  #21                 // Method java/lang/System.currentTimeMillis:()J
       3: lstore        7
       5: aload_0
       6: invokestatic  #9                  // Method getWaitForRatio:(Lorg/apache/hadoop/conf/Configuration;)F
       9: lload_1
      10: l2f
      11: fmul
      12: f2l
      13: lstore        9
      15: lload         7
      17: lload         9
      19: ladd
      20: lstore        11
      22: lconst_0
      23: lstore        13
      25: lconst_0
      26: lstore        15
      28: iconst_0
      29: invokestatic  #22                 // Method java/lang/Boolean.valueOf:(Z)Ljava/lang/Boolean;
      32: astore        17
      34: iconst_0
      35: invokestatic  #22                 // Method java/lang/Boolean.valueOf:(Z)Ljava/lang/Boolean;
      38: astore        18
      40: getstatic     #12                 // Field LOG:Lorg/slf4j/Logger;
      43: ldc           #23                 // String Waiting up to [{0}] milli-secs(wait.for.ratio=[{1}])
      45: iconst_2
      46: anewarray     #14                 // class java/lang/Object
      49: dup
      50: iconst_0
      51: lload         9
      53: invokestatic  #24                 // Method java/lang/Long.valueOf:(J)Ljava/lang/Long;
      56: aastore
      57: dup
      58: iconst_1
      59: aload_0
      60: invokestatic  #9                  // Method getWaitForRatio:(Lorg/apache/hadoop/conf/Configuration;)F
      63: invokestatic  #25                 // Method java/lang/Float.valueOf:(F)Ljava/lang/Float;
      66: aastore
      67: invokestatic  #16                 // Method java/text/MessageFormat.format:(Ljava/lang/String;[Ljava/lang/Object;)Ljava/lang/String;
      70: invokeinterface #26,  2           // InterfaceMethod org/slf4j/Logger.info:(Ljava/lang/String;)V
      75: aload         6
      77: invokeinterface #27,  1           // InterfaceMethod org/apache/hadoop/hbase/Waiter$Predicate.evaluate:()Z
      82: invokestatic  #22                 // Method java/lang/Boolean.valueOf:(Z)Ljava/lang/Boolean;
      85: dup
      86: astore        17
      88: invokevirtual #28                 // Method java/lang/Boolean.booleanValue:()Z
      91: ifne          154
      94: lload         11
      96: invokestatic  #21                 // Method java/lang/System.currentTimeMillis:()J
      99: lsub
     100: dup2
     101: lstore        13
     103: lconst_0
     104: lcmp
     105: ifle          154
     108: lload         13
     110: lload_3
     111: lcmp
     112: ifle          119
     115: lload_3
     116: goto          121
     119: lload         13
     121: lstore        15
     123: lload         15
     125: invokestatic  #10                 // Method java/lang/Thread.sleep:(J)V
     128: goto          75
     131: astore        19
     133: aload         6
     135: invokeinterface #27,  1           // InterfaceMethod org/apache/hadoop/hbase/Waiter$Predicate.evaluate:()Z
     140: invokestatic  #22                 // Method java/lang/Boolean.valueOf:(Z)Ljava/lang/Boolean;
     143: astore        17
     145: iconst_1
     146: invokestatic  #22                 // Method java/lang/Boolean.valueOf:(Z)Ljava/lang/Boolean;
     149: astore        18
     151: goto          154
     154: aload         17
     156: invokevirtual #28                 // Method java/lang/Boolean.booleanValue:()Z
     159: ifne          305
     162: aload         18
     164: invokevirtual #28                 // Method java/lang/Boolean.booleanValue:()Z
     167: ifeq          202
     170: getstatic     #12                 // Field LOG:Lorg/slf4j/Logger;
     173: ldc           #29                 // String Waiting interrupted after [{0}] msec
     175: iconst_1
     176: anewarray     #14                 // class java/lang/Object
     179: dup
     180: iconst_0
     181: invokestatic  #21                 // Method java/lang/System.currentTimeMillis:()J
     184: lload         7
     186: lsub
     187: invokestatic  #24                 // Method java/lang/Long.valueOf:(J)Ljava/lang/Long;
     190: aastore
     191: invokestatic  #16                 // Method java/text/MessageFormat.format:(Ljava/lang/String;[Ljava/lang/Object;)Ljava/lang/String;
     194: invokeinterface #17,  2           // InterfaceMethod org/slf4j/Logger.warn:(Ljava/lang/String;)V
     199: goto          305
     202: iload         5
     204: ifeq          255
     207: aload         6
     209: invokestatic  #30                 // Method getExplanation:(Lorg/apache/hadoop/hbase/Waiter$Predicate;)Ljava/lang/String;
     212: astore        19
     214: new           #31                 // class java/lang/StringBuilder
     217: dup
     218: invokespecial #32                 // Method java/lang/StringBuilder."<init>":()V
     221: ldc           #33                 // String Waiting timed out after [{0}] msec
     223: iconst_1
     224: anewarray     #14                 // class java/lang/Object
     227: dup
     228: iconst_0
     229: lload         9
     231: invokestatic  #24                 // Method java/lang/Long.valueOf:(J)Ljava/lang/Long;
     234: aastore
     235: invokestatic  #16                 // Method java/text/MessageFormat.format:(Ljava/lang/String;[Ljava/lang/Object;)Ljava/lang/String;
     238: invokevirtual #34                 // Method java/lang/StringBuilder.append:(Ljava/lang/String;)Ljava/lang/StringBuilder;
     241: aload         19
     243: invokevirtual #34                 // Method java/lang/StringBuilder.append:(Ljava/lang/String;)Ljava/lang/StringBuilder;
     246: invokevirtual #35                 // Method java/lang/StringBuilder.toString:()Ljava/lang/String;
     249: invokestatic  #36                 // Method org/junit/Assert.fail:(Ljava/lang/String;)V
     252: goto          305
     255: aload         6
     257: invokestatic  #30                 // Method getExplanation:(Lorg/apache/hadoop/hbase/Waiter$Predicate;)Ljava/lang/String;
     260: astore        19
     262: getstatic     #12                 // Field LOG:Lorg/slf4j/Logger;
     265: new           #31                 // class java/lang/StringBuilder
     268: dup
     269: invokespecial #32                 // Method java/lang/StringBuilder."<init>":()V
     272: ldc           #33                 // String Waiting timed out after [{0}] msec
     274: iconst_1
     275: anewarray     #14                 // class java/lang/Object
     278: dup
     279: iconst_0
     280: lload         9
     282: invokestatic  #24                 // Method java/lang/Long.valueOf:(J)Ljava/lang/Long;
     285: aastore
     286: invokestatic  #16                 // Method java/text/MessageFormat.format:(Ljava/lang/String;[Ljava/lang/Object;)Ljava/lang/String;
     289: invokevirtual #34                 // Method java/lang/StringBuilder.append:(Ljava/lang/String;)Ljava/lang/StringBuilder;
     292: aload         19
     294: invokevirtual #34                 // Method java/lang/StringBuilder.append:(Ljava/lang/String;)Ljava/lang/StringBuilder;
     297: invokevirtual #35                 // Method java/lang/StringBuilder.toString:()Ljava/lang/String;
     300: invokeinterface #17,  2           // InterfaceMethod org/slf4j/Logger.warn:(Ljava/lang/String;)V
     305: aload         17
     307: invokevirtual #28                 // Method java/lang/Boolean.booleanValue:()Z
     310: ifne          321
     313: aload         18
     315: invokevirtual #28                 // Method java/lang/Boolean.booleanValue:()Z
     318: ifeq          330
     321: invokestatic  #21                 // Method java/lang/System.currentTimeMillis:()J
     324: lload         7
     326: lsub
     327: goto          333
     330: ldc2_w        #37                 // long -1l
     333: lreturn
     334: astore        19
     336: new           #40                 // class java/lang/RuntimeException
     339: dup
     340: aload         19
     342: invokespecial #41                 // Method java/lang/RuntimeException."<init>":(Ljava/lang/Throwable;)V
     345: athrow
    Exception table:
       from    to  target type
         108   128   131   Class java/lang/InterruptedException
          40   333   334   Class java/lang/Exception

  public static java.lang.String getExplanation(org.apache.hadoop.hbase.Waiter$Predicate<?>);
    Code:
       0: aload_0
       1: instanceof    #42                 // class org/apache/hadoop/hbase/Waiter$ExplainingPredicate
       4: ifeq          52
       7: new           #31                 // class java/lang/StringBuilder
      10: dup
      11: invokespecial #32                 // Method java/lang/StringBuilder."<init>":()V
      14: ldc           #43                 // String
      16: invokevirtual #34                 // Method java/lang/StringBuilder.append:(Ljava/lang/String;)Ljava/lang/StringBuilder;
      19: aload_0
      20: checkcast     #42                 // class org/apache/hadoop/hbase/Waiter$ExplainingPredicate
      23: invokeinterface #44,  1           // InterfaceMethod org/apache/hadoop/hbase/Waiter$ExplainingPredicate.explainFailure:()Ljava/lang/String;
      28: invokevirtual #34                 // Method java/lang/StringBuilder.append:(Ljava/lang/String;)Ljava/lang/StringBuilder;
      31: invokevirtual #35                 // Method java/lang/StringBuilder.toString:()Ljava/lang/String;
      34: areturn
      35: astore_1
      36: getstatic     #12                 // Field LOG:Lorg/slf4j/Logger;
      39: ldc           #45                 // String Failed to get explanation,
      41: aload_1
      42: invokeinterface #46,  3           // InterfaceMethod org/slf4j/Logger.error:(Ljava/lang/String;Ljava/lang/Throwable;)V
      47: aload_1
      48: invokevirtual #47                 // Method java/lang/Exception.getMessage:()Ljava/lang/String;
      51: areturn
      52: ldc           #48                 // String
      54: areturn
    Exception table:
       from    to  target type
           7    34    35   Class java/lang/Exception

  static {};
    Code:
       0: ldc           #3                  // class org/apache/hadoop/hbase/Waiter
       2: invokestatic  #49                 // Method org/slf4j/LoggerFactory.getLogger:(Ljava/lang/Class;)Lorg/slf4j/Logger;
       5: putstatic     #12                 // Field LOG:Lorg/slf4j/Logger;
       8: fconst_1
       9: putstatic     #7                  // Field HBASE_WAIT_FOR_RATIO_DEFAULT:F
      12: ldc           #50                 // float -1.0f
      14: putstatic     #2                  // Field waitForRatio:F
      17: return
}
