Compiled from "WALCellCodec.java"
public class org.apache.hadoop.hbase.regionserver.wal.WALCellCodec implements org.apache.hadoop.hbase.codec.Codec {
  public static final java.lang.String WAL_CELL_CODEC_CLASS_KEY;

  protected final org.apache.hadoop.hbase.regionserver.wal.CompressionContext compression;

  public org.apache.hadoop.hbase.regionserver.wal.WALCellCodec();
    Code:
       0: aload_0
       1: invokespecial #2                  // Method java/lang/Object."<init>":()V
       4: aload_0
       5: aconst_null
       6: putfield      #3                  // Field compression:Lorg/apache/hadoop/hbase/regionserver/wal/CompressionContext;
       9: return

  public org.apache.hadoop.hbase.regionserver.wal.WALCellCodec(org.apache.hadoop.conf.Configuration, org.apache.hadoop.hbase.regionserver.wal.CompressionContext);
    Code:
       0: aload_0
       1: invokespecial #2                  // Method java/lang/Object."<init>":()V
       4: aload_0
       5: aload_2
       6: putfield      #3                  // Field compression:Lorg/apache/hadoop/hbase/regionserver/wal/CompressionContext;
       9: return

  public static java.lang.Class<?> getWALCellCodecClass(org.apache.hadoop.conf.Configuration);
    Code:
       0: aload_0
       1: ldc           #5                  // String hbase.regionserver.wal.codec
       3: ldc           #4                  // class org/apache/hadoop/hbase/regionserver/wal/WALCellCodec
       5: invokevirtual #6                  // Method org/apache/hadoop/conf/Configuration.getClass:(Ljava/lang/String;Ljava/lang/Class;)Ljava/lang/Class;
       8: areturn

  public static org.apache.hadoop.hbase.regionserver.wal.WALCellCodec create(org.apache.hadoop.conf.Configuration, java.lang.String, org.apache.hadoop.hbase.regionserver.wal.CompressionContext) throws java.lang.UnsupportedOperationException;
    Code:
       0: aload_1
       1: ifnonnull     12
       4: aload_0
       5: invokestatic  #7                  // Method getWALCellCodecClass:(Lorg/apache/hadoop/conf/Configuration;)Ljava/lang/Class;
       8: invokevirtual #8                  // Method java/lang/Class.getName:()Ljava/lang/String;
      11: astore_1
      12: aload_1
      13: iconst_2
      14: anewarray     #9                  // class java/lang/Class
      17: dup
      18: iconst_0
      19: ldc           #10                 // class org/apache/hadoop/conf/Configuration
      21: aastore
      22: dup
      23: iconst_1
      24: ldc           #11                 // class org/apache/hadoop/hbase/regionserver/wal/CompressionContext
      26: aastore
      27: iconst_2
      28: anewarray     #12                 // class java/lang/Object
      31: dup
      32: iconst_0
      33: aload_0
      34: aastore
      35: dup
      36: iconst_1
      37: aload_2
      38: aastore
      39: invokestatic  #13                 // Method org/apache/hadoop/hbase/util/ReflectionUtils.instantiateWithCustomCtor:(Ljava/lang/String;[Ljava/lang/Class;[Ljava/lang/Object;)Ljava/lang/Object;
      42: checkcast     #4                  // class org/apache/hadoop/hbase/regionserver/wal/WALCellCodec
      45: areturn

  public static org.apache.hadoop.hbase.regionserver.wal.WALCellCodec create(org.apache.hadoop.conf.Configuration, org.apache.hadoop.hbase.regionserver.wal.CompressionContext) throws java.lang.UnsupportedOperationException;
    Code:
       0: aload_0
       1: invokestatic  #7                  // Method getWALCellCodecClass:(Lorg/apache/hadoop/conf/Configuration;)Ljava/lang/Class;
       4: invokevirtual #8                  // Method java/lang/Class.getName:()Ljava/lang/String;
       7: astore_2
       8: aload_2
       9: iconst_2
      10: anewarray     #9                  // class java/lang/Class
      13: dup
      14: iconst_0
      15: ldc           #10                 // class org/apache/hadoop/conf/Configuration
      17: aastore
      18: dup
      19: iconst_1
      20: ldc           #11                 // class org/apache/hadoop/hbase/regionserver/wal/CompressionContext
      22: aastore
      23: iconst_2
      24: anewarray     #12                 // class java/lang/Object
      27: dup
      28: iconst_0
      29: aload_0
      30: aastore
      31: dup
      32: iconst_1
      33: aload_1
      34: aastore
      35: invokestatic  #13                 // Method org/apache/hadoop/hbase/util/ReflectionUtils.instantiateWithCustomCtor:(Ljava/lang/String;[Ljava/lang/Class;[Ljava/lang/Object;)Ljava/lang/Object;
      38: checkcast     #4                  // class org/apache/hadoop/hbase/regionserver/wal/WALCellCodec
      41: areturn

  public org.apache.hadoop.hbase.codec.Codec$Decoder getDecoder(java.io.InputStream);
    Code:
       0: aload_0
       1: getfield      #3                  // Field compression:Lorg/apache/hadoop/hbase/regionserver/wal/CompressionContext;
       4: ifnonnull     18
       7: new           #32                 // class org/apache/hadoop/hbase/codec/KeyValueCodecWithTags$KeyValueDecoder
      10: dup
      11: aload_1
      12: invokespecial #33                 // Method org/apache/hadoop/hbase/codec/KeyValueCodecWithTags$KeyValueDecoder."<init>":(Ljava/io/InputStream;)V
      15: goto          30
      18: new           #34                 // class org/apache/hadoop/hbase/regionserver/wal/WALCellCodec$CompressedKvDecoder
      21: dup
      22: aload_1
      23: aload_0
      24: getfield      #3                  // Field compression:Lorg/apache/hadoop/hbase/regionserver/wal/CompressionContext;
      27: invokespecial #35                 // Method org/apache/hadoop/hbase/regionserver/wal/WALCellCodec$CompressedKvDecoder."<init>":(Ljava/io/InputStream;Lorg/apache/hadoop/hbase/regionserver/wal/CompressionContext;)V
      30: areturn

  public org.apache.hadoop.hbase.codec.Codec$Decoder getDecoder(org.apache.hadoop.hbase.nio.ByteBuff);
    Code:
       0: aload_0
       1: new           #36                 // class org/apache/hadoop/hbase/io/ByteBuffInputStream
       4: dup
       5: aload_1
       6: invokespecial #37                 // Method org/apache/hadoop/hbase/io/ByteBuffInputStream."<init>":(Lorg/apache/hadoop/hbase/nio/ByteBuff;)V
       9: invokevirtual #38                 // Method getDecoder:(Ljava/io/InputStream;)Lorg/apache/hadoop/hbase/codec/Codec$Decoder;
      12: areturn

  public org.apache.hadoop.hbase.codec.Codec$Encoder getEncoder(java.io.OutputStream);
    Code:
       0: aload_1
       1: instanceof    #39                 // class org/apache/hadoop/hbase/io/ByteBufferWriter
       4: ifeq          11
       7: aload_1
       8: goto          19
      11: new           #40                 // class org/apache/hadoop/hbase/io/ByteBufferWriterOutputStream
      14: dup
      15: aload_1
      16: invokespecial #41                 // Method org/apache/hadoop/hbase/io/ByteBufferWriterOutputStream."<init>":(Ljava/io/OutputStream;)V
      19: astore_1
      20: aload_0
      21: getfield      #3                  // Field compression:Lorg/apache/hadoop/hbase/regionserver/wal/CompressionContext;
      24: ifnonnull     36
      27: new           #42                 // class org/apache/hadoop/hbase/regionserver/wal/WALCellCodec$EnsureKvEncoder
      30: dup
      31: aload_1
      32: invokespecial #43                 // Method org/apache/hadoop/hbase/regionserver/wal/WALCellCodec$EnsureKvEncoder."<init>":(Ljava/io/OutputStream;)V
      35: areturn
      36: new           #44                 // class org/apache/hadoop/hbase/regionserver/wal/WALCellCodec$CompressedKvEncoder
      39: dup
      40: aload_1
      41: aload_0
      42: getfield      #3                  // Field compression:Lorg/apache/hadoop/hbase/regionserver/wal/CompressionContext;
      45: invokespecial #45                 // Method org/apache/hadoop/hbase/regionserver/wal/WALCellCodec$CompressedKvEncoder."<init>":(Ljava/io/OutputStream;Lorg/apache/hadoop/hbase/regionserver/wal/CompressionContext;)V
      48: areturn

  public org.apache.hadoop.hbase.regionserver.wal.WALCellCodec$ByteStringCompressor getByteStringCompressor();
    Code:
       0: new           #46                 // class org/apache/hadoop/hbase/regionserver/wal/WALCellCodec$BaosAndCompressor
       3: dup
       4: aload_0
       5: getfield      #3                  // Field compression:Lorg/apache/hadoop/hbase/regionserver/wal/CompressionContext;
       8: invokespecial #47                 // Method org/apache/hadoop/hbase/regionserver/wal/WALCellCodec$BaosAndCompressor."<init>":(Lorg/apache/hadoop/hbase/regionserver/wal/CompressionContext;)V
      11: areturn

  public org.apache.hadoop.hbase.regionserver.wal.WALCellCodec$ByteStringUncompressor getByteStringUncompressor();
    Code:
       0: new           #48                 // class org/apache/hadoop/hbase/regionserver/wal/WALCellCodec$StatelessUncompressor
       3: dup
       4: aload_0
       5: getfield      #3                  // Field compression:Lorg/apache/hadoop/hbase/regionserver/wal/CompressionContext;
       8: invokespecial #49                 // Method org/apache/hadoop/hbase/regionserver/wal/WALCellCodec$StatelessUncompressor."<init>":(Lorg/apache/hadoop/hbase/regionserver/wal/CompressionContext;)V
      11: areturn

  public static org.apache.hadoop.hbase.regionserver.wal.WALCellCodec$ByteStringCompressor getNoneCompressor();
    Code:
       0: new           #50                 // class org/apache/hadoop/hbase/regionserver/wal/WALCellCodec$NoneCompressor
       3: dup
       4: invokespecial #51                 // Method org/apache/hadoop/hbase/regionserver/wal/WALCellCodec$NoneCompressor."<init>":()V
       7: areturn

  public static org.apache.hadoop.hbase.regionserver.wal.WALCellCodec$ByteStringUncompressor getNoneUncompressor();
    Code:
       0: new           #52                 // class org/apache/hadoop/hbase/regionserver/wal/WALCellCodec$NoneUncompressor
       3: dup
       4: invokespecial #53                 // Method org/apache/hadoop/hbase/regionserver/wal/WALCellCodec$NoneUncompressor."<init>":()V
       7: areturn

  static byte[] access$000(org.apache.hbase.thirdparty.com.google.protobuf.ByteString, org.apache.hadoop.hbase.io.util.Dictionary) throws java.io.IOException;
    Code:
       0: aload_0
       1: aload_1
       2: invokestatic  #1                  // Method uncompressByteString:(Lorg/apache/hbase/thirdparty/com/google/protobuf/ByteString;Lorg/apache/hadoop/hbase/io/util/Dictionary;)[B
       5: areturn
}
