Compiled from "WALCellCodec.java"
class org.apache.hadoop.hbase.regionserver.wal.WALCellCodec$CompressedKvDecoder extends org.apache.hadoop.hbase.codec.BaseDecoder {
  public org.apache.hadoop.hbase.regionserver.wal.WALCellCodec$CompressedKvDecoder(java.io.InputStream, org.apache.hadoop.hbase.regionserver.wal.CompressionContext);
    Code:
       0: aload_0
       1: aload_1
       2: invokespecial #1                  // Method org/apache/hadoop/hbase/codec/BaseDecoder."<init>":(Ljava/io/InputStream;)V
       5: aload_0
       6: aload_2
       7: putfield      #2                  // Field compression:Lorg/apache/hadoop/hbase/regionserver/wal/CompressionContext;
      10: return

  protected org.apache.hadoop.hbase.Cell parseCell() throws java.io.IOException;
    Code:
       0: aload_0
       1: getfield      #3                  // Field in:Ljava/io/InputStream;
       4: invokestatic  #4                  // Method org/apache/hadoop/hbase/io/util/StreamUtils.readRawVarint32:(Ljava/io/InputStream;)I
       7: istore_1
       8: aload_0
       9: getfield      #3                  // Field in:Ljava/io/InputStream;
      12: invokestatic  #4                  // Method org/apache/hadoop/hbase/io/util/StreamUtils.readRawVarint32:(Ljava/io/InputStream;)I
      15: istore_2
      16: aload_0
      17: getfield      #3                  // Field in:Ljava/io/InputStream;
      20: invokestatic  #4                  // Method org/apache/hadoop/hbase/io/util/StreamUtils.readRawVarint32:(Ljava/io/InputStream;)I
      23: istore_3
      24: iconst_0
      25: istore        4
      27: iload_3
      28: ifne          42
      31: bipush        8
      33: iload_1
      34: iadd
      35: iload_2
      36: iadd
      37: istore        4
      39: goto          52
      42: bipush        10
      44: iload_1
      45: iadd
      46: iload_2
      47: iadd
      48: iload_3
      49: iadd
      50: istore        4
      52: iload         4
      54: newarray       byte
      56: astore        5
      58: iconst_0
      59: istore        6
      61: aload         5
      63: iload         6
      65: iload_1
      66: invokestatic  #6                  // Method org/apache/hadoop/hbase/util/Bytes.putInt:([BII)I
      69: istore        6
      71: aload         5
      73: iload         6
      75: iload_2
      76: invokestatic  #6                  // Method org/apache/hadoop/hbase/util/Bytes.putInt:([BII)I
      79: istore        6
      81: aload_0
      82: aload         5
      84: iload         6
      86: iconst_2
      87: iadd
      88: aload_0
      89: getfield      #2                  // Field compression:Lorg/apache/hadoop/hbase/regionserver/wal/CompressionContext;
      92: getstatic     #8                  // Field org/apache/hadoop/hbase/regionserver/wal/CompressionContext$DictionaryIndex.ROW:Lorg/apache/hadoop/hbase/regionserver/wal/CompressionContext$DictionaryIndex;
      95: invokevirtual #9                  // Method org/apache/hadoop/hbase/regionserver/wal/CompressionContext.getDictionary:(Ljava/lang/Enum;)Lorg/apache/hadoop/hbase/io/util/Dictionary;
      98: invokespecial #10                 // Method readIntoArray:([BILorg/apache/hadoop/hbase/io/util/Dictionary;)I
     101: istore        7
     103: iload         7
     105: sipush        32767
     108: invokestatic  #12                 // Method checkLength:(II)V
     111: aload         5
     113: iload         6
     115: iload         7
     117: i2s
     118: invokestatic  #13                 // Method org/apache/hadoop/hbase/util/Bytes.putShort:([BIS)I
     121: istore        6
     123: iload         6
     125: iload         7
     127: iadd
     128: istore        6
     130: aload_0
     131: aload         5
     133: iload         6
     135: iconst_1
     136: iadd
     137: aload_0
     138: getfield      #2                  // Field compression:Lorg/apache/hadoop/hbase/regionserver/wal/CompressionContext;
     141: getstatic     #14                 // Field org/apache/hadoop/hbase/regionserver/wal/CompressionContext$DictionaryIndex.FAMILY:Lorg/apache/hadoop/hbase/regionserver/wal/CompressionContext$DictionaryIndex;
     144: invokevirtual #9                  // Method org/apache/hadoop/hbase/regionserver/wal/CompressionContext.getDictionary:(Ljava/lang/Enum;)Lorg/apache/hadoop/hbase/io/util/Dictionary;
     147: invokespecial #10                 // Method readIntoArray:([BILorg/apache/hadoop/hbase/io/util/Dictionary;)I
     150: istore        7
     152: iload         7
     154: bipush        127
     156: invokestatic  #12                 // Method checkLength:(II)V
     159: aload         5
     161: iload         6
     163: iload         7
     165: i2b
     166: invokestatic  #16                 // Method org/apache/hadoop/hbase/util/Bytes.putByte:([BIB)I
     169: istore        6
     171: iload         6
     173: iload         7
     175: iadd
     176: istore        6
     178: aload_0
     179: aload         5
     181: iload         6
     183: aload_0
     184: getfield      #2                  // Field compression:Lorg/apache/hadoop/hbase/regionserver/wal/CompressionContext;
     187: getstatic     #17                 // Field org/apache/hadoop/hbase/regionserver/wal/CompressionContext$DictionaryIndex.QUALIFIER:Lorg/apache/hadoop/hbase/regionserver/wal/CompressionContext$DictionaryIndex;
     190: invokevirtual #9                  // Method org/apache/hadoop/hbase/regionserver/wal/CompressionContext.getDictionary:(Ljava/lang/Enum;)Lorg/apache/hadoop/hbase/io/util/Dictionary;
     193: invokespecial #10                 // Method readIntoArray:([BILorg/apache/hadoop/hbase/io/util/Dictionary;)I
     196: istore        7
     198: iload         6
     200: iload         7
     202: iadd
     203: istore        6
     205: iload         4
     207: iload         6
     209: isub
     210: istore        8
     212: iload_3
     213: ifle          224
     216: iload         8
     218: iload_3
     219: isub
     220: iconst_2
     221: isub
     222: istore        8
     224: aload_0
     225: getfield      #3                  // Field in:Ljava/io/InputStream;
     228: aload         5
     230: iload         6
     232: iload         8
     234: invokestatic  #18                 // Method org/apache/hadoop/io/IOUtils.readFully:(Ljava/io/InputStream;[BII)V
     237: iload         6
     239: iload         8
     241: iadd
     242: istore        6
     244: iload_3
     245: ifle          302
     248: aload         5
     250: iload         6
     252: iload_3
     253: invokestatic  #19                 // Method org/apache/hadoop/hbase/util/Bytes.putAsShort:([BII)I
     256: istore        6
     258: aload_0
     259: getfield      #2                  // Field compression:Lorg/apache/hadoop/hbase/regionserver/wal/CompressionContext;
     262: getfield      #20                 // Field org/apache/hadoop/hbase/regionserver/wal/CompressionContext.tagCompressionContext:Lorg/apache/hadoop/hbase/io/TagCompressionContext;
     265: ifnull        290
     268: aload_0
     269: getfield      #2                  // Field compression:Lorg/apache/hadoop/hbase/regionserver/wal/CompressionContext;
     272: getfield      #20                 // Field org/apache/hadoop/hbase/regionserver/wal/CompressionContext.tagCompressionContext:Lorg/apache/hadoop/hbase/io/TagCompressionContext;
     275: aload_0
     276: getfield      #3                  // Field in:Ljava/io/InputStream;
     279: aload         5
     281: iload         6
     283: iload_3
     284: invokevirtual #21                 // Method org/apache/hadoop/hbase/io/TagCompressionContext.uncompressTags:(Ljava/io/InputStream;[BII)V
     287: goto          302
     290: aload_0
     291: getfield      #3                  // Field in:Ljava/io/InputStream;
     294: aload         5
     296: iload         6
     298: iload_3
     299: invokestatic  #18                 // Method org/apache/hadoop/io/IOUtils.readFully:(Ljava/io/InputStream;[BII)V
     302: new           #5                  // class org/apache/hadoop/hbase/KeyValue
     305: dup
     306: aload         5
     308: iconst_0
     309: iload         4
     311: invokespecial #22                 // Method org/apache/hadoop/hbase/KeyValue."<init>":([BII)V
     314: areturn
}
