Compiled from "WALCoprocessorHost.java"
class org.apache.hadoop.hbase.regionserver.wal.WALCoprocessorHost$WALEnvironment extends org.apache.hadoop.hbase.coprocessor.BaseEnvironment<org.apache.hadoop.hbase.coprocessor.WALCoprocessor> implements org.apache.hadoop.hbase.coprocessor.WALCoprocessorEnvironment {
  public org.apache.hadoop.hbase.wal.WAL getWAL();
    Code:
       0: aload_0
       1: getfield      #2                  // Field wal:Lorg/apache/hadoop/hbase/wal/WAL;
       4: areturn

  public org.apache.hadoop.hbase.metrics.MetricRegistry getMetricRegistryForRegionServer();
    Code:
       0: aload_0
       1: getfield      #7                  // Field metricRegistry:Lorg/apache/hadoop/hbase/metrics/MetricRegistry;
       4: areturn

  public void shutdown();
    Code:
       0: aload_0
       1: invokespecial #8                  // Method org/apache/hadoop/hbase/coprocessor/BaseEnvironment.shutdown:()V
       4: aload_0
       5: getfield      #7                  // Field metricRegistry:Lorg/apache/hadoop/hbase/metrics/MetricRegistry;
       8: invokestatic  #9                  // Method org/apache/hadoop/hbase/coprocessor/MetricsCoprocessor.removeRegistry:(Lorg/apache/hadoop/hbase/metrics/MetricRegistry;)V
      11: return

  org.apache.hadoop.hbase.regionserver.wal.WALCoprocessorHost$WALEnvironment(org.apache.hadoop.hbase.coprocessor.WALCoprocessor, int, int, org.apache.hadoop.conf.Configuration, org.apache.hadoop.hbase.wal.WAL, org.apache.hadoop.hbase.regionserver.wal.WALCoprocessorHost$1);
    Code:
       0: aload_0
       1: aload_1
       2: iload_2
       3: iload_3
       4: aload         4
       6: aload         5
       8: invokespecial #1                  // Method "<init>":(Lorg/apache/hadoop/hbase/coprocessor/WALCoprocessor;IILorg/apache/hadoop/conf/Configuration;Lorg/apache/hadoop/hbase/wal/WAL;)V
      11: return
}
