Compiled from "WALEntryStream.java"
class org.apache.hadoop.hbase.replication.regionserver.WALEntryStream implements java.io.Closeable {
  public org.apache.hadoop.hbase.replication.regionserver.WALEntryStream(java.util.concurrent.PriorityBlockingQueue<org.apache.hadoop.fs.Path>, org.apache.hadoop.conf.Configuration, long, org.apache.hadoop.hbase.replication.regionserver.WALFileLengthProvider, org.apache.hadoop.hbase.ServerName, org.apache.hadoop.hbase.replication.regionserver.MetricsSource) throws java.io.IOException;
    Code:
       0: aload_0
       1: invokespecial #2                  // Method java/lang/Object."<init>":()V
       4: aload_0
       5: lconst_0
       6: putfield      #3                  // Field currentPositionOfEntry:J
       9: aload_0
      10: lconst_0
      11: putfield      #4                  // Field currentPositionOfReader:J
      14: aload_0
      15: aload_1
      16: putfield      #5                  // Field logQueue:Ljava/util/concurrent/PriorityBlockingQueue;
      19: aload_0
      20: aload_2
      21: invokestatic  #6                  // Method org/apache/hadoop/hbase/util/CommonFSUtils.getWALFileSystem:(Lorg/apache/hadoop/conf/Configuration;)Lorg/apache/hadoop/fs/FileSystem;
      24: putfield      #7                  // Field fs:Lorg/apache/hadoop/fs/FileSystem;
      27: aload_0
      28: aload_2
      29: putfield      #8                  // Field conf:Lorg/apache/hadoop/conf/Configuration;
      32: aload_0
      33: lload_3
      34: putfield      #3                  // Field currentPositionOfEntry:J
      37: aload_0
      38: aload         5
      40: putfield      #9                  // Field walFileLengthProvider:Lorg/apache/hadoop/hbase/replication/regionserver/WALFileLengthProvider;
      43: aload_0
      44: aload         6
      46: putfield      #10                 // Field serverName:Lorg/apache/hadoop/hbase/ServerName;
      49: aload_0
      50: aload         7
      52: putfield      #11                 // Field metrics:Lorg/apache/hadoop/hbase/replication/regionserver/MetricsSource;
      55: return

  public boolean hasNext() throws java.io.IOException;
    Code:
       0: aload_0
       1: getfield      #12                 // Field currentEntry:Lorg/apache/hadoop/hbase/wal/WAL$Entry;
       4: ifnonnull     11
       7: aload_0
       8: invokespecial #13                 // Method tryAdvanceEntry:()V
      11: aload_0
      12: getfield      #12                 // Field currentEntry:Lorg/apache/hadoop/hbase/wal/WAL$Entry;
      15: ifnull        22
      18: iconst_1
      19: goto          23
      22: iconst_0
      23: ireturn

  public org.apache.hadoop.hbase.wal.WAL$Entry peek() throws java.io.IOException;
    Code:
       0: aload_0
       1: invokevirtual #14                 // Method hasNext:()Z
       4: ifeq          14
       7: aload_0
       8: getfield      #12                 // Field currentEntry:Lorg/apache/hadoop/hbase/wal/WAL$Entry;
      11: goto          15
      14: aconst_null
      15: areturn

  public org.apache.hadoop.hbase.wal.WAL$Entry next() throws java.io.IOException;
    Code:
       0: aload_0
       1: invokevirtual #15                 // Method peek:()Lorg/apache/hadoop/hbase/wal/WAL$Entry;
       4: astore_1
       5: aload_0
       6: aload_0
       7: getfield      #4                  // Field currentPositionOfReader:J
      10: putfield      #3                  // Field currentPositionOfEntry:J
      13: aload_0
      14: aconst_null
      15: putfield      #12                 // Field currentEntry:Lorg/apache/hadoop/hbase/wal/WAL$Entry;
      18: aload_1
      19: areturn

  public void close() throws java.io.IOException;
    Code:
       0: aload_0
       1: invokespecial #16                 // Method closeReader:()V
       4: return

  public long getPosition();
    Code:
       0: aload_0
       1: getfield      #3                  // Field currentPositionOfEntry:J
       4: lreturn

  public org.apache.hadoop.fs.Path getCurrentPath();
    Code:
       0: aload_0
       1: getfield      #17                 // Field currentPath:Lorg/apache/hadoop/fs/Path;
       4: areturn

  public void reset() throws java.io.IOException;
    Code:
       0: aload_0
       1: getfield      #28                 // Field reader:Lorg/apache/hadoop/hbase/wal/WAL$Reader;
       4: ifnull        18
       7: aload_0
       8: getfield      #17                 // Field currentPath:Lorg/apache/hadoop/fs/Path;
      11: ifnull        18
      14: aload_0
      15: invokespecial #29                 // Method resetReader:()V
      18: return

  static org.slf4j.Logger access$000();
    Code:
       0: getstatic     #1                  // Field LOG:Lorg/slf4j/Logger;
       3: areturn

  static {};
    Code:
       0: ldc           #131                // class org/apache/hadoop/hbase/replication/regionserver/WALEntryStream
       2: invokestatic  #132                // Method org/slf4j/LoggerFactory.getLogger:(Ljava/lang/Class;)Lorg/slf4j/Logger;
       5: putstatic     #1                  // Field LOG:Lorg/slf4j/Logger;
       8: return
}
