Compiled from "WALFactory.java"
final class org.apache.hadoop.hbase.wal.WALFactory$Providers extends java.lang.Enum<org.apache.hadoop.hbase.wal.WALFactory$Providers> {
  public static final org.apache.hadoop.hbase.wal.WALFactory$Providers defaultProvider;

  public static final org.apache.hadoop.hbase.wal.WALFactory$Providers filesystem;

  public static final org.apache.hadoop.hbase.wal.WALFactory$Providers multiwal;

  public static final org.apache.hadoop.hbase.wal.WALFactory$Providers asyncfs;

  final java.lang.Class<? extends org.apache.hadoop.hbase.wal.WALProvider> clazz;

  public static org.apache.hadoop.hbase.wal.WALFactory$Providers[] values();
    Code:
       0: getstatic     #1                  // Field $VALUES:[Lorg/apache/hadoop/hbase/wal/WALFactory$Providers;
       3: invokevirtual #2                  // Method "[Lorg/apache/hadoop/hbase/wal/WALFactory$Providers;".clone:()Ljava/lang/Object;
       6: checkcast     #3                  // class "[Lorg/apache/hadoop/hbase/wal/WALFactory$Providers;"
       9: areturn

  public static org.apache.hadoop.hbase.wal.WALFactory$Providers valueOf(java.lang.String);
    Code:
       0: ldc           #4                  // class org/apache/hadoop/hbase/wal/WALFactory$Providers
       2: aload_0
       3: invokestatic  #5                  // Method java/lang/Enum.valueOf:(Ljava/lang/Class;Ljava/lang/String;)Ljava/lang/Enum;
       6: checkcast     #4                  // class org/apache/hadoop/hbase/wal/WALFactory$Providers
       9: areturn

  static {};
    Code:
       0: new           #4                  // class org/apache/hadoop/hbase/wal/WALFactory$Providers
       3: dup
       4: ldc           #8                  // String defaultProvider
       6: iconst_0
       7: ldc           #9                  // class org/apache/hadoop/hbase/wal/AsyncFSWALProvider
       9: invokespecial #10                 // Method "<init>":(Ljava/lang/String;ILjava/lang/Class;)V
      12: putstatic     #11                 // Field defaultProvider:Lorg/apache/hadoop/hbase/wal/WALFactory$Providers;
      15: new           #4                  // class org/apache/hadoop/hbase/wal/WALFactory$Providers
      18: dup
      19: ldc           #12                 // String filesystem
      21: iconst_1
      22: ldc           #13                 // class org/apache/hadoop/hbase/wal/FSHLogProvider
      24: invokespecial #10                 // Method "<init>":(Ljava/lang/String;ILjava/lang/Class;)V
      27: putstatic     #14                 // Field filesystem:Lorg/apache/hadoop/hbase/wal/WALFactory$Providers;
      30: new           #4                  // class org/apache/hadoop/hbase/wal/WALFactory$Providers
      33: dup
      34: ldc           #15                 // String multiwal
      36: iconst_2
      37: ldc           #16                 // class org/apache/hadoop/hbase/wal/RegionGroupingProvider
      39: invokespecial #10                 // Method "<init>":(Ljava/lang/String;ILjava/lang/Class;)V
      42: putstatic     #17                 // Field multiwal:Lorg/apache/hadoop/hbase/wal/WALFactory$Providers;
      45: new           #4                  // class org/apache/hadoop/hbase/wal/WALFactory$Providers
      48: dup
      49: ldc           #18                 // String asyncfs
      51: iconst_3
      52: ldc           #9                  // class org/apache/hadoop/hbase/wal/AsyncFSWALProvider
      54: invokespecial #10                 // Method "<init>":(Ljava/lang/String;ILjava/lang/Class;)V
      57: putstatic     #19                 // Field asyncfs:Lorg/apache/hadoop/hbase/wal/WALFactory$Providers;
      60: iconst_4
      61: anewarray     #4                  // class org/apache/hadoop/hbase/wal/WALFactory$Providers
      64: dup
      65: iconst_0
      66: getstatic     #11                 // Field defaultProvider:Lorg/apache/hadoop/hbase/wal/WALFactory$Providers;
      69: aastore
      70: dup
      71: iconst_1
      72: getstatic     #14                 // Field filesystem:Lorg/apache/hadoop/hbase/wal/WALFactory$Providers;
      75: aastore
      76: dup
      77: iconst_2
      78: getstatic     #17                 // Field multiwal:Lorg/apache/hadoop/hbase/wal/WALFactory$Providers;
      81: aastore
      82: dup
      83: iconst_3
      84: getstatic     #19                 // Field asyncfs:Lorg/apache/hadoop/hbase/wal/WALFactory$Providers;
      87: aastore
      88: putstatic     #1                  // Field $VALUES:[Lorg/apache/hadoop/hbase/wal/WALFactory$Providers;
      91: return
}
