Compiled from "WALProcedureStore.java"
class org.apache.hadoop.hbase.procedure2.store.wal.WALProcedureStore$2 implements org.apache.hadoop.hbase.procedure2.store.wal.ProcedureWALFormat$Loader {
  final org.apache.hadoop.hbase.procedure2.store.ProcedureStore$ProcedureLoader val$loader;

  final org.apache.hadoop.hbase.procedure2.store.wal.WALProcedureStore this$0;

  org.apache.hadoop.hbase.procedure2.store.wal.WALProcedureStore$2(org.apache.hadoop.hbase.procedure2.store.wal.WALProcedureStore, org.apache.hadoop.hbase.procedure2.store.ProcedureStore$ProcedureLoader);
    Code:
       0: aload_0
       1: aload_1
       2: putfield      #1                  // Field this$0:Lorg/apache/hadoop/hbase/procedure2/store/wal/WALProcedureStore;
       5: aload_0
       6: aload_2
       7: putfield      #2                  // Field val$loader:Lorg/apache/hadoop/hbase/procedure2/store/ProcedureStore$ProcedureLoader;
      10: aload_0
      11: invokespecial #3                  // Method java/lang/Object."<init>":()V
      14: return

  public void setMaxProcId(long);
    Code:
       0: aload_0
       1: getfield      #2                  // Field val$loader:Lorg/apache/hadoop/hbase/procedure2/store/ProcedureStore$ProcedureLoader;
       4: lload_1
       5: invokeinterface #4,  3            // InterfaceMethod org/apache/hadoop/hbase/procedure2/store/ProcedureStore$ProcedureLoader.setMaxProcId:(J)V
      10: return

  public void load(org.apache.hadoop.hbase.procedure2.store.ProcedureStore$ProcedureIterator) throws java.io.IOException;
    Code:
       0: aload_0
       1: getfield      #2                  // Field val$loader:Lorg/apache/hadoop/hbase/procedure2/store/ProcedureStore$ProcedureLoader;
       4: aload_1
       5: invokeinterface #5,  2            // InterfaceMethod org/apache/hadoop/hbase/procedure2/store/ProcedureStore$ProcedureLoader.load:(Lorg/apache/hadoop/hbase/procedure2/store/ProcedureStore$ProcedureIterator;)V
      10: return

  public void handleCorrupted(org.apache.hadoop.hbase.procedure2.store.ProcedureStore$ProcedureIterator) throws java.io.IOException;
    Code:
       0: aload_0
       1: getfield      #2                  // Field val$loader:Lorg/apache/hadoop/hbase/procedure2/store/ProcedureStore$ProcedureLoader;
       4: aload_1
       5: invokeinterface #6,  2            // InterfaceMethod org/apache/hadoop/hbase/procedure2/store/ProcedureStore$ProcedureLoader.handleCorrupted:(Lorg/apache/hadoop/hbase/procedure2/store/ProcedureStore$ProcedureIterator;)V
      10: return

  public void markCorruptedWAL(org.apache.hadoop.hbase.procedure2.store.wal.ProcedureWALFile, java.io.IOException);
    Code:
       0: aload_0
       1: getfield      #1                  // Field this$0:Lorg/apache/hadoop/hbase/procedure2/store/wal/WALProcedureStore;
       4: invokestatic  #7                  // Method org/apache/hadoop/hbase/procedure2/store/wal/WALProcedureStore.access$400:(Lorg/apache/hadoop/hbase/procedure2/store/wal/WALProcedureStore;)Ljava/util/Set;
       7: ifnonnull     25
      10: aload_0
      11: getfield      #1                  // Field this$0:Lorg/apache/hadoop/hbase/procedure2/store/wal/WALProcedureStore;
      14: new           #8                  // class java/util/HashSet
      17: dup
      18: invokespecial #9                  // Method java/util/HashSet."<init>":()V
      21: invokestatic  #10                 // Method org/apache/hadoop/hbase/procedure2/store/wal/WALProcedureStore.access$402:(Lorg/apache/hadoop/hbase/procedure2/store/wal/WALProcedureStore;Ljava/util/Set;)Ljava/util/Set;
      24: pop
      25: aload_0
      26: getfield      #1                  // Field this$0:Lorg/apache/hadoop/hbase/procedure2/store/wal/WALProcedureStore;
      29: invokestatic  #7                  // Method org/apache/hadoop/hbase/procedure2/store/wal/WALProcedureStore.access$400:(Lorg/apache/hadoop/hbase/procedure2/store/wal/WALProcedureStore;)Ljava/util/Set;
      32: aload_1
      33: invokeinterface #11,  2           // InterfaceMethod java/util/Set.add:(Ljava/lang/Object;)Z
      38: pop
      39: return
}
