Compiled from "WALProtos.java"
public final class org.apache.hadoop.hbase.protobuf.generated.WALProtos$StoreDescriptor$Builder extends com.google.protobuf.GeneratedMessage$Builder<org.apache.hadoop.hbase.protobuf.generated.WALProtos$StoreDescriptor$Builder> implements org.apache.hadoop.hbase.protobuf.generated.WALProtos$StoreDescriptorOrBuilder {
  public static final com.google.protobuf.Descriptors$Descriptor getDescriptor();
    Code:
       0: invokestatic  #3                  // Method org/apache/hadoop/hbase/protobuf/generated/WALProtos.access$8500:()Lcom/google/protobuf/Descriptors$Descriptor;
       3: areturn

  protected com.google.protobuf.GeneratedMessage$FieldAccessorTable internalGetFieldAccessorTable();
    Code:
       0: invokestatic  #4                  // Method org/apache/hadoop/hbase/protobuf/generated/WALProtos.access$8600:()Lcom/google/protobuf/GeneratedMessage$FieldAccessorTable;
       3: ldc           #5                  // class org/apache/hadoop/hbase/protobuf/generated/WALProtos$StoreDescriptor
       5: ldc           #6                  // class org/apache/hadoop/hbase/protobuf/generated/WALProtos$StoreDescriptor$Builder
       7: invokevirtual #7                  // Method com/google/protobuf/GeneratedMessage$FieldAccessorTable.ensureFieldAccessorsInitialized:(Ljava/lang/Class;Ljava/lang/Class;)Lcom/google/protobuf/GeneratedMessage$FieldAccessorTable;
      10: areturn

  public org.apache.hadoop.hbase.protobuf.generated.WALProtos$StoreDescriptor$Builder clear();
    Code:
       0: aload_0
       1: invokespecial #19                 // Method com/google/protobuf/GeneratedMessage$Builder.clear:()Lcom/google/protobuf/GeneratedMessage$Builder;
       4: pop
       5: aload_0
       6: getstatic     #9                  // Field com/google/protobuf/ByteString.EMPTY:Lcom/google/protobuf/ByteString;
       9: putfield      #10                 // Field familyName_:Lcom/google/protobuf/ByteString;
      12: aload_0
      13: aload_0
      14: getfield      #20                 // Field bitField0_:I
      17: bipush        -2
      19: iand
      20: putfield      #20                 // Field bitField0_:I
      23: aload_0
      24: ldc           #11                 // String
      26: putfield      #12                 // Field storeHomeDir_:Ljava/lang/Object;
      29: aload_0
      30: aload_0
      31: getfield      #20                 // Field bitField0_:I
      34: bipush        -3
      36: iand
      37: putfield      #20                 // Field bitField0_:I
      40: aload_0
      41: getstatic     #13                 // Field com/google/protobuf/LazyStringArrayList.EMPTY:Lcom/google/protobuf/LazyStringList;
      44: putfield      #14                 // Field storeFile_:Lcom/google/protobuf/LazyStringList;
      47: aload_0
      48: aload_0
      49: getfield      #20                 // Field bitField0_:I
      52: bipush        -5
      54: iand
      55: putfield      #20                 // Field bitField0_:I
      58: aload_0
      59: lconst_0
      60: putfield      #21                 // Field storeFileSizeBytes_:J
      63: aload_0
      64: aload_0
      65: getfield      #20                 // Field bitField0_:I
      68: bipush        -9
      70: iand
      71: putfield      #20                 // Field bitField0_:I
      74: aload_0
      75: areturn

  public org.apache.hadoop.hbase.protobuf.generated.WALProtos$StoreDescriptor$Builder clone();
    Code:
       0: invokestatic  #2                  // Method create:()Lorg/apache/hadoop/hbase/protobuf/generated/WALProtos$StoreDescriptor$Builder;
       3: aload_0
       4: invokevirtual #22                 // Method buildPartial:()Lorg/apache/hadoop/hbase/protobuf/generated/WALProtos$StoreDescriptor;
       7: invokevirtual #23                 // Method mergeFrom:(Lorg/apache/hadoop/hbase/protobuf/generated/WALProtos$StoreDescriptor;)Lorg/apache/hadoop/hbase/protobuf/generated/WALProtos$StoreDescriptor$Builder;
      10: areturn

  public com.google.protobuf.Descriptors$Descriptor getDescriptorForType();
    Code:
       0: invokestatic  #3                  // Method org/apache/hadoop/hbase/protobuf/generated/WALProtos.access$8500:()Lcom/google/protobuf/Descriptors$Descriptor;
       3: areturn

  public org.apache.hadoop.hbase.protobuf.generated.WALProtos$StoreDescriptor getDefaultInstanceForType();
    Code:
       0: invokestatic  #24                 // Method org/apache/hadoop/hbase/protobuf/generated/WALProtos$StoreDescriptor.getDefaultInstance:()Lorg/apache/hadoop/hbase/protobuf/generated/WALProtos$StoreDescriptor;
       3: areturn

  public org.apache.hadoop.hbase.protobuf.generated.WALProtos$StoreDescriptor build();
    Code:
       0: aload_0
       1: invokevirtual #22                 // Method buildPartial:()Lorg/apache/hadoop/hbase/protobuf/generated/WALProtos$StoreDescriptor;
       4: astore_1
       5: aload_1
       6: invokevirtual #25                 // Method org/apache/hadoop/hbase/protobuf/generated/WALProtos$StoreDescriptor.isInitialized:()Z
       9: ifne          17
      12: aload_1
      13: invokestatic  #26                 // Method newUninitializedMessageException:(Lcom/google/protobuf/Message;)Lcom/google/protobuf/UninitializedMessageException;
      16: athrow
      17: aload_1
      18: areturn

  public org.apache.hadoop.hbase.protobuf.generated.WALProtos$StoreDescriptor buildPartial();
    Code:
       0: new           #5                  // class org/apache/hadoop/hbase/protobuf/generated/WALProtos$StoreDescriptor
       3: dup
       4: aload_0
       5: aconst_null
       6: invokespecial #27                 // Method org/apache/hadoop/hbase/protobuf/generated/WALProtos$StoreDescriptor."<init>":(Lcom/google/protobuf/GeneratedMessage$Builder;Lorg/apache/hadoop/hbase/protobuf/generated/WALProtos$1;)V
       9: astore_1
      10: aload_0
      11: getfield      #20                 // Field bitField0_:I
      14: istore_2
      15: iconst_0
      16: istore_3
      17: iload_2
      18: iconst_1
      19: iand
      20: iconst_1
      21: if_icmpne     28
      24: iload_3
      25: iconst_1
      26: ior
      27: istore_3
      28: aload_1
      29: aload_0
      30: getfield      #10                 // Field familyName_:Lcom/google/protobuf/ByteString;
      33: invokestatic  #28                 // Method org/apache/hadoop/hbase/protobuf/generated/WALProtos$StoreDescriptor.access$9202:(Lorg/apache/hadoop/hbase/protobuf/generated/WALProtos$StoreDescriptor;Lcom/google/protobuf/ByteString;)Lcom/google/protobuf/ByteString;
      36: pop
      37: iload_2
      38: iconst_2
      39: iand
      40: iconst_2
      41: if_icmpne     48
      44: iload_3
      45: iconst_2
      46: ior
      47: istore_3
      48: aload_1
      49: aload_0
      50: getfield      #12                 // Field storeHomeDir_:Ljava/lang/Object;
      53: invokestatic  #29                 // Method org/apache/hadoop/hbase/protobuf/generated/WALProtos$StoreDescriptor.access$9302:(Lorg/apache/hadoop/hbase/protobuf/generated/WALProtos$StoreDescriptor;Ljava/lang/Object;)Ljava/lang/Object;
      56: pop
      57: aload_0
      58: getfield      #20                 // Field bitField0_:I
      61: iconst_4
      62: iand
      63: iconst_4
      64: if_icmpne     93
      67: aload_0
      68: new           #30                 // class com/google/protobuf/UnmodifiableLazyStringList
      71: dup
      72: aload_0
      73: getfield      #14                 // Field storeFile_:Lcom/google/protobuf/LazyStringList;
      76: invokespecial #31                 // Method com/google/protobuf/UnmodifiableLazyStringList."<init>":(Lcom/google/protobuf/LazyStringList;)V
      79: putfield      #14                 // Field storeFile_:Lcom/google/protobuf/LazyStringList;
      82: aload_0
      83: aload_0
      84: getfield      #20                 // Field bitField0_:I
      87: bipush        -5
      89: iand
      90: putfield      #20                 // Field bitField0_:I
      93: aload_1
      94: aload_0
      95: getfield      #14                 // Field storeFile_:Lcom/google/protobuf/LazyStringList;
      98: invokestatic  #32                 // Method org/apache/hadoop/hbase/protobuf/generated/WALProtos$StoreDescriptor.access$9402:(Lorg/apache/hadoop/hbase/protobuf/generated/WALProtos$StoreDescriptor;Lcom/google/protobuf/LazyStringList;)Lcom/google/protobuf/LazyStringList;
     101: pop
     102: iload_2
     103: bipush        8
     105: iand
     106: bipush        8
     108: if_icmpne     115
     111: iload_3
     112: iconst_4
     113: ior
     114: istore_3
     115: aload_1
     116: aload_0
     117: getfield      #21                 // Field storeFileSizeBytes_:J
     120: invokestatic  #33                 // Method org/apache/hadoop/hbase/protobuf/generated/WALProtos$StoreDescriptor.access$9502:(Lorg/apache/hadoop/hbase/protobuf/generated/WALProtos$StoreDescriptor;J)J
     123: pop2
     124: aload_1
     125: iload_3
     126: invokestatic  #34                 // Method org/apache/hadoop/hbase/protobuf/generated/WALProtos$StoreDescriptor.access$9602:(Lorg/apache/hadoop/hbase/protobuf/generated/WALProtos$StoreDescriptor;I)I
     129: pop
     130: aload_0
     131: invokevirtual #35                 // Method onBuilt:()V
     134: aload_1
     135: areturn

  public org.apache.hadoop.hbase.protobuf.generated.WALProtos$StoreDescriptor$Builder mergeFrom(com.google.protobuf.Message);
    Code:
       0: aload_1
       1: instanceof    #5                  // class org/apache/hadoop/hbase/protobuf/generated/WALProtos$StoreDescriptor
       4: ifeq          16
       7: aload_0
       8: aload_1
       9: checkcast     #5                  // class org/apache/hadoop/hbase/protobuf/generated/WALProtos$StoreDescriptor
      12: invokevirtual #23                 // Method mergeFrom:(Lorg/apache/hadoop/hbase/protobuf/generated/WALProtos$StoreDescriptor;)Lorg/apache/hadoop/hbase/protobuf/generated/WALProtos$StoreDescriptor$Builder;
      15: areturn
      16: aload_0
      17: aload_1
      18: invokespecial #36                 // Method com/google/protobuf/GeneratedMessage$Builder.mergeFrom:(Lcom/google/protobuf/Message;)Lcom/google/protobuf/AbstractMessage$Builder;
      21: pop
      22: aload_0
      23: areturn

  public org.apache.hadoop.hbase.protobuf.generated.WALProtos$StoreDescriptor$Builder mergeFrom(org.apache.hadoop.hbase.protobuf.generated.WALProtos$StoreDescriptor);
    Code:
       0: aload_1
       1: invokestatic  #24                 // Method org/apache/hadoop/hbase/protobuf/generated/WALProtos$StoreDescriptor.getDefaultInstance:()Lorg/apache/hadoop/hbase/protobuf/generated/WALProtos$StoreDescriptor;
       4: if_acmpne     9
       7: aload_0
       8: areturn
       9: aload_1
      10: invokevirtual #37                 // Method org/apache/hadoop/hbase/protobuf/generated/WALProtos$StoreDescriptor.hasFamilyName:()Z
      13: ifeq          25
      16: aload_0
      17: aload_1
      18: invokevirtual #38                 // Method org/apache/hadoop/hbase/protobuf/generated/WALProtos$StoreDescriptor.getFamilyName:()Lcom/google/protobuf/ByteString;
      21: invokevirtual #39                 // Method setFamilyName:(Lcom/google/protobuf/ByteString;)Lorg/apache/hadoop/hbase/protobuf/generated/WALProtos$StoreDescriptor$Builder;
      24: pop
      25: aload_1
      26: invokevirtual #40                 // Method org/apache/hadoop/hbase/protobuf/generated/WALProtos$StoreDescriptor.hasStoreHomeDir:()Z
      29: ifeq          54
      32: aload_0
      33: dup
      34: getfield      #20                 // Field bitField0_:I
      37: iconst_2
      38: ior
      39: putfield      #20                 // Field bitField0_:I
      42: aload_0
      43: aload_1
      44: invokestatic  #41                 // Method org/apache/hadoop/hbase/protobuf/generated/WALProtos$StoreDescriptor.access$9300:(Lorg/apache/hadoop/hbase/protobuf/generated/WALProtos$StoreDescriptor;)Ljava/lang/Object;
      47: putfield      #12                 // Field storeHomeDir_:Ljava/lang/Object;
      50: aload_0
      51: invokevirtual #42                 // Method onChanged:()V
      54: aload_1
      55: invokestatic  #43                 // Method org/apache/hadoop/hbase/protobuf/generated/WALProtos$StoreDescriptor.access$9400:(Lorg/apache/hadoop/hbase/protobuf/generated/WALProtos$StoreDescriptor;)Lcom/google/protobuf/LazyStringList;
      58: invokeinterface #44,  1           // InterfaceMethod com/google/protobuf/LazyStringList.isEmpty:()Z
      63: ifne          122
      66: aload_0
      67: getfield      #14                 // Field storeFile_:Lcom/google/protobuf/LazyStringList;
      70: invokeinterface #44,  1           // InterfaceMethod com/google/protobuf/LazyStringList.isEmpty:()Z
      75: ifeq          100
      78: aload_0
      79: aload_1
      80: invokestatic  #43                 // Method org/apache/hadoop/hbase/protobuf/generated/WALProtos$StoreDescriptor.access$9400:(Lorg/apache/hadoop/hbase/protobuf/generated/WALProtos$StoreDescriptor;)Lcom/google/protobuf/LazyStringList;
      83: putfield      #14                 // Field storeFile_:Lcom/google/protobuf/LazyStringList;
      86: aload_0
      87: aload_0
      88: getfield      #20                 // Field bitField0_:I
      91: bipush        -5
      93: iand
      94: putfield      #20                 // Field bitField0_:I
      97: goto          118
     100: aload_0
     101: invokespecial #45                 // Method ensureStoreFileIsMutable:()V
     104: aload_0
     105: getfield      #14                 // Field storeFile_:Lcom/google/protobuf/LazyStringList;
     108: aload_1
     109: invokestatic  #43                 // Method org/apache/hadoop/hbase/protobuf/generated/WALProtos$StoreDescriptor.access$9400:(Lorg/apache/hadoop/hbase/protobuf/generated/WALProtos$StoreDescriptor;)Lcom/google/protobuf/LazyStringList;
     112: invokeinterface #46,  2           // InterfaceMethod com/google/protobuf/LazyStringList.addAll:(Ljava/util/Collection;)Z
     117: pop
     118: aload_0
     119: invokevirtual #42                 // Method onChanged:()V
     122: aload_1
     123: invokevirtual #47                 // Method org/apache/hadoop/hbase/protobuf/generated/WALProtos$StoreDescriptor.hasStoreFileSizeBytes:()Z
     126: ifeq          138
     129: aload_0
     130: aload_1
     131: invokevirtual #48                 // Method org/apache/hadoop/hbase/protobuf/generated/WALProtos$StoreDescriptor.getStoreFileSizeBytes:()J
     134: invokevirtual #49                 // Method setStoreFileSizeBytes:(J)Lorg/apache/hadoop/hbase/protobuf/generated/WALProtos$StoreDescriptor$Builder;
     137: pop
     138: aload_0
     139: aload_1
     140: invokevirtual #50                 // Method org/apache/hadoop/hbase/protobuf/generated/WALProtos$StoreDescriptor.getUnknownFields:()Lcom/google/protobuf/UnknownFieldSet;
     143: invokevirtual #51                 // Method mergeUnknownFields:(Lcom/google/protobuf/UnknownFieldSet;)Lcom/google/protobuf/GeneratedMessage$Builder;
     146: pop
     147: aload_0
     148: areturn

  public final boolean isInitialized();
    Code:
       0: aload_0
       1: invokevirtual #52                 // Method hasFamilyName:()Z
       4: ifne          9
       7: iconst_0
       8: ireturn
       9: aload_0
      10: invokevirtual #53                 // Method hasStoreHomeDir:()Z
      13: ifne          18
      16: iconst_0
      17: ireturn
      18: iconst_1
      19: ireturn

  public org.apache.hadoop.hbase.protobuf.generated.WALProtos$StoreDescriptor$Builder mergeFrom(com.google.protobuf.CodedInputStream, com.google.protobuf.ExtensionRegistryLite) throws java.io.IOException;
    Code:
       0: aconst_null
       1: astore_3
       2: getstatic     #54                 // Field org/apache/hadoop/hbase/protobuf/generated/WALProtos$StoreDescriptor.PARSER:Lcom/google/protobuf/Parser;
       5: aload_1
       6: aload_2
       7: invokeinterface #55,  3           // InterfaceMethod com/google/protobuf/Parser.parsePartialFrom:(Lcom/google/protobuf/CodedInputStream;Lcom/google/protobuf/ExtensionRegistryLite;)Ljava/lang/Object;
      12: checkcast     #5                  // class org/apache/hadoop/hbase/protobuf/generated/WALProtos$StoreDescriptor
      15: astore_3
      16: aload_3
      17: ifnull        58
      20: aload_0
      21: aload_3
      22: invokevirtual #23                 // Method mergeFrom:(Lorg/apache/hadoop/hbase/protobuf/generated/WALProtos$StoreDescriptor;)Lorg/apache/hadoop/hbase/protobuf/generated/WALProtos$StoreDescriptor$Builder;
      25: pop
      26: goto          58
      29: astore        4
      31: aload         4
      33: invokevirtual #57                 // Method com/google/protobuf/InvalidProtocolBufferException.getUnfinishedMessage:()Lcom/google/protobuf/MessageLite;
      36: checkcast     #5                  // class org/apache/hadoop/hbase/protobuf/generated/WALProtos$StoreDescriptor
      39: astore_3
      40: aload         4
      42: athrow
      43: astore        5
      45: aload_3
      46: ifnull        55
      49: aload_0
      50: aload_3
      51: invokevirtual #23                 // Method mergeFrom:(Lorg/apache/hadoop/hbase/protobuf/generated/WALProtos$StoreDescriptor;)Lorg/apache/hadoop/hbase/protobuf/generated/WALProtos$StoreDescriptor$Builder;
      54: pop
      55: aload         5
      57: athrow
      58: aload_0
      59: areturn
    Exception table:
       from    to  target type
           2    16    29   Class com/google/protobuf/InvalidProtocolBufferException
           2    16    43   any
          29    45    43   any

  public boolean hasFamilyName();
    Code:
       0: aload_0
       1: getfield      #20                 // Field bitField0_:I
       4: iconst_1
       5: iand
       6: iconst_1
       7: if_icmpne     14
      10: iconst_1
      11: goto          15
      14: iconst_0
      15: ireturn

  public com.google.protobuf.ByteString getFamilyName();
    Code:
       0: aload_0
       1: getfield      #10                 // Field familyName_:Lcom/google/protobuf/ByteString;
       4: areturn

  public org.apache.hadoop.hbase.protobuf.generated.WALProtos$StoreDescriptor$Builder setFamilyName(com.google.protobuf.ByteString);
    Code:
       0: aload_1
       1: ifnonnull     12
       4: new           #58                 // class java/lang/NullPointerException
       7: dup
       8: invokespecial #59                 // Method java/lang/NullPointerException."<init>":()V
      11: athrow
      12: aload_0
      13: dup
      14: getfield      #20                 // Field bitField0_:I
      17: iconst_1
      18: ior
      19: putfield      #20                 // Field bitField0_:I
      22: aload_0
      23: aload_1
      24: putfield      #10                 // Field familyName_:Lcom/google/protobuf/ByteString;
      27: aload_0
      28: invokevirtual #42                 // Method onChanged:()V
      31: aload_0
      32: areturn

  public org.apache.hadoop.hbase.protobuf.generated.WALProtos$StoreDescriptor$Builder clearFamilyName();
    Code:
       0: aload_0
       1: aload_0
       2: getfield      #20                 // Field bitField0_:I
       5: bipush        -2
       7: iand
       8: putfield      #20                 // Field bitField0_:I
      11: aload_0
      12: invokestatic  #24                 // Method org/apache/hadoop/hbase/protobuf/generated/WALProtos$StoreDescriptor.getDefaultInstance:()Lorg/apache/hadoop/hbase/protobuf/generated/WALProtos$StoreDescriptor;
      15: invokevirtual #38                 // Method org/apache/hadoop/hbase/protobuf/generated/WALProtos$StoreDescriptor.getFamilyName:()Lcom/google/protobuf/ByteString;
      18: putfield      #10                 // Field familyName_:Lcom/google/protobuf/ByteString;
      21: aload_0
      22: invokevirtual #42                 // Method onChanged:()V
      25: aload_0
      26: areturn

  public boolean hasStoreHomeDir();
    Code:
       0: aload_0
       1: getfield      #20                 // Field bitField0_:I
       4: iconst_2
       5: iand
       6: iconst_2
       7: if_icmpne     14
      10: iconst_1
      11: goto          15
      14: iconst_0
      15: ireturn

  public java.lang.String getStoreHomeDir();
    Code:
       0: aload_0
       1: getfield      #12                 // Field storeHomeDir_:Ljava/lang/Object;
       4: astore_1
       5: aload_1
       6: instanceof    #60                 // class java/lang/String
       9: ifne          27
      12: aload_1
      13: checkcast     #61                 // class com/google/protobuf/ByteString
      16: invokevirtual #62                 // Method com/google/protobuf/ByteString.toStringUtf8:()Ljava/lang/String;
      19: astore_2
      20: aload_0
      21: aload_2
      22: putfield      #12                 // Field storeHomeDir_:Ljava/lang/Object;
      25: aload_2
      26: areturn
      27: aload_1
      28: checkcast     #60                 // class java/lang/String
      31: areturn

  public com.google.protobuf.ByteString getStoreHomeDirBytes();
    Code:
       0: aload_0
       1: getfield      #12                 // Field storeHomeDir_:Ljava/lang/Object;
       4: astore_1
       5: aload_1
       6: instanceof    #60                 // class java/lang/String
       9: ifeq          27
      12: aload_1
      13: checkcast     #60                 // class java/lang/String
      16: invokestatic  #63                 // Method com/google/protobuf/ByteString.copyFromUtf8:(Ljava/lang/String;)Lcom/google/protobuf/ByteString;
      19: astore_2
      20: aload_0
      21: aload_2
      22: putfield      #12                 // Field storeHomeDir_:Ljava/lang/Object;
      25: aload_2
      26: areturn
      27: aload_1
      28: checkcast     #61                 // class com/google/protobuf/ByteString
      31: areturn

  public org.apache.hadoop.hbase.protobuf.generated.WALProtos$StoreDescriptor$Builder setStoreHomeDir(java.lang.String);
    Code:
       0: aload_1
       1: ifnonnull     12
       4: new           #58                 // class java/lang/NullPointerException
       7: dup
       8: invokespecial #59                 // Method java/lang/NullPointerException."<init>":()V
      11: athrow
      12: aload_0
      13: dup
      14: getfield      #20                 // Field bitField0_:I
      17: iconst_2
      18: ior
      19: putfield      #20                 // Field bitField0_:I
      22: aload_0
      23: aload_1
      24: putfield      #12                 // Field storeHomeDir_:Ljava/lang/Object;
      27: aload_0
      28: invokevirtual #42                 // Method onChanged:()V
      31: aload_0
      32: areturn

  public org.apache.hadoop.hbase.protobuf.generated.WALProtos$StoreDescriptor$Builder clearStoreHomeDir();
    Code:
       0: aload_0
       1: aload_0
       2: getfield      #20                 // Field bitField0_:I
       5: bipush        -3
       7: iand
       8: putfield      #20                 // Field bitField0_:I
      11: aload_0
      12: invokestatic  #24                 // Method org/apache/hadoop/hbase/protobuf/generated/WALProtos$StoreDescriptor.getDefaultInstance:()Lorg/apache/hadoop/hbase/protobuf/generated/WALProtos$StoreDescriptor;
      15: invokevirtual #64                 // Method org/apache/hadoop/hbase/protobuf/generated/WALProtos$StoreDescriptor.getStoreHomeDir:()Ljava/lang/String;
      18: putfield      #12                 // Field storeHomeDir_:Ljava/lang/Object;
      21: aload_0
      22: invokevirtual #42                 // Method onChanged:()V
      25: aload_0
      26: areturn

  public org.apache.hadoop.hbase.protobuf.generated.WALProtos$StoreDescriptor$Builder setStoreHomeDirBytes(com.google.protobuf.ByteString);
    Code:
       0: aload_1
       1: ifnonnull     12
       4: new           #58                 // class java/lang/NullPointerException
       7: dup
       8: invokespecial #59                 // Method java/lang/NullPointerException."<init>":()V
      11: athrow
      12: aload_0
      13: dup
      14: getfield      #20                 // Field bitField0_:I
      17: iconst_2
      18: ior
      19: putfield      #20                 // Field bitField0_:I
      22: aload_0
      23: aload_1
      24: putfield      #12                 // Field storeHomeDir_:Ljava/lang/Object;
      27: aload_0
      28: invokevirtual #42                 // Method onChanged:()V
      31: aload_0
      32: areturn

  public java.util.List<java.lang.String> getStoreFileList();
    Code:
       0: aload_0
       1: getfield      #14                 // Field storeFile_:Lcom/google/protobuf/LazyStringList;
       4: invokestatic  #67                 // Method java/util/Collections.unmodifiableList:(Ljava/util/List;)Ljava/util/List;
       7: areturn

  public int getStoreFileCount();
    Code:
       0: aload_0
       1: getfield      #14                 // Field storeFile_:Lcom/google/protobuf/LazyStringList;
       4: invokeinterface #68,  1           // InterfaceMethod com/google/protobuf/LazyStringList.size:()I
       9: ireturn

  public java.lang.String getStoreFile(int);
    Code:
       0: aload_0
       1: getfield      #14                 // Field storeFile_:Lcom/google/protobuf/LazyStringList;
       4: iload_1
       5: invokeinterface #69,  2           // InterfaceMethod com/google/protobuf/LazyStringList.get:(I)Ljava/lang/Object;
      10: checkcast     #60                 // class java/lang/String
      13: areturn

  public com.google.protobuf.ByteString getStoreFileBytes(int);
    Code:
       0: aload_0
       1: getfield      #14                 // Field storeFile_:Lcom/google/protobuf/LazyStringList;
       4: iload_1
       5: invokeinterface #70,  2           // InterfaceMethod com/google/protobuf/LazyStringList.getByteString:(I)Lcom/google/protobuf/ByteString;
      10: areturn

  public org.apache.hadoop.hbase.protobuf.generated.WALProtos$StoreDescriptor$Builder setStoreFile(int, java.lang.String);
    Code:
       0: aload_2
       1: ifnonnull     12
       4: new           #58                 // class java/lang/NullPointerException
       7: dup
       8: invokespecial #59                 // Method java/lang/NullPointerException."<init>":()V
      11: athrow
      12: aload_0
      13: invokespecial #45                 // Method ensureStoreFileIsMutable:()V
      16: aload_0
      17: getfield      #14                 // Field storeFile_:Lcom/google/protobuf/LazyStringList;
      20: iload_1
      21: aload_2
      22: invokeinterface #71,  3           // InterfaceMethod com/google/protobuf/LazyStringList.set:(ILjava/lang/Object;)Ljava/lang/Object;
      27: pop
      28: aload_0
      29: invokevirtual #42                 // Method onChanged:()V
      32: aload_0
      33: areturn

  public org.apache.hadoop.hbase.protobuf.generated.WALProtos$StoreDescriptor$Builder addStoreFile(java.lang.String);
    Code:
       0: aload_1
       1: ifnonnull     12
       4: new           #58                 // class java/lang/NullPointerException
       7: dup
       8: invokespecial #59                 // Method java/lang/NullPointerException."<init>":()V
      11: athrow
      12: aload_0
      13: invokespecial #45                 // Method ensureStoreFileIsMutable:()V
      16: aload_0
      17: getfield      #14                 // Field storeFile_:Lcom/google/protobuf/LazyStringList;
      20: aload_1
      21: invokeinterface #72,  2           // InterfaceMethod com/google/protobuf/LazyStringList.add:(Ljava/lang/Object;)Z
      26: pop
      27: aload_0
      28: invokevirtual #42                 // Method onChanged:()V
      31: aload_0
      32: areturn

  public org.apache.hadoop.hbase.protobuf.generated.WALProtos$StoreDescriptor$Builder addAllStoreFile(java.lang.Iterable<java.lang.String>);
    Code:
       0: aload_0
       1: invokespecial #45                 // Method ensureStoreFileIsMutable:()V
       4: aload_1
       5: aload_0
       6: getfield      #14                 // Field storeFile_:Lcom/google/protobuf/LazyStringList;
       9: invokestatic  #73                 // Method com/google/protobuf/GeneratedMessage$Builder.addAll:(Ljava/lang/Iterable;Ljava/util/Collection;)V
      12: aload_0
      13: invokevirtual #42                 // Method onChanged:()V
      16: aload_0
      17: areturn

  public org.apache.hadoop.hbase.protobuf.generated.WALProtos$StoreDescriptor$Builder clearStoreFile();
    Code:
       0: aload_0
       1: getstatic     #13                 // Field com/google/protobuf/LazyStringArrayList.EMPTY:Lcom/google/protobuf/LazyStringList;
       4: putfield      #14                 // Field storeFile_:Lcom/google/protobuf/LazyStringList;
       7: aload_0
       8: aload_0
       9: getfield      #20                 // Field bitField0_:I
      12: bipush        -5
      14: iand
      15: putfield      #20                 // Field bitField0_:I
      18: aload_0
      19: invokevirtual #42                 // Method onChanged:()V
      22: aload_0
      23: areturn

  public org.apache.hadoop.hbase.protobuf.generated.WALProtos$StoreDescriptor$Builder addStoreFileBytes(com.google.protobuf.ByteString);
    Code:
       0: aload_1
       1: ifnonnull     12
       4: new           #58                 // class java/lang/NullPointerException
       7: dup
       8: invokespecial #59                 // Method java/lang/NullPointerException."<init>":()V
      11: athrow
      12: aload_0
      13: invokespecial #45                 // Method ensureStoreFileIsMutable:()V
      16: aload_0
      17: getfield      #14                 // Field storeFile_:Lcom/google/protobuf/LazyStringList;
      20: aload_1
      21: invokeinterface #74,  2           // InterfaceMethod com/google/protobuf/LazyStringList.add:(Lcom/google/protobuf/ByteString;)V
      26: aload_0
      27: invokevirtual #42                 // Method onChanged:()V
      30: aload_0
      31: areturn

  public boolean hasStoreFileSizeBytes();
    Code:
       0: aload_0
       1: getfield      #20                 // Field bitField0_:I
       4: bipush        8
       6: iand
       7: bipush        8
       9: if_icmpne     16
      12: iconst_1
      13: goto          17
      16: iconst_0
      17: ireturn

  public long getStoreFileSizeBytes();
    Code:
       0: aload_0
       1: getfield      #21                 // Field storeFileSizeBytes_:J
       4: lreturn

  public org.apache.hadoop.hbase.protobuf.generated.WALProtos$StoreDescriptor$Builder setStoreFileSizeBytes(long);
    Code:
       0: aload_0
       1: dup
       2: getfield      #20                 // Field bitField0_:I
       5: bipush        8
       7: ior
       8: putfield      #20                 // Field bitField0_:I
      11: aload_0
      12: lload_1
      13: putfield      #21                 // Field storeFileSizeBytes_:J
      16: aload_0
      17: invokevirtual #42                 // Method onChanged:()V
      20: aload_0
      21: areturn

  public org.apache.hadoop.hbase.protobuf.generated.WALProtos$StoreDescriptor$Builder clearStoreFileSizeBytes();
    Code:
       0: aload_0
       1: aload_0
       2: getfield      #20                 // Field bitField0_:I
       5: bipush        -9
       7: iand
       8: putfield      #20                 // Field bitField0_:I
      11: aload_0
      12: lconst_0
      13: putfield      #21                 // Field storeFileSizeBytes_:J
      16: aload_0
      17: invokevirtual #42                 // Method onChanged:()V
      20: aload_0
      21: areturn

  public com.google.protobuf.GeneratedMessage$Builder clear();
    Code:
       0: aload_0
       1: invokevirtual #75                 // Method clear:()Lorg/apache/hadoop/hbase/protobuf/generated/WALProtos$StoreDescriptor$Builder;
       4: areturn

  public com.google.protobuf.GeneratedMessage$Builder clone();
    Code:
       0: aload_0
       1: invokevirtual #76                 // Method clone:()Lorg/apache/hadoop/hbase/protobuf/generated/WALProtos$StoreDescriptor$Builder;
       4: areturn

  public com.google.protobuf.AbstractMessage$Builder mergeFrom(com.google.protobuf.CodedInputStream, com.google.protobuf.ExtensionRegistryLite) throws java.io.IOException;
    Code:
       0: aload_0
       1: aload_1
       2: aload_2
       3: invokevirtual #77                 // Method mergeFrom:(Lcom/google/protobuf/CodedInputStream;Lcom/google/protobuf/ExtensionRegistryLite;)Lorg/apache/hadoop/hbase/protobuf/generated/WALProtos$StoreDescriptor$Builder;
       6: areturn

  public com.google.protobuf.AbstractMessage$Builder mergeFrom(com.google.protobuf.Message);
    Code:
       0: aload_0
       1: aload_1
       2: invokevirtual #78                 // Method mergeFrom:(Lcom/google/protobuf/Message;)Lorg/apache/hadoop/hbase/protobuf/generated/WALProtos$StoreDescriptor$Builder;
       5: areturn

  public com.google.protobuf.AbstractMessage$Builder clear();
    Code:
       0: aload_0
       1: invokevirtual #75                 // Method clear:()Lorg/apache/hadoop/hbase/protobuf/generated/WALProtos$StoreDescriptor$Builder;
       4: areturn

  public com.google.protobuf.AbstractMessage$Builder clone();
    Code:
       0: aload_0
       1: invokevirtual #76                 // Method clone:()Lorg/apache/hadoop/hbase/protobuf/generated/WALProtos$StoreDescriptor$Builder;
       4: areturn

  public com.google.protobuf.Message$Builder mergeFrom(com.google.protobuf.CodedInputStream, com.google.protobuf.ExtensionRegistryLite) throws java.io.IOException;
    Code:
       0: aload_0
       1: aload_1
       2: aload_2
       3: invokevirtual #77                 // Method mergeFrom:(Lcom/google/protobuf/CodedInputStream;Lcom/google/protobuf/ExtensionRegistryLite;)Lorg/apache/hadoop/hbase/protobuf/generated/WALProtos$StoreDescriptor$Builder;
       6: areturn

  public com.google.protobuf.Message$Builder clone();
    Code:
       0: aload_0
       1: invokevirtual #76                 // Method clone:()Lorg/apache/hadoop/hbase/protobuf/generated/WALProtos$StoreDescriptor$Builder;
       4: areturn

  public com.google.protobuf.Message buildPartial();
    Code:
       0: aload_0
       1: invokevirtual #22                 // Method buildPartial:()Lorg/apache/hadoop/hbase/protobuf/generated/WALProtos$StoreDescriptor;
       4: areturn

  public com.google.protobuf.Message build();
    Code:
       0: aload_0
       1: invokevirtual #79                 // Method build:()Lorg/apache/hadoop/hbase/protobuf/generated/WALProtos$StoreDescriptor;
       4: areturn

  public com.google.protobuf.Message$Builder mergeFrom(com.google.protobuf.Message);
    Code:
       0: aload_0
       1: aload_1
       2: invokevirtual #78                 // Method mergeFrom:(Lcom/google/protobuf/Message;)Lorg/apache/hadoop/hbase/protobuf/generated/WALProtos$StoreDescriptor$Builder;
       5: areturn

  public com.google.protobuf.Message$Builder clear();
    Code:
       0: aload_0
       1: invokevirtual #75                 // Method clear:()Lorg/apache/hadoop/hbase/protobuf/generated/WALProtos$StoreDescriptor$Builder;
       4: areturn

  public com.google.protobuf.MessageLite$Builder mergeFrom(com.google.protobuf.CodedInputStream, com.google.protobuf.ExtensionRegistryLite) throws java.io.IOException;
    Code:
       0: aload_0
       1: aload_1
       2: aload_2
       3: invokevirtual #77                 // Method mergeFrom:(Lcom/google/protobuf/CodedInputStream;Lcom/google/protobuf/ExtensionRegistryLite;)Lorg/apache/hadoop/hbase/protobuf/generated/WALProtos$StoreDescriptor$Builder;
       6: areturn

  public com.google.protobuf.MessageLite$Builder clone();
    Code:
       0: aload_0
       1: invokevirtual #76                 // Method clone:()Lorg/apache/hadoop/hbase/protobuf/generated/WALProtos$StoreDescriptor$Builder;
       4: areturn

  public com.google.protobuf.MessageLite buildPartial();
    Code:
       0: aload_0
       1: invokevirtual #22                 // Method buildPartial:()Lorg/apache/hadoop/hbase/protobuf/generated/WALProtos$StoreDescriptor;
       4: areturn

  public com.google.protobuf.MessageLite build();
    Code:
       0: aload_0
       1: invokevirtual #79                 // Method build:()Lorg/apache/hadoop/hbase/protobuf/generated/WALProtos$StoreDescriptor;
       4: areturn

  public com.google.protobuf.MessageLite$Builder clear();
    Code:
       0: aload_0
       1: invokevirtual #75                 // Method clear:()Lorg/apache/hadoop/hbase/protobuf/generated/WALProtos$StoreDescriptor$Builder;
       4: areturn

  public com.google.protobuf.MessageLite getDefaultInstanceForType();
    Code:
       0: aload_0
       1: invokevirtual #80                 // Method getDefaultInstanceForType:()Lorg/apache/hadoop/hbase/protobuf/generated/WALProtos$StoreDescriptor;
       4: areturn

  public com.google.protobuf.Message getDefaultInstanceForType();
    Code:
       0: aload_0
       1: invokevirtual #80                 // Method getDefaultInstanceForType:()Lorg/apache/hadoop/hbase/protobuf/generated/WALProtos$StoreDescriptor;
       4: areturn

  public com.google.protobuf.AbstractMessageLite$Builder mergeFrom(com.google.protobuf.CodedInputStream, com.google.protobuf.ExtensionRegistryLite) throws java.io.IOException;
    Code:
       0: aload_0
       1: aload_1
       2: aload_2
       3: invokevirtual #77                 // Method mergeFrom:(Lcom/google/protobuf/CodedInputStream;Lcom/google/protobuf/ExtensionRegistryLite;)Lorg/apache/hadoop/hbase/protobuf/generated/WALProtos$StoreDescriptor$Builder;
       6: areturn

  public com.google.protobuf.AbstractMessageLite$Builder clone();
    Code:
       0: aload_0
       1: invokevirtual #76                 // Method clone:()Lorg/apache/hadoop/hbase/protobuf/generated/WALProtos$StoreDescriptor$Builder;
       4: areturn

  public java.lang.Object clone() throws java.lang.CloneNotSupportedException;
    Code:
       0: aload_0
       1: invokevirtual #76                 // Method clone:()Lorg/apache/hadoop/hbase/protobuf/generated/WALProtos$StoreDescriptor$Builder;
       4: areturn

  static org.apache.hadoop.hbase.protobuf.generated.WALProtos$StoreDescriptor$Builder access$8800();
    Code:
       0: invokestatic  #2                  // Method create:()Lorg/apache/hadoop/hbase/protobuf/generated/WALProtos$StoreDescriptor$Builder;
       3: areturn

  org.apache.hadoop.hbase.protobuf.generated.WALProtos$StoreDescriptor$Builder(com.google.protobuf.GeneratedMessage$BuilderParent, org.apache.hadoop.hbase.protobuf.generated.WALProtos$1);
    Code:
       0: aload_0
       1: aload_1
       2: invokespecial #1                  // Method "<init>":(Lcom/google/protobuf/GeneratedMessage$BuilderParent;)V
       5: return
}
