Compiled from "WALProcedureTree.java"
final class org.apache.hadoop.hbase.procedure2.store.wal.WALProcedureTree$Entry {
  public org.apache.hadoop.hbase.procedure2.store.wal.WALProcedureTree$Entry(org.apache.hadoop.hbase.shaded.protobuf.generated.ProcedureProtos$Procedure);
    Code:
       0: aload_0
       1: invokespecial #3                  // Method java/lang/Object."<init>":()V
       4: aload_0
       5: new           #4                  // class java/util/ArrayList
       8: dup
       9: invokespecial #5                  // Method java/util/ArrayList."<init>":()V
      12: putfield      #1                  // Field subProcs:Ljava/util/List;
      15: aload_0
      16: aload_1
      17: putfield      #2                  // Field proc:Lorg/apache/hadoop/hbase/shaded/protobuf/generated/ProcedureProtos$Procedure;
      20: return

  public java.lang.String toString();
    Code:
       0: new           #6                  // class java/lang/StringBuilder
       3: dup
       4: invokespecial #7                  // Method java/lang/StringBuilder."<init>":()V
       7: astore_1
       8: aload_1
       9: ldc           #8                  // String Procedure(pid=
      11: invokevirtual #9                  // Method java/lang/StringBuilder.append:(Ljava/lang/String;)Ljava/lang/StringBuilder;
      14: pop
      15: aload_1
      16: aload_0
      17: getfield      #2                  // Field proc:Lorg/apache/hadoop/hbase/shaded/protobuf/generated/ProcedureProtos$Procedure;
      20: invokevirtual #10                 // Method org/apache/hadoop/hbase/shaded/protobuf/generated/ProcedureProtos$Procedure.getProcId:()J
      23: invokevirtual #11                 // Method java/lang/StringBuilder.append:(J)Ljava/lang/StringBuilder;
      26: pop
      27: aload_1
      28: ldc           #12                 // String , ppid=
      30: invokevirtual #9                  // Method java/lang/StringBuilder.append:(Ljava/lang/String;)Ljava/lang/StringBuilder;
      33: pop
      34: aload_1
      35: aload_0
      36: getfield      #2                  // Field proc:Lorg/apache/hadoop/hbase/shaded/protobuf/generated/ProcedureProtos$Procedure;
      39: invokevirtual #13                 // Method org/apache/hadoop/hbase/shaded/protobuf/generated/ProcedureProtos$Procedure.hasParentId:()Z
      42: ifeq          55
      45: aload_0
      46: getfield      #2                  // Field proc:Lorg/apache/hadoop/hbase/shaded/protobuf/generated/ProcedureProtos$Procedure;
      49: invokevirtual #14                 // Method org/apache/hadoop/hbase/shaded/protobuf/generated/ProcedureProtos$Procedure.getParentId:()J
      52: goto          58
      55: ldc2_w        #16                 // long -1l
      58: invokevirtual #11                 // Method java/lang/StringBuilder.append:(J)Ljava/lang/StringBuilder;
      61: pop
      62: aload_1
      63: ldc           #18                 // String , class=
      65: invokevirtual #9                  // Method java/lang/StringBuilder.append:(Ljava/lang/String;)Ljava/lang/StringBuilder;
      68: pop
      69: aload_1
      70: aload_0
      71: getfield      #2                  // Field proc:Lorg/apache/hadoop/hbase/shaded/protobuf/generated/ProcedureProtos$Procedure;
      74: invokevirtual #19                 // Method org/apache/hadoop/hbase/shaded/protobuf/generated/ProcedureProtos$Procedure.getClassName:()Ljava/lang/String;
      77: invokevirtual #9                  // Method java/lang/StringBuilder.append:(Ljava/lang/String;)Ljava/lang/StringBuilder;
      80: pop
      81: aload_1
      82: ldc           #20                 // String )
      84: invokevirtual #9                  // Method java/lang/StringBuilder.append:(Ljava/lang/String;)Ljava/lang/StringBuilder;
      87: pop
      88: aload_1
      89: invokevirtual #21                 // Method java/lang/StringBuilder.toString:()Ljava/lang/String;
      92: areturn

  static org.apache.hadoop.hbase.shaded.protobuf.generated.ProcedureProtos$Procedure access$000(org.apache.hadoop.hbase.procedure2.store.wal.WALProcedureTree$Entry);
    Code:
       0: aload_0
       1: getfield      #2                  // Field proc:Lorg/apache/hadoop/hbase/shaded/protobuf/generated/ProcedureProtos$Procedure;
       4: areturn

  static java.util.List access$100(org.apache.hadoop.hbase.procedure2.store.wal.WALProcedureTree$Entry);
    Code:
       0: aload_0
       1: getfield      #1                  // Field subProcs:Ljava/util/List;
       4: areturn
}
