Compiled from "WeakObjectPool.java"
class org.apache.hadoop.hbase.util.WeakObjectPool$WeakObjectReference extends java.lang.ref.WeakReference<V> {
  final K key;

  final org.apache.hadoop.hbase.util.WeakObjectPool this$0;

  org.apache.hadoop.hbase.util.WeakObjectPool$WeakObjectReference(K, V);
    Code:
       0: aload_0
       1: aload_1
       2: putfield      #1                  // Field this$0:Lorg/apache/hadoop/hbase/util/WeakObjectPool;
       5: aload_0
       6: aload_3
       7: aload_1
       8: getfield      #2                  // Field org/apache/hadoop/hbase/util/WeakObjectPool.staleRefQueue:Ljava/lang/ref/ReferenceQueue;
      11: invokespecial #3                  // Method java/lang/ref/WeakReference."<init>":(Ljava/lang/Object;Ljava/lang/ref/ReferenceQueue;)V
      14: aload_0
      15: aload_2
      16: putfield      #4                  // Field key:Ljava/lang/Object;
      19: return
}
