Compiled from "ZKLeaderManager.java"
public class org.apache.hadoop.hbase.zookeeper.ZKLeaderManager extends org.apache.hadoop.hbase.zookeeper.ZKListener {
  public org.apache.hadoop.hbase.zookeeper.ZKLeaderManager(org.apache.hadoop.hbase.zookeeper.ZKWatcher, java.lang.String, byte[], org.apache.hadoop.hbase.Stoppable);
    Code:
       0: aload_0
       1: aload_1
       2: invokespecial #1                  // Method org/apache/hadoop/hbase/zookeeper/ZKListener."<init>":(Lorg/apache/hadoop/hbase/zookeeper/ZKWatcher;)V
       5: aload_0
       6: new           #2                  // class java/lang/Object
       9: dup
      10: invokespecial #3                  // Method java/lang/Object."<init>":()V
      13: putfield      #4                  // Field lock:Ljava/lang/Object;
      16: aload_0
      17: new           #5                  // class java/util/concurrent/atomic/AtomicBoolean
      20: dup
      21: invokespecial #6                  // Method java/util/concurrent/atomic/AtomicBoolean."<init>":()V
      24: putfield      #7                  // Field leaderExists:Ljava/util/concurrent/atomic/AtomicBoolean;
      27: aload_0
      28: aload_2
      29: putfield      #8                  // Field leaderZNode:Ljava/lang/String;
      32: aload_0
      33: aload_3
      34: putfield      #9                  // Field nodeId:[B
      37: aload_0
      38: aload         4
      40: putfield      #10                 // Field candidate:Lorg/apache/hadoop/hbase/Stoppable;
      43: return

  public void start();
    Code:
       0: aload_0
       1: getfield      #11                 // Field watcher:Lorg/apache/hadoop/hbase/zookeeper/ZKWatcher;
       4: aload_0
       5: invokevirtual #12                 // Method org/apache/hadoop/hbase/zookeeper/ZKWatcher.registerListener:(Lorg/apache/hadoop/hbase/zookeeper/ZKListener;)V
       8: aload_0
       9: getfield      #8                  // Field leaderZNode:Ljava/lang/String;
      12: invokestatic  #13                 // Method org/apache/hadoop/hbase/zookeeper/ZKUtil.getParent:(Ljava/lang/String;)Ljava/lang/String;
      15: astore_1
      16: aload_0
      17: getfield      #11                 // Field watcher:Lorg/apache/hadoop/hbase/zookeeper/ZKWatcher;
      20: aload_1
      21: invokestatic  #14                 // Method org/apache/hadoop/hbase/zookeeper/ZKUtil.checkExists:(Lorg/apache/hadoop/hbase/zookeeper/ZKWatcher;Ljava/lang/String;)I
      24: ifge          35
      27: aload_0
      28: getfield      #11                 // Field watcher:Lorg/apache/hadoop/hbase/zookeeper/ZKWatcher;
      31: aload_1
      32: invokestatic  #15                 // Method org/apache/hadoop/hbase/zookeeper/ZKUtil.createWithParents:(Lorg/apache/hadoop/hbase/zookeeper/ZKWatcher;Ljava/lang/String;)V
      35: goto          80
      38: astore_1
      39: aload_0
      40: getfield      #11                 // Field watcher:Lorg/apache/hadoop/hbase/zookeeper/ZKWatcher;
      43: ldc           #17                 // String Unhandled zk exception when starting
      45: aload_1
      46: invokevirtual #18                 // Method org/apache/hadoop/hbase/zookeeper/ZKWatcher.abort:(Ljava/lang/String;Ljava/lang/Throwable;)V
      49: aload_0
      50: getfield      #10                 // Field candidate:Lorg/apache/hadoop/hbase/Stoppable;
      53: new           #19                 // class java/lang/StringBuilder
      56: dup
      57: invokespecial #20                 // Method java/lang/StringBuilder."<init>":()V
      60: ldc           #21                 // String Unhandled zk exception starting up:
      62: invokevirtual #22                 // Method java/lang/StringBuilder.append:(Ljava/lang/String;)Ljava/lang/StringBuilder;
      65: aload_1
      66: invokevirtual #23                 // Method org/apache/zookeeper/KeeperException.getMessage:()Ljava/lang/String;
      69: invokevirtual #22                 // Method java/lang/StringBuilder.append:(Ljava/lang/String;)Ljava/lang/StringBuilder;
      72: invokevirtual #24                 // Method java/lang/StringBuilder.toString:()Ljava/lang/String;
      75: invokeinterface #25,  2           // InterfaceMethod org/apache/hadoop/hbase/Stoppable.stop:(Ljava/lang/String;)V
      80: return
    Exception table:
       from    to  target type
           0    35    38   Class org/apache/zookeeper/KeeperException

  public void nodeCreated(java.lang.String);
    Code:
       0: aload_0
       1: getfield      #8                  // Field leaderZNode:Ljava/lang/String;
       4: aload_1
       5: invokevirtual #26                 // Method java/lang/String.equals:(Ljava/lang/Object;)Z
       8: ifeq          27
      11: aload_0
      12: getfield      #10                 // Field candidate:Lorg/apache/hadoop/hbase/Stoppable;
      15: invokeinterface #27,  1           // InterfaceMethod org/apache/hadoop/hbase/Stoppable.isStopped:()Z
      20: ifne          27
      23: aload_0
      24: invokespecial #28                 // Method handleLeaderChange:()V
      27: return

  public void nodeDeleted(java.lang.String);
    Code:
       0: aload_0
       1: getfield      #8                  // Field leaderZNode:Ljava/lang/String;
       4: aload_1
       5: invokevirtual #26                 // Method java/lang/String.equals:(Ljava/lang/Object;)Z
       8: ifeq          27
      11: aload_0
      12: getfield      #10                 // Field candidate:Lorg/apache/hadoop/hbase/Stoppable;
      15: invokeinterface #27,  1           // InterfaceMethod org/apache/hadoop/hbase/Stoppable.isStopped:()Z
      20: ifne          27
      23: aload_0
      24: invokespecial #28                 // Method handleLeaderChange:()V
      27: return

  public void waitToBecomeLeader();
    Code:
       0: aload_0
       1: getfield      #10                 // Field candidate:Lorg/apache/hadoop/hbase/Stoppable;
       4: invokeinterface #27,  1           // InterfaceMethod org/apache/hadoop/hbase/Stoppable.isStopped:()Z
       9: ifne          329
      12: aload_0
      13: getfield      #11                 // Field watcher:Lorg/apache/hadoop/hbase/zookeeper/ZKWatcher;
      16: aload_0
      17: getfield      #8                  // Field leaderZNode:Ljava/lang/String;
      20: aload_0
      21: getfield      #9                  // Field nodeId:[B
      24: invokestatic  #38                 // Method org/apache/hadoop/hbase/zookeeper/ZKUtil.createEphemeralNodeAndWatch:(Lorg/apache/hadoop/hbase/zookeeper/ZKWatcher;Ljava/lang/String;[B)Z
      27: ifeq          88
      30: aload_0
      31: getfield      #7                  // Field leaderExists:Ljava/util/concurrent/atomic/AtomicBoolean;
      34: iconst_1
      35: invokevirtual #33                 // Method java/util/concurrent/atomic/AtomicBoolean.set:(Z)V
      38: getstatic     #30                 // Field LOG:Lorg/slf4j/Logger;
      41: invokeinterface #39,  1           // InterfaceMethod org/slf4j/Logger.isDebugEnabled:()Z
      46: ifeq          87
      49: getstatic     #30                 // Field LOG:Lorg/slf4j/Logger;
      52: new           #19                 // class java/lang/StringBuilder
      55: dup
      56: invokespecial #20                 // Method java/lang/StringBuilder."<init>":()V
      59: ldc           #40                 // String Claimed the leader znode as '
      61: invokevirtual #22                 // Method java/lang/StringBuilder.append:(Ljava/lang/String;)Ljava/lang/StringBuilder;
      64: aload_0
      65: getfield      #9                  // Field nodeId:[B
      68: invokestatic  #41                 // Method org/apache/hadoop/hbase/util/Bytes.toStringBinary:([B)Ljava/lang/String;
      71: invokevirtual #22                 // Method java/lang/StringBuilder.append:(Ljava/lang/String;)Ljava/lang/StringBuilder;
      74: ldc           #42                 // String '
      76: invokevirtual #22                 // Method java/lang/StringBuilder.append:(Ljava/lang/String;)Ljava/lang/StringBuilder;
      79: invokevirtual #24                 // Method java/lang/StringBuilder.toString:()Ljava/lang/String;
      82: invokeinterface #43,  2           // InterfaceMethod org/slf4j/Logger.debug:(Ljava/lang/String;)V
      87: return
      88: aload_0
      89: getfield      #11                 // Field watcher:Lorg/apache/hadoop/hbase/zookeeper/ZKWatcher;
      92: aload_0
      93: getfield      #8                  // Field leaderZNode:Ljava/lang/String;
      96: invokestatic  #44                 // Method org/apache/hadoop/hbase/zookeeper/ZKUtil.getDataAndWatch:(Lorg/apache/hadoop/hbase/zookeeper/ZKWatcher;Ljava/lang/String;)[B
      99: astore_1
     100: aload_1
     101: ifnull        175
     104: aload_1
     105: aload_0
     106: getfield      #9                  // Field nodeId:[B
     109: invokestatic  #45                 // Method org/apache/hadoop/hbase/util/Bytes.equals:([B[B)Z
     112: ifeq          175
     115: getstatic     #30                 // Field LOG:Lorg/slf4j/Logger;
     118: new           #19                 // class java/lang/StringBuilder
     121: dup
     122: invokespecial #20                 // Method java/lang/StringBuilder."<init>":()V
     125: ldc           #46                 // String Found existing leader with our ID (
     127: invokevirtual #22                 // Method java/lang/StringBuilder.append:(Ljava/lang/String;)Ljava/lang/StringBuilder;
     130: aload_0
     131: getfield      #9                  // Field nodeId:[B
     134: invokestatic  #41                 // Method org/apache/hadoop/hbase/util/Bytes.toStringBinary:([B)Ljava/lang/String;
     137: invokevirtual #22                 // Method java/lang/StringBuilder.append:(Ljava/lang/String;)Ljava/lang/StringBuilder;
     140: ldc           #47                 // String ), removing
     142: invokevirtual #22                 // Method java/lang/StringBuilder.append:(Ljava/lang/String;)Ljava/lang/StringBuilder;
     145: invokevirtual #24                 // Method java/lang/StringBuilder.toString:()Ljava/lang/String;
     148: invokeinterface #32,  2           // InterfaceMethod org/slf4j/Logger.info:(Ljava/lang/String;)V
     153: aload_0
     154: getfield      #11                 // Field watcher:Lorg/apache/hadoop/hbase/zookeeper/ZKWatcher;
     157: aload_0
     158: getfield      #8                  // Field leaderZNode:Ljava/lang/String;
     161: invokestatic  #48                 // Method org/apache/hadoop/hbase/zookeeper/ZKUtil.deleteNode:(Lorg/apache/hadoop/hbase/zookeeper/ZKWatcher;Ljava/lang/String;)V
     164: aload_0
     165: getfield      #7                  // Field leaderExists:Ljava/util/concurrent/atomic/AtomicBoolean;
     168: iconst_0
     169: invokevirtual #33                 // Method java/util/concurrent/atomic/AtomicBoolean.set:(Z)V
     172: goto          216
     175: getstatic     #30                 // Field LOG:Lorg/slf4j/Logger;
     178: new           #19                 // class java/lang/StringBuilder
     181: dup
     182: invokespecial #20                 // Method java/lang/StringBuilder."<init>":()V
     185: ldc           #49                 // String Found existing leader with ID:
     187: invokevirtual #22                 // Method java/lang/StringBuilder.append:(Ljava/lang/String;)Ljava/lang/StringBuilder;
     190: aload_0
     191: getfield      #9                  // Field nodeId:[B
     194: invokestatic  #41                 // Method org/apache/hadoop/hbase/util/Bytes.toStringBinary:([B)Ljava/lang/String;
     197: invokevirtual #22                 // Method java/lang/StringBuilder.append:(Ljava/lang/String;)Ljava/lang/StringBuilder;
     200: invokevirtual #24                 // Method java/lang/StringBuilder.toString:()Ljava/lang/String;
     203: invokeinterface #32,  2           // InterfaceMethod org/slf4j/Logger.info:(Ljava/lang/String;)V
     208: aload_0
     209: getfield      #7                  // Field leaderExists:Ljava/util/concurrent/atomic/AtomicBoolean;
     212: iconst_1
     213: invokevirtual #33                 // Method java/util/concurrent/atomic/AtomicBoolean.set:(Z)V
     216: goto          262
     219: astore_1
     220: aload_0
     221: getfield      #11                 // Field watcher:Lorg/apache/hadoop/hbase/zookeeper/ZKWatcher;
     224: ldc           #50                 // String Unexpected error from ZK, stopping candidate
     226: aload_1
     227: invokevirtual #18                 // Method org/apache/hadoop/hbase/zookeeper/ZKWatcher.abort:(Ljava/lang/String;Ljava/lang/Throwable;)V
     230: aload_0
     231: getfield      #10                 // Field candidate:Lorg/apache/hadoop/hbase/Stoppable;
     234: new           #19                 // class java/lang/StringBuilder
     237: dup
     238: invokespecial #20                 // Method java/lang/StringBuilder."<init>":()V
     241: ldc           #51                 // String Unexpected error from ZK:
     243: invokevirtual #22                 // Method java/lang/StringBuilder.append:(Ljava/lang/String;)Ljava/lang/StringBuilder;
     246: aload_1
     247: invokevirtual #23                 // Method org/apache/zookeeper/KeeperException.getMessage:()Ljava/lang/String;
     250: invokevirtual #22                 // Method java/lang/StringBuilder.append:(Ljava/lang/String;)Ljava/lang/StringBuilder;
     253: invokevirtual #24                 // Method java/lang/StringBuilder.toString:()Ljava/lang/String;
     256: invokeinterface #25,  2           // InterfaceMethod org/apache/hadoop/hbase/Stoppable.stop:(Ljava/lang/String;)V
     261: return
     262: aload_0
     263: getfield      #4                  // Field lock:Ljava/lang/Object;
     266: dup
     267: astore_1
     268: monitorenter
     269: aload_0
     270: getfield      #7                  // Field leaderExists:Ljava/util/concurrent/atomic/AtomicBoolean;
     273: invokevirtual #52                 // Method java/util/concurrent/atomic/AtomicBoolean.get:()Z
     276: ifeq          316
     279: aload_0
     280: getfield      #10                 // Field candidate:Lorg/apache/hadoop/hbase/Stoppable;
     283: invokeinterface #27,  1           // InterfaceMethod org/apache/hadoop/hbase/Stoppable.isStopped:()Z
     288: ifne          316
     291: aload_0
     292: getfield      #4                  // Field lock:Ljava/lang/Object;
     295: invokevirtual #53                 // Method java/lang/Object.wait:()V
     298: goto          269
     301: astore_2
     302: getstatic     #30                 // Field LOG:Lorg/slf4j/Logger;
     305: ldc           #55                 // String Interrupted waiting on leader
     307: aload_2
     308: invokeinterface #56,  3           // InterfaceMethod org/slf4j/Logger.debug:(Ljava/lang/String;Ljava/lang/Throwable;)V
     313: goto          269
     316: aload_1
     317: monitorexit
     318: goto          326
     321: astore_3
     322: aload_1
     323: monitorexit
     324: aload_3
     325: athrow
     326: goto          0
     329: return
    Exception table:
       from    to  target type
          12    87   219   Class org/apache/zookeeper/KeeperException
          88   216   219   Class org/apache/zookeeper/KeeperException
         291   298   301   Class java/lang/InterruptedException
         269   318   321   any
         321   324   321   any

  public void stepDownAsLeader();
    Code:
       0: aload_0
       1: getfield      #4                  // Field lock:Ljava/lang/Object;
       4: dup
       5: astore_1
       6: monitorenter
       7: aload_0
       8: getfield      #7                  // Field leaderExists:Ljava/util/concurrent/atomic/AtomicBoolean;
      11: invokevirtual #52                 // Method java/util/concurrent/atomic/AtomicBoolean.get:()Z
      14: ifne          20
      17: aload_1
      18: monitorexit
      19: return
      20: aload_0
      21: getfield      #11                 // Field watcher:Lorg/apache/hadoop/hbase/zookeeper/ZKWatcher;
      24: aload_0
      25: getfield      #8                  // Field leaderZNode:Ljava/lang/String;
      28: invokestatic  #57                 // Method org/apache/hadoop/hbase/zookeeper/ZKUtil.getData:(Lorg/apache/hadoop/hbase/zookeeper/ZKWatcher;Ljava/lang/String;)[B
      31: astore_2
      32: aload_2
      33: ifnull        79
      36: aload_0
      37: getfield      #9                  // Field nodeId:[B
      40: aload_2
      41: invokestatic  #45                 // Method org/apache/hadoop/hbase/util/Bytes.equals:([B[B)Z
      44: ifeq          79
      47: getstatic     #30                 // Field LOG:Lorg/slf4j/Logger;
      50: ldc           #58                 // String Stepping down as leader
      52: invokeinterface #32,  2           // InterfaceMethod org/slf4j/Logger.info:(Ljava/lang/String;)V
      57: aload_0
      58: getfield      #11                 // Field watcher:Lorg/apache/hadoop/hbase/zookeeper/ZKWatcher;
      61: aload_0
      62: getfield      #8                  // Field leaderZNode:Ljava/lang/String;
      65: invokestatic  #59                 // Method org/apache/hadoop/hbase/zookeeper/ZKUtil.deleteNodeFailSilent:(Lorg/apache/hadoop/hbase/zookeeper/ZKWatcher;Ljava/lang/String;)V
      68: aload_0
      69: getfield      #7                  // Field leaderExists:Ljava/util/concurrent/atomic/AtomicBoolean;
      72: iconst_0
      73: invokevirtual #33                 // Method java/util/concurrent/atomic/AtomicBoolean.set:(Z)V
      76: goto          89
      79: getstatic     #30                 // Field LOG:Lorg/slf4j/Logger;
      82: ldc           #60                 // String Not current leader, no need to step down
      84: invokeinterface #32,  2           // InterfaceMethod org/slf4j/Logger.info:(Ljava/lang/String;)V
      89: aload_1
      90: monitorexit
      91: goto          99
      94: astore_3
      95: aload_1
      96: monitorexit
      97: aload_3
      98: athrow
      99: goto          189
     102: astore_1
     103: aload_0
     104: getfield      #11                 // Field watcher:Lorg/apache/hadoop/hbase/zookeeper/ZKWatcher;
     107: ldc           #61                 // String Unhandled zookeeper exception removing leader node
     109: aload_1
     110: invokevirtual #18                 // Method org/apache/hadoop/hbase/zookeeper/ZKWatcher.abort:(Ljava/lang/String;Ljava/lang/Throwable;)V
     113: aload_0
     114: getfield      #10                 // Field candidate:Lorg/apache/hadoop/hbase/Stoppable;
     117: new           #19                 // class java/lang/StringBuilder
     120: dup
     121: invokespecial #20                 // Method java/lang/StringBuilder."<init>":()V
     124: ldc           #62                 // String Unhandled zookeeper exception removing leader node:
     126: invokevirtual #22                 // Method java/lang/StringBuilder.append:(Ljava/lang/String;)Ljava/lang/StringBuilder;
     129: aload_1
     130: invokevirtual #23                 // Method org/apache/zookeeper/KeeperException.getMessage:()Ljava/lang/String;
     133: invokevirtual #22                 // Method java/lang/StringBuilder.append:(Ljava/lang/String;)Ljava/lang/StringBuilder;
     136: invokevirtual #24                 // Method java/lang/StringBuilder.toString:()Ljava/lang/String;
     139: invokeinterface #25,  2           // InterfaceMethod org/apache/hadoop/hbase/Stoppable.stop:(Ljava/lang/String;)V
     144: goto          189
     147: astore_1
     148: aload_0
     149: getfield      #11                 // Field watcher:Lorg/apache/hadoop/hbase/zookeeper/ZKWatcher;
     152: ldc           #61                 // String Unhandled zookeeper exception removing leader node
     154: aload_1
     155: invokevirtual #18                 // Method org/apache/hadoop/hbase/zookeeper/ZKWatcher.abort:(Ljava/lang/String;Ljava/lang/Throwable;)V
     158: aload_0
     159: getfield      #10                 // Field candidate:Lorg/apache/hadoop/hbase/Stoppable;
     162: new           #19                 // class java/lang/StringBuilder
     165: dup
     166: invokespecial #20                 // Method java/lang/StringBuilder."<init>":()V
     169: ldc           #62                 // String Unhandled zookeeper exception removing leader node:
     171: invokevirtual #22                 // Method java/lang/StringBuilder.append:(Ljava/lang/String;)Ljava/lang/StringBuilder;
     174: aload_1
     175: invokevirtual #63                 // Method java/lang/InterruptedException.getMessage:()Ljava/lang/String;
     178: invokevirtual #22                 // Method java/lang/StringBuilder.append:(Ljava/lang/String;)Ljava/lang/StringBuilder;
     181: invokevirtual #24                 // Method java/lang/StringBuilder.toString:()Ljava/lang/String;
     184: invokeinterface #25,  2           // InterfaceMethod org/apache/hadoop/hbase/Stoppable.stop:(Ljava/lang/String;)V
     189: return
    Exception table:
       from    to  target type
           7    19    94   any
          20    91    94   any
          94    97    94   any
           0    19   102   Class org/apache/zookeeper/KeeperException
          20    99   102   Class org/apache/zookeeper/KeeperException
           0    19   147   Class java/lang/InterruptedException
          20    99   147   Class java/lang/InterruptedException

  public boolean hasLeader();
    Code:
       0: aload_0
       1: getfield      #7                  // Field leaderExists:Ljava/util/concurrent/atomic/AtomicBoolean;
       4: invokevirtual #52                 // Method java/util/concurrent/atomic/AtomicBoolean.get:()Z
       7: ireturn

  static {};
    Code:
       0: ldc           #64                 // class org/apache/hadoop/hbase/zookeeper/ZKLeaderManager
       2: invokestatic  #65                 // Method org/slf4j/LoggerFactory.getLogger:(Ljava/lang/Class;)Lorg/slf4j/Logger;
       5: putstatic     #30                 // Field LOG:Lorg/slf4j/Logger;
       8: return
}
