Compiled from "ZKPermissionWatcher.java"
class org.apache.hadoop.hbase.security.access.ZKPermissionWatcher$4 implements java.lang.Runnable {
  final java.lang.String val$path;

  final org.apache.hadoop.hbase.security.access.ZKPermissionWatcher this$0;

  org.apache.hadoop.hbase.security.access.ZKPermissionWatcher$4(org.apache.hadoop.hbase.security.access.ZKPermissionWatcher, java.lang.String);
    Code:
       0: aload_0
       1: aload_1
       2: putfield      #1                  // Field this$0:Lorg/apache/hadoop/hbase/security/access/ZKPermissionWatcher;
       5: aload_0
       6: aload_2
       7: putfield      #2                  // Field val$path:Ljava/lang/String;
      10: aload_0
      11: invokespecial #3                  // Method java/lang/Object."<init>":()V
      14: return

  public void run();
    Code:
       0: aload_0
       1: getfield      #2                  // Field val$path:Ljava/lang/String;
       4: invokestatic  #4                  // Method org/apache/hadoop/hbase/zookeeper/ZKUtil.getNodeName:(Ljava/lang/String;)Ljava/lang/String;
       7: astore_1
       8: aload_0
       9: getfield      #1                  // Field this$0:Lorg/apache/hadoop/hbase/security/access/ZKPermissionWatcher;
      12: invokestatic  #5                  // Method org/apache/hadoop/hbase/security/access/ZKPermissionWatcher.access$700:(Lorg/apache/hadoop/hbase/security/access/ZKPermissionWatcher;)Lorg/apache/hadoop/hbase/zookeeper/ZKWatcher;
      15: aload_0
      16: getfield      #2                  // Field val$path:Ljava/lang/String;
      19: invokestatic  #6                  // Method org/apache/hadoop/hbase/zookeeper/ZKUtil.getDataAndWatch:(Lorg/apache/hadoop/hbase/zookeeper/ZKWatcher;Ljava/lang/String;)[B
      22: astore_2
      23: aload_0
      24: getfield      #1                  // Field this$0:Lorg/apache/hadoop/hbase/security/access/ZKPermissionWatcher;
      27: aload_1
      28: aload_2
      29: invokestatic  #7                  // Method org/apache/hadoop/hbase/security/access/ZKPermissionWatcher.access$800:(Lorg/apache/hadoop/hbase/security/access/ZKPermissionWatcher;Ljava/lang/String;[B)V
      32: goto          109
      35: astore_2
      36: invokestatic  #9                  // Method org/apache/hadoop/hbase/security/access/ZKPermissionWatcher.access$400:()Lorg/slf4j/Logger;
      39: new           #10                 // class java/lang/StringBuilder
      42: dup
      43: invokespecial #11                 // Method java/lang/StringBuilder."<init>":()V
      46: ldc           #12                 // String Error reading data from zookeeper for node
      48: invokevirtual #13                 // Method java/lang/StringBuilder.append:(Ljava/lang/String;)Ljava/lang/StringBuilder;
      51: aload_1
      52: invokevirtual #13                 // Method java/lang/StringBuilder.append:(Ljava/lang/String;)Ljava/lang/StringBuilder;
      55: invokevirtual #14                 // Method java/lang/StringBuilder.toString:()Ljava/lang/String;
      58: aload_2
      59: invokeinterface #15,  3           // InterfaceMethod org/slf4j/Logger.error:(Ljava/lang/String;Ljava/lang/Throwable;)V
      64: aload_0
      65: getfield      #1                  // Field this$0:Lorg/apache/hadoop/hbase/security/access/ZKPermissionWatcher;
      68: invokestatic  #16                 // Method org/apache/hadoop/hbase/security/access/ZKPermissionWatcher.access$900:(Lorg/apache/hadoop/hbase/security/access/ZKPermissionWatcher;)Lorg/apache/hadoop/hbase/zookeeper/ZKWatcher;
      71: new           #10                 // class java/lang/StringBuilder
      74: dup
      75: invokespecial #11                 // Method java/lang/StringBuilder."<init>":()V
      78: ldc           #17                 // String ZooKeeper error getting data for node
      80: invokevirtual #13                 // Method java/lang/StringBuilder.append:(Ljava/lang/String;)Ljava/lang/StringBuilder;
      83: aload_1
      84: invokevirtual #13                 // Method java/lang/StringBuilder.append:(Ljava/lang/String;)Ljava/lang/StringBuilder;
      87: invokevirtual #14                 // Method java/lang/StringBuilder.toString:()Ljava/lang/String;
      90: aload_2
      91: invokevirtual #18                 // Method org/apache/hadoop/hbase/zookeeper/ZKWatcher.abort:(Ljava/lang/String;Ljava/lang/Throwable;)V
      94: goto          109
      97: astore_2
      98: invokestatic  #9                  // Method org/apache/hadoop/hbase/security/access/ZKPermissionWatcher.access$400:()Lorg/slf4j/Logger;
     101: ldc           #20                 // String Error reading permissions writables
     103: aload_2
     104: invokeinterface #15,  3           // InterfaceMethod org/slf4j/Logger.error:(Ljava/lang/String;Ljava/lang/Throwable;)V
     109: return
    Exception table:
       from    to  target type
           8    32    35   Class org/apache/zookeeper/KeeperException
           8    32    97   Class java/io/IOException
}
