Compiled from "ZKPermissionWatcher.java"
class org.apache.hadoop.hbase.security.access.ZKPermissionWatcher$2 implements java.lang.Runnable {
  final org.apache.hadoop.hbase.security.access.ZKPermissionWatcher this$0;

  org.apache.hadoop.hbase.security.access.ZKPermissionWatcher$2(org.apache.hadoop.hbase.security.access.ZKPermissionWatcher);
    Code:
       0: aload_0
       1: aload_1
       2: putfield      #1                  // Field this$0:Lorg/apache/hadoop/hbase/security/access/ZKPermissionWatcher;
       5: aload_0
       6: invokespecial #2                  // Method java/lang/Object."<init>":()V
       9: return

  public void run();
    Code:
       0: aload_0
       1: getfield      #1                  // Field this$0:Lorg/apache/hadoop/hbase/security/access/ZKPermissionWatcher;
       4: invokestatic  #3                  // Method org/apache/hadoop/hbase/security/access/ZKPermissionWatcher.access$300:(Lorg/apache/hadoop/hbase/security/access/ZKPermissionWatcher;)Lorg/apache/hadoop/hbase/zookeeper/ZKWatcher;
       7: aload_0
       8: getfield      #1                  // Field this$0:Lorg/apache/hadoop/hbase/security/access/ZKPermissionWatcher;
      11: invokestatic  #4                  // Method org/apache/hadoop/hbase/security/access/ZKPermissionWatcher.access$100:(Lorg/apache/hadoop/hbase/security/access/ZKPermissionWatcher;)Ljava/lang/String;
      14: invokestatic  #5                  // Method org/apache/hadoop/hbase/zookeeper/ZKUtil.getChildDataAndWatchForNewChildren:(Lorg/apache/hadoop/hbase/zookeeper/ZKWatcher;Ljava/lang/String;)Ljava/util/List;
      17: astore_1
      18: aload_0
      19: getfield      #1                  // Field this$0:Lorg/apache/hadoop/hbase/security/access/ZKPermissionWatcher;
      22: aload_1
      23: invokestatic  #6                  // Method org/apache/hadoop/hbase/security/access/ZKPermissionWatcher.access$200:(Lorg/apache/hadoop/hbase/security/access/ZKPermissionWatcher;Ljava/util/List;)V
      26: goto          54
      29: astore_1
      30: invokestatic  #8                  // Method org/apache/hadoop/hbase/security/access/ZKPermissionWatcher.access$400:()Lorg/slf4j/Logger;
      33: ldc           #9                  // String Error reading data from zookeeper
      35: aload_1
      36: invokeinterface #10,  3           // InterfaceMethod org/slf4j/Logger.error:(Ljava/lang/String;Ljava/lang/Throwable;)V
      41: aload_0
      42: getfield      #1                  // Field this$0:Lorg/apache/hadoop/hbase/security/access/ZKPermissionWatcher;
      45: invokestatic  #11                 // Method org/apache/hadoop/hbase/security/access/ZKPermissionWatcher.access$500:(Lorg/apache/hadoop/hbase/security/access/ZKPermissionWatcher;)Lorg/apache/hadoop/hbase/zookeeper/ZKWatcher;
      48: ldc           #12                 // String ZooKeeper error obtaining acl node children
      50: aload_1
      51: invokevirtual #13                 // Method org/apache/hadoop/hbase/zookeeper/ZKWatcher.abort:(Ljava/lang/String;Ljava/lang/Throwable;)V
      54: return
    Exception table:
       from    to  target type
           0    26    29   Class org/apache/zookeeper/KeeperException
}
