Compiled from "ZKProcedureCoordinator.java"
class org.apache.hadoop.hbase.procedure.ZKProcedureCoordinator$1 extends org.apache.hadoop.hbase.procedure.ZKProcedureUtil {
  final org.apache.hadoop.hbase.procedure.ProcedureCoordinator val$coordinator;

  final org.apache.hadoop.hbase.procedure.ZKProcedureCoordinator this$0;

  org.apache.hadoop.hbase.procedure.ZKProcedureCoordinator$1(org.apache.hadoop.hbase.procedure.ZKProcedureCoordinator, org.apache.hadoop.hbase.zookeeper.ZKWatcher, java.lang.String, org.apache.hadoop.hbase.procedure.ProcedureCoordinator);
    Code:
       0: aload_0
       1: aload_1
       2: putfield      #1                  // Field this$0:Lorg/apache/hadoop/hbase/procedure/ZKProcedureCoordinator;
       5: aload_0
       6: aload         4
       8: putfield      #2                  // Field val$coordinator:Lorg/apache/hadoop/hbase/procedure/ProcedureCoordinator;
      11: aload_0
      12: aload_2
      13: aload_3
      14: invokespecial #3                  // Method org/apache/hadoop/hbase/procedure/ZKProcedureUtil."<init>":(Lorg/apache/hadoop/hbase/zookeeper/ZKWatcher;Ljava/lang/String;)V
      17: return

  public void nodeCreated(java.lang.String);
    Code:
       0: aload_0
       1: aload_1
       2: invokevirtual #4                  // Method isInProcedurePath:(Ljava/lang/String;)Z
       5: ifne          9
       8: return
       9: invokestatic  #5                  // Method org/apache/hadoop/hbase/procedure/ZKProcedureCoordinator.access$000:()Lorg/slf4j/Logger;
      12: new           #6                  // class java/lang/StringBuilder
      15: dup
      16: invokespecial #7                  // Method java/lang/StringBuilder."<init>":()V
      19: ldc           #8                  // String Node created:
      21: invokevirtual #9                  // Method java/lang/StringBuilder.append:(Ljava/lang/String;)Ljava/lang/StringBuilder;
      24: aload_1
      25: invokevirtual #9                  // Method java/lang/StringBuilder.append:(Ljava/lang/String;)Ljava/lang/StringBuilder;
      28: invokevirtual #10                 // Method java/lang/StringBuilder.toString:()Ljava/lang/String;
      31: invokeinterface #11,  2           // InterfaceMethod org/slf4j/Logger.debug:(Ljava/lang/String;)V
      36: aload_0
      37: aload_0
      38: getfield      #12                 // Field baseZNode:Ljava/lang/String;
      41: invokevirtual #13                 // Method logZKTree:(Ljava/lang/String;)V
      44: aload_0
      45: aload_1
      46: invokevirtual #14                 // Method isAcquiredPathNode:(Ljava/lang/String;)Z
      49: ifeq          73
      52: aload_0
      53: getfield      #2                  // Field val$coordinator:Lorg/apache/hadoop/hbase/procedure/ProcedureCoordinator;
      56: aload_1
      57: invokestatic  #15                 // Method org/apache/hadoop/hbase/zookeeper/ZKUtil.getParent:(Ljava/lang/String;)Ljava/lang/String;
      60: invokestatic  #16                 // Method org/apache/hadoop/hbase/zookeeper/ZKUtil.getNodeName:(Ljava/lang/String;)Ljava/lang/String;
      63: aload_1
      64: invokestatic  #16                 // Method org/apache/hadoop/hbase/zookeeper/ZKUtil.getNodeName:(Ljava/lang/String;)Ljava/lang/String;
      67: invokevirtual #17                 // Method org/apache/hadoop/hbase/procedure/ProcedureCoordinator.memberAcquiredBarrier:(Ljava/lang/String;Ljava/lang/String;)V
      70: goto          361
      73: aload_0
      74: aload_1
      75: invokevirtual #18                 // Method isReachedPathNode:(Ljava/lang/String;)Z
      78: ifeq          315
      81: aload_1
      82: invokestatic  #15                 // Method org/apache/hadoop/hbase/zookeeper/ZKUtil.getParent:(Ljava/lang/String;)Ljava/lang/String;
      85: invokestatic  #16                 // Method org/apache/hadoop/hbase/zookeeper/ZKUtil.getNodeName:(Ljava/lang/String;)Ljava/lang/String;
      88: astore_2
      89: aload_1
      90: invokestatic  #16                 // Method org/apache/hadoop/hbase/zookeeper/ZKUtil.getNodeName:(Ljava/lang/String;)Ljava/lang/String;
      93: astore_3
      94: aload_0
      95: getfield      #19                 // Field watcher:Lorg/apache/hadoop/hbase/zookeeper/ZKWatcher;
      98: aload_1
      99: invokestatic  #20                 // Method org/apache/hadoop/hbase/zookeeper/ZKUtil.getData:(Lorg/apache/hadoop/hbase/zookeeper/ZKWatcher;Ljava/lang/String;)[B
     102: astore        4
     104: aload         4
     106: ifnull        235
     109: aload         4
     111: arraylength
     112: ifle          235
     115: aload         4
     117: invokestatic  #21                 // Method org/apache/hadoop/hbase/shaded/protobuf/ProtobufUtil.isPBMagicPrefix:([B)Z
     120: ifne          171
     123: new           #22                 // class org/apache/hadoop/hbase/errorhandling/ForeignException
     126: dup
     127: aload_0
     128: getfield      #1                  // Field this$0:Lorg/apache/hadoop/hbase/procedure/ZKProcedureCoordinator;
     131: getfield      #23                 // Field org/apache/hadoop/hbase/procedure/ZKProcedureCoordinator.coordName:Ljava/lang/String;
     134: new           #6                  // class java/lang/StringBuilder
     137: dup
     138: invokespecial #7                  // Method java/lang/StringBuilder."<init>":()V
     141: ldc           #24                 // String Failed to get data from finished node or data is illegally formatted:
     143: invokevirtual #9                  // Method java/lang/StringBuilder.append:(Ljava/lang/String;)Ljava/lang/StringBuilder;
     146: aload_1
     147: invokevirtual #9                  // Method java/lang/StringBuilder.append:(Ljava/lang/String;)Ljava/lang/StringBuilder;
     150: invokevirtual #10                 // Method java/lang/StringBuilder.toString:()Ljava/lang/String;
     153: invokespecial #25                 // Method org/apache/hadoop/hbase/errorhandling/ForeignException."<init>":(Ljava/lang/String;Ljava/lang/String;)V
     156: astore        5
     158: aload_0
     159: getfield      #2                  // Field val$coordinator:Lorg/apache/hadoop/hbase/procedure/ProcedureCoordinator;
     162: aload_2
     163: aload         5
     165: invokevirtual #26                 // Method org/apache/hadoop/hbase/procedure/ProcedureCoordinator.abortProcedure:(Ljava/lang/String;Lorg/apache/hadoop/hbase/errorhandling/ForeignException;)V
     168: goto          246
     171: aload         4
     173: invokestatic  #27                 // Method org/apache/hadoop/hbase/shaded/protobuf/ProtobufUtil.lengthOfPBMagic:()I
     176: aload         4
     178: arraylength
     179: invokestatic  #28                 // Method java/util/Arrays.copyOfRange:([BII)[B
     182: astore        4
     184: invokestatic  #5                  // Method org/apache/hadoop/hbase/procedure/ZKProcedureCoordinator.access$000:()Lorg/slf4j/Logger;
     187: ldc           #29                 // String Finished data from procedure '{}' member '{}': {}
     189: iconst_3
     190: anewarray     #30                 // class java/lang/Object
     193: dup
     194: iconst_0
     195: aload_2
     196: aastore
     197: dup
     198: iconst_1
     199: aload_3
     200: aastore
     201: dup
     202: iconst_2
     203: new           #31                 // class java/lang/String
     206: dup
     207: aload         4
     209: getstatic     #32                 // Field java/nio/charset/StandardCharsets.UTF_8:Ljava/nio/charset/Charset;
     212: invokespecial #33                 // Method java/lang/String."<init>":([BLjava/nio/charset/Charset;)V
     215: aastore
     216: invokeinterface #34,  3           // InterfaceMethod org/slf4j/Logger.debug:(Ljava/lang/String;[Ljava/lang/Object;)V
     221: aload_0
     222: getfield      #2                  // Field val$coordinator:Lorg/apache/hadoop/hbase/procedure/ProcedureCoordinator;
     225: aload_2
     226: aload_3
     227: aload         4
     229: invokevirtual #35                 // Method org/apache/hadoop/hbase/procedure/ProcedureCoordinator.memberFinishedBarrier:(Ljava/lang/String;Ljava/lang/String;[B)V
     232: goto          246
     235: aload_0
     236: getfield      #2                  // Field val$coordinator:Lorg/apache/hadoop/hbase/procedure/ProcedureCoordinator;
     239: aload_2
     240: aload_3
     241: aload         4
     243: invokevirtual #35                 // Method org/apache/hadoop/hbase/procedure/ProcedureCoordinator.memberFinishedBarrier:(Ljava/lang/String;Ljava/lang/String;[B)V
     246: goto          312
     249: astore        4
     251: new           #22                 // class org/apache/hadoop/hbase/errorhandling/ForeignException
     254: dup
     255: aload_0
     256: getfield      #1                  // Field this$0:Lorg/apache/hadoop/hbase/procedure/ZKProcedureCoordinator;
     259: getfield      #23                 // Field org/apache/hadoop/hbase/procedure/ZKProcedureCoordinator.coordName:Ljava/lang/String;
     262: aload         4
     264: invokespecial #37                 // Method org/apache/hadoop/hbase/errorhandling/ForeignException."<init>":(Ljava/lang/String;Ljava/lang/Throwable;)V
     267: astore        5
     269: aload_0
     270: getfield      #2                  // Field val$coordinator:Lorg/apache/hadoop/hbase/procedure/ProcedureCoordinator;
     273: aload_2
     274: aload         5
     276: invokevirtual #26                 // Method org/apache/hadoop/hbase/procedure/ProcedureCoordinator.abortProcedure:(Ljava/lang/String;Lorg/apache/hadoop/hbase/errorhandling/ForeignException;)V
     279: goto          312
     282: astore        4
     284: new           #22                 // class org/apache/hadoop/hbase/errorhandling/ForeignException
     287: dup
     288: aload_0
     289: getfield      #1                  // Field this$0:Lorg/apache/hadoop/hbase/procedure/ZKProcedureCoordinator;
     292: getfield      #23                 // Field org/apache/hadoop/hbase/procedure/ZKProcedureCoordinator.coordName:Ljava/lang/String;
     295: aload         4
     297: invokespecial #37                 // Method org/apache/hadoop/hbase/errorhandling/ForeignException."<init>":(Ljava/lang/String;Ljava/lang/Throwable;)V
     300: astore        5
     302: aload_0
     303: getfield      #2                  // Field val$coordinator:Lorg/apache/hadoop/hbase/procedure/ProcedureCoordinator;
     306: aload_2
     307: aload         5
     309: invokevirtual #26                 // Method org/apache/hadoop/hbase/procedure/ProcedureCoordinator.abortProcedure:(Ljava/lang/String;Lorg/apache/hadoop/hbase/errorhandling/ForeignException;)V
     312: goto          361
     315: aload_0
     316: aload_1
     317: invokevirtual #39                 // Method isAbortPathNode:(Ljava/lang/String;)Z
     320: ifeq          334
     323: aload_0
     324: getfield      #1                  // Field this$0:Lorg/apache/hadoop/hbase/procedure/ZKProcedureCoordinator;
     327: aload_1
     328: invokevirtual #40                 // Method org/apache/hadoop/hbase/procedure/ZKProcedureCoordinator.abort:(Ljava/lang/String;)V
     331: goto          361
     334: invokestatic  #5                  // Method org/apache/hadoop/hbase/procedure/ZKProcedureCoordinator.access$000:()Lorg/slf4j/Logger;
     337: new           #6                  // class java/lang/StringBuilder
     340: dup
     341: invokespecial #7                  // Method java/lang/StringBuilder."<init>":()V
     344: ldc           #41                 // String Ignoring created notification for node:
     346: invokevirtual #9                  // Method java/lang/StringBuilder.append:(Ljava/lang/String;)Ljava/lang/StringBuilder;
     349: aload_1
     350: invokevirtual #9                  // Method java/lang/StringBuilder.append:(Ljava/lang/String;)Ljava/lang/StringBuilder;
     353: invokevirtual #10                 // Method java/lang/StringBuilder.toString:()Ljava/lang/String;
     356: invokeinterface #11,  2           // InterfaceMethod org/slf4j/Logger.debug:(Ljava/lang/String;)V
     361: return
    Exception table:
       from    to  target type
          94   246   249   Class org/apache/zookeeper/KeeperException
          94   246   282   Class java/lang/InterruptedException
}
