Compiled from "ZKProcedureMemberRpcs.java"
public class org.apache.hadoop.hbase.procedure.ZKProcedureMemberRpcs implements org.apache.hadoop.hbase.procedure.ProcedureMemberRpcs {
  protected org.apache.hadoop.hbase.procedure.ProcedureMember member;

  public org.apache.hadoop.hbase.procedure.ZKProcedureMemberRpcs(org.apache.hadoop.hbase.zookeeper.ZKWatcher, java.lang.String) throws org.apache.zookeeper.KeeperException;
    Code:
       0: aload_0
       1: invokespecial #6                  // Method java/lang/Object."<init>":()V
       4: aload_0
       5: new           #7                  // class org/apache/hadoop/hbase/procedure/ZKProcedureMemberRpcs$1
       8: dup
       9: aload_0
      10: aload_1
      11: aload_2
      12: invokespecial #8                  // Method org/apache/hadoop/hbase/procedure/ZKProcedureMemberRpcs$1."<init>":(Lorg/apache/hadoop/hbase/procedure/ZKProcedureMemberRpcs;Lorg/apache/hadoop/hbase/zookeeper/ZKWatcher;Ljava/lang/String;)V
      15: putfield      #9                  // Field zkController:Lorg/apache/hadoop/hbase/procedure/ZKProcedureUtil;
      18: return

  public org.apache.hadoop.hbase.procedure.ZKProcedureUtil getZkController();
    Code:
       0: aload_0
       1: getfield      #9                  // Field zkController:Lorg/apache/hadoop/hbase/procedure/ZKProcedureUtil;
       4: areturn

  public java.lang.String getMemberName();
    Code:
       0: aload_0
       1: getfield      #10                 // Field memberName:Ljava/lang/String;
       4: areturn

  public void sendMemberAcquired(org.apache.hadoop.hbase.procedure.Subprocedure) throws java.io.IOException;
    Code:
       0: aload_1
       1: invokevirtual #73                 // Method org/apache/hadoop/hbase/procedure/Subprocedure.getName:()Ljava/lang/String;
       4: astore_2
       5: getstatic     #5                  // Field LOG:Lorg/slf4j/Logger;
       8: new           #11                 // class java/lang/StringBuilder
      11: dup
      12: invokespecial #12                 // Method java/lang/StringBuilder."<init>":()V
      15: ldc           #74                 // String Member: '
      17: invokevirtual #14                 // Method java/lang/StringBuilder.append:(Ljava/lang/String;)Ljava/lang/StringBuilder;
      20: aload_0
      21: getfield      #10                 // Field memberName:Ljava/lang/String;
      24: invokevirtual #14                 // Method java/lang/StringBuilder.append:(Ljava/lang/String;)Ljava/lang/StringBuilder;
      27: ldc           #75                 // String ' joining acquired barrier for procedure (
      29: invokevirtual #14                 // Method java/lang/StringBuilder.append:(Ljava/lang/String;)Ljava/lang/StringBuilder;
      32: aload_2
      33: invokevirtual #14                 // Method java/lang/StringBuilder.append:(Ljava/lang/String;)Ljava/lang/StringBuilder;
      36: ldc           #76                 // String ) in zk
      38: invokevirtual #14                 // Method java/lang/StringBuilder.append:(Ljava/lang/String;)Ljava/lang/StringBuilder;
      41: invokevirtual #15                 // Method java/lang/StringBuilder.toString:()Ljava/lang/String;
      44: invokeinterface #16,  2           // InterfaceMethod org/slf4j/Logger.debug:(Ljava/lang/String;)V
      49: aload_0
      50: getfield      #9                  // Field zkController:Lorg/apache/hadoop/hbase/procedure/ZKProcedureUtil;
      53: aload_2
      54: invokestatic  #77                 // Method org/apache/hadoop/hbase/procedure/ZKProcedureUtil.getAcquireBarrierNode:(Lorg/apache/hadoop/hbase/procedure/ZKProcedureUtil;Ljava/lang/String;)Ljava/lang/String;
      57: aload_0
      58: getfield      #10                 // Field memberName:Ljava/lang/String;
      61: invokestatic  #30                 // Method org/apache/hadoop/hbase/zookeeper/ZNodePaths.joinZNode:(Ljava/lang/String;Ljava/lang/String;)Ljava/lang/String;
      64: astore_3
      65: aload_0
      66: getfield      #9                  // Field zkController:Lorg/apache/hadoop/hbase/procedure/ZKProcedureUtil;
      69: invokevirtual #23                 // Method org/apache/hadoop/hbase/procedure/ZKProcedureUtil.getWatcher:()Lorg/apache/hadoop/hbase/zookeeper/ZKWatcher;
      72: aload_3
      73: invokestatic  #78                 // Method org/apache/hadoop/hbase/zookeeper/ZKUtil.createAndFailSilent:(Lorg/apache/hadoop/hbase/zookeeper/ZKWatcher;Ljava/lang/String;)V
      76: aload_0
      77: getfield      #9                  // Field zkController:Lorg/apache/hadoop/hbase/procedure/ZKProcedureUtil;
      80: aload_2
      81: invokevirtual #79                 // Method org/apache/hadoop/hbase/procedure/ZKProcedureUtil.getReachedBarrierNode:(Ljava/lang/String;)Ljava/lang/String;
      84: astore        4
      86: getstatic     #5                  // Field LOG:Lorg/slf4j/Logger;
      89: new           #11                 // class java/lang/StringBuilder
      92: dup
      93: invokespecial #12                 // Method java/lang/StringBuilder."<init>":()V
      96: ldc           #80                 // String Watch for global barrier reached:
      98: invokevirtual #14                 // Method java/lang/StringBuilder.append:(Ljava/lang/String;)Ljava/lang/StringBuilder;
     101: aload         4
     103: invokevirtual #14                 // Method java/lang/StringBuilder.append:(Ljava/lang/String;)Ljava/lang/StringBuilder;
     106: invokevirtual #15                 // Method java/lang/StringBuilder.toString:()Ljava/lang/String;
     109: invokeinterface #16,  2           // InterfaceMethod org/slf4j/Logger.debug:(Ljava/lang/String;)V
     114: aload_0
     115: getfield      #9                  // Field zkController:Lorg/apache/hadoop/hbase/procedure/ZKProcedureUtil;
     118: invokevirtual #23                 // Method org/apache/hadoop/hbase/procedure/ZKProcedureUtil.getWatcher:()Lorg/apache/hadoop/hbase/zookeeper/ZKWatcher;
     121: aload         4
     123: invokestatic  #41                 // Method org/apache/hadoop/hbase/zookeeper/ZKUtil.watchAndCheckExists:(Lorg/apache/hadoop/hbase/zookeeper/ZKWatcher;Ljava/lang/String;)Z
     126: ifeq          135
     129: aload_0
     130: aload         4
     132: invokespecial #2                  // Method receivedReachedGlobalBarrier:(Ljava/lang/String;)V
     135: goto          179
     138: astore_3
     139: aload_0
     140: getfield      #18                 // Field member:Lorg/apache/hadoop/hbase/procedure/ProcedureMember;
     143: new           #11                 // class java/lang/StringBuilder
     146: dup
     147: invokespecial #12                 // Method java/lang/StringBuilder."<init>":()V
     150: ldc           #81                 // String Failed to acquire barrier for procedure:
     152: invokevirtual #14                 // Method java/lang/StringBuilder.append:(Ljava/lang/String;)Ljava/lang/StringBuilder;
     155: aload_2
     156: invokevirtual #14                 // Method java/lang/StringBuilder.append:(Ljava/lang/String;)Ljava/lang/StringBuilder;
     159: ldc           #82                 // String  and member:
     161: invokevirtual #14                 // Method java/lang/StringBuilder.append:(Ljava/lang/String;)Ljava/lang/StringBuilder;
     164: aload_0
     165: getfield      #10                 // Field memberName:Ljava/lang/String;
     168: invokevirtual #14                 // Method java/lang/StringBuilder.append:(Ljava/lang/String;)Ljava/lang/StringBuilder;
     171: invokevirtual #15                 // Method java/lang/StringBuilder.toString:()Ljava/lang/String;
     174: aload_3
     175: aload_2
     176: invokevirtual #34                 // Method org/apache/hadoop/hbase/procedure/ProcedureMember.controllerConnectionFailure:(Ljava/lang/String;Ljava/lang/Throwable;Ljava/lang/String;)V
     179: return
    Exception table:
       from    to  target type
           5   135   138   Class org/apache/zookeeper/KeeperException

  public void sendMemberCompleted(org.apache.hadoop.hbase.procedure.Subprocedure, byte[]) throws java.io.IOException;
    Code:
       0: aload_1
       1: invokevirtual #73                 // Method org/apache/hadoop/hbase/procedure/Subprocedure.getName:()Ljava/lang/String;
       4: astore_3
       5: getstatic     #5                  // Field LOG:Lorg/slf4j/Logger;
       8: new           #11                 // class java/lang/StringBuilder
      11: dup
      12: invokespecial #12                 // Method java/lang/StringBuilder."<init>":()V
      15: ldc           #83                 // String Marking procedure  '
      17: invokevirtual #14                 // Method java/lang/StringBuilder.append:(Ljava/lang/String;)Ljava/lang/StringBuilder;
      20: aload_3
      21: invokevirtual #14                 // Method java/lang/StringBuilder.append:(Ljava/lang/String;)Ljava/lang/StringBuilder;
      24: ldc           #84                 // String ' completed for member '
      26: invokevirtual #14                 // Method java/lang/StringBuilder.append:(Ljava/lang/String;)Ljava/lang/StringBuilder;
      29: aload_0
      30: getfield      #10                 // Field memberName:Ljava/lang/String;
      33: invokevirtual #14                 // Method java/lang/StringBuilder.append:(Ljava/lang/String;)Ljava/lang/StringBuilder;
      36: ldc           #85                 // String ' in zk
      38: invokevirtual #14                 // Method java/lang/StringBuilder.append:(Ljava/lang/String;)Ljava/lang/StringBuilder;
      41: invokevirtual #15                 // Method java/lang/StringBuilder.toString:()Ljava/lang/String;
      44: invokeinterface #16,  2           // InterfaceMethod org/slf4j/Logger.debug:(Ljava/lang/String;)V
      49: aload_0
      50: getfield      #9                  // Field zkController:Lorg/apache/hadoop/hbase/procedure/ZKProcedureUtil;
      53: aload_3
      54: invokevirtual #79                 // Method org/apache/hadoop/hbase/procedure/ZKProcedureUtil.getReachedBarrierNode:(Ljava/lang/String;)Ljava/lang/String;
      57: aload_0
      58: getfield      #10                 // Field memberName:Ljava/lang/String;
      61: invokestatic  #30                 // Method org/apache/hadoop/hbase/zookeeper/ZNodePaths.joinZNode:(Ljava/lang/String;Ljava/lang/String;)Ljava/lang/String;
      64: astore        4
      66: aload_2
      67: ifnonnull     74
      70: iconst_0
      71: newarray       byte
      73: astore_2
      74: aload_0
      75: getfield      #9                  // Field zkController:Lorg/apache/hadoop/hbase/procedure/ZKProcedureUtil;
      78: invokevirtual #23                 // Method org/apache/hadoop/hbase/procedure/ZKProcedureUtil.getWatcher:()Lorg/apache/hadoop/hbase/zookeeper/ZKWatcher;
      81: aload         4
      83: aload_2
      84: invokestatic  #86                 // Method org/apache/hadoop/hbase/shaded/protobuf/ProtobufUtil.prependPBMagic:([B)[B
      87: invokestatic  #87                 // Method org/apache/hadoop/hbase/zookeeper/ZKUtil.createAndFailSilent:(Lorg/apache/hadoop/hbase/zookeeper/ZKWatcher;Ljava/lang/String;[B)V
      90: goto          130
      93: astore        5
      95: aload_0
      96: getfield      #18                 // Field member:Lorg/apache/hadoop/hbase/procedure/ProcedureMember;
      99: new           #11                 // class java/lang/StringBuilder
     102: dup
     103: invokespecial #12                 // Method java/lang/StringBuilder."<init>":()V
     106: ldc           #88                 // String Failed to post zk node:
     108: invokevirtual #14                 // Method java/lang/StringBuilder.append:(Ljava/lang/String;)Ljava/lang/StringBuilder;
     111: aload         4
     113: invokevirtual #14                 // Method java/lang/StringBuilder.append:(Ljava/lang/String;)Ljava/lang/StringBuilder;
     116: ldc           #89                 // String  to join procedure barrier.
     118: invokevirtual #14                 // Method java/lang/StringBuilder.append:(Ljava/lang/String;)Ljava/lang/StringBuilder;
     121: invokevirtual #15                 // Method java/lang/StringBuilder.toString:()Ljava/lang/String;
     124: aload         5
     126: aload_3
     127: invokevirtual #34                 // Method org/apache/hadoop/hbase/procedure/ProcedureMember.controllerConnectionFailure:(Ljava/lang/String;Ljava/lang/Throwable;Ljava/lang/String;)V
     130: return
    Exception table:
       from    to  target type
          74    90    93   Class org/apache/zookeeper/KeeperException

  public void sendMemberAborted(org.apache.hadoop.hbase.procedure.Subprocedure, org.apache.hadoop.hbase.errorhandling.ForeignException);
    Code:
       0: aload_1
       1: ifnonnull     16
       4: getstatic     #5                  // Field LOG:Lorg/slf4j/Logger;
       7: ldc           #90                 // String Failed due to null subprocedure
       9: aload_2
      10: invokeinterface #62,  3           // InterfaceMethod org/slf4j/Logger.error:(Ljava/lang/String;Ljava/lang/Throwable;)V
      15: return
      16: aload_1
      17: invokevirtual #73                 // Method org/apache/hadoop/hbase/procedure/Subprocedure.getName:()Ljava/lang/String;
      20: astore_3
      21: getstatic     #5                  // Field LOG:Lorg/slf4j/Logger;
      24: new           #11                 // class java/lang/StringBuilder
      27: dup
      28: invokespecial #12                 // Method java/lang/StringBuilder."<init>":()V
      31: ldc           #91                 // String Aborting procedure (
      33: invokevirtual #14                 // Method java/lang/StringBuilder.append:(Ljava/lang/String;)Ljava/lang/StringBuilder;
      36: aload_3
      37: invokevirtual #14                 // Method java/lang/StringBuilder.append:(Ljava/lang/String;)Ljava/lang/StringBuilder;
      40: ldc           #76                 // String ) in zk
      42: invokevirtual #14                 // Method java/lang/StringBuilder.append:(Ljava/lang/String;)Ljava/lang/StringBuilder;
      45: invokevirtual #15                 // Method java/lang/StringBuilder.toString:()Ljava/lang/String;
      48: invokeinterface #16,  2           // InterfaceMethod org/slf4j/Logger.debug:(Ljava/lang/String;)V
      53: aload_0
      54: getfield      #9                  // Field zkController:Lorg/apache/hadoop/hbase/procedure/ZKProcedureUtil;
      57: aload_3
      58: invokevirtual #40                 // Method org/apache/hadoop/hbase/procedure/ZKProcedureUtil.getAbortZNode:(Ljava/lang/String;)Ljava/lang/String;
      61: astore        4
      63: aload_2
      64: invokevirtual #92                 // Method org/apache/hadoop/hbase/errorhandling/ForeignException.getSource:()Ljava/lang/String;
      67: ifnonnull     77
      70: aload_0
      71: getfield      #10                 // Field memberName:Ljava/lang/String;
      74: goto          81
      77: aload_2
      78: invokevirtual #92                 // Method org/apache/hadoop/hbase/errorhandling/ForeignException.getSource:()Ljava/lang/String;
      81: astore        5
      83: aload         5
      85: aload_2
      86: invokestatic  #93                 // Method org/apache/hadoop/hbase/errorhandling/ForeignException.serialize:(Ljava/lang/String;Ljava/lang/Throwable;)[B
      89: invokestatic  #86                 // Method org/apache/hadoop/hbase/shaded/protobuf/ProtobufUtil.prependPBMagic:([B)[B
      92: astore        6
      94: aload_0
      95: getfield      #9                  // Field zkController:Lorg/apache/hadoop/hbase/procedure/ZKProcedureUtil;
      98: invokevirtual #23                 // Method org/apache/hadoop/hbase/procedure/ZKProcedureUtil.getWatcher:()Lorg/apache/hadoop/hbase/zookeeper/ZKWatcher;
     101: aload         4
     103: aload         6
     105: invokestatic  #87                 // Method org/apache/hadoop/hbase/zookeeper/ZKUtil.createAndFailSilent:(Lorg/apache/hadoop/hbase/zookeeper/ZKWatcher;Ljava/lang/String;[B)V
     108: getstatic     #5                  // Field LOG:Lorg/slf4j/Logger;
     111: new           #11                 // class java/lang/StringBuilder
     114: dup
     115: invokespecial #12                 // Method java/lang/StringBuilder."<init>":()V
     118: ldc           #94                 // String Finished creating abort znode:
     120: invokevirtual #14                 // Method java/lang/StringBuilder.append:(Ljava/lang/String;)Ljava/lang/StringBuilder;
     123: aload         4
     125: invokevirtual #14                 // Method java/lang/StringBuilder.append:(Ljava/lang/String;)Ljava/lang/StringBuilder;
     128: invokevirtual #15                 // Method java/lang/StringBuilder.toString:()Ljava/lang/String;
     131: invokeinterface #16,  2           // InterfaceMethod org/slf4j/Logger.debug:(Ljava/lang/String;)V
     136: goto          190
     139: astore        5
     141: aload_0
     142: getfield      #9                  // Field zkController:Lorg/apache/hadoop/hbase/procedure/ZKProcedureUtil;
     145: aload_0
     146: getfield      #9                  // Field zkController:Lorg/apache/hadoop/hbase/procedure/ZKProcedureUtil;
     149: invokevirtual #95                 // Method org/apache/hadoop/hbase/procedure/ZKProcedureUtil.getBaseZnode:()Ljava/lang/String;
     152: invokevirtual #96                 // Method org/apache/hadoop/hbase/procedure/ZKProcedureUtil.logZKTree:(Ljava/lang/String;)V
     155: aload_0
     156: getfield      #18                 // Field member:Lorg/apache/hadoop/hbase/procedure/ProcedureMember;
     159: new           #11                 // class java/lang/StringBuilder
     162: dup
     163: invokespecial #12                 // Method java/lang/StringBuilder."<init>":()V
     166: ldc           #88                 // String Failed to post zk node:
     168: invokevirtual #14                 // Method java/lang/StringBuilder.append:(Ljava/lang/String;)Ljava/lang/StringBuilder;
     171: aload         4
     173: invokevirtual #14                 // Method java/lang/StringBuilder.append:(Ljava/lang/String;)Ljava/lang/StringBuilder;
     176: ldc           #97                 // String  to abort procedure
     178: invokevirtual #14                 // Method java/lang/StringBuilder.append:(Ljava/lang/String;)Ljava/lang/StringBuilder;
     181: invokevirtual #15                 // Method java/lang/StringBuilder.toString:()Ljava/lang/String;
     184: aload         5
     186: aload_3
     187: invokevirtual #34                 // Method org/apache/hadoop/hbase/procedure/ProcedureMember.controllerConnectionFailure:(Ljava/lang/String;Ljava/lang/Throwable;Ljava/lang/String;)V
     190: return
    Exception table:
       from    to  target type
          63   136   139   Class org/apache/zookeeper/KeeperException

  protected void abort(java.lang.String);
    Code:
       0: getstatic     #5                  // Field LOG:Lorg/slf4j/Logger;
       3: new           #11                 // class java/lang/StringBuilder
       6: dup
       7: invokespecial #12                 // Method java/lang/StringBuilder."<init>":()V
      10: ldc           #98                 // String Aborting procedure member for znode
      12: invokevirtual #14                 // Method java/lang/StringBuilder.append:(Ljava/lang/String;)Ljava/lang/StringBuilder;
      15: aload_1
      16: invokevirtual #14                 // Method java/lang/StringBuilder.append:(Ljava/lang/String;)Ljava/lang/StringBuilder;
      19: invokevirtual #15                 // Method java/lang/StringBuilder.toString:()Ljava/lang/String;
      22: invokeinterface #16,  2           // InterfaceMethod org/slf4j/Logger.debug:(Ljava/lang/String;)V
      27: aload_1
      28: invokestatic  #17                 // Method org/apache/hadoop/hbase/zookeeper/ZKUtil.getNodeName:(Ljava/lang/String;)Ljava/lang/String;
      31: astore_2
      32: aload_0
      33: getfield      #9                  // Field zkController:Lorg/apache/hadoop/hbase/procedure/ZKProcedureUtil;
      36: invokevirtual #23                 // Method org/apache/hadoop/hbase/procedure/ZKProcedureUtil.getWatcher:()Lorg/apache/hadoop/hbase/zookeeper/ZKWatcher;
      39: aload_1
      40: invokestatic  #46                 // Method org/apache/hadoop/hbase/zookeeper/ZKUtil.getData:(Lorg/apache/hadoop/hbase/zookeeper/ZKWatcher;Ljava/lang/String;)[B
      43: astore_3
      44: aload_3
      45: ifnull        53
      48: aload_3
      49: arraylength
      50: ifne          54
      53: return
      54: aload_3
      55: invokestatic  #47                 // Method org/apache/hadoop/hbase/shaded/protobuf/ProtobufUtil.isPBMagicPrefix:([B)Z
      58: ifne          122
      61: new           #11                 // class java/lang/StringBuilder
      64: dup
      65: invokespecial #12                 // Method java/lang/StringBuilder."<init>":()V
      68: ldc           #99                 // String Illegally formatted data in abort node for proc
      70: invokevirtual #14                 // Method java/lang/StringBuilder.append:(Ljava/lang/String;)Ljava/lang/StringBuilder;
      73: aload_2
      74: invokevirtual #14                 // Method java/lang/StringBuilder.append:(Ljava/lang/String;)Ljava/lang/StringBuilder;
      77: ldc           #100                // String .  Killing the procedure.
      79: invokevirtual #14                 // Method java/lang/StringBuilder.append:(Ljava/lang/String;)Ljava/lang/StringBuilder;
      82: invokevirtual #15                 // Method java/lang/StringBuilder.toString:()Ljava/lang/String;
      85: astore        5
      87: getstatic     #5                  // Field LOG:Lorg/slf4j/Logger;
      90: aload         5
      92: invokeinterface #51,  2           // InterfaceMethod org/slf4j/Logger.error:(Ljava/lang/String;)V
      97: new           #63                 // class org/apache/hadoop/hbase/errorhandling/ForeignException
     100: dup
     101: aload_0
     102: invokevirtual #64                 // Method getMemberName:()Ljava/lang/String;
     105: new           #52                 // class java/lang/IllegalArgumentException
     108: dup
     109: aload         5
     111: invokespecial #53                 // Method java/lang/IllegalArgumentException."<init>":(Ljava/lang/String;)V
     114: invokespecial #65                 // Method org/apache/hadoop/hbase/errorhandling/ForeignException."<init>":(Ljava/lang/String;Ljava/lang/Throwable;)V
     117: astore        4
     119: goto          138
     122: aload_3
     123: invokestatic  #56                 // Method org/apache/hadoop/hbase/shaded/protobuf/ProtobufUtil.lengthOfPBMagic:()I
     126: aload_3
     127: arraylength
     128: invokestatic  #57                 // Method java/util/Arrays.copyOfRange:([BII)[B
     131: astore_3
     132: aload_3
     133: invokestatic  #101                // Method org/apache/hadoop/hbase/errorhandling/ForeignException.deserialize:([B)Lorg/apache/hadoop/hbase/errorhandling/ForeignException;
     136: astore        4
     138: goto          190
     141: astore        5
     143: getstatic     #5                  // Field LOG:Lorg/slf4j/Logger;
     146: new           #11                 // class java/lang/StringBuilder
     149: dup
     150: invokespecial #12                 // Method java/lang/StringBuilder."<init>":()V
     153: ldc           #103                // String Got an error notification for op:
     155: invokevirtual #14                 // Method java/lang/StringBuilder.append:(Ljava/lang/String;)Ljava/lang/StringBuilder;
     158: aload_2
     159: invokevirtual #14                 // Method java/lang/StringBuilder.append:(Ljava/lang/String;)Ljava/lang/StringBuilder;
     162: ldc           #104                // String  but we can't read the information. Killing the procedure.
     164: invokevirtual #14                 // Method java/lang/StringBuilder.append:(Ljava/lang/String;)Ljava/lang/StringBuilder;
     167: invokevirtual #15                 // Method java/lang/StringBuilder.toString:()Ljava/lang/String;
     170: invokeinterface #105,  2          // InterfaceMethod org/slf4j/Logger.warn:(Ljava/lang/String;)V
     175: new           #63                 // class org/apache/hadoop/hbase/errorhandling/ForeignException
     178: dup
     179: aload_0
     180: invokevirtual #64                 // Method getMemberName:()Ljava/lang/String;
     183: aload         5
     185: invokespecial #65                 // Method org/apache/hadoop/hbase/errorhandling/ForeignException."<init>":(Ljava/lang/String;Ljava/lang/Throwable;)V
     188: astore        4
     190: aload_0
     191: getfield      #18                 // Field member:Lorg/apache/hadoop/hbase/procedure/ProcedureMember;
     194: aload_2
     195: aload         4
     197: invokevirtual #106                // Method org/apache/hadoop/hbase/procedure/ProcedureMember.receiveAbortProcedure:(Ljava/lang/String;Lorg/apache/hadoop/hbase/errorhandling/ForeignException;)V
     200: goto          263
     203: astore_3
     204: aload_0
     205: getfield      #18                 // Field member:Lorg/apache/hadoop/hbase/procedure/ProcedureMember;
     208: new           #11                 // class java/lang/StringBuilder
     211: dup
     212: invokespecial #12                 // Method java/lang/StringBuilder."<init>":()V
     215: ldc           #107                // String Failed to get data for abort znode:
     217: invokevirtual #14                 // Method java/lang/StringBuilder.append:(Ljava/lang/String;)Ljava/lang/StringBuilder;
     220: aload_1
     221: invokevirtual #14                 // Method java/lang/StringBuilder.append:(Ljava/lang/String;)Ljava/lang/StringBuilder;
     224: aload_0
     225: getfield      #9                  // Field zkController:Lorg/apache/hadoop/hbase/procedure/ZKProcedureUtil;
     228: invokevirtual #21                 // Method org/apache/hadoop/hbase/procedure/ZKProcedureUtil.getAbortZnode:()Ljava/lang/String;
     231: invokevirtual #14                 // Method java/lang/StringBuilder.append:(Ljava/lang/String;)Ljava/lang/StringBuilder;
     234: invokevirtual #15                 // Method java/lang/StringBuilder.toString:()Ljava/lang/String;
     237: aload_3
     238: aload_2
     239: invokevirtual #34                 // Method org/apache/hadoop/hbase/procedure/ProcedureMember.controllerConnectionFailure:(Ljava/lang/String;Ljava/lang/Throwable;Ljava/lang/String;)V
     242: goto          263
     245: astore_3
     246: getstatic     #5                  // Field LOG:Lorg/slf4j/Logger;
     249: ldc           #108                // String abort already in progress
     251: aload_3
     252: invokeinterface #109,  3          // InterfaceMethod org/slf4j/Logger.warn:(Ljava/lang/String;Ljava/lang/Throwable;)V
     257: invokestatic  #71                 // Method java/lang/Thread.currentThread:()Ljava/lang/Thread;
     260: invokevirtual #72                 // Method java/lang/Thread.interrupt:()V
     263: return
    Exception table:
       from    to  target type
          44    53   141   Class java/io/IOException
          54   138   141   Class java/io/IOException
          32    53   203   Class org/apache/zookeeper/KeeperException
          54   200   203   Class org/apache/zookeeper/KeeperException
          32    53   245   Class java/lang/InterruptedException
          54   200   245   Class java/lang/InterruptedException

  public void start(java.lang.String, org.apache.hadoop.hbase.procedure.ProcedureMember);
    Code:
       0: getstatic     #5                  // Field LOG:Lorg/slf4j/Logger;
       3: new           #11                 // class java/lang/StringBuilder
       6: dup
       7: invokespecial #12                 // Method java/lang/StringBuilder."<init>":()V
      10: ldc           #110                // String Starting procedure member '
      12: invokevirtual #14                 // Method java/lang/StringBuilder.append:(Ljava/lang/String;)Ljava/lang/StringBuilder;
      15: aload_1
      16: invokevirtual #14                 // Method java/lang/StringBuilder.append:(Ljava/lang/String;)Ljava/lang/StringBuilder;
      19: ldc           #22                 // String '
      21: invokevirtual #14                 // Method java/lang/StringBuilder.append:(Ljava/lang/String;)Ljava/lang/StringBuilder;
      24: invokevirtual #15                 // Method java/lang/StringBuilder.toString:()Ljava/lang/String;
      27: invokeinterface #16,  2           // InterfaceMethod org/slf4j/Logger.debug:(Ljava/lang/String;)V
      32: aload_0
      33: aload_2
      34: putfield      #18                 // Field member:Lorg/apache/hadoop/hbase/procedure/ProcedureMember;
      37: aload_0
      38: aload_1
      39: putfield      #10                 // Field memberName:Ljava/lang/String;
      42: aload_0
      43: invokespecial #3                  // Method watchForAbortedProcedures:()V
      46: aload_0
      47: invokespecial #4                  // Method waitForNewProcedures:()V
      50: return

  public void close() throws java.io.IOException;
    Code:
       0: aload_0
       1: getfield      #9                  // Field zkController:Lorg/apache/hadoop/hbase/procedure/ZKProcedureUtil;
       4: invokevirtual #111                // Method org/apache/hadoop/hbase/procedure/ZKProcedureUtil.close:()V
       7: return

  static org.slf4j.Logger access$000();
    Code:
       0: getstatic     #5                  // Field LOG:Lorg/slf4j/Logger;
       3: areturn

  static void access$100(org.apache.hadoop.hbase.procedure.ZKProcedureMemberRpcs);
    Code:
       0: aload_0
       1: invokespecial #4                  // Method waitForNewProcedures:()V
       4: return

  static void access$200(org.apache.hadoop.hbase.procedure.ZKProcedureMemberRpcs);
    Code:
       0: aload_0
       1: invokespecial #3                  // Method watchForAbortedProcedures:()V
       4: return

  static void access$300(org.apache.hadoop.hbase.procedure.ZKProcedureMemberRpcs, java.lang.String);
    Code:
       0: aload_0
       1: aload_1
       2: invokespecial #2                  // Method receivedReachedGlobalBarrier:(Ljava/lang/String;)V
       5: return

  static void access$400(org.apache.hadoop.hbase.procedure.ZKProcedureMemberRpcs, java.lang.String);
    Code:
       0: aload_0
       1: aload_1
       2: invokespecial #1                  // Method startNewSubprocedure:(Ljava/lang/String;)V
       5: return

  static {};
    Code:
       0: ldc           #112                // class org/apache/hadoop/hbase/procedure/ZKProcedureMemberRpcs
       2: invokestatic  #113                // Method org/slf4j/LoggerFactory.getLogger:(Ljava/lang/Class;)Lorg/slf4j/Logger;
       5: putstatic     #5                  // Field LOG:Lorg/slf4j/Logger;
       8: return
}
