Compiled from "ZKProcedureCoordinationManager.java"
public class org.apache.hadoop.hbase.procedure.ZKProcedureCoordinationManager implements org.apache.hadoop.hbase.procedure.ProcedureCoordinationManager {
  org.apache.hadoop.hbase.zookeeper.ZKWatcher watcher;

  public org.apache.hadoop.hbase.procedure.ZKProcedureCoordinationManager(org.apache.hadoop.hbase.Server);
    Code:
       0: aload_0
       1: invokespecial #1                  // Method java/lang/Object."<init>":()V
       4: aload_0
       5: aload_1
       6: invokeinterface #2,  1            // InterfaceMethod org/apache/hadoop/hbase/Server.getZooKeeper:()Lorg/apache/hadoop/hbase/zookeeper/ZKWatcher;
      11: putfield      #3                  // Field watcher:Lorg/apache/hadoop/hbase/zookeeper/ZKWatcher;
      14: return

  public org.apache.hadoop.hbase.procedure.ProcedureCoordinatorRpcs getProcedureCoordinatorRpcs(java.lang.String, java.lang.String);
    Code:
       0: new           #4                  // class org/apache/hadoop/hbase/procedure/ZKProcedureCoordinator
       3: dup
       4: aload_0
       5: getfield      #3                  // Field watcher:Lorg/apache/hadoop/hbase/zookeeper/ZKWatcher;
       8: aload_1
       9: aload_2
      10: invokespecial #5                  // Method org/apache/hadoop/hbase/procedure/ZKProcedureCoordinator."<init>":(Lorg/apache/hadoop/hbase/zookeeper/ZKWatcher;Ljava/lang/String;Ljava/lang/String;)V
      13: areturn

  public org.apache.hadoop.hbase.procedure.ProcedureMemberRpcs getProcedureMemberRpcs(java.lang.String) throws org.apache.zookeeper.KeeperException;
    Code:
       0: new           #6                  // class org/apache/hadoop/hbase/procedure/ZKProcedureMemberRpcs
       3: dup
       4: aload_0
       5: getfield      #3                  // Field watcher:Lorg/apache/hadoop/hbase/zookeeper/ZKWatcher;
       8: aload_1
       9: invokespecial #7                  // Method org/apache/hadoop/hbase/procedure/ZKProcedureMemberRpcs."<init>":(Lorg/apache/hadoop/hbase/zookeeper/ZKWatcher;Ljava/lang/String;)V
      12: areturn
}
