Compiled from "ZKTableArchiveClient.java"
public class org.apache.hadoop.hbase.backup.example.ZKTableArchiveClient extends org.apache.hadoop.conf.Configured {
  public org.apache.hadoop.hbase.backup.example.ZKTableArchiveClient(org.apache.hadoop.conf.Configuration, org.apache.hadoop.hbase.client.ClusterConnection);
    Code:
       0: aload_0
       1: aload_1
       2: invokespecial #1                  // Method org/apache/hadoop/conf/Configured."<init>":(Lorg/apache/hadoop/conf/Configuration;)V
       5: aload_0
       6: aload_2
       7: putfield      #2                  // Field connection:Lorg/apache/hadoop/hbase/client/ClusterConnection;
      10: return

  public void enableHFileBackupAsync(byte[]) throws java.io.IOException, org.apache.zookeeper.KeeperException;
    Code:
       0: aload_0
       1: invokespecial #3                  // Method createHFileArchiveManager:()Lorg/apache/hadoop/hbase/backup/example/HFileArchiveManager;
       4: aload_1
       5: invokevirtual #4                  // Method org/apache/hadoop/hbase/backup/example/HFileArchiveManager.enableHFileBackup:([B)Lorg/apache/hadoop/hbase/backup/example/HFileArchiveManager;
       8: invokevirtual #5                  // Method org/apache/hadoop/hbase/backup/example/HFileArchiveManager.stop:()V
      11: return

  public void disableHFileBackup(java.lang.String) throws java.io.IOException, org.apache.zookeeper.KeeperException;
    Code:
       0: aload_0
       1: aload_1
       2: invokestatic  #6                  // Method org/apache/hadoop/hbase/util/Bytes.toBytes:(Ljava/lang/String;)[B
       5: invokevirtual #7                  // Method disableHFileBackup:([B)V
       8: return

  public void disableHFileBackup(byte[]) throws java.io.IOException, org.apache.zookeeper.KeeperException;
    Code:
       0: aload_0
       1: invokespecial #3                  // Method createHFileArchiveManager:()Lorg/apache/hadoop/hbase/backup/example/HFileArchiveManager;
       4: aload_1
       5: invokevirtual #8                  // Method org/apache/hadoop/hbase/backup/example/HFileArchiveManager.disableHFileBackup:([B)Lorg/apache/hadoop/hbase/backup/example/HFileArchiveManager;
       8: invokevirtual #5                  // Method org/apache/hadoop/hbase/backup/example/HFileArchiveManager.stop:()V
      11: return

  public void disableHFileBackup() throws java.io.IOException, org.apache.zookeeper.KeeperException;
    Code:
       0: aload_0
       1: invokespecial #3                  // Method createHFileArchiveManager:()Lorg/apache/hadoop/hbase/backup/example/HFileArchiveManager;
       4: invokevirtual #9                  // Method org/apache/hadoop/hbase/backup/example/HFileArchiveManager.disableHFileBackup:()Lorg/apache/hadoop/hbase/backup/example/HFileArchiveManager;
       7: invokevirtual #5                  // Method org/apache/hadoop/hbase/backup/example/HFileArchiveManager.stop:()V
      10: return

  public boolean getArchivingEnabled(byte[]) throws java.io.IOException, org.apache.zookeeper.KeeperException;
    Code:
       0: aload_0
       1: invokespecial #3                  // Method createHFileArchiveManager:()Lorg/apache/hadoop/hbase/backup/example/HFileArchiveManager;
       4: astore_2
       5: aload_2
       6: aload_1
       7: invokevirtual #10                 // Method org/apache/hadoop/hbase/backup/example/HFileArchiveManager.isArchivingEnabled:([B)Z
      10: istore_3
      11: aload_2
      12: invokevirtual #5                  // Method org/apache/hadoop/hbase/backup/example/HFileArchiveManager.stop:()V
      15: iload_3
      16: ireturn
      17: astore        4
      19: aload_2
      20: invokevirtual #5                  // Method org/apache/hadoop/hbase/backup/example/HFileArchiveManager.stop:()V
      23: aload         4
      25: athrow
    Exception table:
       from    to  target type
           5    11    17   any
          17    19    17   any

  public boolean getArchivingEnabled(java.lang.String) throws java.io.IOException, org.apache.zookeeper.KeeperException;
    Code:
       0: aload_0
       1: aload_1
       2: invokestatic  #6                  // Method org/apache/hadoop/hbase/util/Bytes.toBytes:(Ljava/lang/String;)[B
       5: invokevirtual #11                 // Method getArchivingEnabled:([B)Z
       8: ireturn

  public static java.lang.String getArchiveZNode(org.apache.hadoop.conf.Configuration, org.apache.hadoop.hbase.zookeeper.ZKWatcher);
    Code:
       0: aload_1
       1: invokevirtual #15                 // Method org/apache/hadoop/hbase/zookeeper/ZKWatcher.getZNodePaths:()Lorg/apache/hadoop/hbase/zookeeper/ZNodePaths;
       4: getfield      #16                 // Field org/apache/hadoop/hbase/zookeeper/ZNodePaths.baseZNode:Ljava/lang/String;
       7: aload_0
       8: ldc           #18                 // String zookeeper.znode.hfile.archive
      10: ldc           #20                 // String hfilearchive
      12: invokevirtual #21                 // Method org/apache/hadoop/conf/Configuration.get:(Ljava/lang/String;Ljava/lang/String;)Ljava/lang/String;
      15: invokestatic  #22                 // Method org/apache/hadoop/hbase/zookeeper/ZNodePaths.joinZNode:(Ljava/lang/String;Ljava/lang/String;)Ljava/lang/String;
      18: areturn
}
