Compiled from "ZKUtil.java"
public abstract class org.apache.hadoop.hbase.zookeeper.ZKUtil$ZKUtilOp {
  public static org.apache.hadoop.hbase.zookeeper.ZKUtil$ZKUtilOp createAndFailSilent(java.lang.String, byte[]);
    Code:
       0: new           #4                  // class org/apache/hadoop/hbase/zookeeper/ZKUtil$ZKUtilOp$CreateAndFailSilent
       3: dup
       4: aload_0
       5: aload_1
       6: aconst_null
       7: invokespecial #5                  // Method org/apache/hadoop/hbase/zookeeper/ZKUtil$ZKUtilOp$CreateAndFailSilent."<init>":(Ljava/lang/String;[BLorg/apache/hadoop/hbase/zookeeper/ZKUtil$1;)V
      10: areturn

  public static org.apache.hadoop.hbase.zookeeper.ZKUtil$ZKUtilOp deleteNodeFailSilent(java.lang.String);
    Code:
       0: new           #6                  // class org/apache/hadoop/hbase/zookeeper/ZKUtil$ZKUtilOp$DeleteNodeFailSilent
       3: dup
       4: aload_0
       5: aconst_null
       6: invokespecial #7                  // Method org/apache/hadoop/hbase/zookeeper/ZKUtil$ZKUtilOp$DeleteNodeFailSilent."<init>":(Ljava/lang/String;Lorg/apache/hadoop/hbase/zookeeper/ZKUtil$1;)V
       9: areturn

  public static org.apache.hadoop.hbase.zookeeper.ZKUtil$ZKUtilOp setData(java.lang.String, byte[]);
    Code:
       0: new           #8                  // class org/apache/hadoop/hbase/zookeeper/ZKUtil$ZKUtilOp$SetData
       3: dup
       4: aload_0
       5: aload_1
       6: aconst_null
       7: invokespecial #9                  // Method org/apache/hadoop/hbase/zookeeper/ZKUtil$ZKUtilOp$SetData."<init>":(Ljava/lang/String;[BLorg/apache/hadoop/hbase/zookeeper/ZKUtil$1;)V
      10: areturn

  public static org.apache.hadoop.hbase.zookeeper.ZKUtil$ZKUtilOp setData(java.lang.String, byte[], int);
    Code:
       0: new           #8                  // class org/apache/hadoop/hbase/zookeeper/ZKUtil$ZKUtilOp$SetData
       3: dup
       4: aload_0
       5: aload_1
       6: iload_2
       7: aconst_null
       8: invokespecial #10                 // Method org/apache/hadoop/hbase/zookeeper/ZKUtil$ZKUtilOp$SetData."<init>":(Ljava/lang/String;[BILorg/apache/hadoop/hbase/zookeeper/ZKUtil$1;)V
      11: areturn

  public java.lang.String getPath();
    Code:
       0: aload_0
       1: getfield      #3                  // Field path:Ljava/lang/String;
       4: areturn

  org.apache.hadoop.hbase.zookeeper.ZKUtil$ZKUtilOp(java.lang.String, org.apache.hadoop.hbase.zookeeper.ZKUtil$1);
    Code:
       0: aload_0
       1: aload_1
       2: invokespecial #1                  // Method "<init>":(Ljava/lang/String;)V
       5: return
}
