Compiled from "ZKUtil.java"
public final class org.apache.hadoop.hbase.zookeeper.ZKUtil$ZKUtilOp$DeleteNodeFailSilent extends org.apache.hadoop.hbase.zookeeper.ZKUtil$ZKUtilOp {
  public boolean equals(java.lang.Object);
    Code:
       0: aload_0
       1: aload_1
       2: if_acmpne     7
       5: iconst_1
       6: ireturn
       7: aload_1
       8: instanceof    #3                  // class org/apache/hadoop/hbase/zookeeper/ZKUtil$ZKUtilOp$DeleteNodeFailSilent
      11: ifne          16
      14: iconst_0
      15: ireturn
      16: aload_0
      17: aload_1
      18: invokespecial #4                  // Method java/lang/Object.equals:(Ljava/lang/Object;)Z
      21: ireturn

  public int hashCode();
    Code:
       0: aload_0
       1: invokevirtual #5                  // Method getPath:()Ljava/lang/String;
       4: invokevirtual #6                  // Method java/lang/String.hashCode:()I
       7: ireturn

  org.apache.hadoop.hbase.zookeeper.ZKUtil$ZKUtilOp$DeleteNodeFailSilent(java.lang.String, org.apache.hadoop.hbase.zookeeper.ZKUtil$1);
    Code:
       0: aload_0
       1: aload_1
       2: invokespecial #1                  // Method "<init>":(Ljava/lang/String;)V
       5: return
}
