Compiled from "ZKVisibilityLabelWatcher.java"
public class org.apache.hadoop.hbase.security.visibility.ZKVisibilityLabelWatcher extends org.apache.hadoop.hbase.zookeeper.ZKListener {
  public org.apache.hadoop.hbase.security.visibility.ZKVisibilityLabelWatcher(org.apache.hadoop.hbase.zookeeper.ZKWatcher, org.apache.hadoop.hbase.security.visibility.VisibilityLabelsCache, org.apache.hadoop.conf.Configuration);
    Code:
       0: aload_0
       1: aload_1
       2: invokespecial #1                  // Method org/apache/hadoop/hbase/zookeeper/ZKListener."<init>":(Lorg/apache/hadoop/hbase/zookeeper/ZKWatcher;)V
       5: aload_0
       6: aload_2
       7: putfield      #2                  // Field labelsCache:Lorg/apache/hadoop/hbase/security/visibility/VisibilityLabelsCache;
      10: aload_3
      11: ldc           #4                  // String zookeeper.znode.visibility.label.parent
      13: ldc           #5                  // String visibility/labels
      15: invokevirtual #6                  // Method org/apache/hadoop/conf/Configuration.get:(Ljava/lang/String;Ljava/lang/String;)Ljava/lang/String;
      18: astore        4
      20: aload_3
      21: ldc           #7                  // String zookeeper.znode.visibility.user.auths.parent
      23: ldc           #8                  // String visibility/user_auths
      25: invokevirtual #6                  // Method org/apache/hadoop/conf/Configuration.get:(Ljava/lang/String;Ljava/lang/String;)Ljava/lang/String;
      28: astore        5
      30: aload_0
      31: aload_1
      32: invokevirtual #9                  // Method org/apache/hadoop/hbase/zookeeper/ZKWatcher.getZNodePaths:()Lorg/apache/hadoop/hbase/zookeeper/ZNodePaths;
      35: getfield      #10                 // Field org/apache/hadoop/hbase/zookeeper/ZNodePaths.baseZNode:Ljava/lang/String;
      38: aload         4
      40: invokestatic  #11                 // Method org/apache/hadoop/hbase/zookeeper/ZNodePaths.joinZNode:(Ljava/lang/String;Ljava/lang/String;)Ljava/lang/String;
      43: putfield      #12                 // Field labelZnode:Ljava/lang/String;
      46: aload_0
      47: aload_1
      48: invokevirtual #9                  // Method org/apache/hadoop/hbase/zookeeper/ZKWatcher.getZNodePaths:()Lorg/apache/hadoop/hbase/zookeeper/ZNodePaths;
      51: getfield      #10                 // Field org/apache/hadoop/hbase/zookeeper/ZNodePaths.baseZNode:Ljava/lang/String;
      54: aload         5
      56: invokestatic  #11                 // Method org/apache/hadoop/hbase/zookeeper/ZNodePaths.joinZNode:(Ljava/lang/String;Ljava/lang/String;)Ljava/lang/String;
      59: putfield      #13                 // Field userAuthsZnode:Ljava/lang/String;
      62: return

  public void start() throws org.apache.zookeeper.KeeperException;
    Code:
       0: aload_0
       1: getfield      #14                 // Field watcher:Lorg/apache/hadoop/hbase/zookeeper/ZKWatcher;
       4: aload_0
       5: invokevirtual #15                 // Method org/apache/hadoop/hbase/zookeeper/ZKWatcher.registerListener:(Lorg/apache/hadoop/hbase/zookeeper/ZKListener;)V
       8: aload_0
       9: getfield      #14                 // Field watcher:Lorg/apache/hadoop/hbase/zookeeper/ZKWatcher;
      12: aload_0
      13: getfield      #12                 // Field labelZnode:Ljava/lang/String;
      16: invokestatic  #16                 // Method org/apache/hadoop/hbase/zookeeper/ZKUtil.createWithParents:(Lorg/apache/hadoop/hbase/zookeeper/ZKWatcher;Ljava/lang/String;)V
      19: aload_0
      20: getfield      #14                 // Field watcher:Lorg/apache/hadoop/hbase/zookeeper/ZKWatcher;
      23: aload_0
      24: getfield      #13                 // Field userAuthsZnode:Ljava/lang/String;
      27: invokestatic  #16                 // Method org/apache/hadoop/hbase/zookeeper/ZKUtil.createWithParents:(Lorg/apache/hadoop/hbase/zookeeper/ZKWatcher;Ljava/lang/String;)V
      30: aload_0
      31: getfield      #14                 // Field watcher:Lorg/apache/hadoop/hbase/zookeeper/ZKWatcher;
      34: aload_0
      35: getfield      #12                 // Field labelZnode:Ljava/lang/String;
      38: invokestatic  #17                 // Method org/apache/hadoop/hbase/zookeeper/ZKUtil.getDataAndWatch:(Lorg/apache/hadoop/hbase/zookeeper/ZKWatcher;Ljava/lang/String;)[B
      41: astore_1
      42: aload_1
      43: ifnull        56
      46: aload_1
      47: arraylength
      48: ifle          56
      51: aload_0
      52: aload_1
      53: invokespecial #18                 // Method refreshVisibilityLabelsCache:([B)V
      56: aload_0
      57: getfield      #14                 // Field watcher:Lorg/apache/hadoop/hbase/zookeeper/ZKWatcher;
      60: aload_0
      61: getfield      #13                 // Field userAuthsZnode:Ljava/lang/String;
      64: invokestatic  #17                 // Method org/apache/hadoop/hbase/zookeeper/ZKUtil.getDataAndWatch:(Lorg/apache/hadoop/hbase/zookeeper/ZKWatcher;Ljava/lang/String;)[B
      67: astore_1
      68: aload_1
      69: ifnull        82
      72: aload_1
      73: arraylength
      74: ifle          82
      77: aload_0
      78: aload_1
      79: invokespecial #19                 // Method refreshUserAuthsCache:([B)V
      82: return

  public void nodeCreated(java.lang.String);
    Code:
       0: aload_1
       1: aload_0
       2: getfield      #12                 // Field labelZnode:Ljava/lang/String;
       5: invokevirtual #26                 // Method java/lang/String.equals:(Ljava/lang/Object;)Z
       8: ifne          22
      11: aload_1
      12: aload_0
      13: getfield      #13                 // Field userAuthsZnode:Ljava/lang/String;
      16: invokevirtual #26                 // Method java/lang/String.equals:(Ljava/lang/Object;)Z
      19: ifeq          73
      22: aload_0
      23: getfield      #14                 // Field watcher:Lorg/apache/hadoop/hbase/zookeeper/ZKWatcher;
      26: aload_1
      27: invokestatic  #27                 // Method org/apache/hadoop/hbase/zookeeper/ZKUtil.watchAndCheckExists:(Lorg/apache/hadoop/hbase/zookeeper/ZKWatcher;Ljava/lang/String;)Z
      30: pop
      31: goto          73
      34: astore_2
      35: getstatic     #22                 // Field LOG:Lorg/slf4j/Logger;
      38: new           #29                 // class java/lang/StringBuilder
      41: dup
      42: invokespecial #30                 // Method java/lang/StringBuilder."<init>":()V
      45: ldc           #31                 // String Error setting watcher on node
      47: invokevirtual #32                 // Method java/lang/StringBuilder.append:(Ljava/lang/String;)Ljava/lang/StringBuilder;
      50: aload_1
      51: invokevirtual #32                 // Method java/lang/StringBuilder.append:(Ljava/lang/String;)Ljava/lang/StringBuilder;
      54: invokevirtual #33                 // Method java/lang/StringBuilder.toString:()Ljava/lang/String;
      57: aload_2
      58: invokeinterface #24,  3           // InterfaceMethod org/slf4j/Logger.error:(Ljava/lang/String;Ljava/lang/Throwable;)V
      63: aload_0
      64: getfield      #14                 // Field watcher:Lorg/apache/hadoop/hbase/zookeeper/ZKWatcher;
      67: ldc           #34                 // String ZooKeeper error obtaining label node children
      69: aload_2
      70: invokevirtual #35                 // Method org/apache/hadoop/hbase/zookeeper/ZKWatcher.abort:(Ljava/lang/String;Ljava/lang/Throwable;)V
      73: return
    Exception table:
       from    to  target type
          22    31    34   Class org/apache/zookeeper/KeeperException

  public void nodeDeleted(java.lang.String);
    Code:
       0: return

  public void nodeDataChanged(java.lang.String);
    Code:
       0: aload_1
       1: aload_0
       2: getfield      #12                 // Field labelZnode:Ljava/lang/String;
       5: invokevirtual #26                 // Method java/lang/String.equals:(Ljava/lang/Object;)Z
       8: ifne          22
      11: aload_1
      12: aload_0
      13: getfield      #13                 // Field userAuthsZnode:Ljava/lang/String;
      16: invokevirtual #26                 // Method java/lang/String.equals:(Ljava/lang/Object;)Z
      19: ifeq          122
      22: aload_0
      23: getfield      #14                 // Field watcher:Lorg/apache/hadoop/hbase/zookeeper/ZKWatcher;
      26: aload_1
      27: invokevirtual #36                 // Method org/apache/hadoop/hbase/zookeeper/ZKWatcher.sync:(Ljava/lang/String;)V
      30: aload_0
      31: getfield      #14                 // Field watcher:Lorg/apache/hadoop/hbase/zookeeper/ZKWatcher;
      34: aload_1
      35: invokestatic  #17                 // Method org/apache/hadoop/hbase/zookeeper/ZKUtil.getDataAndWatch:(Lorg/apache/hadoop/hbase/zookeeper/ZKWatcher;Ljava/lang/String;)[B
      38: astore_2
      39: aload_1
      40: aload_0
      41: getfield      #12                 // Field labelZnode:Ljava/lang/String;
      44: invokevirtual #26                 // Method java/lang/String.equals:(Ljava/lang/Object;)Z
      47: ifeq          58
      50: aload_0
      51: aload_2
      52: invokespecial #18                 // Method refreshVisibilityLabelsCache:([B)V
      55: goto          63
      58: aload_0
      59: aload_2
      60: invokespecial #19                 // Method refreshUserAuthsCache:([B)V
      63: goto          122
      66: astore_2
      67: getstatic     #22                 // Field LOG:Lorg/slf4j/Logger;
      70: new           #29                 // class java/lang/StringBuilder
      73: dup
      74: invokespecial #30                 // Method java/lang/StringBuilder."<init>":()V
      77: ldc           #37                 // String Error reading data from zookeeper for node
      79: invokevirtual #32                 // Method java/lang/StringBuilder.append:(Ljava/lang/String;)Ljava/lang/StringBuilder;
      82: aload_1
      83: invokevirtual #32                 // Method java/lang/StringBuilder.append:(Ljava/lang/String;)Ljava/lang/StringBuilder;
      86: invokevirtual #33                 // Method java/lang/StringBuilder.toString:()Ljava/lang/String;
      89: aload_2
      90: invokeinterface #24,  3           // InterfaceMethod org/slf4j/Logger.error:(Ljava/lang/String;Ljava/lang/Throwable;)V
      95: aload_0
      96: getfield      #14                 // Field watcher:Lorg/apache/hadoop/hbase/zookeeper/ZKWatcher;
      99: new           #29                 // class java/lang/StringBuilder
     102: dup
     103: invokespecial #30                 // Method java/lang/StringBuilder."<init>":()V
     106: ldc           #38                 // String ZooKeeper error getting data for node
     108: invokevirtual #32                 // Method java/lang/StringBuilder.append:(Ljava/lang/String;)Ljava/lang/StringBuilder;
     111: aload_1
     112: invokevirtual #32                 // Method java/lang/StringBuilder.append:(Ljava/lang/String;)Ljava/lang/StringBuilder;
     115: invokevirtual #33                 // Method java/lang/StringBuilder.toString:()Ljava/lang/String;
     118: aload_2
     119: invokevirtual #35                 // Method org/apache/hadoop/hbase/zookeeper/ZKWatcher.abort:(Ljava/lang/String;Ljava/lang/Throwable;)V
     122: return
    Exception table:
       from    to  target type
          22    63    66   Class org/apache/zookeeper/KeeperException

  public void nodeChildrenChanged(java.lang.String);
    Code:
       0: return

  public void writeToZookeeper(byte[], boolean);
    Code:
       0: aload_0
       1: getfield      #12                 // Field labelZnode:Ljava/lang/String;
       4: astore_3
       5: iload_2
       6: ifne          14
       9: aload_0
      10: getfield      #13                 // Field userAuthsZnode:Ljava/lang/String;
      13: astore_3
      14: aload_0
      15: getfield      #14                 // Field watcher:Lorg/apache/hadoop/hbase/zookeeper/ZKWatcher;
      18: aload_3
      19: aload_1
      20: iconst_m1
      21: invokestatic  #39                 // Method org/apache/hadoop/hbase/zookeeper/ZKUtil.updateExistingNodeData:(Lorg/apache/hadoop/hbase/zookeeper/ZKWatcher;Ljava/lang/String;[BI)V
      24: goto          91
      27: astore        4
      29: getstatic     #22                 // Field LOG:Lorg/slf4j/Logger;
      32: new           #29                 // class java/lang/StringBuilder
      35: dup
      36: invokespecial #30                 // Method java/lang/StringBuilder."<init>":()V
      39: ldc           #40                 // String Failed writing to
      41: invokevirtual #32                 // Method java/lang/StringBuilder.append:(Ljava/lang/String;)Ljava/lang/StringBuilder;
      44: aload_3
      45: invokevirtual #32                 // Method java/lang/StringBuilder.append:(Ljava/lang/String;)Ljava/lang/StringBuilder;
      48: invokevirtual #33                 // Method java/lang/StringBuilder.toString:()Ljava/lang/String;
      51: aload         4
      53: invokeinterface #24,  3           // InterfaceMethod org/slf4j/Logger.error:(Ljava/lang/String;Ljava/lang/Throwable;)V
      58: aload_0
      59: getfield      #14                 // Field watcher:Lorg/apache/hadoop/hbase/zookeeper/ZKWatcher;
      62: new           #29                 // class java/lang/StringBuilder
      65: dup
      66: invokespecial #30                 // Method java/lang/StringBuilder."<init>":()V
      69: ldc           #41                 // String Failed writing node
      71: invokevirtual #32                 // Method java/lang/StringBuilder.append:(Ljava/lang/String;)Ljava/lang/StringBuilder;
      74: aload_3
      75: invokevirtual #32                 // Method java/lang/StringBuilder.append:(Ljava/lang/String;)Ljava/lang/StringBuilder;
      78: ldc           #42                 // String  to zookeeper
      80: invokevirtual #32                 // Method java/lang/StringBuilder.append:(Ljava/lang/String;)Ljava/lang/StringBuilder;
      83: invokevirtual #33                 // Method java/lang/StringBuilder.toString:()Ljava/lang/String;
      86: aload         4
      88: invokevirtual #35                 // Method org/apache/hadoop/hbase/zookeeper/ZKWatcher.abort:(Ljava/lang/String;Ljava/lang/Throwable;)V
      91: return
    Exception table:
       from    to  target type
          14    24    27   Class org/apache/zookeeper/KeeperException

  static {};
    Code:
       0: ldc           #3                  // class org/apache/hadoop/hbase/security/visibility/ZKVisibilityLabelWatcher
       2: invokestatic  #43                 // Method org/slf4j/LoggerFactory.getLogger:(Ljava/lang/Class;)Lorg/slf4j/Logger;
       5: putstatic     #22                 // Field LOG:Lorg/slf4j/Logger;
       8: return
}
