Compiled from "ZKWatcher.java"
public class org.apache.hadoop.hbase.zookeeper.ZKWatcher implements org.apache.zookeeper.Watcher,org.apache.hadoop.hbase.Abortable,java.io.Closeable {
  protected org.apache.hadoop.hbase.Abortable abortable;

  public org.apache.hadoop.hbase.zookeeper.ZKWatcher(org.apache.hadoop.conf.Configuration, java.lang.String, org.apache.hadoop.hbase.Abortable) throws org.apache.hadoop.hbase.ZooKeeperConnectionException, java.io.IOException;
    Code:
       0: aload_0
       1: aload_1
       2: aload_2
       3: aload_3
       4: iconst_0
       5: invokespecial #1                  // Method "<init>":(Lorg/apache/hadoop/conf/Configuration;Ljava/lang/String;Lorg/apache/hadoop/hbase/Abortable;Z)V
       8: return

  public org.apache.hadoop.hbase.zookeeper.ZKWatcher(org.apache.hadoop.conf.Configuration, java.lang.String, org.apache.hadoop.hbase.Abortable, boolean) throws java.io.IOException, org.apache.hadoop.hbase.ZooKeeperConnectionException;
    Code:
       0: aload_0
       1: aload_1
       2: aload_2
       3: aload_3
       4: iload         4
       6: iconst_0
       7: invokespecial #2                  // Method "<init>":(Lorg/apache/hadoop/conf/Configuration;Ljava/lang/String;Lorg/apache/hadoop/hbase/Abortable;ZZ)V
      10: return

  public org.apache.hadoop.hbase.zookeeper.ZKWatcher(org.apache.hadoop.conf.Configuration, java.lang.String, org.apache.hadoop.hbase.Abortable, boolean, boolean) throws java.io.IOException, org.apache.hadoop.hbase.ZooKeeperConnectionException;
    Code:
       0: aload_0
       1: invokespecial #3                  // Method java/lang/Object."<init>":()V
       4: aload_0
       5: iconst_0
       6: putfield      #4                  // Field aborted:Z
       9: aload_0
      10: new           #5                  // class java/util/concurrent/CopyOnWriteArrayList
      13: dup
      14: invokespecial #6                  // Method java/util/concurrent/CopyOnWriteArrayList."<init>":()V
      17: putfield      #7                  // Field listeners:Ljava/util/List;
      20: aload_0
      21: new           #8                  // class java/util/concurrent/CountDownLatch
      24: dup
      25: iconst_1
      26: invokespecial #9                  // Method java/util/concurrent/CountDownLatch."<init>":(I)V
      29: putfield      #10                 // Field saslLatch:Ljava/util/concurrent/CountDownLatch;
      32: aload_0
      33: aload_1
      34: putfield      #11                 // Field conf:Lorg/apache/hadoop/conf/Configuration;
      37: iload         5
      39: ifeq          97
      42: aload_1
      43: invokestatic  #12                 // Method org/apache/hadoop/hbase/zookeeper/ZKConfig.getClientZKQuorumServersString:(Lorg/apache/hadoop/conf/Configuration;)Ljava/lang/String;
      46: astore        6
      48: aload_1
      49: invokestatic  #13                 // Method org/apache/hadoop/hbase/zookeeper/ZKConfig.getZKQuorumServersString:(Lorg/apache/hadoop/conf/Configuration;)Ljava/lang/String;
      52: astore        7
      54: aload         6
      56: ifnull        88
      59: aload         6
      61: aload         7
      63: invokevirtual #14                 // Method java/lang/String.equals:(Ljava/lang/Object;)Z
      66: ifeq          79
      69: new           #15                 // class java/lang/IllegalArgumentException
      72: dup
      73: ldc           #16                 // String The quorum settings for client ZK should be different from those for server
      75: invokespecial #17                 // Method java/lang/IllegalArgumentException."<init>":(Ljava/lang/String;)V
      78: athrow
      79: aload_0
      80: aload         6
      82: putfield      #18                 // Field quorum:Ljava/lang/String;
      85: goto          94
      88: aload_0
      89: aload         7
      91: putfield      #18                 // Field quorum:Ljava/lang/String;
      94: goto          105
      97: aload_0
      98: aload_1
      99: invokestatic  #13                 // Method org/apache/hadoop/hbase/zookeeper/ZKConfig.getZKQuorumServersString:(Lorg/apache/hadoop/conf/Configuration;)Ljava/lang/String;
     102: putfield      #18                 // Field quorum:Ljava/lang/String;
     105: aload_0
     106: aload_2
     107: putfield      #19                 // Field prefix:Ljava/lang/String;
     110: aload_0
     111: new           #20                 // class java/lang/StringBuilder
     114: dup
     115: invokespecial #21                 // Method java/lang/StringBuilder."<init>":()V
     118: aload_2
     119: invokevirtual #22                 // Method java/lang/StringBuilder.append:(Ljava/lang/String;)Ljava/lang/StringBuilder;
     122: ldc           #23                 // String 0x0
     124: invokevirtual #22                 // Method java/lang/StringBuilder.append:(Ljava/lang/String;)Ljava/lang/StringBuilder;
     127: invokevirtual #24                 // Method java/lang/StringBuilder.toString:()Ljava/lang/String;
     130: putfield      #25                 // Field identifier:Ljava/lang/String;
     133: aload_0
     134: aload_3
     135: putfield      #26                 // Field abortable:Lorg/apache/hadoop/hbase/Abortable;
     138: aload_0
     139: new           #27                 // class org/apache/hadoop/hbase/zookeeper/ZNodePaths
     142: dup
     143: aload_1
     144: invokespecial #28                 // Method org/apache/hadoop/hbase/zookeeper/ZNodePaths."<init>":(Lorg/apache/hadoop/conf/Configuration;)V
     147: putfield      #29                 // Field znodePaths:Lorg/apache/hadoop/hbase/zookeeper/ZNodePaths;
     150: new           #30                 // class org/apache/hadoop/hbase/zookeeper/PendingWatcher
     153: dup
     154: invokespecial #31                 // Method org/apache/hadoop/hbase/zookeeper/PendingWatcher."<init>":()V
     157: astore        6
     159: aload_0
     160: aload_1
     161: aload_0
     162: getfield      #18                 // Field quorum:Ljava/lang/String;
     165: aload         6
     167: aload_2
     168: invokestatic  #32                 // Method org/apache/hadoop/hbase/zookeeper/ZKUtil.connect:(Lorg/apache/hadoop/conf/Configuration;Ljava/lang/String;Lorg/apache/zookeeper/Watcher;Ljava/lang/String;)Lorg/apache/hadoop/hbase/zookeeper/RecoverableZooKeeper;
     171: putfield      #33                 // Field recoverableZooKeeper:Lorg/apache/hadoop/hbase/zookeeper/RecoverableZooKeeper;
     174: aload         6
     176: aload_0
     177: invokevirtual #34                 // Method org/apache/hadoop/hbase/zookeeper/PendingWatcher.prepare:(Lorg/apache/zookeeper/Watcher;)V
     180: iload         4
     182: ifeq          245
     185: aload_0
     186: invokespecial #35                 // Method createBaseZNodes:()V
     189: goto          245
     192: astore        7
     194: aload_0
     195: getfield      #33                 // Field recoverableZooKeeper:Lorg/apache/hadoop/hbase/zookeeper/RecoverableZooKeeper;
     198: invokevirtual #37                 // Method org/apache/hadoop/hbase/zookeeper/RecoverableZooKeeper.close:()V
     201: goto          242
     204: astore        8
     206: getstatic     #39                 // Field LOG:Lorg/slf4j/Logger;
     209: new           #20                 // class java/lang/StringBuilder
     212: dup
     213: invokespecial #21                 // Method java/lang/StringBuilder."<init>":()V
     216: ldc           #40                 // String Encountered InterruptedException when closing
     218: invokevirtual #22                 // Method java/lang/StringBuilder.append:(Ljava/lang/String;)Ljava/lang/StringBuilder;
     221: aload_0
     222: getfield      #33                 // Field recoverableZooKeeper:Lorg/apache/hadoop/hbase/zookeeper/RecoverableZooKeeper;
     225: invokevirtual #41                 // Method java/lang/StringBuilder.append:(Ljava/lang/Object;)Ljava/lang/StringBuilder;
     228: invokevirtual #24                 // Method java/lang/StringBuilder.toString:()Ljava/lang/String;
     231: invokeinterface #42,  2           // InterfaceMethod org/slf4j/Logger.debug:(Ljava/lang/String;)V
     236: invokestatic  #43                 // Method java/lang/Thread.currentThread:()Ljava/lang/Thread;
     239: invokevirtual #44                 // Method java/lang/Thread.interrupt:()V
     242: aload         7
     244: athrow
     245: return
    Exception table:
       from    to  target type
         185   189   192   Class org/apache/hadoop/hbase/ZooKeeperConnectionException
         194   201   204   Class java/lang/InterruptedException

  public void checkAndSetZNodeAcls();
    Code:
       0: aload_0
       1: invokevirtual #59                 // Method getConfiguration:()Lorg/apache/hadoop/conf/Configuration;
       4: invokestatic  #60                 // Method org/apache/hadoop/hbase/zookeeper/ZKUtil.isSecureZooKeeper:(Lorg/apache/hadoop/conf/Configuration;)Z
       7: ifne          21
      10: getstatic     #39                 // Field LOG:Lorg/slf4j/Logger;
      13: ldc           #61                 // String not a secure deployment, proceeding
      15: invokeinterface #62,  2           // InterfaceMethod org/slf4j/Logger.info:(Ljava/lang/String;)V
      20: return
      21: aload_0
      22: getfield      #33                 // Field recoverableZooKeeper:Lorg/apache/hadoop/hbase/zookeeper/RecoverableZooKeeper;
      25: aload_0
      26: getfield      #29                 // Field znodePaths:Lorg/apache/hadoop/hbase/zookeeper/ZNodePaths;
      29: getfield      #45                 // Field org/apache/hadoop/hbase/zookeeper/ZNodePaths.baseZNode:Ljava/lang/String;
      32: new           #63                 // class org/apache/zookeeper/data/Stat
      35: dup
      36: invokespecial #64                 // Method org/apache/zookeeper/data/Stat."<init>":()V
      39: invokevirtual #65                 // Method org/apache/hadoop/hbase/zookeeper/RecoverableZooKeeper.getAcl:(Ljava/lang/String;Lorg/apache/zookeeper/data/Stat;)Ljava/util/List;
      42: astore_1
      43: aload_0
      44: aload_1
      45: invokespecial #66                 // Method isBaseZnodeAclSetup:(Ljava/util/List;)Z
      48: ifne          72
      51: getstatic     #39                 // Field LOG:Lorg/slf4j/Logger;
      54: ldc           #67                 // String setting znode ACLs
      56: invokeinterface #62,  2           // InterfaceMethod org/slf4j/Logger.info:(Ljava/lang/String;)V
      61: aload_0
      62: aload_0
      63: getfield      #29                 // Field znodePaths:Lorg/apache/hadoop/hbase/zookeeper/ZNodePaths;
      66: getfield      #45                 // Field org/apache/hadoop/hbase/zookeeper/ZNodePaths.baseZNode:Ljava/lang/String;
      69: invokespecial #68                 // Method setZnodeAclsRecursive:(Ljava/lang/String;)V
      72: goto          99
      75: astore_1
      76: return
      77: astore_1
      78: aload_0
      79: aload_1
      80: iconst_0
      81: invokevirtual #70                 // Method interruptedExceptionNoThrow:(Ljava/lang/InterruptedException;Z)V
      84: goto          99
      87: astore_1
      88: getstatic     #39                 // Field LOG:Lorg/slf4j/Logger;
      91: ldc           #72                 // String Received exception while checking and setting zookeeper ACLs
      93: aload_1
      94: invokeinterface #73,  3           // InterfaceMethod org/slf4j/Logger.warn:(Ljava/lang/String;Ljava/lang/Throwable;)V
      99: return
    Exception table:
       from    to  target type
          21    72    75   Class org/apache/zookeeper/KeeperException$NoNodeException
          21    72    77   Class java/lang/InterruptedException
          21    72    87   Class java/io/IOException
          21    72    87   Class org/apache/zookeeper/KeeperException

  public static boolean isSuperUserId(java.lang.String[], org.apache.zookeeper.data.Id);
    Code:
       0: aload_0
       1: astore_2
       2: aload_2
       3: arraylength
       4: istore_3
       5: iconst_0
       6: istore        4
       8: iload         4
      10: iload_3
      11: if_icmpge     54
      14: aload_2
      15: iload         4
      17: aaload
      18: astore        5
      20: aload         5
      22: invokestatic  #115                // Method org/apache/hadoop/hbase/AuthUtil.isGroupPrincipal:(Ljava/lang/String;)Z
      25: ifne          48
      28: new           #117                // class org/apache/zookeeper/data/Id
      31: dup
      32: ldc           #105                // String sasl
      34: aload         5
      36: invokespecial #118                // Method org/apache/zookeeper/data/Id."<init>":(Ljava/lang/String;Ljava/lang/String;)V
      39: aload_1
      40: invokevirtual #98                 // Method org/apache/zookeeper/data/Id.equals:(Ljava/lang/Object;)Z
      43: ifeq          48
      46: iconst_1
      47: ireturn
      48: iinc          4, 1
      51: goto          8
      54: iconst_0
      55: ireturn

  public java.lang.String toString();
    Code:
       0: new           #20                 // class java/lang/StringBuilder
       3: dup
       4: invokespecial #21                 // Method java/lang/StringBuilder."<init>":()V
       7: aload_0
       8: getfield      #25                 // Field identifier:Ljava/lang/String;
      11: invokevirtual #22                 // Method java/lang/StringBuilder.append:(Ljava/lang/String;)Ljava/lang/StringBuilder;
      14: ldc           #119                // String , quorum=
      16: invokevirtual #22                 // Method java/lang/StringBuilder.append:(Ljava/lang/String;)Ljava/lang/StringBuilder;
      19: aload_0
      20: getfield      #18                 // Field quorum:Ljava/lang/String;
      23: invokevirtual #22                 // Method java/lang/StringBuilder.append:(Ljava/lang/String;)Ljava/lang/StringBuilder;
      26: ldc           #120                // String , baseZNode=
      28: invokevirtual #22                 // Method java/lang/StringBuilder.append:(Ljava/lang/String;)Ljava/lang/StringBuilder;
      31: aload_0
      32: getfield      #29                 // Field znodePaths:Lorg/apache/hadoop/hbase/zookeeper/ZNodePaths;
      35: getfield      #45                 // Field org/apache/hadoop/hbase/zookeeper/ZNodePaths.baseZNode:Ljava/lang/String;
      38: invokevirtual #22                 // Method java/lang/StringBuilder.append:(Ljava/lang/String;)Ljava/lang/StringBuilder;
      41: invokevirtual #24                 // Method java/lang/StringBuilder.toString:()Ljava/lang/String;
      44: areturn

  public java.lang.String prefix(java.lang.String);
    Code:
       0: new           #20                 // class java/lang/StringBuilder
       3: dup
       4: invokespecial #21                 // Method java/lang/StringBuilder."<init>":()V
       7: aload_0
       8: invokevirtual #121                // Method toString:()Ljava/lang/String;
      11: invokevirtual #22                 // Method java/lang/StringBuilder.append:(Ljava/lang/String;)Ljava/lang/StringBuilder;
      14: ldc           #122                // String
      16: invokevirtual #22                 // Method java/lang/StringBuilder.append:(Ljava/lang/String;)Ljava/lang/StringBuilder;
      19: aload_1
      20: invokevirtual #22                 // Method java/lang/StringBuilder.append:(Ljava/lang/String;)Ljava/lang/StringBuilder;
      23: invokevirtual #24                 // Method java/lang/StringBuilder.toString:()Ljava/lang/String;
      26: areturn

  public java.util.List<java.lang.String> getMetaReplicaNodes() throws org.apache.zookeeper.KeeperException;
    Code:
       0: aload_0
       1: aload_0
       2: getfield      #29                 // Field znodePaths:Lorg/apache/hadoop/hbase/zookeeper/ZNodePaths;
       5: getfield      #45                 // Field org/apache/hadoop/hbase/zookeeper/ZNodePaths.baseZNode:Ljava/lang/String;
       8: invokestatic  #123                // Method org/apache/hadoop/hbase/zookeeper/ZKUtil.listChildrenNoWatch:(Lorg/apache/hadoop/hbase/zookeeper/ZKWatcher;Ljava/lang/String;)Ljava/util/List;
      11: astore_1
      12: new           #124                // class java/util/ArrayList
      15: dup
      16: iconst_2
      17: invokespecial #125                // Method java/util/ArrayList."<init>":(I)V
      20: astore_2
      21: aload_1
      22: ifnull        88
      25: aload_0
      26: getfield      #11                 // Field conf:Lorg/apache/hadoop/conf/Configuration;
      29: ldc           #126                // String zookeeper.znode.metaserver
      31: ldc           #127                // String meta-region-server
      33: invokevirtual #128                // Method org/apache/hadoop/conf/Configuration.get:(Ljava/lang/String;Ljava/lang/String;)Ljava/lang/String;
      36: astore_3
      37: aload_1
      38: invokeinterface #75,  1           // InterfaceMethod java/util/List.iterator:()Ljava/util/Iterator;
      43: astore        4
      45: aload         4
      47: invokeinterface #76,  1           // InterfaceMethod java/util/Iterator.hasNext:()Z
      52: ifeq          88
      55: aload         4
      57: invokeinterface #77,  1           // InterfaceMethod java/util/Iterator.next:()Ljava/lang/Object;
      62: checkcast     #78                 // class java/lang/String
      65: astore        5
      67: aload         5
      69: aload_3
      70: invokevirtual #129                // Method java/lang/String.startsWith:(Ljava/lang/String;)Z
      73: ifeq          85
      76: aload_2
      77: aload         5
      79: invokeinterface #130,  2          // InterfaceMethod java/util/List.add:(Ljava/lang/Object;)Z
      84: pop
      85: goto          45
      88: aload_2
      89: areturn

  public void registerListener(org.apache.hadoop.hbase.zookeeper.ZKListener);
    Code:
       0: aload_0
       1: getfield      #7                  // Field listeners:Ljava/util/List;
       4: aload_1
       5: invokeinterface #130,  2          // InterfaceMethod java/util/List.add:(Ljava/lang/Object;)Z
      10: pop
      11: return

  public void registerListenerFirst(org.apache.hadoop.hbase.zookeeper.ZKListener);
    Code:
       0: aload_0
       1: getfield      #7                  // Field listeners:Ljava/util/List;
       4: iconst_0
       5: aload_1
       6: invokeinterface #131,  3          // InterfaceMethod java/util/List.add:(ILjava/lang/Object;)V
      11: return

  public void unregisterListener(org.apache.hadoop.hbase.zookeeper.ZKListener);
    Code:
       0: aload_0
       1: getfield      #7                  // Field listeners:Ljava/util/List;
       4: aload_1
       5: invokeinterface #132,  2          // InterfaceMethod java/util/List.remove:(Ljava/lang/Object;)Z
      10: pop
      11: return

  public void unregisterAllListeners();
    Code:
       0: aload_0
       1: getfield      #7                  // Field listeners:Ljava/util/List;
       4: invokeinterface #133,  1          // InterfaceMethod java/util/List.clear:()V
       9: return

  public java.util.List<org.apache.hadoop.hbase.zookeeper.ZKListener> getListeners();
    Code:
       0: new           #124                // class java/util/ArrayList
       3: dup
       4: aload_0
       5: getfield      #7                  // Field listeners:Ljava/util/List;
       8: invokespecial #134                // Method java/util/ArrayList."<init>":(Ljava/util/Collection;)V
      11: areturn

  public int getNumberOfListeners();
    Code:
       0: aload_0
       1: getfield      #7                  // Field listeners:Ljava/util/List;
       4: invokeinterface #135,  1          // InterfaceMethod java/util/List.size:()I
       9: ireturn

  public org.apache.hadoop.hbase.zookeeper.RecoverableZooKeeper getRecoverableZooKeeper();
    Code:
       0: aload_0
       1: getfield      #33                 // Field recoverableZooKeeper:Lorg/apache/hadoop/hbase/zookeeper/RecoverableZooKeeper;
       4: areturn

  public void reconnectAfterExpiration() throws java.io.IOException, org.apache.zookeeper.KeeperException, java.lang.InterruptedException;
    Code:
       0: aload_0
       1: getfield      #33                 // Field recoverableZooKeeper:Lorg/apache/hadoop/hbase/zookeeper/RecoverableZooKeeper;
       4: invokevirtual #136                // Method org/apache/hadoop/hbase/zookeeper/RecoverableZooKeeper.reconnectAfterExpiration:()V
       7: return

  public java.lang.String getQuorum();
    Code:
       0: aload_0
       1: getfield      #18                 // Field quorum:Ljava/lang/String;
       4: areturn

  public org.apache.hadoop.hbase.zookeeper.ZNodePaths getZNodePaths();
    Code:
       0: aload_0
       1: getfield      #29                 // Field znodePaths:Lorg/apache/hadoop/hbase/zookeeper/ZNodePaths;
       4: areturn

  public void process(org.apache.zookeeper.WatchedEvent);
    Code:
       0: getstatic     #39                 // Field LOG:Lorg/slf4j/Logger;
       3: aload_0
       4: new           #20                 // class java/lang/StringBuilder
       7: dup
       8: invokespecial #21                 // Method java/lang/StringBuilder."<init>":()V
      11: ldc           #137                // String Received ZooKeeper Event, type=
      13: invokevirtual #22                 // Method java/lang/StringBuilder.append:(Ljava/lang/String;)Ljava/lang/StringBuilder;
      16: aload_1
      17: invokevirtual #138                // Method org/apache/zookeeper/WatchedEvent.getType:()Lorg/apache/zookeeper/Watcher$Event$EventType;
      20: invokevirtual #41                 // Method java/lang/StringBuilder.append:(Ljava/lang/Object;)Ljava/lang/StringBuilder;
      23: ldc           #139                // String , state=
      25: invokevirtual #22                 // Method java/lang/StringBuilder.append:(Ljava/lang/String;)Ljava/lang/StringBuilder;
      28: aload_1
      29: invokevirtual #140                // Method org/apache/zookeeper/WatchedEvent.getState:()Lorg/apache/zookeeper/Watcher$Event$KeeperState;
      32: invokevirtual #41                 // Method java/lang/StringBuilder.append:(Ljava/lang/Object;)Ljava/lang/StringBuilder;
      35: ldc           #141                // String , path=
      37: invokevirtual #22                 // Method java/lang/StringBuilder.append:(Ljava/lang/String;)Ljava/lang/StringBuilder;
      40: aload_1
      41: invokevirtual #142                // Method org/apache/zookeeper/WatchedEvent.getPath:()Ljava/lang/String;
      44: invokevirtual #22                 // Method java/lang/StringBuilder.append:(Ljava/lang/String;)Ljava/lang/StringBuilder;
      47: invokevirtual #24                 // Method java/lang/StringBuilder.toString:()Ljava/lang/String;
      50: invokevirtual #57                 // Method prefix:(Ljava/lang/String;)Ljava/lang/String;
      53: invokeinterface #42,  2           // InterfaceMethod org/slf4j/Logger.debug:(Ljava/lang/String;)V
      58: getstatic     #143                // Field org/apache/hadoop/hbase/zookeeper/ZKWatcher$1.$SwitchMap$org$apache$zookeeper$Watcher$Event$EventType:[I
      61: aload_1
      62: invokevirtual #138                // Method org/apache/zookeeper/WatchedEvent.getType:()Lorg/apache/zookeeper/Watcher$Event$EventType;
      65: invokevirtual #144                // Method org/apache/zookeeper/Watcher$Event$EventType.ordinal:()I
      68: iaload
      69: tableswitch   { // 1 to 5
                     1: 104
                     2: 112
                     3: 155
                     4: 198
                     5: 241
               default: 284
          }
     104: aload_0
     105: aload_1
     106: invokespecial #145                // Method connectionEvent:(Lorg/apache/zookeeper/WatchedEvent;)V
     109: goto          314
     112: aload_0
     113: getfield      #7                  // Field listeners:Ljava/util/List;
     116: invokeinterface #75,  1           // InterfaceMethod java/util/List.iterator:()Ljava/util/Iterator;
     121: astore_2
     122: aload_2
     123: invokeinterface #76,  1           // InterfaceMethod java/util/Iterator.hasNext:()Z
     128: ifeq          152
     131: aload_2
     132: invokeinterface #77,  1           // InterfaceMethod java/util/Iterator.next:()Ljava/lang/Object;
     137: checkcast     #146                // class org/apache/hadoop/hbase/zookeeper/ZKListener
     140: astore_3
     141: aload_3
     142: aload_1
     143: invokevirtual #142                // Method org/apache/zookeeper/WatchedEvent.getPath:()Ljava/lang/String;
     146: invokevirtual #147                // Method org/apache/hadoop/hbase/zookeeper/ZKListener.nodeCreated:(Ljava/lang/String;)V
     149: goto          122
     152: goto          314
     155: aload_0
     156: getfield      #7                  // Field listeners:Ljava/util/List;
     159: invokeinterface #75,  1           // InterfaceMethod java/util/List.iterator:()Ljava/util/Iterator;
     164: astore_2
     165: aload_2
     166: invokeinterface #76,  1           // InterfaceMethod java/util/Iterator.hasNext:()Z
     171: ifeq          195
     174: aload_2
     175: invokeinterface #77,  1           // InterfaceMethod java/util/Iterator.next:()Ljava/lang/Object;
     180: checkcast     #146                // class org/apache/hadoop/hbase/zookeeper/ZKListener
     183: astore_3
     184: aload_3
     185: aload_1
     186: invokevirtual #142                // Method org/apache/zookeeper/WatchedEvent.getPath:()Ljava/lang/String;
     189: invokevirtual #148                // Method org/apache/hadoop/hbase/zookeeper/ZKListener.nodeDeleted:(Ljava/lang/String;)V
     192: goto          165
     195: goto          314
     198: aload_0
     199: getfield      #7                  // Field listeners:Ljava/util/List;
     202: invokeinterface #75,  1           // InterfaceMethod java/util/List.iterator:()Ljava/util/Iterator;
     207: astore_2
     208: aload_2
     209: invokeinterface #76,  1           // InterfaceMethod java/util/Iterator.hasNext:()Z
     214: ifeq          238
     217: aload_2
     218: invokeinterface #77,  1           // InterfaceMethod java/util/Iterator.next:()Ljava/lang/Object;
     223: checkcast     #146                // class org/apache/hadoop/hbase/zookeeper/ZKListener
     226: astore_3
     227: aload_3
     228: aload_1
     229: invokevirtual #142                // Method org/apache/zookeeper/WatchedEvent.getPath:()Ljava/lang/String;
     232: invokevirtual #149                // Method org/apache/hadoop/hbase/zookeeper/ZKListener.nodeDataChanged:(Ljava/lang/String;)V
     235: goto          208
     238: goto          314
     241: aload_0
     242: getfield      #7                  // Field listeners:Ljava/util/List;
     245: invokeinterface #75,  1           // InterfaceMethod java/util/List.iterator:()Ljava/util/Iterator;
     250: astore_2
     251: aload_2
     252: invokeinterface #76,  1           // InterfaceMethod java/util/Iterator.hasNext:()Z
     257: ifeq          281
     260: aload_2
     261: invokeinterface #77,  1           // InterfaceMethod java/util/Iterator.next:()Ljava/lang/Object;
     266: checkcast     #146                // class org/apache/hadoop/hbase/zookeeper/ZKListener
     269: astore_3
     270: aload_3
     271: aload_1
     272: invokevirtual #142                // Method org/apache/zookeeper/WatchedEvent.getPath:()Ljava/lang/String;
     275: invokevirtual #150                // Method org/apache/hadoop/hbase/zookeeper/ZKListener.nodeChildrenChanged:(Ljava/lang/String;)V
     278: goto          251
     281: goto          314
     284: new           #151                // class java/lang/IllegalStateException
     287: dup
     288: new           #20                 // class java/lang/StringBuilder
     291: dup
     292: invokespecial #21                 // Method java/lang/StringBuilder."<init>":()V
     295: ldc           #152                // String Received event is not valid:
     297: invokevirtual #22                 // Method java/lang/StringBuilder.append:(Ljava/lang/String;)Ljava/lang/StringBuilder;
     300: aload_1
     301: invokevirtual #140                // Method org/apache/zookeeper/WatchedEvent.getState:()Lorg/apache/zookeeper/Watcher$Event$KeeperState;
     304: invokevirtual #41                 // Method java/lang/StringBuilder.append:(Ljava/lang/Object;)Ljava/lang/StringBuilder;
     307: invokevirtual #24                 // Method java/lang/StringBuilder.toString:()Ljava/lang/String;
     310: invokespecial #153                // Method java/lang/IllegalStateException."<init>":(Ljava/lang/String;)V
     313: athrow
     314: return

  public void sync(java.lang.String) throws org.apache.zookeeper.KeeperException;
    Code:
       0: aload_0
       1: getfield      #33                 // Field recoverableZooKeeper:Lorg/apache/hadoop/hbase/zookeeper/RecoverableZooKeeper;
       4: aload_1
       5: aconst_null
       6: aconst_null
       7: invokevirtual #165                // Method org/apache/hadoop/hbase/zookeeper/RecoverableZooKeeper.sync:(Ljava/lang/String;Lorg/apache/zookeeper/AsyncCallback$VoidCallback;Ljava/lang/Object;)V
      10: return

  public void keeperException(org.apache.zookeeper.KeeperException) throws org.apache.zookeeper.KeeperException;
    Code:
       0: getstatic     #39                 // Field LOG:Lorg/slf4j/Logger;
       3: aload_0
       4: ldc           #166                // String Received unexpected KeeperException, re-throwing exception
       6: invokevirtual #57                 // Method prefix:(Ljava/lang/String;)Ljava/lang/String;
       9: aload_1
      10: invokeinterface #167,  3          // InterfaceMethod org/slf4j/Logger.error:(Ljava/lang/String;Ljava/lang/Throwable;)V
      15: aload_1
      16: athrow

  public void interruptedException(java.lang.InterruptedException) throws org.apache.zookeeper.KeeperException;
    Code:
       0: aload_0
       1: aload_1
       2: iconst_1
       3: invokevirtual #70                 // Method interruptedExceptionNoThrow:(Ljava/lang/InterruptedException;Z)V
       6: new           #168                // class org/apache/zookeeper/KeeperException$SystemErrorException
       9: dup
      10: invokespecial #169                // Method org/apache/zookeeper/KeeperException$SystemErrorException."<init>":()V
      13: astore_2
      14: aload_2
      15: aload_1
      16: invokevirtual #170                // Method org/apache/zookeeper/KeeperException.initCause:(Ljava/lang/Throwable;)Ljava/lang/Throwable;
      19: pop
      20: aload_2
      21: athrow

  public void interruptedExceptionNoThrow(java.lang.InterruptedException, boolean);
    Code:
       0: getstatic     #39                 // Field LOG:Lorg/slf4j/Logger;
       3: aload_0
       4: new           #20                 // class java/lang/StringBuilder
       7: dup
       8: invokespecial #21                 // Method java/lang/StringBuilder."<init>":()V
      11: ldc           #171                // String Received InterruptedException, will interrupt current thread
      13: invokevirtual #22                 // Method java/lang/StringBuilder.append:(Ljava/lang/String;)Ljava/lang/StringBuilder;
      16: iload_2
      17: ifeq          25
      20: ldc           #172                // String  and rethrow a SystemErrorException
      22: goto          27
      25: ldc           #173                // String
      27: invokevirtual #22                 // Method java/lang/StringBuilder.append:(Ljava/lang/String;)Ljava/lang/StringBuilder;
      30: invokevirtual #24                 // Method java/lang/StringBuilder.toString:()Ljava/lang/String;
      33: invokevirtual #57                 // Method prefix:(Ljava/lang/String;)Ljava/lang/String;
      36: aload_1
      37: invokeinterface #174,  3          // InterfaceMethod org/slf4j/Logger.debug:(Ljava/lang/String;Ljava/lang/Throwable;)V
      42: invokestatic  #43                 // Method java/lang/Thread.currentThread:()Ljava/lang/Thread;
      45: invokevirtual #44                 // Method java/lang/Thread.interrupt:()V
      48: return

  public void close();
    Code:
       0: aload_0
       1: getfield      #33                 // Field recoverableZooKeeper:Lorg/apache/hadoop/hbase/zookeeper/RecoverableZooKeeper;
       4: invokevirtual #37                 // Method org/apache/hadoop/hbase/zookeeper/RecoverableZooKeeper.close:()V
       7: goto          17
      10: astore_1
      11: invokestatic  #43                 // Method java/lang/Thread.currentThread:()Ljava/lang/Thread;
      14: invokevirtual #44                 // Method java/lang/Thread.interrupt:()V
      17: return
    Exception table:
       from    to  target type
           0     7    10   Class java/lang/InterruptedException

  public org.apache.hadoop.conf.Configuration getConfiguration();
    Code:
       0: aload_0
       1: getfield      #11                 // Field conf:Lorg/apache/hadoop/conf/Configuration;
       4: areturn

  public void abort(java.lang.String, java.lang.Throwable);
    Code:
       0: aload_0
       1: getfield      #26                 // Field abortable:Lorg/apache/hadoop/hbase/Abortable;
       4: ifnull        21
       7: aload_0
       8: getfield      #26                 // Field abortable:Lorg/apache/hadoop/hbase/Abortable;
      11: aload_1
      12: aload_2
      13: invokeinterface #164,  3          // InterfaceMethod org/apache/hadoop/hbase/Abortable.abort:(Ljava/lang/String;Ljava/lang/Throwable;)V
      18: goto          26
      21: aload_0
      22: iconst_1
      23: putfield      #4                  // Field aborted:Z
      26: return

  public boolean isAborted();
    Code:
       0: aload_0
       1: getfield      #26                 // Field abortable:Lorg/apache/hadoop/hbase/Abortable;
       4: ifnonnull     14
       7: aload_0
       8: getfield      #4                  // Field aborted:Z
      11: goto          23
      14: aload_0
      15: getfield      #26                 // Field abortable:Lorg/apache/hadoop/hbase/Abortable;
      18: invokeinterface #175,  1          // InterfaceMethod org/apache/hadoop/hbase/Abortable.isAborted:()Z
      23: ireturn

  static {};
    Code:
       0: ldc           #176                // class org/apache/hadoop/hbase/zookeeper/ZKWatcher
       2: invokestatic  #177                // Method org/slf4j/LoggerFactory.getLogger:(Ljava/lang/Class;)Lorg/slf4j/Logger;
       5: putstatic     #39                 // Field LOG:Lorg/slf4j/Logger;
       8: ldc           #178                // String ([^/@]*)(/([^/@]*))?@([^/@]*)
      10: invokestatic  #179                // Method java/util/regex/Pattern.compile:(Ljava/lang/String;)Ljava/util/regex/Pattern;
      13: putstatic     #108                // Field NAME_PATTERN:Ljava/util/regex/Pattern;
      16: return
}
