Compiled from "ZNodePaths.java"
public class org.apache.hadoop.hbase.zookeeper.ZNodePaths {
  public static final char ZNODE_PATH_SEPARATOR;

  public static final java.lang.String META_ZNODE_PREFIX;

  public final java.lang.String baseZNode;

  public final java.lang.String metaZNodePrefix;

  public final org.apache.hbase.thirdparty.com.google.common.collect.ImmutableMap<java.lang.Integer, java.lang.String> metaReplicaZNodes;

  public final java.lang.String rsZNode;

  public final java.lang.String drainingZNode;

  public final java.lang.String masterAddressZNode;

  public final java.lang.String backupMasterAddressesZNode;

  public final java.lang.String clusterStateZNode;

  public final java.lang.String tableZNode;

  public final java.lang.String clusterIdZNode;

  public final java.lang.String splitLogZNode;

  public final java.lang.String balancerZNode;

  public final java.lang.String regionNormalizerZNode;

  public final java.lang.String switchZNode;

  public final java.lang.String tableLockZNode;

  public final java.lang.String namespaceZNode;

  public final java.lang.String masterMaintZNode;

  public final java.lang.String replicationZNode;

  public final java.lang.String peersZNode;

  public final java.lang.String queuesZNode;

  public final java.lang.String hfileRefsZNode;

  public org.apache.hadoop.hbase.zookeeper.ZNodePaths(org.apache.hadoop.conf.Configuration);
    Code:
       0: aload_0
       1: invokespecial #3                  // Method java/lang/Object."<init>":()V
       4: aload_0
       5: aload_1
       6: ldc           #4                  // String zookeeper.znode.parent
       8: ldc           #5                  // String /hbase
      10: invokevirtual #6                  // Method org/apache/hadoop/conf/Configuration.get:(Ljava/lang/String;Ljava/lang/String;)Ljava/lang/String;
      13: putfield      #7                  // Field baseZNode:Ljava/lang/String;
      16: invokestatic  #8                  // Method org/apache/hbase/thirdparty/com/google/common/collect/ImmutableMap.builder:()Lorg/apache/hbase/thirdparty/com/google/common/collect/ImmutableMap$Builder;
      19: astore_2
      20: aload_0
      21: aload_1
      22: ldc           #9                  // String zookeeper.znode.metaserver
      24: ldc           #11                 // String meta-region-server
      26: invokevirtual #6                  // Method org/apache/hadoop/conf/Configuration.get:(Ljava/lang/String;Ljava/lang/String;)Ljava/lang/String;
      29: putfield      #12                 // Field metaZNodePrefix:Ljava/lang/String;
      32: aload_0
      33: getfield      #7                  // Field baseZNode:Ljava/lang/String;
      36: aload_0
      37: getfield      #12                 // Field metaZNodePrefix:Ljava/lang/String;
      40: invokestatic  #13                 // Method joinZNode:(Ljava/lang/String;Ljava/lang/String;)Ljava/lang/String;
      43: astore_3
      44: aload_2
      45: iconst_0
      46: invokestatic  #14                 // Method java/lang/Integer.valueOf:(I)Ljava/lang/Integer;
      49: aload_3
      50: invokevirtual #15                 // Method org/apache/hbase/thirdparty/com/google/common/collect/ImmutableMap$Builder.put:(Ljava/lang/Object;Ljava/lang/Object;)Lorg/apache/hbase/thirdparty/com/google/common/collect/ImmutableMap$Builder;
      53: pop
      54: aload_1
      55: ldc           #16                 // String hbase.meta.replica.count
      57: iconst_1
      58: invokevirtual #17                 // Method org/apache/hadoop/conf/Configuration.getInt:(Ljava/lang/String;I)I
      61: istore        4
      63: iconst_1
      64: iload         4
      66: invokestatic  #18                 // InterfaceMethod java/util/stream/IntStream.range:(II)Ljava/util/stream/IntStream;
      69: aload_2
      70: aload_3
      71: invokedynamic #19,  0             // InvokeDynamic #0:accept:(Lorg/apache/hbase/thirdparty/com/google/common/collect/ImmutableMap$Builder;Ljava/lang/String;)Ljava/util/function/IntConsumer;
      76: invokeinterface #20,  2           // InterfaceMethod java/util/stream/IntStream.forEachOrdered:(Ljava/util/function/IntConsumer;)V
      81: aload_0
      82: aload_2
      83: invokevirtual #21                 // Method org/apache/hbase/thirdparty/com/google/common/collect/ImmutableMap$Builder.build:()Lorg/apache/hbase/thirdparty/com/google/common/collect/ImmutableMap;
      86: putfield      #22                 // Field metaReplicaZNodes:Lorg/apache/hbase/thirdparty/com/google/common/collect/ImmutableMap;
      89: aload_0
      90: aload_0
      91: getfield      #7                  // Field baseZNode:Ljava/lang/String;
      94: aload_1
      95: ldc           #23                 // String zookeeper.znode.rs
      97: ldc           #24                 // String rs
      99: invokevirtual #6                  // Method org/apache/hadoop/conf/Configuration.get:(Ljava/lang/String;Ljava/lang/String;)Ljava/lang/String;
     102: invokestatic  #13                 // Method joinZNode:(Ljava/lang/String;Ljava/lang/String;)Ljava/lang/String;
     105: putfield      #25                 // Field rsZNode:Ljava/lang/String;
     108: aload_0
     109: aload_0
     110: getfield      #7                  // Field baseZNode:Ljava/lang/String;
     113: aload_1
     114: ldc           #26                 // String zookeeper.znode.draining.rs
     116: ldc           #27                 // String draining
     118: invokevirtual #6                  // Method org/apache/hadoop/conf/Configuration.get:(Ljava/lang/String;Ljava/lang/String;)Ljava/lang/String;
     121: invokestatic  #13                 // Method joinZNode:(Ljava/lang/String;Ljava/lang/String;)Ljava/lang/String;
     124: putfield      #28                 // Field drainingZNode:Ljava/lang/String;
     127: aload_0
     128: aload_0
     129: getfield      #7                  // Field baseZNode:Ljava/lang/String;
     132: aload_1
     133: ldc           #29                 // String zookeeper.znode.master
     135: ldc           #30                 // String master
     137: invokevirtual #6                  // Method org/apache/hadoop/conf/Configuration.get:(Ljava/lang/String;Ljava/lang/String;)Ljava/lang/String;
     140: invokestatic  #13                 // Method joinZNode:(Ljava/lang/String;Ljava/lang/String;)Ljava/lang/String;
     143: putfield      #31                 // Field masterAddressZNode:Ljava/lang/String;
     146: aload_0
     147: aload_0
     148: getfield      #7                  // Field baseZNode:Ljava/lang/String;
     151: aload_1
     152: ldc           #32                 // String zookeeper.znode.backup.masters
     154: ldc           #33                 // String backup-masters
     156: invokevirtual #6                  // Method org/apache/hadoop/conf/Configuration.get:(Ljava/lang/String;Ljava/lang/String;)Ljava/lang/String;
     159: invokestatic  #13                 // Method joinZNode:(Ljava/lang/String;Ljava/lang/String;)Ljava/lang/String;
     162: putfield      #34                 // Field backupMasterAddressesZNode:Ljava/lang/String;
     165: aload_0
     166: aload_0
     167: getfield      #7                  // Field baseZNode:Ljava/lang/String;
     170: aload_1
     171: ldc           #35                 // String zookeeper.znode.state
     173: ldc           #36                 // String running
     175: invokevirtual #6                  // Method org/apache/hadoop/conf/Configuration.get:(Ljava/lang/String;Ljava/lang/String;)Ljava/lang/String;
     178: invokestatic  #13                 // Method joinZNode:(Ljava/lang/String;Ljava/lang/String;)Ljava/lang/String;
     181: putfield      #37                 // Field clusterStateZNode:Ljava/lang/String;
     184: aload_0
     185: aload_0
     186: getfield      #7                  // Field baseZNode:Ljava/lang/String;
     189: aload_1
     190: ldc           #38                 // String zookeeper.znode.tableEnableDisable
     192: ldc           #39                 // String table
     194: invokevirtual #6                  // Method org/apache/hadoop/conf/Configuration.get:(Ljava/lang/String;Ljava/lang/String;)Ljava/lang/String;
     197: invokestatic  #13                 // Method joinZNode:(Ljava/lang/String;Ljava/lang/String;)Ljava/lang/String;
     200: putfield      #40                 // Field tableZNode:Ljava/lang/String;
     203: aload_0
     204: aload_0
     205: getfield      #7                  // Field baseZNode:Ljava/lang/String;
     208: aload_1
     209: ldc           #41                 // String zookeeper.znode.clusterId
     211: ldc           #42                 // String hbaseid
     213: invokevirtual #6                  // Method org/apache/hadoop/conf/Configuration.get:(Ljava/lang/String;Ljava/lang/String;)Ljava/lang/String;
     216: invokestatic  #13                 // Method joinZNode:(Ljava/lang/String;Ljava/lang/String;)Ljava/lang/String;
     219: putfield      #43                 // Field clusterIdZNode:Ljava/lang/String;
     222: aload_0
     223: aload_0
     224: getfield      #7                  // Field baseZNode:Ljava/lang/String;
     227: aload_1
     228: ldc           #44                 // String zookeeper.znode.splitlog
     230: ldc           #45                 // String splitWAL
     232: invokevirtual #6                  // Method org/apache/hadoop/conf/Configuration.get:(Ljava/lang/String;Ljava/lang/String;)Ljava/lang/String;
     235: invokestatic  #13                 // Method joinZNode:(Ljava/lang/String;Ljava/lang/String;)Ljava/lang/String;
     238: putfield      #46                 // Field splitLogZNode:Ljava/lang/String;
     241: aload_0
     242: aload_0
     243: getfield      #7                  // Field baseZNode:Ljava/lang/String;
     246: aload_1
     247: ldc           #47                 // String zookeeper.znode.balancer
     249: ldc           #48                 // String balancer
     251: invokevirtual #6                  // Method org/apache/hadoop/conf/Configuration.get:(Ljava/lang/String;Ljava/lang/String;)Ljava/lang/String;
     254: invokestatic  #13                 // Method joinZNode:(Ljava/lang/String;Ljava/lang/String;)Ljava/lang/String;
     257: putfield      #49                 // Field balancerZNode:Ljava/lang/String;
     260: aload_0
     261: aload_0
     262: getfield      #7                  // Field baseZNode:Ljava/lang/String;
     265: aload_1
     266: ldc           #50                 // String zookeeper.znode.regionNormalizer
     268: ldc           #51                 // String normalizer
     270: invokevirtual #6                  // Method org/apache/hadoop/conf/Configuration.get:(Ljava/lang/String;Ljava/lang/String;)Ljava/lang/String;
     273: invokestatic  #13                 // Method joinZNode:(Ljava/lang/String;Ljava/lang/String;)Ljava/lang/String;
     276: putfield      #52                 // Field regionNormalizerZNode:Ljava/lang/String;
     279: aload_0
     280: aload_0
     281: getfield      #7                  // Field baseZNode:Ljava/lang/String;
     284: aload_1
     285: ldc           #53                 // String zookeeper.znode.switch
     287: ldc           #54                 // String switch
     289: invokevirtual #6                  // Method org/apache/hadoop/conf/Configuration.get:(Ljava/lang/String;Ljava/lang/String;)Ljava/lang/String;
     292: invokestatic  #13                 // Method joinZNode:(Ljava/lang/String;Ljava/lang/String;)Ljava/lang/String;
     295: putfield      #55                 // Field switchZNode:Ljava/lang/String;
     298: aload_0
     299: aload_0
     300: getfield      #7                  // Field baseZNode:Ljava/lang/String;
     303: aload_1
     304: ldc           #56                 // String zookeeper.znode.tableLock
     306: ldc           #57                 // String table-lock
     308: invokevirtual #6                  // Method org/apache/hadoop/conf/Configuration.get:(Ljava/lang/String;Ljava/lang/String;)Ljava/lang/String;
     311: invokestatic  #13                 // Method joinZNode:(Ljava/lang/String;Ljava/lang/String;)Ljava/lang/String;
     314: putfield      #58                 // Field tableLockZNode:Ljava/lang/String;
     317: aload_0
     318: aload_0
     319: getfield      #7                  // Field baseZNode:Ljava/lang/String;
     322: aload_1
     323: ldc           #59                 // String zookeeper.znode.namespace
     325: ldc           #60                 // String namespace
     327: invokevirtual #6                  // Method org/apache/hadoop/conf/Configuration.get:(Ljava/lang/String;Ljava/lang/String;)Ljava/lang/String;
     330: invokestatic  #13                 // Method joinZNode:(Ljava/lang/String;Ljava/lang/String;)Ljava/lang/String;
     333: putfield      #61                 // Field namespaceZNode:Ljava/lang/String;
     336: aload_0
     337: aload_0
     338: getfield      #7                  // Field baseZNode:Ljava/lang/String;
     341: aload_1
     342: ldc           #62                 // String zookeeper.znode.masterMaintenance
     344: ldc           #63                 // String master-maintenance
     346: invokevirtual #6                  // Method org/apache/hadoop/conf/Configuration.get:(Ljava/lang/String;Ljava/lang/String;)Ljava/lang/String;
     349: invokestatic  #13                 // Method joinZNode:(Ljava/lang/String;Ljava/lang/String;)Ljava/lang/String;
     352: putfield      #64                 // Field masterMaintZNode:Ljava/lang/String;
     355: aload_0
     356: aload_0
     357: getfield      #7                  // Field baseZNode:Ljava/lang/String;
     360: aload_1
     361: ldc           #65                 // String zookeeper.znode.replication
     363: ldc           #66                 // String replication
     365: invokevirtual #6                  // Method org/apache/hadoop/conf/Configuration.get:(Ljava/lang/String;Ljava/lang/String;)Ljava/lang/String;
     368: invokestatic  #13                 // Method joinZNode:(Ljava/lang/String;Ljava/lang/String;)Ljava/lang/String;
     371: putfield      #67                 // Field replicationZNode:Ljava/lang/String;
     374: aload_0
     375: aload_0
     376: getfield      #67                 // Field replicationZNode:Ljava/lang/String;
     379: aload_1
     380: ldc           #68                 // String zookeeper.znode.replication.peers
     382: ldc           #69                 // String peers
     384: invokevirtual #6                  // Method org/apache/hadoop/conf/Configuration.get:(Ljava/lang/String;Ljava/lang/String;)Ljava/lang/String;
     387: invokestatic  #13                 // Method joinZNode:(Ljava/lang/String;Ljava/lang/String;)Ljava/lang/String;
     390: putfield      #70                 // Field peersZNode:Ljava/lang/String;
     393: aload_0
     394: aload_0
     395: getfield      #67                 // Field replicationZNode:Ljava/lang/String;
     398: aload_1
     399: ldc           #71                 // String zookeeper.znode.replication.rs
     401: ldc           #24                 // String rs
     403: invokevirtual #6                  // Method org/apache/hadoop/conf/Configuration.get:(Ljava/lang/String;Ljava/lang/String;)Ljava/lang/String;
     406: invokestatic  #13                 // Method joinZNode:(Ljava/lang/String;Ljava/lang/String;)Ljava/lang/String;
     409: putfield      #72                 // Field queuesZNode:Ljava/lang/String;
     412: aload_0
     413: aload_0
     414: getfield      #67                 // Field replicationZNode:Ljava/lang/String;
     417: aload_1
     418: ldc           #73                 // String zookeeper.znode.replication.hfile.refs
     420: ldc           #74                 // String hfile-refs
     422: invokevirtual #6                  // Method org/apache/hadoop/conf/Configuration.get:(Ljava/lang/String;Ljava/lang/String;)Ljava/lang/String;
     425: invokestatic  #13                 // Method joinZNode:(Ljava/lang/String;Ljava/lang/String;)Ljava/lang/String;
     428: putfield      #75                 // Field hfileRefsZNode:Ljava/lang/String;
     431: return

  public java.lang.String toString();
    Code:
       0: new           #76                 // class java/lang/StringBuilder
       3: dup
       4: invokespecial #77                 // Method java/lang/StringBuilder."<init>":()V
       7: ldc           #78                 // String ZNodePaths [baseZNode=
       9: invokevirtual #79                 // Method java/lang/StringBuilder.append:(Ljava/lang/String;)Ljava/lang/StringBuilder;
      12: aload_0
      13: getfield      #7                  // Field baseZNode:Ljava/lang/String;
      16: invokevirtual #79                 // Method java/lang/StringBuilder.append:(Ljava/lang/String;)Ljava/lang/StringBuilder;
      19: ldc           #80                 // String , metaReplicaZNodes=
      21: invokevirtual #79                 // Method java/lang/StringBuilder.append:(Ljava/lang/String;)Ljava/lang/StringBuilder;
      24: aload_0
      25: getfield      #22                 // Field metaReplicaZNodes:Lorg/apache/hbase/thirdparty/com/google/common/collect/ImmutableMap;
      28: invokevirtual #81                 // Method java/lang/StringBuilder.append:(Ljava/lang/Object;)Ljava/lang/StringBuilder;
      31: ldc           #82                 // String , rsZNode=
      33: invokevirtual #79                 // Method java/lang/StringBuilder.append:(Ljava/lang/String;)Ljava/lang/StringBuilder;
      36: aload_0
      37: getfield      #25                 // Field rsZNode:Ljava/lang/String;
      40: invokevirtual #79                 // Method java/lang/StringBuilder.append:(Ljava/lang/String;)Ljava/lang/StringBuilder;
      43: ldc           #83                 // String , drainingZNode=
      45: invokevirtual #79                 // Method java/lang/StringBuilder.append:(Ljava/lang/String;)Ljava/lang/StringBuilder;
      48: aload_0
      49: getfield      #28                 // Field drainingZNode:Ljava/lang/String;
      52: invokevirtual #79                 // Method java/lang/StringBuilder.append:(Ljava/lang/String;)Ljava/lang/StringBuilder;
      55: ldc           #84                 // String , masterAddressZNode=
      57: invokevirtual #79                 // Method java/lang/StringBuilder.append:(Ljava/lang/String;)Ljava/lang/StringBuilder;
      60: aload_0
      61: getfield      #31                 // Field masterAddressZNode:Ljava/lang/String;
      64: invokevirtual #79                 // Method java/lang/StringBuilder.append:(Ljava/lang/String;)Ljava/lang/StringBuilder;
      67: ldc           #85                 // String , backupMasterAddressesZNode=
      69: invokevirtual #79                 // Method java/lang/StringBuilder.append:(Ljava/lang/String;)Ljava/lang/StringBuilder;
      72: aload_0
      73: getfield      #34                 // Field backupMasterAddressesZNode:Ljava/lang/String;
      76: invokevirtual #79                 // Method java/lang/StringBuilder.append:(Ljava/lang/String;)Ljava/lang/StringBuilder;
      79: ldc           #86                 // String , clusterStateZNode=
      81: invokevirtual #79                 // Method java/lang/StringBuilder.append:(Ljava/lang/String;)Ljava/lang/StringBuilder;
      84: aload_0
      85: getfield      #37                 // Field clusterStateZNode:Ljava/lang/String;
      88: invokevirtual #79                 // Method java/lang/StringBuilder.append:(Ljava/lang/String;)Ljava/lang/StringBuilder;
      91: ldc           #87                 // String , tableZNode=
      93: invokevirtual #79                 // Method java/lang/StringBuilder.append:(Ljava/lang/String;)Ljava/lang/StringBuilder;
      96: aload_0
      97: getfield      #40                 // Field tableZNode:Ljava/lang/String;
     100: invokevirtual #79                 // Method java/lang/StringBuilder.append:(Ljava/lang/String;)Ljava/lang/StringBuilder;
     103: ldc           #88                 // String , clusterIdZNode=
     105: invokevirtual #79                 // Method java/lang/StringBuilder.append:(Ljava/lang/String;)Ljava/lang/StringBuilder;
     108: aload_0
     109: getfield      #43                 // Field clusterIdZNode:Ljava/lang/String;
     112: invokevirtual #79                 // Method java/lang/StringBuilder.append:(Ljava/lang/String;)Ljava/lang/StringBuilder;
     115: ldc           #89                 // String , splitLogZNode=
     117: invokevirtual #79                 // Method java/lang/StringBuilder.append:(Ljava/lang/String;)Ljava/lang/StringBuilder;
     120: aload_0
     121: getfield      #46                 // Field splitLogZNode:Ljava/lang/String;
     124: invokevirtual #79                 // Method java/lang/StringBuilder.append:(Ljava/lang/String;)Ljava/lang/StringBuilder;
     127: ldc           #90                 // String , balancerZNode=
     129: invokevirtual #79                 // Method java/lang/StringBuilder.append:(Ljava/lang/String;)Ljava/lang/StringBuilder;
     132: aload_0
     133: getfield      #49                 // Field balancerZNode:Ljava/lang/String;
     136: invokevirtual #79                 // Method java/lang/StringBuilder.append:(Ljava/lang/String;)Ljava/lang/StringBuilder;
     139: ldc           #91                 // String , regionNormalizerZNode=
     141: invokevirtual #79                 // Method java/lang/StringBuilder.append:(Ljava/lang/String;)Ljava/lang/StringBuilder;
     144: aload_0
     145: getfield      #52                 // Field regionNormalizerZNode:Ljava/lang/String;
     148: invokevirtual #79                 // Method java/lang/StringBuilder.append:(Ljava/lang/String;)Ljava/lang/StringBuilder;
     151: ldc           #92                 // String , switchZNode=
     153: invokevirtual #79                 // Method java/lang/StringBuilder.append:(Ljava/lang/String;)Ljava/lang/StringBuilder;
     156: aload_0
     157: getfield      #55                 // Field switchZNode:Ljava/lang/String;
     160: invokevirtual #79                 // Method java/lang/StringBuilder.append:(Ljava/lang/String;)Ljava/lang/StringBuilder;
     163: ldc           #93                 // String , tableLockZNode=
     165: invokevirtual #79                 // Method java/lang/StringBuilder.append:(Ljava/lang/String;)Ljava/lang/StringBuilder;
     168: aload_0
     169: getfield      #58                 // Field tableLockZNode:Ljava/lang/String;
     172: invokevirtual #79                 // Method java/lang/StringBuilder.append:(Ljava/lang/String;)Ljava/lang/StringBuilder;
     175: ldc           #94                 // String , namespaceZNode=
     177: invokevirtual #79                 // Method java/lang/StringBuilder.append:(Ljava/lang/String;)Ljava/lang/StringBuilder;
     180: aload_0
     181: getfield      #61                 // Field namespaceZNode:Ljava/lang/String;
     184: invokevirtual #79                 // Method java/lang/StringBuilder.append:(Ljava/lang/String;)Ljava/lang/StringBuilder;
     187: ldc           #95                 // String , masterMaintZNode=
     189: invokevirtual #79                 // Method java/lang/StringBuilder.append:(Ljava/lang/String;)Ljava/lang/StringBuilder;
     192: aload_0
     193: getfield      #64                 // Field masterMaintZNode:Ljava/lang/String;
     196: invokevirtual #79                 // Method java/lang/StringBuilder.append:(Ljava/lang/String;)Ljava/lang/StringBuilder;
     199: ldc           #96                 // String , replicationZNode=
     201: invokevirtual #79                 // Method java/lang/StringBuilder.append:(Ljava/lang/String;)Ljava/lang/StringBuilder;
     204: aload_0
     205: getfield      #67                 // Field replicationZNode:Ljava/lang/String;
     208: invokevirtual #79                 // Method java/lang/StringBuilder.append:(Ljava/lang/String;)Ljava/lang/StringBuilder;
     211: ldc           #97                 // String , peersZNode=
     213: invokevirtual #79                 // Method java/lang/StringBuilder.append:(Ljava/lang/String;)Ljava/lang/StringBuilder;
     216: aload_0
     217: getfield      #70                 // Field peersZNode:Ljava/lang/String;
     220: invokevirtual #79                 // Method java/lang/StringBuilder.append:(Ljava/lang/String;)Ljava/lang/StringBuilder;
     223: ldc           #98                 // String , queuesZNode=
     225: invokevirtual #79                 // Method java/lang/StringBuilder.append:(Ljava/lang/String;)Ljava/lang/StringBuilder;
     228: aload_0
     229: getfield      #72                 // Field queuesZNode:Ljava/lang/String;
     232: invokevirtual #79                 // Method java/lang/StringBuilder.append:(Ljava/lang/String;)Ljava/lang/StringBuilder;
     235: ldc           #99                 // String , hfileRefsZNode=
     237: invokevirtual #79                 // Method java/lang/StringBuilder.append:(Ljava/lang/String;)Ljava/lang/StringBuilder;
     240: aload_0
     241: getfield      #75                 // Field hfileRefsZNode:Ljava/lang/String;
     244: invokevirtual #79                 // Method java/lang/StringBuilder.append:(Ljava/lang/String;)Ljava/lang/StringBuilder;
     247: ldc           #100                // String ]
     249: invokevirtual #79                 // Method java/lang/StringBuilder.append:(Ljava/lang/String;)Ljava/lang/StringBuilder;
     252: invokevirtual #101                // Method java/lang/StringBuilder.toString:()Ljava/lang/String;
     255: areturn

  public boolean isAnyMetaReplicaZNode(java.lang.String);
    Code:
       0: aload_0
       1: getfield      #22                 // Field metaReplicaZNodes:Lorg/apache/hbase/thirdparty/com/google/common/collect/ImmutableMap;
       4: aload_1
       5: invokevirtual #102                // Method org/apache/hbase/thirdparty/com/google/common/collect/ImmutableMap.containsValue:(Ljava/lang/Object;)Z
       8: ifeq          13
      11: iconst_1
      12: ireturn
      13: iconst_0
      14: ireturn

  public java.lang.String getZNodeForReplica(int);
    Code:
       0: aload_0
       1: getfield      #22                 // Field metaReplicaZNodes:Lorg/apache/hbase/thirdparty/com/google/common/collect/ImmutableMap;
       4: iload_1
       5: invokestatic  #14                 // Method java/lang/Integer.valueOf:(I)Ljava/lang/Integer;
       8: invokevirtual #103                // Method org/apache/hbase/thirdparty/com/google/common/collect/ImmutableMap.get:(Ljava/lang/Object;)Ljava/lang/Object;
      11: invokestatic  #104                // Method java/util/Optional.ofNullable:(Ljava/lang/Object;)Ljava/util/Optional;
      14: aload_0
      15: iload_1
      16: invokedynamic #105,  0            // InvokeDynamic #1:get:(Lorg/apache/hadoop/hbase/zookeeper/ZNodePaths;I)Ljava/util/function/Supplier;
      21: invokevirtual #106                // Method java/util/Optional.orElseGet:(Ljava/util/function/Supplier;)Ljava/lang/Object;
      24: checkcast     #107                // class java/lang/String
      27: areturn

  public int getMetaReplicaIdFromZnode(java.lang.String);
    Code:
       0: aload_1
       1: aload_0
       2: getfield      #12                 // Field metaZNodePrefix:Ljava/lang/String;
       5: invokevirtual #108                // Method java/lang/String.equals:(Ljava/lang/Object;)Z
       8: ifeq          13
      11: iconst_0
      12: ireturn
      13: aload_1
      14: aload_0
      15: getfield      #12                 // Field metaZNodePrefix:Ljava/lang/String;
      18: invokevirtual #109                // Method java/lang/String.length:()I
      21: iconst_1
      22: iadd
      23: invokevirtual #110                // Method java/lang/String.substring:(I)Ljava/lang/String;
      26: invokestatic  #111                // Method java/lang/Integer.parseInt:(Ljava/lang/String;)I
      29: ireturn

  public boolean isDefaultMetaReplicaZnode(java.lang.String);
    Code:
       0: aload_0
       1: getfield      #22                 // Field metaReplicaZNodes:Lorg/apache/hbase/thirdparty/com/google/common/collect/ImmutableMap;
       4: iconst_0
       5: invokestatic  #14                 // Method java/lang/Integer.valueOf:(I)Ljava/lang/Integer;
       8: invokevirtual #103                // Method org/apache/hbase/thirdparty/com/google/common/collect/ImmutableMap.get:(Ljava/lang/Object;)Ljava/lang/Object;
      11: checkcast     #107                // class java/lang/String
      14: aload_1
      15: invokevirtual #108                // Method java/lang/String.equals:(Ljava/lang/Object;)Z
      18: ireturn

  public boolean isClientReadable(java.lang.String);
    Code:
       0: aload_1
       1: aload_0
       2: getfield      #7                  // Field baseZNode:Ljava/lang/String;
       5: invokevirtual #108                // Method java/lang/String.equals:(Ljava/lang/Object;)Z
       8: ifne          92
      11: aload_0
      12: aload_1
      13: invokevirtual #112                // Method isAnyMetaReplicaZNode:(Ljava/lang/String;)Z
      16: ifne          92
      19: aload_1
      20: aload_0
      21: getfield      #31                 // Field masterAddressZNode:Ljava/lang/String;
      24: invokevirtual #108                // Method java/lang/String.equals:(Ljava/lang/Object;)Z
      27: ifne          92
      30: aload_1
      31: aload_0
      32: getfield      #43                 // Field clusterIdZNode:Ljava/lang/String;
      35: invokevirtual #108                // Method java/lang/String.equals:(Ljava/lang/Object;)Z
      38: ifne          92
      41: aload_1
      42: aload_0
      43: getfield      #25                 // Field rsZNode:Ljava/lang/String;
      46: invokevirtual #108                // Method java/lang/String.equals:(Ljava/lang/Object;)Z
      49: ifne          92
      52: aload_1
      53: aload_0
      54: getfield      #40                 // Field tableZNode:Ljava/lang/String;
      57: invokevirtual #108                // Method java/lang/String.equals:(Ljava/lang/Object;)Z
      60: ifne          92
      63: aload_1
      64: new           #76                 // class java/lang/StringBuilder
      67: dup
      68: invokespecial #77                 // Method java/lang/StringBuilder."<init>":()V
      71: aload_0
      72: getfield      #40                 // Field tableZNode:Ljava/lang/String;
      75: invokevirtual #79                 // Method java/lang/StringBuilder.append:(Ljava/lang/String;)Ljava/lang/StringBuilder;
      78: ldc           #113                // String /
      80: invokevirtual #79                 // Method java/lang/StringBuilder.append:(Ljava/lang/String;)Ljava/lang/StringBuilder;
      83: invokevirtual #101                // Method java/lang/StringBuilder.toString:()Ljava/lang/String;
      86: invokevirtual #114                // Method java/lang/String.startsWith:(Ljava/lang/String;)Z
      89: ifeq          96
      92: iconst_1
      93: goto          97
      96: iconst_0
      97: ireturn

  public static java.lang.String joinZNode(java.lang.String, java.lang.String);
    Code:
       0: new           #76                 // class java/lang/StringBuilder
       3: dup
       4: invokespecial #77                 // Method java/lang/StringBuilder."<init>":()V
       7: aload_0
       8: invokevirtual #79                 // Method java/lang/StringBuilder.append:(Ljava/lang/String;)Ljava/lang/StringBuilder;
      11: bipush        47
      13: invokevirtual #115                // Method java/lang/StringBuilder.append:(C)Ljava/lang/StringBuilder;
      16: aload_1
      17: invokevirtual #79                 // Method java/lang/StringBuilder.append:(Ljava/lang/String;)Ljava/lang/StringBuilder;
      20: invokevirtual #101                // Method java/lang/StringBuilder.toString:()Ljava/lang/String;
      23: areturn
}
