Compiled from "ZooKeeperProtos.java"
public final class org.apache.hadoop.hbase.protobuf.generated.ZooKeeperProtos$MetaRegionServer$Builder extends com.google.protobuf.GeneratedMessage$Builder<org.apache.hadoop.hbase.protobuf.generated.ZooKeeperProtos$MetaRegionServer$Builder> implements org.apache.hadoop.hbase.protobuf.generated.ZooKeeperProtos$MetaRegionServerOrBuilder {
  public static final com.google.protobuf.Descriptors$Descriptor getDescriptor();
    Code:
       0: invokestatic  #3                  // Method org/apache/hadoop/hbase/protobuf/generated/ZooKeeperProtos.access$000:()Lcom/google/protobuf/Descriptors$Descriptor;
       3: areturn

  protected com.google.protobuf.GeneratedMessage$FieldAccessorTable internalGetFieldAccessorTable();
    Code:
       0: invokestatic  #4                  // Method org/apache/hadoop/hbase/protobuf/generated/ZooKeeperProtos.access$100:()Lcom/google/protobuf/GeneratedMessage$FieldAccessorTable;
       3: ldc           #5                  // class org/apache/hadoop/hbase/protobuf/generated/ZooKeeperProtos$MetaRegionServer
       5: ldc           #6                  // class org/apache/hadoop/hbase/protobuf/generated/ZooKeeperProtos$MetaRegionServer$Builder
       7: invokevirtual #7                  // Method com/google/protobuf/GeneratedMessage$FieldAccessorTable.ensureFieldAccessorsInitialized:(Ljava/lang/Class;Ljava/lang/Class;)Lcom/google/protobuf/GeneratedMessage$FieldAccessorTable;
      10: areturn

  public org.apache.hadoop.hbase.protobuf.generated.ZooKeeperProtos$MetaRegionServer$Builder clear();
    Code:
       0: aload_0
       1: invokespecial #18                 // Method com/google/protobuf/GeneratedMessage$Builder.clear:()Lcom/google/protobuf/GeneratedMessage$Builder;
       4: pop
       5: aload_0
       6: getfield      #19                 // Field serverBuilder_:Lcom/google/protobuf/SingleFieldBuilder;
       9: ifnonnull     22
      12: aload_0
      13: invokestatic  #9                  // Method org/apache/hadoop/hbase/protobuf/generated/HBaseProtos$ServerName.getDefaultInstance:()Lorg/apache/hadoop/hbase/protobuf/generated/HBaseProtos$ServerName;
      16: putfield      #10                 // Field server_:Lorg/apache/hadoop/hbase/protobuf/generated/HBaseProtos$ServerName;
      19: goto          30
      22: aload_0
      23: getfield      #19                 // Field serverBuilder_:Lcom/google/protobuf/SingleFieldBuilder;
      26: invokevirtual #20                 // Method com/google/protobuf/SingleFieldBuilder.clear:()Lcom/google/protobuf/SingleFieldBuilder;
      29: pop
      30: aload_0
      31: aload_0
      32: getfield      #21                 // Field bitField0_:I
      35: bipush        -2
      37: iand
      38: putfield      #21                 // Field bitField0_:I
      41: aload_0
      42: iconst_0
      43: putfield      #22                 // Field rpcVersion_:I
      46: aload_0
      47: aload_0
      48: getfield      #21                 // Field bitField0_:I
      51: bipush        -3
      53: iand
      54: putfield      #21                 // Field bitField0_:I
      57: aload_0
      58: getstatic     #11                 // Field org/apache/hadoop/hbase/protobuf/generated/ClusterStatusProtos$RegionState$State.OFFLINE:Lorg/apache/hadoop/hbase/protobuf/generated/ClusterStatusProtos$RegionState$State;
      61: putfield      #12                 // Field state_:Lorg/apache/hadoop/hbase/protobuf/generated/ClusterStatusProtos$RegionState$State;
      64: aload_0
      65: aload_0
      66: getfield      #21                 // Field bitField0_:I
      69: bipush        -5
      71: iand
      72: putfield      #21                 // Field bitField0_:I
      75: aload_0
      76: areturn

  public org.apache.hadoop.hbase.protobuf.generated.ZooKeeperProtos$MetaRegionServer$Builder clone();
    Code:
       0: invokestatic  #2                  // Method create:()Lorg/apache/hadoop/hbase/protobuf/generated/ZooKeeperProtos$MetaRegionServer$Builder;
       3: aload_0
       4: invokevirtual #23                 // Method buildPartial:()Lorg/apache/hadoop/hbase/protobuf/generated/ZooKeeperProtos$MetaRegionServer;
       7: invokevirtual #24                 // Method mergeFrom:(Lorg/apache/hadoop/hbase/protobuf/generated/ZooKeeperProtos$MetaRegionServer;)Lorg/apache/hadoop/hbase/protobuf/generated/ZooKeeperProtos$MetaRegionServer$Builder;
      10: areturn

  public com.google.protobuf.Descriptors$Descriptor getDescriptorForType();
    Code:
       0: invokestatic  #3                  // Method org/apache/hadoop/hbase/protobuf/generated/ZooKeeperProtos.access$000:()Lcom/google/protobuf/Descriptors$Descriptor;
       3: areturn

  public org.apache.hadoop.hbase.protobuf.generated.ZooKeeperProtos$MetaRegionServer getDefaultInstanceForType();
    Code:
       0: invokestatic  #25                 // Method org/apache/hadoop/hbase/protobuf/generated/ZooKeeperProtos$MetaRegionServer.getDefaultInstance:()Lorg/apache/hadoop/hbase/protobuf/generated/ZooKeeperProtos$MetaRegionServer;
       3: areturn

  public org.apache.hadoop.hbase.protobuf.generated.ZooKeeperProtos$MetaRegionServer build();
    Code:
       0: aload_0
       1: invokevirtual #23                 // Method buildPartial:()Lorg/apache/hadoop/hbase/protobuf/generated/ZooKeeperProtos$MetaRegionServer;
       4: astore_1
       5: aload_1
       6: invokevirtual #26                 // Method org/apache/hadoop/hbase/protobuf/generated/ZooKeeperProtos$MetaRegionServer.isInitialized:()Z
       9: ifne          17
      12: aload_1
      13: invokestatic  #27                 // Method newUninitializedMessageException:(Lcom/google/protobuf/Message;)Lcom/google/protobuf/UninitializedMessageException;
      16: athrow
      17: aload_1
      18: areturn

  public org.apache.hadoop.hbase.protobuf.generated.ZooKeeperProtos$MetaRegionServer buildPartial();
    Code:
       0: new           #5                  // class org/apache/hadoop/hbase/protobuf/generated/ZooKeeperProtos$MetaRegionServer
       3: dup
       4: aload_0
       5: aconst_null
       6: invokespecial #28                 // Method org/apache/hadoop/hbase/protobuf/generated/ZooKeeperProtos$MetaRegionServer."<init>":(Lcom/google/protobuf/GeneratedMessage$Builder;Lorg/apache/hadoop/hbase/protobuf/generated/ZooKeeperProtos$1;)V
       9: astore_1
      10: aload_0
      11: getfield      #21                 // Field bitField0_:I
      14: istore_2
      15: iconst_0
      16: istore_3
      17: iload_2
      18: iconst_1
      19: iand
      20: iconst_1
      21: if_icmpne     28
      24: iload_3
      25: iconst_1
      26: ior
      27: istore_3
      28: aload_0
      29: getfield      #19                 // Field serverBuilder_:Lcom/google/protobuf/SingleFieldBuilder;
      32: ifnonnull     47
      35: aload_1
      36: aload_0
      37: getfield      #10                 // Field server_:Lorg/apache/hadoop/hbase/protobuf/generated/HBaseProtos$ServerName;
      40: invokestatic  #29                 // Method org/apache/hadoop/hbase/protobuf/generated/ZooKeeperProtos$MetaRegionServer.access$702:(Lorg/apache/hadoop/hbase/protobuf/generated/ZooKeeperProtos$MetaRegionServer;Lorg/apache/hadoop/hbase/protobuf/generated/HBaseProtos$ServerName;)Lorg/apache/hadoop/hbase/protobuf/generated/HBaseProtos$ServerName;
      43: pop
      44: goto          62
      47: aload_1
      48: aload_0
      49: getfield      #19                 // Field serverBuilder_:Lcom/google/protobuf/SingleFieldBuilder;
      52: invokevirtual #30                 // Method com/google/protobuf/SingleFieldBuilder.build:()Lcom/google/protobuf/GeneratedMessage;
      55: checkcast     #31                 // class org/apache/hadoop/hbase/protobuf/generated/HBaseProtos$ServerName
      58: invokestatic  #29                 // Method org/apache/hadoop/hbase/protobuf/generated/ZooKeeperProtos$MetaRegionServer.access$702:(Lorg/apache/hadoop/hbase/protobuf/generated/ZooKeeperProtos$MetaRegionServer;Lorg/apache/hadoop/hbase/protobuf/generated/HBaseProtos$ServerName;)Lorg/apache/hadoop/hbase/protobuf/generated/HBaseProtos$ServerName;
      61: pop
      62: iload_2
      63: iconst_2
      64: iand
      65: iconst_2
      66: if_icmpne     73
      69: iload_3
      70: iconst_2
      71: ior
      72: istore_3
      73: aload_1
      74: aload_0
      75: getfield      #22                 // Field rpcVersion_:I
      78: invokestatic  #32                 // Method org/apache/hadoop/hbase/protobuf/generated/ZooKeeperProtos$MetaRegionServer.access$802:(Lorg/apache/hadoop/hbase/protobuf/generated/ZooKeeperProtos$MetaRegionServer;I)I
      81: pop
      82: iload_2
      83: iconst_4
      84: iand
      85: iconst_4
      86: if_icmpne     93
      89: iload_3
      90: iconst_4
      91: ior
      92: istore_3
      93: aload_1
      94: aload_0
      95: getfield      #12                 // Field state_:Lorg/apache/hadoop/hbase/protobuf/generated/ClusterStatusProtos$RegionState$State;
      98: invokestatic  #33                 // Method org/apache/hadoop/hbase/protobuf/generated/ZooKeeperProtos$MetaRegionServer.access$902:(Lorg/apache/hadoop/hbase/protobuf/generated/ZooKeeperProtos$MetaRegionServer;Lorg/apache/hadoop/hbase/protobuf/generated/ClusterStatusProtos$RegionState$State;)Lorg/apache/hadoop/hbase/protobuf/generated/ClusterStatusProtos$RegionState$State;
     101: pop
     102: aload_1
     103: iload_3
     104: invokestatic  #34                 // Method org/apache/hadoop/hbase/protobuf/generated/ZooKeeperProtos$MetaRegionServer.access$1002:(Lorg/apache/hadoop/hbase/protobuf/generated/ZooKeeperProtos$MetaRegionServer;I)I
     107: pop
     108: aload_0
     109: invokevirtual #35                 // Method onBuilt:()V
     112: aload_1
     113: areturn

  public org.apache.hadoop.hbase.protobuf.generated.ZooKeeperProtos$MetaRegionServer$Builder mergeFrom(com.google.protobuf.Message);
    Code:
       0: aload_1
       1: instanceof    #5                  // class org/apache/hadoop/hbase/protobuf/generated/ZooKeeperProtos$MetaRegionServer
       4: ifeq          16
       7: aload_0
       8: aload_1
       9: checkcast     #5                  // class org/apache/hadoop/hbase/protobuf/generated/ZooKeeperProtos$MetaRegionServer
      12: invokevirtual #24                 // Method mergeFrom:(Lorg/apache/hadoop/hbase/protobuf/generated/ZooKeeperProtos$MetaRegionServer;)Lorg/apache/hadoop/hbase/protobuf/generated/ZooKeeperProtos$MetaRegionServer$Builder;
      15: areturn
      16: aload_0
      17: aload_1
      18: invokespecial #36                 // Method com/google/protobuf/GeneratedMessage$Builder.mergeFrom:(Lcom/google/protobuf/Message;)Lcom/google/protobuf/AbstractMessage$Builder;
      21: pop
      22: aload_0
      23: areturn

  public org.apache.hadoop.hbase.protobuf.generated.ZooKeeperProtos$MetaRegionServer$Builder mergeFrom(org.apache.hadoop.hbase.protobuf.generated.ZooKeeperProtos$MetaRegionServer);
    Code:
       0: aload_1
       1: invokestatic  #25                 // Method org/apache/hadoop/hbase/protobuf/generated/ZooKeeperProtos$MetaRegionServer.getDefaultInstance:()Lorg/apache/hadoop/hbase/protobuf/generated/ZooKeeperProtos$MetaRegionServer;
       4: if_acmpne     9
       7: aload_0
       8: areturn
       9: aload_1
      10: invokevirtual #37                 // Method org/apache/hadoop/hbase/protobuf/generated/ZooKeeperProtos$MetaRegionServer.hasServer:()Z
      13: ifeq          25
      16: aload_0
      17: aload_1
      18: invokevirtual #38                 // Method org/apache/hadoop/hbase/protobuf/generated/ZooKeeperProtos$MetaRegionServer.getServer:()Lorg/apache/hadoop/hbase/protobuf/generated/HBaseProtos$ServerName;
      21: invokevirtual #39                 // Method mergeServer:(Lorg/apache/hadoop/hbase/protobuf/generated/HBaseProtos$ServerName;)Lorg/apache/hadoop/hbase/protobuf/generated/ZooKeeperProtos$MetaRegionServer$Builder;
      24: pop
      25: aload_1
      26: invokevirtual #40                 // Method org/apache/hadoop/hbase/protobuf/generated/ZooKeeperProtos$MetaRegionServer.hasRpcVersion:()Z
      29: ifeq          41
      32: aload_0
      33: aload_1
      34: invokevirtual #41                 // Method org/apache/hadoop/hbase/protobuf/generated/ZooKeeperProtos$MetaRegionServer.getRpcVersion:()I
      37: invokevirtual #42                 // Method setRpcVersion:(I)Lorg/apache/hadoop/hbase/protobuf/generated/ZooKeeperProtos$MetaRegionServer$Builder;
      40: pop
      41: aload_1
      42: invokevirtual #43                 // Method org/apache/hadoop/hbase/protobuf/generated/ZooKeeperProtos$MetaRegionServer.hasState:()Z
      45: ifeq          57
      48: aload_0
      49: aload_1
      50: invokevirtual #44                 // Method org/apache/hadoop/hbase/protobuf/generated/ZooKeeperProtos$MetaRegionServer.getState:()Lorg/apache/hadoop/hbase/protobuf/generated/ClusterStatusProtos$RegionState$State;
      53: invokevirtual #45                 // Method setState:(Lorg/apache/hadoop/hbase/protobuf/generated/ClusterStatusProtos$RegionState$State;)Lorg/apache/hadoop/hbase/protobuf/generated/ZooKeeperProtos$MetaRegionServer$Builder;
      56: pop
      57: aload_0
      58: aload_1
      59: invokevirtual #46                 // Method org/apache/hadoop/hbase/protobuf/generated/ZooKeeperProtos$MetaRegionServer.getUnknownFields:()Lcom/google/protobuf/UnknownFieldSet;
      62: invokevirtual #47                 // Method mergeUnknownFields:(Lcom/google/protobuf/UnknownFieldSet;)Lcom/google/protobuf/GeneratedMessage$Builder;
      65: pop
      66: aload_0
      67: areturn

  public final boolean isInitialized();
    Code:
       0: aload_0
       1: invokevirtual #48                 // Method hasServer:()Z
       4: ifne          9
       7: iconst_0
       8: ireturn
       9: aload_0
      10: invokevirtual #49                 // Method getServer:()Lorg/apache/hadoop/hbase/protobuf/generated/HBaseProtos$ServerName;
      13: invokevirtual #50                 // Method org/apache/hadoop/hbase/protobuf/generated/HBaseProtos$ServerName.isInitialized:()Z
      16: ifne          21
      19: iconst_0
      20: ireturn
      21: iconst_1
      22: ireturn

  public org.apache.hadoop.hbase.protobuf.generated.ZooKeeperProtos$MetaRegionServer$Builder mergeFrom(com.google.protobuf.CodedInputStream, com.google.protobuf.ExtensionRegistryLite) throws java.io.IOException;
    Code:
       0: aconst_null
       1: astore_3
       2: getstatic     #51                 // Field org/apache/hadoop/hbase/protobuf/generated/ZooKeeperProtos$MetaRegionServer.PARSER:Lcom/google/protobuf/Parser;
       5: aload_1
       6: aload_2
       7: invokeinterface #52,  3           // InterfaceMethod com/google/protobuf/Parser.parsePartialFrom:(Lcom/google/protobuf/CodedInputStream;Lcom/google/protobuf/ExtensionRegistryLite;)Ljava/lang/Object;
      12: checkcast     #5                  // class org/apache/hadoop/hbase/protobuf/generated/ZooKeeperProtos$MetaRegionServer
      15: astore_3
      16: aload_3
      17: ifnull        58
      20: aload_0
      21: aload_3
      22: invokevirtual #24                 // Method mergeFrom:(Lorg/apache/hadoop/hbase/protobuf/generated/ZooKeeperProtos$MetaRegionServer;)Lorg/apache/hadoop/hbase/protobuf/generated/ZooKeeperProtos$MetaRegionServer$Builder;
      25: pop
      26: goto          58
      29: astore        4
      31: aload         4
      33: invokevirtual #54                 // Method com/google/protobuf/InvalidProtocolBufferException.getUnfinishedMessage:()Lcom/google/protobuf/MessageLite;
      36: checkcast     #5                  // class org/apache/hadoop/hbase/protobuf/generated/ZooKeeperProtos$MetaRegionServer
      39: astore_3
      40: aload         4
      42: athrow
      43: astore        5
      45: aload_3
      46: ifnull        55
      49: aload_0
      50: aload_3
      51: invokevirtual #24                 // Method mergeFrom:(Lorg/apache/hadoop/hbase/protobuf/generated/ZooKeeperProtos$MetaRegionServer;)Lorg/apache/hadoop/hbase/protobuf/generated/ZooKeeperProtos$MetaRegionServer$Builder;
      54: pop
      55: aload         5
      57: athrow
      58: aload_0
      59: areturn
    Exception table:
       from    to  target type
           2    16    29   Class com/google/protobuf/InvalidProtocolBufferException
           2    16    43   any
          29    45    43   any

  public boolean hasServer();
    Code:
       0: aload_0
       1: getfield      #21                 // Field bitField0_:I
       4: iconst_1
       5: iand
       6: iconst_1
       7: if_icmpne     14
      10: iconst_1
      11: goto          15
      14: iconst_0
      15: ireturn

  public org.apache.hadoop.hbase.protobuf.generated.HBaseProtos$ServerName getServer();
    Code:
       0: aload_0
       1: getfield      #19                 // Field serverBuilder_:Lcom/google/protobuf/SingleFieldBuilder;
       4: ifnonnull     12
       7: aload_0
       8: getfield      #10                 // Field server_:Lorg/apache/hadoop/hbase/protobuf/generated/HBaseProtos$ServerName;
      11: areturn
      12: aload_0
      13: getfield      #19                 // Field serverBuilder_:Lcom/google/protobuf/SingleFieldBuilder;
      16: invokevirtual #55                 // Method com/google/protobuf/SingleFieldBuilder.getMessage:()Lcom/google/protobuf/GeneratedMessage;
      19: checkcast     #31                 // class org/apache/hadoop/hbase/protobuf/generated/HBaseProtos$ServerName
      22: areturn

  public org.apache.hadoop.hbase.protobuf.generated.ZooKeeperProtos$MetaRegionServer$Builder setServer(org.apache.hadoop.hbase.protobuf.generated.HBaseProtos$ServerName);
    Code:
       0: aload_0
       1: getfield      #19                 // Field serverBuilder_:Lcom/google/protobuf/SingleFieldBuilder;
       4: ifnonnull     31
       7: aload_1
       8: ifnonnull     19
      11: new           #56                 // class java/lang/NullPointerException
      14: dup
      15: invokespecial #57                 // Method java/lang/NullPointerException."<init>":()V
      18: athrow
      19: aload_0
      20: aload_1
      21: putfield      #10                 // Field server_:Lorg/apache/hadoop/hbase/protobuf/generated/HBaseProtos$ServerName;
      24: aload_0
      25: invokevirtual #58                 // Method onChanged:()V
      28: goto          40
      31: aload_0
      32: getfield      #19                 // Field serverBuilder_:Lcom/google/protobuf/SingleFieldBuilder;
      35: aload_1
      36: invokevirtual #59                 // Method com/google/protobuf/SingleFieldBuilder.setMessage:(Lcom/google/protobuf/GeneratedMessage;)Lcom/google/protobuf/SingleFieldBuilder;
      39: pop
      40: aload_0
      41: dup
      42: getfield      #21                 // Field bitField0_:I
      45: iconst_1
      46: ior
      47: putfield      #21                 // Field bitField0_:I
      50: aload_0
      51: areturn

  public org.apache.hadoop.hbase.protobuf.generated.ZooKeeperProtos$MetaRegionServer$Builder setServer(org.apache.hadoop.hbase.protobuf.generated.HBaseProtos$ServerName$Builder);
    Code:
       0: aload_0
       1: getfield      #19                 // Field serverBuilder_:Lcom/google/protobuf/SingleFieldBuilder;
       4: ifnonnull     22
       7: aload_0
       8: aload_1
       9: invokevirtual #60                 // Method org/apache/hadoop/hbase/protobuf/generated/HBaseProtos$ServerName$Builder.build:()Lorg/apache/hadoop/hbase/protobuf/generated/HBaseProtos$ServerName;
      12: putfield      #10                 // Field server_:Lorg/apache/hadoop/hbase/protobuf/generated/HBaseProtos$ServerName;
      15: aload_0
      16: invokevirtual #58                 // Method onChanged:()V
      19: goto          34
      22: aload_0
      23: getfield      #19                 // Field serverBuilder_:Lcom/google/protobuf/SingleFieldBuilder;
      26: aload_1
      27: invokevirtual #60                 // Method org/apache/hadoop/hbase/protobuf/generated/HBaseProtos$ServerName$Builder.build:()Lorg/apache/hadoop/hbase/protobuf/generated/HBaseProtos$ServerName;
      30: invokevirtual #59                 // Method com/google/protobuf/SingleFieldBuilder.setMessage:(Lcom/google/protobuf/GeneratedMessage;)Lcom/google/protobuf/SingleFieldBuilder;
      33: pop
      34: aload_0
      35: dup
      36: getfield      #21                 // Field bitField0_:I
      39: iconst_1
      40: ior
      41: putfield      #21                 // Field bitField0_:I
      44: aload_0
      45: areturn

  public org.apache.hadoop.hbase.protobuf.generated.ZooKeeperProtos$MetaRegionServer$Builder mergeServer(org.apache.hadoop.hbase.protobuf.generated.HBaseProtos$ServerName);
    Code:
       0: aload_0
       1: getfield      #19                 // Field serverBuilder_:Lcom/google/protobuf/SingleFieldBuilder;
       4: ifnonnull     60
       7: aload_0
       8: getfield      #21                 // Field bitField0_:I
      11: iconst_1
      12: iand
      13: iconst_1
      14: if_icmpne     48
      17: aload_0
      18: getfield      #10                 // Field server_:Lorg/apache/hadoop/hbase/protobuf/generated/HBaseProtos$ServerName;
      21: invokestatic  #9                  // Method org/apache/hadoop/hbase/protobuf/generated/HBaseProtos$ServerName.getDefaultInstance:()Lorg/apache/hadoop/hbase/protobuf/generated/HBaseProtos$ServerName;
      24: if_acmpeq     48
      27: aload_0
      28: aload_0
      29: getfield      #10                 // Field server_:Lorg/apache/hadoop/hbase/protobuf/generated/HBaseProtos$ServerName;
      32: invokestatic  #61                 // Method org/apache/hadoop/hbase/protobuf/generated/HBaseProtos$ServerName.newBuilder:(Lorg/apache/hadoop/hbase/protobuf/generated/HBaseProtos$ServerName;)Lorg/apache/hadoop/hbase/protobuf/generated/HBaseProtos$ServerName$Builder;
      35: aload_1
      36: invokevirtual #62                 // Method org/apache/hadoop/hbase/protobuf/generated/HBaseProtos$ServerName$Builder.mergeFrom:(Lorg/apache/hadoop/hbase/protobuf/generated/HBaseProtos$ServerName;)Lorg/apache/hadoop/hbase/protobuf/generated/HBaseProtos$ServerName$Builder;
      39: invokevirtual #63                 // Method org/apache/hadoop/hbase/protobuf/generated/HBaseProtos$ServerName$Builder.buildPartial:()Lorg/apache/hadoop/hbase/protobuf/generated/HBaseProtos$ServerName;
      42: putfield      #10                 // Field server_:Lorg/apache/hadoop/hbase/protobuf/generated/HBaseProtos$ServerName;
      45: goto          53
      48: aload_0
      49: aload_1
      50: putfield      #10                 // Field server_:Lorg/apache/hadoop/hbase/protobuf/generated/HBaseProtos$ServerName;
      53: aload_0
      54: invokevirtual #58                 // Method onChanged:()V
      57: goto          69
      60: aload_0
      61: getfield      #19                 // Field serverBuilder_:Lcom/google/protobuf/SingleFieldBuilder;
      64: aload_1
      65: invokevirtual #64                 // Method com/google/protobuf/SingleFieldBuilder.mergeFrom:(Lcom/google/protobuf/GeneratedMessage;)Lcom/google/protobuf/SingleFieldBuilder;
      68: pop
      69: aload_0
      70: dup
      71: getfield      #21                 // Field bitField0_:I
      74: iconst_1
      75: ior
      76: putfield      #21                 // Field bitField0_:I
      79: aload_0
      80: areturn

  public org.apache.hadoop.hbase.protobuf.generated.ZooKeeperProtos$MetaRegionServer$Builder clearServer();
    Code:
       0: aload_0
       1: getfield      #19                 // Field serverBuilder_:Lcom/google/protobuf/SingleFieldBuilder;
       4: ifnonnull     21
       7: aload_0
       8: invokestatic  #9                  // Method org/apache/hadoop/hbase/protobuf/generated/HBaseProtos$ServerName.getDefaultInstance:()Lorg/apache/hadoop/hbase/protobuf/generated/HBaseProtos$ServerName;
      11: putfield      #10                 // Field server_:Lorg/apache/hadoop/hbase/protobuf/generated/HBaseProtos$ServerName;
      14: aload_0
      15: invokevirtual #58                 // Method onChanged:()V
      18: goto          29
      21: aload_0
      22: getfield      #19                 // Field serverBuilder_:Lcom/google/protobuf/SingleFieldBuilder;
      25: invokevirtual #20                 // Method com/google/protobuf/SingleFieldBuilder.clear:()Lcom/google/protobuf/SingleFieldBuilder;
      28: pop
      29: aload_0
      30: aload_0
      31: getfield      #21                 // Field bitField0_:I
      34: bipush        -2
      36: iand
      37: putfield      #21                 // Field bitField0_:I
      40: aload_0
      41: areturn

  public org.apache.hadoop.hbase.protobuf.generated.HBaseProtos$ServerName$Builder getServerBuilder();
    Code:
       0: aload_0
       1: dup
       2: getfield      #21                 // Field bitField0_:I
       5: iconst_1
       6: ior
       7: putfield      #21                 // Field bitField0_:I
      10: aload_0
      11: invokevirtual #58                 // Method onChanged:()V
      14: aload_0
      15: invokespecial #16                 // Method getServerFieldBuilder:()Lcom/google/protobuf/SingleFieldBuilder;
      18: invokevirtual #65                 // Method com/google/protobuf/SingleFieldBuilder.getBuilder:()Lcom/google/protobuf/GeneratedMessage$Builder;
      21: checkcast     #66                 // class org/apache/hadoop/hbase/protobuf/generated/HBaseProtos$ServerName$Builder
      24: areturn

  public org.apache.hadoop.hbase.protobuf.generated.HBaseProtos$ServerNameOrBuilder getServerOrBuilder();
    Code:
       0: aload_0
       1: getfield      #19                 // Field serverBuilder_:Lcom/google/protobuf/SingleFieldBuilder;
       4: ifnull        18
       7: aload_0
       8: getfield      #19                 // Field serverBuilder_:Lcom/google/protobuf/SingleFieldBuilder;
      11: invokevirtual #67                 // Method com/google/protobuf/SingleFieldBuilder.getMessageOrBuilder:()Lcom/google/protobuf/MessageOrBuilder;
      14: checkcast     #68                 // class org/apache/hadoop/hbase/protobuf/generated/HBaseProtos$ServerNameOrBuilder
      17: areturn
      18: aload_0
      19: getfield      #10                 // Field server_:Lorg/apache/hadoop/hbase/protobuf/generated/HBaseProtos$ServerName;
      22: areturn

  public boolean hasRpcVersion();
    Code:
       0: aload_0
       1: getfield      #21                 // Field bitField0_:I
       4: iconst_2
       5: iand
       6: iconst_2
       7: if_icmpne     14
      10: iconst_1
      11: goto          15
      14: iconst_0
      15: ireturn

  public int getRpcVersion();
    Code:
       0: aload_0
       1: getfield      #22                 // Field rpcVersion_:I
       4: ireturn

  public org.apache.hadoop.hbase.protobuf.generated.ZooKeeperProtos$MetaRegionServer$Builder setRpcVersion(int);
    Code:
       0: aload_0
       1: dup
       2: getfield      #21                 // Field bitField0_:I
       5: iconst_2
       6: ior
       7: putfield      #21                 // Field bitField0_:I
      10: aload_0
      11: iload_1
      12: putfield      #22                 // Field rpcVersion_:I
      15: aload_0
      16: invokevirtual #58                 // Method onChanged:()V
      19: aload_0
      20: areturn

  public org.apache.hadoop.hbase.protobuf.generated.ZooKeeperProtos$MetaRegionServer$Builder clearRpcVersion();
    Code:
       0: aload_0
       1: aload_0
       2: getfield      #21                 // Field bitField0_:I
       5: bipush        -3
       7: iand
       8: putfield      #21                 // Field bitField0_:I
      11: aload_0
      12: iconst_0
      13: putfield      #22                 // Field rpcVersion_:I
      16: aload_0
      17: invokevirtual #58                 // Method onChanged:()V
      20: aload_0
      21: areturn

  public boolean hasState();
    Code:
       0: aload_0
       1: getfield      #21                 // Field bitField0_:I
       4: iconst_4
       5: iand
       6: iconst_4
       7: if_icmpne     14
      10: iconst_1
      11: goto          15
      14: iconst_0
      15: ireturn

  public org.apache.hadoop.hbase.protobuf.generated.ClusterStatusProtos$RegionState$State getState();
    Code:
       0: aload_0
       1: getfield      #12                 // Field state_:Lorg/apache/hadoop/hbase/protobuf/generated/ClusterStatusProtos$RegionState$State;
       4: areturn

  public org.apache.hadoop.hbase.protobuf.generated.ZooKeeperProtos$MetaRegionServer$Builder setState(org.apache.hadoop.hbase.protobuf.generated.ClusterStatusProtos$RegionState$State);
    Code:
       0: aload_1
       1: ifnonnull     12
       4: new           #56                 // class java/lang/NullPointerException
       7: dup
       8: invokespecial #57                 // Method java/lang/NullPointerException."<init>":()V
      11: athrow
      12: aload_0
      13: dup
      14: getfield      #21                 // Field bitField0_:I
      17: iconst_4
      18: ior
      19: putfield      #21                 // Field bitField0_:I
      22: aload_0
      23: aload_1
      24: putfield      #12                 // Field state_:Lorg/apache/hadoop/hbase/protobuf/generated/ClusterStatusProtos$RegionState$State;
      27: aload_0
      28: invokevirtual #58                 // Method onChanged:()V
      31: aload_0
      32: areturn

  public org.apache.hadoop.hbase.protobuf.generated.ZooKeeperProtos$MetaRegionServer$Builder clearState();
    Code:
       0: aload_0
       1: aload_0
       2: getfield      #21                 // Field bitField0_:I
       5: bipush        -5
       7: iand
       8: putfield      #21                 // Field bitField0_:I
      11: aload_0
      12: getstatic     #11                 // Field org/apache/hadoop/hbase/protobuf/generated/ClusterStatusProtos$RegionState$State.OFFLINE:Lorg/apache/hadoop/hbase/protobuf/generated/ClusterStatusProtos$RegionState$State;
      15: putfield      #12                 // Field state_:Lorg/apache/hadoop/hbase/protobuf/generated/ClusterStatusProtos$RegionState$State;
      18: aload_0
      19: invokevirtual #58                 // Method onChanged:()V
      22: aload_0
      23: areturn

  public com.google.protobuf.GeneratedMessage$Builder clear();
    Code:
       0: aload_0
       1: invokevirtual #73                 // Method clear:()Lorg/apache/hadoop/hbase/protobuf/generated/ZooKeeperProtos$MetaRegionServer$Builder;
       4: areturn

  public com.google.protobuf.GeneratedMessage$Builder clone();
    Code:
       0: aload_0
       1: invokevirtual #74                 // Method clone:()Lorg/apache/hadoop/hbase/protobuf/generated/ZooKeeperProtos$MetaRegionServer$Builder;
       4: areturn

  public com.google.protobuf.AbstractMessage$Builder mergeFrom(com.google.protobuf.CodedInputStream, com.google.protobuf.ExtensionRegistryLite) throws java.io.IOException;
    Code:
       0: aload_0
       1: aload_1
       2: aload_2
       3: invokevirtual #75                 // Method mergeFrom:(Lcom/google/protobuf/CodedInputStream;Lcom/google/protobuf/ExtensionRegistryLite;)Lorg/apache/hadoop/hbase/protobuf/generated/ZooKeeperProtos$MetaRegionServer$Builder;
       6: areturn

  public com.google.protobuf.AbstractMessage$Builder mergeFrom(com.google.protobuf.Message);
    Code:
       0: aload_0
       1: aload_1
       2: invokevirtual #76                 // Method mergeFrom:(Lcom/google/protobuf/Message;)Lorg/apache/hadoop/hbase/protobuf/generated/ZooKeeperProtos$MetaRegionServer$Builder;
       5: areturn

  public com.google.protobuf.AbstractMessage$Builder clear();
    Code:
       0: aload_0
       1: invokevirtual #73                 // Method clear:()Lorg/apache/hadoop/hbase/protobuf/generated/ZooKeeperProtos$MetaRegionServer$Builder;
       4: areturn

  public com.google.protobuf.AbstractMessage$Builder clone();
    Code:
       0: aload_0
       1: invokevirtual #74                 // Method clone:()Lorg/apache/hadoop/hbase/protobuf/generated/ZooKeeperProtos$MetaRegionServer$Builder;
       4: areturn

  public com.google.protobuf.Message$Builder mergeFrom(com.google.protobuf.CodedInputStream, com.google.protobuf.ExtensionRegistryLite) throws java.io.IOException;
    Code:
       0: aload_0
       1: aload_1
       2: aload_2
       3: invokevirtual #75                 // Method mergeFrom:(Lcom/google/protobuf/CodedInputStream;Lcom/google/protobuf/ExtensionRegistryLite;)Lorg/apache/hadoop/hbase/protobuf/generated/ZooKeeperProtos$MetaRegionServer$Builder;
       6: areturn

  public com.google.protobuf.Message$Builder clone();
    Code:
       0: aload_0
       1: invokevirtual #74                 // Method clone:()Lorg/apache/hadoop/hbase/protobuf/generated/ZooKeeperProtos$MetaRegionServer$Builder;
       4: areturn

  public com.google.protobuf.Message buildPartial();
    Code:
       0: aload_0
       1: invokevirtual #23                 // Method buildPartial:()Lorg/apache/hadoop/hbase/protobuf/generated/ZooKeeperProtos$MetaRegionServer;
       4: areturn

  public com.google.protobuf.Message build();
    Code:
       0: aload_0
       1: invokevirtual #77                 // Method build:()Lorg/apache/hadoop/hbase/protobuf/generated/ZooKeeperProtos$MetaRegionServer;
       4: areturn

  public com.google.protobuf.Message$Builder mergeFrom(com.google.protobuf.Message);
    Code:
       0: aload_0
       1: aload_1
       2: invokevirtual #76                 // Method mergeFrom:(Lcom/google/protobuf/Message;)Lorg/apache/hadoop/hbase/protobuf/generated/ZooKeeperProtos$MetaRegionServer$Builder;
       5: areturn

  public com.google.protobuf.Message$Builder clear();
    Code:
       0: aload_0
       1: invokevirtual #73                 // Method clear:()Lorg/apache/hadoop/hbase/protobuf/generated/ZooKeeperProtos$MetaRegionServer$Builder;
       4: areturn

  public com.google.protobuf.MessageLite$Builder mergeFrom(com.google.protobuf.CodedInputStream, com.google.protobuf.ExtensionRegistryLite) throws java.io.IOException;
    Code:
       0: aload_0
       1: aload_1
       2: aload_2
       3: invokevirtual #75                 // Method mergeFrom:(Lcom/google/protobuf/CodedInputStream;Lcom/google/protobuf/ExtensionRegistryLite;)Lorg/apache/hadoop/hbase/protobuf/generated/ZooKeeperProtos$MetaRegionServer$Builder;
       6: areturn

  public com.google.protobuf.MessageLite$Builder clone();
    Code:
       0: aload_0
       1: invokevirtual #74                 // Method clone:()Lorg/apache/hadoop/hbase/protobuf/generated/ZooKeeperProtos$MetaRegionServer$Builder;
       4: areturn

  public com.google.protobuf.MessageLite buildPartial();
    Code:
       0: aload_0
       1: invokevirtual #23                 // Method buildPartial:()Lorg/apache/hadoop/hbase/protobuf/generated/ZooKeeperProtos$MetaRegionServer;
       4: areturn

  public com.google.protobuf.MessageLite build();
    Code:
       0: aload_0
       1: invokevirtual #77                 // Method build:()Lorg/apache/hadoop/hbase/protobuf/generated/ZooKeeperProtos$MetaRegionServer;
       4: areturn

  public com.google.protobuf.MessageLite$Builder clear();
    Code:
       0: aload_0
       1: invokevirtual #73                 // Method clear:()Lorg/apache/hadoop/hbase/protobuf/generated/ZooKeeperProtos$MetaRegionServer$Builder;
       4: areturn

  public com.google.protobuf.MessageLite getDefaultInstanceForType();
    Code:
       0: aload_0
       1: invokevirtual #78                 // Method getDefaultInstanceForType:()Lorg/apache/hadoop/hbase/protobuf/generated/ZooKeeperProtos$MetaRegionServer;
       4: areturn

  public com.google.protobuf.Message getDefaultInstanceForType();
    Code:
       0: aload_0
       1: invokevirtual #78                 // Method getDefaultInstanceForType:()Lorg/apache/hadoop/hbase/protobuf/generated/ZooKeeperProtos$MetaRegionServer;
       4: areturn

  public com.google.protobuf.AbstractMessageLite$Builder mergeFrom(com.google.protobuf.CodedInputStream, com.google.protobuf.ExtensionRegistryLite) throws java.io.IOException;
    Code:
       0: aload_0
       1: aload_1
       2: aload_2
       3: invokevirtual #75                 // Method mergeFrom:(Lcom/google/protobuf/CodedInputStream;Lcom/google/protobuf/ExtensionRegistryLite;)Lorg/apache/hadoop/hbase/protobuf/generated/ZooKeeperProtos$MetaRegionServer$Builder;
       6: areturn

  public com.google.protobuf.AbstractMessageLite$Builder clone();
    Code:
       0: aload_0
       1: invokevirtual #74                 // Method clone:()Lorg/apache/hadoop/hbase/protobuf/generated/ZooKeeperProtos$MetaRegionServer$Builder;
       4: areturn

  public java.lang.Object clone() throws java.lang.CloneNotSupportedException;
    Code:
       0: aload_0
       1: invokevirtual #74                 // Method clone:()Lorg/apache/hadoop/hbase/protobuf/generated/ZooKeeperProtos$MetaRegionServer$Builder;
       4: areturn

  static org.apache.hadoop.hbase.protobuf.generated.ZooKeeperProtos$MetaRegionServer$Builder access$300();
    Code:
       0: invokestatic  #2                  // Method create:()Lorg/apache/hadoop/hbase/protobuf/generated/ZooKeeperProtos$MetaRegionServer$Builder;
       3: areturn

  org.apache.hadoop.hbase.protobuf.generated.ZooKeeperProtos$MetaRegionServer$Builder(com.google.protobuf.GeneratedMessage$BuilderParent, org.apache.hadoop.hbase.protobuf.generated.ZooKeeperProtos$1);
    Code:
       0: aload_0
       1: aload_1
       2: invokespecial #1                  // Method "<init>":(Lcom/google/protobuf/GeneratedMessage$BuilderParent;)V
       5: return
}
