Compiled from "ZooKeeperProtos.java"
final class org.apache.hadoop.hbase.protobuf.generated.ZooKeeperProtos$DeprecatedTableState$State$1 implements com.google.protobuf.Internal$EnumLiteMap<org.apache.hadoop.hbase.protobuf.generated.ZooKeeperProtos$DeprecatedTableState$State> {
  org.apache.hadoop.hbase.protobuf.generated.ZooKeeperProtos$DeprecatedTableState$State$1();
    Code:
       0: aload_0
       1: invokespecial #1                  // Method java/lang/Object."<init>":()V
       4: return

  public org.apache.hadoop.hbase.protobuf.generated.ZooKeeperProtos$DeprecatedTableState$State findValueByNumber(int);
    Code:
       0: iload_1
       1: invokestatic  #2                  // Method org/apache/hadoop/hbase/protobuf/generated/ZooKeeperProtos$DeprecatedTableState$State.valueOf:(I)Lorg/apache/hadoop/hbase/protobuf/generated/ZooKeeperProtos$DeprecatedTableState$State;
       4: areturn

  public com.google.protobuf.Internal$EnumLite findValueByNumber(int);
    Code:
       0: aload_0
       1: iload_1
       2: invokevirtual #3                  // Method findValueByNumber:(I)Lorg/apache/hadoop/hbase/protobuf/generated/ZooKeeperProtos$DeprecatedTableState$State;
       5: areturn
}
